{
  "document_metadata": {
    "page_number": "4",
    "document_number": "4-397-85573",
    "date": "Oct 14, 2002",
    "document_type": "FedEx Express Payment Type Detail",
    "has_handwriting": false,
    "has_stamps": false
  },
  "full_text": "FedEx\nInvoice Number: 4-397-85573\nInvoice Date: Oct 14, 2002\nAccount Number: 1144 2081 6\nPage: 4 of 9\nFedEx Express Payment Type Detail (Original)\nDropped off: Oct 02, 2002 Payer: Shipper Reference: NO REFERENCE INFORMATION FedEx Internal Use: 423530768/01574_/J\nFuel Surcharge FedEx has applied a fuel surcharge of 2.50% to this shipment.\nPackage sent from: 33461 zip code\nDistance Based Pricing, Zone 6\nInternetShip Tracking ID 790606208535\nService Type FedEx Priority Overnight\nPackage Type FedEx Box\nZone 6\nPieces 1\nWeight 2.0 lbs, 0.9 kgs\nDelivered Oct 03, 2002 09:47\nService Area Code A1\nSigned by S.GRIFFIS\nBundle ID 000\nSender HELEN H KIM\nRecipient HELEN EPSTEIN INTERESTS\nJEFFREY E EPSTEIN 457 MADISON AVE.\nNEW YORK NY 10022 6843 US 457 MADISON AVE.\nNEW YORK NY 10022 US\nTransportation Charge 27.50\nDiscount 2.75\nFuel Surcharge 0.62\nTotal Transportation Charges USD $ 25.37\nPicked up: Oct 03, 2002 Payer: Shipper Reference: NO REFERENCE INFORMATION FedEx Internal Use: 281229300/06112_/08\nFuel Surcharge FedEx has applied a fuel surcharge of 2.50% to this shipment.\nThe delivery commitment for FedEx 2day to homes or private residences (including home offices) is 7 P.M. the second business day for A1, A2, AA, A3, AM, PM, 01 and RM service areas.\nPackage sent from: 10021 zip code\n1st attempt Oct 07, 2002 at 01:34 PM.\nRecipient not in/business closed.\nDistance Based Pricing, Zone 8\nTracking ID 83537097329\nService Type FedEx 2Day\nPackage Type FedEx Pak\nZone 8\nPieces 1\nWeight 3.0 lbs, 1.4 kgs\nDelivered Oct 08, 2002 09:36\nService Area Code 2R\nSigned by C.DAVIES\nDec. Value USD 400.00\nBundle ID 000\nSender J EPSTEIN\nRecipient DOJ REDACTION\nJEFFREY E EPSTEIN 457 MADISON AVE\nNEW YORK NY 10022 6843 US\nTransportation Charge 13.00\nDiscount 1.30\nDeclared Value Charge 2.50\nFuel Surcharge 0.29\nCourier Pickup Charge 0.00\nResidential Delivery 1.35\nTotal Transportation Charges USD $ 15.84\nDOJ-OGR-00016088",
  "text_blocks": [
    {
      "type": "printed",
      "content": "FedEx",
      "position": "header"
    },
    {
      "type": "printed",
      "content": "Invoice Number: 4-397-85573\nInvoice Date: Oct 14, 2002\nAccount Number: 1144 2081 6\nPage: 4 of 9",
      "position": "header"
    },
    {
      "type": "printed",
      "content": "FedEx Express Payment Type Detail (Original)",
      "position": "header"
    },
    {
      "type": "printed",
      "content": "Dropped off: Oct 02, 2002 Payer: Shipper Reference: NO REFERENCE INFORMATION FedEx Internal Use: 423530768/01574_/J",
      "position": "top"
    },
    {
      "type": "printed",
      "content": "Fuel Surcharge FedEx has applied a fuel surcharge of 2.50% to this shipment.\nPackage sent from: 33461 zip code\nDistance Based Pricing, Zone 6",
      "position": "top"
    },
    {
      "type": "printed",
      "content": "InternetShip Tracking ID 790606208535\nService Type FedEx Priority Overnight\nPackage Type FedEx Box\nZone 6\nPieces 1\nWeight 2.0 lbs, 0.9 kgs\nDelivered Oct 03, 2002 09:47\nService Area Code A1\nSigned by S.GRIFFIS\nBundle ID 000",
      "position": "top"
    },
    {
      "type": "printed",
      "content": "Sender HELEN H KIM\nRecipient HELEN EPSTEIN INTERESTS\nJEFFREY E EPSTEIN 457 MADISON AVE.\nNEW YORK NY 10022 6843 US 457 MADISON AVE.\nNEW YORK NY 10022 US",
      "position": "top"
    },
    {
      "type": "printed",
      "content": "Transportation Charge 27.50\nDiscount 2.75\nFuel Surcharge 0.62\nTotal Transportation Charges USD $ 25.37",
      "position": "top"
    },
    {
      "type": "printed",
      "content": "Picked up: Oct 03, 2002 Payer: Shipper Reference: NO REFERENCE INFORMATION FedEx Internal Use: 281229300/06112_/08",
      "position": "middle"
    },
    {
      "type": "printed",
      "content": "Fuel Surcharge FedEx has applied a fuel surcharge of 2.50% to this shipment.\nThe delivery commitment for FedEx 2day to homes or private residences (including home offices) is 7 P.M. the second business day for A1, A2, AA, A3, AM, PM, 01 and RM service areas.",
      "position": "middle"
    },
    {
      "type": "printed",
      "content": "Package sent from: 10021 zip code\n1st attempt Oct 07, 2002 at 01:34 PM.\nRecipient not in/business closed.\nDistance Based Pricing, Zone 8",
      "position": "middle"
    },
    {
      "type": "printed",
      "content": "Tracking ID 83537097329\nService Type FedEx 2Day\nPackage Type FedEx Pak\nZone 8\nPieces 1\nWeight 3.0 lbs, 1.4 kgs\nDelivered Oct 08, 2002 09:36\nService Area Code 2R\nSigned by C.DAVIES\nDec. Value USD 400.00\nBundle ID 000",
      "position": "middle"
    },
    {
      "type": "printed",
      "content": "Sender J EPSTEIN\nRecipient DOJ REDACTION\nJEFFREY E EPSTEIN 457 MADISON AVE\nNEW YORK NY 10022 6843 US",
      "position": "middle"
    },
    {
      "type": "printed",
      "content": "Transportation Charge 13.00\nDiscount 1.30\nDeclared Value Charge 2.50\nFuel Surcharge 0.29\nCourier Pickup Charge 0.00\nResidential Delivery 1.35\nTotal Transportation Charges USD $ 15.84",
      "position": "middle"
    },
    {
      "type": "printed",
      "content": "DOJ-OGR-00016088",
      "position": "footer"
    }
  ],
  "entities": {
    "people": [
      "HELEN H KIM",
      "HELEN EPSTEIN INTERESTS",
      "JEFFREY E EPSTEIN",
      "S.GRIFFIS",
      "C.DAVIES",
      "J EPSTEIN"
    ],
    "organizations": [
      "FedEx"
    ],
    "locations": [
      "NEW YORK",
      "457 MADISON AVE"
    ],
    "dates": [
      "Oct 02, 2002",
      "Oct 03, 2002",
      "Oct 07, 2002",
      "Oct 08, 2002",
      "Oct 14, 2002"
    ],
    "reference_numbers": [
      "4-397-85573",
      "1144 2081 6",
      "790606208535",
      "83537097329",
      "DOJ-OGR-00016088"
    ]
  },
  "additional_notes": "The document appears to be a FedEx invoice with two shipment details. The recipient's name is redacted in the second shipment detail."
}