{
  "document_metadata": {
    "page_number": "4",
    "document_number": "4-495-75031",
    "date": "Dec 23, 2002",
    "document_type": "Invoice",
    "has_handwriting": false,
    "has_stamps": false
  },
  "full_text": "FedEx Invoice Number: 4-495-75031 Invoice Date: Dec 23, 2002 Account Number: 1144-2081-6 Page: 4 of 21 FedEx Express Shipment Detail By Payment Type (Original) Picked up: Dec 09, 2002 Payer: Shipper Reference: NO REFERENCE INFORMATION Fuel Surcharge FedEx has applied a fuel surcharge of 4.00% to this shipment. Distance Based Pricing, Zone 4 Package sent from: 10021 zip code Tracking ID 837133956336 Sender NDREA MITRONCH Recipient MARC LINDBERG Service Type FedEx Priority Overnight JEFFREY E EPSTEIN 457 MADISON AVE NEW YORK NY 10022 6843 US Package Type FedEx Pak Zone 4 Packages 1 Weight 1.0 lbs, 0.5 kgs Delivered Dec 10, 2002 09:32 Svc Area A2 Signed by D.OAKLEY FedEx Use 347191900/01530/_ Transportation Charge 21.00 Discount -2.10 Fuel Surcharge 0.76 Courier Pickup Charge 0.00 Total Transportation Charges USD $ 19.66 Picked up: Dec 09, 2002 Payer: Shipper Reference: NO REFERENCE INFORMATION Fuel Surcharge FedEx has applied a fuel surcharge of 4.00% to this shipment. The delivery commitment for FedEx 2day to homes or private residences (including home offices) is 7 P.M. the second business day for A1, A2, AA, A3, AM, PM, 01 and RM service areas. Distance Based Pricing, Zone 8 Package sent from: 10021 zip code Release signature on file. Tracking ID 837133956369 Sender G MAXWELL Recipient LAURA CASEY WASSERMAN Service Type FedEx 2Day JEFFREY E EPSTEIN 457 MADISON AVE NEW YORK NY 10022 6843 US Package Type Customer Packaging Zone 8 Packages 1 Weight 5.0 lbs, 2.3 kgs Delivered Dec 11, 2002 13:24 Svc Area 2R Signed by MAXWELL FedEx Use 347 191900/06112/02 Transportation Charge 16.75 Discount -1.68 Fuel Surcharge 0.60 Courier Pickup Charge 0.00 Residential Delivery 1.35 Total Transportation Charges USD $ 17.02 Picked up: Dec 09, 2002 Payer: Shipper Reference: NO REFERENCE INFORMATION Fuel Surcharge FedEx has applied a fuel surcharge of 4.00% to this shipment. Distance Based Pricing, Zone 8 Package sent from: 91201 zip code Tracking ID 837657306295 Sender BRAN FERREN Recipient EDWINA SIMMONDS Service Type FedEx Standard Overnight JEFFREY E EPSTEIN 457 MADISON AVE NEW YORK NY 10022 6843 US Package Type Customer Packaging Zone 8 Packages 1 Weight 10.0 lbs, 4.5 kgs Delivered Dec 10, 2002 11:54 Svc Area A1 Signed by S.MAXWELL FedEx Use 343063970/01415/_ Transportation Charge 45.75 Discount 4.58 Fuel Surcharge 1.65 Residential Delivery 1.35 Total Transportation Charges USD $ 44.17 DOJ-OGR-00016067",
  "text_blocks": [
    {
      "type": "printed",
      "content": "FedEx Invoice Number: 4-495-75031 Invoice Date: Dec 23, 2002 Account Number: 1144-2081-6 Page: 4 of 21",
      "position": "header"
    },
    {
      "type": "printed",
      "content": "FedEx Express Shipment Detail By Payment Type (Original)",
      "position": "header"
    },
    {
      "type": "printed",
      "content": "Picked up: Dec 09, 2002 Payer: Shipper Reference: NO REFERENCE INFORMATION",
      "position": "top"
    },
    {
      "type": "printed",
      "content": "Fuel Surcharge FedEx has applied a fuel surcharge of 4.00% to this shipment. Distance Based Pricing, Zone 4 Package sent from: 10021 zip code",
      "position": "top"
    },
    {
      "type": "printed",
      "content": "Tracking ID 837133956336 Sender NDREA MITRONCH Recipient MARC LINDBERG Service Type FedEx Priority Overnight JEFFREY E EPSTEIN 457 MADISON AVE NEW YORK NY 10022 6843 US Package Type FedEx Pak Zone 4 Packages 1 Weight 1.0 lbs, 0.5 kgs Delivered Dec 10, 2002 09:32 Svc Area A2 Signed by D.OAKLEY FedEx Use 347191900/01530/_",
      "position": "top"
    },
    {
      "type": "printed",
      "content": "Transportation Charge 21.00 Discount -2.10 Fuel Surcharge 0.76 Courier Pickup Charge 0.00 Total Transportation Charges USD $ 19.66",
      "position": "top"
    },
    {
      "type": "printed",
      "content": "Picked up: Dec 09, 2002 Payer: Shipper Reference: NO REFERENCE INFORMATION",
      "position": "middle"
    },
    {
      "type": "printed",
      "content": "Fuel Surcharge FedEx has applied a fuel surcharge of 4.00% to this shipment. The delivery commitment for FedEx 2day to homes or private residences (including home offices) is 7 P.M. the second business day for A1, A2, AA, A3, AM, PM, 01 and RM service areas. Distance Based Pricing, Zone 8 Package sent from: 10021 zip code Release signature on file.",
      "position": "middle"
    },
    {
      "type": "printed",
      "content": "Tracking ID 837133956369 Sender G MAXWELL Recipient LAURA CASEY WASSERMAN Service Type FedEx 2Day JEFFREY E EPSTEIN 457 MADISON AVE NEW YORK NY 10022 6843 US Package Type Customer Packaging Zone 8 Packages 1 Weight 5.0 lbs, 2.3 kgs Delivered Dec 11, 2002 13:24 Svc Area 2R Signed by MAXWELL FedEx Use 347 191900/06112/02",
      "position": "middle"
    },
    {
      "type": "printed",
      "content": "Transportation Charge 16.75 Discount -1.68 Fuel Surcharge 0.60 Courier Pickup Charge 0.00 Residential Delivery 1.35 Total Transportation Charges USD $ 17.02",
      "position": "middle"
    },
    {
      "type": "printed",
      "content": "Picked up: Dec 09, 2002 Payer: Shipper Reference: NO REFERENCE INFORMATION",
      "position": "bottom"
    },
    {
      "type": "printed",
      "content": "Fuel Surcharge FedEx has applied a fuel surcharge of 4.00% to this shipment. Distance Based Pricing, Zone 8 Package sent from: 91201 zip code",
      "position": "bottom"
    },
    {
      "type": "printed",
      "content": "Tracking ID 837657306295 Sender BRAN FERREN Recipient EDWINA SIMMONDS Service Type FedEx Standard Overnight JEFFREY E EPSTEIN 457 MADISON AVE NEW YORK NY 10022 6843 US Package Type Customer Packaging Zone 8 Packages 1 Weight 10.0 lbs, 4.5 kgs Delivered Dec 10, 2002 11:54 Svc Area A1 Signed by S.MAXWELL FedEx Use 343063970/01415/_",
      "position": "bottom"
    },
    {
      "type": "printed",
      "content": "Transportation Charge 45.75 Discount 4.58 Fuel Surcharge 1.65 Residential Delivery 1.35 Total Transportation Charges USD $ 44.17",
      "position": "bottom"
    },
    {
      "type": "printed",
      "content": "DOJ-OGR-00016067",
      "position": "footer"
    }
  ],
  "entities": {
    "people": [
      "NDREA MITRONCH",
      "MARC LINDBERG",
      "JEFFREY E EPSTEIN",
      "G MAXWELL",
      "LAURA CASEY WASSERMAN",
      "BRAN FERREN",
      "EDWINA SIMMONDS",
      "D.OAKLEY",
      "MAXWELL",
      "S.MAXWELL"
    ],
    "organizations": [
      "FedEx"
    ],
    "locations": [
      "NEW YORK",
      "457 MADISON AVE"
    ],
    "dates": [
      "Dec 09, 2002",
      "Dec 10, 2002",
      "Dec 11, 2002",
      "Dec 23, 2002"
    ],
    "reference_numbers": [
      "4-495-75031",
      "1144-2081-6",
      "837133956336",
      "837133956369",
      "837657306295",
      "347191900/01530/_",
      "347 191900/06112/02",
      "343063970/01415/_"
    ]
  },
  "additional_notes": "The document appears to be a FedEx invoice with multiple shipment details. The document is clear and legible, with no visible damage or redactions."
}