{
  "document_metadata": {
    "page_number": "3 of 3",
    "document_number": "806",
    "date": "08/06/25",
    "document_type": "letter",
    "has_handwriting": true,
    "has_stamps": false
  },
  "full_text": "PANISH SHEA RAVIPUDI LLP\n11111 Santa Monica Boulevard Suite 700 Los Angeles, CA 90025 Phone 310.477.1700 Fax 310.477.1699 panish.law\nAugust 6, 2025\nVIA E-MAIL\nSDNY Victim and Witness Coordinator United States Attorney's Office 26 Federal Plaza, 37th Floor New York, New York 10278 Email: USANYS.EpsteinMaxwellVictims@usdoj.gov\nRe: Unsealing of Grand Jury Transcripts in U.S. v. Epstein, 19-cr-490 (RMB) and U.S. v. Maxwell, 20-cr-330 (PAE)\nDear SDNY Victim and Witness Coordinator:\nI represented a victim identified as Jane Doe in U.S. v. Maxwell, 20-cr-330. Please be advised I am hereby joining in the letter submitted to you previously on August 5, 2025 on behalf of victim Annie Farmer by her attorney Sigrid McCawley.\nWith that said, I am strongly opposed to any portions of the grand jury transcripts being released that would in any way identify the victims. If any materials are released, the victims' names and other identifying information should be redacted.\nVery truly yours,\nRobert S. Glassman\nDOJ-OGR-00015129",
  "text_blocks": [
    {
      "type": "printed",
      "content": "PANISH SHEA RAVIPUDI LLP",
      "position": "header"
    },
    {
      "type": "printed",
      "content": "11111 Santa Monica Boulevard Suite 700 Los Angeles, CA 90025 Phone 310.477.1700 Fax 310.477.1699 panish.law",
      "position": "header"
    },
    {
      "type": "printed",
      "content": "August 6, 2025",
      "position": "top"
    },
    {
      "type": "printed",
      "content": "VIA E-MAIL",
      "position": "top"
    },
    {
      "type": "printed",
      "content": "SDNY Victim and Witness Coordinator United States Attorney's Office 26 Federal Plaza, 37th Floor New York, New York 10278 Email: USANYS.EpsteinMaxwellVictims@usdoj.gov",
      "position": "top"
    },
    {
      "type": "printed",
      "content": "Re: Unsealing of Grand Jury Transcripts in U.S. v. Epstein, 19-cr-490 (RMB) and U.S. v. Maxwell, 20-cr-330 (PAE)",
      "position": "middle"
    },
    {
      "type": "printed",
      "content": "Dear SDNY Victim and Witness Coordinator:",
      "position": "middle"
    },
    {
      "type": "printed",
      "content": "I represented a victim identified as Jane Doe in U.S. v. Maxwell, 20-cr-330. Please be advised I am hereby joining in the letter submitted to you previously on August 5, 2025 on behalf of victim Annie Farmer by her attorney Sigrid McCawley.",
      "position": "middle"
    },
    {
      "type": "printed",
      "content": "With that said, I am strongly opposed to any portions of the grand jury transcripts being released that would in any way identify the victims. If any materials are released, the victims' names and other identifying information should be redacted.",
      "position": "middle"
    },
    {
      "type": "handwritten",
      "content": "Robert S. Glassman",
      "position": "bottom"
    },
    {
      "type": "printed",
      "content": "Very truly yours,",
      "position": "bottom"
    },
    {
      "type": "printed",
      "content": "DOJ-OGR-00015129",
      "position": "footer"
    }
  ],
  "entities": {
    "people": [
      "Robert S. Glassman",
      "Annie Farmer",
      "Sigrid McCawley",
      "Jane Doe"
    ],
    "organizations": [
      "PANISH SHEA RAVIPUDI LLP",
      "United States Attorney's Office"
    ],
    "locations": [
      "Los Angeles",
      "New York"
    ],
    "dates": [
      "August 6, 2025",
      "August 5, 2025",
      "08/06/25"
    ],
    "reference_numbers": [
      "19-cr-490",
      "20-cr-330",
      "DOJ-OGR-00015129"
    ]
  },
  "additional_notes": "The document appears to be a formal letter from a law firm to the SDNY Victim and Witness Coordinator regarding the unsealing of grand jury transcripts in U.S. v. Epstein and U.S. v. Maxwell. The letter is signed by Robert S. Glassman and includes a reference number at the bottom."
}