{
  "document_metadata": {
    "page_number": "148",
    "document_number": "761",
    "date": "08/10/22",
    "document_type": "court transcript",
    "has_handwriting": false,
    "has_stamps": false
  },
  "full_text": "Case 1:20-cr-00330-PAE Document 761 Filed 08/10/22 Page 148 of 246\nLGCmax4 Loftus - direct\nsaid no and we have a witness who says otherwise. To let it just stand is only her statement, which we have the ability to contest.\nMR. ROHRBACH: That would only be true if it went to bias and motive, which it doesn't for the reasons I've explained. As the Court is aware, I think we had this conversation at a sidebar during Kate's testimony when Ms. Sternheim had this declaration and we all agreed this is a collateral matter at that time.\nMS. STERNHEIM: Judge, collateral during the testimony of that witness. Having another witness to counter what that witness says elevates it to another category.\nMR. ROHRBACH: It's impeachment with extrinsic evidence, whether that extrinsic evidence is a declaration or live testimony by a witness.\nTHE COURT: It's not just the impeachment, it's not just the question of did she say it or not. Although, there is that impeachment embedded in it. But there is just the testimony itself and the question is whether that's relevant evidence of bias or motive; right? Isn't that the analysis?\nMR. ROHRBACH: I didn't understand the defense to be offering this as affirmative evidence of bias or motive, just as impeachment for those reasons. The defense has never turned this over in Rule 16 discovery, for example, which they would do if it was part of their case in chief because they were\nSOUTHERN DISTRICT REPORTERS, P.C. (212) 805-0300\nDOJ-OGR-00016631",
  "text_blocks": [
    {
      "type": "printed",
      "content": "Case 1:20-cr-00330-PAE Document 761 Filed 08/10/22 Page 148 of 246",
      "position": "header"
    },
    {
      "type": "printed",
      "content": "LGCmax4 Loftus - direct",
      "position": "header"
    },
    {
      "type": "printed",
      "content": "said no and we have a witness who says otherwise. To let it just stand is only her statement, which we have the ability to contest.\nMR. ROHRBACH: That would only be true if it went to bias and motive, which it doesn't for the reasons I've explained. As the Court is aware, I think we had this conversation at a sidebar during Kate's testimony when Ms. Sternheim had this declaration and we all agreed this is a collateral matter at that time.\nMS. STERNHEIM: Judge, collateral during the testimony of that witness. Having another witness to counter what that witness says elevates it to another category.\nMR. ROHRBACH: It's impeachment with extrinsic evidence, whether that extrinsic evidence is a declaration or live testimony by a witness.\nTHE COURT: It's not just the impeachment, it's not just the question of did she say it or not. Although, there is that impeachment embedded in it. But there is just the testimony itself and the question is whether that's relevant evidence of bias or motive; right? Isn't that the analysis?\nMR. ROHRBACH: I didn't understand the defense to be offering this as affirmative evidence of bias or motive, just as impeachment for those reasons. The defense has never turned this over in Rule 16 discovery, for example, which they would do if it was part of their case in chief because they were",
      "position": "main"
    },
    {
      "type": "printed",
      "content": "SOUTHERN DISTRICT REPORTERS, P.C. (212) 805-0300",
      "position": "footer"
    },
    {
      "type": "printed",
      "content": "DOJ-OGR-00016631",
      "position": "footer"
    }
  ],
  "entities": {
    "people": [
      "MR. ROHRBACH",
      "MS. STERNHEIM",
      "Kate"
    ],
    "organizations": [
      "SOUTHERN DISTRICT REPORTERS, P.C."
    ],
    "locations": [],
    "dates": [
      "08/10/22"
    ],
    "reference_numbers": [
      "1:20-cr-00330-PAE",
      "761",
      "DOJ-OGR-00016631"
    ]
  },
  "additional_notes": "The document appears to be a court transcript with a clear and legible format. There are no visible redactions or damage."
}