{
  "document_metadata": {
    "page_number": "238",
    "document_number": "759",
    "date": "08/10/22",
    "document_type": "court transcript",
    "has_handwriting": false,
    "has_stamps": false
  },
  "full_text": "Case 1:20-cr-00330-PAE Document 759 Filed 08/10/22 Page 238 of 267 2266 LCAVMAX8\n\n1 THE COURT: Go ahead, Mr. Everdell.\n2 Do you want to come to the podium?\n3 MR. EVERDELL: Yes, please.\n4 Your Honor, the defense moves at this time for a\n5 judgment of acquittal under Rule 29(a) on the grounds that the\n6 evidence elicited by the government in its case-in-chief is\n7 insufficient to establish each element of the offenses charged\n8 in the S2 indictment beyond a reasonable doubt.\n9 THE COURT: Move as to all counts?\n10 MR. EVERDELL: Move as to all counts, your Honor.\n11 THE COURT: Go ahead.\n12 MR. EVERDELL: Your Honor, we do make this application\n13 with respect to every count in the S2 indictment; but for\n14 purposes of today, I'm going to confine my comments to address\n15 specifically Counts One and Two.\n16 THE COURT: Okay.\n17 MR. EVERDELL: Which are the enticement counts,\n18 conspiracy, and the substantive enticement counts.\n19 Your Honor, as the Court is aware, those counts depend\n20 on the testimony of Jane.\n21 To convict Ms. Maxwell, the government must show that\n22 Ms. Maxwell persuaded or enticed Jane to travel to New York to\n23 engage in sex acts that would violate New York law and the\n24 specific law that's cited in the indictment. There is no\n25 evidence in the record that Ms. Maxwell or anyone else who\n\nSOUTHERN DISTRICT REPORTERS, P.C.\n(212) 805-0300\n\nDOJ-OGR-00016454",
  "text_blocks": [
    {
      "type": "printed",
      "content": "Case 1:20-cr-00330-PAE Document 759 Filed 08/10/22 Page 238 of 267 2266 LCAVMAX8",
      "position": "header"
    },
    {
      "type": "printed",
      "content": "1 THE COURT: Go ahead, Mr. Everdell.\n2 Do you want to come to the podium?\n3 MR. EVERDELL: Yes, please.\n4 Your Honor, the defense moves at this time for a\n5 judgment of acquittal under Rule 29(a) on the grounds that the\n6 evidence elicited by the government in its case-in-chief is\n7 insufficient to establish each element of the offenses charged\n8 in the S2 indictment beyond a reasonable doubt.\n9 THE COURT: Move as to all counts?\n10 MR. EVERDELL: Move as to all counts, your Honor.\n11 THE COURT: Go ahead.\n12 MR. EVERDELL: Your Honor, we do make this application\n13 with respect to every count in the S2 indictment; but for\n14 purposes of today, I'm going to confine my comments to address\n15 specifically Counts One and Two.\n16 THE COURT: Okay.\n17 MR. EVERDELL: Which are the enticement counts,\n18 conspiracy, and the substantive enticement counts.\n19 Your Honor, as the Court is aware, those counts depend\n20 on the testimony of Jane.\n21 To convict Ms. Maxwell, the government must show that\n22 Ms. Maxwell persuaded or enticed Jane to travel to New York to\n23 engage in sex acts that would violate New York law and the\n24 specific law that's cited in the indictment. There is no\n25 evidence in the record that Ms. Maxwell or anyone else who",
      "position": "main content"
    },
    {
      "type": "printed",
      "content": "SOUTHERN DISTRICT REPORTERS, P.C.\n(212) 805-0300",
      "position": "footer"
    },
    {
      "type": "printed",
      "content": "DOJ-OGR-00016454",
      "position": "footer"
    }
  ],
  "entities": {
    "people": [
      "Mr. Everdell",
      "Jane",
      "Ms. Maxwell"
    ],
    "organizations": [
      "SOUTHERN DISTRICT REPORTERS, P.C."
    ],
    "locations": [
      "New York"
    ],
    "dates": [
      "08/10/22"
    ],
    "reference_numbers": [
      "1:20-cr-00330-PAE",
      "759",
      "DOJ-OGR-00016454"
    ]
  },
  "additional_notes": "The document appears to be a court transcript with clear and legible text. There are no visible redactions or damage."
}