{
  "document_metadata": {
    "page_number": "87",
    "document_number": "759",
    "date": "08/10/22",
    "document_type": "court transcript",
    "has_handwriting": false,
    "has_stamps": false
  },
  "full_text": "Case 1:20-cr-00330-PAE Document 759 Filed 08/10/22 Page 87 of 267 2115\nLCACmax3 A. Farmer - cross\n1 (Jury present)\n2 Thank you so much, members of the jury.\n3 Ms. Menninger, you may continue with your cross examination.\n4\n5 MS. MENNINGER: Thank you, your Honor.\n6 BY MS. MENNINGER:\n7 Q. I think when we left off, I was asking you about the dates of your trip.\n8\n9 MS. MENNINGER: If I could pull up Government Exhibit 603. As this is in evidence, your Honor, if I could also publish it to the jury.\n10\n11 THE COURT: You may.\n12\n13 Q. So this is your journal; right?\n14 A. It is, yes. I see what you're referring to.\n15 Q. In your journal, you gave a date of January 7th, 1996; correct?\n16\n17 A. Yes.\n18 Q. And what you wrote is, I got back from my trip to New York today?\n19\n20 A. Yes, I was right on top of that journal entry, yes.\n21 Q. So it's now your memory that you got back on January 7th; right?\n22\n23 A. Correct.\n24 Q. And you had been there for about a week; correct?\n25 A. Yes.\nSOUTHERN DISTRICT REPORTERS, P.C. (212) 805-0300\nDOJ-OGR-00016303",
  "text_blocks": [
    {
      "type": "printed",
      "content": "Case 1:20-cr-00330-PAE Document 759 Filed 08/10/22 Page 87 of 267 2115",
      "position": "header"
    },
    {
      "type": "printed",
      "content": "LCACmax3 A. Farmer - cross",
      "position": "header"
    },
    {
      "type": "printed",
      "content": "(Jury present)\nThank you so much, members of the jury.\nMs. Menninger, you may continue with your cross examination.",
      "position": "top"
    },
    {
      "type": "printed",
      "content": "MS. MENNINGER: Thank you, your Honor.\nBY MS. MENNINGER:\nQ. I think when we left off, I was asking you about the dates of your trip.",
      "position": "middle"
    },
    {
      "type": "printed",
      "content": "MS. MENNINGER: If I could pull up Government Exhibit 603. As this is in evidence, your Honor, if I could also publish it to the jury.",
      "position": "middle"
    },
    {
      "type": "printed",
      "content": "THE COURT: You may.",
      "position": "middle"
    },
    {
      "type": "printed",
      "content": "Q. So this is your journal; right?\nA. It is, yes. I see what you're referring to.\nQ. In your journal, you gave a date of January 7th, 1996; correct?\nA. Yes.\nQ. And what you wrote is, I got back from my trip to New York today?\nA. Yes, I was right on top of that journal entry, yes.\nQ. So it's now your memory that you got back on January 7th; right?\nA. Correct.\nQ. And you had been there for about a week; correct?\nA. Yes.",
      "position": "middle"
    },
    {
      "type": "printed",
      "content": "SOUTHERN DISTRICT REPORTERS, P.C. (212) 805-0300",
      "position": "footer"
    },
    {
      "type": "printed",
      "content": "DOJ-OGR-00016303",
      "position": "footer"
    }
  ],
  "entities": {
    "people": [
      "Ms. Menninger"
    ],
    "organizations": [
      "SOUTHERN DISTRICT REPORTERS, P.C."
    ],
    "locations": [
      "New York"
    ],
    "dates": [
      "08/10/22",
      "January 7th, 1996"
    ],
    "reference_numbers": [
      "1:20-cr-00330-PAE",
      "759",
      "603",
      "DOJ-OGR-00016303"
    ]
  },
  "additional_notes": "The document appears to be a court transcript with a clear and legible format. There are no visible redactions or damage."
}