{
  "document_metadata": {
    "page_number": "75 of 101",
    "document_number": "779",
    "date": "08/22/22",
    "document_type": "court document",
    "has_handwriting": false,
    "has_stamps": false
  },
  "full_text": "Case 1:20-cr-00330-PAE Document 779 Filed 08/22/22 Page 75 of 101 75\nM6SQmaxS1\naspirations of going to law school, and I knew I could not do\nso without my undergraduate degree, so I declined it.\nWhen Ghislaine found out, she flew into a rage. I\ndidn't understand why until she told me that she and Epstein\nwere responsible for giving me that opportunity and that in\nturning it down I was being ungrateful. I now know that this\nwas their standard operating procedure. Give a gift or a favor\nand then demand sex in return. Nevertheless, I completed my\ncourse work, got my degree from FIT, at which point I left\nHenri Bendel and took a position at Bloomingdales. I wanted to\nleave Epstein and Maxwell and the abuse they perpetrated\nagainst me behind as I started my professional life. I never\nwanted to or expected to see them again.\nOne day in the fall of 1995, Maxwell showed up at\nBloomingdales looking for me. When I asked her how she knew\nwhere I was, she said she asked my colleagues at Henri Bendel.\nShe immediately began befriending me once again, asking me to\ngo out socially. I tried to resist but eventually she wore me\ndown, and I began spending time with them again. They made me\nfeel like they were friends, contemporaries.\nIn one instance, they took me to Florida and insisted\nthat I stay longer than planned which caused me to miss work\nand led to me being fired. Seizing on this new vulnerability\nthey began trafficking me to their friends. By that time I was\ntrapped. I was assaulted, raped and trafficked countless times\nSOUTHERN DISTRICT REPORTERS, P.C.\n(212) 805-0300    DOJ-OGR-00014822",
  "text_blocks": [
    {
      "type": "printed",
      "content": "Case 1:20-cr-00330-PAE Document 779 Filed 08/22/22 Page 75 of 101 75",
      "position": "header"
    },
    {
      "type": "printed",
      "content": "M6SQmaxS1",
      "position": "header"
    },
    {
      "type": "printed",
      "content": "aspirations of going to law school, and I knew I could not do\nso without my undergraduate degree, so I declined it.\nWhen Ghislaine found out, she flew into a rage. I\ndidn't understand why until she told me that she and Epstein\nwere responsible for giving me that opportunity and that in\nturning it down I was being ungrateful. I now know that this\nwas their standard operating procedure. Give a gift or a favor\nand then demand sex in return. Nevertheless, I completed my\ncourse work, got my degree from FIT, at which point I left\nHenri Bendel and took a position at Bloomingdales. I wanted to\nleave Epstein and Maxwell and the abuse they perpetrated\nagainst me behind as I started my professional life. I never\nwanted to or expected to see them again.\nOne day in the fall of 1995, Maxwell showed up at\nBloomingdales looking for me. When I asked her how she knew\nwhere I was, she said she asked my colleagues at Henri Bendel.\nShe immediately began befriending me once again, asking me to\ngo out socially. I tried to resist but eventually she wore me\ndown, and I began spending time with them again. They made me\nfeel like they were friends, contemporaries.\nIn one instance, they took me to Florida and insisted\nthat I stay longer than planned which caused me to miss work\nand led to me being fired. Seizing on this new vulnerability\nthey began trafficking me to their friends. By that time I was\ntrapped. I was assaulted, raped and trafficked countless times",
      "position": "main body"
    },
    {
      "type": "printed",
      "content": "SOUTHERN DISTRICT REPORTERS, P.C.\n(212) 805-0300    DOJ-OGR-00014822",
      "position": "footer"
    }
  ],
  "entities": {
    "people": [
      "Ghislaine",
      "Epstein",
      "Maxwell"
    ],
    "organizations": [
      "FIT",
      "Henri Bendel",
      "Bloomingdales",
      "SOUTHERN DISTRICT REPORTERS, P.C."
    ],
    "locations": [
      "Florida"
    ],
    "dates": [
      "08/22/22",
      "1995"
    ],
    "reference_numbers": [
      "1:20-cr-00330-PAE",
      "779",
      "DOJ-OGR-00014822"
    ]
  },
  "additional_notes": "The document appears to be a court transcript or statement detailing experiences with Jeffrey Epstein and Ghislaine Maxwell. The text is typed, and there are no visible redactions or damage."
}