{
  "document_metadata": {
    "page_number": "222",
    "document_number": "767",
    "date": "08/10/22",
    "document_type": "Court Document",
    "has_handwriting": false,
    "has_stamps": false
  },
  "full_text": "Case 1:20-cr-00330-PAE Document 767 Filed 08/10/22 Page 222 of 257 3056 LCKCmax9 Charge by at least one of the conspirators in furtherance of that conspiracy. In other words, the government must show that the agreement went beyond the mere talking stage. It must show that at least one the conspirators in furtherance of the conspiracy. With respect to the overt acts for Count One, the indictment alleges as follows: One, between in or about 1994 and in or about 1997, when Jane was under the age of 17, Maxwell participated in multiple group sexual encounters with Epstein and Jane in New York and Florida. Two, in or about 1996, when Jane was under the age of 17, Jane was enticed to travel from Florida to New York for purposes of sexually abusing her at the New York residence in violation of New York Penal Law, Section 130.55. Three, in or about 1996, Maxwell provided Annie with an unsolicited massage in New Mexico during which Annie was topless. Four, between in or about 2001 and in or about 2002, when Carolyn was under the age of 17, Maxwell and Epstein invited Carolyn to travel from Florida to a place outside of Florida with Epstein. With respect to the overt acts to Count Three, the indictment alleges as follows: Between in or about 1994 and in or about 1997 when SOUTHERN DISTRICT REPORTERS, P.C. (212) 805-0300 DOJ-OGR-00017243",
  "text_blocks": [
    {
      "type": "printed",
      "content": "Case 1:20-cr-00330-PAE Document 767 Filed 08/10/22 Page 222 of 257 3056 LCKCmax9 Charge",
      "position": "header"
    },
    {
      "type": "printed",
      "content": "by at least one of the conspirators in furtherance of that conspiracy. In other words, the government must show that the agreement went beyond the mere talking stage. It must show that at least one the conspirators in furtherance of the conspiracy.",
      "position": "top"
    },
    {
      "type": "printed",
      "content": "With respect to the overt acts for Count One, the indictment alleges as follows: One, between in or about 1994 and in or about 1997, when Jane was under the age of 17, Maxwell participated in multiple group sexual encounters with Epstein and Jane in New York and Florida. Two, in or about 1996, when Jane was under the age of 17, Jane was enticed to travel from Florida to New York for purposes of sexually abusing her at the New York residence in violation of New York Penal Law, Section 130.55. Three, in or about 1996, Maxwell provided Annie with an unsolicited massage in New Mexico during which Annie was topless. Four, between in or about 2001 and in or about 2002, when Carolyn was under the age of 17, Maxwell and Epstein invited Carolyn to travel from Florida to a place outside of Florida with Epstein.",
      "position": "middle"
    },
    {
      "type": "printed",
      "content": "With respect to the overt acts to Count Three, the indictment alleges as follows: Between in or about 1994 and in or about 1997 when",
      "position": "middle"
    },
    {
      "type": "printed",
      "content": "SOUTHERN DISTRICT REPORTERS, P.C. (212) 805-0300",
      "position": "footer"
    },
    {
      "type": "printed",
      "content": "DOJ-OGR-00017243",
      "position": "footer"
    }
  ],
  "entities": {
    "people": [
      "Maxwell",
      "Epstein",
      "Jane",
      "Annie",
      "Carolyn"
    ],
    "organizations": [
      "SOUTHERN DISTRICT REPORTERS, P.C."
    ],
    "locations": [
      "New York",
      "Florida",
      "New Mexico"
    ],
    "dates": [
      "1994",
      "1997",
      "1996",
      "2001",
      "2002",
      "08/10/22"
    ],
    "reference_numbers": [
      "1:20-cr-00330-PAE",
      "767",
      "DOJ-OGR-00017243"
    ]
  },
  "additional_notes": "The document appears to be a court transcript or legal document related to a case involving Maxwell and Epstein. The text is printed and there are no visible stamps or handwritten notes. The document is from a court case and contains specific details about the allegations and charges."
}