{
  "document_metadata": {
    "page_number": "22",
    "document_number": "741",
    "date": "08/10/22",
    "document_type": "court document",
    "has_handwriting": false,
    "has_stamps": false
  },
  "full_text": "Case 1:20-cr-00330-AJN Document 741 Filed 08/10/22 Page 22 of 106\nLBTVMAX1 26\nyour family and friends that you're a juror in a criminal case,\nbut you may not tell them anything else about it until you've\nbeen discharged by me.\nThird, do not let anyone talk to you about the case or\nabout anyone who has anything to do with it. If any person\nshould attempt to communicate with you about this case at any\ntime throughout the trial, either in or out of the courthouse,\nyou must immediately report that to my deputy, Ms. Williams,\nand to no one else. Ms. Williams will report it to me. And\nwhen I say report that communication to no one else, I mean you\nshould not tell anyone, including your fellow jurors. To\nminimize the probability of any such improper communication, it\nis important that you go straight to the jury room when you\ncome in in the morning, and that you remain in the jury room\nfor the duration of the trial day. You should not linger in\nthe public areas of the courthouse on this floor or elsewhere\non your way in and out.\nFourth, do not do any research or any investigation\nabout the case or about anyone who has anything to do with the\ncase on your own. Don't go visit any place described in the\ntrial, don't read or listen to or watch any news reports about\nthe case, don't go on the internet or use whatever digital or\ncommunications device it is you use to see what you can learn\nto inform yourself about this matter. Again, I know that in\nthis day and age there is a temptation, but as I've made clear\nSOUTHERN DISTRICT REPORTERS, P.C.\n(212) 805-0300\nDOJ-OGR-00016132",
  "text_blocks": [
    {
      "type": "printed",
      "content": "Case 1:20-cr-00330-AJN Document 741 Filed 08/10/22 Page 22 of 106",
      "position": "header"
    },
    {
      "type": "printed",
      "content": "LBTVMAX1 26\nyour family and friends that you're a juror in a criminal case,\nbut you may not tell them anything else about it until you've\nbeen discharged by me.\nThird, do not let anyone talk to you about the case or\nabout anyone who has anything to do with it. If any person\nshould attempt to communicate with you about this case at any\ntime throughout the trial, either in or out of the courthouse,\nyou must immediately report that to my deputy, Ms. Williams,\nand to no one else. Ms. Williams will report it to me. And\nwhen I say report that communication to no one else, I mean you\nshould not tell anyone, including your fellow jurors. To\nminimize the probability of any such improper communication, it\nis important that you go straight to the jury room when you\ncome in in the morning, and that you remain in the jury room\nfor the duration of the trial day. You should not linger in\nthe public areas of the courthouse on this floor or elsewhere\non your way in and out.\nFourth, do not do any research or any investigation\nabout the case or about anyone who has anything to do with the\ncase on your own. Don't go visit any place described in the\ntrial, don't read or listen to or watch any news reports about\nthe case, don't go on the internet or use whatever digital or\ncommunications device it is you use to see what you can learn\nto inform yourself about this matter. Again, I know that in\nthis day and age there is a temptation, but as I've made clear",
      "position": "main"
    },
    {
      "type": "printed",
      "content": "SOUTHERN DISTRICT REPORTERS, P.C.\n(212) 805-0300",
      "position": "footer"
    },
    {
      "type": "printed",
      "content": "DOJ-OGR-00016132",
      "position": "footer"
    }
  ],
  "entities": {
    "people": [
      "Ms. Williams"
    ],
    "organizations": [
      "SOUTHERN DISTRICT REPORTERS, P.C."
    ],
    "locations": [
      "courthouse",
      "jury room"
    ],
    "dates": [
      "08/10/22"
    ],
    "reference_numbers": [
      "1:20-cr-00330-AJN",
      "741",
      "DOJ-OGR-00016132"
    ]
  },
  "additional_notes": "The document appears to be a court transcript or instruction to jurors. The text is clear and legible, with no visible redactions or damage."
}