{
  "document_metadata": {
    "page_number": null,
    "document_number": "S2 20 CR 330 (AJN)",
    "date": "August 17, 2021",
    "document_type": "Stipulation",
    "has_handwriting": true,
    "has_stamps": false
  },
  "full_text": "UNITED STATES DISTRICT COURT SOUTHERN DISTRICT OF NEW YORK UNITED STATES OF AMERICA - v. - GHISLAINE MAXWELL, Defendant. STIPULATION S2 20 CR 330 (AJN) IT IS HEREBY STIPULATED AND AGREED by and among the United States of America, by Damian Williams, United States Attorney for the Southern District of New York, and Maurene Comey, Alison Moe, Lara Pomerantz, and Andrew Rohrbach, Assistant United States Attorneys, of counsel, and defendant Ghislaine Maxwell, by and with the consent of her attorneys, Christian Everdell, Esq., Laura Menninger, Esq., Jeffrey Pagliuca, Esq., and Bobbi Sternheim, Esq., that: 1. On August 17, 2021, Robert Glassman, counsel for the witness testifying using the pseudonym Jane, spoke by phone with a prosecutor in this case. The notes of the call reflect that: 2. Glassman stated that before the Government charged the case, Jane had discussed with Glassman whether to cooperate with the case, and during those conversations Glassman had advised Jane to cooperate and discussed with Jane that cooperating with the case was the morally right thing to do, and they had discussed how testifying at trial was the right thing to do. Glassman also mentioned that Glassman had told Jane it would \"help her case.\" S2 20 Cr. 330 (AJN) Defendant's Ex. A-6 DOJ-OGR-00015169",
  "text_blocks": [
    {
      "type": "printed",
      "content": "UNITED STATES DISTRICT COURT SOUTHERN DISTRICT OF NEW YORK",
      "position": "header"
    },
    {
      "type": "printed",
      "content": "UNITED STATES OF AMERICA - v. - GHISLAINE MAXWELL, Defendant.",
      "position": "middle"
    },
    {
      "type": "printed",
      "content": "STIPULATION S2 20 CR 330 (AJN)",
      "position": "middle"
    },
    {
      "type": "printed",
      "content": "IT IS HEREBY STIPULATED AND AGREED by and among the United States of America, by Damian Williams, United States Attorney for the Southern District of New York, and Maurene Comey, Alison Moe, Lara Pomerantz, and Andrew Rohrbach, Assistant United States Attorneys, of counsel, and defendant Ghislaine Maxwell, by and with the consent of her attorneys, Christian Everdell, Esq., Laura Menninger, Esq., Jeffrey Pagliuca, Esq., and Bobbi Sternheim, Esq., that:",
      "position": "middle"
    },
    {
      "type": "printed",
      "content": "1. On August 17, 2021, Robert Glassman, counsel for the witness testifying using the pseudonym Jane, spoke by phone with a prosecutor in this case. The notes of the call reflect that:",
      "position": "middle"
    },
    {
      "type": "printed",
      "content": "2. Glassman stated that before the Government charged the case, Jane had discussed with Glassman whether to cooperate with the case, and during those conversations Glassman had advised Jane to cooperate and discussed with Jane that cooperating with the case was the morally right thing to do, and they had discussed how testifying at trial was the right thing to do. Glassman also mentioned that Glassman had told Jane it would \"help her case.\"",
      "position": "middle"
    },
    {
      "type": "handwritten",
      "content": "A-6",
      "position": "footer"
    },
    {
      "type": "printed",
      "content": "S2 20 Cr. 330 (AJN) Defendant's Ex.",
      "position": "footer"
    },
    {
      "type": "printed",
      "content": "DOJ-OGR-00015169",
      "position": "footer"
    }
  ],
  "entities": {
    "people": [
      "Damian Williams",
      "Maurene Comey",
      "Alison Moe",
      "Lara Pomerantz",
      "Andrew Rohrbach",
      "Ghislaine Maxwell",
      "Christian Everdell",
      "Laura Menninger",
      "Jeffrey Pagliuca",
      "Bobbi Sternheim",
      "Robert Glassman",
      "Jane"
    ],
    "organizations": [
      "United States District Court",
      "United States Attorney for the Southern District of New York"
    ],
    "locations": [
      "New York"
    ],
    "dates": [
      "August 17, 2021"
    ],
    "reference_numbers": [
      "S2 20 CR 330 (AJN)",
      "DOJ-OGR-00015169"
    ]
  },
  "additional_notes": "The document appears to be a court filing with a stipulation agreement between the United States of America and Ghislaine Maxwell. The document is typed with some handwritten annotations."
}