{
  "document_metadata": {
    "page_number": "99",
    "document_number": "763",
    "date": "08/10/22",
    "document_type": "court transcript",
    "has_handwriting": false,
    "has_stamps": false
  },
  "full_text": "Case 1:20-cr-00330-AJN Document 763 Filed 08/10/22 Page 99 of 197\nLCHCmax3 Dubin - direct\n1 be on his planes, et cetera. So it is foundational for her\n2 knowledge about Mr. Epstein, about why she was with Mr. Epstein\n3 during the relevant timeframe, why her children are with\n4 Mr. Epstein during the relevant timeframe.\n5 THE COURT: You've already established she was\n6 comfortable with the children. So I think you have -- you'll\n7 move on.\n8 MR. PAGLIUCA: Yes, I am.\n9 THE COURT: I'll sustain on the current question and\n10 then move on.\n11 (Continued on next page)\n12\n13\n14\n15\n16\n17\n18\n19\n20\n21\n22\n23\n24\n25\nSOUTHERN DISTRICT REPORTERS, P.C.\n(212) 805-0300\nDOJ-OGR-00016828",
  "text_blocks": [
    {
      "type": "printed",
      "content": "Case 1:20-cr-00330-AJN Document 763 Filed 08/10/22 Page 99 of 197",
      "position": "header"
    },
    {
      "type": "printed",
      "content": "LCHCmax3 Dubin - direct",
      "position": "header"
    },
    {
      "type": "printed",
      "content": "1 be on his planes, et cetera. So it is foundational for her\n2 knowledge about Mr. Epstein, about why she was with Mr. Epstein\n3 during the relevant timeframe, why her children are with\n4 Mr. Epstein during the relevant timeframe.\n5 THE COURT: You've already established she was\n6 comfortable with the children. So I think you have -- you'll\n7 move on.\n8 MR. PAGLIUCA: Yes, I am.\n9 THE COURT: I'll sustain on the current question and\n10 then move on.\n11 (Continued on next page)",
      "position": "main"
    },
    {
      "type": "printed",
      "content": "SOUTHERN DISTRICT REPORTERS, P.C.\n(212) 805-0300",
      "position": "footer"
    },
    {
      "type": "printed",
      "content": "DOJ-OGR-00016828",
      "position": "footer"
    }
  ],
  "entities": {
    "people": [
      "Mr. Epstein",
      "Mr. Pagliuca"
    ],
    "organizations": [
      "SOUTHERN DISTRICT REPORTERS, P.C."
    ],
    "locations": [],
    "dates": [
      "08/10/22"
    ],
    "reference_numbers": [
      "1:20-cr-00330-AJN",
      "763",
      "DOJ-OGR-00016828"
    ]
  },
  "additional_notes": "The document appears to be a court transcript with a clear and readable format. There are no visible redactions or damage."
}