{
  "document_metadata": {
    "page_number": "33",
    "document_number": "741",
    "date": "08/10/22",
    "document_type": "Court Document",
    "has_handwriting": false,
    "has_stamps": false
  },
  "full_text": "Case 1:20-cr-00330-AJN Document 741 Filed 08/10/22 Page 33 of 106\nLBTCMAX2\n37\nOpening - Ms. Pomerantz\n1 adult woman, she was able to provide a cover of respectability\n2 to Epstein that lulled these girls and their families into a\n3 false sense of security. She was in on it from the start. The\n4 defendant and Epstein lured their victims with the promise of a\n5 brighter future only to sexually exploit them and forever\n6 change their lives. And while this horrific abuse was going on\n7 behind closed doors, the defendant was jet setting in private\n8 planes and living a life of extraordinary luxury. These girls\n9 were just a means to support her lifestyle, a way for the\n10 defendant to make sure that Epstein - who demanded constant\n11 sexual gratification from young girls - remained satisfied so\n12 that the defendant could stay in the lifestyle to which she was\n13 accustomed.\n14 So what happened to Jane, the 14-year-old who met the\n15 defendant and Epstein at her summer camp in 1994? You will\n16 hear from Jane about the day she met these predators. You'll\n17 hear that after Jane returned to Florida from camp, someone\n18 from Epstein's office reached out to Jane and invited her to\n19 Epstein's house in Palm Beach for tea. Jane went to Epstein's\n20 house with her mother. Epstein explained that he liked to\n21 mentor young talented people, that he gave scholarships and\n22 that he wanted to help Jane.\n23 Jane started spending time with the defendant and\n24 Epstein at Epstein's house in Palm Beach. Jane was 14 years\n25 old. She was a kid. Epstein was in his early 40s, the\nSOUTHERN DISTRICT REPORTERS, P.C.\n(212) 805-0300\nDOJ-OGR-00016143",
  "text_blocks": [
    {
      "type": "printed",
      "content": "Case 1:20-cr-00330-AJN Document 741 Filed 08/10/22 Page 33 of 106",
      "position": "header"
    },
    {
      "type": "printed",
      "content": "LBTCMAX2\n37\nOpening - Ms. Pomerantz",
      "position": "header"
    },
    {
      "type": "printed",
      "content": "1 adult woman, she was able to provide a cover of respectability\n2 to Epstein that lulled these girls and their families into a\n3 false sense of security. She was in on it from the start. The\n4 defendant and Epstein lured their victims with the promise of a\n5 brighter future only to sexually exploit them and forever\n6 change their lives. And while this horrific abuse was going on\n7 behind closed doors, the defendant was jet setting in private\n8 planes and living a life of extraordinary luxury. These girls\n9 were just a means to support her lifestyle, a way for the\n10 defendant to make sure that Epstein - who demanded constant\n11 sexual gratification from young girls - remained satisfied so\n12 that the defendant could stay in the lifestyle to which she was\n13 accustomed.",
      "position": "main"
    },
    {
      "type": "printed",
      "content": "14 So what happened to Jane, the 14-year-old who met the\n15 defendant and Epstein at her summer camp in 1994? You will\n16 hear from Jane about the day she met these predators. You'll\n17 hear that after Jane returned to Florida from camp, someone\n18 from Epstein's office reached out to Jane and invited her to\n19 Epstein's house in Palm Beach for tea. Jane went to Epstein's\n20 house with her mother. Epstein explained that he liked to\n21 mentor young talented people, that he gave scholarships and\n22 that he wanted to help Jane.",
      "position": "main"
    },
    {
      "type": "printed",
      "content": "23 Jane started spending time with the defendant and\n24 Epstein at Epstein's house in Palm Beach. Jane was 14 years\n25 old. She was a kid. Epstein was in his early 40s, the",
      "position": "main"
    },
    {
      "type": "printed",
      "content": "SOUTHERN DISTRICT REPORTERS, P.C.\n(212) 805-0300",
      "position": "footer"
    },
    {
      "type": "printed",
      "content": "DOJ-OGR-00016143",
      "position": "footer"
    }
  ],
  "entities": {
    "people": [
      "Epstein",
      "Jane",
      "Ms. Pomerantz"
    ],
    "organizations": [
      "SOUTHERN DISTRICT REPORTERS, P.C."
    ],
    "locations": [
      "Florida",
      "Palm Beach"
    ],
    "dates": [
      "08/10/22",
      "1994"
    ],
    "reference_numbers": [
      "1:20-cr-00330-AJN",
      "741",
      "DOJ-OGR-00016143"
    ]
  },
  "additional_notes": "The document appears to be a court transcript or legal document related to a case involving Jeffrey Epstein. The text is typed and there are no visible handwritten notes or stamps. The document is from the Southern District Reporters, P.C. and contains a reference number."
}