{
  "document_metadata": {
    "page_number": "1",
    "document_number": "765",
    "date": "08/10/22",
    "document_type": "Court Document",
    "has_handwriting": false,
    "has_stamps": false
  },
  "full_text": "Case 1:20-cr-00330-AJN Document 765 Filed 08/10/22 Page 1 of 95 LCI1MAX1 UNITED STATES DISTRICT COURT SOUTHERN DISTRICT OF NEW YORK -------------------------------------------------------x UNITED STATES OF AMERICA, v. 20 CR 330 (AJN) GHISLAINE MAXWELL, Defendant. Jury Trial -------------------------------------------------------x New York, N.Y. December 18, 2021 9:10 a.m. Before: HON. ALISON J. NATHAN, District Judge APPEARANCES DAMIAN WILLIAMS United States Attorney for the Southern District of New York BY: MAURENE COMEY LARA POMERANTZ ANDREW ROHRBACH Assistant United States Attorneys HADDON MORGAN AND FOREMAN Attorneys for Defendant BY: JEFFREY S. PAGLIUCA LAURA A. MENNINGER -and- BOBBI C. STERNHEIM -and- COHEN & GRESSER BY: CHRISTIAN R. EVERDELL SOUTHERN DISTRICT REPORTERS, P.C. (212) 805-0300 DOJ-OGR-00016927",
  "text_blocks": [
    {
      "type": "printed",
      "content": "Case 1:20-cr-00330-AJN Document 765 Filed 08/10/22 Page 1 of 95",
      "position": "header"
    },
    {
      "type": "printed",
      "content": "LCI1MAX1",
      "position": "header"
    },
    {
      "type": "printed",
      "content": "UNITED STATES DISTRICT COURT SOUTHERN DISTRICT OF NEW YORK -------------------------------------------------------x UNITED STATES OF AMERICA, v. 20 CR 330 (AJN) GHISLAINE MAXWELL, Defendant. Jury Trial -------------------------------------------------------x New York, N.Y. December 18, 2021 9:10 a.m. Before: HON. ALISON J. NATHAN, District Judge APPEARANCES DAMIAN WILLIAMS United States Attorney for the Southern District of New York BY: MAURENE COMEY LARA POMERANTZ ANDREW ROHRBACH Assistant United States Attorneys HADDON MORGAN AND FOREMAN Attorneys for Defendant BY: JEFFREY S. PAGLIUCA LAURA A. MENNINGER -and- BOBBI C. STERNHEIM -and- COHEN & GRESSER BY: CHRISTIAN R. EVERDELL",
      "position": "main"
    },
    {
      "type": "printed",
      "content": "SOUTHERN DISTRICT REPORTERS, P.C. (212) 805-0300",
      "position": "footer"
    },
    {
      "type": "printed",
      "content": "DOJ-OGR-00016927",
      "position": "footer"
    }
  ],
  "entities": {
    "people": [
      "GHISLAINE MAXWELL",
      "ALISON J. NATHAN",
      "DAMIAN WILLIAMS",
      "MAURENE COMEY",
      "LARA POMERANTZ",
      "ANDREW ROHRBACH",
      "JEFFREY S. PAGLIUCA",
      "LAURA A. MENNINGER",
      "BOBBI C. STERNHEIM",
      "CHRISTIAN R. EVERDELL"
    ],
    "organizations": [
      "UNITED STATES DISTRICT COURT",
      "SOUTHERN DISTRICT OF NEW YORK",
      "COHEN & GRESSER",
      "SOUTHERN DISTRICT REPORTERS, P.C.",
      "HADDON MORGAN AND FOREMAN"
    ],
    "locations": [
      "New York"
    ],
    "dates": [
      "08/10/22",
      "December 18, 2021"
    ],
    "reference_numbers": [
      "20 CR 330 (AJN)",
      "1:20-cr-00330-AJN",
      "Document 765",
      "DOJ-OGR-00016927"
    ]
  },
  "additional_notes": "The document appears to be a court transcript from the United States District Court for the Southern District of New York. The case involves Ghislaine Maxwell and is dated December 18, 2021. The document is well-formatted and legible."
}