{
  "document_metadata": {
    "page_number": "61",
    "document_number": "761",
    "date": "08/10/22",
    "document_type": "court transcript",
    "has_handwriting": false,
    "has_stamps": false
  },
  "full_text": "Case 1:20-cr-00330-PAE Document 761 Filed 08/10/22 Page 61 of 246 2356 LCGCmax2 Espinosa - direct\n1 Q. Do you see that document in front of you?\n2 A. Yes, I do.\n3 Q. Now, without saying the name of that person out loud, do you recognize the name of the person on that document?\n4 A. Yes, I do.\n5 Q. I'm going to refer to that person as Jane and you should, too. Okay?\n6 A. Okay.\n7 MR. EVERDELL: You can take that down now.\n8 Q. Ms. Espinosa, do you ever recall seeing Jane in the office?\n9 A. Yes.\n10 Q. How old did she appear to you to be when you first saw her?\n11 A. Probably 18.\n12 Q. And about when do you recall first seeing Jane in the office?\n13 A. I remember seeing Jane in the office with her mother.\n14 Q. And about when do you recall that happening for the first time?\n15 A. Probably the beginning to middle of my time there.\n16 Q. And about how many times did Jane visit the office, to your recollection?\n17 A. There was a few times. I can't really say how many times, but I would say maybe five.\n18 Q. And you mentioned Jane's mother. Do you recall how many times Jane's mother came with her to the office?\n19 SOUTHERN DISTRICT REPORTERS, P.C. (212) 805-0300 DOJ-OGR-00016544",
  "text_blocks": [
    {
      "type": "printed",
      "content": "Case 1:20-cr-00330-PAE Document 761 Filed 08/10/22 Page 61 of 246 2356 LCGCmax2 Espinosa - direct",
      "position": "header"
    },
    {
      "type": "printed",
      "content": "1 Q. Do you see that document in front of you?\n2 A. Yes, I do.\n3 Q. Now, without saying the name of that person out loud, do you recognize the name of the person on that document?\n4 A. Yes, I do.\n5 Q. I'm going to refer to that person as Jane and you should, too. Okay?\n6 A. Okay.\n7 MR. EVERDELL: You can take that down now.\n8 Q. Ms. Espinosa, do you ever recall seeing Jane in the office?\n9 A. Yes.\n10 Q. How old did she appear to you to be when you first saw her?\n11 A. Probably 18.\n12 Q. And about when do you recall first seeing Jane in the office?\n13 A. I remember seeing Jane in the office with her mother.\n14 Q. And about when do you recall that happening for the first time?\n15 A. Probably the beginning to middle of my time there.\n16 Q. And about how many times did Jane visit the office, to your recollection?\n17 A. There was a few times. I can't really say how many times, but I would say maybe five.\n18 Q. And you mentioned Jane's mother. Do you recall how many times Jane's mother came with her to the office?",
      "position": "main"
    },
    {
      "type": "printed",
      "content": "SOUTHERN DISTRICT REPORTERS, P.C. (212) 805-0300",
      "position": "footer"
    },
    {
      "type": "printed",
      "content": "DOJ-OGR-00016544",
      "position": "footer"
    }
  ],
  "entities": {
    "people": [
      "Espinosa",
      "Jane",
      "Jane's mother",
      "MR. EVERDELL"
    ],
    "organizations": [
      "SOUTHERN DISTRICT REPORTERS, P.C."
    ],
    "locations": [],
    "dates": [
      "08/10/22"
    ],
    "reference_numbers": [
      "1:20-cr-00330-PAE",
      "761",
      "DOJ-OGR-00016544"
    ]
  },
  "additional_notes": "The document appears to be a court transcript with a clear and legible format. There are no visible redactions or damage."
}