{
  "document_metadata": {
    "page_number": "120",
    "document_number": "763",
    "date": "08/10/22",
    "document_type": "court transcript",
    "has_handwriting": false,
    "has_stamps": false
  },
  "full_text": "Case 1:20-cr-00330-AJN Document 763 Filed 08/10/22 Page 120 of 197 2661 LCHVMAX4 Dubin - direct entries? A. I've heard the name Jeff Schantz, but I can't remember who he is. Q. Okay. Anyone else in that entry, which is 915? A. I can't read the name after Jeff Schantz. Q. Neither can I. And then below that, do you see any names that you recognize? A. I see my husband's name, yes. Q. Okay. And then the next entry, flight 916, do you see any names that you recognize in that entry? A. I see my name, I see JE, I see Sophie. I can't read what comes after Sophie. Q. That's fine. MR. PAGLIUCA: We can take that down now. I'd like to next show the witness 662-RR, page 49. THE COURT: And if it's 662-RR, it may be published. MR. PAGLIUCA: Thank you, your Honor. And if we can go to the entries that are the fifth and fourth entries from the bottom. Q. I want to focus on someone named -- well, do you recognize the name Celina Midelfart? A. I do. Q. Do you recognize that as someone that was dating Mr. Epstein in the '97 time frame? SOUTHERN DISTRICT REPORTERS, P.C. (212) 805-0300 DOJ-OGR-00016849",
  "text_blocks": [
    {
      "type": "printed",
      "content": "Case 1:20-cr-00330-AJN Document 763 Filed 08/10/22 Page 120 of 197 2661",
      "position": "header"
    },
    {
      "type": "printed",
      "content": "LCHVMAX4 Dubin - direct",
      "position": "header"
    },
    {
      "type": "printed",
      "content": "1 entries? A. I've heard the name Jeff Schantz, but I can't remember who he is. Q. Okay. Anyone else in that entry, which is 915? A. I can't read the name after Jeff Schantz. Q. Neither can I. And then below that, do you see any names that you recognize? A. I see my husband's name, yes. Q. Okay. And then the next entry, flight 916, do you see any names that you recognize in that entry? A. I see my name, I see JE, I see Sophie. I can't read what comes after Sophie. Q. That's fine. MR. PAGLIUCA: We can take that down now. I'd like to next show the witness 662-RR, page 49. THE COURT: And if it's 662-RR, it may be published. MR. PAGLIUCA: Thank you, your Honor. And if we can go to the entries that are the fifth and fourth entries from the bottom. Q. I want to focus on someone named -- well, do you recognize the name Celina Midelfart? A. I do. Q. Do you recognize that as someone that was dating Mr. Epstein in the '97 time frame?",
      "position": "main"
    },
    {
      "type": "printed",
      "content": "SOUTHERN DISTRICT REPORTERS, P.C. (212) 805-0300",
      "position": "footer"
    },
    {
      "type": "printed",
      "content": "DOJ-OGR-00016849",
      "position": "footer"
    }
  ],
  "entities": {
    "people": [
      "Jeff Schantz",
      "Sophie",
      "Celina Midelfart",
      "Mr. Epstein",
      "JE",
      "MR. PAGLIUCA"
    ],
    "organizations": [
      "SOUTHERN DISTRICT REPORTERS, P.C."
    ],
    "locations": [],
    "dates": [
      "08/10/22",
      "'97"
    ],
    "reference_numbers": [
      "1:20-cr-00330-AJN",
      "763",
      "662-RR",
      "915",
      "916",
      "49",
      "DOJ-OGR-00016849"
    ]
  },
  "additional_notes": "The document appears to be a court transcript with a clear and readable format. There are no visible redactions or damage."
}