{
  "document_metadata": {
    "page_number": "73",
    "document_number": "763",
    "date": "08/10/22",
    "document_type": "Court Transcript",
    "has_handwriting": false,
    "has_stamps": false
  },
  "full_text": "Case 1:20-cr-00330-AJN Document 763 Filed 08/10/22 Page 73 of 197 2614\nLCHCmax3 Young - direct\n1 BY MS. MENNINGER:\n2 Q. And I think it's Jane, not Kate?\n3 A. I'm sorry. I'm sorry.\n4 Q. That's fine. If you don't mind reading it again with Jane.\n5 A. In the beginning, Jane would be with her mother and brothers at Epstein's house.\n6 \n7 Q. Now, if I could have you take a look at the tab 3. Do you recognize this report?\n8 \n9 A. Yes.\n10 Q. This one actually was authored by your partner, Mr. Byrne or Detective Byrne; right?\n11 \n12 A. Yes.\n13 Q. But you checked his work?\n14 A. Yes, I signed off on it.\n15 Q. And this one relates to an interview that took place in November of 2019; right?\n16 \n17 A. Yes, that's correct.\n18 Q. And if I could direct your attention on this interview with Jane to the fourth full paragraph, the third line, begins Jane, Jane was not. If you could read that sentence with Jane.\n19 \n20 Jane was not sure if Maxwell ever called her to make appointments.\n21 A. \n22 \n23 Q. Thank you. And now if I could have you turn to tab 5. Are you there?\n24 \n25 A. Yes.\nSOUTHERN DISTRICT REPORTERS, P.C. (212) 805-0300\nDOJ-OGR-00016802",
  "text_blocks": [
    {
      "type": "printed",
      "content": "Case 1:20-cr-00330-AJN Document 763 Filed 08/10/22 Page 73 of 197 2614",
      "position": "header"
    },
    {
      "type": "printed",
      "content": "LCHCmax3 Young - direct",
      "position": "header"
    },
    {
      "type": "printed",
      "content": "BY MS. MENNINGER: ...",
      "position": "main"
    },
    {
      "type": "printed",
      "content": "SOUTHERN DISTRICT REPORTERS, P.C. (212) 805-0300",
      "position": "footer"
    },
    {
      "type": "printed",
      "content": "DOJ-OGR-00016802",
      "position": "footer"
    }
  ],
  "entities": {
    "people": [
      "MS. MENNINGER",
      "Jane",
      "Kate",
      "Mr. Byrne",
      "Detective Byrne",
      "Maxwell",
      "Young"
    ],
    "organizations": [
      "SOUTHERN DISTRICT REPORTERS, P.C."
    ],
    "locations": [
      "Epstein's house"
    ],
    "dates": [
      "08/10/22",
      "November 2019"
    ],
    "reference_numbers": [
      "1:20-cr-00330-AJN",
      "763",
      "DOJ-OGR-00016802"
    ]
  },
  "additional_notes": "The document appears to be a court transcript with a clear and readable format. There are no visible redactions or damage."
}