{
  "document_metadata": {
    "page_number": "14",
    "document_number": "DOJ-OGR-00015743",
    "date": "2/14/2005",
    "document_type": "Checklist",
    "has_handwriting": false,
    "has_stamps": false
  },
  "full_text": "MS MAXWELL'S BATHROOM TOILETRIES\nCHECK OFF LIST\nFacial Moisturizer (La Mer)\nBabor Foam Mask\nKiehl's Cucumber Toner\nKiehl's Washable Cleansing Milk\nLa Mer Eye Balm\nEvian Face Mist\nClarins Crème Masvelt Body Shaping Crème\nBabor Natural Body Peeling\nLancôme Exfoliance Gel\nBody Lotion (Frédéric Fekkai, Clinique Deep Comfort Body Moisture)\nAquaphor Hand Cream\nSecret Original Solid Deodorant\nRound cotton pads\nQ-Tips\nToothbrush (Oral B / Hard)\nElectric Toothbrush (Braun Ultra Plaque Remover)\nToothpaste (Arm & Hammer Dental Care and Mentadent)\nDental Floss (Johnson & Johnson Reach / Mint waxed)\nScope mouthwash\nSunscreen (Lancôme Soleil SPF 30 Face Creme)\nKiehl's Lip Balm with SPF\n2/14/200514\nDOJ-OGR-00015743",
  "text_blocks": [
    {
      "type": "printed",
      "content": "MS MAXWELL'S BATHROOM TOILETRIES\nCHECK OFF LIST",
      "position": "header"
    },
    {
      "type": "printed",
      "content": "Facial Moisturizer (La Mer)\nBabor Foam Mask\nKiehl's Cucumber Toner\nKiehl's Washable Cleansing Milk\nLa Mer Eye Balm\nEvian Face Mist\nClarins Crème Masvelt Body Shaping Crème\nBabor Natural Body Peeling\nLancôme Exfoliance Gel\nBody Lotion (Frédéric Fekkai, Clinique Deep Comfort Body Moisture)\nAquaphor Hand Cream\nSecret Original Solid Deodorant\nRound cotton pads\nQ-Tips\nToothbrush (Oral B / Hard)\nElectric Toothbrush (Braun Ultra Plaque Remover)\nToothpaste (Arm & Hammer Dental Care and Mentadent)\nDental Floss (Johnson & Johnson Reach / Mint waxed)\nScope mouthwash\nSunscreen (Lancôme Soleil SPF 30 Face Creme)\nKiehl's Lip Balm with SPF",
      "position": "middle"
    },
    {
      "type": "printed",
      "content": "2/14/2005\n14\nDOJ-OGR-00015743",
      "position": "footer"
    }
  ],
  "entities": {
    "people": [
      "MS MAXWELL"
    ],
    "organizations": [
      "La Mer",
      "Babor",
      "Kiehl's",
      "Evian",
      "Clarins",
      "Lancôme",
      "Frédéric Fekkai",
      "Clinique",
      "Aquaphor",
      "Secret",
      "Oral B",
      "Braun",
      "Arm & Hammer",
      "Johnson & Johnson",
      "Mentadent",
      "Scope",
      "Soleil"
    ],
    "locations": [],
    "dates": [
      "2/14/2005"
    ],
    "reference_numbers": [
      "DOJ-OGR-00015743"
    ]
  },
  "additional_notes": "The document is a checklist of bathroom toiletries used by MS MAXWELL. The list includes various skincare and oral care products from different brands. The document is dated 2/14/2005 and has a page number 14. It also contains a reference number DOJ-OGR-00015743."
}