{
  "document_metadata": {
    "page_number": "6",
    "document_number": "20-20033-PAE",
    "date": null,
    "document_type": "Court Document",
    "has_handwriting": false,
    "has_stamps": false
  },
  "full_text": "Statutes § 796.07,2 and to one count of solicitation of minors to engage in prostitution, in violation of Florida Statutes § 796.03.3 He agreed to receive a sentence of eighteen months' imprisonment on the two charges. In consideration of Epstein's agreement, the NPA states that \"the United States also agrees that it will not institute any criminal charges against any potential co-conspirators of Epstein, including but not limited to Sarah Kellen, Adriana Ross, Lesley Groff, or Nadia Marcinkova.\"4\n\n2. Maxwell's Indictment and Trial-Related Proceedings\n\nThe Indictment filed against Maxwell contained eight counts, six of which proceeded to trial.5 Prior to the commencement of trial,\n\n2 Florida Statutes § 796.07 provides in relevant part:\n\n(2) It is unlawful:\n\n(f) To solicit, induce, entice, or procure another to commit prostitution, lewdness, or assignation.\n\n3 Florida Statutes § 796.03, which has since been repealed, provided in relevant part: \"A person who procures for prostitution, or causes to be prostituted, any person who is under the age of 18 years commits a felony of the second degree.\"\n\n4 A-178.\n\n5 Count One charged Maxwell with conspiracy to entice minors to travel to engage in illegal sex acts, in violation of 18 U.S.C. § 371. Count Two charged Maxwell with enticement of a minor to travel to engage in illegal sex acts, in violation of 18 U.S.C. §§ 2422 and 2. Count Three charged Maxwell with conspiracy to transport minors with intent to engage in criminal sexual activity, in violation of 18 U.S.C. § 371. Count Four charged Maxwell with transportation of a minor with intent to engage in criminal sexual activity, in violation of 18 U.S.C. §§ 2423(a) and 2. Count Five charged Maxwell with sex trafficking conspiracy, in",
  "text_blocks": [
    {
      "type": "printed",
      "content": "Statutes § 796.07,2 and to one count of solicitation of minors to engage in prostitution, in violation of Florida Statutes § 796.03.3 He agreed to receive a sentence of eighteen months' imprisonment on the two charges. In consideration of Epstein's agreement, the NPA states that \"the United States also agrees that it will not institute any criminal charges against any potential co-conspirators of Epstein, including but not limited to Sarah Kellen, Adriana Ross, Lesley Groff, or Nadia Marcinkova.\"4",
      "position": "top"
    },
    {
      "type": "printed",
      "content": "2. Maxwell's Indictment and Trial-Related Proceedings",
      "position": "middle"
    },
    {
      "type": "printed",
      "content": "The Indictment filed against Maxwell contained eight counts, six of which proceeded to trial.5 Prior to the commencement of trial,",
      "position": "middle"
    },
    {
      "type": "printed",
      "content": "2 Florida Statutes § 796.07 provides in relevant part:\n\n(2) It is unlawful:\n\n(f) To solicit, induce, entice, or procure another to commit prostitution, lewdness, or assignation.",
      "position": "middle"
    },
    {
      "type": "printed",
      "content": "3 Florida Statutes § 796.03, which has since been repealed, provided in relevant part: \"A person who procures for prostitution, or causes to be prostituted, any person who is under the age of 18 years commits a felony of the second degree.\"",
      "position": "middle"
    },
    {
      "type": "printed",
      "content": "4 A-178.",
      "position": "middle"
    },
    {
      "type": "printed",
      "content": "5 Count One charged Maxwell with conspiracy to entice minors to travel to engage in illegal sex acts, in violation of 18 U.S.C. § 371. Count Two charged Maxwell with enticement of a minor to travel to engage in illegal sex acts, in violation of 18 U.S.C. §§ 2422 and 2. Count Three charged Maxwell with conspiracy to transport minors with intent to engage in criminal sexual activity, in violation of 18 U.S.C. § 371. Count Four charged Maxwell with transportation of a minor with intent to engage in criminal sexual activity, in violation of 18 U.S.C. §§ 2423(a) and 2. Count Five charged Maxwell with sex trafficking conspiracy, in",
      "position": "bottom"
    }
  ],
  "entities": {
    "people": [
      "Epstein",
      "Sarah Kellen",
      "Adriana Ross",
      "Lesley Groff",
      "Nadia Marcinkova",
      "Maxwell"
    ],
    "organizations": [
      "United States"
    ],
    "locations": [
      "Florida"
    ],
    "dates": [],
    "reference_numbers": [
      "20-20033-PAE",
      "18 U.S.C. § 371",
      "18 U.S.C. §§ 2422 and 2",
      "18 U.S.C. §§ 2423(a) and 2",
      "Florida Statutes § 796.07",
      "Florida Statutes § 796.03"
    ]
  },
  "additional_notes": "The document appears to be a court document related to the case of Maxwell, discussing the indictment and trial proceedings. The text is mostly printed, with no visible handwriting or stamps. The document is likely a page from a larger report or filing."
}