{
  "document_metadata": {
    "page_number": "6",
    "document_number": "779",
    "date": "08/22/22",
    "document_type": "court transcript",
    "has_handwriting": false,
    "has_stamps": false
  },
  "full_text": "Case 1:20-cr-00330-PAE Document 779 Filed 08/22/22 Page 6 of 101\nM6SQmax1\n1 presentence report?\n2 MS. MOE: Yes, your Honor.\n3 THE COURT: Thank you.\n4 So we will turn first -- we'll set aside first the guideline calculation. We'll turn to the factual accuracy of the report. And I did receive substantial factual objections to factual assertions in the report. I am prepared to go through those with respect to any continuing factual objections by the defense.\n10 Let me confirm, Ms. Moe, does the government have any objections to the report regarding factual accuracy?\n12 MS. MOE: None, aside from those which are already noted in the PSR.\n14 THE COURT: No continuing objections.\n15 MS. MOE: That's correct, your Honor.\n16 THE COURT: Mr. Everdell, I know that you do have continuing objections. Tell me where you'd like to begin.\n18 MR. EVERDELL: Well, your Honor, I don't know if the Court is planning on resolving each and every factual discrepancy or dispute or whether there are certain ones that the court will find are relevant to sentencing or whether we should go through each in detail.\n23 THE COURT: I am prepared to -- what I typically do is go through each one so that if there is a correction to the report that is being requested to be made, whether it's\nSOUTHERN DISTRICT REPORTERS, P.C.\n(212) 805-0300\nDOJ-OGR-00014753",
  "text_blocks": [
    {
      "type": "printed",
      "content": "Case 1:20-cr-00330-PAE Document 779 Filed 08/22/22 Page 6 of 101",
      "position": "header"
    },
    {
      "type": "printed",
      "content": "M6SQmax1",
      "position": "header"
    },
    {
      "type": "printed",
      "content": "1 presentence report?\n2 MS. MOE: Yes, your Honor.\n3 THE COURT: Thank you.\n4 So we will turn first -- we'll set aside first the guideline calculation. We'll turn to the factual accuracy of the report. And I did receive substantial factual objections to factual assertions in the report. I am prepared to go through those with respect to any continuing factual objections by the defense.\n10 Let me confirm, Ms. Moe, does the government have any objections to the report regarding factual accuracy?\n12 MS. MOE: None, aside from those which are already noted in the PSR.\n14 THE COURT: No continuing objections.\n15 MS. MOE: That's correct, your Honor.\n16 THE COURT: Mr. Everdell, I know that you do have continuing objections. Tell me where you'd like to begin.\n18 MR. EVERDELL: Well, your Honor, I don't know if the Court is planning on resolving each and every factual discrepancy or dispute or whether there are certain ones that the court will find are relevant to sentencing or whether we should go through each in detail.\n23 THE COURT: I am prepared to -- what I typically do is go through each one so that if there is a correction to the report that is being requested to be made, whether it's",
      "position": "main content"
    },
    {
      "type": "printed",
      "content": "SOUTHERN DISTRICT REPORTERS, P.C.\n(212) 805-0300\nDOJ-OGR-00014753",
      "position": "footer"
    }
  ],
  "entities": {
    "people": [
      "Ms. Moe",
      "Mr. Everdell"
    ],
    "organizations": [
      "SOUTHERN DISTRICT REPORTERS, P.C."
    ],
    "locations": [],
    "dates": [
      "08/22/22"
    ],
    "reference_numbers": [
      "1:20-cr-00330-PAE",
      "779",
      "DOJ-OGR-00014753"
    ]
  },
  "additional_notes": "The document appears to be a court transcript with a clear and legible format. There are no visible redactions or damage."
}