{
  "document_metadata": {
    "page_number": "54",
    "document_number": "761",
    "date": "08/10/22",
    "document_type": "court transcript",
    "has_handwriting": false,
    "has_stamps": false
  },
  "full_text": "Case 1:20-cr-00330-PAE Document 761 Filed 08/10/22 Page 54 of 246 2349 LCGCmax2 Espinosa - direct 1 Q. When you arranged these commercial flights, did you call the airlines directly or did you use a travel service? 2 A. We used a travel agency. 3 Q. And what was the name of that travel agency? 4 A. Shoppers Travel. 5 Q. Do you know where that was located? 6 A. It was in New York, but I don't know where. I never was there in person, just on the phone. 7 Q. As part of your responsibilities as Ghislaine's executive assistant, did you ever book massages for Ms. Maxwell? 8 A. Yes. 9 Q. And where did you book those massages? 10 A. She had her places in SoHo. She liked Bliss Spa, she liked the Red Door, Elizabeth Arden, places like that. 11 Q. Were these professional massage places? 12 A. Yes. 13 Q. Did you ever schedule a massage for Jeffrey Epstein? 14 A. Yes. 15 Q. Do you remember how many times, roughly, you did that? 16 A. Maybe ten my entire time I was there. I don't -- five to ten. A handful of times. 17 Q. Do you remember any of the masseuses he used? 18 A. I do remember a few names. What comes to mind is there was a Lydia, a Monica. I don't really remember. It's hard for me to recall off the top of my head, but if I hear them that's SOUTHERN DISTRICT REPORTERS, P.C. (212) 805-0300 DOJ-OGR-00016537",
  "text_blocks": [
    {
      "type": "printed",
      "content": "Case 1:20-cr-00330-PAE Document 761 Filed 08/10/22 Page 54 of 246 2349",
      "position": "header"
    },
    {
      "type": "printed",
      "content": "LCGCmax2 Espinosa - direct",
      "position": "header"
    },
    {
      "type": "printed",
      "content": "1 Q. When you arranged these commercial flights, did you call the airlines directly or did you use a travel service? 2 A. We used a travel agency. 3 Q. And what was the name of that travel agency? 4 A. Shoppers Travel. 5 Q. Do you know where that was located? 6 A. It was in New York, but I don't know where. I never was there in person, just on the phone. 7 Q. As part of your responsibilities as Ghislaine's executive assistant, did you ever book massages for Ms. Maxwell? 8 A. Yes. 9 Q. And where did you book those massages? 10 A. She had her places in SoHo. She liked Bliss Spa, she liked the Red Door, Elizabeth Arden, places like that. 11 Q. Were these professional massage places? 12 A. Yes. 13 Q. Did you ever schedule a massage for Jeffrey Epstein? 14 A. Yes. 15 Q. Do you remember how many times, roughly, you did that? 16 A. Maybe ten my entire time I was there. I don't -- five to ten. A handful of times. 17 Q. Do you remember any of the masseuses he used? 18 A. I do remember a few names. What comes to mind is there was a Lydia, a Monica. I don't really remember. It's hard for me to recall off the top of my head, but if I hear them that's",
      "position": "main"
    },
    {
      "type": "printed",
      "content": "SOUTHERN DISTRICT REPORTERS, P.C. (212) 805-0300",
      "position": "footer"
    },
    {
      "type": "printed",
      "content": "DOJ-OGR-00016537",
      "position": "footer"
    }
  ],
  "entities": {
    "people": [
      "Ghislaine",
      "Ms. Maxwell",
      "Jeffrey Epstein",
      "Lydia",
      "Monica"
    ],
    "organizations": [
      "Shoppers Travel",
      "Bliss Spa",
      "Red Door",
      "Elizabeth Arden",
      "SOUTHERN DISTRICT REPORTERS, P.C."
    ],
    "locations": [
      "New York",
      "SoHo"
    ],
    "dates": [
      "08/10/22"
    ],
    "reference_numbers": [
      "1:20-cr-00330-PAE",
      "761",
      "DOJ-OGR-00016537"
    ]
  },
  "additional_notes": "The document appears to be a court transcript with a clear and legible format. There are no visible redactions or damage."
}