{
  "document_metadata": {
    "page_number": "44",
    "document_number": "DOJ-OGR-00015959",
    "date": null,
    "document_type": "Pilot's Flight Log",
    "has_handwriting": true,
    "has_stamps": false
  },
  "full_text": "Date Aircraft Make and Model Aircraft Identification Mark Points of Departure & Arrival Miles Flown Flight No. Remarks, Procedures, Maneuvers, Endorsements Number of Landings Aircraft Category... 1966 26 G1159B N908JE TEB CMH 846 JE 1 1 2 26 \" \" \" CMH PBI 897 JE 1 91 26 \" \" \" PBI TEB 908 JE, GM, DEDIER 1 1 2 4 10 \" \" \" TEB PBI 902 JE 2 5 14 \" \" \" PBI TEB 903 JE, 1 FEMALE 2 4 15 \" \" \" TEB CMH 904 TO CMH FOR PICK UP 1 2 15 \" \" \" CMH TEB 905 JE DARREN IRA LEAGSMAP, JEFF SCHANTZ 1 2 19 \" \" \" TEB PBI 906 JE, DEDIER AZADUMGE 2 3 22 \" \" \" PBI TEB 907 JE, GM, DEDIER CALADUMGE 2 3 24 \" \" \" TEB SAF 908 JE, GM, LARRY 4 1 25 \" \" \" SAF PBI 909 JE, GM, SHANNON 3 2 27 \" \" \" PBI TEB 910 JE, GM, JOE POSHCKOW, SHARON 2 4 30 \" \" \" TEB DCA 911 JE, ANDY STEWART, LESLIE GELB, BRIAN MATTHEW, LESTER POLLACK, STEPHEN BURST 1 1 6 30 \" \" \" DCA TEB 912 JE, ANDY STEWART, LESLIE GELB, 3PAX 6 31 \" \" \" TEB PBI 913 JE, GM, DEDIER CALADUMGE 2 2 Nov 4 \" \" \" PBI TEB 914 JE, GM, DEDIER CALADUMGE 2 5 7 \" \" \" TEB PBI 915 JE, ANDY STEWART, JEFF SCHANTZ, JEANNE (4) GLENN, CHUCK MANNY, LINDA LEIGH 2 2 11 \" \" \" PBI TEB 916 JE, GM, JEFF SCHANTZ, JOE some text 2 2 15 \" \" \" TEB CMH 917 JE, GM, JEFF SCHANTZ, DARREN some text 1 3 I certify that the statements made by me on this form are true. Pilot's Signature David Rodgers Page Total 11 9 387 Amount Forward 5573 6768 7 Total to Date 5647 680 74",
  "text_blocks": [
    {
      "type": "printed",
      "content": "Date Aircraft Make and Model Aircraft Identification Mark Points of Departure & Arrival Miles Flown Flight No. Remarks, Procedures, Maneuvers, Endorsements Number of Landings Aircraft Category...",
      "position": "header"
    },
    {
      "type": "handwritten",
      "content": "1966 26 G1159B N908JE TEB CMH 846 JE 1 1 2 26 \" \" \" CMH PBI 897 JE 1 91 26 \" \" \" PBI TEB 908 JE, GM, DEDIER 1 1 2 4 10 \" \" \" TEB PBI 902 JE 2 5 14 \" \" \" PBI TEB 903 JE, 1 FEMALE 2 4 15 \" \" \" TEB CMH 904 TO CMH FOR PICK UP 1 2 15 \" \" \" CMH TEB 905 JE DARREN IRA LEAGSMAP, JEFF SCHANTZ 1 2 19 \" \" \" TEB PBI 906 JE, DEDIER AZADUMGE 2 3 22 \" \" \" PBI TEB 907 JE, GM, DEDIER CALADUMGE 2 3 24 \" \" \" TEB SAF 908 JE, GM, LARRY 4 1 25 \" \" \" SAF PBI 909 JE, GM, SHANNON 3 2 27 \" \" \" PBI TEB 910 JE, GM, JOE POSHCKOW, SHARON 2 4 30 \" \" \" TEB DCA 911 JE, ANDY STEWART, LESLIE GELB, BRIAN MATTHEW, LESTER POLLACK, STEPHEN BURST 1 1 6 30 \" \" \" DCA TEB 912 JE, ANDY STEWART, LESLIE GELB, 3PAX 6 31 \" \" \" TEB PBI 913 JE, GM, DEDIER CALADUMGE 2 2 Nov 4 \" \" \" PBI TEB 914 JE, GM, DEDIER CALADUMGE 2 5 7 \" \" \" TEB PBI 915 JE, ANDY STEWART, JEFF SCHANTZ, JEANNE (4) GLENN, CHUCK MANNY, LINDA LEIGH 2 2 11 \" \" \" PBI TEB 916 JE, GM, JEFF SCHANTZ, JOE some text 2 2 15 \" \" \" TEB CMH 917 JE, GM, JEFF SCHANTZ, DARREN some text 1 3",
      "position": "main"
    },
    {
      "type": "handwritten",
      "content": "I certify that the statements made by me on this form are true. Pilot's Signature David Rodgers",
      "position": "footer"
    },
    {
      "type": "printed",
      "content": "Page Total 11 9 387 Amount Forward 5573 6768 7 Total to Date 5647 680 74",
      "position": "footer"
    }
  ],
  "entities": {
    "people": [
      "David Rodgers",
      "Darren Ira Leagsmap",
      "Jeff Schantz",
      "Dedier Azadumge",
      "Larry",
      "Shannon",
      "Joe Poshckow",
      "Andy Stewart",
      "Leslie Gelb",
      "Brian Matthew",
      "Lester Pollack",
      "Stephen Burst",
      "Jeanne",
      "Glenn",
      "Chuck Manny",
      "Linda Leigh"
    ],
    "organizations": [],
    "locations": [
      "TEB",
      "CMH",
      "PBI",
      "SAF",
      "DCA"
    ],
    "dates": [
      "1966"
    ],
    "reference_numbers": [
      "G1159B",
      "N908JE",
      "DOJ-OGR-00015959"
    ]
  },
  "additional_notes": "The document is a pilot's flight log with handwritten entries. The log includes details such as date, aircraft make and model, identification mark, points of departure and arrival, miles flown, flight number, remarks, procedures, maneuvers, endorsements, number of landings, and aircraft category. The document has some minor redactions."
}