{
  "document_metadata": {
    "page_number": "82",
    "document_number": "759",
    "date": "08/10/22",
    "document_type": "court transcript",
    "has_handwriting": false,
    "has_stamps": false
  },
  "full_text": "Case 1:20-cr-00330-PAE Document 759 Filed 08/10/22 Page 82 of 267 2110\nLCACmax3 A. Farmer - cross\n1 York; right?\n2 A. That's correct.\n3 Q. When you went to Epstein's house, you were there the whole time with your sister; correct?\n4 A. Yes.\n5 Q. And it was there that Mr. Epstein spoke with you about college applications?\n6 A. Yes.\n7 Q. And discussed the college application process; right?\n8 A. That's right.\n9 Q. He urged you to consider UCLA, I think it was?\n10 A. Yes.\n11 Q. He talked to you about traveling abroad for the summer?\n12 A. Yes.\n13 Q. And how that might help your college applications?\n14 A. Yes.\n15 Q. You did ultimately go to an ivy league school; right?\n16 A. Yes.\n17 Q. And he surprised you with tickets to the Phantom of the Opera; right?\n18 A. Yes.\n19 Q. You said you were really excited about seeing the Phantom of the Opera; right?\n20 A. I was.\n21 Q. It wasn't the first time you had seen it?\n22 SOUTHERN DISTRICT REPORTERS, P.C. (212) 805-0300 DOJ-OGR-00016298",
  "text_blocks": [
    {
      "type": "printed",
      "content": "Case 1:20-cr-00330-PAE Document 759 Filed 08/10/22 Page 82 of 267 2110",
      "position": "header"
    },
    {
      "type": "printed",
      "content": "LCACmax3 A. Farmer - cross",
      "position": "header"
    },
    {
      "type": "printed",
      "content": "1 York; right?\n2 A. That's correct.\n3 Q. When you went to Epstein's house, you were there the whole time with your sister; correct?\n4 A. Yes.\n5 Q. And it was there that Mr. Epstein spoke with you about college applications?\n6 A. Yes.\n7 Q. And discussed the college application process; right?\n8 A. That's right.\n9 Q. He urged you to consider UCLA, I think it was?\n10 A. Yes.\n11 Q. He talked to you about traveling abroad for the summer?\n12 A. Yes.\n13 Q. And how that might help your college applications?\n14 A. Yes.\n15 Q. You did ultimately go to an ivy league school; right?\n16 A. Yes.\n17 Q. And he surprised you with tickets to the Phantom of the Opera; right?\n18 A. Yes.\n19 Q. You said you were really excited about seeing the Phantom of the Opera; right?\n20 A. I was.\n21 Q. It wasn't the first time you had seen it?",
      "position": "main"
    },
    {
      "type": "printed",
      "content": "SOUTHERN DISTRICT REPORTERS, P.C. (212) 805-0300",
      "position": "footer"
    },
    {
      "type": "printed",
      "content": "DOJ-OGR-00016298",
      "position": "footer"
    }
  ],
  "entities": {
    "people": [
      "Epstein",
      "Farmer"
    ],
    "organizations": [
      "UCLA",
      "SOUTHERN DISTRICT REPORTERS, P.C.",
      "ivy league school"
    ],
    "locations": [
      "York",
      "Epstein's house"
    ],
    "dates": [
      "08/10/22"
    ],
    "reference_numbers": [
      "1:20-cr-00330-PAE",
      "759",
      "DOJ-OGR-00016298"
    ]
  },
  "additional_notes": "The document appears to be a court transcript, likely from a criminal case involving Jeffrey Epstein. The text is mostly printed, with no visible handwriting or stamps. The footer contains the name and contact information of the court reporters and a reference number."
}