{
  "document_metadata": {
    "page_number": "1",
    "document_number": "159224/2016",
    "date": "03/05/2020",
    "document_type": "Court Document",
    "has_handwriting": false,
    "has_stamps": true
  },
  "full_text": "FILED: NEW YORK COUNTY CLERK 03/05/2020 12:59 PM INDEX NO. 159224/2016 RECEIVED NYSCEF: 03/05/2020 Page 1 April 9, 2019 1 SUPREME COURT OF THE STATE OF NEW YORK COUNTY OF NEW YORK -------------------------------------------------------------------X SHELDON BARR and THOMAS GARDNER, Plaintiffs, -against- CITY OF NEW YORK and 116 EAST 65TH STREET, LLC, Defendants, INDEX NO.: 159225/2010 -------------------------------------------------------------------X 535 Fifth Avenue New York, New York April 9, 2019 10:07 a.m. EXAMINATION BEFORE TRIAL of the Defendant, 116 EAST 65TH STREET, LLC, by GHISLAINE MAXWELL, in the above-entitled action, held at the above time and place, taken before a Notary Public of the State of New York, pursuant to Order and Stipulations between Counsel. DEITZ Court Reporting... A Lexitas Company 800-678-0166 GOVERNMENT EXHIBIT 610-A S2 20 Cr. 330 (AJN) DOJ-OGR-00015788",
  "text_blocks": [
    {
      "type": "printed",
      "content": "FILED: NEW YORK COUNTY CLERK 03/05/2020 12:59 PM INDEX NO. 159224/2016 RECEIVED NYSCEF: 03/05/2020 Page 1",
      "position": "header"
    },
    {
      "type": "printed",
      "content": "April 9, 2019 1 SUPREME COURT OF THE STATE OF NEW YORK COUNTY OF NEW YORK -------------------------------------------------------------------X SHELDON BARR and THOMAS GARDNER, Plaintiffs, -against- CITY OF NEW YORK and 116 EAST 65TH STREET, LLC, Defendants, INDEX NO.: 159225/2010 -------------------------------------------------------------------X 535 Fifth Avenue New York, New York April 9, 2019 10:07 a.m. EXAMINATION BEFORE TRIAL of the Defendant, 116 EAST 65TH STREET, LLC, by GHISLAINE MAXWELL, in the above-entitled action, held at the above time and place, taken before a Notary Public of the State of New York, pursuant to Order and Stipulations between Counsel.",
      "position": "middle"
    },
    {
      "type": "printed",
      "content": "DEITZ Court Reporting... A Lexitas Company 800-678-0166",
      "position": "footer"
    },
    {
      "type": "stamp",
      "content": "GOVERNMENT EXHIBIT 610-A S2 20 Cr. 330 (AJN) DOJ-OGR-00015788",
      "position": "footer"
    }
  ],
  "entities": {
    "people": [
      "SHELDON BARR",
      "THOMAS GARDNER",
      "GHISLAINE MAXWELL"
    ],
    "organizations": [
      "CITY OF NEW YORK",
      "116 EAST 65TH STREET, LLC",
      "DEITZ Court Reporting",
      "Lexitas Company"
    ],
    "locations": [
      "NEW YORK",
      "Fifth Avenue"
    ],
    "dates": [
      "April 9, 2019",
      "03/05/2020"
    ],
    "reference_numbers": [
      "159224/2016",
      "159225/2010",
      "S2 20 Cr. 330 (AJN)",
      "DOJ-OGR-00015788"
    ]
  },
  "additional_notes": "The document appears to be a court filing with a stamp indicating it is a government exhibit. The quality is clear, and there are no visible redactions or damage."
}