{
  "document_metadata": {
    "page_number": "12",
    "document_number": "DOJ-OGR-00015741",
    "date": "2/14/2005",
    "document_type": "Checklist",
    "has_handwriting": false,
    "has_stamps": false
  },
  "full_text": "MASTER BATHROOM TOILETRIES CHECK OFF LIST\n\nGillette MACH 3 Razor with extra blades (change blade after every use)\nShaving Cream (Kiehl's Close Shavers Squadron)\nSecret Original Solid Deodorant\nLever 2000 soap\nNoxzema Plus Face Wash\nFacial moisturizers (Kiehl's Ultra Facial Moisturizer, Babor)\nAquaphor Hand Cream\nCalifornia Mango Lotion\nBubble bath and shower gels (variety)\nShampoo / Conditioner (White Rain Coconut Essence, Biolage, Nexxus Simply Silver)\nHair finishing cream (Paul Mitchell Stickworks)\nPeter Thomas Roth Sunscreen (face and body)\nKiehl's Lip Balm with SPF\nQ-Tips\nRound cotton pads\nToothpaste (Arm & Hammer Dental Care and Mentadent)\nToothbrush (Oral B / Hard)\nElectric Toothbrush (Braun Ultra Plaque Remover)\nScope mouthwash\nDental Floss (Johnson & Johnson Reach / Mint waxed)\nBaby Powder (Johnson & Johnson)\nMason Pearson Hairbrush\nHair Comb\nTweezers\nFingernail clippers and file\n\nDATE: 2/14/2005 SIGNATURE: 12",
  "text_blocks": [
    {
      "type": "printed",
      "content": "MASTER BATHROOM TOILETRIES CHECK OFF LIST",
      "position": "header"
    },
    {
      "type": "printed",
      "content": "Gillette MACH 3 Razor with extra blades (change blade after every use)\nShaving Cream (Kiehl's Close Shavers Squadron)\nSecret Original Solid Deodorant\nLever 2000 soap\nNoxzema Plus Face Wash\nFacial moisturizers (Kiehl's Ultra Facial Moisturizer, Babor)\nAquaphor Hand Cream\nCalifornia Mango Lotion\nBubble bath and shower gels (variety)\nShampoo / Conditioner (White Rain Coconut Essence, Biolage, Nexxus Simply Silver)\nHair finishing cream (Paul Mitchell Stickworks)\nPeter Thomas Roth Sunscreen (face and body)\nKiehl's Lip Balm with SPF\nQ-Tips\nRound cotton pads\nToothpaste (Arm & Hammer Dental Care and Mentadent)\nToothbrush (Oral B / Hard)\nElectric Toothbrush (Braun Ultra Plaque Remover)\nScope mouthwash\nDental Floss (Johnson & Johnson Reach / Mint waxed)\nBaby Powder (Johnson & Johnson)\nMason Pearson Hairbrush\nHair Comb\nTweezers\nFingernail clippers and file",
      "position": "middle"
    },
    {
      "type": "printed",
      "content": "DATE: 2/14/2005 SIGNATURE:",
      "position": "footer"
    },
    {
      "type": "printed",
      "content": "12",
      "position": "footer"
    },
    {
      "type": "printed",
      "content": "DOJ-OGR-00015741",
      "position": "margin"
    }
  ],
  "entities": {
    "people": [
      "Peter Thomas Roth",
      "Paul Mitchell"
    ],
    "organizations": [
      "Gillette",
      "Kiehl's",
      "Secret",
      "Lever",
      "Noxzema",
      "Babor",
      "Aquaphor",
      "White Rain",
      "Biolage",
      "Nexxus",
      "Arm & Hammer",
      "Oral B",
      "Braun",
      "Johnson & Johnson",
      "Mason Pearson"
    ],
    "locations": [
      "California"
    ],
    "dates": [
      "2/14/2005"
    ],
    "reference_numbers": [
      "DOJ-OGR-00015741"
    ]
  },
  "additional_notes": "The document is a checklist of toiletries found in a master bathroom. It includes a list of various personal care items and their corresponding brands. The document is dated 2/14/2005 and has a page number of 12."
}