{
  "document_metadata": {
    "page_number": "246 of 247",
    "document_number": "743",
    "date": "08/10/22",
    "document_type": "INDEX OF EXAMINATION",
    "has_handwriting": false,
    "has_stamps": false
  },
  "full_text": "Case 1:20-cr-00330-PAE Document 743 Filed 08/10/22 Page 246 of 247 405\n\n1 INDEX OF EXAMINATION\n2 Examination of: Page\n3 LAWRENCE VISOSKI\n4 Direct By Ms. Comey . . . . . . . . . . . . . . 138\n5 Cross By Mr. Everdell . . . . . . . . . . . . . . 182\n6 Redirect By Ms. Comey . . . . . . . . . . . . . . 281\n7 JANE\n8 Direct By Ms. Moe . . . . . . . . . . . . . . . . 286\n9 Cross By Ms. Menninger . . . . . . . . . . . . . . 363\n10 GOVERNMENT EXHIBITS Received\n11 Exhibit No.\n12 327, 310 . . . . . . . . . . . . . . . . . . . . 141\n13 334, 335 . . . . . . . . . . . . . . . . . . . . 142\n14 328 . . . . . . . . . . . . . . . . . . . . . . 143\n15 323, 706 . . . . . . . . . . . . . . . . . . . . 148\n16 705 . . . . . . . . . . . . . . . . . . . . . . 152\n17 346 . . . . . . . . . . . . . . . . . . . . . . 155\n18 308 . . . . . . . . . . . . . . . . . . . . . . 156\n19 326 . . . . . . . . . . . . . . . . . . . . . . 157\n20 703 . . . . . . . . . . . . . . . . . . . . . . 158\n21 311, 312 . . . . . . . . . . . . . . . . . . . . 163\n22 344, 345 . . . . . . . . . . . . . . . . . . . . 164\n23 315, 336 . . . . . . . . . . . . . . . . . . . . 165\n24 301, 302 . . . . . . . . . . . . . . . . . . . . 167\n25 303 . . . . . . . . . . . . . . . . . . . . . . 169\nSOUTHERN DISTRICT REPORTERS, P.C. (212) 805-0300\nDOJ-OGR-00017608",
  "text_blocks": [
    {
      "type": "printed",
      "content": "Case 1:20-cr-00330-PAE Document 743 Filed 08/10/22 Page 246 of 247 405",
      "position": "header"
    },
    {
      "type": "printed",
      "content": "INDEX OF EXAMINATION",
      "position": "top"
    },
    {
      "type": "printed",
      "content": "Examination of: LAWRENCE VISOSKI\nDirect By Ms. Comey . . . . . . . . . . . . . . 138\nCross By Mr. Everdell . . . . . . . . . . . . . . 182\nRedirect By Ms. Comey . . . . . . . . . . . . . . 281\nJANE\nDirect By Ms. Moe . . . . . . . . . . . . . . . . 286\nCross By Ms. Menninger . . . . . . . . . . . . . . 363",
      "position": "middle"
    },
    {
      "type": "printed",
      "content": "GOVERNMENT EXHIBITS Received\nExhibit No.\n327, 310 . . . . . . . . . . . . . . . . . . . . 141\n334, 335 . . . . . . . . . . . . . . . . . . . . 142\n328 . . . . . . . . . . . . . . . . . . . . . . 143\n323, 706 . . . . . . . . . . . . . . . . . . . . 148\n705 . . . . . . . . . . . . . . . . . . . . . . 152\n346 . . . . . . . . . . . . . . . . . . . . . . 155\n308 . . . . . . . . . . . . . . . . . . . . . . 156\n326 . . . . . . . . . . . . . . . . . . . . . . 157\n703 . . . . . . . . . . . . . . . . . . . . . . 158\n311, 312 . . . . . . . . . . . . . . . . . . . . 163\n344, 345 . . . . . . . . . . . . . . . . . . . . 164\n315, 336 . . . . . . . . . . . . . . . . . . . . 165\n301, 302 . . . . . . . . . . . . . . . . . . . . 167\n303 . . . . . . . . . . . . . . . . . . . . . . 169",
      "position": "middle"
    },
    {
      "type": "printed",
      "content": "SOUTHERN DISTRICT REPORTERS, P.C. (212) 805-0300",
      "position": "footer"
    },
    {
      "type": "printed",
      "content": "DOJ-OGR-00017608",
      "position": "footer"
    }
  ],
  "entities": {
    "people": [
      "LAWRENCE VISOSKI",
      "Ms. Comey",
      "Mr. Everdell",
      "JANE",
      "Ms. Moe",
      "Ms. Menninger"
    ],
    "organizations": [
      "SOUTHERN DISTRICT REPORTERS, P.C."
    ],
    "locations": [],
    "dates": [
      "08/10/22"
    ],
    "reference_numbers": [
      "1:20-cr-00330-PAE",
      "743",
      "327",
      "310",
      "334",
      "335",
      "328",
      "323",
      "706",
      "705",
      "346",
      "308",
      "326",
      "703",
      "311",
      "312",
      "344",
      "345",
      "315",
      "336",
      "301",
      "302",
      "303",
      "DOJ-OGR-00017608"
    ]
  },
  "additional_notes": "The document appears to be a court transcript index. The text is clear and legible. There are no visible redactions or damage."
}