{
  "document_metadata": {
    "page_number": "131",
    "document_number": "767",
    "date": "08/10/22",
    "document_type": "Court Document",
    "has_handwriting": false,
    "has_stamps": false
  },
  "full_text": "Case 1:20-cr-00330-PAE Document 767 Filed 08/10/22 Page 131 of 257 2965 LCKVMAX6 Summation - Ms. Menninger introducing her, taking her upstairs, anything like that. She gave extensive testimony about it. And it happened shortly in time after the events. She didn't say anything about Ghislaine Maxwell. She had a therapist, Susan Pope, she met with for years. She didn't tell her therapist about Ghislaine Maxwell. She didn't tell the other doctor that she met with. And soon after she files these lawsuits, she starts mentioning Ghislaine. And that's the story that you heard from the stand. For the first time in 17 years, all of a sudden, her too; Ghislaine Maxwell's involved too. And she gets several million dollars. Is that the kind of evidence you would rely on in a matter of importance to yourself? She told you that she saw a photograph of Ghislaine pregnant. There's no evidence that Ghislaine was ever pregnant. No one so Ghislaine Maxwell pregnant, and there's no photograph of Ghislaine Maxwell being pregnant. But that's what Carolyn told you, that she saw a photograph of her pregnant. Money. The first time that Maxwell is accused of anything by Carolyn is during this victims' compensation fund, where she ultimately got $2.8 million. The government argues that Carolyn has no financial incentive to stick with her story here, but that's not supported by the facts. The new story is the one she told the fund. And the fund tells you, if you SOUTHERN DISTRICT REPORTERS, P.C. (212) 805-0300 DOJ-OGR-00017152",
  "text_blocks": [
    {
      "type": "printed",
      "content": "Case 1:20-cr-00330-PAE Document 767 Filed 08/10/22 Page 131 of 257 2965 LCKVMAX6 Summation - Ms. Menninger",
      "position": "header"
    },
    {
      "type": "printed",
      "content": "introducing her, taking her upstairs, anything like that. She gave extensive testimony about it. And it happened shortly in time after the events. She didn't say anything about Ghislaine Maxwell. She had a therapist, Susan Pope, she met with for years. She didn't tell her therapist about Ghislaine Maxwell. She didn't tell the other doctor that she met with. And soon after she files these lawsuits, she starts mentioning Ghislaine. And that's the story that you heard from the stand. For the first time in 17 years, all of a sudden, her too; Ghislaine Maxwell's involved too. And she gets several million dollars. Is that the kind of evidence you would rely on in a matter of importance to yourself? She told you that she saw a photograph of Ghislaine pregnant. There's no evidence that Ghislaine was ever pregnant. No one so Ghislaine Maxwell pregnant, and there's no photograph of Ghislaine Maxwell being pregnant. But that's what Carolyn told you, that she saw a photograph of her pregnant. Money. The first time that Maxwell is accused of anything by Carolyn is during this victims' compensation fund, where she ultimately got $2.8 million. The government argues that Carolyn has no financial incentive to stick with her story here, but that's not supported by the facts. The new story is the one she told the fund. And the fund tells you, if you",
      "position": "main"
    },
    {
      "type": "printed",
      "content": "SOUTHERN DISTRICT REPORTERS, P.C. (212) 805-0300",
      "position": "footer"
    },
    {
      "type": "printed",
      "content": "DOJ-OGR-00017152",
      "position": "footer"
    }
  ],
  "entities": {
    "people": [
      "Ghislaine Maxwell",
      "Susan Pope",
      "Carolyn",
      "Ms. Menninger"
    ],
    "organizations": [
      "SOUTHERN DISTRICT REPORTERS, P.C."
    ],
    "locations": [],
    "dates": [
      "08/10/22"
    ],
    "reference_numbers": [
      "1:20-cr-00330-PAE",
      "767",
      "2965",
      "LCKVMAX6",
      "DOJ-OGR-00017152",
      "$2.8 million"
    ]
  },
  "additional_notes": "The document appears to be a court transcript from a legal proceeding involving Ghislaine Maxwell. The text is typed and there are no visible handwritten notes or stamps. The document includes a header with case information and a footer with the name and contact information of the reporting agency."
}