{
  "document_metadata": {
    "page_number": "161",
    "document_number": "763",
    "date": "08/10/22",
    "document_type": "court transcript",
    "has_handwriting": false,
    "has_stamps": false
  },
  "full_text": "Case 1:20-cr-00330-AJN Document 763 Filed 08/10/22 Page 161 of 197 2702 LCHCmax5 lived there from '92 to '93; right? In fact, your argument is it's a factual impossibility that she lived there in '92, '93? MR. EVERDELL: I'm saying the witness is mistaken based on the property records, yes, your Honor. MS. MOE: Just like Ms. Maxwell, your Honor. That's why this is such a sideshow. THE COURT: Look, I always say, I have so many bridges to across, I cross the bridge that's in front of me. So what is the question? MR. EVERDELL: Well, so, there are, I think, a few questions. We still have to confer on the stipulation to the Kinnerton Street records. We are going to propose being able to admit the land registry records showing the transfer of title of both the Kinnerton Street residence and the Stanhope Mews residence. Those are both land registry documents. And by the way, your Honor, those are selfauthenticating because they came from the land registry and they are selfauthenticating foreign public documents. Those can be admitted just by themselves, but we want a stipulation to the fact that they reflect certain information. And I think what the Court said is if we're going to be permitted to admit those, the defense should be able to permit -- sorry. The prosecution should be able to admit that deposition testimony from when Ms. Maxwell said '92, '93. So we have to -- SOUTHERN DISTRICT REPORTERS, P.C. (212) 805-0300 DOJ-OGR-00016890",
  "text_blocks": [
    {
      "type": "printed",
      "content": "Case 1:20-cr-00330-AJN Document 763 Filed 08/10/22 Page 161 of 197 2702 LCHCmax5",
      "position": "header"
    },
    {
      "type": "printed",
      "content": "lived there from '92 to '93; right? In fact, your argument is it's a factual impossibility that she lived there in '92, '93? MR. EVERDELL: I'm saying the witness is mistaken based on the property records, yes, your Honor. MS. MOE: Just like Ms. Maxwell, your Honor. That's why this is such a sideshow. THE COURT: Look, I always say, I have so many bridges to across, I cross the bridge that's in front of me. So what is the question? MR. EVERDELL: Well, so, there are, I think, a few questions. We still have to confer on the stipulation to the Kinnerton Street records. We are going to propose being able to admit the land registry records showing the transfer of title of both the Kinnerton Street residence and the Stanhope Mews residence. Those are both land registry documents. And by the way, your Honor, those are selfauthenticating because they came from the land registry and they are selfauthenticating foreign public documents. Those can be admitted just by themselves, but we want a stipulation to the fact that they reflect certain information. And I think what the Court said is if we're going to be permitted to admit those, the defense should be able to permit -- sorry. The prosecution should be able to admit that deposition testimony from when Ms. Maxwell said '92, '93. So we have to --",
      "position": "main content"
    },
    {
      "type": "printed",
      "content": "SOUTHERN DISTRICT REPORTERS, P.C. (212) 805-0300",
      "position": "footer"
    },
    {
      "type": "printed",
      "content": "DOJ-OGR-00016890",
      "position": "footer"
    }
  ],
  "entities": {
    "people": [
      "MR. EVERDELL",
      "MS. MOE",
      "MS. MAXWELL"
    ],
    "organizations": [
      "SOUTHERN DISTRICT REPORTERS, P.C.",
      "land registry"
    ],
    "locations": [
      "Kinnerton Street",
      "Stanhope Mews"
    ],
    "dates": [
      "'92",
      "'93",
      "08/10/22"
    ],
    "reference_numbers": [
      "1:20-cr-00330-AJN",
      "763",
      "DOJ-OGR-00016890"
    ]
  },
  "additional_notes": "The document appears to be a court transcript with a clear and legible format. There are no visible redactions or damage."
}