{
  "document_metadata": {
    "page_number": null,
    "document_number": "DOJ-OGR-00015870",
    "date": null,
    "document_type": "Flight Log",
    "has_handwriting": true,
    "has_stamps": false
  },
  "full_text": "Date Aircraft Make and Model Aircraft Identification Mark Points of Departure & Arrival Miles Flown Flight No. Remarks, Procedures, Maneuvers, Endorsements Number of Landings Aircraft Category... Airplane Glider Helicopter 25&2 C-18 23 206L3 N72PB PMP - FXE - PMP 24 206L3 N72PB PMP - FXE - PMP 25 206L3 N72PB PMP - FXE - PMP 26 206L3 N72PB PMP - LNA - Sub-LNA-PMP 29 11 11 FMY URB 29 11 11 VRB FXE-PMP 2 11 11 PMP - FXE - PMP PRE 2 11 11 PMP-FXE-LNA-PMP PRE 3 11 11 PMP PMP PRE 3 11 11 PMP LNA PRE 10 11 11 PMP PMP 14 11 11 PMP PMP 14R 11 11 PMP-LNA-EXCELSIORPMP 24 May 3 C-1159B N909JC PBI PBI 133 3 11 11 11 133 4 11 11 PBI TCB 133 4 11 11 TCB PBE 133 7 11 11 PBI TST 133 I certify that the statements made by me on this form are true. Pilot's Signature David R. Rogers FLIGHT TIMES 3 REPORTED TO INSURANCE ADMINISTRATION Page Total 3210 22 Amount Forward 6251 814 7760 4 33 96 Total to Date 6292 5336 7863 3 33 1126 DOJ-OGR-00015870",
  "text_blocks": [
    {
      "type": "printed",
      "content": "Date Aircraft Make and Model Aircraft Identification Mark Points of Departure & Arrival Miles Flown Flight No. Remarks, Procedures, Maneuvers, Endorsements Number of Landings Aircraft Category... Airplane Glider Helicopter",
      "position": "header"
    },
    {
      "type": "handwritten",
      "content": "25&2 C-18 23 206L3 N72PB PMP - FXE - PMP ...",
      "position": "middle"
    },
    {
      "type": "handwritten",
      "content": "I certify that the statements made by me on this form are true. Pilot's Signature David R. Rogers",
      "position": "bottom"
    },
    {
      "type": "printed",
      "content": "FLIGHT TIMES 3 REPORTED TO INSURANCE ADMINISTRATION",
      "position": "bottom"
    },
    {
      "type": "printed",
      "content": "Page Total Amount Forward Total to Date",
      "position": "footer"
    },
    {
      "type": "handwritten",
      "content": "3210 22 6251 814 7760 4 33 96 6292 5336 7863 3 33 1126",
      "position": "footer"
    },
    {
      "type": "printed",
      "content": "DOJ-OGR-00015870",
      "position": "footer"
    }
  ],
  "entities": {
    "people": [
      "David R. Rogers"
    ],
    "organizations": [
      "Insurance Administration"
    ],
    "locations": [
      "PMP",
      "FXE",
      "LNA",
      "FMY",
      "URB",
      "VRB",
      "PBI",
      "TCB",
      "TST",
      "EXCELSIOR"
    ],
    "dates": [
      "25&2",
      "23",
      "24",
      "25",
      "26",
      "29",
      "2",
      "3",
      "10",
      "14",
      "14R",
      "24 May 3",
      "3",
      "4",
      "4",
      "7"
    ],
    "reference_numbers": [
      "N72PB",
      "N909JC",
      "C-18",
      "206L3",
      "C-1159B",
      "N72PB",
      "DOJ-OGR-00015870"
    ]
  },
  "additional_notes": "The document is a flight log with handwritten entries and a signature. The 'Remarks, Procedures, Maneuvers, Endorsements' column is partially obscured."
}