{
  "document_metadata": {
    "page_number": "237",
    "document_number": "761",
    "date": "08/10/22",
    "document_type": "court transcript",
    "has_handwriting": false,
    "has_stamps": false
  },
  "full_text": "Case 1:20-cr-00330-PAE Document 761 Filed 08/10/22 Page 237 of 246 2532 LCGVMAX7 Hyppolite - direct 1 THE COURT: Everyone may be seated. 2 All right. Matters to take up. 3 MS. COMEY: Your Honor, I would just note that we previously offered to stipulate to this witness's testimony. We're happy to stipulate to the remainder of it if he can be released. I don't know whether the defense would like that. They did us that courtesy with another witness from Florida who had to stay overnight, so I wanted to offer it. 9 THE COURT: Thank you. 10 MS. MENNINGER: Thank you, your Honor. 11 I'll speak with the government afterwards about a potential stipulation. 13 THE COURT: Okay. Thank you. 14 Other matters? 15 MS. COMEY: Nothing from the government, your Honor. 16 MS. MENNINGER: No, your Honor. Just that we have conferrals on the inconsistent statements we are planning to do after we finish. 19 THE COURT: What I'd like is for you to identify what remains in dispute. What time can I hear from you on that? 21 MS. MENNINGER: 7:30? 22 MS. COMEY: That sounds reasonable to us, your Honor. 23 THE COURT: Okay. If there are issues that remain in dispute, I guess I could ask for anything, just like a joint chart that -- 25 SOUTHERN DISTRICT REPORTERS, P.C. (212) 805-0300 DOJ-OGR-00016720",
  "text_blocks": [
    {
      "type": "printed",
      "content": "Case 1:20-cr-00330-PAE Document 761 Filed 08/10/22 Page 237 of 246 2532 LCGVMAX7 Hyppolite - direct",
      "position": "header"
    },
    {
      "type": "printed",
      "content": "1 THE COURT: Everyone may be seated. 2 All right. Matters to take up. 3 MS. COMEY: Your Honor, I would just note that we previously offered to stipulate to this witness's testimony. We're happy to stipulate to the remainder of it if he can be released. I don't know whether the defense would like that. They did us that courtesy with another witness from Florida who had to stay overnight, so I wanted to offer it. 9 THE COURT: Thank you. 10 MS. MENNINGER: Thank you, your Honor. 11 I'll speak with the government afterwards about a potential stipulation. 13 THE COURT: Okay. Thank you. 14 Other matters? 15 MS. COMEY: Nothing from the government, your Honor. 16 MS. MENNINGER: No, your Honor. Just that we have conferrals on the inconsistent statements we are planning to do after we finish. 19 THE COURT: What I'd like is for you to identify what remains in dispute. What time can I hear from you on that? 21 MS. MENNINGER: 7:30? 22 MS. COMEY: That sounds reasonable to us, your Honor. 23 THE COURT: Okay. If there are issues that remain in dispute, I guess I could ask for anything, just like a joint chart that --",
      "position": "main content"
    },
    {
      "type": "printed",
      "content": "SOUTHERN DISTRICT REPORTERS, P.C. (212) 805-0300",
      "position": "footer"
    },
    {
      "type": "printed",
      "content": "DOJ-OGR-00016720",
      "position": "footer"
    }
  ],
  "entities": {
    "people": [
      "MS. COMEY",
      "MS. MENNINGER",
      "Hyppolite"
    ],
    "organizations": [
      "SOUTHERN DISTRICT REPORTERS, P.C."
    ],
    "locations": [
      "Florida"
    ],
    "dates": [
      "08/10/22"
    ],
    "reference_numbers": [
      "1:20-cr-00330-PAE",
      "761",
      "DOJ-OGR-00016720"
    ]
  },
  "additional_notes": "The document appears to be a court transcript with a clear and legible format. There are no visible redactions or damage."
}