{
  "document_metadata": {
    "page_number": "101",
    "document_number": "767",
    "date": "08/10/22",
    "document_type": "Court Document",
    "has_handwriting": false,
    "has_stamps": false
  },
  "full_text": "Case 1:20-cr-00330-PAE Document 767 Filed 08/10/22 Page 101 of 257 2935 LCKCmax5 Summation - Ms. Menninger with the three most important people to her at her school? Is that credible? It is not credible, I submit to you. And if Jane is unable to tell her mother about sexual abuse, but she's able to tell her mother that she got her hair pulled one time and she gets a lawsuit out of it, what makes her think her mother is not going to get her back. This sounds like a whole lot of hindsight changing the stories around. And where is her mother? Why didn't her mother come to testify about this? Oh, I kept that lawsuit from Jane, I didn't want her to know we were in a lawsuit for two years. And by the way, if you're getting wads of cash from Jeffrey Epstein every time you go over there, why do you need to file a lawsuit? There's a flight log entry with Jane's first name in May of '97 that goes from New Jersey to New Mexico. She's almost 17 at that point. And then in August of '97, she turns 17. Before that, though, while she's still 16, she takes another international trip. She doesn't remember that trip either when I asked her. She turns 17 in the fall of '97, The Lion King is released. She told you originally her first trip to New York was when The Lion King was released. It turns out she was 17 when that happened. She got her dates wrong in a case that's about dates and about travel. She got her dates wrong by three years. And then in January of '98, she goes to Europe again with her family. You can see the cities that she SOUTHERN DISTRICT REPORTERS, P.C. (212) 805-0300 DOJ-OGR-00017122",
  "text_blocks": [
    {
      "type": "printed",
      "content": "Case 1:20-cr-00330-PAE Document 767 Filed 08/10/22 Page 101 of 257 2935 LCKCmax5 Summation - Ms. Menninger",
      "position": "header"
    },
    {
      "type": "printed",
      "content": "with the three most important people to her at her school? Is that credible? It is not credible, I submit to you. And if Jane is unable to tell her mother about sexual abuse, but she's able to tell her mother that she got her hair pulled one time and she gets a lawsuit out of it, what makes her think her mother is not going to get her back. This sounds like a whole lot of hindsight changing the stories around. And where is her mother? Why didn't her mother come to testify about this? Oh, I kept that lawsuit from Jane, I didn't want her to know we were in a lawsuit for two years. And by the way, if you're getting wads of cash from Jeffrey Epstein every time you go over there, why do you need to file a lawsuit? There's a flight log entry with Jane's first name in May of '97 that goes from New Jersey to New Mexico. She's almost 17 at that point. And then in August of '97, she turns 17. Before that, though, while she's still 16, she takes another international trip. She doesn't remember that trip either when I asked her. She turns 17 in the fall of '97, The Lion King is released. She told you originally her first trip to New York was when The Lion King was released. It turns out she was 17 when that happened. She got her dates wrong in a case that's about dates and about travel. She got her dates wrong by three years. And then in January of '98, she goes to Europe again with her family. You can see the cities that she",
      "position": "main"
    },
    {
      "type": "printed",
      "content": "SOUTHERN DISTRICT REPORTERS, P.C. (212) 805-0300",
      "position": "footer"
    },
    {
      "type": "printed",
      "content": "DOJ-OGR-00017122",
      "position": "footer"
    }
  ],
  "entities": {
    "people": [
      "Jane",
      "Jeffrey Epstein",
      "Ms. Menninger"
    ],
    "organizations": [
      "SOUTHERN DISTRICT REPORTERS, P.C."
    ],
    "locations": [
      "New Jersey",
      "New Mexico",
      "New York",
      "Europe"
    ],
    "dates": [
      "May '97",
      "August '97",
      "Fall '97",
      "January '98"
    ],
    "reference_numbers": [
      "1:20-cr-00330-PAE",
      "767",
      "DOJ-OGR-00017122"
    ]
  },
  "additional_notes": "The document appears to be a court transcript or legal document related to a case involving Jeffrey Epstein. The text discusses the credibility of a witness named Jane and her interactions with Epstein. The document is typed and contains no handwritten text or stamps."
}