{
  "document_metadata": {
    "page_number": "155",
    "document_number": "761",
    "date": "08/10/22",
    "document_type": "court transcript",
    "has_handwriting": false,
    "has_stamps": false
  },
  "full_text": "Case 1:20-cr-00330-PAE Document 761 Filed 08/10/22 Page 155 of 246 2450 LCGVMAX5 Loftus - direct\n1 BY MS. STERNHEIM:\n2 Q. Earlier today I asked you various questions concerning the context of your curriculum vitae, you remember that?\n3 A. Yes.\n4 Q. Fair to say that we didn't go into great detail about it; correct?\n5 A. Well, no, not great detail.\n6 Q. And there was much more that you could have told the jury about it, but it would be time-consuming, wouldn't it?\n7 A. It would, yes.\n8 MS. STERNHEIM: Judge, at this time I would move into evidence Judge Loftus's CV, which is EF-1.\n9 MS. POMERANTZ: Objection, your Honor.\n10 THE COURT: I'm sorry?\n11 MS. POMERANTZ: The government objects.\n12 THE COURT: Overruled. EF-1 is admitted.\n13 MS. STERNHEIM: Thank you.\n14 (Defendant's Exhibit EF-1 received in evidence)\n15 BY MS. STERNHEIM:\n16 Q. Professor Loftus, just to be clear, you are being compensated for your time; correct?\n17 A. I am, or I hope so, yes.\n18 Q. I hope so, too.\n19 You don't have any stake in the outcome of this trial, do you?\n20 SOUTHERN DISTRICT REPORTERS, P.C. (212) 805-0300 DOJ-OGR-00016638",
  "text_blocks": [
    {
      "type": "printed",
      "content": "Case 1:20-cr-00330-PAE Document 761 Filed 08/10/22 Page 155 of 246 2450 LCGVMAX5 Loftus - direct",
      "position": "header"
    },
    {
      "type": "printed",
      "content": "SOUTHERN DISTRICT REPORTERS, P.C. (212) 805-0300",
      "position": "footer"
    },
    {
      "type": "printed",
      "content": "DOJ-OGR-00016638",
      "position": "footer"
    },
    {
      "type": "printed",
      "content": "1 BY MS. STERNHEIM: ... 20",
      "position": "middle"
    }
  ],
  "entities": {
    "people": [
      "MS. STERNHEIM",
      "MS. POMERANTZ",
      "Loftus"
    ],
    "organizations": [
      "SOUTHERN DISTRICT REPORTERS, P.C."
    ],
    "locations": [],
    "dates": [
      "08/10/22"
    ],
    "reference_numbers": [
      "1:20-cr-00330-PAE",
      "761",
      "EF-1",
      "DOJ-OGR-00016638"
    ]
  },
  "additional_notes": "The document appears to be a court transcript with a clear and readable format. There are no visible redactions or damage."
}