{
  "document_metadata": {
    "page_number": "79",
    "document_number": "743",
    "date": "08/10/22",
    "document_type": "court transcript",
    "has_handwriting": false,
    "has_stamps": false
  },
  "full_text": "Case 1:20-cr-00330-PAE Document 743 Filed 08/10/22 Page 79 of 247\nLBUCmax3\nVisoski - cross\n1\nA. Exactly.\nQ. So, for example, I believe former president Bill Clinton flew on Epstein's planes a few times in the 2000s; isn't that right?\nA. Yes, he did.\nQ. So if he were going to be on the flight, you might be told that information in advance?\nA. Yes.\nQ. Because you might want to make sure the plane looked nice?\nA. Exactly.\nQ. You might want to invite some special caterer?\nA. Sure.\nQ. But otherwise, you might not know who would be traveling on the flight at all; is that right?\nA. Correct.\nQ. And even when the passengers arrived at the airport, even then, you wouldn't necessarily meet all the passengers; right?\nA. No, not at all.\nQ. A lot of the time you didn't meet them?\nA. Correct.\nQ. Sometimes you were just given their names?\nA. Yes.\nQ. And you wouldn't always be given all of their names; right?\nA. Correct.\nQ. Sometimes you would just be given a first name?\nSOUTHERN DISTRICT REPORTERS, P.C.\n(212) 805-0300\nDOJ-OGR-00017441",
  "text_blocks": [
    {
      "type": "printed",
      "content": "Case 1:20-cr-00330-PAE Document 743 Filed 08/10/22 Page 79 of 247",
      "position": "header"
    },
    {
      "type": "printed",
      "content": "LBUCmax3\nVisoski - cross",
      "position": "header"
    },
    {
      "type": "printed",
      "content": "1\nA. Exactly.\nQ. So, for example, I believe former president Bill Clinton flew on Epstein's planes a few times in the 2000s; isn't that right?\nA. Yes, he did.\nQ. So if he were going to be on the flight, you might be told that information in advance?\nA. Yes.\nQ. Because you might want to make sure the plane looked nice?\nA. Exactly.\nQ. You might want to invite some special caterer?\nA. Sure.\nQ. But otherwise, you might not know who would be traveling on the flight at all; is that right?\nA. Correct.\nQ. And even when the passengers arrived at the airport, even then, you wouldn't necessarily meet all the passengers; right?\nA. No, not at all.\nQ. A lot of the time you didn't meet them?\nA. Correct.\nQ. Sometimes you were just given their names?\nA. Yes.\nQ. And you wouldn't always be given all of their names; right?\nA. Correct.\nQ. Sometimes you would just be given a first name?",
      "position": "main"
    },
    {
      "type": "printed",
      "content": "SOUTHERN DISTRICT REPORTERS, P.C.\n(212) 805-0300",
      "position": "footer"
    },
    {
      "type": "printed",
      "content": "DOJ-OGR-00017441",
      "position": "footer"
    }
  ],
  "entities": {
    "people": [
      "Bill Clinton",
      "Epstein"
    ],
    "organizations": [
      "SOUTHERN DISTRICT REPORTERS, P.C."
    ],
    "locations": [],
    "dates": [
      "08/10/22"
    ],
    "reference_numbers": [
      "1:20-cr-00330-PAE",
      "743",
      "DOJ-OGR-00017441"
    ]
  },
  "additional_notes": "The document appears to be a court transcript with a clear and legible format. There are no visible redactions or damage."
}