{
  "document_metadata": {
    "page_number": "80",
    "document_number": "759",
    "date": "08/10/22",
    "document_type": "court transcript",
    "has_handwriting": false,
    "has_stamps": false
  },
  "full_text": "Case 1:20-cr-00330-PAE Document 759 Filed 08/10/22 Page 80 of 267 2108\nLCACmax3 A. Farmer - cross\n1 Q. You stayed overnight there?\n2 A. I think that's correct.\n3 Q. With your sister?\n4 A. Yes.\n5 Q. And with your sister's boyfriend and his brother were at that cabin; correct?\n6 A. That's correct.\n7 Q. You went shopping with your sister; right?\n8 A. I did.\n9 Q. You went to flea markets?\n10 A. Uh-huh.\n11 Q. Thrift stores?\n12 A. Yes.\n13 Q. You went to see some bands with your sister?\n14 A. Yes.\n15 Q. You did all of those things on this trip in New York with your sister; right?\n16 A. I did.\n17 Q. She was with you, I think you said without the exception of perhaps Blue Man Group, she was with you the entire time; right?\n18 A. Yes.\n19 Q. Now, when you arrived in New York, Ghislaine Maxwell didn't pick you up at the airport?\n20 A. No.\nSOUTHERN DISTRICT REPORTERS, P.C. (212) 805-0300\nDOJ-OGR-00016296",
  "text_blocks": [
    {
      "type": "printed",
      "content": "Case 1:20-cr-00330-PAE Document 759 Filed 08/10/22 Page 80 of 267 2108",
      "position": "header"
    },
    {
      "type": "printed",
      "content": "LCACmax3 A. Farmer - cross",
      "position": "header"
    },
    {
      "type": "printed",
      "content": "1 Q. You stayed overnight there?\n2 A. I think that's correct.\n3 Q. With your sister?\n4 A. Yes.\n5 Q. And with your sister's boyfriend and his brother were at that cabin; correct?\n6 A. That's correct.\n7 Q. You went shopping with your sister; right?\n8 A. I did.\n9 Q. You went to flea markets?\n10 A. Uh-huh.\n11 Q. Thrift stores?\n12 A. Yes.\n13 Q. You went to see some bands with your sister?\n14 A. Yes.\n15 Q. You did all of those things on this trip in New York with your sister; right?\n16 A. I did.\n17 Q. She was with you, I think you said without the exception of perhaps Blue Man Group, she was with you the entire time; right?\n18 A. Yes.\n19 Q. Now, when you arrived in New York, Ghislaine Maxwell didn't pick you up at the airport?\n20 A. No.",
      "position": "main"
    },
    {
      "type": "printed",
      "content": "SOUTHERN DISTRICT REPORTERS, P.C. (212) 805-0300",
      "position": "footer"
    },
    {
      "type": "printed",
      "content": "DOJ-OGR-00016296",
      "position": "footer"
    }
  ],
  "entities": {
    "people": [
      "Ghislaine Maxwell"
    ],
    "organizations": [
      "Blue Man Group",
      "SOUTHERN DISTRICT REPORTERS, P.C."
    ],
    "locations": [
      "New York"
    ],
    "dates": [
      "08/10/22"
    ],
    "reference_numbers": [
      "1:20-cr-00330-PAE",
      "759",
      "DOJ-OGR-00016296"
    ]
  },
  "additional_notes": "The document appears to be a court transcript with a clear Q&A format. The content is related to a legal case involving Ghislaine Maxwell."
}