{
  "document_metadata": {
    "page_number": "34",
    "document_number": "743",
    "date": "08/10/22",
    "document_type": "Court Transcript",
    "has_handwriting": false,
    "has_stamps": false
  },
  "full_text": "Case 1:20-cr-00330-PAE Document 743 Filed 08/10/22 Page 34 of 247 162 LBUVMAX2 Visoski - direct level, the second and third floors, I believe were the guest bedrooms and the master bedroom. And then once you got to the top, which, if memory serves me correctly, might have been the fifth floor where we installed a home theater for her. Q. Switching gears. Between 1991 and 2004, what planes did you fly for Mr. Epstein? A. From '91 to 2004? Q. Yes. A. The first aircraft was a Hawker Siddeley, what's called an HS125. Mr. Epstein purchased that. He had that aircraft from '91 till 1994. And then in 1994, he sold that aircraft and he purchased a Gulfstream, which is called the G2B. And he had the Gulfstream from 1994 up until 2000, when he added another aircraft, is when he bought the Boeing 727. And he continued to keep both of those aircraft. So we flew both aircraft, the Boeing and the Gulfstream, up until 2004, to the date you mentioned. MS. COMEY: Ms. Drescher, would you please pull up Government Exhibits 311 and 312 for the witness, the Court, and the parties. Q. Mr. Visoski, do you recognize these? A. Yes. Q. What are they? A. That is the first aircraft Mr. Epstein purchased, which is the Hawker Siddeley 125. SOUTHERN DISTRICT REPORTERS, P.C. (212) 805-0300 DOJ-OGR-00017396",
  "text_blocks": [
    {
      "type": "printed",
      "content": "Case 1:20-cr-00330-PAE Document 743 Filed 08/10/22 Page 34 of 247 162 LBUVMAX2 Visoski - direct",
      "position": "header"
    },
    {
      "type": "printed",
      "content": "level, the second and third floors, I believe were the guest bedrooms and the master bedroom. And then once you got to the top, which, if memory serves me correctly, might have been the fifth floor where we installed a home theater for her. Q. Switching gears. Between 1991 and 2004, what planes did you fly for Mr. Epstein? A. From '91 to 2004? Q. Yes. A. The first aircraft was a Hawker Siddeley, what's called an HS125. Mr. Epstein purchased that. He had that aircraft from '91 till 1994. And then in 1994, he sold that aircraft and he purchased a Gulfstream, which is called the G2B. And he had the Gulfstream from 1994 up until 2000, when he added another aircraft, is when he bought the Boeing 727. And he continued to keep both of those aircraft. So we flew both aircraft, the Boeing and the Gulfstream, up until 2004, to the date you mentioned. MS. COMEY: Ms. Drescher, would you please pull up Government Exhibits 311 and 312 for the witness, the Court, and the parties. Q. Mr. Visoski, do you recognize these? A. Yes. Q. What are they? A. That is the first aircraft Mr. Epstein purchased, which is the Hawker Siddeley 125.",
      "position": "main"
    },
    {
      "type": "printed",
      "content": "SOUTHERN DISTRICT REPORTERS, P.C. (212) 805-0300",
      "position": "footer"
    },
    {
      "type": "printed",
      "content": "DOJ-OGR-00017396",
      "position": "footer"
    }
  ],
  "entities": {
    "people": [
      "Mr. Epstein",
      "Mr. Visoski",
      "Ms. Drescher",
      "Ms. Comey"
    ],
    "organizations": [
      "SOUTHERN DISTRICT REPORTERS, P.C."
    ],
    "locations": [],
    "dates": [
      "1991",
      "2004",
      "1994",
      "2000",
      "08/10/22"
    ],
    "reference_numbers": [
      "1:20-cr-00330-PAE",
      "743",
      "311",
      "312",
      "DOJ-OGR-00017396"
    ]
  },
  "additional_notes": "The document appears to be a court transcript with a clear and legible format. There are no visible redactions or damage."
}