{
  "document_metadata": {
    "page_number": "7",
    "document_number": "4-447-12299",
    "date": "Nov 04, 2002",
    "document_type": "FedEx Express Shipment Detail By Payment Type",
    "has_handwriting": false,
    "has_stamps": false
  },
  "full_text": "FedEx Invoice Number: 4-447-12299 Invoice Date: Nov 04, 2002 Account Number: 1144-2081-6 Page: 7 of 8 FedEx Express Shipment Detail By Payment Type (Original) Picked up: Oct 29, 2002 Payor: Shipper Reference: NO REFERENCE INFORMATION Fuel Surcharge - FedEx has applied a fuel surcharge of 3.00% to this shipment. Tracking D 792765011265 Sender CECILIA STEEN JEFFREY E. EPSTE N 457 MADISON AVENUE 4TH FLOOR NEW YORK NY 10022 US Recipient JAL LA HASHEMI Package Type FedEx Envelope Zone D Orig./Dest. JRB/LON Packages 1 Weight 0.5 lbs, 0.2 kgs Delivered Oct 31, 2002 10 33 Signed by A.STARBUCK FedEx Use _/US01O/_ Transportation Charge 28.00 Fuel Surcharge 0.81 Discount -0.84 Total Transportation Charges USD $ 27.97 Picked up: Nov 01, 2002 Payor: Shipper Reference: NO REFERENCE INFORMATION Fuel Surcharge - FedEx has applied a fuel surcharge of 3.00% to this shipment. Tracking D 790131129061 Sender CECILIA STEEN JEFFREY E. EPSTE N 457 MADISON AVENUE 4TH FLOOR NEW YORK NY 10022 US Recipient MAR ELISE LACHAPELLE Package Type FedEx Envelope Zone A Orig./Dest. JRB/YMX Packages 1 Weight 0.5 lbs, 0.2 kgs Delivered Nov 02, 2002 12 08 Signed by M.LACHAPELLE FedEx Use _/US01O/_ Transportation Charge 20.75 Saturday Delivery 10.00 Fuel Surcharge 0.60 Discount -0.62 Total Transportation Charges USD $ 30.73 Dropped off: Oct 30, 2002 Payor: Recipient Reference: NO REFERENCE INFORMATION Fuel Surcharge - FedEx has applied a fuel surcharge of 2.00% to this shipment. Discount applied is the greater of volume discount or dropoff discount. No additional discount applies. Tracking D 834797164256 Sender EROKHINA Recipient EPSTEINE JEFFREY E EPSTEIN 457 MADISON AVE 4TH FL NEW YORK NY 10022-6843 US Package Type FedEx Envelope Zone C Orig./Dest. MOW/JRB Packages 1 Weight 0.2 kgs, 0.4 lbs Delivered Oct 31, 2002 09 21 Signed by W.DOULIN FedEx Use _/RU01O/_ Transportation Charge 68.90 Russia Pickup Surcharge 2.00 Fuel Surcharge 1.34 Discount -2.07 Total Transportation Charges USD $ 70.17 Shipment Detail Subtotal USD $ 362.67 CONFIDENTIAL SDNY_GM_00340677 7 DOJ-OGR-00015316",
  "text_blocks": [
    {
      "type": "printed",
      "content": "FedEx Invoice Number: 4-447-12299 Invoice Date: Nov 04, 2002 Account Number: 1144-2081-6 Page: 7 of 8",
      "position": "header"
    },
    {
      "type": "printed",
      "content": "FedEx Express Shipment Detail By Payment Type (Original)",
      "position": "header"
    },
    {
      "type": "printed",
      "content": "CONFIDENTIAL",
      "position": "bottom"
    }
  ],
  "entities": {
    "people": [
      "CECILIA STEEN",
      "JEFFREY E. EPSTE N",
      "JAL LA HASHEMI",
      "A.STARBUCK",
      "M.LACHAPELLE",
      "EROKHINA",
      "EPSTEINE",
      "JEFFREY E EPSTEIN",
      "W.DOULIN"
    ],
    "organizations": [
      "FedEx"
    ],
    "locations": [
      "NEW YORK",
      "NY",
      "JRB",
      "LON",
      "YMX",
      "MOW"
    ],
    "dates": [
      "Oct 29, 2002",
      "Nov 04, 2002",
      "Oct 31, 2002",
      "Nov 01, 2002",
      "Nov 02, 2002",
      "Oct 30, 2002"
    ],
    "reference_numbers": [
      "4-447-12299",
      "1144-2081-6",
      "792765011265",
      "790131129061",
      "834797164256",
      "SDNY_GM_00340677",
      "DOJ-OGR-00015316"
    ]
  },
  "additional_notes": "The document appears to be a FedEx invoice with shipment details. It contains confidential information and has a clear header and footer. The document is well-structured and easy to read."
}