{
  "document_metadata": {
    "page_number": null,
    "document_number": "S2 20 Cr. 330 (AJN)",
    "date": null,
    "document_type": "Stipulation",
    "has_handwriting": false,
    "has_stamps": true
  },
  "full_text": "UNITED STATES DISTRICT COURT SOUTHERN DISTRICT OF NEW YORK UNITED STATES OF AMERICA v. GHISLAINE MAXWELL, Defendant. STIPULATION S2 20 Cr. 330 (AJN) IT IS HEREBY STIPULATED AND AGREED by and among the United States of America, by Damian Williams, United States Attorney for the Southern District of New York, and Maurene Comey, Alison Moe, Lara Pomerantz, and Andrew Rohrbach, Assistant United States Attorneys, of counsel, and defendant Ghislaine Maxwell, by and with the consent of her attorneys, Christian Everdell, Esq., Laura Menninger, Esq., Jeffrey Pagliuca, Esq., and Bobbi Sternheim, Esq., that: 1. Sgt. Michael Dawson, who previously testified in this case, would have given the following additional testimony on cross-examination: a. The cardboard box shown in GX-294, which was recovered during the search of Jeffrey Epstein's Palm Beach residence on October 20, 2005, was found in the closet of one of the guest bedrooms on the second floor of the residence. b. The two items inside the cardboard box, which are visible in GX-294, were still in their original boxes, unopened. DEFENDANT'S EXHIBIT B S2 20 Cr. 330 (AJN) DOJ-OGR-00015185",
  "text_blocks": [
    {
      "type": "printed",
      "content": "UNITED STATES DISTRICT COURT SOUTHERN DISTRICT OF NEW YORK",
      "position": "header"
    },
    {
      "type": "printed",
      "content": "UNITED STATES OF AMERICA v. GHISLAINE MAXWELL, Defendant.",
      "position": "header"
    },
    {
      "type": "printed",
      "content": "STIPULATION S2 20 Cr. 330 (AJN)",
      "position": "header"
    },
    {
      "type": "printed",
      "content": "IT IS HEREBY STIPULATED AND AGREED by and among the United States of America, by Damian Williams, United States Attorney for the Southern District of New York, and Maurene Comey, Alison Moe, Lara Pomerantz, and Andrew Rohrbach, Assistant United States Attorneys, of counsel, and defendant Ghislaine Maxwell, by and with the consent of her attorneys, Christian Everdell, Esq., Laura Menninger, Esq., Jeffrey Pagliuca, Esq., and Bobbi Sternheim, Esq., that:",
      "position": "body"
    },
    {
      "type": "printed",
      "content": "1. Sgt. Michael Dawson, who previously testified in this case, would have given the following additional testimony on cross-examination:",
      "position": "body"
    },
    {
      "type": "printed",
      "content": "a. The cardboard box shown in GX-294, which was recovered during the search of Jeffrey Epstein's Palm Beach residence on October 20, 2005, was found in the closet of one of the guest bedrooms on the second floor of the residence.",
      "position": "body"
    },
    {
      "type": "printed",
      "content": "b. The two items inside the cardboard box, which are visible in GX-294, were still in their original boxes, unopened.",
      "position": "body"
    },
    {
      "type": "stamp",
      "content": "DEFENDANT'S EXHIBIT B S2 20 Cr. 330 (AJN)",
      "position": "footer"
    },
    {
      "type": "printed",
      "content": "DOJ-OGR-00015185",
      "position": "footer"
    }
  ],
  "entities": {
    "people": [
      "Damian Williams",
      "Maurene Comey",
      "Alison Moe",
      "Lara Pomerantz",
      "Andrew Rohrbach",
      "Ghislaine Maxwell",
      "Christian Everdell",
      "Laura Menninger",
      "Jeffrey Pagliuca",
      "Bobbi Sternheim",
      "Michael Dawson",
      "Jeffrey Epstein"
    ],
    "organizations": [
      "United States District Court",
      "United States Attorney for the Southern District of New York"
    ],
    "locations": [
      "New York",
      "Palm Beach"
    ],
    "dates": [
      "October 20, 2005"
    ],
    "reference_numbers": [
      "S2 20 Cr. 330 (AJN)",
      "GX-294",
      "DOJ-OGR-00015185"
    ]
  },
  "additional_notes": "The document appears to be a court filing with a stamp indicating it is Defendant's Exhibit B. The content discusses a stipulation between the United States of America and Ghislaine Maxwell regarding testimony about a search of Jeffrey Epstein's Palm Beach residence."
}