{
  "document_metadata": {
    "page_number": "59",
    "document_number": "743",
    "date": "08/10/22",
    "document_type": "court transcript",
    "has_handwriting": false,
    "has_stamps": false
  },
  "full_text": "Case 1:20-cr-00330-PAE Document 743 Filed 08/10/22 Page 59 of 247 187 LBUVMAX2 Visoski - cross 1 A. Sometimes. 2 Q. There were times when Epstein or Ghislaine introduced you 3 to passengers? 4 A. Correct. 5 Q. There were times when the plane and the passengers had to 6 clear customs, right, and the pilots and the passengers would 7 have to get out of the plane and clear customs to do that? 8 A. Yes, that's correct. 9 Q. And you'd see the passengers then too? 10 A. Sure. 11 Q. Okay. And there were times when the passengers came up to 12 the cockpit before takeoff and you might have met some of them 13 then? 14 A. Occasionally that would happen, sure. 15 Q. Okay. Now, you testified that the cockpit doors for the 16 Gulfstream and the Boeing were always closed during the flights 17 while you were in the air; is that right? 18 A. Yes. 19 Q. But you left the door open to the cockpit as you were 20 getting the plane ready for takeoff before you took off, right? 21 A. Yes. 22 Q. As you were in the cockpit, if you were looking back 23 through the cockpit door, you could see the passengers in the 24 entranceway if you wanted to, right? 25 A. Most of them, yes. It wasn't a clear view to every seat in SOUTHERN DISTRICT REPORTERS, P.C. (212) 805-0300 DOJ-OGR-00017421",
  "text_blocks": [
    {
      "type": "printed",
      "content": "Case 1:20-cr-00330-PAE Document 743 Filed 08/10/22 Page 59 of 247 187 LBUVMAX2 Visoski - cross",
      "position": "header"
    },
    {
      "type": "printed",
      "content": "1 A. Sometimes. 2 Q. There were times when Epstein or Ghislaine introduced you 3 to passengers? 4 A. Correct. 5 Q. There were times when the plane and the passengers had to 6 clear customs, right, and the pilots and the passengers would 7 have to get out of the plane and clear customs to do that? 8 A. Yes, that's correct. 9 Q. And you'd see the passengers then too? 10 A. Sure. 11 Q. Okay. And there were times when the passengers came up to 12 the cockpit before takeoff and you might have met some of them 13 then? 14 A. Occasionally that would happen, sure. 15 Q. Okay. Now, you testified that the cockpit doors for the 16 Gulfstream and the Boeing were always closed during the flights 17 while you were in the air; is that right? 18 A. Yes. 19 Q. But you left the door open to the cockpit as you were 20 getting the plane ready for takeoff before you took off, right? 21 A. Yes. 22 Q. As you were in the cockpit, if you were looking back 23 through the cockpit door, you could see the passengers in the 24 entranceway if you wanted to, right? 25 A. Most of them, yes. It wasn't a clear view to every seat in",
      "position": "main content"
    },
    {
      "type": "printed",
      "content": "SOUTHERN DISTRICT REPORTERS, P.C. (212) 805-0300",
      "position": "footer"
    },
    {
      "type": "printed",
      "content": "DOJ-OGR-00017421",
      "position": "footer"
    }
  ],
  "entities": {
    "people": [
      "Epstein",
      "Ghislaine"
    ],
    "organizations": [
      "SOUTHERN DISTRICT REPORTERS, P.C."
    ],
    "locations": [],
    "dates": [
      "08/10/22"
    ],
    "reference_numbers": [
      "1:20-cr-00330-PAE",
      "743",
      "DOJ-OGR-00017421"
    ]
  },
  "additional_notes": "The document appears to be a court transcript with a clear and legible format. There are no visible redactions or damage."
}