{
  "document_metadata": {
    "page_number": "131",
    "document_number": "763",
    "date": "08/10/22",
    "document_type": "court transcript",
    "has_handwriting": false,
    "has_stamps": false
  },
  "full_text": "Case 1:20-cr-00330-AJN Document 763 Filed 08/10/22 Page 131 of 197\nLCHVMAX4 Healy - direct\n1 THE COURT: All right. Defense may call -- we have about ten minutes before the lunch break. Defense may call its next witness.\n2 MS. MENNINGER: At this time we call Michelle Healy.\n3 THE COURT: Michelle Healy may come forward.\n4 MICHELLE HEALY\n5 called as a witness by the Defendant, having been duly sworn, testified as follows:\n6 THE COURT: You may inquire.\n7 MS. MENNINGER: Thank you, your Honor.\n8 DIRECT EXAMINATION\n9 BY MS. MENNINGER:\n10 Q. Good afternoon, Ms. Healy.\n11 A. Good afternoon.\n12 Q. How old are you?\n13 A. I'm 47.\n14 Q. And where do you live?\n15 A. I live in Dallas, Texas.\n16 Q. Are you married?\n17 A. I am.\n18 Q. And what do you do for a living?\n19 A. I'm a housewife.\n20 Q. What does your husband do?\n21 A. He's an architect.\n22 Q. There in Texas?\n23 SOUTHERN DISTRICT REPORTERS, P.C. (212) 805-0300\n24 DOJ-OGR-00016860",
  "text_blocks": [
    {
      "type": "printed",
      "content": "Case 1:20-cr-00330-AJN Document 763 Filed 08/10/22 Page 131 of 197",
      "position": "header"
    },
    {
      "type": "printed",
      "content": "LCHVMAX4 Healy - direct",
      "position": "header"
    },
    {
      "type": "printed",
      "content": "THE COURT: All right. Defense may call -- we have about ten minutes before the lunch break. Defense may call its next witness. MS. MENNINGER: At this time we call Michelle Healy. THE COURT: Michelle Healy may come forward. MICHELLE HEALY called as a witness by the Defendant, having been duly sworn, testified as follows: THE COURT: You may inquire. MS. MENNINGER: Thank you, your Honor. DIRECT EXAMINATION BY MS. MENNINGER: Q. Good afternoon, Ms. Healy. A. Good afternoon. Q. How old are you? A. I'm 47. Q. And where do you live? A. I live in Dallas, Texas. Q. Are you married? A. I am. Q. And what do you do for a living? A. I'm a housewife. Q. What does your husband do? A. He's an architect. Q. There in Texas?",
      "position": "main"
    },
    {
      "type": "printed",
      "content": "SOUTHERN DISTRICT REPORTERS, P.C. (212) 805-0300",
      "position": "footer"
    },
    {
      "type": "printed",
      "content": "DOJ-OGR-00016860",
      "position": "footer"
    }
  ],
  "entities": {
    "people": [
      "Michelle Healy",
      "MS. MENNINGER"
    ],
    "organizations": [
      "SOUTHERN DISTRICT REPORTERS, P.C."
    ],
    "locations": [
      "Dallas, Texas"
    ],
    "dates": [
      "08/10/22"
    ],
    "reference_numbers": [
      "1:20-cr-00330-AJN",
      "763",
      "DOJ-OGR-00016860"
    ]
  },
  "additional_notes": "The document appears to be a court transcript with a clear and legible format. There are no visible redactions or damage."
}