{
  "document_metadata": {
    "page_number": "3",
    "document_number": "804",
    "date": "08/06/25",
    "document_type": "Letter",
    "has_handwriting": false,
    "has_stamps": true
  },
  "full_text": "Case 1:20-cr-00330-PAE Document 804 Filed 08/06/25 Page 3 of 27 U.S. Department of Justice United States Attorney Southern District of New York The Jacob K. Javits Federal Building 26 Federal Plaza, 37th Floor New York, New York 10278 August 6, 2025 BY HAND Honorable Paul A. Engelmayer Attention: A.J. Smallman United States District Court Southern District of New York Chambers 2201 40 Foley Square New York, NY 10007 Re: United States v. Ghislaine Maxwell, 20 Cr. 330 (PAE) Dear Judge Engelmayer: The Government respectfully submits this letter and its attachments pursuant to the Court's order, dated August 5, 2025. (Dkt. 801). The Government has received five submissions, which are enclosed. The following is a list of those submissions and an indication of whether they may be publicly filed with or without redactions. 1. Response to Victim Notification Request, dated August 4, 2025, and signed by John Scarola, Esq.: The submission does not contain any identifying information for victims and therefore it may be filed without redactions. 2. Letter dated August 5, 2025, and signed by Sigrid McCawley, Esq.: Counsel informed the Government that they are not seeking any redactions to this submission and therefore it may be filed without redactions. 3. Letter dated August 5, 2025, and signed by Bradley Edwards, Esq.: Counsel informed the Government that they are not seeking any redactions to this submission and therefore it may be filed without redactions. 4. Letter dated August 5, 2025, which is unsigned but was submitted to the Government by Bradley Edwards, Esq.: The submission does not contain any identifying information for victims and therefore it may be filed without redactions. 5. Letter dated August 5, 2025, and signed by Neil S. Binder, Esq.: Counsel provided two versions of the letter—one for filing under seal and the other with redactions for public filing. DOJ-OGR-00015098",
  "text_blocks": [
    {
      "type": "printed",
      "content": "Case 1:20-cr-00330-PAE Document 804 Filed 08/06/25 Page 3 of 27",
      "position": "header"
    },
    {
      "type": "printed",
      "content": "U.S. Department of Justice",
      "position": "header"
    },
    {
      "type": "printed",
      "content": "United States Attorney Southern District of New York",
      "position": "header"
    },
    {
      "type": "printed",
      "content": "The Jacob K. Javits Federal Building 26 Federal Plaza, 37th Floor New York, New York 10278 August 6, 2025",
      "position": "header"
    },
    {
      "type": "printed",
      "content": "BY HAND",
      "position": "top"
    },
    {
      "type": "printed",
      "content": "Honorable Paul A. Engelmayer Attention: A.J. Smallman United States District Court Southern District of New York Chambers 2201 40 Foley Square New York, NY 10007",
      "position": "top"
    },
    {
      "type": "printed",
      "content": "Re: United States v. Ghislaine Maxwell, 20 Cr. 330 (PAE)",
      "position": "top"
    },
    {
      "type": "printed",
      "content": "Dear Judge Engelmayer: The Government respectfully submits this letter and its attachments pursuant to the Court's order, dated August 5, 2025. (Dkt. 801). The Government has received five submissions, which are enclosed. The following is a list of those submissions and an indication of whether they may be publicly filed with or without redactions.",
      "position": "middle"
    },
    {
      "type": "printed",
      "content": "1. Response to Victim Notification Request, dated August 4, 2025, and signed by John Scarola, Esq.: The submission does not contain any identifying information for victims and therefore it may be filed without redactions.",
      "position": "middle"
    },
    {
      "type": "printed",
      "content": "2. Letter dated August 5, 2025, and signed by Sigrid McCawley, Esq.: Counsel informed the Government that they are not seeking any redactions to this submission and therefore it may be filed without redactions.",
      "position": "middle"
    },
    {
      "type": "printed",
      "content": "3. Letter dated August 5, 2025, and signed by Bradley Edwards, Esq.: Counsel informed the Government that they are not seeking any redactions to this submission and therefore it may be filed without redactions.",
      "position": "middle"
    },
    {
      "type": "printed",
      "content": "4. Letter dated August 5, 2025, which is unsigned but was submitted to the Government by Bradley Edwards, Esq.: The submission does not contain any identifying information for victims and therefore it may be filed without redactions.",
      "position": "middle"
    },
    {
      "type": "printed",
      "content": "5. Letter dated August 5, 2025, and signed by Neil S. Binder, Esq.: Counsel provided two versions of the letter—one for filing under seal and the other with redactions for public filing.",
      "position": "middle"
    },
    {
      "type": "stamp",
      "content": "DOJ-OGR-00015098",
      "position": "footer"
    }
  ],
  "entities": {
    "people": [
      "Paul A. Engelmayer",
      "A.J. Smallman",
      "Ghislaine Maxwell",
      "John Scarola",
      "Sigrid McCawley",
      "Bradley Edwards",
      "Neil S. Binder"
    ],
    "organizations": [
      "U.S. Department of Justice",
      "United States Attorney",
      "United States District Court",
      "Southern District of New York"
    ],
    "locations": [
      "New York",
      "New York 10278",
      "40 Foley Square",
      "New York, NY 10007"
    ],
    "dates": [
      "August 6, 2025",
      "August 5, 2025",
      "August 4, 2025",
      "08/06/25"
    ],
    "reference_numbers": [
      "1:20-cr-00330-PAE",
      "Document 804",
      "20 Cr. 330 (PAE)",
      "Dkt. 801",
      "DOJ-OGR-00015098"
    ]
  },
  "additional_notes": "The document is a letter from the U.S. Department of Justice to Judge Paul A. Engelmayer regarding the case United States v. Ghislaine Maxwell. The letter discusses five submissions received by the Government and whether they may be publicly filed with or without redactions. The document is stamped with the reference number DOJ-OGR-00015098."
}