{
  "document_metadata": {
    "page_number": "146",
    "document_number": "761",
    "date": "08/10/22",
    "document_type": "court transcript",
    "has_handwriting": false,
    "has_stamps": false
  },
  "full_text": "Case 1:20-cr-00330-PAE Document 761 Filed 08/10/22 Page 146 of 246 2441 LCGCmax4 Loftus - direct\n1 MS. STERNHEIM: I'd appreciate that so that I can have all of the documents in front of me.\n2 THE COURT: Okay.\n3 MS. STERNHEIM: Thank you very much.\n4 THE COURT: Just so I can marinate on it. So the basic idea is that you want this witness to testify about one or two conversations that he had with this witness, who we're calling Kate, the one or two conversations that he had with Kate in which -- and his proffered testimony is that, at one point, Kate said, regarding the subject of Jeffrey Epstein, that it, quote, fell right into my lap.\nMS. STERNHEIM: That's correct.\nTHE COURT: Let's start with that one. What is the purpose for which it is being offered?\nMS. STERNHEIM: It certainly shows motive and bias on the part of Kate. There is a monetary issue here. That is not the statement of someone who feels that they are a victim as much as they feel -- it suggests that it's an opportunity that is anything but placing her in the category of victim. It sounds more like someone who is interested in a windfall.\nTHE COURT: So broadly stated, the purpose for which it's being offered?\nMS. STERNHEIM: Is her bias and motive.\nTHE COURT: And the government's objection?\nMR. ROHRBACH: The government's objection is that this\nSOUTHERN DISTRICT REPORTERS, P.C. (212) 805-0300 DOJ-OGR-00016629",
  "text_blocks": [
    {
      "type": "printed",
      "content": "Case 1:20-cr-00330-PAE Document 761 Filed 08/10/22 Page 146 of 246 2441 LCGCmax4 Loftus - direct",
      "position": "header"
    },
    {
      "type": "printed",
      "content": "1 MS. STERNHEIM: I'd appreciate that so that I can have all of the documents in front of me.\n2 THE COURT: Okay.\n3 MS. STERNHEIM: Thank you very much.\n4 THE COURT: Just so I can marinate on it. So the basic idea is that you want this witness to testify about one or two conversations that he had with this witness, who we're calling Kate, the one or two conversations that he had with Kate in which -- and his proffered testimony is that, at one point, Kate said, regarding the subject of Jeffrey Epstein, that it, quote, fell right into my lap.\nMS. STERNHEIM: That's correct.\nTHE COURT: Let's start with that one. What is the purpose for which it is being offered?\nMS. STERNHEIM: It certainly shows motive and bias on the part of Kate. There is a monetary issue here. That is not the statement of someone who feels that they are a victim as much as they feel -- it suggests that it's an opportunity that is anything but placing her in the category of victim. It sounds more like someone who is interested in a windfall.\nTHE COURT: So broadly stated, the purpose for which it's being offered?\nMS. STERNHEIM: Is her bias and motive.\nTHE COURT: And the government's objection?\nMR. ROHRBACH: The government's objection is that this",
      "position": "main"
    },
    {
      "type": "printed",
      "content": "SOUTHERN DISTRICT REPORTERS, P.C. (212) 805-0300",
      "position": "footer"
    },
    {
      "type": "printed",
      "content": "DOJ-OGR-00016629",
      "position": "footer"
    }
  ],
  "entities": {
    "people": [
      "MS. STERNHEIM",
      "THE COURT",
      "MR. ROHRBACH",
      "Jeffrey Epstein",
      "Kate"
    ],
    "organizations": [
      "SOUTHERN DISTRICT REPORTERS, P.C."
    ],
    "locations": [],
    "dates": [
      "08/10/22"
    ],
    "reference_numbers": [
      "1:20-cr-00330-PAE",
      "761",
      "DOJ-OGR-00016629"
    ]
  },
  "additional_notes": "The document appears to be a court transcript with a clear and legible format. There are no visible redactions or damage."
}