{
  "document_metadata": {
    "page_number": "50",
    "document_number": "761",
    "date": "08/10/22",
    "document_type": "court transcript",
    "has_handwriting": false,
    "has_stamps": false
  },
  "full_text": "Case 1:20-cr-00330-PAE Document 761 Filed 08/10/22 Page 50 of 246 2345 LCGCmax2 Espinosa - direct 1 Q. When she did travel, would she always travel with Jeffrey Epstein or would she sometimes travel herself? 2 A. She sometimes traveled herself. 3 Q. Did you ever travel with her? 4 A. No. 5 Q. If Mr. Epstein wanted to travel to one of his properties to visit, what preparation would need to occur before he traveled? 6 A. Well, Jeffrey had -- we always had the houses prepared, all 7 of the houses prepared for wherever he decided he wanted to go. 8 So what needed to happen was there was bread flown in, his 9 favorite bread that he liked. I think we did butter, as well. 10 Make sure that the houses were stocked. There were certain 11 things from New York that he wanted specifically in all of the 12 residences, and it needed to be fresh for his arrival. So on 13 occasion, it wouldn't be odd to ship out this food to each of 14 the residences so that it would be there for whenever he 15 decided to show up or go. 16 Q. And whose job was it to supervise all of these logistics? 17 A. It would be Ghislaine's. 18 Q. And did you assist her with those? 19 A. Absolutely. 20 \"Q. Do you recall someone named, I think you mentioned before, 21 Emmy Taylor? 22 A. Yes. 23 Q. Who was Emmy Taylor? 24 SOUTHERN DISTRICT REPORTERS, P.C. (212) 805-0300 DOJ-OGR-00016533",
  "text_blocks": [
    {
      "type": "printed",
      "content": "Case 1:20-cr-00330-PAE Document 761 Filed 08/10/22 Page 50 of 246 2345 LCGCmax2 Espinosa - direct",
      "position": "header"
    },
    {
      "type": "printed",
      "content": "1 Q. When she did travel, would she always travel with Jeffrey Epstein or would she sometimes travel herself? 2 A. She sometimes traveled herself. 3 Q. Did you ever travel with her? 4 A. No. 5 Q. If Mr. Epstein wanted to travel to one of his properties to visit, what preparation would need to occur before he traveled? 6 A. Well, Jeffrey had -- we always had the houses prepared, all 7 of the houses prepared for wherever he decided he wanted to go. 8 So what needed to happen was there was bread flown in, his 9 favorite bread that he liked. I think we did butter, as well. 10 Make sure that the houses were stocked. There were certain 11 things from New York that he wanted specifically in all of the 12 residences, and it needed to be fresh for his arrival. So on 13 occasion, it wouldn't be odd to ship out this food to each of 14 the residences so that it would be there for whenever he 15 decided to show up or go. 16 Q. And whose job was it to supervise all of these logistics? 17 A. It would be Ghislaine's. 18 Q. And did you assist her with those? 19 A. Absolutely. 20 \"Q. Do you recall someone named, I think you mentioned before, 21 Emmy Taylor? 22 A. Yes. 23 Q. Who was Emmy Taylor?",
      "position": "main"
    },
    {
      "type": "printed",
      "content": "SOUTHERN DISTRICT REPORTERS, P.C. (212) 805-0300 DOJ-OGR-00016533",
      "position": "footer"
    }
  ],
  "entities": {
    "people": [
      "Jeffrey Epstein",
      "Ghislaine",
      "Emmy Taylor"
    ],
    "organizations": [
      "SOUTHERN DISTRICT REPORTERS, P.C."
    ],
    "locations": [
      "New York"
    ],
    "dates": [
      "08/10/22"
    ],
    "reference_numbers": [
      "1:20-cr-00330-PAE",
      "761",
      "DOJ-OGR-00016533"
    ]
  },
  "additional_notes": "The document appears to be a court transcript with clear and legible text. There are no visible redactions or damage."
}