{
  "document_metadata": {
    "page_number": "1",
    "document_number": "798-2",
    "date": "08/01/25",
    "document_type": "Court Order",
    "has_handwriting": false,
    "has_stamps": false
  },
  "full_text": "Case 1:20-cr-00330-PAE Document 798-2 Filed 08/01/25 Page 1 of 1\n\nUNITED STATES DISTRICT COURT\nSOUTHERN DISTRICT OF NEW YORK\n---------------------------------------------------------------X\nUNITED STATES OF AMERICA,\n: 20 CR. 330 (PAE)\n- against -\n[PROPOSED]\nORDER GRANTING MOTION TO\nWITHDRAW\nGHISLAINE MAXWELL,\n:\nDefendant.\n---------------------------------------------------------------X\n\nUpon consideration of the Motion to Withdraw, it is HEREBY ORDERED THAT\nChristian R. Everdell and Mark S. Cohen of Cohen & Gresser LLP are granted leave to withdraw\nas co-counsel for defendant Ghislaine Maxwell in the above-captioned matter.\n\nDated: ______________, 2025\n\nThe Honorable Paul A. Engelmayer\nUnited States District Judge\n\nDOJ-OGR-00015077",
  "text_blocks": [
    {
      "type": "printed",
      "content": "Case 1:20-cr-00330-PAE Document 798-2 Filed 08/01/25 Page 1 of 1",
      "position": "header"
    },
    {
      "type": "printed",
      "content": "UNITED STATES DISTRICT COURT\nSOUTHERN DISTRICT OF NEW YORK",
      "position": "top"
    },
    {
      "type": "printed",
      "content": "UNITED STATES OF AMERICA,\n: 20 CR. 330 (PAE)\n- against -\n[PROPOSED]\nORDER GRANTING MOTION TO\nWITHDRAW\nGHISLAINE MAXWELL,\n:\nDefendant.",
      "position": "top"
    },
    {
      "type": "printed",
      "content": "Upon consideration of the Motion to Withdraw, it is HEREBY ORDERED THAT\nChristian R. Everdell and Mark S. Cohen of Cohen & Gresser LLP are granted leave to withdraw\nas co-counsel for defendant Ghislaine Maxwell in the above-captioned matter.",
      "position": "middle"
    },
    {
      "type": "printed",
      "content": "Dated: ______________, 2025",
      "position": "middle"
    },
    {
      "type": "printed",
      "content": "The Honorable Paul A. Engelmayer\nUnited States District Judge",
      "position": "bottom"
    },
    {
      "type": "printed",
      "content": "DOJ-OGR-00015077",
      "position": "footer"
    }
  ],
  "entities": {
    "people": [
      "Ghislaine Maxwell",
      "Christian R. Everdell",
      "Mark S. Cohen",
      "Paul A. Engelmayer"
    ],
    "organizations": [
      "United States District Court",
      "Cohen & Gresser LLP",
      "United States District Court for the Southern District of New York"
    ],
    "locations": [
      "New York"
    ],
    "dates": [
      "08/01/25",
      "2025"
    ],
    "reference_numbers": [
      "1:20-cr-00330-PAE",
      "20 CR. 330 (PAE)",
      "798-2",
      "DOJ-OGR-00015077"
    ]
  },
  "additional_notes": "The document appears to be a court order granting a motion to withdraw as counsel for Ghislaine Maxwell. The document is dated August 1, 2025, and is signed by The Honorable Paul A. Engelmayer, United States District Judge. The document is a proposed order and has a blank date line for the judge's signature."
}