{
  "document_metadata": {
    "page_number": "122",
    "document_number": "782",
    "date": "01/15/25",
    "document_type": "court transcript",
    "has_handwriting": false,
    "has_stamps": false
  },
  "full_text": "Case 1:20-cr-00330-PAE Document 782 Filed 01/15/25 Page 122 of 158 122 LBAGmax4 Rocchio - Cross 1 you, but off the top of my head, no. 2 Q. And would you agree with me that there are many things that 3 can interfere with accurate memories? 4 A. Yes. 5 Q. You're not a neuropsychologist; correct? 6 A. Correct. 7 Q. Neuropsychology is the study of human behavior as it 8 relates to the normal and abnormal functioning of the central 9 nervous system, which includes the brain; right? 10 A. Correct. 11 Q. You're familiar with the term confabulation? 12 A. I am. 13 Q. And confabulation is a brain under certain circumstances 14 will fill in gaps to make a whole picture; correct? 15 A. An individual will fill in gaps, yes. 16 Q. Their brain will do that; right? 17 A. Their brain, their mouths. I mean, semantics at this 18 point. But generally, the way I understand confabulation is 19 consistent with your description, yes. 20 Q. And those may or may not be accurate pieces of information, 21 but the person actually believes them; right? 22 A. Are you asking if that's possible? Yes. 23 Q. That's part of what confabulation is; correct? 24 A. That those gaps may or may not be accurate, yes. 25 Q. I want to talk now about some of the exhibits that you SOUTHER DISTRICT REPORTERS, P.C. (212) 805-0300 DOJ-OGR-00014998",
  "text_blocks": [
    {
      "type": "printed",
      "content": "Case 1:20-cr-00330-PAE Document 782 Filed 01/15/25 Page 122 of 158 122",
      "position": "header"
    },
    {
      "type": "printed",
      "content": "LBAGmax4 Rocchio - Cross",
      "position": "header"
    },
    {
      "type": "printed",
      "content": "1 you, but off the top of my head, no. 2 Q. And would you agree with me that there are many things that 3 can interfere with accurate memories? 4 A. Yes. 5 Q. You're not a neuropsychologist; correct? 6 A. Correct. 7 Q. Neuropsychology is the study of human behavior as it 8 relates to the normal and abnormal functioning of the central 9 nervous system, which includes the brain; right? 10 A. Correct. 11 Q. You're familiar with the term confabulation? 12 A. I am. 13 Q. And confabulation is a brain under certain circumstances 14 will fill in gaps to make a whole picture; correct? 15 A. An individual will fill in gaps, yes. 16 Q. Their brain will do that; right? 17 A. Their brain, their mouths. I mean, semantics at this 18 point. But generally, the way I understand confabulation is 19 consistent with your description, yes. 20 Q. And those may or may not be accurate pieces of information, 21 but the person actually believes them; right? 22 A. Are you asking if that's possible? Yes. 23 Q. That's part of what confabulation is; correct? 24 A. That those gaps may or may not be accurate, yes. 25 Q. I want to talk now about some of the exhibits that you",
      "position": "main"
    },
    {
      "type": "printed",
      "content": "SOUTHER DISTRICT REPORTERS, P.C. (212) 805-0300",
      "position": "footer"
    },
    {
      "type": "printed",
      "content": "DOJ-OGR-00014998",
      "position": "footer"
    }
  ],
  "entities": {
    "people": [],
    "organizations": [
      "SOUTHER DISTRICT REPORTERS, P.C."
    ],
    "locations": [],
    "dates": [
      "01/15/25"
    ],
    "reference_numbers": [
      "1:20-cr-00330-PAE",
      "782",
      "DOJ-OGR-00014998"
    ]
  },
  "additional_notes": "The document appears to be a court transcript with a clear Q&A format. The text is mostly legible, with some minor formatting issues. There are no visible redactions or damage."
}