{
  "document_metadata": {
    "page_number": "39",
    "document_number": "782",
    "date": "01/15/25",
    "document_type": "court transcript",
    "has_handwriting": false,
    "has_stamps": false
  },
  "full_text": "Case 1:20-cr-00330-PAE Document 782 Filed 01/15/25 Page 39 of 158 39 LBAGmax2 Rocchio - Direct impairments. And if so, to what degree, if any, are those attributable in whole or in part to the alleged sexual abuse. So as part of that assessment, I'm looking at the dynamics in the relationship between the individual and the perpetrator. And we know that the grooming behaviors that induce that relationship of trust and attachment have a significant negative affect on an individual's psyche and can strongly and negatively impact their functioning afterwards. So those are things I'm looking for. Q. Dr. Rocchio, to be clear, in your forensic work, do you assume that everything a victim reports is true? A. Absolutely not. Q. Can you explain that? A. My role in a forensic capacity is to provide an objective answer based upon my evaluation and my review of the literature. And it is not dependent on who is hiring me, for example. So as I mentioned, the reason that I look at all of these other documents and the reason I administer psychological tests and talk to third parties is precisely because I'm looking for consistencies and inconsistencies in what the individual is telling me in order to form an opinion. As part of my duty in that role is to investigate various hypotheses, in a forensic setting, it has to be that I'm not being told the truth. Q. To take a step back, to be clear, in your clinical work, do SOUTHERN DISTRICT REPORTERS, P.C. (212) 805-0300 DOJ-OGR-00014915",
  "text_blocks": [
    {
      "type": "printed",
      "content": "Case 1:20-cr-00330-PAE Document 782 Filed 01/15/25 Page 39 of 158 39",
      "position": "header"
    },
    {
      "type": "printed",
      "content": "LBAGmax2 Rocchio - Direct",
      "position": "header"
    },
    {
      "type": "printed",
      "content": "impairments. And if so, to what degree, if any, are those attributable in whole or in part to the alleged sexual abuse. So as part of that assessment, I'm looking at the dynamics in the relationship between the individual and the perpetrator. And we know that the grooming behaviors that induce that relationship of trust and attachment have a significant negative affect on an individual's psyche and can strongly and negatively impact their functioning afterwards. So those are things I'm looking for.",
      "position": "main"
    },
    {
      "type": "printed",
      "content": "Q. Dr. Rocchio, to be clear, in your forensic work, do you assume that everything a victim reports is true? A. Absolutely not. Q. Can you explain that? A. My role in a forensic capacity is to provide an objective answer based upon my evaluation and my review of the literature. And it is not dependent on who is hiring me, for example. So as I mentioned, the reason that I look at all of these other documents and the reason I administer psychological tests and talk to third parties is precisely because I'm looking for consistencies and inconsistencies in what the individual is telling me in order to form an opinion. As part of my duty in that role is to investigate various hypotheses, in a forensic setting, it has to be that I'm not being told the truth. Q. To take a step back, to be clear, in your clinical work, do",
      "position": "main"
    },
    {
      "type": "printed",
      "content": "SOUTHERN DISTRICT REPORTERS, P.C. (212) 805-0300",
      "position": "footer"
    },
    {
      "type": "printed",
      "content": "DOJ-OGR-00014915",
      "position": "footer"
    }
  ],
  "entities": {
    "people": [
      "Dr. Rocchio"
    ],
    "organizations": [
      "SOUTHERN DISTRICT REPORTERS, P.C."
    ],
    "locations": [],
    "dates": [
      "01/15/25"
    ],
    "reference_numbers": [
      "1:20-cr-00330-PAE",
      "782",
      "DOJ-OGR-00014915"
    ]
  },
  "additional_notes": "The document appears to be a court transcript with a clear Q&A format. The content discusses the role of a forensic expert in assessing the impact of alleged sexual abuse on an individual. The document is well-formatted and legible."
}