{
  "document_metadata": {
    "page_number": "1",
    "document_number": "DOJ-OGR-00015274",
    "date": "12/14/2021",
    "document_type": "TECS - Person Encounter List",
    "has_handwriting": false,
    "has_stamps": false
  },
  "full_text": "U.S. Customs and Border Protection U.S. Department of Homeland Security TECS - Person Encounter List Generated By: MICHAEL AZNARAN 12/14/2021 14:25 EST Page 1 of 2 Last Name First Name DOB Doc Type Document Number Date - Time (Eastern) Carrier Code Carrier Num. I/O Site Type Status Updated Status Arr Loc Dep Loc 10/14/2006 21:40 VS 23 I A272 APIS LAX LHR 01/18/2006 13:27 UNKN I A461 AIRLINE (NOT API) 04/14/2005 00:00 UA 934 O APIS PASSENGER LHR LAX 03/05/2005 18:03 UA 935 I APIS PASSENGER LAX LHR 07/24/2000 21:18 BA 179 I 4701 APIS JFK LHR 04/17/1999 18:48 AA 173 I APIS RDU LGW 11/10/1997 17:11 00 1 I A523 AIRLINE (NOT API) 11/01/1997 18:46 VS 000003 I A476 AIRLINE (NOT API) Total Number of Records: 13 Legend Codes Value Loc LOS ANGELES, CA INTL RALEIGH - DURHAM INTL AIRPORT LONDON / HEATHROW INTL LONDON / GATWICK INTL JOHN F KENNEDY INTL Doc Type For Official Use Only / Law Enforcement Sensitive 7 DOJ-OGR-00015274",
  "text_blocks": [
    {
      "type": "printed",
      "content": "U.S. Customs and Border Protection U.S. Department of Homeland Security TECS - Person Encounter List",
      "position": "header"
    },
    {
      "type": "printed",
      "content": "Generated By: MICHAEL AZNARAN",
      "position": "header"
    },
    {
      "type": "printed",
      "content": "12/14/2021 14:25 EST",
      "position": "header"
    },
    {
      "type": "printed",
      "content": "Page 1 of 2",
      "position": "header"
    },
    {
      "type": "printed",
      "content": "Last Name First Name DOB Doc Type Document Number Date - Time (Eastern) Carrier Code Carrier Num. I/O Site Type Status Updated Status Arr Loc Dep Loc",
      "position": "table header"
    },
    {
      "type": "printed",
      "content": "10/14/2006 21:40 VS 23 I A272 APIS LAX LHR 01/18/2006 13:27 UNKN I A461 AIRLINE (NOT API) 04/14/2005 00:00 UA 934 O APIS PASSENGER LHR LAX 03/05/2005 18:03 UA 935 I APIS PASSENGER LAX LHR 07/24/2000 21:18 BA 179 I 4701 APIS JFK LHR 04/17/1999 18:48 AA 173 I APIS RDU LGW 11/10/1997 17:11 00 1 I A523 AIRLINE (NOT API) 11/01/1997 18:46 VS 000003 I A476 AIRLINE (NOT API)",
      "position": "table body"
    },
    {
      "type": "printed",
      "content": "Total Number of Records: 13",
      "position": "footer"
    },
    {
      "type": "printed",
      "content": "Legend Codes Value Loc LOS ANGELES, CA INTL RALEIGH - DURHAM INTL AIRPORT LONDON / HEATHROW INTL LONDON / GATWICK INTL JOHN F KENNEDY INTL",
      "position": "footer"
    },
    {
      "type": "printed",
      "content": "Doc Type For Official Use Only / Law Enforcement Sensitive 7 DOJ-OGR-00015274",
      "position": "footer"
    }
  ],
  "entities": {
    "people": [
      "MICHAEL AZNARAN"
    ],
    "organizations": [
      "U.S. Customs and Border Protection",
      "U.S. Department of Homeland Security"
    ],
    "locations": [
      "LOS ANGELES, CA",
      "RALEIGH - DURHAM",
      "LONDON / HEATHROW",
      "LONDON / GATWICK",
      "JOHN F KENNEDY",
      "LAX",
      "LHR",
      "JFK",
      "RDU",
      "LGW"
    ],
    "dates": [
      "12/14/2021",
      "10/14/2006",
      "01/18/2006",
      "04/14/2005",
      "03/05/2005",
      "07/24/2000",
      "04/17/1999",
      "11/10/1997",
      "11/01/1997"
    ],
    "reference_numbers": [
      "DOJ-OGR-00015274",
      "A272",
      "A461",
      "934",
      "935",
      "179",
      "4701",
      "173",
      "1",
      "A523",
      "000003",
      "A476"
    ]
  },
  "additional_notes": "The document appears to be a TECS - Person Encounter List generated by MICHAEL AZNARAN on 12/14/2021. The list contains 13 records of person encounters with various airlines and locations. Some information is redacted."
}