{
  "document_metadata": {
    "page_number": "159",
    "document_number": "743",
    "date": "08/10/22",
    "document_type": "court transcript",
    "has_handwriting": false,
    "has_stamps": false
  },
  "full_text": "Case 1:20-cr-00330-PAE Document 743 Filed 08/10/22 Page 159 of 247 287 LBUVMAX4 Jane - direct 1 today? 2 A. Yes. 3 Q. Leading up to this trial, did you ask to testify under a pseudonym to protect your privacy? 4 A. Yes. 5 6 Q. I'd ask you to please take a look in the binder in front of you on the witness stand. If you could please turn to what's marked for identification as Government Exhibit 12. Just let me know when you are there please. 7 8 9 A. Here. 10 11 Q. Do you recognize that? 12 A. Yes, I do. 13 THE COURT: I just want to make sure that defense has 14 what they need. 15 MS. MENNINGER: I do. Thank you. 16 THE COURT: Okay. Thank you. Go ahead. 17 Q. What is Government Exhibit 12? 18 A. My birth certificate. 19 MS. MOE: At this time, your Honor, Government Exhibit 20 12 is in evidence under seal. I'd ask the jurors be permitted 21 to remove their juror binders and turn to Tab 12. 22 THE COURT: Without objection, Ms. Menninger? 23 MS. MENNINGER: No objection. 24 THE COURT: Okay. Jurors, you may open the binder and 25 look at what's been admitted as GX-12, please. SOUTHERN DISTRICT REPORTERS, P.C. (212) 805-0300 DOJ-OGR-00017521",
  "text_blocks": [
    {
      "type": "printed",
      "content": "Case 1:20-cr-00330-PAE Document 743 Filed 08/10/22 Page 159 of 247 287 LBUVMAX4 Jane - direct",
      "position": "header"
    },
    {
      "type": "printed",
      "content": "1 today? 2 A. Yes. 3 Q. Leading up to this trial, did you ask to testify under a pseudonym to protect your privacy? 4 A. Yes. 5 6 Q. I'd ask you to please take a look in the binder in front of you on the witness stand. If you could please turn to what's marked for identification as Government Exhibit 12. Just let me know when you are there please. 7 8 9 A. Here. 10 11 Q. Do you recognize that? 12 A. Yes, I do. 13 THE COURT: I just want to make sure that defense has 14 what they need. 15 MS. MENNINGER: I do. Thank you. 16 THE COURT: Okay. Thank you. Go ahead. 17 Q. What is Government Exhibit 12? 18 A. My birth certificate. 19 MS. MOE: At this time, your Honor, Government Exhibit 20 12 is in evidence under seal. I'd ask the jurors be permitted 21 to remove their juror binders and turn to Tab 12. 22 THE COURT: Without objection, Ms. Menninger? 23 MS. MENNINGER: No objection. 24 THE COURT: Okay. Jurors, you may open the binder and 25 look at what's been admitted as GX-12, please.",
      "position": "main"
    },
    {
      "type": "printed",
      "content": "SOUTHERN DISTRICT REPORTERS, P.C. (212) 805-0300",
      "position": "footer"
    },
    {
      "type": "printed",
      "content": "DOJ-OGR-00017521",
      "position": "footer"
    }
  ],
  "entities": {
    "people": [
      "Jane",
      "Ms. Menninger",
      "Ms. Moe"
    ],
    "organizations": [
      "SOUTHERN DISTRICT REPORTERS, P.C."
    ],
    "locations": [],
    "dates": [
      "08/10/22"
    ],
    "reference_numbers": [
      "1:20-cr-00330-PAE",
      "743",
      "159",
      "247",
      "287",
      "LBUVMAX4",
      "12",
      "GX-12",
      "DOJ-OGR-00017521"
    ]
  },
  "additional_notes": "The document appears to be a court transcript with a clear and readable format. There are no visible redactions or damage."
}