{
  "document_metadata": {
    "page_number": "182",
    "document_number": "743",
    "date": "08/10/22",
    "document_type": "Court Transcript",
    "has_handwriting": false,
    "has_stamps": false
  },
  "full_text": "Case 1:20-cr-00330-PAE Document 743 Filed 08/10/22 Page 182 of 247 310 LBUVMAX4 Jane - direct 1 A. Yes. 2 Q. Where did Epstein touch your body? 3 A. He would touch my breasts, he would touch my vagina. 4 Q. During these incidents we've been discussing when you were 5 14, did you touch Epstein's body? 6 A. Yes 7 Q. Where did you touch his body? 8 A. Everywhere. 9 Q. When you were alone with Maxwell and Epstein when you were 10 14, did anyone ever use a sex toy? 11 A. Yes. 12 Q. I'm sorry to ask you this, but could you please describe 13 for the jury what would happen during those incidents. 14 A. He liked to, like, use, like, vibrators that were different 15 sizes; and even, like, those -- like -- like the back massagers 16 that were, like, really, you know, painful. 17 Q. During those incidents, what did Epstein do with that back 18 massager? 19 A. He would -- he would put it on my vagina even if I said 20 that it hurt. 21 Q. During these incidents, did Maxwell ever touch your body? 22 A. Yes. 23 Q. Where would she touch you? 24 A. I would say mainly my breast. 25 Q. Earlier, I believe you said that during these incidents, SOUTHERN DISTRICT REPORTERS, P.C. (212) 805-0300 DOJ-OGR-00017544",
  "text_blocks": [
    {
      "type": "printed",
      "content": "Case 1:20-cr-00330-PAE Document 743 Filed 08/10/22 Page 182 of 247 310 LBUVMAX4 Jane - direct",
      "position": "header"
    },
    {
      "type": "printed",
      "content": "1 A. Yes. 2 Q. Where did Epstein touch your body? 3 A. He would touch my breasts, he would touch my vagina. 4 Q. During these incidents we've been discussing when you were 5 14, did you touch Epstein's body? 6 A. Yes 7 Q. Where did you touch his body? 8 A. Everywhere. 9 Q. When you were alone with Maxwell and Epstein when you were 10 14, did anyone ever use a sex toy? 11 A. Yes. 12 Q. I'm sorry to ask you this, but could you please describe 13 for the jury what would happen during those incidents. 14 A. He liked to, like, use, like, vibrators that were different 15 sizes; and even, like, those -- like -- like the back massagers 16 that were, like, really, you know, painful. 17 Q. During those incidents, what did Epstein do with that back 18 massager? 19 A. He would -- he would put it on my vagina even if I said 20 that it hurt. 21 Q. During these incidents, did Maxwell ever touch your body? 22 A. Yes. 23 Q. Where would she touch you? 24 A. I would say mainly my breast. 25 Q. Earlier, I believe you said that during these incidents,",
      "position": "main"
    },
    {
      "type": "printed",
      "content": "SOUTHERN DISTRICT REPORTERS, P.C. (212) 805-0300",
      "position": "footer"
    },
    {
      "type": "printed",
      "content": "DOJ-OGR-00017544",
      "position": "footer"
    }
  ],
  "entities": {
    "people": [
      "Epstein",
      "Maxwell",
      "Jane"
    ],
    "organizations": [
      "SOUTHERN DISTRICT REPORTERS, P.C."
    ],
    "locations": [],
    "dates": [
      "08/10/22"
    ],
    "reference_numbers": [
      "1:20-cr-00330-PAE",
      "743",
      "DOJ-OGR-00017544"
    ]
  },
  "additional_notes": "The document appears to be a court transcript with sensitive content. The text is clear and legible, with no visible redactions or damage."
}