{
  "document_metadata": {
    "page_number": "64",
    "document_number": "765",
    "date": "08/10/22",
    "document_type": "court transcript",
    "has_handwriting": false,
    "has_stamps": false
  },
  "full_text": "Case 1:20-cr-00330-AJN Document 765 Filed 08/10/22 Page 64 of 95 LCIAMAX2ps 2802 1 record that relates to that topic. So I think that -- 2 THE COURT: So the defense has questioned multiple 3 witnesses on their perceptions of individual ages, of relevant 4 individuals' ages, so that puts into question the knowledge 5 element with respect to ages, and it's true there's testimony 6 from each of the alleged victims as to what they told 7 Ms. Maxwell, but of course I don't know whether the jury will 8 accept that testimony or not, or any of those individual pieces 9 of testimony. So it seems like having -- the question here is 10 whether there are specific elements, knowledge elements that 11 are in issue, either because it's what some of the evidence 12 goes to or because the defense has made cross-points or will 13 make arguments regarding that. I mean, I don't suppose it's 14 the case that the defense won't -- will it not argue during 15 closing anything with respect to whether Ms. Maxwell knew of 16 the relevant ages? 17 MS. STERNHEIM: May we have a moment, Judge? 18 THE COURT: Sure. 19 MR. PAGLIUCA: Here's the -- I'm going to try to 20 address -- there's a larger concern. I need to break this into 21 two pieces. 22 THE COURT: OK. 23 MR. PAGLIUCA: One that I view as an evidentiary issue 24 with the indictment and the evidence in the case is that there 25 was testimony about multiple females being at the Palm Beach  SOUTHERN DISTRICT REPORTERS, P.C. (212) 805-0300 DOJ-OGR-00016990",
  "text_blocks": [
    {
      "type": "printed",
      "content": "Case 1:20-cr-00330-AJN Document 765 Filed 08/10/22 Page 64 of 95",
      "position": "header"
    },
    {
      "type": "printed",
      "content": "LCIAMAX2ps 2802",
      "position": "header"
    },
    {
      "type": "printed",
      "content": "1 record that relates to that topic. So I think that --",
      "position": "main"
    },
    {
      "type": "printed",
      "content": "2 THE COURT: So the defense has questioned multiple",
      "position": "main"
    },
    {
      "type": "printed",
      "content": "3 witnesses on their perceptions of individual ages, of relevant",
      "position": "main"
    },
    {
      "type": "printed",
      "content": "4 individuals' ages, so that puts into question the knowledge",
      "position": "main"
    },
    {
      "type": "printed",
      "content": "5 element with respect to ages, and it's true there's testimony",
      "position": "main"
    },
    {
      "type": "printed",
      "content": "6 from each of the alleged victims as to what they told",
      "position": "main"
    },
    {
      "type": "printed",
      "content": "7 Ms. Maxwell, but of course I don't know whether the jury will",
      "position": "main"
    },
    {
      "type": "printed",
      "content": "8 accept that testimony or not, or any of those individual pieces",
      "position": "main"
    },
    {
      "type": "printed",
      "content": "9 of testimony. So it seems like having -- the question here is",
      "position": "main"
    },
    {
      "type": "printed",
      "content": "10 whether there are specific elements, knowledge elements that",
      "position": "main"
    },
    {
      "type": "printed",
      "content": "11 are in issue, either because it's what some of the evidence",
      "position": "main"
    },
    {
      "type": "printed",
      "content": "12 goes to or because the defense has made cross-points or will",
      "position": "main"
    },
    {
      "type": "printed",
      "content": "13 make arguments regarding that. I mean, I don't suppose it's",
      "position": "main"
    },
    {
      "type": "printed",
      "content": "14 the case that the defense won't -- will it not argue during",
      "position": "main"
    },
    {
      "type": "printed",
      "content": "15 closing anything with respect to whether Ms. Maxwell knew of",
      "position": "main"
    },
    {
      "type": "printed",
      "content": "16 the relevant ages?",
      "position": "main"
    },
    {
      "type": "printed",
      "content": "17 MS. STERNHEIM: May we have a moment, Judge?",
      "position": "main"
    },
    {
      "type": "printed",
      "content": "18 THE COURT: Sure.",
      "position": "main"
    },
    {
      "type": "printed",
      "content": "19 MR. PAGLIUCA: Here's the -- I'm going to try to",
      "position": "main"
    },
    {
      "type": "printed",
      "content": "20 address -- there's a larger concern. I need to break this into",
      "position": "main"
    },
    {
      "type": "printed",
      "content": "21 two pieces.",
      "position": "main"
    },
    {
      "type": "printed",
      "content": "22 THE COURT: OK.",
      "position": "main"
    },
    {
      "type": "printed",
      "content": "23 MR. PAGLIUCA: One that I view as an evidentiary issue",
      "position": "main"
    },
    {
      "type": "printed",
      "content": "24 with the indictment and the evidence in the case is that there",
      "position": "main"
    },
    {
      "type": "printed",
      "content": "25 was testimony about multiple females being at the Palm Beach",
      "position": "main"
    },
    {
      "type": "printed",
      "content": "SOUTHERN DISTRICT REPORTERS, P.C. (212) 805-0300",
      "position": "footer"
    },
    {
      "type": "printed",
      "content": "DOJ-OGR-00016990",
      "position": "footer"
    }
  ],
  "entities": {
    "people": [
      "Ms. Maxwell",
      "Ms. Sternheim",
      "Mr. Pagliuca"
    ],
    "organizations": [
      "SOUTHERN DISTRICT REPORTERS, P.C."
    ],
    "locations": [
      "Palm Beach"
    ],
    "dates": [
      "08/10/22"
    ],
    "reference_numbers": [
      "1:20-cr-00330-AJN",
      "765",
      "DOJ-OGR-00016990"
    ]
  },
  "additional_notes": "The document appears to be a court transcript with a clear and legible format. There are no visible redactions or damage to the document."
}