{
  "document_metadata": {
    "page_number": "27",
    "document_number": "773",
    "date": "08/10/22",
    "document_type": "court transcript",
    "has_handwriting": false,
    "has_stamps": false
  },
  "full_text": "Case 1:20-cr-00330-PAE Document 773 Filed 08/10/22 Page 27 of 29\nLCRVMAXT\n1 MS. MENNINGER: But the rest of the language, your\n2 Honor, last Thursday was \"if you want to.\" And this one seems\n3 a little bit more like we're suggesting that you do it unless\n4 you have a hardship.\n5 THE COURT: I clearly have discretion to set the\n6 schedule, there's no doubt about that. And I can do it over\n7 your objection. So I'm happy to give -- I think we should set\n8 it as a default, unless there's a hardship.\n9 MS. MENNINGER: I understand that, your Honor. I just\n10 would request -- and it's our request that your Honor not\n11 include the language \"unless deliberations are complete.\"\n12 THE COURT: I will use the same language that I used\n13 last week. It's precisely the same language I used on multiple\n14 occasions without objection. And I don't want them to assume\n15 that I think it should take longer than that. That's the\n16 concern. So I don't want them to assume what I'm saying, that\n17 I'm suggesting it should take longer. I don't want them to\n18 assume it should take shorter. I'm happy to add, if you want,\n19 Of course, I don't mean this in any way to pressure you; you\n20 should take all the time you need.\n21 MS. MENNINGER: Yes, very much would appreciate that,\n22 your Honor.\n23 THE COURT: Ms. Moe.\n24 MS. MOE: No objection, your Honor. Thank you.\n25 THE COURT: All right. Bring in the jury.\nSOUTHERN DISTRICT REPORTERS, P.C.\n(212) 805-0300\nDOJ-OGR-00017331",
  "text_blocks": [
    {
      "type": "printed",
      "content": "Case 1:20-cr-00330-PAE Document 773 Filed 08/10/22 Page 27 of 29",
      "position": "header"
    },
    {
      "type": "printed",
      "content": "LCRVMAXT",
      "position": "header"
    },
    {
      "type": "printed",
      "content": "1 MS. MENNINGER: But the rest of the language, your\n2 Honor, last Thursday was \"if you want to.\" And this one seems\n3 a little bit more like we're suggesting that you do it unless\n4 you have a hardship.\n5 THE COURT: I clearly have discretion to set the\n6 schedule, there's no doubt about that. And I can do it over\n7 your objection. So I'm happy to give -- I think we should set\n8 it as a default, unless there's a hardship.\n9 MS. MENNINGER: I understand that, your Honor. I just\n10 would request -- and it's our request that your Honor not\n11 include the language \"unless deliberations are complete.\"\n12 THE COURT: I will use the same language that I used\n13 last week. It's precisely the same language I used on multiple\n14 occasions without objection. And I don't want them to assume\n15 that I think it should take longer than that. That's the\n16 concern. So I don't want them to assume what I'm saying, that\n17 I'm suggesting it should take longer. I don't want them to\n18 assume it should take shorter. I'm happy to add, if you want,\n19 Of course, I don't mean this in any way to pressure you; you\n20 should take all the time you need.\n21 MS. MENNINGER: Yes, very much would appreciate that,\n22 your Honor.\n23 THE COURT: Ms. Moe.\n24 MS. MOE: No objection, your Honor. Thank you.\n25 THE COURT: All right. Bring in the jury.",
      "position": "main"
    },
    {
      "type": "printed",
      "content": "SOUTHERN DISTRICT REPORTERS, P.C.\n(212) 805-0300",
      "position": "footer"
    },
    {
      "type": "printed",
      "content": "DOJ-OGR-00017331",
      "position": "footer"
    }
  ],
  "entities": {
    "people": [
      "MS. MENNINGER",
      "THE COURT",
      "MS. MOE"
    ],
    "organizations": [
      "SOUTHERN DISTRICT REPORTERS, P.C."
    ],
    "locations": [],
    "dates": [
      "08/10/22"
    ],
    "reference_numbers": [
      "1:20-cr-00330-PAE",
      "773",
      "DOJ-OGR-00017331"
    ]
  },
  "additional_notes": "The document appears to be a court transcript with a clear and legible format. There are no visible redactions or damage."
}