{
  "document_metadata": {
    "page_number": "95",
    "document_number": "759",
    "date": "08/10/22",
    "document_type": "court transcript",
    "has_handwriting": false,
    "has_stamps": false
  },
  "full_text": "Case 1:20-cr-00330-PAE Document 759 Filed 08/10/22 Page 95 of 267\nLCACmax3 A. Farmer - cross\n1 THE COURT: And that's behind tab 1?\n2 MS. MENNINGER: I think we have the 3500 material\n3 first, your Honor. So it's about halfway through the binder is\n4 when the AF exhibits start.\n5 THE COURT: I see. Thank you.\n6 MS. MENNINGER: Your Honor, I've marked for\n7 identification AF1. What I would like to do is to draw the\n8 witness's attention --\n9 THE COURT: You want to direct the witness to a page?\n10 MS. MENNINGER: Page 2, exactly, of that entry.\n11 THE COURT: Of AF1?\n12 MS. MENNINGER: Yes.\n13 BY MS. MENNINGER:\n14 Q. Do you see that entry?\n15 A. Yes.\n16 Q. Do you recognize this was another entry in the same\n17 journal?\n18 A. Yes.\n19 MS. MENNINGER: And I don't believe it was in the\n20 government's exhibit, and that's why I'm asking to introduce\n21 this page, and I can work out with the government later if\n22 there is any redactions. I don't think any are appropriate,\n23 but --\n24 MS. POMERANTZ: No objection, your Honor.\n25 THE COURT: AF1 is admitted temporarily under seal so\nSOUTHERN DISTRICT REPORTERS, P.C.\n(212) 805-0300\nDOJ-OGR-00016311",
  "text_blocks": [
    {
      "type": "printed",
      "content": "Case 1:20-cr-00330-PAE Document 759 Filed 08/10/22 Page 95 of 267",
      "position": "header"
    },
    {
      "type": "printed",
      "content": "LCACmax3 A. Farmer - cross",
      "position": "header"
    },
    {
      "type": "printed",
      "content": "1 THE COURT: And that's behind tab 1?\n2 MS. MENNINGER: I think we have the 3500 material\n3 first, your Honor. So it's about halfway through the binder is\n4 when the AF exhibits start.\n5 THE COURT: I see. Thank you.\n6 MS. MENNINGER: Your Honor, I've marked for\n7 identification AF1. What I would like to do is to draw the\n8 witness's attention --\n9 THE COURT: You want to direct the witness to a page?\n10 MS. MENNINGER: Page 2, exactly, of that entry.\n11 THE COURT: Of AF1?\n12 MS. MENNINGER: Yes.\n13 BY MS. MENNINGER:\n14 Q. Do you see that entry?\n15 A. Yes.\n16 Q. Do you recognize this was another entry in the same\n17 journal?\n18 A. Yes.\n19 MS. MENNINGER: And I don't believe it was in the\n20 government's exhibit, and that's why I'm asking to introduce\n21 this page, and I can work out with the government later if\n22 there is any redactions. I don't think any are appropriate,\n23 but --\n24 MS. POMERANTZ: No objection, your Honor.\n25 THE COURT: AF1 is admitted temporarily under seal so",
      "position": "main"
    },
    {
      "type": "printed",
      "content": "SOUTHERN DISTRICT REPORTERS, P.C.\n(212) 805-0300",
      "position": "footer"
    },
    {
      "type": "printed",
      "content": "DOJ-OGR-00016311",
      "position": "footer"
    }
  ],
  "entities": {
    "people": [
      "MS. MENNINGER",
      "THE COURT",
      "MS. POMERANTZ",
      "A. Farmer"
    ],
    "organizations": [
      "SOUTHERN DISTRICT REPORTERS, P.C."
    ],
    "locations": [],
    "dates": [
      "08/10/22"
    ],
    "reference_numbers": [
      "1:20-cr-00330-PAE",
      "759",
      "DOJ-OGR-00016311"
    ]
  },
  "additional_notes": "The document appears to be a court transcript with a clear and legible format. There are no visible redactions or damage to the text."
}