{
  "document_metadata": {
    "page_number": "105",
    "document_number": "743",
    "date": "08/10/22",
    "document_type": "Court Document",
    "has_handwriting": false,
    "has_stamps": false
  },
  "full_text": "Case 1:20-cr-00330-PAE Document 743 Filed 08/10/22 Page 105 of 247 233 LBUCmax3 Visoski - cross 1 A. I do not. 2 Q. Do you recall meeting or seeing anyone with Carolyn's full 3 name on any flights? 4 A. I do not. 5 Q. And to your knowledge, there is no record of anyone with 6 Carolyn's full name flying on any of Epstein's flights? 7 A. Not to my knowledge. I don't have any memory at all. 8 Q. Mr. Visoski, during your testimony so far, you've mentioned 9 the names of some pretty important people; isn't that fair to 10 say? 11 A. Yes. 12 Q. You already said that former president Bill Clinton flew on 13 some of the flights? 14 A. Yes, he did. 15 Q. And Prince Andrew on some of the flights? 16 A. Yes. 17 Q. Itzhak Perlman, the famous violinist, on some of the 18 flights? 19 A. Yes. 20 Q. Donald Trump, before he was president, also flew on 21 Epstein's flights; isn't that right? 22 A. Yes, he did. 23 Q. He flew on them a number of times; right? 24 A. There was more than once I believe, yes. 25 Q. Sometimes he flew with his family members, too; right? SOUTHERN DISTRICT REPORTERS, P.C. (212) 805-0300 DOJ-OGR-00017467",
  "text_blocks": [
    {
      "type": "printed",
      "content": "Case 1:20-cr-00330-PAE Document 743 Filed 08/10/22 Page 105 of 247 233",
      "position": "header"
    },
    {
      "type": "printed",
      "content": "LBUCmax3 Visoski - cross",
      "position": "header"
    },
    {
      "type": "printed",
      "content": "1 A. I do not. 2 Q. Do you recall meeting or seeing anyone with Carolyn's full 3 name on any flights? 4 A. I do not. 5 Q. And to your knowledge, there is no record of anyone with 6 Carolyn's full name flying on any of Epstein's flights? 7 A. Not to my knowledge. I don't have any memory at all. 8 Q. Mr. Visoski, during your testimony so far, you've mentioned 9 the names of some pretty important people; isn't that fair to 10 say? 11 A. Yes. 12 Q. You already said that former president Bill Clinton flew on 13 some of the flights? 14 A. Yes, he did. 15 Q. And Prince Andrew on some of the flights? 16 A. Yes. 17 Q. Itzhak Perlman, the famous violinist, on some of the 18 flights? 19 A. Yes. 20 Q. Donald Trump, before he was president, also flew on 21 Epstein's flights; isn't that right? 22 A. Yes, he did. 23 Q. He flew on them a number of times; right? 24 A. There was more than once I believe, yes. 25 Q. Sometimes he flew with his family members, too; right?",
      "position": "main"
    },
    {
      "type": "printed",
      "content": "SOUTHERN DISTRICT REPORTERS, P.C. (212) 805-0300",
      "position": "footer"
    },
    {
      "type": "printed",
      "content": "DOJ-OGR-00017467",
      "position": "footer"
    }
  ],
  "entities": {
    "people": [
      "Carolyn",
      "Mr. Visoski",
      "Bill Clinton",
      "Prince Andrew",
      "Itzhak Perlman",
      "Donald Trump",
      "Epstein"
    ],
    "organizations": [
      "SOUTHERN DISTRICT REPORTERS, P.C."
    ],
    "locations": [],
    "dates": [
      "08/10/22"
    ],
    "reference_numbers": [
      "1:20-cr-00330-PAE",
      "743",
      "DOJ-OGR-00017467"
    ]
  },
  "additional_notes": "The document appears to be a court transcript with a clear and legible format. There are no visible redactions or damage."
}