{
  "document_metadata": {
    "page_number": "159",
    "document_number": "763",
    "date": "08/10/22",
    "document_type": "court transcript",
    "has_handwriting": false,
    "has_stamps": false
  },
  "full_text": "Case 1:20-cr-00330-AJN Document 763 Filed 08/10/22 Page 159 of 197\nLCHCmax5\n2700\n1 THE COURT: That testimony that she committed to the\n2 Kinnerton.\n3 MR. EVERDELL: She had said two different things in\n4 the 302s to the government.\n5 THE COURT: I'm talking about at trial.\n6 MR. EVERDELL: What day was in the trial transcript?\n7 THE COURT: Yes.\n8 MR. EVERDELL: I think Kate testified on 12/6, your\n9 Honor.\n10 MS. MOE: It was Monday of last week, your Honor.\n11 MR. EVERDELL: Yes. And in order to counter that, we\n12 thought we were just going to use the property records.\n13 THE COURT: Right.\n14 MR. EVERDELL: But because then the government raised\n15 the issue of the deposition testimony, which we weren't\n16 anticipating, which we think is misleading, because we think\n17 that is factually inaccurate, we thought, well, okay, now we\n18 better get somebody who can testify about her actual residency\n19 there. That's why we scrambled to find Mr. Moran, who we now\n20 have.\n21 THE COURT: From the pub across the street?\n22 MR. EVERDELL: Yes.\n23 THE COURT: Isn't that funny.\n24 MS. MOE: Your Honor, just a few things in response.\n25 The first is the defense now has property records for\nSOUTHERN DISTRICT REPORTERS, P.C.\n(212) 805-0300\nDOJ-OGR-00016888",
  "text_blocks": [
    {
      "type": "printed",
      "content": "Case 1:20-cr-00330-AJN Document 763 Filed 08/10/22 Page 159 of 197",
      "position": "header"
    },
    {
      "type": "printed",
      "content": "LCHCmax5\n2700",
      "position": "header"
    },
    {
      "type": "printed",
      "content": "1 THE COURT: That testimony that she committed to the\n2 Kinnerton.\n3 MR. EVERDELL: She had said two different things in\n4 the 302s to the government.\n5 THE COURT: I'm talking about at trial.\n6 MR. EVERDELL: What day was in the trial transcript?\n7 THE COURT: Yes.\n8 MR. EVERDELL: I think Kate testified on 12/6, your\n9 Honor.\n10 MS. MOE: It was Monday of last week, your Honor.\n11 MR. EVERDELL: Yes. And in order to counter that, we\n12 thought we were just going to use the property records.\n13 THE COURT: Right.\n14 MR. EVERDELL: But because then the government raised\n15 the issue of the deposition testimony, which we weren't\n16 anticipating, which we think is misleading, because we think\n17 that is factually inaccurate, we thought, well, okay, now we\n18 better get somebody who can testify about her actual residency\n19 there. That's why we scrambled to find Mr. Moran, who we now\n20 have.\n21 THE COURT: From the pub across the street?\n22 MR. EVERDELL: Yes.\n23 THE COURT: Isn't that funny.\n24 MS. MOE: Your Honor, just a few things in response.\n25 The first is the defense now has property records for",
      "position": "main"
    },
    {
      "type": "printed",
      "content": "SOUTHERN DISTRICT REPORTERS, P.C.\n(212) 805-0300",
      "position": "footer"
    },
    {
      "type": "printed",
      "content": "DOJ-OGR-00016888",
      "position": "footer"
    }
  ],
  "entities": {
    "people": [
      "MR. EVERDELL",
      "MS. MOE",
      "Kate",
      "Mr. Moran"
    ],
    "organizations": [
      "SOUTHERN DISTRICT REPORTERS, P.C."
    ],
    "locations": [
      "Kinnerton"
    ],
    "dates": [
      "12/6",
      "08/10/22"
    ],
    "reference_numbers": [
      "1:20-cr-00330-AJN",
      "763",
      "DOJ-OGR-00016888"
    ]
  },
  "additional_notes": "The document is a court transcript with a clear and readable format. There are no visible redactions or damage."
}