{
  "document_metadata": {
    "page_number": "53",
    "document_number": "767",
    "date": "08/10/22",
    "document_type": "Court Document",
    "has_handwriting": false,
    "has_stamps": false
  },
  "full_text": "Case 1:20-cr-00330-PAE Document 767 Filed 08/10/22 Page 53 of 257 2886 LCKCmax3 Summation - Ms. Moe 1 Maxwell delivered Kate to Epstein. 2 In 1995 and 1996, Maxwell was still in contact with 3 Kate, encouraging Kate to travel to see her and Epstein, and in 4 that same period, Maxwell was traveling with Jane, still 5 exploiting Jane, in Palm Beach, in New York, and in New Mexico. 6 And in the spring of 1996, Annie Farmer went to New 7 Mexico where Maxwell groomed her for sexual abuse, where 8 Maxwell massaged Annie's breasts. 9 In 1999, Epstein sent Maxwell $18.3 million, and the 10 abuse continued. 11 Maxwell recruited Virginia Roberts at Mar-a-Lago. In 12 2000, Virginia Roberts was 17 years old and flying with Maxwell 13 and Epstein on Epstein's private jet. And in 2001, Virginia 14 Roberts was still 17 and still flying on the jet with Maxwell 15 and Epstein. They were flying around with a teenage girl. 16 In 2001, Virginia brought Carolyn to the Palm Beach 17 house. Carolyn was 14 years old. That's when Carolyn met 18 Maxwell and Epstein, and that was the beginning of the pyramid 19 scheme of abuse, the scheme that no longer required Maxwell to 20 personally find young girls for Epstein, girls like Carolyn 21 incentivized by extra cash were now bringing their friends, 22 girls who needed money. 23 And one year later in 2002, Epstein paid Maxwell 24 $5 million. 25 In 2002, 2003, and 2004, Carolyn was sexually abused SOUTHERN DISTRICT REPORTERS, P.C. (212) 805-0300 DOJ-OGR-00017074",
  "text_blocks": [
    {
      "type": "printed",
      "content": "Case 1:20-cr-00330-PAE Document 767 Filed 08/10/22 Page 53 of 257 2886 LCKCmax3 Summation - Ms. Moe",
      "position": "header"
    },
    {
      "type": "printed",
      "content": "1 Maxwell delivered Kate to Epstein. 2 In 1995 and 1996, Maxwell was still in contact with 3 Kate, encouraging Kate to travel to see her and Epstein, and in 4 that same period, Maxwell was traveling with Jane, still 5 exploiting Jane, in Palm Beach, in New York, and in New Mexico. 6 And in the spring of 1996, Annie Farmer went to New 7 Mexico where Maxwell groomed her for sexual abuse, where 8 Maxwell massaged Annie's breasts. 9 In 1999, Epstein sent Maxwell $18.3 million, and the 10 abuse continued. 11 Maxwell recruited Virginia Roberts at Mar-a-Lago. In 12 2000, Virginia Roberts was 17 years old and flying with Maxwell 13 and Epstein on Epstein's private jet. And in 2001, Virginia 14 Roberts was still 17 and still flying on the jet with Maxwell 15 and Epstein. They were flying around with a teenage girl. 16 In 2001, Virginia brought Carolyn to the Palm Beach 17 house. Carolyn was 14 years old. That's when Carolyn met 18 Maxwell and Epstein, and that was the beginning of the pyramid 19 scheme of abuse, the scheme that no longer required Maxwell to 20 personally find young girls for Epstein, girls like Carolyn 21 incentivized by extra cash were now bringing their friends, 22 girls who needed money. 23 And one year later in 2002, Epstein paid Maxwell 24 $5 million. 25 In 2002, 2003, and 2004, Carolyn was sexually abused",
      "position": "main"
    },
    {
      "type": "printed",
      "content": "SOUTHERN DISTRICT REPORTERS, P.C. (212) 805-0300",
      "position": "footer"
    },
    {
      "type": "printed",
      "content": "DOJ-OGR-00017074",
      "position": "footer"
    }
  ],
  "entities": {
    "people": [
      "Maxwell",
      "Kate",
      "Epstein",
      "Jane",
      "Annie Farmer",
      "Virginia Roberts",
      "Carolyn"
    ],
    "organizations": [
      "SOUTHERN DISTRICT REPORTERS, P.C."
    ],
    "locations": [
      "Palm Beach",
      "New York",
      "New Mexico",
      "Mar-a-Lago"
    ],
    "dates": [
      "1995",
      "1996",
      "1999",
      "2000",
      "2001",
      "2002",
      "2003",
      "2004",
      "08/10/22"
    ],
    "reference_numbers": [
      "1:20-cr-00330-PAE",
      "767",
      "DOJ-OGR-00017074",
      "$18.3 million",
      "$5 million"
    ]
  },
  "additional_notes": "The document appears to be a court transcript or legal document related to the case against Maxwell. The text describes the alleged abuse and exploitation of young girls by Maxwell and Epstein. The document is typed and contains no handwritten text or stamps."
}