{
  "document_metadata": {
    "page_number": "85",
    "document_number": "761",
    "date": "08/10/22",
    "document_type": "court transcript",
    "has_handwriting": false,
    "has_stamps": false
  },
  "full_text": "Case 1:20-cr-00330-PAE Document 761 Filed 08/10/22 Page 85 of 246 2380 LCGVMAX3 Espinosa - direct 1 time you met with him? 2 A. I don't -- 3 MS. POMERANTZ: Objection. 4 A. I don't know. 5 THE COURT: The response was \"I don't know.\" 6 I'll allow that. Move on. 7 Q. And just jumping back, do you recall roughly when it was 8 that Ghislaine started seeing Ted Waitt as a couple? 9 A. Well, it was before I left in 2002. Maybe -- 10 THE COURT: Could you speak into the mic? 11 A. It was before I left in 2002, so probably 2001 or so. 12 Q. The best guess from your recollection? 13 A. Best guess. 14 15 THE COURT: Mr. Everdell, we'll break here for the morning, unless -- 16 MR. EVERDELL: Actually, if I could just have one moment, your Honor. 17 18 THE COURT: Sure. 19 (Counsel conferred with defendant) 20 MR. EVERDELL: I think it's a good time to take a break, your Honor, if we could. 21 22 THE COURT: How much longer do you anticipate? 23 MR. EVERDELL: I don't think I have very much, but I just wanted the chance to confer. 24 25 THE COURT: All right. So we'll break for 15 minutes, SOUTHERN DISTRICT REPORTERS, P.C. (212) 805-0300 DOJ-OGR-00016568",
  "text_blocks": [
    {
      "type": "printed",
      "content": "Case 1:20-cr-00330-PAE Document 761 Filed 08/10/22 Page 85 of 246 2380 LCGVMAX3 Espinosa - direct",
      "position": "header"
    },
    {
      "type": "printed",
      "content": "1 time you met with him? 2 A. I don't -- 3 MS. POMERANTZ: Objection. 4 A. I don't know. 5 THE COURT: The response was \"I don't know.\" 6 I'll allow that. Move on. 7 Q. And just jumping back, do you recall roughly when it was 8 that Ghislaine started seeing Ted Waitt as a couple? 9 A. Well, it was before I left in 2002. Maybe -- 10 THE COURT: Could you speak into the mic? 11 A. It was before I left in 2002, so probably 2001 or so. 12 Q. The best guess from your recollection? 13 A. Best guess. 14 15 THE COURT: Mr. Everdell, we'll break here for the morning, unless -- 16 MR. EVERDELL: Actually, if I could just have one moment, your Honor. 17 18 THE COURT: Sure. 19 (Counsel conferred with defendant) 20 MR. EVERDELL: I think it's a good time to take a break, your Honor, if we could. 21 22 THE COURT: How much longer do you anticipate? 23 MR. EVERDELL: I don't think I have very much, but I just wanted the chance to confer. 24 25 THE COURT: All right. So we'll break for 15 minutes,",
      "position": "main"
    },
    {
      "type": "printed",
      "content": "SOUTHERN DISTRICT REPORTERS, P.C. (212) 805-0300",
      "position": "footer"
    },
    {
      "type": "printed",
      "content": "DOJ-OGR-00016568",
      "position": "footer"
    }
  ],
  "entities": {
    "people": [
      "Ghislaine",
      "Ted Waitt",
      "Mr. Everdell",
      "MS. POMERANTZ"
    ],
    "organizations": [
      "SOUTHERN DISTRICT REPORTERS, P.C."
    ],
    "locations": [],
    "dates": [
      "08/10/22",
      "2002",
      "2001"
    ],
    "reference_numbers": [
      "1:20-cr-00330-PAE",
      "761",
      "DOJ-OGR-00016568"
    ]
  },
  "additional_notes": "The document appears to be a court transcript with clear and legible text. There are no visible redactions or damage."
}