{
  "document_metadata": {
    "page_number": "817",
    "document_number": "NYM-19-0076",
    "date": "7/23/2019",
    "document_type": "Form 583 Report of Incident",
    "has_handwriting": false,
    "has_stamps": false
  },
  "full_text": "Page 817 Form 583 Report of Incident Incident #: NYM-19-0076 Submitted By: Date/Time Of Incident: 7/23/2019 1:27 AM [b](7)(A) Section 3: Others Involved Name: [b](6); [b](7)(C) Person Type: Staff Medical Attention Required: No Death: No Injury Category: No Injury Staff Injury by Inmate: No Sexual Assault: No Name: [b](6); [b](7)(C) Person Type: Staff Medical Attention Required: No Death: No Injury Category: No Injury Staff Injury by Inmate: No Sexual Assault: No Name: [b](6); [b](7)(C) Person Type: Staff Medical Attention Required: No Death: No Injury Category: No Injury Staff Injury by Inmate: No Sexual Assault: No Name: [b](6); [b](7)(C) Person Type: Staff Medical Attention Required: No Death: No Injury Category: No Injury Staff Injury by Inmate: No Sexual Assault: No Name: [b](6); [b](7)(C) Person Type: Staff Medical Attention Required: No Death: No Injury Category: No Injury Staff Injury by Inmate: No Sexual Assault: No Name: [b](6); [b](7)(C) Person Type: Staff Medical Attention Required: No Death: No UNCLASSIFIED/LIMITED OFFICIAL USE ONLY/LAW ENFORCEMENT SENSITIVE This document is marked Unclassified/Limited Official Use Only/Law Enforcement Sensitive and may be disseminated, with proper attribution, to active Law Enforcement, DOD, or U.S. Intelligence Agencies. This document, or any segment/attachment thereof, may not be released without the approval of the Bureau of Prisons to any media sources, any non-law enforcement entity, the general public or those without a \"need to know.\" It contains information that may be exempt from public release under the provisions of the Privacy Act (5 U.S.C. 552). 2 of 3 DOJ-OGR-00025135",
  "text_blocks": [
    {
      "type": "printed",
      "content": "Form 583 Report of Incident",
      "position": "header"
    },
    {
      "type": "printed",
      "content": "Incident #: NYM-19-0076 Submitted By: Date/Time Of Incident: 7/23/2019 1:27 AM",
      "position": "header"
    },
    {
      "type": "printed",
      "content": "Section 3: Others Involved",
      "position": "middle"
    },
    {
      "type": "printed",
      "content": "UNCLASSIFIED/LIMITED OFFICIAL USE ONLY/LAW ENFORCEMENT SENSITIVE",
      "position": "footer"
    },
    {
      "type": "printed",
      "content": "2 of 3",
      "position": "footer"
    },
    {
      "type": "printed",
      "content": "DOJ-OGR-00025135",
      "position": "footer"
    }
  ],
  "entities": {
    "people": [
      "[b](6); [b](7)(C)",
      "[b](6); [b](7)(C)",
      "[b](6); [b](7)(C)",
      "[b](6); [b](7)(C)",
      "[b](6); [b](7)(C)",
      "[b](6); [b](7)(C)"
    ],
    "organizations": [
      "Bureau of Prisons",
      "DOD",
      "U.S. Intelligence Agencies",
      "DOJ"
    ],
    "locations": [],
    "dates": [
      "7/23/2019"
    ],
    "reference_numbers": [
      "NYM-19-0076",
      "DOJ-OGR-00025135"
    ]
  },
  "additional_notes": "The document contains redacted names and is marked as 'Unclassified/Limited Official Use Only/Law Enforcement Sensitive'. It is page 2 of 3."
}