{
  "document_metadata": {
    "page_number": "1",
    "document_number": "PD11",
    "date": "07-23-2019",
    "document_type": "Inmate Discipline Update Charges",
    "has_handwriting": false,
    "has_stamps": false
  },
  "full_text": "PD11\n\nNYMA7             INMATE DISCIPLINE             07-23-2019\nPAGE 001 OF 001   UPDATE CHARGES                22:14:24\n\nREGISTER NUMBER...: 76318-054         NAME..........: EPSTEIN\nREPORT NUMBER.....: 3282555          FUNCTION.......: REP\nINCIDENT DATE/TIME: 07-23-2019 0127   INCIDENT FACL..: NYM\nREPORT DATE/TIME..: 07-23-2019 0330   INVESTIGATOR...: UNKNOWN\nSTATUS............: SUSPENDED         STATUS UPDT BY: [b)(6); (b)(7)(C)\nSTATUS DATE/TIME..: 07-23-2019 2213   STATUS FACL....: NYM\nREPORT REMARKS....( I/R SUSPENDED PEND MENTAL HEALTH EVAL. )\n\nCHARGE: 228 TATTOOING OR SELF-MUTILATION\nCHARGE:\nCHARGE:\nCHARGE:\nCHARGE:\nCHARGE:\nCHARGE:\nCHARGE:\nCHARGE:\n\nG0005   TRANSACTION SUCCESSFULLY COMPLETED - CONTINUE PROCESSING IF DESIRED\n\nhttps://bop.tcp.doj.gov:9049/SENTRY/J1PPD10.do 7/23/2019 DOJ-OGR-00025275",
  "text_blocks": [
    {
      "type": "printed",
      "content": "PD11",
      "position": "header"
    },
    {
      "type": "printed",
      "content": "INMATE DISCIPLINE UPDATE CHARGES",
      "position": "header"
    },
    {
      "type": "printed",
      "content": "REGISTER NUMBER...: 76318-054         NAME..........: EPSTEIN",
      "position": "middle"
    },
    {
      "type": "printed",
      "content": "CHARGE: 228 TATTOOING OR SELF-MUTILATION",
      "position": "middle"
    },
    {
      "type": "printed",
      "content": "G0005   TRANSACTION SUCCESSFULLY COMPLETED - CONTINUE PROCESSING IF DESIRED",
      "position": "middle"
    },
    {
      "type": "printed",
      "content": "https://bop.tcp.doj.gov:9049/SENTRY/J1PPD10.do 7/23/2019 DOJ-OGR-00025275",
      "position": "footer"
    }
  ],
  "entities": {
    "people": [
      "EPSTEIN"
    ],
    "organizations": [],
    "locations": [
      "NYM"
    ],
    "dates": [
      "07-23-2019",
      "07-23-2019",
      "07-23-2019"
    ],
    "reference_numbers": [
      "76318-054",
      "3282555",
      "G0005",
      "DOJ-OGR-00025275"
    ]
  },
  "additional_notes": "The document appears to be a prison disciplinary report regarding an inmate named Epstein. The report is related to an incident of tattooing or self-mutilation."
}