{
  "document_metadata": {
    "page_number": "397",
    "document_number": "DOJ-OGR-00024894",
    "date": "7/24/2019",
    "document_type": "Email correspondence",
    "has_handwriting": false,
    "has_stamps": false
  },
  "full_text": "Page 397 >>> Shirley V. Skipper-Scott 7/24/2019 9:39 AM >>> Hello, Inmate Epstein #76318-054 was removed from Suicide Watch and stepped down to Psychological Observation. He was just escorted to Health Services for a follow-up assessment/evaluation. Once completed, he will be escorted to Attorney Conference to meet with his Attorney. I will provide you with information concerning the medical assessment, once I receive it. Thanks. Shirley Skipper-Scott Associate Warden MCC New York 150 Park Row New York, New York 10007 Office: 646-836- Black Berry: 646-423- @bop.gov >>> Ray Ormond 7/24/2019 8:45 AM >>> Shirley - Please provide me with a daily update on this inmate, including his status and any changes/activities I should be aware of. Thanks! J. Ray Ormond Regional Director Northeast Region 215-521- Page 1093 DOJ-OGR-00024894",
  "text_blocks": [
    {
      "type": "printed",
      "content": ">>> Shirley V. Skipper-Scott 7/24/2019 9:39 AM >>> Hello, Inmate Epstein #76318-054 was removed from Suicide Watch and stepped down to Psychological Observation. He was just escorted to Health Services for a follow-up assessment/evaluation. Once completed, he will be escorted to Attorney Conference to meet with his Attorney. I will provide you with information concerning the medical assessment, once I receive it. Thanks.",
      "position": "top"
    },
    {
      "type": "printed",
      "content": "Shirley Skipper-Scott Associate Warden MCC New York 150 Park Row New York, New York 10007 Office: 646-836- Black Berry: 646-423- @bop.gov",
      "position": "middle"
    },
    {
      "type": "printed",
      "content": ">>> Ray Ormond 7/24/2019 8:45 AM >>> Shirley - Please provide me with a daily update on this inmate, including his status and any changes/activities I should be aware of. Thanks!",
      "position": "middle"
    },
    {
      "type": "printed",
      "content": "J. Ray Ormond Regional Director Northeast Region 215-521-",
      "position": "middle"
    },
    {
      "type": "printed",
      "content": "Page 1093 DOJ-OGR-00024894",
      "position": "footer"
    }
  ],
  "entities": {
    "people": [
      "Shirley V. Skipper-Scott",
      "Ray Ormond",
      "Epstein"
    ],
    "organizations": [
      "MCC New York",
      "BOP"
    ],
    "locations": [
      "New York"
    ],
    "dates": [
      "7/24/2019"
    ],
    "reference_numbers": [
      "76318-054",
      "DOJ-OGR-00024894"
    ]
  },
  "additional_notes": "The document contains redactions in phone numbers and email addresses."
}