{
  "document_metadata": {
    "page_number": "500",
    "document_number": "DOJ-OGR-00024959",
    "date": "Aug 10, 2019",
    "document_type": "email",
    "has_handwriting": false,
    "has_stamps": false
  },
  "full_text": "Page 500\nSubject: Re: Automatic reply: Epstein update\nFYI:\nThe BOP just informed us that Epstein is being taken by ambulance to the hospital from another apparent suicide attempt- no other information was provided.\nThey will update us as more info becomes available.\nOn Aug 10, 2019, at 7:26 AM, [b(6); b(7)(C)] (USANYS) [b(6); b(7)(C)]@usa.doj.gov wrote:\nI will be out of the office on vacation until Monday, August 12th. Although I will have access to email during my absence, my responses may be delayed. For urgent matters, please contact the other AUSA(s) on the case, or AUSA [b(6); b(7)(C)] at 212-637-[b(6); b(7)(C)] or [b(6); b(7)(C)]@usdoj.gov\nPage 1363\nDOJ-OGR-00024959",
  "text_blocks": [
    {
      "type": "printed",
      "content": "Page 500",
      "position": "header"
    },
    {
      "type": "printed",
      "content": "Subject: Re: Automatic reply: Epstein update",
      "position": "top"
    },
    {
      "type": "printed",
      "content": "FYI:\nThe BOP just informed us that Epstein is being taken by ambulance to the hospital from another apparent suicide attempt- no other information was provided.\nThey will update us as more info becomes available.",
      "position": "top"
    },
    {
      "type": "printed",
      "content": "On Aug 10, 2019, at 7:26 AM, [b(6); b(7)(C)] (USANYS) [b(6); b(7)(C)]@usa.doj.gov wrote:",
      "position": "top"
    },
    {
      "type": "printed",
      "content": "I will be out of the office on vacation until Monday, August 12th. Although I will have access to email during my absence, my responses may be delayed. For urgent matters, please contact the other AUSA(s) on the case, or AUSA [b(6); b(7)(C)] at 212-637-[b(6); b(7)(C)] or [b(6); b(7)(C)]@usdoj.gov",
      "position": "middle"
    },
    {
      "type": "printed",
      "content": "Page 1363",
      "position": "footer"
    },
    {
      "type": "printed",
      "content": "DOJ-OGR-00024959",
      "position": "footer"
    }
  ],
  "entities": {
    "people": [
      "Epstein"
    ],
    "organizations": [
      "BOP",
      "USANYS",
      "DOJ"
    ],
    "locations": [],
    "dates": [
      "Aug 10, 2019",
      "August 12th"
    ],
    "reference_numbers": [
      "212-637-[b(6); b(7)(C)]",
      "DOJ-OGR-00024959"
    ]
  },
  "additional_notes": "The document appears to be a redacted email chain discussing Jeffrey Epstein's medical situation. Multiple redactions are present, obscuring names, email addresses, and phone numbers."
}