{
  "document_metadata": {
    "page_number": "563",
    "document_number": "DOJ-OGR-00024579",
    "date": "08/19/2019",
    "document_type": "Log Entries By Event Date",
    "has_handwriting": false,
    "has_stamps": false
  },
  "full_text": "Date: 08/19/2019 Time: 10:15 AM Federal Bureau of Prisons TRUINTEL Log Entries By Event Date Sensitive But Unclassified Entered Date Alpha Code Level 1 Location Level 2 Location Level 3 Location Event Date Shift User Event Base Count 7/23/2019 6:52 PM NYM Housing Units Housing Units, General Population GN 7/23/2019 6:00 PM Evening (b)(6) (b)(7)(C) Watch Call 7/23/2019 6:52 PM NYM Housing Units Housing Units, General Population GN 7/23/2019 6:12 PM Evening Daily Activity 7/23/2019 6:20 PM NYM Housing Units Housing Units, General Population ES 7/23/2019 6:20 PM Evening Watch Call 7/23/2019 6:21 PM NYM Housing Units Housing Units, General Population ES 7/23/2019 6:20 PM Evening Rounds (Officer) 7/23/2019 6:53 PM NYM Housing Units Housing Units, General Population GN 7/23/2019 6:52 PM Evening Change to Base Count In 0/1/3 7/23/2019 7:08 PM NYM Housing Units Housing Units, General Population GN 7/23/2019 7:08 PM Evening (b)(6)-7441 Rounds (Officer) 7/23/2019 7:08 PM NYM Housing Units Housing Units, General Population GN 7/23/2019 7:08 PM Evening Watch Call 7/23/2019 10:06 PM NYM Housing Units Housing Units, General Population ES 7/23/2019 10:06 PM Evening Sensitive Information 7/23/2019 10:07 PM NYM Housing Units Housing Units, General Population ES 7/23/2019 10:06 PM Evening Search (Cells) 7/23/2019 10:07 PM NYM Housing Units Housing Units, General Population ES 7/23/2019 10:07 PM Evening (b)(6) (b)(7)(C) Search (Cells) User Id: (b)(6)(b)(7)(C) Page 563 of 1155 DOJ-OGR-00024579",
  "text_blocks": [
    {
      "type": "printed",
      "content": "Date: 08/19/2019 Time: 10:15 AM Federal Bureau of Prisons TRUINTEL Log Entries By Event Date Sensitive But Unclassified",
      "position": "header"
    },
    {
      "type": "printed",
      "content": "Entered Date Alpha Code Level 1 Location Level 2 Location Level 3 Location Event Date Shift User Event Base Count",
      "position": "header"
    },
    {
      "type": "printed",
      "content": "7/23/2019 6:52 PM NYM Housing Units Housing Units, General Population GN 7/23/2019 6:00 PM Evening (b)(6) (b)(7)(C) Watch Call",
      "position": "body"
    },
    {
      "type": "printed",
      "content": "7/23/2019 6:52 PM NYM Housing Units Housing Units, General Population GN 7/23/2019 6:12 PM Evening Daily Activity",
      "position": "body"
    },
    {
      "type": "printed",
      "content": "7/23/2019 6:20 PM NYM Housing Units Housing Units, General Population ES 7/23/2019 6:20 PM Evening Watch Call",
      "position": "body"
    },
    {
      "type": "printed",
      "content": "7/23/2019 6:21 PM NYM Housing Units Housing Units, General Population ES 7/23/2019 6:20 PM Evening Rounds (Officer)",
      "position": "body"
    },
    {
      "type": "printed",
      "content": "7/23/2019 6:53 PM NYM Housing Units Housing Units, General Population GN 7/23/2019 6:52 PM Evening Change to Base Count In 0/1/3",
      "position": "body"
    },
    {
      "type": "printed",
      "content": "7/23/2019 7:08 PM NYM Housing Units Housing Units, General Population GN 7/23/2019 7:08 PM Evening (b)(6)-7441 Rounds (Officer)",
      "position": "body"
    },
    {
      "type": "printed",
      "content": "7/23/2019 7:08 PM NYM Housing Units Housing Units, General Population GN 7/23/2019 7:08 PM Evening Watch Call",
      "position": "body"
    },
    {
      "type": "printed",
      "content": "7/23/2019 10:06 PM NYM Housing Units Housing Units, General Population ES 7/23/2019 10:06 PM Evening Sensitive Information",
      "position": "body"
    },
    {
      "type": "printed",
      "content": "7/23/2019 10:07 PM NYM Housing Units Housing Units, General Population ES 7/23/2019 10:06 PM Evening Search (Cells)",
      "position": "body"
    },
    {
      "type": "printed",
      "content": "7/23/2019 10:07 PM NYM Housing Units Housing Units, General Population ES 7/23/2019 10:07 PM Evening (b)(6) (b)(7)(C) Search (Cells)",
      "position": "body"
    },
    {
      "type": "handwritten",
      "content": "(b)(6)-7441",
      "position": "body"
    },
    {
      "type": "printed",
      "content": "User Id: (b)(6)(b)(7)(C) Page 563 of 1155 DOJ-OGR-00024579",
      "position": "footer"
    }
  ],
  "entities": {
    "people": [],
    "organizations": [
      "Federal Bureau of Prisons"
    ],
    "locations": [],
    "dates": [
      "08/19/2019",
      "7/23/2019"
    ],
    "reference_numbers": [
      "DOJ-OGR-00024579"
    ]
  },
  "additional_notes": "The document appears to be a log entry report from the Federal Bureau of Prisons, containing various events and activities that occurred on July 23, 2019. The report includes information such as the date, time, location, and user ID associated with each event. Some of the user IDs have been redacted with '(b)(6)' and '(b)(7)(C)'. The document is labeled as 'Sensitive But Unclassified'."
}