{
  "document_metadata": {
    "page_number": "3261",
    "document_number": "76318-054",
    "date": "July 30, 2019",
    "document_type": "Email",
    "has_handwriting": false,
    "has_stamps": false
  },
  "full_text": "Fwd: for Mr. Jeffrey Edward Epstein, Register Number: 76318-054\nFrom NYM/Exec Assistant~ (b)(6), (b)(7)(C) Charisma Edge (b)(6), (b)(7)(C)\nTo Lamine N'Diaye, Lee Plourde, NYM/Executive Staff, Shirley V. Skipper-Scott, (b)(6), (b)(7)(C)\nDate 2019/07/31 06:33\nSubject: Fwd: for Mr. Jeffrey Edward Epstein, Register Number: 76318-054\nAttachments: TEXT.htm, IMAGE.png, IMAGE.png, Epstein_Letter_VI.pdf, Mime.822\n>>> (b)(6), (b)(7)(C) @morgan.edu> 7/30/2019 4:01 PM >>>\nJuly 30, 2019\nMr. Jeffrey Edward Epstein\nRegister Number: 76318-054\nAge 66, White Male\nMCC New York\nMetropolitan Correctional Center\nEmail: NYM/ExecAssistant@bop.gov\nPhone: 646-836-6300\nFax: 646-836-7751\n150 Park Row\nNew York City, NY 10007\nDear Mr. Epstein,\nYou called me circa August 2017 and you and I had a Skype call with my Ph.D. student, (b)(6), (b)(7)(C) , in December 2017.\nPage 3261\nDOJ-OGR-00023819",
  "text_blocks": [
    {
      "type": "printed",
      "content": "Fwd: for Mr. Jeffrey Edward Epstein, Register Number: 76318-054",
      "position": "header"
    },
    {
      "type": "printed",
      "content": "From NYM/Exec Assistant~ (b)(6), (b)(7)(C) Charisma Edge (b)(6), (b)(7)(C)",
      "position": "header"
    },
    {
      "type": "printed",
      "content": "To Lamine N'Diaye, Lee Plourde, NYM/Executive Staff, Shirley V. Skipper-Scott, (b)(6), (b)(7)(C)",
      "position": "header"
    },
    {
      "type": "printed",
      "content": "Date 2019/07/31 06:33",
      "position": "header"
    },
    {
      "type": "printed",
      "content": "Subject: Fwd: for Mr. Jeffrey Edward Epstein, Register Number: 76318-054",
      "position": "header"
    },
    {
      "type": "printed",
      "content": "Attachments: TEXT.htm, IMAGE.png, IMAGE.png, Epstein_Letter_VI.pdf, Mime.822",
      "position": "header"
    },
    {
      "type": "printed",
      "content": ">>> (b)(6), (b)(7)(C) @morgan.edu> 7/30/2019 4:01 PM >>>",
      "position": "body"
    },
    {
      "type": "printed",
      "content": "July 30, 2019",
      "position": "body"
    },
    {
      "type": "printed",
      "content": "Mr. Jeffrey Edward Epstein\nRegister Number: 76318-054\nAge 66, White Male\nMCC New York\nMetropolitan Correctional Center\nEmail: NYM/ExecAssistant@bop.gov\nPhone: 646-836-6300\nFax: 646-836-7751\n150 Park Row\nNew York City, NY 10007",
      "position": "body"
    },
    {
      "type": "printed",
      "content": "Dear Mr. Epstein,",
      "position": "body"
    },
    {
      "type": "printed",
      "content": "You called me circa August 2017 and you and I had a Skype call with my Ph.D. student, (b)(6), (b)(7)(C) , in December 2017.",
      "position": "body"
    },
    {
      "type": "printed",
      "content": "Page 3261",
      "position": "footer"
    },
    {
      "type": "printed",
      "content": "DOJ-OGR-00023819",
      "position": "footer"
    }
  ],
  "entities": {
    "people": [
      "Jeffrey Edward Epstein",
      "Lamine N'Diaye",
      "Lee Plourde",
      "Shirley V. Skipper-Scott",
      "Charisma Edge",
      "S. Allen Counter",
      "Benedict H. Gross",
      "Jonathan David Farley"
    ],
    "organizations": [
      "NYM",
      "MCC New York",
      "Metropolitan Correctional Center",
      "Harvard University",
      "Harvard College",
      "Massachusetts Institute of Technology",
      "Oxford University",
      "Morgan.edu",
      "BOP"
    ],
    "locations": [
      "New York City",
      "NY",
      "Harvard"
    ],
    "dates": [
      "July 30, 2019",
      "2019/07/31",
      "7/30/2019",
      "August 2017",
      "December 2017"
    ],
    "reference_numbers": [
      "76318-054",
      "DOJ-OGR-00023819"
    ]
  },
  "additional_notes": "The document appears to be a forwarded email with attachments. Some names and email addresses have been redacted."
}