{
  "document_metadata": {
    "page_number": "329 and 837",
    "document_number": "DOJ-OGR-00024855",
    "date": "7/24/2019",
    "document_type": "Email chain",
    "has_handwriting": false,
    "has_stamps": false
  },
  "full_text": "Page 329 MCC New York 150 Park Row New York, New York 10007 Office: 646-836 BlackBerry: 646-42 >>> Ray Ormond 7/24/2019 9:42 AM >>> Thanks. Where and with who will he be housed after his Attorney visit? Also, what does \"Psychology Observation\" status mean? J. Ray Ormond Regional Director Northeast Region 215-521 >>> Shirley V. Skipper-Scott 7/24/2019 9:39 AM >>> Hello, Inmate Epstein #76318-054 was removed from Suicide Watch and stepped down to Psychological Observation. He was just escorted to Health Services for a follow-up assessment/evaluation. Once completed, he will be escorted to Attorney Conference to meet with his Attorney. I will provide you with information concerning the medical assessment, once I receive it. Thanks. Shirley Skipper-Scott Associate Warden MCC New York 150 Park Row New York, New York 10007 Office: 646-836 Black Berry: 646-423 >>> Ray Ormond 7/24/2019 8:45 AM >>> Shirley - Please provide me with a daily update on this inmate, including his status and any changes/activities I should be aware of. Thanks! J. Ray Ormond Regional Director Northeast Region 215-521 Page 837 DOJ-OGR-00024855",
  "text_blocks": [
    {
      "type": "printed",
      "content": "MCC New York 150 Park Row New York, New York 10007 Office: 646-836 BlackBerry: 646-42",
      "position": "top"
    },
    {
      "type": "printed",
      "content": ">>> Ray Ormond 7/24/2019 9:42 AM >>> Thanks. Where and with who will he be housed after his Attorney visit? Also, what does \"Psychology Observation\" status mean?",
      "position": "middle"
    },
    {
      "type": "printed",
      "content": "J. Ray Ormond Regional Director Northeast Region 215-521",
      "position": "middle"
    },
    {
      "type": "printed",
      "content": ">>> Shirley V. Skipper-Scott 7/24/2019 9:39 AM >>> Hello, Inmate Epstein #76318-054 was removed from Suicide Watch and stepped down to Psychological Observation. He was just escorted to Health Services for a follow-up assessment/evaluation. Once completed, he will be escorted to Attorney Conference to meet with his Attorney. I will provide you with information concerning the medical assessment, once I receive it. Thanks.",
      "position": "middle"
    },
    {
      "type": "printed",
      "content": "Shirley Skipper-Scott Associate Warden MCC New York 150 Park Row New York, New York 10007 Office: 646-836 Black Berry: 646-423",
      "position": "middle"
    },
    {
      "type": "printed",
      "content": ">>> Ray Ormond 7/24/2019 8:45 AM >>> Shirley - Please provide me with a daily update on this inmate, including his status and any changes/activities I should be aware of. Thanks!",
      "position": "middle"
    },
    {
      "type": "printed",
      "content": "J. Ray Ormond Regional Director Northeast Region 215-521",
      "position": "middle"
    },
    {
      "type": "printed",
      "content": "Page 837 DOJ-OGR-00024855",
      "position": "bottom"
    }
  ],
  "entities": {
    "people": [
      "Ray Ormond",
      "Shirley V. Skipper-Scott",
      "Epstein"
    ],
    "organizations": [
      "MCC New York"
    ],
    "locations": [
      "New York"
    ],
    "dates": [
      "7/24/2019"
    ],
    "reference_numbers": [
      "76318-054",
      "DOJ-OGR-00024855"
    ]
  },
  "additional_notes": "The document appears to be an email chain discussing the status of inmate Epstein (#76318-054). Some phone numbers and email addresses have been redacted."
}