{
  "document_metadata": {
    "page_number": "3663",
    "document_number": "DOJ-OGR-00023855",
    "date": "2019/08/06",
    "document_type": "email",
    "has_handwriting": false,
    "has_stamps": false
  },
  "full_text": "Re: Fwd: Client Jeffrey Epstein (Out of the Office)\nFrom [redacted]\nTo [redacted]\nDate 2019/08/06 15:25\nSubject: Re: Fwd: Client Jeffrey Epstein (Out of the Office)\n\nI will be out of the office August 5, 2019 to August 9, 2019. Counselor [redacted] will be acting in my capacity August 5, 2019. He can be reached at ext. [redacted]. Case Manager [redacted] will be acting in my capacity from August 6,2019 - August 9, 2019 and can be reached at ext. [redacted].\n\nPlease extend the usual courtesies.\n\nThank you,\n[redacted] 08/06/19 15:25\n\nGood afternoon all,\n\nBelow please find complaints from Epstein's attorneys. Can you check to see if he has toilet paper and that his CPAP is plugged in?\n[redacted]\n\nThank you,\n[redacted]\nSupervisory Staff Attorney\nCLC New York\nMetropolitan Correctional Center\n150 Park Row\nNew York, New York 10007\np: (646)836-[redacted]\nf: (646)836-7665\n\n[b)(6). (b)(7)(C) 8/6/2019 3:20 PM\n\nGood afternoon Mr. [redacted],\n\nOur client, Jeffrey Epstein, has informed us that he has no toilet paper in his cell. His CPap machine was not plugged in last night, so he was unable to use it.\n\nAlso, since his arrival at MCC, he has only been able to make two fifteen minute phone calls. Both times, the calls were on speaker phone, with officers present.\n\nPage 3663\nDOJ-OGR-00023855",
  "text_blocks": [
    {
      "type": "printed",
      "content": "Re: Fwd: Client Jeffrey Epstein (Out of the Office)\nFrom [redacted]\nTo [redacted]\nDate 2019/08/06 15:25\nSubject: Re: Fwd: Client Jeffrey Epstein (Out of the Office)",
      "position": "header"
    },
    {
      "type": "printed",
      "content": "I will be out of the office August 5, 2019 to August 9, 2019. Counselor [redacted] will be acting in my capacity August 5, 2019. He can be reached at ext. [redacted]. Case Manager [redacted] will be acting in my capacity from August 6,2019 - August 9, 2019 and can be reached at ext. [redacted].\n\nPlease extend the usual courtesies.\n\nThank you,",
      "position": "top"
    },
    {
      "type": "printed",
      "content": "Good afternoon all,\n\nBelow please find complaints from Epstein's attorneys. Can you check to see if he has toilet paper and that his CPAP is plugged in?",
      "position": "middle"
    },
    {
      "type": "printed",
      "content": "Thank you,\n[redacted]\nSupervisory Staff Attorney\nCLC New York\nMetropolitan Correctional Center\n150 Park Row\nNew York, New York 10007\np: (646)836-[redacted]\nf: (646)836-7665",
      "position": "middle"
    },
    {
      "type": "printed",
      "content": "Good afternoon Mr. [redacted],\n\nOur client, Jeffrey Epstein, has informed us that he has no toilet paper in his cell. His CPap machine was not plugged in last night, so he was unable to use it.\n\nAlso, since his arrival at MCC, he has only been able to make two fifteen minute phone calls. Both times, the calls were on speaker phone, with officers present.",
      "position": "bottom"
    },
    {
      "type": "printed",
      "content": "Page 3663\nDOJ-OGR-00023855",
      "position": "footer"
    }
  ],
  "entities": {
    "people": [
      "Jeffrey Epstein"
    ],
    "organizations": [
      "Metropolitan Correctional Center",
      "CLC New York"
    ],
    "locations": [
      "New York"
    ],
    "dates": [
      "August 5, 2019",
      "August 9, 2019",
      "2019/08/06"
    ],
    "reference_numbers": [
      "DOJ-OGR-00023855"
    ]
  },
  "additional_notes": "The document contains multiple redactions, likely for privacy or security reasons. The content appears to be related to Jeffrey Epstein's detention and complaints made by his attorneys."
}