{
  "document_metadata": {
    "page_number": "3370",
    "document_number": "DOJ-OGR-00023828",
    "date": "2019/07/22",
    "document_type": "email",
    "has_handwriting": false,
    "has_stamps": false
  },
  "full_text": "Re: Fwd: Client Jeffrey Epstein ((Out of Office))\nFrom\nTo\nDate 2019/07/22 14:45\nSubject: Re: Fwd: Client Jeffrey Epstein ((Out of Office))\nI will be out of the office for the remainder of today (Monday, July 22). If you need immediate assistance, please contact Supervisory Attorney or call the institution at 646-836-6300 and ask for the Operations Lieutenant or the Institution Duty Officer. Thank you.\n07/22/19 14:45 >>>\nI addressed the phone calls with Lt. You may want to check in with him regarding that issue.\nChief Psychologist\nU.S. Department of Justice/Federal Bureau of Prisons\nMetropolitan Correctional Center\n150 Park Row\nNew York, New York 10007\nOffice: (646) 836-\nFax: (646) 836-7712\nE-mail: @bop.gov\n>>> 7/22/2019 2:44 PM >>>\nGood afternoon all,\nBelow please find concerns raised by Epstein's attorneys with legal visiting. To summarize, they are requesting:\n1) greater access for Epstein using the bathroom during legal visits;\n2) the 2 social calls he was allegedly promised; and\n3) the ability to eat his lunch meal in attorney conference.\nPlease review and advise so that I can respond. Thank you.\nSupervisory Staff Attorney\nCLC New York\nMetropolitan Correctional Center\n150 Park Row\nNew York, New York 10007\np: (646)836-\nf: (646)836-7665\nPage 3370\nDOJ-OGR-00023828",
  "text_blocks": [
    {
      "type": "printed",
      "content": "Re: Fwd: Client Jeffrey Epstein ((Out of Office))\nFrom\nTo\nDate 2019/07/22 14:45\nSubject: Re: Fwd: Client Jeffrey Epstein ((Out of Office))",
      "position": "header"
    },
    {
      "type": "printed",
      "content": "I will be out of the office for the remainder of today (Monday, July 22). If you need immediate assistance, please contact Supervisory Attorney or call the institution at 646-836-6300 and ask for the Operations Lieutenant or the Institution Duty Officer. Thank you.",
      "position": "middle"
    },
    {
      "type": "printed",
      "content": "07/22/19 14:45 >>>\nI addressed the phone calls with Lt. You may want to check in with him regarding that issue.",
      "position": "middle"
    },
    {
      "type": "printed",
      "content": "Chief Psychologist\nU.S. Department of Justice/Federal Bureau of Prisons\nMetropolitan Correctional Center\n150 Park Row\nNew York, New York 10007\nOffice: (646) 836-\nFax: (646) 836-7712\nE-mail: @bop.gov",
      "position": "middle"
    },
    {
      "type": "printed",
      "content": ">>> 7/22/2019 2:44 PM >>>\nGood afternoon all,\nBelow please find concerns raised by Epstein's attorneys with legal visiting. To summarize, they are requesting:\n1) greater access for Epstein using the bathroom during legal visits;\n2) the 2 social calls he was allegedly promised; and\n3) the ability to eat his lunch meal in attorney conference.\nPlease review and advise so that I can respond. Thank you.",
      "position": "middle"
    },
    {
      "type": "printed",
      "content": "Supervisory Staff Attorney\nCLC New York\nMetropolitan Correctional Center\n150 Park Row\nNew York, New York 10007\np: (646)836-\nf: (646)836-7665",
      "position": "middle"
    },
    {
      "type": "printed",
      "content": "Page 3370\nDOJ-OGR-00023828",
      "position": "footer"
    }
  ],
  "entities": {
    "people": [
      "Jeffrey Epstein"
    ],
    "organizations": [
      "U.S. Department of Justice",
      "Federal Bureau of Prisons",
      "Metropolitan Correctional Center",
      "CLC New York"
    ],
    "locations": [
      "New York"
    ],
    "dates": [
      "2019/07/22",
      "7/22/2019"
    ],
    "reference_numbers": [
      "DOJ-OGR-00023828",
      "646-836-6300",
      "646-836-7712",
      "646-836-7665"
    ]
  },
  "additional_notes": "The document contains multiple redactions, likely for privacy or security reasons."
}