{
  "document_metadata": {
    "page_number": "4426",
    "document_number": "DOJ-OGR-00024369",
    "date": "8/10/19",
    "document_type": "email",
    "has_handwriting": false,
    "has_stamps": false
  },
  "full_text": "https://abc13.com/sources-jeffrey-epstein-dies-by-suicide-in-manhattan-jail/5457853/ Sent from my Verizon, Samsung Galaxy smartphone -------- Original message -------- From: (b)(6), (b)(7)(C) (b)(6), (b)(7)(C) @bop.gov Date: 8/10/19 8:58 AM (GMT-05:00) To: Lamine N'Diaye (b)(6) (b)(6) @bop.gov Cc: Lee Plourde (b)(6) (b)(6) @bop.gov, \"Shirley V. Skipper-Scott\" (b)(6), (b)(7)(C) (b)(6), (b)(7)(C) @bop.gov Subject: Fwd: Here is the draft press release that I'll email to Mike & Lee momentarily from my Samsung assuming it refreshes quickly >>> (b)(6), (b)(7)(C) 08/10/2019 08:58 >>> Lamine, I am working with IPPA to finalize the press release (1st draft attached). Can you please give me answers to the below. (b)(3) Thanks, (b)(6) (b)(7)(C) Page 4426 DOJ-OGR-00024369",
  "text_blocks": [
    {
      "type": "printed",
      "content": "https://abc13.com/sources-jeffrey-epstein-dies-by-suicide-in-manhattan-jail/5457853/",
      "position": "top"
    },
    {
      "type": "printed",
      "content": "Sent from my Verizon, Samsung Galaxy smartphone",
      "position": "top"
    },
    {
      "type": "printed",
      "content": "-------- Original message --------",
      "position": "top"
    },
    {
      "type": "printed",
      "content": "From: (b)(6), (b)(7)(C) (b)(6), (b)(7)(C) @bop.gov",
      "position": "top"
    },
    {
      "type": "printed",
      "content": "Date: 8/10/19 8:58 AM (GMT-05:00)",
      "position": "top"
    },
    {
      "type": "printed",
      "content": "To: Lamine N'Diaye (b)(6) (b)(6) @bop.gov",
      "position": "top"
    },
    {
      "type": "printed",
      "content": "Cc: Lee Plourde (b)(6) (b)(6) @bop.gov, \"Shirley V. Skipper-Scott\" (b)(6), (b)(7)(C) (b)(6), (b)(7)(C) @bop.gov",
      "position": "top"
    },
    {
      "type": "printed",
      "content": "Subject: Fwd: Here is the draft press release that I'll email to Mike & Lee momentarily from my Samsung assuming it refreshes quickly",
      "position": "top"
    },
    {
      "type": "printed",
      "content": ">>> (b)(6), (b)(7)(C) 08/10/2019 08:58 >>>",
      "position": "middle"
    },
    {
      "type": "printed",
      "content": "Lamine,",
      "position": "middle"
    },
    {
      "type": "printed",
      "content": "I am working with IPPA to finalize the press release (1st draft attached). Can you please give me answers to the below.",
      "position": "middle"
    },
    {
      "type": "printed",
      "content": "(b)(3)",
      "position": "middle"
    },
    {
      "type": "printed",
      "content": "Thanks,",
      "position": "middle"
    },
    {
      "type": "printed",
      "content": "(b)(6) (b)(7)(C)",
      "position": "middle"
    },
    {
      "type": "printed",
      "content": "Page 4426",
      "position": "footer"
    },
    {
      "type": "printed",
      "content": "DOJ-OGR-00024369",
      "position": "footer"
    }
  ],
  "entities": {
    "people": [
      "Lamine N'Diaye",
      "Lee Plourde",
      "Shirley V. Skipper-Scott",
      "Mike"
    ],
    "organizations": [
      "BOP"
    ],
    "locations": [
      "Manhattan"
    ],
    "dates": [
      "8/10/19",
      "8/10/2019"
    ],
    "reference_numbers": [
      "DOJ-OGR-00024369"
    ]
  },
  "additional_notes": "The document appears to be a redacted email chain discussing a press release related to Jeffrey Epstein's death. The email contains several redactions, likely due to FOIA exemptions."
}