{
  "document_metadata": {
    "page_number": "3071",
    "document_number": "DOJ-OGR-00024339",
    "date": null,
    "document_type": "email chain",
    "has_handwriting": false,
    "has_stamps": false
  },
  "full_text": "Ok. Let's check in at noon. You can call my cell or send a call in number for the three of use. Either way works (b)(6) (b)(7)(C) 508.951 (b)(6) (b)(7)(C) On Aug 11, 2019, at 9:31 AM, Hugh Hurwitz (b)(6) (b)(7)(C) @bop.gov> wrote: Sure. Noon is fine, nothing pressing but we can talk anytime you want. Hugh Sent from my Verizon, Samsung Galaxy smartphone -------- Original message -------- From: (b)(6) (b)(7)(C) (OAG)\" (b)(6) (b)(7)(C) @usdoj.gov> Date: 8/11/19 9:29 AM (GMT-05:00) To: Hugh Hurwitz (b)(6) (b)(7)(C) @bop.gov> Cc: Ray Ormond (b)(6) (b)(7)(C) @bop.gov> Subject: Re: Reuters: Prison Guards Skipped Mandatory Checks Before Epstein Death >>> (b)(6) (b)(7)(C) (OAG)\" 08/11/2019 09:29 >>> Gentlemen. Do you have time for a quick update call before I leave for my trip with the AG? Does 12 noon work?  If there is something new and pressing, we can do a call earlier. (b)(6) (b)(7)(C) On Aug 10, 2019, at 10:20 PM, Hugh Hurwitz (b)(6) (b)(7)(C) @bop.gov> wrote: How do they have this info? Unbelieveable. https://www.breitbart.com/politics/2019/08/10/report-prison-guards-skipped-mandatory-checks-before-jeffrey-epsteins-death/ Hugh Sent from my Verizon, Samsung Galaxy smartphone Page 3071 DOJ-OGR-00024339",
  "text_blocks": [
    {
      "type": "printed",
      "content": "Ok. Let's check in at noon. You can call my cell or send a call in number for the three of use. Either way works",
      "position": "top"
    },
    {
      "type": "handwritten",
      "content": "(b)(6) (b)(7)(C)",
      "position": "inline"
    },
    {
      "type": "printed",
      "content": "On Aug 11, 2019, at 9:31 AM, Hugh Hurwitz (b)(6) (b)(7)(C) @bop.gov> wrote: Sure. Noon is fine, nothing pressing but we can talk anytime you want.",
      "position": "middle"
    },
    {
      "type": "printed",
      "content": "Hugh Sent from my Verizon, Samsung Galaxy smartphone",
      "position": "middle"
    },
    {
      "type": "printed",
      "content": "-------- Original message -------- From: (b)(6) (b)(7)(C) (OAG)\" (b)(6) (b)(7)(C) @usdoj.gov> Date: 8/11/19 9:29 AM (GMT-05:00) To: Hugh Hurwitz (b)(6) (b)(7)(C) @bop.gov> Cc: Ray Ormond (b)(6) (b)(7)(C) @bop.gov> Subject: Re: Reuters: Prison Guards Skipped Mandatory Checks Before Epstein Death",
      "position": "middle"
    },
    {
      "type": "printed",
      "content": ">>> (b)(6) (b)(7)(C) (OAG)\" 08/11/2019 09:29 >>> Gentlemen. Do you have time for a quick update call before I leave for my trip with the AG? Does 12 noon work?  If there is something new and pressing, we can do a call earlier.",
      "position": "middle"
    },
    {
      "type": "handwritten",
      "content": "(b)(6) (b)(7)(C)",
      "position": "inline"
    },
    {
      "type": "printed",
      "content": "On Aug 10, 2019, at 10:20 PM, Hugh Hurwitz (b)(6) (b)(7)(C) @bop.gov> wrote: How do they have this info? Unbelieveable. https://www.breitbart.com/politics/2019/08/10/report-prison-guards-skipped-mandatory-checks-before-jeffrey-epsteins-death/",
      "position": "bottom"
    },
    {
      "type": "printed",
      "content": "Hugh Sent from my Verizon, Samsung Galaxy smartphone",
      "position": "bottom"
    },
    {
      "type": "printed",
      "content": "Page 3071 DOJ-OGR-00024339",
      "position": "footer"
    }
  ],
  "entities": {
    "people": [
      "Hugh Hurwitz",
      "Ray Ormond"
    ],
    "organizations": [
      "OAG",
      "BOP",
      "DOJ",
      "Verizon",
      "Reuters",
      "Breitbart"
    ],
    "locations": [],
    "dates": [
      "Aug 11, 2019",
      "8/11/19",
      "Aug 10, 2019"
    ],
    "reference_numbers": [
      "508.951",
      "DOJ-OGR-00024339"
    ]
  },
  "additional_notes": "The document appears to be a redacted email chain discussing a call and referencing an article about Jeffrey Epstein's death. The redactions are likely due to privacy or sensitivity concerns."
}