{
  "document_metadata": {
    "page_number": "1236",
    "document_number": "DOJ-OGR-00025441",
    "date": "3/25/2019",
    "document_type": "Email",
    "has_handwriting": false,
    "has_stamps": false
  },
  "full_text": "Page 1236\n\n[b)(6); (b)(7)(C)\n\nThese are my suggested edits/comments on the version you sent to us on Friday. I have not yet reviewed your updated version from today, but wanted to send this to you now so you could review. Thanks.\n\nJames\n\nJames C. Wills\nSenior Deputy General Counsel\nFederal Bureau of Prisons\n320 First Street, N.W.\nWashington, D.C. 20534\n202-353-[b)(6); (b)(7)(C)]\n202-598-[b)(6); (b)(7)(C)]\n\nATTORNEY/CLIENT PRIVILEGED COMMUNICATION\n\nATTORNEY WORK PRODUCT\n\nSENSITIVE/PRIVILEGED COMMUNICATION\nThe information contained in this electronic message and any and all accompanying documents constitutes sensitive information. This information is the property of the U.S. Department of Justice.\nIf you are not the intended recipient of this information, any disclosure, copying, distribution, or the taking of any action in reliance on this information is strictly prohibited. If you received this message in error, please notify us immediately at the above number to make arrangements for its return to us.\n\n>> [b)(6); (b)(7)(C)] 3/25/2019 5:24 PM >>\nMr. Hurwitz, Mr. Carvajal, Mr. Wills, Mr. Keller and [b)(6); (b)(7)(C)]\n\nI have done some additional edits to the Epstein Reconstruction. Please review and return with your comments. This remain a working document and should not be distributed beyond yourselves.\n\nThanks for your consideration,\n\n[b)(6); (b)(7)(C)]\nPsy.D.\nNational Suicide Prevention Coordinator\nFederal Bureau of Prisons\nPsychology Services Branch\n320 First Street, NW\nWashington, DC, DC 20534\n202-598[b)(6); (b)(7)(C)]\n\nPage 3564\nDOJ-OGR-00025441",
  "text_blocks": [
    {
      "type": "printed",
      "content": "These are my suggested edits/comments on the version you sent to us on Friday. I have not yet reviewed your updated version from today, but wanted to send this to you now so you could review. Thanks.",
      "position": "top"
    },
    {
      "type": "printed",
      "content": "James C. Wills\nSenior Deputy General Counsel\nFederal Bureau of Prisons\n320 First Street, N.W.\nWashington, D.C. 20534\n202-353-[b)(6); (b)(7)(C)]\n202-598-[b)(6); (b)(7)(C)]",
      "position": "top"
    },
    {
      "type": "printed",
      "content": "ATTORNEY/CLIENT PRIVILEGED COMMUNICATION\n\nATTORNEY WORK PRODUCT\n\nSENSITIVE/PRIVILEGED COMMUNICATION",
      "position": "middle"
    },
    {
      "type": "printed",
      "content": "The information contained in this electronic message and any and all accompanying documents constitutes sensitive information. This information is the property of the U.S. Department of Justice.\nIf you are not the intended recipient of this information, any disclosure, copying, distribution, or the taking of any action in reliance on this information is strictly prohibited. If you received this message in error, please notify us immediately at the above number to make arrangements for its return to us.",
      "position": "middle"
    },
    {
      "type": "printed",
      "content": "I have done some additional edits to the Epstein Reconstruction. Please review and return with your comments. This remain a working document and should not be distributed beyond yourselves.",
      "position": "middle"
    },
    {
      "type": "printed",
      "content": "Thanks for your consideration,",
      "position": "middle"
    },
    {
      "type": "printed",
      "content": "Psy.D.\nNational Suicide Prevention Coordinator\nFederal Bureau of Prisons\nPsychology Services Branch\n320 First Street, NW\nWashington, DC, DC 20534\n202-598[b)(6); (b)(7)(C)]",
      "position": "bottom"
    }
  ],
  "entities": {
    "people": [
      "James C. Wills",
      "Mr. Hurwitz",
      "Mr. Carvajal",
      "Mr. Wills",
      "Mr. Keller",
      "James"
    ],
    "organizations": [
      "Federal Bureau of Prisons",
      "U.S. Department of Justice",
      "Psychology Services Branch"
    ],
    "locations": [
      "Washington, D.C.",
      "320 First Street, N.W.",
      "320 First Street, NW"
    ],
    "dates": [
      "3/25/2019"
    ],
    "reference_numbers": [
      "202-353",
      "202-598",
      "DOJ-OGR-00025441"
    ]
  },
  "additional_notes": "The document contains redactions marked as [b)(6); (b)(7)(C)]. The email is marked as 'ATTORNEY/CLIENT PRIVILEGED COMMUNICATION' and 'ATTORNEY WORK PRODUCT' and 'SENSITIVE/PRIVILEGED COMMUNICATION'."
}