{
  "document_metadata": {
    "page_number": "542",
    "document_number": "DOJ-OGR-00024558",
    "date": "08/19/2019",
    "document_type": "Log Entries By Event Date",
    "has_handwriting": false,
    "has_stamps": false
  },
  "full_text": "Date: 08/19/2019 Time: 10:15 AM Federal Bureau of Prisons TRUINTEL Log Entries By Event Date Sensitive But Unclassified Entered Date Alpha Code Level 1 Location Level 2 Location Level 3 Location Event Date Shift User Event Base Count Population 7/22/2019 4:33 PM NYM Housing Units Housing Units, General Population EN 7/22/2019 4:33 PM Evening (b)(6),(b)(7)(C) Bed Book Check - Summary Text: Completed. 7/22/2019 4:33 PM NYM Housing Units Housing Units, General Population EN 7/22/2019 4:33 PM Evening (b)(6),(b)(7)(C) Base Count Verified - Summary Text: Completed. 7/22/2019 4:34 PM NYM Housing Units Housing Units, General Population EN 7/22/2019 4:34 PM Evening Official Count - Summary Text: Base Count (b)(6) 7/22/2019 4:34 PM NYM Housing Units Housing Units, General Population EN 7/22/2019 4:34 PM Evening (b)(6),(b)(7)(C) Sensitive Information - Summary Text: Clear Count: (b)(6) 7/22/2019 5:03 PM NYM Housing Units Housing Units, General Population KN 7/22/2019 5:03 PM Evening Rounds (Lieutenant) - Summary Text: Nothing To Report 7/22/2019 5:09 PM NYM Housing Units Housing Units, General Population KS 7/22/2019 5:09 PM Evening Rounds (Lieutenant) - Summary Text: Completed - PREA 7/22/2019 5:17 PM NYM Housing Units Housing Units, General Population IN 7/22/2019 5:17 PM Evening Rounds (Lieutenant) - Summary Text: Completed - PREA 7/22/2019 5:22 PM NYM Housing Units Housing Units, General Population GN 7/22/2019 5:22 PM Evening Rounds (Lieutenant) - Summary Text: Completed - PREA 7/22/2019 5:27 PM NYM Housing Units Housing Units, General Population GS 7/22/2019 5:27 PM Evening Rounds (Lieutenant) - Summary Text: Completed - PREA 7/22/2019 5:32 PM NYM Housing Units Housing Units, General Population BA 7/22/2019 5:31 PM Evening Daily Activity - Summary Text: Completed - PREA User ID: (b)(6),(b)(7)(C) Page 542 of 1155 DOJ-OGR-00024558",
  "text_blocks": [
    {
      "type": "printed",
      "content": "Date: 08/19/2019 Time: 10:15 AM Federal Bureau of Prisons TRUINTEL Log Entries By Event Date Sensitive But Unclassified",
      "position": "header"
    },
    {
      "type": "printed",
      "content": "Entered Date Alpha Code Level 1 Location Level 2 Location Level 3 Location Event Date Shift User Event Base Count Population",
      "position": "header"
    },
    {
      "type": "printed",
      "content": "7/22/2019 4:33 PM NYM Housing Units Housing Units, General Population EN 7/22/2019 4:33 PM Evening (b)(6),(b)(7)(C) Bed Book Check - Summary Text: Completed.",
      "position": "body"
    },
    {
      "type": "printed",
      "content": "User ID: (b)(6),(b)(7)(C)",
      "position": "footer"
    },
    {
      "type": "printed",
      "content": "Page 542 of 1155 DOJ-OGR-00024558",
      "position": "footer"
    }
  ],
  "entities": {
    "people": [],
    "organizations": [
      "Federal Bureau of Prisons"
    ],
    "locations": [],
    "dates": [
      "08/19/2019",
      "7/22/2019"
    ],
    "reference_numbers": [
      "DOJ-OGR-00024558"
    ]
  },
  "additional_notes": "The document appears to be a log entry report from the Federal Bureau of Prisons. The report contains various events and activities that occurred on July 22, 2019. Some of the text is redacted, indicated by '(b)(6),(b)(7)(C)'."
}