{
  "document_metadata": {
    "page_number": "11531",
    "document_number": "DOJ-OGR-00023938",
    "date": "2019/11/14",
    "document_type": "email",
    "has_handwriting": false,
    "has_stamps": false
  },
  "full_text": "Fwd: Re: Media inquiry - Fox News - re: former AW Shirley Skipper Scott\nFrom Lee Plourde\nTo (b)(6), (b)(7)(C), James Petrucci, Marti Licon-Vitale\nDate 2019/11/14 18:04\nSubject: Fwd: Re: Media inquiry - Fox News - re: former AW Shirley Skipper Scott\nAttachments: TEXT.htm\nSent from my Verizon, Samsung Galaxy smartphone\n\nOriginal message ---------\nFrom: (b)(6), (b)(7)(C) @bop.gov>\nDate: 11/14/19 5:53 PM (GMT-05:00)\nTo: (b)(6), (b)(7)(C) @bop.gov>, Lee Plourde (b)(6) @bop.gov>\nSubject: Fwd: Re: Media inquiry - Fox News - re: former AW Shirley Skipper Scott\n(b)(6), (b)(7)(C) 11/14/2019 17:53>>\nThis is the final version approved by IPPA that I'm sending now to the reporter\nReporter: (b)(6) - Fox News\nQuestion:\nHi there can you confirm whether case manager (b)(6), (b)(7)(C) is still working with SHU inmates at MCC or has he been transferred to a different case (b)(6)\n(b)(6), (b)(7)(C)\nPublic Information Office\nFederal Bureau of Prisons\n(202) 353 (b)(6)\nPage 11531\nDOJ-OGR-00023938",
  "text_blocks": [
    {
      "type": "printed",
      "content": "Fwd: Re: Media inquiry - Fox News - re: former AW Shirley Skipper Scott\nFrom Lee Plourde\nTo (b)(6), (b)(7)(C), James Petrucci, Marti Licon-Vitale\nDate 2019/11/14 18:04\nSubject: Fwd: Re: Media inquiry - Fox News - re: former AW Shirley Skipper Scott\nAttachments: TEXT.htm",
      "position": "top"
    },
    {
      "type": "printed",
      "content": "Sent from my Verizon, Samsung Galaxy smartphone\n\nOriginal message ---------\nFrom: (b)(6), (b)(7)(C) @bop.gov>\nDate: 11/14/19 5:53 PM (GMT-05:00)\nTo: (b)(6), (b)(7)(C) @bop.gov>, Lee Plourde (b)(6) @bop.gov>\nSubject: Fwd: Re: Media inquiry - Fox News - re: former AW Shirley Skipper Scott",
      "position": "middle"
    },
    {
      "type": "printed",
      "content": "(b)(6), (b)(7)(C) 11/14/2019 17:53>>\nThis is the final version approved by IPPA that I'm sending now to the reporter\nReporter: (b)(6) - Fox News\nQuestion:\nHi there can you confirm whether case manager (b)(6), (b)(7)(C) is still working with SHU inmates at MCC or has he been transferred to a different case (b)(6)",
      "position": "middle"
    },
    {
      "type": "printed",
      "content": "(b)(6), (b)(7)(C)\nPublic Information Office\nFederal Bureau of Prisons\n(202) 353 (b)(6)",
      "position": "middle"
    },
    {
      "type": "printed",
      "content": "Page 11531\nDOJ-OGR-00023938",
      "position": "footer"
    }
  ],
  "entities": {
    "people": [
      "Lee Plourde",
      "James Petrucci",
      "Marti Licon-Vitale",
      "Shirley Skipper Scott"
    ],
    "organizations": [
      "Fox News",
      "Federal Bureau of Prisons"
    ],
    "locations": [
      "MCC"
    ],
    "dates": [
      "2019/11/14",
      "11/14/19"
    ],
    "reference_numbers": [
      "DOJ-OGR-00023938"
    ]
  },
  "additional_notes": "The document contains redacted information marked as (b)(6) and (b)(7)(C), indicating potentially sensitive or personal information."
}