{
  "document_metadata": {
    "page_number": "1254",
    "document_number": "DOJ-OGR-00025448",
    "date": "2019/08/12",
    "document_type": "SW Chronological Log",
    "has_handwriting": false,
    "has_stamps": false
  },
  "full_text": "Page 1254\nSW Chronological Log 7/23-24/19 re: Epstein, Jeffrey Edward, Reg. No. 73618-054\nFrom N'Diaye, Lamine (Charisma Edge)\nTo Ray Ormond\nDate 2019/08/12 15:30\nSubject: SW Chronological Log 7/23-24/19 re: Epstein, Jeffrey Edward, Reg. No. 73618-054\nAttachments: TEXT.htm, 2019_08_12_15_10_43.pdf, Charisma Edge.vcf\nI/M companion assumed duties from staff on 7/23/19 @ 7 am until 7/24/19 @ 8:45 am (S/W)\nEpstein was transferred to psych observation on 7/24/19 @ 8:45 am until 7/30/19 at 8:15 am (I/M companion was utilized).\nCharisma Edge\nAssociate Warden\nMCC New York\n150 Park Row\nNew York, NY 10007\n646-836-6300 ext @bop.gov\nNYM/AW-Programs-@bop.gov\nPage 3632\nDOJ-OGR-00025448",
  "text_blocks": [
    {
      "type": "printed",
      "content": "SW Chronological Log 7/23-24/19 re: Epstein, Jeffrey Edward, Reg. No. 73618-054",
      "position": "top"
    },
    {
      "type": "printed",
      "content": "From N'Diaye, Lamine (Charisma Edge)\nTo Ray Ormond\nDate 2019/08/12 15:30\nSubject: SW Chronological Log 7/23-24/19 re: Epstein, Jeffrey Edward, Reg. No. 73618-054\nAttachments: TEXT.htm, 2019_08_12_15_10_43.pdf, Charisma Edge.vcf",
      "position": "top"
    },
    {
      "type": "printed",
      "content": "I/M companion assumed duties from staff on 7/23/19 @ 7 am until 7/24/19 @ 8:45 am (S/W)\nEpstein was transferred to psych observation on 7/24/19 @ 8:45 am until 7/30/19 at 8:15 am (I/M companion was utilized).",
      "position": "middle"
    },
    {
      "type": "printed",
      "content": "Charisma Edge\nAssociate Warden\nMCC New York\n150 Park Row\nNew York, NY 10007\n646-836-6300 ext @bop.gov\nNYM/AW-Programs-@bop.gov",
      "position": "middle"
    },
    {
      "type": "printed",
      "content": "Page 3632\nDOJ-OGR-00025448",
      "position": "footer"
    }
  ],
  "entities": {
    "people": [
      "Jeffrey Edward Epstein",
      "Lamine N'Diaye",
      "Ray Ormond",
      "Charisma Edge"
    ],
    "organizations": [
      "MCC New York",
      "BOP"
    ],
    "locations": [
      "New York"
    ],
    "dates": [
      "7/23/19",
      "7/24/19",
      "7/30/19",
      "2019/08/12"
    ],
    "reference_numbers": [
      "73618-054",
      "DOJ-OGR-00025448"
    ]
  },
  "additional_notes": "The document appears to be a chronological log related to Jeffrey Epstein's detention. It includes details about his transfer to psych observation and the involvement of a companion. The document is from the Department of Justice and contains contact information for Charisma Edge, an Associate Warden at MCC New York."
}