{
  "document_metadata": {
    "page_number": "1193",
    "document_number": "DOJ-OGR-00025398",
    "date": "2019/08/10",
    "document_type": "email",
    "has_handwriting": false,
    "has_stamps": false
  },
  "full_text": "Page 1193\n\nFwd: Epstein, Jeffrey, Register No. 76318-054\nFrom Shirley V. Skipper-Scott\nTo [b)(6); (b)(7)(C)\nDate 2019/08/10 15:50\nSubject: Fwd: Epstein, Jeffrey, Register No. 76318-054\nAttachments: TEXT.htm\n\nShirley Skipper-Scott\nAssociate Warden\nMCC New York\n150 Park Row\nNew York, New York 10007\nOffice: 646-836 [b)(6); (b)(7)(C)\nBlack Berry: 646-423 [b)(6); (b)(7)(C)\n[b)(6); (b)(7)(C) @bop.gov\n\n>>> Shirley V. Skipper-Scott 8/10/2019 9:48 AM >>>\nOn August 10, 2019, at approximately 6:33 a.m., while attempting to serve inmate Epstein, Jeffrey, Register No. 76318-054, the breakfast meal, he was found unresponsive in his cell. Staff called for assistance and began life saving measures. He was escorted to Health Services and subsequently to the local hospital where he was pronounced dead at 7:36 am. He was escorted to Health Services at approximately 6:45 a.m., and EMS arrived at 6:59 a.m. He was transported to the local hospital at approximately 7:23 a.m. Institution medical staff stated he had circumfrical bruising around the neck. An orange make shift noose was found in his cell.\n\nShirley Skipper-Scott\nAssociate Warden\nMCC New York\n150 Park Row\nNew York, New York 10007\nOffice: 646-836 [b)(6); (b)(7)(C)\nBlack Berry: 646-423 [b)(6); (b)(7)(C)\n[b)(6); (b)(7)(C) @bop.gov\n\nPage 3193\nDOJ-OGR-00025398",
  "text_blocks": [
    {
      "type": "printed",
      "content": "Fwd: Epstein, Jeffrey, Register No. 76318-054\nFrom Shirley V. Skipper-Scott\nTo [b)(6); (b)(7)(C)\nDate 2019/08/10 15:50\nSubject: Fwd: Epstein, Jeffrey, Register No. 76318-054\nAttachments: TEXT.htm",
      "position": "top"
    },
    {
      "type": "printed",
      "content": "Shirley Skipper-Scott\nAssociate Warden\nMCC New York\n150 Park Row\nNew York, New York 10007\nOffice: 646-836 [b)(6); (b)(7)(C)\nBlack Berry: 646-423 [b)(6); (b)(7)(C)\n[b)(6); (b)(7)(C) @bop.gov",
      "position": "middle"
    },
    {
      "type": "printed",
      "content": ">>> Shirley V. Skipper-Scott 8/10/2019 9:48 AM >>>\nOn August 10, 2019, at approximately 6:33 a.m., while attempting to serve inmate Epstein, Jeffrey, Register No. 76318-054, the breakfast meal, he was found unresponsive in his cell. Staff called for assistance and began life saving measures. He was escorted to Health Services and subsequently to the local hospital where he was pronounced dead at 7:36 am. He was escorted to Health Services at approximately 6:45 a.m., and EMS arrived at 6:59 a.m. He was transported to the local hospital at approximately 7:23 a.m. Institution medical staff stated he had circumfrical bruising around the neck. An orange make shift noose was found in his cell.",
      "position": "middle"
    },
    {
      "type": "printed",
      "content": "Shirley Skipper-Scott\nAssociate Warden\nMCC New York\n150 Park Row\nNew York, New York 10007\nOffice: 646-836 [b)(6); (b)(7)(C)\nBlack Berry: 646-423 [b)(6); (b)(7)(C)\n[b)(6); (b)(7)(C) @bop.gov",
      "position": "middle"
    },
    {
      "type": "printed",
      "content": "Page 3193\nDOJ-OGR-00025398",
      "position": "bottom"
    }
  ],
  "entities": {
    "people": [
      "Jeffrey Epstein",
      "Shirley V. Skipper-Scott"
    ],
    "organizations": [
      "MCC New York",
      "Health Services",
      "EMS"
    ],
    "locations": [
      "New York",
      "150 Park Row"
    ],
    "dates": [
      "August 10, 2019",
      "8/10/2019"
    ],
    "reference_numbers": [
      "76318-054",
      "DOJ-OGR-00025398"
    ]
  },
  "additional_notes": "The document contains redactions marked as [b)(6); (b)(7)(C)]. The document appears to be an email chain discussing the death of Jeffrey Epstein."
}