{
  "document_metadata": {
    "page_number": "159",
    "document_number": "DOJ-OGR-00024591",
    "date": "08/19/2019",
    "document_type": "Log Entries By Event Date",
    "has_handwriting": false,
    "has_stamps": false
  },
  "full_text": "Date: 08/19/2019 Time: 10:27 AM Federal Bureau of Prisons TRUINTEL Log Entries By Event Date Sensitive But Unclassified Entered Date Alpha Code Level 1 Location Level 2 Location Level 3 Location Event Date Shift User Event Base Count 7/23/2019 4:10 AM NYM SHU Housing Unit, Special (SHU) 9 SOUTH SHU 7/23/2019 12:10 AM Morning Key Check 7/23/2019 4:10 AM NYM SHU Housing Unit, Special (SHU) 9 SOUTH SHU 7/23/2019 12:10 AM Morning OC Spray Check 7/23/2019 4:10 AM NYM SHU Housing Unit, Special (SHU) 9 SOUTH SHU 7/23/2019 12:10 AM Morning Radio Check 7/23/2019 4:10 AM NYM SHU Housing Unit, Special (SHU) 9 SOUTH SHU 7/23/2019 12:10 AM Morning Radio Check 7/23/2019 4:06 AM NYM SHU Housing Unit, Special (SHU) 9 SOUTH SHU 7/23/2019 12:18 AM Morning Fire and Security Check 7/23/2019 4:11 AM NYM SHU Housing Unit, Special (SHU) 9 SOUTH SHU 7/23/2019 12:30 AM Morning Watch Call 7/23/2019 4:11 AM NYM SHU Housing Unit, Special (SHU) 9 SOUTH SHU 7/23/2019 12:35 AM Morning Rounds (Officer) 7/23/2019 4:12 AM NYM SHU Housing Unit, Special (SHU) 9 SOUTH SHU 7/23/2019 1:00 AM Morning Watch Call 7/23/2019 4:12 AM NYM SHU Housing Unit, Special (SHU) 9 SOUTH SHU 7/23/2019 1:27 AM Morning Watch Call 7/23/2019 4:20 AM NYM SHU Housing Unit, Special (SHU) 9 SOUTH SHU 7/23/2019 1:27 AM Morning Daily Activity User ID: Page 159 of 395 DOJ-OGR-00024591",
  "text_blocks": [
    {
      "type": "printed",
      "content": "Date: 08/19/2019 Time: 10:27 AM Federal Bureau of Prisons TRUINTEL Log Entries By Event Date Sensitive But Unclassified",
      "position": "header"
    },
    {
      "type": "printed",
      "content": "Entered Date Alpha Code Level 1 Location Level 2 Location Level 3 Location Event Date Shift User Event Base Count",
      "position": "header"
    },
    {
      "type": "printed",
      "content": "7/23/2019 4:10 AM NYM SHU Housing Unit, Special (SHU) 9 SOUTH SHU 7/23/2019 12:10 AM Morning Key Check",
      "position": "body"
    },
    {
      "type": "printed",
      "content": "7/23/2019 4:10 AM NYM SHU Housing Unit, Special (SHU) 9 SOUTH SHU 7/23/2019 12:10 AM Morning OC Spray Check",
      "position": "body"
    },
    {
      "type": "printed",
      "content": "7/23/2019 4:10 AM NYM SHU Housing Unit, Special (SHU) 9 SOUTH SHU 7/23/2019 12:10 AM Morning Radio Check",
      "position": "body"
    },
    {
      "type": "printed",
      "content": "7/23/2019 4:10 AM NYM SHU Housing Unit, Special (SHU) 9 SOUTH SHU 7/23/2019 12:10 AM Morning Radio Check",
      "position": "body"
    },
    {
      "type": "printed",
      "content": "7/23/2019 4:06 AM NYM SHU Housing Unit, Special (SHU) 9 SOUTH SHU 7/23/2019 12:18 AM Morning Fire and Security Check",
      "position": "body"
    },
    {
      "type": "printed",
      "content": "7/23/2019 4:11 AM NYM SHU Housing Unit, Special (SHU) 9 SOUTH SHU 7/23/2019 12:30 AM Morning Watch Call",
      "position": "body"
    },
    {
      "type": "printed",
      "content": "7/23/2019 4:11 AM NYM SHU Housing Unit, Special (SHU) 9 SOUTH SHU 7/23/2019 12:35 AM Morning Rounds (Officer)",
      "position": "body"
    },
    {
      "type": "printed",
      "content": "7/23/2019 4:12 AM NYM SHU Housing Unit, Special (SHU) 9 SOUTH SHU 7/23/2019 1:00 AM Morning Watch Call",
      "position": "body"
    },
    {
      "type": "printed",
      "content": "7/23/2019 4:12 AM NYM SHU Housing Unit, Special (SHU) 9 SOUTH SHU 7/23/2019 1:27 AM Morning Watch Call",
      "position": "body"
    },
    {
      "type": "printed",
      "content": "7/23/2019 4:20 AM NYM SHU Housing Unit, Special (SHU) 9 SOUTH SHU 7/23/2019 1:27 AM Morning Daily Activity",
      "position": "body"
    },
    {
      "type": "printed",
      "content": "User ID:",
      "position": "footer"
    },
    {
      "type": "printed",
      "content": "Page 159 of 395",
      "position": "footer"
    },
    {
      "type": "printed",
      "content": "DOJ-OGR-00024591",
      "position": "footer"
    }
  ],
  "entities": {
    "people": [],
    "organizations": [
      "Federal Bureau of Prisons"
    ],
    "locations": [
      "9 SOUTH SHU",
      "Housing Unit, Special (SHU)"
    ],
    "dates": [
      "08/19/2019",
      "7/23/2019"
    ],
    "reference_numbers": [
      "DOJ-OGR-00024591"
    ]
  },
  "additional_notes": "The document appears to be a log entry report from the Federal Bureau of Prisons, detailing various events and activities at a specific facility on July 23, 2019. The report includes information such as the date, time, location, and type of event, as well as the user who entered the data. The document is marked as 'Sensitive But Unclassified'."
}