{
  "document_metadata": {
    "page_number": "381",
    "document_number": null,
    "date": "6 Nov 2019",
    "document_type": "email",
    "has_handwriting": false,
    "has_stamps": false
  },
  "full_text": "Page 381\nTo: Charisma Edge\nFrom: [redacted]\nSubject: Re: Epstein, Jeffrey 76318-054\nSent: Wed, 6 Nov 2019 00:10:52 +0000\n10.4. Thanks\nOn Nov 5, 2019, at 7:07 PM, Charisma Edge wrote:\nHi [redacted]\nI have forwarded your request to the legal department for a response. I'll get back to you in the morning.\nSent from my Verizon, Samsung Galaxy smartphone\n------- Original message -------\nFrom: [redacted]\nDate: 11/5/19 6:45 PM (GMT-05:00)\nTo: Charisma Edge\nSubject: Epstein, Jeffrey 76318-054\n[redacted] 11/05/2019 18:45\nCharisma\nOur Prisoner Operations Division in Headquarters is requesting any reports prepared in the investigation surrounding the death of EPSTEIN. They are requesting the information by tomorrow 11/6/2019- I apologize for the short notice, but can you please provide me with the reports prepared by BOP.\nThank you\n[redacted]\nSupervisory Deputy United States Marshal\nSouthern District of New York\n646-942-[redacted]\nDOJ-OGR-00024879",
  "text_blocks": [
    {
      "type": "printed",
      "content": "Page 381\nTo: Charisma Edge\nFrom: [redacted]\nSubject: Re: Epstein, Jeffrey 76318-054\nSent: Wed, 6 Nov 2019 00:10:52 +0000",
      "position": "header"
    },
    {
      "type": "printed",
      "content": "10.4. Thanks\nOn Nov 5, 2019, at 7:07 PM, Charisma Edge wrote:\nHi [redacted]\nI have forwarded your request to the legal department for a response. I'll get back to you in the morning.",
      "position": "middle"
    },
    {
      "type": "printed",
      "content": "Sent from my Verizon, Samsung Galaxy smartphone",
      "position": "middle"
    },
    {
      "type": "printed",
      "content": "------- Original message -------\nFrom: [redacted]\nDate: 11/5/19 6:45 PM (GMT-05:00)\nTo: Charisma Edge\nSubject: Epstein, Jeffrey 76318-054",
      "position": "middle"
    },
    {
      "type": "printed",
      "content": "[redacted] 11/05/2019 18:45\nCharisma\nOur Prisoner Operations Division in Headquarters is requesting any reports prepared in the investigation surrounding the death of EPSTEIN. They are requesting the information by tomorrow 11/6/2019- I apologize for the short notice, but can you please provide me with the reports prepared by BOP.",
      "position": "middle"
    },
    {
      "type": "printed",
      "content": "Thank you\n[redacted]\nSupervisory Deputy United States Marshal\nSouthern District of New York\n646-942-[redacted]",
      "position": "middle"
    },
    {
      "type": "printed",
      "content": "DOJ-OGR-00024879",
      "position": "footer"
    }
  ],
  "entities": {
    "people": [
      "Charisma Edge",
      "Jeffrey Epstein"
    ],
    "organizations": [
      "USMS",
      "DOJ",
      "BOP",
      "Verizon"
    ],
    "locations": [
      "New York"
    ],
    "dates": [
      "6 Nov 2019",
      "Nov 5, 2019",
      "11/5/19",
      "11/6/2019"
    ],
    "reference_numbers": [
      "76318-054",
      "DOJ-OGR-00024879",
      "646-942-[redacted]"
    ]
  },
  "additional_notes": "The document contains redactions, likely for privacy or security reasons."
}