{
  "document_metadata": {
    "page_number": "751",
    "document_number": "DOJ-OGR-00023552",
    "date": "2019/08/12",
    "document_type": "Email",
    "has_handwriting": false,
    "has_stamps": false
  },
  "full_text": "Fwd: RE: United States v. Jeffrey Epstein\nFrom\n(b)(6), (b)(7)(C)\n(b)(6), (b)(7)(C)\nCharisma Edge, (b)(6), (b)(7)(C)\nTo\n(b)(6)\nLamine N'Diaye, Lee Plourde, (b)(6), (b)(7)(C)\nNYM/Executive Staff, NYM/Lieutenants, (b)(6), (b)(7)(C)\nShirley V. Skipper-Scott, (b)(6), (b)(7)(C)\nDate\n2019/08/12 07:15\nSubject:\nFwd: RE: United States v. Jeffrey Epstein\nAttachments:\nTEXT.htm\nGood morning,\nPlease see the below request for preservation and production of various documents, videos, and other information. Please preserve the material requested below to prevent deletion. We will advise that they need to request production of the requested documentation through FOIA.\nThank you,\nAdam\n(b)(6), (b)(7)(C)\nSupervisory Staff Attorney\nCLC New York\nMetropolitan Correctional Center\n150 Park Row\nNew York, New York 10007\np: (646)836(b)(6)\nf: (646)836-7665\n>>> (b)(6), (b)(7)(C) 8/11/2019 3:56 PM >>>\n(b)(6), (b)(7)(C) Mr. Epstein's family has asked me to send to you and (b)(6), (b)(7)(C) at the MCC a request for the preservation of any and all documents, records, reports, videos, pictures, physical evidence, electronic communication data, tape recordings, logs, notes, papers, emails and any and all other forms of information that would be in the possession of the MCC, its Warden, their legal counsel, the USMS, the FBI, the Inspector General, the USAO for the SDNY or any other federal or relevant state or city agency that relate to Jeffrey Epstein's imprisonment/detention since July 6, 2019 and that relate particularly but not exclusively to the July 23, 2019 occurrence which was investigated as an attempted suicide by the MCC and the events relating to his death on August 10, 2019. The request encompasses but is not limited to any videos of the 9th floor area in the proximity of his cell during the evening of August 9 through the time Mr. Epstein was taken out of his cell for the last time on August 10, 2019, or videos of the cell itself during that time period, records of the identities of (i.e. MCC employees or independent contractors or anyone else) who were on duty from midnight through 8 AM on August 10, 2019 or otherwise had access to the 9th floor unit where Mr. Epstein was incarcerated during this time period, records of any observations of Mr. Epstein on August 9-10, 2019, any and all photographs of Mr. Epstein or his cell taken on August 10, 2019, any and all electronic or tape recordings or records of any internal communications within the MCC or any external communications by MCC staff on August 9 and August 10, 2019, records of any mental health interviews or assessments of Mr. Epstein at anytime during his detention, records of any decision to put him on or take Mr Epstein off suicide watch\nPage 751\nDOJ-OGR-00023552",
  "text_blocks": [
    {
      "type": "printed",
      "content": "Fwd: RE: United States v. Jeffrey Epstein\nFrom\n(b)(6), (b)(7)(C)\n(b)(6), (b)(7)(C)\nCharisma Edge, (b)(6), (b)(7)(C)\nTo\n(b)(6)\nLamine N'Diaye, Lee Plourde, (b)(6), (b)(7)(C)\nNYM/Executive Staff, NYM/Lieutenants, (b)(6), (b)(7)(C)\nShirley V. Skipper-Scott, (b)(6), (b)(7)(C)\nDate\n2019/08/12 07:15\nSubject:\nFwd: RE: United States v. Jeffrey Epstein\nAttachments:\nTEXT.htm",
      "position": "header"
    },
    {
      "type": "printed",
      "content": "Good morning,\nPlease see the below request for preservation and production of various documents, videos, and other information. Please preserve the material requested below to prevent deletion. We will advise that they need to request production of the requested documentation through FOIA.\nThank you,\nAdam",
      "position": "middle"
    },
    {
      "type": "printed",
      "content": "(b)(6), (b)(7)(C)\nSupervisory Staff Attorney\nCLC New York\nMetropolitan Correctional Center\n150 Park Row\nNew York, New York 10007\np: (646)836(b)(6)\nf: (646)836-7665",
      "position": "middle"
    },
    {
      "type": "printed",
      "content": ">>> (b)(6), (b)(7)(C) 8/11/2019 3:56 PM >>>\n(b)(6), (b)(7)(C) Mr. Epstein's family has asked me to send to you and (b)(6), (b)(7)(C) at the MCC a request for the preservation of any and all documents, records, reports, videos, pictures, physical evidence, electronic communication data, tape recordings, logs, notes, papers, emails and any and all other forms of information that would be in the possession of the MCC, its Warden, their legal counsel, the USMS, the FBI, the Inspector General, the USAO for the SDNY or any other federal or relevant state or city agency that relate to Jeffrey Epstein's imprisonment/detention since July 6, 2019 and that relate particularly but not exclusively to the July 23, 2019 occurrence which was investigated as an attempted suicide by the MCC and the events relating to his death on August 10, 2019. The request encompasses but is not limited to any videos of the 9th floor area in the proximity of his cell during the evening of August 9 through the time Mr. Epstein was taken out of his cell for the last time on August 10, 2019, or videos of the cell itself during that time period, records of the identities of (i.e. MCC employees or independent contractors or anyone else) who were on duty from midnight through 8 AM on August 10, 2019 or otherwise had access to the 9th floor unit where Mr. Epstein was incarcerated during this time period, records of any observations of Mr. Epstein on August 9-10, 2019, any and all photographs of Mr. Epstein or his cell taken on August 10, 2019, any and all electronic or tape recordings or records of any internal communications within the MCC or any external communications by MCC staff on August 9 and August 10, 2019, records of any mental health interviews or assessments of Mr. Epstein at anytime during his detention, records of any decision to put him on or take Mr Epstein off suicide watch",
      "position": "middle"
    },
    {
      "type": "printed",
      "content": "Page 751\nDOJ-OGR-00023552",
      "position": "footer"
    }
  ],
  "entities": {
    "people": [
      "Jeffrey Epstein",
      "Lamine N'Diaye",
      "Lee Plourde",
      "Shirley V. Skipper-Scott",
      "Adam"
    ],
    "organizations": [
      "MCC",
      "FBI",
      "USMS",
      "USAO",
      "SDNY"
    ],
    "locations": [
      "New York",
      "Metropolitan Correctional Center",
      "150 Park Row"
    ],
    "dates": [
      "2019/08/12",
      "2019/08/11",
      "July 6, 2019",
      "July 23, 2019",
      "August 9, 2019",
      "August 10, 2019"
    ],
    "reference_numbers": [
      "DOJ-OGR-00023552"
    ]
  },
  "additional_notes": "The document contains multiple redactions, indicated by (b)(6) and (b)(7)(C), suggesting sensitive information has been withheld."
}