{
  "document_metadata": {
    "page_number": "1",
    "document_number": "DOJ-OGR-00024977",
    "date": "08/01/2019",
    "document_type": "Suicide Risk Assessment",
    "has_handwriting": false,
    "has_stamps": false
  },
  "full_text": "Page 520\n\nBureau of Prisons\nPsychology Services\nSuicide Risk Assessment\n\n**SENSITIVE BUT UNCLASSIFIED**\n\nInmate Name: EPSTEIN, JEFFREY EDWARD\nDate of Birth: 01/20/1953\nSex: M\nFacility: NYM\nReg #: 76318-054\nDate: 08/01/2019 13:29\nProvider: [b(6); (b)(7)(C)]\nPsyD\nUnit Team: 5\n\nType of Housing: SHU- Administrative Segregation\nCell Accommodation: Double-Cell\n\nFINDINGS\nThis assessment and the resulting recommendations are based on the following sources of information:\nClinical Interview, Medical Record, Psychology Data System, Sentry\n\nReason for Referral\nR & D staff reported to this writer this morning at about 8:30 AM on 8/01/19 that yesterday when Mr. Epstein was brought back from court the US Marshals asked him to sign a form that noted Mr. Epstein has \"suicidal tendencies.\" Mr. Epstein was seen for a Suicide Risk Assessment at about 1:00 PM on 8/01/19 in Attorney Conference.\n\nThis note is being entered at about 4:20 PM on 8/01/19.\n\nMental Health History\nAccording to a Suicide Risk Assessment dated 7/09/19 by [b(6); (b)(7)(C)] \"Inmate Epstein denied any history of mental health treatment, either on an inpatient or outpatient basis. Inmate Epstein denied any treatment in the past or present with psychotropic medication. He also denied any acute mental health symptoms at this time.\"\n\nSelf-Harm History\nAccording to a Suicide Risk Assessment dated 7/09/19 by [b(6); (b)(7)(C)] \"Inmate Epstein denied any past or present suicidal ideation, intention or plan. He denied ever engaging in any suicide attempts or self-injurious behavior in the past.\"\n\n[b(7)(A)]\n\nCurrent Problem\nR & D staff reported to this writer this morning at about 8:30 AM on 8/01/19 that yesterday when Mr. Epstein was brought back from court the US Marshals asked him to sign a form that noted Mr. Epstein has \"suicidal tendencies.\" This is likely due to the incident on 7/23/19, but as a precaution another Suicide Risk Assessment was conducted.\n\nMr. Epstein seemed surprised that there was a form noting suicidal tendencies. He denied stating he was suicidal.\n\nHe said he saw the DHO today and he said his incident report for the marks on his neck was expunged. He stated even though he has his cpap machine now, he said his cellmate talks at night and he stated this keeps him up. This writer offered to talk to the SHU Lt. to have him housed with a different cellmate, but he stated he wants to give it 3 to 4 days to see if he wants a different cellmate. He complained about the noise in SHU.\n\nCurrent Mental Status\nLevel of Consciousness: Alert and Oriented\nPsychomotor Activity: Normal\nGeneral Appearance: Normal\nBehavior: Cooperative\nMood: Appropriate to Content\nThought Process: Goal Directed\nThought Content: Normal\nCurrent Mental Status: He exhibited a neutral mood with a mildly restricted range of affect. His speech was logical and\n\nGenerated 08/01/2019 16:21 by [b(6); (b)(7)(C)] PsyD Bureau of Prisons - NYM Page 1 of 3",
  "text_blocks": [
    {
      "type": "printed",
      "content": "Bureau of Prisons Psychology Services Suicide Risk Assessment",
      "position": "header"
    },
    {
      "type": "printed",
      "content": "Inmate Name: EPSTEIN, JEFFREY EDWARD Date of Birth: 01/20/1953 Sex: M Facility: NYM Reg #: 76318-054 Date: 08/01/2019 13:29 Provider: [b(6); (b)(7)(C)] PsyD Unit Team: 5",
      "position": "top"
    },
    {
      "type": "printed",
      "content": "Type of Housing: SHU- Administrative Segregation Cell Accommodation: Double-Cell",
      "position": "top"
    },
    {
      "type": "printed",
      "content": "FINDINGS This assessment and the resulting recommendations are based on the following sources of information: Clinical Interview, Medical Record, Psychology Data System, Sentry",
      "position": "middle"
    },
    {
      "type": "printed",
      "content": "Reason for Referral R & D staff reported to this writer this morning at about 8:30 AM on 8/01/19 that yesterday when Mr. Epstein was brought back from court the US Marshals asked him to sign a form that noted Mr. Epstein has \"suicidal tendencies.\" Mr. Epstein was seen for a Suicide Risk Assessment at about 1:00 PM on 8/01/19 in Attorney Conference.",
      "position": "middle"
    },
    {
      "type": "printed",
      "content": "Mental Health History According to a Suicide Risk Assessment dated 7/09/19 by [b(6); (b)(7)(C)] \"Inmate Epstein denied any history of mental health treatment, either on an inpatient or outpatient basis. Inmate Epstein denied any treatment in the past or present with psychotropic medication. He also denied any acute mental health symptoms at this time.\"",
      "position": "middle"
    },
    {
      "type": "printed",
      "content": "Self-Harm History According to a Suicide Risk Assessment dated 7/09/19 by [b(6); (b)(7)(C)] \"Inmate Epstein denied any past or present suicidal ideation, intention or plan. He denied ever engaging in any suicide attempts or self-injurious behavior in the past.\"",
      "position": "middle"
    },
    {
      "type": "printed",
      "content": "Current Problem R & D staff reported to this writer this morning at about 8:30 AM on 8/01/19 that yesterday when Mr. Epstein was brought back from court the US Marshals asked him to sign a form that noted Mr. Epstein has \"suicidal tendencies.\" This is likely due to the incident on 7/23/19, but as a precaution another Suicide Risk Assessment was conducted.",
      "position": "middle"
    },
    {
      "type": "printed",
      "content": "Current Mental Status Level of Consciousness: Alert and Oriented Psychomotor Activity: Normal General Appearance: Normal Behavior: Cooperative Mood: Appropriate to Content Thought Process: Goal Directed Thought Content: Normal Current Mental Status: He exhibited a neutral mood with a mildly restricted range of affect. His speech was logical and",
      "position": "bottom"
    },
    {
      "type": "printed",
      "content": "Generated 08/01/2019 16:21 by [b(6); (b)(7)(C)] PsyD Bureau of Prisons - NYM Page 1 of 3",
      "position": "footer"
    }
  ],
  "entities": {
    "people": [
      "JEFFREY EDWARD EPSTEIN"
    ],
    "organizations": [
      "Bureau of Prisons",
      "US Marshals"
    ],
    "locations": [
      "NYM"
    ],
    "dates": [
      "01/20/1953",
      "08/01/2019",
      "7/09/19",
      "7/23/19"
    ],
    "reference_numbers": [
      "76318-054",
      "DOJ-OGR-00024977"
    ]
  },
  "additional_notes": "The document appears to be a sensitive but unclassified suicide risk assessment for Jeffrey Epstein. It contains redactions for certain names and identifiers."
}