{
  "document_metadata": {
    "page_number": "165",
    "document_number": "DOJ-OGR-00024597",
    "date": "08/19/2019",
    "document_type": "Log Entries By Event Date",
    "has_handwriting": false,
    "has_stamps": false
  },
  "full_text": "Date: 08/19/2019 Time: 10:27 AM Federal Bureau of Prisons TRUINTEL Log Entries By Event Date Sensitive But Unclassified Entered Date Alpha Code Level 1 Location Level 2 Location Level 3 Location Event Date Shift User Event Base Count 7/23/2019 NYM SHU Housing Unit, Special (SHU) 9 SOUTH SHU 7/23/2019 4:05 PM Evening myles b(7)(6) Official Count - Summary Text: Completed. 7/23/2019 4:56 PM NYM SHU Housing Unit, Special (SHU) 9 SOUTH SHU 7/23/2019 4:10 PM Evening b(7)(6) - Summary Text: Clear Count b(6) 7/23/2019 4:56 PM NYM SHU Housing Unit, Special (SHU) 9 SOUTH SHU 7/23/2019 4:10 PM Evening b(7)(F) - Summary Text: Radio Number b(7)(6) 7/23/2019 4:56 PM NYM SHU Housing Unit, Special (SHU) 9 SOUTH SHU 7/23/2019 4:10 PM Evening b(7)(F) - Summary Text: Radio Number b(7)(6) 7/23/2019 4:56 PM NYM SHU Housing Unit, Special (SHU) 9 SOUTH SHU 7/23/2019 4:10 PM Evening b(7)(F) - Summary Text: Radio Number b(7)(6) 7/23/2019 4:56 PM NYM SHU Housing Unit, Special (SHU) 9 SOUTH SHU 7/23/2019 4:10 PM Evening Fire Alarm Panel Check - Summary Text: Completed. 7/23/2019 4:56 PM NYM SHU Housing Unit, Special (SHU) 9 SOUTH SHU 7/23/2019 4:10 PM Evening Inventory Sheet Verified - Summary Text: Completed. 7/23/2019 4:56 PM NYM SHU Housing Unit, Special (SHU) 9 SOUTH SHU 7/23/2019 4:10 PM Evening Key Check - Summary Text: Ring Number b(7)(6) 7/23/2019 4:56 PM NYM SHU Housing Unit, Special (SHU) 9 SOUTH SHU 7/23/2019 4:10 PM Evening Key Check - Summary Text: Ring Number b(7)(6) 7/23/2019 4:56 PM NYM SHU Housing Unit, Special (SHU) 9 SOUTH SHU 7/23/2019 4:10 PM Evening OC Spray Check User ID: b(7)(6) Page 165 of 395 DOJ-OGR-00024597",
  "text_blocks": [
    {
      "type": "printed",
      "content": "Date: 08/19/2019 Time: 10:27 AM Federal Bureau of Prisons TRUINTEL Log Entries By Event Date Sensitive But Unclassified",
      "position": "header"
    },
    {
      "type": "printed",
      "content": "Entered Date Alpha Code Level 1 Location Level 2 Location Level 3 Location Event Date Shift User Event Base Count",
      "position": "header"
    },
    {
      "type": "printed",
      "content": "7/23/2019 NYM SHU Housing Unit, Special (SHU) 9 SOUTH SHU 7/23/2019 4:05 PM Evening myles b(7)(6) Official Count - Summary Text: Completed.",
      "position": "body"
    },
    {
      "type": "printed",
      "content": "User ID: b(7)(6)",
      "position": "footer"
    },
    {
      "type": "printed",
      "content": "Page 165 of 395 DOJ-OGR-00024597",
      "position": "footer"
    }
  ],
  "entities": {
    "people": [
      "myles"
    ],
    "organizations": [
      "Federal Bureau of Prisons"
    ],
    "locations": [
      "9 SOUTH SHU",
      "Housing Unit, Special (SHU)"
    ],
    "dates": [
      "7/23/2019",
      "08/19/2019"
    ],
    "reference_numbers": [
      "DOJ-OGR-00024597"
    ]
  },
  "additional_notes": "The document appears to be a log entry report from the Federal Bureau of Prisons. It contains various events and activities recorded on July 23, 2019. The document is marked 'Sensitive But Unclassified'."
}