{
  "document_metadata": {
    "page_number": "89",
    "document_number": "DOJ-OGR-00023507",
    "date": null,
    "document_type": "email correspondence",
    "has_handwriting": false,
    "has_stamps": false
  },
  "full_text": "(202) 514-6620 - fax >>> [b)(6). (b)(7)(C) @thedailybeast.com> 8/10/2019 9:02 AM >>> Hello, Hearing Jeffrey Epstein commuted suicide at MCC in manhattan if someone could confirm? Thanks â€\" [b)(6). (b)(7)(C) Senior Editor, writer The Daily Beast M: 267-257-[b)(6) Facebook, Twitter, Instagram: @[b)(6). (b)(7)(C) From: BOP-IPP/Public Affairs <BOP-IPP/PublicAffairs@bop.gov> Sent: Thursday, July 25, 2019 11:15:50 AM To: [b)(6). (b)(7)(C) @thedailybeast.com> Subject: Re: Jeffrey Epstein [b)(6). (b)(7)(C) Jeffrey Epstein is currently housed at MCC New York and not in a local hospital as has been reported. As with all inmates, for privacy and security reasons, we do not share information on an inmate's medical status or their conditions of confinement. Thanks Office of Public Affairs Information, Policy and Public Affairs Division Federal Bureau of Prisons (202) 514-6551 - phone (202) 514-6620 - fax >>> [b)(6). (b)(7)(C) @thedailybeast.com> 7/25/2019 9:44 AM >>> Hello, Reaching out about reports that Jeffrey Epstein tried to kill himself in prison/was injured in someway. [b)(6). (b)(7)(C) â€\" [b)(6). (b)(7)(C) Senior Editor, writer The Daily Beast M: 267-257[b)(6) Page 89 DOJ-OGR-00023507",
  "text_blocks": [
    {
      "type": "printed",
      "content": "(202) 514-6620 - fax",
      "position": "header"
    },
    {
      "type": "printed",
      "content": ">>> [b)(6). (b)(7)(C) @thedailybeast.com> 8/10/2019 9:02 AM >>> Hello, Hearing Jeffrey Epstein commuted suicide at MCC in manhattan if someone could confirm? Thanks â€\" [b)(6). (b)(7)(C) Senior Editor, writer The Daily Beast M: 267-257-[b)(6) Facebook, Twitter, Instagram: @[b)(6). (b)(7)(C)",
      "position": "top"
    },
    {
      "type": "printed",
      "content": "From: BOP-IPP/Public Affairs <BOP-IPP/PublicAffairs@bop.gov> Sent: Thursday, July 25, 2019 11:15:50 AM To: [b)(6). (b)(7)(C) @thedailybeast.com> Subject: Re: Jeffrey Epstein",
      "position": "middle"
    },
    {
      "type": "printed",
      "content": "[b)(6). (b)(7)(C) Jeffrey Epstein is currently housed at MCC New York and not in a local hospital as has been reported. As with all inmates, for privacy and security reasons, we do not share information on an inmate's medical status or their conditions of confinement. Thanks Office of Public Affairs Information, Policy and Public Affairs Division Federal Bureau of Prisons (202) 514-6551 - phone (202) 514-6620 - fax",
      "position": "middle"
    },
    {
      "type": "printed",
      "content": ">>> [b)(6). (b)(7)(C) @thedailybeast.com> 7/25/2019 9:44 AM >>> Hello, Reaching out about reports that Jeffrey Epstein tried to kill himself in prison/was injured in someway. [b)(6). (b)(7)(C) â€\" [b)(6). (b)(7)(C) Senior Editor, writer The Daily Beast M: 267-257[b)(6)",
      "position": "bottom"
    },
    {
      "type": "printed",
      "content": "Page 89 DOJ-OGR-00023507",
      "position": "footer"
    }
  ],
  "entities": {
    "people": [
      "Jeffrey Epstein"
    ],
    "organizations": [
      "The Daily Beast",
      "Federal Bureau of Prisons"
    ],
    "locations": [
      "MCC New York",
      "Manhattan"
    ],
    "dates": [
      "July 25, 2019",
      "8/10/2019",
      "7/25/2019"
    ],
    "reference_numbers": [
      "DOJ-OGR-00023507",
      "(202) 514-6620",
      "(202) 514-6551"
    ]
  },
  "additional_notes": "The document contains multiple email correspondences between The Daily Beast and the Federal Bureau of Prisons regarding Jeffrey Epstein's status. The document has redactions for personal information."
}