{
  "document_metadata": {
    "page_number": "1718",
    "document_number": "DOJ-OGR-00023646",
    "date": "8/6/2019",
    "document_type": "email",
    "has_handwriting": false,
    "has_stamps": false
  },
  "full_text": "Good afternoon all,\nBelow please find complaints from Epstein's attorneys. Can you check to see if he has toilet paper and that his CPAP is plugged in?\n\nThank you,\n\nSupervisory Staff Attorney\nCLC New York\nMetropolitan Correctional Center\n150 Park Row\nNew York, New York  10007\np: (646)836-\nf: (646)836-7665\n\nGood afternoon Mr.\nOur client, Jeffrey Epstein, has informed us that he has no toilet paper in his cell. His CPap machine was not plugged in last night, so he was unable to use it.\nAlso, since his arrival at MCC, he has only been able to make two fifteen minute phone calls. Both times, the calls were on speaker phone, with officers present.\nThank you in advance for your help.\nBest,\n\nNOTICE: This message may contain information that is privileged or confidential. If you receive this transmission in error, please notify the sender by reply e-mail and delete the message and any attachments.\n\nPage 1718\nDOJ-OGR-00023646",
  "text_blocks": [
    {
      "type": "printed",
      "content": "Good afternoon all,",
      "position": "top"
    },
    {
      "type": "printed",
      "content": "Below please find complaints from Epstein's attorneys. Can you check to see if he has toilet paper and that his CPAP is plugged in?",
      "position": "top"
    },
    {
      "type": "printed",
      "content": "Thank you,",
      "position": "top"
    },
    {
      "type": "printed",
      "content": "Supervisory Staff Attorney\nCLC New York\nMetropolitan Correctional Center\n150 Park Row\nNew York, New York  10007\np: (646)836-\nf: (646)836-7665",
      "position": "top"
    },
    {
      "type": "printed",
      "content": "Good afternoon Mr.",
      "position": "middle"
    },
    {
      "type": "printed",
      "content": "Our client, Jeffrey Epstein, has informed us that he has no toilet paper in his cell. His CPap machine was not plugged in last night, so he was unable to use it.",
      "position": "middle"
    },
    {
      "type": "printed",
      "content": "Also, since his arrival at MCC, he has only been able to make two fifteen minute phone calls. Both times, the calls were on speaker phone, with officers present.",
      "position": "middle"
    },
    {
      "type": "printed",
      "content": "Thank you in advance for your help.",
      "position": "middle"
    },
    {
      "type": "printed",
      "content": "Best,",
      "position": "middle"
    },
    {
      "type": "printed",
      "content": "NOTICE: This message may contain information that is privileged or confidential. If you receive this transmission in error, please notify the sender by reply e-mail and delete the message and any attachments.",
      "position": "bottom"
    },
    {
      "type": "printed",
      "content": "Page 1718\nDOJ-OGR-00023646",
      "position": "footer"
    }
  ],
  "entities": {
    "people": [
      "Jeffrey Epstein"
    ],
    "organizations": [
      "CLC New York",
      "Metropolitan Correctional Center"
    ],
    "locations": [
      "New York"
    ],
    "dates": [
      "8/6/2019"
    ],
    "reference_numbers": [
      "DOJ-OGR-00023646"
    ]
  },
  "additional_notes": "The document contains redactions, likely for privacy or confidentiality reasons."
}