{
  "document_metadata": {
    "page_number": null,
    "document_number": "BP-A0489",
    "date": "JUN 10",
    "document_type": "HIV COUNSELING DOCUMENTATION",
    "has_handwriting": true,
    "has_stamps": false
  },
  "full_text": "BP-A0489 JUN 10 U.S. DEPARTMENT OF JUSTICE FEDERAL BUREAU OF PRISONS HIV COUNSELING DOCUMENTATION Directions: Use the following criteria to counsel the patient who is tested for the HIV antibody. Check off each item as they are discussed. Write NA beside any item that is inappropriate to the situation. The reverse side of this form will be utilized to document seronegative and inconclusive test result. Then file in the patient's record, documenting in progress notes that counseling was completed. PRETEST: 1. Explain purpose of session. 2. Explain confidentiality. 3. Explain HIV antibody test. a. What HIV is b. What the test is c. Test Procedure d. Meaning of test results e. Inability of detecting early infection (false negatives) f. Potential need for additional testing g. Significance of a positive test 4. List risk factors/clinical signs: (check all that apply) a. Injecting drug use, sharing drug or tattoo equipment b. Unprotected or multiple sex partners c. Treated for: sexually transmitted infections, hepatitis, or TB d. Clinical s/s: fever or illness of unknown cause, symptoms of AIDS opportunistic infections. e. Exposure: recent occupational or non-occupational exposure/incident. f. Pregnant female g. Other 5. Obtain informed consent (when applicable). 6. Risk Reduction Behaviors. Educational material given. 7. Patient Reactions/Comments. 8. Explain how the patient will be notified of the result. The above information has been explained to me in a language I can understand. Signature of Inmate Tyler Son Date: 2/4/15 76310-065 Signature of Staff Counselor (b)(6), (b)(7)(C) Date: (b)(6), (b)(7)(C) Inmate Name: Register No.: Institution: File in the Medical Record: Section 6. Prescribed by P6190 Replaces BP-S489.061 of APR DOJ-OGR-00024176",
  "text_blocks": [
    {
      "type": "printed",
      "content": "BP-A0489 JUN 10 U.S. DEPARTMENT OF JUSTICE FEDERAL BUREAU OF PRISONS HIV COUNSELING DOCUMENTATION",
      "position": "header"
    },
    {
      "type": "printed",
      "content": "Directions: Use the following criteria to counsel the patient who is tested for the HIV antibody. Check off each item as they are discussed. Write NA beside any item that is inappropriate to the situation. The reverse side of this form will be utilized to document seronegative and inconclusive test result. Then file in the patient's record, documenting in progress notes that counseling was completed.",
      "position": "top"
    },
    {
      "type": "printed",
      "content": "PRETEST: 1. Explain purpose of session. 2. Explain confidentiality. 3. Explain HIV antibody test. a. What HIV is b. What the test is c. Test Procedure d. Meaning of test results e. Inability of detecting early infection (false negatives) f. Potential need for additional testing g. Significance of a positive test 4. List risk factors/clinical signs: (check all that apply) a. Injecting drug use, sharing drug or tattoo equipment b. Unprotected or multiple sex partners c. Treated for: sexually transmitted infections, hepatitis, or TB d. Clinical s/s: fever or illness of unknown cause, symptoms of AIDS opportunistic infections. e. Exposure: recent occupational or non-occupational exposure/incident. f. Pregnant female g. Other 5. Obtain informed consent (when applicable). 6. Risk Reduction Behaviors. Educational material given. 7. Patient Reactions/Comments. 8. Explain how the patient will be notified of the result.",
      "position": "middle"
    },
    {
      "type": "printed",
      "content": "The above information has been explained to me in a language I can understand.",
      "position": "middle"
    },
    {
      "type": "handwritten",
      "content": "Tyler Son 2/4/15 76310-065",
      "position": "bottom"
    },
    {
      "type": "printed",
      "content": "Signature of Inmate Signature of Staff Counselor Date: Date: Inmate Name: Register No.: Institution: File in the Medical Record: Section 6. Prescribed by P6190 Replaces BP-S489.061 of APR DOJ-OGR-00024176",
      "position": "bottom"
    }
  ],
  "entities": {
    "people": [
      "Tyler Son"
    ],
    "organizations": [
      "U.S. Department of Justice",
      "Federal Bureau of Prisons"
    ],
    "locations": [],
    "dates": [
      "JUN 10",
      "2/4/15"
    ],
    "reference_numbers": [
      "BP-A0489",
      "76310-065",
      "P6190",
      "BP-S489.061",
      "DOJ-OGR-00024176"
    ]
  },
  "additional_notes": "The document contains handwritten signatures and dates. Some information is redacted, marked as '(b)(6), (b)(7)(C)'."
}