{
  "document_metadata": {
    "page_number": "3431",
    "document_number": "DOJ-OGR-00024353",
    "date": "2019/07/10",
    "document_type": "email",
    "has_handwriting": false,
    "has_stamps": false
  },
  "full_text": "Re: Fwd: Bloomberg News - seeking information on Jeffrey Epstein detention\nFrom: [b)(6), (b)(7)(C)]\nTo: Lee Plourde, NYM/ExecAssistant~@bop.gov\nDate: 2019/07/10 09:23\nSubject: Re: Fwd: Bloomberg News - seeking information on Jeffrey Epstein detention\nAttachments: TEXT.htm\nHere is the approved response:\nFor privacy and safety and security reasons, the Bureau of Prisons (BOP) does not release information on an individual inmate's conditions of confinement. However, we can share that Jeffrey Edward Epstein is currently located at the Metropolitan Correctional Center (MCC) New York.\n>>> NYM/Exec Assistant~ 7/10/2019 7:01 AM >>>\n>>> [b)(6), (b)(7)(C) BLOOMBERG/NEWSROOM) [b)(6), (b)(7)(C)@bloomberg.net> 7/9/2019 4:19 PM >>>\nGood afternoon, my name is [b)(6), (b)(7)(C)] and I am a reporter with Bloomberg News. I am working a story about Jeffrey Epstein's detention and I had some questions for the warden regarding his accomodations at the MCC. If someone could please get back to me I can be reached at this email address or by phone at 609-230[b)(6)].\n[b)(6), (b)(7)(C)]\nBloomberg News Legal Reporter\nOffice: (212) 617[b)(6)]\nManhattan federal courthouse: (212) 233-8327\nMobile: (609) 23[b)(6)]\nNew York State Supreme Court: (212) 233-2257 Fax: (646) 268-5217\nEmail [b)(6), (b)(7)(C)]@bloomberg.net\nTwitter [b)(6), (b)(7)(C)]\nPage 3431\nDOJ-OGR-00024353",
  "text_blocks": [
    {
      "type": "printed",
      "content": "Re: Fwd: Bloomberg News - seeking information on Jeffrey Epstein detention\nFrom: [b)(6), (b)(7)(C)]\nTo: Lee Plourde, NYM/ExecAssistant~@bop.gov\nDate: 2019/07/10 09:23\nSubject: Re: Fwd: Bloomberg News - seeking information on Jeffrey Epstein detention\nAttachments: TEXT.htm",
      "position": "top"
    },
    {
      "type": "printed",
      "content": "Here is the approved response:\nFor privacy and safety and security reasons, the Bureau of Prisons (BOP) does not release information on an individual inmate's conditions of confinement. However, we can share that Jeffrey Edward Epstein is currently located at the Metropolitan Correctional Center (MCC) New York.",
      "position": "middle"
    },
    {
      "type": "printed",
      "content": ">>> NYM/Exec Assistant~ 7/10/2019 7:01 AM >>>\n>>> [b)(6), (b)(7)(C) BLOOMBERG/NEWSROOM) [b)(6), (b)(7)(C)@bloomberg.net> 7/9/2019 4:19 PM >>>\nGood afternoon, my name is [b)(6), (b)(7)(C)] and I am a reporter with Bloomberg News. I am working a story about Jeffrey Epstein's detention and I had some questions for the warden regarding his accomodations at the MCC. If someone could please get back to me I can be reached at this email address or by phone at 609-230[b)(6)].",
      "position": "middle"
    },
    {
      "type": "printed",
      "content": "[b)(6), (b)(7)(C)]\nBloomberg News Legal Reporter\nOffice: (212) 617[b)(6)]\nManhattan federal courthouse: (212) 233-8327\nMobile: (609) 23[b)(6)]\nNew York State Supreme Court: (212) 233-2257 Fax: (646) 268-5217\nEmail [b)(6), (b)(7)(C)]@bloomberg.net\nTwitter [b)(6), (b)(7)(C)]",
      "position": "middle"
    },
    {
      "type": "printed",
      "content": "Page 3431\nDOJ-OGR-00024353",
      "position": "bottom"
    }
  ],
  "entities": {
    "people": [
      "Jeffrey Epstein",
      "Jeffrey Edward Epstein",
      "Lee Plourde"
    ],
    "organizations": [
      "Bureau of Prisons",
      "Bloomberg News",
      "Metropolitan Correctional Center"
    ],
    "locations": [
      "New York",
      "Manhattan"
    ],
    "dates": [
      "2019/07/10",
      "7/10/2019",
      "7/9/2019"
    ],
    "reference_numbers": [
      "DOJ-OGR-00024353"
    ]
  },
  "additional_notes": "The document contains redactions marked as [b)(6), (b)(7)(C)]. The document appears to be an email chain discussing Jeffrey Epstein's detention."
}