{
  "document_metadata": {
    "page_number": "2087",
    "document_number": "DOJ-OGR-00023699",
    "date": "2019/07/24",
    "document_type": "email chain",
    "has_handwriting": false,
    "has_stamps": false
  },
  "full_text": "Re: EPSTEIN (b)(6) (b)(7)(C) Application From (b)(6) (b)(7)(C) To (b)(6) (b)(7)(C) Date 2019/07/24 16:24 Subject: Re: EPSTEIN (b)(6) (b)(7)(C) Application Attachments: TEXT.htm, Mime.822 Great, thank you. On Wed, Jul 24, 2019 at 3:54 PM (b)(6) (b)(7)(C) @bop.gov> wrote: Correct. You have to re-clear your background investigation. >> (b)(6) (b)(7)(C) @nyu.edu> 7/24/2019 3:37 PM >>> No worries. Thank you for the update. Just to clarify, this means that until my application is cleared I will be unable to visit Mr. Epstein, correct? On Wed, Jul 24, 2019 at 3:33 PM (b)(6) (b)(7)(C) @bop.gov> wrote: My apologies. I forwarded it yesterday for processing. So we do have it. >>> (b)(6) (b)(7)(C) @nyu.edu> 7/24/2019 3:29 PM >>> Hi (b)(6) (b)(7)(C) Thank you for letting me know and for your response. I was informed by (b)(6) (b)(7)(C) that he had submitted my completed application to the legal department for the inmate Jeffrey Epstein yesterday morning. Does this reflect any of your records? If not, I will be happy to resubmit. If so, can I send the application to you directly via email? Please let me know. Thanks again, (b)(6) (b)(7)(C) On Wed, Jul 24, 2019 at 3:23 PM (b)(6) (b)(7)(C) @bop.gov> wrote: Hi (b)(6) (b)(7)(C) Attached starting at p. 26, please find the application and NCIC check form. Paralegals must submit new applications yearly to retain legal visiting privileges. Please be advised, our records reflected that your last application expired in September 2018. Please complete the attached and return them for processing at your earliest convenience. Thank you, (b)(6) (b)(7)(C) Supervisory Staff Attorney CLC New York Metropolitan Correctional Center Page 2087 DOJ-OGR-00023699",
  "text_blocks": [
    {
      "type": "printed",
      "content": "Re: EPSTEIN (b)(6) (b)(7)(C) Application",
      "position": "header"
    },
    {
      "type": "printed",
      "content": "From (b)(6) (b)(7)(C) To (b)(6) (b)(7)(C) Date 2019/07/24 16:24 Subject: Re: EPSTEIN (b)(6) (b)(7)(C) Application Attachments: TEXT.htm, Mime.822",
      "position": "header"
    },
    {
      "type": "printed",
      "content": "Great, thank you.",
      "position": "top"
    },
    {
      "type": "printed",
      "content": "On Wed, Jul 24, 2019 at 3:54 PM (b)(6) (b)(7)(C) @bop.gov> wrote: Correct. You have to re-clear your background investigation.",
      "position": "top"
    },
    {
      "type": "printed",
      "content": ">> (b)(6) (b)(7)(C) @nyu.edu> 7/24/2019 3:37 PM >>> No worries. Thank you for the update. Just to clarify, this means that until my application is cleared I will be unable to visit Mr. Epstein, correct?",
      "position": "middle"
    },
    {
      "type": "printed",
      "content": "On Wed, Jul 24, 2019 at 3:33 PM (b)(6) (b)(7)(C) @bop.gov> wrote: My apologies. I forwarded it yesterday for processing. So we do have it.",
      "position": "middle"
    },
    {
      "type": "printed",
      "content": ">>> (b)(6) (b)(7)(C) @nyu.edu> 7/24/2019 3:29 PM >>> Hi (b)(6) (b)(7)(C) Thank you for letting me know and for your response. I was informed by (b)(6) (b)(7)(C) that he had submitted my completed application to the legal department for the inmate Jeffrey Epstein yesterday morning. Does this reflect any of your records? If not, I will be happy to resubmit. If so, can I send the application to you directly via email? Please let me know.",
      "position": "middle"
    },
    {
      "type": "printed",
      "content": "Thanks again, (b)(6) (b)(7)(C)",
      "position": "middle"
    },
    {
      "type": "printed",
      "content": "On Wed, Jul 24, 2019 at 3:23 PM (b)(6) (b)(7)(C) @bop.gov> wrote: Hi (b)(6) (b)(7)(C) Attached starting at p. 26, please find the application and NCIC check form. Paralegals must submit new applications yearly to retain legal visiting privileges. Please be advised, our records reflected that your last application expired in September 2018. Please complete the attached and return them for processing at your earliest convenience. Thank you, (b)(6) (b)(7)(C) Supervisory Staff Attorney CLC New York Metropolitan Correctional Center",
      "position": "bottom"
    },
    {
      "type": "printed",
      "content": "Page 2087 DOJ-OGR-00023699",
      "position": "footer"
    }
  ],
  "entities": {
    "people": [
      "Jeffrey Epstein"
    ],
    "organizations": [
      "BOP",
      "CLC New York",
      "Metropolitan Correctional Center",
      "NYU"
    ],
    "locations": [
      "New York"
    ],
    "dates": [
      "2019/07/24",
      "September 2018"
    ],
    "reference_numbers": [
      "DOJ-OGR-00023699"
    ]
  },
  "additional_notes": "The document is an email chain discussing an application related to Jeffrey Epstein. Multiple names and email addresses are redacted."
}