{
  "document_metadata": {
    "page_number": null,
    "document_number": "DOJ-OGR-00023528",
    "date": "July 25, 2019",
    "document_type": "email chain",
    "has_handwriting": false,
    "has_stamps": false
  },
  "full_text": "Please see the attached press release. Thanks Office of Public Affairs Information, Policy and Public Affairs Division Federal Bureau of Prisons (202) 514-6551 - phone (202) 514-6620 - fax >>> (b)(6), (b)(7)(C) @thedailybeast.com> 8/10/2019 9:02 AM >>> Hello, Hearing Jeffrey Epstein commuted suicide at MCC in manhattan if someone could confirm? Thanks (b)(6), (b)(7)(C) Senior Editor, writer The Daily Beast M: 267-257(b)(6) Facebook, Twitter, Instagram: @ (b)(6), (b)(7)(C) From: BOP-IPP/Public Affairs <BOP-IPP/PublicAffairs@bop.gov> Sent: Thursday, July 25, 2019 11:15:50 AM To: (b)(6), (b)(7)(C) @thedailybeast.com> Subject: Re: Jeffrey Epstein (b)(6)... Jeffrey Epstein is currently housed at MCC New York and not in a local hospital as has been reported. As with all inmates, for privacy and security reasons, we do not share information on an inmate's medical status or their conditions of confinement. Thanks Office of Public Affairs Information, Policy and Public Affairs Division Federal Bureau of Prisons (202) 514-6551 - phone (202) 514-6620 - fax >>> (b)(6), (b)(7)(C) @thedailybeast.com> 7/25/2019 9:44 AM >>> Hello, Reaching out about reports that Jeffrey Epstein tried to kill himself in prison/was injured in someway. (b)(6) (b)(7)(C) (b)(6), (b)(7)(C) Senior Editor, writer The Daily Beast M: 267-257-(b)(6) Facebook, Twitter, Instagram: @ (b)(6), (b)(7)(C)",
  "text_blocks": [
    {
      "type": "printed",
      "content": "Please see the attached press release. Thanks Office of Public Affairs Information, Policy and Public Affairs Division Federal Bureau of Prisons (202) 514-6551 - phone (202) 514-6620 - fax",
      "position": "top"
    },
    {
      "type": "printed",
      "content": ">>> (b)(6), (b)(7)(C) @thedailybeast.com> 8/10/2019 9:02 AM >>> Hello, Hearing Jeffrey Epstein commuted suicide at MCC in manhattan if someone could confirm? Thanks (b)(6), (b)(7)(C) Senior Editor, writer The Daily Beast M: 267-257(b)(6) Facebook, Twitter, Instagram: @ (b)(6), (b)(7)(C)",
      "position": "middle"
    },
    {
      "type": "printed",
      "content": "From: BOP-IPP/Public Affairs <BOP-IPP/PublicAffairs@bop.gov> Sent: Thursday, July 25, 2019 11:15:50 AM To: (b)(6), (b)(7)(C) @thedailybeast.com> Subject: Re: Jeffrey Epstein (b)(6)... Jeffrey Epstein is currently housed at MCC New York and not in a local hospital as has been reported. As with all inmates, for privacy and security reasons, we do not share information on an inmate's medical status or their conditions of confinement. Thanks Office of Public Affairs Information, Policy and Public Affairs Division Federal Bureau of Prisons (202) 514-6551 - phone (202) 514-6620 - fax",
      "position": "middle"
    },
    {
      "type": "printed",
      "content": ">>> (b)(6), (b)(7)(C) @thedailybeast.com> 7/25/2019 9:44 AM >>> Hello, Reaching out about reports that Jeffrey Epstein tried to kill himself in prison/was injured in someway. (b)(6) (b)(7)(C) (b)(6), (b)(7)(C) Senior Editor, writer The Daily Beast M: 267-257-(b)(6) Facebook, Twitter, Instagram: @ (b)(6), (b)(7)(C)",
      "position": "bottom"
    }
  ],
  "entities": {
    "people": [
      "Jeffrey Epstein"
    ],
    "organizations": [
      "Federal Bureau of Prisons",
      "The Daily Beast",
      "Office of Public Affairs",
      "Information, Policy and Public Affairs Division"
    ],
    "locations": [
      "MCC New York",
      "Manhattan"
    ],
    "dates": [
      "July 25, 2019",
      "8/10/2019",
      "7/25/2019"
    ],
    "reference_numbers": [
      "(202) 514-6551",
      "(202) 514-6620",
      "DOJ-OGR-00023528"
    ]
  },
  "additional_notes": "The document contains redacted information, indicated by (b)(6) and (b)(7)(C), suggesting sensitive or personal details have been withheld."
}