{
  "document_metadata": {
    "page_number": "772",
    "document_number": "DOJ-OGR-00023557",
    "date": "2019/08/26",
    "document_type": "email",
    "has_handwriting": false,
    "has_stamps": false
  },
  "full_text": "Fwd: Epstein/Washington Post question\nFrom Lee Plourde\nTo (b)(6), (b)(7)(C)\nDate 2019/08/26 15:12\nSubject: Fwd: Epstein/Washington Post question\nAttachments: TEXT.htm\nSent from my Verizon, Samsung Galaxy smartphone\n------- Original message -------\nFrom: (b)(6), (b)(7)(C-1) @washpost.com\nDate: 8/26/19 3:00 PM (GMT-05:00)\nTo: BOP-IPP/PublicAffairs@bop.gov, Lee Plourde (b)(6), (b)(7)(C) @bop.gov\nSubject: Epstein/Washington Post question\n>>> (b)(6), (b)(7)(C) 08/26/2019 15:00 >>>\nHi-\n(b)(6), (b)(7)(C) from the Washington Post here. We are in the process of working on a story about the cameras outside Jeffrey Epstein's cell on the morn\nCan the BOP comment on that assertion? Is the functionality of cameras a larger issue at BOP or MCC? Are you able to say what other cameras might ha\nThank you,\n(b)(6), (b)(7)(C-1) The Washington Post\n(202) 629 (b)(6) cell)\nPage 772\nDOJ-OGR-00023557",
  "text_blocks": [
    {
      "type": "printed",
      "content": "Fwd: Epstein/Washington Post question\nFrom Lee Plourde\nTo (b)(6), (b)(7)(C)\nDate 2019/08/26 15:12\nSubject: Fwd: Epstein/Washington Post question\nAttachments: TEXT.htm",
      "position": "top"
    },
    {
      "type": "printed",
      "content": "Sent from my Verizon, Samsung Galaxy smartphone\n------- Original message -------\nFrom: (b)(6), (b)(7)(C-1) @washpost.com\nDate: 8/26/19 3:00 PM (GMT-05:00)\nTo: BOP-IPP/PublicAffairs@bop.gov, Lee Plourde (b)(6), (b)(7)(C) @bop.gov\nSubject: Epstein/Washington Post question",
      "position": "middle"
    },
    {
      "type": "printed",
      "content": ">>> (b)(6), (b)(7)(C) 08/26/2019 15:00 >>>\nHi-\n(b)(6), (b)(7)(C) from the Washington Post here. We are in the process of working on a story about the cameras outside Jeffrey Epstein's cell on the morn\nCan the BOP comment on that assertion? Is the functionality of cameras a larger issue at BOP or MCC? Are you able to say what other cameras might ha\nThank you,\n(b)(6), (b)(7)(C-1) The Washington Post\n(202) 629 (b)(6) cell)",
      "position": "middle"
    },
    {
      "type": "printed",
      "content": "Page 772\nDOJ-OGR-00023557",
      "position": "footer"
    }
  ],
  "entities": {
    "people": [
      "Lee Plourde",
      "Jeffrey Epstein"
    ],
    "organizations": [
      "Washington Post",
      "BOP",
      "MCC"
    ],
    "locations": [],
    "dates": [
      "2019/08/26",
      "8/26/19"
    ],
    "reference_numbers": [
      "DOJ-OGR-00023557",
      "(202) 629 (b)(6)"
    ]
  },
  "additional_notes": "The document is an email chain with redactions. The email discusses cameras outside Jeffrey Epstein's cell and the functionality of cameras at BOP or MCC."
}