{
  "document_metadata": {
    "page_number": "2077",
    "document_number": "DOJ-OGR-00023695",
    "date": "2019/07/22",
    "document_type": "email chain",
    "has_handwriting": false,
    "has_stamps": false
  },
  "full_text": "Re: Fwd: Client Jeffrey Epstein\nFrom\n(b)(6), (b)(7)(C)\nNYM/Executive Staff (b)(6), (b)(7)(C)\nTo\n(b)(6), (b)(7)(C)\nDate 2019/07/22 14:45\nSubject: Re: Fwd: Client Jeffrey Epstein\nAttachments: TEXT.htm\nI addressed the phone calls with Lt. (b)(6). You may want to check in with him regarding that issue.\n(b)(6), (b)(7)(C)\nChief Psychologist\nU.S. Department of Justice/Federal Bureau of Prisons\nMetropolitan Correctional Center\n150 Park Row\nNew York, New York 10007\nOffice: (646) 836-(b)(6)\nFax: (646) 836-7712\nE-mail: (b)(6)@bop.gov\n>>> (b)(6), (b)(7)(C) 7/22/2019 2:44 PM >>>\nGood afternoon all,\nBelow please find concerns raised by Epstein's attorneys with legal visiting. To summarize, they are requesting:\n1) greater access for Epstein using the bathroom during legal visits;\n2) the 2 social calls he was allegedly promised; and\n3) the ability to eat his lunch meal in attorney conference.\nPlease review and advise so that I can respond. Thank you.\n(b)(6), (b)(7)(C)\nSupervisory Staff Attorney\nCLC New York\nMetropolitan Correctional Center\n150 Park Row\nNew York, New York 10007\np: (646)836-(b)(6)\nf: (646)836-7665\n(b)(6), (b)(7)(C)@gmail.com> 7/22/2019 12:34 PM >>>\nGood morning Mr (b)(6), (b)(7)(C)\nI tried calling you earlier. My client, Jeffrey Epstein (76318-054) informed me that he had a meeting last",
  "text_blocks": [
    {
      "type": "printed",
      "content": "Re: Fwd: Client Jeffrey Epstein",
      "position": "header"
    },
    {
      "type": "printed",
      "content": "From (b)(6), (b)(7)(C) NYM/Executive Staff (b)(6), (b)(7)(C) To (b)(6), (b)(7)(C) Date 2019/07/22 14:45 Subject: Re: Fwd: Client Jeffrey Epstein Attachments: TEXT.htm",
      "position": "header"
    },
    {
      "type": "printed",
      "content": "I addressed the phone calls with Lt. (b)(6). You may want to check in with him regarding that issue.",
      "position": "body"
    },
    {
      "type": "printed",
      "content": "(b)(6), (b)(7)(C) Chief Psychologist U.S. Department of Justice/Federal Bureau of Prisons Metropolitan Correctional Center 150 Park Row New York, New York 10007 Office: (646) 836-(b)(6) Fax: (646) 836-7712 E-mail: (b)(6)@bop.gov",
      "position": "body"
    },
    {
      "type": "printed",
      "content": ">>> (b)(6), (b)(7)(C) 7/22/2019 2:44 PM >>> Good afternoon all, Below please find concerns raised by Epstein's attorneys with legal visiting. To summarize, they are requesting: 1) greater access for Epstein using the bathroom during legal visits; 2) the 2 social calls he was allegedly promised; and 3) the ability to eat his lunch meal in attorney conference. Please review and advise so that I can respond. Thank you.",
      "position": "body"
    },
    {
      "type": "printed",
      "content": "(b)(6), (b)(7)(C) Supervisory Staff Attorney CLC New York Metropolitan Correctional Center 150 Park Row New York, New York 10007 p: (646)836-(b)(6) f: (646)836-7665",
      "position": "body"
    },
    {
      "type": "printed",
      "content": "(b)(6), (b)(7)(C)@gmail.com> 7/22/2019 12:34 PM >>> Good morning Mr (b)(6), (b)(7)(C) I tried calling you earlier. My client, Jeffrey Epstein (76318-054) informed me that he had a meeting last",
      "position": "body"
    },
    {
      "type": "printed",
      "content": "Page 2077 DOJ-OGR-00023695",
      "position": "footer"
    }
  ],
  "entities": {
    "people": [
      "Jeffrey Epstein"
    ],
    "organizations": [
      "U.S. Department of Justice",
      "Federal Bureau of Prisons",
      "Metropolitan Correctional Center",
      "CLC New York"
    ],
    "locations": [
      "New York"
    ],
    "dates": [
      "2019/07/22"
    ],
    "reference_numbers": [
      "76318-054",
      "DOJ-OGR-00023695"
    ]
  },
  "additional_notes": "The document is an email chain discussing concerns raised by Jeffrey Epstein's attorneys regarding his treatment during legal visits. The emails are redacted, with names, email addresses, and phone numbers obscured."
}