{
  "document_metadata": {
    "page_number": "626",
    "document_number": "DOJ-OGR-00025079",
    "date": "Friday August 09, 2019",
    "document_type": "Daily Assignment Roster",
    "has_handwriting": true,
    "has_stamps": false
  },
  "full_text": "Page 626 MCC NEW YORK NEW YORK, NY Daily Assignment Roster Friday August 09, 2019 Page 1 Post Split Shift 2 00:00 - 08:00 3 06:00 - 14:00 6 07:00 - 15:00 8 08:00 - 16:00 9 12:00 - 20:00 10 14:00 - 22:00 12 16:00 - 00:00 CAPTAIN (b)(6); (b)(7)(C); (b)(7)(F) (b)(6); (b)(7)(C); (b)(7)(F) (b)(6); (b)(7)(C); (b)(7)(F) (b)(6); (b)(7)(C); (b)(7)(F) (b)(6); (b)(7)(C); (b)(7)(F) CAPTAIN SEC OPS LT ACT LT SHU LT SIS LT SIS LT #2 SIA SIS TECH #1 PHONE MONITOR SEC OFFICER #1 SEC OFFICER #2 TOOL ROOM SEARCH OFFICER 2 SALLY OFF 3 SALLY OFF LOBBY CONTROL #1 CONTROL #2 INTERNAL INTERNAL #2 ATTY CONF UNIT 2 UNIT 3 5 NORTH 5 NORTH Y 5 SOUTH 7 NORTH 7 SOUTH 9 NORTH SHU #1 SHU #2 SHU #3 SHU #4 1/9/2020 10:39:17 AM DOJ-OGR-00025079",
  "text_blocks": [
    {
      "type": "printed",
      "content": "MCC NEW YORK NEW YORK, NY Daily Assignment Roster",
      "position": "header"
    },
    {
      "type": "printed",
      "content": "Friday August 09, 2019 Page 1",
      "position": "header"
    },
    {
      "type": "printed",
      "content": "Post Split Shift 2 00:00 - 08:00 3 06:00 - 14:00 6 07:00 - 15:00 8 08:00 - 16:00 9 12:00 - 20:00 10 14:00 - 22:00 12 16:00 - 00:00",
      "position": "header"
    },
    {
      "type": "printed",
      "content": "CAPTAIN (b)(6); (b)(7)(C); (b)(7)(F) (b)(6); (b)(7)(C); (b)(7)(F) (b)(6); (b)(7)(C); (b)(7)(F) (b)(6); (b)(7)(C); (b)(7)(F) (b)(6); (b)(7)(C); (b)(7)(F)",
      "position": "body"
    },
    {
      "type": "printed",
      "content": "CAPTAIN SEC OPS LT ACT LT SHU LT SIS LT SIS LT #2 SIA SIS TECH #1 PHONE MONITOR SEC OFFICER #1 SEC OFFICER #2 TOOL ROOM SEARCH OFFICER 2 SALLY OFF 3 SALLY OFF LOBBY CONTROL #1 CONTROL #2 INTERNAL INTERNAL #2 ATTY CONF UNIT 2 UNIT 3 5 NORTH 5 NORTH Y 5 SOUTH 7 NORTH 7 SOUTH 9 NORTH SHU #1 SHU #2 SHU #3 SHU #4",
      "position": "body"
    },
    {
      "type": "handwritten",
      "content": "Y",
      "position": "body"
    },
    {
      "type": "printed",
      "content": "1/9/2020 10:39:17 AM",
      "position": "footer"
    },
    {
      "type": "printed",
      "content": "DOJ-OGR-00025079",
      "position": "footer"
    }
  ],
  "entities": {
    "people": [],
    "organizations": [
      "MCC NEW YORK"
    ],
    "locations": [
      "NEW YORK, NY"
    ],
    "dates": [
      "Friday August 09, 2019",
      "1/9/2020"
    ],
    "reference_numbers": [
      "DOJ-OGR-00025079"
    ]
  },
  "additional_notes": "The document appears to be a Daily Assignment Roster for MCC NEW YORK on Friday August 09, 2019. The document contains redacted names and some handwritten text. The document is in good condition with no visible damage or redactions other than the redacted names."
}