{
  "document_metadata": {
    "page_number": "893",
    "document_number": "DOJ-OGR-00025182",
    "date": "2019/08/25",
    "document_type": "email",
    "has_handwriting": false,
    "has_stamps": false
  },
  "full_text": "Page 893\nEpstein Reconstruction 76318-054 draft5\nFrom [b(6); (b)(7)(C)]\nTo [b(6); (b)(7)(C)] Hugh Hurwitz, Jeffrey Keller, James Wills [b(6); (b)(7)(C)]\n[b(6); (b)(7)(C)] Michael Carvajal\nDate 2019/08/25 17:24\nSubject: Epstein Reconstruction 76318-054 draft5\nAttachments: TEXT.htm, Epstein Reconstruction 76318-054 draft5.docx, Nagle, Robert.vcf\nMr. Hurwitz, Mr. Carvajal, Mr. Wills, Mr. Keller and [b(6); (b)(7)(C)]\nI have done some additional edits to the Epstein Reconstruction. Please review and return with your comments. This remain a working document and should not be distributed beyond yourselves.\nThanks for your consideration,\n[b(6); (b)(7)(C)]\nPsy.D.\nNational Suicide Prevention Coordinator\nFederal Bureau of Prisons\nPsychology Services Branch\n320 First Street, NW\nWashington, DC, DC 20534\n202-598 [b(6); (b)(7)(C)]\nPage 1909\nDOJ-OGR-00025182",
  "text_blocks": [
    {
      "type": "printed",
      "content": "Epstein Reconstruction 76318-054 draft5",
      "position": "top"
    },
    {
      "type": "printed",
      "content": "From [b(6); (b)(7)(C)]",
      "position": "top"
    },
    {
      "type": "printed",
      "content": "To [b(6); (b)(7)(C)] Hugh Hurwitz, Jeffrey Keller, James Wills [b(6); (b)(7)(C)]",
      "position": "top"
    },
    {
      "type": "printed",
      "content": "[b(6); (b)(7)(C)] Michael Carvajal",
      "position": "top"
    },
    {
      "type": "printed",
      "content": "Date 2019/08/25 17:24",
      "position": "top"
    },
    {
      "type": "printed",
      "content": "Subject: Epstein Reconstruction 76318-054 draft5",
      "position": "top"
    },
    {
      "type": "printed",
      "content": "Attachments: TEXT.htm, Epstein Reconstruction 76318-054 draft5.docx, Nagle, Robert.vcf",
      "position": "top"
    },
    {
      "type": "printed",
      "content": "Mr. Hurwitz, Mr. Carvajal, Mr. Wills, Mr. Keller and [b(6); (b)(7)(C)]",
      "position": "middle"
    },
    {
      "type": "printed",
      "content": "I have done some additional edits to the Epstein Reconstruction. Please review and return with your comments. This remain a working document and should not be distributed beyond yourselves.",
      "position": "middle"
    },
    {
      "type": "printed",
      "content": "Thanks for your consideration,",
      "position": "middle"
    },
    {
      "type": "printed",
      "content": "[b(6); (b)(7)(C)] Psy.D.",
      "position": "middle"
    },
    {
      "type": "printed",
      "content": "National Suicide Prevention Coordinator",
      "position": "middle"
    },
    {
      "type": "printed",
      "content": "Federal Bureau of Prisons",
      "position": "middle"
    },
    {
      "type": "printed",
      "content": "Psychology Services Branch",
      "position": "middle"
    },
    {
      "type": "printed",
      "content": "320 First Street, NW",
      "position": "middle"
    },
    {
      "type": "printed",
      "content": "Washington, DC, DC 20534",
      "position": "middle"
    },
    {
      "type": "printed",
      "content": "202-598 [b(6); (b)(7)(C)]",
      "position": "middle"
    },
    {
      "type": "printed",
      "content": "Page 1909",
      "position": "bottom"
    },
    {
      "type": "printed",
      "content": "DOJ-OGR-00025182",
      "position": "bottom"
    }
  ],
  "entities": {
    "people": [
      "Hugh Hurwitz",
      "Jeffrey Keller",
      "James Wills",
      "Michael Carvajal"
    ],
    "organizations": [
      "Federal Bureau of Prisons"
    ],
    "locations": [
      "Washington, DC"
    ],
    "dates": [
      "2019/08/25"
    ],
    "reference_numbers": [
      "76318-054",
      "DOJ-OGR-00025182"
    ]
  },
  "additional_notes": "The document contains multiple redactions marked as [b(6); (b)(7)(C)]. The document appears to be an email discussing edits to a document related to Epstein Reconstruction."
}