{
  "document_metadata": {
    "page_number": "518",
    "document_number": "76318-054",
    "date": "08/10/2019",
    "document_type": "Inmate Information Form",
    "has_handwriting": false,
    "has_stamps": false
  },
  "full_text": "Page 518\nReg #: 76318-054 Inmate Name: EPSTEIN, JEFFREY EDWARD\nSENSITIVE BUT UNCLASSIFIED - This information is confidential and must be appropriately safeguarded.\nLimitations/Restrictions/Diets: Cell: lower bunk --- 10/09/2019 Cleared for Food Service: Yes Other diet restrictions: FISH ALLERGIES. --- 07/30/2020\nComments:\nAllergies No Known Allergies\nDevices / Equipment C-Pap\nTravel: Direct Travel: No Travel Restrictions: None\nUNIVERSAL PRECAUTIONS OBSERVED WHEN TRANSPORTING ANY INMATE:\nTransfer From Institution: NEW YORK MCC Phone Number: 6468366300 Address 1: 150 PARK ROW Address 2: City/State/Zip: NEW YORK, New York 10007\nName/Title of Person Completing Form: (b)(6); (b)(7)(C) RN Date: 08/10/2019\nInmate Name: EPSTEIN, JEFFREY EDWARD Reg #: 76318-054 DOB: 01/20/1953 Sex: M\nGenerated 08/10/2019 07:00 by (b)(6); (b)(7)(C) RN Bureau of Prisons - NYM Page 2 of 2 DOJ-OGR-00024975",
  "text_blocks": [
    {
      "type": "printed",
      "content": "Page 518",
      "position": "header"
    },
    {
      "type": "printed",
      "content": "Reg #: 76318-054 Inmate Name: EPSTEIN, JEFFREY EDWARD",
      "position": "header"
    },
    {
      "type": "printed",
      "content": "SENSITIVE BUT UNCLASSIFIED - This information is confidential and must be appropriately safeguarded.",
      "position": "header"
    },
    {
      "type": "printed",
      "content": "Limitations/Restrictions/Diets: Cell: lower bunk --- 10/09/2019 Cleared for Food Service: Yes Other diet restrictions: FISH ALLERGIES. --- 07/30/2020",
      "position": "body"
    },
    {
      "type": "printed",
      "content": "Comments:",
      "position": "body"
    },
    {
      "type": "printed",
      "content": "Allergies No Known Allergies",
      "position": "body"
    },
    {
      "type": "printed",
      "content": "Devices / Equipment C-Pap",
      "position": "body"
    },
    {
      "type": "printed",
      "content": "Travel: Direct Travel: No Travel Restrictions: None",
      "position": "body"
    },
    {
      "type": "printed",
      "content": "UNIVERSAL PRECAUTIONS OBSERVED WHEN TRANSPORTING ANY INMATE:",
      "position": "body"
    },
    {
      "type": "printed",
      "content": "Transfer From Institution: NEW YORK MCC Phone Number: 6468366300 Address 1: 150 PARK ROW Address 2: City/State/Zip: NEW YORK, New York 10007",
      "position": "body"
    },
    {
      "type": "handwritten",
      "content": "(b)(6); (b)(7)(C)",
      "position": "body"
    },
    {
      "type": "printed",
      "content": "Name/Title of Person Completing Form: RN Date: 08/10/2019",
      "position": "body"
    },
    {
      "type": "printed",
      "content": "Inmate Name: EPSTEIN, JEFFREY EDWARD Reg #: 76318-054 DOB: 01/20/1953 Sex: M",
      "position": "body"
    },
    {
      "type": "printed",
      "content": "Generated 08/10/2019 07:00 by (b)(6); (b)(7)(C) RN Bureau of Prisons - NYM Page 2 of 2 DOJ-OGR-00024975",
      "position": "footer"
    }
  ],
  "entities": {
    "people": [
      "JEFFREY EDWARD EPSTEIN"
    ],
    "organizations": [
      "Bureau of Prisons",
      "NEW YORK MCC"
    ],
    "locations": [
      "NEW YORK",
      "New York"
    ],
    "dates": [
      "10/09/2019",
      "07/30/2020",
      "08/10/2019",
      "01/20/1953"
    ],
    "reference_numbers": [
      "76318-054",
      "6468366300",
      "10007",
      "DOJ-OGR-00024975"
    ]
  },
  "additional_notes": "The document contains sensitive information about an inmate, Jeffrey Edward Epstein, including his medical history and travel restrictions. The document is marked 'SENSITIVE BUT UNCLASSIFIED' and contains redactions."
}