{
  "document_metadata": {
    "page_number": "1252",
    "document_number": "DOJ-OGR-00025446",
    "date": "2019/08/12",
    "document_type": "email",
    "has_handwriting": false,
    "has_stamps": false
  },
  "full_text": "Page 1252 Fwd: Re: Need you to reconstruct 292 data for Inmate Epstein, 76318-054 From [b(6); (b)(7)(C) To [b(6); (b)(7)(C) onya Thompson Date 2019/08/12 12:20 Subject: Fwd: Re: Need you to reconstruct 292 data for Inmate Epstein, 76318-054 TEXT.htm, Epstein [b(6); (b)(7)(C) 6318-054_20190804-20190810.pdf, Epstein [b(6); (b)(7)(C) 76318-054_20190729-20190803.pdf, Epstein- [b(6); (b)(7)(C) 76318-054_20190721-20190728.pdf, Epstein [b(6); (b)(7)(C) 76318-054_20190714-20190720.pdf, Epstein [b(6); (b)(7)(C) 76318-054_20190707-20190713.pdf Attachments: FYI, See attached. > [b(6); (b)(7)(C) 8/12/2019 11:37 AM >>> [b(6); (b)(7)(C) I attached Epstein 292 forms from 7/7-2019 to 8/10/2019. During this periods, Epstein was moved in and out from SHU 3 times. I looked into his SHU history records and filled SHU administration data into 292 history reports. Thanks, [b(6); (b)(7)(C) >>> [b(6); (b)(7)(C) /11/2019 7:35 PM >>> [b(6); (b)(7)(C) As you are probably aware inmate Epstein was found dead in his SHU cell in NYM this past Saturday morning. We need to reconstruct as best we can inmate Epstein's 292 record for the week prior to his death (Monday, August 5, 2019 through Friday, August 9, 2019). Please make this your number one priority and e-mail me the results when you are done. This is a time critical task. Thanks. Page 3612 DOJ-OGR-00025446",
  "text_blocks": [
    {
      "type": "printed",
      "content": "Fwd: Re: Need you to reconstruct 292 data for Inmate Epstein, 76318-054",
      "position": "top"
    },
    {
      "type": "printed",
      "content": "From [b(6); (b)(7)(C) To [b(6); (b)(7)(C) onya Thompson Date 2019/08/12 12:20 Subject: Fwd: Re: Need you to reconstruct 292 data for Inmate Epstein, 76318-054",
      "position": "top"
    },
    {
      "type": "printed",
      "content": "TEXT.htm, Epstein [b(6); (b)(7)(C) 6318-054_20190804-20190810.pdf, Epstein [b(6); (b)(7)(C) 76318-054_20190729-20190803.pdf, Epstein- [b(6); (b)(7)(C) 76318-054_20190721-20190728.pdf, Epstein [b(6); (b)(7)(C) 76318-054_20190714-20190720.pdf, Epstein [b(6); (b)(7)(C) 76318-054_20190707-20190713.pdf",
      "position": "top"
    },
    {
      "type": "printed",
      "content": "FYI, See attached.",
      "position": "middle"
    },
    {
      "type": "printed",
      "content": "I attached Epstein 292 forms from 7/7-2019 to 8/10/2019. During this periods, Epstein was moved in and out from SHU 3 times. I looked into his SHU history records and filled SHU administration data into 292 history reports.",
      "position": "middle"
    },
    {
      "type": "printed",
      "content": "Thanks, [b(6); (b)(7)(C)",
      "position": "middle"
    },
    {
      "type": "printed",
      "content": "As you are probably aware inmate Epstein was found dead in his SHU cell in NYM this past Saturday morning. We need to reconstruct as best we can inmate Epstein's 292 record for the week prior to his death (Monday, August 5, 2019 through Friday, August 9, 2019). Please make this your number one priority and e-mail me the results when you are done. This is a time critical task.",
      "position": "bottom"
    },
    {
      "type": "printed",
      "content": "Thanks.",
      "position": "bottom"
    }
  ],
  "entities": {
    "people": [
      "Epstein",
      "Tonya Thompson"
    ],
    "organizations": [],
    "locations": [
      "NYM"
    ],
    "dates": [
      "2019/08/12",
      "7/7-2019",
      "8/10/2019",
      "August 5, 2019",
      "August 9, 2019"
    ],
    "reference_numbers": [
      "76318-054",
      "292",
      "DOJ-OGR-00025446"
    ]
  },
  "additional_notes": "The document appears to be an email chain discussing the reconstruction of inmate Epstein's 292 data. The email contains several redacted names and is related to an investigation or administrative task following Epstein's death."
}