{
  "document_metadata": {
    "page_number": "6435",
    "document_number": "DOJ-OGR-00024412",
    "date": "2019/08/15",
    "document_type": "email",
    "has_handwriting": false,
    "has_stamps": false
  },
  "full_text": "FYI - I'm answering the Hill re: NY Daily News article that published on release of IM Matthews From Lee Plourde To [redacted] Date 2019/08/15 15:25 Subject: FYI - I'm answering the Hill re: NY Daily News article that published on release of [redacted] Attachments: TEXT.htm Thank you [redacted] 8/15/2019 3:24 PM >>> You don't need to answer this Hill reporter below (I will). [redacted] Public Information Office Federal Bureau of Prisons (202) 353 [redacted] [redacted] 8/15/2019 3:11 PM >>> [redacted] Story: http://www.nydailynews.com/new-york/ny-inmate-at-mcc-mistakenly-released-after-jeffrey-epstein-suicide-20190815-h2r76qxnfcodp225goyte6y7a-story.html Reporter: [redacted] the Hill Question: My name's [redacted] and I'm a reporter with The Hill. I'm reaching out to see if the BOP has any comment on this report (https://www.nydailynews.com/new-york/ny-inmate-at-mcc-mistakenly-released-after-jeffrey-epstein-suicide-20190815-h2r76qxnfcodp225goyte6y7a-story.html) that convicted bank robber [redacted] as mistakenly released on Aug. 7; he is still listed as \"released\" in the \"find an inmate\" portal as of 10:21 on Thursday. Proposed Response: [redacted] Page 6435 DOJ-OGR-00024412",
  "text_blocks": [
    {
      "type": "printed",
      "content": "FYI - I'm answering the Hill re: NY Daily News article that published on release of IM Matthews From Lee Plourde To [redacted] Date 2019/08/15 15:25 Subject: FYI - I'm answering the Hill re: NY Daily News article that published on release of [redacted] Attachments: TEXT.htm Thank you",
      "position": "top"
    },
    {
      "type": "printed",
      "content": "[redacted] 8/15/2019 3:24 PM >>> You don't need to answer this Hill reporter below (I will). [redacted]",
      "position": "middle"
    },
    {
      "type": "printed",
      "content": "Public Information Office Federal Bureau of Prisons (202) 353 [redacted]",
      "position": "middle"
    },
    {
      "type": "printed",
      "content": "[redacted] 8/15/2019 3:11 PM >>> [redacted]",
      "position": "middle"
    },
    {
      "type": "printed",
      "content": "Story: http://www.nydailynews.com/new-york/ny-inmate-at-mcc-mistakenly-released-after-jeffrey-epstein-suicide-20190815-h2r76qxnfcodp225goyte6y7a-story.html",
      "position": "middle"
    },
    {
      "type": "printed",
      "content": "Reporter: [redacted] the Hill",
      "position": "middle"
    },
    {
      "type": "printed",
      "content": "Question: My name's [redacted] and I'm a reporter with The Hill. I'm reaching out to see if the BOP has any comment on this report (https://www.nydailynews.com/new-york/ny-inmate-at-mcc-mistakenly-released-after-jeffrey-epstein-suicide-20190815-h2r76qxnfcodp225goyte6y7a-story.html) that convicted bank robber [redacted] as mistakenly released on Aug. 7; he is still listed as \"released\" in the \"find an inmate\" portal as of 10:21 on Thursday.",
      "position": "middle"
    },
    {
      "type": "printed",
      "content": "Proposed Response: [redacted]",
      "position": "bottom"
    },
    {
      "type": "printed",
      "content": "Page 6435 DOJ-OGR-00024412",
      "position": "footer"
    }
  ],
  "entities": {
    "people": [
      "Lee Plourde",
      "Jeffrey Epstein"
    ],
    "organizations": [
      "The Hill",
      "NY Daily News",
      "Federal Bureau of Prisons",
      "BOP"
    ],
    "locations": [
      "New York"
    ],
    "dates": [
      "2019/08/15",
      "2019/08/07"
    ],
    "reference_numbers": [
      "DOJ-OGR-00024412"
    ]
  },
  "additional_notes": "The document is a redacted email chain discussing a news article about an inmate mistakenly released after Jeffrey Epstein's suicide. Multiple sections are redacted."
}