{
  "document_metadata": {
    "page_number": "838",
    "document_number": "DOJ-OGR-00025149",
    "date": "2019/07/24",
    "document_type": "email",
    "has_handwriting": false,
    "has_stamps": false
  },
  "full_text": "Page 838\nRe: EPSTEIN Application\nFrom [b)(6); (b)(7)(C)\nTo [b)(6); (b)(7)(C)\nDate 2019/07/24 15:54\nSubject: Re: EPSTEIN [b)(6); (b)(7)(C) Application\nAttachments: TEXT.htm\nCorrect. You have to re-clear your background investigation.\n>> [b)(6); (b)(7)(C) @nyu.edu> 7/24/2019 3:37 PM >>>\nNo worries. Thank you for the update.\nJust to clarify, this means that until my application is cleared I will be unable to visit Mr. Epstein, correct?\nOn Wed, Jul 24, 2019 at 3:33 PM [b)(6); (b)(7)(C) @bop.gov> wrote:\nMy apologies. I forwarded it yesterday for processing. So we do have it.\n>> [b)(6); (b)(7)(C) @nyu.edu> 7/24/2019 3:29 PM >>>\nHi [b)(6); (b)(7)(C)\nThank you for letting me know and for your response.\nI was informed by [b)(6); (b)(7)(C) that he had submitted my completed application to the legal department for the inmate Jeffrey Epstein yesterday morning. Does this reflect any of your records? If not, I will be happy to resubmit. If so, can I send the application to you directly via email? Please let me know.\nThanks again,\n[b)(6); (b)(7)(C)\nOn Wed, Jul 24, 2019 at 3:23 PM [b)(6); (b)(7)(C) @bop.gov> wrote:\nHi [b)(6); (b)(7)(C)\nAttached starting at p. 26, please find the application and NCIC check form. Paralegals must submit new applications yearly to retain legal visiting privileges. Please be advised, our records reflected that your last application expired in September 2018. Please complete the attached and return them for processing at your earliest convenience.\nThank you,\n[b)(6); (b)(7)(C)\nSupervisory Staff Attorney\nCLC New York\nMetropolitan Correctional Center\n150 Park Row\nNew York, New York 10007\np: (646)836[b)(6); (b)(7)(C)\nf: (646)836-7665\nPage 1525\nDOJ-OGR-00025149",
  "text_blocks": [
    {
      "type": "printed",
      "content": "Re: EPSTEIN Application",
      "position": "header"
    },
    {
      "type": "printed",
      "content": "From [b)(6); (b)(7)(C)\nTo [b)(6); (b)(7)(C)\nDate 2019/07/24 15:54\nSubject: Re: EPSTEIN [b)(6); (b)(7)(C) Application\nAttachments: TEXT.htm",
      "position": "header"
    },
    {
      "type": "printed",
      "content": "Correct. You have to re-clear your background investigation.",
      "position": "body"
    },
    {
      "type": "printed",
      "content": ">> [b)(6); (b)(7)(C) @nyu.edu> 7/24/2019 3:37 PM >>>\nNo worries. Thank you for the update.",
      "position": "body"
    },
    {
      "type": "printed",
      "content": "Just to clarify, this means that until my application is cleared I will be unable to visit Mr. Epstein, correct?",
      "position": "body"
    },
    {
      "type": "printed",
      "content": "On Wed, Jul 24, 2019 at 3:33 PM [b)(6); (b)(7)(C) @bop.gov> wrote:\nMy apologies. I forwarded it yesterday for processing. So we do have it.",
      "position": "body"
    },
    {
      "type": "printed",
      "content": ">> [b)(6); (b)(7)(C) @nyu.edu> 7/24/2019 3:29 PM >>>\nHi [b)(6); (b)(7)(C)\nThank you for letting me know and for your response.",
      "position": "body"
    },
    {
      "type": "printed",
      "content": "I was informed by [b)(6); (b)(7)(C) that he had submitted my completed application to the legal department for the inmate Jeffrey Epstein yesterday morning. Does this reflect any of your records? If not, I will be happy to resubmit. If so, can I send the application to you directly via email? Please let me know.",
      "position": "body"
    },
    {
      "type": "printed",
      "content": "Thanks again,\n[b)(6); (b)(7)(C)",
      "position": "body"
    },
    {
      "type": "printed",
      "content": "On Wed, Jul 24, 2019 at 3:23 PM [b)(6); (b)(7)(C) @bop.gov> wrote:\nHi [b)(6); (b)(7)(C)",
      "position": "body"
    },
    {
      "type": "printed",
      "content": "Attached starting at p. 26, please find the application and NCIC check form. Paralegals must submit new applications yearly to retain legal visiting privileges. Please be advised, our records reflected that your last application expired in September 2018. Please complete the attached and return them for processing at your earliest convenience.",
      "position": "body"
    },
    {
      "type": "printed",
      "content": "Thank you,\n[b)(6); (b)(7)(C)\nSupervisory Staff Attorney\nCLC New York\nMetropolitan Correctional Center\n150 Park Row\nNew York, New York 10007\np: (646)836[b)(6); (b)(7)(C)\nf: (646)836-7665",
      "position": "footer"
    }
  ],
  "entities": {
    "people": [
      "Jeffrey Epstein",
      "EPSTEIN"
    ],
    "organizations": [
      "CLC New York",
      "Metropolitan Correctional Center"
    ],
    "locations": [
      "New York"
    ],
    "dates": [
      "2019/07/24",
      "September 2018"
    ],
    "reference_numbers": [
      "DOJ-OGR-00025149"
    ]
  },
  "additional_notes": "The document is an email chain discussing an application related to Jeffrey Epstein. Multiple names and email addresses are redacted."
}