{
  "document_metadata": {
    "page_number": "1299",
    "document_number": "DOJ-OGR-00025489",
    "date": "2019/08/12",
    "document_type": "Email",
    "has_handwriting": false,
    "has_stamps": false
  },
  "full_text": "Page 1299\nRe: Psych Observation 7/8/19 6 pm until 7/10/19 at 9 am re: Epstein, Jeffrey Edward, Reg. No. 73618-054\nFrom Charisma Edge\nTo Ray Ormond\nDate 2019/08/12 15:59\nSubject: Re: Psych Observation 7/8/19 6 pm until 7/10/19 at 9 am re: Epstein, Jeffrey Edward, Reg. No. 73618-054\nAttachments: TEXT.htm, Charisma Edge.vcf\nPlease check your email. I resent the 4 emails. The attachments appear fine on my end. Please advise if the attachments are clear.\nCharisma Edge\nAssociate Warden\nMCC New York\n150 Park Row\nNew York, NY 10007\n646-836-6300 ext\n\n\n>>> Ray Ormond  8/12/2019 3:35 PM >>>\nWhen I try to open it says \"document cannot be opened because it is corrupted or damaged\"\nSent from my Verizon, Samsung Galaxy smartphone\n---------- Original message ---------\nFrom: \"N'Diaye, Lamine (Charisma Edge)\" \nDate: 8/12/19 3:33 PM (GMT-05:00)\nTo: Ray Ormond \nCc: Lamine N'Diaye \nSubject: Psych Observation 7/8/19 6 pm until 7/10/19 at 9 am re: Epstein, Jeffrey Edward, Reg. No. 73618-054\n>>> \"N'Diaye, Lamine (Charisma Edge)\" 08/12/2019 15:33 >>>\nPsych Observation 7/8/19 6 pm until 7/10/19 at 9 am (I/M companion utilized)\nPage 4169\nDOJ-OGR-00025489",
  "text_blocks": [
    {
      "type": "printed",
      "content": "Re: Psych Observation 7/8/19 6 pm until 7/10/19 at 9 am re: Epstein, Jeffrey Edward, Reg. No. 73618-054",
      "position": "top"
    },
    {
      "type": "printed",
      "content": "From: Charisma Edge\nTo: Ray Ormond\nDate: 2019/08/12 15:59\nSubject: Re: Psych Observation 7/8/19 6 pm until 7/10/19 at 9 am re: Epstein, Jeffrey Edward, Reg. No. 73618-054\nAttachments: TEXT.htm, Charisma Edge.vcf",
      "position": "top"
    },
    {
      "type": "printed",
      "content": "Please check your email. I resent the 4 emails. The attachments appear fine on my end. Please advise if the attachments are clear.",
      "position": "middle"
    },
    {
      "type": "printed",
      "content": "Charisma Edge\nAssociate Warden\nMCC New York\n150 Park Row\nNew York, NY 10007\n646-836-6300 ext",
      "position": "middle"
    },
    {
      "type": "printed",
      "content": ">>> Ray Ormond  8/12/2019 3:35 PM >>>\nWhen I try to open it says \"document cannot be opened because it is corrupted or damaged\"",
      "position": "middle"
    },
    {
      "type": "printed",
      "content": "Sent from my Verizon, Samsung Galaxy smartphone\n---------- Original message ---------\nFrom: \"N'Diaye, Lamine (Charisma Edge)\" \nDate: 8/12/19 3:33 PM (GMT-05:00)\nTo: Ray Ormond \nCc: Lamine N'Diaye \nSubject: Psych Observation 7/8/19 6 pm until 7/10/19 at 9 am re: Epstein, Jeffrey Edward, Reg. No. 73618-054",
      "position": "middle"
    },
    {
      "type": "printed",
      "content": ">>> \"N'Diaye, Lamine (Charisma Edge)\" 08/12/2019 15:33 >>>\nPsych Observation 7/8/19 6 pm until 7/10/19 at 9 am (I/M companion utilized)",
      "position": "bottom"
    },
    {
      "type": "printed",
      "content": "Page 4169\nDOJ-OGR-00025489",
      "position": "footer"
    }
  ],
  "entities": {
    "people": [
      "Charisma Edge",
      "Ray Ormond",
      "Jeffrey Edward Epstein",
      "Lamine N'Diaye"
    ],
    "organizations": [
      "MCC New York",
      "BOP"
    ],
    "locations": [
      "New York"
    ],
    "dates": [
      "7/8/19",
      "7/10/19",
      "2019/08/12",
      "8/12/2019"
    ],
    "reference_numbers": [
      "73618-054",
      "DOJ-OGR-00025489"
    ]
  },
  "additional_notes": "The document appears to be an email chain discussing a psychological observation report regarding Jeffrey Epstein. The email contains redactions of personal contact information."
}