{
  "document_metadata": {
    "page_number": "12753",
    "document_number": "DOJ-OGR-00023948",
    "date": "2019/07/07",
    "document_type": "email",
    "has_handwriting": false,
    "has_stamps": false
  },
  "full_text": "RE: counsel having difficulty meeting with client\nFrom\n(b)(6), (b)(7)(C)\n(USANYS)\nTo\n(b)(6), (b)(7)(C)\nDate\n2019/07/07 18:18\nSubject:\nRE: counsel having difficulty meeting with client\nAttachments:\nTEXT.htm, Mime.822\nMassachusetts\nFrom\n(b)(6), (b)(7)(C)\n@bop.gov>\nSent: Sunday, July 07, 2019 18:18\nTo\n(b)(6), (b)(7)(C)\n@bop.gov>\n(b)(6), (b)(7)(C)\n(USANYS)\n(b)(6), (b)(7)(C)\n@usa.doj.gov>\nSubject: Re: counsel having difficulty meeting with client\nSorry\n(b)(6)\n, just seeing this now. Where is he barred?\nSent from my Verizon, Samsung Galaxy smartphone\n-------- Original message --------\nFrom:\n(b)(6), (b)(7)(C)\n(USANYS)\n(b)(6), (b)(7)(C)\n@usdoj.gov>\nDate: 7/7/19 5:36 PM (GMT-05:00)\nTo:\n(b)(6), (b)(7)(C)\n@bop.gov>\n(b)(6), (b)(7)(C)\n(b)(6), (b)(7)(C)\nSubject: RE: counsel having difficulty meeting with client\n>>>\n(b)(6), (b)(7)(C)\n(USANYS)\n07/07/2019 17:36 >>>\nWith apologies for the weekend email, we have a defendant, Jeffrey Epstein, who was arrested last night and is currently being detained at MCC, and is expected to be presented on an indictment tomorrow. His attorney\n(b)(6), (b)(7)(C)\nhas represented him in the past, and represents him in connection with our case and has been in touch with us throughout the weekend. He went to MCC today to meet with him in advance of the presentment tomorrow, but was just told he is not allowed in because he is from out-of-state.\nWe're concerned about the defendant not having access to his attorney in advance of the presentment (as we would be for any defendant) and so I wanted to reach out to you—is it at all possible to address this issue so\n(b)(6), (b)(7)(C)\ncan meet with his client this evening? I'm available anytime at\n(b)(6)\n(b)(6)\nto discuss, if that's helpful, or\n(b)(6), (b)(7)(C)\ncan also be reached directly at\n(b)(6), (b)(7)(C)\nif that's easier (though if you reach out directly to him if you could please just let me know afterward I'd be grateful).\nthanks very much,\n(b)(6)\nPage 12753\nDOJ-OGR-00023948",
  "text_blocks": [
    {
      "type": "printed",
      "content": "RE: counsel having difficulty meeting with client\nFrom\n(b)(6), (b)(7)(C)\n(USANYS)\nTo\n(b)(6), (b)(7)(C)\nDate\n2019/07/07 18:18\nSubject:\nRE: counsel having difficulty meeting with client\nAttachments:\nTEXT.htm, Mime.822",
      "position": "top"
    },
    {
      "type": "printed",
      "content": "Massachusetts\nFrom\n(b)(6), (b)(7)(C)\n@bop.gov>\nSent: Sunday, July 07, 2019 18:18\nTo\n(b)(6), (b)(7)(C)\n@bop.gov>\n(b)(6), (b)(7)(C)\n(USANYS)\n(b)(6), (b)(7)(C)\n@usa.doj.gov>\nSubject: Re: counsel having difficulty meeting with client",
      "position": "middle"
    },
    {
      "type": "printed",
      "content": "Sorry\n(b)(6)\n, just seeing this now. Where is he barred?\nSent from my Verizon, Samsung Galaxy smartphone",
      "position": "middle"
    },
    {
      "type": "printed",
      "content": "-------- Original message --------\nFrom:\n(b)(6), (b)(7)(C)\n(USANYS)\n(b)(6), (b)(7)(C)\n@usdoj.gov>\nDate: 7/7/19 5:36 PM (GMT-05:00)\nTo:\n(b)(6), (b)(7)(C)\n@bop.gov>\n(b)(6), (b)(7)(C)\n(b)(6), (b)(7)(C)\nSubject: RE: counsel having difficulty meeting with client",
      "position": "middle"
    },
    {
      "type": "printed",
      "content": "With apologies for the weekend email, we have a defendant, Jeffrey Epstein, who was arrested last night and is currently being detained at MCC, and is expected to be presented on an indictment tomorrow. His attorney\n(b)(6), (b)(7)(C)\nhas represented him in the past, and represents him in connection with our case and has been in touch with us throughout the weekend. He went to MCC today to meet with him in advance of the presentment tomorrow, but was just told he is not allowed in because he is from out-of-state.\nWe're concerned about the defendant not having access to his attorney in advance of the presentment (as we would be for any defendant) and so I wanted to reach out to you—is it at all possible to address this issue so\n(b)(6), (b)(7)(C)\ncan meet with his client this evening? I'm available anytime at\n(b)(6)\n(b)(6)\nto discuss, if that's helpful, or\n(b)(6), (b)(7)(C)\ncan also be reached directly at\n(b)(6), (b)(7)(C)\nif that's easier (though if you reach out directly to him if you could please just let me know afterward I'd be grateful).",
      "position": "middle"
    },
    {
      "type": "printed",
      "content": "thanks very much,\n(b)(6)",
      "position": "middle"
    },
    {
      "type": "printed",
      "content": "Page 12753\nDOJ-OGR-00023948",
      "position": "footer"
    }
  ],
  "entities": {
    "people": [
      "Jeffrey Epstein"
    ],
    "organizations": [
      "MCC",
      "USANYS",
      "DOJ"
    ],
    "locations": [
      "Massachusetts"
    ],
    "dates": [
      "2019/07/07",
      "7/7/19"
    ],
    "reference_numbers": [
      "DOJ-OGR-00023948"
    ]
  },
  "additional_notes": "The document is an email chain discussing the issue of a defendant, Jeffrey Epstein, not having access to his attorney before his presentment. The email contains redactions of personal information."
}