{
  "document_metadata": {
    "page_number": "907",
    "document_number": "Epstein.76318-054.ReconstructionReport.draft3.docx",
    "date": "2019/08/23",
    "document_type": "email",
    "has_handwriting": false,
    "has_stamps": false
  },
  "full_text": "Epstein.76318-054.ReconstructionReport.draft3.docx\nFrom\n(b)(6); (b)(7)(C)\nTo\nHugh Hurwitz, Jeffery Keller, James Wills, Michael Carvajal\nDate\n2019/08/23 16:10\nSubject:\nEpstein.76318-054.ReconstructionReport.draft3.docx\nAttachments:\nTEXTT.htm, Epstein.76318-054.ReconstructionReport.draft3.docx, Nagle, Robert.vcf\nMr. Wills, Keller and Carvajal,\nAttached is a working draft of the Epstein reconstruction. I am forwarding it for your review and return. Please return as soon as possible but no later than Monday with any comments or questions.\nPlease maintain security as this is a working copy.\nThanks,\n(b)(6); (b)(7)(C)\n(b)(6); (b)(7)(C)\nPsy.D.\nNational Suicide Prevention Coordinator\nFederal Bureau of Prisons\nPsychology Services Branch\n320 First Street, NW\nWashington, DC, DC 20534\n202-598(b)(6); (b)(7)(C)",
  "text_blocks": [
    {
      "type": "printed",
      "content": "Epstein.76318-054.ReconstructionReport.draft3.docx",
      "position": "top"
    },
    {
      "type": "printed",
      "content": "From\n(b)(6); (b)(7)(C)\nTo\nHugh Hurwitz, Jeffery Keller, James Wills, Michael Carvajal\nDate\n2019/08/23 16:10\nSubject:\nEpstein.76318-054.ReconstructionReport.draft3.docx\nAttachments:\nTEXTT.htm, Epstein.76318-054.ReconstructionReport.draft3.docx, Nagle, Robert.vcf",
      "position": "top"
    },
    {
      "type": "printed",
      "content": "Mr. Wills, Keller and Carvajal,\nAttached is a working draft of the Epstein reconstruction. I am forwarding it for your review and return. Please return as soon as possible but no later than Monday with any comments or questions.\nPlease maintain security as this is a working copy.",
      "position": "middle"
    },
    {
      "type": "printed",
      "content": "Thanks,\n(b)(6); (b)(7)(C)\n(b)(6); (b)(7)(C)\nPsy.D.\nNational Suicide Prevention Coordinator\nFederal Bureau of Prisons\nPsychology Services Branch\n320 First Street, NW\nWashington, DC, DC 20534\n202-598(b)(6); (b)(7)(C)",
      "position": "bottom"
    }
  ],
  "entities": {
    "people": [
      "Hugh Hurwitz",
      "Jeffery Keller",
      "James Wills",
      "Michael Carvajal",
      "Nagle, Robert"
    ],
    "organizations": [
      "Federal Bureau of Prisons",
      "Psychology Services Branch"
    ],
    "locations": [
      "Washington, DC"
    ],
    "dates": [
      "2019/08/23"
    ],
    "reference_numbers": [
      "Epstein.76318-054.ReconstructionReport.draft3.docx",
      "202-598"
    ]
  },
  "additional_notes": "The document contains redactions marked as (b)(6); (b)(7)(C)."
}