{
  "document_metadata": {
    "page_number": "1000",
    "document_number": "DOJ-OGR-00025244",
    "date": "2019/09/10",
    "document_type": "email",
    "has_handwriting": false,
    "has_stamps": false
  },
  "full_text": "Re: Fwd: Epstein Reconstruction 76318-054 draft7\nFrom Kenneth Hyle\nTo Hugh Hurwitz\nDate 2019/09/10 16:50\nSubject: Re: Fwd: Epstein Reconstruction 76318-054 draft7\nAttachments: TEXTT.htm, Epstein Reconstruction 76318-054 draft7 OGC Comments.docx\n\nHugh - please see attached. If my suggested edits are not accurate, please go with original language. I also had a few questions we can discuss if easier- thanks-\n\n>>> Hugh Hurwitz 9/10/2019 3:57 PM >>>\nKen as discussed, please review and lets discuss finalizing this so we can give to Kathy and she can send to DOJ. Thanks.\n\n>>> (b)(6); (b)(7)(C) 9/10/2019 3:53 PM >>>\nHugh,\n\nHere is the reconstruction on Mr. Epstein. If you want any change, just let me know.\n\nThank you,\n(b)(6); (b)(7)(C)\n\nPage 2267\nDOJ-OGR-00025244",
  "text_blocks": [
    {
      "type": "printed",
      "content": "Re: Fwd: Epstein Reconstruction 76318-054 draft7\nFrom Kenneth Hyle\nTo Hugh Hurwitz\nDate 2019/09/10 16:50\nSubject: Re: Fwd: Epstein Reconstruction 76318-054 draft7\nAttachments: TEXTT.htm, Epstein Reconstruction 76318-054 draft7 OGC Comments.docx",
      "position": "top"
    },
    {
      "type": "printed",
      "content": "Hugh - please see attached. If my suggested edits are not accurate, please go with original language. I also had a few questions we can discuss if easier- thanks-",
      "position": "middle"
    },
    {
      "type": "printed",
      "content": ">>> Hugh Hurwitz 9/10/2019 3:57 PM >>>\nKen as discussed, please review and lets discuss finalizing this so we can give to Kathy and she can send to DOJ. Thanks.",
      "position": "middle"
    },
    {
      "type": "printed",
      "content": ">>> (b)(6); (b)(7)(C) 9/10/2019 3:53 PM >>>\nHugh,\n\nHere is the reconstruction on Mr. Epstein. If you want any change, just let me know.\n\nThank you,\n(b)(6); (b)(7)(C)",
      "position": "middle"
    },
    {
      "type": "printed",
      "content": "Page 2267\nDOJ-OGR-00025244",
      "position": "footer"
    }
  ],
  "entities": {
    "people": [
      "Kenneth Hyle",
      "Hugh Hurwitz",
      "Kathy",
      "Mr. Epstein"
    ],
    "organizations": [
      "DOJ"
    ],
    "locations": [],
    "dates": [
      "2019/09/10",
      "9/10/2019"
    ],
    "reference_numbers": [
      "76318-054",
      "DOJ-OGR-00025244"
    ]
  },
  "additional_notes": "The document appears to be an email chain discussing a reconstruction related to Mr. Epstein. Some names and emails are redacted."
}