{
  "document_metadata": {
    "page_number": "548",
    "document_number": "DOJ-OGR-00024564",
    "date": "08/19/2019",
    "document_type": "Log Entries By Event Date",
    "has_handwriting": false,
    "has_stamps": false
  },
  "full_text": "Date: 08/19/2019 Time: 10:15 AM Federal Bureau of Prisons TRUINTEL Log Entries By Event Date Sensitive But Unclassified Entered Date Alpha Code Level 1 Location Level 2 Location Level 3 Location Event Date Shift User Event Base Count 7/23/2019 12:49 AM NYM Housing Units Housing Units, General Population ES 7/23/2019 12:49 AM Morning (b)(6) Base Count Verified (b)(6) 7/23/2019 (b)(6) AM NYM (b)(6) Housing Units Housing Units, General Population ES 7/23/2019 12:49 AM Morning Official Count 7/23/2019 1:44 AM NYM Housing Units Housing Units, General Population ES 7/23/2019 1:00 AM Morning Watch Call 7/23/2019 1:10 AM NYM Housing Units Housing Units, General Population GS 7/23/2019 1:10 AM Morning Rounds (Officer) 7/23/2019 1:10 AM NYM Housing Units Housing Units, General Population GS 7/23/2019 1:10 AM Morning Watch Call 7/23/2019 1:44 AM NYM Housing Units Housing Units, General Population ES 7/23/2019 1:30 AM Morning Watch Call 7/23/2019 2:26 AM NYM Housing Units Housing Units, General Population GS 7/23/2019 2:26 AM Morning Rounds (Officer) 7/23/2019 2:26 AM NYM Housing Units Housing Units, General Population GS 7/23/2019 2:26 AM Morning Watch Call 7/23/2019 3:45 AM NYM Housing Units Housing Units, General Population GS 7/23/2019 3:45 AM Morning Rounds (Officer) 7/23/2019 3:45 AM NYM Housing Units Housing Units, General Population GS 7/23/2019 3:45 AM Morning Watch Call User ID: (b)(6) Page 548 of 1135 DOJ-OGR-00024564",
  "text_blocks": [
    {
      "type": "printed",
      "content": "Date: 08/19/2019 Time: 10:15 AM Federal Bureau of Prisons TRUINTEL Log Entries By Event Date Sensitive But Unclassified",
      "position": "header"
    },
    {
      "type": "printed",
      "content": "Entered Date Alpha Code Level 1 Location Level 2 Location Level 3 Location Event Date Shift User Event Base Count",
      "position": "header"
    },
    {
      "type": "printed",
      "content": "7/23/2019 12:49 AM NYM Housing Units Housing Units, General Population ES 7/23/2019 12:49 AM Morning (b)(6) Base Count Verified (b)(6)",
      "position": "body"
    },
    {
      "type": "printed",
      "content": "User ID: (b)(6) Page 548 of 1135 DOJ-OGR-00024564",
      "position": "footer"
    }
  ],
  "entities": {
    "people": [],
    "organizations": [
      "Federal Bureau of Prisons"
    ],
    "locations": [],
    "dates": [
      "08/19/2019",
      "7/23/2019"
    ],
    "reference_numbers": [
      "DOJ-OGR-00024564"
    ]
  },
  "additional_notes": "The document appears to be a log entry report from the Federal Bureau of Prisons, containing various events and activities recorded on July 23, 2019. The report includes details such as event dates, times, locations, and personnel involved. Some information has been redacted, indicated by '(b)(6)'."
}