{
  "document_metadata": {
    "page_number": "168",
    "document_number": "DOJ-OGR-00024600",
    "date": "08/19/2019",
    "document_type": "Log Entries By Event Date",
    "has_handwriting": false,
    "has_stamps": false
  },
  "full_text": "Date: 08/19/2019 Time: 10:27 AM Federal Bureau of Prisons TRUINTEL Log Entries By Event Date Sensitive But Unclassified Entered Date Alpha Code Level 1 Location Level 2 Location (SHU) Level 3 Location Event Date Shift User Event Base Count 7/23/2019 7:51 PM NYM SHU Housing Unit, Special (SHU) 9 SOUTH SHU 7/23/2019 7:10 PM Evening Search (Cells) 7/23/2019 7:52 PM NYM SHU Housing Unit, Special (SHU) 9 SOUTH SHU 7/23/2019 7:20 PM Evening Search (Cells) 7/23/2019 7:52 PM NYM SHU Housing Unit, Special (SHU) 9 SOUTH SHU 7/23/2019 7:30 PM Evening Watch Call 7/23/2019 7:57 PM NYM SHU Housing Unit, Special (SHU) 9 SOUTH SHU 7/23/2019 7:57 PM Evening Search (Areas) 7/23/2019 7:57 PM NYM SHU Housing Unit, Special (SHU) 9 SOUTH SHU 7/23/2019 7:57 PM Evening Search (Areas) 7/23/2019 7:57 PM NYM SHU Housing Unit, Special (SHU) 9 SOUTH SHU 7/23/2019 7:57 PM Evening Search (Areas) 7/23/2019 7:57 PM NYM SHU Housing Unit, Special (SHU) 9 SOUTH SHU 7/23/2019 8:00 PM Evening Watch Call 7/23/2019 10:29 PM NYM SHU Housing Unit, Special (SHU) 9 SOUTH SHU 7/23/2019 8:20 PM Evening Rounds (Officer) 7/23/2019 10:30 PM NYM SHU Housing Unit, Special (SHU) 9 SOUTH SHU 7/23/2019 8:30 PM Evening Watch Call 7/23/2019 10:30 PM NYM SHU Housing Unit, Special (SHU) 9 SOUTH SHU 7/23/2019 8:30 PM Evening User ID: Page 168 of 395 DOJ-OGR-00024600",
  "text_blocks": [
    {
      "type": "printed",
      "content": "Date: 08/19/2019 Time: 10:27 AM",
      "position": "header"
    },
    {
      "type": "printed",
      "content": "Federal Bureau of Prisons TRUINTEL Log Entries By Event Date Sensitive But Unclassified",
      "position": "header"
    },
    {
      "type": "printed",
      "content": "Entered Date Alpha Code Level 1 Location Level 2 Location (SHU) Level 3 Location Event Date Shift User Event Base Count",
      "position": "header"
    },
    {
      "type": "printed",
      "content": "7/23/2019 7:51 PM NYM SHU Housing Unit, Special (SHU) 9 SOUTH SHU 7/23/2019 7:10 PM Evening Search (Cells)",
      "position": "body"
    },
    {
      "type": "printed",
      "content": "7/23/2019 7:52 PM NYM SHU Housing Unit, Special (SHU) 9 SOUTH SHU 7/23/2019 7:20 PM Evening Search (Cells)",
      "position": "body"
    },
    {
      "type": "printed",
      "content": "7/23/2019 7:52 PM NYM SHU Housing Unit, Special (SHU) 9 SOUTH SHU 7/23/2019 7:30 PM Evening Watch Call",
      "position": "body"
    },
    {
      "type": "printed",
      "content": "7/23/2019 7:57 PM NYM SHU Housing Unit, Special (SHU) 9 SOUTH SHU 7/23/2019 7:57 PM Evening Search (Areas)",
      "position": "body"
    },
    {
      "type": "printed",
      "content": "7/23/2019 7:57 PM NYM SHU Housing Unit, Special (SHU) 9 SOUTH SHU 7/23/2019 7:57 PM Evening Search (Areas)",
      "position": "body"
    },
    {
      "type": "printed",
      "content": "7/23/2019 7:57 PM NYM SHU Housing Unit, Special (SHU) 9 SOUTH SHU 7/23/2019 7:57 PM Evening Search (Areas)",
      "position": "body"
    },
    {
      "type": "printed",
      "content": "7/23/2019 7:57 PM NYM SHU Housing Unit, Special (SHU) 9 SOUTH SHU 7/23/2019 8:00 PM Evening Watch Call",
      "position": "body"
    },
    {
      "type": "printed",
      "content": "7/23/2019 10:29 PM NYM SHU Housing Unit, Special (SHU) 9 SOUTH SHU 7/23/2019 8:20 PM Evening Rounds (Officer)",
      "position": "body"
    },
    {
      "type": "printed",
      "content": "7/23/2019 10:30 PM NYM SHU Housing Unit, Special (SHU) 9 SOUTH SHU 7/23/2019 8:30 PM Evening Watch Call",
      "position": "body"
    },
    {
      "type": "printed",
      "content": "7/23/2019 10:30 PM NYM SHU Housing Unit, Special (SHU) 9 SOUTH SHU 7/23/2019 8:30 PM Evening",
      "position": "body"
    },
    {
      "type": "printed",
      "content": "User ID:",
      "position": "footer"
    },
    {
      "type": "printed",
      "content": "Page 168 of 395",
      "position": "footer"
    },
    {
      "type": "printed",
      "content": "DOJ-OGR-00024600",
      "position": "footer"
    }
  ],
  "entities": {
    "people": [],
    "organizations": [
      "Federal Bureau of Prisons"
    ],
    "locations": [
      "9 SOUTH SHU",
      "Housing Unit, Special (SHU)"
    ],
    "dates": [
      "08/19/2019",
      "7/23/2019"
    ],
    "reference_numbers": [
      "DOJ-OGR-00024600"
    ]
  },
  "additional_notes": "The document appears to be a log entry report from the Federal Bureau of Prisons, detailing various events and activities at a correctional facility on July 23, 2019. The report includes information on the date, time, location, and type of event, as well as the user who entered the data. The document is marked as 'Sensitive But Unclassified'."
}