{
  "document_metadata": {
    "page_number": "653",
    "document_number": "DOJ-OGR-00025100",
    "date": null,
    "document_type": "Suicide Timeline Report",
    "has_handwriting": false,
    "has_stamps": false
  },
  "full_text": "Page 653\n\nSuicide Timeline:\n\nRE: Epstein, Jeffrey Edward, Reg. No. 76318-054\n\nFriday, August 9, 2019\n\n8:00 am: inmate Reyes Efrain, Reg. No. 85993-054 departs for court (WAB-USMS-SDNY). Reyes is Epstein's cellmate.\n8:30 am: inmate Epstein arrives in Attorney Conference. He is visited by several attorneys throughout the day.\n6:45 pm: inmate Epstein departs attorney conference and returns to SHU.\n7:00 pm: inmate Epstein provided a social call by IDO. IDO reports inmate Epstein was in good spirits, nothing unusual.\n\nSaturday, August 10, 2019\n\n6:33 am: (b)(7)(E) activated in SHU. Staff found inmate Epstein unresponsive in cell. Staff reported to bedside of inmate and attempted to wake him. Control announced medical emergency. CPR initiated\n6:35 am: Medical staff (on duty PA) on site, CPR already in progress medical staff continues CPR and AED applied on inmate. Control called for ambulance\n6:40 am: S. Skipper-Scott, AW notified\n6:45 am: EMS arrives, paramedics continue CPR. Inmate Epstein remains unresponsive. Inmate Epstein is intubated, given three rounds of Epinephrine, IV access started, IO initiated. No pulse found, no shock advised, inmate prepared for transport to local hospital.\n7:00 am: Institution placed on modified operations\n7:10 am: EMS departs institution enroute to Beekman Hospital.\n7:19 am: USMS notified of incident.\n\nDOJ-OGR-00025100",
  "text_blocks": [
    {
      "type": "printed",
      "content": "Suicide Timeline:",
      "position": "top"
    },
    {
      "type": "printed",
      "content": "RE: Epstein, Jeffrey Edward, Reg. No. 76318-054",
      "position": "top"
    },
    {
      "type": "printed",
      "content": "Friday, August 9, 2019",
      "position": "top"
    },
    {
      "type": "printed",
      "content": "8:00 am: inmate Reyes Efrain, Reg. No. 85993-054 departs for court (WAB-USMS-SDNY). Reyes is Epstein's cellmate.",
      "position": "middle"
    },
    {
      "type": "printed",
      "content": "8:30 am: inmate Epstein arrives in Attorney Conference. He is visited by several attorneys throughout the day.",
      "position": "middle"
    },
    {
      "type": "printed",
      "content": "6:45 pm: inmate Epstein departs attorney conference and returns to SHU.",
      "position": "middle"
    },
    {
      "type": "printed",
      "content": "7:00 pm: inmate Epstein provided a social call by IDO. IDO reports inmate Epstein was in good spirits, nothing unusual.",
      "position": "middle"
    },
    {
      "type": "printed",
      "content": "Saturday, August 10, 2019",
      "position": "middle"
    },
    {
      "type": "printed",
      "content": "6:33 am: (b)(7)(E) activated in SHU. Staff found inmate Epstein unresponsive in cell. Staff reported to bedside of inmate and attempted to wake him. Control announced medical emergency. CPR initiated",
      "position": "middle"
    },
    {
      "type": "printed",
      "content": "6:35 am: Medical staff (on duty PA) on site, CPR already in progress medical staff continues CPR and AED applied on inmate. Control called for ambulance",
      "position": "middle"
    },
    {
      "type": "printed",
      "content": "6:40 am: S. Skipper-Scott, AW notified",
      "position": "middle"
    },
    {
      "type": "printed",
      "content": "6:45 am: EMS arrives, paramedics continue CPR. Inmate Epstein remains unresponsive. Inmate Epstein is intubated, given three rounds of Epinephrine, IV access started, IO initiated. No pulse found, no shock advised, inmate prepared for transport to local hospital.",
      "position": "middle"
    },
    {
      "type": "printed",
      "content": "7:00 am: Institution placed on modified operations",
      "position": "middle"
    },
    {
      "type": "printed",
      "content": "7:10 am: EMS departs institution enroute to Beekman Hospital.",
      "position": "middle"
    },
    {
      "type": "printed",
      "content": "7:19 am: USMS notified of incident.",
      "position": "middle"
    },
    {
      "type": "printed",
      "content": "DOJ-OGR-00025100",
      "position": "footer"
    }
  ],
  "entities": {
    "people": [
      "Jeffrey Edward Epstein",
      "Reyes Efrain",
      "S. Skipper-Scott"
    ],
    "organizations": [
      "USMS"
    ],
    "locations": [
      "WAB-USMS-SDNY",
      "SHU",
      "Beekman Hospital"
    ],
    "dates": [
      "Friday, August 9, 2019",
      "Saturday, August 10, 2019"
    ],
    "reference_numbers": [
      "76318-054",
      "85993-054",
      "DOJ-OGR-00025100"
    ]
  },
  "additional_notes": "The document appears to be a report detailing the events surrounding Jeffrey Epstein's death. It includes a timeline of events on August 9 and 10, 2019. The document is typed and contains no handwritten text or stamps. The document is labeled with a document number 'DOJ-OGR-00025100' at the bottom right corner."
}