{
  "document_metadata": {
    "page_number": "3217",
    "document_number": "DOJ-OGR-00024208",
    "date": "August 12, 2019",
    "document_type": "email chain",
    "has_handwriting": false,
    "has_stamps": false
  },
  "full_text": "FYI >>> (b)(6), (b)(7)(C) @nysd.uscourts.gov> 8/12/2019 2:42 PM >>> (b)(6) please thank the Warden for his prompt response to my letter. Richard M. Berman On Aug 12, 2019, at 2:37 PM, Christine Murray (b)(6), (b)(7)(C) @nysd.uscourts.gov> wrote: fyi ----- Forwarded by Christine Murray/NYSD/02/USCOURTS on 08/12/2019 02:37 PM ----- From: (b)(6), (b)(7)(C) @bop.gov> To: \"Lamine N'Diaye\" (b)(6) @bop.gov>, <BermanNYSDChambers@nysd.uscourts.gov> Cc: (b)(6) @att.net>, (b)(6) @nysd.uscourts.gov>, (b)(6), (b)(7)(C) @nysd.uscourts.gov>, (b)(6) @usdoj.gov>, \"Michael Greco\" (b)(6), (b)(7)(C) @usdoj.gov> Date: 08/12/2019 02:33 PM Subject: Re: Jeffrey Epstein 19 cr 490 Good afternoon, Attached please find Warden N'Diaye's response to Your Honor's inquiry. Please let us know if you need further information. Thank you, (b)(6), (b)(7)(C) Supervisory Staff Attorney CLC New York Metropolitan Correctional Center 150 Park Row New York, New York 10007 p: (646)836-(b)(6) f: (646)836-7665 >>> <BermanNYSDChambers@nysd.uscourts.gov> 8/12/2019 12:47 PM >>> Please see attached letter from Judge Richard M. Berman. (See attached file: Aug 12 letter.pdf)(See attached file: 2019_08_12_14_31_06.pdf) <2019_08_12-14_31_06.pdf> Page 3217 DOJ-OGR-00024208",
  "text_blocks": [
    {
      "type": "printed",
      "content": "FYI",
      "position": "top"
    },
    {
      "type": "printed",
      "content": ">>> (b)(6), (b)(7)(C) @nysd.uscourts.gov> 8/12/2019 2:42 PM >>>",
      "position": "top"
    },
    {
      "type": "printed",
      "content": "(b)(6) please thank the Warden for his prompt response to my letter. Richard M. Berman",
      "position": "top"
    },
    {
      "type": "printed",
      "content": "On Aug 12, 2019, at 2:37 PM, Christine Murray (b)(6), (b)(7)(C) @nysd.uscourts.gov> wrote:",
      "position": "top"
    },
    {
      "type": "printed",
      "content": "fyi ----- Forwarded by Christine Murray/NYSD/02/USCOURTS on 08/12/2019 02:37 PM -----",
      "position": "middle"
    },
    {
      "type": "printed",
      "content": "From: (b)(6), (b)(7)(C) @bop.gov> To: \"Lamine N'Diaye\" (b)(6) @bop.gov>, <BermanNYSDChambers@nysd.uscourts.gov> Cc: (b)(6) @att.net>, (b)(6) @nysd.uscourts.gov>, (b)(6), (b)(7)(C) @nysd.uscourts.gov>, (b)(6) @usdoj.gov>, \"Michael Greco\" (b)(6), (b)(7)(C) @usdoj.gov> Date: 08/12/2019 02:33 PM Subject: Re: Jeffrey Epstein 19 cr 490",
      "position": "middle"
    },
    {
      "type": "printed",
      "content": "Good afternoon, Attached please find Warden N'Diaye's response to Your Honor's inquiry. Please let us know if you need further information. Thank you, (b)(6), (b)(7)(C)",
      "position": "middle"
    },
    {
      "type": "printed",
      "content": "Supervisory Staff Attorney CLC New York Metropolitan Correctional Center 150 Park Row New York, New York 10007 p: (646)836-(b)(6) f: (646)836-7665",
      "position": "middle"
    },
    {
      "type": "printed",
      "content": ">>> <BermanNYSDChambers@nysd.uscourts.gov> 8/12/2019 12:47 PM >>> Please see attached letter from Judge Richard M. Berman.",
      "position": "bottom"
    },
    {
      "type": "printed",
      "content": "(See attached file: Aug 12 letter.pdf)(See attached file: 2019_08_12_14_31_06.pdf) <2019_08_12-14_31_06.pdf>",
      "position": "bottom"
    },
    {
      "type": "printed",
      "content": "Page 3217 DOJ-OGR-00024208",
      "position": "footer"
    }
  ],
  "entities": {
    "people": [
      "Richard M. Berman",
      "Christine Murray",
      "Lamine N'Diaye",
      "Michael Greco"
    ],
    "organizations": [
      "US Courts",
      "Bureau of Prisons",
      "US Department of Justice",
      "Metropolitan Correctional Center"
    ],
    "locations": [
      "New York"
    ],
    "dates": [
      "August 12, 2019"
    ],
    "reference_numbers": [
      "19 cr 490",
      "DOJ-OGR-00024208"
    ]
  },
  "additional_notes": "The document appears to be an email chain with redactions. The content is related to a legal case involving Jeffrey Epstein."
}