{
  "document_metadata": {
    "page_number": "3919",
    "document_number": "DOJ-OGR-00023869",
    "date": "2019/08/27",
    "document_type": "email chain",
    "has_handwriting": false,
    "has_stamps": false
  },
  "full_text": "Re: Epstein\nFrom\n(b)(6), (b)(7)(C)\nTo\n(b)(6), (b)(7)(C)\nDate\n2019/08/27 08:46\nSubject:\nRe: Epstein\nAttachments:\nTEXT.htm\nHi\n(b)(6)\n(b)(7)(A)(C)\nJust a heads-up that Judge Berman invited the Warden and I to the hearing this morning. The Warden declined because of another meeting and asked to meet the Judge at a later date, but I'll be attending. I asked\n(b)(6)\nif Judge Berman's expectation was for me to sit at counsel's table or in the galley, but she never responded. In that case, I defer to you unless we hear otherwise when we get there.\nThanks,\n(b)(6), (b)(7)(C)\nStaff Attorney\nCLC New York\nMetropolitan Correctional Center\n150 Park Row\nNew York, NY 10007\np: 646-836-(b)(6)\nf. 646-836-7665\n>>> (b)(6), (b)(7)(C) (USANYS)\" (b)(6), (b)(7)(C) @usdoj.gov> 7/30/2019 7:11 PM >>>\nHi (b)(6), (b)(7)(C)\n(b)(5)\nThanks,\n(b)(6), (b)(7)(C)\nAssistant United States Attorney\nSouthern District of New York\n1 St. Andrew's Plaza\nNew York, NY 10007\n212-637-(b)(6)\n(b)(6), (b)(7)(C) @usdoj.gov\nPage 3919\nDOJ-OGR-00023869",
  "text_blocks": [
    {
      "type": "printed",
      "content": "Re: Epstein\nFrom\n(b)(6), (b)(7)(C)\nTo\n(b)(6), (b)(7)(C)\nDate\n2019/08/27 08:46\nSubject:\nRe: Epstein\nAttachments:\nTEXT.htm",
      "position": "top"
    },
    {
      "type": "printed",
      "content": "Hi\n(b)(6)\n(b)(7)(A)(C)\nJust a heads-up that Judge Berman invited the Warden and I to the hearing this morning. The Warden declined because of another meeting and asked to meet the Judge at a later date, but I'll be attending. I asked\n(b)(6)\nif Judge Berman's expectation was for me to sit at counsel's table or in the galley, but she never responded. In that case, I defer to you unless we hear otherwise when we get there.",
      "position": "middle"
    },
    {
      "type": "printed",
      "content": "Thanks,\n(b)(6), (b)(7)(C)\nStaff Attorney\nCLC New York\nMetropolitan Correctional Center\n150 Park Row\nNew York, NY 10007\np: 646-836-(b)(6)\nf. 646-836-7665",
      "position": "middle"
    },
    {
      "type": "printed",
      "content": ">>> (b)(6), (b)(7)(C) (USANYS)\" (b)(6), (b)(7)(C) @usdoj.gov> 7/30/2019 7:11 PM >>>\nHi (b)(6), (b)(7)(C)\n(b)(5)",
      "position": "middle"
    },
    {
      "type": "printed",
      "content": "Thanks,\n(b)(6), (b)(7)(C)\nAssistant United States Attorney\nSouthern District of New York\n1 St. Andrew's Plaza\nNew York, NY 10007\n212-637-(b)(6)\n(b)(6), (b)(7)(C) @usdoj.gov",
      "position": "middle"
    },
    {
      "type": "printed",
      "content": "Page 3919\nDOJ-OGR-00023869",
      "position": "footer"
    }
  ],
  "entities": {
    "people": [
      "Judge Berman",
      "Warden"
    ],
    "organizations": [
      "CLC New York",
      "Metropolitan Correctional Center",
      "Southern District of New York",
      "USDOJ"
    ],
    "locations": [
      "New York"
    ],
    "dates": [
      "2019/08/27",
      "7/30/2019"
    ],
    "reference_numbers": [
      "DOJ-OGR-00023869"
    ]
  },
  "additional_notes": "The document is an email chain with redactions. The content appears to be related to a legal case involving Epstein."
}