{
  "document_metadata": {
    "page_number": "967",
    "document_number": "DOJ-OGR-00023580",
    "date": "2019/08/11",
    "document_type": "email chain",
    "has_handwriting": false,
    "has_stamps": false
  },
  "full_text": "Fwd: [EXTERNAL] OCME Determination Pending: Jeffrey Epstein\nFrom\n(b)(5)\n(NBCUniversal)\nTo\nLee Plourde\nDate\n2019/08/11 18:56\nSubject:\nFwd: [EXTERNAL] OCME Determination Pending: Jeffrey Epstein\nAttachments:\nTEXT.htm, Mime.822\nJust FYI\nSent from my iPhone\nBegin forwarded message:\nFrom: (b)(5)\n(NBCUniversal)\" (b)(5) @nbcuni.com>\nDate: August 11, 2019 at 6:53:42 PM EDT\nTo: (b)(5)\n(NBCUniversal)\" (b)(5) @nbcuni.com>\nSubject: RE: [EXTERNAL] OCME Determination Pending: Jeffrey Epstein\nSo no further info will be put out tonight? Right? Just need to figure out if I should move George off of it now. Thanks again!\nFrom: (b)(5)\n(NBCUniversal)\nSent: Sunday, August 11, 2019 6:52 PM\nTo: @NBC Uni Wnbc News Updates <WnbcNewsUpdates@nbcuni.com>\nSubject: Fwd: [EXTERNAL] OCME Determination Pending: Jeffrey Epstein\nSent from my iPhone\nBegin forwarded message:\nFrom: (b)(3)\n(OCME)\" <(b)(6)\n@ocme.nyc.gov>\nDate: August 11, 2019 at 6:51:20 PM EDT\nTo: (b)(6)\n(OCME)\" (b)(6) @ocme.nyc.gov>\nSubject: [EXTERNAL] OCME Determination Pending: Jeffrey Epstein\n***IF YOU WOULD LIKE TO BE REMOVED FROM OCME'S PRESS LIST, PLEASE EMAIL (b)(6)\n@OCME.NYC.GOV WITH THE SUBJECT TITLE: UNSUBSCRIBE***\nThe Chief Medical Examiner released the below statement today:\n\"Today, a medical examiner performed the autopsy of Jeffrey Epstein. The ME's determination is pending further information at this time. At the request of those representing the decedent, and with the awareness of the federal prosecutor, I allowed a private pathologist (Dr. Michael Baden) to",
  "text_blocks": [
    {
      "type": "printed",
      "content": "Fwd: [EXTERNAL] OCME Determination Pending: Jeffrey Epstein",
      "position": "header"
    },
    {
      "type": "printed",
      "content": "From: (b)(5) (NBCUniversal)",
      "position": "header"
    },
    {
      "type": "printed",
      "content": "To: Lee Plourde",
      "position": "header"
    },
    {
      "type": "printed",
      "content": "Date: 2019/08/11 18:56",
      "position": "header"
    },
    {
      "type": "printed",
      "content": "Subject: Fwd: [EXTERNAL] OCME Determination Pending: Jeffrey Epstein",
      "position": "header"
    },
    {
      "type": "printed",
      "content": "Attachments: TEXT.htm, Mime.822",
      "position": "header"
    },
    {
      "type": "printed",
      "content": "Just FYI",
      "position": "body"
    },
    {
      "type": "printed",
      "content": "Sent from my iPhone",
      "position": "body"
    },
    {
      "type": "printed",
      "content": "Begin forwarded message:",
      "position": "body"
    },
    {
      "type": "printed",
      "content": "From: (b)(5) (NBCUniversal) (b)(5) @nbcuni.com>",
      "position": "body"
    },
    {
      "type": "printed",
      "content": "Date: August 11, 2019 at 6:53:42 PM EDT",
      "position": "body"
    },
    {
      "type": "printed",
      "content": "To: (b)(5) (NBCUniversal) (b)(5) @nbcuni.com>",
      "position": "body"
    },
    {
      "type": "printed",
      "content": "Subject: RE: [EXTERNAL] OCME Determination Pending: Jeffrey Epstein",
      "position": "body"
    },
    {
      "type": "printed",
      "content": "So no further info will be put out tonight? Right? Just need to figure out if I should move George off of it now. Thanks again!",
      "position": "body"
    },
    {
      "type": "printed",
      "content": "From: (b)(5) (NBCUniversal)",
      "position": "body"
    },
    {
      "type": "printed",
      "content": "Sent: Sunday, August 11, 2019 6:52 PM",
      "position": "body"
    },
    {
      "type": "printed",
      "content": "To: @NBC Uni Wnbc News Updates <WnbcNewsUpdates@nbcuni.com>",
      "position": "body"
    },
    {
      "type": "printed",
      "content": "Subject: Fwd: [EXTERNAL] OCME Determination Pending: Jeffrey Epstein",
      "position": "body"
    },
    {
      "type": "printed",
      "content": "Sent from my iPhone",
      "position": "body"
    },
    {
      "type": "printed",
      "content": "Begin forwarded message:",
      "position": "body"
    },
    {
      "type": "printed",
      "content": "From: (b)(3) (OCME) <(b)(6) @ocme.nyc.gov>",
      "position": "body"
    },
    {
      "type": "printed",
      "content": "Date: August 11, 2019 at 6:51:20 PM EDT",
      "position": "body"
    },
    {
      "type": "printed",
      "content": "To: (b)(6) (OCME) (b)(6) @ocme.nyc.gov>",
      "position": "body"
    },
    {
      "type": "printed",
      "content": "Subject: [EXTERNAL] OCME Determination Pending: Jeffrey Epstein",
      "position": "body"
    },
    {
      "type": "printed",
      "content": "***IF YOU WOULD LIKE TO BE REMOVED FROM OCME'S PRESS LIST, PLEASE EMAIL (b)(6) @OCME.NYC.GOV WITH THE SUBJECT TITLE: UNSUBSCRIBE***",
      "position": "body"
    },
    {
      "type": "printed",
      "content": "The Chief Medical Examiner released the below statement today:",
      "position": "body"
    },
    {
      "type": "printed",
      "content": "\"Today, a medical examiner performed the autopsy of Jeffrey Epstein. The ME's determination is pending further information at this time. At the request of those representing the decedent, and with the awareness of the federal prosecutor, I allowed a private pathologist (Dr. Michael Baden) to",
      "position": "body"
    },
    {
      "type": "printed",
      "content": "Page 967",
      "position": "footer"
    },
    {
      "type": "printed",
      "content": "DOJ-OGR-00023580",
      "position": "footer"
    }
  ],
  "entities": {
    "people": [
      "Jeffrey Epstein",
      "Lee Plourde",
      "George",
      "Michael Baden"
    ],
    "organizations": [
      "NBCUniversal",
      "OCME"
    ],
    "locations": [],
    "dates": [
      "August 11, 2019",
      "2019/08/11"
    ],
    "reference_numbers": [
      "DOJ-OGR-00023580"
    ]
  },
  "additional_notes": "The document appears to be an email chain discussing the death of Jeffrey Epstein and the pending determination by the Office of the Chief Medical Examiner (OCME). The emails contain redactions, indicated by (b)(5), (b)(3), and (b)(6), which are likely related to privacy or confidentiality concerns."
}