{
  "document_metadata": {
    "page_number": "1667",
    "document_number": "DOJ-OGR-00023637",
    "date": "2019/07/23",
    "document_type": "email chain",
    "has_handwriting": false,
    "has_stamps": false
  },
  "full_text": "Re: Epstein, Jeffrey, Register No. 76318-054\nFrom: Ray Ormond\nTo: Sonya Thompson\nDate: 2019/07/23 13:57\nSubject: Re: Epstein, Jeffrey, Register No. 76318-054\nAttachments: TEXT.htm\n(b)(7)(A), (b)(7)(B)\nSent from my Verizon, Samsung Galaxy smartphone\n\n----- Original message -----\nFrom: Sonya Thompson (b)(6) @bop.gov>\nDate: 7/23/19 1:55 PM (GMT-05:00)\nTo: Ray Ormond (b)(6) @bop.gov>\nSubject: Re: Epstein, Jeffrey, Register No. 76318-054\n\n>>> \"Sonya Thompson\" 07/23/2019 13:55 >>>\n(b)(7)(A) (b)(7)(B)\nFrom: Ray Ormond (b)(6) @bop.gov>\nTo: (b)(6) @bop.gov\nCC: (b)(6) @bop.gov, (b)(6) @bop.gov, (b)(6) @bop.gov\nDate: 7/23/2019 1:52 PM\nSubject: Epstein, Jeffrey, Register No. 76318-054\nSonya - See below for possible media attention. (b)(7)(A), (b)(7)(B)\nSent from my Verizon, Samsung Galaxy smartphone\n\n----- Original message -----\nFrom: \"Shirley V. Skipper-Scott\" (b)(6) @bop.gov>\nDate: 7/23/19 1:41 PM (GMT-05:00)\nTo: Ray Ormond (b)(6) @bop.gov>\nSubject: Re: Fwd: Epstein\n\n>>> \"Shirley V. Skipper-Scott\" 07/23/2019 13:41 >>>\nIf you need additional information, please let me know. Thanks\n(b)(7)(E)\n\nShirley Skipper-Scott\nAssociate Warden\nMCC New York\n150 Park Row\nNew York, New York 10007\nOffice: 646-836(b)(6)\nBlack Berry: 646-423(b)(6)\n(b)(6) @bop.gov",
  "text_blocks": [
    {
      "type": "printed",
      "content": "Re: Epstein, Jeffrey, Register No. 76318-054\nFrom: Ray Ormond\nTo: Sonya Thompson\nDate: 2019/07/23 13:57\nSubject: Re: Epstein, Jeffrey, Register No. 76318-054\nAttachments: TEXT.htm",
      "position": "top"
    },
    {
      "type": "printed",
      "content": "(b)(7)(A), (b)(7)(B)",
      "position": "top"
    },
    {
      "type": "printed",
      "content": "Sent from my Verizon, Samsung Galaxy smartphone",
      "position": "top"
    },
    {
      "type": "printed",
      "content": "----- Original message -----\nFrom: Sonya Thompson (b)(6) @bop.gov>\nDate: 7/23/19 1:55 PM (GMT-05:00)\nTo: Ray Ormond (b)(6) @bop.gov>\nSubject: Re: Epstein, Jeffrey, Register No. 76318-054",
      "position": "middle"
    },
    {
      "type": "printed",
      "content": ">>> \"Sonya Thompson\" 07/23/2019 13:55 >>>\n(b)(7)(A) (b)(7)(B)\nFrom: Ray Ormond (b)(6) @bop.gov>\nTo: (b)(6) @bop.gov\nCC: (b)(6) @bop.gov, (b)(6) @bop.gov, (b)(6) @bop.gov\nDate: 7/23/2019 1:52 PM\nSubject: Epstein, Jeffrey, Register No. 76318-054",
      "position": "middle"
    },
    {
      "type": "printed",
      "content": "Sonya - See below for possible media attention. (b)(7)(A), (b)(7)(B)",
      "position": "middle"
    },
    {
      "type": "printed",
      "content": "Sent from my Verizon, Samsung Galaxy smartphone",
      "position": "middle"
    },
    {
      "type": "printed",
      "content": "----- Original message -----\nFrom: \"Shirley V. Skipper-Scott\" (b)(6) @bop.gov>\nDate: 7/23/19 1:41 PM (GMT-05:00)\nTo: Ray Ormond (b)(6) @bop.gov>\nSubject: Re: Fwd: Epstein",
      "position": "middle"
    },
    {
      "type": "printed",
      "content": ">>> \"Shirley V. Skipper-Scott\" 07/23/2019 13:41 >>>\nIf you need additional information, please let me know. Thanks",
      "position": "middle"
    },
    {
      "type": "printed",
      "content": "(b)(7)(E)",
      "position": "middle"
    },
    {
      "type": "printed",
      "content": "Shirley Skipper-Scott\nAssociate Warden\nMCC New York\n150 Park Row\nNew York, New York 10007\nOffice: 646-836(b)(6)\nBlack Berry: 646-423(b)(6)\n(b)(6) @bop.gov",
      "position": "bottom"
    },
    {
      "type": "printed",
      "content": "Page 1667\nDOJ-OGR-00023637",
      "position": "footer"
    }
  ],
  "entities": {
    "people": [
      "Jeffrey Epstein",
      "Ray Ormond",
      "Sonya Thompson",
      "Shirley V. Skipper-Scott"
    ],
    "organizations": [
      "MCC New York",
      "BOP"
    ],
    "locations": [
      "New York"
    ],
    "dates": [
      "2019/07/23",
      "7/23/19"
    ],
    "reference_numbers": [
      "76318-054"
    ]
  },
  "additional_notes": "The document is an email chain with redactions. The redactions are marked as (b)(6), (b)(7)(A), (b)(7)(B), and (b)(7)(E)."
}