{
  "document_metadata": {
    "page_number": "9472",
    "document_number": "DOJ-OGR-00023921",
    "date": "2019/07/24",
    "document_type": "email",
    "has_handwriting": false,
    "has_stamps": false
  },
  "full_text": "Fwd: hi and a question From Lee Plourde To (b)(6), (b)(7)(C), (b)(7)(E), (b)(7)(F) Date 2019/07/24 23:01 Subject: Fwd: hi and a question Attachments: TEXT.htm Sent from my Verizon, Samsung Galaxy smartphone -------- Original message -------- From: (b)(6), (b)(7)(C), (b)(7)(E), (b)(7)(F) @nytimes.com> Date: 7/24/19 10:47 PM (GMT-05:00) To: Lee Plourde (b)(6), (b)(7)(C) @bop.gov> Subject: hi and a question (b)(6), (b)(7)(C): 07/24/2019 22:47 hi Lee, hope you are well. We saw an article tonight on someting called RadarOnline reporting that Jeffrey Epstein attempted to commit suicide at the MCC (unsuccessfully.) Are you in a position to help me on that with some sort of confirmation or information. (Or to dispel its veracity?) thanks. (b)(6), (b)(7)(C), (b)(7)(E), (b)(7)(F) Reporter, The New York Times Office: 212-556- (b)(6) (b)(7)(C) Mobile: 914-672-1595 Email: (b)(6), (b)(7)(C) @nytimes.com (b)(6), (b)(7)(C), (b)(7)(E), (b)(7)(F) Page 9472 DOJ-OGR-00023921",
  "text_blocks": [
    {
      "type": "printed",
      "content": "Fwd: hi and a question From Lee Plourde To (b)(6), (b)(7)(C), (b)(7)(E), (b)(7)(F) Date 2019/07/24 23:01 Subject: Fwd: hi and a question Attachments: TEXT.htm",
      "position": "top"
    },
    {
      "type": "printed",
      "content": "Sent from my Verizon, Samsung Galaxy smartphone -------- Original message -------- From: (b)(6), (b)(7)(C), (b)(7)(E), (b)(7)(F) @nytimes.com> Date: 7/24/19 10:47 PM (GMT-05:00) To: Lee Plourde (b)(6), (b)(7)(C) @bop.gov> Subject: hi and a question",
      "position": "middle"
    },
    {
      "type": "printed",
      "content": "(b)(6), (b)(7)(C): 07/24/2019 22:47 hi Lee, hope you are well. We saw an article tonight on someting called RadarOnline reporting that Jeffrey Epstein attempted to commit suicide at the MCC (unsuccessfully.) Are you in a position to help me on that with some sort of confirmation or information. (Or to dispel its veracity?) thanks.",
      "position": "middle"
    },
    {
      "type": "printed",
      "content": "(b)(6), (b)(7)(C), (b)(7)(E), (b)(7)(F) Reporter, The New York Times Office: 212-556- (b)(6) (b)(7)(C) Mobile: 914-672-1595 Email: (b)(6), (b)(7)(C) @nytimes.com (b)(6), (b)(7)(C), (b)(7)(E), (b)(7)(F)",
      "position": "middle"
    },
    {
      "type": "printed",
      "content": "Page 9472 DOJ-OGR-00023921",
      "position": "footer"
    }
  ],
  "entities": {
    "people": [
      "Lee Plourde",
      "Jeffrey Epstein"
    ],
    "organizations": [
      "The New York Times",
      "Verizon",
      "Samsung",
      "MCC",
      "BOP",
      "DOJ"
    ],
    "locations": [],
    "dates": [
      "2019/07/24",
      "7/24/19",
      "07/24/2019"
    ],
    "reference_numbers": [
      "212-556",
      "914-672-1595",
      "DOJ-OGR-00023921"
    ]
  },
  "additional_notes": "The document is an email chain with redactions. The email discusses an article on RadarOnline reporting Jeffrey Epstein's attempted suicide at the MCC."
}