{
  "document_metadata": {
    "page_number": "1077",
    "document_number": "DOJ-OGR-00025300",
    "date": "2019/07/24",
    "document_type": "email",
    "has_handwriting": false,
    "has_stamps": false
  },
  "full_text": "Page 1077\nRe: Epstein\nFrom Ray Ormond\nTo Shirley V. Skipper-Scott\nDate 2019/07/24 10:53\nSubject: Re: Epstein\nAttachments: TEXT.htm, Ray Ormond.vcf\nThanks!!\nJ. Ray Ormond\nRegional Director\nNortheast Region\n215-521 (b)(6); (b)(7)(C)\n>>> Shirley V. Skipper-Scott 7/24/2019 10:49 AM >>>\nBelow is the definition of Psychological Observation provided by (b)(6); (b)(7)(C) Chief Psychologist. He will remain on Psychological Observation until tomorrow, where he will be reassessed.\nDEFINITION: A Psychological Observation occurs when an inmate who suffers from a mental illness, a serious personality disorder, a medical problem (impairing their mental status), or drug intoxication and/or withdrawal symptoms begins to deteriorate. The inmate is no longer mentally stable and therefore, it is inappropriate for s/he to remain in general population or the Special Housing Unit (SHU). Inmates placed on psychological observation differ from inmates placed on suicide watch as they are not imminently suicidal (e.g., have not expressed self-harm or engaged in self-harming behavior), but rather, due to his/her impairment in mental status or functioning (e.g., not eating, not sleeping, disorganized/unusual thinking, poor self-care), his/her behavior can be unpredictable. Psychological Observation status is intended as a temporary designation to be utilized until such time as the inmate becomes sufficiently stable (e.g., able to function independently in general population) to be returned to his/her housing assignment or transferred to an inpatient psychiatric facility such as a Federal Medical Center.\nHe has a pending incident report for Self-Mutilation and therefore, he will return to the Special Housing Unit (SHU) and will be celled with inmate (b)(6); (b)(7)(C) (b)(6); (b)(7)(C) .\n(b)(6); (b)(7)(C) he requested Protective Custody.\nHis case has been highly publicized and he is in SHU because\nShirley Skipper-Scott\nAssociate Warden\nMCC New York\n150 Park Row\nNew York, New York 10007\nOffice: 646-836 (b)(6); (b)(7)(C) \nBlack Berry: 646-423 (b)(6); (b)(7)(C) \n(b)(6); (b)(7)(C) @bop.gov\nPage 2633\nDOJ-OGR-00025300",
  "text_blocks": [
    {
      "type": "printed",
      "content": "Re: Epstein\nFrom Ray Ormond\nTo Shirley V. Skipper-Scott\nDate 2019/07/24 10:53\nSubject: Re: Epstein\nAttachments: TEXT.htm, Ray Ormond.vcf",
      "position": "top"
    },
    {
      "type": "printed",
      "content": "Thanks!!\nJ. Ray Ormond\nRegional Director\nNortheast Region\n215-521",
      "position": "middle"
    },
    {
      "type": "printed",
      "content": ">>> Shirley V. Skipper-Scott 7/24/2019 10:49 AM >>>\nBelow is the definition of Psychological Observation provided by Chief Psychologist. He will remain on Psychological Observation until tomorrow, where he will be reassessed.",
      "position": "middle"
    },
    {
      "type": "printed",
      "content": "DEFINITION: A Psychological Observation occurs when an inmate who suffers from a mental illness, a serious personality disorder, a medical problem (impairing their mental status), or drug intoxication and/or withdrawal symptoms begins to deteriorate. The inmate is no longer mentally stable and therefore, it is inappropriate for s/he to remain in general population or the Special Housing Unit (SHU). Inmates placed on psychological observation differ from inmates placed on suicide watch as they are not imminently suicidal (e.g., have not expressed self-harm or engaged in self-harming behavior), but rather, due to his/her impairment in mental status or functioning (e.g., not eating, not sleeping, disorganized/unusual thinking, poor self-care), his/her behavior can be unpredictable. Psychological Observation status is intended as a temporary designation to be utilized until such time as the inmate becomes sufficiently stable (e.g., able to function independently in general population) to be returned to his/her housing assignment or transferred to an inpatient psychiatric facility such as a Federal Medical Center.",
      "position": "middle"
    },
    {
      "type": "printed",
      "content": "He has a pending incident report for Self-Mutilation and therefore, he will return to the Special Housing Unit (SHU) and will be celled with inmate",
      "position": "middle"
    },
    {
      "type": "printed",
      "content": "he requested Protective Custody.\nHis case has been highly publicized and he is in SHU because",
      "position": "middle"
    },
    {
      "type": "printed",
      "content": "Shirley Skipper-Scott\nAssociate Warden\nMCC New York\n150 Park Row\nNew York, New York 10007\nOffice: 646-836\nBlack Berry: 646-423\n@bop.gov",
      "position": "bottom"
    }
  ],
  "entities": {
    "people": [
      "Ray Ormond",
      "Shirley V. Skipper-Scott",
      "J. Ray Ormond",
      "Shirley Skipper-Scott"
    ],
    "organizations": [
      "MCC New York",
      "BOP"
    ],
    "locations": [
      "Northeast Region",
      "New York",
      "Federal Medical Center"
    ],
    "dates": [
      "2019/07/24",
      "7/24/2019"
    ],
    "reference_numbers": [
      "215-521",
      "646-836",
      "646-423",
      "DOJ-OGR-00025300"
    ]
  },
  "additional_notes": "The document contains redactions marked as (b)(6); (b)(7)(C)."
}