{
  "document_metadata": {
    "page_number": "10",
    "document_number": "734",
    "date": "07/15/22",
    "document_type": "court document",
    "has_handwriting": false,
    "has_stamps": false
  },
  "full_text": "Case 1:20-cr-00330-PAE Document 734 Filed 07/15/22 Page 10 of 16\n\nNovember 19, 2021\nPage Ten\n\nConfidentiality was a “cornerstone” of the EVCP,41 “critical” to its success,42 and of “paramount importance.”43 Confidentiality was an indispensable term necessary to interested parties' support for the EVCP.44 Without the expectation of confidentiality, many victims would not have participated, and the whole purpose of the program would have been frustrated.45\n\nThe Supreme Court in Nixon recognized—in the context of a President's claim of confidentiality over communications with advisors—that the “interest in preserving confidentiality is weighty indeed and entitled to great respect.” Nixon, 418 U.S. at 712. And while the Supreme Court ultimately upheld the denial of a motion to quash given that the President's confidentiality concerns were “general in nature” and would “not be vitiated by disclosure of a limited number of conversations,” id. at 713, the facts here show that the EVCP has a particularized interest in maintaining the confidentiality of sexual-abuse victims' information and that opening the door to any such disclosures poses a real risk of “vitiat[ing]” such a program's effectiveness, id., and would “turn the Program on its head with far-reaching consequences to this victim population and beyond.”46\n\nIndeed, as another district court held in quashing a subpoena under Rule 17(c)(2), “individuals could be deterred from participating in the program if it were possible for” outside parties “to obtain this type of information.” THCF Med. Clinic Recs., 504 F. Supp. 2d at 1090-91 (quashing subpoena under Rule 17(c)(2) that sought information about participants in state-run medical marijuana program and recognizing the state's interest in “keeping its contract with its citizens to preserve the confidentiality of their records”). The existence of the U.S. Virgin\n\n41 Ex. F at 1 (8/9/21 Press Release) (statement of Ms. Feldman).\n42 Ex. F at 1 (8/9/21 Press Release).\n43 Ex. C at 2 (6/25/20 Press Release).\n44 See Ex. A ¶¶ 7-8, 12 (Feldman Decl.).\n45 See Ex. A ¶¶ 7-14 (Feldman Decl.).\n46 Ex. A ¶¶ 13-14 (Feldman Decl.).\n\nDOJ-OGR-00011460",
  "text_blocks": [
    {
      "type": "printed",
      "content": "Case 1:20-cr-00330-PAE Document 734 Filed 07/15/22 Page 10 of 16",
      "position": "header"
    },
    {
      "type": "printed",
      "content": "November 19, 2021\nPage Ten",
      "position": "top"
    },
    {
      "type": "printed",
      "content": "Confidentiality was a “cornerstone” of the EVCP,41 “critical” to its success,42 and of “paramount importance.”43 Confidentiality was an indispensable term necessary to interested parties' support for the EVCP.44 Without the expectation of confidentiality, many victims would not have participated, and the whole purpose of the program would have been frustrated.45",
      "position": "middle"
    },
    {
      "type": "printed",
      "content": "The Supreme Court in Nixon recognized—in the context of a President's claim of confidentiality over communications with advisors—that the “interest in preserving confidentiality is weighty indeed and entitled to great respect.” Nixon, 418 U.S. at 712. And while the Supreme Court ultimately upheld the denial of a motion to quash given that the President's confidentiality concerns were “general in nature” and would “not be vitiated by disclosure of a limited number of conversations,” id. at 713, the facts here show that the EVCP has a particularized interest in maintaining the confidentiality of sexual-abuse victims' information and that opening the door to any such disclosures poses a real risk of “vitiat[ing]” such a program's effectiveness, id., and would “turn the Program on its head with far-reaching consequences to this victim population and beyond.”46",
      "position": "middle"
    },
    {
      "type": "printed",
      "content": "Indeed, as another district court held in quashing a subpoena under Rule 17(c)(2), “individuals could be deterred from participating in the program if it were possible for” outside parties “to obtain this type of information.” THCF Med. Clinic Recs., 504 F. Supp. 2d at 1090-91 (quashing subpoena under Rule 17(c)(2) that sought information about participants in state-run medical marijuana program and recognizing the state's interest in “keeping its contract with its citizens to preserve the confidentiality of their records”). The existence of the U.S. Virgin",
      "position": "middle"
    },
    {
      "type": "printed",
      "content": "41 Ex. F at 1 (8/9/21 Press Release) (statement of Ms. Feldman).\n42 Ex. F at 1 (8/9/21 Press Release).\n43 Ex. C at 2 (6/25/20 Press Release).\n44 See Ex. A ¶¶ 7-8, 12 (Feldman Decl.).\n45 See Ex. A ¶¶ 7-14 (Feldman Decl.).\n46 Ex. A ¶¶ 13-14 (Feldman Decl.).",
      "position": "footer"
    },
    {
      "type": "printed",
      "content": "DOJ-OGR-00011460",
      "position": "footer"
    }
  ],
  "entities": {
    "people": [
      "Nixon",
      "Ms. Feldman"
    ],
    "organizations": [
      "Supreme Court",
      "U.S. Virgin"
    ],
    "locations": [],
    "dates": [
      "November 19, 2021",
      "07/15/22",
      "8/9/21",
      "6/25/20"
    ],
    "reference_numbers": [
      "1:20-cr-00330-PAE",
      "Document 734",
      "DOJ-OGR-00011460"
    ]
  },
  "additional_notes": "The document appears to be a court filing related to a case involving the Epstein Victim Compensation Program (EVCP). The text discusses the importance of confidentiality in the program and cites various legal precedents and references."
}