{
  "document_metadata": {
    "page_number": "284",
    "document_number": "688",
    "date": "06/29/22",
    "document_type": "Juror Questionnaire",
    "has_handwriting": true,
    "has_stamps": false
  },
  "full_text": "Case 1:20-cr-00330-PAE Document 688 Filed 06/29/22 Page 284 of 353 Juror ID: 89 36. Based on anything that you have read, seen, or heard about Ms. Maxwell, including anything about criminal charges against Ms. Maxwell, have you formed any opinions about Ms. Maxwell that might make it difficult for you to be a fair and impartial juror in this case? Yes No Unsure Not applicable, I have not read/seen/heard about Ms. Maxwell 36a. If yes or unsure, please explain why it might be difficult for you to be a fair and impartial juror in this case: 37. Before today, had you read, seen, or heard anything about Jeffrey Epstein? Yes No Unsure 37a. If yes or unsure, please state what you remember hearing, and how or from whom you may have heard (e.g., a friend, the newspaper, a website, social media). If you heard about Mr. Epstein from a media source, please identify the media source by name: I HAVE HEARD THIS NAME IN THE NEWS AND I AM AWARE THAT HE COMMITTED SUICIDE WHILE IN JAIL. 38. Have you verbally stated or posted your opinion on social media or online about Ms. Maxwell or Mr. Epstein? Yes No Not applicable, I have not read/seen/heard about Mr. Epstein/Ms. Maxwell 38a. If yes, when and where did you state or post your opinion? -20- DOJ-OGR-00011037",
  "text_blocks": [
    {
      "type": "printed",
      "content": "Case 1:20-cr-00330-PAE Document 688 Filed 06/29/22 Page 284 of 353",
      "position": "header"
    },
    {
      "type": "handwritten",
      "content": "89",
      "position": "header"
    },
    {
      "type": "printed",
      "content": "Juror ID:",
      "position": "header"
    },
    {
      "type": "printed",
      "content": "36. Based on anything that you have read, seen, or heard about Ms. Maxwell, including anything about criminal charges against Ms. Maxwell, have you formed any opinions about Ms. Maxwell that might make it difficult for you to be a fair and impartial juror in this case?",
      "position": "body"
    },
    {
      "type": "printed",
      "content": "Yes No Unsure Not applicable, I have not read/seen/heard about Ms. Maxwell",
      "position": "body"
    },
    {
      "type": "handwritten",
      "content": "No",
      "position": "body"
    },
    {
      "type": "printed",
      "content": "36a. If yes or unsure, please explain why it might be difficult for you to be a fair and impartial juror in this case:",
      "position": "body"
    },
    {
      "type": "printed",
      "content": "37. Before today, had you read, seen, or heard anything about Jeffrey Epstein?",
      "position": "body"
    },
    {
      "type": "printed",
      "content": "Yes No Unsure",
      "position": "body"
    },
    {
      "type": "handwritten",
      "content": "Yes",
      "position": "body"
    },
    {
      "type": "printed",
      "content": "37a. If yes or unsure, please state what you remember hearing, and how or from whom you may have heard (e.g., a friend, the newspaper, a website, social media). If you heard about Mr. Epstein from a media source, please identify the media source by name:",
      "position": "body"
    },
    {
      "type": "handwritten",
      "content": "I HAVE HEARD THIS NAME IN THE NEWS AND I AM AWARE THAT HE COMMITTED SUICIDE WHILE IN JAIL.",
      "position": "body"
    },
    {
      "type": "printed",
      "content": "38. Have you verbally stated or posted your opinion on social media or online about Ms. Maxwell or Mr. Epstein?",
      "position": "body"
    },
    {
      "type": "printed",
      "content": "Yes No Not applicable, I have not read/seen/heard about Mr. Epstein/Ms. Maxwell",
      "position": "body"
    },
    {
      "type": "handwritten",
      "content": "No",
      "position": "body"
    },
    {
      "type": "printed",
      "content": "38a. If yes, when and where did you state or post your opinion?",
      "position": "body"
    },
    {
      "type": "printed",
      "content": "-20-",
      "position": "footer"
    },
    {
      "type": "printed",
      "content": "DOJ-OGR-00011037",
      "position": "footer"
    }
  ],
  "entities": {
    "people": [
      "Ms. Maxwell",
      "Jeffrey Epstein",
      "Mr. Epstein"
    ],
    "organizations": [],
    "locations": [
      "Jail"
    ],
    "dates": [
      "06/29/22"
    ],
    "reference_numbers": [
      "1:20-cr-00330-PAE",
      "688",
      "284",
      "353",
      "89",
      "DOJ-OGR-00011037"
    ]
  },
  "additional_notes": "The document is a juror questionnaire from a court case involving Ms. Maxwell and Jeffrey Epstein. The juror has answered some questions and provided handwritten responses. The document is generally legible, but some handwritten text may be difficult to read due to the quality of the scan."
}