{
  "document_metadata": {
    "page_number": "252",
    "document_number": "688",
    "date": "06/29/22",
    "document_type": "Juror Questionnaire",
    "has_handwriting": true,
    "has_stamps": false
  },
  "full_text": "Case 1:20-cr-00330-PAE Document 688 Filed 06/29/22 Page 252 of 353\n\nJunior ID: 74\n\n32a. If yes, please explain:\n\nPERSONAL RELATIONSHIP WITH CASE PARTICIPANTS\n\n33. The next subset of questions asks whether you or any member of your family or a close friend personally knows or has past or present dealings with individuals involved in this case. To \"personally know\" means to have some direct or personal knowledge or connection to the following individuals. If you have only heard the names through media or social media, for example, that is not personal knowledge.\n\n33a. Do you or does any member of your family or a close friend personally know or have past or present dealings with the Defendant in this case, Ghislaine Maxwell, or her family members?\nYes No\n\n33b. Do you or does any member of your family or a close friend personally know or have past or present dealings with Jeffrey Epstein?\nYes No\n\n33c. Do you or does any member of your family or a close friend personally know or have past or present dealings with the U.S. Attorney for the Southern District of New York, Damian Williams, the former Acting U.S. Attorney for the Southern District of New York, Audrey Strauss, or anyone else who works for or used to work for the U.S. Attorney's Office for the Southern District of New York?\nYes No\n\n33d. Do you or does any member of your family or a close friend personally know or have past or present dealings with any of the Assistant United States Attorneys who are prosecuting this case:\nMaurene Comey Yes No\nAlison Moe Yes No\nLara Pomerantz Yes No\nAndrew Rohrbach Yes No\n\n-17-\nDOJ-OGR-00011005",
  "text_blocks": [
    {
      "type": "printed",
      "content": "Case 1:20-cr-00330-PAE Document 688 Filed 06/29/22 Page 252 of 353",
      "position": "header"
    },
    {
      "type": "handwritten",
      "content": "74",
      "position": "margin"
    },
    {
      "type": "printed",
      "content": "Junior ID:",
      "position": "margin"
    },
    {
      "type": "printed",
      "content": "32a. If yes, please explain:",
      "position": "body"
    },
    {
      "type": "printed",
      "content": "PERSONAL RELATIONSHIP WITH CASE PARTICIPANTS",
      "position": "body"
    },
    {
      "type": "printed",
      "content": "33. The next subset of questions asks whether you or any member of your family or a close friend personally knows or has past or present dealings with individuals involved in this case. To \"personally know\" means to have some direct or personal knowledge or connection to the following individuals. If you have only heard the names through media or social media, for example, that is not personal knowledge.",
      "position": "body"
    },
    {
      "type": "printed",
      "content": "33a. Do you or does any member of your family or a close friend personally know or have past or present dealings with the Defendant in this case, Ghislaine Maxwell, or her family members?",
      "position": "body"
    },
    {
      "type": "handwritten",
      "content": "No",
      "position": "body"
    },
    {
      "type": "printed",
      "content": "33b. Do you or does any member of your family or a close friend personally know or have past or present dealings with Jeffrey Epstein?",
      "position": "body"
    },
    {
      "type": "handwritten",
      "content": "No",
      "position": "body"
    },
    {
      "type": "printed",
      "content": "33c. Do you or does any member of your family or a close friend personally know or have past or present dealings with the U.S. Attorney for the Southern District of New York, Damian Williams, the former Acting U.S. Attorney for the Southern District of New York, Audrey Strauss, or anyone else who works for or used to work for the U.S. Attorney's Office for the Southern District of New York?",
      "position": "body"
    },
    {
      "type": "handwritten",
      "content": "No",
      "position": "body"
    },
    {
      "type": "printed",
      "content": "33d. Do you or does any member of your family or a close friend personally know or have past or present dealings with any of the Assistant United States Attorneys who are prosecuting this case:",
      "position": "body"
    },
    {
      "type": "printed",
      "content": "Maurene Comey Yes No\nAlison Moe Yes No\nLara Pomerantz Yes No\nAndrew Rohrbach Yes No",
      "position": "body"
    },
    {
      "type": "handwritten",
      "content": "No No No No",
      "position": "body"
    },
    {
      "type": "printed",
      "content": "-17-",
      "position": "footer"
    },
    {
      "type": "printed",
      "content": "DOJ-OGR-00011005",
      "position": "footer"
    }
  ],
  "entities": {
    "people": [
      "Ghislaine Maxwell",
      "Jeffrey Epstein",
      "Damian Williams",
      "Audrey Strauss",
      "Maurene Comey",
      "Alison Moe",
      "Lara Pomerantz",
      "Andrew Rohrbach"
    ],
    "organizations": [
      "U.S. Attorney's Office for the Southern District of New York"
    ],
    "locations": [
      "New York",
      "Southern District of New York"
    ],
    "dates": [
      "06/29/22"
    ],
    "reference_numbers": [
      "1:20-cr-00330-PAE",
      "688",
      "252",
      "353",
      "74",
      "DOJ-OGR-00011005"
    ]
  },
  "additional_notes": "The document appears to be a juror questionnaire from a court case involving Ghislaine Maxwell. The juror has answered 'No' to all questions regarding personal relationships with case participants. The document is in good condition with clear handwriting."
}