{
  "document_metadata": {
    "page_number": "16 of 55",
    "document_number": "670",
    "date": "06/22/22",
    "document_type": "court document",
    "has_handwriting": false,
    "has_stamps": false
  },
  "full_text": "Case 1:20-cr-00330-PAE Document 670 Filed 06/22/22 Page 16 of 55\nfully nude when the defendant walked into the massage room. (Id.). The defendant told Carolyn that she had a nice body and touched Carolyn's breasts. (Id.).\nAt some point, Epstein asked Carolyn if she had any young friends she could bring for massages. (PSR ¶ 71). Carolyn ended up bringing multiple girls to massage Epstein, including multiple minors. (Id.). When Carolyn brought girls to massage Epstein, both the girl and Carolyn would be paid hundreds of dollars in cash. (Id.). During those massages, Epstein masturbated and touched Carolyn's and her friend's breasts and buttocks. (Id.).\n6. Sexual Abuse of Melissa\nOne of the minor girls Carolyn brought to provide paid sexualized massages to Epstein was named Melissa. (PSR ¶ 80). Melissa was just 16 years old when she went with Carolyn to Epstein's Palm Beach residence. (Id.). Melissa went to Epstein's residence to provide Epstein with massages on multiple occasions when she was under the age of 18. (Id.). When Melissa and Carolyn went to the Palm Beach house, they remained in the home for about an hour and then returned with hundreds of dollars in cash. (Id.). An entry entitled \"Melissa's cell (Carolyn's friend),\" as well as multiple entries with Carolyn's full name and an entry entitled \"Virginia (parents)\" were listed in the defendant and Epstein's black address book under the heading \"Massage - Florida.\" (Id.; PSR ¶ 57). Thus, as a direct result of the pyramid scheme that began with Virginia and continued with Carolyn, Melissa suffered repeated sexual abuse.\nII. The Pre-Sentence Report and Sentencing Guidelines\nThe United States Probation Office, in its Pre-Sentence Investigation Report, recommends a sentence of twenty years' imprisonment. In making that recommendation, the Probation Office characterized the defendant's offense conduct as \"heinous and predatory in nature.\" (PSR at 67). Regarding the defendant's role, the Probation Office emphasized that \"[t]he gravity of Maxwell's\n14\nDOJ-OGR-00010551",
  "text_blocks": [
    {
      "type": "printed",
      "content": "Case 1:20-cr-00330-PAE Document 670 Filed 06/22/22 Page 16 of 55",
      "position": "header"
    },
    {
      "type": "printed",
      "content": "fully nude when the defendant walked into the massage room. (Id.). The defendant told Carolyn that she had a nice body and touched Carolyn's breasts. (Id.).\nAt some point, Epstein asked Carolyn if she had any young friends she could bring for massages. (PSR ¶ 71). Carolyn ended up bringing multiple girls to massage Epstein, including multiple minors. (Id.). When Carolyn brought girls to massage Epstein, both the girl and Carolyn would be paid hundreds of dollars in cash. (Id.). During those massages, Epstein masturbated and touched Carolyn's and her friend's breasts and buttocks. (Id.).\n6. Sexual Abuse of Melissa\nOne of the minor girls Carolyn brought to provide paid sexualized massages to Epstein was named Melissa. (PSR ¶ 80). Melissa was just 16 years old when she went with Carolyn to Epstein's Palm Beach residence. (Id.). Melissa went to Epstein's residence to provide Epstein with massages on multiple occasions when she was under the age of 18. (Id.). When Melissa and Carolyn went to the Palm Beach house, they remained in the home for about an hour and then returned with hundreds of dollars in cash. (Id.). An entry entitled \"Melissa's cell (Carolyn's friend),\" as well as multiple entries with Carolyn's full name and an entry entitled \"Virginia (parents)\" were listed in the defendant and Epstein's black address book under the heading \"Massage - Florida.\" (Id.; PSR ¶ 57). Thus, as a direct result of the pyramid scheme that began with Virginia and continued with Carolyn, Melissa suffered repeated sexual abuse.",
      "position": "main content"
    },
    {
      "type": "printed",
      "content": "II. The Pre-Sentence Report and Sentencing Guidelines\nThe United States Probation Office, in its Pre-Sentence Investigation Report, recommends a sentence of twenty years' imprisonment. In making that recommendation, the Probation Office characterized the defendant's offense conduct as \"heinous and predatory in nature.\" (PSR at 67). Regarding the defendant's role, the Probation Office emphasized that \"[t]he gravity of Maxwell's",
      "position": "main content"
    },
    {
      "type": "printed",
      "content": "14",
      "position": "footer"
    },
    {
      "type": "printed",
      "content": "DOJ-OGR-00010551",
      "position": "footer"
    }
  ],
  "entities": {
    "people": [
      "Carolyn",
      "Epstein",
      "Melissa",
      "Virginia",
      "Maxwell"
    ],
    "organizations": [
      "United States Probation Office"
    ],
    "locations": [
      "Palm Beach",
      "Florida"
    ],
    "dates": [
      "06/22/22"
    ],
    "reference_numbers": [
      "1:20-cr-00330-PAE",
      "Document 670",
      "PSR ¶ 71",
      "PSR ¶ 80",
      "PSR ¶ 57",
      "PSR at 67",
      "DOJ-OGR-00010551"
    ]
  },
  "additional_notes": "The document appears to be a court filing related to the case of Ghislaine Maxwell, detailing allegations of sexual abuse and the pre-sentence report. The text is printed and there are no visible stamps or handwritten notes."
}