{
  "document_metadata": {
    "page_number": "iv",
    "document_number": "646210",
    "date": null,
    "document_type": "Trial Transcript",
    "has_handwriting": false,
    "has_stamps": false
  },
  "full_text": "Case 1:09-cr-00338-JDB Document 646-10 Filed 08/22/11 Page 4 of 767 iv PAGE Transcript—Trial, Day 47, May 23, 2011 ............................... A-2637 Transcript—Trial, Day 48, May 25, 2011 ............................... A-2644 Requests To Charge Of The United States, May 2, 2011 ................. A-2652 Letter from Stanley J. Okula, Jr. to Judge Pauley, May 3, 2011 ...... A-2734 Letter from Laurie Edelstein to Judge Pauley, May 4, 2011 ........... A-2742 Letter from Laurie Edelstein to Judge Pauley, May 5, 2011 ........... A-2746 Email from Nicholas Cutaia, May 6, 2011, attaching revised draft jury charge ....................................... A-2814 Letter from Laurie Edelstein to Judge Pauley, May 8, 2011 ........... A-2882 Court Exhibit 3—Note from Catherine Conrad, May 10, 2011 ...... A-2955 Defendant David Parse's Motion For Judgment Of Acquittal Pursuant To Rule 29, June 7, 2011 ............................... A-3021 Government's Trial Exhibits GX12-60 Deutsche Bank Alex. Brown Confirmation ....................... A-3027 GX24-5A Fax from Carrie Yackee to John Beery, August 29, 2002 ............................................... A-3035 GX24-16 Deutsche Bank Alex. Brown Client Statement ......... A-3076 GX24-22 Letter from Matt Coleman to David Parse, December 24, 2001 ....................................... A-3083 GX24-23 Letter from Matt Coleman to David Parse, December 28, 2001 ....................................... A-3085 GX37-4 Documents Relating To C.R. Gibb ....................... A-3360 DOJ-OGR-00009907",
  "text_blocks": [
    {
      "type": "printed",
      "content": "Case 1:09-cr-00338-JDB Document 646-10 Filed 08/22/11 Page 4 of 767",
      "position": "header"
    },
    {
      "type": "printed",
      "content": "iv PAGE Transcript—Trial, Day 47, May 23, 2011 ............................... A-2637 Transcript—Trial, Day 48, May 25, 2011 ............................... A-2644 Requests To Charge Of The United States, May 2, 2011 ................. A-2652 Letter from Stanley J. Okula, Jr. to Judge Pauley, May 3, 2011 ...... A-2734 Letter from Laurie Edelstein to Judge Pauley, May 4, 2011 ........... A-2742 Letter from Laurie Edelstein to Judge Pauley, May 5, 2011 ........... A-2746 Email from Nicholas Cutaia, May 6, 2011, attaching revised draft jury charge ....................................... A-2814 Letter from Laurie Edelstein to Judge Pauley, May 8, 2011 ........... A-2882 Court Exhibit 3—Note from Catherine Conrad, May 10, 2011 ...... A-2955 Defendant David Parse's Motion For Judgment Of Acquittal Pursuant To Rule 29, June 7, 2011 ............................... A-3021 Government's Trial Exhibits GX12-60 Deutsche Bank Alex. Brown Confirmation ....................... A-3027 GX24-5A Fax from Carrie Yackee to John Beery, August 29, 2002 ............................................... A-3035 GX24-16 Deutsche Bank Alex. Brown Client Statement ......... A-3076 GX24-22 Letter from Matt Coleman to David Parse, December 24, 2001 ....................................... A-3083 GX24-23 Letter from Matt Coleman to David Parse, December 28, 2001 ....................................... A-3085 GX37-4 Documents Relating To C.R. Gibb ....................... A-3360",
      "position": "main"
    },
    {
      "type": "printed",
      "content": "DOJ-OGR-00009907",
      "position": "footer"
    }
  ],
  "entities": {
    "people": [
      "Stanley J. Okula, Jr.",
      "Laurie Edelstein",
      "Judge Pauley",
      "Nicholas Cutaia",
      "Catherine Conrad",
      "David Parse",
      "Carrie Yackee",
      "John Beery",
      "Matt Coleman",
      "C.R. Gibb"
    ],
    "organizations": [
      "Deutsche Bank",
      "Alex. Brown"
    ],
    "locations": [],
    "dates": [
      "May 23, 2011",
      "May 25, 2011",
      "May 2, 2011",
      "May 3, 2011",
      "May 4, 2011",
      "May 5, 2011",
      "May 6, 2011",
      "May 8, 2011",
      "May 10, 2011",
      "June 7, 2011",
      "August 29, 2002",
      "December 24, 2001",
      "December 28, 2001",
      "08/22/11"
    ],
    "reference_numbers": [
      "A-2637",
      "A-2644",
      "A-2652",
      "A-2734",
      "A-2742",
      "A-2746",
      "A-2814",
      "A-2882",
      "A-2955",
      "A-3021",
      "A-3027",
      "A-3035",
      "A-3076",
      "A-3083",
      "A-3085",
      "A-3360",
      "646-10",
      "1:09-cr-00338-JDB"
    ]
  },
  "additional_notes": "The document appears to be a table of contents or index for a trial transcript, listing various documents and exhibits related to the case."
}