{
  "document_metadata": {
    "page_number": "18 of 30",
    "document_number": "613-1",
    "date": "02/24/22",
    "document_type": "Juror Questionnaire",
    "has_handwriting": true,
    "has_stamps": false
  },
  "full_text": "Case 1:20-cr-00330-PAE Document 613-1 Filed 02/24/22 Page 18 of 30\nJuror ID: 50\nKNOWLEDGE OF CASE AND PEOPLE\nThis case has been widely reported in the national and local media. There is nothing wrong with having heard something about this case. It is important to answer all of the following questions truthfully and fully.\n34. Before today, had you read, seen, or heard anything about Ms. Maxwell? Yes No Unsure\n34a. If yes or unsure, please state what you remember hearing, and how or from whom you may have heard (e.g., a friend, the newspaper, a website, social media). If you heard about Ms. Maxwell from a media source, please identify the media source by name: I read on a website that she was Jeffrey Epsteins girlfried - source was CNN.com\n35. Have you personally formed an opinion about Ms. Maxwell's guilt or innocence of the crimes charged as a result of anything you have heard, read or seen? Yes No Unsure Not applicable, I have not read/seen/heard about Ms. Maxwell\n35a. If yes or unsure, please summarize your opinion:\n-19-\nDOJ-OGR-00009085",
  "text_blocks": [
    {
      "type": "printed",
      "content": "Case 1:20-cr-00330-PAE Document 613-1 Filed 02/24/22 Page 18 of 30",
      "position": "header"
    },
    {
      "type": "handwritten",
      "content": "50",
      "position": "header"
    },
    {
      "type": "printed",
      "content": "KNOWLEDGE OF CASE AND PEOPLE",
      "position": "top"
    },
    {
      "type": "printed",
      "content": "This case has been widely reported in the national and local media. There is nothing wrong with having heard something about this case. It is important to answer all of the following questions truthfully and fully.",
      "position": "top"
    },
    {
      "type": "printed",
      "content": "34. Before today, had you read, seen, or heard anything about Ms. Maxwell?",
      "position": "middle"
    },
    {
      "type": "handwritten",
      "content": "Yes",
      "position": "middle"
    },
    {
      "type": "printed",
      "content": "34a. If yes or unsure, please state what you remember hearing, and how or from whom you may have heard (e.g., a friend, the newspaper, a website, social media). If you heard about Ms. Maxwell from a media source, please identify the media source by name:",
      "position": "middle"
    },
    {
      "type": "handwritten",
      "content": "I read on a website that she was Jeffrey Epsteins girlfried - source was CNN.com",
      "position": "middle"
    },
    {
      "type": "printed",
      "content": "35. Have you personally formed an opinion about Ms. Maxwell's guilt or innocence of the crimes charged as a result of anything you have heard, read or seen?",
      "position": "middle"
    },
    {
      "type": "handwritten",
      "content": "No",
      "position": "middle"
    },
    {
      "type": "printed",
      "content": "35a. If yes or unsure, please summarize your opinion:",
      "position": "bottom"
    },
    {
      "type": "printed",
      "content": "-19-",
      "position": "footer"
    },
    {
      "type": "printed",
      "content": "DOJ-OGR-00009085",
      "position": "footer"
    }
  ],
  "entities": {
    "people": [
      "Ms. Maxwell",
      "Jeffrey Epstein"
    ],
    "organizations": [
      "CNN"
    ],
    "locations": [],
    "dates": [
      "02/24/22"
    ],
    "reference_numbers": [
      "1:20-cr-00330-PAE",
      "613-1",
      "DOJ-OGR-00009085"
    ]
  },
  "additional_notes": "The document is a juror questionnaire from a court case involving Ms. Maxwell. The juror has answered questions about their knowledge of the case and Ms. Maxwell. The document contains handwritten answers to the questions."
}