{
  "document_metadata": {
    "page_number": "22",
    "document_number": "A-5707",
    "date": "08/24/22",
    "document_type": "Court Document",
    "has_handwriting": false,
    "has_stamps": false
  },
  "full_text": "Case 1:20-cr-00336-PAE Document 612 Filed 08/24/22 Page 22 of 130 A-5707\n\nC2GFDAU1 Brune - direct 250\n1 Q. And making strategic choices is a major part of\n2 representing any client, correct?\n3 A. That's right.\n4 Q. And that was a major part of representing David Parse in\n5 this case?\n6 A. Certainly.\n7 Q. And you didn't necessarily clear every decision that you\n8 made with Mr. Parse, correct?\n9 A. That's right.\n10 Q. And he in fact trusted you to make decisions on his behalf\n11 as his lawyer, correct?\n12 A. Yes.\n13 Q. And that was true of the other attorneys in your firm who\n14 worked on this case, correct?\n15 A. I'm sorry, what was true?\n16 Q. That Mr. Parse trusted not only you but the people in your\n17 employ, correct?\n18 A. I believe so. We had a very good working relationship.\n19 Q. Now, you're not afraid, are you, to raise issues with a\n20 Court about any issues that might come up with regard to your\n21 clients, correct?\n22 A. Well, I'm certainly not afraid to speak to the Court if\n23 that's what you're asking.\n24 Q. You raised many issues with the Court, with this Court\n25 before trial, correct?\nSOUTHERN DISTRICT REPORTERS, P.C. (212) 805-0300\n\nDOJ-OGR-00009311",
  "text_blocks": [
    {
      "type": "printed",
      "content": "Case 1:20-cr-00336-PAE Document 612 Filed 08/24/22 Page 22 of 130 A-5707",
      "position": "header"
    },
    {
      "type": "printed",
      "content": "C2GFDAU1 Brune - direct 250",
      "position": "top"
    },
    {
      "type": "printed",
      "content": "1 Q. And making strategic choices is a major part of\n2 representing any client, correct?\n3 A. That's right.\n4 Q. And that was a major part of representing David Parse in\n5 this case?\n6 A. Certainly.\n7 Q. And you didn't necessarily clear every decision that you\n8 made with Mr. Parse, correct?\n9 A. That's right.\n10 Q. And he in fact trusted you to make decisions on his behalf\n11 as his lawyer, correct?\n12 A. Yes.\n13 Q. And that was true of the other attorneys in your firm who\n14 worked on this case, correct?\n15 A. I'm sorry, what was true?\n16 Q. That Mr. Parse trusted not only you but the people in your\n17 employ, correct?\n18 A. I believe so. We had a very good working relationship.\n19 Q. Now, you're not afraid, are you, to raise issues with a\n20 Court about any issues that might come up with regard to your\n21 clients, correct?\n22 A. Well, I'm certainly not afraid to speak to the Court if\n23 that's what you're asking.\n24 Q. You raised many issues with the Court, with this Court\n25 before trial, correct?",
      "position": "middle"
    },
    {
      "type": "printed",
      "content": "SOUTHERN DISTRICT REPORTERS, P.C. (212) 805-0300",
      "position": "footer"
    },
    {
      "type": "printed",
      "content": "DOJ-OGR-00009311",
      "position": "footer"
    }
  ],
  "entities": {
    "people": [
      "David Parse",
      "Brune",
      "Parse"
    ],
    "organizations": [
      "SOUTHERN DISTRICT REPORTERS, P.C.",
      "DOJ"
    ],
    "locations": [],
    "dates": [
      "08/24/22"
    ],
    "reference_numbers": [
      "1:20-cr-00336-PAE",
      "Document 612",
      "A-5707",
      "DOJ-OGR-00009311"
    ]
  },
  "additional_notes": "The document appears to be a court transcript with a clear and legible format. There are no visible redactions or damage."
}