{
  "document_metadata": {
    "page_number": "21",
    "document_number": "636",
    "date": "03/01/22",
    "document_type": "court document",
    "has_handwriting": false,
    "has_stamps": false
  },
  "full_text": "Case 1:20-cr-00330-PAE Document 636 Filed 03/01/22 Page 21 of 22\nThe Honorable Alison J. Nathan\nMarch 1, 2022\nPage 21\nd. Was it after the verdict?\n4. You did not shy away from speaking publicly about your jury service?\n5. You did not shy away from publicly revealing that you were a victim of child sex abuse?\n6. What was your reason for going public?\na. You told the reporter from The Independent: \"This verdict is for all the victims\" and \"shows that you can be found guilty no matter your status.\"\nb. When Annie Farmer posted a Tweet thanking you for your jury service, you Tweeted back \"Thanks for sharing my story.\"\nc. In early January, shortly after the trial was over, you posted the following message on Instagram: \"I can now tell everyone that I was a juror on the Ghislaine Maxwell trial.\"\n7. Did you want to be on the Maxwell jury?\na. Did you think it was important that you be on the Maxwell jury as a survivor of childhood sexual abuse?\nb. Did you view your role on the jury as someone who could provide the perspective of someone who had been abused as a child?\nc. Did you view the verdict as a triumph for victims over abusers?\nd. Was your intent to \"share your own story\" about being a juror on the Maxwell case after the trial was over?\n2100689.3 DOJ-OGR-00009658",
  "text_blocks": [
    {
      "type": "printed",
      "content": "Case 1:20-cr-00330-PAE Document 636 Filed 03/01/22 Page 21 of 22",
      "position": "header"
    },
    {
      "type": "printed",
      "content": "The Honorable Alison J. Nathan\nMarch 1, 2022\nPage 21",
      "position": "top"
    },
    {
      "type": "printed",
      "content": "d. Was it after the verdict?\n4. You did not shy away from speaking publicly about your jury service?\n5. You did not shy away from publicly revealing that you were a victim of child sex abuse?\n6. What was your reason for going public?\na. You told the reporter from The Independent: \"This verdict is for all the victims\" and \"shows that you can be found guilty no matter your status.\"\nb. When Annie Farmer posted a Tweet thanking you for your jury service, you Tweeted back \"Thanks for sharing my story.\"\nc. In early January, shortly after the trial was over, you posted the following message on Instagram: \"I can now tell everyone that I was a juror on the Ghislaine Maxwell trial.\"\n7. Did you want to be on the Maxwell jury?\na. Did you think it was important that you be on the Maxwell jury as a survivor of childhood sexual abuse?\nb. Did you view your role on the jury as someone who could provide the perspective of someone who had been abused as a child?\nc. Did you view the verdict as a triumph for victims over abusers?\nd. Was your intent to \"share your own story\" about being a juror on the Maxwell case after the trial was over?",
      "position": "middle"
    },
    {
      "type": "printed",
      "content": "2100689.3 DOJ-OGR-00009658",
      "position": "footer"
    }
  ],
  "entities": {
    "people": [
      "Alison J. Nathan",
      "Annie Farmer",
      "Ghislaine Maxwell"
    ],
    "organizations": [
      "The Independent"
    ],
    "locations": [],
    "dates": [
      "March 1, 2022",
      "03/01/22",
      "early January"
    ],
    "reference_numbers": [
      "1:20-cr-00330-PAE",
      "636",
      "2100689.3",
      "DOJ-OGR-00009658"
    ]
  },
  "additional_notes": "The document appears to be a court transcript or a legal document related to the Ghislaine Maxwell trial. The text is mostly printed, with no visible handwriting or stamps. The document is well-formatted and easy to read."
}