{
  "document_metadata": {
    "page_number": "24",
    "document_number": "A-5709",
    "date": "08/24/22",
    "document_type": "Court Document",
    "has_handwriting": false,
    "has_stamps": false
  },
  "full_text": "Case 1:20-cr-00336-PAE Document 616 Filed 08/24/22 Page 24 of 130\nA-5709\n252\nC2GFDAU1 Brune - direct\n1 long time prior to the start of the criminal case, correct?\n2 A. I have represented him since 2004.\n3 Q. And you've gotten close to him as a person, correct?\n4 A. Yes.\n5 Q. And you wanted to obtain an acquittal for him on a\n6 professional level, is that right?\n7 A. Both on a personal and professional level.\n8 Q. And on a personal level because you like and care about him\n9 as a person, correct?\n10 A. And I believe in his innocence.\n11 Q. But you like and care about him as a person?\n12 A. I do.\n13 Q. Now, with regard to the hierarchy of Brune & Richard, as\n14 the named partners I would take it that you and Ms. Richard are\n15 basically at the top of the heap there?\n16 A. Well, we try to treat everyone with respect, but you're\n17 right, it's our firm in the sense that we're the named partners\n18 and we're certainly at the top of the hierarchy.\n19 Q. And everyone answers to you on your particular cases who\n20 work for you, correct?\n21 A. That's typically the way it's structured.\n22 Q. And you are the ultimate decision maker?\n23 A. Not on every case, but on those where I'm the lead counsel\n24 working, yes.\n25 Q. And that was true of this case, correct?\nSOUTHERN DISTRICT REPORTERS, P.C.\n(212) 805-0300\nDOJ-OGR-00009313",
  "text_blocks": [
    {
      "type": "printed",
      "content": "Case 1:20-cr-00336-PAE Document 616 Filed 08/24/22 Page 24 of 130",
      "position": "header"
    },
    {
      "type": "printed",
      "content": "A-5709",
      "position": "header"
    },
    {
      "type": "printed",
      "content": "252\nC2GFDAU1 Brune - direct",
      "position": "header"
    },
    {
      "type": "printed",
      "content": "1 long time prior to the start of the criminal case, correct?\n2 A. I have represented him since 2004.\n3 Q. And you've gotten close to him as a person, correct?\n4 A. Yes.\n5 Q. And you wanted to obtain an acquittal for him on a\n6 professional level, is that right?\n7 A. Both on a personal and professional level.\n8 Q. And on a personal level because you like and care about him\n9 as a person, correct?\n10 A. And I believe in his innocence.\n11 Q. But you like and care about him as a person?\n12 A. I do.\n13 Q. Now, with regard to the hierarchy of Brune & Richard, as\n14 the named partners I would take it that you and Ms. Richard are\n15 basically at the top of the heap there?\n16 A. Well, we try to treat everyone with respect, but you're\n17 right, it's our firm in the sense that we're the named partners\n18 and we're certainly at the top of the hierarchy.\n19 Q. And everyone answers to you on your particular cases who\n20 work for you, correct?\n21 A. That's typically the way it's structured.\n22 Q. And you are the ultimate decision maker?\n23 A. Not on every case, but on those where I'm the lead counsel\n24 working, yes.\n25 Q. And that was true of this case, correct?",
      "position": "main"
    },
    {
      "type": "printed",
      "content": "SOUTHERN DISTRICT REPORTERS, P.C.\n(212) 805-0300",
      "position": "footer"
    },
    {
      "type": "printed",
      "content": "DOJ-OGR-00009313",
      "position": "footer"
    }
  ],
  "entities": {
    "people": [
      "Brune",
      "Richard",
      "Ms. Richard"
    ],
    "organizations": [
      "Brune & Richard",
      "SOUTHERN DISTRICT REPORTERS, P.C."
    ],
    "locations": [],
    "dates": [
      "08/24/22",
      "2004"
    ],
    "reference_numbers": [
      "1:20-cr-00336-PAE",
      "616",
      "A-5709",
      "DOJ-OGR-00009313"
    ]
  },
  "additional_notes": "The document appears to be a court transcript with a clear and legible format. There are no visible redactions or damage."
}