{
  "document_metadata": {
    "page_number": "1",
    "document_number": "604",
    "date": "02/17/22",
    "document_type": "Court Document",
    "has_handwriting": true,
    "has_stamps": false
  },
  "full_text": "Case 1:20-cr-00330-PAE Document 604 Filed 02/17/22 Page 1 of 6 USDC SDNY DOCUMENT ELECTRONICALLY FILED DOC #: DATE FILED: 2/17/22 UNITED STATES DISTRICT COURT FOR THE SOUTHERN DISTRICT OF NEW YORK UNITED STATES OF AMERICA, Plaintiff, v. GHISLAINE MAXWELL Defendant. Case No. 20-CR-330 (AJN) MOTION FOR LEAVE TO FILE AN AMICUS CURIAE BRIEF The National Association of Criminal Defense Lawyers (\"NACDL\"), through undersigned counsel, moves the Court for leave to file an amicus brief according to the instructions in the Court's February 11, 2022 order. In support of this motion, proposed amicus states as follows: 1. NACDL is a nonprofit voluntary professional bar association made up of and working on behalf of criminal defense attorneys to ensure justice and due process for those accused of crime or misconduct. 2. NACDL was founded in 1958. It has a nationwide membership of approximately 10,000 direct members in 28 countries, and 90 state, provincial and local affiliate organizations totaling approximately 40,000 attorneys. NACDL's members include private criminal defense lawyers, public defenders, military defense counsel, and law professors. 3. NACDL files numerous amicus briefs each year in the Supreme Court, the Second Circuit Court of Appeals, and other courts, seeking to address issues of broad importance to criminal defendants, criminal defense lawyers, and the criminal justice system as a whole. It does not ordinarily file in the district court but seeks leave to do so here pursuant to the approval The request for leave to file an amicus brief in accordance with this Court's February 11, 2022 order is GRANTED. SO ORDERED. Alison J. Nathan 2/17/22 DOJ-OGR-00008966",
  "text_blocks": [
    {
      "type": "printed",
      "content": "Case 1:20-cr-00330-PAE Document 604 Filed 02/17/22 Page 1 of 6",
      "position": "header"
    },
    {
      "type": "printed",
      "content": "USDC SDNY DOCUMENT ELECTRONICALLY FILED DOC #: DATE FILED: 2/17/22",
      "position": "header"
    },
    {
      "type": "printed",
      "content": "UNITED STATES DISTRICT COURT FOR THE SOUTHERN DISTRICT OF NEW YORK",
      "position": "header"
    },
    {
      "type": "printed",
      "content": "UNITED STATES OF AMERICA, Plaintiff, v. GHISLAINE MAXWELL Defendant. Case No. 20-CR-330 (AJN)",
      "position": "top"
    },
    {
      "type": "printed",
      "content": "MOTION FOR LEAVE TO FILE AN AMICUS CURIAE BRIEF",
      "position": "top"
    },
    {
      "type": "printed",
      "content": "The National Association of Criminal Defense Lawyers (\"NACDL\"), through undersigned counsel, moves the Court for leave to file an amicus brief according to the instructions in the Court's February 11, 2022 order. In support of this motion, proposed amicus states as follows:",
      "position": "middle"
    },
    {
      "type": "printed",
      "content": "1. NACDL is a nonprofit voluntary professional bar association made up of and working on behalf of criminal defense attorneys to ensure justice and due process for those accused of crime or misconduct.",
      "position": "middle"
    },
    {
      "type": "printed",
      "content": "2. NACDL was founded in 1958. It has a nationwide membership of approximately 10,000 direct members in 28 countries, and 90 state, provincial and local affiliate organizations totaling approximately 40,000 attorneys. NACDL's members include private criminal defense lawyers, public defenders, military defense counsel, and law professors.",
      "position": "middle"
    },
    {
      "type": "printed",
      "content": "3. NACDL files numerous amicus briefs each year in the Supreme Court, the Second Circuit Court of Appeals, and other courts, seeking to address issues of broad importance to criminal defendants, criminal defense lawyers, and the criminal justice system as a whole. It does not ordinarily file in the district court but seeks leave to do so here pursuant to the approval",
      "position": "middle"
    },
    {
      "type": "handwritten",
      "content": "Alison J. Nathan 2/17/22",
      "position": "bottom"
    },
    {
      "type": "printed",
      "content": "The request for leave to file an amicus brief in accordance with this Court's February 11, 2022 order is GRANTED. SO ORDERED.",
      "position": "bottom"
    },
    {
      "type": "printed",
      "content": "DOJ-OGR-00008966",
      "position": "footer"
    }
  ],
  "entities": {
    "people": [
      "Ghislaine Maxwell",
      "Alison J. Nathan"
    ],
    "organizations": [
      "National Association of Criminal Defense Lawyers",
      "United States District Court for the Southern District of New York",
      "Supreme Court",
      "Second Circuit Court of Appeals"
    ],
    "locations": [
      "New York"
    ],
    "dates": [
      "02/17/22",
      "February 11, 2022",
      "1958"
    ],
    "reference_numbers": [
      "Case 1:20-cr-00330-PAE",
      "Document 604",
      "Case No. 20-CR-330 (AJN)",
      "DOJ-OGR-00008966"
    ]
  },
  "additional_notes": "The document appears to be a court filing with a handwritten signature. The text is mostly printed, with some formatting indicating headers and footers."
}