{
  "document_metadata": {
    "page_number": "1 of 29",
    "document_number": "674",
    "date": "06/24/22",
    "document_type": "Letter",
    "has_handwriting": false,
    "has_stamps": true
  },
  "full_text": "Case 1:20-cr-00330-PAE Document 674 Filed 06/24/22 Page 1 of 29 U.S. Department of Justice United States Attorney Southern District of New York The Silvio J. Mollo Building One Saint Andrew's Plaza New York, New York 10007 June 24, 2022 By ECF The Honorable Alison J. Nathan, Sitting by Designation United States District Court Southern District of New York United States Courthouse 40 Foley Square New York, New York 10007 Re: United States v. Ghislaine Maxwell, S2 20 Cr. 330 (AJN) Dear Judge Nathan: The Government respectfully submits this letter in response to the Court's June 24, 2022 Order directing the Government to promptly docket the written victim impact statements it has received. Enclosed please find victim impact statements from Annie Farmer, Kate, Virginia Roberts Giuffre, Maria Farmer, Teresa Helm, Juliette Bryant, and Sarah Ransome. Respectfully submitted, DAMIAN WILLIAMS United States Attorney By: s/ Maurene Comey / Alison Moe Lara Pomerantz / Andrew Rohrbach Assistant United States Attorneys Southern District of New York Cc: Defense Counsel (by ECF) DOJ-OGR-00010663",
  "text_blocks": [
    {
      "type": "printed",
      "content": "Case 1:20-cr-00330-PAE Document 674 Filed 06/24/22 Page 1 of 29",
      "position": "header"
    },
    {
      "type": "printed",
      "content": "U.S. Department of Justice United States Attorney Southern District of New York The Silvio J. Mollo Building One Saint Andrew's Plaza New York, New York 10007 June 24, 2022",
      "position": "top"
    },
    {
      "type": "printed",
      "content": "By ECF The Honorable Alison J. Nathan, Sitting by Designation United States District Court Southern District of New York United States Courthouse 40 Foley Square New York, New York 10007",
      "position": "middle"
    },
    {
      "type": "printed",
      "content": "Re: United States v. Ghislaine Maxwell, S2 20 Cr. 330 (AJN) Dear Judge Nathan: The Government respectfully submits this letter in response to the Court's June 24, 2022 Order directing the Government to promptly docket the written victim impact statements it has received. Enclosed please find victim impact statements from Annie Farmer, Kate, Virginia Roberts Giuffre, Maria Farmer, Teresa Helm, Juliette Bryant, and Sarah Ransome.",
      "position": "middle"
    },
    {
      "type": "printed",
      "content": "Respectfully submitted, DAMIAN WILLIAMS United States Attorney By: s/ Maurene Comey / Alison Moe Lara Pomerantz / Andrew Rohrbach Assistant United States Attorneys Southern District of New York",
      "position": "middle"
    },
    {
      "type": "printed",
      "content": "Cc: Defense Counsel (by ECF) DOJ-OGR-00010663",
      "position": "bottom"
    },
    {
      "type": "stamp",
      "content": "DOJ-OGR-00010663",
      "position": "footer"
    }
  ],
  "entities": {
    "people": [
      "Alison J. Nathan",
      "Ghislaine Maxwell",
      "Annie Farmer",
      "Kate",
      "Virginia Roberts Giuffre",
      "Maria Farmer",
      "Teresa Helm",
      "Juliette Bryant",
      "Sarah Ransome",
      "Damian Williams",
      "Maurene Comey",
      "Alison Moe",
      "Lara Pomerantz",
      "Andrew Rohrbach"
    ],
    "organizations": [
      "U.S. Department of Justice",
      "United States Attorney",
      "United States District Court",
      "Southern District of New York"
    ],
    "locations": [
      "New York",
      "The Silvio J. Mollo Building",
      "One Saint Andrew's Plaza",
      "United States Courthouse",
      "40 Foley Square"
    ],
    "dates": [
      "June 24, 2022"
    ],
    "reference_numbers": [
      "1:20-cr-00330-PAE",
      "Document 674",
      "S2 20 Cr. 330 (AJN)",
      "DOJ-OGR-00010663"
    ]
  },
  "additional_notes": "The document appears to be a formal letter from the U.S. Department of Justice to the Honorable Alison J. Nathan regarding the case United States v. Ghislaine Maxwell. The letter is typed and includes a stamp with the reference number DOJ-OGR-00010663."
}