{
  "document_metadata": {
    "page_number": "21",
    "document_number": "732",
    "date": "07/14/22",
    "document_type": "court document",
    "has_handwriting": false,
    "has_stamps": false
  },
  "full_text": "Case 1:20-cr-00330-PAE Document 732 Filed 07/14/22 Page 21 of 25 The Honorable Alison J. Nathan November 22, 2021 Page 21 Witness-3 is Finally, Accuser-4 has widely publicized her account of being abused by Mr. Epstein, an account that only very recently came to include Ms. Maxwell. Accuser-4 was first contacted by the FBI in 2007. She was interviewed on August 7, 2007, by Special Agents Nesbitt Kuyrkendall and Jason Richards and asked the alleged abuse. According to Accuser-4, during that interview, she was recruited to perform sex acts with Mr. Epstein by Ms. Giuffre in the 2002-2003 timeframe. Accuser-4 did not identify Ms. Maxwell as someone who recruited her, groomed her, or otherwise interacted with her in Palm Beach, Florida, or any other location. Accuser-4 identified Sarah Kellen as someone she interacted with and who took nude photographs of her at Mr. Epstein's direction. She advised the agents that she became pregnant in 2003 and moved to Georgia. After her FBI interview, DOJ-OGR-0001144",
  "text_blocks": [
    {
      "type": "printed",
      "content": "Case 1:20-cr-00330-PAE Document 732 Filed 07/14/22 Page 21 of 25",
      "position": "header"
    },
    {
      "type": "printed",
      "content": "The Honorable Alison J. Nathan November 22, 2021 Page 21",
      "position": "header"
    },
    {
      "type": "printed",
      "content": "Witness-3 is",
      "position": "top"
    },
    {
      "type": "printed",
      "content": "Finally, Accuser-4 has widely publicized her account of being abused by Mr. Epstein, an account that only very recently came to include Ms. Maxwell. Accuser-4 was first contacted by the FBI in 2007. She was interviewed on August 7, 2007, by Special Agents Nesbitt Kuyrkendall and Jason Richards and asked the alleged abuse. According to Accuser-4, during that interview, she was recruited to perform sex acts with Mr. Epstein by Ms. Giuffre in the 2002-2003 timeframe. Accuser-4 did not identify Ms. Maxwell as someone who recruited her, groomed her, or otherwise interacted with her in Palm Beach, Florida, or any other location. Accuser-4 identified Sarah Kellen as someone she interacted with and who took nude photographs of her at Mr. Epstein's direction. She advised the agents that she became pregnant in 2003 and moved to Georgia. After her FBI interview,",
      "position": "middle"
    },
    {
      "type": "printed",
      "content": "DOJ-OGR-0001144",
      "position": "footer"
    }
  ],
  "entities": {
    "people": [
      "Alison J. Nathan",
      "Accuser-4",
      "Mr. Epstein",
      "Ms. Maxwell",
      "Nesbitt Kuyrkendall",
      "Jason Richards",
      "Ms. Giuffre",
      "Sarah Kellen"
    ],
    "organizations": [
      "FBI"
    ],
    "locations": [
      "Palm Beach",
      "Florida",
      "Georgia"
    ],
    "dates": [
      "November 22, 2021",
      "2007",
      "August 7, 2007",
      "2002",
      "2003",
      "07/14/22"
    ],
    "reference_numbers": [
      "1:20-cr-00330-PAE",
      "732",
      "DOJ-OGR-0001144"
    ]
  },
  "additional_notes": "The document contains redactions, indicated by black bars, likely for sensitive or personal information."
}