{
  "document_metadata": {
    "page_number": "246",
    "document_number": "A-5703",
    "date": null,
    "document_type": "Hearing Transcript",
    "has_handwriting": false,
    "has_stamps": false
  },
  "full_text": "C2GFDAU1 Hearing 246\n1 called as a witness by the Government,\n2 having been duly sworn, testified as follows:\n3 THE COURT: Take a seat, state your full name and\n4 spell your last name slowly for the court reporter.\n5 THE WITNESS: My name is Susan Elizabeth Brune. My\n6 last name is spelled B-r-u-n-e.\n7 THE COURT: You may inquire, Ms. Davis.\n8 MS. DAVIS: Thank you, your Honor.\n9 DIRECT EXAMINATION\n10 BY MS. DAVIS:\n11 Q. Good morning Ms. Brune.\n12 A. Good morning.\n13 Q. Are you represented by counsel for purposes of this\n14 hearing?\n15 A. No.\n16 Q. You went to Harvard Law School, correct?\n17 A. Correct.\n18 Q. Graduating in 1988?\n19 A. That's right.\n20 Q. So you've been a practicing lawyer for almost 25 years, is\n21 that right?\n22 A. That's right.\n23 Q. And you're a member of the New York Bar?\n24 A. I am.\n25 Q. And you were an Assistant United States Attorney for\nSOUTHERN DISTRICT REPORTERS, P.C.\n(212) 805-0300\nDOJ-OGR-00009986",
  "text_blocks": [
    {
      "type": "printed",
      "content": "C2GFDAU1 Hearing 246",
      "position": "header"
    },
    {
      "type": "printed",
      "content": "1 called as a witness by the Government,\n2 having been duly sworn, testified as follows:\n3 THE COURT: Take a seat, state your full name and\n4 spell your last name slowly for the court reporter.\n5 THE WITNESS: My name is Susan Elizabeth Brune. My\n6 last name is spelled B-r-u-n-e.\n7 THE COURT: You may inquire, Ms. Davis.\n8 MS. DAVIS: Thank you, your Honor.\n9 DIRECT EXAMINATION\n10 BY MS. DAVIS:\n11 Q. Good morning Ms. Brune.\n12 A. Good morning.\n13 Q. Are you represented by counsel for purposes of this\n14 hearing?\n15 A. No.\n16 Q. You went to Harvard Law School, correct?\n17 A. Correct.\n18 Q. Graduating in 1988?\n19 A. That's right.\n20 Q. So you've been a practicing lawyer for almost 25 years, is\n21 that right?\n22 A. That's right.\n23 Q. And you're a member of the New York Bar?\n24 A. I am.\n25 Q. And you were an Assistant United States Attorney for",
      "position": "main"
    },
    {
      "type": "printed",
      "content": "SOUTHERN DISTRICT REPORTERS, P.C.\n(212) 805-0300",
      "position": "footer"
    },
    {
      "type": "printed",
      "content": "DOJ-OGR-00009986",
      "position": "footer"
    }
  ],
  "entities": {
    "people": [
      "Susan Elizabeth Brune",
      "Ms. Davis"
    ],
    "organizations": [
      "Harvard Law School",
      "New York Bar",
      "SOUTHERN DISTRICT REPORTERS, P.C.",
      "United States Attorney"
    ],
    "locations": [
      "New York"
    ],
    "dates": [
      "1988"
    ],
    "reference_numbers": [
      "A-5703",
      "DOJ-OGR-00009986"
    ]
  },
  "additional_notes": "The document is a transcript of a hearing. The text is clear and legible. There are no visible redactions or damage."
}