{
  "document_metadata": {
    "page_number": "163",
    "document_number": "688",
    "date": "06/29/22",
    "document_type": "Juror Questionnaire",
    "has_handwriting": true,
    "has_stamps": false
  },
  "full_text": "Case 1:20-cr-00330-PAE Document 688 Filed 06/29/22 Page 163 of 353 Juror ID: 48 28b. If yes to 28, would this affect your ability to serve as a fair and impartial juror in this case? Yes No 28c. If yes to 28b, please explain: 29. Do you know or have any association—professional, business, or social, direct or indirect—with any member of the staff of the United States Attorney's Office for the Southern District of New York? Yes No 29a. If yes, please explain: 29b. If yes to 29, would this affect your ability to serve as a fair and impartial juror in this case? Yes No 29c. If yes to 29b, please explain: 30. Do you know or have any association—professional, business, or social, direct or indirect—with the Federal Bureau of Investigation, commonly known as the FBI? Yes No 30a. If yes, please explain: -15- DOJ-OGR-00010916",
  "text_blocks": [
    {
      "type": "printed",
      "content": "Case 1:20-cr-00330-PAE Document 688 Filed 06/29/22 Page 163 of 353",
      "position": "header"
    },
    {
      "type": "handwritten",
      "content": "48",
      "position": "header"
    },
    {
      "type": "printed",
      "content": "28b. If yes to 28, would this affect your ability to serve as a fair and impartial juror in this case? Yes No",
      "position": "middle"
    },
    {
      "type": "printed",
      "content": "28c. If yes to 28b, please explain:",
      "position": "middle"
    },
    {
      "type": "printed",
      "content": "29. Do you know or have any association—professional, business, or social, direct or indirect—with any member of the staff of the United States Attorney's Office for the Southern District of New York? Yes No",
      "position": "middle"
    },
    {
      "type": "handwritten",
      "content": "No",
      "position": "middle"
    },
    {
      "type": "printed",
      "content": "29a. If yes, please explain:",
      "position": "middle"
    },
    {
      "type": "printed",
      "content": "29b. If yes to 29, would this affect your ability to serve as a fair and impartial juror in this case? Yes No",
      "position": "middle"
    },
    {
      "type": "printed",
      "content": "29c. If yes to 29b, please explain:",
      "position": "middle"
    },
    {
      "type": "printed",
      "content": "30. Do you know or have any association—professional, business, or social, direct or indirect—with the Federal Bureau of Investigation, commonly known as the FBI? Yes No",
      "position": "middle"
    },
    {
      "type": "handwritten",
      "content": "No",
      "position": "middle"
    },
    {
      "type": "printed",
      "content": "30a. If yes, please explain:",
      "position": "middle"
    },
    {
      "type": "printed",
      "content": "-15-",
      "position": "footer"
    },
    {
      "type": "printed",
      "content": "DOJ-OGR-00010916",
      "position": "footer"
    }
  ],
  "entities": {
    "people": [],
    "organizations": [
      "United States Attorney's Office",
      "Federal Bureau of Investigation"
    ],
    "locations": [
      "Southern District of New York"
    ],
    "dates": [
      "06/29/22"
    ],
    "reference_numbers": [
      "1:20-cr-00330-PAE",
      "688",
      "48",
      "DOJ-OGR-00010916"
    ]
  },
  "additional_notes": "The document is a juror questionnaire with some handwritten responses. The juror ID is 48. The document is part of a larger case file."
}