{
  "document_metadata": {
    "page_number": "5",
    "document_number": "632",
    "date": "03/07/22",
    "document_type": "Declaration",
    "has_handwriting": false,
    "has_stamps": false
  },
  "full_text": "Case 1:20-cr-00330-PAE Document 632 Filed 03/07/22 Page 5 of 8\n\nUNITED STATES DISTRICT COURT SOUTHERN DISTRICT OF NEW YORK\n------------------------------------X\nUnited States : DECLARATION\nv. : S2 20 Cr. 330 (AJN)\nGhislaine Maxwell :\n------------------------------------X\n\nState of New York County of New York\nLara Pomerantz, pursuant to Title 28, United States Code, Section 1746, hereby declares under penalty of perjury:\n1. I am an Assistant United States Attorney in the office of DAMIAN WILLIAMS, United States Attorney for the Southern District of New York, and as such I am one of the Assistant United States Attorneys responsible for the prosecution United States v. Ghislaine Maxwell, S2 20 Cr. 330 (AJN).\n2. This Declaration is made in support of the application by the United States Attorney for the Southern District of New York for an order pursuant to Title 18, United States Code, Sections 6002 and 6003 directing to give testimony at the March 8, 2022 hearing in United States v. Ghislaine Maxwell, S2 20 Cr. 330 (AJN).\n3. has refused to testify on the basis of his privilege against self-incrimination;\n4. Upon information and belief, can give relevant testimony before in the above-mentioned matter, which testimony may be necessary to the protection of the public interest.\n5. This application for immunity is made in good faith. Other than as may be\n1\nDOJ-OGR-00009630",
  "text_blocks": [
    {
      "type": "printed",
      "content": "Case 1:20-cr-00330-PAE Document 632 Filed 03/07/22 Page 5 of 8",
      "position": "header"
    },
    {
      "type": "printed",
      "content": "UNITED STATES DISTRICT COURT SOUTHERN DISTRICT OF NEW YORK",
      "position": "top"
    },
    {
      "type": "printed",
      "content": "------------------------------------X\nUnited States : DECLARATION\nv. : S2 20 Cr. 330 (AJN)\nGhislaine Maxwell :\n------------------------------------X",
      "position": "top"
    },
    {
      "type": "printed",
      "content": "State of New York County of New York",
      "position": "middle"
    },
    {
      "type": "printed",
      "content": "Lara Pomerantz, pursuant to Title 28, United States Code, Section 1746, hereby declares under penalty of perjury:",
      "position": "middle"
    },
    {
      "type": "printed",
      "content": "1. I am an Assistant United States Attorney in the office of DAMIAN WILLIAMS, United States Attorney for the Southern District of New York, and as such I am one of the Assistant United States Attorneys responsible for the prosecution United States v. Ghislaine Maxwell, S2 20 Cr. 330 (AJN).",
      "position": "middle"
    },
    {
      "type": "printed",
      "content": "2. This Declaration is made in support of the application by the United States Attorney for the Southern District of New York for an order pursuant to Title 18, United States Code, Sections 6002 and 6003 directing to give testimony at the March 8, 2022 hearing in United States v. Ghislaine Maxwell, S2 20 Cr. 330 (AJN).",
      "position": "middle"
    },
    {
      "type": "printed",
      "content": "3. has refused to testify on the basis of his privilege against self-incrimination;",
      "position": "middle"
    },
    {
      "type": "printed",
      "content": "4. Upon information and belief, can give relevant testimony before in the above-mentioned matter, which testimony may be necessary to the protection of the public interest.",
      "position": "middle"
    },
    {
      "type": "printed",
      "content": "5. This application for immunity is made in good faith. Other than as may be",
      "position": "middle"
    },
    {
      "type": "printed",
      "content": "1",
      "position": "footer"
    },
    {
      "type": "printed",
      "content": "DOJ-OGR-00009630",
      "position": "footer"
    }
  ],
  "entities": {
    "people": [
      "Lara Pomerantz",
      "DAMIAN WILLIAMS",
      "Ghislaine Maxwell"
    ],
    "organizations": [
      "UNITED STATES DISTRICT COURT",
      "SOUTHERN DISTRICT OF NEW YORK",
      "United States Attorney"
    ],
    "locations": [
      "New York"
    ],
    "dates": [
      "03/07/22",
      "March 8, 2022"
    ],
    "reference_numbers": [
      "1:20-cr-00330-PAE",
      "Document 632",
      "S2 20 Cr. 330 (AJN)",
      "DOJ-OGR-00009630"
    ]
  },
  "additional_notes": "The document appears to be a formal declaration in a court case, with some redacted information."
}