{
  "document_metadata": {
    "page_number": "127",
    "document_number": "1:20-cr-00303-PAE Document 611 Filed 02/24/22",
    "date": "02/24/22",
    "document_type": "court transcript",
    "has_handwriting": false,
    "has_stamps": false
  },
  "full_text": "Case 1:20-cr-00303-PAE Document 611 Filed 02/24/22 Page 127 of 130 A-5812 C2GFDAU3 Edelstein - redirect 355 1 A. Yes. 2 THE COURT: Mr. Schectman? 3 MR. SCHECTMAN: And I take it because you thought it 4 was in conceivable that this was the same person. 5 THE WITNESS: That's right. 6 THE COURT: Anything further, Mr. Okula? 7 MR. OKULA: Nothing, thank you, your honor. 8 MS. DAVIS: Just one housekeeping matter, your Honor? 9 THE COURT: We don't need housekeeping. 10 MS. DAVIS: It's in regard to one of the exhibits we 11 want to move into evidence. 12 THE COURT: Let's complete the inquiry, Ms. Davis, 13 that's the way it proceeds. I have a few questions for the 14 witness. 15 MS. DAVIS: I apologize, your Honor. 16 THE COURT: Ms. Edelstein, I want to put a question to 17 you that I put to Ms. Brune. Focusing on the July 21 letter to 18 the Court, would your law firm have disclosed the information 19 set forth in that letter and the investigation of Juror No. 1 20 if the Court had not inquired or the government failed to raise 21 the waiver issue? 22 THE WITNESS: I think by that point, I mean, I think 23 yes, that we had thought that it would come out at some point 24 during -- 25 (Continued next page) SOUTHERN DISTRICT REPORTERS, P.C. (212) 805-0300 DOJ-OGR-00009416",
  "text_blocks": [
    {
      "type": "printed",
      "content": "Case 1:20-cr-00303-PAE Document 611 Filed 02/24/22 Page 127 of 130",
      "position": "header"
    },
    {
      "type": "printed",
      "content": "A-5812",
      "position": "header"
    },
    {
      "type": "printed",
      "content": "C2GFDAU3 Edelstein - redirect 355",
      "position": "header"
    },
    {
      "type": "printed",
      "content": "1 A. Yes. 2 THE COURT: Mr. Schectman? 3 MR. SCHECTMAN: And I take it because you thought it 4 was in conceivable that this was the same person. 5 THE WITNESS: That's right. 6 THE COURT: Anything further, Mr. Okula? 7 MR. OKULA: Nothing, thank you, your honor. 8 MS. DAVIS: Just one housekeeping matter, your Honor? 9 THE COURT: We don't need housekeeping. 10 MS. DAVIS: It's in regard to one of the exhibits we 11 want to move into evidence. 12 THE COURT: Let's complete the inquiry, Ms. Davis, 13 that's the way it proceeds. I have a few questions for the 14 witness. 15 MS. DAVIS: I apologize, your Honor. 16 THE COURT: Ms. Edelstein, I want to put a question to 17 you that I put to Ms. Brune. Focusing on the July 21 letter to 18 the Court, would your law firm have disclosed the information 19 set forth in that letter and the investigation of Juror No. 1 20 if the Court had not inquired or the government failed to raise 21 the waiver issue? 22 THE WITNESS: I think by that point, I mean, I think 23 yes, that we had thought that it would come out at some point 24 during -- 25 (Continued next page)",
      "position": "main content"
    },
    {
      "type": "printed",
      "content": "SOUTHERN DISTRICT REPORTERS, P.C. (212) 805-0300",
      "position": "footer"
    },
    {
      "type": "printed",
      "content": "DOJ-OGR-00009416",
      "position": "footer"
    }
  ],
  "entities": {
    "people": [
      "Schectman",
      "Okula",
      "Davis",
      "Edelstein",
      "Brune"
    ],
    "organizations": [
      "SOUTHERN DISTRICT REPORTERS, P.C."
    ],
    "locations": [],
    "dates": [
      "July 21"
    ],
    "reference_numbers": [
      "1:20-cr-00303-PAE",
      "611",
      "DOJ-OGR-00009416"
    ]
  },
  "additional_notes": "The document is a court transcript with a clear and legible format. The text is typed, and there are no visible handwritten notes or stamps. The document appears to be a continuation of a previous page, as indicated by the '(Continued next page)' notation at the bottom."
}