{
  "document_metadata": {
    "page_number": "9",
    "document_number": "711",
    "date": "07/12/22",
    "document_type": "court document",
    "has_handwriting": false,
    "has_stamps": false
  },
  "full_text": "Case 1:20-cr-00330-PAE Document 711 Filed 07/12/22 Page 9 of 11\n2174:18 - 2176:20 2194:20 - 2195:18 | 3514-012, p. 2, 3/4 way down | At that time, limited to massaging and talking about the foot massage. Do not remember the specifics re: what JE was saying. Do not remember it being sexualized or going beyond massaging JE foot. | Objection. This testimony is not inconsistent. The witness explained the ways in which she understood the massage to be sexualized and not sexualized, eliminating any inconsistency. Tr. 2176:1-5. To the extent the witness gave more details about what Epstein said during the massage in an earlier interview with the Government, she agreed to that fact on page 2195. | Government allowed to put on evidence that the massages were \"sexualized\" in re-direct, although witness had earlier told the government they were not.\n2182:19 - 2183:15 | 3514-012, p. 3, section \"GM massage of AF\" | GM massage of AF.... \"rubbed around breasts, not on her nipples or nipple area\"; \"was awkward and uncomfortable but not explicitly sexual - no touching of nipples, genitals, etc.\" | Objection. This testimony is not inconsistent. | Government allowed to put on evidence that the massages were \"sexualized\" in re-direct, although witness had earlier told the government they were not.\n2185:7 - 12 2185:21 - 2186:13 | 3514-012, p. 4, \"Incident in the bed\" | \"Do not remember it being a sexual touch - do not remember grabbing or touching her breasts or | Objection. This testimony is not inconsistent. The Court has already | Government allowed to put on evidence",
  "text_blocks": [
    {
      "type": "printed",
      "content": "Case 1:20-cr-00330-PAE Document 711 Filed 07/12/22 Page 9 of 11",
      "position": "header"
    },
    {
      "type": "printed",
      "content": "The table contents discussing testimony and objections.",
      "position": "middle"
    },
    {
      "type": "printed",
      "content": "9",
      "position": "footer"
    },
    {
      "type": "printed",
      "content": "DOJ-OGR-00011297",
      "position": "footer"
    }
  ],
  "entities": {
    "people": [
      "JE",
      "Epstein",
      "GM",
      "AF"
    ],
    "organizations": [
      "Government"
    ],
    "locations": [],
    "dates": [
      "07/12/22"
    ],
    "reference_numbers": [
      "1:20-cr-00330-PAE",
      "711",
      "3514-012",
      "2174:18 - 2176:20",
      "2194:20 - 2195:18",
      "2182:19 - 2183:15",
      "2185:7 - 12",
      "2185:21 - 2186:13"
    ]
  },
  "additional_notes": "The document appears to be a court transcript or legal document discussing witness testimony and objections related to a case involving Jeffrey Epstein. The document is well-formatted but contains legal jargon and references to specific court documents and testimony."
}