{
  "document_metadata": {
    "page_number": "318",
    "document_number": "A-5775",
    "date": null,
    "document_type": "Court Transcript",
    "has_handwriting": false,
    "has_stamps": false
  },
  "full_text": "C2GFDAU3 Brune - recross 318\n1 thinking about, well, what will happen if nobody ever raises\n2 it. But if nobody ever raised it, I don't think that I would\n3 have even been acting ethically if I said on behalf of my\n4 client, hey, here's an argument I don't even think is\n5 meritorious but the government has omitted to raise it so I on\n6 the defense side will raise it.\n7 THE COURT: All right. Any further inquiries?\n8 Ms. Davis or Mr. Schectman?\n9 MS. DAVIS: Can I have one brief followup on that,\n10 your Honor?\n11 THE COURT: Yes.\n12 MS. DAVIS: Can I just do it from right here?\n13 THE COURT: Yes.\n14 REDIRECT EXAMINATION\n15 BY MS. DAVIS:\n16 Q. Are you talking about facts or argument, Ms. Brune, when\n17 you say you wouldn't have -- are you saying you would not have\n18 disclosed the underlying facts or wouldn't have made the legal\n19 argument?\n20 A. If it was put in issue by the Court or by the government, I\n21 would have done and in fact did do what I did. It's a little\n22 tangled up. What I'm trying to say is, I would have laid it\n23 out, which is what I did.\n24 Q. The facts, though?\n25 A. Well, I also try to lay out the applicable law. I'm not\nSOUTHERN DISTRICT REPORTERS, P.C.\n(212) 805-0300\nDOJ-OGR-00010058",
  "text_blocks": [
    {
      "type": "printed",
      "content": "C2GFDAU3 Brune - recross 318",
      "position": "header"
    },
    {
      "type": "printed",
      "content": "1 thinking about, well, what will happen if nobody ever raises\n2 it. But if nobody ever raised it, I don't think that I would\n3 have even been acting ethically if I said on behalf of my\n4 client, hey, here's an argument I don't even think is\n5 meritorious but the government has omitted to raise it so I on\n6 the defense side will raise it.\n7 THE COURT: All right. Any further inquiries?\n8 Ms. Davis or Mr. Schectman?\n9 MS. DAVIS: Can I have one brief followup on that,\n10 your Honor?\n11 THE COURT: Yes.\n12 MS. DAVIS: Can I just do it from right here?\n13 THE COURT: Yes.\n14 REDIRECT EXAMINATION\n15 BY MS. DAVIS:\n16 Q. Are you talking about facts or argument, Ms. Brune, when\n17 you say you wouldn't have -- are you saying you would not have\n18 disclosed the underlying facts or wouldn't have made the legal\n19 argument?\n20 A. If it was put in issue by the Court or by the government, I\n21 would have done and in fact did do what I did. It's a little\n22 tangled up. What I'm trying to say is, I would have laid it\n23 out, which is what I did.\n24 Q. The facts, though?\n25 A. Well, I also try to lay out the applicable law. I'm not",
      "position": "main"
    },
    {
      "type": "printed",
      "content": "SOUTHERN DISTRICT REPORTERS, P.C.\n(212) 805-0300",
      "position": "footer"
    },
    {
      "type": "printed",
      "content": "DOJ-OGR-00010058",
      "position": "footer"
    }
  ],
  "entities": {
    "people": [
      "Ms. Brune",
      "Ms. Davis",
      "Mr. Schectman"
    ],
    "organizations": [
      "SOUTHERN DISTRICT REPORTERS, P.C.",
      "DOJ"
    ],
    "locations": [],
    "dates": [],
    "reference_numbers": [
      "A-5775",
      "C2GFDAU3",
      "DOJ-OGR-00010058"
    ]
  },
  "additional_notes": "The document appears to be a court transcript with a clear structure and formatting. The text is mostly printed, with no visible handwriting or stamps. The footer contains the name and contact information of the reporting agency and a reference number."
}