{
  "document_metadata": {
    "page_number": "9",
    "document_number": "645",
    "date": "03/11/22",
    "document_type": "court transcript",
    "has_handwriting": false,
    "has_stamps": false
  },
  "full_text": "Case 1:20-cr-00330-PAE Document 645 Filed 03/11/22 Page 9 of 50 M38TMAX1 9\n1 I don't know if anything was actually filed or anything done.\n2 There were no charges brought.\n3 Q. You said a family member, no longer a family member.\n4 Again, without listing names, what was the nature of the familial relationship?\n5 A. A stepbrother.\n6 Q. You said stepbrother?\n7 A. Yes.\n8 Q. I'm going to ask you to look at question 48B. Question 48B reads: If your answer to 48 was yes, do you believe this would affect your ability to serve fairly and impartially as a juror in this case?\n9 When you filled this out on November 4, you left that blank. What is an accurate answer to 48B?\n10 A. It would have been no, because it did not affect my ability to be fair and impartial at all.\n11 Q. I'm going to ask you to turn to page 13 of the questionnaire. Question 25 reads: Have you or any of your relatives or close friends ever been a victim of a crime?\n12 And you checked no when you filled this out on November 4. Is no an accurate answer?\n13 A. Looking back at it now, no, it's an incorrect answer.\n14 Q. Who would have an accurate answer have been?\n15 A. It would have been yes.\n16 Q. Yes self, yes friend or family?\n17 SOUTHERN DISTRICT REPORTERS, P.C. (212) 805-0300 DOJ-OGR-00010224",
  "text_blocks": [
    {
      "type": "printed",
      "content": "Case 1:20-cr-00330-PAE Document 645 Filed 03/11/22 Page 9 of 50 M38TMAX1 9",
      "position": "header"
    },
    {
      "type": "printed",
      "content": "1 I don't know if anything was actually filed or anything done.\n2 There were no charges brought.\n3 Q. You said a family member, no longer a family member.\n4 Again, without listing names, what was the nature of the familial relationship?\n5 A. A stepbrother.\n6 Q. You said stepbrother?\n7 A. Yes.\n8 Q. I'm going to ask you to look at question 48B. Question 48B reads: If your answer to 48 was yes, do you believe this would affect your ability to serve fairly and impartially as a juror in this case?\n9 When you filled this out on November 4, you left that blank. What is an accurate answer to 48B?\n10 A. It would have been no, because it did not affect my ability to be fair and impartial at all.\n11 Q. I'm going to ask you to turn to page 13 of the questionnaire. Question 25 reads: Have you or any of your relatives or close friends ever been a victim of a crime?\n12 And you checked no when you filled this out on November 4. Is no an accurate answer?\n13 A. Looking back at it now, no, it's an incorrect answer.\n14 Q. Who would have an accurate answer have been?\n15 A. It would have been yes.\n16 Q. Yes self, yes friend or family?",
      "position": "main"
    },
    {
      "type": "printed",
      "content": "SOUTHERN DISTRICT REPORTERS, P.C. (212) 805-0300",
      "position": "footer"
    },
    {
      "type": "printed",
      "content": "DOJ-OGR-00010224",
      "position": "footer"
    }
  ],
  "entities": {
    "people": [],
    "organizations": [
      "SOUTHERN DISTRICT REPORTERS, P.C."
    ],
    "locations": [],
    "dates": [
      "03/11/22",
      "November 4"
    ],
    "reference_numbers": [
      "1:20-cr-00330-PAE",
      "645",
      "48B",
      "25",
      "DOJ-OGR-00010224"
    ]
  },
  "additional_notes": "The document appears to be a court transcript with a clear and legible format. There are no visible redactions or damage."
}