{
  "document_metadata": {
    "page_number": "8",
    "document_number": "6988",
    "date": "10/06/21",
    "document_type": "court transcript",
    "has_handwriting": false,
    "has_stamps": false
  },
  "full_text": "Case2:20-cr-00808-RGK Document 6988 Filed 10/06/21 Page 815 of 623 L9L5ber1 paralegals, I will ask each of you to stand as I say your name so that the jurors can see you, the panelists can see you. So, I will note Mr. Schneider is part of the team but not present today and may not be present every day of the trial. Appropriate, Mr. DeMarco? MR. DeMARCO: Yes, Judge. THE COURT: OK. So Jesus Ortiz is the pronunciation. How about, Mr. Hobson, how do I pronounce no. Q? MR. HOBSON: I believe, your Honor, it is Vyacheslav, and the last name is Polosin. THE COURT: Vyacheslav Polosin. OK. Special Agent Stefano Braccini? MR. HOBSON: And he is in the courtroom. THE COURT: OK. I think that's it. Other issues to take up? MR. HOBSON: I don't think so, your Honor. THE COURT: Mr. DeMarco? MR. DeMARCO: No, your Honor. Not now. Judge, how much time do we have before we walk over? Maybe we could use this time efficiently, because I do have -- I raised with the government an issue I was going to raise with their first witness so you tell me. THE COURT: I was told around between 10:00 and 10:30 but we won't know until they actually call over so I'm happy to use the time and if we get the call, we will pause. SOUTHERN DISTRICT REPORTERS, P.C. (212) 805-0300 DOJ-OGR-00011123",
  "text_blocks": [
    {
      "type": "printed",
      "content": "Case2:20-cr-00808-RGK Document 6988 Filed 10/06/21 Page 815 of 623 L9L5ber1",
      "position": "header"
    },
    {
      "type": "printed",
      "content": "paralegals, I will ask each of you to stand as I say your name so that the jurors can see you, the panelists can see you. So, I will note Mr. Schneider is part of the team but not present today and may not be present every day of the trial. Appropriate, Mr. DeMarco? MR. DeMARCO: Yes, Judge. THE COURT: OK. So Jesus Ortiz is the pronunciation. How about, Mr. Hobson, how do I pronounce no. Q? MR. HOBSON: I believe, your Honor, it is Vyacheslav, and the last name is Polosin. THE COURT: Vyacheslav Polosin. OK. Special Agent Stefano Braccini? MR. HOBSON: And he is in the courtroom. THE COURT: OK. I think that's it. Other issues to take up? MR. HOBSON: I don't think so, your Honor. THE COURT: Mr. DeMarco? MR. DeMARCO: No, your Honor. Not now. Judge, how much time do we have before we walk over? Maybe we could use this time efficiently, because I do have -- I raised with the government an issue I was going to raise with their first witness so you tell me. THE COURT: I was told around between 10:00 and 10:30 but we won't know until they actually call over so I'm happy to use the time and if we get the call, we will pause.",
      "position": "main"
    },
    {
      "type": "printed",
      "content": "SOUTHERN DISTRICT REPORTERS, P.C. (212) 805-0300",
      "position": "footer"
    },
    {
      "type": "printed",
      "content": "DOJ-OGR-00011123",
      "position": "footer"
    }
  ],
  "entities": {
    "people": [
      "Mr. Schneider",
      "Mr. DeMarco",
      "Jesus Ortiz",
      "Mr. Hobson",
      "Vyacheslav Polosin",
      "Stefano Braccini"
    ],
    "organizations": [
      "SOUTHERN DISTRICT REPORTERS, P.C."
    ],
    "locations": [],
    "dates": [
      "10/06/21",
      "10:00",
      "10:30"
    ],
    "reference_numbers": [
      "Case2:20-cr-00808-RGK",
      "Document 6988",
      "DOJ-OGR-00011123"
    ]
  },
  "additional_notes": "The document appears to be a court transcript with a clear and readable format. There are no visible redactions or damage."
}