{
  "document_metadata": {
    "page_number": "3",
    "document_number": "702",
    "date": "07/12/22",
    "document_type": "court document",
    "has_handwriting": false,
    "has_stamps": false
  },
  "full_text": "Case 1:20-cr-00330-PAE Document 702 Filed 07/12/22 Page 3 of 4\nThe Honorable Alison J. Nathan\nDecember 17, 2021\nPage 3\nfrom an order of confinement under this section shall be disposed of as soon as practicable, but not later than thirty days from the filing of such appeal.\n(c) Whoever escapes or attempts to escape from the custody of any facility or from any place in which or to which he is confined pursuant to this section or section 4243 of title 18, or whoever rescues or attempts to rescue or instigates, aids, or assists the escape or attempt to escape of such a person, shall be subject to imprisonment for not more than three years, or a fine of not more than $10,000, or both.\n28 U.S.C. § 1826.\nThis Court also has authority to order the arrest of Ms. Bovino under the Material Witness Statute, 18 U.S.C. § 3144. That statute says:\nIf it appears from an affidavit filed by a party that the testimony of a person is material in a criminal proceeding, and if it is shown that it may become impracticable to secure the presence of the person by subpoena, a judicial officer may order the arrest of the person and treat the person in accordance with the provisions of section 3142 of this title.\n18 U.S.C. § 3144. The required affidavit is attached as Exhibit 3 to this letter.\nOn information and belief, this is the last known contact information for Ms. Bovino and her attorney:\nMs. Bovino:\n[REDACTED]\nCounsel:\nBecky S. James\nJames & Associates\n4500 Park Granada, Suite 202\nCalabasas, CA 91302\n310-492-5104\nbjames@jamesaa.com\nDOJ-OGR-00011199",
  "text_blocks": [
    {
      "type": "printed",
      "content": "Case 1:20-cr-00330-PAE Document 702 Filed 07/12/22 Page 3 of 4",
      "position": "header"
    },
    {
      "type": "printed",
      "content": "The Honorable Alison J. Nathan\nDecember 17, 2021\nPage 3",
      "position": "top"
    },
    {
      "type": "printed",
      "content": "from an order of confinement under this section shall be disposed of as soon as practicable, but not later than thirty days from the filing of such appeal.\n(c) Whoever escapes or attempts to escape from the custody of any facility or from any place in which or to which he is confined pursuant to this section or section 4243 of title 18, or whoever rescues or attempts to rescue or instigates, aids, or assists the escape or attempt to escape of such a person, shall be subject to imprisonment for not more than three years, or a fine of not more than $10,000, or both.",
      "position": "middle"
    },
    {
      "type": "printed",
      "content": "28 U.S.C. § 1826.",
      "position": "middle"
    },
    {
      "type": "printed",
      "content": "This Court also has authority to order the arrest of Ms. Bovino under the Material Witness Statute, 18 U.S.C. § 3144. That statute says:\nIf it appears from an affidavit filed by a party that the testimony of a person is material in a criminal proceeding, and if it is shown that it may become impracticable to secure the presence of the person by subpoena, a judicial officer may order the arrest of the person and treat the person in accordance with the provisions of section 3142 of this title.",
      "position": "middle"
    },
    {
      "type": "printed",
      "content": "18 U.S.C. § 3144. The required affidavit is attached as Exhibit 3 to this letter.",
      "position": "middle"
    },
    {
      "type": "printed",
      "content": "On information and belief, this is the last known contact information for Ms. Bovino and her attorney:",
      "position": "middle"
    },
    {
      "type": "printed",
      "content": "Ms. Bovino:\n[REDACTED]",
      "position": "middle"
    },
    {
      "type": "printed",
      "content": "Counsel:\nBecky S. James\nJames & Associates\n4500 Park Granada, Suite 202\nCalabasas, CA 91302\n310-492-5104\nbjames@jamesaa.com",
      "position": "bottom"
    },
    {
      "type": "printed",
      "content": "DOJ-OGR-00011199",
      "position": "footer"
    }
  ],
  "entities": {
    "people": [
      "Alison J. Nathan",
      "Ms. Bovino",
      "Becky S. James"
    ],
    "organizations": [
      "James & Associates"
    ],
    "locations": [
      "Calabasas, CA"
    ],
    "dates": [
      "December 17, 2021",
      "07/12/22"
    ],
    "reference_numbers": [
      "1:20-cr-00330-PAE",
      "Document 702",
      "28 U.S.C. § 1826",
      "18 U.S.C. § 3144",
      "18 U.S.C. § 3142",
      "Exhibit 3",
      "DOJ-OGR-00011199"
    ]
  },
  "additional_notes": "The document appears to be a court filing with a redacted section for Ms. Bovino's contact information."
}