{
  "document_metadata": {
    "page_number": "310 of 353",
    "document_number": "688",
    "date": "06/29/22",
    "document_type": "Jury Questionnaire",
    "has_handwriting": true,
    "has_stamps": false
  },
  "full_text": "Case 1:20-cr-00330-PAE Document 688 Filed 06/29/22 Page 310 of 353\nJuror ID: 119\n32a. If yes, please explain:\n\n\n\n\n\nPERSONAL RELATIONSHIP WITH CASE PARTICIPANTS\n33. The next subset of questions asks whether you or any member of your family or a close friend personally knows or has past or present dealings with individuals involved in this case. To \"personally know\" means to have some direct or personal knowledge or connection to the following individuals. If you have only heard the names through media or social media, for example, that is not personal knowledge.\n33a. Do you or does any member of your family or a close friend personally know or have past or present dealings with the Defendant in this case, Ghislaine Maxwell, or her family members?\nYes No\n33b. Do you or does any member of your family or a close friend personally know or have past or present dealings with Jeffrey Epstein?\nYes No\n33c. Do you or does any member of your family or a close friend personally know or have past or present dealings with the U.S. Attorney for the Southern District of New York, Damian Williams, the former Acting U.S. Attorney for the Southern District of New York, Audrey Strauss, or anyone else who works for or used to work for the U.S. Attorney's Office for the Southern District of New York?\nYes No\n33d. Do you or does any member of your family or a close friend personally know or have past or present dealings with any of the Assistant United States Attorneys who are prosecuting this case:\nMaurene Comey Yes No\nAllison Moe Yes No\nLara Pomerantz Yes No\nAndrew Rohrbach Yes No\n-17-\nDOJ-OGR-00011063",
  "text_blocks": [
    {
      "type": "printed",
      "content": "Case 1:20-cr-00330-PAE Document 688 Filed 06/29/22 Page 310 of 353",
      "position": "header"
    },
    {
      "type": "handwritten",
      "content": "119",
      "position": "margin"
    },
    {
      "type": "printed",
      "content": "Juror ID:",
      "position": "margin"
    },
    {
      "type": "printed",
      "content": "32a. If yes, please explain:",
      "position": "body"
    },
    {
      "type": "printed",
      "content": "PERSONAL RELATIONSHIP WITH CASE PARTICIPANTS",
      "position": "body"
    },
    {
      "type": "printed",
      "content": "33. The next subset of questions asks whether you or any member of your family or a close friend personally knows or has past or present dealings with individuals involved in this case. To \"personally know\" means to have some direct or personal knowledge or connection to the following individuals. If you have only heard the names through media or social media, for example, that is not personal knowledge.",
      "position": "body"
    },
    {
      "type": "printed",
      "content": "33a. Do you or does any member of your family or a close friend personally know or have past or present dealings with the Defendant in this case, Ghislaine Maxwell, or her family members?",
      "position": "body"
    },
    {
      "type": "handwritten",
      "content": "No",
      "position": "body"
    },
    {
      "type": "printed",
      "content": "33b. Do you or does any member of your family or a close friend personally know or have past or present dealings with Jeffrey Epstein?",
      "position": "body"
    },
    {
      "type": "handwritten",
      "content": "No",
      "position": "body"
    },
    {
      "type": "printed",
      "content": "33c. Do you or does any member of your family or a close friend personally know or have past or present dealings with the U.S. Attorney for the Southern District of New York, Damian Williams, the former Acting U.S. Attorney for the Southern District of New York, Audrey Strauss, or anyone else who works for or used to work for the U.S. Attorney's Office for the Southern District of New York?",
      "position": "body"
    },
    {
      "type": "handwritten",
      "content": "No",
      "position": "body"
    },
    {
      "type": "printed",
      "content": "33d. Do you or does any member of your family or a close friend personally know or have past or present dealings with any of the Assistant United States Attorneys who are prosecuting this case:",
      "position": "body"
    },
    {
      "type": "printed",
      "content": "Maurene Comey Yes No",
      "position": "body"
    },
    {
      "type": "handwritten",
      "content": "No",
      "position": "body"
    },
    {
      "type": "printed",
      "content": "Allison Moe Yes No",
      "position": "body"
    },
    {
      "type": "handwritten",
      "content": "No",
      "position": "body"
    },
    {
      "type": "printed",
      "content": "Lara Pomerantz Yes No",
      "position": "body"
    },
    {
      "type": "handwritten",
      "content": "No",
      "position": "body"
    },
    {
      "type": "printed",
      "content": "Andrew Rohrbach Yes No",
      "position": "body"
    },
    {
      "type": "handwritten",
      "content": "No",
      "position": "body"
    },
    {
      "type": "printed",
      "content": "-17-",
      "position": "footer"
    },
    {
      "type": "printed",
      "content": "DOJ-OGR-00011063",
      "position": "footer"
    }
  ],
  "entities": {
    "people": [
      "Ghislaine Maxwell",
      "Jeffrey Epstein",
      "Damian Williams",
      "Audrey Strauss",
      "Maurene Comey",
      "Allison Moe",
      "Lara Pomerantz",
      "Andrew Rohrbach"
    ],
    "organizations": [
      "U.S. Attorney's Office for the Southern District of New York"
    ],
    "locations": [
      "Southern District of New York"
    ],
    "dates": [
      "06/29/22"
    ],
    "reference_numbers": [
      "1:20-cr-00330-PAE",
      "688",
      "DOJ-OGR-00011063"
    ]
  },
  "additional_notes": "The document is a jury questionnaire with multiple choice questions and handwritten answers. The juror ID is 119. All answers are 'No'."
}