{
  "document_metadata": {
    "page_number": "6",
    "document_number": "700",
    "date": "07/12/22",
    "document_type": "Court Document",
    "has_handwriting": false,
    "has_stamps": false
  },
  "full_text": "Case 1:20-cr-00330-PAE Document 700 Filed 07/12/22 Page 6 of 6\n\nAlessi is therefore a witness able to authenticate the Government Exhibit 606. Although the manual itself is dated to 2005 on its face, Alessi is expected to testify that the exhibit is largely unchanged from the version he had when he received from the defendant and Epstein. He is therefore a witness with \"knowledge that a matter is what it is claimed to be,\" which \"is sufficient to satisfy [the authentication] standard.\" United States v. Gagliardi, 506 F.3d 140, 151 (2d Cir. 2007); see id. (\"Based on the[] testimony [that electronic communications were accurate], a reasonable juror could have found that the exhibits did represent those conversations, notwithstanding that the e-mails and online chats were editable.\").5\n\nRespectfully submitted,\n\nDAMIAN WILLIAMS\nUnited States Attorney\n\nBy: s/\nMaurene Comey\nAlison Moe\nLara Pomerantz\nAndrew Rohrbach\nAssistant United States Attorneys\nSouthern District of New York\n\nCc: Defense Counsel (by e-mail)\n\n5 The Government also expects another employee of Epstein's (\"Employee-2\") to also be able to authenticate the household manual.\n\n6\nDOJ-OGR-00011179",
  "text_blocks": [
    {
      "type": "printed",
      "content": "Case 1:20-cr-00330-PAE Document 700 Filed 07/12/22 Page 6 of 6",
      "position": "header"
    },
    {
      "type": "printed",
      "content": "Alessi is therefore a witness able to authenticate the Government Exhibit 606. Although the manual itself is dated to 2005 on its face, Alessi is expected to testify that the exhibit is largely unchanged from the version he had when he received from the defendant and Epstein. He is therefore a witness with \"knowledge that a matter is what it is claimed to be,\" which \"is sufficient to satisfy [the authentication] standard.\" United States v. Gagliardi, 506 F.3d 140, 151 (2d Cir. 2007); see id. (\"Based on the[] testimony [that electronic communications were accurate], a reasonable juror could have found that the exhibits did represent those conversations, notwithstanding that the e-mails and online chats were editable.\").5",
      "position": "top"
    },
    {
      "type": "printed",
      "content": "Respectfully submitted,",
      "position": "middle"
    },
    {
      "type": "printed",
      "content": "DAMIAN WILLIAMS\nUnited States Attorney",
      "position": "middle"
    },
    {
      "type": "printed",
      "content": "By: s/\nMaurene Comey\nAlison Moe\nLara Pomerantz\nAndrew Rohrbach\nAssistant United States Attorneys\nSouthern District of New York",
      "position": "middle"
    },
    {
      "type": "printed",
      "content": "Cc: Defense Counsel (by e-mail)",
      "position": "middle"
    },
    {
      "type": "printed",
      "content": "5 The Government also expects another employee of Epstein's (\"Employee-2\") to also be able to authenticate the household manual.",
      "position": "footer"
    },
    {
      "type": "printed",
      "content": "6",
      "position": "footer"
    },
    {
      "type": "printed",
      "content": "DOJ-OGR-00011179",
      "position": "footer"
    }
  ],
  "entities": {
    "people": [
      "Alessi",
      "Damian Williams",
      "Maurene Comey",
      "Alison Moe",
      "Lara Pomerantz",
      "Andrew Rohrbach",
      "Epstein"
    ],
    "organizations": [
      "United States Attorney",
      "Southern District of New York"
    ],
    "locations": [
      "New York"
    ],
    "dates": [
      "07/12/22",
      "2005",
      "2007"
    ],
    "reference_numbers": [
      "1:20-cr-00330-PAE",
      "Document 700",
      "Government Exhibit 606",
      "DOJ-OGR-00011179"
    ]
  },
  "additional_notes": "The document appears to be a court filing with a clear and legible text. There are no visible redactions or damage."
}