{
  "document_metadata": {
    "page_number": "83",
    "document_number": "741",
    "date": "08/10/22",
    "document_type": "court transcript",
    "has_handwriting": false,
    "has_stamps": false
  },
  "full_text": "Case 1:20-cr-00330-PAE Document 741 Filed 08/10/22 Page 83 of 106 96 LBTCMAX4 Visoski - direct was issued a cellphone. Q. During that same period between 1994 and 2004, how much notice would you typically receive before a flight on one of Mr. Epstein's planes? A. It was typically short notice. It could be a day notice. Probably -- a day notice at least, sometimes shorter notice, but it was -- it was short notice. Q. Again, focusing on that same period between 1994 and 2004, based on your observations of Ms. Maxwell and Mr. Epstein, did they appear to have a personal relationship? A. From what I could see, I thought it was more personal than business, yes. Q. What did you observe, for example, that gave you that impression? A. I guess it's the way you would talk to another person if you were closer. It was more of a smalltalk as far as thinking that they were together as opposed to, you know, boss or not. But it was just a conversation that I saw, really. Q. About how long did that romantic relationship last from what you observed? A. It probably went to the 2000s. Yeah, about the 2000s. I wouldn't even categorize romantic, but more couplish than anything else. I don't think I ever witnessed them kiss or hold hands kind of thing. Q. To your knowledge, did Mr. Epstein only fly by private SOUTHERN DISTRICT REPORTERS, P.C. (212) 805-0300 DOJ-OGR-00011748",
  "text_blocks": [
    {
      "type": "printed",
      "content": "Case 1:20-cr-00330-PAE Document 741 Filed 08/10/22 Page 83 of 106 96 LBTCMAX4 Visoski - direct",
      "position": "header"
    },
    {
      "type": "printed",
      "content": "was issued a cellphone. Q. During that same period between 1994 and 2004, how much notice would you typically receive before a flight on one of Mr. Epstein's planes? A. It was typically short notice. It could be a day notice. Probably -- a day notice at least, sometimes shorter notice, but it was -- it was short notice. Q. Again, focusing on that same period between 1994 and 2004, based on your observations of Ms. Maxwell and Mr. Epstein, did they appear to have a personal relationship? A. From what I could see, I thought it was more personal than business, yes. Q. What did you observe, for example, that gave you that impression? A. I guess it's the way you would talk to another person if you were closer. It was more of a smalltalk as far as thinking that they were together as opposed to, you know, boss or not. But it was just a conversation that I saw, really. Q. About how long did that romantic relationship last from what you observed? A. It probably went to the 2000s. Yeah, about the 2000s. I wouldn't even categorize romantic, but more couplish than anything else. I don't think I ever witnessed them kiss or hold hands kind of thing. Q. To your knowledge, did Mr. Epstein only fly by private",
      "position": "main"
    },
    {
      "type": "printed",
      "content": "SOUTHERN DISTRICT REPORTERS, P.C. (212) 805-0300",
      "position": "footer"
    },
    {
      "type": "printed",
      "content": "DOJ-OGR-00011748",
      "position": "footer"
    }
  ],
  "entities": {
    "people": [
      "Mr. Epstein",
      "Ms. Maxwell"
    ],
    "organizations": [
      "SOUTHERN DISTRICT REPORTERS, P.C."
    ],
    "locations": [],
    "dates": [
      "1994",
      "2004",
      "08/10/22",
      "2000s"
    ],
    "reference_numbers": [
      "1:20-cr-00330-PAE",
      "741",
      "DOJ-OGR-00011748"
    ]
  },
  "additional_notes": "The document appears to be a court transcript with a clear and readable format. There are no visible redactions or damage."
}