{
  "document_metadata": {
    "page_number": "330 of 353",
    "document_number": "688",
    "date": "06/29/22",
    "document_type": "Jury Questionnaire",
    "has_handwriting": true,
    "has_stamps": false
  },
  "full_text": "Case 1:20-cr-00330-PAE Document 688 Filed 06/29/22 Page 330 of 353\n\nJuror ID: 124\n\n9. Do you have any religious, philosophical, or other beliefs that would make you unable to render a verdict in a criminal case?\n\nYes No\n\n9a. If yes, please explain:\n\n\n\n\n\nBASIC LEGAL PRINCIPLES AND MEDIA RESTRICTIONS\n\n10. Under the law, the facts are for the jury to determine and the law is for the Judge to determine. You are required to accept the law as the Judge explains it to you even if you do not like the law or disagree with it, and you must determine the facts according to those instructions. Do you accept this principle, and will you be able to follow the Judge's instructions if selected to serve on this jury?\n\nYes No\n\n10a. If no, please explain:\n\n\n\n\n\n11. The law provides that a defendant in a criminal case is presumed innocent at all stages of the trial and is not required to put on any defense at all. The Government is required to prove the defendant guilty beyond a reasonable doubt on each charge. Do you accept these principles, and will you be able to apply them if selected to serve on this jury?\n\nYes No\n\n11a. If no, please explain:\n\n\n\n\n\n-8-\n\nDOJ-OGR-00011083",
  "text_blocks": [
    {
      "type": "printed",
      "content": "Case 1:20-cr-00330-PAE Document 688 Filed 06/29/22 Page 330 of 353",
      "position": "header"
    },
    {
      "type": "handwritten",
      "content": "124",
      "position": "margin"
    },
    {
      "type": "printed",
      "content": "Juror ID:",
      "position": "header"
    },
    {
      "type": "printed",
      "content": "9. Do you have any religious, philosophical, or other beliefs that would make you unable to render a verdict in a criminal case?",
      "position": "body"
    },
    {
      "type": "handwritten",
      "content": "No",
      "position": "body"
    },
    {
      "type": "printed",
      "content": "9a. If yes, please explain:",
      "position": "body"
    },
    {
      "type": "printed",
      "content": "BASIC LEGAL PRINCIPLES AND MEDIA RESTRICTIONS",
      "position": "header"
    },
    {
      "type": "printed",
      "content": "10. Under the law, the facts are for the jury to determine and the law is for the Judge to determine. You are required to accept the law as the Judge explains it to you even if you do not like the law or disagree with it, and you must determine the facts according to those instructions. Do you accept this principle, and will you be able to follow the Judge's instructions if selected to serve on this jury?",
      "position": "body"
    },
    {
      "type": "handwritten",
      "content": "Yes",
      "position": "body"
    },
    {
      "type": "printed",
      "content": "10a. If no, please explain:",
      "position": "body"
    },
    {
      "type": "printed",
      "content": "11. The law provides that a defendant in a criminal case is presumed innocent at all stages of the trial and is not required to put on any defense at all. The Government is required to prove the defendant guilty beyond a reasonable doubt on each charge. Do you accept these principles, and will you be able to apply them if selected to serve on this jury?",
      "position": "body"
    },
    {
      "type": "handwritten",
      "content": "Yes",
      "position": "body"
    },
    {
      "type": "printed",
      "content": "11a. If no, please explain:",
      "position": "body"
    },
    {
      "type": "printed",
      "content": "-8-",
      "position": "footer"
    },
    {
      "type": "printed",
      "content": "DOJ-OGR-00011083",
      "position": "footer"
    }
  ],
  "entities": {
    "people": [],
    "organizations": [
      "Government"
    ],
    "locations": [],
    "dates": [
      "06/29/22"
    ],
    "reference_numbers": [
      "1:20-cr-00330-PAE",
      "688",
      "124",
      "DOJ-OGR-00011083"
    ]
  },
  "additional_notes": "The document is a jury questionnaire with handwritten answers. The juror ID is 124. The document is part of a larger case file (1:20-cr-00330-PAE, Document 688)."
}