{
  "document_metadata": {
    "page_number": "213",
    "document_number": "688",
    "date": "06/29/22",
    "document_type": "Juror Questionnaire",
    "has_handwriting": true,
    "has_stamps": false
  },
  "full_text": "Case 1:20-cr-00330-PAE Document 688 Filed 06/29/22 Page 213 of 353\nJuror ID: 50\n5. Do you have any personal commitments that would make it difficult for you to get to court by 9:30 a.m., every day of trial, or remain at the courthouse until 5:00 p.m.?(Please note, the Court will arrange and provide transportation to and from the Courthouse each day for selected jurors).\nYes No\n5a. If yes, please explain why you would be unable to get to court by 9:30 a.m. or remain until 5:00 p.m.:\n6. Do you have any difficulty reading, speaking, or understanding English?\nYes No\n7. Do you have any medical, physical, or mental condition or illness that makes you unable to serve on a jury, including difficulty hearing, seeing, reading, or concentrating?\nYes No\n7a. If yes, please briefly describe the condition or illness. If you believe you could serve as a juror if such condition were accommodated in some way, please state the accommodation.\n8. Are you taking any medication which would prevent you from giving full attention to all the evidence at this trial?\nYes No\n8a. If yes, please explain:\n-7-\nDOJ-OGR-00010966",
  "text_blocks": [
    {
      "type": "printed",
      "content": "Case 1:20-cr-00330-PAE Document 688 Filed 06/29/22 Page 213 of 353",
      "position": "header"
    },
    {
      "type": "handwritten",
      "content": "50",
      "position": "inline"
    },
    {
      "type": "printed",
      "content": "Juror ID:",
      "position": "inline"
    },
    {
      "type": "printed",
      "content": "5. Do you have any personal commitments that would make it difficult for you to get to court by 9:30 a.m., every day of trial, or remain at the courthouse until 5:00 p.m.?(Please note, the Court will arrange and provide transportation to and from the Courthouse each day for selected jurors).",
      "position": "inline"
    },
    {
      "type": "handwritten",
      "content": "X",
      "position": "inline"
    },
    {
      "type": "printed",
      "content": "Yes No",
      "position": "inline"
    },
    {
      "type": "printed",
      "content": "5a. If yes, please explain why you would be unable to get to court by 9:30 a.m. or remain until 5:00 p.m.:",
      "position": "inline"
    },
    {
      "type": "printed",
      "content": "6. Do you have any difficulty reading, speaking, or understanding English?",
      "position": "inline"
    },
    {
      "type": "handwritten",
      "content": "X",
      "position": "inline"
    },
    {
      "type": "printed",
      "content": "Yes No",
      "position": "inline"
    },
    {
      "type": "printed",
      "content": "7. Do you have any medical, physical, or mental condition or illness that makes you unable to serve on a jury, including difficulty hearing, seeing, reading, or concentrating?",
      "position": "inline"
    },
    {
      "type": "handwritten",
      "content": "X",
      "position": "inline"
    },
    {
      "type": "printed",
      "content": "Yes No",
      "position": "inline"
    },
    {
      "type": "printed",
      "content": "7a. If yes, please briefly describe the condition or illness. If you believe you could serve as a juror if such condition were accommodated in some way, please state the accommodation.",
      "position": "inline"
    },
    {
      "type": "printed",
      "content": "8. Are you taking any medication which would prevent you from giving full attention to all the evidence at this trial?",
      "position": "inline"
    },
    {
      "type": "handwritten",
      "content": "X",
      "position": "inline"
    },
    {
      "type": "printed",
      "content": "Yes No",
      "position": "inline"
    },
    {
      "type": "printed",
      "content": "8a. If yes, please explain:",
      "position": "inline"
    },
    {
      "type": "printed",
      "content": "-7-",
      "position": "footer"
    },
    {
      "type": "printed",
      "content": "DOJ-OGR-00010966",
      "position": "footer"
    }
  ],
  "entities": {
    "people": [],
    "organizations": [
      "Court"
    ],
    "locations": [
      "Courthouse"
    ],
    "dates": [
      "06/29/22"
    ],
    "reference_numbers": [
      "1:20-cr-00330-PAE",
      "688",
      "213",
      "353",
      "50",
      "DOJ-OGR-00010966"
    ]
  },
  "additional_notes": "The document is a juror questionnaire with some handwritten marks indicating 'No' to several questions. The juror ID is 50."
}