{
  "document_metadata": {
    "page_number": "1",
    "document_number": "702-4",
    "date": "07/12/22",
    "document_type": "Court Order",
    "has_handwriting": false,
    "has_stamps": false
  },
  "full_text": "Case 1:20-cr-00330-PAE Document 702-4 Filed 07/12/22 Page 1 of 1\n\nUNITED STATES DISTRICT COURT\nSOUTHERN DISTRICT OF NEW YORK\n\nUNITED STATES OF AMERICA,\nPlaintiff,\nv.\nGHISLAINE MAXWELL,\nDefendant.\n20-CR-330-AJN\n\nORDER\n\nBefore the Court is Ms. Maxwell's December 17, 2021 motion for an arrest warrant for Kelly Bovino for her non-compliance with a subpoena to testify in this criminal proceeding. The motion is GRANTED.\n\nIt is ORDERED that an arrest warrant for Ms. Bovino will issue.\n\nIt is FURTHER ORDERED that the U.S. Marshals are directed to arrest Ms. Bovino and to bring her to the United States District Court for the Southern District of New York, Thurgood Marshall U.S. Courthouse at 40 Foley Square, New York, New York.\n\nDated: December 17, 2021.\n\nDOJ-OGR-00011205",
  "text_blocks": [
    {
      "type": "printed",
      "content": "Case 1:20-cr-00330-PAE Document 702-4 Filed 07/12/22 Page 1 of 1",
      "position": "header"
    },
    {
      "type": "printed",
      "content": "UNITED STATES DISTRICT COURT\nSOUTHERN DISTRICT OF NEW YORK",
      "position": "top"
    },
    {
      "type": "printed",
      "content": "UNITED STATES OF AMERICA,\nPlaintiff,\nv.\nGHISLAINE MAXWELL,\nDefendant.",
      "position": "top"
    },
    {
      "type": "printed",
      "content": "20-CR-330-AJN",
      "position": "top"
    },
    {
      "type": "printed",
      "content": "ORDER",
      "position": "middle"
    },
    {
      "type": "printed",
      "content": "Before the Court is Ms. Maxwell's December 17, 2021 motion for an arrest warrant for Kelly Bovino for her non-compliance with a subpoena to testify in this criminal proceeding. The motion is GRANTED.",
      "position": "middle"
    },
    {
      "type": "printed",
      "content": "It is ORDERED that an arrest warrant for Ms. Bovino will issue.",
      "position": "middle"
    },
    {
      "type": "printed",
      "content": "It is FURTHER ORDERED that the U.S. Marshals are directed to arrest Ms. Bovino and to bring her to the United States District Court for the Southern District of New York, Thurgood Marshall U.S. Courthouse at 40 Foley Square, New York, New York.",
      "position": "middle"
    },
    {
      "type": "printed",
      "content": "Dated: December 17, 2021.",
      "position": "bottom"
    },
    {
      "type": "printed",
      "content": "DOJ-OGR-00011205",
      "position": "footer"
    }
  ],
  "entities": {
    "people": [
      "Ghislaine Maxwell",
      "Kelly Bovino"
    ],
    "organizations": [
      "United States District Court",
      "U.S. Marshals"
    ],
    "locations": [
      "New York",
      "Southern District of New York",
      "Thurgood Marshall U.S. Courthouse",
      "40 Foley Square"
    ],
    "dates": [
      "December 17, 2021",
      "07/12/22"
    ],
    "reference_numbers": [
      "1:20-cr-00330-PAE",
      "Document 702-4",
      "20-CR-330-AJN",
      "DOJ-OGR-00011205"
    ]
  },
  "additional_notes": "The document is a court order from the United States District Court for the Southern District of New York. It appears to be a formal and official document, with no visible redactions or damage."
}