{
  "document_metadata": {
    "page_number": "12 of 30",
    "document_number": "613-1",
    "date": "02/24/22",
    "document_type": "Juror Questionnaire",
    "has_handwriting": true,
    "has_stamps": false
  },
  "full_text": "Case 1:20-cr-00330-PAE Document 613-1 Filed 02/24/22 Page 12 of 30\n\nJuror ID: 50\n\n24. Have you, or has any relative or close friend, ever been the subject of any investigation or accusation by any grand jury, state or federal, or any other investigation?\nYes (self) Yes (friend or family member) No\n\n24a. If yes, is there anything about that experience that would prevent you from acting as a fair and impartial juror in this case?\nYes No\n\n24b. If yes to 24a, please explain:\n\n25. Have you, or any of your relatives or close friends, ever been a victim of a crime?\nYes (self) Yes (friend or family member) No\n\n25a. If yes, is there anything about that experience that would prevent you from acting as a fair and impartial juror in this case?\nYes No\n\n25b. If yes to 25a, please explain:\n\n26. Have you, or has any member of your family or any of your close friends - either as individuals or in the course of their business affairs - ever been a party to a legal action or dispute with the United States, or with any of the officers, departments, agencies, or employees of the United States, including the United States Attorney's Office, the FBI, or the NYPD?\nYes (self) Yes (friend or family member) No\n\n-13-\nDOJ-OGR-00009079",
  "text_blocks": [
    {
      "type": "printed",
      "content": "Case 1:20-cr-00330-PAE Document 613-1 Filed 02/24/22 Page 12 of 30",
      "position": "header"
    },
    {
      "type": "printed",
      "content": "Juror ID: 50",
      "position": "header"
    },
    {
      "type": "printed",
      "content": "24. Have you, or has any relative or close friend, ever been the subject of any investigation or accusation by any grand jury, state or federal, or any other investigation?",
      "position": "body"
    },
    {
      "type": "handwritten",
      "content": "No",
      "position": "body"
    },
    {
      "type": "printed",
      "content": "24a. If yes, is there anything about that experience that would prevent you from acting as a fair and impartial juror in this case?",
      "position": "body"
    },
    {
      "type": "handwritten",
      "content": "No",
      "position": "body"
    },
    {
      "type": "printed",
      "content": "25. Have you, or any of your relatives or close friends, ever been a victim of a crime?",
      "position": "body"
    },
    {
      "type": "handwritten",
      "content": "No",
      "position": "body"
    },
    {
      "type": "printed",
      "content": "25a. If yes, is there anything about that experience that would prevent you from acting as a fair and impartial juror in this case?",
      "position": "body"
    },
    {
      "type": "handwritten",
      "content": "No",
      "position": "body"
    },
    {
      "type": "printed",
      "content": "26. Have you, or has any member of your family or any of your close friends - either as individuals or in the course of their business affairs - ever been a party to a legal action or dispute with the United States, or with any of the officers, departments, agencies, or employees of the United States, including the United States Attorney's Office, the FBI, or the NYPD?",
      "position": "body"
    },
    {
      "type": "handwritten",
      "content": "No",
      "position": "body"
    },
    {
      "type": "printed",
      "content": "-13-",
      "position": "footer"
    },
    {
      "type": "printed",
      "content": "DOJ-OGR-00009079",
      "position": "footer"
    }
  ],
  "entities": {
    "people": [],
    "organizations": [
      "FBI",
      "NYPD",
      "United States Attorney's Office"
    ],
    "locations": [],
    "dates": [
      "02/24/22"
    ],
    "reference_numbers": [
      "1:20-cr-00330-PAE",
      "613-1",
      "DOJ-OGR-00009079"
    ]
  },
  "additional_notes": "The document appears to be a juror questionnaire with some handwritten responses. The responses are mostly 'No' to various questions about the juror's background and experiences."
}