{
  "document_metadata": {
    "page_number": "14",
    "document_number": "741",
    "date": "08/10/22",
    "document_type": "court transcript",
    "has_handwriting": false,
    "has_stamps": false
  },
  "full_text": "Case 1:20-cr-00330-PAE Document 741 Filed 08/10/22 Page 14 of 106 LBTVMAX1 18 1 (In open court) 2 MS. STERNHEIM: Judge? 3 THE COURT: Just a moment. 4 Yes, Ms. Sternheim. 5 MS. STERNHEIM: I'm just inquiring if that format was 6 satisfactory to the Court. 7 THE COURT: I think so. 8 MS. STERNHEIM: Thank you. 9 THE COURT: I think the information I'm getting is 10 that we're missing three jurors who are not yet accounted for 11 on the security line. 12 (Pause) 13 THE COURT: Current status is we're missing one juror 14 from the fifth floor, and two from the first floor. I think 15 we'll give it five more minutes and then I'll move one juror 16 from the first floor to the fifth floor, unless counsel has 17 concerns with that. And I'm not going to tell you who the 18 juror is yet. 19 MS. COMEY: Your Honor, we would just ask whether the 20 Court has attempted to call the missing jurors. 21 THE COURT: That's happening now. 22 MS. COMEY: Thank you, your Honor. 23 (Pause) 24 (Continued on next page) 25 SOUTHERN DISTRICT REPORTERS, P.C. (212) 805-0300 DOJ-OGR-00011679",
  "text_blocks": [
    {
      "type": "printed",
      "content": "Case 1:20-cr-00330-PAE Document 741 Filed 08/10/22 Page 14 of 106 LBTVMAX1 18",
      "position": "header"
    },
    {
      "type": "printed",
      "content": "(In open court) MS. STERNHEIM: Judge? THE COURT: Just a moment. Yes, Ms. Sternheim. MS. STERNHEIM: I'm just inquiring if that format was satisfactory to the Court. THE COURT: I think so. MS. STERNHEIM: Thank you. THE COURT: I think the information I'm getting is that we're missing three jurors who are not yet accounted for on the security line. (Pause) THE COURT: Current status is we're missing one juror from the fifth floor, and two from the first floor. I think we'll give it five more minutes and then I'll move one juror from the first floor to the fifth floor, unless counsel has concerns with that. And I'm not going to tell you who the juror is yet. MS. COMEY: Your Honor, we would just ask whether the Court has attempted to call the missing jurors. THE COURT: That's happening now. MS. COMEY: Thank you, your Honor. (Pause) (Continued on next page)",
      "position": "main"
    },
    {
      "type": "printed",
      "content": "SOUTHERN DISTRICT REPORTERS, P.C. (212) 805-0300",
      "position": "footer"
    },
    {
      "type": "printed",
      "content": "DOJ-OGR-00011679",
      "position": "footer"
    }
  ],
  "entities": {
    "people": [
      "MS. STERNHEIM",
      "THE COURT",
      "MS. COMEY"
    ],
    "organizations": [
      "SOUTHERN DISTRICT REPORTERS, P.C."
    ],
    "locations": [],
    "dates": [
      "08/10/22"
    ],
    "reference_numbers": [
      "1:20-cr-00330-PAE",
      "741",
      "DOJ-OGR-00011679"
    ]
  },
  "additional_notes": "The document appears to be a court transcript with a clear and readable format. There are no visible redactions or damage."
}