{
  "document_metadata": {
    "page_number": "1",
    "document_number": "A-5840",
    "date": "Dec. 9, 2010",
    "document_type": "Court Document",
    "has_handwriting": false,
    "has_stamps": false
  },
  "full_text": "Westlaw Page 1 80 A.D.3d 168, 913 N.Y.S.2d 187, 2010 N.Y. Slip Op. 09090 (Cite as: 80 A.D.3d 168, 913 N.Y.S.2d 187) H Supreme Court, Appellate Division, First Department, New York. In the Matter of Catherine M. CONRAD, a suspended attorney: Departmental Disciplinary Committee for the First Judicial Department, Petitioner, Catherine M. Conrad, Respondent. Dec. 9, 2010. Background: Departmental Disciplinary Committee instituted disciplinary proceedings against attorney. The Supreme Court, Appellate Division, 48 A.D.3d 187, 846 N.Y.S.2d 912, suspended attorney from practice of law for failure to respond to requests made by Committee pursuant to its investigations of complaints made against her. Committee subsequently moved for order suspending attorney on ground that she suffered from disability by reason of physical or mental infirmity or illness. Attorney cross-moved for order converting her current suspension to medical suspension nunc pro tunc and order vacating suspension and reinstating her to practice of law. Holdings: The Supreme Court, Appellate Division, held that: (1) attorney's immediate reinstatement was not warranted, and (2) attorney was required to prove her fitness to be reinstated. Suspension ordered. West Headnotes [1] Attorney and Client 45 C 61 45 Attorney and Client 45I The Office of Attorney 45I(C) Discipline 45k61 k. Reinstatement. Most Cited Cases Immediate reinstatement of suspended attorney to practice of law was not warranted; alcohol dependence rendered attorney unfit to practice law, and attorney acknowledged during her deposition that her failure to cooperate and her underlying conduct was related to alcohol dependency. N.Y.Ct.Rules, §§ 603.16(c)(1), (f). [2] Attorney and Client 45 C 61 45 Attorney and Client 45I The Office of Attorney 45I(C) Discipline 45k61 k. Reinstatement. Most Cited Cases Attorney who was suspended from practice of law due to her alcohol dependence was required to prove her fitness to be reinstated, and that burden could not be satisfied by attorney's own self-assessment; rather, evaluation by © 2011 Thomson Reuters. No Claim to Orig. US Gov. Works. PMD 20 DOJ-OGR-00010123",
  "text_blocks": [
    {
      "type": "printed",
      "content": "Westlaw Page 1 80 A.D.3d 168, 913 N.Y.S.2d 187, 2010 N.Y. Slip Op. 09090 (Cite as: 80 A.D.3d 168, 913 N.Y.S.2d 187)",
      "position": "header"
    },
    {
      "type": "printed",
      "content": "H Supreme Court, Appellate Division, First Department, New York. In the Matter of Catherine M. CONRAD, a suspended attorney: Departmental Disciplinary Committee for the First Judicial Department, Petitioner, Catherine M. Conrad, Respondent. Dec. 9, 2010.",
      "position": "top"
    },
    {
      "type": "printed",
      "content": "Background: Departmental Disciplinary Committee instituted disciplinary proceedings against attorney. The Supreme Court, Appellate Division, 48 A.D.3d 187, 846 N.Y.S.2d 912, suspended attorney from practice of law for failure to respond to requests made by Committee pursuant to its investigations of complaints made against her. Committee subsequently moved for order suspending attorney on ground that she suffered from disability by reason of physical or mental infirmity or illness. Attorney cross-moved for order converting her current suspension to medical suspension nunc pro tunc and order vacating suspension and reinstating her to practice of law.",
      "position": "middle"
    },
    {
      "type": "printed",
      "content": "Holdings: The Supreme Court, Appellate Division, held that: (1) attorney's immediate reinstatement was not warranted, and (2) attorney was required to prove her fitness to be reinstated. Suspension ordered.",
      "position": "middle"
    },
    {
      "type": "printed",
      "content": "West Headnotes [1] Attorney and Client 45 C 61 45 Attorney and Client 45I The Office of Attorney 45I(C) Discipline 45k61 k. Reinstatement. Most Cited Cases Immediate reinstatement of suspended attorney to practice of law was not warranted; alcohol dependence rendered attorney unfit to practice law, and attorney acknowledged during her deposition that her failure to cooperate and her underlying conduct was related to alcohol dependency. N.Y.Ct.Rules, §§ 603.16(c)(1), (f).",
      "position": "middle"
    },
    {
      "type": "printed",
      "content": "[2] Attorney and Client 45 C 61 45 Attorney and Client 45I The Office of Attorney 45I(C) Discipline 45k61 k. Reinstatement. Most Cited Cases Attorney who was suspended from practice of law due to her alcohol dependence was required to prove her fitness to be reinstated, and that burden could not be satisfied by attorney's own self-assessment; rather, evaluation by",
      "position": "middle"
    },
    {
      "type": "printed",
      "content": "© 2011 Thomson Reuters. No Claim to Orig. US Gov. Works.",
      "position": "footer"
    },
    {
      "type": "printed",
      "content": "PMD 20",
      "position": "footer"
    },
    {
      "type": "printed",
      "content": "DOJ-OGR-00010123",
      "position": "footer"
    }
  ],
  "entities": {
    "people": [
      "Catherine M. Conrad"
    ],
    "organizations": [
      "Departmental Disciplinary Committee",
      "Supreme Court, Appellate Division",
      "Thomson Reuters"
    ],
    "locations": [
      "New York"
    ],
    "dates": [
      "Dec. 9, 2010"
    ],
    "reference_numbers": [
      "A-5840",
      "80 A.D.3d 168",
      "913 N.Y.S.2d 187",
      "2010 N.Y. Slip Op. 09090",
      "48 A.D.3d 187",
      "846 N.Y.S.2d 912",
      "DOJ-OGR-00010123"
    ]
  },
  "additional_notes": "The document appears to be a court document from the Supreme Court, Appellate Division, First Department, New York. It is a disciplinary proceeding against an attorney, Catherine M. Conrad. The document is from Westlaw and has a copyright notice from Thomson Reuters."
}