{
  "document_metadata": {
    "page_number": "15",
    "document_number": "645",
    "date": "03/11/22",
    "document_type": "court transcript",
    "has_handwriting": false,
    "has_stamps": false
  },
  "full_text": "Case 1:20-cr-00330-PAE Document 645 Filed 03/11/22 Page 15 of 50 M38TMAX1 actually taken the time to read this appropriately, I would in a heartbeat. Q. There are other questions on the questionnaire that are structured with similar yes self, yes friend or family, or no. Do you recall seeing those questions? A. Only after I have reread this do I recall that. Q. So on none of the questions that included yes, parenthesis self, yes friend or family member, or no -- A. I did not pick up on that when I was filling this out. Q. Okay. When did you first learn that an answer to the questionnaire was inaccurate? A. When an article had come out about the article that I had given to Lucia through The Independent. Q. So you learned of an inaccurate answer in an article about an interview? A. Yes. Q. And what about during the interview? A. During the interview, no. Q. When did you first learn that the questionnaire may contain a question that asked about sexual abuse history? A. That was during my Daily Mail interview with the reporter Laura Collins. Q. So we're talking about your response to 48 which you have indicated was inaccurate. Did you in any way intentionally provide an inaccurate answer to this question? SOUTHERN DISTRICT REPORTERS, P.C. (212) 805-0300 DOJ-OGR-00010230",
  "text_blocks": [
    {
      "type": "printed",
      "content": "Case 1:20-cr-00330-PAE Document 645 Filed 03/11/22 Page 15 of 50 M38TMAX1",
      "position": "header"
    },
    {
      "type": "printed",
      "content": "actually taken the time to read this appropriately, I would in a heartbeat. Q. There are other questions on the questionnaire that are structured with similar yes self, yes friend or family, or no. Do you recall seeing those questions? A. Only after I have reread this do I recall that. Q. So on none of the questions that included yes, parenthesis self, yes friend or family member, or no -- A. I did not pick up on that when I was filling this out. Q. Okay. When did you first learn that an answer to the questionnaire was inaccurate? A. When an article had come out about the article that I had given to Lucia through The Independent. Q. So you learned of an inaccurate answer in an article about an interview? A. Yes. Q. And what about during the interview? A. During the interview, no. Q. When did you first learn that the questionnaire may contain a question that asked about sexual abuse history? A. That was during my Daily Mail interview with the reporter Laura Collins. Q. So we're talking about your response to 48 which you have indicated was inaccurate. Did you in any way intentionally provide an inaccurate answer to this question?",
      "position": "main"
    },
    {
      "type": "printed",
      "content": "SOUTHERN DISTRICT REPORTERS, P.C. (212) 805-0300",
      "position": "footer"
    },
    {
      "type": "printed",
      "content": "DOJ-OGR-00010230",
      "position": "footer"
    }
  ],
  "entities": {
    "people": [
      "Lucia",
      "Laura Collins"
    ],
    "organizations": [
      "The Independent",
      "Daily Mail",
      "SOUTHERN DISTRICT REPORTERS, P.C."
    ],
    "locations": [],
    "dates": [
      "03/11/22"
    ],
    "reference_numbers": [
      "1:20-cr-00330-PAE",
      "645",
      "48",
      "DOJ-OGR-00010230"
    ]
  },
  "additional_notes": "The document appears to be a court transcript with a clear and legible format. There are no visible redactions or damage."
}