{
  "document_metadata": {
    "page_number": "1",
    "document_number": "640",
    "date": "03/10/22",
    "document_type": "Court Order",
    "has_handwriting": true,
    "has_stamps": true
  },
  "full_text": "Case 1:20-cr-00330-PAE Document 640 Filed 03/10/22 Page 1 of 1\nUNITED STATES DISTRICT COURT SOUTHERN DISTRICT OF NEW YORK\nUnited States of America,\n-v-\nGhislain Maxwell,\nDefendant.\nALISON J. NATHAN, District Judge:\nPer the Court's instruction at the March 8 hearing, the parties submitted revised redactions to their briefing on the Defendant's motion for a new trial. The Court rejects the Defendant's proposed redaction to page 8, lines 6-7 of her reply because it is not necessary to protect any continuing interest in juror anonymity and privacy. See Dkt. No. 607. The Court concludes that the remaining proposed redactions are narrowly tailored to further the important interest of protecting juror anonymity and privacy. Press-Enter. Co. v. Superior Ct. of Cal., Riverside Cnty., 464 U.S. 501, 511-12 (1984). The parties are ORDERED to file the redacted briefs (with the above noted line unredacted) on the docket on or before March 11, 2022. The Court will file the unredacted briefs under seal.\nSO ORDERED.\nDated: March 10, 2022 New York, New York\nALISON J. NATHAN United States District Judge\n1\nDOJ-OGR-00009692",
  "text_blocks": [
    {
      "type": "printed",
      "content": "Case 1:20-cr-00330-PAE Document 640 Filed 03/10/22 Page 1 of 1",
      "position": "header"
    },
    {
      "type": "printed",
      "content": "UNITED STATES DISTRICT COURT SOUTHERN DISTRICT OF NEW YORK",
      "position": "header"
    },
    {
      "type": "printed",
      "content": "United States of America,\n-v-\nGhislain Maxwell,\nDefendant.",
      "position": "top"
    },
    {
      "type": "printed",
      "content": "ALISON J. NATHAN, District Judge:",
      "position": "top"
    },
    {
      "type": "printed",
      "content": "Per the Court's instruction at the March 8 hearing, the parties submitted revised redactions to their briefing on the Defendant's motion for a new trial. The Court rejects the Defendant's proposed redaction to page 8, lines 6-7 of her reply because it is not necessary to protect any continuing interest in juror anonymity and privacy. See Dkt. No. 607. The Court concludes that the remaining proposed redactions are narrowly tailored to further the important interest of protecting juror anonymity and privacy. Press-Enter. Co. v. Superior Ct. of Cal., Riverside Cnty., 464 U.S. 501, 511-12 (1984). The parties are ORDERED to file the redacted briefs (with the above noted line unredacted) on the docket on or before March 11, 2022. The Court will file the unredacted briefs under seal.",
      "position": "middle"
    },
    {
      "type": "printed",
      "content": "SO ORDERED.",
      "position": "middle"
    },
    {
      "type": "printed",
      "content": "Dated: March 10, 2022 New York, New York",
      "position": "bottom"
    },
    {
      "type": "handwritten",
      "content": "ALISON J. NATHAN",
      "position": "bottom"
    },
    {
      "type": "printed",
      "content": "ALISON J. NATHAN United States District Judge",
      "position": "bottom"
    },
    {
      "type": "stamp",
      "content": "USDC SDNY DOCUMENT ELECTRONICALLY FILED DOC #: DATE FILED: 3/10/22",
      "position": "margin"
    },
    {
      "type": "printed",
      "content": "1",
      "position": "footer"
    },
    {
      "type": "printed",
      "content": "DOJ-OGR-00009692",
      "position": "footer"
    }
  ],
  "entities": {
    "people": [
      "Ghislain Maxwell",
      "Alison J. Nathan"
    ],
    "organizations": [
      "United States District Court",
      "United States of America"
    ],
    "locations": [
      "New York"
    ],
    "dates": [
      "March 8",
      "March 10, 2022",
      "March 11, 2022",
      "1984"
    ],
    "reference_numbers": [
      "1:20-cr-00330-PAE",
      "Document 640",
      "Dkt. No. 607",
      "464 U.S. 501",
      "DOJ-OGR-00009692"
    ]
  },
  "additional_notes": "The document is a court order from the United States District Court for the Southern District of New York. It is signed by Judge Alison J. Nathan and dated March 10, 2022. The document contains a stamp indicating that it was electronically filed on March 10, 2022."
}