{
  "document_metadata": {
    "page_number": "4",
    "document_number": "711",
    "date": "07/12/22",
    "document_type": "Court Document",
    "has_handwriting": false,
    "has_stamps": false
  },
  "full_text": "Case 1:20-cr-00330-PAE Document 711 Filed 07/12/22 Page 4 of 11 476:8-10 3509-005, p. 4, 4th full paragraph, last sentence Jane was not sure if Maxwell talked about how Epstein liked to be massaged. Objection. Defense counsel did not show the witness the inconsistent statement. FRE 613(a) does not require witness be shown statement; the testimony tracks the 302. 476:14-16 3509-008, p. 10, 1st full paragraph Jane cannot remember if Maxwell was ever present for instances of oral sex or hand jobs with Epstein and Jane. Objection. Not inconsistent, and defense counsel did not show the witness the inconsistent statement. The 3500 material is consistent with the witness's testimony that she does not recall if the defendant was present for instances of oral sex with Epstein. FRE 613(a) does not require witness be shown statement; the testimony tracks the 302. Inconsistent with prior testimony. 476:17-19 3509-008, p. 9, last paragraph Jane was then asked if Maxwell was present for when any of these 4 options (masturbation, hand job, oral sex, and sex) were performed on her and she responded, \"I can't remember.\" Objection. Defense counsel did not show the witness the statement, and the testimony is not inconsistent FRE 613(a) does not require witness be shown statement; the testimony tracks the 302. 477:2-5 3509-008, p. 9, last paragraph Jane was then asked if Maxwell was present for when any of these 4 options (masturbation, hand job, oral sex, and sex) were performed on her and she responded, \"I can't remember.\" Objection. Defense counsel did not show the witness the statement, and the testimony is not inconsistent FRE 613(a) does not require witness be shown statement; the testimony tracks the 302. 478:8-23 3509-008, p. 5, last paragraph When Jane was asked if there were times when it was only Epstein, Maxwell and her in the room, Jane was not Objection. Not inconsistent with the witness's testimony. The witness testified FRE 613(b) Denial or statement that the notes are inaccurate may 4 DOJ-OGR-00011292",
  "text_blocks": [
    {
      "type": "printed",
      "content": "Case 1:20-cr-00330-PAE Document 711 Filed 07/12/22 Page 4 of 11",
      "position": "header"
    },
    {
      "type": "printed",
      "content": "476:8-10 3509-005, p. 4, 4th full paragraph, last sentence Jane was not sure if Maxwell talked about how Epstein liked to be massaged. Objection. Defense counsel did not show the witness the inconsistent statement. FRE 613(a) does not require witness be shown statement; the testimony tracks the 302.",
      "position": "middle"
    },
    {
      "type": "printed",
      "content": "476:14-16 3509-008, p. 10, 1st full paragraph Jane cannot remember if Maxwell was ever present for instances of oral sex or hand jobs with Epstein and Jane. Objection. Not inconsistent, and defense counsel did not show the witness the inconsistent statement. The 3500 material is consistent with the witness's testimony that she does not recall if the defendant was present for instances of oral sex with Epstein. FRE 613(a) does not require witness be shown statement; the testimony tracks the 302. Inconsistent with prior testimony.",
      "position": "middle"
    },
    {
      "type": "printed",
      "content": "476:17-19 3509-008, p. 9, last paragraph Jane was then asked if Maxwell was present for when any of these 4 options (masturbation, hand job, oral sex, and sex) were performed on her and she responded, \"I can't remember.\" Objection. Defense counsel did not show the witness the statement, and the testimony is not inconsistent FRE 613(a) does not require witness be shown statement; the testimony tracks the 302.",
      "position": "middle"
    },
    {
      "type": "printed",
      "content": "477:2-5 3509-008, p. 9, last paragraph Jane was then asked if Maxwell was present for when any of these 4 options (masturbation, hand job, oral sex, and sex) were performed on her and she responded, \"I can't remember.\" Objection. Defense counsel did not show the witness the statement, and the testimony is not inconsistent FRE 613(a) does not require witness be shown statement; the testimony tracks the 302.",
      "position": "middle"
    },
    {
      "type": "printed",
      "content": "478:8-23 3509-008, p. 5, last paragraph When Jane was asked if there were times when it was only Epstein, Maxwell and her in the room, Jane was not Objection. Not inconsistent with the witness's testimony. The witness testified FRE 613(b) Denial or statement that the notes are inaccurate may 4",
      "position": "middle"
    },
    {
      "type": "printed",
      "content": "DOJ-OGR-00011292",
      "position": "footer"
    }
  ],
  "entities": {
    "people": [
      "Jane",
      "Maxwell",
      "Epstein"
    ],
    "organizations": [
      "DOJ"
    ],
    "locations": [],
    "dates": [
      "07/12/22"
    ],
    "reference_numbers": [
      "1:20-cr-00330-PAE",
      "711",
      "3509-005",
      "3509-008",
      "DOJ-OGR-00011292"
    ]
  },
  "additional_notes": "The document appears to be a court transcript or a legal document related to a court case. The content includes objections raised by defense counsel and references to specific pages and paragraphs of a witness's statement. The document is well-formatted and legible."
}