{
  "document_metadata": {
    "page_number": "220 of 353",
    "document_number": "688",
    "date": "06/29/22",
    "document_type": "Juror Questionnaire",
    "has_handwriting": true,
    "has_stamps": false
  },
  "full_text": "Case 1:20-cr-00330-PAE Document 688 Filed 06/29/22 Page 220 of 353 Juror ID: 50 26a. If yes, is there anything about that experience that would prevent you from acting as a fair and impartial juror in this case? Yes No 26b. If yes to 26a, please explain: 27. Have you, or has any member of your family, ever had a dispute concerning money owed to you by the Government or owed by you to the Government? Yes (self) Yes (friend or family member) No 27a. If yes, is there anything about that experience that would prevent you from acting as a fair and impartial juror in this case? Yes No 27b. If yes to 27a, please explain: RELATIONSHIP WITH, AND VIEW OF, GOVERNMENT, DEFENSE, AND OTHERS 28. Do you or any member of your family or a close friend work in law, law enforcement, the justice system, or the courts? Yes No 28a. If yes, please explain: -14- DOJ-OGR-00010973",
  "text_blocks": [
    {
      "type": "printed",
      "content": "Case 1:20-cr-00330-PAE Document 688 Filed 06/29/22 Page 220 of 353",
      "position": "header"
    },
    {
      "type": "handwritten",
      "content": "50",
      "position": "inline"
    },
    {
      "type": "printed",
      "content": "Juror ID:",
      "position": "inline"
    },
    {
      "type": "printed",
      "content": "26a. If yes, is there anything about that experience that would prevent you from acting as a fair and impartial juror in this case? Yes No",
      "position": "inline"
    },
    {
      "type": "printed",
      "content": "26b. If yes to 26a, please explain:",
      "position": "inline"
    },
    {
      "type": "printed",
      "content": "27. Have you, or has any member of your family, ever had a dispute concerning money owed to you by the Government or owed by you to the Government? Yes (self) Yes (friend or family member) No",
      "position": "inline"
    },
    {
      "type": "handwritten",
      "content": "X",
      "position": "inline"
    },
    {
      "type": "printed",
      "content": "27a. If yes, is there anything about that experience that would prevent you from acting as a fair and impartial juror in this case? Yes No",
      "position": "inline"
    },
    {
      "type": "printed",
      "content": "27b. If yes to 27a, please explain:",
      "position": "inline"
    },
    {
      "type": "printed",
      "content": "RELATIONSHIP WITH, AND VIEW OF, GOVERNMENT, DEFENSE, AND OTHERS",
      "position": "header"
    },
    {
      "type": "printed",
      "content": "28. Do you or any member of your family or a close friend work in law, law enforcement, the justice system, or the courts? Yes No",
      "position": "inline"
    },
    {
      "type": "handwritten",
      "content": "X",
      "position": "inline"
    },
    {
      "type": "printed",
      "content": "28a. If yes, please explain:",
      "position": "inline"
    },
    {
      "type": "printed",
      "content": "-14-",
      "position": "footer"
    },
    {
      "type": "printed",
      "content": "DOJ-OGR-00010973",
      "position": "footer"
    }
  ],
  "entities": {
    "people": [],
    "organizations": [
      "Government"
    ],
    "locations": [],
    "dates": [
      "06/29/22"
    ],
    "reference_numbers": [
      "1:20-cr-00330-PAE",
      "688",
      "DOJ-OGR-00010973"
    ]
  },
  "additional_notes": "The document is a juror questionnaire with some handwritten marks indicating 'No' to questions 27 and 28. The juror ID is 50."
}