{
  "document_metadata": {
    "page_number": "258",
    "document_number": "688",
    "date": "06/29/22",
    "document_type": "Juror Questionnaire",
    "has_handwriting": true,
    "has_stamps": false
  },
  "full_text": "Case 1:20-cr-00330-PAE Document 688 Filed 06/29/22 Page 258 of 353\n\nJuror ID: 70\n44a. If yes, please explain:\n\n45. Have you or a family member ever supported, lobbied, petitioned, protested, or worked in any other manner for or against any laws, regulations, or organizations relating to sex trafficking, sex crimes against minors, sex abuse, or sexual harassment? Yes No\n45a. If yes, please explain when and what you or your family member did:\n\n45b. If your answer to 45 was yes, do you believe that this would affect your ability to serve fairly and impartially as a juror in this case? Yes No N/A\n45c. If yes to 45b, please explain:\n\n46. The witnesses in this case may include law enforcement witnesses. Would you have any difficulty assessing the credibility of a law enforcement officer just like you would any other witness? Yes No\n46a. If yes, please explain:\n\n-23-\nDOJ-OGR-00011011",
  "text_blocks": [
    {
      "type": "printed",
      "content": "Case 1:20-cr-00330-PAE Document 688 Filed 06/29/22 Page 258 of 353",
      "position": "header"
    },
    {
      "type": "handwritten",
      "content": "70",
      "position": "margin"
    },
    {
      "type": "printed",
      "content": "Juror ID:",
      "position": "top"
    },
    {
      "type": "printed",
      "content": "44a. If yes, please explain:",
      "position": "body"
    },
    {
      "type": "printed",
      "content": "45. Have you or a family member ever supported, lobbied, petitioned, protested, or worked in any other manner for or against any laws, regulations, or organizations relating to sex trafficking, sex crimes against minors, sex abuse, or sexual harassment? Yes No",
      "position": "body"
    },
    {
      "type": "handwritten",
      "content": "No",
      "position": "body"
    },
    {
      "type": "printed",
      "content": "45a. If yes, please explain when and what you or your family member did:",
      "position": "body"
    },
    {
      "type": "printed",
      "content": "45b. If your answer to 45 was yes, do you believe that this would affect your ability to serve fairly and impartially as a juror in this case? Yes No N/A",
      "position": "body"
    },
    {
      "type": "handwritten",
      "content": "N/A",
      "position": "body"
    },
    {
      "type": "printed",
      "content": "45c. If yes to 45b, please explain:",
      "position": "body"
    },
    {
      "type": "printed",
      "content": "46. The witnesses in this case may include law enforcement witnesses. Would you have any difficulty assessing the credibility of a law enforcement officer just like you would any other witness? Yes No",
      "position": "body"
    },
    {
      "type": "handwritten",
      "content": "No",
      "position": "body"
    },
    {
      "type": "printed",
      "content": "46a. If yes, please explain:",
      "position": "body"
    },
    {
      "type": "printed",
      "content": "-23-",
      "position": "footer"
    },
    {
      "type": "printed",
      "content": "DOJ-OGR-00011011",
      "position": "footer"
    }
  ],
  "entities": {
    "people": [],
    "organizations": [
      "DOJ"
    ],
    "locations": [],
    "dates": [
      "06/29/22"
    ],
    "reference_numbers": [
      "1:20-cr-00330-PAE",
      "688",
      "258",
      "353",
      "70",
      "DOJ-OGR-00011011"
    ]
  },
  "additional_notes": "The document is a juror questionnaire with some handwritten responses. The juror ID is 70. The document is related to a court case with the reference number 1:20-cr-00330-PAE."
}