{
  "document_metadata": {
    "page_number": "55",
    "document_number": "688",
    "date": "06/29/22",
    "document_type": "Juror Questionnaire",
    "has_handwriting": true,
    "has_stamps": false
  },
  "full_text": "Case 1:20-cr-00330-PAE Document 688 Filed 06/29/22 Page 55 of 353\n\nJuror ID: 2\n\n44a. If yes, please explain:\n\n45. Have you or a family member ever supported, lobbied, petitioned, protested, or worked in any other manner for or against any laws, regulations, or organizations relating to sex trafficking, sex crimes against minors, sex abuse, or sexual harassment?\nYes No\n\n45a. If yes, please explain when and what you or your family member did:\n\n45b. If your answer to 45 was yes, do you believe that this would affect your ability to serve fairly and impartially as a juror in this case?\nYes No\n\n45c. If yes to 45b, please explain:\n\n46. The witnesses in this case may include law enforcement witnesses. Would you have any difficulty assessing the credibility of a law enforcement officer just like you would any other witness?\nYes No\n\n46a. If yes, please explain:\n\n-23-\nDOJ-OGR-00010808",
  "text_blocks": [
    {
      "type": "printed",
      "content": "Case 1:20-cr-00330-PAE Document 688 Filed 06/29/22 Page 55 of 353",
      "position": "header"
    },
    {
      "type": "printed",
      "content": "Juror ID:",
      "position": "header"
    },
    {
      "type": "handwritten",
      "content": "2",
      "position": "header"
    },
    {
      "type": "printed",
      "content": "44a. If yes, please explain:",
      "position": "main"
    },
    {
      "type": "printed",
      "content": "45. Have you or a family member ever supported, lobbied, petitioned, protested, or worked in any other manner for or against any laws, regulations, or organizations relating to sex trafficking, sex crimes against minors, sex abuse, or sexual harassment?",
      "position": "main"
    },
    {
      "type": "handwritten",
      "content": "No",
      "position": "main"
    },
    {
      "type": "printed",
      "content": "45a. If yes, please explain when and what you or your family member did:",
      "position": "main"
    },
    {
      "type": "printed",
      "content": "45b. If your answer to 45 was yes, do you believe that this would affect your ability to serve fairly and impartially as a juror in this case?",
      "position": "main"
    },
    {
      "type": "printed",
      "content": "45c. If yes to 45b, please explain:",
      "position": "main"
    },
    {
      "type": "printed",
      "content": "46. The witnesses in this case may include law enforcement witnesses. Would you have any difficulty assessing the credibility of a law enforcement officer just like you would any other witness?",
      "position": "main"
    },
    {
      "type": "handwritten",
      "content": "No",
      "position": "main"
    },
    {
      "type": "printed",
      "content": "46a. If yes, please explain:",
      "position": "main"
    },
    {
      "type": "printed",
      "content": "-23-",
      "position": "footer"
    },
    {
      "type": "printed",
      "content": "DOJ-OGR-00010808",
      "position": "footer"
    }
  ],
  "entities": {
    "people": [],
    "organizations": [
      "DOJ"
    ],
    "locations": [],
    "dates": [
      "06/29/22"
    ],
    "reference_numbers": [
      "1:20-cr-00330-PAE",
      "688",
      "DOJ-OGR-00010808"
    ]
  },
  "additional_notes": "The document appears to be a juror questionnaire with some handwritten answers. The juror ID is '2'. The questions relate to the juror's background and potential biases. The document is generally legible, but some sections are blank or contain minimal handwritten text."
}