{
  "document_metadata": {
    "page_number": "165",
    "document_number": "688",
    "date": "06/29/22",
    "document_type": "Juror Questionnaire",
    "has_handwriting": true,
    "has_stamps": false
  },
  "full_text": "Case 1:20-cr-00330-PAE Document 688 Filed 06/29/22 Page 165 of 353\n\nJuror ID: 48\n\n32a. If yes, please explain:\n\n\n\nPERSONAL RELATIONSHIP WITH CASE PARTICIPANTS\n\n33. The next subset of questions asks whether you or any member of your family or a close friend personally knows or has past or present dealings with individuals involved in this case. To \"personally know\" means to have some direct or personal knowledge or connection to the following individuals. If you have only heard the names through media or social media, for example, that is not personal knowledge.\n\n33a. Do you or does any member of your family or a close friend personally know or have past or present dealings with the Defendant in this case, Ghislaine Maxwell, or her family members?   No\n\n33b. Do you or does any member of your family or a close friend personally know or have past or present dealings with Jeffrey Epstein?   No\n\n33c. Do you or does any member of your family or a close friend personally know or have past or present dealings with the U.S. Attorney for the Southern District of New York, Damian Williams, the former Acting U.S. Attorney for the Southern District of New York, Audrey Strauss, or anyone else who works for or used to work for the U.S. Attorney's Office for the Southern District of New York?   No\n\n33d. Do you or does any member of your family or a close friend personally know or have past or present dealings with any of the Assistant United States Attorneys who are prosecuting this case:   Maurene Comey   No   Alison Moe   No   Lara Pomerantz   No   Andrew Rohrbach   No\n\n-17-\n\nDOJ-OGR-00010918",
  "text_blocks": [
    {
      "type": "printed",
      "content": "Case 1:20-cr-00330-PAE Document 688 Filed 06/29/22 Page 165 of 353",
      "position": "header"
    },
    {
      "type": "handwritten",
      "content": "48",
      "position": "header"
    },
    {
      "type": "printed",
      "content": "Juror ID:",
      "position": "header"
    },
    {
      "type": "printed",
      "content": "32a. If yes, please explain:",
      "position": "body"
    },
    {
      "type": "printed",
      "content": "PERSONAL RELATIONSHIP WITH CASE PARTICIPANTS",
      "position": "body"
    },
    {
      "type": "printed",
      "content": "33. The next subset of questions asks whether you or any member of your family or a close friend personally knows or has past or present dealings with individuals involved in this case. To \"personally know\" means to have some direct or personal knowledge or connection to the following individuals. If you have only heard the names through media or social media, for example, that is not personal knowledge.",
      "position": "body"
    },
    {
      "type": "printed",
      "content": "33a. Do you or does any member of your family or a close friend personally know or have past or present dealings with the Defendant in this case, Ghislaine Maxwell, or her family members?",
      "position": "body"
    },
    {
      "type": "printed",
      "content": "No",
      "position": "body"
    },
    {
      "type": "printed",
      "content": "33b. Do you or does any member of your family or a close friend personally know or have past or present dealings with Jeffrey Epstein?",
      "position": "body"
    },
    {
      "type": "printed",
      "content": "No",
      "position": "body"
    },
    {
      "type": "printed",
      "content": "33c. Do you or does any member of your family or a close friend personally know or have past or present dealings with the U.S. Attorney for the Southern District of New York, Damian Williams, the former Acting U.S. Attorney for the Southern District of New York, Audrey Strauss, or anyone else who works for or used to work for the U.S. Attorney's Office for the Southern District of New York?",
      "position": "body"
    },
    {
      "type": "printed",
      "content": "No",
      "position": "body"
    },
    {
      "type": "printed",
      "content": "33d. Do you or does any member of your family or a close friend personally know or have past or present dealings with any of the Assistant United States Attorneys who are prosecuting this case:",
      "position": "body"
    },
    {
      "type": "printed",
      "content": "Maurene Comey   No   Alison Moe   No   Lara Pomerantz   No   Andrew Rohrbach   No",
      "position": "body"
    },
    {
      "type": "printed",
      "content": "-17-",
      "position": "footer"
    },
    {
      "type": "printed",
      "content": "DOJ-OGR-00010918",
      "position": "footer"
    }
  ],
  "entities": {
    "people": [
      "Ghislaine Maxwell",
      "Jeffrey Epstein",
      "Damian Williams",
      "Audrey Strauss",
      "Maurene Comey",
      "Alison Moe",
      "Lara Pomerantz",
      "Andrew Rohrbach"
    ],
    "organizations": [
      "U.S. Attorney's Office for the Southern District of New York"
    ],
    "locations": [
      "New York"
    ],
    "dates": [
      "06/29/22"
    ],
    "reference_numbers": [
      "1:20-cr-00330-PAE",
      "688",
      "165",
      "353",
      "48",
      "DOJ-OGR-00010918"
    ]
  },
  "additional_notes": "The document appears to be a juror questionnaire from a court case involving Ghislaine Maxwell. The juror has answered 'No' to all questions regarding personal relationships with case participants. The document is in good condition with clear text and checkboxes."
}