{
  "document_metadata": {
    "page_number": "1",
    "document_number": "658",
    "date": "05/10/22",
    "document_type": "Letter",
    "has_handwriting": false,
    "has_stamps": false
  },
  "full_text": "Case 1:20-cr-00330-AJN Document 658 Filed 05/10/22 Page 1 of 1\nLAW OFFICES OF BOBBI C. STERNHEIM\n212-243-1100 • Main\n917-912-9698 • Cell\n888-587-4737 • Fax\n225 Broadway, Suite 715\nNew York, NY 10007\nbcsternheim@mac.com\nMay 10, 2022\nHonorable Alison J. Nathan\nUnited States United States District Judge Sitting by Designation\nUnited States Courthouse\n40 Foley Square\nNew York, NY 10007\nRe: United States v. Ghislaine Maxwell\nS2 20 Cr. 330 (AJN)\nDear Judge Nathan:\nThe defense requests a two-day extension to file Ms. Maxwell's sentencing submission.\nSentencing is scheduled for June 28, 2022. Currently, the defense submission is due June 15 and the government submission is due June 22.\nI will be out of the country on June 15 in connection with a pre-COVID commitment, returning to New York on the evening of June 16. I am requesting permission to file Ms. Maxwell's submission on June 17 and for the government to file on June 24.\nThe government consents to this request. No previous application has been made.\nYour consideration is greatly appreciated.\nVery truly yours,\n/s/\nBobbi C. Sternheim\ncc: Counsel of record\nDOJ-OGR-00010412",
  "text_blocks": [
    {
      "type": "printed",
      "content": "Case 1:20-cr-00330-AJN Document 658 Filed 05/10/22 Page 1 of 1",
      "position": "header"
    },
    {
      "type": "printed",
      "content": "LAW OFFICES OF BOBBI C. STERNHEIM",
      "position": "header"
    },
    {
      "type": "printed",
      "content": "212-243-1100 • Main\n917-912-9698 • Cell\n888-587-4737 • Fax\n225 Broadway, Suite 715\nNew York, NY 10007\nbcsternheim@mac.com",
      "position": "header"
    },
    {
      "type": "printed",
      "content": "May 10, 2022",
      "position": "top"
    },
    {
      "type": "printed",
      "content": "Honorable Alison J. Nathan\nUnited States United States District Judge Sitting by Designation\nUnited States Courthouse\n40 Foley Square\nNew York, NY 10007",
      "position": "top"
    },
    {
      "type": "printed",
      "content": "Re: United States v. Ghislaine Maxwell\nS2 20 Cr. 330 (AJN)",
      "position": "top"
    },
    {
      "type": "printed",
      "content": "Dear Judge Nathan:",
      "position": "middle"
    },
    {
      "type": "printed",
      "content": "The defense requests a two-day extension to file Ms. Maxwell's sentencing submission.\nSentencing is scheduled for June 28, 2022. Currently, the defense submission is due June 15 and the government submission is due June 22.\nI will be out of the country on June 15 in connection with a pre-COVID commitment, returning to New York on the evening of June 16. I am requesting permission to file Ms. Maxwell's submission on June 17 and for the government to file on June 24.\nThe government consents to this request. No previous application has been made.\nYour consideration is greatly appreciated.",
      "position": "middle"
    },
    {
      "type": "printed",
      "content": "Very truly yours,\n/s/\nBobbi C. Sternheim",
      "position": "bottom"
    },
    {
      "type": "printed",
      "content": "cc: Counsel of record",
      "position": "bottom"
    },
    {
      "type": "printed",
      "content": "DOJ-OGR-00010412",
      "position": "footer"
    }
  ],
  "entities": {
    "people": [
      "Alison J. Nathan",
      "Ghislaine Maxwell",
      "Bobbi C. Sternheim"
    ],
    "organizations": [
      "Law Offices of Bobbi C. Sternheim",
      "United States District Court"
    ],
    "locations": [
      "New York"
    ],
    "dates": [
      "May 10, 2022",
      "June 15",
      "June 16",
      "June 17",
      "June 22",
      "June 24",
      "June 28, 2022",
      "05/10/22"
    ],
    "reference_numbers": [
      "1:20-cr-00330-AJN",
      "658",
      "S2 20 Cr. 330 (AJN)",
      "DOJ-OGR-00010412"
    ]
  },
  "additional_notes": "The document is a letter from Bobbi C. Sternheim to Honorable Alison J. Nathan requesting a two-day extension to file Ghislaine Maxwell's sentencing submission. The document is well-formatted and legible."
}