{
  "document_metadata": {
    "page_number": "336 of 353",
    "document_number": "688",
    "date": "06/29/22",
    "document_type": "Juror Questionnaire",
    "has_handwriting": true,
    "has_stamps": false
  },
  "full_text": "Case 1:20-cr-00330-PAE Document 688 Filed 06/29/22 Page 336 of 353 Juror ID: 129 26a. If yes, is there anything about that experience that would prevent you from acting as a fair and impartial juror in this case? Yes No 26b. If yes to 26a, please explain: 27. Have you, or has any member of your family, ever had a dispute concerning money owed to you by the Government or owed by you to the Government? Yes (self) Yes (friend or family member) No 27a. If yes, is there anything about that experience that would prevent you from acting as a fair and impartial juror in this case? Yes No 27b. If yes to 27a, please explain: RELATIONSHIP WITH, AND VIEW OF, GOVERNMENT, DEFENSE, AND OTHERS 28. Do you or any member of your family or a close friend work in law, law enforcement, the justice system, or the courts? Yes No 28a. If yes, please explain: Friends with occupations of: Attorney, Police officers, legal counsel, etc. -14- DOJ-OGR-00011089",
  "text_blocks": [
    {
      "type": "printed",
      "content": "Case 1:20-cr-00330-PAE Document 688 Filed 06/29/22 Page 336 of 353",
      "position": "header"
    },
    {
      "type": "handwritten",
      "content": "129",
      "position": "inline"
    },
    {
      "type": "printed",
      "content": "Juror ID:",
      "position": "inline"
    },
    {
      "type": "printed",
      "content": "26a. If yes, is there anything about that experience that would prevent you from acting as a fair and impartial juror in this case?",
      "position": "inline"
    },
    {
      "type": "printed",
      "content": "Yes No",
      "position": "inline"
    },
    {
      "type": "printed",
      "content": "26b. If yes to 26a, please explain:",
      "position": "inline"
    },
    {
      "type": "printed",
      "content": "27. Have you, or has any member of your family, ever had a dispute concerning money owed to you by the Government or owed by you to the Government?",
      "position": "inline"
    },
    {
      "type": "handwritten",
      "content": "No",
      "position": "inline"
    },
    {
      "type": "printed",
      "content": "Yes (self) Yes (friend or family member) No",
      "position": "inline"
    },
    {
      "type": "printed",
      "content": "27a. If yes, is there anything about that experience that would prevent you from acting as a fair and impartial juror in this case?",
      "position": "inline"
    },
    {
      "type": "printed",
      "content": "Yes No",
      "position": "inline"
    },
    {
      "type": "printed",
      "content": "27b. If yes to 27a, please explain:",
      "position": "inline"
    },
    {
      "type": "printed",
      "content": "RELATIONSHIP WITH, AND VIEW OF, GOVERNMENT, DEFENSE, AND OTHERS",
      "position": "header"
    },
    {
      "type": "printed",
      "content": "28. Do you or any member of your family or a close friend work in law, law enforcement, the justice system, or the courts?",
      "position": "inline"
    },
    {
      "type": "handwritten",
      "content": "Yes",
      "position": "inline"
    },
    {
      "type": "printed",
      "content": "Yes No",
      "position": "inline"
    },
    {
      "type": "printed",
      "content": "28a. If yes, please explain:",
      "position": "inline"
    },
    {
      "type": "handwritten",
      "content": "Friends with occupations of: Attorney, Police officers, legal counsel, etc.",
      "position": "inline"
    },
    {
      "type": "printed",
      "content": "-14-",
      "position": "footer"
    },
    {
      "type": "printed",
      "content": "DOJ-OGR-00011089",
      "position": "footer"
    }
  ],
  "entities": {
    "people": [],
    "organizations": [
      "Government"
    ],
    "locations": [],
    "dates": [
      "06/29/22"
    ],
    "reference_numbers": [
      "1:20-cr-00330-PAE",
      "688",
      "129",
      "DOJ-OGR-00011089"
    ]
  },
  "additional_notes": "The document is a juror questionnaire with some handwritten responses. The juror ID is 129. The document is page 336 of 353."
}