{
  "document_metadata": {
    "page_number": "20 of 29",
    "document_number": "638",
    "date": "03/09/22",
    "document_type": "Juror Questionnaire",
    "has_handwriting": true,
    "has_stamps": false
  },
  "full_text": "Case 1:20-cr-00330-PAE Document 638 Filed 03/09/22 Page 20 of 29 Juror ID: 50 41a. If no or unsure, please explain: NATURE OF CHARGES 42. During the trial, you will hear evidence alleging sex crimes against underage girls. Some of the evidence in this case will involve sexually suggestive or sexually explicit conduct. Is there anything about the nature of this case and the accusations as summarized at the beginning of this questionnaire that might make it difficult for you to be a fair and impartial juror in this case? Yes No 42a. If yes, please explain: 43. Do you have any specific views or feelings concerning laws regarding the age at which individuals can or cannot consent to sexual activity with other individuals that would affect your ability to serve as a fair and impartial juror? Yes No 43a. If yes, please explain: 44. Do you have any opinion about the enforcement of the federal sex trafficking laws or the federal laws concerning sex crimes against minors that might prevent you from being fair and impartial in this case? Yes No -22- DOJ-OGR-00009681",
  "text_blocks": [
    {
      "type": "printed",
      "content": "Case 1:20-cr-00330-PAE Document 638 Filed 03/09/22 Page 20 of 29",
      "position": "header"
    },
    {
      "type": "handwritten",
      "content": "50",
      "position": "inline"
    },
    {
      "type": "printed",
      "content": "Juror ID:",
      "position": "inline"
    },
    {
      "type": "printed",
      "content": "41a. If no or unsure, please explain:",
      "position": "inline"
    },
    {
      "type": "printed",
      "content": "NATURE OF CHARGES",
      "position": "inline"
    },
    {
      "type": "printed",
      "content": "42. During the trial, you will hear evidence alleging sex crimes against underage girls. Some of the evidence in this case will involve sexually suggestive or sexually explicit conduct. Is there anything about the nature of this case and the accusations as summarized at the beginning of this questionnaire that might make it difficult for you to be a fair and impartial juror in this case?",
      "position": "inline"
    },
    {
      "type": "handwritten",
      "content": "No",
      "position": "inline"
    },
    {
      "type": "printed",
      "content": "42a. If yes, please explain:",
      "position": "inline"
    },
    {
      "type": "printed",
      "content": "43. Do you have any specific views or feelings concerning laws regarding the age at which individuals can or cannot consent to sexual activity with other individuals that would affect your ability to serve as a fair and impartial juror?",
      "position": "inline"
    },
    {
      "type": "handwritten",
      "content": "No",
      "position": "inline"
    },
    {
      "type": "printed",
      "content": "43a. If yes, please explain:",
      "position": "inline"
    },
    {
      "type": "printed",
      "content": "44. Do you have any opinion about the enforcement of the federal sex trafficking laws or the federal laws concerning sex crimes against minors that might prevent you from being fair and impartial in this case?",
      "position": "inline"
    },
    {
      "type": "handwritten",
      "content": "No",
      "position": "inline"
    },
    {
      "type": "printed",
      "content": "-22-",
      "position": "footer"
    },
    {
      "type": "printed",
      "content": "DOJ-OGR-00009681",
      "position": "footer"
    }
  ],
  "entities": {
    "people": [],
    "organizations": [
      "DOJ"
    ],
    "locations": [],
    "dates": [
      "03/09/22"
    ],
    "reference_numbers": [
      "1:20-cr-00330-PAE",
      "638",
      "DOJ-OGR-00009681"
    ]
  },
  "additional_notes": "The document is a juror questionnaire with some handwritten answers. The juror ID is 50. The document is related to a court case involving sex crimes against minors."
}