{
  "document_metadata": {
    "page_number": "42",
    "document_number": "93",
    "date": "12/10/20",
    "document_type": "court transcript",
    "has_handwriting": false,
    "has_stamps": false
  },
  "full_text": "Case 1:20-cr-00330-AJN Document 93 Filed 12/10/20 Page 42 of 91 42\n\n1 THE COURT: Thank you, Ms. Moe.\n2 Mr. Cohen, you may proceed.\n3 MR. COHEN: Thank you, your Honor. Thank you very much for the opportunity to be heard and also for accommodating us with regard to the briefing schedule. We appreciate that, your Honor.\n4\n5 Your Honor, this is a very important proceeding for my client. It is critical and we submit, as we laid out in our papers, that under the Bail Reform Act and related case law, none of which, by the way, was discussed in the government's presentation, she is -- she ought to be released on a bail package with strict conditions, your Honor.\n6\n7 And, frankly, in order to defend a case like this during the COVID crisis, with the extent of discovery which was discussed earlier in the proceeding, that's going to take the government until November to produce to us, the notion of preparing a defense with our client while she is in custody under these conditions is just not realistic.\n8\n9 I would also like to take a moment, your Honor, to address a few things. As we noted in our papers, our client is not Jeffrey Epstein, and she has been the target of essentially endless media spin that apparently the government has picked up in its reply brief and in its presentation today, trying to portray her before the court as a ruthless, aimless, sinister person.\n10\n11 SOUTHERN DISTRICT REPORTERS, P.C. (212) 805-0300 DOJ-OGR-00001919",
  "text_blocks": [
    {
      "type": "printed",
      "content": "Case 1:20-cr-00330-AJN Document 93 Filed 12/10/20 Page 42 of 91 42",
      "position": "header"
    },
    {
      "type": "printed",
      "content": "1 THE COURT: Thank you, Ms. Moe.\n2 Mr. Cohen, you may proceed.\n3 MR. COHEN: Thank you, your Honor. Thank you very much for the opportunity to be heard and also for accommodating us with regard to the briefing schedule. We appreciate that, your Honor.\n4\n5 Your Honor, this is a very important proceeding for my client. It is critical and we submit, as we laid out in our papers, that under the Bail Reform Act and related case law, none of which, by the way, was discussed in the government's presentation, she is -- she ought to be released on a bail package with strict conditions, your Honor.\n6\n7 And, frankly, in order to defend a case like this during the COVID crisis, with the extent of discovery which was discussed earlier in the proceeding, that's going to take the government until November to produce to us, the notion of preparing a defense with our client while she is in custody under these conditions is just not realistic.\n8\n9 I would also like to take a moment, your Honor, to address a few things. As we noted in our papers, our client is not Jeffrey Epstein, and she has been the target of essentially endless media spin that apparently the government has picked up in its reply brief and in its presentation today, trying to portray her before the court as a ruthless, aimless, sinister person.",
      "position": "main"
    },
    {
      "type": "printed",
      "content": "SOUTHERN DISTRICT REPORTERS, P.C. (212) 805-0300 DOJ-OGR-00001919",
      "position": "footer"
    }
  ],
  "entities": {
    "people": [
      "Ms. Moe",
      "Mr. Cohen",
      "Jeffrey Epstein"
    ],
    "organizations": [
      "SOUTHERN DISTRICT REPORTERS, P.C."
    ],
    "locations": [],
    "dates": [
      "12/10/20",
      "November"
    ],
    "reference_numbers": [
      "1:20-cr-00330-AJN",
      "93",
      "DOJ-OGR-00001919"
    ]
  },
  "additional_notes": "The document appears to be a court transcript with a clear and legible format. There are no visible redactions or damage."
}