{
  "document_metadata": {
    "page_number": "4",
    "document_number": "63",
    "date": "07/22/25",
    "document_type": "Court Document",
    "has_handwriting": true,
    "has_stamps": false
  },
  "full_text": "Case 1:19-cr-00490-RMB Document 63 Filed 07/22/25 Page 4 of 4\njury disclosure. Any such letters are due on or before Tuesday, August 5, 2025. See Gov't Motion at 1 n.1 (This is a 2 page, undated, unsigned, U.S. Department of Justice and Federal Bureau of Investigation memo. According to the Government, \"Epstein harmed over one thousand victims. Each suffered unique trauma. Sensitive information relating to these victims is intertwined throughout the materials. This includes specific details such as victim names and likenesses, physical descriptions, places of birth, associates, and employment history.\")\nSO ORDERED.\nDated: New York, New York July 22, 2025\nRi.Cha.M. Berman\nRICHARD M. BERMAN, U.S.D.J.\n4\nDOJ-OGR-00000740",
  "text_blocks": [
    {
      "type": "printed",
      "content": "Case 1:19-cr-00490-RMB Document 63 Filed 07/22/25 Page 4 of 4",
      "position": "header"
    },
    {
      "type": "printed",
      "content": "jury disclosure. Any such letters are due on or before Tuesday, August 5, 2025. See Gov't Motion at 1 n.1 (This is a 2 page, undated, unsigned, U.S. Department of Justice and Federal Bureau of Investigation memo. According to the Government, \"Epstein harmed over one thousand victims. Each suffered unique trauma. Sensitive information relating to these victims is intertwined throughout the materials. This includes specific details such as victim names and likenesses, physical descriptions, places of birth, associates, and employment history.\")",
      "position": "top"
    },
    {
      "type": "printed",
      "content": "SO ORDERED.",
      "position": "middle"
    },
    {
      "type": "printed",
      "content": "Dated: New York, New York July 22, 2025",
      "position": "middle"
    },
    {
      "type": "handwritten",
      "content": "Ri.Cha.M. Berman",
      "position": "middle"
    },
    {
      "type": "printed",
      "content": "RICHARD M. BERMAN, U.S.D.J.",
      "position": "middle"
    },
    {
      "type": "printed",
      "content": "4",
      "position": "footer"
    },
    {
      "type": "printed",
      "content": "DOJ-OGR-00000740",
      "position": "footer"
    }
  ],
  "entities": {
    "people": [
      "Epstein",
      "Richard M. Berman"
    ],
    "organizations": [
      "U.S. Department of Justice",
      "Federal Bureau of Investigation"
    ],
    "locations": [
      "New York"
    ],
    "dates": [
      "July 22, 2025",
      "August 5, 2025",
      "07/22/25"
    ],
    "reference_numbers": [
      "1:19-cr-00490-RMB",
      "Document 63",
      "DOJ-OGR-00000740"
    ]
  },
  "additional_notes": "The document appears to be a court filing related to the case of Jeffrey Epstein. It is signed by Judge Richard M. Berman and includes a reference to a government motion and a memo from the U.S. Department of Justice and Federal Bureau of Investigation. The document is dated July 22, 2025, and is page 4 of 4."
}