{
  "document_metadata": {
    "page_number": "4",
    "document_number": "36",
    "date": "07/24/19",
    "document_type": "court document",
    "has_handwriting": false,
    "has_stamps": false
  },
  "full_text": "Case 1:19-cr-00490-RMB Document 36 Filed 07/24/19 Page 4 of 74 4 required and the safety of the community.\" It goes on to conclude that: \"Therefore, pretrial services respectfully recommends the defendant be detained.\" Now, of course this ultimately is the issue that I have to decide and will do so with your help. You should be aware, incidentally, that I have not yet reached a decision on this matter, and I do not intend to do so today. I need a little bit more time to absorb everything that's been submitted, and I will probably do so, that is to say, give my decision here in the courtroom, on Thursday, July 18, at 9:30 here in Courtroom 17B. I will endeavor to finish by then and to be able to share with you my determination. We also have in the court today several persons who are contending that they are victims in the legal context of Mr. Epstein's conduct. They're welcome in these proceedings. Indeed, they have the right to be present, and they also have the right to be heard under federal law. As I understand it, they have advised the Court, through counsel and through the government counsel, that they oppose bail for Mr. Epstein. They may also be heard today in court if they wish to be heard. So for today, I thought, if this is agreeable to the government and the defense, I would give each side say up to 20 minutes, if they wish to have it and if they do wish to be SOUTHERN DISTRICT REPORTERS, P.C. (212) 805-0300",
  "text_blocks": [
    {
      "type": "printed",
      "content": "Case 1:19-cr-00490-RMB Document 36 Filed 07/24/19 Page 4 of 74 4",
      "position": "header"
    },
    {
      "type": "printed",
      "content": "required and the safety of the community.\" It goes on to conclude that: \"Therefore, pretrial services respectfully recommends the defendant be detained.\" Now, of course this ultimately is the issue that I have to decide and will do so with your help. You should be aware, incidentally, that I have not yet reached a decision on this matter, and I do not intend to do so today. I need a little bit more time to absorb everything that's been submitted, and I will probably do so, that is to say, give my decision here in the courtroom, on Thursday, July 18, at 9:30 here in Courtroom 17B. I will endeavor to finish by then and to be able to share with you my determination. We also have in the court today several persons who are contending that they are victims in the legal context of Mr. Epstein's conduct. They're welcome in these proceedings. Indeed, they have the right to be present, and they also have the right to be heard under federal law. As I understand it, they have advised the Court, through counsel and through the government counsel, that they oppose bail for Mr. Epstein. They may also be heard today in court if they wish to be heard. So for today, I thought, if this is agreeable to the government and the defense, I would give each side say up to 20 minutes, if they wish to have it and if they do wish to be",
      "position": "main content"
    },
    {
      "type": "printed",
      "content": "SOUTHERN DISTRICT REPORTERS, P.C. (212) 805-0300",
      "position": "footer"
    }
  ],
  "entities": {
    "people": [
      "Mr. Epstein"
    ],
    "organizations": [
      "SOUTHERN DISTRICT REPORTERS, P.C.",
      "pretrial services"
    ],
    "locations": [
      "Courtroom 17B"
    ],
    "dates": [
      "July 18",
      "07/24/19"
    ],
    "reference_numbers": [
      "1:19-cr-00490-RMB",
      "Document 36"
    ]
  },
  "additional_notes": "The document appears to be a court transcript, with a clear and legible format. There are no visible redactions or damage."
}