{
  "document_metadata": {
    "page_number": "31",
    "document_number": "53",
    "date": "09/03/19",
    "document_type": "court document",
    "has_handwriting": false,
    "has_stamps": false
  },
  "full_text": "Case 1:19-cr-00490-RMB Document 53 Filed 09/03/19 Page 31 of 86\nJ8RsEPS1\n1 Mr. Epstein that goes to the estate, certainly the victims are interested in that as they might help to repair the damage done.\n2\n3 Second, Mr. Epstein's untimely death, the timing is curious to us. But more so, it makes it absolutely impossible for the victims to ever get the day in court that they wanted in court and to get full justice. That now can never happen.\n4\n5 I know that Mr. Epstein's attorneys say he wanted it, and they know, we did too. And there are a lot of people here today that are very sad by the way that this ended for both Mr. Epstein and the fact that full justice was robbed from them, once again.\n6\n7 The second issue I wanted to address was the Law Review or the Law Journal article that your Honor referenced, which is troubling because the opinion seems to say that transparency is not appropriate in the criminal system and is not appropriate at this point in time.\n8\n9 That's tough to swallow, especially in this case, given the long history of this case. Personally, it is tough to swallow, and on behalf of my clients, I can say that is very concerning. Transparency is the only way that the justice system works. We know this because there was a similar investigation of Mr. Epstein many years ago, from 2005 to 2008.\n10\n11 My personal involvement in this case was because a young female came into my office named Courtney Wild, and she\nSOUTHERN DISTRICT REPORTERS, P.C. (212) 805-0300\nDOJ-OGR-00000669",
  "text_blocks": [
    {
      "type": "printed",
      "content": "Case 1:19-cr-00490-RMB Document 53 Filed 09/03/19 Page 31 of 86",
      "position": "header"
    },
    {
      "type": "printed",
      "content": "J8RsEPS1",
      "position": "header"
    },
    {
      "type": "printed",
      "content": "1 Mr. Epstein that goes to the estate, certainly the victims are interested in that as they might help to repair the damage done.",
      "position": "main body"
    },
    {
      "type": "printed",
      "content": "2",
      "position": "main body"
    },
    {
      "type": "printed",
      "content": "3 Second, Mr. Epstein's untimely death, the timing is curious to us. But more so, it makes it absolutely impossible for the victims to ever get the day in court that they wanted in court and to get full justice. That now can never happen.",
      "position": "main body"
    },
    {
      "type": "printed",
      "content": "4",
      "position": "main body"
    },
    {
      "type": "printed",
      "content": "5 I know that Mr. Epstein's attorneys say he wanted it, and they know, we did too. And there are a lot of people here today that are very sad by the way that this ended for both Mr. Epstein and the fact that full justice was robbed from them, once again.",
      "position": "main body"
    },
    {
      "type": "printed",
      "content": "6",
      "position": "main body"
    },
    {
      "type": "printed",
      "content": "7 The second issue I wanted to address was the Law Review or the Law Journal article that your Honor referenced, which is troubling because the opinion seems to say that transparency is not appropriate in the criminal system and is not appropriate at this point in time.",
      "position": "main body"
    },
    {
      "type": "printed",
      "content": "8",
      "position": "main body"
    },
    {
      "type": "printed",
      "content": "9 That's tough to swallow, especially in this case, given the long history of this case. Personally, it is tough to swallow, and on behalf of my clients, I can say that is very concerning. Transparency is the only way that the justice system works. We know this because there was a similar investigation of Mr. Epstein many years ago, from 2005 to 2008.",
      "position": "main body"
    },
    {
      "type": "printed",
      "content": "10",
      "position": "main body"
    },
    {
      "type": "printed",
      "content": "11 My personal involvement in this case was because a young female came into my office named Courtney Wild, and she",
      "position": "main body"
    },
    {
      "type": "printed",
      "content": "SOUTHERN DISTRICT REPORTERS, P.C. (212) 805-0300",
      "position": "footer"
    },
    {
      "type": "printed",
      "content": "DOJ-OGR-00000669",
      "position": "footer"
    }
  ],
  "entities": {
    "people": [
      "Mr. Epstein",
      "Courtney Wild"
    ],
    "organizations": [
      "SOUTHERN DISTRICT REPORTERS, P.C."
    ],
    "locations": [],
    "dates": [
      "09/03/19",
      "2005",
      "2008"
    ],
    "reference_numbers": [
      "1:19-cr-00490-RMB",
      "Document 53",
      "DOJ-OGR-00000669"
    ]
  },
  "additional_notes": "The document appears to be a court transcript or legal document related to the case of Mr. Epstein. The text is typed and there are no visible handwritten notes or stamps. The document is from the Southern District Reporters, P.C. and includes a reference number."
}