{
  "document_metadata": {
    "page_number": "1",
    "document_number": "182-1",
    "date": "03/26/21",
    "document_type": "Declaration",
    "has_handwriting": false,
    "has_stamps": false
  },
  "full_text": "Case 1:20-cr-00330-PAE Document 182-1 Filed 03/26/21 Page 1 of 1\nUNITED STATES DISTRICT COURT\nSOUTHERN DISTRICT OF NEW YORK\nUNITED STATES OF AMERICA,\nCase No. 20-CR-330-AJN\nv.\nGHISLAINE MAXWELL\nDefendant.\nDECLARATION OF SIGRID S. MCCAWLEY IN SUPPORT OF APPLICATION FOR ADMISSION PRO HAC VICE\nI, Sigrid S. McCawley, hereby declare as follows:\n1. I have never been convicted of a felony.\n2. I have never been censured, suspended, disbarred or denied admission or readmission by any court.\n3. There are no pending disciplinary proceedings against me in any state or federal court.\n4. I am a member in good standing of the bars of the State of Florida and Washington, D.C.\nI hereby declare under penalty of perjury that the foregoing statements are true and correct.\nDated: March 26, 2021 Respectfully Submitted,\n/s/ Sigrid S. McCawley\nSigrid S. McCawley\nBoies Schiller Flexner LLP\n401 E. Las Olas Boulevard, Suite 1200\nFort Lauderdale, FL 33301\nTel: (954) 356-0011\nFax: (954) 356 0022\nEmail: smccawley@bsfllp.com\nAttorney for Intervenor\nBoies Schiller Flexner LLP\nand the victims it represents\nDOJ-OGR-00002807",
  "text_blocks": [
    {
      "type": "printed",
      "content": "Case 1:20-cr-00330-PAE Document 182-1 Filed 03/26/21 Page 1 of 1",
      "position": "header"
    },
    {
      "type": "printed",
      "content": "UNITED STATES DISTRICT COURT\nSOUTHERN DISTRICT OF NEW YORK",
      "position": "header"
    },
    {
      "type": "printed",
      "content": "UNITED STATES OF AMERICA,\nCase No. 20-CR-330-AJN\nv.\nGHISLAINE MAXWELL\nDefendant.",
      "position": "middle"
    },
    {
      "type": "printed",
      "content": "DECLARATION OF SIGRID S. MCCAWLEY IN SUPPORT OF APPLICATION FOR ADMISSION PRO HAC VICE",
      "position": "middle"
    },
    {
      "type": "printed",
      "content": "I, Sigrid S. McCawley, hereby declare as follows:\n1. I have never been convicted of a felony.\n2. I have never been censured, suspended, disbarred or denied admission or readmission by any court.\n3. There are no pending disciplinary proceedings against me in any state or federal court.\n4. I am a member in good standing of the bars of the State of Florida and Washington, D.C.",
      "position": "middle"
    },
    {
      "type": "printed",
      "content": "I hereby declare under penalty of perjury that the foregoing statements are true and correct.",
      "position": "middle"
    },
    {
      "type": "printed",
      "content": "Dated: March 26, 2021 Respectfully Submitted,",
      "position": "middle"
    },
    {
      "type": "signature",
      "content": "/s/ Sigrid S. McCawley",
      "position": "middle"
    },
    {
      "type": "printed",
      "content": "Sigrid S. McCawley\nBoies Schiller Flexner LLP\n401 E. Las Olas Boulevard, Suite 1200\nFort Lauderdale, FL 33301\nTel: (954) 356-0011\nFax: (954) 356 0022\nEmail: smccawley@bsfllp.com",
      "position": "middle"
    },
    {
      "type": "printed",
      "content": "Attorney for Intervenor\nBoies Schiller Flexner LLP\nand the victims it represents",
      "position": "middle"
    },
    {
      "type": "printed",
      "content": "DOJ-OGR-00002807",
      "position": "footer"
    }
  ],
  "entities": {
    "people": [
      "Sigrid S. McCawley",
      "Ghislaine Maxwell"
    ],
    "organizations": [
      "Boies Schiller Flexner LLP",
      "UNITED STATES DISTRICT COURT",
      "UNITED STATES OF AMERICA"
    ],
    "locations": [
      "SOUTHERN DISTRICT OF NEW YORK",
      "Florida",
      "Washington, D.C.",
      "Fort Lauderdale"
    ],
    "dates": [
      "March 26, 2021",
      "03/26/21"
    ],
    "reference_numbers": [
      "20-CR-330-AJN",
      "1:20-cr-00330-PAE",
      "182-1",
      "DOJ-OGR-00002807"
    ]
  },
  "additional_notes": "The document appears to be a declaration in support of an application for admission pro hac vice, signed by Sigrid S. McCawley. The document is well-formatted and legible."
}