{
  "document_metadata": {
    "page_number": "8",
    "document_number": "14",
    "date": "07/15/19",
    "document_type": "SORA HEARING",
    "has_handwriting": false,
    "has_stamps": false
  },
  "full_text": "Case 1:19-cr-00490-RMB Document 14 Filed 07/15/19 Page 8 of 18\nSORA HEARING page 7\n1 He is registered in the U.S. Virgin Islands, he has been since his release from jail. He notifies the Virgin Island authorities every time he leaves that jurisdiction. Virgin Island authorities rated him at the lowest level of registration.\n2 He also registered in Florida, which is the state of this particular offense, and the only reason that this conviction is even before Your Honor.\n3 The offense for which he was convicted is not a registrable offense in New York. He is only registrable here arguably because based on the provision of SORA that says if a crime is registrable in the state of conviction, then it is registrable here in New York. And the Florida authorities that considered that rated him at the lowest level of their SORA statute.\n4 He additionally has a vacation home in New Mexico and is registered in New Mexico. The New Mexican authorities when they considered his offenses, determined he need not register at all. Nevertheless, he has voluntarily registered with New Mexico and maintains that registration.\n5 Additionally, because of his possession of a vacation home in New York, he has been voluntarily registered with New York SOMU, the Sex Offender Monitoring Unit since May of this year. He notifies them whenever he comes to travel to New York. He never comes to New York for\nVikki J. Benkel Senior Court Reporter\nDOJ-OGR-00000373",
  "text_blocks": [
    {
      "type": "printed",
      "content": "Case 1:19-cr-00490-RMB Document 14 Filed 07/15/19 Page 8 of 18",
      "position": "header"
    },
    {
      "type": "printed",
      "content": "SORA HEARING page 7",
      "position": "header"
    },
    {
      "type": "printed",
      "content": "1 He is registered in the U.S. Virgin Islands, he has been since his release from jail. He notifies the Virgin Island authorities every time he leaves that jurisdiction. Virgin Island authorities rated him at the lowest level of registration.\n2 He also registered in Florida, which is the state of this particular offense, and the only reason that this conviction is even before Your Honor.\n3 The offense for which he was convicted is not a registrable offense in New York. He is only registrable here arguably because based on the provision of SORA that says if a crime is registrable in the state of conviction, then it is registrable here in New York. And the Florida authorities that considered that rated him at the lowest level of their SORA statute.\n4 He additionally has a vacation home in New Mexico and is registered in New Mexico. The New Mexican authorities when they considered his offenses, determined he need not register at all. Nevertheless, he has voluntarily registered with New Mexico and maintains that registration.\n5 Additionally, because of his possession of a vacation home in New York, he has been voluntarily registered with New York SOMU, the Sex Offender Monitoring Unit since May of this year. He notifies them whenever he comes to travel to New York. He never comes to New York for",
      "position": "main"
    },
    {
      "type": "printed",
      "content": "Vikki J. Benkel Senior Court Reporter",
      "position": "footer"
    },
    {
      "type": "printed",
      "content": "DOJ-OGR-00000373",
      "position": "footer"
    }
  ],
  "entities": {
    "people": [
      "Vikki J. Benkel"
    ],
    "organizations": [
      "New York SOMU",
      "Sex Offender Monitoring Unit"
    ],
    "locations": [
      "U.S. Virgin Islands",
      "Florida",
      "New York",
      "New Mexico"
    ],
    "dates": [
      "07/15/19",
      "May"
    ],
    "reference_numbers": [
      "1:19-cr-00490-RMB",
      "Document 14",
      "DOJ-OGR-00000373"
    ]
  },
  "additional_notes": "The document appears to be a court transcript or hearing document related to a SORA (Sex Offender Registration Act) hearing. The text is typed, and there are no visible handwritten notes or stamps. The document is from a legal case with the identifier 1:19-cr-00490-RMB."
}