{
  "document_metadata": {
    "page_number": "11",
    "document_number": "14",
    "date": "07/15/19",
    "document_type": "Court Transcript",
    "has_handwriting": false,
    "has_stamps": false
  },
  "full_text": "Case 1:19-cr-00490-RMB Document 14 Filed 07/15/19 Page 11 of 18\n\nSORA HEARING page 10\n1\nMr. Epstein plead to two charges, one was an indictment which is an offense that is not registrable, it is a Florida indictment for --\nTHE COURT: Then why does he have to register here?\nMS. MUSUMECI: It was a second offense that he plead to --\nTHE COURT: That is registrable.\nMS. MUSUMECI: That is registrable.\nThat offense was by information and that is the only registrable offense, that is what the DA's office is considering in doing their scoring.\nThe indictment which was the only case that the prosecutor even prosecuted through grand jury is not even a registrable offense.\nTHE COURT: He plead guilty to a registrable offense.\nMS. MUSUMECI: Yes.\nTHE COURT: What did he plead guilty to?\nMS. GAFFNEY: He plead guilty to the procuring a person under 18 for prostitution.\nTHE COURT: Procuring a person under 18 for prostitution.\nMS. GAFFNEY: Right.\nTHE COURT: How old was she?\n\nVikki J. Benkel\nSenior Court Reporter\nDOJ-OGR-00000376",
  "text_blocks": [
    {
      "type": "printed",
      "content": "Case 1:19-cr-00490-RMB Document 14 Filed 07/15/19 Page 11 of 18",
      "position": "header"
    },
    {
      "type": "printed",
      "content": "SORA HEARING page 10",
      "position": "header"
    },
    {
      "type": "printed",
      "content": "1\nMr. Epstein plead to two charges, one was an indictment which is an offense that is not registrable, it is a Florida indictment for --\nTHE COURT: Then why does he have to register here?\nMS. MUSUMECI: It was a second offense that he plead to --\nTHE COURT: That is registrable.\nMS. MUSUMECI: That is registrable.\nThat offense was by information and that is the only registrable offense, that is what the DA's office is considering in doing their scoring.\nThe indictment which was the only case that the prosecutor even prosecuted through grand jury is not even a registrable offense.\nTHE COURT: He plead guilty to a registrable offense.\nMS. MUSUMECI: Yes.\nTHE COURT: What did he plead guilty to?\nMS. GAFFNEY: He plead guilty to the procuring a person under 18 for prostitution.\nTHE COURT: Procuring a person under 18 for prostitution.\nMS. GAFFNEY: Right.\nTHE COURT: How old was she?",
      "position": "main"
    },
    {
      "type": "printed",
      "content": "Vikki J. Benkel\nSenior Court Reporter",
      "position": "footer"
    },
    {
      "type": "printed",
      "content": "DOJ-OGR-00000376",
      "position": "footer"
    }
  ],
  "entities": {
    "people": [
      "Mr. Epstein",
      "MS. MUSUMECI",
      "MS. GAFFNEY",
      "Vikki J. Benkel"
    ],
    "organizations": [
      "DA's office",
      "DOJ"
    ],
    "locations": [
      "Florida"
    ],
    "dates": [
      "07/15/19"
    ],
    "reference_numbers": [
      "1:19-cr-00490-RMB",
      "Document 14",
      "DOJ-OGR-00000376"
    ]
  },
  "additional_notes": "The document appears to be a court transcript from a SORA hearing. The conversation is between the court and lawyers MS. MUSUMECI and MS. GAFFNEY regarding Mr. Epstein's charges and guilty plea."
}