{
  "document_metadata": {
    "page_number": "54",
    "document_number": "53",
    "date": "09/03/19",
    "document_type": "court transcript",
    "has_handwriting": false,
    "has_stamps": false
  },
  "full_text": "Case 1:19-cr-00490-RMB Document 53 Filed 09/03/19 Page 54 of 86\nJ8RPEPS2\n1 well.\n2 My partner Sig McCawley, who's been working with me\n3 for more than five years on this case, is going to, with the\n4 Court's permission, introduce five of our clients who will\n5 speak briefly to your Court. Thank you very much.\n6 THE COURT: Thank you very much, Mr. Boies. Pleasure\n7 to have you here.\n8\n9 MS. MCCAWLEY: Thank you, your Honor, the first victim\n10 that would like to speak today is Theresa J. Helm.\n11 THE COURT: Can we have the spelling of your name?\n12 MS. MCCAWLEY: Sure. Sigrid, S-i-g-r-i-d, and the\n13 last name is M-c-C-a-w-l-e-y, and I'm a partner at Boies\n14 Schiller Flexner.\n15 THE COURT: Thank you.\n16 MS. HELM: Good morning.\n17 THE COURT: Good morning.\n18 MS. HELM: Thank you, prosecutors and Judge, and the\n19 Court. My name is Theresa Helm. I note today I do feel\n20 respected and listened to; so I appreciate that, and I have to\n21 say that I commend the boldness of the New York prosecutors for\n22 pursuing a man that has, you know -- and others, that have\n23 clearly taken a lot from a lot of people.\n24 17 years ago I knew him only as \"Jeffrey.\" I was\n25 recruited and brought from California to New York, and that\nSOUTHERN DISTRICT REPORTERS, P.C.\n(212) 805-0300",
  "text_blocks": [
    {
      "type": "printed",
      "content": "Case 1:19-cr-00490-RMB Document 53 Filed 09/03/19 Page 54 of 86",
      "position": "header"
    },
    {
      "type": "printed",
      "content": "J8RPEPS2",
      "position": "header"
    },
    {
      "type": "printed",
      "content": "SOUTHERN DISTRICT REPORTERS, P.C.\n(212) 805-0300",
      "position": "footer"
    },
    {
      "type": "printed",
      "content": "1 well.\n2 My partner Sig McCawley, who's been working with me\n3 for more than five years on this case, is going to, with the\n4 Court's permission, introduce five of our clients who will\n5 speak briefly to your Court. Thank you very much.\n6 THE COURT: Thank you very much, Mr. Boies. Pleasure\n7 to have you here.\n8\n9 MS. MCCAWLEY: Thank you, your Honor, the first victim\n10 that would like to speak today is Theresa J. Helm.\n11 THE COURT: Can we have the spelling of your name?\n12 MS. MCCAWLEY: Sure. Sigrid, S-i-g-r-i-d, and the\n13 last name is M-c-C-a-w-l-e-y, and I'm a partner at Boies\n14 Schiller Flexner.\n15 THE COURT: Thank you.\n16 MS. HELM: Good morning.\n17 THE COURT: Good morning.\n18 MS. HELM: Thank you, prosecutors and Judge, and the\n19 Court. My name is Theresa Helm. I note today I do feel\n20 respected and listened to; so I appreciate that, and I have to\n21 say that I commend the boldness of the New York prosecutors for\n22 pursuing a man that has, you know -- and others, that have\n23 clearly taken a lot from a lot of people.\n24 17 years ago I knew him only as \"Jeffrey.\" I was\n25 recruited and brought from California to New York, and that",
      "position": "main"
    }
  ],
  "entities": {
    "people": [
      "Sig McCawley",
      "Theresa J. Helm",
      "Mr. Boies",
      "Sigrid McCawley",
      "Jeffrey"
    ],
    "organizations": [
      "Boies Schiller Flexner",
      "Southern District Reporters, P.C."
    ],
    "locations": [
      "New York",
      "California"
    ],
    "dates": [
      "09/03/19"
    ],
    "reference_numbers": [
      "1:19-cr-00490-RMB",
      "Document 53"
    ]
  },
  "additional_notes": "The document appears to be a court transcript with clear and legible text. There are no visible redactions or damage."
}