{
  "document_metadata": {
    "page_number": "9",
    "document_number": "1",
    "date": "06/29/20",
    "document_type": "court document",
    "has_handwriting": false,
    "has_stamps": false
  },
  "full_text": "Case 1:20-cr-00330-AJN Document 1 Filed 06/29/20 Page 9 of 18\nan unsolicited massage to Minor Victim-2, during which Minor Victim-2 was topless. MAXWELL also encouraged Minor Victim-2 to massage Epstein.\nc. MAXWELL groomed and befriended Minor Victim-3 in London, England between approximately 1994 and 1995, including during a period of time in which MAXWELL knew that Minor Victim-3 was under the age of 18. Among other things, MAXWELL discussed Minor Victim-3's life and family with Minor Victim-3. MAXWELL introduced Minor Victim-3 to Epstein and arranged for multiple interactions between Minor Victim-3 and Epstein. During those interactions, MAXWELL encouraged Minor Victim-3 to massage Epstein, knowing that Epstein would engage in sex acts with Minor Victim-3 during those massages. Minor Victim-3 provided Epstein with the requested massages, and during those massages, Epstein sexually abused Minor Victim-3. MAXWELL was aware that Epstein engaged in sexual activity with Minor Victim-3 on multiple occasions, including at times when Minor Victim-3 was under the age of 18, including in the context of a sexualized massage.\nMAXWELL'S EFFORTS TO CONCEAL HER CONDUCT\n8. In or around 2016, in the context of a deposition as part of civil litigation, GHISLAINE MAXWELL, the defendant, repeatedly provided false and perjurious statements, under oath, regarding, among other subjects, her role in facilitating the\n9\nDOJ-OGR-00001475",
  "text_blocks": [
    {
      "type": "printed",
      "content": "Case 1:20-cr-00330-AJN Document 1 Filed 06/29/20 Page 9 of 18",
      "position": "header"
    },
    {
      "type": "printed",
      "content": "an unsolicited massage to Minor Victim-2, during which Minor Victim-2 was topless. MAXWELL also encouraged Minor Victim-2 to massage Epstein.\nc. MAXWELL groomed and befriended Minor Victim-3 in London, England between approximately 1994 and 1995, including during a period of time in which MAXWELL knew that Minor Victim-3 was under the age of 18. Among other things, MAXWELL discussed Minor Victim-3's life and family with Minor Victim-3. MAXWELL introduced Minor Victim-3 to Epstein and arranged for multiple interactions between Minor Victim-3 and Epstein. During those interactions, MAXWELL encouraged Minor Victim-3 to massage Epstein, knowing that Epstein would engage in sex acts with Minor Victim-3 during those massages. Minor Victim-3 provided Epstein with the requested massages, and during those massages, Epstein sexually abused Minor Victim-3. MAXWELL was aware that Epstein engaged in sexual activity with Minor Victim-3 on multiple occasions, including at times when Minor Victim-3 was under the age of 18, including in the context of a sexualized massage.",
      "position": "main"
    },
    {
      "type": "printed",
      "content": "MAXWELL'S EFFORTS TO CONCEAL HER CONDUCT",
      "position": "header"
    },
    {
      "type": "printed",
      "content": "8. In or around 2016, in the context of a deposition as part of civil litigation, GHISLAINE MAXWELL, the defendant, repeatedly provided false and perjurious statements, under oath, regarding, among other subjects, her role in facilitating the",
      "position": "main"
    },
    {
      "type": "printed",
      "content": "9",
      "position": "footer"
    },
    {
      "type": "printed",
      "content": "DOJ-OGR-00001475",
      "position": "footer"
    }
  ],
  "entities": {
    "people": [
      "MAXWELL",
      "Epstein",
      "Minor Victim-2",
      "Minor Victim-3",
      "GHISLAINE MAXWELL"
    ],
    "organizations": [],
    "locations": [
      "London",
      "England"
    ],
    "dates": [
      "1994",
      "1995",
      "2016",
      "06/29/20"
    ],
    "reference_numbers": [
      "1:20-cr-00330-AJN",
      "Document 1",
      "DOJ-OGR-00001475"
    ]
  },
  "additional_notes": "The document appears to be a court filing related to the case against Ghislaine Maxwell. The text is typed, and there are no visible stamps or handwritten notes. The document is page 9 of 18."
}