{
  "document_metadata": {
    "page_number": "25",
    "document_number": "20-1",
    "date": "04/01/2021",
    "document_type": "court document",
    "has_handwriting": false,
    "has_stamps": false
  },
  "full_text": "Case 21-770, Document 20-1, 04/01/2021, 3068530, Page25 of 31\n\nThe government shotguns manufactured assertions in support of the supposed flight risk. First, the ridiculous contention that she was hiding before her arrest. In fact, she was living in, and arrested in, her own home in New Hampshire. She was in touch with her lawyers and as the government has to concede, her lawyers were communicating with the government. Ex.D at 27. Despite plenty of opportunities, she had not left the United States since Epstein's arrest, and had been living in the United States for 30 years. She became a U.S. citizen. She lived and worked here for 30 years. The government knew exactly where she was. (FBI New York Assistant Director William Sweeney Jr.: \"We'd been discretely keeping tabs on Maxwell's whereabouts as we worked this investigation.\")\n\nThe fact that she was holed up in her home because she was being relentlessly harassed by the media is not evidence of hiding from the government. In fact, one sensational tabloid put a £10,000 bounty on her. \"Wanted: The Sun is offering a £10,000 reward for information on ... Ghislaine Maxwell,\" The Sun, November 20, 2019, available at: https://tinyurl.com/3vewtnx3. Anyone facing these unprecedented safety concerns from the media mob would try to keep a low profile. But a low 23\n\nDOJ-OGR-00000935",
  "text_blocks": [
    {
      "type": "printed",
      "content": "Case 21-770, Document 20-1, 04/01/2021, 3068530, Page25 of 31",
      "position": "header"
    },
    {
      "type": "printed",
      "content": "The government shotguns manufactured assertions in support of the supposed flight risk. First, the ridiculous contention that she was hiding before her arrest. In fact, she was living in, and arrested in, her own home in New Hampshire. She was in touch with her lawyers and as the government has to concede, her lawyers were communicating with the government. Ex.D at 27. Despite plenty of opportunities, she had not left the United States since Epstein's arrest, and had been living in the United States for 30 years. She became a U.S. citizen. She lived and worked here for 30 years. The government knew exactly where she was. (FBI New York Assistant Director William Sweeney Jr.: \"We'd been discretely keeping tabs on Maxwell's whereabouts as we worked this investigation.\")",
      "position": "main content"
    },
    {
      "type": "printed",
      "content": "The fact that she was holed up in her home because she was being relentlessly harassed by the media is not evidence of hiding from the government. In fact, one sensational tabloid put a £10,000 bounty on her. \"Wanted: The Sun is offering a £10,000 reward for information on ... Ghislaine Maxwell,\" The Sun, November 20, 2019, available at: https://tinyurl.com/3vewtnx3. Anyone facing these unprecedented safety concerns from the media mob would try to keep a low profile. But a low",
      "position": "main content"
    },
    {
      "type": "printed",
      "content": "23",
      "position": "footer"
    },
    {
      "type": "printed",
      "content": "DOJ-OGR-00000935",
      "position": "footer"
    }
  ],
  "entities": {
    "people": [
      "Ghislaine Maxwell",
      "William Sweeney Jr.",
      "Epstein"
    ],
    "organizations": [
      "FBI",
      "The Sun"
    ],
    "locations": [
      "New Hampshire",
      "United States",
      "New York"
    ],
    "dates": [
      "04/01/2021",
      "November 20, 2019"
    ],
    "reference_numbers": [
      "Case 21-770",
      "Document 20-1",
      "3068530",
      "DOJ-OGR-00000935"
    ]
  },
  "additional_notes": "The document appears to be a court filing related to the case of Ghislaine Maxwell. The text is printed and there are no visible stamps or handwritten annotations. The document is page 25 of 31."
}