{
  "document_metadata": {
    "page_number": "19",
    "document_number": "22",
    "date": "July 13, 2020",
    "document_type": "court document",
    "has_handwriting": true,
    "has_stamps": false
  },
  "full_text": "Case 1:20-cr-00330-AJN Document 22 Filed 07/13/20 Page 19 of 19 Dated: New York, New York July 13, 2020 CONCLUSION The Government respectfully submits that the defendant is an extreme risk of flight. As set forth above, the defendant cannot meet her burden of overcoming the statutory presumption in favor of detention. There are no conditions of bail that would assure the defendant's presence in court proceedings in this case. Accordingly, any application for bail should be denied. Respectfully submitted, AUDREY STRAUSS Acting United States Attorney By: Alison Moe Alex Rossmiller Mailee Conley Assistant United States Attorneys (212) 637-2225 18 DOJ-OGR-00001629",
  "text_blocks": [
    {
      "type": "printed",
      "content": "Case 1:20-cr-00330-AJN Document 22 Filed 07/13/20 Page 19 of 19",
      "position": "header"
    },
    {
      "type": "printed",
      "content": "Dated: New York, New York July 13, 2020",
      "position": "top"
    },
    {
      "type": "printed",
      "content": "CONCLUSION",
      "position": "middle"
    },
    {
      "type": "printed",
      "content": "The Government respectfully submits that the defendant is an extreme risk of flight. As set forth above, the defendant cannot meet her burden of overcoming the statutory presumption in favor of detention. There are no conditions of bail that would assure the defendant's presence in court proceedings in this case. Accordingly, any application for bail should be denied.",
      "position": "middle"
    },
    {
      "type": "printed",
      "content": "Respectfully submitted,",
      "position": "middle"
    },
    {
      "type": "printed",
      "content": "AUDREY STRAUSS Acting United States Attorney",
      "position": "middle"
    },
    {
      "type": "handwritten",
      "content": "Alison G. J.",
      "position": "middle"
    },
    {
      "type": "printed",
      "content": "By: Alison Moe Alex Rossmiller Mailee Conley Assistant United States Attorneys (212) 637-2225",
      "position": "bottom"
    },
    {
      "type": "printed",
      "content": "DOJ-OGR-00001629",
      "position": "footer"
    }
  ],
  "entities": {
    "people": [
      "AUDREY STRAUSS",
      "Alison Moe",
      "Alex Rossmiller",
      "Mailee Conley"
    ],
    "organizations": [
      "United States Attorney"
    ],
    "locations": [
      "New York"
    ],
    "dates": [
      "July 13, 2020"
    ],
    "reference_numbers": [
      "1:20-cr-00330-AJN",
      "DOJ-OGR-00001629",
      "(212) 637-2225"
    ]
  },
  "additional_notes": "The document appears to be a court filing related to a criminal case. The text is mostly printed, with one handwritten signature. The document is in good condition, with no visible redactions or damage."
}