{
  "document_metadata": {
    "page_number": "3",
    "document_number": "3-2",
    "date": "03/24/2021",
    "document_type": "CRIMINAL DOCKET",
    "has_handwriting": false,
    "has_stamps": false
  },
  "full_text": "Case 21-770, Document 3-2, 03/24/2021, 3065978, Page3 of 25\nAPPEAL,ECF,INTAPP\nU.S. District Court\nSouthern District of New York (Foley Square)\nCRIMINAL DOCKET FOR CASE #: 1:20-cr-00330-AJN All Defendants\nCase title: USA v. Maxwell\nDate Filed: 06/29/2020\nAssigned to: Judge Alison J. Nathan\nAppeals court case number: 21-0058 U.S. Court of Appeals, 2nd Circ.\nDefendant (1)\nGhislaine Maxwell\nalso known as\nSealed Defendant 1\nrepresented by Christian R. Everdell\nCohen & Gresser LLP\n800 Third Avenue\nNew York, NY 10022\n212-707-7268\nFax: 212-957-4514\nEmail: ceverdell@cohengresser.com\nLEAD ATTORNEY\nATTORNEY TO BE NOTICED\nJeffrey S. Pagliuca\nHaddon Morgan and Foreman\n150 East 10th Avenue\nDenver, CO 80203\n(303)-831-7364\nFax: (303)-832-2628\nEmail: jpagliuca@hmflaw.com\nLEAD ATTORNEY\nATTORNEY TO BE NOTICED\nLaura A. Menninger\nHaddon, Morgan and Foreman, P.C.\n150 East Tenth Avenue\nDenver, CO 80203\n(303)-831-7364\nFax: (303)-832-2628\nEmail: lmenninger@hmflaw.com\nLEAD ATTORNEY\nATTORNEY TO BE NOTICED\nMark Stewart Cohen\nCohen & Gresser, LLP (NYC)\n800 Third Avenue\nNew York, NY 10022\n(212) 957-7600\nFax: (212)957-4514\nEmail: mcohen@cohengresser.com\nLEAD ATTORNEY\nATTORNEY TO BE NOTICED\nBobbi C Sternheim\nLaw Offices of Bobbi C. Sternheim\n33 West 19th Street–4th Fl.\nNew York, NY 10007\n(212) 243-1100\nFax: (888) 587-4737\nEmail: bc@sternheimlaw.com\nDOJ-OGR-00000879",
  "text_blocks": [
    {
      "type": "printed",
      "content": "Case 21-770, Document 3-2, 03/24/2021, 3065978, Page3 of 25",
      "position": "header"
    },
    {
      "type": "printed",
      "content": "U.S. District Court\nSouthern District of New York (Foley Square)\nCRIMINAL DOCKET FOR CASE #: 1:20-cr-00330-AJN All Defendants",
      "position": "header"
    },
    {
      "type": "printed",
      "content": "Case title: USA v. Maxwell\nDate Filed: 06/29/2020",
      "position": "header"
    },
    {
      "type": "printed",
      "content": "Assigned to: Judge Alison J. Nathan\nAppeals court case number: 21-0058 U.S. Court of Appeals, 2nd Circ.",
      "position": "body"
    },
    {
      "type": "printed",
      "content": "Defendant (1)\nGhislaine Maxwell\nalso known as\nSealed Defendant 1",
      "position": "body"
    },
    {
      "type": "printed",
      "content": "represented by Christian R. Everdell\nCohen & Gresser LLP\n800 Third Avenue\nNew York, NY 10022\n212-707-7268\nFax: 212-957-4514\nEmail: ceverdell@cohengresser.com\nLEAD ATTORNEY\nATTORNEY TO BE NOTICED",
      "position": "body"
    },
    {
      "type": "printed",
      "content": "Jeffrey S. Pagliuca\nHaddon Morgan and Foreman\n150 East 10th Avenue\nDenver, CO 80203\n(303)-831-7364\nFax: (303)-832-2628\nEmail: jpagliuca@hmflaw.com\nLEAD ATTORNEY\nATTORNEY TO BE NOTICED",
      "position": "body"
    },
    {
      "type": "printed",
      "content": "Laura A. Menninger\nHaddon, Morgan and Foreman, P.C.\n150 East Tenth Avenue\nDenver, CO 80203\n(303)-831-7364\nFax: (303)-832-2628\nEmail: lmenninger@hmflaw.com\nLEAD ATTORNEY\nATTORNEY TO BE NOTICED",
      "position": "body"
    },
    {
      "type": "printed",
      "content": "Mark Stewart Cohen\nCohen & Gresser, LLP (NYC)\n800 Third Avenue\nNew York, NY 10022\n(212) 957-7600\nFax: (212)957-4514\nEmail: mcohen@cohengresser.com\nLEAD ATTORNEY\nATTORNEY TO BE NOTICED",
      "position": "body"
    },
    {
      "type": "printed",
      "content": "Bobbi C Sternheim\nLaw Offices of Bobbi C. Sternheim\n33 West 19th Street–4th Fl.\nNew York, NY 10007\n(212) 243-1100\nFax: (888) 587-4737\nEmail: bc@sternheimlaw.com",
      "position": "body"
    },
    {
      "type": "printed",
      "content": "DOJ-OGR-00000879",
      "position": "footer"
    }
  ],
  "entities": {
    "people": [
      "Ghislaine Maxwell",
      "Alison J. Nathan",
      "Christian R. Everdell",
      "Jeffrey S. Pagliuca",
      "Laura A. Menninger",
      "Mark Stewart Cohen",
      "Bobbi C Sternheim"
    ],
    "organizations": [
      "U.S. District Court",
      "Southern District of New York",
      "Cohen & Gresser LLP",
      "Haddon Morgan and Foreman",
      "Haddon, Morgan and Foreman, P.C.",
      "Law Offices of Bobbi C. Sternheim",
      "U.S. Court of Appeals"
    ],
    "locations": [
      "New York",
      "Denver",
      "CO",
      "NYC"
    ],
    "dates": [
      "03/24/2021",
      "06/29/2020"
    ],
    "reference_numbers": [
      "1:20-cr-00330-AJN",
      "21-0058",
      "21-770",
      "3-2",
      "3065978",
      "DOJ-OGR-00000879"
    ]
  },
  "additional_notes": "The document appears to be a court docket sheet with printed text. There are no visible handwritten notes or stamps."
}