{
  "document_metadata": {
    "page_number": "1",
    "document_number": "51",
    "date": "08/27/19",
    "document_type": "Court Document",
    "has_handwriting": true,
    "has_stamps": true
  },
  "full_text": "Case 1:19-cr-00490-RMB Document 51 Filed 08/27/19 Page 1 of 4\n\nUSDC SDNY DOCUMENT ELECTRONICALLY FILED DOC #: DATE FILED: 8/27/19 District Judge Richard Berman\n\nIN THE SOUTHERN DISTRICT CIRCUIT COURT of NEW YORK FOR THE UNITED STATES OF AMERICA\n\nTHE UNITED STATES OF AMERICA, Plaintiffs, v. JEFFREY EPSTEIN, Defendants, and: David A. Golden (alias Jeremy Thundercloud/ G.) Intervenor CRIMINAL ACTION NO. 1:19-cr-00490 Motion to Intervene Application respectfully denied. SO ORDERED: Date: 8/27/19 Richard M. Berman Richard M. Berman, U.S.D.J.\n\nMOTION TO INTERVENE\n\nDavid Golden (herewith referred to as G.) respectfully moves to Intervene in the action, as this case involves common issues of law and fact that are common with his own case, including criminal fraud and conspiracy. G.'s complaint (No. CV186051 RBL) was filed under the False Claims Act in the District Ct. of Western Washington in December of 2018.\n\nDAVID GOLDEN 15151 NW MASON HILL RD NORTH PLAINS, OR 97133\n\nMOTION TO INTERVENE - 1 DOJ-OGR-00000633",
  "text_blocks": [
    {
      "type": "printed",
      "content": "Case 1:19-cr-00490-RMB Document 51 Filed 08/27/19 Page 1 of 4",
      "position": "header"
    },
    {
      "type": "stamp",
      "content": "USDC SDNY DOCUMENT ELECTRONICALLY FILED DOC #: DATE FILED: 8/27/19",
      "position": "header"
    },
    {
      "type": "printed",
      "content": "IN THE SOUTHERN DISTRICT CIRCUIT COURT of NEW YORK FOR THE UNITED STATES OF AMERICA",
      "position": "header"
    },
    {
      "type": "printed",
      "content": "THE UNITED STATES OF AMERICA, Plaintiffs, v. JEFFREY EPSTEIN, Defendants, and: David A. Golden (alias Jeremy Thundercloud/ G.) Intervenor CRIMINAL ACTION NO. 1:19-cr-00490 Motion to Intervene",
      "position": "middle"
    },
    {
      "type": "handwritten",
      "content": "Application respectfully denied.",
      "position": "middle"
    },
    {
      "type": "printed",
      "content": "SO ORDERED: Date: 8/27/19",
      "position": "middle"
    },
    {
      "type": "signature",
      "content": "Richard M. Berman",
      "position": "middle"
    },
    {
      "type": "printed",
      "content": "Richard M. Berman, U.S.D.J.",
      "position": "middle"
    },
    {
      "type": "printed",
      "content": "MOTION TO INTERVENE David Golden (herewith referred to as G.) respectfully moves to Intervene in the action, as this case involves common issues of law and fact that are common with his own case, including criminal fraud and conspiracy. G.'s complaint (No. CV186051 RBL) was filed under the False Claims Act in the District Ct. of Western Washington in December of 2018.",
      "position": "middle"
    },
    {
      "type": "printed",
      "content": "DAVID GOLDEN 15151 NW MASON HILL RD NORTH PLAINS, OR 97133",
      "position": "footer"
    },
    {
      "type": "printed",
      "content": "MOTION TO INTERVENE - 1 DOJ-OGR-00000633",
      "position": "footer"
    }
  ],
  "entities": {
    "people": [
      "Richard Berman",
      "Jeffrey Epstein",
      "David A. Golden",
      "Jeremy Thundercloud"
    ],
    "organizations": [
      "United States of America",
      "USDC SDNY"
    ],
    "locations": [
      "New York",
      "Western Washington",
      "North Plains, OR"
    ],
    "dates": [
      "08/27/19",
      "December 2018"
    ],
    "reference_numbers": [
      "1:19-cr-00490",
      "CV186051 RBL",
      "DOJ-OGR-00000633"
    ]
  },
  "additional_notes": "The document is a court filing with a mix of printed and handwritten text. The handwritten text includes a denial of an application and a signature. The document is related to a criminal case involving Jeffrey Epstein."
}