{
  "document_metadata": {
    "page_number": "15",
    "document_number": "9:08-cv-81078-KAM Document 80 Entered on FLSD Docket 07/05/2010",
    "date": "07/05/2010",
    "document_type": "Court Document",
    "has_handwriting": true,
    "has_stamps": false
  },
  "full_text": "Case 9:08-cv-81078-KAM Document 80 Entered on FLSD Docket 07/05/2010 Page 15 of 20\n\nRespectfully submitted,\nWIFREDO A. FERRER\nUNITED STATES ATTORNEY\nBy:\nDexter A. Lee\nAssistant United States Attorney\nFlorida Bar No. 0936693\n99 N.E. 4th Street\nMiami, Florida 33132\nTel: (305) 961-9320; Fax: (305) 530-7139\nEmail: dexter.lee@usdoj.gov\n\nEduardo I. Sánchez\nAssistant United States Attorney\nFlorida Bar No. 877875\n99 N.E. 4th Street\nMiami, Florida 33132\nTel: (305) 961-9057; Fax: (305) 536-4676\nEmail: eduardo.i.sanchez@usdoj.gov\n\nA. Marie Villafaña\nAssistant United States Attorney\nFlorida Bar No. 0018255\n500 S. Australian Avenue, Suite 400\nWest Palm Beach, FL 33401\nTel: (561) 820-8711; Fax: (561) 820-8777\nEmail: ann.marie.c.villafana@usdoj.gov\n\nAttorneys for Respondent\n\n14\nDOJ-OGR-00000319",
  "text_blocks": [
    {
      "type": "printed",
      "content": "Case 9:08-cv-81078-KAM Document 80 Entered on FLSD Docket 07/05/2010 Page 15 of 20",
      "position": "header"
    },
    {
      "type": "printed",
      "content": "Respectfully submitted,\nWIFREDO A. FERRER\nUNITED STATES ATTORNEY",
      "position": "top"
    },
    {
      "type": "handwritten",
      "content": "",
      "position": "middle"
    },
    {
      "type": "printed",
      "content": "By:\nDexter A. Lee\nAssistant United States Attorney\nFlorida Bar No. 0936693\n99 N.E. 4th Street\nMiami, Florida 33132\nTel: (305) 961-9320; Fax: (305) 530-7139\nEmail: dexter.lee@usdoj.gov",
      "position": "middle"
    },
    {
      "type": "printed",
      "content": "Eduardo I. Sánchez\nAssistant United States Attorney\nFlorida Bar No. 877875\n99 N.E. 4th Street\nMiami, Florida 33132\nTel: (305) 961-9057; Fax: (305) 536-4676\nEmail: eduardo.i.sanchez@usdoj.gov",
      "position": "middle"
    },
    {
      "type": "printed",
      "content": "A. Marie Villafaña\nAssistant United States Attorney\nFlorida Bar No. 0018255\n500 S. Australian Avenue, Suite 400\nWest Palm Beach, FL 33401\nTel: (561) 820-8711; Fax: (561) 820-8777\nEmail: ann.marie.c.villafana@usdoj.gov",
      "position": "middle"
    },
    {
      "type": "printed",
      "content": "Attorneys for Respondent",
      "position": "middle"
    },
    {
      "type": "printed",
      "content": "14",
      "position": "footer"
    },
    {
      "type": "printed",
      "content": "DOJ-OGR-00000319",
      "position": "footer"
    }
  ],
  "entities": {
    "people": [
      "WIFREDO A. FERRER",
      "Dexter A. Lee",
      "Eduardo I. Sánchez",
      "A. Marie Villafaña"
    ],
    "organizations": [
      "UNITED STATES ATTORNEY"
    ],
    "locations": [
      "Miami",
      "Florida",
      "West Palm Beach"
    ],
    "dates": [
      "07/05/2010"
    ],
    "reference_numbers": [
      "9:08-cv-81078-KAM",
      "0936693",
      "877875",
      "0018255",
      "DOJ-OGR-00000319"
    ]
  },
  "additional_notes": "The document appears to be a court filing with contact information for several Assistant United States Attorneys. The document is signed by Dexter A. Lee."
}