{
  "document_metadata": {
    "page_number": "23",
    "document_number": "136-9",
    "date": "02/04/21",
    "document_type": "court document",
    "has_handwriting": false,
    "has_stamps": false
  },
  "full_text": "Case 1:20-cr-00330-AJN Document 136-9 Filed 02/04/21 Page 23 of 33 22\n1 observe it.\n2 I think we are up to 369-10. This is a January 22,\n3 2015 Daily Mail article. That may be unsealed in full but,\n4 apparently, it's publicly available anyway.\n5 369-11. Excerpts from Detective Recarey's deposition.\n6 Same. Same. Unseal and redact names and identifying\n7 information of nonparties.\n8 369-12. Excerpts from a deposition of a Doe. We are\n9 not up to that Doe. Remain sealed.\n10 369-13. Excerpts from the deposition of a Doe. We\n11 are not up to that Doe yet. Keep sealed.\n12 Same with 369-14. Another Doe.\n13 369-15. Another Doe.\n14 And 369-16, another Doe. We are not up to any of\n15 those yet. Those transcripts shall remain sealed.\n16 320. This is defendant's submission regarding search\n17 terms. Unseal and redact only the names and identifying\n18 information of nonparties. People's e-mails, including Ms.\n19 Maxwell's, should be redacted.\n20 321. Ms. Menninger's declaration. Unseal and keep\n21 redacted the e-mail addresses and any names, identifying\n22 information, or e-mail addresses of nonparties.\n23 321-1. Correspondence from Ms. Schultz. Unseal and\n24 redact only the names and identifying information of nonparties\n25 and Ms. Maxwell's e-mail address.\nSOUTHERN DISTRICT REPORTERS, P.C.\n(212) 805-0300",
  "text_blocks": [
    {
      "type": "printed",
      "content": "Case 1:20-cr-00330-AJN Document 136-9 Filed 02/04/21 Page 23 of 33 22",
      "position": "header"
    },
    {
      "type": "printed",
      "content": "1 observe it.\n2 I think we are up to 369-10. This is a January 22,\n3 2015 Daily Mail article. That may be unsealed in full but,\n4 apparently, it's publicly available anyway.\n5 369-11. Excerpts from Detective Recarey's deposition.\n6 Same. Same. Unseal and redact names and identifying\n7 information of nonparties.\n8 369-12. Excerpts from a deposition of a Doe. We are\n9 not up to that Doe. Remain sealed.\n10 369-13. Excerpts from the deposition of a Doe. We\n11 are not up to that Doe yet. Keep sealed.\n12 Same with 369-14. Another Doe.\n13 369-15. Another Doe.\n14 And 369-16, another Doe. We are not up to any of\n15 those yet. Those transcripts shall remain sealed.\n16 320. This is defendant's submission regarding search\n17 terms. Unseal and redact only the names and identifying\n18 information of nonparties. People's e-mails, including Ms.\n19 Maxwell's, should be redacted.\n20 321. Ms. Menninger's declaration. Unseal and keep\n21 redacted the e-mail addresses and any names, identifying\n22 information, or e-mail addresses of nonparties.\n23 321-1. Correspondence from Ms. Schultz. Unseal and\n24 redact only the names and identifying information of nonparties\n25 and Ms. Maxwell's e-mail address.",
      "position": "main"
    },
    {
      "type": "printed",
      "content": "SOUTHERN DISTRICT REPORTERS, P.C.\n(212) 805-0300",
      "position": "footer"
    }
  ],
  "entities": {
    "people": [
      "Detective Recarey",
      "Ms. Menninger",
      "Ms. Schultz",
      "Ms. Maxwell"
    ],
    "organizations": [
      "Daily Mail",
      "SOUTHERN DISTRICT REPORTERS, P.C."
    ],
    "locations": [],
    "dates": [
      "January 22, 2015",
      "02/04/21"
    ],
    "reference_numbers": [
      "1:20-cr-00330-AJN",
      "136-9",
      "369-10",
      "369-11",
      "369-12",
      "369-13",
      "369-14",
      "369-15",
      "369-16",
      "320",
      "321",
      "321-1"
    ]
  },
  "additional_notes": "The document appears to be a court transcript or filing, discussing the sealing and redaction of various documents and depositions. The text is typed, with no visible handwriting or stamps."
}