{
  "document_metadata": {
    "page_number": "1 of 26",
    "document_number": "18",
    "date": "07/10/20",
    "document_type": "court document",
    "has_handwriting": false,
    "has_stamps": false
  },
  "full_text": "Case 1:20-cr-00330-AJN Document 18 Filed 07/10/20 Page 1 of 26\n\nUNITED STATES DISTRICT COURT\nSOUTHERN DISTRICT OF NEW YORK\n--------------------------------------------------------X\n\nUNITED STATES OF AMERICA,\n\nv.\n\nGHISLAINE MAXWELL,\n\nDefendant.\n\n--------------------------------------------------------X\n\nMEMORANDUM OF GHISLAINE MAXWELL\nIN OPPOSITION TO THE GOVERNMENT'S MOTION FOR DETENTION\n\nMark S. Cohen\nChristian R. Everdell\nCOHEN & GRESSER LLP\n800 Third Avenue\nNew York, NY 10022\nPhone: 212-957-7600\n\nJeffrey S. Pagliuca\n(pro hac vice admission pending)\nLaura A. Menninger\nHADDON, MORGAN & FORMAN P.C.\n150 East 10th Avenue\nDenver, Colorado 80203\nPhone: 303-831-7364\n\nAttorneys for Ghislaine Maxwell\n\nDOJ-OGR-00001581",
  "text_blocks": [
    {
      "type": "printed",
      "content": "Case 1:20-cr-00330-AJN Document 18 Filed 07/10/20 Page 1 of 26",
      "position": "header"
    },
    {
      "type": "printed",
      "content": "UNITED STATES DISTRICT COURT\nSOUTHERN DISTRICT OF NEW YORK\n--------------------------------------------------------X\n\nUNITED STATES OF AMERICA,\n\nv.\n\nGHISLAINE MAXWELL,\n\nDefendant.\n\n--------------------------------------------------------X",
      "position": "top"
    },
    {
      "type": "printed",
      "content": "MEMORANDUM OF GHISLAINE MAXWELL\nIN OPPOSITION TO THE GOVERNMENT'S MOTION FOR DETENTION",
      "position": "middle"
    },
    {
      "type": "printed",
      "content": "Mark S. Cohen\nChristian R. Everdell\nCOHEN & GRESSER LLP\n800 Third Avenue\nNew York, NY 10022\nPhone: 212-957-7600\n\nJeffrey S. Pagliuca\n(pro hac vice admission pending)\nLaura A. Menninger\nHADDON, MORGAN & FORMAN P.C.\n150 East 10th Avenue\nDenver, Colorado 80203\nPhone: 303-831-7364\n\nAttorneys for Ghislaine Maxwell",
      "position": "middle"
    },
    {
      "type": "printed",
      "content": "DOJ-OGR-00001581",
      "position": "footer"
    }
  ],
  "entities": {
    "people": [
      "Ghislaine Maxwell",
      "Mark S. Cohen",
      "Christian R. Everdell",
      "Jeffrey S. Pagliuca",
      "Laura A. Menninger"
    ],
    "organizations": [
      "COHEN & GRESSER LLP",
      "HADDON, MORGAN & FORMAN P.C.",
      "UNITED STATES DISTRICT COURT",
      "UNITED STATES OF AMERICA"
    ],
    "locations": [
      "New York",
      "Denver",
      "Colorado"
    ],
    "dates": [
      "07/10/20"
    ],
    "reference_numbers": [
      "1:20-cr-00330-AJN",
      "Document 18",
      "20 Cr. 330 (AJN)",
      "DOJ-OGR-00001581"
    ]
  },
  "additional_notes": "The document appears to be a court filing in a criminal case against Ghislaine Maxwell. The text is clear and legible, with no apparent redactions or damage."
}