{
  "document_metadata": {
    "page_number": "51",
    "document_number": "53",
    "date": "09/03/19",
    "document_type": "court transcript",
    "has_handwriting": false,
    "has_stamps": false
  },
  "full_text": "Case 1:19-cr-00490-RMB Document 53 Filed 09/03/19 Page 51 of 86 51 J8RPEPS2 the leading expert formerly of the District Court of Utah, I believe, and it's a pleasure to have you here today. MR. CASSELL: Thank you, your Honor. THE COURT: Thanks. Mr. Boies? MR. BOIES: Thank you, your Honor. David Boies of Boies Schiller Flexner. We have with us today five of the victims that we represent. There are a number of additional victims who either were unable to attend or are still unwilling to come forward publicly. This has been an enormously traumatic aspect of their lives, something that, as you've already heard and will hear more today, is something that they can never entirely escape from. I want to, as prior counsel have, commend both the Court and counsel for the Department of Justice for the consideration and respect and attention that they have paid to the victims. We believe that that is not only right, as a matter of human dignity, but we think that is exactly what the law requires and intends. I will be more blunt than the Court has been, or Professor Cassell has been about Professor Green's article. That is an article that cites no authority, and I believe there is no authority for his proposition. I entirely respect his right to advocate on behalf of his client Alan Dershowitz, who has retained him in connection with litigation that we've SOUTHERN DISTRICT REPORTERS, P.C. (212) 805-0300 DOJ-OGR-00000689",
  "text_blocks": [
    {
      "type": "printed",
      "content": "Case 1:19-cr-00490-RMB Document 53 Filed 09/03/19 Page 51 of 86 51 J8RPEPS2",
      "position": "header"
    },
    {
      "type": "printed",
      "content": "the leading expert formerly of the District Court of Utah, I believe, and it's a pleasure to have you here today. MR. CASSELL: Thank you, your Honor. THE COURT: Thanks. Mr. Boies? MR. BOIES: Thank you, your Honor. David Boies of Boies Schiller Flexner. We have with us today five of the victims that we represent. There are a number of additional victims who either were unable to attend or are still unwilling to come forward publicly. This has been an enormously traumatic aspect of their lives, something that, as you've already heard and will hear more today, is something that they can never entirely escape from. I want to, as prior counsel have, commend both the Court and counsel for the Department of Justice for the consideration and respect and attention that they have paid to the victims. We believe that that is not only right, as a matter of human dignity, but we think that is exactly what the law requires and intends. I will be more blunt than the Court has been, or Professor Cassell has been about Professor Green's article. That is an article that cites no authority, and I believe there is no authority for his proposition. I entirely respect his right to advocate on behalf of his client Alan Dershowitz, who has retained him in connection with litigation that we've",
      "position": "main content"
    },
    {
      "type": "printed",
      "content": "SOUTHERN DISTRICT REPORTERS, P.C. (212) 805-0300",
      "position": "footer"
    },
    {
      "type": "printed",
      "content": "DOJ-OGR-00000689",
      "position": "footer"
    }
  ],
  "entities": {
    "people": [
      "David Boies",
      "Alan Dershowitz",
      "Cassell",
      "Green"
    ],
    "organizations": [
      "Boies Schiller Flexner",
      "Department of Justice",
      "Southern District Reporters, P.C.",
      "District Court of Utah"
    ],
    "locations": [
      "Utah"
    ],
    "dates": [
      "09/03/19"
    ],
    "reference_numbers": [
      "1:19-cr-00490-RMB",
      "53",
      "DOJ-OGR-00000689"
    ]
  },
  "additional_notes": "The document appears to be a court transcript with a clear and legible format. There are no visible redactions or damage."
}