{
  "document_metadata": {
    "page_number": "1",
    "document_number": "14",
    "date": "07/08/20",
    "document_type": "NOTICE OF APPEARANCE",
    "has_handwriting": false,
    "has_stamps": false
  },
  "full_text": "Case 1:20-cr-00330-AJN Document 14 Filed 07/08/20 Page 1 of 1\n\nUNITED STATES DISTRICT COURT\nSOUTHERN DISTRICT OF NEW YORK\n\nUNITED STATES OF AMERICA,\nPlaintiff,\nv.\nGHISLAINE MAXWELL,\nDefendant.\n\n20-CR-330-AJN\n\nNOTICE OF APPEARANCE\n\nPLEASE TAKE NOTICE that the undersigned attorney, Laura A. Menninger, who is a member in good standing of the bar of this Court, hereby appears as counsel for Defendant Ghislaine Maxwell in the above-captioned proceeding.\n\nDated: Denver, Colorado\nJuly 8, 2020.\n\nRespectfully submitted,\n\n/s/ Laura A. Menninger\nLaura A. Menninger (LM-1374)\nHADDON, MORGAN AND FOREMAN, P.C.\n150 East 10th Avenue\nDenver, CO 80203\nPhone: 303.831.7364\nFax: 303.832.2628\nlmenninger@hmflaw.com\nAttorney for Ghislaine Maxwell\n\nDOJ-OGR-00001548",
  "text_blocks": [
    {
      "type": "printed",
      "content": "Case 1:20-cr-00330-AJN Document 14 Filed 07/08/20 Page 1 of 1",
      "position": "header"
    },
    {
      "type": "printed",
      "content": "UNITED STATES DISTRICT COURT\nSOUTHERN DISTRICT OF NEW YORK",
      "position": "header"
    },
    {
      "type": "printed",
      "content": "UNITED STATES OF AMERICA,\nPlaintiff,\nv.\nGHISLAINE MAXWELL,\nDefendant.",
      "position": "middle"
    },
    {
      "type": "printed",
      "content": "20-CR-330-AJN",
      "position": "middle"
    },
    {
      "type": "printed",
      "content": "NOTICE OF APPEARANCE",
      "position": "middle"
    },
    {
      "type": "printed",
      "content": "PLEASE TAKE NOTICE that the undersigned attorney, Laura A. Menninger, who is a member in good standing of the bar of this Court, hereby appears as counsel for Defendant Ghislaine Maxwell in the above-captioned proceeding.",
      "position": "middle"
    },
    {
      "type": "printed",
      "content": "Dated: Denver, Colorado\nJuly 8, 2020.",
      "position": "middle"
    },
    {
      "type": "printed",
      "content": "Respectfully submitted,",
      "position": "middle"
    },
    {
      "type": "signature",
      "content": "/s/ Laura A. Menninger",
      "position": "middle"
    },
    {
      "type": "printed",
      "content": "Laura A. Menninger (LM-1374)\nHADDON, MORGAN AND FOREMAN, P.C.\n150 East 10th Avenue\nDenver, CO 80203\nPhone: 303.831.7364\nFax: 303.832.2628\nlmenninger@hmflaw.com\nAttorney for Ghislaine Maxwell",
      "position": "footer"
    },
    {
      "type": "printed",
      "content": "DOJ-OGR-00001548",
      "position": "footer"
    }
  ],
  "entities": {
    "people": [
      "Laura A. Menninger",
      "Ghislaine Maxwell"
    ],
    "organizations": [
      "UNITED STATES DISTRICT COURT",
      "SOUTHERN DISTRICT OF NEW YORK",
      "HADDON, MORGAN AND FOREMAN, P.C."
    ],
    "locations": [
      "Denver, Colorado",
      "New York"
    ],
    "dates": [
      "July 8, 2020",
      "07/08/20"
    ],
    "reference_numbers": [
      "1:20-cr-00330-AJN",
      "20-CR-330-AJN",
      "LM-1374",
      "DOJ-OGR-00001548"
    ]
  },
  "additional_notes": "The document is a Notice of Appearance filed by Laura A. Menninger on behalf of Ghislaine Maxwell in the United States District Court for the Southern District of New York. The document is dated July 8, 2020, and is related to case number 1:20-cr-00330-AJN."
}