{
  "document_metadata": {
    "page_number": "23",
    "document_number": "93",
    "date": "12/10/20",
    "document_type": "court transcript",
    "has_handwriting": false,
    "has_stamps": false
  },
  "full_text": "Case 1:20-cr-00330-AJN Document 93 Filed 12/10/20 Page 23 of 91 23\n\n1 hearing from the government first, and then any alleged victims\n2 who have indicated that they wish to be heard pursuant to 18\n3 U.S.C. 3771(a)(4), and then I will hear from Mr. Cohen.\n4 Any objection to proceeding thusly, Mr. Cohen?\n5 MR. COHEN: No, your Honor.\n6 THE COURT: Ms. Moe.\n7 MS. MOE: Thank you, your Honor.\n8 Your Honor, as we set forth in our moving papers, the\n9 government strongly believes that this defendant poses an\n10 extreme risk of flight. Pretrial Services has recommended\n11 detention, the victims seek detention, and the government\n12 respectfully submits that the defendant should be detained\n13 pending trial.\n14 Your Honor, there are serious red flags here. The\n15 defendant has significant financial means. It appears that she\n16 has been less than candid with Pretrial Services. She has not\n17 come close to thoroughly disclosing her finances to the court.\n18 She has strong international ties and appears to have the\n19 ability to live beyond the reach of extradition. She has few,\n20 if any, community ties, much less a stable residence that she\n21 can propose to the court to be bailed to. And she has a strong\n22 incentive to flee to avoid being held accountable for her\n23 crimes.\n24 Because the defendant is charged with serious offenses\n25 involving the sexual abuse of minors, your Honor, there is a\n\nSOUTHERN DISTRICT REPORTERS, P.C.\n(212) 805-0300\nDOJ-OGR-00001900",
  "text_blocks": [
    {
      "type": "printed",
      "content": "Case 1:20-cr-00330-AJN Document 93 Filed 12/10/20 Page 23 of 91 23",
      "position": "header"
    },
    {
      "type": "printed",
      "content": "1 hearing from the government first, and then any alleged victims\n2 who have indicated that they wish to be heard pursuant to 18\n3 U.S.C. 3771(a)(4), and then I will hear from Mr. Cohen.\n4 Any objection to proceeding thusly, Mr. Cohen?\n5 MR. COHEN: No, your Honor.\n6 THE COURT: Ms. Moe.\n7 MS. MOE: Thank you, your Honor.\n8 Your Honor, as we set forth in our moving papers, the\n9 government strongly believes that this defendant poses an\n10 extreme risk of flight. Pretrial Services has recommended\n11 detention, the victims seek detention, and the government\n12 respectfully submits that the defendant should be detained\n13 pending trial.\n14 Your Honor, there are serious red flags here. The\n15 defendant has significant financial means. It appears that she\n16 has been less than candid with Pretrial Services. She has not\n17 come close to thoroughly disclosing her finances to the court.\n18 She has strong international ties and appears to have the\n19 ability to live beyond the reach of extradition. She has few,\n20 if any, community ties, much less a stable residence that she\n21 can propose to the court to be bailed to. And she has a strong\n22 incentive to flee to avoid being held accountable for her\n23 crimes.\n24 Because the defendant is charged with serious offenses\n25 involving the sexual abuse of minors, your Honor, there is a",
      "position": "main content"
    },
    {
      "type": "printed",
      "content": "SOUTHERN DISTRICT REPORTERS, P.C.\n(212) 805-0300",
      "position": "footer"
    },
    {
      "type": "printed",
      "content": "DOJ-OGR-00001900",
      "position": "footer"
    }
  ],
  "entities": {
    "people": [
      "Mr. Cohen",
      "Ms. Moe"
    ],
    "organizations": [
      "Pretrial Services",
      "SOUTHERN DISTRICT REPORTERS, P.C."
    ],
    "locations": [],
    "dates": [
      "12/10/20"
    ],
    "reference_numbers": [
      "1:20-cr-00330-AJN",
      "Document 93",
      "DOJ-OGR-00001900"
    ]
  },
  "additional_notes": "The document appears to be a court transcript with a clear and legible format. There are no visible redactions or damage."
}