{
  "document_metadata": {
    "page_number": "12",
    "document_number": "17",
    "date": "07/08/20",
    "document_type": "Court Document",
    "has_handwriting": false,
    "has_stamps": false
  },
  "full_text": "Case 1:20-cr-00330-AJN Document 17 Filed 07/08/20 Page 12 of 18\n\n13. From at least in or about 1994, up to and including in or about 1997, in the Southern District of New York and elsewhere, GHISLAINE MAXWELL, the defendant, knowingly did persuade, induce, entice, and coerce an individual to travel in interstate and foreign commerce to engage in sexual activity for which a person can be charged with a criminal offense, and attempted to do the same, and aided and abetted the same, to wit, MAXWELL persuaded, induced, enticed, and coerced Minor Victim-1 to travel from Florida to New York, New York on multiple occasions with the intention that Minor Victim-1 would engage in one or more sex acts with Jeffrey Epstein, in violation of New York Penal Law, Section 130.55.\n(Title 18, United States Code, Sections 2422 and 2.)\n\nCOUNT THREE\n(Conspiracy to Transport Minors with Intent to Engage in Criminal Sexual Activity)\nThe Grand Jury further charges:\n14. The allegations contained in paragraphs 1 through 8 of this Indictment are repeated and realleged as if fully set forth within.\n\n15. From at least in or about 1994, up to and including in or about 1997, in the Southern District of New York and elsewhere, GHISLAINE MAXWELL, the defendant, Jeffrey Epstein, and others known and unknown, willfully and knowingly did combine, conspire, confederate, and agree together and with each other to commit an offense against the United States, to\n12\nDOJ-OGR-00001574",
  "text_blocks": [
    {
      "type": "printed",
      "content": "Case 1:20-cr-00330-AJN Document 17 Filed 07/08/20 Page 12 of 18",
      "position": "header"
    },
    {
      "type": "printed",
      "content": "13. From at least in or about 1994, up to and including in or about 1997, in the Southern District of New York and elsewhere, GHISLAINE MAXWELL, the defendant, knowingly did persuade, induce, entice, and coerce an individual to travel in interstate and foreign commerce to engage in sexual activity for which a person can be charged with a criminal offense, and attempted to do the same, and aided and abetted the same, to wit, MAXWELL persuaded, induced, enticed, and coerced Minor Victim-1 to travel from Florida to New York, New York on multiple occasions with the intention that Minor Victim-1 would engage in one or more sex acts with Jeffrey Epstein, in violation of New York Penal Law, Section 130.55.\n(Title 18, United States Code, Sections 2422 and 2.)",
      "position": "main"
    },
    {
      "type": "printed",
      "content": "COUNT THREE\n(Conspiracy to Transport Minors with Intent to Engage in Criminal Sexual Activity)\nThe Grand Jury further charges:",
      "position": "main"
    },
    {
      "type": "printed",
      "content": "14. The allegations contained in paragraphs 1 through 8 of this Indictment are repeated and realleged as if fully set forth within.",
      "position": "main"
    },
    {
      "type": "printed",
      "content": "15. From at least in or about 1994, up to and including in or about 1997, in the Southern District of New York and elsewhere, GHISLAINE MAXWELL, the defendant, Jeffrey Epstein, and others known and unknown, willfully and knowingly did combine, conspire, confederate, and agree together and with each other to commit an offense against the United States, to",
      "position": "main"
    },
    {
      "type": "printed",
      "content": "12",
      "position": "footer"
    },
    {
      "type": "printed",
      "content": "DOJ-OGR-00001574",
      "position": "footer"
    }
  ],
  "entities": {
    "people": [
      "GHISLAINE MAXWELL",
      "Jeffrey Epstein",
      "Minor Victim-1"
    ],
    "organizations": [
      "Grand Jury"
    ],
    "locations": [
      "New York",
      "Florida",
      "Southern District of New York",
      "United States"
    ],
    "dates": [
      "1994",
      "1997",
      "07/08/20"
    ],
    "reference_numbers": [
      "1:20-cr-00330-AJN",
      "Document 17",
      "DOJ-OGR-00001574"
    ]
  },
  "additional_notes": "The document appears to be a court filing related to the case against Ghislaine Maxwell. The text is typed, and there are no visible redactions or damage."
}