{
  "document_metadata": {
    "page_number": "10",
    "document_number": "20",
    "date": "07/16/19",
    "document_type": "court transcript",
    "has_handwriting": false,
    "has_stamps": false
  },
  "full_text": "Case 1:19-cr-00490-RMB Document 20 Filed 07/16/19 Page 10 of 24 10\nguilty to that kind of offense in Florida. Those allegations include verbal harassment, evasion of legal process, and forcing off the road the father of an individual relevant to that investigation.\nTHE COURT: Can you elaborate on that last point about forcing somebody off the road?\nMR. ROSSMILLER: Your Honor, what we have is the record evidence from an underlying civil dispute in Florida that discusses this incident and discusses it in the context of a potential plea of the defendant to obstruction or harassment charges. The government sets before this court that if the defendant was willing to undertake such measure simply as a result of an investigation, the potential for dangerous and obstructive activity in an indicted case is alarming and very real.\nDespite having been previously convicted of a sex offense involving an underage victim and being a registered sex offender, the defendant has continued to maintain a vast trove of lewd photography of young-looking women or girls at his mansion. Your Honor, pursuant to judicially authorized warrants, law enforcement agents searched his home on Saturday and found at least hundreds, and perhaps thousands, of sexually suggestive photographs of nude females, many of whom appear to be underage.\nI also want to note that the search revealed specific\nSOUTHERN DISTRICT REPORTERS, P.C.\n(212) 805-0300\nDOJ-OGR-00000415",
  "text_blocks": [
    {
      "type": "printed",
      "content": "Case 1:19-cr-00490-RMB Document 20 Filed 07/16/19 Page 10 of 24 10",
      "position": "header"
    },
    {
      "type": "printed",
      "content": "guilty to that kind of offense in Florida. Those allegations include verbal harassment, evasion of legal process, and forcing off the road the father of an individual relevant to that investigation.\nTHE COURT: Can you elaborate on that last point about forcing somebody off the road?\nMR. ROSSMILLER: Your Honor, what we have is the record evidence from an underlying civil dispute in Florida that discusses this incident and discusses it in the context of a potential plea of the defendant to obstruction or harassment charges. The government sets before this court that if the defendant was willing to undertake such measure simply as a result of an investigation, the potential for dangerous and obstructive activity in an indicted case is alarming and very real.\nDespite having been previously convicted of a sex offense involving an underage victim and being a registered sex offender, the defendant has continued to maintain a vast trove of lewd photography of young-looking women or girls at his mansion. Your Honor, pursuant to judicially authorized warrants, law enforcement agents searched his home on Saturday and found at least hundreds, and perhaps thousands, of sexually suggestive photographs of nude females, many of whom appear to be underage.\nI also want to note that the search revealed specific",
      "position": "main content"
    },
    {
      "type": "printed",
      "content": "SOUTHERN DISTRICT REPORTERS, P.C.\n(212) 805-0300",
      "position": "footer"
    },
    {
      "type": "printed",
      "content": "DOJ-OGR-00000415",
      "position": "footer"
    }
  ],
  "entities": {
    "people": [
      "MR. ROSSMILLER"
    ],
    "organizations": [
      "SOUTHERN DISTRICT REPORTERS, P.C."
    ],
    "locations": [
      "Florida"
    ],
    "dates": [
      "07/16/19",
      "Saturday"
    ],
    "reference_numbers": [
      "1:19-cr-00490-RMB",
      "Document 20",
      "DOJ-OGR-00000415"
    ]
  },
  "additional_notes": "The document appears to be a court transcript with a clear and legible format. There are no visible redactions or damage."
}