{
  "document_metadata": {
    "page_number": "16 of 19",
    "document_number": "22",
    "date": "07/13/20",
    "document_type": "court document",
    "has_handwriting": false,
    "has_stamps": false
  },
  "full_text": "Case 1:20-cr-00330-AJN Document 22 Filed 07/13/20 Page 16 of 19 defendant with asthma); United States v. Medina, 19 Cr. 351, ECF No. 68 (S.D.N.Y. Apr. 14, 2020) (Marrero, J.) (denying pre-trial bail application by defendant with diabetes and hypertension); United States v. Bradley, No. 19 Cr. 632, ECF No. 34 (S.D.N.Y. Apr. 14, 2020) (Daniels, J.) (denying pre-trial bail application by defendant with high blood pressure and obesity (see ECF Nos. 29, 33, 34)); United States v. Vizcaino, No. 20 Cr. 241, 2020 WL 1862631, at *3 (S.D.N.Y. Apr. 14, 2020) (Parker, J.) (denying pre-trial bail application and collecting cases in which bail applications have been denied even where defendants have underlying health conditions); United States v. Irizarry, 17 Cr. 283, 2020 WL 1705424 (S.D.N.Y. Apr. 8, 2020) (Preska, J.) (denying pre-trial bail application by defendant with asthma and anxiety); United States v. Daniels, 20 Cr. 69, ECF No. 26 (S.D.N.Y. Apr. 3, 2020) (Woods, J.) (denying pre-trial bail application (see ECF Nos. 19, 26)); United States v. Parker, 14 Cr. 139, ECF No. 51 (S.D.N.Y. Apr. 2, 2020) (Preska, J.) (denying pre-VOSR hearing bail application by inmate on MDC high-risk list with asthma (see ECF Nos. 48, 51)); United States v. Conley, No. 19 Cr. 131, ECF No. 366 (S.D.N.Y. Mar. 31, 2020) (Engelmayer, J.) (denying pre-trial bail application by defendant on high-risk list with asthma, partial lung removal, diabetes, high blood pressure, and hypertension (see ECF Nos. 363, 366)); United States v. Chambers, No. 20 Cr. 135, 2020 WL 1530746 (S.D.N.Y. Mar. 31, 2020) (Furman, J.) (denying pre-trial bail application by defendant with asthma); United States v. Acosta, No. 19 Cr. 848, ECF No. 14 (S.D.N.Y. Mar. 25, 2020) (Buchwald, J.) (denying bail application by defendant that relied on general reasons to release inmates because of the spread of the COVID-19 virus). As the foregoing citations make clear, the defendants in many of these cases asserted underlying health conditions that purportedly placed them at heightened risk with respect to COVID-19, but courts nevertheless denied their 15 DOJ-OGR-00001626",
  "text_blocks": [
    {
      "type": "printed",
      "content": "Case 1:20-cr-00330-AJN Document 22 Filed 07/13/20 Page 16 of 19",
      "position": "header"
    },
    {
      "type": "printed",
      "content": "defendant with asthma); United States v. Medina, 19 Cr. 351, ECF No. 68 (S.D.N.Y. Apr. 14, 2020) (Marrero, J.) (denying pre-trial bail application by defendant with diabetes and hypertension); United States v. Bradley, No. 19 Cr. 632, ECF No. 34 (S.D.N.Y. Apr. 14, 2020) (Daniels, J.) (denying pre-trial bail application by defendant with high blood pressure and obesity (see ECF Nos. 29, 33, 34)); United States v. Vizcaino, No. 20 Cr. 241, 2020 WL 1862631, at *3 (S.D.N.Y. Apr. 14, 2020) (Parker, J.) (denying pre-trial bail application and collecting cases in which bail applications have been denied even where defendants have underlying health conditions); United States v. Irizarry, 17 Cr. 283, 2020 WL 1705424 (S.D.N.Y. Apr. 8, 2020) (Preska, J.) (denying pre-trial bail application by defendant with asthma and anxiety); United States v. Daniels, 20 Cr. 69, ECF No. 26 (S.D.N.Y. Apr. 3, 2020) (Woods, J.) (denying pre-trial bail application (see ECF Nos. 19, 26)); United States v. Parker, 14 Cr. 139, ECF No. 51 (S.D.N.Y. Apr. 2, 2020) (Preska, J.) (denying pre-VOSR hearing bail application by inmate on MDC high-risk list with asthma (see ECF Nos. 48, 51)); United States v. Conley, No. 19 Cr. 131, ECF No. 366 (S.D.N.Y. Mar. 31, 2020) (Engelmayer, J.) (denying pre-trial bail application by defendant on high-risk list with asthma, partial lung removal, diabetes, high blood pressure, and hypertension (see ECF Nos. 363, 366)); United States v. Chambers, No. 20 Cr. 135, 2020 WL 1530746 (S.D.N.Y. Mar. 31, 2020) (Furman, J.) (denying pre-trial bail application by defendant with asthma); United States v. Acosta, No. 19 Cr. 848, ECF No. 14 (S.D.N.Y. Mar. 25, 2020) (Buchwald, J.) (denying bail application by defendant that relied on general reasons to release inmates because of the spread of the COVID-19 virus). As the foregoing citations make clear, the defendants in many of these cases asserted underlying health conditions that purportedly placed them at heightened risk with respect to COVID-19, but courts nevertheless denied their",
      "position": "main content"
    },
    {
      "type": "printed",
      "content": "15",
      "position": "footer"
    },
    {
      "type": "printed",
      "content": "DOJ-OGR-00001626",
      "position": "footer"
    }
  ],
  "entities": {
    "people": [
      "Marrero, J.",
      "Daniels, J.",
      "Parker, J.",
      "Preska, J.",
      "Woods, J.",
      "Engelmayer, J.",
      "Furman, J.",
      "Buchwald, J."
    ],
    "organizations": [],
    "locations": [
      "S.D.N.Y."
    ],
    "dates": [
      "Apr. 14, 2020",
      "Apr. 14, 2020",
      "Apr. 14, 2020",
      "Apr. 8, 2020",
      "Apr. 3, 2020",
      "Apr. 2, 2020",
      "Mar. 31, 2020",
      "Mar. 31, 2020",
      "Mar. 25, 2020",
      "07/13/20"
    ],
    "reference_numbers": [
      "1:20-cr-00330-AJN",
      "19 Cr. 351",
      "19 Cr. 632",
      "20 Cr. 241",
      "17 Cr. 283",
      "20 Cr. 69",
      "14 Cr. 139",
      "19 Cr. 131",
      "20 Cr. 135",
      "19 Cr. 848",
      "ECF No. 68",
      "ECF No. 34",
      "ECF Nos. 29, 33, 34",
      "ECF Nos. 19, 26",
      "ECF No. 51",
      "ECF Nos. 48, 51",
      "ECF No. 366",
      "ECF Nos. 363, 366",
      "ECF No. 14",
      "Document 22"
    ]
  },
  "additional_notes": "The document appears to be a court filing discussing various cases related to bail applications during the COVID-19 pandemic. The text is well-formatted and printed, with no visible handwriting or stamps. The footer contains a page number and a reference number."
}