{
  "document_metadata": {
    "page_number": "2",
    "document_number": "163",
    "date": "03/01/21",
    "document_type": "court document",
    "has_handwriting": true,
    "has_stamps": false
  },
  "full_text": "Case 1:20-cr-00330-AJN Document 163 Filed 03/01/21 Page 2 of 2\nThe Honorable Alison J. Nathan\nMarch 1, 2021\nPage 2\nWe now respectfully request that the deadline for filing the defendant's reply be moved to Monday, March 15, 2021. The next scheduled appearance before the Court is the first day of trial on July 12, 2021.\nSincerely,\n/s/ Christian Everdell\nChristian R. Everdell\nCOHEN & GRESSER LLP\n800 Third Avenue, 21st Floor\nNew York, New York 10022\n(212) 957-7600\ncc: All Counsel of Record (By ECF)\nThe Defendant's request is GRANTED. Her reply to the Government's Omnibus Memorandum in Opposition to the Defendant's Pre-trial Motions is now due on March 15, 2021. SO ORDERED.\n3/1/2021\nAlison J. Nathan\nUnited States District Judge\nDOJ-OGR-00002747",
  "text_blocks": [
    {
      "type": "printed",
      "content": "Case 1:20-cr-00330-AJN Document 163 Filed 03/01/21 Page 2 of 2",
      "position": "header"
    },
    {
      "type": "printed",
      "content": "The Honorable Alison J. Nathan\nMarch 1, 2021\nPage 2",
      "position": "top"
    },
    {
      "type": "printed",
      "content": "We now respectfully request that the deadline for filing the defendant's reply be moved to Monday, March 15, 2021. The next scheduled appearance before the Court is the first day of trial on July 12, 2021.",
      "position": "middle"
    },
    {
      "type": "printed",
      "content": "Sincerely,",
      "position": "middle"
    },
    {
      "type": "signature",
      "content": "/s/ Christian Everdell",
      "position": "middle"
    },
    {
      "type": "printed",
      "content": "Christian R. Everdell\nCOHEN & GRESSER LLP\n800 Third Avenue, 21st Floor\nNew York, New York 10022\n(212) 957-7600",
      "position": "middle"
    },
    {
      "type": "printed",
      "content": "cc: All Counsel of Record (By ECF)",
      "position": "middle"
    },
    {
      "type": "handwritten",
      "content": "The Defendant's request is GRANTED. Her reply to the Government's Omnibus Memorandum in Opposition to the Defendant's Pre-trial Motions is now due on March 15, 2021. SO ORDERED.",
      "position": "bottom"
    },
    {
      "type": "printed",
      "content": "3/1/2021",
      "position": "bottom"
    },
    {
      "type": "signature",
      "content": "Alison J. Nathan",
      "position": "bottom"
    },
    {
      "type": "printed",
      "content": "ALISON J. NATHAN\nUnited States District Judge",
      "position": "bottom"
    },
    {
      "type": "printed",
      "content": "DOJ-OGR-00002747",
      "position": "footer"
    }
  ],
  "entities": {
    "people": [
      "Alison J. Nathan",
      "Christian R. Everdell"
    ],
    "organizations": [
      "COHEN & GRESSER LLP"
    ],
    "locations": [
      "New York"
    ],
    "dates": [
      "March 1, 2021",
      "March 15, 2021",
      "July 12, 2021",
      "3/1/2021"
    ],
    "reference_numbers": [
      "1:20-cr-00330-AJN",
      "Document 163",
      "DOJ-OGR-00002747"
    ]
  },
  "additional_notes": "The document is a court filing with a handwritten note from the judge. The document is well-formatted and legible."
}