{
  "document_metadata": {
    "page_number": "48",
    "document_number": "36",
    "date": "07/24/19",
    "document_type": "court document",
    "has_handwriting": false,
    "has_stamps": false
  },
  "full_text": "Case 1:19-cr-00490-RMB Document 36 Filed 07/24/19 Page 48 of 74 48\nthat your Honor has clear and convincing proof occurred, much less the predictive factor that if Mr. Epstein was released under the kind of combination of conditions, there would be any risk of his influencing adversely a witness, now that there is a federal prosecution. That would be self-destructive. It would constitute a crime with a nexus to what the statutes require.\nBut the conditions also, your Honor, radically limit -- we've asked your Honor for home detention, and I will get to the monetary conditions and the risk of flight in a moment.\nWe've asked for home detention. We've asked for the visiting list to be approved by pretrial, meaning almost nobody except Mr. Weingarten and myself, Mr. Fernich, lawyers on our defense team.\nWe would rip out the cell phones. There is one line. We consent to the monitoring of that line. We consent to the waiver of search and seizure. These are the conditions that have been accepted and, again, not always, Judge. There are detention orders.\nI'm a Boston lawyer. I remember arguing before the Former Chief Judge Mark Wolf on behalf of a defendant who was arrested about two months after an induction ceremony for organized crime about 20 years ago.\nAnd Judge Wolf found that along with financial\nSOUTHERN DISTRICT REPORTERS, P.C. (212) 805-0300\nDOJ-OGR-00000558",
  "text_blocks": [
    {
      "type": "printed",
      "content": "Case 1:19-cr-00490-RMB Document 36 Filed 07/24/19 Page 48 of 74 48",
      "position": "header"
    },
    {
      "type": "printed",
      "content": "that your Honor has clear and convincing proof occurred, much less the predictive factor that if Mr. Epstein was released under the kind of combination of conditions, there would be any risk of his influencing adversely a witness, now that there is a federal prosecution. That would be self-destructive. It would constitute a crime with a nexus to what the statutes require.",
      "position": "main"
    },
    {
      "type": "printed",
      "content": "But the conditions also, your Honor, radically limit -- we've asked your Honor for home detention, and I will get to the monetary conditions and the risk of flight in a moment.",
      "position": "main"
    },
    {
      "type": "printed",
      "content": "We've asked for home detention. We've asked for the visiting list to be approved by pretrial, meaning almost nobody except Mr. Weingarten and myself, Mr. Fernich, lawyers on our defense team.",
      "position": "main"
    },
    {
      "type": "printed",
      "content": "We would rip out the cell phones. There is one line. We consent to the monitoring of that line. We consent to the waiver of search and seizure. These are the conditions that have been accepted and, again, not always, Judge. There are detention orders.",
      "position": "main"
    },
    {
      "type": "printed",
      "content": "I'm a Boston lawyer. I remember arguing before the Former Chief Judge Mark Wolf on behalf of a defendant who was arrested about two months after an induction ceremony for organized crime about 20 years ago.",
      "position": "main"
    },
    {
      "type": "printed",
      "content": "And Judge Wolf found that along with financial",
      "position": "main"
    },
    {
      "type": "printed",
      "content": "SOUTHERN DISTRICT REPORTERS, P.C. (212) 805-0300",
      "position": "footer"
    },
    {
      "type": "printed",
      "content": "DOJ-OGR-00000558",
      "position": "footer"
    }
  ],
  "entities": {
    "people": [
      "Mr. Epstein",
      "Mr. Weingarten",
      "Mr. Fernich",
      "Judge Wolf",
      "Mark Wolf"
    ],
    "organizations": [
      "SOUTHERN DISTRICT REPORTERS, P.C."
    ],
    "locations": [
      "Boston"
    ],
    "dates": [
      "07/24/19",
      "20 years ago"
    ],
    "reference_numbers": [
      "1:19-cr-00490-RMB",
      "Document 36",
      "DOJ-OGR-00000558"
    ]
  },
  "additional_notes": "The document appears to be a court transcript, with a formal tone and language. The text is mostly printed, with no visible handwriting or stamps. The footer contains a reference number and a phone number."
}