{
  "document_metadata": {
    "page_number": "1",
    "document_number": "45",
    "date": "08/20/20",
    "document_type": "Notice of Appearance",
    "has_handwriting": false,
    "has_stamps": false
  },
  "full_text": "Case 1:20-cr-00330-AJN Document 45 Filed 08/20/20 Page 1 of 1\n\nUNITED STATES DISTRICT COURT\nSOUTHERN DISTRICT OF NEW YORK\n---------------------------------------------------------------X\n\nUNITED STATES OF AMERICA\n\nNotice of Appearance\n\n- v. -\n\n20 Cr. 330 (AJN)\n\nGHISLAINE MAXWELL,\n\nDefendant.\n\n---------------------------------------------------------------X\n\nTO: Clerk of Court\nUnited States District Court\nSouthern District of New York\n\nThe undersigned attorney respectfully requests the Clerk to note her appearance in this case and to add her as a Filing User to whom Notices of Electronic Filing will be transmitted in this case.\n\nRespectfully submitted,\n\nAUDREY STRAUSS\nActing United States Attorney for the\nSouthern District of New York\n\nby: s/\nLara Pomerantz\nAssistant United States Attorney\n(212) 637-2343\n\nDOJ-OGR-00001731",
  "text_blocks": [
    {
      "type": "printed",
      "content": "Case 1:20-cr-00330-AJN Document 45 Filed 08/20/20 Page 1 of 1",
      "position": "header"
    },
    {
      "type": "printed",
      "content": "UNITED STATES DISTRICT COURT\nSOUTHERN DISTRICT OF NEW YORK\n---------------------------------------------------------------X",
      "position": "top"
    },
    {
      "type": "printed",
      "content": "UNITED STATES OF AMERICA\n\nNotice of Appearance\n\n- v. -\n\n20 Cr. 330 (AJN)\n\nGHISLAINE MAXWELL,\n\nDefendant.\n\n---------------------------------------------------------------X",
      "position": "top"
    },
    {
      "type": "printed",
      "content": "TO: Clerk of Court\nUnited States District Court\nSouthern District of New York",
      "position": "middle"
    },
    {
      "type": "printed",
      "content": "The undersigned attorney respectfully requests the Clerk to note her appearance in this case and to add her as a Filing User to whom Notices of Electronic Filing will be transmitted in this case.",
      "position": "middle"
    },
    {
      "type": "printed",
      "content": "Respectfully submitted,\n\nAUDREY STRAUSS\nActing United States Attorney for the\nSouthern District of New York",
      "position": "middle"
    },
    {
      "type": "printed",
      "content": "by: s/\nLara Pomerantz\nAssistant United States Attorney\n(212) 637-2343",
      "position": "bottom"
    },
    {
      "type": "printed",
      "content": "DOJ-OGR-00001731",
      "position": "footer"
    }
  ],
  "entities": {
    "people": [
      "GHISLAINE MAXWELL",
      "AUDREY STRAUSS",
      "Lara Pomerantz"
    ],
    "organizations": [
      "UNITED STATES DISTRICT COURT",
      "UNITED STATES OF AMERICA",
      "Southern District of New York"
    ],
    "locations": [
      "New York"
    ],
    "dates": [
      "08/20/20"
    ],
    "reference_numbers": [
      "1:20-cr-00330-AJN",
      "Document 45",
      "20 Cr. 330 (AJN)",
      "(212) 637-2343",
      "DOJ-OGR-00001731"
    ]
  },
  "additional_notes": "The document is a Notice of Appearance filed by Lara Pomerantz, Assistant United States Attorney, in the case United States of America v. Ghislaine Maxwell. The document is typed and contains no handwritten text or stamps."
}