{
  "document_metadata": {
    "page_number": "30",
    "document_number": "3",
    "date": "July 2, 2020",
    "document_type": "Commitment to Another District",
    "has_handwriting": true,
    "has_stamps": false
  },
  "full_text": "Case: 20mj060033AJ Document: 3 Filed: 07/06/20 Page: 30 of 33\nAO 94 (Rev. 06/09) Commitment to Another District (NH 06/09)\nThe United States marshal must transport the defendant, together with a copy of this order, to the charging district and deliver the defendant to the United States marshal for that district, or to another officer authorized to receive the defendant. The marshal or officer in the charging district should immediately notify the United States attorney and the clerk of court for that district of the defendant's arrival so that further proceedings may be promptly scheduled. The clerk of this district must promptly transmit the papers and any bail to the charging district.\nSO ORDERED.\nAndrea K. Johnstone\nUnited States Magistrate Judge\nJuly 2, 2020\nRETURN\nTHIS COMMITMENT WAS RECEIVED AND EXECUTED AS FOLLOWS:\nDATE COMMITMENT ORDER RECEIVED | PLACE OF COMMITMENT | DATE DEFENDANT COMMITTED\nDATE | UNITED STATES MARSHAL | (BY) DEPUTY MARSHAL",
  "text_blocks": [
    {
      "type": "printed",
      "content": "Case: 20mj060033AJ Document: 3 Filed: 07/06/20 Page: 30 of 33",
      "position": "header"
    },
    {
      "type": "printed",
      "content": "AO 94 (Rev. 06/09) Commitment to Another District (NH 06/09)",
      "position": "header"
    },
    {
      "type": "printed",
      "content": "The United States marshal must transport the defendant, together with a copy of this order, to the charging district and deliver the defendant to the United States marshal for that district, or to another officer authorized to receive the defendant. The marshal or officer in the charging district should immediately notify the United States attorney and the clerk of court for that district of the defendant's arrival so that further proceedings may be promptly scheduled. The clerk of this district must promptly transmit the papers and any bail to the charging district.",
      "position": "body"
    },
    {
      "type": "printed",
      "content": "SO ORDERED.",
      "position": "body"
    },
    {
      "type": "handwritten",
      "content": "Andrea K. Johnstone",
      "position": "body"
    },
    {
      "type": "printed",
      "content": "Andrea K. Johnstone\nUnited States Magistrate Judge",
      "position": "body"
    },
    {
      "type": "printed",
      "content": "July 2, 2020",
      "position": "body"
    },
    {
      "type": "printed",
      "content": "RETURN\nTHIS COMMITMENT WAS RECEIVED AND EXECUTED AS FOLLOWS:",
      "position": "body"
    },
    {
      "type": "printed",
      "content": "DATE COMMITMENT ORDER RECEIVED | PLACE OF COMMITMENT | DATE DEFENDANT COMMITTED",
      "position": "body"
    },
    {
      "type": "printed",
      "content": "DATE | UNITED STATES MARSHAL | (BY) DEPUTY MARSHAL",
      "position": "body"
    }
  ],
  "entities": {
    "people": [
      "Andrea K. Johnstone"
    ],
    "organizations": [
      "United States Marshal",
      "United States Attorney"
    ],
    "locations": [],
    "dates": [
      "July 2, 2020",
      "07/06/20"
    ],
    "reference_numbers": [
      "20mj060033AJ",
      "3",
      "DOJ-OGR-00001528"
    ]
  },
  "additional_notes": "The document is a Commitment to Another District form, filled out and signed by United States Magistrate Judge Andrea K. Johnstone. The form includes a return section that has not been filled out."
}