{
  "document_metadata": {
    "page_number": "119",
    "document_number": "1:20-cr-00382-AJN Document 16 Filed 07/06/20 Page 119 of 133",
    "date": "July 6, 2020",
    "document_type": "Court Document",
    "has_handwriting": false,
    "has_stamps": false
  },
  "full_text": "Case 1:20-cr-00382-AJN Document 16 Filed 07/06/20 Page 119 of 133\nQ. List all the people under the age of 18 that you interacted with at any of Jeffrey's properties?\nA. I'm not aware of anybody that I interacted with, other than obviously [the plaintiff] who was 17 at this point.\n(Title 18, United States Code, Section 1623.)\nCOUNT SIX\n(Perjury)\nThe Grand Jury further charges:\n22. The allegations contained in paragraphs 1 through 8 of this Indictment are repeated and realleged as if fully set forth within.\n23. On or about July 22, 2016, in the Southern District of New York, GHISLAINE MAXWELL, the defendant, having taken an oath to testify truthfully in a deposition in connection with a case then pending before the United States District Court for the Southern District of New York under docket number 15 Civ. 7344, knowingly made false material declarations, to wit, MAXWELL gave the following underlined false testimony:\nQ: Were you aware of the presence of sex toys or devices used in sexual activities in Mr. Epstein's Palm Beach house?\nA: No, not that I recall. . . .\nQ. Do you know whether Mr. Epstein possessed sex toys or devices used in sexual activities?\nA. No.\n16\nDOJ-OGR-00001517",
  "text_blocks": [
    {
      "type": "printed",
      "content": "Case 1:20-cr-00382-AJN Document 16 Filed 07/06/20 Page 119 of 133",
      "position": "header"
    },
    {
      "type": "printed",
      "content": "Q. List all the people under the age of 18 that you interacted with at any of Jeffrey's properties?\nA. I'm not aware of anybody that I interacted with, other than obviously [the plaintiff] who was 17 at this point.",
      "position": "top"
    },
    {
      "type": "printed",
      "content": "(Title 18, United States Code, Section 1623.)",
      "position": "top"
    },
    {
      "type": "printed",
      "content": "COUNT SIX\n(Perjury)",
      "position": "middle"
    },
    {
      "type": "printed",
      "content": "The Grand Jury further charges:\n22. The allegations contained in paragraphs 1 through 8 of this Indictment are repeated and realleged as if fully set forth within.",
      "position": "middle"
    },
    {
      "type": "printed",
      "content": "23. On or about July 22, 2016, in the Southern District of New York, GHISLAINE MAXWELL, the defendant, having taken an oath to testify truthfully in a deposition in connection with a case then pending before the United States District Court for the Southern District of New York under docket number 15 Civ. 7344, knowingly made false material declarations, to wit, MAXWELL gave the following underlined false testimony:",
      "position": "middle"
    },
    {
      "type": "printed",
      "content": "Q: Were you aware of the presence of sex toys or devices used in sexual activities in Mr. Epstein's Palm Beach house?\nA: No, not that I recall. . . .\nQ. Do you know whether Mr. Epstein possessed sex toys or devices used in sexual activities?\nA. No.",
      "position": "bottom"
    },
    {
      "type": "printed",
      "content": "16",
      "position": "footer"
    },
    {
      "type": "printed",
      "content": "DOJ-OGR-00001517",
      "position": "footer"
    }
  ],
  "entities": {
    "people": [
      "Jeffrey",
      "GHISLAINE MAXWELL",
      "Epstein"
    ],
    "organizations": [
      "United States District Court for the Southern District of New York"
    ],
    "locations": [
      "New York",
      "Palm Beach"
    ],
    "dates": [
      "July 22, 2016",
      "July 6, 2020"
    ],
    "reference_numbers": [
      "1:20-cr-00382-AJN",
      "15 Civ. 7344",
      "DOJ-OGR-00001517"
    ]
  },
  "additional_notes": "The document appears to be a court filing related to the case against Ghislaine Maxwell. It includes a transcript of a deposition and allegations of perjury."
}