{
  "document_metadata": {
    "page_number": "1",
    "document_number": "22",
    "date": "07/13/20",
    "document_type": "court document",
    "has_handwriting": false,
    "has_stamps": false
  },
  "full_text": "Case 1:20-cr-00330-AJN Document 22 Filed 07/13/20 Page 1 of 19\n\nUNITED STATES DISTRICT COURT\nSOUTHERN DISTRICT OF NEW YORK\n---------------------------------------------------------------X\n\nUNITED STATES OF AMERICA\n\n-v.-\n\nGHISLAINE MAXWELL,\n\nDefendant.\n\n---------------------------------------------------------------X\n\nTHE GOVERNMENT'S REPLY MEMORANDUM\nIN SUPPORT OF DETENTION\n\nAUDREY STRAUSS\nActing United States Attorney\nSouthern District of New York\nAttorney for the United States of America\n\nAlison Moe\nAlex Rossmiller\nMaurene Comey\nAssistant United States Attorneys\n- Of Counsel -\n\nDOJ-OGR-00001611",
  "text_blocks": [
    {
      "type": "printed",
      "content": "Case 1:20-cr-00330-AJN Document 22 Filed 07/13/20 Page 1 of 19",
      "position": "header"
    },
    {
      "type": "printed",
      "content": "UNITED STATES DISTRICT COURT\nSOUTHERN DISTRICT OF NEW YORK",
      "position": "top"
    },
    {
      "type": "printed",
      "content": "UNITED STATES OF AMERICA\n-v.-\nGHISLAINE MAXWELL,\nDefendant.",
      "position": "top"
    },
    {
      "type": "printed",
      "content": "THE GOVERNMENT'S REPLY MEMORANDUM\nIN SUPPORT OF DETENTION",
      "position": "middle"
    },
    {
      "type": "printed",
      "content": "AUDREY STRAUSS\nActing United States Attorney\nSouthern District of New York\nAttorney for the United States of America",
      "position": "middle"
    },
    {
      "type": "printed",
      "content": "Alison Moe\nAlex Rossmiller\nMaurene Comey\nAssistant United States Attorneys\n- Of Counsel -",
      "position": "bottom"
    },
    {
      "type": "printed",
      "content": "DOJ-OGR-00001611",
      "position": "footer"
    }
  ],
  "entities": {
    "people": [
      "Ghislaine Maxwell",
      "Audrey Strauss",
      "Alison Moe",
      "Alex Rossmiller",
      "Maurene Comey"
    ],
    "organizations": [
      "UNITED STATES DISTRICT COURT",
      "SOUTHERN DISTRICT OF NEW YORK",
      "UNITED STATES OF AMERICA"
    ],
    "locations": [
      "New York"
    ],
    "dates": [
      "07/13/20"
    ],
    "reference_numbers": [
      "1:20-cr-00330-AJN",
      "Document 22",
      "20 Cr. 330 (AJN)",
      "DOJ-OGR-00001611"
    ]
  },
  "additional_notes": "The document appears to be a court filing in a criminal case against Ghislaine Maxwell. The text is clear and legible, with no visible redactions or damage."
}