{
  "document_metadata": {
    "page_number": "9",
    "document_number": "144",
    "date": "02/04/21",
    "document_type": "court document",
    "has_handwriting": false,
    "has_stamps": false
  },
  "full_text": "Case 1:20-cr-00330-AJN Document 144 Filed 02/04/21 Page 9 of 25\n\nthat Minor Victim-1 would engage in one or more sex acts with Jeffrey Epstein, in violation of New York Penal Law, Section 130.55.\" Id. ¶ 19.\n\nARGUMENT\n\n\"Except as otherwise expressly provided by law,\" a non-capital criminal offense must be charged \"within five years next after such offense shall have been committed.\" 18 U.S.C. § 3282(a); see 18 U.S.C. § 3282 (1994) (same). Because Counts One through Four charge Ms. Maxwell with offenses that were completed no later than 1997, and because the indictment was not returned until July 2020, these counts are time-barred unless \"otherwise expressly provided by law.\" Id.\n\nFor two independent reasons, § 3283, on which the government relies (see Government's Memorandum in Support of Detention (\"Gov. Mem.\"), Dkt. No. 4, (filed Jul. 2, 2020), at 5), does not save Counts One through Four. First, under the version of § 3283 that was in effect at the time of the alleged offenses, the limitations period expired when the accuser reached the age of 25, which indisputably occurred many years ago here. 18 U.S.C. § 3283 (1994). While Congress amended the statute in 2003 to extend the limitations period to \"during the life of the child,\" see Prosecutorial Remedies and Tools Against the Exploitation of Children Today Act of 2003 (PROTECT Act) (the \"2003 Amendment\"), PL 108-21, April 30, 2003, § 202, 117 Stat. 650, 660, that amendment cannot apply to conduct that occurred during the 1990s. Second, by its plain terms, § 3283 applies only to offenses \"involving the sexual or physical abuse, or kidnapping, of a child.\" 18 U.S.C. § 3283. But the sexual or physical abuse or kidnapping of a child is not an element of any of the offenses charged here. Accordingly, § 3283—regardless of which version is considered—simply does not apply.\n\nI. The 2003 Amendment Does Not Apply Retroactively.\n\nAt the time of the alleged offenses, § 3283 provided as follows:\n\n3\n\nDOJ-OGR-00002657",
  "text_blocks": [
    {
      "type": "printed",
      "content": "Case 1:20-cr-00330-AJN Document 144 Filed 02/04/21 Page 9 of 25",
      "position": "header"
    },
    {
      "type": "printed",
      "content": "that Minor Victim-1 would engage in one or more sex acts with Jeffrey Epstein, in violation of New York Penal Law, Section 130.55.\" Id. ¶ 19.\n\nARGUMENT\n\n\"Except as otherwise expressly provided by law,\" a non-capital criminal offense must be charged \"within five years next after such offense shall have been committed.\" 18 U.S.C. § 3282(a); see 18 U.S.C. § 3282 (1994) (same). Because Counts One through Four charge Ms. Maxwell with offenses that were completed no later than 1997, and because the indictment was not returned until July 2020, these counts are time-barred unless \"otherwise expressly provided by law.\" Id.\n\nFor two independent reasons, § 3283, on which the government relies (see Government's Memorandum in Support of Detention (\"Gov. Mem.\"), Dkt. No. 4, (filed Jul. 2, 2020), at 5), does not save Counts One through Four. First, under the version of § 3283 that was in effect at the time of the alleged offenses, the limitations period expired when the accuser reached the age of 25, which indisputably occurred many years ago here. 18 U.S.C. § 3283 (1994). While Congress amended the statute in 2003 to extend the limitations period to \"during the life of the child,\" see Prosecutorial Remedies and Tools Against the Exploitation of Children Today Act of 2003 (PROTECT Act) (the \"2003 Amendment\"), PL 108-21, April 30, 2003, § 202, 117 Stat. 650, 660, that amendment cannot apply to conduct that occurred during the 1990s. Second, by its plain terms, § 3283 applies only to offenses \"involving the sexual or physical abuse, or kidnapping, of a child.\" 18 U.S.C. § 3283. But the sexual or physical abuse or kidnapping of a child is not an element of any of the offenses charged here. Accordingly, § 3283—regardless of which version is considered—simply does not apply.\n\nI. The 2003 Amendment Does Not Apply Retroactively.\n\nAt the time of the alleged offenses, § 3283 provided as follows:",
      "position": "main content"
    },
    {
      "type": "printed",
      "content": "3",
      "position": "footer"
    },
    {
      "type": "printed",
      "content": "DOJ-OGR-00002657",
      "position": "footer"
    }
  ],
  "entities": {
    "people": [
      "Jeffrey Epstein",
      "Ms. Maxwell",
      "Minor Victim-1"
    ],
    "organizations": [],
    "locations": [
      "New York"
    ],
    "dates": [
      "02/04/21",
      "July 2020",
      "1997",
      "April 30, 2003",
      "Jul. 2, 2020"
    ],
    "reference_numbers": [
      "1:20-cr-00330-AJN",
      "Document 144",
      "Dkt. No. 4",
      "PL 108-21",
      "§ 202",
      "117 Stat. 650, 660",
      "18 U.S.C. § 3282(a)",
      "18 U.S.C. § 3283"
    ]
  },
  "additional_notes": "The document appears to be a court filing related to the case against Ms. Maxwell, discussing the statute of limitations for certain offenses."
}