{
  "document_metadata": {
    "page_number": "1",
    "document_number": "66",
    "date": "April 27, 2021",
    "document_type": "NOTICE OF CASE MANAGER CHANGE",
    "has_handwriting": false,
    "has_stamps": false
  },
  "full_text": "Case 21-770, Document 66, 04/27/2021, 3087699, Page1 of 1\nUnited States Court of Appeals for the Second Circuit\nThurgood Marshall U.S. Courthouse\n40 Foley Square\nNew York, NY 10007\nDEBRA ANN LIVINGSTON\nCHIEF JUDGE\nCATHERINE O'HAGAN WOLFE\nCLERK OF COURT\nDate: April 27, 2021\nDC Docket #: 1:20-cr-330-1\nDocket #: 21-58cr\nDC Court: SDNY (NEW YORK CITY)\nShort Title: United States of America v. Maxwell\nDC Docket #: 1:20-cr-330-1\nDC Court: SDNY (NEW YORK CITY)\nDC Judge: Nathan\nNOTICE OF CASE MANAGER CHANGE\nThe case manager assigned to this matter has been changed.\nInquiries regarding this case may be directed to 212-857-8513.\nDOJ-OGR-00001404",
  "text_blocks": [
    {
      "type": "printed",
      "content": "Case 21-770, Document 66, 04/27/2021, 3087699, Page1 of 1",
      "position": "header"
    },
    {
      "type": "printed",
      "content": "United States Court of Appeals for the Second Circuit\nThurgood Marshall U.S. Courthouse\n40 Foley Square\nNew York, NY 10007",
      "position": "header"
    },
    {
      "type": "printed",
      "content": "DEBRA ANN LIVINGSTON\nCHIEF JUDGE\nDate: April 27, 2021\nDocket #: 21-58cr\nShort Title: United States of America v. Maxwell",
      "position": "left"
    },
    {
      "type": "printed",
      "content": "CATHERINE O'HAGAN WOLFE\nCLERK OF COURT\nDC Docket #: 1:20-cr-330-1\nDC Court: SDNY (NEW YORK CITY)\nDC Docket #: 1:20-cr-330-1\nDC Court: SDNY (NEW YORK CITY)\nDC Judge: Nathan",
      "position": "right"
    },
    {
      "type": "printed",
      "content": "NOTICE OF CASE MANAGER CHANGE",
      "position": "middle"
    },
    {
      "type": "printed",
      "content": "The case manager assigned to this matter has been changed.\nInquiries regarding this case may be directed to 212-857-8513.",
      "position": "middle"
    },
    {
      "type": "printed",
      "content": "DOJ-OGR-00001404",
      "position": "footer"
    }
  ],
  "entities": {
    "people": [
      "DEBRA ANN LIVINGSTON",
      "CATHERINE O'HAGAN WOLFE",
      "Nathan",
      "Maxwell"
    ],
    "organizations": [
      "United States Court of Appeals for the Second Circuit",
      "United States of America"
    ],
    "locations": [
      "New York",
      "Thurgood Marshall U.S. Courthouse",
      "40 Foley Square"
    ],
    "dates": [
      "April 27, 2021",
      "04/27/2021"
    ],
    "reference_numbers": [
      "21-770",
      "66",
      "3087699",
      "21-58cr",
      "1:20-cr-330-1",
      "212-857-8513",
      "DOJ-OGR-00001404"
    ]
  },
  "additional_notes": "The document appears to be a formal court notice with clear and legible text. There are no visible redactions or damage."
}