{
  "document_metadata": {
    "page_number": "154",
    "document_number": "20-2",
    "date": "04/01/2021",
    "document_type": "court transcript",
    "has_handwriting": false,
    "has_stamps": false
  },
  "full_text": "Case 21-770, Document 20-2, 04/01/2021, 3068530, Page154 of 200\nk7e2MaxC kjc\n1    client. If the defense finds this process inadequate in any\n2    way, it may make a specific application to this court for\n3    further relief.\n4        In sum and for all of the foregoing reasons, the court\n5    finds that the government has met its burden of showing by a\n6    preponderance of the evidence that the defendant is a risk of\n7    flight and that no combination of conditions could reasonably\n8    assure the presence of the defendant at court.\n9        The defendant is hereby ordered to be detained pending\n10   trial.\n11       Counsel, is there anything else that I can address at\n12   this time?\n13       Mr. Cohen?\n14       MR. COHEN: Not from the defense, your Honor.\n15       THE COURT: Thank you.\n16       Ms. Moe?\n17       MS. MOE: Not from the government, your Honor.  Thank\n18   you.\n19       THE COURT: All right. My thanks to counsel for your\n20   advocacy and my thanks to the staff of the court who worked\n21   hard to provide the access to these proceedings in the\n22   pandemic.\n23       We are hereby adjourned.\n24       oOo\n25\nSOUTHERN DISTRICT REPORTERS, P.C.\n(212) 805-0300\nDOJ-OGR-00001095",
  "text_blocks": [
    {
      "type": "printed",
      "content": "Case 21-770, Document 20-2, 04/01/2021, 3068530, Page154 of 200",
      "position": "header"
    },
    {
      "type": "printed",
      "content": "k7e2MaxC kjc",
      "position": "header"
    },
    {
      "type": "printed",
      "content": "1    client. If the defense finds this process inadequate in any\n2    way, it may make a specific application to this court for\n3    further relief.\n4        In sum and for all of the foregoing reasons, the court\n5    finds that the government has met its burden of showing by a\n6    preponderance of the evidence that the defendant is a risk of\n7    flight and that no combination of conditions could reasonably\n8    assure the presence of the defendant at court.\n9        The defendant is hereby ordered to be detained pending\n10   trial.\n11       Counsel, is there anything else that I can address at\n12   this time?\n13       Mr. Cohen?\n14       MR. COHEN: Not from the defense, your Honor.\n15       THE COURT: Thank you.\n16       Ms. Moe?\n17       MS. MOE: Not from the government, your Honor.  Thank\n18   you.\n19       THE COURT: All right. My thanks to counsel for your\n20   advocacy and my thanks to the staff of the court who worked\n21   hard to provide the access to these proceedings in the\n22   pandemic.\n23       We are hereby adjourned.",
      "position": "main"
    },
    {
      "type": "printed",
      "content": "24       oOo\n25",
      "position": "main"
    },
    {
      "type": "printed",
      "content": "SOUTHERN DISTRICT REPORTERS, P.C.\n(212) 805-0300",
      "position": "footer"
    },
    {
      "type": "printed",
      "content": "DOJ-OGR-00001095",
      "position": "footer"
    }
  ],
  "entities": {
    "people": [
      "Mr. Cohen",
      "Ms. Moe"
    ],
    "organizations": [
      "SOUTHERN DISTRICT REPORTERS, P.C."
    ],
    "locations": [],
    "dates": [
      "04/01/2021"
    ],
    "reference_numbers": [
      "Case 21-770",
      "Document 20-2",
      "3068530",
      "DOJ-OGR-00001095"
    ]
  },
  "additional_notes": "The document appears to be a court transcript with a clear and legible format. There are no visible redactions or damage."
}