{
  "document_metadata": {
    "page_number": "1 of 12",
    "document_number": "169",
    "date": "03/22/21",
    "document_type": "Court Order",
    "has_handwriting": false,
    "has_stamps": true
  },
  "full_text": "Case 1:20-cr-00330-AJN Document 169 Filed 03/22/21 Page 1 of 12 UNITED STATES DISTRICT COURT SOUTHERN DISTRICT OF NEW YORK United States of America, -v- Ghislaine Maxwell, Defendant. 20-CR-330 (AJN) ORDER ALISON J. NATHAN, District Judge: Defendant Ghislaine Maxwell has been indicted by a grand jury on charges of conspiracy to entice minors to travel to engage in illegal sex acts, in violation of 18 U.S.C. § 371; enticing a minor to travel to engage in illegal sex acts, in violation of 18 U.S.C. §§ 2422 and 2; conspiracy to transport minors to participate in illegal sex acts, in violation of 18 U.S.C. § 371; transporting minors to participate in illegal sex acts, in violation of 18 U.S.C. §§ 2423 and 2; and two charges of perjury, in violation of 18 U.S.C. § 1623. On July 14, 2020, the Court held a lengthy bail hearing and concluded that the Defendant was a clear risk of flight and that no conditions or combination of conditions would ensure her appearance. It therefore denied bail. On December 8, 2020, the Defendant filed a renewed motion for release on bail pending trial, which was entered into the public docket on December 14, 2020. Dkt. No. 96. On December 28, 2020, the Court denied that motion, concluding that the Defendant posed a risk of flight and that no combination of conditions could ensure her appearance. Dkt. Nos. 104, 106. The Defendant then filed a third motion for release on bail on February 23, 2021. Dkt. No. 160. In this motion, the Defendant attempts to respond to the reasons that the Court 1 DOJ-OGR-00002767",
  "text_blocks": [
    {
      "type": "printed",
      "content": "Case 1:20-cr-00330-AJN Document 169 Filed 03/22/21 Page 1 of 12",
      "position": "header"
    },
    {
      "type": "printed",
      "content": "UNITED STATES DISTRICT COURT SOUTHERN DISTRICT OF NEW YORK",
      "position": "header"
    },
    {
      "type": "printed",
      "content": "United States of America, -v- Ghislaine Maxwell, Defendant.",
      "position": "middle"
    },
    {
      "type": "printed",
      "content": "20-CR-330 (AJN) ORDER",
      "position": "middle"
    },
    {
      "type": "printed",
      "content": "ALISON J. NATHAN, District Judge: Defendant Ghislaine Maxwell has been indicted by a grand jury on charges of conspiracy to entice minors to travel to engage in illegal sex acts, in violation of 18 U.S.C. § 371; enticing a minor to travel to engage in illegal sex acts, in violation of 18 U.S.C. §§ 2422 and 2; conspiracy to transport minors to participate in illegal sex acts, in violation of 18 U.S.C. § 371; transporting minors to participate in illegal sex acts, in violation of 18 U.S.C. §§ 2423 and 2; and two charges of perjury, in violation of 18 U.S.C. § 1623.",
      "position": "middle"
    },
    {
      "type": "printed",
      "content": "On July 14, 2020, the Court held a lengthy bail hearing and concluded that the Defendant was a clear risk of flight and that no conditions or combination of conditions would ensure her appearance. It therefore denied bail. On December 8, 2020, the Defendant filed a renewed motion for release on bail pending trial, which was entered into the public docket on December 14, 2020. Dkt. No. 96. On December 28, 2020, the Court denied that motion, concluding that the Defendant posed a risk of flight and that no combination of conditions could ensure her appearance. Dkt. Nos. 104, 106.",
      "position": "middle"
    },
    {
      "type": "printed",
      "content": "The Defendant then filed a third motion for release on bail on February 23, 2021. Dkt. No. 160. In this motion, the Defendant attempts to respond to the reasons that the Court",
      "position": "middle"
    },
    {
      "type": "stamp",
      "content": "USDC SDNY DOCUMENT ELECTRONICALLY FILED DOC #: DATE FILED: 3/22/21",
      "position": "margin"
    },
    {
      "type": "printed",
      "content": "1 DOJ-OGR-00002767",
      "position": "footer"
    }
  ],
  "entities": {
    "people": [
      "Ghislaine Maxwell",
      "Alison J. Nathan"
    ],
    "organizations": [
      "United States District Court",
      "United States of America"
    ],
    "locations": [
      "New York"
    ],
    "dates": [
      "July 14, 2020",
      "December 8, 2020",
      "December 14, 2020",
      "December 28, 2020",
      "February 23, 2021",
      "03/22/21"
    ],
    "reference_numbers": [
      "1:20-cr-00330-AJN",
      "Document 169",
      "20-CR-330 (AJN)",
      "Dkt. No. 96",
      "Dkt. Nos. 104, 106",
      "Dkt. No. 160"
    ]
  },
  "additional_notes": "The document appears to be a court order from the United States District Court for the Southern District of New York. It is a printed document with a stamp indicating electronic filing. The document is related to the case of Ghislaine Maxwell and discusses her bail hearings and motions."
}