{
  "document_metadata": {
    "page_number": "1",
    "document_number": "187",
    "date": "03/29/21",
    "document_type": "Superseding Indictment",
    "has_handwriting": false,
    "has_stamps": false
  },
  "full_text": "Case 1:20-cr-00330-PAE Document 187 Filed 03/29/21 Page 1 of 24\n\nORIGINAL\n\nUNITED STATES DISTRICT COURT\nSOUTHERN DISTRICT OF NEW YORK\n\nUNITED STATES OF AMERICA\n- v. -\nGHISLAINE MAXWELL,\nDefendant.\n\nSUPERSEDING INDICTMENT\nS2 20 Cr. 330 (AJN)\n\nCOUNT ONE\n(Conspiracy to Entice Minors to Travel to Engage in Illegal Sex Acts)\n\nThe Grand Jury charges:\n\nOVERVIEW\n1. The charges set forth herein stem from the role of GHISLAINE MAXWELL, the defendant, in the sexual exploitation and abuse of multiple minor girls by Jeffrey Epstein. In particular, from at least in or about 1994, up to and including at least in or about 2004, MAXWELL assisted, facilitated, and contributed to Jeffrey Epstein's abuse of minor girls by, among other things, helping Epstein to recruit, groom, and ultimately abuse victims known to MAXWELL and Epstein to be under the age of 18. The victims were as young as 14 years old when they were groomed and abused by MAXWELL and Epstein, both of whom knew that certain victims were in fact under the age of 18.\n2. As a part and in furtherance of their scheme to abuse minor victims, GHISLAINE MAXWELL, the defendant, and Jeffrey Epstein enticed and caused minor victims to travel to",
  "text_blocks": [
    {
      "type": "printed",
      "content": "Case 1:20-cr-00330-PAE Document 187 Filed 03/29/21 Page 1 of 24",
      "position": "header"
    },
    {
      "type": "printed",
      "content": "ORIGINAL",
      "position": "header"
    },
    {
      "type": "printed",
      "content": "UNITED STATES DISTRICT COURT\nSOUTHERN DISTRICT OF NEW YORK\n\nUNITED STATES OF AMERICA\n- v. -\nGHISLAINE MAXWELL,\nDefendant.",
      "position": "top"
    },
    {
      "type": "printed",
      "content": "SUPERSEDING INDICTMENT\nS2 20 Cr. 330 (AJN)",
      "position": "top"
    },
    {
      "type": "printed",
      "content": "COUNT ONE\n(Conspiracy to Entice Minors to Travel to Engage in Illegal Sex Acts)\n\nThe Grand Jury charges:",
      "position": "middle"
    },
    {
      "type": "printed",
      "content": "OVERVIEW\n1. The charges set forth herein stem from the role of GHISLAINE MAXWELL, the defendant, in the sexual exploitation and abuse of multiple minor girls by Jeffrey Epstein. In particular, from at least in or about 1994, up to and including at least in or about 2004, MAXWELL assisted, facilitated, and contributed to Jeffrey Epstein's abuse of minor girls by, among other things, helping Epstein to recruit, groom, and ultimately abuse victims known to MAXWELL and Epstein to be under the age of 18. The victims were as young as 14 years old when they were groomed and abused by MAXWELL and Epstein, both of whom knew that certain victims were in fact under the age of 18.\n2. As a part and in furtherance of their scheme to abuse minor victims, GHISLAINE MAXWELL, the defendant, and Jeffrey Epstein enticed and caused minor victims to travel to",
      "position": "middle"
    },
    {
      "type": "printed",
      "content": "DOJ-OGR-00002843",
      "position": "footer"
    }
  ],
  "entities": {
    "people": [
      "GHISLAINE MAXWELL",
      "Jeffrey Epstein",
      "Jeffrey Epstein's"
    ],
    "organizations": [
      "UNITED STATES DISTRICT COURT",
      "SOUTHERN DISTRICT OF NEW YORK"
    ],
    "locations": [
      "NEW YORK"
    ],
    "dates": [
      "03/29/21",
      "1994",
      "2004"
    ],
    "reference_numbers": [
      "1:20-cr-00330-PAE",
      "Document 187",
      "S2 20 Cr. 330 (AJN)"
    ]
  },
  "additional_notes": "The document appears to be a court filing, specifically a superseding indictment, in a criminal case against Ghislaine Maxwell. The text is typed, and there are no visible handwritten notes or stamps. The document is labeled as 'ORIGINAL' at the top."
}