{
  "document_metadata": {
    "page_number": "14",
    "document_number": "17",
    "date": "07/08/20",
    "document_type": "Court Document",
    "has_handwriting": false,
    "has_stamps": false
  },
  "full_text": "Case 1:20-cr-00330-AJN Document 17 Filed 07/08/20 Page 14 of 18\nNew York Residence, in violation of New York Penal Law, Section 130.55.\nC. In or about 1996, when Minor Victim-2 was under the age of 18, MAXWELL provided Minor Victim-2 with an unsolicited massage in New Mexico, during which Minor Victim-2 was topless.\nd. Between in or about 1994 and in or about 1995, when Minor Victim-3 was under the age of 18, MAXWELL encouraged Minor Victim-3 to provide massages to Epstein in London, England, knowing that Epstein intended to sexually abuse Minor Victim-3 during those massages.\n(Title 18, United States Code, Section 371.)\nCOUNT FOUR\n(Transportation of a Minor with Intent to Engage in Criminal Sexual Activity)\nThe Grand Jury further charges:\n18. The allegations contained in paragraphs 1 through 8 of this Indictment are repeated and realleged as if fully set forth within.\n19. From at least in or about 1994, up to and including in or about 1997, in the Southern District of New York and elsewhere, GHISLAINE MAXWELL, the defendant, knowingly did transport an individual who had not attained the age of 18 in interstate and foreign commerce, with the intent that the individual engage in sexual activity for which a person can be charged with a criminal offense, and attempted to do so, and\n14\nDOJ-OGR-00001576",
  "text_blocks": [
    {
      "type": "printed",
      "content": "Case 1:20-cr-00330-AJN Document 17 Filed 07/08/20 Page 14 of 18",
      "position": "header"
    },
    {
      "type": "printed",
      "content": "New York Residence, in violation of New York Penal Law, Section 130.55.\nC. In or about 1996, when Minor Victim-2 was under the age of 18, MAXWELL provided Minor Victim-2 with an unsolicited massage in New Mexico, during which Minor Victim-2 was topless.\nd. Between in or about 1994 and in or about 1995, when Minor Victim-3 was under the age of 18, MAXWELL encouraged Minor Victim-3 to provide massages to Epstein in London, England, knowing that Epstein intended to sexually abuse Minor Victim-3 during those massages.\n(Title 18, United States Code, Section 371.)",
      "position": "top"
    },
    {
      "type": "printed",
      "content": "COUNT FOUR\n(Transportation of a Minor with Intent to Engage in Criminal Sexual Activity)",
      "position": "middle"
    },
    {
      "type": "printed",
      "content": "The Grand Jury further charges:\n18. The allegations contained in paragraphs 1 through 8 of this Indictment are repeated and realleged as if fully set forth within.\n19. From at least in or about 1994, up to and including in or about 1997, in the Southern District of New York and elsewhere, GHISLAINE MAXWELL, the defendant, knowingly did transport an individual who had not attained the age of 18 in interstate and foreign commerce, with the intent that the individual engage in sexual activity for which a person can be charged with a criminal offense, and attempted to do so, and",
      "position": "bottom"
    },
    {
      "type": "printed",
      "content": "14",
      "position": "footer"
    },
    {
      "type": "printed",
      "content": "DOJ-OGR-00001576",
      "position": "footer"
    }
  ],
  "entities": {
    "people": [
      "MAXWELL",
      "GHISLAINE MAXWELL",
      "Epstein",
      "Minor Victim-2",
      "Minor Victim-3"
    ],
    "organizations": [
      "Grand Jury"
    ],
    "locations": [
      "New York",
      "New Mexico",
      "London",
      "England",
      "Southern District of New York"
    ],
    "dates": [
      "1994",
      "1995",
      "1996",
      "1997",
      "07/08/20"
    ],
    "reference_numbers": [
      "1:20-cr-00330-AJN",
      "Document 17",
      "Page 14 of 18",
      "DOJ-OGR-00001576"
    ]
  },
  "additional_notes": "The document appears to be a court filing related to the case against Ghislaine Maxwell. The text is typed, and there are no visible handwritten notes or stamps. The document is page 14 of 18."
}