{
  "document_metadata": {
    "page_number": "3",
    "document_number": "2",
    "date": "07/02/19",
    "document_type": "Indictment",
    "has_handwriting": false,
    "has_stamps": false
  },
  "full_text": "Case 1:19-cr-00490-RMB Document 2 Filed 07/02/19 Page 3 of 14\n\nrecruited, dozens of minor girls to engage in sex acts with him, after which EPSTEIN paid the victims hundreds of dollars in cash, at the New York Residence and the Palm Beach Residence.\n\n7. In both New York and Florida, JEFFREY EPSTEIN, the defendant, perpetuated this abuse in similar ways. Victims were initially recruited to provide \"massages\" to EPSTEIN, which would be performed nude or partially nude, would become increasingly sexual in nature, and would typically include one or more sex acts. EPSTEIN paid his victims hundreds of dollars in cash for each encounter. Moreover, EPSTEIN actively encouraged certain of his victims to recruit additional girls to be similarly sexually abused. EPSTEIN incentivized his victims to become recruiters by paying these victim-recruiters hundreds of dollars for each girl that they brought to EPSTEIN. In so doing, EPSTEIN maintained a steady supply of new victims to exploit.\n\nThe New York Residence\n\n8. At all times relevant to this Indictment, JEFFREY EPSTEIN, the defendant, possessed and controlled a multi-story private residence on the Upper East Side of Manhattan, New York, i.e., the New York Residence. Between at least in or about 2002 and in or about 2005, EPSTEIN abused numerous minor victims at the New York Residence by causing these victims to be recruited to engage in paid sex acts with him.\n\n3\nDOJ-OGR-00000260",
  "text_blocks": [
    {
      "type": "printed",
      "content": "Case 1:19-cr-00490-RMB Document 2 Filed 07/02/19 Page 3 of 14",
      "position": "header"
    },
    {
      "type": "printed",
      "content": "recruited, dozens of minor girls to engage in sex acts with him, after which EPSTEIN paid the victims hundreds of dollars in cash, at the New York Residence and the Palm Beach Residence.",
      "position": "top"
    },
    {
      "type": "printed",
      "content": "7. In both New York and Florida, JEFFREY EPSTEIN, the defendant, perpetuated this abuse in similar ways. Victims were initially recruited to provide \"massages\" to EPSTEIN, which would be performed nude or partially nude, would become increasingly sexual in nature, and would typically include one or more sex acts. EPSTEIN paid his victims hundreds of dollars in cash for each encounter. Moreover, EPSTEIN actively encouraged certain of his victims to recruit additional girls to be similarly sexually abused. EPSTEIN incentivized his victims to become recruiters by paying these victim-recruiters hundreds of dollars for each girl that they brought to EPSTEIN. In so doing, EPSTEIN maintained a steady supply of new victims to exploit.",
      "position": "middle"
    },
    {
      "type": "printed",
      "content": "The New York Residence",
      "position": "middle"
    },
    {
      "type": "printed",
      "content": "8. At all times relevant to this Indictment, JEFFREY EPSTEIN, the defendant, possessed and controlled a multi-story private residence on the Upper East Side of Manhattan, New York, i.e., the New York Residence. Between at least in or about 2002 and in or about 2005, EPSTEIN abused numerous minor victims at the New York Residence by causing these victims to be recruited to engage in paid sex acts with him.",
      "position": "bottom"
    },
    {
      "type": "printed",
      "content": "3",
      "position": "footer"
    },
    {
      "type": "printed",
      "content": "DOJ-OGR-00000260",
      "position": "footer"
    }
  ],
  "entities": {
    "people": [
      "JEFFREY EPSTEIN",
      "EPSTEIN"
    ],
    "organizations": [
      "DOJ"
    ],
    "locations": [
      "New York",
      "Florida",
      "Manhattan",
      "Upper East Side",
      "Palm Beach"
    ],
    "dates": [
      "07/02/19",
      "2002",
      "2005"
    ],
    "reference_numbers": [
      "1:19-cr-00490-RMB",
      "Document 2",
      "DOJ-OGR-00000260"
    ]
  },
  "additional_notes": "The document appears to be a court filing related to the indictment of Jeffrey Epstein. The text is typed, and there are no visible redactions or damage."
}