{
  "document_metadata": {
    "page_number": "15",
    "document_number": "20-cr-00330",
    "date": "07/07/20",
    "document_type": "Court Document",
    "has_handwriting": false,
    "has_stamps": false
  },
  "full_text": "take to protect herself, her family members, her friends and colleagues, and their children, from unrelenting and intrusive media coverage, threats, and irreparable reputational harm.\n\nEver since Epstein’s arrest, Ms. Maxwell has been at the center of a crushing onslaught of press articles, television specials, and social media posts painting her in the most damning light possible and prejudging her guilt. The sheer volume of media reporting mentioning Ms. Maxwell is staggering. Since Epstein’s arrest, she has been mentioned in literally thousands of media publications, news reports, and other online content. The media attention also spawned a carnival-like atmosphere of speculation about her whereabouts. In November 2019, the British tabloid, The Sun, even offered a £10,000 bounty for information about Ms. Maxwell’s location. A headline reminiscent of a Wild West wanted poster read: “WANTED: The Sun is offering a £10,000 reward for information on Jeffrey Epstein pal Ghislaine Maxwell.”10 And in the days leading up to her arrest, there was a deluge of media reports (all untrue) claiming that Ms. Maxwell was hiding out in an apartment in Paris to avoid questioning by the FBI.11 She has seen helicopters flying over her home and reporters hiding in the bushes. Indeed, since Ms. Maxwell’s arrest on July 2, 2020, her counsel has been flooded with hundreds of media inquiries and solicitations from members of the public.\n\nThe “open season” declared on Ms. Maxwell after Epstein’s death has come with an even darker cost – she has been the target of alarming physical threats, even death threats, and has had to hire security guards to ensure her safety. The media feeding frenzy, which has only intensified in recent months, has also deeply affected her family and friends. Some of Ms. Maxwell’s closest friends who had nothing whatsoever to do with Epstein have lost their jobs or\n\n10 See https://www.the-sun.com/news/74018/the-sun-is-offering-a-10000-reward-for-information-on-jeffrey-epstein-pal-ghislaine-maxwell/.\n\n11 See, e.g., https://www.dailymail.co.uk/news/ article-8444137/Jeffrey-Epsteins-fugitive-madam-Ghislaine-Maxwell-hiding-luxury-Paris.html.\n\n15\nDOJ-OGR-00000976",
  "text_blocks": [
    {
      "type": "printed",
      "content": "take to protect herself, her family members, her friends and colleagues, and their children, from unrelenting and intrusive media coverage, threats, and irreparable reputational harm.",
      "position": "top"
    },
    {
      "type": "printed",
      "content": "Ever since Epstein’s arrest, Ms. Maxwell has been at the center of a crushing onslaught of press articles, television specials, and social media posts painting her in the most damning light possible and prejudging her guilt. The sheer volume of media reporting mentioning Ms. Maxwell is staggering. Since Epstein’s arrest, she has been mentioned in literally thousands of media publications, news reports, and other online content. The media attention also spawned a carnival-like atmosphere of speculation about her whereabouts. In November 2019, the British tabloid, The Sun, even offered a £10,000 bounty for information about Ms. Maxwell’s location. A headline reminiscent of a Wild West wanted poster read: “WANTED: The Sun is offering a £10,000 reward for information on Jeffrey Epstein pal Ghislaine Maxwell.”10 And in the days leading up to her arrest, there was a deluge of media reports (all untrue) claiming that Ms. Maxwell was hiding out in an apartment in Paris to avoid questioning by the FBI.11 She has seen helicopters flying over her home and reporters hiding in the bushes. Indeed, since Ms. Maxwell’s arrest on July 2, 2020, her counsel has been flooded with hundreds of media inquiries and solicitations from members of the public.",
      "position": "middle"
    },
    {
      "type": "printed",
      "content": "The “open season” declared on Ms. Maxwell after Epstein’s death has come with an even darker cost – she has been the target of alarming physical threats, even death threats, and has had to hire security guards to ensure her safety. The media feeding frenzy, which has only intensified in recent months, has also deeply affected her family and friends. Some of Ms. Maxwell’s closest friends who had nothing whatsoever to do with Epstein have lost their jobs or",
      "position": "middle"
    },
    {
      "type": "printed",
      "content": "10 See https://www.the-sun.com/news/74018/the-sun-is-offering-a-10000-reward-for-information-on-jeffrey-epstein-pal-ghislaine-maxwell/.",
      "position": "footer"
    },
    {
      "type": "printed",
      "content": "11 See, e.g., https://www.dailymail.co.uk/news/ article-8444137/Jeffrey-Epsteins-fugitive-madam-Ghislaine-Maxwell-hiding-luxury-Paris.html.",
      "position": "footer"
    },
    {
      "type": "printed",
      "content": "15",
      "position": "footer"
    },
    {
      "type": "printed",
      "content": "DOJ-OGR-00000976",
      "position": "footer"
    }
  ],
  "entities": {
    "people": [
      "Epstein",
      "Ms. Maxwell",
      "Ghislaine Maxwell",
      "Jeffrey Epstein"
    ],
    "organizations": [
      "The Sun",
      "FBI"
    ],
    "locations": [
      "Paris"
    ],
    "dates": [
      "November 2019",
      "July 2, 2020"
    ],
    "reference_numbers": [
      "20-cr-00330",
      "DOJ-OGR-00000976"
    ]
  },
  "additional_notes": "The document appears to be a court filing discussing the media coverage and public reaction to Ghislaine Maxwell's arrest and its impact on her and her associates."
}