{
  "document_metadata": {
    "page_number": "4",
    "document_number": "17",
    "date": "07/08/20",
    "document_type": "court document",
    "has_handwriting": false,
    "has_stamps": false
  },
  "full_text": "Case 1:20-cr-00330-AJN Document 17 Filed 07/08/20 Page 4 of 18\n\nmassage Epstein in front of a minor victim. In other instances, MAXWELL encouraged minor victims to provide massages to Epstein, including sexualized massages during which a minor victim would be fully or partially nude. Many of those massages resulted in Epstein sexually abusing the minor victims.\nd. In addition, Epstein offered to help some minor victims by paying for travel and/or educational opportunities, and MAXWELL encouraged certain victims to accept Epstein's assistance. As a result, victims were made to feel indebted and believed that MAXWELL and Epstein were trying to help them.\ne. Through this process, MAXWELL and Epstein enticed victims to engage in sexual activity with Epstein. In some instances, MAXWELL was present for and participated in the sexual abuse of minor victims. Some such incidents occurred in the context of massages, which developed into sexual encounters.\n5. GHISLAINE MAXWELL, the defendant, facilitated Jeffrey Epstein's access to minor victims knowing that he had a sexual preference for underage girls and that he intended to engage in sexual activity with those victims. Epstein's resulting abuse of minor victims included, among other things, touching a victim's breast, touching a victim's genitals, placing a sex toy such as a vibrator on a victim's genitals,\n\n4\nDOJ-OGR-00001566",
  "text_blocks": [
    {
      "type": "printed",
      "content": "Case 1:20-cr-00330-AJN Document 17 Filed 07/08/20 Page 4 of 18",
      "position": "header"
    },
    {
      "type": "printed",
      "content": "massage Epstein in front of a minor victim. In other instances, MAXWELL encouraged minor victims to provide massages to Epstein, including sexualized massages during which a minor victim would be fully or partially nude. Many of those massages resulted in Epstein sexually abusing the minor victims.\nd. In addition, Epstein offered to help some minor victims by paying for travel and/or educational opportunities, and MAXWELL encouraged certain victims to accept Epstein's assistance. As a result, victims were made to feel indebted and believed that MAXWELL and Epstein were trying to help them.\ne. Through this process, MAXWELL and Epstein enticed victims to engage in sexual activity with Epstein. In some instances, MAXWELL was present for and participated in the sexual abuse of minor victims. Some such incidents occurred in the context of massages, which developed into sexual encounters.",
      "position": "main content"
    },
    {
      "type": "printed",
      "content": "5. GHISLAINE MAXWELL, the defendant, facilitated Jeffrey Epstein's access to minor victims knowing that he had a sexual preference for underage girls and that he intended to engage in sexual activity with those victims. Epstein's resulting abuse of minor victims included, among other things, touching a victim's breast, touching a victim's genitals, placing a sex toy such as a vibrator on a victim's genitals,",
      "position": "main content"
    },
    {
      "type": "printed",
      "content": "4",
      "position": "footer"
    },
    {
      "type": "printed",
      "content": "DOJ-OGR-00001566",
      "position": "footer"
    }
  ],
  "entities": {
    "people": [
      "MAXWELL",
      "Epstein",
      "Jeffrey Epstein",
      "GHISLAINE MAXWELL"
    ],
    "organizations": [],
    "locations": [],
    "dates": [
      "07/08/20"
    ],
    "reference_numbers": [
      "1:20-cr-00330-AJN",
      "17",
      "DOJ-OGR-00001566"
    ]
  },
  "additional_notes": "The document appears to be a court filing related to the case against Ghislaine Maxwell. The text describes the alleged abuse of minor victims by Jeffrey Epstein and Maxwell's involvement. The document is typed and contains no handwritten text or stamps."
}