{
  "document_metadata": {
    "page_number": "5",
    "document_number": "36",
    "date": "07/30/20",
    "document_type": "Court Order",
    "has_handwriting": false,
    "has_stamps": false
  },
  "full_text": "Case 1:20-cr-00330-AJN Document 36 Filed 07/30/20 Page 5 of 12\ndisclosing or disseminating the identity of any victims or witnesses referenced in the Discovery. This Order does not prohibit Defense Counsel or Defense Staff from referencing the identities of individuals they believe may be relevant to the defense to Potential Defense Witnesses and their counsel during the course of the investigation and preparation of the defense case at trial. Any Potential Defense Witnesses and their counsel who are provided identifying information by Defense Counsel or Defense Staff are prohibited from further disclosing or disseminating such identifying information. This Order does not prohibit Defense Counsel from publicly referencing individuals who have spoken by name on the public record in this case.\n6. The Defendant, Defense Counsel, Defense Staff, Defense Experts/Advisors, Potential Defense Witnesses, and Other Authorized Persons are prohibited from filing publicly as an attachment to a filing or excerpted within a filing the identity of any victims or witnesses referenced in the Discovery, who have not spoken by name on the public record in this case, unless authorized by the Government in writing or by Order of the Court. Any such filings must be filed under seal, unless authorized by the Government in writing or by Order of the Court.\n5\nDOJ-OGR-00001694",
  "text_blocks": [
    {
      "type": "printed",
      "content": "Case 1:20-cr-00330-AJN Document 36 Filed 07/30/20 Page 5 of 12",
      "position": "header"
    },
    {
      "type": "printed",
      "content": "disclosing or disseminating the identity of any victims or witnesses referenced in the Discovery. This Order does not prohibit Defense Counsel or Defense Staff from referencing the identities of individuals they believe may be relevant to the defense to Potential Defense Witnesses and their counsel during the course of the investigation and preparation of the defense case at trial. Any Potential Defense Witnesses and their counsel who are provided identifying information by Defense Counsel or Defense Staff are prohibited from further disclosing or disseminating such identifying information. This Order does not prohibit Defense Counsel from publicly referencing individuals who have spoken by name on the public record in this case.",
      "position": "top"
    },
    {
      "type": "printed",
      "content": "6. The Defendant, Defense Counsel, Defense Staff, Defense Experts/Advisors, Potential Defense Witnesses, and Other Authorized Persons are prohibited from filing publicly as an attachment to a filing or excerpted within a filing the identity of any victims or witnesses referenced in the Discovery, who have not spoken by name on the public record in this case, unless authorized by the Government in writing or by Order of the Court. Any such filings must be filed under seal, unless authorized by the Government in writing or by Order of the Court.",
      "position": "middle"
    },
    {
      "type": "printed",
      "content": "5",
      "position": "footer"
    },
    {
      "type": "printed",
      "content": "DOJ-OGR-00001694",
      "position": "footer"
    }
  ],
  "entities": {
    "people": [
      "Defendant",
      "Defense Counsel",
      "Defense Staff",
      "Defense Experts/Advisors",
      "Potential Defense Witnesses"
    ],
    "organizations": [
      "Government",
      "Court"
    ],
    "locations": [],
    "dates": [
      "07/30/20"
    ],
    "reference_numbers": [
      "1:20-cr-00330-AJN",
      "Document 36",
      "DOJ-OGR-00001694"
    ]
  },
  "additional_notes": "The document appears to be a court order related to a criminal case. The text is clear and legible, with no visible redactions or damage."
}