{
  "document_metadata": {
    "page_number": "9",
    "document_number": "70-1",
    "date": "05/17/2021",
    "document_type": "court document",
    "has_handwriting": false,
    "has_stamps": false
  },
  "full_text": "Case 21-770, Document 70-1, 05/17/2021, 3102450, Page9 of 14\nactually told to clean with our own hands. It was humiliating. Floating, dead water bugs, mice, chunks of defecation coming out of the pipes and urine-filled water gushing all through the area. The water was as high as my ankles, and the smell was as bad. It was so bad, the inmates were vomiting due to nausea. Chunks of feces. And officers telling us that we had to clean it and clean it quick because lunch was on the way.\" She continued: \"MCC and MDC are the most degrading and humiliating memories of my life. I will hold onto these memories forever, but these memories are my motivation to stay out of trouble, your Honor.\" United States v. Tiffany Days, April 29, 2021, which can be accessed at: https://tinyurl.com/ytf8cyw5. The judge in that case was upset, finding: \"it is the finding of this Court that the conditions to which [Tiffany Days] was subjected are as disgusting, inhuman as anything I've heard about in any Colombian prison, but more so because we're supposed to be better than that.\" See transcript of sentencing hearing, United States v. Tiffany Days, April 29, 2021, which can be accessed at: https://tinyurl.com/48yw29px.\n4. BOP false accusation to the district court concerning Ms. Maxwell's lawyers: \"Those [privileged] materials that defense counsel\n7\nDOJ-OGR-00001415",
  "text_blocks": [
    {
      "type": "printed",
      "content": "Case 21-770, Document 70-1, 05/17/2021, 3102450, Page9 of 14",
      "position": "header"
    },
    {
      "type": "printed",
      "content": "actually told to clean with our own hands. It was humiliating. Floating, dead water bugs, mice, chunks of defecation coming out of the pipes and urine-filled water gushing all through the area. The water was as high as my ankles, and the smell was as bad. It was so bad, the inmates were vomiting due to nausea. Chunks of feces. And officers telling us that we had to clean it and clean it quick because lunch was on the way.\" She continued: \"MCC and MDC are the most degrading and humiliating memories of my life. I will hold onto these memories forever, but these memories are my motivation to stay out of trouble, your Honor.\" United States v. Tiffany Days, April 29, 2021, which can be accessed at: https://tinyurl.com/ytf8cyw5. The judge in that case was upset, finding: \"it is the finding of this Court that the conditions to which [Tiffany Days] was subjected are as disgusting, inhuman as anything I've heard about in any Colombian prison, but more so because we're supposed to be better than that.\" See transcript of sentencing hearing, United States v. Tiffany Days, April 29, 2021, which can be accessed at: https://tinyurl.com/48yw29px.",
      "position": "main"
    },
    {
      "type": "printed",
      "content": "4. BOP false accusation to the district court concerning Ms. Maxwell's lawyers: \"Those [privileged] materials that defense counsel",
      "position": "main"
    },
    {
      "type": "printed",
      "content": "7",
      "position": "footer"
    },
    {
      "type": "printed",
      "content": "DOJ-OGR-00001415",
      "position": "footer"
    }
  ],
  "entities": {
    "people": [
      "Tiffany Days",
      "Maxwell"
    ],
    "organizations": [
      "MCC",
      "MDC",
      "BOP"
    ],
    "locations": [
      "Colombian"
    ],
    "dates": [
      "April 29, 2021",
      "05/17/2021"
    ],
    "reference_numbers": [
      "21-770",
      "70-1",
      "3102450",
      "DOJ-OGR-00001415"
    ]
  },
  "additional_notes": "The document appears to be a court filing with a header indicating the case number, document number, date, and page number. The text describes unsanitary conditions in a prison and references a previous case involving Tiffany Days. The document is likely related to a legal proceeding involving Ms. Maxwell."
}