{
  "document_metadata": {
    "page_number": "1",
    "document_number": "89",
    "date": "12/07/20",
    "document_type": "Court Order",
    "has_handwriting": true,
    "has_stamps": true
  },
  "full_text": "Case 1:20-cr-00330-AJN Document 89 Filed 12/07/20 Page 1 of 1\nUSDC SDNY DOCUMENT ELECTRONICALLY FILED DOC #: DATE FILED: 12/7/20\nUNITED STATES DISTRICT COURT SOUTHERN DISTRICT OF NEW YORK\nUnited States of America,\n-v-\nGhislain Maxwell,\nDefendant.\n20-CR-330 (AJN)\nORDER\nALISON J. NATHAN, District Judge:\nThe Court is in receipt of the Defendant's December 4, 2020 letter, Dkt. No. 85, and hereby sets the following schedule:\n- The Defendant's submission is due December 8, 2020;\n- The Government's response is due December 16, 2020;\n- The Defendant's reply is due December 18, 2020.\nAfter reviewing these submissions, the Court will determine whether a hearing on the renewed bail motion is necessary.\nThe Court grants the Defendant's request that the Government shall file its submission under seal with proposed redactions. Any objections to proposed redactions are due within 24 hours after any brief has been filed.\nFinally, the Defendant is granted leave to file a motion not to exceed 40 pages. The Government's response shall also be limited to 40 pages. The Defendant's reply shall not exceed 10 pages.\nSO ORDERED.\nDated: December 7, 2020 New York, New York\nALISON J. NATHAN United States District Judge\nDOJ-OGR-00001861",
  "text_blocks": [
    {
      "type": "printed",
      "content": "Case 1:20-cr-00330-AJN Document 89 Filed 12/07/20 Page 1 of 1",
      "position": "header"
    },
    {
      "type": "stamp",
      "content": "USDC SDNY DOCUMENT ELECTRONICALLY FILED DOC #: DATE FILED: 12/7/20",
      "position": "header"
    },
    {
      "type": "printed",
      "content": "UNITED STATES DISTRICT COURT SOUTHERN DISTRICT OF NEW YORK",
      "position": "header"
    },
    {
      "type": "printed",
      "content": "United States of America, -v- Ghislain Maxwell, Defendant.",
      "position": "middle"
    },
    {
      "type": "printed",
      "content": "20-CR-330 (AJN) ORDER",
      "position": "middle"
    },
    {
      "type": "printed",
      "content": "ALISON J. NATHAN, District Judge: The Court is in receipt of the Defendant's December 4, 2020 letter, Dkt. No. 85, and hereby sets the following schedule: - The Defendant's submission is due December 8, 2020; - The Government's response is due December 16, 2020; - The Defendant's reply is due December 18, 2020.",
      "position": "middle"
    },
    {
      "type": "printed",
      "content": "After reviewing these submissions, the Court will determine whether a hearing on the renewed bail motion is necessary.",
      "position": "middle"
    },
    {
      "type": "printed",
      "content": "The Court grants the Defendant's request that the Government shall file its submission under seal with proposed redactions. Any objections to proposed redactions are due within 24 hours after any brief has been filed.",
      "position": "middle"
    },
    {
      "type": "printed",
      "content": "Finally, the Defendant is granted leave to file a motion not to exceed 40 pages. The Government's response shall also be limited to 40 pages. The Defendant's reply shall not exceed 10 pages.",
      "position": "middle"
    },
    {
      "type": "printed",
      "content": "SO ORDERED.",
      "position": "middle"
    },
    {
      "type": "printed",
      "content": "Dated: December 7, 2020 New York, New York",
      "position": "footer"
    },
    {
      "type": "signature",
      "content": "ALISON J. NATHAN United States District Judge",
      "position": "footer"
    },
    {
      "type": "printed",
      "content": "DOJ-OGR-00001861",
      "position": "footer"
    }
  ],
  "entities": {
    "people": [
      "Ghislain Maxwell",
      "Alison J. Nathan"
    ],
    "organizations": [
      "United States District Court",
      "United States of America"
    ],
    "locations": [
      "New York"
    ],
    "dates": [
      "December 4, 2020",
      "December 8, 2020",
      "December 16, 2020",
      "December 18, 2020",
      "December 7, 2020"
    ],
    "reference_numbers": [
      "1:20-cr-00330-AJN",
      "Document 89",
      "Dkt. No. 85",
      "20-CR-330 (AJN)",
      "DOJ-OGR-00001861"
    ]
  },
  "additional_notes": "The document is a court order from the United States District Court for the Southern District of New York. It is signed by Judge Alison J. Nathan and includes a stamp indicating it was electronically filed."
}