{
  "document_metadata": {
    "page_number": "1 of 2",
    "document_number": "165-1",
    "date": "03/09/21",
    "document_type": "Official Letter",
    "has_handwriting": false,
    "has_stamps": true
  },
  "full_text": "Case 1:20-cr-00330-AJN Document 165-1 Filed 03/09/21 Page 1 of 2 MINISTÈRE DE LA JUSTICE Liberté Égalité Fraternité Direction des affaires criminelles et des grâces Sous-direction de la justice pénale spécialisée Bureau de l'entraide pénale internationale Paris, le 9 mars 2021 Monsieur le garde des Sceaux, ministre de la Justice à Department of Justice (D.O.J) Par l'intermédiaire d'Andrew FINKELMAN, magistrat de liaison Ambassade des Etats-Unis d'Amérique à Paris J'ai l'honneur de porter à votre connaissance que la procédure et les conditions d'extradition sont régies en France par les articles 696 et suivants du code de procédure pénale. L'article 696-2 de ce code prévoit ainsi que « le gouvernement français peut remettre, sur leur demande, aux gouvernements étrangers, toute personne n'ayant pas la nationalité française qui, étant l'objet d'une poursuite intentée au nom de l'Etat requérant ou d'une condamnation prononcée par ses tribunaux, est trouvée sur le territoire de la République. » L'article 694-4 précise expressément que : « L'extradition n'est pas accordée : 1° Lorsque la personne réclamée a la nationalité française, cette dernière étant appréciée à l'époque de l'infraction pour laquelle l'extradition est requise ». Ainsi, le fait que la personne recherchée ait la nationalité française constitue un obstacle insurmontable à son extradition. Dès lors que cette nationalité s'apprécie au moment de la commission de l'infraction, la perte de la nationalité, postérieurement à la commission de cette dernière, est sans incidence sur la procédure d'extradition, et ne permet pas de lever cet obstacle. Le Chef du Bureau de l'Entraide Pénale Internationale Philippe JAEGIÉ 13, place Vendôme - 75042 Paris Cedex 01 Téléphone : 01 44 77 60 60 www.justice.gouv.fr DOJ-OGR-00002757",
  "text_blocks": [
    {
      "type": "printed",
      "content": "MINISTÈRE DE LA JUSTICE Liberté Égalité Fraternité",
      "position": "header"
    },
    {
      "type": "printed",
      "content": "Direction des affaires criminelles et des grâces",
      "position": "header"
    },
    {
      "type": "printed",
      "content": "Sous-direction de la justice pénale spécialisée Bureau de l'entraide pénale internationale",
      "position": "header"
    },
    {
      "type": "printed",
      "content": "Paris, le 9 mars 2021",
      "position": "top"
    },
    {
      "type": "printed",
      "content": "Monsieur le garde des Sceaux, ministre de la Justice à Department of Justice (D.O.J)",
      "position": "top"
    },
    {
      "type": "printed",
      "content": "Par l'intermédiaire d'Andrew FINKELMAN, magistrat de liaison Ambassade des Etats-Unis d'Amérique à Paris",
      "position": "top"
    },
    {
      "type": "printed",
      "content": "J'ai l'honneur de porter à votre connaissance que la procédure et les conditions d'extradition sont régies en France par les articles 696 et suivants du code de procédure pénale.",
      "position": "middle"
    },
    {
      "type": "printed",
      "content": "L'article 696-2 de ce code prévoit ainsi que « le gouvernement français peut remettre, sur leur demande, aux gouvernements étrangers, toute personne n'ayant pas la nationalité française qui, étant l'objet d'une poursuite intentée au nom de l'Etat requérant ou d'une condamnation prononcée par ses tribunaux, est trouvée sur le territoire de la République. »",
      "position": "middle"
    },
    {
      "type": "printed",
      "content": "L'article 694-4 précise expressément que : « L'extradition n'est pas accordée : 1° Lorsque la personne réclamée a la nationalité française, cette dernière étant appréciée à l'époque de l'infraction pour laquelle l'extradition est requise ».",
      "position": "middle"
    },
    {
      "type": "printed",
      "content": "Ainsi, le fait que la personne recherchée ait la nationalité française constitue un obstacle insurmontable à son extradition. Dès lors que cette nationalité s'apprécie au moment de la commission de l'infraction, la perte de la nationalité, postérieurement à la commission de cette dernière, est sans incidence sur la procédure d'extradition, et ne permet pas de lever cet obstacle.",
      "position": "middle"
    },
    {
      "type": "printed",
      "content": "Le Chef du Bureau de l'Entraide Pénale Internationale",
      "position": "bottom"
    },
    {
      "type": "signature",
      "content": "Philippe JAEGIÉ",
      "position": "bottom"
    },
    {
      "type": "printed",
      "content": "13, place Vendôme - 75042 Paris Cedex 01 Téléphone : 01 44 77 60 60 www.justice.gouv.fr",
      "position": "footer"
    },
    {
      "type": "printed",
      "content": "DOJ-OGR-00002757",
      "position": "footer"
    }
  ],
  "entities": {
    "people": [
      "Andrew FINKELMAN",
      "Philippe JAEGIÉ"
    ],
    "organizations": [
      "MINISTÈRE DE LA JUSTICE",
      "Department of Justice",
      "Ambassade des Etats-Unis d'Amérique"
    ],
    "locations": [
      "France",
      "Paris",
      "États-Unis d'Amérique"
    ],
    "dates": [
      "9 mars 2021",
      "03/09/21"
    ],
    "reference_numbers": [
      "1:20-cr-00330-AJN",
      "165-1",
      "DOJ-OGR-00002757"
    ]
  },
  "additional_notes": "The document is an official letter from the French Ministry of Justice to the US Department of Justice regarding extradition procedures. It is written in French and includes a signature and a stamp."
}