{
  "document_metadata": {
    "page_number": "64",
    "document_number": "20-2",
    "date": "04/01/2021",
    "document_type": "Court Document",
    "has_handwriting": false,
    "has_stamps": false
  },
  "full_text": "Case 21-770, Document 20-2, 04/01/2021, 3068530, Page64 of 200\n1\nUNITED STATES DISTRICT COURT\nSOUTHERN DISTRICT OF NEW YORK\n-------------------------------x\nUNITED STATES OF AMERICA,\nNew York, N.Y.\nv.\n20 Cr. 330 (AJN)\nGHISLAINE MAXWELL,\nDefendant.\n-------------------------------x Teleconference\nArraignment\nBail Hearing\nJuly 14, 2020\n3:05 p.m.\nBefore:\nHON. ALISON J. NATHAN,\nDistrict Judge\nAPPEARANCES\nAUDREY STRAUSS\nUnited States Attorney for the\nSouthern District of New York\nBY: ALISON J. MOE\nMAURENE R. COMEY\nALEXANDER ROSSMILLER\nAssistant United States Attorneys\nCOHEN & GRESSER, LLP\nAttorneys for Defendant\nBY: MARK S. COHEN\nCHRISTIAN R. EVERDELL\nHADDON MORGAN & FOREMAN, P.C.\nAttorneys for Defendant\nBY: JEFFREY S. PAGLIUCA\nLAURA A. MENNINGER\nSOUTHERN DISTRICT REPORTERS, P.C.\n(212) 805-0300\nDOJ-OGR-00001005",
  "text_blocks": [
    {
      "type": "printed",
      "content": "Case 21-770, Document 20-2, 04/01/2021, 3068530, Page64 of 200",
      "position": "header"
    },
    {
      "type": "printed",
      "content": "UNITED STATES DISTRICT COURT\nSOUTHERN DISTRICT OF NEW YORK\n-------------------------------x\nUNITED STATES OF AMERICA,\nNew York, N.Y.\nv.\n20 Cr. 330 (AJN)\nGHISLAINE MAXWELL,\nDefendant.\n-------------------------------x Teleconference\nArraignment\nBail Hearing\nJuly 14, 2020\n3:05 p.m.\nBefore:\nHON. ALISON J. NATHAN,\nDistrict Judge",
      "position": "top"
    },
    {
      "type": "printed",
      "content": "APPEARANCES\nAUDREY STRAUSS\nUnited States Attorney for the\nSouthern District of New York\nBY: ALISON J. MOE\nMAURENE R. COMEY\nALEXANDER ROSSMILLER\nAssistant United States Attorneys\nCOHEN & GRESSER, LLP\nAttorneys for Defendant\nBY: MARK S. COHEN\nCHRISTIAN R. EVERDELL\nHADDON MORGAN & FOREMAN, P.C.\nAttorneys for Defendant\nBY: JEFFREY S. PAGLIUCA\nLAURA A. MENNINGER",
      "position": "middle"
    },
    {
      "type": "printed",
      "content": "SOUTHERN DISTRICT REPORTERS, P.C.\n(212) 805-0300",
      "position": "bottom"
    },
    {
      "type": "printed",
      "content": "DOJ-OGR-00001005",
      "position": "footer"
    }
  ],
  "entities": {
    "people": [
      "ALISON J. NATHAN",
      "AUDREY STRAUSS",
      "ALISON J. MOE",
      "MAURENE R. COMEY",
      "ALEXANDER ROSSMILLER",
      "MARK S. COHEN",
      "CHRISTIAN R. EVERDELL",
      "JEFFREY S. PAGLIUCA",
      "LAURA A. MENNINGER",
      "GHISLAINE MAXWELL"
    ],
    "organizations": [
      "UNITED STATES DISTRICT COURT",
      "SOUTHERN DISTRICT OF NEW YORK",
      "COHEN & GRESSER, LLP",
      "HADDON MORGAN & FOREMAN, P.C.",
      "SOUTHERN DISTRICT REPORTERS, P.C."
    ],
    "locations": [
      "New York"
    ],
    "dates": [
      "July 14, 2020",
      "04/01/2021"
    ],
    "reference_numbers": [
      "20 Cr. 330 (AJN)",
      "Case 21-770",
      "Document 20-2",
      "3068530",
      "DOJ-OGR-00001005"
    ]
  },
  "additional_notes": "The document appears to be a court transcript or record from a case involving Ghislaine Maxwell. The text is clear and legible, with no visible redactions or damage."
}