{
  "document_metadata": {
    "page_number": "2",
    "document_number": "20-cr-00880-AJN Document 112 Filed 03/23/21 Page 141 of 518",
    "date": null,
    "document_type": "court document",
    "has_handwriting": false,
    "has_stamps": false
  },
  "full_text": "Case#: 20-cr-00880-AJN Document 112 Filed 03/23/21 Page 141 of 518\nWILLIAM JULIÉ\nAVOCAT À LA COUR - ATTORNEY AT LAW\n(ii) Nor is it supported by the spirit of the law;\n(iii) Case law and precedents in fact suggest the opposite.\n7. First, the Ministry's interpretation goes against the letter of the law.\n8. American extradition requests are principally governed by the Extradition Treaty between the USA and France of 23 April 1996 (\"the Treaty\") and the French Code of Criminal Procedure for matters not dealt with under the Treaty. 1\n9. Article 3(1) of the Treaty provides:\n\"There is no obligation upon the Requested State to grant the extradition of a person who is a national of the Requested State, but the executive authority of the United States shall have the power to surrender a national of the United States if, in its discretion, it deems it proper to do so. The nationality of the person sought shall be the nationality of that person at the time the offense was committed\".\n10. Article 696-4 of the French Code of Criminal Procedure provides for the same rule, under similar wording:\n\"Extradition shall not be granted:\n1° When the person claimed has French nationality, the latter being assessed at the time of the offense for which extradition is requested\"\n11. Under a literal reading of these provisions, the nationality protection only applies where French authorities are faced with an extradition request against a person who is a French national at the time of the extradition request. Both the Treaty and the French Code of\n1 Other relevant international treaties include: the Agreement on Extradition between the United States of America and the European Union signed in Washington on 25 June 2003, and the Instrument Amending the Treaty of 23 April 1996 between the United States of America and France signed in the Hague on 30 September 2004.\n51, RUE AMPÈRE - 75017 PARIS - TÉL. 01 88 33 51 80 - FAX. 01 88 33 51 81\nwj@wjavocats.com - www.wjavocats.com - PALAIS C1652\n2\nDOJ-OGR-00001268",
  "text_blocks": [
    {
      "type": "printed",
      "content": "Case#: 20-cr-00880-AJN Document 112 Filed 03/23/21 Page 141 of 518",
      "position": "header"
    },
    {
      "type": "printed",
      "content": "WILLIAM JULIÉ\nAVOCAT À LA COUR - ATTORNEY AT LAW",
      "position": "header"
    },
    {
      "type": "printed",
      "content": "(ii) Nor is it supported by the spirit of the law;\n(iii) Case law and precedents in fact suggest the opposite.\n7. First, the Ministry's interpretation goes against the letter of the law.\n8. American extradition requests are principally governed by the Extradition Treaty between the USA and France of 23 April 1996 (\"the Treaty\") and the French Code of Criminal Procedure for matters not dealt with under the Treaty. 1\n9. Article 3(1) of the Treaty provides:\n\"There is no obligation upon the Requested State to grant the extradition of a person who is a national of the Requested State, but the executive authority of the United States shall have the power to surrender a national of the United States if, in its discretion, it deems it proper to do so. The nationality of the person sought shall be the nationality of that person at the time the offense was committed\".\n10. Article 696-4 of the French Code of Criminal Procedure provides for the same rule, under similar wording:\n\"Extradition shall not be granted:\n1° When the person claimed has French nationality, the latter being assessed at the time of the offense for which extradition is requested\"\n11. Under a literal reading of these provisions, the nationality protection only applies where French authorities are faced with an extradition request against a person who is a French national at the time of the extradition request. Both the Treaty and the French Code of",
      "position": "main body"
    },
    {
      "type": "printed",
      "content": "1 Other relevant international treaties include: the Agreement on Extradition between the United States of America and the European Union signed in Washington on 25 June 2003, and the Instrument Amending the Treaty of 23 April 1996 between the United States of America and France signed in the Hague on 30 September 2004.",
      "position": "footnote"
    },
    {
      "type": "printed",
      "content": "51, RUE AMPÈRE - 75017 PARIS - TÉL. 01 88 33 51 80 - FAX. 01 88 33 51 81\nwj@wjavocats.com - www.wjavocats.com - PALAIS C1652",
      "position": "footer"
    },
    {
      "type": "printed",
      "content": "2",
      "position": "footer"
    },
    {
      "type": "printed",
      "content": "DOJ-OGR-00001268",
      "position": "footer"
    }
  ],
  "entities": {
    "people": [
      "William Julié"
    ],
    "organizations": [
      "United States of America",
      "European Union",
      "French Code of Criminal Procedure"
    ],
    "locations": [
      "USA",
      "France",
      "Washington",
      "Hague",
      "Paris"
    ],
    "dates": [
      "23 April 1996",
      "25 June 2003",
      "30 September 2004",
      "03/23/21"
    ],
    "reference_numbers": [
      "20-cr-00880-AJN",
      "DOJ-OGR-00001268"
    ]
  },
  "additional_notes": "The document appears to be a court filing related to an extradition case, with references to international treaties and French law. The text is mostly printed, with no handwritten content or stamps visible."
}