{
  "document_metadata": {
    "page_number": "2",
    "document_number": "16",
    "date": "07/09/20",
    "document_type": "Court Order",
    "has_handwriting": true,
    "has_stamps": false
  },
  "full_text": "Case 1:20-cr-00330-AJN Document 16 Filed 07/09/20 Page 2 of 2\n\nlimited to approximately 60 seats in order to enable appropriate social distancing and ensure public safety. Counsel for the Defendant and the Government may contact Chambers by email if there is a request to accommodate alleged victims or family members of the Defendant.\n\nMembers of the credentialed in-house press corps may contact the District Executive's Office about seating. Otherwise, all seating will be allocated on a first come, first serve basis and in accordance with the S.D.N.Y. COVID-19 Courthouse Entry Program and this Court's previous order of July 7, 2020. See Dkt. No. 10. If conditions change or the Court otherwise concludes that allowing for in-person viewing of the video feed at the courthouse is not consistent with public health, the Court may provide audio access by telephone only.\n\nAny photographing, recording, or rebroadcasting of federal court proceedings is prohibited by law. Violation of these prohibitions may result in fines or sanctions, including removal of court issued media credentials, restricted entry to future hearings, denial of entry to future hearings, or any other sanctions deemed necessary by the Court.\n\nSO ORDERED.\n\nDated: July 9, 2020\nNew York, New York\n\nALISON J. NATHAN\nUnited States District Judge",
  "text_blocks": [
    {
      "type": "printed",
      "content": "Case 1:20-cr-00330-AJN Document 16 Filed 07/09/20 Page 2 of 2",
      "position": "header"
    },
    {
      "type": "printed",
      "content": "limited to approximately 60 seats in order to enable appropriate social distancing and ensure public safety. Counsel for the Defendant and the Government may contact Chambers by email if there is a request to accommodate alleged victims or family members of the Defendant.",
      "position": "top"
    },
    {
      "type": "printed",
      "content": "Members of the credentialed in-house press corps may contact the District Executive's Office about seating. Otherwise, all seating will be allocated on a first come, first serve basis and in accordance with the S.D.N.Y. COVID-19 Courthouse Entry Program and this Court's previous order of July 7, 2020. See Dkt. No. 10. If conditions change or the Court otherwise concludes that allowing for in-person viewing of the video feed at the courthouse is not consistent with public health, the Court may provide audio access by telephone only.",
      "position": "middle"
    },
    {
      "type": "printed",
      "content": "Any photographing, recording, or rebroadcasting of federal court proceedings is prohibited by law. Violation of these prohibitions may result in fines or sanctions, including removal of court issued media credentials, restricted entry to future hearings, denial of entry to future hearings, or any other sanctions deemed necessary by the Court.",
      "position": "middle"
    },
    {
      "type": "printed",
      "content": "SO ORDERED.",
      "position": "middle"
    },
    {
      "type": "printed",
      "content": "Dated: July 9, 2020\nNew York, New York",
      "position": "bottom"
    },
    {
      "type": "handwritten",
      "content": "Alison J. Nathan",
      "position": "bottom"
    },
    {
      "type": "printed",
      "content": "ALISON J. NATHAN\nUnited States District Judge",
      "position": "bottom"
    }
  ],
  "entities": {
    "people": [
      "Alison J. Nathan"
    ],
    "organizations": [
      "District Executive's Office",
      "S.D.N.Y.",
      "United States District Court"
    ],
    "locations": [
      "New York"
    ],
    "dates": [
      "July 9, 2020",
      "July 7, 2020"
    ],
    "reference_numbers": [
      "1:20-cr-00330-AJN",
      "Document 16",
      "Dkt. No. 10"
    ]
  },
  "additional_notes": "The document appears to be a court order related to COVID-19 protocols in a federal court proceeding. The text is clear and legible, with a handwritten signature at the bottom."
}