{
  "document_metadata": {
    "page_number": "9",
    "document_number": "2684",
    "date": "07/26/17",
    "document_type": "transcript",
    "has_handwriting": false,
    "has_stamps": false
  },
  "full_text": "Censor & Associates Reporting and Transcription, Inc. Page 9 1 MR. LEOPOLD: Lewis, we're not going to do that. 2 3 MR. TEIN: My name is not Lewis. 4 I'm going to finish my question. Okay? 5 6 MR. LEOPOLD: Do not answer until you hear from me. 7 BY MR. TEIN: 8 9 Q. Other than conversations that you have had with Mr. Leopold -- I'm not asking about that -- are you aware that Mr. Leopold has filed a lawsuit in federal court seeking fifty million dollars from Jeffrey Epstein on your behalf? 10 11 12 MR. LEOPOLD: Same objection. 13 Anything that you learn through conversations between you and me, do not answer. 14 Those are protected. If you know through any 15 other realm of knowledge, you may answer. 16 17 THE WITNESS: No. 18 19 BY MR. TEIN: 20 Q. You have no idea that Mr. Leopold filed a 21 fifty million-dollar lawsuit on your behalf against 22 Jeffrey Epstein? 23 MR. LEOPOLD: Same objection. 24 Do not answer that question if it's through discussions that you and I had. Outside of that, 25 Ph. 561.682.0905 - Fax. 561.682.1771 1655 Palm Beach Lakes Blvd., Suite 500 - West Palm Beach, FL 33401 07/26/17 Page 2684 Public Records Request No.: 17-295 DOJ-OGR-00032997",
  "text_blocks": [
    {
      "type": "printed",
      "content": "Censor & Associates Reporting and Transcription, Inc.",
      "position": "header"
    },
    {
      "type": "printed",
      "content": "Page 9",
      "position": "header"
    },
    {
      "type": "printed",
      "content": "1 MR. LEOPOLD: Lewis, we're not going to do that. 2 3 MR. TEIN: My name is not Lewis. 4 I'm going to finish my question. Okay? 5 6 MR. LEOPOLD: Do not answer until you hear from me. 7 BY MR. TEIN: 8 9 Q. Other than conversations that you have had with Mr. Leopold -- I'm not asking about that -- are you aware that Mr. Leopold has filed a lawsuit in federal court seeking fifty million dollars from Jeffrey Epstein on your behalf? 10 11 12 MR. LEOPOLD: Same objection. 13 Anything that you learn through conversations between you and me, do not answer. 14 Those are protected. If you know through any 15 other realm of knowledge, you may answer. 16 17 THE WITNESS: No. 18 19 BY MR. TEIN: 20 Q. You have no idea that Mr. Leopold filed a 21 fifty million-dollar lawsuit on your behalf against 22 Jeffrey Epstein? 23 MR. LEOPOLD: Same objection. 24 Do not answer that question if it's through discussions that you and I had. Outside of that, 25",
      "position": "main"
    },
    {
      "type": "printed",
      "content": "Ph. 561.682.0905 - Fax. 561.682.1771 1655 Palm Beach Lakes Blvd., Suite 500 - West Palm Beach, FL 33401",
      "position": "footer"
    },
    {
      "type": "printed",
      "content": "07/26/17 Page 2684 Public Records Request No.: 17-295 DOJ-OGR-00032997",
      "position": "footer"
    }
  ],
  "entities": {
    "people": [
      "MR. LEOPOLD",
      "MR. TEIN",
      "Lewis",
      "Jeffrey Epstein"
    ],
    "organizations": [
      "Censor & Associates Reporting and Transcription, Inc."
    ],
    "locations": [
      "West Palm Beach",
      "FL"
    ],
    "dates": [
      "07/26/17"
    ],
    "reference_numbers": [
      "17-295",
      "DOJ-OGR-00032997"
    ]
  },
  "additional_notes": "The document appears to be a transcript of a deposition or testimony. The quality is clear, and there are no visible redactions or damage."
}