{
  "document_metadata": {
    "page_number": "22",
    "document_number": "17-295",
    "date": "07/26/17",
    "document_type": "transcription",
    "has_handwriting": false,
    "has_stamps": false
  },
  "full_text": "Page 22\n1 the towels for the plane.\n2 Q. Would you clean his plane too?\n3 A. No, no.\n4 Q. Did you ever travel with him anywhere?\n5 A. No, no.\n6 Q. When he went to New York or Arizona or his\n7 private island?\n8 A. I've been on his island. I've been as a\n9 guest, as a vacation. We just took vacations, and I went\n10 to his island in the Caribbean. And I've been in New\n11 Mexico. I've been at his house in London. But not as a\n12 worker, just vacation.\n13 Q. As a vacation?\n14 A. Uh-huh.\n15 We went to New Mexico for -- it was kind of\n16 a symposium about how to clean homes. It was this lady\n17 who make -- teach all the house people, housemen, and\n18 they invited us to Santa Fe, New Mexico, to teach us how\n19 to clean homes. That was kind of stupid.\n20 Q. How he wanted it to be cleaned?\n21 A. Yes. We didn't get that much.\n22 Q. Can you think of anything that I haven't\n23 asked you that might be relevant to this?\n24 A. I can't think of anything. Basically it's\n25 the same questions that the other investigator asked me.\n\nJ. CONSOR & ASSOCIATES REPORTING & TRANSCRIPTION\n561.835.9738\nPage 23 of 100 Public Records Request No.: 17-295\n07/26/17 DOJ-OGR-00031962",
  "text_blocks": [
    {
      "type": "printed",
      "content": "Page 22\n1 the towels for the plane.\n2 Q. Would you clean his plane too?\n3 A. No, no.\n4 Q. Did you ever travel with him anywhere?\n5 A. No, no.\n6 Q. When he went to New York or Arizona or his\n7 private island?\n8 A. I've been on his island. I've been as a\n9 guest, as a vacation. We just took vacations, and I went\n10 to his island in the Caribbean. And I've been in New\n11 Mexico. I've been at his house in London. But not as a\n12 worker, just vacation.\n13 Q. As a vacation?\n14 A. Uh-huh.\n15 We went to New Mexico for -- it was kind of\n16 a symposium about how to clean homes. It was this lady\n17 who make -- teach all the house people, housemen, and\n18 they invited us to Santa Fe, New Mexico, to teach us how\n19 to clean homes. That was kind of stupid.\n20 Q. How he wanted it to be cleaned?\n21 A. Yes. We didn't get that much.\n22 Q. Can you think of anything that I haven't\n23 asked you that might be relevant to this?\n24 A. I can't think of anything. Basically it's\n25 the same questions that the other investigator asked me.",
      "position": "top"
    },
    {
      "type": "printed",
      "content": "J. CONSOR & ASSOCIATES REPORTING & TRANSCRIPTION\n561.835.9738",
      "position": "bottom"
    },
    {
      "type": "printed",
      "content": "Page 23 of 100 Public Records Request No.: 17-295\n07/26/17 DOJ-OGR-00031962",
      "position": "bottom"
    }
  ],
  "entities": {
    "people": [],
    "organizations": [
      "J. CONSOR & ASSOCIATES"
    ],
    "locations": [
      "New York",
      "Arizona",
      "Caribbean",
      "New Mexico",
      "London",
      "Santa Fe"
    ],
    "dates": [
      "07/26/17"
    ],
    "reference_numbers": [
      "17-295",
      "DOJ-OGR-00031962"
    ]
  },
  "additional_notes": "The document appears to be a transcription of an interview. The text is clear and legible, with no visible redactions or damage."
}