{
  "document_metadata": {
    "page_number": "111",
    "document_number": "17-295",
    "date": "2/19/2005",
    "document_type": "Passenger Manifest",
    "has_handwriting": true,
    "has_stamps": false
  },
  "full_text": "HYPERION AIR, INC. PASSENGER MANIFEST Registration Number: N909JE Type: G-1159B Pilots: Dave Rodgers, Larry Niroshi GARY ROXBURGH DATE: 2 19 2005 FROM PBI TO TIST Departure Time 10 :05 AM Arrival Time 1 :16 PM Trip Number 1755 PASSENGERS 1. COLLEEN 2. +1 FEMALE FROM Identifier Defined City WEST PALM BEACH State or Country FL TO Identifier Defined City ST. THOMAS State or Country USVI Nautical Miles Statute Miles Gallons 1200 Pounds 8564 AIRFRAME 9712.9 Flight Time 2+11 2.2 Altitude FL 430 9715.1 TAKE-OFF POWER Night Flex Take-Off 2.15 T/L 1 Min Take-Off IMC Condition Approach COMMENTS 07/26/17 Page 111 of 151 Public Records Request No.: 17-295 DOJ-OGR-00032150",
  "text_blocks": [
    {
      "type": "printed",
      "content": "HYPERION AIR, INC. PASSENGER MANIFEST",
      "position": "header"
    },
    {
      "type": "printed",
      "content": "Registration Number: N909JE Type: G-1159B Pilots: Dave Rodgers, Larry Niroshi",
      "position": "top"
    },
    {
      "type": "handwritten",
      "content": "GARY ROXBURGH",
      "position": "top"
    },
    {
      "type": "printed",
      "content": "DATE: 2 19 2005 FROM PBI TO TIST",
      "position": "middle"
    },
    {
      "type": "handwritten",
      "content": "10 :05 AM 1 :16 PM 1755",
      "position": "middle"
    },
    {
      "type": "printed",
      "content": "PASSENGERS",
      "position": "middle"
    },
    {
      "type": "handwritten",
      "content": "1. COLLEEN 2. +1 FEMALE",
      "position": "middle"
    },
    {
      "type": "printed",
      "content": "FROM Identifier Defined City WEST PALM BEACH State or Country FL TO Identifier Defined City ST. THOMAS State or Country USVI",
      "position": "middle"
    },
    {
      "type": "handwritten",
      "content": "1200 8564 2+11 430 2.15 1",
      "position": "middle"
    },
    {
      "type": "printed",
      "content": "COMMENTS",
      "position": "bottom"
    },
    {
      "type": "printed",
      "content": "07/26/17 Page 111 of 151 Public Records Request No.: 17-295 DOJ-OGR-00032150",
      "position": "footer"
    }
  ],
  "entities": {
    "people": [
      "Dave Rodgers",
      "Larry Niroshi",
      "GARY ROXBURGH",
      "COLLEEN"
    ],
    "organizations": [
      "HYPERION AIR, INC."
    ],
    "locations": [
      "WEST PALM BEACH",
      "FL",
      "ST. THOMAS",
      "USVI",
      "PBI",
      "TIST"
    ],
    "dates": [
      "2/19/2005",
      "07/26/17"
    ],
    "reference_numbers": [
      "N909JE",
      "G-1159B",
      "1755",
      "17-295",
      "DOJ-OGR-00032150"
    ]
  },
  "additional_notes": "The document is a passenger manifest for a flight from West Palm Beach, FL to St. Thomas, USVI on February 19, 2005. The document contains handwritten notes and appears to be a scanned copy."
}