{
  "document_metadata": {
    "page_number": "79",
    "document_number": "17-295",
    "date": "7/17/2006",
    "document_type": "Application Form",
    "has_handwriting": true,
    "has_stamps": false
  },
  "full_text": "7/17/2006 3:1 FROM: Dell Riley Kiraly TO: 1954763456 AGE: 004 OF 007 Feb-16-2006 02:58pm From- FEB 15 2006 14:57 FR VICTORIA SECRET 9042784321 TO 16144157188 P.04/16 An equal opportunity employer, Victoria Secret Stores, Inc. does not discriminate in hiring or terms and conditions of employment, because of an individual's race, color, religion, gender, national origin, citizenship, age, disability, sexual orientation or marital status. Victoria Secret Stores, Inc. only hires individuals authorized for employment in the United States. VICTORIA'S SECRET Position Desired: Krandlepisales Schedule Desired: Full Time Part Time Temporary / Seasonal Salary Expected: $ 6.50 per hour Date Available: aug 4 12005 Date of Application 8,04,05 EDUCATION Type of School Name and Location of School Degree / Area of Study Number of Years Attended HIGH SCHOOL C Diploma 4 COLLEGE Name f A City State OTHER Name City State EMPLOYMENT HISTORY List employment starting with your most recent position. Account for any time during this period that you were unemployed by stating the nature of your activities. If you have less than four places of employment, include personal references to be contacted. May we contact your current employer? Yes No From To Name and Address of Employer Position Held and Supervisor List Major Duties clerical greeter + sales. greeting + sales greeter + sales 07/26/17 Page 79 of 104 Public Records Request No.: 17-295 DOJ-OGR-00031696",
  "text_blocks": [
    {
      "type": "printed",
      "content": "7/17/2006 3:1 FROM: Dell Riley Kiraly TO: 1954763456 AGE: 004 OF 007",
      "position": "header"
    },
    {
      "type": "printed",
      "content": "FEB 15 2006 14:57 FR VICTORIA SECRET 9042784321 TO 16144157188 P.04/16",
      "position": "header"
    },
    {
      "type": "printed",
      "content": "An equal opportunity employer, Victoria Secret Stores, Inc. does not discriminate in hiring or terms and conditions of employment, because of an individual's race, color, religion, gender, national origin, citizenship, age, disability, sexual orientation or marital status. Victoria Secret Stores, Inc. only hires individuals authorized for employment in the United States.",
      "position": "top"
    },
    {
      "type": "printed",
      "content": "VICTORIA'S SECRET",
      "position": "top"
    },
    {
      "type": "handwritten",
      "content": "Krandlepisales",
      "position": "top"
    },
    {
      "type": "printed",
      "content": "EDUCATION",
      "position": "middle"
    },
    {
      "type": "handwritten",
      "content": "C Diploma 4",
      "position": "middle"
    },
    {
      "type": "printed",
      "content": "EMPLOYMENT HISTORY",
      "position": "middle"
    },
    {
      "type": "handwritten",
      "content": "clerical greeter + sales. greeting + sales greeter + sales",
      "position": "middle"
    },
    {
      "type": "printed",
      "content": "07/26/17 Page 79 of 104 Public Records Request No.: 17-295 DOJ-OGR-00031696",
      "position": "footer"
    }
  ],
  "entities": {
    "people": [
      "Dell Riley Kiraly"
    ],
    "organizations": [
      "Victoria Secret Stores, Inc."
    ],
    "locations": [
      "United States"
    ],
    "dates": [
      "Feb-16-2006",
      "FEB 15 2006",
      "7/17/2006",
      "aug 4 12005",
      "8,04,05",
      "07/26/17"
    ],
    "reference_numbers": [
      "17-295",
      "DOJ-OGR-00031696",
      "1954763456",
      "9042784321",
      "16144157188"
    ]
  },
  "additional_notes": "The document is a Victoria's Secret job application form with handwritten notes and redactions. The image quality is clear, but some information is obscured or redacted."
}