{
  "document_metadata": {
    "page_number": "4",
    "document_number": "DOJ-OGR-00032043",
    "date": "7/24/06",
    "document_type": "newspaper article",
    "has_handwriting": true,
    "has_stamps": false
  },
  "full_text": "Mystery money man faces soliciting charge\nBy NICOLE JANOK\nPalm Beach Post Staff Writer\nA part-time Palm Beacher who has socialized with Donald Trump, Bill Clinton and Kevin Spacey was jailed early Sunday with accused drug dealers, drunken drivers and wife beaters after he was charged with soliciting a prostitute.\nManhattan money manager Jeffrey Epstein, 53, was picked up at his home on El Brillo Way at 1:45 a.m. He was released hours later on $3,000 bond.\nEpstein was indicted last week by a state grand jury, according to state attorney's spokesman Mike Edmondson.\nDespite Epstein's arrest, the indictment containing the allegations remained sealed Sunday and Edmondson provided no details.\nUnlike most accused johns, Epstein was charged with a third-degree felony instead of a misdemeanor. Under state law, a solicitation charge usually is elevated to a more-serious felony when the defendant has at least two solicitation convictions.\nHowever, checks of court records here and in New York Sunday turned up no such convictions.\nEpstein could not be reached. Flemondson said he was being represented by West Palm Beach attorney Jack Goldberg, who declined comment.\nEpstein is the president of J Epstein & Co., a money management company based in Manhattan that caters to ultra-wealthy clientele, according to pub-\nSee SOLICITING, 6B\nJeffrey Epstein\nIndictment related to prostitution.\n07/26/17\nPage 4 of 151\nPublic Records Request No.: 17-295\nDOJ-OGR-00032043",
  "text_blocks": [
    {
      "type": "printed",
      "content": "Mystery money man faces soliciting charge",
      "position": "header"
    },
    {
      "type": "printed",
      "content": "By NICOLE JANOK\nPalm Beach Post Staff Writer",
      "position": "header"
    },
    {
      "type": "printed",
      "content": "A part-time Palm Beacher who has socialized with Donald Trump, Bill Clinton and Kevin Spacey was jailed early Sunday with accused drug dealers, drunken drivers and wife beaters after he was charged with soliciting a prostitute.",
      "position": "body"
    },
    {
      "type": "printed",
      "content": "Manhattan money manager Jeffrey Epstein, 53, was picked up at his home on El Brillo Way at 1:45 a.m. He was released hours later on $3,000 bond.",
      "position": "body"
    },
    {
      "type": "printed",
      "content": "Epstein was indicted last week by a state grand jury, according to state attorney's spokesman Mike Edmondson.",
      "position": "body"
    },
    {
      "type": "printed",
      "content": "Despite Epstein's arrest, the indictment containing the allegations remained sealed Sunday and Edmondson provided no details.",
      "position": "body"
    },
    {
      "type": "printed",
      "content": "Unlike most accused johns, Epstein was charged with a third-degree felony instead of a misdemeanor. Under state law, a solicitation charge usually is elevated to a more-serious felony when the defendant has at least two solicitation convictions.",
      "position": "body"
    },
    {
      "type": "printed",
      "content": "However, checks of court records here and in New York Sunday turned up no such convictions.",
      "position": "body"
    },
    {
      "type": "printed",
      "content": "Epstein could not be reached. Flemondson said he was being represented by West Palm Beach attorney Jack Goldberg, who declined comment.",
      "position": "body"
    },
    {
      "type": "printed",
      "content": "Epstein is the president of J Epstein & Co., a money management company based in Manhattan that caters to ultra-wealthy clientele, according to pub-",
      "position": "body"
    },
    {
      "type": "printed",
      "content": "See SOLICITING, 6B",
      "position": "body"
    },
    {
      "type": "printed",
      "content": "Jeffrey Epstein\nIndictment related to prostitution.",
      "position": "caption"
    },
    {
      "type": "handwritten",
      "content": "7/24/06",
      "position": "margin"
    },
    {
      "type": "printed",
      "content": "07/26/17\nPage 4 of 151\nPublic Records Request No.: 17-295\nDOJ-OGR-00032043",
      "position": "footer"
    }
  ],
  "entities": {
    "people": [
      "Jeffrey Epstein",
      "Donald Trump",
      "Bill Clinton",
      "Kevin Spacey",
      "Nicole Janok",
      "Mike Edmondson",
      "Jack Goldberg"
    ],
    "organizations": [
      "Palm Beach Post",
      "J Epstein & Co."
    ],
    "locations": [
      "Palm Beach",
      "Manhattan",
      "New York",
      "El Brillo Way",
      "West Palm Beach"
    ],
    "dates": [
      "7/24/06",
      "07/26/17"
    ],
    "reference_numbers": [
      "17-295",
      "DOJ-OGR-00032043"
    ]
  },
  "additional_notes": "The document appears to be a scanned newspaper article with some handwritten notes. The article discusses the arrest and indictment of Jeffrey Epstein on soliciting charges. The document is part of a larger collection, as indicated by the 'Page 4 of 151' notation."
}