{
  "document_metadata": {
    "page_number": "1",
    "document_number": "J6-6702",
    "date": "01/21/2006",
    "document_type": "Incident Report",
    "has_handwriting": false,
    "has_stamps": false
  },
  "full_text": "Incident Report\nCHEROKEE COUNTY SHERIFF'S OFFICE\n498 CHATTIN DRIVE\n(678) 493-4200\nJ6-6702 DRAFT\nReported Date: 01/21/2006\nOfficer: ALLEN, AUTUMN\nAdministrative Information\nAgency: CHEROKEE COUNTY SHERIFF'S OFFICE\nReport No: 06-6702\nSupplement No: 0001\nReported Date: 01/21/2006\nReported Time: 15:30\nAssignment: CID DAY SHIFT PERSONS UNIT\nCID DAY SHIFT PERSONS UNIT\nNarrative\nOn 012106 I was notified by dispatch to give B-43 a call. I called and spoke with D/S Ballard and he was taking a report of a missing juvenile age 15. He stated she was supposed to have gone to a basketball game last night but she didn't. He stated she went off with some black males. He told they were stopped by some white friends of her and they fought with the black males. D/S Ballard said the mother had contact with her daughter around 8:00 last night but had not heard from her since then.\nReport Officer: 000284/ALLEN, AUTUMN\nPrinted At: 06/06/2006 11:12\nPage 1 of 1\n07/26/17 Page 52 of 95 Public Records Request No.: 17-295",
  "text_blocks": [
    {
      "type": "printed",
      "content": "Incident Report\nCHEROKEE COUNTY SHERIFF'S OFFICE\n498 CHATTIN DRIVE\n(678) 493-4200",
      "position": "header"
    },
    {
      "type": "printed",
      "content": "J6-6702 DRAFT\nReported Date: 01/21/2006\nOfficer: ALLEN, AUTUMN",
      "position": "header"
    },
    {
      "type": "printed",
      "content": "Administrative Information",
      "position": "top"
    },
    {
      "type": "printed",
      "content": "Agency: CHEROKEE COUNTY SHERIFF'S OFFICE\nReport No: 06-6702\nSupplement No: 0001\nReported Date: 01/21/2006\nReported Time: 15:30\nAssignment: CID DAY SHIFT PERSONS UNIT\nCID DAY SHIFT PERSONS UNIT",
      "position": "middle"
    },
    {
      "type": "printed",
      "content": "Narrative",
      "position": "middle"
    },
    {
      "type": "printed",
      "content": "On 012106 I was notified by dispatch to give B-43 a call. I called and spoke with D/S Ballard and he was taking a report of a missing juvenile age 15. He stated she was supposed to have gone to a basketball game last night but she didn't. He stated she went off with some black males. He told they were stopped by some white friends of her and they fought with the black males. D/S Ballard said the mother had contact with her daughter around 8:00 last night but had not heard from her since then.",
      "position": "middle"
    },
    {
      "type": "printed",
      "content": "Report Officer: 000284/ALLEN, AUTUMN\nPrinted At: 06/06/2006 11:12\nPage 1 of 1",
      "position": "footer"
    },
    {
      "type": "printed",
      "content": "07/26/17 Page 52 of 95 Public Records Request No.: 17-295",
      "position": "footer"
    }
  ],
  "entities": {
    "people": [
      "ALLEN, AUTUMN",
      "D/S Ballard"
    ],
    "organizations": [
      "CHEROKEE COUNTY SHERIFF'S OFFICE",
      "CID DAY SHIFT PERSONS UNIT"
    ],
    "locations": [
      "498 CHATTIN DRIVE"
    ],
    "dates": [
      "01/21/2006",
      "06/06/2006",
      "07/26/17"
    ],
    "reference_numbers": [
      "J6-6702",
      "06-6702",
      "0001",
      "17-295"
    ]
  },
  "additional_notes": "The document is a draft incident report from the Cherokee County Sheriff's Office. It appears to be a scanned or photocopied version of the original document."
}