{
  "document_metadata": {
    "page_number": "1 of 15, 31 of 95",
    "document_number": "17-295",
    "date": "2/9/2006, 07/26/17",
    "document_type": "Public Records Request",
    "has_handwriting": false,
    "has_stamps": false
  },
  "full_text": "www.myspace.com/ Page 1 of 15 MySpace.com | Home The Web MySpace Search Panasonic ideas for life (shaky) hands cause blurry photos Home | Browse | Search | Invite | Rank | Mail | Blog | Favorites | Forum | Groups | Events | Games | Music \"Charmingly Confident And Almost Borderline Cocky\" Last Login: 2/9/2006 View More Pics Contacting Send Message Forward to Friend Add to Friends Add to Favorites Instant Message Block User Add to Group Rank User DAMAGED +add+ +view+ 's Interests General 07/26/17 Page 31 of 95 Public Records Request No.: 17-295 http://profile.myspace.com/index.cfm?fuseaction=user.viewProfile&friendID=27567479 2/9/2006 DOJ-OGR-00032221",
  "text_blocks": [
    {
      "type": "printed",
      "content": "www.myspace.com/",
      "position": "header"
    },
    {
      "type": "printed",
      "content": "Page 1 of 15",
      "position": "header"
    },
    {
      "type": "printed",
      "content": "MySpace.com | Home The Web MySpace Search Panasonic ideas for life (shaky) hands cause blurry photos",
      "position": "top"
    },
    {
      "type": "printed",
      "content": "Home | Browse | Search | Invite | Rank | Mail | Blog | Favorites | Forum | Groups | Events | Games | Music",
      "position": "top"
    },
    {
      "type": "printed",
      "content": "\"Charmingly Confident And Almost Borderline Cocky\" Last Login: 2/9/2006",
      "position": "middle"
    },
    {
      "type": "printed",
      "content": "View More Pics",
      "position": "middle"
    },
    {
      "type": "printed",
      "content": "Contacting Send Message Forward to Friend Add to Friends Add to Favorites Instant Message Block User Add to Group Rank User",
      "position": "middle"
    },
    {
      "type": "printed",
      "content": "DAMAGED +add+ +view+",
      "position": "middle"
    },
    {
      "type": "printed",
      "content": "'s Interests General",
      "position": "middle"
    },
    {
      "type": "printed",
      "content": "07/26/17 Page 31 of 95 Public Records Request No.: 17-295",
      "position": "footer"
    },
    {
      "type": "printed",
      "content": "http://profile.myspace.com/index.cfm?fuseaction=user.viewProfile&friendID=27567479 2/9/2006",
      "position": "footer"
    },
    {
      "type": "printed",
      "content": "DOJ-OGR-00032221",
      "position": "footer"
    }
  ],
  "entities": {
    "people": [],
    "organizations": [
      "MySpace",
      "Panasonic",
      "DOJ"
    ],
    "locations": [],
    "dates": [
      "2/9/2006",
      "07/26/17"
    ],
    "reference_numbers": [
      "17-295",
      "27567479",
      "DOJ-OGR-00032221"
    ]
  },
  "additional_notes": "The document appears to be a printout of a MySpace profile page with some redacted information. The page contains various links and buttons, as well as a public records request number and a DOJ reference number."
}