{
  "document_metadata": {
    "page_number": "11",
    "document_number": "17-295",
    "date": "07/26/17",
    "document_type": "Deposition Transcript",
    "has_handwriting": false,
    "has_stamps": false
  },
  "full_text": "Censor & Associates Reporting and Transcription, Inc. Page 11 1 objections. Check your rules. 2 MR. LEOPOLD: Excuse me. For the record, 3 Counsel asked me a question. I'll state the 4 answer on the record. He asked me the question am 5 I going to be answering that way throughout the 6 deposition. So long as there's improper 7 foundation and predicate asked by the attorney, I 8 will protect my client and I make the record where 9 appropriate. If counsel wishes to ask an 10 appropriate worded question with the proper 11 foundation and predicate, I will certainly allow 12 the client to answer the question. 13 MR. GOLDBERGER: Why don't you just state 14 attorney/client privilege and just be done with 15 it? 16 MR. LEOPOLD: I want the record to be 17 clear. 18 MR. TEIN: You want to waste time is what 19 you want to do. 20 You were supposed to be here this morning 21 and you totally broke the deal, the agreement that 22 you had with us if your hearing got cancelled. 23 But let's move on and maybe you'll stop 24 obstructing this deposition. 25 MR. LEOPOLD: I think the record is very Ph. 561.682.0905 - Fax. 561.682.1771 1655 Palm Beach Lakes Blvd., Suite 500 - West Palm Beach, FL 33401 07/26/17 Page 2686 Public Records Request No.: 17-295 DOJ-OGR-00032999",
  "text_blocks": [
    {
      "type": "printed",
      "content": "Censor & Associates Reporting and Transcription, Inc.",
      "position": "header"
    },
    {
      "type": "printed",
      "content": "Page 11",
      "position": "header"
    },
    {
      "type": "printed",
      "content": "1 objections. Check your rules. 2 MR. LEOPOLD: Excuse me. For the record, 3 Counsel asked me a question. I'll state the 4 answer on the record. He asked me the question am 5 I going to be answering that way throughout the 6 deposition. So long as there's improper 7 foundation and predicate asked by the attorney, I 8 will protect my client and I make the record where 9 appropriate. If counsel wishes to ask an 10 appropriate worded question with the proper 11 foundation and predicate, I will certainly allow 12 the client to answer the question. 13 MR. GOLDBERGER: Why don't you just state 14 attorney/client privilege and just be done with 15 it? 16 MR. LEOPOLD: I want the record to be 17 clear. 18 MR. TEIN: You want to waste time is what 19 you want to do. 20 You were supposed to be here this morning 21 and you totally broke the deal, the agreement that 22 you had with us if your hearing got cancelled. 23 But let's move on and maybe you'll stop 24 obstructing this deposition. 25 MR. LEOPOLD: I think the record is very",
      "position": "main"
    },
    {
      "type": "printed",
      "content": "Ph. 561.682.0905 - Fax. 561.682.1771 1655 Palm Beach Lakes Blvd., Suite 500 - West Palm Beach, FL 33401",
      "position": "footer"
    },
    {
      "type": "printed",
      "content": "07/26/17 Page 2686 Public Records Request No.: 17-295 DOJ-OGR-00032999",
      "position": "footer"
    }
  ],
  "entities": {
    "people": [
      "MR. LEOPOLD",
      "MR. GOLDBERGER",
      "MR. TEIN"
    ],
    "organizations": [
      "Censor & Associates Reporting and Transcription, Inc."
    ],
    "locations": [
      "West Palm Beach, FL"
    ],
    "dates": [
      "07/26/17"
    ],
    "reference_numbers": [
      "17-295",
      "DOJ-OGR-00032999"
    ]
  },
  "additional_notes": "The document appears to be a deposition transcript with some tension between the attorneys. The quality is clear, and there are no visible redactions or damage."
}