{
  "document_metadata": {
    "page_number": "4 of 6",
    "document_number": "DOJ-OGR-00031747",
    "date": "07/26/17",
    "document_type": "Myspace blog printout",
    "has_handwriting": false,
    "has_stamps": false
  },
  "full_text": "blog.myspace.com/sublimehottie Page 4 of 6 Current mood: pissed off I forgot to let everyone know I quit my job at Victoria's Secret. They said they suspected me of \"causing losses to their company.\" -Which by the way is bullshit! I was 'by the book' on EVERYTHING!!!!!!! I got so fed up in that office that I handed the Loss Prevention lady back my keys and walked out. GO ME! STICKIN' IT TO THE MAN! I already have another job if I want it, and it's so much more money$$$$$. I'm going to be making more money than my old bosses at VS. Success is definately the sweetest revenge. ASSHOLES!!!!!! 10:01 AM - 0 Comments - 0 Kudos - Add Comment Slightly Stoopid, BOH?!? Current mood: okay I SAW SLIGHTLY STOOPID LAST NIGHT!!!!!!!!!!!!!!!!!!!!! IT WAS DA SHIT!!!!!!!! BOH! (credit to Will for the use of 'BOH!') because if I didn't give credit he'd say I copied him.) BOH! THE SHOW WAS AWESOME! Pictures will be coming soon. Stay tuned,..... BOH! Currently watching: Dora the Explorer - Dora's Ultimate Adventure Collection Release date: By 26 October, 2004 9:59 AM - 0 Comments - 0 Kudos - Add Comment Sunday, November 06, 2005 nole girlz do it better Current mood: excited I'm going to visit for the next three days!!!! as most of u know, I will attending the beginning in Jan. 2006. i'm going to have so much fun while i'm up there!!!!!!! it's gonna be great getting a taste of college life! Currently watching: 07/26/17 Page 26 of 124 Public Records Request No.: 17-295 http://blog.myspace.com/index.cfm?fuseaction=blog.ListAll&friendID=20425696&MyToken=01ef0dd2-cc14-4480-a758-430ff... 2/20/2006 DOJ-OGR-00031747",
  "text_blocks": [
    {
      "type": "printed",
      "content": "blog.myspace.com/sublimehottie",
      "position": "header"
    },
    {
      "type": "printed",
      "content": "Page 4 of 6",
      "position": "header"
    },
    {
      "type": "printed",
      "content": "Current mood: pissed off",
      "position": "top"
    },
    {
      "type": "printed",
      "content": "I forgot to let everyone know I quit my job at Victoria's Secret. They said they suspected me of \"causing losses to their company.\" -Which by the way is bullshit! I was 'by the book' on EVERYTHING!!!!!!! I got so fed up in that office that I handed the Loss Prevention lady back my keys and walked out. GO ME! STICKIN' IT TO THE MAN! I already have another job if I want it, and it's so much more money$$$$$. I'm going to be making more money than my old bosses at VS. Success is definately the sweetest revenge. ASSHOLES!!!!!!",
      "position": "top"
    },
    {
      "type": "printed",
      "content": "10:01 AM - 0 Comments - 0 Kudos - Add Comment",
      "position": "top"
    },
    {
      "type": "printed",
      "content": "Slightly Stoopid, BOH?!? Current mood: okay",
      "position": "middle"
    },
    {
      "type": "printed",
      "content": "I SAW SLIGHTLY STOOPID LAST NIGHT!!!!!!!!!!!!!!!!!!!!! IT WAS DA SHIT!!!!!!!! BOH! (credit to Will for the use of 'BOH!') because if I didn't give credit he'd say I copied him.) BOH! THE SHOW WAS AWESOME! Pictures will be coming soon. Stay tuned,..... BOH!",
      "position": "middle"
    },
    {
      "type": "printed",
      "content": "Currently watching: Dora the Explorer - Dora's Ultimate Adventure Collection Release date: By 26 October, 2004",
      "position": "middle"
    },
    {
      "type": "printed",
      "content": "9:59 AM - 0 Comments - 0 Kudos - Add Comment",
      "position": "middle"
    },
    {
      "type": "printed",
      "content": "Sunday, November 06, 2005",
      "position": "middle"
    },
    {
      "type": "printed",
      "content": "nole girlz do it better Current mood: excited",
      "position": "middle"
    },
    {
      "type": "printed",
      "content": "I'm going to visit for the next three days!!!! as most of u know, I will attending the beginning in Jan. 2006. i'm going to have so much fun while i'm up there!!!!!!! it's gonna be great getting a taste of college life!",
      "position": "middle"
    },
    {
      "type": "printed",
      "content": "Currently watching:",
      "position": "middle"
    },
    {
      "type": "printed",
      "content": "07/26/17",
      "position": "footer"
    },
    {
      "type": "printed",
      "content": "Page 26 of 124",
      "position": "footer"
    },
    {
      "type": "printed",
      "content": "Public Records Request No.: 17-295",
      "position": "footer"
    },
    {
      "type": "printed",
      "content": "http://blog.myspace.com/index.cfm?fuseaction=blog.ListAll&friendID=20425696&MyToken=01ef0dd2-cc14-4480-a758-430ff... 2/20/2006",
      "position": "footer"
    },
    {
      "type": "printed",
      "content": "DOJ-OGR-00031747",
      "position": "footer"
    }
  ],
  "entities": {
    "people": [
      "Will"
    ],
    "organizations": [
      "Victoria's Secret"
    ],
    "locations": [],
    "dates": [
      "26 October, 2004",
      "November 06, 2005",
      "Jan. 2006",
      "07/26/17",
      "2/20/2006"
    ],
    "reference_numbers": [
      "17-295",
      "DOJ-OGR-00031747"
    ]
  },
  "additional_notes": "This document appears to be a printout of a Myspace blog. The content includes personal updates and reflections from the blog owner. The document quality is clear and legible."
}