{
  "document_metadata": {
    "page_number": "76",
    "document_number": "17-295",
    "date": "07/26/17",
    "document_type": "Public Records Request",
    "has_handwriting": true,
    "has_stamps": false
  },
  "full_text": "IMPORTANT MESSAGE FOR Mr. J.E DATE 12/13/04 TIME 9:36 P.M. M OF PHONE/MOBILE (561) TELEPHONED PLEASE CALL CAME TO SEE YOU WILL CALL AGAIN WANTS TO SEE YOU RUSH RETURNED YOUR CALL SPECIAL ATTENTION MESSAGE Just tell him that I called SIGNED IMPORTANT MESSAGE FOR DATE TIME M OF PHONE/MOBILE TELEPHONED PLEASE CALL CAME TO SEE YOU WILL CALL AGAIN WANTS TO SEE YOU RUSH RETURNED YOUR CALL SPECIAL ATTENTION MESSAGE He'll call 561 208 0782 SIGNED IMPORTANT MESSAGE FOR DATE TIME M OF PHONE/MOBILE TELEPHONED PLEASE CALL CAME TO SEE YOU WILL CALL AGAIN WANTS TO SEE YOU RUSH RETURNED YOUR CALL SPECIAL ATTENTION MESSAGE SIGNED 07/26/17 IMPORTANT MESSAGE FOR Mr. J.F DATE 12/16/04 TIME 2:23 P.M. M Drzen OF PHONE/MOBILE (561) 379-5447 TELEPHONED PLEASE CALL CAME TO SEE YOU WILL CALL AGAIN WANTS TO SEE YOU RUSH RETURNED YOUR CALL SPECIAL ATTENTION MESSAGE SIGNED Public Records Request No.: 17-295 DOJ-OGR-00032015",
  "text_blocks": [
    {
      "type": "printed",
      "content": "IMPORTANT MESSAGE",
      "position": "header"
    },
    {
      "type": "handwritten",
      "content": "FOR Mr. J.E DATE 12/13/04 TIME 9:36 P.M. M OF PHONE/MOBILE (561) Just tell him that I called",
      "position": "top"
    },
    {
      "type": "handwritten",
      "content": "FOR DATE TIME M OF PHONE/MOBILE TELEPHONED PLEASE CALL CAME TO SEE YOU WILL CALL AGAIN WANTS TO SEE YOU RUSH RETURNED YOUR CALL SPECIAL ATTENTION MESSAGE He'll call 561 208 0782",
      "position": "top"
    },
    {
      "type": "handwritten",
      "content": "FOR DATE TIME M OF PHONE/MOBILE TELEPHONED PLEASE CALL CAME TO SEE YOU WILL CALL AGAIN WANTS TO SEE YOU RUSH RETURNED YOUR CALL SPECIAL ATTENTION MESSAGE",
      "position": "middle"
    },
    {
      "type": "handwritten",
      "content": "FOR Mr. J.F DATE 12/16/04 TIME 2:23 P.M. M Drzen OF PHONE/MOBILE (561) 379-5447",
      "position": "bottom"
    },
    {
      "type": "printed",
      "content": "Public Records Request No.: 17-295 DOJ-OGR-00032015",
      "position": "footer"
    }
  ],
  "entities": {
    "people": [
      "Mr. J.E",
      "Mr. J.F",
      "Drzen"
    ],
    "organizations": [],
    "locations": [],
    "dates": [
      "12/13/04",
      "12/16/04",
      "07/26/17"
    ],
    "reference_numbers": [
      "17-295",
      "DOJ-OGR-00032015",
      "(561)",
      "(561) 379-5447",
      "561 208 0782"
    ]
  },
  "additional_notes": "The document appears to be a scanned copy of a public records request with four 'IMPORTANT MESSAGE' forms. The forms contain handwritten notes with phone numbers and messages. The document quality is good, with some minor blurriness. There are no visible redactions or damage."
}