{
  "document_metadata": {
    "page_number": "2 of 3",
    "document_number": "06049528",
    "date": "March 31, 2006",
    "document_type": "Offense Report",
    "has_handwriting": false,
    "has_stamps": false
  },
  "full_text": "OQS - Viewing Case Number 06049528 Page 2 of 3 PALM BEACH COUNTY SHERIFF'S OFFICE OFFENSE REPORT CASE NO 06049528 DISPOSITION: CLEARED BY REPORT NUMBER: 1 FLORIDA VICTIM ? Y WEATHER: CLEAR WITNESS TO CRIME KNOWN ? Y CAN VICTIM I.D. SUSPECT ? Y WILL VICTIM PROSECUTE ? Y IS M.O. SIGNIFICANT ? Y LAYENT'S LIFTED ? Y TAG NUMBER KNOWN ? N ARRESTING OFFICER: D/S SHAFFER/ID 6376 ON MARCH 31, 2006 AT APPROXIMATELY 0925 HOURS, I RESPONDED TO 16745 WEST DOWNERS DRIVE, IN LOXAHATCHEE, IN REFERENCE TO A MISSING PERSON INVESTIGATION. I WAS ADVISED BY DISPATCH THAT SHERIFF'S OFFICE IN ORDER TO REPORT THAT HIS DAUGHTER, HAD CONTACTED THE RESIDENCE ON FOOT IN AN UNKNOWN DIRECTION OF TRAVEL DURING A VERBAL ARGUMENT. UPON MY ARRIVAL TO THE RESIDENCE, REPORTED THAT HAD RETURNED AND WAS INSIDE THE RESIDENCE PACKING HER CLOTHING IN ORDER TO MOVE OUT. THEY STATED THEY HAD ABOUT 4.5 YEARS ON TODAY'S DATE, THEIR DAUGHTER, HAD STUCK BACK INTO THE RESIDENCE AFTER BEING CUT ALL NIGHT BY A YOUNG DRUG DEALER, AND UPON THEIR ARRIVAL WERE UNDER THE INFLUENCE OF A NARCOTIC AS THEY COULD BARLY STAND UP, THEIR EYES WERE BLOODSHOT, AND THEIR PUPILS WERE DILATED. HOWEVER, A SHORT TIME LATER, THE SCHOOL POLICE OFFICER, CALLED AND IN ORDER TO STICK UF BECAUSE SHE WAS BELIEVED TO BE UNDER THE INFLUENCE OF NARCOTICS. DURING THEIR DRIVE FROM THE SCHOOL BACK TO THEIR RESIDENCE, STATED THAT CONTINUOUSLY SAID HOW MUCH SHE HATED HIM AND WISHED THAT HE WOULD DIE. UPON ENTERING THE RESIDENCE, SHE CONTINUED SCREAMING PROFANITIES AT HIM AND STATED THAT SHE WOULD RUN AWAY. STATED THAT HE THEN SHUT HER BEDROOM DOOR AND SAID YOU CAN MAKE A CHOICE, STAY HERE OR LEAVE THE HOUSE. THEN STATED AT THIS TIME, BEGAN TO SWING HER ARMS AND FIST WILDLY AT HIM, STRIKING HIM SEVERAL TIMES IN THE LEFT AND RIGHT FOREARM AND IN THE CHEST, SCREAMING THAT SHE HATED HIM AND WANTED HIM TO DIE. printed by Employee Id #: 4561 on April 05, 2006 04 http://oqs.pbso.org/index.cfm?fa=dspCase&fromrec=1&srhta=d67d41bd0daee93-6BB4D0t... 4/5/2006 07/26/17 Page 78 of 111 Public Records Request No.: 17-295 DOJ-OGR-00031488",
  "text_blocks": [
    {
      "type": "printed",
      "content": "OQS - Viewing Case Number 06049528 Page 2 of 3",
      "position": "header"
    },
    {
      "type": "printed",
      "content": "PALM BEACH COUNTY SHERIFF'S OFFICE OFFENSE REPORT CASE NO 06049528 DISPOSITION: CLEARED BY",
      "position": "header"
    },
    {
      "type": "printed",
      "content": "REPORT NUMBER: 1 FLORIDA VICTIM ? Y WEATHER: CLEAR WITNESS TO CRIME KNOWN ? Y CAN VICTIM I.D. SUSPECT ? Y WILL VICTIM PROSECUTE ? Y IS M.O. SIGNIFICANT ? Y LAYENT'S LIFTED ? Y TAG NUMBER KNOWN ? N ARRESTING OFFICER: D/S SHAFFER/ID 6376",
      "position": "body"
    },
    {
      "type": "printed",
      "content": "ON MARCH 31, 2006 AT APPROXIMATELY 0925 HOURS, I RESPONDED TO 16745 WEST DOWNERS DRIVE, IN LOXAHATCHEE, IN REFERENCE TO A MISSING PERSON INVESTIGATION.",
      "position": "body"
    },
    {
      "type": "printed",
      "content": "I WAS ADVISED BY DISPATCH THAT SHERIFF'S OFFICE IN ORDER TO REPORT THAT HIS DAUGHTER, HAD CONTACTED THE RESIDENCE ON FOOT IN AN UNKNOWN DIRECTION OF TRAVEL DURING A VERBAL ARGUMENT.",
      "position": "body"
    },
    {
      "type": "printed",
      "content": "UPON MY ARRIVAL TO THE RESIDENCE, REPORTED THAT HAD RETURNED AND WAS INSIDE THE RESIDENCE PACKING HER CLOTHING IN ORDER TO MOVE OUT.",
      "position": "body"
    },
    {
      "type": "printed",
      "content": "THEY STATED THEY HAD ABOUT 4.5 YEARS ON TODAY'S DATE, THEIR DAUGHTER, HAD STUCK BACK INTO THE RESIDENCE AFTER BEING CUT ALL NIGHT BY A YOUNG DRUG DEALER, AND UPON THEIR ARRIVAL WERE UNDER THE INFLUENCE OF A NARCOTIC AS THEY COULD BARLY STAND UP, THEIR EYES WERE BLOODSHOT, AND THEIR PUPILS WERE DILATED.",
      "position": "body"
    },
    {
      "type": "printed",
      "content": "HOWEVER, A SHORT TIME LATER, THE SCHOOL POLICE OFFICER, CALLED AND IN ORDER TO STICK UF BECAUSE SHE WAS BELIEVED TO BE UNDER THE INFLUENCE OF NARCOTICS.",
      "position": "body"
    },
    {
      "type": "printed",
      "content": "DURING THEIR DRIVE FROM THE SCHOOL BACK TO THEIR RESIDENCE, STATED THAT CONTINUOUSLY SAID HOW MUCH SHE HATED HIM AND WISHED THAT HE WOULD DIE.",
      "position": "body"
    },
    {
      "type": "printed",
      "content": "UPON ENTERING THE RESIDENCE, SHE CONTINUED SCREAMING PROFANITIES AT HIM AND STATED THAT SHE WOULD RUN AWAY.",
      "position": "body"
    },
    {
      "type": "printed",
      "content": "STATED THAT HE THEN SHUT HER BEDROOM DOOR AND SAID YOU CAN MAKE A CHOICE, STAY HERE OR LEAVE THE HOUSE.",
      "position": "body"
    },
    {
      "type": "printed",
      "content": "THEN STATED AT THIS TIME, BEGAN TO SWING HER ARMS AND FIST WILDLY AT HIM, STRIKING HIM SEVERAL TIMES IN THE LEFT AND RIGHT FOREARM AND IN THE CHEST, SCREAMING THAT SHE HATED HIM AND WANTED HIM TO DIE.",
      "position": "body"
    },
    {
      "type": "printed",
      "content": "printed by Employee Id #: 4561 on April 05, 2006 04",
      "position": "footer"
    },
    {
      "type": "printed",
      "content": "http://oqs.pbso.org/index.cfm?fa=dspCase&fromrec=1&srhta=d67d41bd0daee93-6BB4D0t... 4/5/2006",
      "position": "footer"
    },
    {
      "type": "printed",
      "content": "07/26/17 Page 78 of 111 Public Records Request No.: 17-295",
      "position": "footer"
    },
    {
      "type": "printed",
      "content": "DOJ-OGR-00031488",
      "position": "footer"
    }
  ],
  "entities": {
    "people": [
      "D/S SHAFFER"
    ],
    "organizations": [
      "PALM BEACH COUNTY SHERIFF'S OFFICE"
    ],
    "locations": [
      "LOXAHATCHEE",
      "16745 WEST DOWNERS DRIVE"
    ],
    "dates": [
      "March 31, 2006",
      "April 05, 2006",
      "07/26/17",
      "4/5/2006"
    ],
    "reference_numbers": [
      "06049528",
      "17-295",
      "DOJ-OGR-00031488",
      "4561",
      "6376"
    ]
  },
  "additional_notes": "The document appears to be a police report with some minor formatting issues due to the quality of the scan. The text is mostly clear and legible."
}