{
  "document_metadata": {
    "page_number": "11",
    "document_number": "1-05-000368",
    "date": "2/17/06",
    "document_type": "Incident Report",
    "has_handwriting": false,
    "has_stamps": false
  },
  "full_text": "Date: 2/17/06 Time: 11:36:35 PALM BEACH POLICE DEPARTMENT Page: 11 Incident Report Program: CMS301L Case No. . . . : 1-05-000368 (Continued) Weight . . . . . . : 0 Person Type . . . : OTHER PERSON Other Phone Nbr: ********* O T H E R P E R S O N I N F O R M A T I O N - # 9 ********* Case Number . : 1-05-000368 Last Name . . . : Street Number . : City . . . . . . : Birth Date/Age : Employer? . . . : Occupation . . : Oper Lic No. . : Home Phone No. : 561/000-0000 Race . . . . . : White Sex . . . . . : Female Height . . . . : 0 Weight . . . . : 0 Person Type . . : OTHER PERSON Other Phone Nbr: 561/000-0000 ********* N A R R A T I V E # 1 ********* Original Report LO Reported By: PAGAN, MICHELE D. 9/20/05 Entered By.: OREGERO, LAURA D. 9/20/05 On 03/14/2005, I received a call from a woman who did not wish to identify herself. (Later identified as ) She stated that her fourteen year old step daughter (later identified as ) possibly may have been molested in Palm Beach by a wealthy man. According to , she learned of the possible molestation by a third party. She explained that she had received a call from the mother of her stepdaughter's friend. The mother claimed to have overheard a conversation between her daughter and a male friend; they were talking about . The conversation was about how  had met with a 45-year-old man and had sex with him and was paid for it. I advised  that I would like to meet with her to obtain a more detailed statement and facts.  stated she did not know what to do and had to discuss the matter with her husband. At this point  did not provide me with a call back number or any other information. She stated that she would contact me once she had spoken with her husband and  mother. On 03/14/2005 received a call from Mr. & Mrs.  They stated it was okay to speak to their daughter  via cell phone . Her mother  had been made aware of the case. They agreed to meet me at the police department later this date. (561) On 03/14/2005, Mr.  accompanied by his wife  came to the Palm Beach Police Department were they advised me that they believe their fourteen year old daughter may have had some type of sexual relationship with an older male who resided in Palm Beach. Neither knew the suspect's name or address. Both stated that their daughter did not talk to them about the incident, nor would she admit to it. identified his daughter as  resides with her biological mother at , , , (561) 07/26/17 Page 1983 Public Records Request No.: 17-295 DOJ-OGR-00032296",
  "text_blocks": [
    {
      "type": "printed",
      "content": "Date: 2/17/06 Time: 11:36:35 PALM BEACH POLICE DEPARTMENT Page: 11 Incident Report Program: CMS301L",
      "position": "header"
    },
    {
      "type": "printed",
      "content": "Case No. . . . : 1-05-000368 (Continued) Weight . . . . . . : 0 Person Type . . . : OTHER PERSON Other Phone Nbr:",
      "position": "top"
    },
    {
      "type": "printed",
      "content": "********* O T H E R P E R S O N I N F O R M A T I O N - # 9 *********",
      "position": "top"
    },
    {
      "type": "printed",
      "content": "Case Number . : 1-05-000368 Last Name . . . : Street Number . : City . . . . . . : Birth Date/Age : Employer? . . . : Occupation . . : Oper Lic No. . : Home Phone No. : 561/000-0000 Race . . . . . : White Sex . . . . . : Female Height . . . . : 0 Weight . . . . : 0 Person Type . . : OTHER PERSON Other Phone Nbr: 561/000-0000",
      "position": "middle"
    },
    {
      "type": "printed",
      "content": "********* N A R R A T I V E # 1 ********* Original Report LO Reported By: PAGAN, MICHELE D. 9/20/05 Entered By.: OREGERO, LAURA D. 9/20/05",
      "position": "middle"
    },
    {
      "type": "handwritten",
      "content": "On 03/14/2005, I received a call from a woman who did not wish to identify herself. (Later identified as ) She stated that her fourteen year old step daughter (later identified as ) possibly may have been molested in Palm Beach by a wealthy man. According to , she learned of the possible molestation by a third party. She explained that she had received a call from the mother of her stepdaughter's friend. The mother claimed to have overheard a conversation between her daughter and a male friend; they were talking about . The conversation was about how  had met with a 45-year-old man and had sex with him and was paid for it. I advised  that I would like to meet with her to obtain a more detailed statement and facts.  stated she did not know what to do and had to discuss the matter with her husband. At this point  did not provide me with a call back number or any other information. She stated that she would contact me once she had spoken with her husband and  mother.",
      "position": "middle"
    },
    {
      "type": "handwritten",
      "content": "On 03/14/2005 received a call from Mr. & Mrs.  They stated it was okay to speak to their daughter  via cell phone . Her mother  had been made aware of the case. They agreed to meet me at the police department later this date. (561)",
      "position": "middle"
    },
    {
      "type": "handwritten",
      "content": "On 03/14/2005, Mr.  accompanied by his wife  came to the Palm Beach Police Department were they advised me that they believe their fourteen year old daughter may have had some type of sexual relationship with an older male who resided in Palm Beach. Neither knew the suspect's name or address. Both stated that their daughter did not talk to them about the incident, nor would she admit to it.",
      "position": "middle"
    },
    {
      "type": "handwritten",
      "content": "identified his daughter as  resides with her biological mother at , , , (561)",
      "position": "bottom"
    },
    {
      "type": "printed",
      "content": "07/26/17 Page 1983 Public Records Request No.: 17-295 DOJ-OGR-00032296",
      "position": "footer"
    }
  ],
  "entities": {
    "people": [
      "PAGAN, MICHELE D.",
      "OREGERO, LAURA D."
    ],
    "organizations": [
      "PALM BEACH POLICE DEPARTMENT"
    ],
    "locations": [
      "Palm Beach"
    ],
    "dates": [
      "2/17/06",
      "03/14/2005",
      "9/20/05",
      "07/26/17"
    ],
    "reference_numbers": [
      "1-05-000368",
      "17-295",
      "DOJ-OGR-00032296"
    ]
  },
  "additional_notes": "The document contains multiple redactions, likely for privacy reasons. The narrative sections are handwritten, while the rest of the document appears to be printed. The document is a police incident report."
}