{
  "document_metadata": {
    "page_number": "43",
    "document_number": "17-295",
    "date": "October 11, 2005",
    "document_type": "Defense Transcript",
    "has_handwriting": false,
    "has_stamps": false
  },
  "full_text": "1 //I don't know who Kellen is, I have no idea, I didn't bother to ask, it was none of my business. 4 FRIEND: Maybe that's her last name. 6 DETECTIVE: Oh. Well I don't have anything further, um would you like to add anything else to the statement? 8 9 No. 11 DETECTIVE 2: What do you want to see happening to Jeffrey? 13 I don't think anything is going to happen to him. 15 DETECTIVE 2: No that's not what I asked you. What do you think should happen to Jeffrey for what he did to you? 18 He, I don't even care if he goes to jail, I just don't want this to happen to anybody else. Whatever that means to you guys. 20 DETECTIVE: And that's what we're trying to stop here. 23 DETECTIVE 2: Yeah, that, it means a lot. 25 DETECTIVE: Okay, I'm gonna go ahead and conclude the statement. The time by my watch is 5:40 p.m. 26 Defense Transcript 07/26/17 43 October 11, 2005 PBPD & Page 2382 Public Records Request No.: 17-295 DOJ-OGR-00032695",
  "text_blocks": [
    {
      "type": "printed",
      "content": "1 //I don't know who Kellen is, I have no idea, I didn't bother to ask, it was none of my business. 4 FRIEND: Maybe that's her last name. 6 DETECTIVE: Oh. Well I don't have anything further, um would you like to add anything else to the statement? 8 9 No. 11 DETECTIVE 2: What do you want to see happening to Jeffrey? 13 I don't think anything is going to happen to him. 15 DETECTIVE 2: No that's not what I asked you. What do you think should happen to Jeffrey for what he did to you? 18 He, I don't even care if he goes to jail, I just don't want this to happen to anybody else. Whatever that means to you guys. 20 DETECTIVE: And that's what we're trying to stop here. 23 DETECTIVE 2: Yeah, that, it means a lot. 25 DETECTIVE: Okay, I'm gonna go ahead and conclude the statement. The time by my watch is 5:40 p.m. 26",
      "position": "top"
    },
    {
      "type": "printed",
      "content": "Defense Transcript 07/26/17 43 October 11, 2005 PBPD & Page 2382 Public Records Request No.: 17-295",
      "position": "bottom"
    },
    {
      "type": "printed",
      "content": "DOJ-OGR-00032695",
      "position": "footer"
    }
  ],
  "entities": {
    "people": [
      "Kellen",
      "Jeffrey"
    ],
    "organizations": [
      "PBPD",
      "DOJ"
    ],
    "locations": [],
    "dates": [
      "October 11, 2005",
      "07/26/17"
    ],
    "reference_numbers": [
      "17-295",
      "DOJ-OGR-00032695"
    ]
  },
  "additional_notes": "The document appears to be a transcript of an interview or interrogation. Some names have been redacted."
}