{
  "document_metadata": {
    "page_number": "2/4",
    "document_number": "17-295",
    "date": "March 20, 2008",
    "document_type": "Letter",
    "has_handwriting": true,
    "has_stamps": false
  },
  "full_text": "305-9312200 Herman &Mermelstein,P 11:43:11 a.m. 20-03-2008 2/4 HERMAN & MERMELSTEIN PA ATTORNEYS AT LAW Jeffrey M. Herman Tel 305.931.2200 Fax 305.931.0877 jherman@hermanlaw.com 18205 Biscayne Blvd. Suite 2218 Miami, Florida 33160 www.hermanlaw.com March 20, 2008 Via Facsimile and U.S. Mail Jack A. Goldberger, Esq. 250 Australian Avenue South Suite 1400 West Palm Beach, FL 33401 Re: State of Florida v. Jeffrey E. Epstein Case No.: 2006CF009454AXX Dear Mr. Goldberger: Please be advised that we represent ________ in all matters pertaining to Jeffrey Epstein. Please direct all future correspondence relating to Ms. _____ to our office. We will accept subpoenas on her behalf. I understand that you have scheduled Ms. ____ for deposition on Monday, March 24, 2008. We would like to reschedule the deposition to a date convenient for Ms. ~ and myself. In addition, as we will be filing a civil lawsuit, we would like to conduct a single deposition to be used for both the criminal and the civil matters. Please let us know if you will agree to this or if we should seek court approval for same. Of course, we understand that the State Attorney's Office will need to agree to this as well, and we have not yet contacted them for approval. Sincerely, Jeffrey M. Herman JMH/lr cc: Lanna Leigh Belohlavek, Asst. State Attorney 07/26/17 Page 11 of 94 Public Records Request No.: 17-295 DOJ-OGR-00031856",
  "text_blocks": [
    {
      "type": "printed",
      "content": "HERMAN & MERMELSTEIN PA ATTORNEYS AT LAW",
      "position": "header"
    },
    {
      "type": "printed",
      "content": "Jeffrey M. Herman Tel 305.931.2200 Fax 305.931.0877 jherman@hermanlaw.com 18205 Biscayne Blvd. Suite 2218 Miami, Florida 33160 www.hermanlaw.com",
      "position": "header"
    },
    {
      "type": "printed",
      "content": "March 20, 2008",
      "position": "top"
    },
    {
      "type": "printed",
      "content": "Via Facsimile and U.S. Mail Jack A. Goldberger, Esq. 250 Australian Avenue South Suite 1400 West Palm Beach, FL 33401",
      "position": "top"
    },
    {
      "type": "printed",
      "content": "Re: State of Florida v. Jeffrey E. Epstein Case No.: 2006CF009454AXX",
      "position": "top"
    },
    {
      "type": "printed",
      "content": "Dear Mr. Goldberger:",
      "position": "top"
    },
    {
      "type": "printed",
      "content": "Please be advised that we represent ________ in all matters pertaining to Jeffrey Epstein. Please direct all future correspondence relating to Ms. _____ to our office. We will accept subpoenas on her behalf. I understand that you have scheduled Ms. ____ for deposition on Monday, March 24, 2008. We would like to reschedule the deposition to a date convenient for Ms. ~ and myself. In addition, as we will be filing a civil lawsuit, we would like to conduct a single deposition to be used for both the criminal and the civil matters. Please let us know if you will agree to this or if we should seek court approval for same. Of course, we understand that the State Attorney's Office will need to agree to this as well, and we have not yet contacted them for approval.",
      "position": "middle"
    },
    {
      "type": "handwritten",
      "content": "Sincerely, Jeffrey M. Herman",
      "position": "middle"
    },
    {
      "type": "printed",
      "content": "JMH/lr cc: Lanna Leigh Belohlavek, Asst. State Attorney",
      "position": "bottom"
    },
    {
      "type": "printed",
      "content": "07/26/17 Page 11 of 94 Public Records Request No.: 17-295 DOJ-OGR-00031856",
      "position": "footer"
    }
  ],
  "entities": {
    "people": [
      "Jeffrey M. Herman",
      "Jack A. Goldberger",
      "Jeffrey E. Epstein",
      "Lanna Leigh Belohlavek"
    ],
    "organizations": [
      "Herman & Mermelstein PA",
      "State Attorney's Office"
    ],
    "locations": [
      "Miami",
      "Florida",
      "West Palm Beach"
    ],
    "dates": [
      "March 20, 2008",
      "March 24, 2008",
      "07/26/17"
    ],
    "reference_numbers": [
      "2006CF009454AXX",
      "17-295",
      "DOJ-OGR-00031856"
    ]
  },
  "additional_notes": "The document is a letter from Jeffrey M. Herman to Jack A. Goldberger regarding the case State of Florida v. Jeffrey E. Epstein. The letter is dated March 20, 2008, and is on the letterhead of Herman & Mermelstein PA. The document has been redacted in several places to remove names. The letter discusses the deposition of a witness and the potential for a civil lawsuit. The document also includes a handwritten signature from Jeffrey M. Herman."
}