{
  "document_metadata": {
    "page_number": "10",
    "document_number": "17-295",
    "date": "07/26/17",
    "document_type": "Public Records Request",
    "has_handwriting": false,
    "has_stamps": false
  },
  "full_text": "www.myspace.com/sublimehartie Page 10 of 13 www.gettheammo.com Blizunts & Bizongs Kelli 9/29/2005 7:32 PM I haven't seen you in like a year. I h everything's going good with you, ar you're meeting lots of cool people in place. :) SKE3M 9/25/2005 2:30 PM hey grl...whats the deal..when are w burn one?? wb...we need to chill sometime...and get blizzy!!! wb...... I Heart Garrett Stein 9/22/2005 9:51 PM I love you!!! katie 9/21/2005 4:38 AM where ya been, woadie? I Only Want What I Already Have 9/20/2005 1:04 PM yo alex whats upp??? 07/26/17 Page 7 of 124 Public Records Request No.: 17-295 http://profile.myspace.com/index.cfm?fuseaction=user.viewprofile&friendID=20425696 2/14/2006 DOJ-OGR-00031728",
  "text_blocks": [
    {
      "type": "printed",
      "content": "www.myspace.com/sublimehartie",
      "position": "header"
    },
    {
      "type": "printed",
      "content": "Page 10 of 13",
      "position": "header"
    },
    {
      "type": "printed",
      "content": "www.gettheammo.com Blizunts & Bizongs",
      "position": "top"
    },
    {
      "type": "printed",
      "content": "Kelli 9/29/2005 7:32 PM I haven't seen you in like a year. I h everything's going good with you, ar you're meeting lots of cool people in place. :)",
      "position": "middle"
    },
    {
      "type": "printed",
      "content": "SKE3M 9/25/2005 2:30 PM hey grl...whats the deal..when are w burn one?? wb...we need to chill sometime...and get blizzy!!! wb......",
      "position": "middle"
    },
    {
      "type": "printed",
      "content": "I Heart Garrett Stein 9/22/2005 9:51 PM I love you!!!",
      "position": "middle"
    },
    {
      "type": "printed",
      "content": "katie 9/21/2005 4:38 AM where ya been, woadie?",
      "position": "middle"
    },
    {
      "type": "printed",
      "content": "I Only Want What I Already Have 9/20/2005 1:04 PM yo alex whats upp???",
      "position": "middle"
    },
    {
      "type": "printed",
      "content": "07/26/17 Page 7 of 124 Public Records Request No.: 17-295 http://profile.myspace.com/index.cfm?fuseaction=user.viewprofile&friendID=20425696 2/14/2006 DOJ-OGR-00031728",
      "position": "footer"
    }
  ],
  "entities": {
    "people": [
      "Kelli",
      "SKE3M",
      "Garrett Stein",
      "katie",
      "alex"
    ],
    "organizations": [],
    "locations": [],
    "dates": [
      "9/29/2005",
      "9/25/2005",
      "9/22/2005",
      "9/21/2005",
      "9/20/2005",
      "07/26/17",
      "2/14/2006"
    ],
    "reference_numbers": [
      "17-295",
      "20425696",
      "DOJ-OGR-00031728"
    ]
  },
  "additional_notes": "The document appears to be a printout of a Myspace profile page with comments from friends. The page is labeled as 'Page 10 of 13' and 'Page 7 of 124', indicating it may be part of a larger document or report. The content includes informal conversations and personal messages."
}