{
  "document_metadata": {
    "page_number": "1",
    "document_number": "17-295",
    "date": "January 25, 2008",
    "document_type": "Letter",
    "has_handwriting": true,
    "has_stamps": false
  },
  "full_text": "Received: 1/25/08 8:39AM; 5616404420 --> STATE ATTY OFC; Page 1\n01/23/2008 15:06 5616404420\n\nAileen Josephs, P.A.\nAttorney at Law\n301 Clematis Street\nSuite 300\nWest Palm Beach, Florida 33401\n(561) 802-4119\nFax (561) 640-4420\nE-Mail: josephsA@aol.com\nhttp://www.ImmigrationUS.com\nhttp://www.MuniMundo.net\n\nAileen Josephs\nMember of District of Columbia\nand Florida Bars\n\nJanuary 25, 2008\n\nTO: Ms. Sanchez, Esq.\nRE: Mr. Epstein\nFrom Aileen Josephs, Esq.\n\nMs. Sanchez:\n\nWomen in our County have been watching this case with great concern. I strongly suggest that you do not attack the victim(s). If you feel your client is innocent, you can file a libel suit- of course, the truth is an absolute defense to libel, and please keep in mind that not knowing the age of a child is no defense to statutory rape or any sexual crime committed against a child.\n\nSincerely,\n\nAileen Josephs\nAileen Josephs, Esq.\n\nCc: Ms. Lana Belohavek- State Attorney's Office\nMs. La Tosha Lowe- request to place this letter in State's file\nChief of Police- Palm Beach\n\n07/26/17 Page 88 of 102 Public Records Request No.: 17-295 DOJ-OGR-00031396",
  "text_blocks": [
    {
      "type": "printed",
      "content": "Aileen Josephs, P.A.\nAttorney at Law\n301 Clematis Street\nSuite 300\nWest Palm Beach, Florida 33401\n(561) 802-4119\nFax (561) 640-4420\nE-Mail: josephsA@aol.com\nhttp://www.ImmigrationUS.com\nhttp://www.MuniMundo.net",
      "position": "header"
    },
    {
      "type": "printed",
      "content": "Aileen Josephs\nMember of District of Columbia\nand Florida Bars",
      "position": "header"
    },
    {
      "type": "printed",
      "content": "January 25, 2008",
      "position": "top"
    },
    {
      "type": "printed",
      "content": "TO: Ms. Sanchez, Esq.\nRE: Mr. Epstein\nFrom Aileen Josephs, Esq.",
      "position": "top"
    },
    {
      "type": "printed",
      "content": "Ms. Sanchez:\n\nWomen in our County have been watching this case with great concern. I strongly suggest that you do not attack the victim(s). If you feel your client is innocent, you can file a libel suit- of course, the truth is an absolute defense to libel, and please keep in mind that not knowing the age of a child is no defense to statutory rape or any sexual crime committed against a child.",
      "position": "middle"
    },
    {
      "type": "handwritten",
      "content": "Aileen Josephs",
      "position": "bottom"
    },
    {
      "type": "printed",
      "content": "Sincerely,\nAileen Josephs, Esq.",
      "position": "bottom"
    },
    {
      "type": "printed",
      "content": "Cc: Ms. Lana Belohavek- State Attorney's Office\nMs. La Tosha Lowe- request to place this letter in State's file\nChief of Police- Palm Beach",
      "position": "bottom"
    },
    {
      "type": "printed",
      "content": "07/26/17 Page 88 of 102 Public Records Request No.: 17-295 DOJ-OGR-00031396",
      "position": "footer"
    }
  ],
  "entities": {
    "people": [
      "Aileen Josephs",
      "Ms. Sanchez",
      "Mr. Epstein",
      "Ms. Lana Belohavek",
      "Ms. La Tosha Lowe"
    ],
    "organizations": [
      "State Attorney's Office",
      "Palm Beach Police Department"
    ],
    "locations": [
      "West Palm Beach",
      "Florida",
      "District of Columbia",
      "Palm Beach"
    ],
    "dates": [
      "January 25, 2008",
      "01/23/2008",
      "07/26/17"
    ],
    "reference_numbers": [
      "17-295",
      "DOJ-OGR-00031396",
      "5616404420"
    ]
  },
  "additional_notes": "The document is a letter from Aileen Josephs, Esq. to Ms. Sanchez, Esq. regarding Mr. Epstein. The letter is dated January 25, 2008, and is related to a case involving sexual crimes against a child. The document is part of a public records request (No.: 17-295) and has been stamped with a received date and time."
}