{
  "document_metadata": {
    "page_number": "47",
    "document_number": "17-295",
    "date": "07/26/17",
    "document_type": "transcript",
    "has_handwriting": false,
    "has_stamps": false
  },
  "full_text": "Censor & Associates Reporting and Transcription, Inc. Page 47 1 fashion, you may answer. 2 THE WITNESS: Okay. 3 I wouldn't know. 4 BY MR. TEIN: 5 Q. You don't know? 6 A. No. 7 MR. LEOPOLD: Objection. Foundation. 8 Attorney/client privilege. 9 BY MR. TEIN: 10 Q. And you say you don't know who Jeff Sloman is? 11 12 A. No, sir. 13 Q. Does it refresh your recollection that he's the number two prosecutor at the U.S. Attorney's Office? 14 15 A. No. 16 Q. That he's Marie Villafona's boss? 17 A. No. 18 Q. Does it refresh your memory that he's the ex-partner of Jeff Herman, the first lawyer who sued you -- sued Mr. Epstein on your behalf for fifty million dollars? 19 20 21 A. No, sir. I don't know who he is. 22 23 Q. Without telling me any conversations that you've had with your lawyers, how is it that you selected 24 25 Mr. Herman as your lawyer from the 81,000 members of the Ph. 561.682.0905 - Fax. 561.682.1771 1655 Palm Beach Lakes Blvd., Suite 500 - West Palm Beach, FL 33401 07/26/17 Page 2722 Public Records Request No.: 17-295 DOJ-OGR-00033035",
  "text_blocks": [
    {
      "type": "printed",
      "content": "Censor & Associates Reporting and Transcription, Inc.",
      "position": "header"
    },
    {
      "type": "printed",
      "content": "Page 47",
      "position": "header"
    },
    {
      "type": "printed",
      "content": "1 fashion, you may answer. 2 THE WITNESS: Okay. 3 I wouldn't know. 4 BY MR. TEIN: 5 Q. You don't know? 6 A. No. 7 MR. LEOPOLD: Objection. Foundation. 8 Attorney/client privilege. 9 BY MR. TEIN: 10 Q. And you say you don't know who Jeff Sloman is? 11 12 A. No, sir. 13 Q. Does it refresh your recollection that he's the number two prosecutor at the U.S. Attorney's Office? 14 15 A. No. 16 Q. That he's Marie Villafona's boss? 17 A. No. 18 Q. Does it refresh your memory that he's the ex-partner of Jeff Herman, the first lawyer who sued you -- sued Mr. Epstein on your behalf for fifty million dollars? 19 20 21 A. No, sir. I don't know who he is. 22 23 Q. Without telling me any conversations that you've had with your lawyers, how is it that you selected 24 25 Mr. Herman as your lawyer from the 81,000 members of the",
      "position": "main"
    },
    {
      "type": "printed",
      "content": "Ph. 561.682.0905 - Fax. 561.682.1771 1655 Palm Beach Lakes Blvd., Suite 500 - West Palm Beach, FL 33401",
      "position": "footer"
    },
    {
      "type": "printed",
      "content": "07/26/17 Page 2722 Public Records Request No.: 17-295 DOJ-OGR-00033035",
      "position": "footer"
    }
  ],
  "entities": {
    "people": [
      "Jeff Sloman",
      "Marie Villafona",
      "Jeff Herman",
      "Mr. Epstein",
      "Mr. TEIN",
      "MR. LEOPOLD"
    ],
    "organizations": [
      "Censor & Associates",
      "U.S. Attorney's Office"
    ],
    "locations": [
      "West Palm Beach",
      "FL"
    ],
    "dates": [
      "07/26/17"
    ],
    "reference_numbers": [
      "17-295",
      "DOJ-OGR-00033035"
    ]
  },
  "additional_notes": "The document appears to be a transcript of a deposition or testimony. The quality is clear, and there are no visible redactions or damage."
}