{
  "document_metadata": {
    "page_number": "16",
    "document_number": "17-295",
    "date": "07/26/17",
    "document_type": "Deposition Transcript",
    "has_handwriting": false,
    "has_stamps": false
  },
  "full_text": "Censor & Associates Reporting and Transcription, Inc. Page 16 1 no matter who it is. 2 MR. LEOPOLD: I think we're going to take a 3 break. Perhaps you might want to talk to your 4 co-counsel -- 5 MR. TEIN: I don't need to talk to him. 6 MR. LEOPOLD: But we're going to take a 7 break. 8 MR. TEIN: We're not taking a break unless 9 the witness needs a break. 10 You're obstructing this deposition, Ted. 11 MR. LEOPOLD: Come on, . . .;. 12 You all want to continue in this 13 demeanor -- 14 MR. TEIN: You're obstructing the 15 deposition. Stop making speeches. We're not 16 discussing this with you. The questions are to 17 your client. Go take your five-minute break. 18 MR. LEOPOLD: Fine. We need to make sure 19 the record's clear and clean. 20 And I want to make sure, as I've already 21 asked you -- I know that you're one of the best in 22 town -- that this audio -- this needs to be 23 preserved. Okay? 24 MR. TEIN: Go take your five-minute break, 25 Mr. Leopold, now. Ph. 561.682.0905 - Fax. 561.682.1771 1655 Palm Beach Lakes Blvd., Suite 500 - West Palm Beach, FL 33401 07/26/17 Page 2691 Public Records Request No.: 17-295 DOJ-OGR-00033004",
  "text_blocks": [
    {
      "type": "printed",
      "content": "Censor & Associates Reporting and Transcription, Inc.",
      "position": "header"
    },
    {
      "type": "printed",
      "content": "Page 16",
      "position": "header"
    },
    {
      "type": "printed",
      "content": "1 no matter who it is. 2 MR. LEOPOLD: I think we're going to take a 3 break. Perhaps you might want to talk to your 4 co-counsel -- 5 MR. TEIN: I don't need to talk to him. 6 MR. LEOPOLD: But we're going to take a 7 break. 8 MR. TEIN: We're not taking a break unless 9 the witness needs a break. 10 You're obstructing this deposition, Ted. 11 MR. LEOPOLD: Come on, . . .;. 12 You all want to continue in this 13 demeanor -- 14 MR. TEIN: You're obstructing the 15 deposition. Stop making speeches. We're not 16 discussing this with you. The questions are to 17 your client. Go take your five-minute break. 18 MR. LEOPOLD: Fine. We need to make sure 19 the record's clear and clean. 20 And I want to make sure, as I've already 21 asked you -- I know that you're one of the best in 22 town -- that this audio -- this needs to be 23 preserved. Okay? 24 MR. TEIN: Go take your five-minute break, 25 Mr. Leopold, now.",
      "position": "main"
    },
    {
      "type": "printed",
      "content": "Ph. 561.682.0905 - Fax. 561.682.1771 1655 Palm Beach Lakes Blvd., Suite 500 - West Palm Beach, FL 33401",
      "position": "footer"
    },
    {
      "type": "printed",
      "content": "07/26/17 Page 2691 Public Records Request No.: 17-295 DOJ-OGR-00033004",
      "position": "footer"
    }
  ],
  "entities": {
    "people": [
      "MR. LEOPOLD",
      "MR. TEIN",
      "Ted"
    ],
    "organizations": [
      "Censor & Associates Reporting and Transcription, Inc."
    ],
    "locations": [
      "West Palm Beach",
      "FL"
    ],
    "dates": [
      "07/26/17"
    ],
    "reference_numbers": [
      "17-295",
      "DOJ-OGR-00033004"
    ]
  },
  "additional_notes": "The document appears to be a deposition transcript with some minor formatting issues. The text is mostly clear, but there are a few instances of unclear or missing text due to the quality of the scan."
}