{
  "document_metadata": {
    "page_number": "0",
    "document_number": "06049528",
    "date": "04/06/06",
    "document_type": "Offense Report",
    "has_handwriting": false,
    "has_stamps": false
  },
  "full_text": "TODAYS DATE 04/06/06 T208 PALM BEACH COUNTY SHERIFF'S OFFICE PAGE 0 OFFENSE REPORT CASE NO. 06049528 INJURY TYPE(2): NOT APPLICABLE VICTIM RELATION: PARENT DOMESTIC VIOLENCE RELATED: YES REPORT NUMBER: 1 FLORIDA VICTIM ? N WEATHER: CLEAR WITNESS TO CRIME KNOWN ?. Y SUSPECT NAME KNOWN ?....... Y CAN VICTIM I.D. SUSPECT ? Y SUSPECT LOCATION KNOWN ?.... Y WILL VICTIM PROSECUTE ?.. Y STOLEN PROPERTY TRACEABLE ? N IS M.O. SIGNIFICANT ?.... N EVIDENCE LEFT AT SCENE ?... N WARRANTS LIFTED ?......... N SUSPECT'S VEHICLE KNOWN ?.. N TAG NUMBER KNOWN ?....... N PROPERTY DAMAGE ?.......... N ARRESTING OFFICER ....... D/S SHAFFER/ID 6376 'F1 = RETURN PF7 = NARR PF22 = PREV PF23 = NEXT 07/26/17 Page 87 of 124 Public Records Request No.: 17-295 DOJ-OGR-00031808",
  "text_blocks": [
    {
      "type": "printed",
      "content": "TODAYS DATE 04/06/06 T208 PALM BEACH COUNTY SHERIFF'S OFFICE PAGE 0 OFFENSE REPORT CASE NO. 06049528",
      "position": "header"
    },
    {
      "type": "printed",
      "content": "INJURY TYPE(2): NOT APPLICABLE VICTIM RELATION: PARENT DOMESTIC VIOLENCE RELATED: YES",
      "position": "top"
    },
    {
      "type": "printed",
      "content": "REPORT NUMBER: 1 FLORIDA VICTIM ? N WEATHER: CLEAR WITNESS TO CRIME KNOWN ?. Y CAN VICTIM I.D. SUSPECT ? Y WILL VICTIM PROSECUTE ?.. Y IS M.O. SIGNIFICANT ?.... N WARRANTS LIFTED ?......... N TAG NUMBER KNOWN ?....... N ARRESTING OFFICER ....... D/S SHAFFER/ID 6376",
      "position": "middle"
    },
    {
      "type": "printed",
      "content": "SUSPECT NAME KNOWN ?....... Y SUSPECT LOCATION KNOWN ?.... Y STOLEN PROPERTY TRACEABLE ? N EVIDENCE LEFT AT SCENE ?... N SUSPECT'S VEHICLE KNOWN ?.. N PROPERTY DAMAGE ?.......... N",
      "position": "middle"
    },
    {
      "type": "printed",
      "content": "'F1 = RETURN PF7 = NARR PF22 = PREV PF23 = NEXT",
      "position": "middle"
    },
    {
      "type": "printed",
      "content": "07/26/17 Page 87 of 124 Public Records Request No.: 17-295",
      "position": "footer"
    },
    {
      "type": "printed",
      "content": "DOJ-OGR-00031808",
      "position": "footer"
    }
  ],
  "entities": {
    "people": [
      "SHAFFER"
    ],
    "organizations": [
      "PALM BEACH COUNTY SHERIFF'S OFFICE"
    ],
    "locations": [
      "PALM BEACH COUNTY"
    ],
    "dates": [
      "04/06/06",
      "07/26/17"
    ],
    "reference_numbers": [
      "06049528",
      "17-295",
      "DOJ-OGR-00031808"
    ]
  },
  "additional_notes": "The document appears to be a scanned copy of an offense report from the Palm Beach County Sheriff's Office. The report is dated 04/06/06 and has a case number of 06049528. The document is mostly legible, but some parts may be difficult to read due to the scanning quality."
}