{
  "document_metadata": {
    "page_number": "16",
    "document_number": "1-05-000368",
    "date": "4/20/06",
    "document_type": "Incident Report",
    "has_handwriting": false,
    "has_stamps": false
  },
  "full_text": "ate: 4/20/06 'ime: 13:02:26 PALM BEACH POLICE DEPARTMENT Incident Report Page: 16 Program: CMS301L ase No. . . . : 1-05-000368 (Continued) stated she was afraid that Robson would retaliate against her or her family if she ever went to the police regarding the incident. stated that her father's vehicle was recently vandalized. admitted to telling Brian what had happened with Epstein. According to , Brian became angry and upset, punching a hole in the wall. about the incident, and guessed that it was Brian who told Sheena Nuevo and what she did with Epstein. I then talked to about truth and lying. We talked about the color sweater she was wearing. denied having sexual intercourse with Epstein. She denied touching his penis. again admitted to observing Epstein masturbate. agreed to cooperating with the police department in placing a phone call to Robson in a controlled setting. I met with Ms. Back and advised her of the families' as well as willingness to cooperate with this investigation. Copies of this interview were placed into evidence. I made contact with Jeannie Hernandez, mother of Sheena Nuevo, I advised her briefly of my investigation. She was aware of the incident and stated that she overheard a portion of a conversation that her daughter was having with a boy named Zack. Hernandez stated that it was her opinion that both girls liked Zack. Hernandez recalled hearing her daughter calling - a whore. Hernandez admitted that she did not listen to the entire conversation but did confront her daughter about it later. Sheena told her mother that had slept with an older man for money. Hernandez stated that she would not object to me speaking with her daughter. It was Hernandez s belief that everyone in the school may have known about this because of the fight that her daughter Sheena and had gotten into. I reminded Hernandez that this was an ongoing investigation and requested she not discuss the fact that I had contacted her. On 03/16/2005, PBSO Sgt. Chris Keen left a message that he was returning my call. I spoke with Keen and discussed the case with him and inquired if he had any open allegations or cases where the suspect resided in Palm Beach. Keen stated he was unaware of any. Keen offered any assistance if needed. Keen stated it was his experience that due to the age of the parties involved, it would be difficult to interview them and expect the investigation to remain confidential. Because of the time delay, there was no need for the victim to be taken to a medical facility for a physical for the purpose of obtaining evidence. There was also no need to take her to CPT as she was already in a juvenile facility, with an assigned therapist, in which coordinating a day and time to obtain a statement could be made. On 03/17/2005, I queried Jeffery Epstein on the internet and obtained 07/26/17 Page 2538 Public Records Request No.: 17-295 DOJ-OGR-00032851",
  "text_blocks": [
    {
      "type": "printed",
      "content": "ate: 4/20/06 'ime: 13:02:26 PALM BEACH POLICE DEPARTMENT Incident Report Page: 16 Program: CMS301L ase No. . . . : 1-05-000368 (Continued)",
      "position": "header"
    },
    {
      "type": "printed",
      "content": "stated she was afraid that Robson would retaliate against her or her family if she ever went to the police regarding the incident. stated that her father's vehicle was recently vandalized. admitted to telling Brian what had happened with Epstein. According to , Brian became angry and upset, punching a hole in the wall. about the incident, and guessed that it was Brian who told Sheena Nuevo and what she did with Epstein.",
      "position": "body"
    },
    {
      "type": "printed",
      "content": "I then talked to about truth and lying. We talked about the color sweater she was wearing. denied having sexual intercourse with Epstein. She denied touching his penis. again admitted to observing Epstein masturbate.",
      "position": "body"
    },
    {
      "type": "printed",
      "content": "agreed to cooperating with the police department in placing a phone call to Robson in a controlled setting. I met with Ms. Back and advised her of the families' as well as willingness to cooperate with this investigation. Copies of this interview were placed into evidence.",
      "position": "body"
    },
    {
      "type": "printed",
      "content": "I made contact with Jeannie Hernandez, mother of Sheena Nuevo, I advised her briefly of my investigation. She was aware of the incident and stated that she overheard a portion of a conversation that her daughter was having with a boy named Zack. Hernandez stated that it was her opinion that both girls liked Zack. Hernandez recalled hearing her daughter calling - a whore. Hernandez admitted that she did not listen to the entire conversation but did confront her daughter about it later. Sheena told her mother that had slept with an older man for money. Hernandez stated that she would not object to me speaking with her daughter. It was Hernandez s belief that everyone in the school may have known about this because of the fight that her daughter Sheena and had gotten into. I reminded Hernandez that this was an ongoing investigation and requested she not discuss the fact that I had contacted her.",
      "position": "body"
    },
    {
      "type": "printed",
      "content": "On 03/16/2005, PBSO Sgt. Chris Keen left a message that he was returning my call. I spoke with Keen and discussed the case with him and inquired if he had any open allegations or cases where the suspect resided in Palm Beach. Keen stated he was unaware of any. Keen offered any assistance if needed. Keen stated it was his experience that due to the age of the parties involved, it would be difficult to interview them and expect the investigation to remain confidential.",
      "position": "body"
    },
    {
      "type": "printed",
      "content": "Because of the time delay, there was no need for the victim to be taken to a medical facility for a physical for the purpose of obtaining evidence. There was also no need to take her to CPT as she was already in a juvenile facility, with an assigned therapist, in which coordinating a day and time to obtain a statement could be made.",
      "position": "body"
    },
    {
      "type": "printed",
      "content": "On 03/17/2005, I queried Jeffery Epstein on the internet and obtained",
      "position": "body"
    },
    {
      "type": "printed",
      "content": "07/26/17 Page 2538 Public Records Request No.: 17-295 DOJ-OGR-00032851",
      "position": "footer"
    }
  ],
  "entities": {
    "people": [
      "Robson",
      "Brian",
      "Epstein",
      "Sheena Nuevo",
      "Jeannie Hernandez",
      "Zack",
      "Chris Keen",
      "Jeffery Epstein",
      "Ms. Back"
    ],
    "organizations": [
      "PALM BEACH POLICE DEPARTMENT",
      "PBSO"
    ],
    "locations": [
      "Palm Beach"
    ],
    "dates": [
      "4/20/06",
      "03/16/2005",
      "03/17/2005",
      "07/26/17"
    ],
    "reference_numbers": [
      "1-05-000368",
      "17-295",
      "DOJ-OGR-00032851"
    ]
  },
  "additional_notes": "The document appears to be a police incident report with some names redacted. The content discusses an investigation involving sexual misconduct with a minor and interactions with various individuals related to the case."
}