{
  "document_metadata": {
    "page_number": "1/2",
    "document_number": "17-295",
    "date": "March 28, 2008",
    "document_type": "Fax Transmittal Sheet",
    "has_handwriting": false,
    "has_stamps": false
  },
  "full_text": "305-9312200 Herman &Mermelstein, P 11:24:14 a.m. 28-03-2008 1/2 HERMAN & MERMELSTEIN PA ATTORNEYS AT LAW Stuart S. Mermelstein Tel 305-931-2200 Fax 305-931-0877 ssm&hermanlaw.com 18205 Biscayne Boulevard Suite 2218 Miami, Florida 33160 www.hermanlaw.com FAX TRANSMITTAL SHEET FROM DATE NUMBER OF PAGES Stuart S. Mermelstein, Esq. March 28, 2008 2 TO FAX NUMBER Lanna Leigh Belohlavek State Attorney's Office, 15th Judicial Circuit (561) 355-7379 MESSAGE: RE: State of Florida v. Jeffrey Epstein Please see attached correspondence. THIS MESSAGE IS INTENDED ONLY FOR THE USE OF THE INDIVIDUAL OR ENTITY TO WHICH IT IS ADDRESSED AND MAY CONTAIN INFORMATION THAT IS PRIVILEGED, CONFIDENTIAL AND EXEMPT FROM DISCLOSURE UNDER APPLICABLE LAW. IF THE READER OF THIS MESSAGE IS NOT THE INTENDED RECIPIENT OR THE EMPLOYEE OR AGENT RESPONSIBLE FOR DELIVERING THE MESSAGE TO THE INTENDED RECIPIENT, YOU ARE HEREBY NOTIFIED THAT ANY DISSEMINATION, DISTRIBUTION OR COPYING OF THIS COMMUNICATION IS STRICTLY PROHIBITED. IF YOU HAVE RECEIVED THIS COMMUNICATION IN ERROR, PLEASE NOTIFY US IMMEDIATELY BY TELEPHONE, AND RETURN THE ORIGINAL MESSAGE TO US AT THE ABOVE ADDRESS VIA THE U.S. POSTAL SERVICE. THANK YOU. 07/26/17 Page 48 Public Records Request No.: 17-295 DOJ-OGR-00031569",
  "text_blocks": [
    {
      "type": "printed",
      "content": "HERMAN & MERMELSTEIN PA ATTORNEYS AT LAW",
      "position": "header"
    },
    {
      "type": "printed",
      "content": "Stuart S. Mermelstein Tel 305-931-2200 Fax 305-931-0877 ssm&hermanlaw.com 18205 Biscayne Boulevard Suite 2218 Miami, Florida 33160 www.hermanlaw.com",
      "position": "header"
    },
    {
      "type": "printed",
      "content": "FAX TRANSMITTAL SHEET",
      "position": "top"
    },
    {
      "type": "printed",
      "content": "FROM: Stuart S. Mermelstein, Esq. DATE: March 28, 2008 NUMBER OF PAGES: 2 TO: Lanna Leigh Belohlavek State Attorney's Office, 15th Judicial Circuit FAX NUMBER: (561) 355-7379 MESSAGE: RE: State of Florida v. Jeffrey Epstein Please see attached correspondence.",
      "position": "middle"
    },
    {
      "type": "printed",
      "content": "THIS MESSAGE IS INTENDED ONLY FOR THE USE OF THE INDIVIDUAL OR ENTITY TO WHICH IT IS ADDRESSED AND MAY CONTAIN INFORMATION THAT IS PRIVILEGED, CONFIDENTIAL AND EXEMPT FROM DISCLOSURE UNDER APPLICABLE LAW. IF THE READER OF THIS MESSAGE IS NOT THE INTENDED RECIPIENT OR THE EMPLOYEE OR AGENT RESPONSIBLE FOR DELIVERING THE MESSAGE TO THE INTENDED RECIPIENT, YOU ARE HEREBY NOTIFIED THAT ANY DISSEMINATION, DISTRIBUTION OR COPYING OF THIS COMMUNICATION IS STRICTLY PROHIBITED. IF YOU HAVE RECEIVED THIS COMMUNICATION IN ERROR, PLEASE NOTIFY US IMMEDIATELY BY TELEPHONE, AND RETURN THE ORIGINAL MESSAGE TO US AT THE ABOVE ADDRESS VIA THE U.S. POSTAL SERVICE. THANK YOU.",
      "position": "middle"
    },
    {
      "type": "printed",
      "content": "07/26/17 Page 48 Public Records Request No.: 17-295 DOJ-OGR-00031569",
      "position": "footer"
    }
  ],
  "entities": {
    "people": [
      "Stuart S. Mermelstein",
      "Lanna Leigh Belohlavek",
      "Jeffrey Epstein"
    ],
    "organizations": [
      "Herman & Mermelstein PA",
      "State Attorney's Office"
    ],
    "locations": [
      "Miami",
      "Florida"
    ],
    "dates": [
      "March 28, 2008",
      "07/26/17"
    ],
    "reference_numbers": [
      "17-295",
      "DOJ-OGR-00031569"
    ]
  },
  "additional_notes": "The document is a fax transmittal sheet from Herman & Mermelstein PA to Lanna Leigh Belohlavek regarding the case State of Florida v. Jeffrey Epstein. The document contains a confidentiality notice and is part of a public records request."
}