{
  "document_metadata": {
    "page_number": "2",
    "document_number": "J5-104607",
    "date": "01/24/05",
    "document_type": "Incident Report",
    "has_handwriting": false,
    "has_stamps": false
  },
  "full_text": "incident Report\nCHEROKEE COUNTY SHERIFF'S OFFICE\nJ5-104607\nSupplement No\nORIG\nJUVENILE 1: JAMES\nJUVENILE 1    Individual    JAMES    258904    WHITE    MALE\nWhere\nYes\nThere   Text Phone No\nOTHER (404)316-3145\nOTHER 1:\nInvolvement   Inv No    Type\nOTHER 1    Individual\nDate of Birth    Age    Unknown\n03/17/1969    36\nCity    State\nWALESKA    GEORGIA\nHOME Phone No\nWALESKA    (678)880-2746\nNarrative\nOn 1/24/05 at about 21:49 hours I went to    in reference to a suspicions person. I met with    who stated she has two juvenile daughters. Tonight she noticed they went across the street to a vacant house with some boys. When she went to check on them she caught the boys drinking alcohol. She knew the boys were juveniles so she bok the alcohol (tequila) from them she said a couple of the boys ran off. Juvenile one got in hs silver Mitsubishi and went to the end of the street. He then stopped infront of her house. The juvenile stated he wanted his tequila back and he would come back at midnight.\n\nis concerned juvenile one might return and damage her guests vehicles. Mrs.    asked her juveniles who the subject was and they were unfamiliar. I gave Mrs.    a case card. I returned into service with no further incident. I informed morning watch of this address for an extra patrol for tonight only.\n\nReport Officer\n000202/BEDOYA, BROOKE\nPrinted:\n06/06/2006 11:21    Page 2 of 2\n07/26/17    Page 49 of 95    Public Records Request No.: 17-295    DOJ-OGR-00032239",
  "text_blocks": [
    {
      "type": "printed",
      "content": "incident Report\nCHEROKEE COUNTY SHERIFF'S OFFICE",
      "position": "header"
    },
    {
      "type": "printed",
      "content": "JUVENILE 1: JAMES\nJUVENILE 1    Individual    JAMES    258904    WHITE    MALE",
      "position": "top"
    },
    {
      "type": "printed",
      "content": "OTHER (404)316-3145\nOTHER 1:\nInvolvement   Inv No    Type\nOTHER 1    Individual\nDate of Birth    Age    Unknown\n03/17/1969    36\nCity    State\nWALESKA    GEORGIA\nHOME Phone No\nWALESKA    (678)880-2746",
      "position": "middle"
    },
    {
      "type": "printed",
      "content": "Narrative\nOn 1/24/05 at about 21:49 hours I went to    in reference to a suspicions person. I met with    who stated she has two juvenile daughters. Tonight she noticed they went across the street to a vacant house with some boys. When she went to check on them she caught the boys drinking alcohol. She knew the boys were juveniles so she bok the alcohol (tequila) from them she said a couple of the boys ran off. Juvenile one got in hs silver Mitsubishi and went to the end of the street. He then stopped infront of her house. The juvenile stated he wanted his tequila back and he would come back at midnight.\n\nis concerned juvenile one might return and damage her guests vehicles. Mrs.    asked her juveniles who the subject was and they were unfamiliar. I gave Mrs.    a case card. I returned into service with no further incident. I informed morning watch of this address for an extra patrol for tonight only.",
      "position": "middle"
    },
    {
      "type": "printed",
      "content": "Report Officer\n000202/BEDOYA, BROOKE\nPrinted:\n06/06/2006 11:21    Page 2 of 2",
      "position": "footer"
    },
    {
      "type": "printed",
      "content": "07/26/17    Page 49 of 95    Public Records Request No.: 17-295    DOJ-OGR-00032239",
      "position": "footer"
    }
  ],
  "entities": {
    "people": [
      "JAMES",
      "BEDOYA, BROOKE"
    ],
    "organizations": [
      "CHEROKEE COUNTY SHERIFF'S OFFICE"
    ],
    "locations": [
      "WALESKA",
      "GEORGIA"
    ],
    "dates": [
      "01/24/05",
      "03/17/1969",
      "06/06/2006",
      "07/26/17"
    ],
    "reference_numbers": [
      "J5-104607",
      "258904",
      "17-295",
      "DOJ-OGR-00032239"
    ]
  },
  "additional_notes": "The document contains redactions, likely for privacy or security reasons."
}