{
  "document_metadata": {
    "page_number": "4",
    "document_number": null,
    "date": "12/7/2005",
    "document_type": "List of Trilateral Commission Members",
    "has_handwriting": false,
    "has_stamps": false
  },
  "full_text": "Trilateral Commission Members Page 4 of 9 Yoshimasa Hayashi, Member of the House of Councillors Charles B. Heck, former North American Director, Trilateral Commission David J. Hennigar, Chairman, Crownx, Vice Chairman, Crown Life Carla A. Hills, Chairman and Chief Executive Officer, Hills & Company; former U.S. Trade Representative Richard Holbrooke, Vice Chairman, Credit Suisse First Boston Corporation; former U.S. Ambassador to Germany; former U.S. Assistant Secretary of State for European and Canadian Affairs; former Assistant Secretary of State for East Asia and Pacific Affairs, former U.S. ambassador to the United Nations Robert D. Hormats, Vice Chairman, Goldman Sachs Int. Murray Horn, Managing Director ANZ Bank (New Zealand) Limited Hyun Hong-Choo, senior partner, Kim & Chang, Seoul James R. Houghton, Former Chairman of the Board, Corning Incorporated Claude Imbert, founder, Le Point, Paris Bobby R. Inman, Chmn., Dallas Fed. Res. Bank Joichi Ito, President, CEO, Neoteny Co. Max Jakobson, former Finnish ambassador to the United Nations Baron Daniel Janssen, Chairman, Solvay, Bruxelles Sir Michael Jenkins, vice Chairman, Dresdener Kleinwort Wasserstein, London Trinidad Jimenez, Socialist Party, Madrid Josef Joffe, editor, Die Zeit, Hamburg James A. Johnson, vice Chairman, Perseus LLC, Washington Samuel C. Johnson, Director, Mobil Corp. W. Thomas Johnson, President, Cable News Network Han Sung-joo, former Minister of Foreign Affairs, Seoul Vernon E. Jordan, Senior Partner, Akin, Gum p, Strauss, Hauer & Feld Karl Kaiser, Director, Research Inmstitute of the German Council on foreign relations Donald R. Keough, Chairman of the Board, Allen & Company Incorporated; Coca-Cola Co. Henry A. Kissinger, Chairman, Kissinger Associates, Inc.; former U.S. Secretary of State; former Assistant to the President for National Security Affairs Sir John Kerr, Secretary general, European Convention Kim Kihwan, advisor, Goldman Sachs Il Sa Kong, CEO, Institute for Global Economics, Seoul Kim Kyung-Won, President, Institute of Social Sciences Aotaro Kobayashi, Chairman of the Board, Fuji Xerox Co., Ltd. Akira Kojima, editorialist, The Nihon Keizai Shimbun Marie-Josee Kravis, Adjunct Senior Fellow, Council on Foreign Relations, New York; former Executive Director Hudson Institute of Canada, Montreal Thomas G. Labrecque, President, The Chase Manhattan Bank Manfred Lahnstein, former Member of the Executive Board, Bertelsmann, G�tersloh Count Otto Lambsdorff, partner, Wessing Lawyer, D�sseldorf Kurt Lauk, President, Globe Capital Partners, Stuttgart Anne Lauvergeon, Chairman of the Executive Board, Areva, Paris Kenneth L. Lay, former CEO, Enron Corporation Jim Leach, Member of U.S. House of Representatives Cees van Lede, CEO Akzo Nobel, Arnhem Lee In-ho, President, Korea Foundation Gerald Levin, Chairman and Chief Executive Officer Time Warner Bernard Lewis, Professor of Near Eastern Studies, Emeritus, Princeton University, Princeton, NJ http://www.biblebelievers.org.au/weektc.htm Page 57 of 151 Public Records Request No.: 117295 12/7/2005 DOJ-OGR-00032096",
  "text_blocks": [
    {
      "type": "printed",
      "content": "Trilateral Commission Members Page 4 of 9",
      "position": "header"
    },
    {
      "type": "printed",
      "content": "Yoshimasa Hayashi, Member of the House of Councillors Charles B. Heck, former North American Director, Trilateral Commission David J. Hennigar, Chairman, Crownx, Vice Chairman, Crown Life Carla A. Hills, Chairman and Chief Executive Officer, Hills & Company; former U.S. Trade Representative Richard Holbrooke, Vice Chairman, Credit Suisse First Boston Corporation; former U.S. Ambassador to Germany; former U.S. Assistant Secretary of State for European and Canadian Affairs; former Assistant Secretary of State for East Asia and Pacific Affairs, former U.S. ambassador to the United Nations Robert D. Hormats, Vice Chairman, Goldman Sachs Int. Murray Horn, Managing Director ANZ Bank (New Zealand) Limited Hyun Hong-Choo, senior partner, Kim & Chang, Seoul James R. Houghton, Former Chairman of the Board, Corning Incorporated Claude Imbert, founder, Le Point, Paris Bobby R. Inman, Chmn., Dallas Fed. Res. Bank Joichi Ito, President, CEO, Neoteny Co. Max Jakobson, former Finnish ambassador to the United Nations Baron Daniel Janssen, Chairman, Solvay, Bruxelles Sir Michael Jenkins, vice Chairman, Dresdener Kleinwort Wasserstein, London Trinidad Jimenez, Socialist Party, Madrid Josef Joffe, editor, Die Zeit, Hamburg James A. Johnson, vice Chairman, Perseus LLC, Washington Samuel C. Johnson, Director, Mobil Corp. W. Thomas Johnson, President, Cable News Network Han Sung-joo, former Minister of Foreign Affairs, Seoul Vernon E. Jordan, Senior Partner, Akin, Gum p, Strauss, Hauer & Feld Karl Kaiser, Director, Research Inmstitute of the German Council on foreign relations Donald R. Keough, Chairman of the Board, Allen & Company Incorporated; Coca-Cola Co. Henry A. Kissinger, Chairman, Kissinger Associates, Inc.; former U.S. Secretary of State; former Assistant to the President for National Security Affairs Sir John Kerr, Secretary general, European Convention Kim Kihwan, advisor, Goldman Sachs Il Sa Kong, CEO, Institute for Global Economics, Seoul Kim Kyung-Won, President, Institute of Social Sciences Aotaro Kobayashi, Chairman of the Board, Fuji Xerox Co., Ltd. Akira Kojima, editorialist, The Nihon Keizai Shimbun Marie-Josee Kravis, Adjunct Senior Fellow, Council on Foreign Relations, New York; former Executive Director Hudson Institute of Canada, Montreal Thomas G. Labrecque, President, The Chase Manhattan Bank Manfred Lahnstein, former Member of the Executive Board, Bertelsmann, G�tersloh Count Otto Lambsdorff, partner, Wessing Lawyer, D�sseldorf Kurt Lauk, President, Globe Capital Partners, Stuttgart Anne Lauvergeon, Chairman of the Executive Board, Areva, Paris Kenneth L. Lay, former CEO, Enron Corporation Jim Leach, Member of U.S. House of Representatives Cees van Lede, CEO Akzo Nobel, Arnhem Lee In-ho, President, Korea Foundation Gerald Levin, Chairman and Chief Executive Officer Time Warner Bernard Lewis, Professor of Near Eastern Studies, Emeritus, Princeton University, Princeton, NJ",
      "position": "main content"
    },
    {
      "type": "printed",
      "content": "http://www.biblebelievers.org.au/weektc.htm Page 57 of 151 Public Records Request No.: 117295 12/7/2005 DOJ-OGR-00032096",
      "position": "footer"
    }
  ],
  "entities": {
    "people": [
      "Yoshimasa Hayashi",
      "Charles B. Heck",
      "David J. Hennigar",
      "Carla A. Hills",
      "Richard Holbrooke",
      "Robert D. Hormats",
      "Murray Horn",
      "Hyun Hong-Choo",
      "James R. Houghton",
      "Claude Imbert",
      "Bobby R. Inman",
      "Joichi Ito",
      "Max Jakobson",
      "Baron Daniel Janssen",
      "Sir Michael Jenkins",
      "Trinidad Jimenez",
      "Josef Joffe",
      "James A. Johnson",
      "Samuel C. Johnson",
      "W. Thomas Johnson",
      "Han Sung-joo",
      "Vernon E. Jordan",
      "Karl Kaiser",
      "Donald R. Keough",
      "Henry A. Kissinger",
      "Sir John Kerr",
      "Kim Kihwan",
      "Il Sa Kong",
      "Kim Kyung-Won",
      "Aotaro Kobayashi",
      "Akira Kojima",
      "Marie-Josee Kravis",
      "Thomas G. Labrecque",
      "Manfred Lahnstein",
      "Count Otto Lambsdorff",
      "Kurt Lauk",
      "Anne Lauvergeon",
      "Kenneth L. Lay",
      "Jim Leach",
      "Cees van Lede",
      "Lee In-ho",
      "Gerald Levin",
      "Bernard Lewis"
    ],
    "organizations": [
      "Trilateral Commission",
      "Crownx",
      "Crown Life",
      "Hills & Company",
      "Credit Suisse First Boston Corporation",
      "Goldman Sachs Int.",
      "ANZ Bank (New Zealand) Limited",
      "Kim & Chang",
      "Corning Incorporated",
      "Le Point",
      "Dallas Fed. Res. Bank",
      "Neoteny Co.",
      "Solvay",
      "Dresdener Kleinwort Wasserstein",
      "Die Zeit",
      "Perseus LLC",
      "Mobil Corp.",
      "Cable News Network",
      "Akin, Gum p, Strauss, Hauer & Feld",
      "Allen & Company Incorporated",
      "Coca-Cola Co.",
      "Kissinger Associates, Inc.",
      "European Convention",
      "Institute for Global Economics",
      "Institute of Social Sciences",
      "Fuji Xerox Co., Ltd.",
      "The Nihon Keizai Shimbun",
      "Council on Foreign Relations",
      "Hudson Institute of Canada",
      "The Chase Manhattan Bank",
      "Bertelsmann",
      "Wessing Lawyer",
      "Globe Capital Partners",
      "Areva",
      "Enron Corporation",
      "Akzo Nobel",
      "Korea Foundation",
      "Time Warner",
      "Princeton University"
    ],
    "locations": [
      "Germany",
      "United Nations",
      "New Zealand",
      "Seoul",
      "Paris",
      "London",
      "Madrid",
      "Hamburg",
      "Washington",
      "Stuttgart",
      "New York",
      "Montreal",
      "Düsseldorf",
      "Arnhem",
      "Princeton, NJ"
    ],
    "dates": [
      "12/7/2005"
    ],
    "reference_numbers": [
      "117295",
      "DOJ-OGR-00032096"
    ]
  },
  "additional_notes": "The document appears to be a list of Trilateral Commission members, with their names, titles, and affiliations. The document is page 4 of 9 and has a public records request number and date at the bottom."
}