{
  "document_metadata": {
    "page_number": "9",
    "document_number": "17-295",
    "date": "07/26/17",
    "document_type": "transcript",
    "has_handwriting": false,
    "has_stamps": false
  },
  "full_text": "Page 9\n1 girlfriend. She was our immediate superior.\n2 Q. Did he have girls come over to give\n3 massages?\n4 A. Yes.\n5 Q. How many massages would he have in a day?\n6 A. Sometimes one, sometimes two, three.\n7 Q. Was it the same girl that would come back\n8 to do the massages?\n9 A. Yeah, yeah. Not the same girl -- I mean\n10 during eleven years, I probably saw a hundred, two\n11 hundred different massage therapists.\n12 Q. Did they seem young to you?\n13 A. No, sir. Mostly no. We saw one or two\n14 young ones in the last year. Before that, it was all\n15 adults.\n16 Q. During your last year when you were working\n17 with him, what do you mean that they looked young? Did\n18 they look like they were still in high school?\n19 A. I remember one girl was young. We never\n20 asked how old she was. It was not in my job.\n21 Q. Right. I understand.\n22 A. But I imagine she was 16, 17. In my\n23 judgment, she was 16, 17.\n24 Q. Where would these massages take place?\n25 A. All the time it was in his room. Sometimes\nJ. CONSOR & ASSOCIATES REPORTING & TRANSCRIPTION\n561.835.9738\n07/26/17 Page 2386 Public Records Request No.: 17-295\nDOJ-OGR-00032699",
  "text_blocks": [
    {
      "type": "printed",
      "content": "Page 9",
      "position": "header"
    },
    {
      "type": "printed",
      "content": "1 girlfriend. She was our immediate superior.\n2 Q. Did he have girls come over to give\n3 massages?\n4 A. Yes.\n5 Q. How many massages would he have in a day?\n6 A. Sometimes one, sometimes two, three.\n7 Q. Was it the same girl that would come back\n8 to do the massages?\n9 A. Yeah, yeah. Not the same girl -- I mean\n10 during eleven years, I probably saw a hundred, two\n11 hundred different massage therapists.\n12 Q. Did they seem young to you?\n13 A. No, sir. Mostly no. We saw one or two\n14 young ones in the last year. Before that, it was all\n15 adults.\n16 Q. During your last year when you were working\n17 with him, what do you mean that they looked young? Did\n18 they look like they were still in high school?\n19 A. I remember one girl was young. We never\n20 asked how old she was. It was not in my job.\n21 Q. Right. I understand.\n22 A. But I imagine she was 16, 17. In my\n23 judgment, she was 16, 17.\n24 Q. Where would these massages take place?\n25 A. All the time it was in his room. Sometimes",
      "position": "main"
    },
    {
      "type": "printed",
      "content": "J. CONSOR & ASSOCIATES REPORTING & TRANSCRIPTION\n561.835.9738",
      "position": "footer"
    },
    {
      "type": "printed",
      "content": "07/26/17 Page 2386 Public Records Request No.: 17-295",
      "position": "footer"
    },
    {
      "type": "printed",
      "content": "DOJ-OGR-00032699",
      "position": "footer"
    }
  ],
  "entities": {
    "people": [],
    "organizations": [
      "J. Consor & Associates"
    ],
    "locations": [],
    "dates": [
      "07/26/17"
    ],
    "reference_numbers": [
      "17-295",
      "DOJ-OGR-00032699"
    ]
  },
  "additional_notes": "The document appears to be a transcript of a deposition or interview. The content is sensitive and discusses potentially inappropriate activities involving massage therapists. The document is typed and has a professional format, indicating it was produced by a reporting and transcription service."
}