{
  "document_metadata": {
    "page_number": "66",
    "document_number": "17-295",
    "date": "07/26/17",
    "document_type": "Deposition Transcript",
    "has_handwriting": false,
    "has_stamps": false
  },
  "full_text": "Censor & Associates Reporting and Transcription, Inc. Page 66 1 A. Nothing. 2 Q. Well, we're going to come back to MySpace in a second. 3 4 A. You do that. 5 Q. I'm going to ask you some questions 6 about why you lie about your age so often, okay? 7 MR. LEOPOLD: Objection to the form. 8 Argumentative. 9 BY MR. TEIN: 10 Q. You lie about your age all the time, don't 11 you? 12 MR. LEOPOLD: Objection, argumentative. 13 THE WITNESS: Incorrect. 14 BY MR. TEIN: 15 Q. You lie about your age to get body 16 piercings, don't you? 17 A. Incorrect. 18 Q. You have body piercings, don't you? 19 A. Yes. 20 Q. You have four body piercings; isn't that 21 right? 22 A. Five. 23 Q. Other than the piercings on your ears -- 24 I'm not talking about that -- 25 A. Oh, then no; just one. Ph. 561.682.0905 - Fax. 561.682.1771 1655 Palm Beach Lakes Blvd., Suite 500 - West Palm Beach, FL 33401 07/26/17 Page 2741 Public Records Request No.: 17-295 DOJ-OGR-00033054",
  "text_blocks": [
    {
      "type": "printed",
      "content": "Censor & Associates Reporting and Transcription, Inc.",
      "position": "header"
    },
    {
      "type": "printed",
      "content": "Page 66",
      "position": "header"
    },
    {
      "type": "printed",
      "content": "1 A. Nothing. 2 Q. Well, we're going to come back to MySpace in a second. 3 4 A. You do that. 5 Q. I'm going to ask you some questions 6 about why you lie about your age so often, okay? 7 MR. LEOPOLD: Objection to the form. 8 Argumentative. 9 BY MR. TEIN: 10 Q. You lie about your age all the time, don't 11 you? 12 MR. LEOPOLD: Objection, argumentative. 13 THE WITNESS: Incorrect. 14 BY MR. TEIN: 15 Q. You lie about your age to get body 16 piercings, don't you? 17 A. Incorrect. 18 Q. You have body piercings, don't you? 19 A. Yes. 20 Q. You have four body piercings; isn't that 21 right? 22 A. Five. 23 Q. Other than the piercings on your ears -- 24 I'm not talking about that -- 25 A. Oh, then no; just one.",
      "position": "main"
    },
    {
      "type": "printed",
      "content": "Ph. 561.682.0905 - Fax. 561.682.1771 1655 Palm Beach Lakes Blvd., Suite 500 - West Palm Beach, FL 33401",
      "position": "footer"
    },
    {
      "type": "printed",
      "content": "07/26/17 Page 2741 Public Records Request No.: 17-295 DOJ-OGR-00033054",
      "position": "footer"
    }
  ],
  "entities": {
    "people": [
      "MR. LEOPOLD",
      "MR. TEIN",
      "THE WITNESS"
    ],
    "organizations": [
      "Censor & Associates Reporting and Transcription, Inc."
    ],
    "locations": [
      "West Palm Beach",
      "Palm Beach Lakes Blvd.",
      "FL"
    ],
    "dates": [
      "07/26/17"
    ],
    "reference_numbers": [
      "17-295",
      "DOJ-OGR-00033054"
    ]
  },
  "additional_notes": "The document appears to be a deposition transcript with a clear structure of questions and answers. The footer contains contact information for Censor & Associates and metadata about the document, including the date and public records request number."
}