{
  "document_metadata": {
    "page_number": "85",
    "document_number": "17-295",
    "date": "April 2006",
    "document_type": "State's Attorney Subpoena",
    "has_handwriting": true,
    "has_stamps": true
  },
  "full_text": "IN THE CIRCUIT COURT OF THE FIFTEENTH JUDICIAL CIRCUIT IN AND FOR PALM BEACH COUNTY, FLORIDA (CRIMINAL DIVISION)\nSTATE'S ATTORNEY SUBPOENA\nTO: SPRINT\nCOURT ORDER & SUBPOENA COMPLIANCE\n2000 EDMUND HALLEY DRIVE - MS D3-1\nRESTON, VA 20191\nFAX NUMBER: 703-433-8860\n703-433-8842\nDUCES TECUM: ANY AND ALL INCOMING AND OUTGOING PHONE CALLS FOR TELEPHONE NUMBER (561) 852-3098 FROM MARCH 1, 2006 TO PRESENT.\nYOU MAY COMPLY WITH THIS SUBPOENA BY SUPPLYING THIS INFORMATION TO DETECTIVE JOE RECAREY, PALM BEACH POLICE DEPARTMENT, 345 SOUTH COUNTY ROAD, PALM BEACH, FLORIDA, FAX NUMBER 561-655-9653.\nGREETINGS:\nYOU ARE HEREBY COMMANDED TO BE AND APPEAR BEFORE THE STATE'S ATTORNEY or his assistant, In and for Palm Beach County, Florida, at the Criminal Justice Building, 401 North Dixie Highway, West Palm Beach, Florida, on INSTANTER, 2006, for Interrogation and the truth to speak, in a certain matter pending and under Investigation. Failure to appear will subject you to contempt of Court.\nPLEASE DO NOT DISCLOSE THE EXISTENCE OF THIS REQUEST AS IT MAY IMPEDE AN ONGOING CRIMINAL INVESTIGATION.\nWITNESS my hand and the seal of this Court on day of APRIL 2006.\nSHARON R. BOCK, Clerk\nBy: Deputy Clerk\n(Circuit Court Seal)\nDALIAH H WEISS\nAssistant State Attorney\nReceived this subpoena on the day of , 2006, by delivering a True Copy thereof to the within named witness in the County of Palm Beach, State of Florida.\nSHERIFF, PALM BEACH COUNTY\nBy: Deputy Sheriff\n07/26/17\nPage 85 of 124\nPublic Records Request No.: 17-295",
  "text_blocks": [
    {
      "type": "printed",
      "content": "IN THE CIRCUIT COURT OF THE FIFTEENTH JUDICIAL CIRCUIT IN AND FOR PALM BEACH COUNTY, FLORIDA (CRIMINAL DIVISION)",
      "position": "header"
    },
    {
      "type": "printed",
      "content": "STATE'S ATTORNEY SUBPOENA",
      "position": "header"
    },
    {
      "type": "printed",
      "content": "TO: SPRINT",
      "position": "top"
    },
    {
      "type": "printed",
      "content": "COURT ORDER & SUBPOENA COMPLIANCE\n2000 EDMUND HALLEY DRIVE - MS D3-1\nRESTON, VA 20191\nFAX NUMBER: 703-433-8860\n703-433-8842",
      "position": "top"
    },
    {
      "type": "printed",
      "content": "DUCES TECUM: ANY AND ALL INCOMING AND OUTGOING PHONE CALLS FOR TELEPHONE NUMBER (561) 852-3098 FROM MARCH 1, 2006 TO PRESENT.",
      "position": "middle"
    },
    {
      "type": "printed",
      "content": "YOU MAY COMPLY WITH THIS SUBPOENA BY SUPPLYING THIS INFORMATION TO DETECTIVE JOE RECAREY, PALM BEACH POLICE DEPARTMENT, 345 SOUTH COUNTY ROAD, PALM BEACH, FLORIDA, FAX NUMBER 561-655-9653.",
      "position": "middle"
    },
    {
      "type": "printed",
      "content": "GREETINGS:",
      "position": "middle"
    },
    {
      "type": "printed",
      "content": "YOU ARE HEREBY COMMANDED TO BE AND APPEAR BEFORE THE STATE'S ATTORNEY or his assistant, In and for Palm Beach County, Florida, at the Criminal Justice Building, 401 North Dixie Highway, West Palm Beach, Florida, on INSTANTER, 2006, for Interrogation and the truth to speak, in a certain matter pending and under Investigation. Failure to appear will subject you to contempt of Court.",
      "position": "middle"
    },
    {
      "type": "printed",
      "content": "PLEASE DO NOT DISCLOSE THE EXISTENCE OF THIS REQUEST AS IT MAY IMPEDE AN ONGOING CRIMINAL INVESTIGATION.",
      "position": "middle"
    },
    {
      "type": "printed",
      "content": "WITNESS my hand and the seal of this Court on day of APRIL 2006.",
      "position": "bottom"
    },
    {
      "type": "printed",
      "content": "SHARON R. BOCK, Clerk",
      "position": "bottom"
    },
    {
      "type": "handwritten",
      "content": "E 012",
      "position": "bottom"
    },
    {
      "type": "printed",
      "content": "By: Deputy Clerk",
      "position": "bottom"
    },
    {
      "type": "signature",
      "content": "DALIAH H WEISS",
      "position": "bottom"
    },
    {
      "type": "printed",
      "content": "Assistant State Attorney",
      "position": "bottom"
    },
    {
      "type": "printed",
      "content": "Received this subpoena on the day of , 2006, by delivering a True Copy thereof to the within named witness in the County of Palm Beach, State of Florida.",
      "position": "bottom"
    },
    {
      "type": "printed",
      "content": "SHERIFF, PALM BEACH COUNTY",
      "position": "bottom"
    },
    {
      "type": "printed",
      "content": "By: Deputy Sheriff",
      "position": "bottom"
    }
  ],
  "entities": {
    "people": [
      "DALIAH H WEISS",
      "SHARON R. BOCK",
      "JOE RECAREY"
    ],
    "organizations": [
      "SPRINT",
      "PALM BEACH POLICE DEPARTMENT"
    ],
    "locations": [
      "PALM BEACH COUNTY",
      "FLORIDA",
      "RESTON",
      "VA",
      "WEST PALM BEACH"
    ],
    "dates": [
      "MARCH 1, 2006",
      "APRIL 2006",
      "07/26/17"
    ],
    "reference_numbers": [
      "17-295",
      "(561) 852-3098",
      "703-433-8860",
      "703-433-8842",
      "561-655-9653"
    ]
  },
  "additional_notes": "The document is a subpoena issued by the State's Attorney in Palm Beach County, Florida. It is dated April 2006 and requires Sprint to provide phone call records for a specific number. The document bears a circuit court seal and is signed by DALIAH H WEISS, Assistant State Attorney. The document also contains a section for the sheriff's return of service, which is not completed."
}