{
  "document_metadata": {
    "page_number": "31",
    "document_number": "17-295",
    "date": "APR 05 2005",
    "document_type": "Bill or Invoice",
    "has_handwriting": false,
    "has_stamps": false
  },
  "full_text": "**BELLSOUTH TELECOMMUNICATIONS, INC.**\n561 832 4117 908\nAPR 05 2005 R\nWPB PAGE 6 BST\nCURRENT CHARGES\nITEM CODES AMOUNT\nwhen you're online. Check out our SPECIAL OFFERS at www.fastaccess.com/faster4 or call 1 877 689-2617. Service not available in all areas.\nGoing Home for the Summer? Place your order for BellSouth Vacation Service online. It's quick, easy and available 24/7. Plus, you keep your telephone number. Go to www.bellsouth.com/vacation to suspend your local phone service when you leave, and restore it when you are ready to return.\nVisit us on the Internet: www.bellsouth.com\n07/26/17 Page 31 of 104 Public Records Request No.: 17-295\nDOJ-OGR-00031648",
  "text_blocks": [
    {
      "type": "printed",
      "content": "**BELLSOUTH TELECOMMUNICATIONS, INC.**",
      "position": "header"
    },
    {
      "type": "printed",
      "content": "561 832 4117 908\nAPR 05 2005 R\nWPB PAGE 6 BST",
      "position": "header"
    },
    {
      "type": "printed",
      "content": "CURRENT CHARGES\nITEM CODES AMOUNT",
      "position": "top"
    },
    {
      "type": "printed",
      "content": "when you're online. Check out our SPECIAL OFFERS at www.fastaccess.com/faster4 or call 1 877 689-2617. Service not available in all areas.",
      "position": "top"
    },
    {
      "type": "printed",
      "content": "Going Home for the Summer? Place your order for BellSouth Vacation Service online. It's quick, easy and available 24/7. Plus, you keep your telephone number. Go to www.bellsouth.com/vacation to suspend your local phone service when you leave, and restore it when you are ready to return.",
      "position": "middle"
    },
    {
      "type": "printed",
      "content": "Visit us on the Internet: www.bellsouth.com",
      "position": "middle"
    },
    {
      "type": "printed",
      "content": "07/26/17 Page 31 of 104 Public Records Request No.: 17-295",
      "position": "footer"
    },
    {
      "type": "printed",
      "content": "DOJ-OGR-00031648",
      "position": "footer"
    }
  ],
  "entities": {
    "people": [],
    "organizations": [
      "BellSouth Telecommunications, Inc.",
      "BellSouth"
    ],
    "locations": [],
    "dates": [
      "APR 05 2005",
      "07/26/17"
    ],
    "reference_numbers": [
      "561 832 4117",
      "1 877 689-2617",
      "17-295",
      "DOJ-OGR-00031648"
    ]
  },
  "additional_notes": "The document appears to be a page from a larger document, likely a bill or invoice from BellSouth Telecommunications, Inc. The page contains promotional information and a reference to a public records request."
}