{
  "document_metadata": {
    "page_number": "108",
    "document_number": "17-295",
    "date": "07/26/17",
    "document_type": "transcript",
    "has_handwriting": false,
    "has_stamps": false
  },
  "full_text": "Censor & Associates Reporting and Transcription, Inc. Page 108 1 A. Yes. 2 Q. Are you clothed in this picture? 3 A. Yeah. I have a halter dress on. 4 Q. Where is that picture taken? 5 A. In Steven's house. 6 Q. Did you post that on the Internet? 7 A. Yes. 8 Q. All right. 9 MR. TEIN: You can take that down. 10 BY MR. TEIN: 11 Q. Now your boyfriend is Brett Albritton, correct? 12 A. Yeah. 13 Q. You lie about your age in order to conceal something about your relationship with Brett Albritton; isn't that correct? 14 15 A. No. 16 Q. Brett's 22 years old, isn't he? 17 A. Yes. 18 Q. And Brett is a firefighter with the Palm Beach Fire Department, right? 19 A. Yup. 20 Q. Does the Palm Beach Fire Department know that your boyfriend is dating an underage girl? 21 A. Actually, mister, it's legal. 22 23 Ph. 561.682.0905 - Fax. 561.682.1771 1655 Palm Beach Lakes Blvd., Suite 500 - West Palm Beach, FL 33401 07/26/17 Page 2783 Public Records Request No.: 17-295 DOJ-OGR-00033096",
  "text_blocks": [
    {
      "type": "printed",
      "content": "Censor & Associates Reporting and Transcription, Inc.",
      "position": "header"
    },
    {
      "type": "printed",
      "content": "Page 108",
      "position": "header"
    },
    {
      "type": "printed",
      "content": "1 A. Yes. 2 Q. Are you clothed in this picture? 3 A. Yeah. I have a halter dress on. 4 Q. Where is that picture taken? 5 A. In Steven's house. 6 Q. Did you post that on the Internet? 7 A. Yes. 8 Q. All right. 9 MR. TEIN: You can take that down. 10 BY MR. TEIN: 11 Q. Now your boyfriend is Brett Albritton, correct? 12 A. Yeah. 13 Q. You lie about your age in order to conceal something about your relationship with Brett Albritton; isn't that correct? 14 15 A. No. 16 Q. Brett's 22 years old, isn't he? 17 A. Yes. 18 Q. And Brett is a firefighter with the Palm Beach Fire Department, right? 19 A. Yup. 20 Q. Does the Palm Beach Fire Department know that your boyfriend is dating an underage girl? 21 A. Actually, mister, it's legal. 22 23",
      "position": "main"
    },
    {
      "type": "printed",
      "content": "Ph. 561.682.0905 - Fax. 561.682.1771 1655 Palm Beach Lakes Blvd., Suite 500 - West Palm Beach, FL 33401",
      "position": "footer"
    },
    {
      "type": "printed",
      "content": "07/26/17 Page 2783 Public Records Request No.: 17-295 DOJ-OGR-00033096",
      "position": "footer"
    }
  ],
  "entities": {
    "people": [
      "Brett Albritton",
      "Steven",
      "MR. TEIN"
    ],
    "organizations": [
      "Censor & Associates",
      "Palm Beach Fire Department"
    ],
    "locations": [
      "Palm Beach",
      "West Palm Beach",
      "Steven's house"
    ],
    "dates": [
      "07/26/17"
    ],
    "reference_numbers": [
      "17-295",
      "DOJ-OGR-00033096"
    ]
  },
  "additional_notes": "The document appears to be a transcript of a deposition or interview. The content is related to a legal case involving a relationship between an adult and a minor."
}