{
  "document_metadata": {
    "page_number": "2246",
    "document_number": "17-295",
    "date": "07/26/17",
    "document_type": "Important Message",
    "has_handwriting": true,
    "has_stamps": false
  },
  "full_text": "IMPORTANT MESSAGE FOR: Jeffry DATE: 4/1/05 TIME 8:08 A.M. M. Jean-Luc OF: PHONE/MOBILE: 646 286 7000 TELEPHONED PLEASE CALL CAME TO SEE YOU WILL CALL AGAIN WANTS TO SEE YOU RUSH RETURNED YOUR CALL SPECIAL ATTENTION MESSAGE: He has a teacher for you to teach you how to speak russian. She is 2x8 years old not blonde Lessons are free and you can have 1st today if you call SIGNED 1184 IMPORTANT MESSAGE FOR: Jeffry DATE: 3/31/05 TIME 5:06 A.M. M. Mellisa Hunes OF: PHONE/MOBILE: 51619236 /351 0944 TELEPHONED PLEASE CALL CAME TO SEE YOU WILL CALL AGAIN WANTS TO SEE YOU RUSH RETURNED YOUR CALL SPECIAL ATTENTION MESSAGE: She called if you would like for her to work. She is available tom. till noon and Mon - Fri SIGNED 1184 IMPORTANT MESSAGE FOR: Jeffry DATE: 3/31/05 TIME 3:22 A.M. M. Lauren Strohl OF: PHONE/MOBILE: 212 201 8288 TELEPHONED PLEASE CALL CAME TO SEE YOU WILL CALL AGAIN WANTS TO SEE YOU RUSH RETURNED YOUR CALL SPECIAL ATTENTION MESSAGE: SIGNED 07/26/17 Page 2246 IMPORTANT MESSAGE FOR: Jeffry DATE: 3/31/05 TIME 2:40 A.M. M. Cecilia OF: PHONE/MOBILE: TELEPHONED PLEASE CALL CAME TO SEE YOU WILL CALL AGAIN WANTS TO SEE YOU RUSH RETURNED YOUR CALL SPECIAL ATTENTION MESSAGE: She had Martin Norat on the phone SIGNED Public Records Request No.: 17-295 DOJ-OGR-00032559",
  "text_blocks": [
    {
      "type": "printed",
      "content": "IMPORTANT MESSAGE",
      "position": "header"
    },
    {
      "type": "handwritten",
      "content": "Jeffry 4/1/05 8:08 A.M. Jean-Luc 646 286 7000 He has a teacher for you to teach you how to speak russian. She is 2x8 years old not blonde Lessons are free and you can have 1st today if you call",
      "position": "middle"
    },
    {
      "type": "handwritten",
      "content": "Jeffry 3/31/05 5:06 A.M. Mellisa Hunes 51619236 /351 0944 She called if you would like for her to work. She is available tom. till noon and Mon - Fri",
      "position": "middle"
    },
    {
      "type": "handwritten",
      "content": "Jeffry 3/31/05 3:22 A.M. Lauren Strohl 212 201 8288",
      "position": "middle"
    },
    {
      "type": "handwritten",
      "content": "Jeffry 3/31/05 2:40 A.M. Cecilia She had Martin Norat on the phone",
      "position": "middle"
    },
    {
      "type": "printed",
      "content": "Public Records Request No.: 17-295",
      "position": "footer"
    },
    {
      "type": "printed",
      "content": "DOJ-OGR-00032559",
      "position": "footer"
    }
  ],
  "entities": {
    "people": [
      "Jeffry",
      "Jean-Luc",
      "Mellisa Hunes",
      "Lauren Strohl",
      "Cecilia",
      "Martin Norat"
    ],
    "organizations": [],
    "locations": [],
    "dates": [
      "4/1/05",
      "3/31/05",
      "07/26/17"
    ],
    "reference_numbers": [
      "17-295",
      "DOJ-OGR-00032559"
    ]
  },
  "additional_notes": "The document appears to be a scanned copy of a page containing four 'Important Message' forms, likely from a log or record book. The forms are filled out with handwritten notes, indicating that they were used to record phone calls or messages for someone named Jeffry. The page is stamped with a 'Public Records Request No.' and a 'DOJ-OGR' number, suggesting that it is a document released as part of a public records request."
}