{
  "document_metadata": {
    "page_number": "14",
    "document_number": "17-295",
    "date": "07/26/17",
    "document_type": "transcript",
    "has_handwriting": false,
    "has_stamps": false
  },
  "full_text": "Censor & Associates Reporting and Transcription, Inc. Page 14 1 Q. You know that he had a press conference, 2 don't you, yes or no? 3 A. Yes. 4 Q. In fact, let's go to Exhibit 20-01. 5 6 MR. GOLDBERGER: Look behind you. You'll see it. 7 BY MR. TEIN: 8 Q. Have you ever seen that picture before? 9 A. Yes. 10 Q. Is that a picture of your father, your 11 stepmother and Mr. Herman at the press conference 12 regarding your lawsuit? 13 A. Yes. 14 Q. Now you know that this is a very serious 15 matter, don't you? 16 MR. LEOPOLD: Asked and answered. 17 Objection. 18 MR. GOLDBERGER: All right. You can 19 object. You're representing a witness here, 20 Mr. Leopold. You can object on privilege grounds. 21 You cannot make legal objections. You have no 22 standing to do so. 23 MR. LEOPOLD: I'm going to make them and 24 then -- 25 MR. GOLDBERGER: We're -- Ph. 561.682.0905 - Fax. 561.682.1771 1655 Palm Beach Lakes Blvd., Suite 500 - West Palm Beach, FL 33401 07/26/17 Page 2689 Public Records Request No.: 17-295 DOJ-OGR-00033002",
  "text_blocks": [
    {
      "type": "printed",
      "content": "Censor & Associates Reporting and Transcription, Inc.",
      "position": "header"
    },
    {
      "type": "printed",
      "content": "Page 14",
      "position": "header"
    },
    {
      "type": "printed",
      "content": "1 Q. You know that he had a press conference, 2 don't you, yes or no? 3 A. Yes. 4 Q. In fact, let's go to Exhibit 20-01. 5 6 MR. GOLDBERGER: Look behind you. You'll see it. 7 BY MR. TEIN: 8 Q. Have you ever seen that picture before? 9 A. Yes. 10 Q. Is that a picture of your father, your 11 stepmother and Mr. Herman at the press conference 12 regarding your lawsuit? 13 A. Yes. 14 Q. Now you know that this is a very serious 15 matter, don't you? 16 MR. LEOPOLD: Asked and answered. 17 Objection. 18 MR. GOLDBERGER: All right. You can 19 object. You're representing a witness here, 20 Mr. Leopold. You can object on privilege grounds. 21 You cannot make legal objections. You have no 22 standing to do so. 23 MR. LEOPOLD: I'm going to make them and 24 then -- 25 MR. GOLDBERGER: We're --",
      "position": "main"
    },
    {
      "type": "printed",
      "content": "Ph. 561.682.0905 - Fax. 561.682.1771 1655 Palm Beach Lakes Blvd., Suite 500 - West Palm Beach, FL 33401",
      "position": "footer"
    },
    {
      "type": "printed",
      "content": "07/26/17 Page 2689 Public Records Request No.: 17-295 DOJ-OGR-00033002",
      "position": "footer"
    }
  ],
  "entities": {
    "people": [
      "MR. GOLDBERGER",
      "MR. TEIN",
      "MR. LEOPOLD",
      "Mr. Herman"
    ],
    "organizations": [
      "Censor & Associates Reporting and Transcription, Inc."
    ],
    "locations": [
      "West Palm Beach",
      "Palm Beach Lakes Blvd."
    ],
    "dates": [
      "07/26/17"
    ],
    "reference_numbers": [
      "17-295",
      "DOJ-OGR-00033002",
      "20-01"
    ]
  },
  "additional_notes": "The document appears to be a transcript of a deposition or testimony. The quality is clear, and there are no visible redactions or damage."
}