{
  "document_metadata": {
    "page_number": "2306",
    "document_number": "17-295",
    "date": "07/26/17",
    "document_type": "Public Records Request",
    "has_handwriting": true,
    "has_stamps": false
  },
  "full_text": "Palm Beach Contractors\nGeneral Plumbing\nCustomer Service representative\nAmy\n561 585 2591\nElectrical\nReel Power Inc\nLenny (electrician)\n561 706 0827\nGates\nSamco Systems\nSam (owner)\n561 719 4832\nService gate switch: above garage door controls, when round light is on\nFront gate switch: just above the telephone outlet kitchen area\nGarage doors\nThe Door Smith Inc\nKeith Kelly\n561 391 7768\n561 626 8814 9(Car)\n561 346 8550 (cell)\nTelephones\nSouthern Bell (repairs)\n561 780 2355\nInternal Phone system (NEC)\nRepair and Programming\n561 881 8118\nAlarm System\nBenham Industries Inc\nKeith\n854 491 4112\nLocksmith\nWilson & Rowan\n561 655 3637\nA/C Maintenance\nJohn C Cassidy\n24 hr service\n561 833 6331\nHandyman\nCarlos (carpenter)\nContact Frances\n561 309 5820\nLandscape\nAlan Stopeck\nGarden maintenance\n561 478 4629\n561 591 1718\nPest Control\nPalm Beach Exterminator\nKim\n561 844 8082\nIrrigation\nDolphin Sprinkle\n561 478 4696\nPool Heating\nNational Pool Service\nWhen needed\n561 585 8866\nPool Maintenance\nHack Pool Service\nMonday/ Thursday\n561 588 7493\nTree Trimming\nCountry Wide Trees\nTwice, summer/winter\n561 371 5786\nCarpet Cleaners\nStanley Steamers\nMerry Rug\nwall to wall\narea rug\n561 586 5700\n561 588 8588\nAlarm - 954.\n07/26/17\nPage 2306\nPublic Records Request No.: 17-295\nDOJ-OGR-00032619",
  "text_blocks": [
    {
      "type": "printed",
      "content": "Palm Beach Contractors",
      "position": "top"
    },
    {
      "type": "handwritten",
      "content": "Home Depot 478.0783 Mon",
      "position": "top"
    },
    {
      "type": "printed",
      "content": "General Plumbing\nCustomer Service representative\nAmy\n561 585 2591",
      "position": "middle"
    },
    {
      "type": "handwritten",
      "content": "Available",
      "position": "middle"
    },
    {
      "type": "printed",
      "content": "Alarm - 954.",
      "position": "bottom"
    },
    {
      "type": "printed",
      "content": "07/26/17\nPage 2306\nPublic Records Request No.: 17-295",
      "position": "footer"
    },
    {
      "type": "printed",
      "content": "DOJ-OGR-00032619",
      "position": "footer"
    }
  ],
  "entities": {
    "people": [
      "Amy",
      "Lenny",
      "Sam",
      "Keith Kelly",
      "Keith",
      "John C Cassidy",
      "Carlos",
      "Frances",
      "Alan Stopeck",
      "Kim"
    ],
    "organizations": [
      "Reel Power Inc",
      "Samco Systems",
      "The Door Smith Inc",
      "Southern Bell",
      "Benham Industries Inc",
      "Wilson & Rowan",
      "Palm Beach Exterminator",
      "Dolphin Sprinkle",
      "National Pool Service",
      "Hack Pool Service",
      "Country Wide Trees",
      "Stanley Steamers",
      "Merry Rug"
    ],
    "locations": [
      "Palm Beach"
    ],
    "dates": [
      "07/26/17"
    ],
    "reference_numbers": [
      "17-295",
      "DOJ-OGR-00032619"
    ]
  },
  "additional_notes": "The document appears to be a list of contractors and service providers for a property in Palm Beach, with contact information and notes on their services. The document has some handwritten annotations and appears to be a scanned or photocopied version of the original."
}