{
  "document_metadata": {
    "page_number": "17",
    "document_number": "17-295",
    "date": "07/26/17",
    "document_type": "transcription",
    "has_handwriting": false,
    "has_stamps": false
  },
  "full_text": "Page 17\n1 Before I even spoke to you.\n2 Q. Just when you found the card?\n3 A. When I find the card, I get scared. I\n4 said, What's going on now? Why are you bothering me now\n5 in my house?\n6 That's why I called him.\n7 He said, John, there is an investigation\n8 going on. I have nothing to talk to you. That's it.\n9 I said, Okay.\n10 Q. He didn't give you any information as to --\n11 A. No, not a word.\n12 Q. Has anybody else contacted you from\n13 Mr. Epstein or his organization, his assistants, his\n14 attorney?\n15 A. No, no, no.\n16 Q. Anyone that works for his attorney?\n17 A. For his attorney? Yes. For his attorney,\n18 the present attorney? Yes. That was an investigator\n19 that it was investigated on his side, I can't remember\n20 his name, but I understand it was from Roy Black's\n21 office. That was his attorney. And he -- this\n22 investigator basically asked me the same questions,\n23 exactly the same questions: What did I know, what did I\n24 know.\n25 Q. When did this happen?\n\nJ. CONSOR & ASSOCIATES REPORTING & TRANSCRIPTION\n561.835.9738\nPage 18 of 100 Public Records Request No.: 17-295\n07/26/17 DOJ-OGR-00031957",
  "text_blocks": [
    {
      "type": "printed",
      "content": "Page 17",
      "position": "header"
    },
    {
      "type": "printed",
      "content": "1 Before I even spoke to you.\n2 Q. Just when you found the card?\n3 A. When I find the card, I get scared. I\n4 said, What's going on now? Why are you bothering me now\n5 in my house?\n6 That's why I called him.\n7 He said, John, there is an investigation\n8 going on. I have nothing to talk to you. That's it.\n9 I said, Okay.\n10 Q. He didn't give you any information as to --\n11 A. No, not a word.\n12 Q. Has anybody else contacted you from\n13 Mr. Epstein or his organization, his assistants, his\n14 attorney?\n15 A. No, no, no.\n16 Q. Anyone that works for his attorney?\n17 A. For his attorney? Yes. For his attorney,\n18 the present attorney? Yes. That was an investigator\n19 that it was investigated on his side, I can't remember\n20 his name, but I understand it was from Roy Black's\n21 office. That was his attorney. And he -- this\n22 investigator basically asked me the same questions,\n23 exactly the same questions: What did I know, what did I\n24 know.\n25 Q. When did this happen?",
      "position": "main"
    },
    {
      "type": "printed",
      "content": "J. CONSOR & ASSOCIATES REPORTING & TRANSCRIPTION\n561.835.9738",
      "position": "footer"
    },
    {
      "type": "printed",
      "content": "Page 18 of 100 Public Records Request No.: 17-295\n07/26/17 DOJ-OGR-00031957",
      "position": "footer"
    }
  ],
  "entities": {
    "people": [
      "John",
      "Mr. Epstein",
      "Roy Black"
    ],
    "organizations": [
      "J. Consor & Associates Reporting & Transcription"
    ],
    "locations": [],
    "dates": [
      "07/26/17"
    ],
    "reference_numbers": [
      "17-295",
      "DOJ-OGR-00031957"
    ]
  },
  "additional_notes": "The document appears to be a transcription of an interview or testimony. The text is clear and legible, with no visible redactions or damage."
}