{
  "document_metadata": {
    "page_number": "7 of 13",
    "document_number": "17-295",
    "date": "12/22/2005",
    "document_type": "Myspace profile printout",
    "has_handwriting": false,
    "has_stamps": false
  },
  "full_text": "www.myspace.com/sublimehottie Page 7 of 13 The ribbon on my wrist says do not open before.... 12/22/2005 9:01 PM Jibby 2j 11/22/2005 3:25 PM samatha 11/21/2005 3:21 PM listen! i haven't school at all in the past 2 weeks with high. it's bad! pizza. 11/20/2005 6:38 PM haha i know what picture your talkin good luck at just applied there out if i got in a little after december don't know where i want to go yet. applications suck. maybe i'll be up tl have to go do hw so i'll tty!! <3 isiah 11/14/2005 7:39 AM hey i love you too i wanna come up see you guys hows evrey thing hit m you mafi ~1~ 07/26/17 Page 4 of 124 Public Records Request No.: 17-295 http://profile.myspace.com/index.cfm?fuseaction=user.viewprofile&friendID=20425696 2/14/2006 DOJ-OGR-00031725",
  "text_blocks": [
    {
      "type": "printed",
      "content": "www.myspace.com/sublimehottie",
      "position": "header"
    },
    {
      "type": "printed",
      "content": "The ribbon on my wrist says do not open before....",
      "position": "top"
    },
    {
      "type": "printed",
      "content": "Jibby 2j",
      "position": "middle"
    },
    {
      "type": "printed",
      "content": "samatha",
      "position": "middle"
    },
    {
      "type": "handwritten",
      "content": "listen! i haven't school at all in the past 2 weeks with high. it's bad!",
      "position": "middle"
    },
    {
      "type": "printed",
      "content": "pizza.",
      "position": "middle"
    },
    {
      "type": "handwritten",
      "content": "haha i know what picture your talkin good luck at just applied there out if i got in a little after december don't know where i want to go yet. applications suck. maybe i'll be up tl have to go do hw so i'll tty!! <3",
      "position": "middle"
    },
    {
      "type": "printed",
      "content": "isiah",
      "position": "middle"
    },
    {
      "type": "handwritten",
      "content": "hey i love you too i wanna come up see you guys hows evrey thing hit m you mafi ~1~",
      "position": "middle"
    },
    {
      "type": "printed",
      "content": "Page 4 of 124",
      "position": "footer"
    },
    {
      "type": "printed",
      "content": "Public Records Request No.: 17-295",
      "position": "footer"
    },
    {
      "type": "printed",
      "content": "http://profile.myspace.com/index.cfm?fuseaction=user.viewprofile&friendID=20425696",
      "position": "footer"
    },
    {
      "type": "printed",
      "content": "DOJ-OGR-00031725",
      "position": "footer"
    }
  ],
  "entities": {
    "people": [
      "Jibby",
      "samatha",
      "isiah"
    ],
    "organizations": [
      "Myspace"
    ],
    "locations": [],
    "dates": [
      "12/22/2005",
      "11/22/2005",
      "11/21/2005",
      "11/20/2005",
      "11/14/2005",
      "07/26/17",
      "2/14/2006"
    ],
    "reference_numbers": [
      "17-295",
      "20425696",
      "DOJ-OGR-00031725"
    ]
  },
  "additional_notes": "The document appears to be a printout of a Myspace profile, containing a mix of printed and handwritten text, as well as images. The content includes personal messages and comments from friends, as well as some metadata about the profile and the printout."
}