{
  "document_metadata": {
    "page_number": "1",
    "document_number": "5616404420",
    "date": "01/11/2008",
    "document_type": "Fax",
    "has_handwriting": true,
    "has_stamps": false
  },
  "full_text": "Received: 1/13/08 3:12PM; 5616404420 -> STATE ATTY OFC; Page 1 01/11/2008 21:40 5616404420 PAGE 01 Page 1 of 9 TO: Attorney Lanna Belohlavek SP: Ms. Carolyn Lowe. PRINT THIS New York nyamag.com Features The Fantasist Please place in Jeffrey Epstein File. Thank you. Accused of paying underage girls for sex, superrich money manager Jeffrey Epstein is finding that living in a dream world is dangerous—even if you can pay for it. By Philip Weiss Published Dec 10, 2007 Jeffrey Epstein is under indictment for sex crimes in Palm Beach, Florida, and I'd expected that when he came into the office of PR guru Howard Rubenstein, he would be sober and reserved. Quite the opposite. He was sparkling and ingenuous, apologizing for the half-hour lateness with a charming line—\"I never realized bow many one-way streets and no-right-turns there are in midtown. I finally got out to talk to many of my friends?\" Epstein had been supplying me the phone numbers of important scientists and financiers and media figures. \"Do you understand what an extraordinary group of people http://... Page 94 of 102 Public Records Request No.: 17-295 DOJ-OGR-00031402",
  "text_blocks": [
    {
      "type": "printed",
      "content": "New York nyamag.com",
      "position": "header"
    },
    {
      "type": "printed",
      "content": "Features",
      "position": "top"
    },
    {
      "type": "printed",
      "content": "The Fantasist",
      "position": "top"
    },
    {
      "type": "printed",
      "content": "Accused of paying underage girls for sex, superrich money manager Jeffrey Epstein is finding that living in a dream world is dangerous—even if you can pay for it.",
      "position": "middle"
    },
    {
      "type": "printed",
      "content": "By Philip Weiss Published Dec 10, 2007",
      "position": "middle"
    },
    {
      "type": "printed",
      "content": "Jeffrey Epstein is under indictment for sex crimes in Palm Beach, Florida, and I'd expected that when he came into the office of PR guru Howard Rubenstein, he would be sober and reserved. Quite the opposite. He was sparkling and ingenuous, apologizing for the half-hour lateness with a charming line—\"I never realized bow many one-way streets and no-right-turns there are in midtown. I finally got out to talk to many of my friends?\" Epstein had been supplying me the phone numbers of important scientists and financiers and media figures. \"Do you understand what an extraordinary group of people",
      "position": "bottom"
    },
    {
      "type": "handwritten",
      "content": "TO: Attorney Lanna Belohlavek SP: Ms. Carolyn Lowe. Please place in Jeffrey Epstein File. Thank you.",
      "position": "top"
    }
  ],
  "entities": {
    "people": [
      "Jeffrey Epstein",
      "Philip Weiss",
      "Howard Rubenstein",
      "Lanna Belohlavek",
      "Carolyn Lowe"
    ],
    "organizations": [
      "New York Magazine"
    ],
    "locations": [
      "Palm Beach",
      "Florida",
      "New York"
    ],
    "dates": [
      "01/11/2008",
      "Dec 10, 2007",
      "1/13/08"
    ],
    "reference_numbers": [
      "5616404420",
      "17-295",
      "DOJ-OGR-00031402"
    ]
  },
  "additional_notes": "The document appears to be a faxed copy of an article from New York Magazine. The handwritten note at the top suggests that it was sent to an attorney's office. The document is generally clear, but there are some minor creases and fax artifacts visible."
}