{
  "document_metadata": {
    "page_number": "1",
    "document_number": "17-295",
    "date": "07/26/17",
    "document_type": "Public Records Request",
    "has_handwriting": false,
    "has_stamps": false
  },
  "full_text": "www.myspace.com/ Page 1 of 2 The RadioShack Ultimate Clearance Sale Shop Now Home | Browse | Search | Invite | Film | Mail | Blog | Favorites | Forum | Groups | Events | Videos | Music | Classifieds *Twins Do Have More Fun* ~* is in your extended network Latest Blog Entry [Subscribe to this Blog] [View All Blog Entries] 's Blurbs About me: IM me.... Xxo XX IM FIXING MY PROFILE RIGHT NOW THEY KICKED ME OFF MY OLD ONE..lol Who I'd like to meet: *i already met him * ~ - *'s Friend Space * Page 58 di95 7 friends. Public Records Request No.: 17-295 Tom Mr. HuMpAgE tiffani STiNA DOJ-OGR-00032248 Last Login: 3/5/2006 View My: Pics Videos Contacting Send Message Forward to Friend Add to Friends Add to Favorites Instant Message Block User Add to Group Rank User 07/26/17",
  "text_blocks": [
    {
      "type": "printed",
      "content": "www.myspace.com/",
      "position": "header"
    },
    {
      "type": "printed",
      "content": "The RadioShack Ultimate Clearance Sale",
      "position": "header"
    },
    {
      "type": "printed",
      "content": "Home | Browse | Search | Invite | Film | Mail | Blog | Favorites | Forum | Groups | Events | Videos | Music | Classifieds",
      "position": "header"
    },
    {
      "type": "printed",
      "content": "*Twins Do Have More Fun*",
      "position": "middle"
    },
    {
      "type": "printed",
      "content": "~* is in your extended network",
      "position": "middle"
    },
    {
      "type": "printed",
      "content": "Latest Blog Entry [Subscribe to this Blog]",
      "position": "middle"
    },
    {
      "type": "printed",
      "content": "[View All Blog Entries]",
      "position": "middle"
    },
    {
      "type": "printed",
      "content": "'s Blurbs",
      "position": "middle"
    },
    {
      "type": "handwritten",
      "content": "IM me.... Xxo XX IM FIXING MY PROFILE RIGHT NOW THEY KICKED ME OFF MY OLD ONE..lol",
      "position": "middle"
    },
    {
      "type": "handwritten",
      "content": "*i already met him *",
      "position": "middle"
    },
    {
      "type": "printed",
      "content": "*'s Friend Space",
      "position": "middle"
    },
    {
      "type": "handwritten",
      "content": "* Page 58 di95 7 friends.",
      "position": "middle"
    },
    {
      "type": "printed",
      "content": "Public Records Request No.: 17-295",
      "position": "footer"
    },
    {
      "type": "printed",
      "content": "Tom Mr. HuMpAgE tiffani STiNA",
      "position": "footer"
    },
    {
      "type": "printed",
      "content": "DOJ-OGR-00032248",
      "position": "footer"
    },
    {
      "type": "printed",
      "content": "Last Login: 3/5/2006",
      "position": "middle"
    },
    {
      "type": "printed",
      "content": "View My: Pics Videos",
      "position": "middle"
    },
    {
      "type": "printed",
      "content": "Contacting Send Message Forward to Friend Add to Friends Add to Favorites Instant Message Block User Add to Group Rank User",
      "position": "middle"
    },
    {
      "type": "printed",
      "content": "07/26/17",
      "position": "footer"
    }
  ],
  "entities": {
    "people": [
      "Tom",
      "Mr. HuMpAgE",
      "tiffani",
      "STiNA"
    ],
    "organizations": [
      "RadioShack",
      "MySpace",
      "DOJ"
    ],
    "locations": [],
    "dates": [
      "3/5/2006",
      "07/26/17"
    ],
    "reference_numbers": [
      "17-295",
      "DOJ-OGR-00032248"
    ]
  },
  "additional_notes": "The document appears to be a printed copy of a MySpace profile page with some redacted information. The page includes a header with the MySpace logo and navigation links, as well as a profile section with user information and a list of friends. The document also includes a public records request number and a DOJ reference number."
}