{
  "document_metadata": {
    "page_number": "3",
    "document_number": "17-295",
    "date": "07/26/17",
    "document_type": "Public Records Request",
    "has_handwriting": false,
    "has_stamps": false
  },
  "full_text": "Myspace.com Page 3 of 3 Me and my friend Jenny (from »Post a Comment »E-Mail to a Friend »Report this Image 1 Comment(s) WHAT HEAVEN LOOKS LIKE TO ME »Post a Comment »E-Mail to a Friend »Report this Image 2 Comment(s) My boyfriend just got a cute, new puppy. Isn't she adorable? »Post a Comment »E-Mail to a Friend »Report this Image 0 Comment(s) About | FAQ | Terms | Privacy | Safety Tips | Contact Myspace | Promote! | Advertise ©2003-2006 MySpace.com All Rights Reserved. 07/26/17 Page 31 of 124 Public Records Request No.: 17-295 http://viewmorepics.myspace.com/index.cfm?fuseaction=user.viewPicture&friendID=20425696&MyToken=01ef0dd2-cc14-44... 2/20/2006 DOJ-OGR-00031752",
  "text_blocks": [
    {
      "type": "printed",
      "content": "Myspace.com",
      "position": "header"
    },
    {
      "type": "printed",
      "content": "Page 3 of 3",
      "position": "header"
    },
    {
      "type": "printed",
      "content": "Me and my friend Jenny (from »Post a Comment »E-Mail to a Friend »Report this Image 1 Comment(s)",
      "position": "middle"
    },
    {
      "type": "printed",
      "content": "WHAT HEAVEN LOOKS LIKE TO ME »Post a Comment »E-Mail to a Friend »Report this Image 2 Comment(s)",
      "position": "middle"
    },
    {
      "type": "printed",
      "content": "My boyfriend just got a cute, new puppy. Isn't she adorable? »Post a Comment »E-Mail to a Friend »Report this Image 0 Comment(s)",
      "position": "middle"
    },
    {
      "type": "printed",
      "content": "About | FAQ | Terms | Privacy | Safety Tips | Contact Myspace | Promote! | Advertise",
      "position": "footer"
    },
    {
      "type": "printed",
      "content": "©2003-2006 MySpace.com All Rights Reserved.",
      "position": "footer"
    },
    {
      "type": "printed",
      "content": "07/26/17",
      "position": "footer"
    },
    {
      "type": "printed",
      "content": "Page 31 of 124",
      "position": "footer"
    },
    {
      "type": "printed",
      "content": "Public Records Request No.: 17-295",
      "position": "footer"
    },
    {
      "type": "printed",
      "content": "http://viewmorepics.myspace.com/index.cfm?fuseaction=user.viewPicture&friendID=20425696&MyToken=01ef0dd2-cc14-44...",
      "position": "footer"
    },
    {
      "type": "printed",
      "content": "2/20/2006",
      "position": "footer"
    },
    {
      "type": "printed",
      "content": "DOJ-OGR-00031752",
      "position": "footer"
    }
  ],
  "entities": {
    "people": [
      "Jenny"
    ],
    "organizations": [
      "Myspace",
      "DOJ"
    ],
    "locations": [],
    "dates": [
      "07/26/17",
      "2/20/2006"
    ],
    "reference_numbers": [
      "17-295",
      "DOJ-OGR-00031752"
    ]
  },
  "additional_notes": "The document appears to be a printed copy of a Myspace page, with some metadata and a public records request number added to the footer."
}