{
  "document_metadata": {
    "page_number": "1",
    "document_number": "17-295",
    "date": "07/26/17",
    "document_type": "Public Records Request",
    "has_handwriting": false,
    "has_stamps": false
  },
  "full_text": "myspace.com Page 1 of 2 MySpace.com | Home The Web MySpace Get the next generation of IM Click here! Home | Browse | Search | Invite | Rank | Mail | Blog | Favorites | Forum | Groups | Events | Games | Music Back to : tp;amp;hearts;'s Profile View All Friends Listing 41-80 of 91 1 2 3 of 3 tp;amp;hearts;'s Friends... (91) WAKE UP TH.. encyclopedia My Name is.. sam SUPER RAD .. GirL From .. Ginger Another Da.. Dick Painter Someday..i.. John Jeff Brian The Fight .. D christina. Be Quiet a.. Oh SaMmY-P.. Mel-Y-ssa CharLAAAYY Dat Freaki.. Jenny &hea.. Fixious Miss Mary Shannon Keith ChicaCherr.. Will (ScR.. 07/26/17 http://home8.myspace.com/index.cfm?fuseaction=user.viewfriends&UserName=ashley%... Page 2432 Public Records Request No.: 17-295 11/14/2005 DOJ-OGR-00032745",
  "text_blocks": [
    {
      "type": "printed",
      "content": "myspace.com",
      "position": "header"
    },
    {
      "type": "printed",
      "content": "MySpace.com | Home The Web MySpace",
      "position": "header"
    },
    {
      "type": "printed",
      "content": "Get the next generation of IM Click here!",
      "position": "header"
    },
    {
      "type": "printed",
      "content": "Home | Browse | Search | Invite | Rank | Mail | Blog | Favorites | Forum | Groups | Events | Games | Music",
      "position": "header"
    },
    {
      "type": "printed",
      "content": "Back to : tp;amp;hearts;'s Profile",
      "position": "header"
    },
    {
      "type": "printed",
      "content": "View All Friends",
      "position": "header"
    },
    {
      "type": "printed",
      "content": "Listing 41-80 of 91",
      "position": "header"
    },
    {
      "type": "printed",
      "content": "1 2 3 of 3",
      "position": "header"
    },
    {
      "type": "printed",
      "content": "tp;amp;hearts;'s Friends... (91)",
      "position": "header"
    },
    {
      "type": "printed",
      "content": "WAKE UP TH.. encyclopedia My Name is.. sam SUPER RAD .. GirL From .. Ginger",
      "position": "middle"
    },
    {
      "type": "printed",
      "content": "Another Da.. Dick Painter Someday..i.. John Jeff Brian The Fight ..",
      "position": "middle"
    },
    {
      "type": "printed",
      "content": "D christina. Be Quiet a.. Oh SaMmY-P.. Mel-Y-ssa CharLAAAYY Dat Freaki..",
      "position": "middle"
    },
    {
      "type": "printed",
      "content": "Jenny &hea.. Fixious Miss Mary Shannon Keith ChicaCherr.. Will (ScR..",
      "position": "middle"
    },
    {
      "type": "printed",
      "content": "07/26/17 http://home8.myspace.com/index.cfm?fuseaction=user.viewfriends&UserName=ashley%... Page 2432 Public Records Request No.: 17-295 11/14/2005",
      "position": "footer"
    },
    {
      "type": "printed",
      "content": "DOJ-OGR-00032745",
      "position": "footer"
    }
  ],
  "entities": {
    "people": [
      "tp;amp;hearts;",
      "WAKE UP TH..",
      "encyclopedia",
      "My Name is..",
      "sam",
      "SUPER RAD ..",
      "GirL From ..",
      "Ginger",
      "Another Da..",
      "Dick Painter",
      "Someday..i..",
      "John",
      "Jeff",
      "Brian",
      "The Fight ..",
      "D",
      "christina.",
      "Be Quiet a..",
      "Oh SaMmY-P..",
      "Mel-Y-ssa",
      "CharLAAAYY",
      "Dat Freaki..",
      "Jenny &hea..",
      "Fixious",
      "Miss Mary",
      "Shannon",
      "Keith",
      "ChicaCherr..",
      "Will (ScR..",
      "ashley"
    ],
    "organizations": [
      "MySpace",
      "DOJ"
    ],
    "locations": [],
    "dates": [
      "07/26/17",
      "11/14/2005"
    ],
    "reference_numbers": [
      "17-295",
      "DOJ-OGR-00032745"
    ]
  },
  "additional_notes": "The document appears to be a printout of a MySpace profile page from 2005, with a list of friends and their profile pictures. The page has been annotated with a public records request number and date. The image quality is good, with clear text and images."
}