{
  "document_metadata": {
    "page_number": null,
    "document_number": "DOJ-OGR-00032409",
    "date": "07/26/17",
    "document_type": "Important Message Forms",
    "has_handwriting": true,
    "has_stamps": false
  },
  "full_text": "IMPORTANT MESSAGE FOR: OF: DATE: TIME: A.M. P.M. OF: PHONE/MOBILE TELEPHONED PLEASE CALL CAME TO SEE YOU WILL CALL AGAIN WANTS TO SEE YOU RUSH RETURNED YOUR CALL SPECIAL ATTENTION MESSAGE SIGNED FOR: OE DATE: Sue Hamblin TIME: 9.45 A.M. P.M. 212 972 4006 PLEASE CALL MESSAGE SIGNED FOR: OE DATE: TIME: 3.25 A.M. P.M. TELEPHONED Herfriend got ina accident friday & she didnt have and minute left on her phone - she couldn't call long. discussed weather to call SIGNED FOR: OE DATE: 6.00 M - in office TIME: 9.30 A.M. P.M. 212 258 4999 MESSAGE SIGNED FOR: JS DATE: Katherine M. TIME: 3.30 A.M. P.M. 917 204 9696 PLEASE CALL MESSAGE please call SIGNED Public Records Request No.: 17-295 DOJ-OGR-00032409",
  "text_blocks": [
    {
      "type": "printed",
      "content": "IMPORTANT MESSAGE FOR: OF: DATE: TIME: A.M. P.M. OF: PHONE/MOBILE TELEPHONED PLEASE CALL CAME TO SEE YOU WILL CALL AGAIN WANTS TO SEE YOU RUSH RETURNED YOUR CALL SPECIAL ATTENTION MESSAGE SIGNED",
      "position": "header"
    },
    {
      "type": "handwritten",
      "content": "FOR: OE DATE: Sue Hamblin TIME: 9.45 A.M. P.M. 212 972 4006 PLEASE CALL",
      "position": "top"
    },
    {
      "type": "handwritten",
      "content": "FOR: OE DATE: TIME: 3.25 A.M. P.M. TELEPHONED Herfriend got ina accident friday & she didnt have and minute left on her phone - she couldn't call long. discussed weather to call",
      "position": "top"
    },
    {
      "type": "handwritten",
      "content": "FOR: OE DATE: 6.00 M - in office TIME: 9.30 A.M. P.M. 212 258 4999",
      "position": "middle"
    },
    {
      "type": "handwritten",
      "content": "FOR: JS DATE: Katherine M. TIME: 3.30 A.M. P.M. 917 204 9696 PLEASE CALL MESSAGE please call",
      "position": "bottom"
    },
    {
      "type": "printed",
      "content": "Public Records Request No.: 17-295",
      "position": "footer"
    },
    {
      "type": "printed",
      "content": "DOJ-OGR-00032409",
      "position": "footer"
    }
  ],
  "entities": {
    "people": [
      "Sue Hamblin",
      "Katherine M."
    ],
    "organizations": [],
    "locations": [],
    "dates": [
      "07/26/17",
      "Friday"
    ],
    "reference_numbers": [
      "17-295",
      "DOJ-OGR-00032409",
      "212 972 4006",
      "212 258 4999",
      "917 204 9696"
    ]
  },
  "additional_notes": "The document appears to be a scan of a notepad containing four 'Important Message' forms. The forms contain handwritten notes with phone messages and contact information. The document is dated 07/26/17 and has a Public Records Request No.: 17-295."
}