{
  "document_metadata": {
    "page_number": "82",
    "document_number": "17-295",
    "date": "07/26/17",
    "document_type": "Important Message Forms",
    "has_handwriting": true,
    "has_stamps": false
  },
  "full_text": "IMPORTANT MESSAGE FOR MR ERN DATE TIME A.M. P.M. M OF PHONE/MOBILE TELEPHONED PLEASE CALL CAME TO SEE YOU WILL CALL AGAIN WANTS TO SEE YOU RUSH RETURNED YOUR CALL SPECIAL ATTENTION MESSAGE SIGNED a 1184 IMPORTANT MESSAGE FOR JENNY C DATE 6.6.19 TIME 2.10 A.M. P.M. M OF PHONE/MOBILE TELEPHONED PLEASE CALL CAME TO SEE YOU WILL CALL AGAIN WANTS TO SEE YOU RUSH RETURNED YOUR CALL SPECIAL ATTENTION MESSAGE it is very important if you need SIGNED a 1184 IMPORTANT MESSAGE FOR MR EASTIN DATE 05.02 TIME 4.45 A.M. P.M. M TATIAN OF PHONE/MOBILE # 2010237 TELEPHONED PLEASE CALL CAME TO SEE YOU WILL CALL AGAIN WANTS TO SEE YOU RUSH RETURNED YOUR CALL SPECIAL ATTENTION MESSAGE 07/26/17 SIGNED Page 82 of 100 a 1184 IMPORTANT MESSAGE FOR JE DATE TIME 3.15 A.M. P.M. M Condy Andriano OF PHONE/MOBILE 8560-7047 TELEPHONED PLEASE CALL CAME TO SEE YOU WILL CALL AGAIN WANTS TO SEE YOU RUSH RETURNED YOUR CALL SPECIAL ATTENTION MESSAGE Jim wants to know Public Records Request No.: 17-295 SIGNED a 1184 DOJ-OGR-00032021",
  "text_blocks": [
    {
      "type": "printed",
      "content": "IMPORTANT MESSAGE",
      "position": "header"
    },
    {
      "type": "handwritten",
      "content": "MR ERN",
      "position": "top"
    },
    {
      "type": "printed",
      "content": "FOR DATE TIME A.M. P.M. M OF PHONE/MOBILE",
      "position": "top"
    },
    {
      "type": "printed",
      "content": "TELEPHONED PLEASE CALL CAME TO SEE YOU WILL CALL AGAIN WANTS TO SEE YOU RUSH RETURNED YOUR CALL SPECIAL ATTENTION",
      "position": "middle"
    },
    {
      "type": "printed",
      "content": "MESSAGE",
      "position": "middle"
    },
    {
      "type": "handwritten",
      "content": "it is very important if you need",
      "position": "middle"
    },
    {
      "type": "printed",
      "content": "SIGNED",
      "position": "bottom"
    },
    {
      "type": "handwritten",
      "content": "JENNY C 6.6.19 2.10",
      "position": "top"
    },
    {
      "type": "handwritten",
      "content": "MR EASTIN 05.02 4.45 TATIAN # 2010237",
      "position": "top"
    },
    {
      "type": "handwritten",
      "content": "JE Condy Andriano 8560-7047 Jim wants to know",
      "position": "top"
    },
    {
      "type": "printed",
      "content": "Public Records Request No.: 17-295",
      "position": "footer"
    },
    {
      "type": "printed",
      "content": "Page 82 of 100",
      "position": "footer"
    },
    {
      "type": "printed",
      "content": "07/26/17",
      "position": "footer"
    },
    {
      "type": "printed",
      "content": "DOJ-OGR-00032021",
      "position": "footer"
    }
  ],
  "entities": {
    "people": [
      "MR ERN",
      "JENNY C",
      "MR EASTIN",
      "JE",
      "TATIAN",
      "Condy Andriano",
      "Jim"
    ],
    "organizations": [],
    "locations": [],
    "dates": [
      "6.6.19",
      "05.02",
      "07/26/17"
    ],
    "reference_numbers": [
      "17-295",
      "2010237",
      "8560-7047",
      "DOJ-OGR-00032021"
    ]
  },
  "additional_notes": "The document is a scanned image of four 'Important Message' forms. The forms contain handwritten notes and are likely related to a public records request."
}