{
  "document_metadata": {
    "page_number": "5 of 10",
    "document_number": "DOJ-OGR-00031512",
    "date": "07/26/17",
    "document_type": "Myspace profile and messages",
    "has_handwriting": false,
    "has_stamps": false
  },
  "full_text": "www.myspace.com/iloveanirishboi Page 5 of 10 Hate anyone: I dislike a few Take This Survey CREATE YOUR OWNI - or - GET PAID TO TAKE SURVEYS! Status: Orientation: Hometown: Religion: Zodiac Sign: Smoke / Drink: Children: Income: Details you stayin . for a long time . lol .. he said \"thats fine with me\" lol .. but yea i hope to see you soon and dont forget to call when you get to atlanta .. lol .. love ya alot!! Daddy's LIL' Girl 3/27/2006 6:08 PM Hey Guess what me and jonathan went to the movies and had the best time and omg i love him 4e and then after that he came over for a little while and hung out and TOM is ONE MONTH! im EXSTATIC .. lol Well COngRadS on Tom .. Let me be the first to say : \"WELCOME BACK\" Oh yeah and how about you come to Wellington .. and I BET I WILL GET U BACK INTO DANCING?!! xOox.. i was to excited to keep it in so i told you about our night .. bye !!! mary shake your ziggy zong [&;] 3/27/2006 12:39 PM we are taking pictures tonight =] yay.. don't forget black or blue.. cant wait to see you again!!! i love yo poo nikxx MeG-a-LyNn 3/27/2006 12:07 PM kkkk... lol... megan Daddy's LIL' Girl 3/27/2006 10:05 AM Hey It's been awesome talking 2 you i cant wait to meet you in person lol .. And were going to be beach buddies lol .. and mark my words im going to make Public Records Request No.: 1 -295 4/4/2006 http://profile.myspace.com/index.cfm?fuseaction=user.viewprofile&friendID=65739759 Page 102 of 111 DOJ-OGR-00031512",
  "text_blocks": [
    {
      "type": "printed",
      "content": "www.myspace.com/iloveanirishboi",
      "position": "header"
    },
    {
      "type": "printed",
      "content": "Page 5 of 10",
      "position": "header"
    },
    {
      "type": "printed",
      "content": "Hate anyone: I dislike a few Take This Survey CREATE YOUR OWNI - or - GET PAID TO TAKE SURVEYS!",
      "position": "top"
    },
    {
      "type": "printed",
      "content": "Status: Orientation: Hometown: Religion: Zodiac Sign: Smoke / Drink: Children: Income: Details",
      "position": "top"
    },
    {
      "type": "handwritten",
      "content": "you stayin . for a long time . lol .. he said \"thats fine with me\" lol .. but yea i hope to see you soon and dont forget to call when you get to atlanta .. lol .. love ya alot!!",
      "position": "middle"
    },
    {
      "type": "printed",
      "content": "Daddy's LIL' Girl 3/27/2006 6:08 PM",
      "position": "middle"
    },
    {
      "type": "handwritten",
      "content": "Hey Guess what me and jonathan went to the movies and had the best time and omg i love him 4e and then after that he came over for a little while and hung out and TOM is ONE MONTH! im EXSTATIC .. lol Well COngRadS on Tom .. Let me be the first to say : \"WELCOME BACK\" Oh yeah and how about you come to Wellington .. and I BET I WILL GET U BACK INTO DANCING?!! xOox.. i was to excited to keep it in so i told you about our night .. bye !!!",
      "position": "middle"
    },
    {
      "type": "printed",
      "content": "mary",
      "position": "middle"
    },
    {
      "type": "printed",
      "content": "shake your ziggy zong [&;] 3/27/2006 12:39 PM",
      "position": "middle"
    },
    {
      "type": "handwritten",
      "content": "we are taking pictures tonight =] yay.. don't forget black or blue.. cant wait to see you again!!! i love yo poo",
      "position": "middle"
    },
    {
      "type": "printed",
      "content": "nikxx",
      "position": "middle"
    },
    {
      "type": "printed",
      "content": "MeG-a-LyNn 3/27/2006 12:07 PM",
      "position": "middle"
    },
    {
      "type": "handwritten",
      "content": "kkkk... lol...",
      "position": "middle"
    },
    {
      "type": "printed",
      "content": "megan",
      "position": "middle"
    },
    {
      "type": "printed",
      "content": "Daddy's LIL' Girl 3/27/2006 10:05 AM",
      "position": "bottom"
    },
    {
      "type": "handwritten",
      "content": "Hey It's been awesome talking 2 you i cant wait to meet you in person lol .. And were going to be beach buddies lol .. and mark my words im going to make",
      "position": "bottom"
    },
    {
      "type": "printed",
      "content": "Public Records Request No.: 1 -295 4/4/2006",
      "position": "footer"
    },
    {
      "type": "printed",
      "content": "http://profile.myspace.com/index.cfm?fuseaction=user.viewprofile&friendID=65739759",
      "position": "footer"
    },
    {
      "type": "printed",
      "content": "Page 102 of 111",
      "position": "footer"
    },
    {
      "type": "printed",
      "content": "DOJ-OGR-00031512",
      "position": "footer"
    }
  ],
  "entities": {
    "people": [
      "jonathan",
      "mary",
      "nikxx",
      "MeG-a-LyNn",
      "megan"
    ],
    "organizations": [],
    "locations": [
      "atlanta",
      "Wellington"
    ],
    "dates": [
      "3/27/2006",
      "4/4/2006",
      "07/26/17"
    ],
    "reference_numbers": [
      "65739759",
      "DOJ-OGR-00031512",
      "1-295"
    ]
  },
  "additional_notes": "The document appears to be a printout of a Myspace profile and messages. The text is a mix of printed and handwritten content. The document has a header and footer with page numbers and a URL."
}