{
  "document_metadata": {
    "page_number": "13",
    "document_number": null,
    "date": null,
    "document_type": "Donation List",
    "has_handwriting": false,
    "has_stamps": false
  },
  "full_text": "Albuquerque Tribune Online Page 13 of 28 $10,000 Integrated Control Systems Inc., Albuquerque Conservation consultants $10,000 International Brotherhood of Electrical Workers, Washington, D.C. Labor committee $10,000 John M. Eaves, Albuquerque Attorney $10,000 Kandace Blanchard, Albuquerque Executive clinical director $10,000 Kathy Lang, Corrales Not working $10,000 Kewa Gas Limited, Santa Fe Energy $10,000 Los Alamitos Race Course, Los Alamitos, Calif. Gambling $10,000 New Mexico Conservation Voters Alliance, Albuquerque Political committee $10,000 Orville D. McDonald, Albuquerque Investor $10,000 Paseo Del Norte Limited Partnership, Santa Fe Real estate $10,000 Paul Blanchard, Albuquerque Business owner $10,000 Peabody Holding Company, Kayenta, Ariz. Energy $10,000 PHP Holdings Inc., Tampa, Fla. Investments $10,000 Pia Salazar, Albuquerque Attorney $10,000 Acoma Pueblo, Acoma Pueblo American Indian Pueblo $10,000 Pojoaque Pueblo, Santa Fe American Indian Pueblo http://www.abqtrib.com/archives/news02/12070_pge_28_idonate.shtml Public Records Request No.: 17-2953/7/2006 Page 28 of 38 DOJ-OGR-00031243",
  "text_blocks": [
    {
      "type": "printed",
      "content": "Albuquerque Tribune Online",
      "position": "header"
    },
    {
      "type": "printed",
      "content": "Page 13 of 28",
      "position": "header"
    },
    {
      "type": "printed",
      "content": "$10,000 Integrated Control Systems Inc., Albuquerque Conservation consultants $10,000 International Brotherhood of Electrical Workers, Washington, D.C. Labor committee $10,000 John M. Eaves, Albuquerque Attorney $10,000 Kandace Blanchard, Albuquerque Executive clinical director $10,000 Kathy Lang, Corrales Not working $10,000 Kewa Gas Limited, Santa Fe Energy $10,000 Los Alamitos Race Course, Los Alamitos, Calif. Gambling $10,000 New Mexico Conservation Voters Alliance, Albuquerque Political committee $10,000 Orville D. McDonald, Albuquerque Investor $10,000 Paseo Del Norte Limited Partnership, Santa Fe Real estate $10,000 Paul Blanchard, Albuquerque Business owner $10,000 Peabody Holding Company, Kayenta, Ariz. Energy $10,000 PHP Holdings Inc., Tampa, Fla. Investments $10,000 Pia Salazar, Albuquerque Attorney $10,000 Acoma Pueblo, Acoma Pueblo American Indian Pueblo $10,000 Pojoaque Pueblo, Santa Fe American Indian Pueblo",
      "position": "middle"
    },
    {
      "type": "printed",
      "content": "http://www.abqtrib.com/archives/news02/12070_pge_28_idonate.shtml Public Records Request No.: 17-2953/7/2006 Page 28 of 38 DOJ-OGR-00031243",
      "position": "footer"
    }
  ],
  "entities": {
    "people": [
      "John M. Eaves",
      "Kandace Blanchard",
      "Kathy Lang",
      "Orville D. McDonald",
      "Paul Blanchard",
      "Pia Salazar"
    ],
    "organizations": [
      "Integrated Control Systems Inc.",
      "International Brotherhood of Electrical Workers",
      "New Mexico Conservation Voters Alliance",
      "Paseo Del Norte Limited Partnership",
      "Peabody Holding Company",
      "PHP Holdings Inc.",
      "Acoma Pueblo",
      "Pojoaque Pueblo"
    ],
    "locations": [
      "Albuquerque",
      "Washington, D.C.",
      "Corrales",
      "Santa Fe",
      "Los Alamitos, Calif.",
      "Kayenta, Ariz.",
      "Tampa, Fla."
    ],
    "dates": [
      "7/2006"
    ],
    "reference_numbers": [
      "17-2953",
      "DOJ-OGR-00031243"
    ]
  },
  "additional_notes": "The document appears to be a list of donations, likely from a news article or public records request. The page is clean and well-formatted, with clear headings and bullet points."
}