{
  "document_metadata": {
    "page_number": "1 of 9",
    "document_number": "DOJ-OGR-00032093",
    "date": "April 10, 2003",
    "document_type": "List of Trilateral Commission Members",
    "has_handwriting": true,
    "has_stamps": false
  },
  "full_text": "Trilateral Commission Members April 10, 2003 Krister Ahlstrom, Chairman, Ahlstrom Corp. Helsinki Madelaine K. Albright, former Secretary of State Paul Arthur Allaire, Chairman and Chief Executive Officer Xerox Corporation Graham Allison, Director, Belfer Center for Science and International Affairs, Prof. Of Gov., Harvard. Edmond Alphandery, Chairman, Caisse Nationale de Prevoyance, Paris Dwayne O. Andreas, Chairman of the Board, Archer Daniels Midland Company Stelios Argyros, former Member of the European Parliament Michael Armacost, President, The Brookings Institution; former U.S. Ambassador to Japan Jarzy Baczynsk, editor-in-chief, Polityka, Warsaw Euan Baird, Chairman, Schumberger Limited Piero Bassetti, former Chairman, Chamber of Commerce and Industry of Milan Riley P. Bechtel, Chairman and Chief Executive Officer Bechtel Group, Inc. Erik Belfrage, senior vice President, Skandinaviska Ensklikda Banken, Stockholm C. Fred Bergsten, Director, Institute for International Economics; former U.S. Assistant Secretary of the Treasury for International Affairs Susan V. Berresford, President, Ford Foundation Carl Bildt, Member of Swedish Parliament Lord Conrad M. Black of Crossharbour, Chairman of Hollinger International Geoffrey T. Boisi, vice Chairman, JPMorgan Chase Stephen W. Bosworth, former ambassador to the Republic of Korea Ana Patricia Botin, Chairman, Banesto, Madrid Jacques Bougie, President and Chief Executive Officer, Alcoa Aluminum Limited, Montreal Jorge Braga de Macedo, President of the Development Center, Paris Lord Brittan, vice Chairman, UBS Warburg, London Harold Brown, Counselor, Center for Strategic and International Studies; former U.S. Secretary of State John H. Bryan, Chairman and Chief Executive Officer Sara Lee Corporation Zbigniew Brzezinski, Counselor Center for Strategic and International Studies; Robert Osgood Professor of American Foreign Affairs, Paul Nitze School of Advanced International Studies, Johns Hopkins University; former U.S. Assistant to the President for National Security Affairs Robin Buchanan, senior partner, Brain & Company, London James E. Burke, Chairman, CEO Em., Johnson & Johnson Sven Burmester, writer and explorer, Denmark George Herbert Walker Bush, former President of the USA D. Wayne Calloway, Chairman, CEO, Pepsico Kurt Campbell, Senior Vice President and Director, International Security Program, CSIS Frank C. Carlucci, Vice Chmn., The Carlyle Group Herve de Carmoy, partner, Rhone Group, New York & Paris Gerhard Casper, President Emeritus, Stanford University http://www.biblebelievers.org.au/weektc.htmPage 54 of 151 Public Records Request No.: 42932005 DOJ-OGR-00032093",
  "text_blocks": [
    {
      "type": "printed",
      "content": "Trilateral Commission Members April 10, 2003",
      "position": "header"
    },
    {
      "type": "printed",
      "content": "List of Trilateral Commission Members",
      "position": "body"
    },
    {
      "type": "handwritten",
      "content": "42932005",
      "position": "footer"
    },
    {
      "type": "printed",
      "content": "Public Records Request No.: 42932005",
      "position": "footer"
    },
    {
      "type": "printed",
      "content": "DOJ-OGR-00032093",
      "position": "footer"
    }
  ],
  "entities": {
    "people": [
      "Krister Ahlstrom",
      "Madelaine K. Albright",
      "Paul Arthur Allaire",
      "Graham Allison",
      "Edmond Alphandery",
      "Dwayne O. Andreas",
      "Stelios Argyros",
      "Michael Armacost",
      "Jarzy Baczynsk",
      "Euan Baird",
      "Piero Bassetti",
      "Riley P. Bechtel",
      "Erik Belfrage",
      "C. Fred Bergsten",
      "Susan V. Berresford",
      "Carl Bildt",
      "Lord Conrad M. Black",
      "Geoffrey T. Boisi",
      "Stephen W. Bosworth",
      "Ana Patricia Botin",
      "Jacques Bougie",
      "Jorge Braga de Macedo",
      "Lord Brittan",
      "Harold Brown",
      "John H. Bryan",
      "Zbigniew Brzezinski",
      "Robin Buchanan",
      "James E. Burke",
      "Sven Burmester",
      "George Herbert Walker Bush",
      "D. Wayne Calloway",
      "Kurt Campbell",
      "Frank C. Carlucci",
      "Herve de Carmoy",
      "Gerhard Casper"
    ],
    "organizations": [
      "Ahlstrom Corp.",
      "Xerox Corporation",
      "Belfer Center for Science and International Affairs",
      "Caisse Nationale de Prevoyance",
      "Archer Daniels Midland Company",
      "The Brookings Institution",
      "Polityka",
      "Schumberger Limited",
      "Chamber of Commerce and Industry of Milan",
      "Bechtel Group, Inc.",
      "Skandinaviska Ensklikda Banken",
      "Institute for International Economics",
      "Ford Foundation",
      "JPMorgan Chase",
      "Banesto",
      "Alcoa Aluminum Limited",
      "Development Center",
      "UBS Warburg",
      "Center for Strategic and International Studies",
      "Sara Lee Corporation",
      "Paul Nitze School of Advanced International Studies",
      "Johnson & Johnson",
      "Pepsico",
      "CSIS",
      "The Carlyle Group",
      "Rhone Group",
      "Stanford University"
    ],
    "locations": [
      "Helsinki",
      "Harvard",
      "Paris",
      "European Parliament",
      "Japan",
      "Warsaw",
      "Milan",
      "Stockholm",
      "Sweden",
      "Madrid",
      "Montreal",
      "London",
      "Denmark",
      "USA",
      "New York"
    ],
    "dates": [
      "April 10, 2003",
      "42932005"
    ],
    "reference_numbers": [
      "DOJ-OGR-00032093",
      "42932005"
    ]
  },
  "additional_notes": "The document appears to be a list of Trilateral Commission Members as of April 10, 2003. The list includes names, titles, and affiliations of the members. The document has a handwritten public records request number at the bottom."
}