{
  "document_metadata": {
    "page_number": "2116",
    "document_number": "DOJ-OGR-00032429",
    "date": "07/26/17",
    "document_type": "Important Message Forms",
    "has_handwriting": true,
    "has_stamps": false
  },
  "full_text": "IMPORTANT MESSAGE FOR: Ms. Montwell DATE 9/08 TIME 10 A.M. P.M. M HARRY OF PHONE AREA CODE NUMBER EXTENSION TELEPHONED PLEASE CALL CAME TO SEE YOU WILL CALL AGAIN WANTS TO SEE YOU RUSH RETURNED YOUR CALL SPECIAL ATTENTION MESSAGE Weeks up at 3PM? Please confirm SIGNED 1184 IMPORTANT MESSAGE FOR: Mr. McGrath DATE 6/ TIME 1:40 A.M. P.M. M OF PHONE AREA CODE NUMBER EXTENSION TELEPHONED X PLEASE CALL CAME TO SEE YOU WILL CALL AGAIN WANTS TO SEE YOU RUSH RETURNED YOUR CALL SPECIAL ATTENTION MESSAGE I am waiting for J.T. Latterdale is trying to call about backhoe on lunch break and will call back later. He is the same guy that did a demo for J.E. SIGNED 1184 IMPORTANT MESSAGE FOR: GM DATE 1/9 TIME 9:20 A.M. P.M. M MR HERVAN PELS OF PHONE AREA CODE NUMBER EXTENSION TELEPHONED PLEASE CALL CAME TO SEE YOU WILL CALL AGAIN WANTS TO SEE YOU RUSH RETURNED YOUR CALL SPECIAL ATTENTION MESSAGE SIGNED 07/26/17 1184 Page 2116 IMPORTANT MESSAGE FOR: DATE TIME A.M. P.M. M OF PHONE AREA CODE NUMBER EXTENSION TELEPHONED PLEASE CALL CAME TO SEE YOU WILL CALL AGAIN WANTS TO SEE YOU RUSH RETURNED YOUR CALL SPECIAL ATTENTION MESSAGE SIGNED 1184 Public Records Request No.: 17-295 DOJ-OGR-00032429",
  "text_blocks": [
    {
      "type": "printed",
      "content": "IMPORTANT MESSAGE",
      "position": "header"
    },
    {
      "type": "handwritten",
      "content": "Ms. Montwell 9/08 10 A.M. HARRY Weeks up at 3PM? Please confirm",
      "position": "middle"
    },
    {
      "type": "printed",
      "content": "TELEPHONED PLEASE CALL CAME TO SEE YOU WILL CALL AGAIN WANTS TO SEE YOU RUSH RETURNED YOUR CALL SPECIAL ATTENTION",
      "position": "middle"
    },
    {
      "type": "handwritten",
      "content": "Mr. McGrath 6/ 1:40 P.M. I am waiting for J.T. Latterdale is trying to call about backhoe on lunch break and will call back later. He is the same guy that did a demo for J.E.",
      "position": "middle"
    },
    {
      "type": "handwritten",
      "content": "GM 1/9 9:20 P.M. MR HERVAN PELS",
      "position": "middle"
    },
    {
      "type": "printed",
      "content": "Public Records Request No.: 17-295",
      "position": "footer"
    },
    {
      "type": "printed",
      "content": "DOJ-OGR-00032429",
      "position": "footer"
    }
  ],
  "entities": {
    "people": [
      "Ms. Montwell",
      "HARRY",
      "Mr. McGrath",
      "J.T.",
      "Latterdale",
      "J.E.",
      "MR HERVAN PELS"
    ],
    "organizations": [],
    "locations": [],
    "dates": [
      "9/08",
      "6/",
      "1/9",
      "07/26/17"
    ],
    "reference_numbers": [
      "17-295",
      "DOJ-OGR-00032429"
    ]
  },
  "additional_notes": "The document is a scan of a page containing four 'Important Message' forms, likely from a business or organizational setting. The forms are filled out with handwritten notes and contain various messages and phone call information. The page is dated 07/26/17 and has a document number DOJ-OGR-00032429."
}