{
  "document_metadata": {
    "page_number": "2329",
    "document_number": "17-295",
    "date": "07/26/17",
    "document_type": "Public Records Request",
    "has_handwriting": false,
    "has_stamps": false
  },
  "full_text": "I don't talk to fucking cops and I'm not talking to you\n[Riley] we're not cops\nYou need to leave. Get the fuck off my property, leave now\n[Riley] there is no need to be hostile. We are not cops. We are just trying to learn the truth\nGet the fuck off my property, What, you're still standing here\n[Riley] We're leaving but we don't understand why you're so hostile\nYou have no right to be here. I moved. All that shit is behind me in another world so get the fuck out of here\ngo back inside the house and Mary Parker came outside on the porch.\n[Riley] Ma'am we're not being hostile. We're here just to learn the truth.\n[Parker] Look, is a good girl and she left down there. We're trying to sort things out now and hire her an attorney\n[Riley] I understand but we're not the bad guys and we're not cops\n[Parker] Okay, but she doesn't want to talk with you and you really have no right being here on my property this time of night\n07/26/17 Page 2329 Public Records Request No.: 17-295 DOJ-OGR-00032642",
  "text_blocks": [
    {
      "type": "printed",
      "content": "I don't talk to fucking cops and I'm not talking to you",
      "position": "top"
    },
    {
      "type": "printed",
      "content": "[Riley] we're not cops",
      "position": "top"
    },
    {
      "type": "printed",
      "content": "You need to leave. Get the fuck off my property, leave now",
      "position": "top"
    },
    {
      "type": "printed",
      "content": "[Riley] there is no need to be hostile. We are not cops. We are just trying to learn the truth",
      "position": "top"
    },
    {
      "type": "printed",
      "content": "Get the fuck off my property, What, you're still standing here",
      "position": "top"
    },
    {
      "type": "printed",
      "content": "[Riley] We're leaving but we don't understand why you're so hostile",
      "position": "top"
    },
    {
      "type": "printed",
      "content": "You have no right to be here. I moved. All that shit is behind me in another world so get the fuck out of here",
      "position": "top"
    },
    {
      "type": "printed",
      "content": "goes back inside the house and Mary Parker came outside on the porch.",
      "position": "top"
    },
    {
      "type": "printed",
      "content": "[Riley] Ma'am we're not being hostile. We're here just to learn the truth.",
      "position": "top"
    },
    {
      "type": "printed",
      "content": "[Parker] Look, is a good girl and she left down there. We're trying to sort things out now and hire her an attorney",
      "position": "top"
    },
    {
      "type": "printed",
      "content": "[Riley] I understand but we're not the bad guys and we're not cops",
      "position": "top"
    },
    {
      "type": "printed",
      "content": "[Parker] Okay, but she doesn't want to talk with you and you really have no right being here on my property this time of night",
      "position": "top"
    },
    {
      "type": "printed",
      "content": "07/26/17 Page 2329 Public Records Request No.: 17-295 DOJ-OGR-00032642",
      "position": "footer"
    }
  ],
  "entities": {
    "people": [
      "Riley",
      "Mary Parker"
    ],
    "organizations": [],
    "locations": [],
    "dates": [
      "07/26/17"
    ],
    "reference_numbers": [
      "17-295",
      "DOJ-OGR-00032642"
    ]
  },
  "additional_notes": "The document appears to be a transcript of a conversation between law enforcement or investigators and a private citizen. The tone is confrontational, with the citizen refusing to cooperate. The document has been redacted to remove certain names and details."
}