{
  "document_metadata": {
    "page_number": "1 of 2",
    "document_number": null,
    "date": "Oct 20, 2002",
    "document_type": "Newspaper Article",
    "has_handwriting": false,
    "has_stamps": false
  },
  "full_text": "MURKY WORLD OF CLINTON PAL\nNew York Post. New York, N.Y.: Oct 20, 2002. pg. 010\nAbstract (Document Summary)\nLeslie Wexner, founder and chair of the Limited clothing-store chain, bought the place in 1989 for $15,000. [Jeffrey Epstein]'s mentor and one of his clients, Wexner is rumored to have sold the palatial digs to him for just $1. Epstein quickly spent $10 million to gut the place and completely redo the interior.\nSOCIALITE Samantha Boardman ditched her beau, Conde Nast editorial director James Truman, last year for man-about-town Todd Meister. According to our spies, Boardman ditched Meister after she caught him in flagrante with a 19-year-old coed. But don't feel too bad for her. Women's Wear Daily reports Boardman has a new man - Vanity Fair's Graydon Carter. Truman must not be too pleased. When Boardman dumped him, he needed to recuperate at a Buddhist retreat upstate. Editorial meetings at Conde Nast must be a hoot these days.\n\"DISCO Bloodbath\" author James St. James is following up his notorious tell-all about killer club kid Michael Alig with another true-crime tome. He's shopping around \"Killer Grandpa,\" his investigation into a lynching that his grandfather led in 1935. \"My grandfather was a sheriff in Fort Lauderdale, and he lynched a black man that allegedly raped a white woman,\" James told us. \"About 100 people gathered to watch, and they passed a gun around and everyone took a shot at the body. It became this big town secret, and I write about what really happened.\" James, a 1980s club kid who fell in with Alig's inner circle, is played by Seth Green in \"Party Monster,\" the movie adaptation of \"Disco Bloodbath.\" But James said he was \"shocked\" when he watched a few scenes of Green mincing it up with Macaulay Culkin, who plays Alig. \"I didn't know I was so gay! I thought I was more like Steve McQueen, but Seth is flouncing around the whole time. Seth is much cuter than me, actually, and looks better in drag.\"\nFull Text (1147 words)\n(Copyright 2002, The New York Post. All Rights Reserved)\nPAGE SIX'S scoop last month that mysterious money manager Jeffrey Epstein had flown Bill Clinton, Chris Tucker and Kevin Spacey to Africa on his private 727 has sent journalists all over town trying to find out just who Epstein really is.\nVanity Fair has a reporter on his trail, but New York magazine beats them to the punch with a feature this week on Epstein's strange history.\nEpstein, 49, a former Dalton School math teacher from Coney Island, is said to manage $15 billion for super-wealthy clients he'll only take on if they have at least $1 billion in assets.\n\"According to people who know him,\" New York reports, \"if you were worth $700 million and felt the need for the services of Epstein & Co., you would receive a not-so-polite no-thank-you.\"\nNoted mergers/acquisitions lawyer Dennis Block of Cadwalader, Wickersham & Taft recalls trying to give Epstein a client whose funds were below the $1 billion cutoff.\n\"I sent him a $500 million client a few years ago and he wouldn't take him,\" Block reports. \"Said the account was too small. Both the client and I were amazed. But that's Jeffrey.\"\nMost Wall Streeters, however, aren't even certain what Epstein actually does for a living. \"My belief is that Jeff maintains some sort of money-management firm, though you won't get a straight answer from him,\" says one powerful investor. \"He once told me that he has 300 people working for him, and I've also heard he manages Rockefeller money. But one never knows. It's like looking at the Wizard of Oz.\"\nSome say that Epstein once quit his seat on the board of the Rockefeller Institute because he hates wearing a suit, supposedly telling a friend, \"It feels like wearing a dress.\"\nhttp://pqasb.pqarchiver.com/nypost/222493931.html?MAC=90db373aedcb1e36a203f8bd_11/30/2005\nPage 4 of 15\nPublic Records Request No.: 17-295\nDOJ-OGR-00032080",
  "text_blocks": [
    {
      "type": "printed",
      "content": "MURKY WORLD OF CLINTON PAL\nNew York Post. New York, N.Y.: Oct 20, 2002. pg. 010",
      "position": "header"
    },
    {
      "type": "printed",
      "content": "Abstract (Document Summary)\nLeslie Wexner, founder and chair of the Limited clothing-store chain, bought the place in 1989 for $15,000. [Jeffrey Epstein]'s mentor and one of his clients, Wexner is rumored to have sold the palatial digs to him for just $1. Epstein quickly spent $10 million to gut the place and completely redo the interior.",
      "position": "top"
    },
    {
      "type": "printed",
      "content": "SOCIALITE Samantha Boardman ditched her beau, Conde Nast editorial director James Truman, last year for man-about-town Todd Meister. According to our spies, Boardman ditched Meister after she caught him in flagrante with a 19-year-old coed. But don't feel too bad for her. Women's Wear Daily reports Boardman has a new man - Vanity Fair's Graydon Carter. Truman must not be too pleased. When Boardman dumped him, he needed to recuperate at a Buddhist retreat upstate. Editorial meetings at Conde Nast must be a hoot these days.",
      "position": "middle"
    },
    {
      "type": "printed",
      "content": "\"DISCO Bloodbath\" author James St. James is following up his notorious tell-all about killer club kid Michael Alig with another true-crime tome. He's shopping around \"Killer Grandpa,\" his investigation into a lynching that his grandfather led in 1935. \"My grandfather was a sheriff in Fort Lauderdale, and he lynched a black man that allegedly raped a white woman,\" James told us. \"About 100 people gathered to watch, and they passed a gun around and everyone took a shot at the body. It became this big town secret, and I write about what really happened.\" James, a 1980s club kid who fell in with Alig's inner circle, is played by Seth Green in \"Party Monster,\" the movie adaptation of \"Disco Bloodbath.\" But James said he was \"shocked\" when he watched a few scenes of Green mincing it up with Macaulay Culkin, who plays Alig. \"I didn't know I was so gay! I thought I was more like Steve McQueen, but Seth is flouncing around the whole time. Seth is much cuter than me, actually, and looks better in drag.\"",
      "position": "middle"
    },
    {
      "type": "printed",
      "content": "Full Text (1147 words)\n(Copyright 2002, The New York Post. All Rights Reserved)",
      "position": "middle"
    },
    {
      "type": "printed",
      "content": "PAGE SIX'S scoop last month that mysterious money manager Jeffrey Epstein had flown Bill Clinton, Chris Tucker and Kevin Spacey to Africa on his private 727 has sent journalists all over town trying to find out just who Epstein really is.\nVanity Fair has a reporter on his trail, but New York magazine beats them to the punch with a feature this week on Epstein's strange history.",
      "position": "middle"
    },
    {
      "type": "printed",
      "content": "Epstein, 49, a former Dalton School math teacher from Coney Island, is said to manage $15 billion for super-wealthy clients he'll only take on if they have at least $1 billion in assets.",
      "position": "middle"
    },
    {
      "type": "printed",
      "content": "\"According to people who know him,\" New York reports, \"if you were worth $700 million and felt the need for the services of Epstein & Co., you would receive a not-so-polite no-thank-you.\"",
      "position": "middle"
    },
    {
      "type": "printed",
      "content": "Noted mergers/acquisitions lawyer Dennis Block of Cadwalader, Wickersham & Taft recalls trying to give Epstein a client whose funds were below the $1 billion cutoff.",
      "position": "middle"
    },
    {
      "type": "printed",
      "content": "\"I sent him a $500 million client a few years ago and he wouldn't take him,\" Block reports. \"Said the account was too small. Both the client and I were amazed. But that's Jeffrey.\"",
      "position": "middle"
    },
    {
      "type": "printed",
      "content": "Most Wall Streeters, however, aren't even certain what Epstein actually does for a living. \"My belief is that Jeff maintains some sort of money-management firm, though you won't get a straight answer from him,\" says one powerful investor. \"He once told me that he has 300 people working for him, and I've also heard he manages Rockefeller money. But one never knows. It's like looking at the Wizard of Oz.\"",
      "position": "middle"
    },
    {
      "type": "printed",
      "content": "Some say that Epstein once quit his seat on the board of the Rockefeller Institute because he hates wearing a suit, supposedly telling a friend, \"It feels like wearing a dress.\"",
      "position": "bottom"
    },
    {
      "type": "printed",
      "content": "http://pqasb.pqarchiver.com/nypost/222493931.html?MAC=90db373aedcb1e36a203f8bd_11/30/2005\nPage 4 of 15\nPublic Records Request No.: 17-295\nDOJ-OGR-00032080",
      "position": "footer"
    }
  ],
  "entities": {
    "people": [
      "Leslie Wexner",
      "Jeffrey Epstein",
      "Samantha Boardman",
      "James Truman",
      "Todd Meister",
      "Graydon Carter",
      "James St. James",
      "Michael Alig",
      "Seth Green",
      "Macaulay Culkin",
      "Steve McQueen",
      "Bill Clinton",
      "Chris Tucker",
      "Kevin Spacey",
      "Dennis Block"
    ],
    "organizations": [
      "The Limited",
      "Conde Nast",
      "Vanity Fair",
      "Women's Wear Daily",
      "New York Post",
      "New York magazine",
      "Cadwalader, Wickersham & Taft",
      "Rockefeller Institute",
      "Dalton School"
    ],
    "locations": [
      "New York",
      "Africa",
      "Coney Island",
      "Fort Lauderdale"
    ],
    "dates": [
      "Oct 20, 2002",
      "1989",
      "1935",
      "11/30/2005"
    ],
    "reference_numbers": [
      "17-295",
      "DOJ-OGR-00032080"
    ]
  },
  "additional_notes": "The document appears to be a scanned newspaper article from the New York Post, dated October 20, 2002. The article discusses Jeffrey Epstein's background and his connections to various high-profile individuals. The document is mostly legible, but some minor text may be difficult to read due to the scanning quality."
}