{
  "document_metadata": {
    "page_number": "9",
    "document_number": "17-295",
    "date": "11/23/2005",
    "document_type": "Probable Cause Affidavit",
    "has_handwriting": true,
    "has_stamps": false
  },
  "full_text": "Probable Cause Affidavit\nPalm Beach Police Department\nAgency ORI# FLO 500600\nRobson took them in the kitchen area of the house and introduced to Sarah. Robson and Sarah took upstairs to the main bedroom. advised she doesn't know what happened as did not speak about what happened in the room. received $100.00 from Robson for going with her to Jeff's house and recommending on several occasions with no avail.\nOn October 6, 2005, at 11:45 am, I met with at and explained to her why we there to interview her. She advised she was aware of the ongoing investigation. stated she had previously spoken with k who told her she was interviewed by detectives. During a sworn taped statement, stated she knew that Haley Robson worked for Jeff Epstein in Palm Beach. advised she originally had been taken to the Epstein house by Haley Robson. stated she had been there a lot of times for massages over the past two years. She began going to the house when she was sixteen years of age. I asked her if she had formal training in providing massages, which stated she had not. advised she was told what was expected of her by providing massages and would have to remove clothing but if she felt uncomfortable just to say so and Jeff Epstein would stop pushing the issue. began providing massages and advised she kept her clothes on. She considered Jeff a pervert and he kept pushing to go further and further. explained she would keep telling him she had a boyfriend and would not be right to her boyfriend. It wasn't until recently, admitted to removing her clothes and staying in her thong underwear to provide a massage. explained Jeff wanted to be rubbed on his back and recently he began turning over and have her rub his chest as he masturbated. He would try to touch her breasts as she rubbed his chest. stated \"Jeff would try to get away with more and more on each massage\". stated Esptein would try to touch her more and use the massager/vibrator on her.\nOriginally, Robson drove her to the house for the original massage left Sarah her cell phone number and every time Jeff would come into town, Sarah would call her for an appointment to \"work\". Each time she went, Sarah would meet her at the kitchen door area. She would bring her upstairs and prepare the massage table. advised Jeff would ask her questions about herself. He knew she was a soccer player and would be attending I asked if he knew her real age. stated Epstein did and didn't care.\nThe most recent massage she provided was on October 1, 2005. During the massage, she asked Jeff if she could borrow one of his vehicles to visit her family and boyfriend in Orlando, Florida. Jeff Epstein had told her she could borrow one of his vehicles but later stated he would rent her a car. She continued with the massage as Jeff grabbed her buttocks and caressed the buttocks cheeks. I asked if she was wearing undergarments to which she replied her thong underwear.\nThe foregoing instrument was sworn to or affirmed before me this 23 day of November, 2005 by Det Joe Recarey, who is personally known to me.\nState of Florida\nCounty of Palm Beach\nSignature/Arresting Officer\nDate: 11/23/2005\nSignature of Police Officer (F.S.S. 117.10)\n07/26/17 Page 9 of 17 Public Records Request No.: 17-295 DOJ-OGR-00031872",
  "text_blocks": [
    {
      "type": "printed",
      "content": "Probable Cause Affidavit\nPalm Beach Police Department\nAgency ORI# FLO 500600",
      "position": "header"
    },
    {
      "type": "printed",
      "content": "The foregoing instrument was sworn to or affirmed before me this 23 day of November, 2005 by Det Joe Recarey, who is personally known to me.\nState of Florida\nCounty of Palm Beach\nSignature/Arresting Officer\nDate: 11/23/2005",
      "position": "footer"
    },
    {
      "type": "printed",
      "content": "Signature of Police Officer (F.S.S. 117.10)\n07/26/17 Page 9 of 17 Public Records Request No.: 17-295 DOJ-OGR-00031872",
      "position": "footer"
    },
    {
      "type": "handwritten",
      "content": "",
      "position": "middle"
    },
    {
      "type": "signature",
      "content": "",
      "position": "bottom"
    }
  ],
  "entities": {
    "people": [
      "Jeff Epstein",
      "Haley Robson",
      "Sarah",
      "Joe Recarey"
    ],
    "organizations": [
      "Palm Beach Police Department"
    ],
    "locations": [
      "Palm Beach",
      "Orlando",
      "Florida"
    ],
    "dates": [
      "October 6, 2005",
      "October 1, 2005",
      "November 23, 2005",
      "July 26, 2017"
    ],
    "reference_numbers": [
      "17-295",
      "FLO 500600",
      "DOJ-OGR-00031872"
    ]
  },
  "additional_notes": "The document contains redactions, likely for privacy or sensitive information. The document is a probable cause affidavit from the Palm Beach Police Department, detailing an investigation involving Jeff Epstein."
}