{
  "document_metadata": {
    "page_number": "17",
    "document_number": "17-295",
    "date": "07/26/17",
    "document_type": "transcript",
    "has_handwriting": false,
    "has_stamps": false
  },
  "full_text": "Censor & Associates Reporting and Transcription, Inc. Page 17 You were supposed to be here at nine a.m.; it's now after two. Take your break and come back. MR. LEOPOLD: Okay. If the demeanor keeps up, we will not be here beyond those five minutes. MR. TEIN: Take your break and come back. MR. LEOPOLD: Okay. So I suggest that you relax. MR. TEIN: I suggest that you take your break. MR. GOLDBERGER: Let them take that five-minute break. MR. LEOPOLD: But I would suggest that you take deep breaths. MR. TEIN: Suggest whatever you want. Go take a break. (Thereupon, a recess was taken.) BY MR. TEIN: Q. you agree that giving testimony today at your deposition is something very serious, don't you? A. Yes. Q. And you respect the court, don't you? A. Yes. Q. Let me show you Exhibit 31-001. Can you Ph. 561.682.0905 - Fax. 561.682.1771 1655 Palm Beach Lakes Blvd., Suite 500 - West Palm Beach, FL 33401 07/26/17 Page 2692 Public Records Request No.: 17-295 DOJ-OGR-00033005",
  "text_blocks": [
    {
      "type": "printed",
      "content": "Censor & Associates Reporting and Transcription, Inc.",
      "position": "header"
    },
    {
      "type": "printed",
      "content": "Page 17",
      "position": "header"
    },
    {
      "type": "printed",
      "content": "You were supposed to be here at nine a.m.; it's now after two. Take your break and come back. MR. LEOPOLD: Okay. If the demeanor keeps up, we will not be here beyond those five minutes. MR. TEIN: Take your break and come back. MR. LEOPOLD: Okay. So I suggest that you relax. MR. TEIN: I suggest that you take your break. MR. GOLDBERGER: Let them take that five-minute break. MR. LEOPOLD: But I would suggest that you take deep breaths. MR. TEIN: Suggest whatever you want. Go take a break. (Thereupon, a recess was taken.) BY MR. TEIN: Q. you agree that giving testimony today at your deposition is something very serious, don't you? A. Yes. Q. And you respect the court, don't you? A. Yes. Q. Let me show you Exhibit 31-001. Can you",
      "position": "main"
    },
    {
      "type": "printed",
      "content": "Ph. 561.682.0905 - Fax. 561.682.1771 1655 Palm Beach Lakes Blvd., Suite 500 - West Palm Beach, FL 33401",
      "position": "footer"
    },
    {
      "type": "printed",
      "content": "07/26/17 Page 2692 Public Records Request No.: 17-295 DOJ-OGR-00033005",
      "position": "footer"
    }
  ],
  "entities": {
    "people": [
      "MR. LEOPOLD",
      "MR. TEIN",
      "MR. GOLDBERGER"
    ],
    "organizations": [
      "Censor & Associates Reporting and Transcription, Inc.",
      "court"
    ],
    "locations": [
      "West Palm Beach, FL"
    ],
    "dates": [
      "07/26/17"
    ],
    "reference_numbers": [
      "17-295",
      "31-001",
      "DOJ-OGR-00033005"
    ]
  },
  "additional_notes": "The document is a transcript of a deposition. There is a redacted name in the Q. section."
}