{
  "document_metadata": {
    "page_number": "2 of 14",
    "document_number": "2453",
    "date": "07/26/17",
    "document_type": "Myspace comments",
    "has_handwriting": false,
    "has_stamps": false
  },
  "full_text": "Myspace.com Page 2 of 14 COLOSSUS Jul 6, 2005 12:15 PM Suffocate X Faster xDeathstarx Too Pure To Die Our Battle plus 3 more 10 bucks july 8th. this friday ! Ginger Jul 6, 2005 10:56 AM Thanks for stopping at work to see me. ;) I went to the beach again last night with Tony Diaz. The police picked us up though. They didn't like us swimming with the sea turtles. Juno is a 24 hour beach. We watched the sunrise. Beautiful. How's your summer? Virginia Jul 5, 2005 1:21 PM 07/26/17 Page 2453 Public Records Request No.: 17-295 http://www.myspace.com/index.cfm?fuseaction=user.viewComments&friendID=172831&page=1&Mytoken=09B3DE8B-B3F... 12/2/2005 DOJ-OGR-00032766",
  "text_blocks": [
    {
      "type": "printed",
      "content": "Myspace.com",
      "position": "header"
    },
    {
      "type": "printed",
      "content": "Page 2 of 14",
      "position": "header"
    },
    {
      "type": "printed",
      "content": "COLOSSUS Jul 6, 2005 12:15 PM Suffocate X Faster xDeathstarx Too Pure To Die Our Battle plus 3 more 10 bucks july 8th. this friday !",
      "position": "middle"
    },
    {
      "type": "printed",
      "content": "Ginger Jul 6, 2005 10:56 AM Thanks for stopping at work to see me. ;) I went to the beach again last night with Tony Diaz. The police picked us up though. They didn't like us swimming with the sea turtles. Juno is a 24 hour beach. We watched the sunrise. Beautiful. How's your summer?",
      "position": "middle"
    },
    {
      "type": "printed",
      "content": "Virginia Jul 5, 2005 1:21 PM",
      "position": "middle"
    },
    {
      "type": "printed",
      "content": "07/26/17 Page 2453 Public Records Request No.: 17-295",
      "position": "footer"
    },
    {
      "type": "printed",
      "content": "http://www.myspace.com/index.cfm?fuseaction=user.viewComments&friendID=172831&page=1&Mytoken=09B3DE8B-B3F... 12/2/2005",
      "position": "footer"
    },
    {
      "type": "printed",
      "content": "DOJ-OGR-00032766",
      "position": "footer"
    }
  ],
  "entities": {
    "people": [
      "COLOSSUS",
      "Ginger",
      "Tony Diaz",
      "Virginia"
    ],
    "organizations": [
      "Police"
    ],
    "locations": [
      "Juno",
      "beach"
    ],
    "dates": [
      "Jul 6, 2005",
      "Jul 5, 2005",
      "07/26/17",
      "12/2/2005"
    ],
    "reference_numbers": [
      "17-295",
      "2453",
      "DOJ-OGR-00032766"
    ]
  },
  "additional_notes": "The document appears to be a printout of Myspace comments from 2005. The page is clean and legible, with no visible redactions or damage."
}