{
  "document_metadata": {
    "page_number": "115",
    "document_number": "17-295",
    "date": "07/26/17",
    "document_type": "transcript",
    "has_handwriting": false,
    "has_stamps": false
  },
  "full_text": "Censor & Associates Reporting and Transcription, Inc. Page 115 1 BY MR. TEIN: 2 Q. Okay. When your counsel that it was there 3 was lack of foundation, you agree with your counsel, 4 right? 5 A. I was like saying, \"Yeah, let's move on,\" 6 because there was no point to asking that question. 7 Q. Your father threw out of the house 8 because she was lying, correct? 9 MR. LEOPOLD: Objection. Lack of 10 foundation. 11 Hold on, . Let me just make the 12 objection. 13 Lack of foundation, predicate, calls for 14 speculation. 15 BY MR. TEIN: 16 Q. Answer. 17 A. I'm not my sister. I don't know. 18 Q. I want to know what you know only. 19 A. I don't know. 20 Q. You don't know. That's your answer? 21 A. Yes. 22 Q. Now your parents filed the police report 23 regarding Mr. Epstein, right? 24 A. Yes. 25 Q. Now your parents are also lying, aren't Ph. 561.682.0905 - Fax. 561.682.1771 1655 Palm Beach Lakes Blvd., Suite 500 - West Palm Beach, FL 33401 07/26/17 Page 2790 Public Records Request No.: 17-295 DOJ-OGR-00033103",
  "text_blocks": [
    {
      "type": "printed",
      "content": "Censor & Associates Reporting and Transcription, Inc.",
      "position": "header"
    },
    {
      "type": "printed",
      "content": "Page 115",
      "position": "header"
    },
    {
      "type": "printed",
      "content": "1 BY MR. TEIN: 2 Q. Okay. When your counsel that it was there 3 was lack of foundation, you agree with your counsel, 4 right? 5 A. I was like saying, \"Yeah, let's move on,\" 6 because there was no point to asking that question. 7 Q. Your father threw out of the house 8 because she was lying, correct? 9 MR. LEOPOLD: Objection. Lack of 10 foundation. 11 Hold on, . Let me just make the 12 objection. 13 Lack of foundation, predicate, calls for 14 speculation. 15 BY MR. TEIN: 16 Q. Answer. 17 A. I'm not my sister. I don't know. 18 Q. I want to know what you know only. 19 A. I don't know. 20 Q. You don't know. That's your answer? 21 A. Yes. 22 Q. Now your parents filed the police report 23 regarding Mr. Epstein, right? 24 A. Yes. 25 Q. Now your parents are also lying, aren't",
      "position": "main"
    },
    {
      "type": "printed",
      "content": "Ph. 561.682.0905 - Fax. 561.682.1771 1655 Palm Beach Lakes Blvd., Suite 500 - West Palm Beach, FL 33401",
      "position": "footer"
    },
    {
      "type": "printed",
      "content": "07/26/17 Page 2790 Public Records Request No.: 17-295 DOJ-OGR-00033103",
      "position": "footer"
    }
  ],
  "entities": {
    "people": [
      "MR. TEIN",
      "MR. LEOPOLD",
      "Mr. Epstein"
    ],
    "organizations": [
      "Censor & Associates Reporting and Transcription, Inc."
    ],
    "locations": [
      "West Palm Beach",
      "Palm Beach Lakes Blvd."
    ],
    "dates": [
      "07/26/17"
    ],
    "reference_numbers": [
      "17-295",
      "DOJ-OGR-00033103"
    ]
  },
  "additional_notes": "The document is a transcript of a deposition or testimony. There are redactions in the text, indicated by blacked-out sections."
}