{
  "document_metadata": {
    "page_number": "35",
    "document_number": "17-295",
    "date": "07/26/17",
    "document_type": "transcript",
    "has_handwriting": false,
    "has_stamps": false
  },
  "full_text": "Censor & Associates Reporting and Transcription, Inc. Page 35 1 Q. You can answer the question. 2 A. Sure. 3 Q. Is there anything that would refresh your 4 memory that in fact you told Mr. Epstein's assistant, the 5 one who walked you upstairs, that you went to college and 6 you had just moved down here from Ohio? 7 A. I don't remember saying that, but if you -- 8 I don't remember saying that myself, so -- 9 Q. That would be a lie, right? 10 A. No. I really don't remember. 11 Q. So you told Jeff that you were 18 years 12 old, correct? 13 A. Yes. 14 Q. Do you remember Detective Michelle Pagan of 15 the Police Department, Palm Beach Police Department? 16 A. Yes. 17 Q. Do you remember you spoke to her? 18 A. Yes. 19 Q. Do you remember that you told Detective 20 Pagan that when you lied about your age to Jeff you said 21 it really fast because you didn't want to make it sound 22 like you were lying? 23 A. I don't remember the words exactly, but I 24 do remember telling her I told him I was 18. 25 Q. And do you remember telling Detective Pagan Ph. 561.682.0905 - Fax. 561.682.1771 1655 Palm Beach Lakes Blvd., Suite 500 - West Palm Beach, FL 33401 07/26/17 Page 2710 Public Records Request No.: 17-295 DOJ-OGR-00033023",
  "text_blocks": [
    {
      "type": "printed",
      "content": "Censor & Associates Reporting and Transcription, Inc.",
      "position": "header"
    },
    {
      "type": "printed",
      "content": "Page 35",
      "position": "header"
    },
    {
      "type": "printed",
      "content": "1 Q. You can answer the question. 2 A. Sure. 3 Q. Is there anything that would refresh your 4 memory that in fact you told Mr. Epstein's assistant, the 5 one who walked you upstairs, that you went to college and 6 you had just moved down here from Ohio? 7 A. I don't remember saying that, but if you -- 8 I don't remember saying that myself, so -- 9 Q. That would be a lie, right? 10 A. No. I really don't remember. 11 Q. So you told Jeff that you were 18 years 12 old, correct? 13 A. Yes. 14 Q. Do you remember Detective Michelle Pagan of 15 the Police Department, Palm Beach Police Department? 16 A. Yes. 17 Q. Do you remember you spoke to her? 18 A. Yes. 19 Q. Do you remember that you told Detective 20 Pagan that when you lied about your age to Jeff you said 21 it really fast because you didn't want to make it sound 22 like you were lying? 23 A. I don't remember the words exactly, but I 24 do remember telling her I told him I was 18. 25 Q. And do you remember telling Detective Pagan",
      "position": "main"
    },
    {
      "type": "printed",
      "content": "Ph. 561.682.0905 - Fax. 561.682.1771 1655 Palm Beach Lakes Blvd., Suite 500 - West Palm Beach, FL 33401",
      "position": "footer"
    },
    {
      "type": "printed",
      "content": "07/26/17 Page 2710 Public Records Request No.: 17-295 DOJ-OGR-00033023",
      "position": "footer"
    }
  ],
  "entities": {
    "people": [
      "Mr. Epstein",
      "Jeff",
      "Detective Michelle Pagan"
    ],
    "organizations": [
      "Censor & Associates Reporting and Transcription, Inc.",
      "Palm Beach Police Department"
    ],
    "locations": [
      "Ohio",
      "Palm Beach",
      "West Palm Beach, FL"
    ],
    "dates": [
      "07/26/17"
    ],
    "reference_numbers": [
      "17-295",
      "DOJ-OGR-00033023"
    ]
  },
  "additional_notes": "The document is a transcript of a deposition or interview. It appears to be a photocopy or scan of the original document."
}