{
  "document_metadata": {
    "page_number": "121",
    "document_number": "17-295",
    "date": "07/26/17",
    "document_type": "Deposition Transcript",
    "has_handwriting": false,
    "has_stamps": false
  },
  "full_text": "Censor & Associates Reporting and Transcription, Inc. Page 121 Q. Did she tell you that she was fired from Hawthorne Aviation for stealing? A. No. MR. TEIN: Let's take a break. (Thereupon, a recess was taken.) BY MR. TEIN: Q. before you met Jeffrey Epstein, had you ever had sexual intercourse? A. Yes, yeah. Q. How many times? A. Just a few. Twice. Q. With how many different men? A. Two. Q. How old were they? A. Zack Bryan, being one year older than me, and then the other person was two years older than me. Q. What was his name? A. Ryan Ortell. Q. How old were you when you first had sexual intercourse? A. 14. Q. How many -- before you met Epstein, how many different men had you had any type of sexual activity with? A. Just those two. Ph. 561.682.0905 - Fax. 561.682.1771 1655 Palm Beach Lakes Blvd., Suite 500 - West Palm Beach, FL 33401 07/26/17 Page 2796 Public Records Request No.: 17-295 DOJ-OGR-00033109",
  "text_blocks": [
    {
      "type": "printed",
      "content": "Censor & Associates Reporting and Transcription, Inc.",
      "position": "header"
    },
    {
      "type": "printed",
      "content": "Page 121",
      "position": "header"
    },
    {
      "type": "printed",
      "content": "Q. Did she tell you that she was fired from Hawthorne Aviation for stealing? A. No. MR. TEIN: Let's take a break. (Thereupon, a recess was taken.) BY MR. TEIN: Q. before you met Jeffrey Epstein, had you ever had sexual intercourse? A. Yes, yeah. Q. How many times? A. Just a few. Twice. Q. With how many different men? A. Two. Q. How old were they? A. Zack Bryan, being one year older than me, and then the other person was two years older than me. Q. What was his name? A. Ryan Ortell. Q. How old were you when you first had sexual intercourse? A. 14. Q. How many -- before you met Epstein, how many different men had you had any type of sexual activity with? A. Just those two.",
      "position": "middle"
    },
    {
      "type": "printed",
      "content": "Ph. 561.682.0905 - Fax. 561.682.1771 1655 Palm Beach Lakes Blvd., Suite 500 - West Palm Beach, FL 33401",
      "position": "footer"
    },
    {
      "type": "printed",
      "content": "07/26/17 Page 2796 Public Records Request No.: 17-295 DOJ-OGR-00033109",
      "position": "footer"
    }
  ],
  "entities": {
    "people": [
      "Jeffrey Epstein",
      "Zack Bryan",
      "Ryan Ortell",
      "MR. TEIN"
    ],
    "organizations": [
      "Hawthorne Aviation",
      "Censor & Associates Reporting and Transcription, Inc."
    ],
    "locations": [
      "West Palm Beach",
      "FL"
    ],
    "dates": [
      "07/26/17"
    ],
    "reference_numbers": [
      "17-295",
      "DOJ-OGR-00033109"
    ]
  },
  "additional_notes": "The document appears to be a deposition transcript with sensitive content. The page number is 121, but it also has a secondary page number 2796. The document is from a public records request."
}