{
  "document_metadata": {
    "page_number": "50",
    "document_number": "1-05-000368",
    "date": "2/17/06",
    "document_type": "Incident Report",
    "has_handwriting": false,
    "has_stamps": false
  },
  "full_text": "Date: 2/17/06 Time: 11:36:35 PALM BEACH POLICE DEPARTMENT Incident Report Page: 50 Program: CMS301L Case No. : 1-05-000368 (Continued) closer to him as he masturbated. Epstein also grabbed her breasts and fondled her breast with his hands as she provided the massage. stated on one occasion, he offered extra monies to have vaginal intercourse. She stated this all occurred on the massage table. stated Epstein penetrated her vagina with his penis and began having intercourse with her until he reached the point of climax. Epstein removed his penis from her vagina and climaxed onto the massage table. if she had any formal training in providing massages, stated she did not. continued to state on one other occasion, Epstein introduced his assistant, Nada, into the massage. Nada was brought into room with to provide a massage. Epstein had them kiss and fondle each other around the breasts and buttocks as they provided a massage to Epstein. Epstein, watched and masturbated as this occurred. On occasions, Epstein, introduced the large white vibrator/massager, during the massage. Epstein stroked the vibrator/massager on vagina as she provided the massage. stated the last time she spoke with anyone at the house, was with Sarah during the weekend of October 2 or 3, 2005. stated she had brought two people to the Epstein house. She provided names of and (unknown last name). It should noted, had been previously identified as and had been previously interviewed. The interview was concluded and the videotape was placed into evidence via the locker system. On November 9, 2005, Sgt Frick and I traveled to 6791 Fairway Lakes Drive in Boynton Beach, Florida in hopes to interview Juan Aless, the former houseman of Epstein's home. As no one was home, a business card was left for him to return my call. We then traveled to 11349 SW 86th Lane in Miami in hopes to interview Alfredo Rodriguez, a former house man of Epstein. We did not locate them at home. I left a business card for him to return my call. We then traveled to and met with Dean of Students, Mr. Turner. We requested to speak with ; was re interviewed, as she still was in possession of the rental car that Epstein had acquired for her. stated that Epstein's assistant, had called her on her cellular telephone and informed her that rental was extended for her. Sarah stated she had paid an additional $625.00 for her to keep the rental an extra month. was asked if she had any additional contact with either Epstein or anyone from his organization. stated she did not, other than the telephone call informing her that she could keep the car for an extra month. did not provide any additional information. On November 10, 2005, at approximately 9:47 am, Alfredo Rodriguez had telephoned reference my business card found on his door. Rodriguez stated he had worked with Epstein for approximately six months after the previous houseman left. Rodriguez stated that it was his 07/26/17 Page 2022 Public Records Request No.: 17-295 DOJ-OGR-00032335",
  "text_blocks": [
    {
      "type": "printed",
      "content": "Date: 2/17/06 Time: 11:36:35 PALM BEACH POLICE DEPARTMENT Incident Report Page: 50 Program: CMS301L",
      "position": "header"
    },
    {
      "type": "printed",
      "content": "Case No. : 1-05-000368 (Continued)",
      "position": "top"
    },
    {
      "type": "printed",
      "content": "On November 9, 2005, Sgt Frick and I traveled to 6791 Fairway Lakes Drive in Boynton Beach, Florida in hopes to interview Juan Alessi, the former houseman of Epstein's home. As no one was home, a business card was left for him to return my call. We then traveled to 11349 SW 86th Lane in Miami in hopes to interview Alfredo Rodriguez, a former house man of Epstein. We did not locate them at home. I left a business card for him to return my call.",
      "position": "middle"
    },
    {
      "type": "printed",
      "content": "On November 10, 2005, at approximately 9:47 am, Alfredo Rodriguez had telephoned reference my business card found on his door. Rodriguez stated he had worked with Epstein for approximately six months after the previous houseman left.",
      "position": "bottom"
    },
    {
      "type": "printed",
      "content": "07/26/17 Page 2022 Public Records Request No.: 17-295 DOJ-OGR-00032335",
      "position": "footer"
    }
  ],
  "entities": {
    "people": [
      "Epstein",
      "Nada",
      "Sarah",
      "Juan Alessi",
      "Alfredo Rodriguez",
      "Sgt Frick",
      "Mr. Turner"
    ],
    "organizations": [
      "PALM BEACH POLICE DEPARTMENT"
    ],
    "locations": [
      "Boynton Beach, Florida",
      "Miami",
      "6791 Fairway Lakes Drive",
      "11349 SW 86th Lane"
    ],
    "dates": [
      "2/17/06",
      "November 9, 2005",
      "November 10, 2005",
      "October 2 or 3, 2005",
      "07/26/17"
    ],
    "reference_numbers": [
      "1-05-000368",
      "17-295",
      "DOJ-OGR-00032335"
    ]
  },
  "additional_notes": "The document appears to be a police report detailing allegations against Jeffrey Epstein. The report includes witness statements and details of the investigation. Some names have been redacted."
}