{
  "document_metadata": {
    "page_number": "14",
    "document_number": null,
    "date": "2006-07-17",
    "document_type": "list of donations",
    "has_handwriting": true,
    "has_stamps": false
  },
  "full_text": "Albuquerque Tribune Online Page 14 of 28 $10,000 R. Bart Rutledge, Albuquerque Home builder $10,000 R. D. Hubbard Enterprises Inc., Palm Desert, Calif. Management $10,000 Rick Moms, Austin, Texas Gambling $10,000 Robert S. Bass, Philadelphia, Pa. Attorney $10,000 Sheetmetal Workers, Albuquerque Labor committee $10,000 Sheila Davis, San Diego, Calif. CEO $10,000 Stephen A. Cozen, Philadelphia, Pa. Attorney $10,000 Ted Turner, Caballo Business Executive $10,000 The Village Zoo, Palm Desert, Calif. Real estate shopping center $10,000 Thomas Bonafair, Albuquerque Chairman $10,000 Victor Paul Kearney, Zephyr Cove, Nev. Toy company/president $10,000 Wisznia Associates, New Orleans, La. Architecture firm $10,000 Realtors Association of New Mexico, Santa Fe Real estate $10,000 Bowlin Travel Centers Inc., Albuquerque Recreation/tourism $10,000 Constar Company, Farmington Manufactured homes $10,000 Robert Joe Hanson, Fort Worth, Texas Business owner $10,000 Continental Dairy Products http://abqtrib.com/archives/news02/120702_face_9_colate.shtml PPublic Records Request No.: 17-2357/2006 DOJ-OGR-00031244",
  "text_blocks": [
    {
      "type": "printed",
      "content": "Albuquerque Tribune Online",
      "position": "header"
    },
    {
      "type": "printed",
      "content": "Page 14 of 28",
      "position": "header"
    },
    {
      "type": "printed",
      "content": "$10,000 R. Bart Rutledge, Albuquerque Home builder $10,000 R. D. Hubbard Enterprises Inc., Palm Desert, Calif. Management $10,000 Rick Moms, Austin, Texas Gambling $10,000 Robert S. Bass, Philadelphia, Pa. Attorney $10,000 Sheetmetal Workers, Albuquerque Labor committee $10,000 Sheila Davis, San Diego, Calif. CEO $10,000 Stephen A. Cozen, Philadelphia, Pa. Attorney $10,000 Ted Turner, Caballo Business Executive $10,000 The Village Zoo, Palm Desert, Calif. Real estate shopping center $10,000 Thomas Bonafair, Albuquerque Chairman $10,000 Victor Paul Kearney, Zephyr Cove, Nev. Toy company/president $10,000 Wisznia Associates, New Orleans, La. Architecture firm $10,000 Realtors Association of New Mexico, Santa Fe Real estate $10,000 Bowlin Travel Centers Inc., Albuquerque Recreation/tourism $10,000 Constar Company, Farmington Manufactured homes $10,000 Robert Joe Hanson, Fort Worth, Texas Business owner $10,000 Continental Dairy Products",
      "position": "middle"
    },
    {
      "type": "printed",
      "content": "http://abqtrib.com/archives/news02/120702_face_9_colate.shtml",
      "position": "footer"
    },
    {
      "type": "printed",
      "content": "PPublic Records Request No.: 17-2357/2006",
      "position": "footer"
    },
    {
      "type": "handwritten",
      "content": "2357",
      "position": "footer"
    },
    {
      "type": "printed",
      "content": "DOJ-OGR-00031244",
      "position": "footer"
    }
  ],
  "entities": {
    "people": [
      "R. Bart Rutledge",
      "Rick Moms",
      "Robert S. Bass",
      "Sheila Davis",
      "Stephen A. Cozen",
      "Ted Turner",
      "Thomas Bonafair",
      "Victor Paul Kearney",
      "Robert Joe Hanson"
    ],
    "organizations": [
      "R. D. Hubbard Enterprises Inc.",
      "Sheetmetal Workers",
      "The Village Zoo",
      "Wisznia Associates",
      "Realtors Association of New Mexico",
      "Bowlin Travel Centers Inc.",
      "Constar Company",
      "Continental Dairy Products"
    ],
    "locations": [
      "Albuquerque",
      "Palm Desert",
      "Calif.",
      "Austin",
      "Texas",
      "Philadelphia",
      "Pa.",
      "San Diego",
      "Caballo",
      "Nev.",
      "Zephyr Cove",
      "New Orleans",
      "La.",
      "Santa Fe",
      "Farmington",
      "Fort Worth"
    ],
    "dates": [
      "17-2357/2006"
    ],
    "reference_numbers": [
      "17-2357/2006",
      "DOJ-OGR-00031244"
    ]
  },
  "additional_notes": "The document appears to be a list of donations with amounts and donor information. The page is from the Albuquerque Tribune Online and has a page number of 14 out of 28. There is a handwritten correction to the 'Public Records Request No.' field."
}