{
  "document_metadata": {
    "page_number": "03",
    "document_number": "17-295",
    "date": "August 25, 2006",
    "document_type": "Letter",
    "has_handwriting": true,
    "has_stamps": true
  },
  "full_text": "01/06/2008 22:27 5616404420 X PAGE 03 OFFICE OF THE STATE ATTORNEY FIFTEENTH JUDICIAL CIRCUIT OF FLORIDA IN AND FOR PALM BEACH COUNTY BARRY E. KRISCHER STATE ATTORNEY August 25, 2006 Aileen Josephs, P.A. 515 N. Flagler Drive #300-Pavilion West Palm Beach, FL 33401 RE: Public Records Request Jeffrey Epstein Dear Ms. Josephs: In response to your request dated August 14, 2006, this is an active criminal investigation, exempt per F.S. 119.07(6)(b). If you have any questions, please feel free to contact me at (561)355-7252. Sincerely, LaTo'sha Lowe Public Information 401 North Dixie Highway • West Palm Beach, FL 33401-4209 (561)-355-7100 \"There is no excuse for child abuse\" 07/26/17 Page 51 of 104 Public Records Request No.: 17-295 DOJ-OGR-00031668",
  "text_blocks": [
    {
      "type": "printed",
      "content": "OFFICE OF THE STATE ATTORNEY FIFTEENTH JUDICIAL CIRCUIT OF FLORIDA IN AND FOR PALM BEACH COUNTY",
      "position": "header"
    },
    {
      "type": "printed",
      "content": "BARRY E. KRISCHER STATE ATTORNEY",
      "position": "header"
    },
    {
      "type": "printed",
      "content": "August 25, 2006",
      "position": "top"
    },
    {
      "type": "printed",
      "content": "Aileen Josephs, P.A. 515 N. Flagler Drive #300-Pavilion West Palm Beach, FL 33401",
      "position": "top"
    },
    {
      "type": "printed",
      "content": "RE: Public Records Request Jeffrey Epstein",
      "position": "top"
    },
    {
      "type": "printed",
      "content": "Dear Ms. Josephs:",
      "position": "middle"
    },
    {
      "type": "printed",
      "content": "In response to your request dated August 14, 2006, this is an active criminal investigation, exempt per F.S. 119.07(6)(b).",
      "position": "middle"
    },
    {
      "type": "printed",
      "content": "If you have any questions, please feel free to contact me at (561)355-7252.",
      "position": "middle"
    },
    {
      "type": "handwritten",
      "content": "LaTo'sha Lowe",
      "position": "middle"
    },
    {
      "type": "printed",
      "content": "Sincerely, LaTo'sha Lowe Public Information",
      "position": "middle"
    },
    {
      "type": "printed",
      "content": "401 North Dixie Highway • West Palm Beach, FL 33401-4209 (561)-355-7100 \"There is no excuse for child abuse\"",
      "position": "footer"
    },
    {
      "type": "printed",
      "content": "07/26/17 Page 51 of 104 Public Records Request No.: 17-295 DOJ-OGR-00031668",
      "position": "footer"
    }
  ],
  "entities": {
    "people": [
      "Aileen Josephs",
      "Jeffrey Epstein",
      "LaTo'sha Lowe",
      "Barry E. Krischer"
    ],
    "organizations": [
      "Office of the State Attorney"
    ],
    "locations": [
      "Palm Beach County",
      "West Palm Beach",
      "Florida"
    ],
    "dates": [
      "August 25, 2006",
      "August 14, 2006",
      "01/06/2008",
      "07/26/17"
    ],
    "reference_numbers": [
      "17-295",
      "5616404420",
      "DOJ-OGR-00031668"
    ]
  },
  "additional_notes": "The document is a letter from LaTo'sha Lowe, Public Information, to Aileen Josephs regarding a public records request for Jeffrey Epstein. The letter is dated August 25, 2006, and is on the letterhead of the Office of the State Attorney for the Fifteenth Judicial Circuit of Florida. The document has a stamp and a handwritten signature."
}