{
  "document_metadata": {
    "page_number": "2 of 10",
    "document_number": "DOJ-OGR-00031509",
    "date": "07/26/17",
    "document_type": "Myspace profile printout",
    "has_handwriting": false,
    "has_stamps": false
  },
  "full_text": "www.myspace.com/iloveanirishboi Page 2 of 10 Boy Shorts Triple J +add+ +view+ Interests General I love shopping, tanning, hanging out with friends and playing volleyball sleeping in and being lazy Music I dont have a favorite i listen to all kinds!! Movies Name: Birthdate: Birthplace: Current Location: Eye Color: Hair Color: Height: Weight: Piercings: Tatoos: Boyfriend/Girlfriend: Overused Phraze: FAV Food: Candy: Number: Color: Animal: Drink: Alcohol Drink: Bagel: Letter: Body Part on Opposite sex: This Pepsi or Coke: McDonalds or BurgerKing: Strawberry or 07/26/17 http://profile.myspace.com/index.cfm?fuseaction= ser.viewprofile&friendID=65739759 1'ce U Go ZaCk U DoNt Go BaK Chels-ifer Is this 1-214 or what? ¿Merda? View All of Friends Friends Comments Displaying 29 of 29 comments (View/Edit All Comments) lynds 3/31/2006 6:18 PM hey i miss u so much i want u to come back up here :( love ya lynds 3/29/2006 4:24 PM Hey...i miss you like crazy i wish you were here i hate cherokee it sucks balls lol...well newayz i cant wait until this summer it will be great CANT WAT....well love ya babe Amayz ((~\"Wonderful-Winslow\"~)) Public Records Request No.: 17295 4/4/2006 Page 99 of 111",
  "text_blocks": [
    {
      "type": "printed",
      "content": "www.myspace.com/iloveanirishboi",
      "position": "header"
    },
    {
      "type": "printed",
      "content": "Boy Shorts Triple J +add+ +view+",
      "position": "top"
    },
    {
      "type": "printed",
      "content": "Interests General I love shopping, tanning, hanging out with friends and playing volleyball sleeping in and being lazy Music I dont have a favorite i listen to all kinds!! Movies",
      "position": "left"
    },
    {
      "type": "printed",
      "content": "Name: Birthdate: Birthplace: Current Location: Eye Color: Hair Color: Height: Weight: Piercings: Tatoos: Boyfriend/Girlfriend: Overused Phraze: FAV Food: Candy: Number: Color: Animal: Drink: Alcohol Drink: Bagel: Letter: Body Part on Opposite sex: This Pepsi or Coke: McDonalds or BurgerKing: Strawberry or",
      "position": "left"
    },
    {
      "type": "printed",
      "content": "1'ce U Go ZaCk U DoNt Go BaK Chels-ifer Is this 1-214 or what? ¿Merda?",
      "position": "top-right"
    },
    {
      "type": "printed",
      "content": "View All of Friends",
      "position": "right"
    },
    {
      "type": "printed",
      "content": "Friends Comments Displaying 29 of 29 comments (View/Edit All Comments)",
      "position": "bottom-right"
    },
    {
      "type": "printed",
      "content": "lynds 3/31/2006 6:18 PM hey i miss u so much i want u to come back up here :( love ya lynds",
      "position": "bottom-right"
    },
    {
      "type": "printed",
      "content": "3/29/2006 4:24 PM Hey...i miss you like crazy i wish you were here i hate cherokee it sucks balls lol...well newayz i cant wait until this summer it will be great CANT WAT....well love ya babe Amayz ((~\"Wonderful-Winslow\"~))",
      "position": "bottom-right"
    },
    {
      "type": "printed",
      "content": "Public Records Request No.: 17295 4/4/2006",
      "position": "bottom-right"
    },
    {
      "type": "printed",
      "content": "Page 99 of 111",
      "position": "footer"
    },
    {
      "type": "printed",
      "content": "http://profile.myspace.com/index.cfm?fuseaction=ser.viewprofile&friendID=65739759",
      "position": "footer"
    },
    {
      "type": "printed",
      "content": "DOJ-OGR-00031509",
      "position": "footer"
    }
  ],
  "entities": {
    "people": [
      "lynds",
      "Amayz",
      "Triple J",
      "Chels-ifer"
    ],
    "organizations": [
      "McDonalds",
      "BurgerKing"
    ],
    "locations": [
      "Cherokee"
    ],
    "dates": [
      "3/31/2006",
      "3/29/2006",
      "4/4/2006",
      "07/26/17"
    ],
    "reference_numbers": [
      "17295",
      "65739759",
      "DOJ-OGR-00031509"
    ]
  },
  "additional_notes": "This document appears to be a printout of a Myspace profile from 2006. The profile contains information about the user's interests, comments from friends, and other personal details. The document has been redacted in some areas, but the majority of the text is legible."
}