{
  "document_metadata": {
    "page_number": "48",
    "document_number": "17-295",
    "date": "07/26/17",
    "document_type": "transcript",
    "has_handwriting": false,
    "has_stamps": false
  },
  "full_text": "Censor & Associates Reporting and Transcription, Inc. Page 48 1 Florida Bar? 2 A. I did not select him. 3 Q. Who did? 4 A. My father. 5 Q. Did you ever meet Mr. Herman? 6 A. Once. 7 Q. Don't -- don't tell me what you discussed 8 with him. Where did you meet him? 9 A. I was shopping in my -- he showed up at my 10 friend's house. 11 Q. Whose house? 12 A. My friend Tiffany Rich. 13 Q. Is that Tiffany from the Quarterdeck 14 Tavern? 15 A. Yes. 16 Q. And did you have a meeting with him at 17 Tiffany Rich's house? 18 A. Yes. I guess you could say that. 19 Q. And who else was there? 20 A. My Aunt 21 Q. And what was that meeting about? 22 MR. LEOPOLD: Objection. That calls for 23 attorney/client privilege. 24 BY MR. TEIN: 25 Q. What discussions did you have with Ph. 561.682.0905 - Fax. 561.682.1771 1655 Palm Beach Lakes Blvd., Suite 500 - West Palm Beach, FL 33401 07/26/17 Page 2723 Public Records Request No.: 17-295 DOJ-OGR-00033036",
  "text_blocks": [
    {
      "type": "printed",
      "content": "Censor & Associates Reporting and Transcription, Inc.",
      "position": "header"
    },
    {
      "type": "printed",
      "content": "Page 48",
      "position": "header"
    },
    {
      "type": "printed",
      "content": "1 Florida Bar? 2 A. I did not select him. 3 Q. Who did? 4 A. My father. 5 Q. Did you ever meet Mr. Herman? 6 A. Once. 7 Q. Don't -- don't tell me what you discussed 8 with him. Where did you meet him? 9 A. I was shopping in my -- he showed up at my 10 friend's house. 11 Q. Whose house? 12 A. My friend Tiffany Rich. 13 Q. Is that Tiffany from the Quarterdeck 14 Tavern? 15 A. Yes. 16 Q. And did you have a meeting with him at 17 Tiffany Rich's house? 18 A. Yes. I guess you could say that. 19 Q. And who else was there? 20 A. My Aunt 21 Q. And what was that meeting about? 22 MR. LEOPOLD: Objection. That calls for 23 attorney/client privilege. 24 BY MR. TEIN: 25 Q. What discussions did you have with",
      "position": "main"
    },
    {
      "type": "printed",
      "content": "Ph. 561.682.0905 - Fax. 561.682.1771 1655 Palm Beach Lakes Blvd., Suite 500 - West Palm Beach, FL 33401",
      "position": "footer"
    },
    {
      "type": "printed",
      "content": "07/26/17 Page 2723 Public Records Request No.: 17-295 DOJ-OGR-00033036",
      "position": "footer"
    }
  ],
  "entities": {
    "people": [
      "Mr. Herman",
      "Tiffany Rich",
      "My Aunt",
      "My father",
      "MR. LEOPOLD",
      "MR. TEIN"
    ],
    "organizations": [
      "Florida Bar",
      "Censor & Associates"
    ],
    "locations": [
      "Quarterdeck Tavern",
      "West Palm Beach",
      "Palm Beach Lakes Blvd."
    ],
    "dates": [
      "07/26/17"
    ],
    "reference_numbers": [
      "17-295",
      "DOJ-OGR-00033036"
    ]
  },
  "additional_notes": "The document appears to be a transcript of a deposition or interview. There is a redacted name on line 20."
}