{
  "document_metadata": {
    "page_number": "78",
    "document_number": "17-295",
    "date": "07/26/17",
    "document_type": "transcript",
    "has_handwriting": false,
    "has_stamps": false
  },
  "full_text": "Censor & Associates Reporting and Transcription, Inc. Page 78 1 A. I don't know. 2 Q. What is his phone number? 3 A. How is that relevant? 4 Q. What is his phone number? 5 A. 561.719.2652. 6 Q. What is his home address? 7 A. I don't know. 8 Q. Where does he live? 9 A. In Palm Beach Lakes somewhere. 10 Q. Ever been to his house? 11 A. Yes. 12 Q. You don't know what his address is? 13 MR. LEOPOLD: Objection. Asked and answered. She just said she doesn't know. 14 15 MR. TEIN: Don't coach. 16 MR. LEOPOLD: Objection. Asked and answered. 17 18 BY MR. TEIN: 19 Q. You can answer the question. 20 A. I don't know the exact address. 21 Q. What street is it on? 22 A. It's an apartment complex; its not a 23 street. 24 Q. What's the name of the apartment complex? 25 A. Something Cove. Ph. 561.682.0905 - Fax. 561.682.1771 1655 Palm Beach Lakes Blvd., Suite 500 - West Palm Beach, FL 33401 07/26/17 Page 2753 Public Records Request No.: 17-295 DOJ-OGR-00033066",
  "text_blocks": [
    {
      "type": "printed",
      "content": "Censor & Associates Reporting and Transcription, Inc.",
      "position": "header"
    },
    {
      "type": "printed",
      "content": "Page 78",
      "position": "header"
    },
    {
      "type": "printed",
      "content": "1 A. I don't know. 2 Q. What is his phone number? 3 A. How is that relevant? 4 Q. What is his phone number? 5 A. 561.719.2652. 6 Q. What is his home address? 7 A. I don't know. 8 Q. Where does he live? 9 A. In Palm Beach Lakes somewhere. 10 Q. Ever been to his house? 11 A. Yes. 12 Q. You don't know what his address is? 13 MR. LEOPOLD: Objection. Asked and answered. She just said she doesn't know. 14 15 MR. TEIN: Don't coach. 16 MR. LEOPOLD: Objection. Asked and answered. 17 18 BY MR. TEIN: 19 Q. You can answer the question. 20 A. I don't know the exact address. 21 Q. What street is it on? 22 A. It's an apartment complex; its not a 23 street. 24 Q. What's the name of the apartment complex? 25 A. Something Cove.",
      "position": "main"
    },
    {
      "type": "printed",
      "content": "Ph. 561.682.0905 - Fax. 561.682.1771 1655 Palm Beach Lakes Blvd., Suite 500 - West Palm Beach, FL 33401",
      "position": "footer"
    },
    {
      "type": "printed",
      "content": "07/26/17 Page 2753 Public Records Request No.: 17-295 DOJ-OGR-00033066",
      "position": "footer"
    }
  ],
  "entities": {
    "people": [
      "MR. LEOPOLD",
      "MR. TEIN"
    ],
    "organizations": [
      "Censor & Associates"
    ],
    "locations": [
      "Palm Beach Lakes",
      "West Palm Beach",
      "FL"
    ],
    "dates": [
      "07/26/17"
    ],
    "reference_numbers": [
      "17-295",
      "DOJ-OGR-00033066",
      "561.719.2652",
      "561.682.0905",
      "561.682.1771"
    ]
  },
  "additional_notes": "The document appears to be a transcript of a deposition or interview. The quality is clear, and there are no visible redactions or damage."
}