{
  "document_metadata": {
    "page_number": "52",
    "document_number": "59",
    "date": "02/28/2023",
    "document_type": "Court Document",
    "has_handwriting": false,
    "has_stamps": false
  },
  "full_text": "Case 22-1426, Document 59, 02/28/2023, 3475902, Page52 of 113\n\nMoreover, the USAO-SDFL's involvement of the USAO for this District in its investigation of Epstein, as well its contact with witnesses in New York, reflect a coordinated effort that transcended the USAO-SDFL (Dkt 142, Exh. A at 46, 48, 60). From these facts, it affirmatively appears that the Government had every reason to foresee a potential prosecution of Epstein's co-conspirators in this District and, after multiple layers of review within the Department of Justice, intended to agree to preclude it. According to the OPR, the NPA originally read that it \"resolves the federal criminal liability of the defendant and any co-conspirators in the Southern District of Florida...\", but this language was modified and the final agreement was not so restricted as to the co-conspirators. Dkt 142, Exh. A at 74-75.\n\nThe OPR demonstrates the trans-district scope of the investigation and the negotiations.\n- Dkt 142, Exh A at 27 n.38 (Feds considered arresting Epstein in the Virgin Islands, rather than Florida, indicating national scope of investigation);\n- Id. at 46 (\"[I]nvestigators had learned that Epstein used hidden cameras in his New York residence to record his sexual encounters\");\n- Id. at 58 (AUSA Villafana requested \"enough time to go to New York, pursue investigative steps involving two of Epstein's assistants, do\n\n37\nDOJ-OGR-00021099",
  "text_blocks": [
    {
      "type": "printed",
      "content": "Case 22-1426, Document 59, 02/28/2023, 3475902, Page52 of 113",
      "position": "header"
    },
    {
      "type": "printed",
      "content": "Moreover, the USAO-SDFL's involvement of the USAO for this District in its investigation of Epstein, as well its contact with witnesses in New York, reflect a coordinated effort that transcended the USAO-SDFL (Dkt 142, Exh. A at 46, 48, 60). From these facts, it affirmatively appears that the Government had every reason to foresee a potential prosecution of Epstein's co-conspirators in this District and, after multiple layers of review within the Department of Justice, intended to agree to preclude it. According to the OPR, the NPA originally read that it \"resolves the federal criminal liability of the defendant and any co-conspirators in the Southern District of Florida...\", but this language was modified and the final agreement was not so restricted as to the co-conspirators. Dkt 142, Exh. A at 74-75.",
      "position": "main"
    },
    {
      "type": "printed",
      "content": "The OPR demonstrates the trans-district scope of the investigation and the negotiations.",
      "position": "main"
    },
    {
      "type": "printed",
      "content": "- Dkt 142, Exh A at 27 n.38 (Feds considered arresting Epstein in the Virgin Islands, rather than Florida, indicating national scope of investigation);\n- Id. at 46 (\"[I]nvestigators had learned that Epstein used hidden cameras in his New York residence to record his sexual encounters\");\n- Id. at 58 (AUSA Villafana requested \"enough time to go to New York, pursue investigative steps involving two of Epstein's assistants, do",
      "position": "main"
    },
    {
      "type": "printed",
      "content": "37",
      "position": "footer"
    },
    {
      "type": "printed",
      "content": "DOJ-OGR-00021099",
      "position": "footer"
    }
  ],
  "entities": {
    "people": [
      "Epstein",
      "Villafana"
    ],
    "organizations": [
      "USAO-SDFL",
      "USAO",
      "Department of Justice",
      "OPR"
    ],
    "locations": [
      "New York",
      "Florida",
      "Virgin Islands",
      "Southern District of Florida"
    ],
    "dates": [
      "02/28/2023"
    ],
    "reference_numbers": [
      "Case 22-1426",
      "Document 59",
      "Dkt 142",
      "Exh. A",
      "DOJ-OGR-00021099"
    ]
  },
  "additional_notes": "The document appears to be a court filing related to the Epstein case, discussing the investigation and prosecution of Epstein and his co-conspirators. The document is well-formatted and free of significant damage or redactions."
}