{
  "document_metadata": {
    "page_number": "3",
    "document_number": "1",
    "date": "11/19/19",
    "document_type": "court document",
    "has_handwriting": false,
    "has_stamps": false
  },
  "full_text": "Case 1:19-cr-00830-AT Document 1 Filed 11/19/19 Page 3 of 20\nmaterials handler supervisor, although THOMAS regularly worked overtime shifts as a correctional officer, including in the SHU. THOMAS worked an overtime shift in the SHU on August 10, 2019, from 12 a.m. to 8 a.m. THOMAS did not work his regular shift on August 8 or August 9, 2019, but did work an overtime shift in the SHU on August 9, 2019 from 12 a.m. to 8 a.m.\n5. As detailed herein, Jeffrey Epstein was incarcerated at the MCC between his arrest on July 6, 2019, and his suicide on August 10, 2019. Epstein was detained pending trial in the Southern District of New York on sex trafficking charges.\nTHE MCC AND INSTITUTIONAL COUNTS\n6. The MCC, which houses approximately 750 inmates at any given time, assigns inmates to various housing units within the MCC. The SHU is a housing unit within the MCC where inmates are securely separated from the general inmate population to ensure their own safety as well as the safety of staff and other inmates. The SHU is located on the ninth floor of the MCC, and access to that floor is controlled by a locked door that can be opened remotely only by an officer in the MCC's centralized control center (the \"Control Center\"), which is located on the first floor of the MCC. Access into the SHU is also controlled by a second locked door to which only correctional officers assigned to the SHU have\n3\nDOJ-OGR-00021910",
  "text_blocks": [
    {
      "type": "printed",
      "content": "Case 1:19-cr-00830-AT Document 1 Filed 11/19/19 Page 3 of 20",
      "position": "header"
    },
    {
      "type": "printed",
      "content": "materials handler supervisor, although THOMAS regularly worked overtime shifts as a correctional officer, including in the SHU. THOMAS worked an overtime shift in the SHU on August 10, 2019, from 12 a.m. to 8 a.m. THOMAS did not work his regular shift on August 8 or August 9, 2019, but did work an overtime shift in the SHU on August 9, 2019 from 12 a.m. to 8 a.m.",
      "position": "main content"
    },
    {
      "type": "printed",
      "content": "5. As detailed herein, Jeffrey Epstein was incarcerated at the MCC between his arrest on July 6, 2019, and his suicide on August 10, 2019. Epstein was detained pending trial in the Southern District of New York on sex trafficking charges.",
      "position": "main content"
    },
    {
      "type": "printed",
      "content": "THE MCC AND INSTITUTIONAL COUNTS",
      "position": "main content"
    },
    {
      "type": "printed",
      "content": "6. The MCC, which houses approximately 750 inmates at any given time, assigns inmates to various housing units within the MCC. The SHU is a housing unit within the MCC where inmates are securely separated from the general inmate population to ensure their own safety as well as the safety of staff and other inmates. The SHU is located on the ninth floor of the MCC, and access to that floor is controlled by a locked door that can be opened remotely only by an officer in the MCC's centralized control center (the \"Control Center\"), which is located on the first floor of the MCC. Access into the SHU is also controlled by a second locked door to which only correctional officers assigned to the SHU have",
      "position": "main content"
    },
    {
      "type": "printed",
      "content": "3",
      "position": "footer"
    },
    {
      "type": "printed",
      "content": "DOJ-OGR-00021910",
      "position": "footer"
    }
  ],
  "entities": {
    "people": [
      "THOMAS",
      "Jeffrey Epstein"
    ],
    "organizations": [
      "MCC",
      "SHU",
      "Control Center"
    ],
    "locations": [
      "Southern District of New York"
    ],
    "dates": [
      "August 10, 2019",
      "August 8, 2019",
      "August 9, 2019",
      "July 6, 2019",
      "11/19/19"
    ],
    "reference_numbers": [
      "1:19-cr-00830-AT",
      "Document 1",
      "DOJ-OGR-00021910"
    ]
  },
  "additional_notes": "The document appears to be a court filing related to the case of Jeffrey Epstein. The text is typed, and there are no visible redactions or damage."
}