{
  "document_metadata": {
    "page_number": "2 of 2",
    "document_number": "103",
    "date": "03/11/2024",
    "document_type": "NOTICE TO THE BAR",
    "has_handwriting": true,
    "has_stamps": false
  },
  "full_text": "Case 22-1426, Document 103, 03/11/2024, 3614272, Page2 of 2\nCase 22-1426, Document 99, 02/29/2024, 3612517, Page2 of 2\n\nName of the Attorney/Pro Se presenting argument: Diana Fabi\nFirm Name (if applicable): Aidala, Bertuna + Kamins, P.C.\nCurrent Telephone Number: 212-486-0011\n\nThe above named attorney represents:\n(√) Appellant/Petitioner () Appellee-Respondent () Intervenor\n\nDate: March 11, 2024 Signature: Diana Fabi\n\nNOTICE TO THE BAR\n\nRecording of Argument. An audio recording of oral argument is available on the Court's website. In addition, a CD of an argument may be purchased for $34 per CD by written request to the Clerk. The request should include the case name, the docket number and the date of oral argument. CDs will be delivered by first class mail unless the request instructs to hold for pick-up or requests Federal Express Service, in which case a Federal Express account number and envelope must be provided.\n\nCourt Reporters. Parties may arrange - at their own expense - for an official court reporter to transcribe argument from a copy of the hearing tape or to attend and transcribe the hearing directly. A party must first obtain written consent from opposing counsel - or move the Court for permission - to have the court reporter attend and transcribe the hearing and must provide the calendar clerk written notice, including the name, address and telephone number of the attending reporter and, if applicable, the reporting firm at least one week prior to the hearing date.\n\nInterpreter Services for the Hearing Impaired. Counsel requiring sign interpreters or other hearing aids must submit a written notice to the Calendar Team at least one week before oral argument.\n\nRev. 10/2023\n\nDOJ-OGR-00021793",
  "text_blocks": [
    {
      "type": "printed",
      "content": "Case 22-1426, Document 103, 03/11/2024, 3614272, Page2 of 2\nCase 22-1426, Document 99, 02/29/2024, 3612517, Page2 of 2",
      "position": "header"
    },
    {
      "type": "handwritten",
      "content": "Diana Fabi\nAidala, Bertuna + Kamins, P.C.\n212-486-0011\n(√) Appellant/Petitioner\nMarch 11, 2024\nDiana Fabi",
      "position": "middle"
    },
    {
      "type": "printed",
      "content": "NOTICE TO THE BAR\n\nRecording of Argument. An audio recording of oral argument is available on the Court's website. In addition, a CD of an argument may be purchased for $34 per CD by written request to the Clerk. The request should include the case name, the docket number and the date of oral argument. CDs will be delivered by first class mail unless the request instructs to hold for pick-up or requests Federal Express Service, in which case a Federal Express account number and envelope must be provided.\n\nCourt Reporters. Parties may arrange - at their own expense - for an official court reporter to transcribe argument from a copy of the hearing tape or to attend and transcribe the hearing directly. A party must first obtain written consent from opposing counsel - or move the Court for permission - to have the court reporter attend and transcribe the hearing and must provide the calendar clerk written notice, including the name, address and telephone number of the attending reporter and, if applicable, the reporting firm at least one week prior to the hearing date.\n\nInterpreter Services for the Hearing Impaired. Counsel requiring sign interpreters or other hearing aids must submit a written notice to the Calendar Team at least one week before oral argument.",
      "position": "middle"
    },
    {
      "type": "printed",
      "content": "Rev. 10/2023",
      "position": "footer"
    },
    {
      "type": "printed",
      "content": "DOJ-OGR-00021793",
      "position": "footer"
    }
  ],
  "entities": {
    "people": [
      "Diana Fabi"
    ],
    "organizations": [
      "Aidala, Bertuna + Kamins, P.C.",
      "Court",
      "Clerk",
      "Calendar Team"
    ],
    "locations": [],
    "dates": [
      "March 11, 2024",
      "03/11/2024",
      "02/29/2024",
      "10/2023"
    ],
    "reference_numbers": [
      "22-1426",
      "Document 103",
      "3614272",
      "Document 99",
      "3612517",
      "212-486-0011",
      "DOJ-OGR-00021793"
    ]
  },
  "additional_notes": "The document appears to be a notice to the bar regarding oral argument procedures. It includes handwritten information about the attorney presenting the argument and the date of the signature."
}