{
  "document_metadata": {
    "page_number": "1",
    "document_number": "9",
    "date": "11/19/19",
    "document_type": "Appearance Bond",
    "has_handwriting": false,
    "has_stamps": true
  },
  "full_text": "Case 1:19-cr-00830-AT Document 9 Filed 11/19/19 Page 1 of 8\nAO 98 (Rev. 12/11) Appearance Bond\nORIGINAL\nUNITED STATES DISTRICT COURT\nfor the\nSouthern District of New York\nUnited States of America\nv.\nTOVA NOEL\nDefendant\n19 CR 830\nAPPEARANCE BOND\nDefendant's Agreement\nI, TOVA NOEL (defendant), agree to follow every order of this court, or any court that considers this case, and I further agree that this bond may be forfeited if I fail:\n( ) to appear for court proceedings;\n( ) if convicted, to surrender to serve a sentence that the court may impose; or\n( ) to comply with all conditions set forth in the Order Setting Conditions of Release.\nType of Bond\n( ) (1) This is a personal recognizance bond.\n( X ) (2) This is an unsecured bond of $100,000 PRB.\n( ) (3) This is a secured bond of $, secured by:\n( ) (a) $, in cash deposited with the court.\n( ) (b) the agreement of the defendant and each surety to forfeit the following cash or other property (describe the cash or other property, including claims on it - such as a lien, mortgage, or loan - and attach proof of ownership and value):\nIf this bond is secured by real property, documents to protect the secured interest may be filed of record.\n( ) (c) a bail bond with a solvent surety (attach a copy of the bail bond, or describe it and identify the surety):\nForfeiture or Release of the Bond\nForfeiture of the Bond. This appearance bond may be forfeited if the defendant does not comply with the above agreement. The court may immediately order the amount of the bond surrendered to the United States, including the security for the bond, if the defendant does not comply with the agreement. At the request of the United States, the court may order a judgment of forfeiture against the defendant and each surety for the entire amount of the bond, including interest and costs.\nDOJ-OGR-00021942",
  "text_blocks": [
    {
      "type": "printed",
      "content": "Case 1:19-cr-00830-AT Document 9 Filed 11/19/19 Page 1 of 8",
      "position": "header"
    },
    {
      "type": "printed",
      "content": "AO 98 (Rev. 12/11) Appearance Bond",
      "position": "header"
    },
    {
      "type": "stamp",
      "content": "ORIGINAL",
      "position": "header"
    },
    {
      "type": "printed",
      "content": "UNITED STATES DISTRICT COURT\nfor the\nSouthern District of New York\nUnited States of America\nv.\nTOVA NOEL\nDefendant\n19 CR 830",
      "position": "top"
    },
    {
      "type": "printed",
      "content": "APPEARANCE BOND\nDefendant's Agreement",
      "position": "top"
    },
    {
      "type": "printed",
      "content": "I, TOVA NOEL (defendant), agree to follow every order of this court, or any court that considers this case, and I further agree that this bond may be forfeited if I fail:\n( ) to appear for court proceedings;\n( ) if convicted, to surrender to serve a sentence that the court may impose; or\n( ) to comply with all conditions set forth in the Order Setting Conditions of Release.",
      "position": "middle"
    },
    {
      "type": "printed",
      "content": "Type of Bond\n( ) (1) This is a personal recognizance bond.\n( X ) (2) This is an unsecured bond of $100,000 PRB.\n( ) (3) This is a secured bond of $, secured by:\n( ) (a) $, in cash deposited with the court.\n( ) (b) the agreement of the defendant and each surety to forfeit the following cash or other property (describe the cash or other property, including claims on it - such as a lien, mortgage, or loan - and attach proof of ownership and value):\nIf this bond is secured by real property, documents to protect the secured interest may be filed of record.\n( ) (c) a bail bond with a solvent surety (attach a copy of the bail bond, or describe it and identify the surety):",
      "position": "middle"
    },
    {
      "type": "printed",
      "content": "Forfeiture or Release of the Bond\nForfeiture of the Bond. This appearance bond may be forfeited if the defendant does not comply with the above agreement. The court may immediately order the amount of the bond surrendered to the United States, including the security for the bond, if the defendant does not comply with the agreement. At the request of the United States, the court may order a judgment of forfeiture against the defendant and each surety for the entire amount of the bond, including interest and costs.",
      "position": "bottom"
    },
    {
      "type": "printed",
      "content": "DOJ-OGR-00021942",
      "position": "footer"
    }
  ],
  "entities": {
    "people": [
      "TOVA NOEL"
    ],
    "organizations": [
      "United States District Court",
      "United States"
    ],
    "locations": [
      "New York"
    ],
    "dates": [
      "11/19/19"
    ],
    "reference_numbers": [
      "1:19-cr-00830-AT",
      "19 CR 830",
      "100,000 PRB",
      "DOJ-OGR-00021942"
    ]
  },
  "additional_notes": "The document is an Appearance Bond filed with the United States District Court for the Southern District of New York. It is related to the case of United States v. TOVA NOEL. The bond is an unsecured bond of $100,000 PRB."
}