{
  "document_metadata": {
    "page_number": "13",
    "document_number": "1:19-cr-00830-AT Document 1",
    "date": "11/19/19",
    "document_type": "Indictment",
    "has_handwriting": false,
    "has_stamps": false
  },
  "full_text": "Case 1:19-cr-00830-AT Document 1 Filed 11/19/19 Page 13 of 20\n27. Epstein was transferred to a local hospital where he was declared dead shortly thereafter. The Office of the Chief Medical Examiner of the City of New York conducted an autopsy and determined that Epstein had committed suicide by hanging himself.\nSTATUTORY ALLEGATIONS\nCOUNT ONE\n(Conspiracy)\nThe Grand Jury charges:\n28. The Grand Jury incorporates the allegations contained in paragraphs 1 through 27 of this Indictment as though fully set forth herein.\n29. In or about August 2019, in the Southern District of New York, TOVA NOEL and MICHAEL THOMAS, the defendants, knowingly conspired with each other to:\na. Knowingly defraud the United States by impairing, obstructing, and defeating the lawful functions of a department or agency of the United States, to wit, the MCC's function to ensure the care, custody, and control of its inmate population.\nb. Knowingly make and use a false writing or document knowing the same to contain a materially false, fictitious, and fraudulent statement and entry with the intent to impede, obstruct, or influence the investigation or proper administration of any matter within the jurisdiction of any 13\nDOJ-OGR-00021920",
  "text_blocks": [
    {
      "type": "printed",
      "content": "Case 1:19-cr-00830-AT Document 1 Filed 11/19/19 Page 13 of 20",
      "position": "header"
    },
    {
      "type": "printed",
      "content": "27. Epstein was transferred to a local hospital where he was declared dead shortly thereafter. The Office of the Chief Medical Examiner of the City of New York conducted an autopsy and determined that Epstein had committed suicide by hanging himself.\nSTATUTORY ALLEGATIONS\nCOUNT ONE\n(Conspiracy)\nThe Grand Jury charges:\n28. The Grand Jury incorporates the allegations contained in paragraphs 1 through 27 of this Indictment as though fully set forth herein.\n29. In or about August 2019, in the Southern District of New York, TOVA NOEL and MICHAEL THOMAS, the defendants, knowingly conspired with each other to:\na. Knowingly defraud the United States by impairing, obstructing, and defeating the lawful functions of a department or agency of the United States, to wit, the MCC's function to ensure the care, custody, and control of its inmate population.\nb. Knowingly make and use a false writing or document knowing the same to contain a materially false, fictitious, and fraudulent statement and entry with the intent to impede, obstruct, or influence the investigation or proper administration of any matter within the jurisdiction of any",
      "position": "main"
    },
    {
      "type": "printed",
      "content": "13",
      "position": "footer"
    },
    {
      "type": "printed",
      "content": "DOJ-OGR-00021920",
      "position": "footer"
    }
  ],
  "entities": {
    "people": [
      "Epstein",
      "TOVA NOEL",
      "MICHAEL THOMAS"
    ],
    "organizations": [
      "Office of the Chief Medical Examiner",
      "MCC",
      "Grand Jury"
    ],
    "locations": [
      "New York",
      "United States",
      "Southern District of New York"
    ],
    "dates": [
      "August 2019",
      "11/19/19"
    ],
    "reference_numbers": [
      "1:19-cr-00830-AT Document 1",
      "DOJ-OGR-00021920"
    ]
  },
  "additional_notes": "The document appears to be a page from a legal indictment. The text is typed, and there are no visible handwritten notes or stamps. The document is related to a criminal case involving the death of Epstein and allegations against TOVA NOEL and MICHAEL THOMAS."
}