{
  "document_metadata": {
    "page_number": "49",
    "document_number": "58",
    "date": "02/28/2023",
    "document_type": "Case Document",
    "has_handwriting": false,
    "has_stamps": false
  },
  "full_text": "Case 22-1426, Document 58, 02/28/2023, 3475901, Page 49 of 221\nA-249\n1/26/22, 3:30 PM Case 1:20-cr-03305-Makwell Morganthau DailyMail Online\nEXCLUSIVE: INMATES ARE 'ITCHING TO GET THEIR HANDS ON' CHARLIESE MUTTON'S STEPDAD - BUT FRIEND INSISTS\nLegal experts said that if David failed to disclose his past experiences before the jury deliberations, Maxwell could have grounds to claim a mistrial and have her convictions quashed.\nHowever, the question of whether a potential juror was a victim of sexual abuse or a relative or friend of a victim was asked in the 50-question survey completed by each juror ahead of selection.\nDavid said he went into the trial firmly believing that Maxwell was 'innocent until proven guilty' and viewing the victims with a skeptical eye.\nBut, he said, 'After all I've learned, she's just as guilty as Epstein. I don't want to call her a monster, but a predator is the right word.\n'She knew what was happening. She knew what Epstein was doing and she allowed it to happen. She participated in getting these girls comfortable so that he could have his way with them.\n'And, to me, them returning repeatedly for the money has nothing to do with anything because these girls were minors, and it doesn't matter what incentivized them. It matters what happened to them.'\nGhislaine Maxwell juror speaks out after guilty verdict\nWatch the full video\nhttps://www.dailymail.co.uk/news/article-10370193/Ghislaine-Maxwell-juror-says-evidence-convinced-panel-predator.html 2/16\nDOJ-OGR-00020875",
  "text_blocks": [
    {
      "type": "printed",
      "content": "Case 22-1426, Document 58, 02/28/2023, 3475901, Page 49 of 221",
      "position": "header"
    },
    {
      "type": "printed",
      "content": "A-249",
      "position": "header"
    },
    {
      "type": "printed",
      "content": "1/26/22, 3:30 PM Case 1:20-cr-03305-Makwell Morganthau DailyMail Online",
      "position": "top"
    },
    {
      "type": "printed",
      "content": "EXCLUSIVE: INMATES ARE 'ITCHING TO GET THEIR HANDS ON' CHARLIESE MUTTON'S STEPDAD - BUT FRIEND INSISTS",
      "position": "top"
    },
    {
      "type": "printed",
      "content": "Legal experts said that if David failed to disclose his past experiences before the jury deliberations, Maxwell could have grounds to claim a mistrial and have her convictions quashed.",
      "position": "middle"
    },
    {
      "type": "printed",
      "content": "However, the question of whether a potential juror was a victim of sexual abuse or a relative or friend of a victim was asked in the 50-question survey completed by each juror ahead of selection.",
      "position": "middle"
    },
    {
      "type": "printed",
      "content": "David said he went into the trial firmly believing that Maxwell was 'innocent until proven guilty' and viewing the victims with a skeptical eye.",
      "position": "middle"
    },
    {
      "type": "printed",
      "content": "But, he said, 'After all I've learned, she's just as guilty as Epstein. I don't want to call her a monster, but a predator is the right word.",
      "position": "middle"
    },
    {
      "type": "printed",
      "content": "'She knew what was happening. She knew what Epstein was doing and she allowed it to happen. She participated in getting these girls comfortable so that he could have his way with them.",
      "position": "middle"
    },
    {
      "type": "printed",
      "content": "'And, to me, them returning repeatedly for the money has nothing to do with anything because these girls were minors, and it doesn't matter what incentivized them. It matters what happened to them.'",
      "position": "middle"
    },
    {
      "type": "printed",
      "content": "Ghislaine Maxwell juror speaks out after guilty verdict",
      "position": "middle"
    },
    {
      "type": "printed",
      "content": "Watch the full video",
      "position": "middle"
    },
    {
      "type": "printed",
      "content": "https://www.dailymail.co.uk/news/article-10370193/Ghislaine-Maxwell-juror-says-evidence-convinced-panel-predator.html 2/16",
      "position": "footer"
    },
    {
      "type": "printed",
      "content": "DOJ-OGR-00020875",
      "position": "footer"
    }
  ],
  "entities": {
    "people": [
      "David",
      "Maxwell",
      "Epstein",
      "Ghislaine Maxwell"
    ],
    "organizations": [
      "DailyMail"
    ],
    "locations": [],
    "dates": [
      "1/26/22",
      "02/28/2023"
    ],
    "reference_numbers": [
      "Case 22-1426",
      "Document 58",
      "Case 1:20-cr-03305",
      "DOJ-OGR-00020875"
    ]
  },
  "additional_notes": "The document appears to be a court filing with an embedded news article about Ghislaine Maxwell's trial. The article includes quotes from a juror named David."
}