{
  "document_metadata": {
    "page_number": "1",
    "document_number": "65",
    "date": "1/3/2022",
    "document_type": "Court Document",
    "has_handwriting": false,
    "has_stamps": true
  },
  "full_text": "Case 1:19-cr-00830-AT Document 65 Filed 01/03/22 Page 1 of 3 UNITED STATES DISTRICT COURT SOUTHERN DISTRICT OF NEW YORK UNITED STATES OF AMERICA -v.- TOVA NOEL and MICHAEL THOMAS, Defendants. NOLLE PROSEQUI 19 Cr. 830 (AT) 1. The filing of this nolle prosequi will dispose of this case with respect to TOVA NOEL and MICHAEL THOMAS, the defendants. 2. On or about November 19, 2019, a grand jury sitting in this District returned Indictment 19 Cr. 830 (AT), which charged TOVA NOEL and MICHAEL THOMAS, the defendants, with committing offenses against the United States, to wit, conspiring to knowingly defraud the United States and to knowingly make and use a false writing or document, in violation of 18 U.S.C. § 371, and knowingly making and using a false writing or document, in violation of 18 U.S.C. § 1001. 3. On or about May 20, 2021, TOVA NOEL and MICHAEL THOMAS, the defendants, entered into deferred prosecution agreements with the Government. Under the agreements, prosecution was deferred for a period of six months during the term of NOEL's and THOMAS's good behavior, completion of community service, and DOJ-OGR-00022147",
  "text_blocks": [
    {
      "type": "printed",
      "content": "Case 1:19-cr-00830-AT Document 65 Filed 01/03/22 Page 1 of 3",
      "position": "header"
    },
    {
      "type": "printed",
      "content": "UNITED STATES DISTRICT COURT SOUTHERN DISTRICT OF NEW YORK",
      "position": "header"
    },
    {
      "type": "printed",
      "content": "UNITED STATES OF AMERICA -v.- TOVA NOEL and MICHAEL THOMAS, Defendants.",
      "position": "header"
    },
    {
      "type": "printed",
      "content": "NOLLE PROSEQUI 19 Cr. 830 (AT)",
      "position": "header"
    },
    {
      "type": "printed",
      "content": "1. The filing of this nolle prosequi will dispose of this case with respect to TOVA NOEL and MICHAEL THOMAS, the defendants.",
      "position": "body"
    },
    {
      "type": "printed",
      "content": "2. On or about November 19, 2019, a grand jury sitting in this District returned Indictment 19 Cr. 830 (AT), which charged TOVA NOEL and MICHAEL THOMAS, the defendants, with committing offenses against the United States, to wit, conspiring to knowingly defraud the United States and to knowingly make and use a false writing or document, in violation of 18 U.S.C. § 371, and knowingly making and using a false writing or document, in violation of 18 U.S.C. § 1001.",
      "position": "body"
    },
    {
      "type": "printed",
      "content": "3. On or about May 20, 2021, TOVA NOEL and MICHAEL THOMAS, the defendants, entered into deferred prosecution agreements with the Government. Under the agreements, prosecution was deferred for a period of six months during the term of NOEL's and THOMAS's good behavior, completion of community service, and",
      "position": "body"
    },
    {
      "type": "stamp",
      "content": "USDC SDNY DOCUMENT ELECTRONICALLY FILED DOC #: DATE FILED: 1/3/2022",
      "position": "margin"
    },
    {
      "type": "printed",
      "content": "DOJ-OGR-00022147",
      "position": "footer"
    }
  ],
  "entities": {
    "people": [
      "TOVA NOEL",
      "MICHAEL THOMAS"
    ],
    "organizations": [
      "UNITED STATES DISTRICT COURT",
      "UNITED STATES OF AMERICA",
      "Government"
    ],
    "locations": [
      "SOUTHERN DISTRICT OF NEW YORK",
      "United States"
    ],
    "dates": [
      "November 19, 2019",
      "May 20, 2021",
      "1/3/2022"
    ],
    "reference_numbers": [
      "19 Cr. 830 (AT)",
      "18 U.S.C. § 371",
      "18 U.S.C. § 1001",
      "DOJ-OGR-00022147"
    ]
  },
  "additional_notes": "The document appears to be a court filing related to a criminal case. It is a formal document with a clear structure and formatting. The text is mostly printed, with a stamp in the margin indicating electronic filing. The document contains specific details about the case, including the names of the defendants, the charges, and the outcome."
}