{
  "document_metadata": {
    "page_number": "29",
    "document_number": "566",
    "date": "12/28/2021",
    "document_type": "Proposed Jury Instruction",
    "has_handwriting": false,
    "has_stamps": false
  },
  "full_text": "Case 22-1426, Document 58, 02/28/2023, 3475901, Page 29 of 221\nA-229\nCase 1:20-cr-00330-AJN Document 566 Filed 12/28/21 Page 7 of 7\nThe Honorable Alison J. Nathan\nDecember 27, 2021\nPage 7\nProposed Jury Instruction\nFor the reasons set forth above, we request that the Court give the jury the following additional instruction tomorrow:\nAs to the third element of Count Two, you must determine whether the Government has proven beyond a reasonable doubt that the Defendant acted with the intent that Jane would engage in sexual activity within the state of New York in violation of New York Penal Law 130.55.\nAs to the second element of Count Four, you must determine whether the Government has proven beyond a reasonable doubt that the Defendant transported Jane with the intent that Jane would engage in sexual activity within the state of New York in violation of New York Penal Law 130.55.\nAn intent that Jane engage in sexual activity in any state other than New York cannot form the basis of these two elements of Counts Two and Four.\nSincerely,\n/s/ Christian Everdell\nChristian R. Everdell\nCOHEN & GRESSER LLP\n800 Third Avenue, 21st Floor\nNew York, New York 10022\n(212) 957-7600\ncc: All Counsel of Record (By Email)\n2068538.1\nDOJ-OGR-00020855",
  "text_blocks": [
    {
      "type": "printed",
      "content": "Case 22-1426, Document 58, 02/28/2023, 3475901, Page 29 of 221",
      "position": "header"
    },
    {
      "type": "printed",
      "content": "A-229",
      "position": "header"
    },
    {
      "type": "printed",
      "content": "Case 1:20-cr-00330-AJN Document 566 Filed 12/28/21 Page 7 of 7",
      "position": "header"
    },
    {
      "type": "printed",
      "content": "The Honorable Alison J. Nathan\nDecember 27, 2021\nPage 7",
      "position": "top"
    },
    {
      "type": "printed",
      "content": "Proposed Jury Instruction",
      "position": "top"
    },
    {
      "type": "printed",
      "content": "For the reasons set forth above, we request that the Court give the jury the following additional instruction tomorrow:\nAs to the third element of Count Two, you must determine whether the Government has proven beyond a reasonable doubt that the Defendant acted with the intent that Jane would engage in sexual activity within the state of New York in violation of New York Penal Law 130.55.\nAs to the second element of Count Four, you must determine whether the Government has proven beyond a reasonable doubt that the Defendant transported Jane with the intent that Jane would engage in sexual activity within the state of New York in violation of New York Penal Law 130.55.\nAn intent that Jane engage in sexual activity in any state other than New York cannot form the basis of these two elements of Counts Two and Four.",
      "position": "middle"
    },
    {
      "type": "printed",
      "content": "Sincerely,",
      "position": "middle"
    },
    {
      "type": "signature",
      "content": "/s/ Christian Everdell",
      "position": "middle"
    },
    {
      "type": "printed",
      "content": "Christian R. Everdell\nCOHEN & GRESSER LLP\n800 Third Avenue, 21st Floor\nNew York, New York 10022\n(212) 957-7600",
      "position": "middle"
    },
    {
      "type": "printed",
      "content": "cc: All Counsel of Record (By Email)",
      "position": "bottom"
    },
    {
      "type": "printed",
      "content": "2068538.1",
      "position": "footer"
    },
    {
      "type": "printed",
      "content": "DOJ-OGR-00020855",
      "position": "footer"
    }
  ],
  "entities": {
    "people": [
      "Alison J. Nathan",
      "Christian Everdell",
      "Jane"
    ],
    "organizations": [
      "COHEN & GRESSER LLP"
    ],
    "locations": [
      "New York"
    ],
    "dates": [
      "December 27, 2021",
      "12/28/2021",
      "02/28/2023"
    ],
    "reference_numbers": [
      "Case 22-1426",
      "Document 58",
      "Case 1:20-cr-00330-AJN",
      "Document 566",
      "2068538.1",
      "DOJ-OGR-00020855"
    ]
  },
  "additional_notes": "The document appears to be a formal legal document, specifically a proposed jury instruction, with a clear and professional layout. There are no visible redactions or damage."
}