{
  "document_metadata": {
    "page_number": "7",
    "document_number": "638",
    "date": "03/09/22",
    "document_type": "Jury Questionnaire",
    "has_handwriting": true,
    "has_stamps": false
  },
  "full_text": "Case 22-1426, Document 58, 02/28/2023, 3475901, Page 95 of 221\nA-295\nCase 1:20-cr-00330-AJN Document 638 Filed 03/09/22 Page 7 of 29\nJuror ID: 50\n12. The law provides that a defendant in a criminal case has an absolute right not to testify, and that a juror cannot hold it against the defendant if she chooses not to testify. Do you accept this principle, and will you be able to apply it if selected to serve on this jury?\nYes No\n12a. If no, please explain:\n13. A juror is required by law to make his or her decision based solely on the evidence or lack of evidence presented in Court, and not on the basis of conjecture, suspicion, bias, sympathy, or prejudice. Do you accept this principle, and will you be able to apply it if selected to serve on this jury?\nYes No\n13a. If no, please explain:\n14. Under the law, the question of punishment is for the Court alone to decide, and thus the issue of punishment must not enter into your deliberations as to whether the defendant is guilty or not guilty as charged. Do you accept this principle, and will you be able to apply it if selected to serve on this jury?\nYes No\n14a. If no, please explain:\n-9-\nDOJ-OGR-00020921",
  "text_blocks": [
    {
      "type": "printed",
      "content": "Case 22-1426, Document 58, 02/28/2023, 3475901, Page 95 of 221",
      "position": "header"
    },
    {
      "type": "printed",
      "content": "Case 1:20-cr-00330-AJN Document 638 Filed 03/09/22 Page 7 of 29",
      "position": "header"
    },
    {
      "type": "handwritten",
      "content": "50",
      "position": "inline"
    },
    {
      "type": "printed",
      "content": "The law provides that a defendant in a criminal case has an absolute right not to testify, and that a juror cannot hold it against the defendant if she chooses not to testify. Do you accept this principle, and will you be able to apply it if selected to serve on this jury?",
      "position": "inline"
    },
    {
      "type": "handwritten",
      "content": "Yes",
      "position": "inline"
    },
    {
      "type": "printed",
      "content": "If no, please explain:",
      "position": "inline"
    },
    {
      "type": "printed",
      "content": "A juror is required by law to make his or her decision based solely on the evidence or lack of evidence presented in Court, and not on the basis of conjecture, suspicion, bias, sympathy, or prejudice. Do you accept this principle, and will you be able to apply it if selected to serve on this jury?",
      "position": "inline"
    },
    {
      "type": "handwritten",
      "content": "Yes",
      "position": "inline"
    },
    {
      "type": "printed",
      "content": "If no, please explain:",
      "position": "inline"
    },
    {
      "type": "printed",
      "content": "Under the law, the question of punishment is for the Court alone to decide, and thus the issue of punishment must not enter into your deliberations as to whether the defendant is guilty or not guilty as charged. Do you accept this principle, and will you be able to apply it if selected to serve on this jury?",
      "position": "inline"
    },
    {
      "type": "handwritten",
      "content": "Yes",
      "position": "inline"
    },
    {
      "type": "printed",
      "content": "If no, please explain:",
      "position": "inline"
    },
    {
      "type": "printed",
      "content": "-9-",
      "position": "footer"
    },
    {
      "type": "printed",
      "content": "DOJ-OGR-00020921",
      "position": "footer"
    }
  ],
  "entities": {
    "people": [],
    "organizations": [
      "Court",
      "DOJ"
    ],
    "locations": [],
    "dates": [
      "02/28/2023",
      "03/09/22"
    ],
    "reference_numbers": [
      "Case 22-1426",
      "Document 58",
      "Case 1:20-cr-00330-AJN",
      "Document 638",
      "DOJ-OGR-00020921"
    ]
  },
  "additional_notes": "The document is a jury questionnaire with handwritten answers. The juror ID is 50, and all answers are 'Yes'."
}