{
  "document_metadata": {
    "page_number": null,
    "document_number": "1:20-cr-0330",
    "date": "7/7/2022",
    "document_type": "Criminal Notice of Appeal - Form A",
    "has_handwriting": true,
    "has_stamps": true
  },
  "full_text": "Case1:20-cr-0330-ALC Document109 Filed07/07/22Page1of1\nCriminal Notice of Appeal - Form A\nNOTICE OF APPEAL\nUnited States District Court\nSouthern District of New York\nCaption:\nUnited States of America,\nGhislaine Maxwell\nDocket No. S2 20 Cr. 330\nAlison J. Nathan (SJD)\n(District Court Judge)\nNotice is hereby given that Ghislaine Maxwell appeals to the United States Court of Appeals for the Second Circuit from the judgment , other (specify)\nentered in this action on 6/29/2022 (date)\nThis appeal concerns: Conviction only Sentence only Conviction & Sentence Other .\nDefendant found guilty by plea trial N/A .\nOffense occurred after November 1, 1987? Yes No N/A .\nDate of sentence: 6/28/2022 N/A\nBail/Jail Disposition: Committed Not committed N/A .\nAppellant is represented by counsel? Yes No If yes, provide the following information:\nDefendant's Counsel: Bobbi C. Sternheim, Law Offices of Bobbi C. Sternheim\nCounsel's Address: 225 Broadway, Suite 715\nNew York, NY 10007\nCounsel's Phone: 212-243-1100\nAssistant U.S. Attorney: Maurene Comey\nAUSA's Address: One Saint Andrew's Plaza\nNew York, NY 10007\nAUSA's Phone: 212-637-2324\n* FOR FILING OF NOTICE OF APPEAL ONLY\n** NOT RETAINED FOR REPRESENTATION ON APPEAL\nSignature\nDOCUMENT ELECTRONICALLY FILED\nDOC#: DATE FILED: 7/7/2022\nS.D.N.Y. 2022 JUL 7 - 7 U.S. DISTRICT COURT\nFILED\nST\n7/7/2022\n$ 505.00\n0822",
  "text_blocks": [
    {
      "type": "printed",
      "content": "Criminal Notice of Appeal - Form A",
      "position": "header"
    },
    {
      "type": "printed",
      "content": "NOTICE OF APPEAL",
      "position": "header"
    },
    {
      "type": "printed",
      "content": "United States District Court",
      "position": "header"
    },
    {
      "type": "printed",
      "content": "Southern District of New York",
      "position": "header"
    },
    {
      "type": "handwritten",
      "content": "Ghislaine Maxwell",
      "position": "middle"
    },
    {
      "type": "printed",
      "content": "Docket No. S2 20 Cr. 330",
      "position": "middle"
    },
    {
      "type": "printed",
      "content": "Alison J. Nathan (SJD)",
      "position": "middle"
    },
    {
      "type": "printed",
      "content": "(District Court Judge)",
      "position": "middle"
    },
    {
      "type": "handwritten",
      "content": "Ghislaine Maxwell",
      "position": "middle"
    },
    {
      "type": "printed",
      "content": "Notice is hereby given that Ghislaine Maxwell appeals to the United States Court of Appeals for the Second Circuit from the judgment , other (specify)",
      "position": "middle"
    },
    {
      "type": "handwritten",
      "content": "6/29/2022",
      "position": "middle"
    },
    {
      "type": "printed",
      "content": "(date)",
      "position": "middle"
    },
    {
      "type": "printed",
      "content": "This appeal concerns: Conviction only Sentence only Conviction & Sentence Other .",
      "position": "middle"
    },
    {
      "type": "handwritten",
      "content": "trial",
      "position": "middle"
    },
    {
      "type": "printed",
      "content": "Defendant found guilty by plea trial N/A .",
      "position": "middle"
    },
    {
      "type": "handwritten",
      "content": "No",
      "position": "middle"
    },
    {
      "type": "printed",
      "content": "Offense occurred after November 1, 1987? Yes No N/A .",
      "position": "middle"
    },
    {
      "type": "handwritten",
      "content": "6/28/2022",
      "position": "middle"
    },
    {
      "type": "printed",
      "content": "Date of sentence: 6/28/2022 N/A",
      "position": "middle"
    },
    {
      "type": "handwritten",
      "content": "Committed",
      "position": "middle"
    },
    {
      "type": "printed",
      "content": "Bail/Jail Disposition: Committed Not committed N/A .",
      "position": "middle"
    },
    {
      "type": "printed",
      "content": "Appellant is represented by counsel? Yes No If yes, provide the following information:",
      "position": "middle"
    },
    {
      "type": "handwritten",
      "content": "Bobbi C. Sternheim, Law Offices of Bobbi C. Sternheim",
      "position": "middle"
    },
    {
      "type": "printed",
      "content": "Defendant's Counsel: Bobbi C. Sternheim, Law Offices of Bobbi C. Sternheim",
      "position": "middle"
    },
    {
      "type": "handwritten",
      "content": "225 Broadway, Suite 715",
      "position": "middle"
    },
    {
      "type": "handwritten",
      "content": "New York, NY 10007",
      "position": "middle"
    },
    {
      "type": "handwritten",
      "content": "212-243-1100",
      "position": "middle"
    },
    {
      "type": "printed",
      "content": "Counsel's Address: 225 Broadway, Suite 715",
      "position": "middle"
    },
    {
      "type": "printed",
      "content": "New York, NY 10007",
      "position": "middle"
    },
    {
      "type": "printed",
      "content": "Counsel's Phone: 212-243-1100",
      "position": "middle"
    },
    {
      "type": "handwritten",
      "content": "Maurene Comey",
      "position": "middle"
    },
    {
      "type": "printed",
      "content": "Assistant U.S. Attorney: Maurene Comey",
      "position": "middle"
    },
    {
      "type": "handwritten",
      "content": "One Saint Andrew's Plaza",
      "position": "middle"
    },
    {
      "type": "handwritten",
      "content": "New York, NY 10007",
      "position": "middle"
    },
    {
      "type": "handwritten",
      "content": "212-637-2324",
      "position": "middle"
    },
    {
      "type": "printed",
      "content": "AUSA's Address: One Saint Andrew's Plaza",
      "position": "middle"
    },
    {
      "type": "printed",
      "content": "New York, NY 10007",
      "position": "middle"
    },
    {
      "type": "printed",
      "content": "AUSA's Phone: 212-637-2324",
      "position": "middle"
    },
    {
      "type": "handwritten",
      "content": "Bobbi C. Sternheim",
      "position": "footer"
    },
    {
      "type": "printed",
      "content": "* FOR FILING OF NOTICE OF APPEAL ONLY",
      "position": "footer"
    },
    {
      "type": "printed",
      "content": "** NOT RETAINED FOR REPRESENTATION ON APPEAL",
      "position": "footer"
    },
    {
      "type": "printed",
      "content": "Signature",
      "position": "footer"
    },
    {
      "type": "stamp",
      "content": "DOCUMENT ELECTRONICALLY FILED",
      "position": "header"
    },
    {
      "type": "stamp",
      "content": "DATE FILED: 7/7/2022",
      "position": "header"
    },
    {
      "type": "stamp",
      "content": "S.D.N.Y. 2022 JUL 7 - 7 U.S. DISTRICT COURT FILED",
      "position": "margin"
    }
  ],
  "entities": {
    "people": [
      "Ghislaine Maxwell",
      "Alison J. Nathan",
      "Bobbi C. Sternheim",
      "Maurene Comey"
    ],
    "organizations": [
      "United States Court of Appeals for the Second Circuit",
      "United States District Court",
      "Law Offices of Bobbi C. Sternheim"
    ],
    "locations": [
      "New York",
      "Southern District of New York"
    ],
    "dates": [
      "6/29/2022",
      "6/28/2022",
      "7/7/2022",
      "November 1, 1987"
    ],
    "reference_numbers": [
      "S2 20 Cr. 330",
      "1:20-cr-0330"
    ]
  },
  "additional_notes": "The document is a Criminal Notice of Appeal - Form A, filed on 7/7/2022. It contains handwritten and printed text, as well as stamps. The document is related to the case of Ghislaine Maxwell, who is appealing a judgment entered on 6/29/2022. The appeal concerns the conviction and sentence. The defendant was found guilty by trial. The document includes information about the defendant's counsel, Bobbi C. Sternheim, and the Assistant U.S. Attorney, Maurene Comey."
}