{
  "document_metadata": {
    "page_number": "1",
    "document_number": "23",
    "date": "01/30/2020",
    "document_type": "Court Order",
    "has_handwriting": true,
    "has_stamps": true
  },
  "full_text": "Case 1:19-cr-00830-AT Document 23 Filed 01/30/20 Page 1 of 1\n\nUNITED STATES DISTRICT COURT SOUTHERN DISTRICT OF NEW YORK\nUNITED STATES OF AMERICA,\n\n-against-\n\nTOVA NOEL and MICHAEL THOMAS,\nDefendants.\n\nANALISA TORRES, District Judge:\n\nAt the status conference held on January 30, 2020, Defendant Michael Thomas informed the Court of his intention to file a motion to dismiss. Accordingly, it is hereby ORDERED that:\n\n(1) By March 20, 2020, Mr. Thomas shall file his motion to dismiss;\n(2) By April 10, 2020, the Government shall file its opposition;\n(3) By April 24, 2020, Mr. Thomas shall file his reply, if any.\n\nSO ORDERED.\n\nDated: January 30, 2020\nNew York, New York\n\nANALISA TORRES\nUnited States District Judge\n\nUSDC SDNY DOCUMENT ELECTRONICALLY FILED DOC #: DATE FILED: 1/30/2020\n\nDOJ-OGR-00022001",
  "text_blocks": [
    {
      "type": "printed",
      "content": "Case 1:19-cr-00830-AT Document 23 Filed 01/30/20 Page 1 of 1",
      "position": "header"
    },
    {
      "type": "printed",
      "content": "UNITED STATES DISTRICT COURT SOUTHERN DISTRICT OF NEW YORK",
      "position": "top"
    },
    {
      "type": "printed",
      "content": "UNITED STATES OF AMERICA, -against- TOVA NOEL and MICHAEL THOMAS, Defendants.",
      "position": "top"
    },
    {
      "type": "printed",
      "content": "ANALISA TORRES, District Judge:",
      "position": "middle"
    },
    {
      "type": "printed",
      "content": "At the status conference held on January 30, 2020, Defendant Michael Thomas informed the Court of his intention to file a motion to dismiss. Accordingly, it is hereby ORDERED that:",
      "position": "middle"
    },
    {
      "type": "printed",
      "content": "(1) By March 20, 2020, Mr. Thomas shall file his motion to dismiss; (2) By April 10, 2020, the Government shall file its opposition; (3) By April 24, 2020, Mr. Thomas shall file his reply, if any.",
      "position": "middle"
    },
    {
      "type": "printed",
      "content": "SO ORDERED.",
      "position": "middle"
    },
    {
      "type": "printed",
      "content": "Dated: January 30, 2020 New York, New York",
      "position": "middle"
    },
    {
      "type": "signature",
      "content": "ANALISA TORRES United States District Judge",
      "position": "bottom"
    },
    {
      "type": "stamp",
      "content": "USDC SDNY DOCUMENT ELECTRONICALLY FILED DOC #: DATE FILED: 1/30/2020",
      "position": "margin"
    },
    {
      "type": "printed",
      "content": "DOJ-OGR-00022001",
      "position": "footer"
    }
  ],
  "entities": {
    "people": [
      "Tova Noel",
      "Michael Thomas",
      "Analisa Torres"
    ],
    "organizations": [
      "United States District Court",
      "United States of America",
      "Government"
    ],
    "locations": [
      "New York"
    ],
    "dates": [
      "January 30, 2020",
      "March 20, 2020",
      "April 10, 2020",
      "April 24, 2020"
    ],
    "reference_numbers": [
      "1:19-cr-00830-AT",
      "Document 23",
      "DOJ-OGR-00022001"
    ]
  },
  "additional_notes": "The document is a court order from the United States District Court for the Southern District of New York. It is signed by Judge Analisa Torres and stamped as electronically filed on January 30, 2020."
}