{
  "document_metadata": {
    "page_number": "117",
    "document_number": "57",
    "date": "02/28/2023",
    "document_type": "Docket Report",
    "has_handwriting": false,
    "has_stamps": false
  },
  "full_text": "Case 22-1426, Document 57, 02/28/2023, 3475900, Page117 of 208\nA-113\n2/22/23, 1:25 PM SDNY CM/ECF NextGen Version 1.6\nTranscript Deadline set for 9/12/2022. Release of Transcript Restriction set for 11/9/2022. (Moya, Goretti) (Entered: 08/10/2022)\n08/10/2022 776 NOTICE OF FILING OF OFFICIAL TRANSCRIPT as to Ghislaine Maxwell. Notice is hereby given that an official transcript of a Trial proceeding held on 12/28/21 has been filed by the court reporter/transcriber in the above-captioned matter. The parties have seven (7) calendar days to file with the court a Notice of Intent to Request Redaction of this transcript. If no such Notice is filed, the transcript may be made remotely electronically available to the public without redaction after 90 calendar days.... (Moya, Goretti) (Entered: 08/10/2022)\n08/10/2022 777 TRANSCRIPT of Proceedings as to Ghislaine Maxwell re: Trial held on 12/29/21 before Judge Alison J. Nathan. Court Reporter/Transcriber: Paula Speer, (212) 805-0300, Reporter/Transcriber before the deadline for Release of Transcript Restriction. After that date it may be obtained through PACER. Redaction Request due 8/31/2022. Redacted Transcript Deadline set for 9/12/2022. Release of Transcript Restriction set for 11/9/2022. (Moya, Goretti) (Entered: 08/10/2022)\n08/10/2022 778 NOTICE OF FILING OF OFFICIAL TRANSCRIPT as to Ghislaine Maxwell. Notice is hereby given that an official transcript of a Trial proceeding held on 12/29/21 has been filed by the court reporter/transcriber in the above-captioned matter. The parties have seven (7) calendar days to file with the court a Notice of Intent to Request Redaction of this transcript. If no such Notice is filed, the transcript may be made remotely electronically available to the public without redaction after 90 calendar days.... (Moya, Goretti) (Entered: 08/10/2022)\n08/22/2022 779 TRANSCRIPT of Proceedings as to Ghislaine Maxwell re: Sentence held on 6/28/2022 before Judge Alison J. Nathan. Court Reporter/Transcriber: Alena Lynch, (212) 805-0300, Reporter/Transcriber before the deadline for Release of Transcript Restriction. After that date it may be obtained through PACER. Redaction Request due 9/12/2022. Redacted Transcript Deadline set for 9/22/2022. Release of Transcript Restriction set for 11/21/2022. (McGuirk, Kelly) (Entered: 08/22/2022)\n08/22/2022 780 NOTICE OF FILING OF OFFICIAL TRANSCRIPT as to Ghislaine Maxwell. Notice is hereby given that an official transcript of a Sentence proceeding held on 6/28/2022 has been filed by the court reporter/transcriber in the above-captioned matter. The parties have seven (7) calendar days to file with the court a Notice of Intent to Request Redaction of this transcript. If no such Notice is filed, the transcript may be made remotely electronically available to the public without redaction after 90 calendar days.... (McGuirk, Kelly) (Entered: 08/22/2022)\nPACER Service Center\nTransaction Receipt\n02/22/2023 13:25:07\nPACER Login: cpnycpara16 Client Code: \nDescription: Docket Report Search Criteria: 1:20-cr-00330-AJN\nBillable Pages: 30 Cost: 3.00",
  "text_blocks": [
    {
      "type": "printed",
      "content": "Case 22-1426, Document 57, 02/28/2023, 3475900, Page117 of 208",
      "position": "header"
    },
    {
      "type": "printed",
      "content": "A-113",
      "position": "header"
    },
    {
      "type": "printed",
      "content": "2/22/23, 1:25 PM SDNY CM/ECF NextGen Version 1.6",
      "position": "top"
    },
    {
      "type": "printed",
      "content": "Transcript Deadline set for 9/12/2022. Release of Transcript Restriction set for 11/9/2022. (Moya, Goretti) (Entered: 08/10/2022)",
      "position": "top"
    },
    {
      "type": "printed",
      "content": "08/10/2022 776 NOTICE OF FILING OF OFFICIAL TRANSCRIPT as to Ghislaine Maxwell. Notice is hereby given that an official transcript of a Trial proceeding held on 12/28/21 has been filed by the court reporter/transcriber in the above-captioned matter. The parties have seven (7) calendar days to file with the court a Notice of Intent to Request Redaction of this transcript. If no such Notice is filed, the transcript may be made remotely electronically available to the public without redaction after 90 calendar days.... (Moya, Goretti) (Entered: 08/10/2022)",
      "position": "middle"
    },
    {
      "type": "printed",
      "content": "08/10/2022 777 TRANSCRIPT of Proceedings as to Ghislaine Maxwell re: Trial held on 12/29/21 before Judge Alison J. Nathan. Court Reporter/Transcriber: Paula Speer, (212) 805-0300, Reporter/Transcriber before the deadline for Release of Transcript Restriction. After that date it may be obtained through PACER. Redaction Request due 8/31/2022. Redacted Transcript Deadline set for 9/12/2022. Release of Transcript Restriction set for 11/9/2022. (Moya, Goretti) (Entered: 08/10/2022)",
      "position": "middle"
    },
    {
      "type": "printed",
      "content": "08/10/2022 778 NOTICE OF FILING OF OFFICIAL TRANSCRIPT as to Ghislaine Maxwell. Notice is hereby given that an official transcript of a Trial proceeding held on 12/29/21 has been filed by the court reporter/transcriber in the above-captioned matter. The parties have seven (7) calendar days to file with the court a Notice of Intent to Request Redaction of this transcript. If no such Notice is filed, the transcript may be made remotely electronically available to the public without redaction after 90 calendar days.... (Moya, Goretti) (Entered: 08/10/2022)",
      "position": "middle"
    },
    {
      "type": "printed",
      "content": "08/22/2022 779 TRANSCRIPT of Proceedings as to Ghislaine Maxwell re: Sentence held on 6/28/2022 before Judge Alison J. Nathan. Court Reporter/Transcriber: Alena Lynch, (212) 805-0300, Reporter/Transcriber before the deadline for Release of Transcript Restriction. After that date it may be obtained through PACER. Redaction Request due 9/12/2022. Redacted Transcript Deadline set for 9/22/2022. Release of Transcript Restriction set for 11/21/2022. (McGuirk, Kelly) (Entered: 08/22/2022)",
      "position": "middle"
    },
    {
      "type": "printed",
      "content": "08/22/2022 780 NOTICE OF FILING OF OFFICIAL TRANSCRIPT as to Ghislaine Maxwell. Notice is hereby given that an official transcript of a Sentence proceeding held on 6/28/2022 has been filed by the court reporter/transcriber in the above-captioned matter. The parties have seven (7) calendar days to file with the court a Notice of Intent to Request Redaction of this transcript. If no such Notice is filed, the transcript may be made remotely electronically available to the public without redaction after 90 calendar days.... (McGuirk, Kelly) (Entered: 08/22/2022)",
      "position": "middle"
    },
    {
      "type": "printed",
      "content": "PACER Service Center\nTransaction Receipt\n02/22/2023 13:25:07\nPACER Login: cpnycpara16 Client Code: \nDescription: Docket Report Search Criteria: 1:20-cr-00330-AJN\nBillable Pages: 30 Cost: 3.00",
      "position": "bottom"
    }
  ],
  "entities": {
    "people": [
      "Ghislaine Maxwell",
      "Alison J. Nathan",
      "Paula Speer",
      "Alena Lynch",
      "Moya Goretti",
      "Kelly McGuirk"
    ],
    "organizations": [
      "PACER Service Center",
      "SDNY CM/ECF"
    ],
    "locations": [],
    "dates": [
      "08/10/2022",
      "12/28/21",
      "12/29/21",
      "08/22/2022",
      "6/28/2022",
      "9/12/2022",
      "11/9/2022",
      "8/31/2022",
      "9/22/2022",
      "11/21/2022",
      "02/22/2023"
    ],
    "reference_numbers": [
      "Case 22-1426",
      "Document 57",
      "3475900",
      "1:20-cr-00330-AJN",
      "776",
      "777",
      "778",
      "779",
      "780"
    ]
  },
  "additional_notes": "The document appears to be a docket report from the PACER Service Center, detailing various transcripts and notices related to the case of Ghislaine Maxwell. The document is well-formatted and legible, with clear headers and sections. There are no visible redactions or damages."
}