{
  "document_metadata": {
    "page_number": "275",
    "document_number": "204-3",
    "date": "04/16/21",
    "document_type": "court document",
    "has_handwriting": false,
    "has_stamps": false
  },
  "full_text": "Case 22-1426, Document 78, 06/29/2023, 3536039, Page21 of 217\nSA-275\nCase 1:20-cr-00330-AJN Document 204-3 Filed 04/16/21 Page 275 of 348\n\n(4) During court proceedings, a responsible official shall ensure that a victim is provided a waiting area removed from and out of the sight and hearing of the defendant and defense witnesses.\n...\n(e) Definitions\n...\n(2) the term \"victim\" means a person that has suffered direct physical, emotional, or pecuniary harm as a result of the commission of a crime...\n\nII. DEPARTMENT POLICY: THE 2005 ATTORNEY GENERAL GUIDELINES FOR VICTIM AND WITNESS ASSISTANCE (2005 GUIDELINES)\n\nIn 2005, the Department revised its guidelines for victim and witness assistance in order to incorporate the provisions of the CVRA. The purpose of the 2005 Guidelines was \"to establish guidelines to be followed by officers and employees of Department of Justice investigative, prosecutorial, and correctional components in the treatment of victims of and witnesses to crime.\" The relevant portions of the 2005 Guidelines are as follows:\n\nArticle IV: Services to Victims and Witnesses\n\nA. Investigation Stage\n\nThe investigative agency's responsibilities begin with the report of the crime and extend through the prosecution of the case. In some instances, when explicitly stated, the investigative agency's responsibility for a certain task is transferred to the prosecuting agency when charges are filed.\n...\n2. Identification of Victims. At the earliest opportunity after the detection of a crime at which it may be done without interfering with an investigation, the responsible official of the investigative agency shall identify the victims of the crime.\n\n3. Description of Services.\n\na. Information, Notice, and Referral\n\n(1) Initial Information and Notice. Responsible officials must advise a victim pursuant to this section at the earliest opportunity after detection of a crime at which it may be done without interfering with an investigation. To comply with this requirement, it is recommended that victims be given a printed brochure or card that briefly describes their rights and the available services, identifies the local\n\n249\nDOJ-OGR-00021451",
  "text_blocks": [
    {
      "type": "printed",
      "content": "Case 22-1426, Document 78, 06/29/2023, 3536039, Page21 of 217",
      "position": "header"
    },
    {
      "type": "printed",
      "content": "SA-275",
      "position": "header"
    },
    {
      "type": "printed",
      "content": "Case 1:20-cr-00330-AJN Document 204-3 Filed 04/16/21 Page 275 of 348",
      "position": "header"
    },
    {
      "type": "printed",
      "content": "(4) During court proceedings, a responsible official shall ensure that a victim is provided a waiting area removed from and out of the sight and hearing of the defendant and defense witnesses.\n...\n(e) Definitions\n...\n(2) the term \"victim\" means a person that has suffered direct physical, emotional, or pecuniary harm as a result of the commission of a crime...",
      "position": "body"
    },
    {
      "type": "printed",
      "content": "II. DEPARTMENT POLICY: THE 2005 ATTORNEY GENERAL GUIDELINES FOR VICTIM AND WITNESS ASSISTANCE (2005 GUIDELINES)",
      "position": "body"
    },
    {
      "type": "printed",
      "content": "In 2005, the Department revised its guidelines for victim and witness assistance in order to incorporate the provisions of the CVRA. The purpose of the 2005 Guidelines was \"to establish guidelines to be followed by officers and employees of Department of Justice investigative, prosecutorial, and correctional components in the treatment of victims of and witnesses to crime.\" The relevant portions of the 2005 Guidelines are as follows:",
      "position": "body"
    },
    {
      "type": "printed",
      "content": "Article IV: Services to Victims and Witnesses",
      "position": "body"
    },
    {
      "type": "printed",
      "content": "A. Investigation Stage",
      "position": "body"
    },
    {
      "type": "printed",
      "content": "The investigative agency's responsibilities begin with the report of the crime and extend through the prosecution of the case. In some instances, when explicitly stated, the investigative agency's responsibility for a certain task is transferred to the prosecuting agency when charges are filed.",
      "position": "body"
    },
    {
      "type": "printed",
      "content": "...\n2. Identification of Victims. At the earliest opportunity after the detection of a crime at which it may be done without interfering with an investigation, the responsible official of the investigative agency shall identify the victims of the crime.",
      "position": "body"
    },
    {
      "type": "printed",
      "content": "3. Description of Services.",
      "position": "body"
    },
    {
      "type": "printed",
      "content": "a. Information, Notice, and Referral",
      "position": "body"
    },
    {
      "type": "printed",
      "content": "(1) Initial Information and Notice. Responsible officials must advise a victim pursuant to this section at the earliest opportunity after detection of a crime at which it may be done without interfering with an investigation. To comply with this requirement, it is recommended that victims be given a printed brochure or card that briefly describes their rights and the available services, identifies the local",
      "position": "body"
    },
    {
      "type": "printed",
      "content": "249",
      "position": "footer"
    },
    {
      "type": "printed",
      "content": "DOJ-OGR-00021451",
      "position": "footer"
    }
  ],
  "entities": {
    "people": [],
    "organizations": [
      "Department of Justice"
    ],
    "locations": [],
    "dates": [
      "2005",
      "04/16/21",
      "06/29/2023"
    ],
    "reference_numbers": [
      "Case 22-1426",
      "Document 78",
      "Case 1:20-cr-00330-AJN",
      "Document 204-3",
      "DOJ-OGR-00021451"
    ]
  },
  "additional_notes": "The document appears to be a court document related to victim and witness assistance guidelines. The text is mostly printed, with no visible handwriting or stamps. The document is well-formatted and easy to read."
}