{
  "document_metadata": {
    "page_number": "217",
    "document_number": "58",
    "date": "02/28/2023",
    "document_type": "court document",
    "has_handwriting": false,
    "has_stamps": false
  },
  "full_text": "Case 22-1426, Document 58, 02/28/2023, 3475901, Page217 of 221\nA-417\n\nM6SQmax1\n42\n1 otherwise extensive.\" Quoting from United States v. Patasnik,\n2 89 F.3d 63 (2d Cir. 1996). The Guidelines define a participant\n3 as a person who is criminally responsible for the commission of\n4 the offense, but need not have been convicted. That's Section\n5 3B1.1, comment note 1. And in assessing whether criminal\n6 activity is extensive, all persons involved during the course\n7 of the entire offense are to be considered, including persons\n8 who provided services unknowingly. Comment note 3.\n9 The defendant argues that she did not lead another\n10 criminal participant. I overrule this objection because I do\n11 conclude that the government has proved by a preponderance that\n12 the defendant supervised Sarah Kellen, who was a knowing\n13 participant in the criminal conspiracy.\n14 Larry Visoski and David Rodgers both testified for\n15 that at least part of the time period at issue Sarah Kellen\n16 acted as a personal assistant to the defendant. I credit that\n17 testimony which is corroborated by further testimony that the\n18 defendant was Epstein's number two and the lady of the house.\n19 At some point, Kellen took over some of the defendants duties.\n20 But even after that time, the defendant retained her leadership\n21 position, as evidenced by Carolyn's testimony, by flight\n22 records in evidence, and the household manual in evidence. I\n23 do conclude by a preponderance of the evidence that the\n24 defendant led a criminally responsible participant.\n25 I further find that the defendant's criminal activity\n\nSOUTHERN DISTRICT REPORTERS, P.C.\n(212) 805-0300\n\nDOJ-OGR-00021043",
  "text_blocks": [
    {
      "type": "printed",
      "content": "Case 22-1426, Document 58, 02/28/2023, 3475901, Page217 of 221",
      "position": "header"
    },
    {
      "type": "printed",
      "content": "A-417",
      "position": "header"
    },
    {
      "type": "printed",
      "content": "M6SQmax1\n42\n1 otherwise extensive.\" Quoting from United States v. Patasnik,\n2 89 F.3d 63 (2d Cir. 1996). The Guidelines define a participant\n3 as a person who is criminally responsible for the commission of\n4 the offense, but need not have been convicted. That's Section\n5 3B1.1, comment note 1. And in assessing whether criminal\n6 activity is extensive, all persons involved during the course\n7 of the entire offense are to be considered, including persons\n8 who provided services unknowingly. Comment note 3.\n9 The defendant argues that she did not lead another\n10 criminal participant. I overrule this objection because I do\n11 conclude that the government has proved by a preponderance that\n12 the defendant supervised Sarah Kellen, who was a knowing\n13 participant in the criminal conspiracy.\n14 Larry Visoski and David Rodgers both testified for\n15 that at least part of the time period at issue Sarah Kellen\n16 acted as a personal assistant to the defendant. I credit that\n17 testimony which is corroborated by further testimony that the\n18 defendant was Epstein's number two and the lady of the house.\n19 At some point, Kellen took over some of the defendants duties.\n20 But even after that time, the defendant retained her leadership\n21 position, as evidenced by Carolyn's testimony, by flight\n22 records in evidence, and the household manual in evidence. I\n23 do conclude by a preponderance of the evidence that the\n24 defendant led a criminally responsible participant.\n25 I further find that the defendant's criminal activity",
      "position": "main content"
    },
    {
      "type": "printed",
      "content": "SOUTHERN DISTRICT REPORTERS, P.C.\n(212) 805-0300",
      "position": "footer"
    },
    {
      "type": "printed",
      "content": "DOJ-OGR-00021043",
      "position": "footer"
    }
  ],
  "entities": {
    "people": [
      "United States",
      "Patasnik",
      "Sarah Kellen",
      "Larry Visoski",
      "David Rodgers",
      "Epstein",
      "Carolyn",
      "defendant"
    ],
    "organizations": [
      "SOUTHERN DISTRICT REPORTERS, P.C."
    ],
    "locations": [],
    "dates": [
      "02/28/2023"
    ],
    "reference_numbers": [
      "Case 22-1426",
      "Document 58",
      "3475901",
      "Page217 of 221",
      "A-417",
      "DOJ-OGR-00021043"
    ]
  },
  "additional_notes": "The document appears to be a court transcript or legal document. The text is mostly printed, with no visible handwriting or stamps. The content discusses a legal case involving a defendant and various individuals, including Sarah Kellen, Larry Visoski, and David Rodgers."
}