{
  "document_metadata": {
    "page_number": "5",
    "document_number": "59",
    "date": "05/25/21",
    "document_type": "Court Document",
    "has_handwriting": true,
    "has_stamps": false
  },
  "full_text": "Case 1:19-cr-00830-AT Document 59 Filed 05/25/21 Page 5 of 5\n\nPursuant to 18 U.S.C. ยง3161(h)(2), exclusion under the Speedy Trial Act of the period of time during which the prosecution of the defendant is deferred pursuant to this Agreement is hereby approved.\n\nDated: New York, New York May 25, 2021\n\nHonorable Analisa Torres United States District Judge\n\nThe undersigned hereby consents to the foregoing and will accept supervision of the above-named defendant on the conditions set forth herein.\n\nDated: New York, New York May 24, 2021\n\nUnited States Pretrial Services Officer\n\n-5-\nDOJ-OGR-00022139",
  "text_blocks": [
    {
      "type": "printed",
      "content": "Case 1:19-cr-00830-AT Document 59 Filed 05/25/21 Page 5 of 5",
      "position": "header"
    },
    {
      "type": "printed",
      "content": "Pursuant to 18 U.S.C. ยง3161(h)(2), exclusion under the Speedy Trial Act of the period of time during which the prosecution of the defendant is deferred pursuant to this Agreement is hereby approved.",
      "position": "top"
    },
    {
      "type": "printed",
      "content": "Dated: New York, New York May 25, 2021",
      "position": "top"
    },
    {
      "type": "signature",
      "content": "",
      "position": "middle"
    },
    {
      "type": "printed",
      "content": "Honorable Analisa Torres United States District Judge",
      "position": "middle"
    },
    {
      "type": "printed",
      "content": "The undersigned hereby consents to the foregoing and will accept supervision of the above-named defendant on the conditions set forth herein.",
      "position": "middle"
    },
    {
      "type": "printed",
      "content": "Dated: New York, New York May 24, 2021",
      "position": "middle"
    },
    {
      "type": "signature",
      "content": "",
      "position": "middle"
    },
    {
      "type": "printed",
      "content": "United States Pretrial Services Officer",
      "position": "middle"
    },
    {
      "type": "printed",
      "content": "-5-",
      "position": "footer"
    },
    {
      "type": "printed",
      "content": "DOJ-OGR-00022139",
      "position": "footer"
    }
  ],
  "entities": {
    "people": [
      "Analisa Torres"
    ],
    "organizations": [
      "United States District Court",
      "United States Pretrial Services"
    ],
    "locations": [
      "New York",
      "New York"
    ],
    "dates": [
      "May 25, 2021",
      "May 24, 2021",
      "05/25/21"
    ],
    "reference_numbers": [
      "1:19-cr-00830-AT",
      "Document 59",
      "DOJ-OGR-00022139"
    ]
  },
  "additional_notes": "The document appears to be a court filing with signatures from a judge and a pretrial services officer. The content is related to a legal case and includes dates and reference numbers."
}