{
  "document_metadata": {
    "page_number": "81 of 217",
    "document_number": "22-1426, Document 78",
    "date": "06/29/2023",
    "document_type": "Non-Prosecution Agreement",
    "has_handwriting": true,
    "has_stamps": false
  },
  "full_text": "Case 22-1426, Document 78, 06/29/2023, 3536039, Page81 of 217 SA-335 Case 1:20-cr-00330-AJN Document 204-3 Filed 04/16/21 Page 335 of 348 By signing this agreement, Epstein asserts and certifies that the above has been read and explained to him. Epstein hereby states that he understands the conditions of this Non-Prosecution Agreement and agrees to comply with them. R. ALEXANDER ACOSTA UNITED STATES ATTORNEY Dated: By: Dated: 9/24/07 By: JEFFREY EPSTEIN Dated: By: GERALD LEFCOURT, ESQ. COUNSEL TO JEFFREY EPSTEIN Dated: By: LILLY ANN SANCHEZ, ESQ. ATTORNEY FOR JEFFREY EPSTEIN Page 7 of 7 DOJ-OGR-00021511",
  "text_blocks": [
    {
      "type": "printed",
      "content": "Case 22-1426, Document 78, 06/29/2023, 3536039, Page81 of 217 SA-335",
      "position": "header"
    },
    {
      "type": "printed",
      "content": "Case 1:20-cr-00330-AJN Document 204-3 Filed 04/16/21 Page 335 of 348",
      "position": "header"
    },
    {
      "type": "printed",
      "content": "By signing this agreement, Epstein asserts and certifies that the above has been read and explained to him. Epstein hereby states that he understands the conditions of this Non-Prosecution Agreement and agrees to comply with them.",
      "position": "middle"
    },
    {
      "type": "printed",
      "content": "R. ALEXANDER ACOSTA UNITED STATES ATTORNEY",
      "position": "middle"
    },
    {
      "type": "printed",
      "content": "Dated: By:",
      "position": "middle"
    },
    {
      "type": "handwritten",
      "content": "9/24/07",
      "position": "middle"
    },
    {
      "type": "signature",
      "content": "JEFFREY EPSTEIN",
      "position": "middle"
    },
    {
      "type": "printed",
      "content": "Dated: By: GERALD LEFCOURT, ESQ. COUNSEL TO JEFFREY EPSTEIN",
      "position": "middle"
    },
    {
      "type": "printed",
      "content": "Dated: By: LILLY ANN SANCHEZ, ESQ. ATTORNEY FOR JEFFREY EPSTEIN",
      "position": "middle"
    },
    {
      "type": "printed",
      "content": "Page 7 of 7",
      "position": "footer"
    },
    {
      "type": "printed",
      "content": "DOJ-OGR-00021511",
      "position": "footer"
    }
  ],
  "entities": {
    "people": [
      "Jeffrey Epstein",
      "R. Alexander Acosta",
      "A. Marie Villafa√±a",
      "Gerald Lefcourt",
      "Lilly Ann Sanchez"
    ],
    "organizations": [
      "United States Attorney"
    ],
    "locations": [],
    "dates": [
      "06/29/2023",
      "04/16/21",
      "9/24/07"
    ],
    "reference_numbers": [
      "22-1426",
      "1:20-cr-00330-AJN",
      "Document 78",
      "Document 204-3",
      "3536039",
      "DOJ-OGR-00021511"
    ]
  },
  "additional_notes": "The document appears to be a Non-Prosecution Agreement signed by Jeffrey Epstein. The document is mostly printed, with some handwritten dates and signatures. There are no visible stamps or redactions."
}