{
  "document_metadata": {
    "page_number": "14",
    "document_number": "1:19-cr-00830-AT Document 1",
    "date": "11/19/19",
    "document_type": "Court Document",
    "has_handwriting": false,
    "has_stamps": false
  },
  "full_text": "Case 1:19-cr-00830-AT Document 1 Filed 11/19/19 Page 14 of 20\ndpartment or agency of the United States, in violation of Title 18, United States Code, Section 1001 (a) (3).\n30. In furtherance of the conspiracy and to effect the illegal objects thereof, TOVA NOEL and MICHAEL THOMAS, the defendants, committed the following overt acts, among others, in the Southern District of New York:\na. On August 10, 2019, NOEL and THOMAS falsely certified, on an MCC count slip, that they had performed the 12 a.m. institutional count of the SHU, when they had not in fact done so.\nb. On August 10, 2019, NOEL and THOMAS falsely certified, on an MCC count slip, that they had performed the 3 a.m. institutional count of the SHU, when they had not in fact done so.\nc. On August 10, 2019, NOEL and THOMAS falsely certified, on an MCC count slip, that they had performed the 5 a.m. institutional count of the SHU at MCC, when they had not in fact done so.\nd. On August 10, 2019, NOEL falsely certified that she and THOMAS had performed a series of 30-minute rounds of the SHU between 12 a.m. and 6:30 a.m., when they had not in fact done so.\n(Title 18, United States Code, Section 371)\n14\nDOJ-OGR-00021921",
  "text_blocks": [
    {
      "type": "printed",
      "content": "Case 1:19-cr-00830-AT Document 1 Filed 11/19/19 Page 14 of 20",
      "position": "header"
    },
    {
      "type": "printed",
      "content": "department or agency of the United States, in violation of Title 18, United States Code, Section 1001 (a) (3).",
      "position": "top"
    },
    {
      "type": "printed",
      "content": "30. In furtherance of the conspiracy and to effect the illegal objects thereof, TOVA NOEL and MICHAEL THOMAS, the defendants, committed the following overt acts, among others, in the Southern District of New York:",
      "position": "top"
    },
    {
      "type": "printed",
      "content": "a. On August 10, 2019, NOEL and THOMAS falsely certified, on an MCC count slip, that they had performed the 12 a.m. institutional count of the SHU, when they had not in fact done so.",
      "position": "middle"
    },
    {
      "type": "printed",
      "content": "b. On August 10, 2019, NOEL and THOMAS falsely certified, on an MCC count slip, that they had performed the 3 a.m. institutional count of the SHU, when they had not in fact done so.",
      "position": "middle"
    },
    {
      "type": "printed",
      "content": "c. On August 10, 2019, NOEL and THOMAS falsely certified, on an MCC count slip, that they had performed the 5 a.m. institutional count of the SHU at MCC, when they had not in fact done so.",
      "position": "middle"
    },
    {
      "type": "printed",
      "content": "d. On August 10, 2019, NOEL falsely certified that she and THOMAS had performed a series of 30-minute rounds of the SHU between 12 a.m. and 6:30 a.m., when they had not in fact done so.",
      "position": "middle"
    },
    {
      "type": "printed",
      "content": "(Title 18, United States Code, Section 371)",
      "position": "bottom"
    },
    {
      "type": "printed",
      "content": "14",
      "position": "footer"
    },
    {
      "type": "printed",
      "content": "DOJ-OGR-00021921",
      "position": "footer"
    }
  ],
  "entities": {
    "people": [
      "TOVA NOEL",
      "MICHAEL THOMAS"
    ],
    "organizations": [
      "United States Department of Justice"
    ],
    "locations": [
      "Southern District of New York",
      "MCC",
      "SHU"
    ],
    "dates": [
      "August 10, 2019",
      "11/19/19"
    ],
    "reference_numbers": [
      "1:19-cr-00830-AT Document 1",
      "DOJ-OGR-00021921"
    ]
  },
  "additional_notes": "The document appears to be a court filing related to a criminal case involving TOVA NOEL and MICHAEL THOMAS. The text is typed, and there are no visible stamps or handwritten notes. The document is page 14 of 20."
}