{
  "document_metadata": {
    "page_number": "6",
    "document_number": "79",
    "date": "06/29/2023",
    "document_type": "Court Document",
    "has_handwriting": false,
    "has_stamps": false
  },
  "full_text": "Case 22-1426, Document 79, 06/29/2023, 3536060, Page6 of 93\n\nv\nPAGE\nCruz v. Maypa,\n773 F.3d 138 (4th Cir. 2014) ............... 39, 40\nFalter v. United States,\n23 F.2d 420 (2d Cir. 1928) .................. 40\nIn re Enter. Mort. Acceptance Co. Sec. Litig.,\n391 F.3d 401 (2d Cir. 2004) ............... 34, 38, 39\nKawashima v. Holder,\n565 U.S. 478 (2012).......................... 48\nKirtsaeng v. John Wiley & Sons, Inc.,\n568 U.S. 519 (2013).......................... 20\nLandgraf v. USI Film Products,\n511 U.S. 244 (1994)....................... 31, 33, 40, 41\nLeocal v. Ashcroft,\n543 U.S. 1 (2004).......................... 47, 48\nMcDonough Power Equip., Inc. v. Greenwood,\n464 U.S. 548 (1984).......................... 56, 57\nNijhawan v. Holder,\n557 U.S. 29 (2009).......................... 47\nSan Pedro v. United States,\n79 F.3d 1065 (11th Cir. 1996) .................. 25\nStogner v. California,\n539 U.S. 607 (2003).......................... 36, 39\nTanner v. United States,\n483 U.S. 107 (1987).......................... 56\nThompson v. United States,\n431 F. App'x 491 (7th Cir. 2011) ............... 26\nDOJ-OGR-00021653",
  "text_blocks": [
    {
      "type": "printed",
      "content": "Case 22-1426, Document 79, 06/29/2023, 3536060, Page6 of 93",
      "position": "header"
    },
    {
      "type": "printed",
      "content": "v\nPAGE",
      "position": "top"
    },
    {
      "type": "printed",
      "content": "Cruz v. Maypa,\n773 F.3d 138 (4th Cir. 2014) ............... 39, 40\nFalter v. United States,\n23 F.2d 420 (2d Cir. 1928) .................. 40\nIn re Enter. Mort. Acceptance Co. Sec. Litig.,\n391 F.3d 401 (2d Cir. 2004) ............... 34, 38, 39\nKawashima v. Holder,\n565 U.S. 478 (2012).......................... 48\nKirtsaeng v. John Wiley & Sons, Inc.,\n568 U.S. 519 (2013).......................... 20\nLandgraf v. USI Film Products,\n511 U.S. 244 (1994)....................... 31, 33, 40, 41\nLeocal v. Ashcroft,\n543 U.S. 1 (2004).......................... 47, 48\nMcDonough Power Equip., Inc. v. Greenwood,\n464 U.S. 548 (1984).......................... 56, 57\nNijhawan v. Holder,\n557 U.S. 29 (2009).......................... 47\nSan Pedro v. United States,\n79 F.3d 1065 (11th Cir. 1996) .................. 25\nStogner v. California,\n539 U.S. 607 (2003).......................... 36, 39\nTanner v. United States,\n483 U.S. 107 (1987).......................... 56\nThompson v. United States,\n431 F. App'x 491 (7th Cir. 2011) ............... 26",
      "position": "middle"
    },
    {
      "type": "printed",
      "content": "DOJ-OGR-00021653",
      "position": "footer"
    }
  ],
  "entities": {
    "people": [
      "Cruz",
      "Maypa",
      "Falter",
      "Kawashima",
      "Holder",
      "Kirtsaeng",
      "John Wiley",
      "Landgraf",
      "Leocal",
      "Ashcroft",
      "McDonough",
      "Greenwood",
      "Nijhawan",
      "San Pedro",
      "Stogner",
      "Tanner",
      "Thompson"
    ],
    "organizations": [
      "USI Film Products",
      "John Wiley & Sons, Inc.",
      "McDonough Power Equip., Inc."
    ],
    "locations": [
      "United States",
      "California"
    ],
    "dates": [
      "2014",
      "1928",
      "2004",
      "2012",
      "2013",
      "1994",
      "1984",
      "2009",
      "1996",
      "2003",
      "1987",
      "2011",
      "06/29/2023"
    ],
    "reference_numbers": [
      "22-1426",
      "79",
      "3536060",
      "DOJ-OGR-00021653"
    ]
  },
  "additional_notes": "The document appears to be a court document, likely a brief or memorandum, containing a list of case citations with corresponding page numbers."
}