{
  "document_metadata": {
    "page_number": "22",
    "document_number": "87",
    "date": "07/27/2023",
    "document_type": "court document",
    "has_handwriting": false,
    "has_stamps": false
  },
  "full_text": "Case 22-1426, Document 87, 07/27/2023, 3548202, Page22 of 35\n\np28. Juror 50's pretrial selective false answers only to questions that would have elicited his child sexual abuse, his post-verdict activity, and his patently false and contradictory explanations in the post-verdict hearing should have disqualified him for service as a juror in this case.\n\nB. Had Juror 50 Disclosed in Voir Dire his Traumatic Experience as a Victim of Child Sex Abuse, the Information Would Have Established a Valid Basis for a Cause Challenge\n\nAt the hearing, Juror 50 disclosed the facts of his sexual abuse, which significantly paralleled the abuse described by the Government's four key victim witnesses at trial. Like the four accusers, Juror 50 (i) was sexually abused as a minor; (ii) was abused on multiple occasions over the course of several years; and (iii) delayed reporting the abuse. A267-268. Like the four accusers, Juror 50 was abused by two people who were friends and who each had participated in the abuse. A267. Furthermore, Juror 50 was not abused by a stranger or sexually assaulted by someone he did not know. Like the four accusers, he was sexually abused by someone familiar to him, namely his stepbrother. These similarities are significant and contrast sharply with other jurors who answered \"Yes\" to Question 48 and were not struck for cause, but who disclosed incidents that were not directly analogous to the facts presented at trial. In this situation, where Juror 50 experienced the same traumatic childhood sexual abuse that the trial victims had experienced, with many of the same surrounding circumstances, he was not capable of setting his experiences aside and\n\n16\n\nDOJ-OGR-00021764",
  "text_blocks": [
    {
      "type": "printed",
      "content": "Case 22-1426, Document 87, 07/27/2023, 3548202, Page22 of 35",
      "position": "header"
    },
    {
      "type": "printed",
      "content": "p28. Juror 50's pretrial selective false answers only to questions that would have elicited his child sexual abuse, his post-verdict activity, and his patently false and contradictory explanations in the post-verdict hearing should have disqualified him for service as a juror in this case.",
      "position": "top"
    },
    {
      "type": "printed",
      "content": "B. Had Juror 50 Disclosed in Voir Dire his Traumatic Experience as a Victim of Child Sex Abuse, the Information Would Have Established a Valid Basis for a Cause Challenge",
      "position": "middle"
    },
    {
      "type": "printed",
      "content": "At the hearing, Juror 50 disclosed the facts of his sexual abuse, which significantly paralleled the abuse described by the Government's four key victim witnesses at trial. Like the four accusers, Juror 50 (i) was sexually abused as a minor; (ii) was abused on multiple occasions over the course of several years; and (iii) delayed reporting the abuse. A267-268. Like the four accusers, Juror 50 was abused by two people who were friends and who each had participated in the abuse. A267. Furthermore, Juror 50 was not abused by a stranger or sexually assaulted by someone he did not know. Like the four accusers, he was sexually abused by someone familiar to him, namely his stepbrother. These similarities are significant and contrast sharply with other jurors who answered \"Yes\" to Question 48 and were not struck for cause, but who disclosed incidents that were not directly analogous to the facts presented at trial. In this situation, where Juror 50 experienced the same traumatic childhood sexual abuse that the trial victims had experienced, with many of the same surrounding circumstances, he was not capable of setting his experiences aside and",
      "position": "middle"
    },
    {
      "type": "printed",
      "content": "16",
      "position": "footer"
    },
    {
      "type": "printed",
      "content": "DOJ-OGR-00021764",
      "position": "footer"
    }
  ],
  "entities": {
    "people": [
      "Juror 50"
    ],
    "organizations": [
      "Government"
    ],
    "locations": [],
    "dates": [
      "07/27/2023"
    ],
    "reference_numbers": [
      "Case 22-1426",
      "Document 87",
      "3548202",
      "A267-268",
      "A267",
      "DOJ-OGR-00021764"
    ]
  },
  "additional_notes": "The document appears to be a court filing discussing a juror's potential bias due to their experience as a victim of child sex abuse. The text is printed and there are no visible stamps or handwritten notes."
}