{
  "document_metadata": {
    "page_number": "220",
    "document_number": "58",
    "date": "02/28/2023",
    "document_type": "Criminal Notice of Appeal - Form A",
    "has_handwriting": true,
    "has_stamps": true
  },
  "full_text": "Case 22-1426, Document 58 02/28/2023, 3475901, Page220 of 221 A-420 Case 1:20-cr-00330-AJN Document 697 Filed 07/07/2022 USDOSDNY DOCUMENT ELECTRONICALLY FILED DOC#: DATE FILED: 7/7/2022 Criminal Notice of Appeal - Form A NOTICE OF APPEAL United States District Court Southern District of New York Caption: United States of America v. Ghislaine Maxwell Docket No. S2 20 Cr. 330 Alison J. Nathan (SBD) (District Court Judge) Notice is hereby given that Ghislaine Maxwell appeals to the United States Court of Appeals for the Second Circuit from the judgment , other entered in this action on 6/29/2022 (date) This appeal concerns: Conviction only Sentence only Conviction & Sentence Other Defendant found guilty by plea trial N/A Offense occurred after November 1, 1987? Yes No N/A Date of sentence: 6/28/2022 N/A Bail/Jail Disposition: Committed Not committed N/A Appellant is represented by counsel? Yes No If yes, provide the following information: Defendant's Counsel: Bobbi C. Sternheim, Law Offices of Bobbi C. Sternheim Counsel's Address: 225 Broadway, Suite 715 New York, NY 10007 Counsel's Phone: 212-243-1100 Assistant U.S. Attorney: Maurene Comey AUSA's Address: One Saint Andrew's Plaza New York, NY 10007 AUSA's Phone: 212-637-2324 Signature * FOR FILING OF NOTICE OF APPEAL ONLY ** NOT RETAINED FOR REPRESENTATION ON APPEAL DOJ-OGR-00021046",
  "text_blocks": [
    {
      "type": "printed",
      "content": "Case 22-1426, Document 58 02/28/2023, 3475901, Page220 of 221",
      "position": "header"
    },
    {
      "type": "printed",
      "content": "Criminal Notice of Appeal - Form A",
      "position": "top"
    },
    {
      "type": "printed",
      "content": "NOTICE OF APPEAL",
      "position": "top"
    },
    {
      "type": "printed",
      "content": "United States District Court Southern District of New York",
      "position": "top"
    },
    {
      "type": "handwritten",
      "content": "7/7/2022",
      "position": "margin"
    },
    {
      "type": "printed",
      "content": "Caption: United States of America v. Ghislaine Maxwell",
      "position": "middle"
    },
    {
      "type": "printed",
      "content": "Docket No. S2 20 Cr. 330",
      "position": "middle"
    },
    {
      "type": "printed",
      "content": "Alison J. Nathan (SBD) (District Court Judge)",
      "position": "middle"
    },
    {
      "type": "printed",
      "content": "Notice is hereby given that Ghislaine Maxwell appeals to the United States Court of Appeals for the Second Circuit from the judgment , other entered in this action on 6/29/2022 (date)",
      "position": "middle"
    },
    {
      "type": "handwritten",
      "content": "6/29/2022",
      "position": "middle"
    },
    {
      "type": "printed",
      "content": "This appeal concerns: Conviction only Sentence only Conviction & Sentence Other",
      "position": "middle"
    },
    {
      "type": "handwritten",
      "content": "",
      "position": "middle"
    },
    {
      "type": "printed",
      "content": "Defendant found guilty by plea trial N/A",
      "position": "middle"
    },
    {
      "type": "handwritten",
      "content": "",
      "position": "middle"
    },
    {
      "type": "printed",
      "content": "Offense occurred after November 1, 1987? Yes No N/A",
      "position": "middle"
    },
    {
      "type": "handwritten",
      "content": "",
      "position": "middle"
    },
    {
      "type": "printed",
      "content": "Date of sentence: 6/28/2022 N/A",
      "position": "middle"
    },
    {
      "type": "handwritten",
      "content": "6/28/2022",
      "position": "middle"
    },
    {
      "type": "printed",
      "content": "Bail/Jail Disposition: Committed Not committed N/A",
      "position": "middle"
    },
    {
      "type": "handwritten",
      "content": "",
      "position": "middle"
    },
    {
      "type": "printed",
      "content": "Appellant is represented by counsel? Yes No If yes, provide the following information:",
      "position": "middle"
    },
    {
      "type": "handwritten",
      "content": "",
      "position": "middle"
    },
    {
      "type": "printed",
      "content": "Defendant's Counsel: Bobbi C. Sternheim, Law Offices of Bobbi C. Sternheim",
      "position": "middle"
    },
    {
      "type": "printed",
      "content": "Counsel's Address: 225 Broadway, Suite 715 New York, NY 10007",
      "position": "middle"
    },
    {
      "type": "printed",
      "content": "Counsel's Phone: 212-243-1100",
      "position": "middle"
    },
    {
      "type": "printed",
      "content": "Assistant U.S. Attorney: Maurene Comey",
      "position": "middle"
    },
    {
      "type": "printed",
      "content": "AUSA's Address: One Saint Andrew's Plaza New York, NY 10007",
      "position": "middle"
    },
    {
      "type": "printed",
      "content": "AUSA's Phone: 212-637-2324",
      "position": "middle"
    },
    {
      "type": "handwritten",
      "content": "Bobbi C. Sternheim",
      "position": "bottom"
    },
    {
      "type": "printed",
      "content": "* FOR FILING OF NOTICE OF APPEAL ONLY ** NOT RETAINED FOR REPRESENTATION ON APPEAL",
      "position": "bottom"
    },
    {
      "type": "stamp",
      "content": "DOJ-OGR-00021046",
      "position": "footer"
    }
  ],
  "entities": {
    "people": [
      "Ghislaine Maxwell",
      "Alison J. Nathan",
      "Bobbi C. Sternheim",
      "Maurene Comey"
    ],
    "organizations": [
      "United States District Court",
      "United States Court of Appeals for the Second Circuit",
      "Law Offices of Bobbi C. Sternheim"
    ],
    "locations": [
      "New York"
    ],
    "dates": [
      "6/29/2022",
      "6/28/2022",
      "7/7/2022",
      "02/28/2023",
      "November 1, 1987"
    ],
    "reference_numbers": [
      "S2 20 Cr. 330",
      "Case 22-1426",
      "Document 58",
      "Document 697",
      "DOJ-OGR-00021046"
    ]
  },
  "additional_notes": "The document is a Criminal Notice of Appeal - Form A, filed on 7/7/2022, in the United States District Court for the Southern District of New York. The appeal is filed by Ghislaine Maxwell, represented by Bobbi C. Sternheim, against the judgment entered on 6/29/2022. The document contains handwritten annotations and stamps."
}