{
  "document_metadata": {
    "page_number": "1",
    "document_number": "43",
    "date": "09/14/20",
    "document_type": "Letter",
    "has_handwriting": false,
    "has_stamps": true
  },
  "full_text": "Case 1:19-cr-00830-AT Document 43 Filed 09/14/20 Page 1 of 1\nThe Law Offices of MONTELL F Figgins\n17 Academy Street, Suite 305\nNewark, New Jersey 07102\nPhone: (973) 242-4700\nFax: (973) 242-4701\nwww.figginslaw.com BRANCH OFFICES:\n140 East Ridgewood Avenue\nParamus, NJ 07640\n30 Wall Street 8th Floor\nNew York, NY 1005\nReply to Newark Office [X]\nOf Counsel\nDouglas Mitchell, Esq.\nLinda Childs, Esq.\nSeptember 14, 2020\nSENT VIA ECF\nHonorable Analisa Torres\nU.S. Southern District of NY\n500 Pearl Street\nNew York, NY 10007\nRe: USA v Michael Thomas, et al.\nDocket No.: 1:19-cr-00830\nRequest for Emergency Out of State Travel\nYour Honor,\nThis firm represents Defendant, Michael Thomas, in the above-captioned matter. We are seeking the courts permission for Michael Thomas to take an emergency trip to the State of Georgia to tend to his sick father.\nKristen McKeown, his pre-trial services officer, does not oppose his emergency travel.\nRespectfully yours,\n/s/ Montell Figgins\nMontell Figgins, Esq.\nAttorney for Defendant Michael Thomas\ncc: Nicolas Roos, Esq., Counsel for Plaintiff\nRebekah Donaleski, Esq., Counsel for Plaintiff\nJessica Lonergan, Esq., Counsel for Plaintiff\nJason Erroy Foy, Esq. Counsel for Defendant Noel\nGRANTED.\nSO ORDERED.\nDated: September 14, 2020\nNew York, New York\nANALISA TORRES\nUnited States District Judge",
  "text_blocks": [
    {
      "type": "printed",
      "content": "The Law Offices of MONTELL F Figgins",
      "position": "header"
    },
    {
      "type": "printed",
      "content": "17 Academy Street, Suite 305\nNewark, New Jersey 07102\nPhone: (973) 242-4700\nFax: (973) 242-4701\nwww.figginslaw.com BRANCH OFFICES:",
      "position": "header"
    },
    {
      "type": "printed",
      "content": "140 East Ridgewood Avenue\nParamus, NJ 07640\n30 Wall Street 8th Floor\nNew York, NY 1005",
      "position": "header"
    },
    {
      "type": "printed",
      "content": "Reply to Newark Office [X]\nOf Counsel\nDouglas Mitchell, Esq.\nLinda Childs, Esq.",
      "position": "header"
    },
    {
      "type": "printed",
      "content": "September 14, 2020",
      "position": "header"
    },
    {
      "type": "printed",
      "content": "SENT VIA ECF\nHonorable Analisa Torres\nU.S. Southern District of NY\n500 Pearl Street\nNew York, NY 10007",
      "position": "body"
    },
    {
      "type": "printed",
      "content": "Re: USA v Michael Thomas, et al.\nDocket No.: 1:19-cr-00830\nRequest for Emergency Out of State Travel",
      "position": "body"
    },
    {
      "type": "printed",
      "content": "Your Honor,\nThis firm represents Defendant, Michael Thomas, in the above-captioned matter. We are seeking the courts permission for Michael Thomas to take an emergency trip to the State of Georgia to tend to his sick father.\nKristen McKeown, his pre-trial services officer, does not oppose his emergency travel.",
      "position": "body"
    },
    {
      "type": "printed",
      "content": "Respectfully yours,\n/s/ Montell Figgins\nMontell Figgins, Esq.\nAttorney for Defendant Michael Thomas",
      "position": "body"
    },
    {
      "type": "printed",
      "content": "cc: Nicolas Roos, Esq., Counsel for Plaintiff\nRebekah Donaleski, Esq., Counsel for Plaintiff\nJessica Lonergan, Esq., Counsel for Plaintiff\nJason Erroy Foy, Esq. Counsel for Defendant Noel",
      "position": "footer"
    },
    {
      "type": "handwritten",
      "content": "GRANTED.",
      "position": "footer"
    },
    {
      "type": "printed",
      "content": "SO ORDERED.",
      "position": "footer"
    },
    {
      "type": "printed",
      "content": "Dated: September 14, 2020\nNew York, New York",
      "position": "footer"
    },
    {
      "type": "signature",
      "content": "ANALISA TORRES\nUnited States District Judge",
      "position": "footer"
    }
  ],
  "entities": {
    "people": [
      "Montell Figgins",
      "Analisa Torres",
      "Michael Thomas",
      "Douglas Mitchell",
      "Linda Childs",
      "Kristen McKeown",
      "Nicolas Roos",
      "Rebekah Donaleski",
      "Jessica Lonergan",
      "Jason Erroy Foy",
      "Noel"
    ],
    "organizations": [
      "The Law Offices of Montell F Figgins",
      "U.S. Southern District of NY"
    ],
    "locations": [
      "Newark",
      "New Jersey",
      "Paramus",
      "NJ",
      "New York",
      "NY",
      "Georgia",
      "United States"
    ],
    "dates": [
      "September 14, 2020",
      "09/14/20"
    ],
    "reference_numbers": [
      "1:19-cr-00830"
    ]
  },
  "additional_notes": "The document is a letter from Montell Figgins to Honorable Analisa Torres requesting emergency out of state travel for Michael Thomas. The letter is dated September 14, 2020, and is stamped as filed on the same date. The document contains a signature from Analisa Torres, indicating that the request was granted."
}