{
  "document_metadata": {
    "page_number": "21",
    "document_number": "1-2",
    "date": "07/08/2022",
    "document_type": "Court Document",
    "has_handwriting": false,
    "has_stamps": false
  },
  "full_text": "Case 22-1426, Document 1-2, 07/08/2022, 3344417, Page21 of 91\nthis Order. (Signed by Judge Alison J. Nathan on 1/25/2021) (ap) (Entered: 01/25/2021)\n01/25/2021 118 LETTER by Ghislaine Maxwell addressed to Judge Alison J. Nathan from Mark S. Cohen dated January 25, 2021 re: Pretrial Motions (Cohen, Mark) (Entered: 01/25/2021)\n01/25/2021 119 MOTION for Separate Trial on Counts Ghislaine Maxwell (1) Count 5s–6s,5–6 . Document filed by Ghislaine Maxwell. (Pagliuca, Jeffrey) (Entered: 01/25/2021)\n01/25/2021 120 MEMORANDUM in Support by Ghislaine Maxwell re 119 MOTION for Separate Trial on Counts Ghislaine Maxwell (1) Count 5s–6s,5–6 .. (Pagliuca, Jeffrey) (Entered: 01/25/2021)\n01/25/2021 121 MOTION to Dismiss Either Count One Or Count Three of the Superseding Indictment as Multiplicitous. Document filed by Ghislaine Maxwell. (Pagliuca, Jeffrey) (Entered: 01/25/2021)\n01/25/2021 122 MEMORANDUM in Support by Ghislaine Maxwell re 121 MOTION to Dismiss Either Count One Or Count Three of the Superseding Indictment as Multiplicitous.. (Pagliuca, Jeffrey) (Entered: 01/25/2021)\n01/25/2021 123 MOTION to Dismiss Counts One through Four of the Superseding Indictment for Lack of Specificity. Document filed by Ghislaine Maxwell. (Pagliuca, Jeffrey) (Entered: 01/25/2021)\n01/25/2021 124 MEMORANDUM in Support by Ghislaine Maxwell re 123 MOTION to Dismiss Counts One through Four of the Superseding Indictment for Lack of Specificity.. (Pagliuca, Jeffrey) (Entered: 01/25/2021)\n01/25/2021 125 MOTION to Dismiss the Superseding Indictment as it was Obtained in Violation of the Sixth Amendment. Document filed by Ghislaine Maxwell. (Cohen, Mark) (Entered: 01/25/2021)\n01/25/2021 126 MEMORANDUM in Support by Ghislaine Maxwell re 125 MOTION to Dismiss the Superseding Indictment as it was Obtained in Violation of the Sixth Amendment.. (Cohen, Mark) (Entered: 01/25/2021)\n01/26/2021 127 ORDER as to Ghislaine Maxwell: On January 25, 2021, the Defendant filed twelve pre-trial motions. Because there is a request to redact sensitive or confidential information, several of the motions have been filed under temporary seal. The Government may respond to the Defendant's proposed redactions within two days of this Order. (Signed by Judge Alison J. Nathan on 1/26/2021) (ap) (Entered: 01/26/2021)\n01/28/2021 128 LETTER by USA as to Ghislaine Maxwell addressed to Judge Alison J. Nathan from AUSAs Maurene Comey, Alison Moe, Lara Pomerantz, and Andrew Rohrbach dated January 28, 2021 re: Defendant's Proposed Redactions to Pre-Trial Motions Document filed by USA. (Pomerantz, Lara) (Entered: 01/28/2021)\n02/01/2021 129 LETTER by USA as to Ghislaine Maxwell addressed to Judge Alison J. Nathan from AUSAs Maurene Comey, Alison Moe, and Lara Pomerantz dated February 1, 2021 re: MDC Laptop Access Document filed by USA. (Comey, Maurene) (Entered: 02/01/2021)\n02/01/2021 130 LETTER by Ghislaine Maxwell addressed to Judge Alison J. Nathan from Bobbi C. Sternheim dated 02/02/2021 re: Opposition to MDC letter (Sternheim, Bobbi) (Entered: 02/01/2021)\n02/02/2021 131 MEMO ENDORSEMENT as to Ghislaine Maxwell on Letter addressed to Judge Alison J. Nathan from Sophia Papapetru ( Staff Attorney, MDC Brooklyn, Federal Bureau of Prisons) dated January 25, 2021. ENDORSEMENT: Having considered the request submitted by the Bureau of Prisons (\"BOP\") that the Court vacate its January 15, 2021 Order, Dkt. No. 117, as well as the Government's and the Defendant's response, the Court hereby DENIES the BOP's request to vacate the Order. SO ORDERED. (Signed by Judge Alison J. Nathan on 2/2/2021)(bw) (Entered: 02/02/2021)\nDOJ-OGR-00020407",
  "text_blocks": [
    {
      "type": "printed",
      "content": "Case 22-1426, Document 1-2, 07/08/2022, 3344417, Page21 of 91",
      "position": "header"
    },
    {
      "type": "printed",
      "content": "this Order. (Signed by Judge Alison J. Nathan on 1/25/2021) (ap) (Entered: 01/25/2021)",
      "position": "header"
    },
    {
      "type": "printed",
      "content": "01/25/2021 118 LETTER by Ghislaine Maxwell addressed to Judge Alison J. Nathan from Mark S. Cohen dated January 25, 2021 re: Pretrial Motions (Cohen, Mark) (Entered: 01/25/2021)",
      "position": "body"
    },
    {
      "type": "printed",
      "content": "01/25/2021 119 MOTION for Separate Trial on Counts Ghislaine Maxwell (1) Count 5s–6s,5–6 . Document filed by Ghislaine Maxwell. (Pagliuca, Jeffrey) (Entered: 01/25/2021)",
      "position": "body"
    },
    {
      "type": "printed",
      "content": "01/25/2021 120 MEMORANDUM in Support by Ghislaine Maxwell re 119 MOTION for Separate Trial on Counts Ghislaine Maxwell (1) Count 5s–6s,5–6 .. (Pagliuca, Jeffrey) (Entered: 01/25/2021)",
      "position": "body"
    },
    {
      "type": "printed",
      "content": "01/25/2021 121 MOTION to Dismiss Either Count One Or Count Three of the Superseding Indictment as Multiplicitous. Document filed by Ghislaine Maxwell. (Pagliuca, Jeffrey) (Entered: 01/25/2021)",
      "position": "body"
    },
    {
      "type": "printed",
      "content": "01/25/2021 122 MEMORANDUM in Support by Ghislaine Maxwell re 121 MOTION to Dismiss Either Count One Or Count Three of the Superseding Indictment as Multiplicitous.. (Pagliuca, Jeffrey) (Entered: 01/25/2021)",
      "position": "body"
    },
    {
      "type": "printed",
      "content": "01/25/2021 123 MOTION to Dismiss Counts One through Four of the Superseding Indictment for Lack of Specificity. Document filed by Ghislaine Maxwell. (Pagliuca, Jeffrey) (Entered: 01/25/2021)",
      "position": "body"
    },
    {
      "type": "printed",
      "content": "01/25/2021 124 MEMORANDUM in Support by Ghislaine Maxwell re 123 MOTION to Dismiss Counts One through Four of the Superseding Indictment for Lack of Specificity.. (Pagliuca, Jeffrey) (Entered: 01/25/2021)",
      "position": "body"
    },
    {
      "type": "printed",
      "content": "01/25/2021 125 MOTION to Dismiss the Superseding Indictment as it was Obtained in Violation of the Sixth Amendment. Document filed by Ghislaine Maxwell. (Cohen, Mark) (Entered: 01/25/2021)",
      "position": "body"
    },
    {
      "type": "printed",
      "content": "01/25/2021 126 MEMORANDUM in Support by Ghislaine Maxwell re 125 MOTION to Dismiss the Superseding Indictment as it was Obtained in Violation of the Sixth Amendment.. (Cohen, Mark) (Entered: 01/25/2021)",
      "position": "body"
    },
    {
      "type": "printed",
      "content": "01/26/2021 127 ORDER as to Ghislaine Maxwell: On January 25, 2021, the Defendant filed twelve pre-trial motions. Because there is a request to redact sensitive or confidential information, several of the motions have been filed under temporary seal. The Government may respond to the Defendant's proposed redactions within two days of this Order. (Signed by Judge Alison J. Nathan on 1/26/2021) (ap) (Entered: 01/26/2021)",
      "position": "body"
    },
    {
      "type": "printed",
      "content": "01/28/2021 128 LETTER by USA as to Ghislaine Maxwell addressed to Judge Alison J. Nathan from AUSAs Maurene Comey, Alison Moe, Lara Pomerantz, and Andrew Rohrbach dated January 28, 2021 re: Defendant's Proposed Redactions to Pre-Trial Motions Document filed by USA. (Pomerantz, Lara) (Entered: 01/28/2021)",
      "position": "body"
    },
    {
      "type": "printed",
      "content": "02/01/2021 129 LETTER by USA as to Ghislaine Maxwell addressed to Judge Alison J. Nathan from AUSAs Maurene Comey, Alison Moe, and Lara Pomerantz dated February 1, 2021 re: MDC Laptop Access Document filed by USA. (Comey, Maurene) (Entered: 02/01/2021)",
      "position": "body"
    },
    {
      "type": "printed",
      "content": "02/01/2021 130 LETTER by Ghislaine Maxwell addressed to Judge Alison J. Nathan from Bobbi C. Sternheim dated 02/02/2021 re: Opposition to MDC letter (Sternheim, Bobbi) (Entered: 02/01/2021)",
      "position": "body"
    },
    {
      "type": "printed",
      "content": "02/02/2021 131 MEMO ENDORSEMENT as to Ghislaine Maxwell on Letter addressed to Judge Alison J. Nathan from Sophia Papapetru ( Staff Attorney, MDC Brooklyn, Federal Bureau of Prisons) dated January 25, 2021. ENDORSEMENT: Having considered the request submitted by the Bureau of Prisons (\"BOP\") that the Court vacate its January 15, 2021 Order, Dkt. No. 117, as well as the Government's and the Defendant's response, the Court hereby DENIES the BOP's request to vacate the Order. SO ORDERED. (Signed by Judge Alison J. Nathan on 2/2/2021)(bw) (Entered: 02/02/2021)",
      "position": "body"
    },
    {
      "type": "printed",
      "content": "DOJ-OGR-00020407",
      "position": "footer"
    }
  ],
  "entities": {
    "people": [
      "Ghislaine Maxwell",
      "Alison J. Nathan",
      "Mark S. Cohen",
      "Jeffrey Pagliuca",
      "Maurene Comey",
      "Alison Moe",
      "Lara Pomerantz",
      "Andrew Rohrbach",
      "Bobbi C. Sternheim",
      "Sophia Papapetru"
    ],
    "organizations": [
      "USA",
      "MDC Brooklyn",
      "Federal Bureau of Prisons"
    ],
    "locations": [],
    "dates": [
      "01/25/2021",
      "01/26/2021",
      "01/28/2021",
      "02/01/2021",
      "02/02/2021",
      "January 25, 2021",
      "January 28, 2021",
      "February 1, 2021",
      "January 15, 2021"
    ],
    "reference_numbers": [
      "118",
      "119",
      "120",
      "121",
      "122",
      "123",
      "124",
      "125",
      "126",
      "127",
      "128",
      "129",
      "130",
      "131",
      "117",
      "DOJ-OGR-00020407"
    ]
  },
  "additional_notes": "The document appears to be a court docket sheet from the case USA v. Ghislaine Maxwell. The document is well-formatted and legible, with clear headings and concise descriptions of the court filings and actions."
}