{
  "document_metadata": {
    "page_number": "21 of 38",
    "document_number": "33",
    "date": "04/09/20",
    "document_type": "Certificate of Service",
    "has_handwriting": false,
    "has_stamps": false
  },
  "full_text": "Case 1:19-cr-00830-AT Document 33 Filed 04/09/20 Page 21 of 38 CERTIFICATE OF SERVICE I HEREBY CERTIFY, that on the 1st day of April, 2020, I uploaded the original of this Motion to Compel onto ECF, and provided courtesy email copies by email to: Nicolas Tyler Landsman Roos Assistant U.S. Attorney United States Attorney's Office, SDNY One Saint Andrew's Plaza New York, NY 10007 (212)-637-2421 Email: nicolas.roos@usdoj.gov Rebekah Allen Donaleski Assistant U.S. Attorney United States Attorney's Office, SDNY One Saint Andrew's Plaza New York, NY 10007 212-637-2423 Fax: 212-637-2443 Email: Rebekah.Donaleski@usdoj.gov Jessica Rose Lonergan Assistant U.S. Attorney U.S. Attorney's Office, SDNY One St. Andrew's Plaza New York, NY 10007 (212)-637-1038 Fax: (212)-637-2937 Email: jessica.lonergan@usdoj.gov /s/ Montell Figgins 1 DOJ-OGR-00022044",
  "text_blocks": [
    {
      "type": "printed",
      "content": "Case 1:19-cr-00830-AT Document 33 Filed 04/09/20 Page 21 of 38",
      "position": "header"
    },
    {
      "type": "printed",
      "content": "CERTIFICATE OF SERVICE",
      "position": "top"
    },
    {
      "type": "printed",
      "content": "I HEREBY CERTIFY, that on the 1st day of April, 2020, I uploaded the original of this Motion to Compel onto ECF, and provided courtesy email copies by email to:",
      "position": "top"
    },
    {
      "type": "printed",
      "content": "Nicolas Tyler Landsman Roos Assistant U.S. Attorney United States Attorney's Office, SDNY One Saint Andrew's Plaza New York, NY 10007 (212)-637-2421 Email: nicolas.roos@usdoj.gov",
      "position": "middle"
    },
    {
      "type": "printed",
      "content": "Rebekah Allen Donaleski Assistant U.S. Attorney United States Attorney's Office, SDNY One Saint Andrew's Plaza New York, NY 10007 212-637-2423 Fax: 212-637-2443 Email: Rebekah.Donaleski@usdoj.gov",
      "position": "middle"
    },
    {
      "type": "printed",
      "content": "Jessica Rose Lonergan Assistant U.S. Attorney U.S. Attorney's Office, SDNY One St. Andrew's Plaza New York, NY 10007 (212)-637-1038 Fax: (212)-637-2937 Email: jessica.lonergan@usdoj.gov",
      "position": "middle"
    },
    {
      "type": "handwritten",
      "content": "/s/ Montell Figgins",
      "position": "bottom"
    },
    {
      "type": "printed",
      "content": "1",
      "position": "footer"
    },
    {
      "type": "printed",
      "content": "DOJ-OGR-00022044",
      "position": "footer"
    }
  ],
  "entities": {
    "people": [
      "Nicolas Tyler Landsman Roos",
      "Rebekah Allen Donaleski",
      "Jessica Rose Lonergan",
      "Montell Figgins"
    ],
    "organizations": [
      "United States Attorney's Office",
      "U.S. Attorney's Office"
    ],
    "locations": [
      "New York",
      "SDNY"
    ],
    "dates": [
      "April 1, 2020",
      "04/09/20"
    ],
    "reference_numbers": [
      "1:19-cr-00830-AT",
      "Document 33",
      "DOJ-OGR-00022044"
    ]
  },
  "additional_notes": "The document appears to be a Certificate of Service from a legal case, filed on April 9, 2020. It contains contact information for several Assistant U.S. Attorneys and is signed by Montell Figgins."
}