{
  "document_metadata": {
    "page_number": "5 of 8",
    "document_number": "9",
    "date": "11/19/19",
    "document_type": "Court Document",
    "has_handwriting": false,
    "has_stamps": false
  },
  "full_text": "Case 1:19-cr-00830-AT Document 9 Filed 11/19/19 Page 5 of 8\n\nADDITIONAL CONDITIONS OF RELEASE\n( ) (s) $100,000 PRB TO BE CO-SIGNED BY 2 FINANCIALLY RESPONSIBLE PERSONS; TRAVEL LIMITED TO SDNY/EDNY; DISTRICT OF NEW JERSEY & EASTERN DISTRICT OF PENNSYLVANIA; SURRENDER TRAVEL DOCUMENTS (& NO NEW APPLICATIONS); PRETRIAL SUPERVISION AS DIRECTED BY PTS; MENTAL HEALTH EVALUATION/TREATMENT AS DIRECTED BY PTS; DEFT NOT TO POSSESS FIREARM/DESTRUCTIVE DEVICE/OTHER WEAPON; DEFT TO BE RELEASED ON OWN SIGNATURE; REMAINING CONDITIONS TO BE MET BY 11/26/2019; NO CONTACT WITH CO-DEFENDANT UNLESS IN THE PRESENCE OF COUNSEL\n\nDOJ-OGR-00021946",
  "text_blocks": [
    {
      "type": "printed",
      "content": "Case 1:19-cr-00830-AT Document 9 Filed 11/19/19 Page 5 of 8",
      "position": "header"
    },
    {
      "type": "printed",
      "content": "ADDITIONAL CONDITIONS OF RELEASE",
      "position": "top"
    },
    {
      "type": "printed",
      "content": "( ) (s) $100,000 PRB TO BE CO-SIGNED BY 2 FINANCIALLY RESPONSIBLE PERSONS; TRAVEL LIMITED TO SDNY/EDNY; DISTRICT OF NEW JERSEY & EASTERN DISTRICT OF PENNSYLVANIA; SURRENDER TRAVEL DOCUMENTS (& NO NEW APPLICATIONS); PRETRIAL SUPERVISION AS DIRECTED BY PTS; MENTAL HEALTH EVALUATION/TREATMENT AS DIRECTED BY PTS; DEFT NOT TO POSSESS FIREARM/DESTRUCTIVE DEVICE/OTHER WEAPON; DEFT TO BE RELEASED ON OWN SIGNATURE; REMAINING CONDITIONS TO BE MET BY 11/26/2019; NO CONTACT WITH CO-DEFENDANT UNLESS IN THE PRESENCE OF COUNSEL",
      "position": "middle"
    },
    {
      "type": "printed",
      "content": "DOJ-OGR-00021946",
      "position": "footer"
    }
  ],
  "entities": {
    "people": [],
    "organizations": [
      "PTS"
    ],
    "locations": [
      "SDNY",
      "EDNY",
      "New Jersey",
      "Eastern District of Pennsylvania"
    ],
    "dates": [
      "11/19/19",
      "11/26/2019"
    ],
    "reference_numbers": [
      "1:19-cr-00830-AT",
      "Document 9",
      "DOJ-OGR-00021946"
    ]
  },
  "additional_notes": "The document appears to be a court document outlining additional conditions of release for a defendant. The text is typed, and there are no visible stamps or handwritten notes."
}