{
  "document_metadata": {
    "page_number": "26",
    "document_number": "109-1",
    "date": "09/17/2024",
    "document_type": "Court Document",
    "has_handwriting": false,
    "has_stamps": false
  },
  "full_text": "Case 22-1426, Document 109-1, 09/17/2024, 3634097, Page26 of 26\n1. The District Court did not err in holding that Epstein's NPA with USAO-SDFL did not bar Maxwell's prosecution by USAO-SDNY.\n2. The District Court did not err in holding that the Indictment was filed within the statute of limitations.\n3. The District Court did not abuse its discretion in denying Maxwell's Rule 33 motion for a new trial.\n4. The District Court's response to a jury note did not result in a constructive amendment of, or prejudicial variance from, the allegations in the Indictment.\n5. The District Court's sentence was procedurally reasonable.\nFor the foregoing reasons, we AFFIRM the District Court's June 29, 2022, judgment of conviction.\n26\nDOJ-OGR-00021820",
  "text_blocks": [
    {
      "type": "printed",
      "content": "Case 22-1426, Document 109-1, 09/17/2024, 3634097, Page26 of 26",
      "position": "header"
    },
    {
      "type": "printed",
      "content": "1. The District Court did not err in holding that Epstein's NPA with USAO-SDFL did not bar Maxwell's prosecution by USAO-SDNY.\n2. The District Court did not err in holding that the Indictment was filed within the statute of limitations.\n3. The District Court did not abuse its discretion in denying Maxwell's Rule 33 motion for a new trial.\n4. The District Court's response to a jury note did not result in a constructive amendment of, or prejudicial variance from, the allegations in the Indictment.\n5. The District Court's sentence was procedurally reasonable.\nFor the foregoing reasons, we AFFIRM the District Court's June 29, 2022, judgment of conviction.",
      "position": "middle"
    },
    {
      "type": "printed",
      "content": "26",
      "position": "footer"
    },
    {
      "type": "printed",
      "content": "DOJ-OGR-00021820",
      "position": "footer"
    }
  ],
  "entities": {
    "people": [
      "Epstein",
      "Maxwell"
    ],
    "organizations": [
      "USAO-SDFL",
      "USAO-SDNY",
      "District Court"
    ],
    "locations": [],
    "dates": [
      "09/17/2024",
      "June 29, 2022"
    ],
    "reference_numbers": [
      "22-1426",
      "109-1",
      "3634097",
      "DOJ-OGR-00021820"
    ]
  },
  "additional_notes": "The document appears to be a court document, specifically a page from a legal brief or decision. The text is well-formatted and clear. There are no visible redactions or damage."
}