{
  "document_metadata": {
    "page_number": "176",
    "document_number": "78",
    "date": "06/29/2023",
    "document_type": "court transcript",
    "has_handwriting": false,
    "has_stamps": false
  },
  "full_text": "Case 22-1426, Document 78, 06/29/2023, 3536039, Page176 of 217\nSA-430\n\nM6SQmaxS1                       61\ndistrust yourself. When a boundary is crossed or an\nexpectation violated, you tell yourself, \"Someone who cares\nabout me to do all these nice things surely wouldn't also be\ntrying to harm me.\" This pattern of thinking is insidious, so\nthese seeds of self-doubt took root even as I learned my sister\nhad also been harmed by them and came to find out years later\nthat many others had been exploited.\n\nTHE COURT: Just a request to slow down.\n\nMS. FARMER: For years these memories triggered\nsignificant self-recrimination, minimization and guilt. I\nblame myself for believing these predators actually wanted to\nhelp me. I felt tremendous survivor guilt when I heard about\nwhat other girls and young women had experienced at hands of\nMaxwell and Epstein. I saw about how my sister's concern about\nme weighed on her and felt guilty about this as well.\n\nThis toxic combination of being sexually exposed and\nexploited, feeling confused and naïve and blaming myself all\nresulted in significant shame; that sickening feeling that\nmakes you want to disappear. It was not constant but would\ncome in waves, similar to the waves that anxiety would also\nshow up. When I think back, I see a slide-show of moments when\nthese feelings would surface and overwhelm me. There are too\nmany of these moments to name and though I have come a long way\nin my path of healing, I know that these feelings will continue\nto be triggered at times.\n\nSOUTHERN DISTRICT REPORTERS, P.C...(212) 805-0300\nDOJ-OGR-00021606",
  "text_blocks": [
    {
      "type": "printed",
      "content": "Case 22-1426, Document 78, 06/29/2023, 3536039, Page176 of 217",
      "position": "header"
    },
    {
      "type": "printed",
      "content": "SA-430",
      "position": "header"
    },
    {
      "type": "printed",
      "content": "M6SQmaxS1                       61\ndistrust yourself. When a boundary is crossed or an\nexpectation violated, you tell yourself, \"Someone who cares\nabout me to do all these nice things surely wouldn't also be\ntrying to harm me.\" This pattern of thinking is insidious, so\nthese seeds of self-doubt took root even as I learned my sister\nhad also been harmed by them and came to find out years later\nthat many others had been exploited.",
      "position": "main content"
    },
    {
      "type": "printed",
      "content": "THE COURT: Just a request to slow down.",
      "position": "main content"
    },
    {
      "type": "printed",
      "content": "MS. FARMER: For years these memories triggered\nsignificant self-recrimination, minimization and guilt. I\nblame myself for believing these predators actually wanted to\nhelp me. I felt tremendous survivor guilt when I heard about\nwhat other girls and young women had experienced at hands of\nMaxwell and Epstein. I saw about how my sister's concern about\nme weighed on her and felt guilty about this as well.",
      "position": "main content"
    },
    {
      "type": "printed",
      "content": "This toxic combination of being sexually exposed and\nexploited, feeling confused and naïve and blaming myself all\nresulted in significant shame; that sickening feeling that\nmakes you want to disappear. It was not constant but would\ncome in waves, similar to the waves that anxiety would also\nshow up. When I think back, I see a slide-show of moments when\nthese feelings would surface and overwhelm me. There are too\nmany of these moments to name and though I have come a long way\nin my path of healing, I know that these feelings will continue\nto be triggered at times.",
      "position": "main content"
    },
    {
      "type": "printed",
      "content": "SOUTHERN DISTRICT REPORTERS, P.C...(212) 805-0300",
      "position": "footer"
    },
    {
      "type": "printed",
      "content": "DOJ-OGR-00021606",
      "position": "footer"
    }
  ],
  "entities": {
    "people": [
      "Maxwell",
      "Epstein",
      "Ms. Farmer"
    ],
    "organizations": [
      "SOUTHERN DISTRICT REPORTERS, P.C"
    ],
    "locations": [],
    "dates": [
      "06/29/2023"
    ],
    "reference_numbers": [
      "Case 22-1426",
      "Document 78",
      "3536039",
      "DOJ-OGR-00021606"
    ]
  },
  "additional_notes": "The document appears to be a court transcript with a clear and readable format. There are no visible redactions or damage."
}