{
  "document_metadata": {
    "page_number": "1",
    "document_number": "13",
    "date": "12/16/2019",
    "document_type": "Court Document",
    "has_handwriting": false,
    "has_stamps": true
  },
  "full_text": "Case 1:19-cr-00830-AT Document 13 Filed 12/16/19 Page 1 of 1 U.S. Department of Justice United States Attorney Southern District of New York The Silvio J. Mollo Building One Saint Andrew's Plaza New York, New York 10007 December 16, 2019 BY ECF The Honorable Analisa Torres United States District Judge Southern District of New York 500 Pearl Street New York, New York 10007 Re: United States v. Noel and Thomas, 19 Cr. 830 (AT) Dear Judge Torres: The Government writes, with the consent of defense counsel, to enclose a proposed protective order for the Court's review and endorsement. Respectfully submitted, GEOFFREY S. BERMAN United States Attorney for the Southern District of New York By: /s/ Rebekah Donaleski Nicolas Roos Jessica Lonergan Assistant United States Attorneys (212) 637-2423/2421/1038 cc: Defense Counsel (by ECF) DOJ-OGR-00021953",
  "text_blocks": [
    {
      "type": "printed",
      "content": "Case 1:19-cr-00830-AT Document 13 Filed 12/16/19 Page 1 of 1",
      "position": "header"
    },
    {
      "type": "printed",
      "content": "U.S. Department of Justice United States Attorney Southern District of New York The Silvio J. Mollo Building One Saint Andrew's Plaza New York, New York 10007 December 16, 2019",
      "position": "header"
    },
    {
      "type": "printed",
      "content": "BY ECF The Honorable Analisa Torres United States District Judge Southern District of New York 500 Pearl Street New York, New York 10007 Re: United States v. Noel and Thomas, 19 Cr. 830 (AT) Dear Judge Torres:",
      "position": "top"
    },
    {
      "type": "printed",
      "content": "The Government writes, with the consent of defense counsel, to enclose a proposed protective order for the Court's review and endorsement.",
      "position": "middle"
    },
    {
      "type": "printed",
      "content": "Respectfully submitted, GEOFFREY S. BERMAN United States Attorney for the Southern District of New York By: /s/ Rebekah Donaleski Nicolas Roos Jessica Lonergan Assistant United States Attorneys (212) 637-2423/2421/1038",
      "position": "middle"
    },
    {
      "type": "printed",
      "content": "cc: Defense Counsel (by ECF)",
      "position": "bottom"
    },
    {
      "type": "stamp",
      "content": "DOJ-OGR-00021953",
      "position": "footer"
    }
  ],
  "entities": {
    "people": [
      "Analisa Torres",
      "Geoffrey S. Berman",
      "Rebekah Donaleski",
      "Nicolas Roos",
      "Jessica Lonergan",
      "Noel",
      "Thomas"
    ],
    "organizations": [
      "U.S. Department of Justice",
      "United States Attorney Southern District of New York"
    ],
    "locations": [
      "New York",
      "Southern District of New York"
    ],
    "dates": [
      "December 16, 2019"
    ],
    "reference_numbers": [
      "1:19-cr-00830-AT",
      "19 Cr. 830 (AT)",
      "DOJ-OGR-00021953"
    ]
  },
  "additional_notes": "The document is a court filing in the case United States v. Noel and Thomas. It is a letter from the U.S. Attorney's office to Judge Analisa Torres, requesting the court's review and endorsement of a proposed protective order. The document is signed by Assistant U.S. Attorneys Rebekah Donaleski, Nicolas Roos, and Jessica Lonergan."
}