{
  "document_metadata": {
    "page_number": "30",
    "document_number": "59",
    "date": "02/28/2023",
    "document_type": "Court Document",
    "has_handwriting": false,
    "has_stamps": false
  },
  "full_text": "Case 22-1426, Document 59, 02/28/2023, 3475902, Page30 of 113\noffenses that arose from the Federal Grand Jury investigation will be instituted in this District, and the charges against Epstein if any, will be dismissed. A175.\n\nAfter detailing the terms of the agreement as they relate to Epstein, the NPA lays out the following provision:\n\nIn consideration of Epstein's agreement to plead guilty and to provide compensation in the manner described above, if Epstein successfully fulfills all of the terms and conditions of this agreement, the United States also agrees that it will not institute any criminal charges against any potential co-conspirators of Epstein, including but not limited to Sarah Kellen, Adriana Ross, Lesley Groff, or Nadia Marcinkova.\n\nA178 (emphasis added).\n\nThe NPA clearly distinguishes \"the United States\" from the USAO-SDFL, repeatedly referring explicitly to the latter where such a limitation is intended.\n\nThus, the NPA's references to the \"United States\" demonstrate a definitional intent not to limit such provisions to the USAO-SDFL. Unlike the provision that Epstein will not be prosecuted \"in this District\" (A175), the sentence regarding co-conspirators contains no provision limiting co-conspirators' immunity to the SDFL; no limitation on the scope of conduct for which \"potential co-conspirators of Epstein\" cannot be prosecuted, and no language limiting its binding effect on other USAOs, as standard agreements typically do.\n\n15\nDOJ-OGR-00021077",
  "text_blocks": [
    {
      "type": "printed",
      "content": "Case 22-1426, Document 59, 02/28/2023, 3475902, Page30 of 113",
      "position": "header"
    },
    {
      "type": "printed",
      "content": "offenses that arose from the Federal Grand Jury investigation will be instituted in this District, and the charges against Epstein if any, will be dismissed. A175.\n\nAfter detailing the terms of the agreement as they relate to Epstein, the NPA lays out the following provision:\n\nIn consideration of Epstein's agreement to plead guilty and to provide compensation in the manner described above, if Epstein successfully fulfills all of the terms and conditions of this agreement, the United States also agrees that it will not institute any criminal charges against any potential co-conspirators of Epstein, including but not limited to Sarah Kellen, Adriana Ross, Lesley Groff, or Nadia Marcinkova.\n\nA178 (emphasis added).\n\nThe NPA clearly distinguishes \"the United States\" from the USAO-SDFL, repeatedly referring explicitly to the latter where such a limitation is intended.\n\nThus, the NPA's references to the \"United States\" demonstrate a definitional intent not to limit such provisions to the USAO-SDFL. Unlike the provision that Epstein will not be prosecuted \"in this District\" (A175), the sentence regarding co-conspirators contains no provision limiting co-conspirators' immunity to the SDFL; no limitation on the scope of conduct for which \"potential co-conspirators of Epstein\" cannot be prosecuted, and no language limiting its binding effect on other USAOs, as standard agreements typically do.",
      "position": "main"
    },
    {
      "type": "printed",
      "content": "15",
      "position": "footer"
    },
    {
      "type": "printed",
      "content": "DOJ-OGR-00021077",
      "position": "footer"
    }
  ],
  "entities": {
    "people": [
      "Epstein",
      "Sarah Kellen",
      "Adriana Ross",
      "Lesley Groff",
      "Nadia Marcinkova"
    ],
    "organizations": [
      "Federal Grand Jury",
      "USAO-SDFL",
      "United States"
    ],
    "locations": [],
    "dates": [
      "02/28/2023"
    ],
    "reference_numbers": [
      "Case 22-1426",
      "Document 59",
      "3475902",
      "A175",
      "A178",
      "DOJ-OGR-00021077"
    ]
  },
  "additional_notes": "The document appears to be a court document related to the case of Jeffrey Epstein. It discusses the terms of a non-prosecution agreement (NPA) and its implications for Epstein and potential co-conspirators. The text is printed and there are no visible stamps or handwritten notes."
}