{
  "document_metadata": {
    "page_number": "90 of 208",
    "document_number": "57",
    "date": "02/28/2023",
    "document_type": "Court Document",
    "has_handwriting": false,
    "has_stamps": false
  },
  "full_text": "Case 22-1426, Document 57 02/28/2023, 3475900, Page90 of 208\nA-86\n2/22/23, 1:25 PM SDNY CM/ECF NextGen Version 1.6\n12/27/2021 | Minute Entry for proceedings held before Judge Alison J. Nathan: Jury Trial as to Ghislaine Maxwell held on 12/27/2021. Defendant Ghislaine Maxwell present with attorney Bobbi Sternheim, Jeff Pagliuca, Christian Everdell and Laura Menninger. AUSA Lara Pomerantz, Maurene Comey, Alison Moe and Andrew Rohrbach for the government. Court Reporter Martha Martin. Jury trial held. See Transcript. (jbo) (Entered: 01/10/2022)\n12/28/2021 | 566 LETTER by Ghislaine Maxwell addressed to Judge Alison J. Nathan from Christian R. Everdell dated December 27, 2021 re: Supplemental Instruction (Everdell, Christian) (Entered: 12/28/2021)\n12/28/2021 | Minute Entry for proceedings held before Judge Alison J. Nathan: Jury Trial as to Ghislaine Maxwell held on 12/28/2021. Defendant Ghislaine Maxwell present with attorney Bobbi Sternheim, Jeff Pagliuca, Christian Everdell and Laura Menninger. AUSA Lara Pomerantz, Maurene Comey, Alison Moe and Andrew Rohrbach for the government. Court Reporter George Malinowski. Jury trial held. See Transcript. (jbo) (Entered: 01/10/2022)\n12/29/2021 | Minute Entry for proceedings held before Judge Alison J. Nathan:Jury Trial as to Ghislaine Maxwell held on 12/29/2021. Defendant Ghislaine Maxwell present with attorney Bobbi Sternheim, Jeff Pagliuca, Christian Everdell and Laura Menninger. AUSA Lara Pomerantz, Maurene Comey, Alison Moe and Andrew Rohrbach for the government. Court Reporter Khris Sellin. Defendant found GUILTY on Counts 1,3,4,5, 6. Defendant found NOT GUILTY on Count 2. Jury trial concluded. (jw) (Entered: 01/11/2022)\n12/29/2021 | JURY VERDICT as to Ghislaine Maxwell (1) Guilty on Count 1ss,3ss,4ss,5ss,6ss; Not Guilty on Count 2ss. (jw) (Entered: 06/29/2022)\n01/03/2022 | 567 ORDER as to Ghislaine Maxwell. The parties are ORDERED to submit a joint letter by January 10, 2022, proposing a briefing schedule for the Defendant's Rule 29 motion and proposing a schedule for sentencing. The joint letter should also propose a schedule for the severed perjury counts. The Defense also inquired about a booster shot for the Defendant. The Court has been advised that MDC is making booster shots available within a week of receiving a request from an inmate. Defense counsel is accordingly advised to follow the MDC's instructions for requesting a booster. If a request is made and a booster not provided, Defense counsel may make a further application to the Court. SO ORDERED. (Signed by Judge Alison J. Nathan on 1/3/2022)(bw) (Entered: 01/03/2022)\n01/05/2022 | 568 LETTER MOTION addressed to Judge Alison J. Nathan from AUSAs Maurene Comey, Alison Moe, Lara Pomerantz, and Andrew Rohrbach dated January 5, 2022 re: Inquiry . Document filed by USA as to Ghislaine Maxwell. (Rohrbach, Andrew) (Entered: 01/05/2022)\n01/05/2022 | 569 LETTER by Ghislaine Maxwell addressed to Judge Alison J. Nathan from Christian R. Everdell dated 1/5/22 re: Juror Issue (Redacted) (Everdell, Christian) (Entered: 01/05/2022)\n01/05/2022 | 570 LETTER by Ghislaine Maxwell addressed to Judge Alison J. Nathan from Jeffrey S. Pagliuca dated January 5, 2022 re: Ms. Maxwell's Response to Government's Letter re Juror's Statements (Dkt. 568) (Pagliuca, Jeffrey) (Entered: 01/05/2022)\n01/05/2022 | 571 ORDER as to Ghislaine Maxwell. The Court is in receipt of the parties' letters. Dkt. Nos. 568, 569, 570. The Court hereby sets the following briefing schedule for the Defense to move for a new trial in light of the issues raised in the parties' letters: Defense motion: January 19, 2022; Government response: February 2, 2022; Defense reply: February 9, https://ecf.nysd.uscourts.gov/cgi-bin/DktRpt.pl?2110870152221896-L_1_0-1 86/113 DOJ-OGR-00020708",
  "text_blocks": [
    {
      "type": "printed",
      "content": "Case 22-1426, Document 57 02/28/2023, 3475900, Page90 of 208",
      "position": "header"
    },
    {
      "type": "printed",
      "content": "A-86",
      "position": "header"
    },
    {
      "type": "printed",
      "content": "2/22/23, 1:25 PM SDNY CM/ECF NextGen Version 1.6",
      "position": "header"
    },
    {
      "type": "printed",
      "content": "12/27/2021 | Minute Entry for proceedings held before Judge Alison J. Nathan: Jury Trial as to Ghislaine Maxwell held on 12/27/2021. Defendant Ghislaine Maxwell present with attorney Bobbi Sternheim, Jeff Pagliuca, Christian Everdell and Laura Menninger. AUSA Lara Pomerantz, Maurene Comey, Alison Moe and Andrew Rohrbach for the government. Court Reporter Martha Martin. Jury trial held. See Transcript. (jbo) (Entered: 01/10/2022)",
      "position": "body"
    },
    {
      "type": "printed",
      "content": "12/28/2021 | 566 LETTER by Ghislaine Maxwell addressed to Judge Alison J. Nathan from Christian R. Everdell dated December 27, 2021 re: Supplemental Instruction (Everdell, Christian) (Entered: 12/28/2021)",
      "position": "body"
    },
    {
      "type": "printed",
      "content": "12/28/2021 | Minute Entry for proceedings held before Judge Alison J. Nathan: Jury Trial as to Ghislaine Maxwell held on 12/28/2021. Defendant Ghislaine Maxwell present with attorney Bobbi Sternheim, Jeff Pagliuca, Christian Everdell and Laura Menninger. AUSA Lara Pomerantz, Maurene Comey, Alison Moe and Andrew Rohrbach for the government. Court Reporter George Malinowski. Jury trial held. See Transcript. (jbo) (Entered: 01/10/2022)",
      "position": "body"
    },
    {
      "type": "printed",
      "content": "12/29/2021 | Minute Entry for proceedings held before Judge Alison J. Nathan:Jury Trial as to Ghislaine Maxwell held on 12/29/2021. Defendant Ghislaine Maxwell present with attorney Bobbi Sternheim, Jeff Pagliuca, Christian Everdell and Laura Menninger. AUSA Lara Pomerantz, Maurene Comey, Alison Moe and Andrew Rohrbach for the government. Court Reporter Khris Sellin. Defendant found GUILTY on Counts 1,3,4,5, 6. Defendant found NOT GUILTY on Count 2. Jury trial concluded. (jw) (Entered: 01/11/2022)",
      "position": "body"
    },
    {
      "type": "printed",
      "content": "12/29/2021 | JURY VERDICT as to Ghislaine Maxwell (1) Guilty on Count 1ss,3ss,4ss,5ss,6ss; Not Guilty on Count 2ss. (jw) (Entered: 06/29/2022)",
      "position": "body"
    },
    {
      "type": "printed",
      "content": "01/03/2022 | 567 ORDER as to Ghislaine Maxwell. The parties are ORDERED to submit a joint letter by January 10, 2022, proposing a briefing schedule for the Defendant's Rule 29 motion and proposing a schedule for sentencing. The joint letter should also propose a schedule for the severed perjury counts. The Defense also inquired about a booster shot for the Defendant. The Court has been advised that MDC is making booster shots available within a week of receiving a request from an inmate. Defense counsel is accordingly advised to follow the MDC's instructions for requesting a booster. If a request is made and a booster not provided, Defense counsel may make a further application to the Court. SO ORDERED. (Signed by Judge Alison J. Nathan on 1/3/2022)(bw) (Entered: 01/03/2022)",
      "position": "body"
    },
    {
      "type": "printed",
      "content": "01/05/2022 | 568 LETTER MOTION addressed to Judge Alison J. Nathan from AUSAs Maurene Comey, Alison Moe, Lara Pomerantz, and Andrew Rohrbach dated January 5, 2022 re: Inquiry . Document filed by USA as to Ghislaine Maxwell. (Rohrbach, Andrew) (Entered: 01/05/2022)",
      "position": "body"
    },
    {
      "type": "printed",
      "content": "01/05/2022 | 569 LETTER by Ghislaine Maxwell addressed to Judge Alison J. Nathan from Christian R. Everdell dated 1/5/22 re: Juror Issue (Redacted) (Everdell, Christian) (Entered: 01/05/2022)",
      "position": "body"
    },
    {
      "type": "printed",
      "content": "01/05/2022 | 570 LETTER by Ghislaine Maxwell addressed to Judge Alison J. Nathan from Jeffrey S. Pagliuca dated January 5, 2022 re: Ms. Maxwell's Response to Government's Letter re Juror's Statements (Dkt. 568) (Pagliuca, Jeffrey) (Entered: 01/05/2022)",
      "position": "body"
    },
    {
      "type": "printed",
      "content": "01/05/2022 | 571 ORDER as to Ghislaine Maxwell. The Court is in receipt of the parties' letters. Dkt. Nos. 568, 569, 570. The Court hereby sets the following briefing schedule for the Defense to move for a new trial in light of the issues raised in the parties' letters: Defense motion: January 19, 2022; Government response: February 2, 2022; Defense reply: February 9,",
      "position": "body"
    },
    {
      "type": "printed",
      "content": "https://ecf.nysd.uscourts.gov/cgi-bin/DktRpt.pl?2110870152221896-L_1_0-1 86/113 DOJ-OGR-00020708",
      "position": "footer"
    }
  ],
  "entities": {
    "people": [
      "Ghislaine Maxwell",
      "Alison J. Nathan",
      "Bobbi Sternheim",
      "Jeff Pagliuca",
      "Christian Everdell",
      "Laura Menninger",
      "Lara Pomerantz",
      "Maurene Comey",
      "Alison Moe",
      "Andrew Rohrbach",
      "Martha Martin",
      "George Malinowski",
      "Khris Sellin",
      "Jeffrey S. Pagliuca"
    ],
    "organizations": [
      "USA",
      "MDC"
    ],
    "locations": [
      "SDNY"
    ],
    "dates": [
      "12/27/2021",
      "12/28/2021",
      "12/29/2021",
      "01/03/2022",
      "01/05/2022",
      "01/10/2022",
      "01/11/2022",
      "06/29/2022",
      "02/28/2023",
      "January 5, 2022",
      "January 10, 2022",
      "January 19, 2022",
      "February 2, 2022",
      "February 9, 2022"
    ],
    "reference_numbers": [
      "Case 22-1426",
      "Document 57",
      "3475900",
      "566",
      "567",
      "568",
      "569",
      "570",
      "571",
      "Dkt. 568",
      "Dkt. 569",
      "Dkt. 570",
      "DOJ-OGR-00020708"
    ]
  },
  "additional_notes": "The document appears to be a court docket sheet from the United States District Court for the Southern District of New York (SDNY). The document is related to the case of Ghislaine Maxwell and includes various entries for proceedings, letters, and orders. The document is 90 pages into a total of 208 pages."
}