{
  "document_metadata": {
    "page_number": "61",
    "document_number": "78",
    "date": "06/29/2023",
    "document_type": "court document",
    "has_handwriting": false,
    "has_stamps": false
  },
  "full_text": "Case 22-1426, Document 78, 06/29/2023, 3536039, Page61 of 217\nSA-315\nCase 1:20-cr-00330-AJN Document 204-3 Filed 04/16/21 Page 315 of 348\n6. U.S. Attorney's Office for the Middle District of Florida Records\nThe U.S. Attorney's Office for the Middle District of Florida provided OPR with records related to its review of evidence against Epstein, after he concluded his Florida state sentence, when the Department recused the USAO in August 2011 from \"all matters, to include the investigation and potential prosecution, relating to Jeffrey Epstein's alleged sexual activities with minor females,\" and assigned the matter to the Middle District of Florida U.S. Attorney's Office for further consideration. The records included a declination of the matter due to the NPA.\n7. U.S. Attorney's Office for the Northern District of Georgia Records\nThe U.S. Attorney's Office for the Northern District of Georgia provided OPR with records related to its work on the CVRA litigation after the recusal of the USAO.\n8. Public Records\nOPR obtained and reviewed a variety of public records, including publicly released records of the Palm Beach Police Department, the State Attorney's Office for the 15th Judicial Circuit, and the Palm Beach Sheriff's Office; documents pertaining to the CVRA litigation and other court proceedings involving Epstein and related individuals; and books and media reports.\nB. Information from Subjects, Witnesses, and Victims\n1. Subjects\nOPR requested that all five subjects provide written responses detailing their involvement in the federal investigation of Epstein, the drafting and execution of the NPA, and decisions relating to victim notification and consultation. In addition, OPR conducted extensive interviews of each subject under oath and before a court reporter. Each subject was represented by counsel and had access to relevant contemporaneous documents before the subject's OPR interview. The subjects reviewed and provided comments on their interview transcripts and on OPR's draft report.\n2. Witnesses\nOPR conducted more than 60 interviews of witnesses, including the FBI case agents, their supervisors, and FBI administrative personnel. OPR interviewed current and former USAO staff and attorneys and current and former Department attorneys and senior managers, including former Deputy Attorney General Mark Filip and former Assistant Attorney General for the Criminal Division Alice Fisher. OPR also interviewed former State Attorney Barry Krischer and former Assistant State Attorney Lanna Behlolovich.\n3. Communications with Victims and Victims' Attorneys\nOPR contacted attorneys known to represent 26 victims among the 30 surviving individuals who were identified in the USAO's July 2008 listing of 32 victims the USAO was prepared to include in federal charges against Epstein and who accordingly were entitled to the benefits of the 18 U.S.C. ยง 2255 monetary damages provision of the NPA. OPR contacted the attorneys to invite\n289\nDOJ-OGR-00021491",
  "text_blocks": [
    {
      "type": "printed",
      "content": "Case 22-1426, Document 78, 06/29/2023, 3536039, Page61 of 217",
      "position": "header"
    },
    {
      "type": "printed",
      "content": "SA-315",
      "position": "header"
    },
    {
      "type": "printed",
      "content": "Case 1:20-cr-00330-AJN Document 204-3 Filed 04/16/21 Page 315 of 348",
      "position": "header"
    },
    {
      "type": "printed",
      "content": "6. U.S. Attorney's Office for the Middle District of Florida Records",
      "position": "body"
    },
    {
      "type": "printed",
      "content": "The U.S. Attorney's Office for the Middle District of Florida provided OPR with records related to its review of evidence against Epstein, after he concluded his Florida state sentence, when the Department recused the USAO in August 2011 from \"all matters, to include the investigation and potential prosecution, relating to Jeffrey Epstein's alleged sexual activities with minor females,\" and assigned the matter to the Middle District of Florida U.S. Attorney's Office for further consideration. The records included a declination of the matter due to the NPA.",
      "position": "body"
    },
    {
      "type": "printed",
      "content": "7. U.S. Attorney's Office for the Northern District of Georgia Records",
      "position": "body"
    },
    {
      "type": "printed",
      "content": "The U.S. Attorney's Office for the Northern District of Georgia provided OPR with records related to its work on the CVRA litigation after the recusal of the USAO.",
      "position": "body"
    },
    {
      "type": "printed",
      "content": "8. Public Records",
      "position": "body"
    },
    {
      "type": "printed",
      "content": "OPR obtained and reviewed a variety of public records, including publicly released records of the Palm Beach Police Department, the State Attorney's Office for the 15th Judicial Circuit, and the Palm Beach Sheriff's Office; documents pertaining to the CVRA litigation and other court proceedings involving Epstein and related individuals; and books and media reports.",
      "position": "body"
    },
    {
      "type": "printed",
      "content": "B. Information from Subjects, Witnesses, and Victims",
      "position": "body"
    },
    {
      "type": "printed",
      "content": "1. Subjects",
      "position": "body"
    },
    {
      "type": "printed",
      "content": "OPR requested that all five subjects provide written responses detailing their involvement in the federal investigation of Epstein, the drafting and execution of the NPA, and decisions relating to victim notification and consultation. In addition, OPR conducted extensive interviews of each subject under oath and before a court reporter. Each subject was represented by counsel and had access to relevant contemporaneous documents before the subject's OPR interview. The subjects reviewed and provided comments on their interview transcripts and on OPR's draft report.",
      "position": "body"
    },
    {
      "type": "printed",
      "content": "2. Witnesses",
      "position": "body"
    },
    {
      "type": "printed",
      "content": "OPR conducted more than 60 interviews of witnesses, including the FBI case agents, their supervisors, and FBI administrative personnel. OPR interviewed current and former USAO staff and attorneys and current and former Department attorneys and senior managers, including former Deputy Attorney General Mark Filip and former Assistant Attorney General for the Criminal Division Alice Fisher. OPR also interviewed former State Attorney Barry Krischer and former Assistant State Attorney Lanna Behlolovich.",
      "position": "body"
    },
    {
      "type": "printed",
      "content": "3. Communications with Victims and Victims' Attorneys",
      "position": "body"
    },
    {
      "type": "printed",
      "content": "OPR contacted attorneys known to represent 26 victims among the 30 surviving individuals who were identified in the USAO's July 2008 listing of 32 victims the USAO was prepared to include in federal charges against Epstein and who accordingly were entitled to the benefits of the 18 U.S.C. ยง 2255 monetary damages provision of the NPA. OPR contacted the attorneys to invite",
      "position": "body"
    },
    {
      "type": "printed",
      "content": "289",
      "position": "footer"
    },
    {
      "type": "printed",
      "content": "DOJ-OGR-00021491",
      "position": "footer"
    }
  ],
  "entities": {
    "people": [
      "Jeffrey Epstein",
      "Mark Filip",
      "Alice Fisher",
      "Barry Krischer",
      "Lanna Behlolovich"
    ],
    "organizations": [
      "U.S. Attorney's Office for the Middle District of Florida",
      "U.S. Attorney's Office for the Northern District of Georgia",
      "Palm Beach Police Department",
      "State Attorney's Office for the 15th Judicial Circuit",
      "Palm Beach Sheriff's Office",
      "FBI",
      "Department of Justice"
    ],
    "locations": [
      "Florida",
      "Georgia",
      "Palm Beach"
    ],
    "dates": [
      "06/29/2023",
      "04/16/21",
      "August 2011",
      "July 2008"
    ],
    "reference_numbers": [
      "Case 22-1426",
      "Document 78",
      "Case 1:20-cr-00330-AJN",
      "Document 204-3",
      "DOJ-OGR-00021491",
      "18 U.S.C. ยง 2255"
    ]
  },
  "additional_notes": "The document appears to be a court filing related to the investigation of Jeffrey Epstein. The text is printed and clear, with no visible handwriting or stamps. The document includes references to various court cases and legal codes."
}