{
  "document_metadata": {
    "page_number": "1",
    "document_number": "19",
    "date": "01/24/20",
    "document_type": "Appearance of Counsel",
    "has_handwriting": false,
    "has_stamps": false
  },
  "full_text": "Case 1:19-cr-00830-AT Document 19 Filed 01/24/20 Page 1 of 1\n\nAO 458 (Rev. 06/09) Appearance of Counsel\n\nUNITED STATES DISTRICT COURT\nfor the\nSouthern District of New York\n\nUnited States )\nPlaintiff )\n) Case No. 19 Cr. 830 (AT)\nv. )\nTova Noel & Michael Thomas )\nDefendant )\n\nAPPEARANCE OF COUNSEL\n\nTo: The clerk of court and all parties of record\n\nI am admitted or otherwise authorized to practice in this court, and I appear in this case as counsel for:\nthe United States\n\nDate: 01/24/2020 /s/ Attorney's signature\n\nJessica Lonergan Printed name and bar number\nU.S. Attorney's Office, SDNY Address\nOne St. Andrew's Plaza New York, New York 10007\n\njessica.lonergan@usdoj.gov E-mail address\n(212) 637-1038 Telephone number\n(212) 637-2615 FAX number\n\nDOJ-OGR-00021993",
  "text_blocks": [
    {
      "type": "printed",
      "content": "Case 1:19-cr-00830-AT Document 19 Filed 01/24/20 Page 1 of 1",
      "position": "header"
    },
    {
      "type": "printed",
      "content": "AO 458 (Rev. 06/09) Appearance of Counsel",
      "position": "header"
    },
    {
      "type": "printed",
      "content": "UNITED STATES DISTRICT COURT for the Southern District of New York",
      "position": "header"
    },
    {
      "type": "printed",
      "content": "United States Plaintiff v. Tova Noel & Michael Thomas Defendant",
      "position": "middle"
    },
    {
      "type": "printed",
      "content": "Case No. 19 Cr. 830 (AT)",
      "position": "middle"
    },
    {
      "type": "printed",
      "content": "APPEARANCE OF COUNSEL",
      "position": "middle"
    },
    {
      "type": "printed",
      "content": "To: The clerk of court and all parties of record",
      "position": "middle"
    },
    {
      "type": "printed",
      "content": "I am admitted or otherwise authorized to practice in this court, and I appear in this case as counsel for: the United States",
      "position": "middle"
    },
    {
      "type": "handwritten",
      "content": "01/24/2020",
      "position": "middle"
    },
    {
      "type": "signature",
      "content": "/s/",
      "position": "middle"
    },
    {
      "type": "printed",
      "content": "Jessica Lonergan Printed name and bar number U.S. Attorney's Office, SDNY One St. Andrew's Plaza New York, New York 10007 Address jessica.lonergan@usdoj.gov E-mail address (212) 637-1038 Telephone number (212) 637-2615 FAX number",
      "position": "middle"
    },
    {
      "type": "printed",
      "content": "DOJ-OGR-00021993",
      "position": "footer"
    }
  ],
  "entities": {
    "people": [
      "Tova Noel",
      "Michael Thomas",
      "Jessica Lonergan"
    ],
    "organizations": [
      "United States District Court",
      "U.S. Attorney's Office, SDNY",
      "United States Department of Justice"
    ],
    "locations": [
      "New York",
      "Southern District of New York"
    ],
    "dates": [
      "01/24/2020"
    ],
    "reference_numbers": [
      "19 Cr. 830 (AT)",
      "DOJ-OGR-00021993"
    ]
  },
  "additional_notes": "The document is a standard form for appearance of counsel in a court case. It is filled out with the relevant information for the case and the attorney appearing. The document is clean and legible, with no visible damage or redactions."
}