{
  "document_metadata": {
    "page_number": "40",
    "document_number": "653",
    "date": "04/01/22",
    "document_type": "Court Order",
    "has_handwriting": true,
    "has_stamps": false
  },
  "full_text": "Case 22-1426, Document 58 02/28/2023, 3475901, Page157 of 221\nA-357\nCase 1:20-cr-00330-AJN Document 653 Filed 04/01/22 Page 40 of 40\nselection process was highly unfortunate, but not deliberate. The Court further concludes that Juror 50 harbored no bias toward the Defendant and could serve as a fair and impartial juror.\nThe requirements for a new trial under McDonough are not satisfied. The Defendant's motion for a new trial pursuant to Rule 33 is therefore DENIED.\nThe Court orders the preparation of the presentence investigation report.\nWith respect to Counts 7 and 8, the Court hereby excludes time under the Speedy Trial Act, 18 U.S.C. ยง 3161(h)(7)(A), from today's date through April 22, 2022. The Court finds that the ends of justice served by granting this exclusion from speedy trial computations outweigh the interests of the public and the Defendant in a speedy trial on these counts because the pending post-trial motions affect the scheduling considerations set forth in the Government's January 10, 2022 letter. See Dkt. No. 574. The Defendant consents to this exclusion. Dkt. No. 650.\nThe Court will rule on the Defendant's remaining post-verdict motions in due course.\nSentencing remains scheduled for June 28, 2022. This resolves docket numbers 613, 614, 642, 650, and 651.\nSO ORDERED.\nDated: April 1, 2022\nNew York, New York\nALISON J. NATHAN\nUnited States Circuit Judge\nSitting by Designation\n40\nDOJ-OGR-00020983",
  "text_blocks": [
    {
      "type": "printed",
      "content": "Case 22-1426, Document 58 02/28/2023, 3475901, Page157 of 221",
      "position": "header"
    },
    {
      "type": "printed",
      "content": "A-357",
      "position": "header"
    },
    {
      "type": "printed",
      "content": "Case 1:20-cr-00330-AJN Document 653 Filed 04/01/22 Page 40 of 40",
      "position": "header"
    },
    {
      "type": "printed",
      "content": "selection process was highly unfortunate, but not deliberate. The Court further concludes that Juror 50 harbored no bias toward the Defendant and could serve as a fair and impartial juror.\nThe requirements for a new trial under McDonough are not satisfied. The Defendant's motion for a new trial pursuant to Rule 33 is therefore DENIED.\nThe Court orders the preparation of the presentence investigation report.\nWith respect to Counts 7 and 8, the Court hereby excludes time under the Speedy Trial Act, 18 U.S.C. ยง 3161(h)(7)(A), from today's date through April 22, 2022. The Court finds that the ends of justice served by granting this exclusion from speedy trial computations outweigh the interests of the public and the Defendant in a speedy trial on these counts because the pending post-trial motions affect the scheduling considerations set forth in the Government's January 10, 2022 letter. See Dkt. No. 574. The Defendant consents to this exclusion. Dkt. No. 650.\nThe Court will rule on the Defendant's remaining post-verdict motions in due course.\nSentencing remains scheduled for June 28, 2022. This resolves docket numbers 613, 614, 642, 650, and 651.",
      "position": "main"
    },
    {
      "type": "printed",
      "content": "SO ORDERED.",
      "position": "main"
    },
    {
      "type": "printed",
      "content": "Dated: April 1, 2022\nNew York, New York",
      "position": "footer"
    },
    {
      "type": "handwritten",
      "content": "Alison J. Nathan",
      "position": "footer"
    },
    {
      "type": "printed",
      "content": "ALISON J. NATHAN\nUnited States Circuit Judge\nSitting by Designation",
      "position": "footer"
    },
    {
      "type": "printed",
      "content": "40",
      "position": "footer"
    },
    {
      "type": "printed",
      "content": "DOJ-OGR-00020983",
      "position": "footer"
    }
  ],
  "entities": {
    "people": [
      "Alison J. Nathan",
      "Juror 50",
      "Defendant"
    ],
    "organizations": [
      "United States Circuit Court"
    ],
    "locations": [
      "New York"
    ],
    "dates": [
      "April 1, 2022",
      "April 22, 2022",
      "January 10, 2022",
      "June 28, 2022",
      "02/28/2023"
    ],
    "reference_numbers": [
      "Case 22-1426",
      "Document 58",
      "Case 1:20-cr-00330-AJN",
      "Document 653",
      "Dkt. No. 574",
      "Dkt. No. 650",
      "Docket numbers 613, 614, 642, 650, and 651",
      "3475901",
      "A-357",
      "DOJ-OGR-00020983"
    ]
  },
  "additional_notes": "The document appears to be a court order from the United States Circuit Court. It is a typed document with a handwritten signature. The document is in good condition, with no visible damage or redactions."
}