{
  "document_metadata": {
    "page_number": "77 of 92",
    "document_number": "3-2",
    "date": "07/08/2022",
    "document_type": "Case Document",
    "has_handwriting": false,
    "has_stamps": false
  },
  "full_text": "Case 22-1426, Document 3-2, 07/08/2022, 3344434, Page77 of 92\n\n|          |          | See Transcript. (jbo) (Entered: 12/22/2021)                                                                                   |\n| 12/21/2021 |          | Minute Entry for proceedings held before Judge Alison J. Nathan: Jury Trial as to Ghislaine Maxwell held on 12/21/2021. Defendant Ghislaine Maxwell present with attorney Bobbi Sternheim, Jeff Pagliuca, Christian Everdell and Laura Menninger. AUSA Lara Pomerantz, Maurene Comey, Alison Moe and Andrew Rohrbach for the government. Court Reporter Martha Martin. Jury trial held. See Transcript. (jbo) (Entered: 12/22/2021) |\n| 12/22/2021 |          | Minute Entry for proceedings held before Judge Alison J. Nathan: Jury Trial as to Ghislaine Maxwell held on 12/22/2021. Defendant Ghislaine Maxwell present with attorney Bobbi Sternheim, Jeff Pagliuca, Christian Everdell and Laura Menninger. AUSA Lara Pomerantz, Maurene Comey, Alison Moe and Andrew Rohrbach for the government. Court Reporter George Malinowski. Jury trial held. See Transcript. (jbo) (Entered: 01/10/2022) |\n| 12/27/2021 |          | Minute Entry for proceedings held before Judge Alison J. Nathan: Jury Trial as to Ghislaine Maxwell held on 12/27/2021. Defendant Ghislaine Maxwell present with attorney Bobbi Sternheim, Jeff Pagliuca, Christian Everdell and Laura Menninger. AUSA Lara Pomerantz, Maurene Comey, Alison Moe and Andrew Rohrbach for the government. Court Reporter Martha Martin. Jury trial held. See Transcript. (jbo) (Entered: 01/10/2022) |\n| 12/28/2021 | 566      | LETTER by Ghislaine Maxwell addressed to Judge Alison J. Nathan from Christian R. Everdell dated December 27, 2021 re: Supplemental Instruction (Everdell, Christian) (Entered: 12/28/2021) |\n| 12/28/2021 |          | Minute Entry for proceedings held before Judge Alison J. Nathan: Jury Trial as to Ghislaine Maxwell held on 12/28/2021. Defendant Ghislaine Maxwell present with attorney Bobbi Sternheim, Jeff Pagliuca, Christian Everdell and Laura Menninger. AUSA Lara Pomerantz, Maurene Comey, Alison Moe and Andrew Rohrbach for the government. Court Reporter George Malinowski. Jury trial held. See Transcript. (jbo) (Entered: 01/10/2022) |\n| 12/29/2021 |          | Minute Entry for proceedings held before Judge Alison J. Nathan:Jury Trial as to Ghislaine Maxwell held on 12/29/2021. Defendant Ghislaine Maxwell present with attorney Bobbi Sternheim, Jeff Pagliuca, Christian Everdell and Laura Menninger. AUSA Lara Pomerantz, Maurene Comey, Alison Moe and Andrew Rohrbach for the government. Court Reporter Khris Sellin. Defendant found GUILTY on Counts 1, 3, 4, 5, 6. Defendant found NOT GUILTY on Count 2. Jury trial concluded. (jw) (Entered: 01/11/2022) |\n| 12/29/2021 |          | JURY VERDICT as to Ghislaine Maxwell (1) Guilty on Count 1ss,3ss,4ss,5ss,6ss; Not Guilty on Count 2ss. (jw) (Entered: 06/29/2022) |\n| 01/03/2022 | 567      | ORDER as to Ghislaine Maxwell. The parties are ORDERED to submit a joint letter by January 10, 2022, proposing a briefing schedule for the Defendant's Rule 29 motion and proposing a schedule for sentencing. The joint letter should also propose a shot for the severed perjury counts. The Defense also inquired about a booster available within a week of receiving a request from an inmate. Defense counsel is accordingly advised to follow the MDC's instructions for requesting a booster. If a request is made and a booster not provided, Defense counsel may make a further application to the Court. SO ORDERED. (Signed by Judge Alison J. Nathan on 1/3/2022)(bw) (Entered: 01/03/2022) |\n| 01/05/2022 | 568      | LETTER MOTION addressed to Judge Alison J. Nathan from AUSAs Maurene Comey, Alison Moe, Lara Pomerantz, and Andrew Rohrbach dated January 5, 2022 re: Inquiry. Document filed by USA as to Ghislaine Maxwell. (Rohrbach, Andrew) (Entered: 01/05/2022) |\n| 01/05/2022 | 569      | LETTER by Ghislaine Maxwell addressed to Judge Alison J. Nathan from Christian R. Everdell dated 1/5/22 re: Juror Issue (Redacted) (Everdell, Christian) (Entered: 01/05/2022) |\n| 01/05/2022 | 570      | LETTER by Ghislaine Maxwell addressed to Judge Alison J. Nathan from Jeffrey S. Pagliuca dated January 5, 2022 re: Ms. Maxwell's Response to Government's Letter re. |\n\nDOJ-OGR-00020563",
  "text_blocks": [
    {
      "type": "printed",
      "content": "Case 22-1426, Document 3-2, 07/08/2022, 3344434, Page77 of 92",
      "position": "header"
    },
    {
      "type": "printed",
      "content": "The table contains minute entries and other court documents related to the case of Ghislaine Maxwell.",
      "position": "main content"
    },
    {
      "type": "printed",
      "content": "DOJ-OGR-00020563",
      "position": "footer"
    }
  ],
  "entities": {
    "people": [
      "Ghislaine Maxwell",
      "Alison J. Nathan",
      "Bobbi Sternheim",
      "Jeff Pagliuca",
      "Christian Everdell",
      "Laura Menninger",
      "Lara Pomerantz",
      "Maurene Comey",
      "Alison Moe",
      "Andrew Rohrbach",
      "Martha Martin",
      "George Malinowski",
      "Khris Sellin"
    ],
    "organizations": [
      "USA"
    ],
    "locations": [],
    "dates": [
      "12/21/2021",
      "12/22/2021",
      "12/27/2021",
      "12/28/2021",
      "12/29/2021",
      "01/03/2022",
      "01/05/2022",
      "01/10/2022",
      "01/11/2022",
      "06/29/2022",
      "07/08/2022"
    ],
    "reference_numbers": [
      "22-1426",
      "3-2",
      "3344434",
      "566",
      "567",
      "568",
      "569",
      "570",
      "DOJ-OGR-00020563"
    ]
  },
  "additional_notes": "The document appears to be a court docket sheet for the case of Ghislaine Maxwell. It contains minute entries and other court documents related to the case. The document is well-formatted and legible."
}