{
  "document_metadata": {
    "page_number": null,
    "document_number": "2006CF009454AXX",
    "date": "February 8, 2008",
    "document_type": "NOTICE OF DEPOSITION",
    "has_handwriting": true,
    "has_stamps": false
  },
  "full_text": "IN THE CIRCUIT COURT OF THE FIFTEENTH JUDICIAL CIRCUIT, IN AND FOR PALM BEACH COUNTY, FLORIDA\nSTATE OF FLORIDA\nVS.\nJEFFREY EPSTEIN,\nDefendant.\nCASE NO.: 2006CF009454AXX\nNOTICE OF DEPOSITION\n(Time change only pursuant to the request of Theodore J. Leopold, Esquire)\nTO: Lanna Belohlavek, Esquire\nOffice of the State Attorney\n401 N. Dixie Hwy\nWest Palm Beach, Florida 33401\nPLEASE TAKE NOTICE that pursuant to the Florida Rules of Criminal Procedure that on February 20, 2008 beginning at the hour of 2:00 P.M., at the Palm Beach County Courthouse, 4th Floor, 205 North Dixie Highway, West Palm Beach, Florida 33401:\nbefore Consor & Associates who is authorized by law to take depositions in the State of Florida, the Plaintiffs will, upon oral examination, take the deposition of the following named via telephone, to wit:\n2:00 P.M.\nSuch oral examination will continue from day to day until completed. You are hereby notified to phone in and take part in said examination as you may be advised, and as shall be fit and proper.\nThis deposition is being taken for the purposes of discovery, for use as primary evidence or for such other purposes as are permitted under the applicable Statutes or Rules of Court.\nI HEREBY CERTIFY that a copy of the foregoing Notice of Taking Deposition has been furnished to the above named addressee, Thedore J. Leopold, Esquire, 2925 PGA Boulevard, Suite 200, Palm Beach Gardens, Florida 33410 and Jeffrey Herman, Esquire, 18205 Biscayne Boulevard, Suite 2218, Miami, Florida, 33160 by via fax & mail this 8th day of February, 2008.\nATTERBURY, GOLDBERGER, & WEISS, P.A.\n250 Australian Avenue South, Suite 1400\nWest Palm Beach, Florida 33401\n(561) 659-8300\nfax (561) 835-8691\nJACK A. GOLDBERGER, ESQUIRE\nFlorida Bar No. 262013\nPublic Records Request No.: 17-295\n07/26/17 DOJ-OGR-00030539",
  "text_blocks": [
    {
      "type": "printed",
      "content": "IN THE CIRCUIT COURT OF THE FIFTEENTH JUDICIAL CIRCUIT, IN AND FOR PALM BEACH COUNTY, FLORIDA",
      "position": "header"
    },
    {
      "type": "printed",
      "content": "STATE OF FLORIDA\nVS.\nJEFFREY EPSTEIN,\nDefendant.",
      "position": "top"
    },
    {
      "type": "printed",
      "content": "CASE NO.: 2006CF009454AXX\nNOTICE OF DEPOSITION",
      "position": "top"
    },
    {
      "type": "printed",
      "content": "(Time change only pursuant to the request of Theodore J. Leopold, Esquire)",
      "position": "top"
    },
    {
      "type": "printed",
      "content": "TO: Lanna Belohlavek, Esquire\nOffice of the State Attorney\n401 N. Dixie Hwy\nWest Palm Beach, Florida 33401",
      "position": "middle"
    },
    {
      "type": "printed",
      "content": "PLEASE TAKE NOTICE that pursuant to the Florida Rules of Criminal Procedure that on February 20, 2008 beginning at the hour of 2:00 P.M., at the Palm Beach County Courthouse, 4th Floor, 205 North Dixie Highway, West Palm Beach, Florida 33401:",
      "position": "middle"
    },
    {
      "type": "printed",
      "content": "before Consor & Associates who is authorized by law to take depositions in the State of Florida, the Plaintiffs will, upon oral examination, take the deposition of the following named via telephone, to wit:",
      "position": "middle"
    },
    {
      "type": "printed",
      "content": "2:00 P.M.",
      "position": "middle"
    },
    {
      "type": "printed",
      "content": "Such oral examination will continue from day to day until completed. You are hereby notified to phone in and take part in said examination as you may be advised, and as shall be fit and proper.",
      "position": "middle"
    },
    {
      "type": "printed",
      "content": "This deposition is being taken for the purposes of discovery, for use as primary evidence or for such other purposes as are permitted under the applicable Statutes or Rules of Court.",
      "position": "middle"
    },
    {
      "type": "printed",
      "content": "I HEREBY CERTIFY that a copy of the foregoing Notice of Taking Deposition has been furnished to the above named addressee, Thedore J. Leopold, Esquire, 2925 PGA Boulevard, Suite 200, Palm Beach Gardens, Florida 33410 and Jeffrey Herman, Esquire, 18205 Biscayne Boulevard, Suite 2218, Miami, Florida, 33160 by via fax & mail this 8th day of February, 2008.",
      "position": "middle"
    },
    {
      "type": "printed",
      "content": "ATTERBURY, GOLDBERGER, & WEISS, P.A.\n250 Australian Avenue South, Suite 1400\nWest Palm Beach, Florida 33401\n(561) 659-8300\nfax (561) 835-8691",
      "position": "bottom"
    },
    {
      "type": "handwritten",
      "content": "JACK A. GOLDBERGER, ESQUIRE\nFlorida Bar No. 262013",
      "position": "bottom"
    },
    {
      "type": "printed",
      "content": "Public Records Request No.: 17-295",
      "position": "footer"
    },
    {
      "type": "handwritten",
      "content": "07/26/17 DOJ-OGR-00030539",
      "position": "footer"
    }
  ],
  "entities": {
    "people": [
      "Jeffrey Epstein",
      "Theodore J. Leopold",
      "Lanna Belohlavek",
      "Jeffrey Herman",
      "Jack A. Goldberger"
    ],
    "organizations": [
      "Office of the State Attorney",
      "Consor & Associates",
      "ATTERBURY, GOLDBERGER, & WEISS, P.A."
    ],
    "locations": [
      "Palm Beach County",
      "Florida",
      "West Palm Beach",
      "Palm Beach Gardens",
      "Miami"
    ],
    "dates": [
      "February 20, 2008",
      "February 8, 2008",
      "07/26/17"
    ],
    "reference_numbers": [
      "2006CF009454AXX",
      "17-295",
      "DOJ-OGR-00030539",
      "262013"
    ]
  },
  "additional_notes": "The document appears to be a Notice of Deposition in a court case involving Jeffrey Epstein. The document is mostly printed, but contains some handwritten elements, including a signature and a date stamp. The document is in good condition, with no visible redactions or damage."
}