{
  "document_metadata": {
    "page_number": "13 of 14",
    "document_number": "17-295",
    "date": "07/26/17",
    "document_type": "Public Records Request",
    "has_handwriting": false,
    "has_stamps": false
  },
  "full_text": "www.myspace.com/dixiedelight5 Page 13 of 14 out So call me Whenever you get time!! I'm glad your doing so well!!! DONT CHA WISH YOUR GIRLFRIEND WAS HOT LIKE ME 1/24/2006 11:02 AM SO I GUESS YOU FORGOT ABOUT TOGETHER...... AND HOW COME I ALWAYS SEE AND COMMENTS AND YOU NEVER WRITE ME ANYTHING?? LATER TODAY I WILL CHECK IN AND HOPEFULLY I WILL HAVE YOU, MY SEXY FRIEND... LOVE Wow, I&love&Hym 1/24/2006 10:19 AM hey gurlie, how you been doing.... nothing rele much here just home fre and i didnt rele feel like going but ye you and you boyfriend will yeh hope and hope to see you on 4th of july lil xoxo love ya xoxo comment back w/ please xoxo \"Briana\" 1/24/2006 5:34 AM hey girl.. reds is looking for a waitre waitress before right??the money is too... just letting you know b/c if ya couldn't be better now\\hope everythi haaven't talk to u in a while! but let m u want it...xoxoxox I WANNA BE A COWBOYS SWEETHEART 1/23/2006 1:36 PM hey hunnie i thought i might stop by you and i am in ohio with danielle i w while how is everything goin? well t you 07/26/17 Page 80 of 81 Public Records Request No.: 17-295 http://profile.myspace.com/index.cfm?fuseaction=user.viewprofile&friendID=32653405 2/9/2006 DOJ-OGR-00031172",
  "text_blocks": [
    {
      "type": "printed",
      "content": "www.myspace.com/dixiedelight5",
      "position": "header"
    },
    {
      "type": "printed",
      "content": "Page 13 of 14",
      "position": "header"
    },
    {
      "type": "printed",
      "content": "DONT CHA WISH YOUR GIRLFRIEND WAS HOT LIKE ME",
      "position": "middle"
    },
    {
      "type": "printed",
      "content": "1/24/2006 11:02 AM",
      "position": "middle"
    },
    {
      "type": "printed",
      "content": "SO I GUESS YOU FORGOT ABOUT TOGETHER...... AND HOW COME I ALWAYS SEE AND COMMENTS AND YOU NEVER WRITE ME ANYTHING?? LATER TODAY I WILL CHECK IN AND HOPEFULLY I WILL HAVE YOU, MY SEXY FRIEND... LOVE",
      "position": "middle"
    },
    {
      "type": "printed",
      "content": "Wow, I&love&Hym",
      "position": "middle"
    },
    {
      "type": "printed",
      "content": "1/24/2006 10:19 AM",
      "position": "middle"
    },
    {
      "type": "printed",
      "content": "hey gurlie, how you been doing.... nothing rele much here just home fre and i didnt rele feel like going but ye you and you boyfriend will yeh hope and hope to see you on 4th of july lil xoxo love ya xoxo comment back w/ please xoxo",
      "position": "middle"
    },
    {
      "type": "printed",
      "content": "\"Briana\"",
      "position": "middle"
    },
    {
      "type": "printed",
      "content": "1/24/2006 5:34 AM",
      "position": "middle"
    },
    {
      "type": "printed",
      "content": "hey girl.. reds is looking for a waitre waitress before right??the money is too... just letting you know b/c if ya couldn't be better now\\hope everythi haaven't talk to u in a while! but let m u want it...xoxoxox",
      "position": "middle"
    },
    {
      "type": "printed",
      "content": "I WANNA BE A COWBOYS SWEETHEART",
      "position": "middle"
    },
    {
      "type": "printed",
      "content": "1/23/2006 1:36 PM",
      "position": "middle"
    },
    {
      "type": "printed",
      "content": "hey hunnie i thought i might stop by you and i am in ohio with danielle i w while how is everything goin? well t you",
      "position": "middle"
    },
    {
      "type": "printed",
      "content": "07/26/17",
      "position": "footer"
    },
    {
      "type": "printed",
      "content": "Page 80 of 81",
      "position": "footer"
    },
    {
      "type": "printed",
      "content": "Public Records Request No.: 17-295",
      "position": "footer"
    },
    {
      "type": "printed",
      "content": "http://profile.myspace.com/index.cfm?fuseaction=user.viewprofile&friendID=32653405",
      "position": "footer"
    },
    {
      "type": "printed",
      "content": "2/9/2006",
      "position": "footer"
    },
    {
      "type": "printed",
      "content": "DOJ-OGR-00031172",
      "position": "footer"
    }
  ],
  "entities": {
    "people": [
      "Briana",
      "Danielle"
    ],
    "organizations": [],
    "locations": [
      "Ohio"
    ],
    "dates": [
      "1/24/2006",
      "1/23/2006",
      "07/26/17",
      "2/9/2006"
    ],
    "reference_numbers": [
      "17-295",
      "32653405",
      "DOJ-OGR-00031172"
    ]
  },
  "additional_notes": "The document appears to be a printout of a Myspace conversation or profile, with various images and text. The text includes informal language and abbreviations typical of online communication in the early 2000s. The document has been stamped or annotated with a public records request number and date."
}