{
  "document_metadata": {
    "page_number": "7",
    "document_number": "J6-6702",
    "date": "01/21/2006",
    "document_type": "Incident Report",
    "has_handwriting": false,
    "has_stamps": false
  },
  "full_text": "Incident Report CHEROKEE COUNTY SHERIFF'S OFFICE J6-6702 DRAFT Reported Date 01/21/2006 Nature of Call Officer ALLEN, AUTUMN 498 CHATTIN DRIVE (678) 493-4200 Administrative Information Agency CHEROKEE COUNTY SHERIFF'S OFFICE Report No 06-6702 Supplement No 0001 Reported Date 01/21/2006 Reported Time 15:30 Officer 000284 / ALLEN, AUTUMN Assignment CID DAY SHIFT PERSONS UNIT Approving Officer  Assignment CID DAY SHIFT PERSONS UNIT Entered by 000284 Approval Time  Approval Date  Narrative On 012106 I was notified by dispatch to give B-43 a call. I called and spoke with D/S Ballard and he was taking a report of a missing juvenile age 15. He stated she was supposed to have went to a basketball game last night but she didn't. He stated she went off with some black males. He told they were stopped by some white friends of her and they fought with the black males. D/S Ballard said the mother had contact with her daughter around 8:00 last night but had not heard from her since then. Report Officer 000284 / ALLEN, AUTUMN Printed At 06/06/2006 11:12 Page 1 of 1 07/26/17 Page 7 of 95 Public Records Request No.: 17-295 DOJ-OGR-00031004",
  "text_blocks": [
    {
      "type": "printed",
      "content": "Incident Report CHEROKEE COUNTY SHERIFF'S OFFICE J6-6702 DRAFT Reported Date 01/21/2006 Nature of Call Officer ALLEN, AUTUMN 498 CHATTIN DRIVE (678) 493-4200",
      "position": "header"
    },
    {
      "type": "printed",
      "content": "Administrative Information",
      "position": "middle"
    },
    {
      "type": "printed",
      "content": "Narrative On 012106 I was notified by dispatch to give B-43 a call. I called and spoke with D/S Ballard and he was taking a report of a missing juvenile age 15. He stated she was supposed to have went to a basketball game last night but she didn't. He stated she went off with some black males. He told they were stopped by some white friends of her and they fought with the black males. D/S Ballard said the mother had contact with her daughter around 8:00 last night but had not heard from her since then.",
      "position": "middle"
    },
    {
      "type": "printed",
      "content": "Report Officer 000284 / ALLEN, AUTUMN Printed At 06/06/2006 11:12 Page 1 of 1 07/26/17 Page 7 of 95 Public Records Request No.: 17-295 DOJ-OGR-00031004",
      "position": "footer"
    }
  ],
  "entities": {
    "people": [
      "ALLEN, AUTUMN",
      "Ballard"
    ],
    "organizations": [
      "CHEROKEE COUNTY SHERIFF'S OFFICE"
    ],
    "locations": [
      "498 CHATTIN DRIVE"
    ],
    "dates": [
      "01/21/2006",
      "06/06/2006",
      "07/26/17",
      "01/21/06"
    ],
    "reference_numbers": [
      "J6-6702",
      "06-6702",
      "0001",
      "000284",
      "17-295",
      "DOJ-OGR-00031004"
    ]
  },
  "additional_notes": "The document is a draft incident report from the Cherokee County Sheriff's Office. It appears to be a scanned copy with some metadata at the bottom indicating it was printed on 06/06/2006 and is part of a public records request."
}