{
  "document_metadata": {
    "page_number": "20",
    "document_number": "17-295",
    "date": "07/26/17",
    "document_type": "Public Records Request",
    "has_handwriting": false,
    "has_stamps": false
  },
  "full_text": "1 MP: By yourself?\n2 Yes, but I thought that Haley, cause she said she was gonna get paid, so I thought Haley and the girl was gonna get paid in like, you know, like private, privacy and cause it was just him and her and the other girl in the kitchen. And so I went upstairs and as I was walking upstairs, there was a picture of him in like a different country and then I'm like that's really cool and the lady said isn't it and she was just walking upstairs and there was like a door and then, it was like to a little (inaudible) this big and it had a couch and a couch and it was like another walkway towards that way. And then walked towards, like keep walking forward and then to my right and there was a bedroom and then we turned right again and there was a big bathroom, a big...it was humongous. And the bathroom. It wasn't like a bathroom, bathroom, it was like a sitting area with a shower there. Humongous shower. Like a jillion people could be in that shower. And then it was humongous. And there was like a door here and you opened it and there was like a little desk with paper and pads and stuff. And I don't know (inaudible) like sitting on the couch right here, like against my... there's big long couch. And it was pink and green. Hot pink and green. And there....\n18 MP: The room or the sofa?\n19 The sofa.\n20 MP: Okay.\n21 And there's a table with a phone on it. And um, during when I was giving him a massage, he made a phone call but I don't remember whether he just said, like he said four words and then hung up. Yeah, I don't remember. And he made a\nPage 20 of 43\n07/26/17 Page 34 of 81 Public Records Request No.: 17-295 DOJ-OGR-00031126",
  "text_blocks": [
    {
      "type": "printed",
      "content": "1 MP: By yourself?\n2 Yes, but I thought that Haley, cause she said she was gonna get paid, so I thought Haley and the girl was gonna get paid in like, you know, like private, privacy and cause it was just him and her and the other girl in the kitchen. And so I went upstairs and as I was walking upstairs, there was a picture of him in like a different country and then I'm like that's really cool and the lady said isn't it and she was just walking upstairs and there was like a door and then, it was like to a little (inaudible) this big and it had a couch and a couch and it was like another walkway towards that way. And then walked towards, like keep walking forward and then to my right and there was a bedroom and then we turned right again and there was a big bathroom, a big...it was humongous. And the bathroom. It wasn't like a bathroom, bathroom, it was like a sitting area with a shower there. Humongous shower. Like a jillion people could be in that shower. And then it was humongous. And there was like a door here and you opened it and there was like a little desk with paper and pads and stuff. And I don't know (inaudible) like sitting on the couch right here, like against my... there's big long couch. And it was pink and green. Hot pink and green. And there....\n18 MP: The room or the sofa?\n19 The sofa.\n20 MP: Okay.\n21 And there's a table with a phone on it. And um, during when I was giving him a massage, he made a phone call but I don't remember whether he just said, like he said four words and then hung up. Yeah, I don't remember. And he made a",
      "position": "main content"
    },
    {
      "type": "printed",
      "content": "Page 20 of 43",
      "position": "footer"
    },
    {
      "type": "printed",
      "content": "07/26/17 Page 34 of 81 Public Records Request No.: 17-295",
      "position": "footer"
    },
    {
      "type": "printed",
      "content": "DOJ-OGR-00031126",
      "position": "footer"
    }
  ],
  "entities": {
    "people": [
      "Haley"
    ],
    "organizations": [
      "DOJ"
    ],
    "locations": [],
    "dates": [
      "07/26/17"
    ],
    "reference_numbers": [
      "17-295",
      "DOJ-OGR-00031126"
    ]
  },
  "additional_notes": "The document appears to be a transcript of an interview or testimony. There are some inaudible sections marked as '(inaudible)'. The document has a clear structure with numbered lines and a footer with page numbers and a reference number."
}