{
  "document_metadata": {
    "page_number": "2",
    "document_number": "17-295",
    "date": "4/4/2006",
    "document_type": "Public Records Request",
    "has_handwriting": false,
    "has_stamps": false
  },
  "full_text": "www.myspace.com/iloveanirishboi Page 2 of 10 Interests General i love shopping, tanning, hanging out with friends and playing volleyball sleeping in and being lazy Music I dont have a favorite I listen to all kinds!! Movies Name: Birthdate: Birthplace: Current Location: Eye Color: Hair Color: Height: Weight: Piercings: Tatoos: Boyfriend/Girlfriend: Overused Phraze: FAVO Food: Candy: Number: Color: Animal: Drink: Alcohol Drink: Bagel: Letter: Body Part on Opposite sex: This Pepsi or Coke: McDonalds or BurgerKing: Strawberry or 1'ce U Go ZaCk U DoNt Go BaK Is this 1-214 or what? View All of Friends Displaying 29 of 29 comments (View/Edit All Comments) lynds 3/31/2006 6:18 PM i miss u so much i want u to come back up here :( love ya lynds ~~~I CAN LOVE YOU BETTER!!!*~ 3/29/2006 4:24 PM He i miss you like crazy i wish you were here i hate cherokee it sucks balls ol...well newayz i cant wait until this summer it will be great CANT WIAT....well love ya babe Alwayz ((~\"Wonderful-Winslow~\")) Public Records Request No.: 17-295 4/4/2006 DOJ-OGR-00030402",
  "text_blocks": [
    {
      "type": "printed",
      "content": "www.myspace.com/iloveanirishboi",
      "position": "top"
    },
    {
      "type": "printed",
      "content": "Interests",
      "position": "middle"
    },
    {
      "type": "printed",
      "content": "General\ni love shopping, tanning, hanging out with friends and playing volleyball sleeping in and being lazy",
      "position": "middle"
    },
    {
      "type": "printed",
      "content": "Music\nI dont have a favorite I listen to all kinds!!",
      "position": "middle"
    },
    {
      "type": "printed",
      "content": "1'ce U Go ZaCk U DoNt Go BaK\nIs this 1-214 or what?",
      "position": "middle"
    },
    {
      "type": "printed",
      "content": "Displaying 29 of 29 comments (View/Edit All Comments)",
      "position": "middle"
    },
    {
      "type": "handwritten",
      "content": "lynds\n3/31/2006 6:18 PM\ni miss u so much i want u to come back up here :( love ya lynds",
      "position": "middle"
    },
    {
      "type": "handwritten",
      "content": "~I CAN LOVE YOU BETTER!!!*~\n3/29/2006 4:24 PM",
      "position": "middle"
    },
    {
      "type": "handwritten",
      "content": "He i miss you like crazy i wish you were here i hate cherokee it sucks balls ol...well newayz i cant wait until this summer it will be great CANT WIAT....well love ya babe Alwayz ((~\"Wonderful-Winslow~\"))",
      "position": "middle"
    },
    {
      "type": "printed",
      "content": "Public Records Request No.: 17-295",
      "position": "bottom"
    },
    {
      "type": "printed",
      "content": "4/4/2006",
      "position": "bottom"
    },
    {
      "type": "printed",
      "content": "DOJ-OGR-00030402",
      "position": "bottom"
    }
  ],
  "entities": {
    "people": [
      "lynds",
      "Wonderful-Winslow"
    ],
    "organizations": [
      "McDonalds",
      "BurgerKing"
    ],
    "locations": [
      "Cherokee"
    ],
    "dates": [
      "3/31/2006",
      "3/29/2006",
      "4/4/2006"
    ],
    "reference_numbers": [
      "17-295",
      "DOJ-OGR-00030402"
    ]
  },
  "additional_notes": "The document appears to be a printout of a MySpace profile page with comments and a public records request number. The text is mostly printed, with some handwritten comments. The document has been redacted in some areas."
}