{
  "document_metadata": {
    "page_number": "20",
    "document_number": "17-295",
    "date": "07/26/17",
    "document_type": "Plea in the Circuit Court",
    "has_handwriting": false,
    "has_stamps": false
  },
  "full_text": "PLEA IN THE CIRCUIT COURT THE FOLLOWING IS TO REFLECT ALL TERMS OF THE NEGOTIATED SETTLEMENT Name: Jefirey E. Epstein Plea: Guilty X Case No. Charge Count Lesser Degree 06CF009454AMB Felony Solicitation of Prostitution 1 No 3 FEL 08CF009381AMB Procuring Person Under 18 for Prostitution 1 No 2 FEL PSI: Waived/Not Required X Required/Requested ADJUDICATION: Adjudicate [x ] SENTENCE: On 06CF009454AMB, the Defendant is sentenced to 12 months in the Palm Beach County Detention Facility, with credit for 1 (one) day time served. On 08CF009381AMB, the Defendant is sentenced to 6 months in the Palm Beach County Detention Facility, with credit for 1 (one) day time served. This 6 month sentence is to be served consecutive to the 12 month sentence in 06CF009454AMB. Following this 6 month sentence, the Defendant will be placed on 12 months Community Control 1 (one). The conditions of community control are attached hereto and incorporated herein. OTHER COMMENTS OR CONDITIONS: As a special condition of his community control, the Defendant is to have no unsupervised contact with minors, and the supervising adult must be approved by the Department of Corrections. The Defendant is designated as a Sexual Offender pursuant to Florida Statute 943.0435 and must abide by all the corresponding requirements of the statute, a copy of which is attached hereto and incorporated herein. The Defendant must provide a DNA sample in court at the time of this plea. Assistant State Attorney Attorney for the Defendant Date of Plea Defendant 07/26/17 Page 20 of 114 Public Records Request No.: 17-295 DOJ-OGR-00030373",
  "text_blocks": [
    {
      "type": "printed",
      "content": "PLEA IN THE CIRCUIT COURT THE FOLLOWING IS TO REFLECT ALL TERMS OF THE NEGOTIATED SETTLEMENT",
      "position": "header"
    },
    {
      "type": "printed",
      "content": "Name: Jefirey E. Epstein Plea: Guilty X",
      "position": "top"
    },
    {
      "type": "printed",
      "content": "Case No. Charge Count Lesser Degree 06CF009454AMB Felony Solicitation of Prostitution 1 No 3 FEL 08CF009381AMB Procuring Person Under 18 for Prostitution 1 No 2 FEL",
      "position": "top"
    },
    {
      "type": "printed",
      "content": "PSI: Waived/Not Required X Required/Requested ADJUDICATION: Adjudicate [x ]",
      "position": "middle"
    },
    {
      "type": "printed",
      "content": "SENTENCE: On 06CF009454AMB, the Defendant is sentenced to 12 months in the Palm Beach County Detention Facility, with credit for 1 (one) day time served. On 08CF009381AMB, the Defendant is sentenced to 6 months in the Palm Beach County Detention Facility, with credit for 1 (one) day time served. This 6 month sentence is to be served consecutive to the 12 month sentence in 06CF009454AMB. Following this 6 month sentence, the Defendant will be placed on 12 months Community Control 1 (one). The conditions of community control are attached hereto and incorporated herein.",
      "position": "middle"
    },
    {
      "type": "printed",
      "content": "OTHER COMMENTS OR CONDITIONS: As a special condition of his community control, the Defendant is to have no unsupervised contact with minors, and the supervising adult must be approved by the Department of Corrections. The Defendant is designated as a Sexual Offender pursuant to Florida Statute 943.0435 and must abide by all the corresponding requirements of the statute, a copy of which is attached hereto and incorporated herein. The Defendant must provide a DNA sample in court at the time of this plea.",
      "position": "middle"
    },
    {
      "type": "printed",
      "content": "Assistant State Attorney Attorney for the Defendant Date of Plea Defendant",
      "position": "bottom"
    },
    {
      "type": "printed",
      "content": "07/26/17 Page 20 of 114 Public Records Request No.: 17-295 DOJ-OGR-00030373",
      "position": "footer"
    }
  ],
  "entities": {
    "people": [
      "Jefirey E. Epstein"
    ],
    "organizations": [
      "Department of Corrections"
    ],
    "locations": [
      "Palm Beach County"
    ],
    "dates": [
      "07/26/17"
    ],
    "reference_numbers": [
      "06CF009454AMB",
      "08CF009381AMB",
      "17-295",
      "943.0435",
      "DOJ-OGR-00030373"
    ]
  },
  "additional_notes": "The document appears to be a plea agreement for Jefirey E. Epstein, with handwritten marks indicating guilty pleas and adjudication. The document is from a public records request and has a page number and request number at the bottom."
}