{
  "document_metadata": {
    "page_number": "0003",
    "document_number": "DOJ-OGR-00028197",
    "date": "04282014",
    "document_type": "TECSII - PRIMARY QUERY HISTORY PASSENGER ACTIVITY",
    "has_handwriting": false,
    "has_stamps": false
  },
  "full_text": "08:07 TECSII - PRIMARY QUERY HISTORY 04282014 *A *B PASSENGER ACTIVITY *C PAGE NO. 0003 NAME DOB QUERY ---- DATE TIME AGN ---- LNE TERM/ RS LT TYP REF LANE API DIM EPSTEIN, JEFFREY 012053 031913 0804 CUS *D AIR EY09 N N A512-CBP-ST THOMAS, VI PRECL DOC: 46991107 US P INSP: *E EPSTEIN, JEFFREY 012053 021413 0729 CUS *F AIR CUS EY10 N N A512-CBP-ST THOMAS, VI PRECL DOC: 46991107 US P INSP: *G EPSTEIN, JEFFREY 012053 011013 1138 CUS *H AIR CUS EY10 N N A512-CBP-ST THOMAS, VI PRECL DOC: 46991107 US P INSP: *I EPSTEIN, JEFFREY 012053 111512 1433 CUS *J AIR CUS EY09 N N A512-CBP-ST THOMAS, VI PRECL DOC: 46991107 US P INSP: *K EPSTEIN, JEFFREY 012053 112712 0000 *L API 01 R N PARIS, CH. DE GAULLE DOC: INSP: APIS QRY EPSTEIN, JEFFREY 012053 100612 1516 CUS *M AIR EY06 N N A512-CBP-ST THOMAS, VI PRECL DOC: 46991107 US P INSP: *N (b)(7)(E) (b)(7)(E) (b)(7)(E) (b)(7)(E) <...MORE...> (b)(7)(E) (b)(7)(E) (b)(7)(E) (b)(7)(E) Key: *A - (b)(7)(E) *B - (b)(6), (b)(7)(C) *C - (b)(7)(E) *D - (b)(7)(E) *E - (b)(6), (b)(7)(C) *F - (b)(7)(E) *G - (b)(6), (b)(7)(C) *H - (b)(7)(E) *I - (b)(6), (b)(7)(C) *J - (b)(7)(E) *K - (b)(6), (b)(7)(C) *L - (b)(7)(E) *M - (b)(7)(E) *N - (b)(6), (b)(7)(C) DOJ-OGR-00028197",
  "text_blocks": [
    {
      "type": "printed",
      "content": "TECSII - PRIMARY QUERY HISTORY PASSENGER ACTIVITY",
      "position": "header"
    },
    {
      "type": "printed",
      "content": "PAGE NO. 0003",
      "position": "header"
    },
    {
      "type": "printed",
      "content": "NAME DOB QUERY ---- DATE TIME AGN ---- LNE TERM/ RS LT TYP REF LANE API DIM",
      "position": "header"
    },
    {
      "type": "printed",
      "content": "EPSTEIN, JEFFREY 012053 031913 0804 CUS *D AIR EY09 N N A512-CBP-ST THOMAS, VI PRECL DOC: 46991107 US P INSP: *E",
      "position": "body"
    },
    {
      "type": "printed",
      "content": "Key: *A - (b)(7)(E) *B - (b)(6), (b)(7)(C) *C - (b)(7)(E) *D - (b)(7)(E) *E - (b)(6), (b)(7)(C) *F - (b)(7)(E) *G - (b)(6), (b)(7)(C) *H - (b)(7)(E) *I - (b)(6), (b)(7)(C) *J - (b)(7)(E) *K - (b)(6), (b)(7)(C) *L - (b)(7)(E) *M - (b)(7)(E) *N - (b)(6), (b)(7)(C)",
      "position": "footer"
    },
    {
      "type": "printed",
      "content": "DOJ-OGR-00028197",
      "position": "footer"
    }
  ],
  "entities": {
    "people": [
      "JEFFREY EPSTEIN",
      "THOMAS",
      "CH. DE GAULLE"
    ],
    "organizations": [
      "CBP"
    ],
    "locations": [
      "PARIS"
    ],
    "dates": [
      "031913",
      "021413",
      "011013",
      "111512",
      "112712",
      "100612",
      "04282014"
    ],
    "reference_numbers": [
      "46991107",
      "DOJ-OGR-00028197"
    ]
  },
  "additional_notes": "The document contains redacted information marked as (b)(6), (b)(7)(C), and (b)(7)(E). The document appears to be a query history for a passenger activity report."
}