{
  "document_metadata": {
    "page_number": null,
    "document_number": "DOJ-OGR-00028720",
    "date": "042814",
    "document_type": "PQH API/HIT DATA",
    "has_handwriting": false,
    "has_stamps": false
  },
  "full_text": "08:08 PQH API/HIT DATA 042814 *B *A *C NAME EPSTEIN, JEFFREY E BFI -BOEING FLD INTL DOB 012053 DATE TIME AGN RSLT TYP REF TERM/ LANE API 032014 0000 CUS *D API C US P INSP: *E DOC: 469911707 API DATA ---- API INDICATOR : C CONFIRMED CARRIER CODE : *GA GENERAL AVIATION FLT/VES NUMBER : N212JE ARRIVAL LOCATION : BFI BOEING FLD INTL DEPARTURE LOCATION : XXX UNKNOWN AIRPORT (USED ON TRANSMITTED BY : APGA928N GENERAL AVIATION INBOUND/OUTBOUND : INBOUND (b) (7) (E) Key: *A - (b) (7) (E) *B - (b) (6), (b) (7) (C) *C - (b) (7) (E) *D - (b) (7) (E) *E - (b) (7), (b) (7) (C) (b) (7) (E) DOJ-OGR-00028720",
  "text_blocks": [
    {
      "type": "printed",
      "content": "08:08 PQH API/HIT DATA 042814",
      "position": "header"
    },
    {
      "type": "printed",
      "content": "NAME EPSTEIN, JEFFREY E BFI -BOEING FLD INTL",
      "position": "middle"
    },
    {
      "type": "printed",
      "content": "API DATA ----",
      "position": "middle"
    },
    {
      "type": "printed",
      "content": "Key:",
      "position": "middle"
    },
    {
      "type": "printed",
      "content": "DOJ-OGR-00028720",
      "position": "footer"
    }
  ],
  "entities": {
    "people": [
      "JEFFREY E EPSTEIN"
    ],
    "organizations": [
      "BOEING"
    ],
    "locations": [
      "BOEING FLD INTL",
      "BFI"
    ],
    "dates": [
      "032014",
      "042814"
    ],
    "reference_numbers": [
      "469911707",
      "N212JE",
      "APGA928N",
      "DOJ-OGR-00028720"
    ]
  },
  "additional_notes": "The document contains redacted information marked with (b) (6), (b) (7) (C), and (b) (7) (E)."
}