{
  "document_metadata": {
    "page_number": "16",
    "document_number": "17-295",
    "date": "07/26/17",
    "document_type": "transcription",
    "has_handwriting": false,
    "has_stamps": false
  },
  "full_text": "1 and the bedroom?\n2 A. Yes. That was 2001. Before that, we had\n3 an apartment upstairs in their house, in the main house.\n4 Q. In the little rooms upstairs across from\n5 his master bedroom?\n6 A. Right.\n7 Q. Was there ever any photographs that you can\n8 recall around the house?\n9 A. Girls, girls' photographs and guests'\n10 photographs, yes.\n11 Q. Were they dressed or were they naked?\n12 A. Most of them were dressed. It was a lot of\n13 entertainment in the pool, around the pool area. But\n14 most of them were dressed.\n15 Q. When was the last time you spoke with\n16 Mr. Epstein?\n17 A. The last time I spoke with Mr. Epstein was\n18 about a week ago, when you left me the card. I got\n19 scared because of that fallout that we had, and I thought\n20 it was a consequence of that. And I called and says,\n21 Jeffrey, what's going on, what's happening? Because I\n22 thought it was an investigation against me on his part.\n23 Q. I'm sorry if I gave you that impression.\n24 A. That's why I called him. That's the only\n25 reason that I called.\n\nJ. CONSOR & ASSOCIATES REPORTING & TRANSCRIPTION\n561.835.9738\nPage 96 of 131 Public Records Request No.: 17-295 DOJ-OGR-00030563",
  "text_blocks": [
    {
      "type": "printed",
      "content": "1 and the bedroom?\n2 A. Yes. That was 2001. Before that, we had\n3 an apartment upstairs in their house, in the main house.\n4 Q. In the little rooms upstairs across from\n5 his master bedroom?\n6 A. Right.\n7 Q. Was there ever any photographs that you can\n8 recall around the house?\n9 A. Girls, girls' photographs and guests'\n10 photographs, yes.\n11 Q. Were they dressed or were they naked?\n12 A. Most of them were dressed. It was a lot of\n13 entertainment in the pool, around the pool area. But\n14 most of them were dressed.\n15 Q. When was the last time you spoke with\n16 Mr. Epstein?\n17 A. The last time I spoke with Mr. Epstein was\n18 about a week ago, when you left me the card. I got\n19 scared because of that fallout that we had, and I thought\n20 it was a consequence of that. And I called and says,\n21 Jeffrey, what's going on, what's happening? Because I\n22 thought it was an investigation against me on his part.\n23 Q. I'm sorry if I gave you that impression.\n24 A. That's why I called him. That's the only\n25 reason that I called.",
      "position": "main"
    },
    {
      "type": "printed",
      "content": "J. CONSOR & ASSOCIATES REPORTING & TRANSCRIPTION\n561.835.9738",
      "position": "footer"
    },
    {
      "type": "printed",
      "content": "Page 96 of 131 Public Records Request No.: 17-295 DOJ-OGR-00030563",
      "position": "footer"
    },
    {
      "type": "printed",
      "content": "Page 16",
      "position": "header"
    }
  ],
  "entities": {
    "people": [
      "Jeffrey",
      "Mr. Epstein"
    ],
    "organizations": [
      "J. Consor & Associates Reporting & Transcription"
    ],
    "locations": [],
    "dates": [
      "2001",
      "07/26/17"
    ],
    "reference_numbers": [
      "17-295",
      "DOJ-OGR-00030563"
    ]
  },
  "additional_notes": "The document appears to be a transcription of an interview or testimony. The content is related to a conversation about Mr. Epstein and his activities. The document is from a public records request."
}