{
  "document_metadata": {
    "page_number": "0004",
    "document_number": "DOJ-OGR-00028198",
    "date": "04282014",
    "document_type": "TECSII - PRIMARY QUERY HISTORY PASSENGER ACTIVITY",
    "has_handwriting": false,
    "has_stamps": false
  },
  "full_text": "08:07 TECSII - PRIMARY QUERY HISTORY 04282014 *A *B PASSENGER ACTIVITY *C PAGE NO. 0004 NAME DOB DATE TIME AGN RSLT TYP REF LANE TERM/ API DIM EPSTEIN, JEFFREY 012053 100812 0000 *D API 01 R N PARIS, ORLY DOC: US INSP: APIS QRY EPSTEIN, JEFFREY 012053 090612 1541 CUS *E AIR CUS EY07 N N A512-CBP-ST THOMAS, VI PRECL DOC: 46991107 US P INSP: *F EPSTEIN, JEFFREY 012053 072112 1511 CUS *G AIR CUS EY08 N N A512-CBP-ST THOMAS, VI PRECL DOC: 46991107 US P INSP: *H EPSTEIN, JEFFREY 012053 061712 1522 CUS *I AIR EY12 N N A512-CBP-ST THOMAS, VI PRECL DOC: 46991107 US P INSP: *J EPSTEIN, JEFFREY 012053 050312 1501 CUS *K AIR EY11 N N A512-CBP-ST THOMAS, VI PRECL DOC: 46991107 US P INSP: *L EPSTEIN, JEFFREY 012053 051112 0000 *M API 01 R N PARIS, ORLY DOC: US INSP: APIS QRY (b)(7)(E) <...MORE...> (b)(7)(E) (b)(7)(E) (b)(7)(E) (b)(7)(E) (b)(7)(E) (b)(7)(E) (b)(7)(E) Key: *A - (b)(7)(E) *B - (b)(6), (b)(7)(C) *C - (b)(7)(E) *D - (b)(7)(E) *E - (b)(7)(E) *F - (b)(6), (b)(7)(C) *G - (b)(7)(E) *H - (b)(6), (b)(7)(C) *I - (b)(7)(E) *J - (b)(6), (b)(7)(C) *K - (b)(7)(E) *L - (b)(6), (b)(7)(C) *M - (b)(7)(E) DOJ-OGR-00028198",
  "text_blocks": [
    {
      "type": "printed",
      "content": "TECSII - PRIMARY QUERY HISTORY PASSENGER ACTIVITY",
      "position": "header"
    },
    {
      "type": "printed",
      "content": "PAGE NO. 0004",
      "position": "header"
    },
    {
      "type": "printed",
      "content": "NAME DOB DATE TIME AGN RSLT TYP REF LANE TERM/ API DIM",
      "position": "middle"
    },
    {
      "type": "printed",
      "content": "EPSTEIN, JEFFREY 012053 100812 0000 *D API 01 R N PARIS, ORLY DOC: US INSP: APIS QRY",
      "position": "middle"
    },
    {
      "type": "printed",
      "content": "Key:",
      "position": "middle"
    },
    {
      "type": "printed",
      "content": "*A - (b)(7)(E) *B - (b)(6), (b)(7)(C) *C - (b)(7)(E) *D - (b)(7)(E) *E - (b)(7)(E) *F - (b)(6), (b)(7)(C) *G - (b)(7)(E) *H - (b)(6), (b)(7)(C) *I - (b)(7)(E) *J - (b)(6), (b)(7)(C) *K - (b)(7)(E) *L - (b)(6), (b)(7)(C) *M - (b)(7)(E)",
      "position": "middle"
    },
    {
      "type": "printed",
      "content": "DOJ-OGR-00028198",
      "position": "footer"
    }
  ],
  "entities": {
    "people": [
      "JEFFREY EPSTEIN",
      "ORLY PARIS"
    ],
    "organizations": [],
    "locations": [
      "PARIS"
    ],
    "dates": [
      "100812",
      "090612",
      "072112",
      "061712",
      "050312",
      "051112",
      "04282014"
    ],
    "reference_numbers": [
      "46991107",
      "DOJ-OGR-00028198"
    ]
  },
  "additional_notes": "The document appears to be a redacted TECSII query history report. Multiple redactions are present throughout the document, marked as (b)(7)(E) and (b)(6), (b)(7)(C)."
}