{
  "document_metadata": {
    "page_number": "22",
    "document_number": "DOJ-OGR-00028881",
    "date": "07/23/2019",
    "document_type": "TECS - Person Query",
    "has_handwriting": false,
    "has_stamps": false
  },
  "full_text": "U.S. Customs and Border Protection U.S. Department of Homeland Security TECS - Person Query Generated By: (b)(6),(b)(7)(C) Interpol Washington 07/23/2019 06:41 AM EDT Page 22 of 26 TECS RECORD ID (b)(7)(E) IMAGE INFORMATION - PART I (0) PERSON SUBJECT QUERY DETAILS INFORMATION Tecs Record ID (b)(7)(E) Entry Date 07/07/2019 Update Date 07/07/2019 Record Status (b)(7)(E) Category Query Notification (b)(7)(E) Primary Action 0 - NOT ON PRIMARY Start Date Stop Date Last Name EPSTEIN First Name JEFFREY Middle Name EDWARD Alias (0) Approval Status Hispanic Indicator N - NOT OF HISPANIC OR LATINO ORIGIN Date of Birth (1) 1) 01/20/1953 (66 years old) Race (1) 1) W - WHITE Gender (1) 1) MALE REMARKS INFORMATION (1) No Date Remarks 1 07/07/2019 (b)(7)(E) (b)(7)(E) PERSONAL DATA INFORMATION Nickname (0) Hair (0) Eyes (0) Height Weight Units Scars/Marks/Tattoos ENGLISH PERSONAL IDENTIFICATION INFORMATION Citizenship (1) 1) USA - UNITED STATES SSN (0) Residency Status BIRTH PLACE INFORMATION (0) ALIEN INFORMATION (0) EXCLUSION INFORMATION (0) PASSPORT INFORMATION (0) For Official Use Only / Law Enforcement Sensitive DOJ-OGR-00028881",
  "text_blocks": [
    {
      "type": "printed",
      "content": "U.S. Customs and Border Protection U.S. Department of Homeland Security TECS - Person Query",
      "position": "header"
    },
    {
      "type": "printed",
      "content": "Generated By: (b)(6),(b)(7)(C) Interpol Washington",
      "position": "header"
    },
    {
      "type": "printed",
      "content": "07/23/2019 06:41 AM EDT Page 22 of 26",
      "position": "header"
    },
    {
      "type": "printed",
      "content": "TECS RECORD ID (b)(7)(E)",
      "position": "body"
    },
    {
      "type": "printed",
      "content": "PERSON SUBJECT QUERY DETAILS INFORMATION",
      "position": "body"
    },
    {
      "type": "printed",
      "content": "Tecs Record ID (b)(7)(E) Entry Date 07/07/2019 Update Date 07/07/2019",
      "position": "body"
    },
    {
      "type": "printed",
      "content": "Record Status (b)(7)(E) Category",
      "position": "body"
    },
    {
      "type": "printed",
      "content": "Query Notification (b)(7)(E)",
      "position": "body"
    },
    {
      "type": "printed",
      "content": "Primary Action 0 - NOT ON PRIMARY Start Date Stop Date",
      "position": "body"
    },
    {
      "type": "printed",
      "content": "Last Name EPSTEIN First Name JEFFREY Middle Name EDWARD",
      "position": "body"
    },
    {
      "type": "printed",
      "content": "Alias (0) Approval Status Hispanic Indicator N - NOT OF HISPANIC OR LATINO ORIGIN",
      "position": "body"
    },
    {
      "type": "printed",
      "content": "Date of Birth (1) 1) 01/20/1953 (66 years old) Race (1) 1) W - WHITE Gender (1) 1) MALE",
      "position": "body"
    },
    {
      "type": "printed",
      "content": "REMARKS INFORMATION (1)",
      "position": "body"
    },
    {
      "type": "printed",
      "content": "No Date Remarks 1 07/07/2019 (b)(7)(E) (b)(7)(E)",
      "position": "body"
    },
    {
      "type": "printed",
      "content": "PERSONAL DATA INFORMATION",
      "position": "body"
    },
    {
      "type": "printed",
      "content": "Nickname (0) Hair (0) Eyes (0)",
      "position": "body"
    },
    {
      "type": "printed",
      "content": "Height Weight Units Scars/Marks/Tattoos ENGLISH",
      "position": "body"
    },
    {
      "type": "printed",
      "content": "PERSONAL IDENTIFICATION INFORMATION",
      "position": "body"
    },
    {
      "type": "printed",
      "content": "Citizenship (1) 1) USA - UNITED STATES SSN (0) Residency Status",
      "position": "body"
    },
    {
      "type": "printed",
      "content": "BIRTH PLACE INFORMATION (0) ALIEN INFORMATION (0) EXCLUSION INFORMATION (0) PASSPORT INFORMATION (0)",
      "position": "body"
    },
    {
      "type": "printed",
      "content": "For Official Use Only / Law Enforcement Sensitive",
      "position": "footer"
    },
    {
      "type": "printed",
      "content": "DOJ-OGR-00028881",
      "position": "footer"
    }
  ],
  "entities": {
    "people": [
      "JEFFREY EDWARD EPSTEIN"
    ],
    "organizations": [
      "U.S. Customs and Border Protection",
      "U.S. Department of Homeland Security",
      "Interpol Washington"
    ],
    "locations": [
      "USA",
      "United States"
    ],
    "dates": [
      "07/23/2019",
      "07/07/2019",
      "01/20/1953"
    ],
    "reference_numbers": [
      "DOJ-OGR-00028881",
      "(b)(7)(E)"
    ]
  },
  "additional_notes": "The document contains redacted information marked as '(b)(7)(E)' and '(b)(6),(b)(7)(C)'. The document is labeled 'For Official Use Only / Law Enforcement Sensitive'."
}