{
  "document_metadata": {
    "page_number": null,
    "document_number": "DOJ-OGR-00028679",
    "date": "08/02/2010",
    "document_type": "IO95 Inspection Results",
    "has_handwriting": false,
    "has_stamps": false
  },
  "full_text": "08:08:02 IO95 Inspection Results 042814 *A *B A461 TETERBORO, AIRP FLT/VES#: *UU 909JE U.S. CARRIER UNKNOWN DOCTYP*: P #*: 469911707 CTRY*: US UNITED STATES ST: M/F: M DNAME (LAST) : EPSTEIN FRST: JEFFREY EDWARD DOB: 012053 RFRD BY: *D -CBP OFFCR-C DTE: 08022010 TME: 2045 REASON: (b)(7)(E) CCD:*E (b)(7)(E) SNAME (LAST) : FRST: NO FIN NUMBER NATIONALITY: US UNITED STATES DOB: DISP: USC U.S. CITIZEN RCPT#: AUDATE: CHARGE (CODED) : FIN#: DFRD TO: SEC OFCR: *F -CBP OFFCR-C 08/02/2010 20:53 IOEM#: REFR CDE: COMMENTS: VIOLS: (b)(7)(E) ISE ADMISSIBLE. OTHERW WHTI CMPLNT? ADDL COMMTS: (b)(7)(E) *G (b)(7)(E) (b)(7)(E) (b)(7)(E) (b)(7)(E) *H *I Key: *A - (b)(7)(E) *B - (b)(6), (b)(7)(C) *C - (b)(7)(E) *D - (b)(6) (b)(7)(C) *E - (b)(7)(E) *F - (b)(6) (b)(7)(C) *G - (b)(7)(E) *H - (b)(7)(E) *I - (b)(7)(E)",
  "text_blocks": [
    {
      "type": "printed",
      "content": "08:08:02 IO95 Inspection Results 042814",
      "position": "top"
    },
    {
      "type": "printed",
      "content": "*B A461 TETERBORO, AIRP FLT/VES#: *UU 909JE U.S. CARRIER UNKNOWN DOCTYP*: P #*: 469911707 CTRY*: US UNITED STATES ST: M/F: M",
      "position": "top"
    },
    {
      "type": "printed",
      "content": "DNAME (LAST) : EPSTEIN FRST: JEFFREY EDWARD DOB: 012053 RFRD BY: *D -CBP OFFCR-C DTE: 08022010 TME: 2045 REASON: (b)(7)(E) CCD:*E (b)(7)(E)",
      "position": "top"
    },
    {
      "type": "printed",
      "content": "SNAME (LAST) : FRST: NO FIN NUMBER NATIONALITY: US UNITED STATES DOB: DISP: USC U.S. CITIZEN RCPT#: AUDATE: CHARGE (CODED) : FIN#: DFRD TO: SEC OFCR: *F -CBP OFFCR-C 08/02/2010 20:53 IOEM#: REFR CDE: COMMENTS: VIOLS: (b)(7)(E) ISE ADMISSIBLE. OTHERW",
      "position": "middle"
    },
    {
      "type": "printed",
      "content": "WHTI CMPLNT? ADDL COMMTS: (b)(7)(E)",
      "position": "middle"
    },
    {
      "type": "printed",
      "content": "*G (b)(7)(E) (b)(7)(E) (b)(7)(E) (b)(7)(E) *H *I Key: *A - (b)(7)(E) *B - (b)(6), (b)(7)(C) *C - (b)(7)(E) *D - (b)(6) (b)(7)(C) *E - (b)(7)(E) *F - (b)(6) (b)(7)(C) *G - (b)(7)(E) *H - (b)(7)(E) *I - (b)(7)(E)",
      "position": "bottom"
    },
    {
      "type": "printed",
      "content": "DOJ-OGR-00028679",
      "position": "footer"
    }
  ],
  "entities": {
    "people": [
      "JEFFREY EDWARD EPSTEIN"
    ],
    "organizations": [
      "CBP"
    ],
    "locations": [
      "TETERBORO",
      "UNITED STATES"
    ],
    "dates": [
      "08/02/2010",
      "08022010",
      "012053"
    ],
    "reference_numbers": [
      "469911707",
      "UU 909JE",
      "DOJ-OGR-00028679"
    ]
  },
  "additional_notes": "The document contains multiple redactions marked as '(b)(7)(E)' and '(b)(6)'. The document appears to be an inspection result related to an individual, JEFFREY EDWARD EPSTEIN, who was referred by a CBP officer."
}