{
  "document_metadata": {
    "page_number": "13",
    "document_number": "17-295",
    "date": "07/26/17",
    "document_type": "transcript",
    "has_handwriting": false,
    "has_stamps": false
  },
  "full_text": "1 talking to that lady and the lady was like, Haley, Haley was actually saying I'm coming, I'm coming, and Haley was like, can I bring somebody? And then Haley was like, the lady was like what does she look like and she started describing me and then Zack turned around and said to Haley who are you talking to. And then Haley went like that and she was talking to the lady and like just describing me, what I was wearing that night and then the lady was like okay, well Jeff is gonna want to talk to you and Haley was like, that's fine. And then she got off the phone and then Zack said, I was like too, why are you describing me, who are you talking to. And she was like Saige, do you want to go with me tomorrow, I'm gonna go pick up some money from my boss's house. And then she's like, cause I get paid tomorrow and then I said okay. And Zack's like no because I guess Zack knew what she did because Zack said no and he got really mad at me and said no, you're not going, you're not going with her. And then I was like, and she's like, you know, but you just have to come with me and I was like cause the old man's gonna give us both money so we can go shopping. Cause that's like my boss and he's really nice. And I was like okay. And then Zack didn't say anything the rest of the night about it, he was just like really (inaudible) out there and mad. Not really mad but he was just like frustrated that Haley, I guess, would say that.\nMP: And you didn't know what was really going on.\nI didn't know it was gonna, that I had to give him a massage and get naked.\nMP: What did you think was going to happen?\nThat, like she just said, I don't know but I knew something was wrong, nobody's\nPage 13 of 43\n07/26/17 Page 27 of 81 Public Records Request No.: 17-295 DOJ-OGR-00031119",
  "text_blocks": [
    {
      "type": "printed",
      "content": "1 talking to that lady and the lady was like, Haley, Haley was actually saying I'm coming, I'm coming, and Haley was like, can I bring somebody? And then Haley was like, the lady was like what does she look like and she started describing me and then Zack turned around and said to Haley who are you talking to. And then Haley went like that and she was talking to the lady and like just describing me, what I was wearing that night and then the lady was like okay, well Jeff is gonna want to talk to you and Haley was like, that's fine. And then she got off the phone and then Zack said, I was like too, why are you describing me, who are you talking to. And she was like Saige, do you want to go with me tomorrow, I'm gonna go pick up some money from my boss's house. And then she's like, cause I get paid tomorrow and then I said okay. And Zack's like no because I guess Zack knew what she did because Zack said no and he got really mad at me and said no, you're not going, you're not going with her. And then I was like, and she's like, you know, but you just have to come with me and I was like cause the old man's gonna give us both money so we can go shopping. Cause that's like my boss and he's really nice. And I was like okay. And then Zack didn't say anything the rest of the night about it, he was just like really (inaudible) out there and mad. Not really mad but he was just like frustrated that Haley, I guess, would say that.",
      "position": "top"
    },
    {
      "type": "printed",
      "content": "MP: And you didn't know what was really going on.",
      "position": "middle"
    },
    {
      "type": "printed",
      "content": "I didn't know it was gonna, that I had to give him a massage and get naked.",
      "position": "middle"
    },
    {
      "type": "printed",
      "content": "MP: What did you think was going to happen?",
      "position": "middle"
    },
    {
      "type": "printed",
      "content": "That, like she just said, I don't know but I knew something was wrong, nobody's",
      "position": "middle"
    },
    {
      "type": "printed",
      "content": "Page 13 of 43",
      "position": "footer"
    },
    {
      "type": "printed",
      "content": "07/26/17 Page 27 of 81 Public Records Request No.: 17-295",
      "position": "footer"
    },
    {
      "type": "printed",
      "content": "DOJ-OGR-00031119",
      "position": "footer"
    }
  ],
  "entities": {
    "people": [
      "Haley",
      "Zack",
      "Jeff",
      "Saige"
    ],
    "organizations": [
      "DOJ"
    ],
    "locations": [],
    "dates": [
      "07/26/17"
    ],
    "reference_numbers": [
      "17-295",
      "DOJ-OGR-00031119"
    ]
  },
  "additional_notes": "The document appears to be a transcript of an interview or testimony. The text is mostly printed, with some indication of speaker changes (e.g., 'MP:'). The content discusses a conversation between the speaker and others, including Haley and Zack. The tone is informal, and the language is conversational. There are no visible stamps or handwritten annotations."
}