{
  "document_metadata": {
    "page_number": "33",
    "document_number": "17-295",
    "date": "11/14/2005",
    "document_type": "Public Records Request",
    "has_handwriting": false,
    "has_stamps": false
  },
  "full_text": "myspace.com Page 1 of 15 <33 YellowBeetIE (on Hiatus) Aug 22, 2005 1:12 PM Havent said hi yet. so Howdy 'Lord of the Fire' Aug 19, 2005 12:41 PM Hey what's the 411 on the party??? Beef Knuckles Aug 18, 2005 11:16 AM Yoooooooo just figured i'd say whats up since it says you're online now. holla fuck this city in your mouth Aug 16, 2005 12:35 PM word up nigga. Snipsnap in yo bubble wrap Dane Aug 10, 2005 12:27 PM wats up. Its your boy Dane, hey lets smoke soon. Alright hit me back. amy lynn. Aug 9, 2005 12:31 PM hey. peekaboos was fun. when are you leaving?? http://www.myspace.com/index.cfm?fuseaction=user.viewComments&friendID=204256... 11/14/2005 07/26/17 Page 33 of 125 Public Records Request No.: 17-295 DOJ-OGR-00030833",
  "text_blocks": [
    {
      "type": "printed",
      "content": "myspace.com",
      "position": "header"
    },
    {
      "type": "printed",
      "content": "Page 1 of 15",
      "position": "header"
    },
    {
      "type": "printed",
      "content": "<33",
      "position": "top"
    },
    {
      "type": "printed",
      "content": "YellowBeetIE (on Hiatus) Aug 22, 2005 1:12 PM Havent said hi yet. so Howdy",
      "position": "top"
    },
    {
      "type": "printed",
      "content": "'Lord of the Fire' Aug 19, 2005 12:41 PM Hey what's the 411 on the party???",
      "position": "middle"
    },
    {
      "type": "printed",
      "content": "Beef Knuckles Aug 18, 2005 11:16 AM Yoooooooo just figured i'd say whats up since it says you're online now. holla",
      "position": "middle"
    },
    {
      "type": "printed",
      "content": "fuck this city in your mouth Aug 16, 2005 12:35 PM word up nigga. Snipsnap in yo bubble wrap",
      "position": "middle"
    },
    {
      "type": "printed",
      "content": "Dane Aug 10, 2005 12:27 PM wats up. Its your boy Dane, hey lets smoke soon. Alright hit me back.",
      "position": "middle"
    },
    {
      "type": "printed",
      "content": "amy lynn. Aug 9, 2005 12:31 PM hey. peekaboos was fun. when are you leaving??",
      "position": "middle"
    },
    {
      "type": "printed",
      "content": "http://www.myspace.com/index.cfm?fuseaction=user.viewComments&friendID=204256... 11/14/2005",
      "position": "footer"
    },
    {
      "type": "printed",
      "content": "07/26/17 Page 33 of 125 Public Records Request No.: 17-295",
      "position": "footer"
    },
    {
      "type": "printed",
      "content": "DOJ-OGR-00030833",
      "position": "footer"
    }
  ],
  "entities": {
    "people": [
      "YellowBeetIE",
      "Lord of the Fire",
      "Beef Knuckles",
      "fuck this city in your mouth",
      "Dane",
      "amy lynn"
    ],
    "organizations": [
      "myspace.com",
      "DOJ"
    ],
    "locations": [],
    "dates": [
      "Aug 22, 2005",
      "Aug 19, 2005",
      "Aug 18, 2005",
      "Aug 16, 2005",
      "Aug 10, 2005",
      "Aug 9, 2005",
      "11/14/2005",
      "07/26/17"
    ],
    "reference_numbers": [
      "17-295",
      "204256",
      "DOJ-OGR-00030833"
    ]
  },
  "additional_notes": "The document appears to be a printout of a Myspace page with comments from various users. The page is part of a larger document, as indicated by the 'Page 33 of 125' notation. The content includes informal conversations and slang."
}