{
  "document_metadata": {
    "page_number": "26",
    "document_number": "DOJ-OGR-00028885",
    "date": "07/23/2019",
    "document_type": "TECS - Person Query",
    "has_handwriting": false,
    "has_stamps": false
  },
  "full_text": "U.S. Customs and Border Protection U.S. Department of Homeland Security TECS - Person Query 07/23/2019 06:41 AM EDT Generated By (b) (6), (b) (7)(C) Interpol Washington Page 26 of 26 ADDRESS INFORMATION (0) DRIVERS' LICENSE INFORMATION (0) PHONE INFORMATION (0) ALTERNATE COMMUNICATION INFORMATION (0) MISCELLANEOUS INFORMATION (0) CRIMINAL AFFILIATION INFORMATION (0) CONTACT INFORMATION Organization Full Name Telephone CBP FIELD OPS - HQ, PRIVATE AIRCRAFT OPS (b) (6), (b) (7)(C) CASE NUMBER INFORMATION (0) FINGER PRINT INFORMATION No Left Right Code Description Code Description 1 2 3 4 5 SPOUSE INFORMATION (0) WARRANT INFORMATION (0) ATF PROFILE INFORMATION (0) BAGGAGE DECLARATION (CF6059) INFORMATION (0) FINANCIAL INFORMATION (0) EMPLOYMENT INFORMATION (0) PILOT LICENSE INFORMATION (0) IMAGE INFORMATION - PART II (0) For Official Use Only / Law Enforcement Sensitive DOJ-OGR-00028885",
  "text_blocks": [
    {
      "type": "printed",
      "content": "U.S. Customs and Border Protection U.S. Department of Homeland Security TECS - Person Query",
      "position": "header"
    },
    {
      "type": "printed",
      "content": "Generated By (b) (6), (b) (7)(C) Interpol Washington",
      "position": "header"
    },
    {
      "type": "printed",
      "content": "07/23/2019 06:41 AM EDT",
      "position": "header"
    },
    {
      "type": "printed",
      "content": "Page 26 of 26",
      "position": "header"
    },
    {
      "type": "printed",
      "content": "ADDRESS INFORMATION (0) DRIVERS' LICENSE INFORMATION (0) PHONE INFORMATION (0) ALTERNATE COMMUNICATION INFORMATION (0) MISCELLANEOUS INFORMATION (0) CRIMINAL AFFILIATION INFORMATION (0) CONTACT INFORMATION Organization Full Name Telephone CBP FIELD OPS - HQ, PRIVATE AIRCRAFT OPS (b) (6), (b) (7)(C) CASE NUMBER INFORMATION (0) FINGER PRINT INFORMATION No Left Right Code Description Code Description 1 2 3 4 5 SPOUSE INFORMATION (0) WARRANT INFORMATION (0) ATF PROFILE INFORMATION (0) BAGGAGE DECLARATION (CF6059) INFORMATION (0) FINANCIAL INFORMATION (0) EMPLOYMENT INFORMATION (0) PILOT LICENSE INFORMATION (0) IMAGE INFORMATION - PART II (0)",
      "position": "body"
    },
    {
      "type": "printed",
      "content": "For Official Use Only / Law Enforcement Sensitive",
      "position": "footer"
    },
    {
      "type": "printed",
      "content": "DOJ-OGR-00028885",
      "position": "footer"
    }
  ],
  "entities": {
    "people": [],
    "organizations": [
      "U.S. Customs and Border Protection",
      "U.S. Department of Homeland Security",
      "Interpol Washington",
      "CBP FIELD OPS - HQ, PRIVATE AIRCRAFT OPS"
    ],
    "locations": [],
    "dates": [
      "07/23/2019"
    ],
    "reference_numbers": [
      "DOJ-OGR-00028885"
    ]
  },
  "additional_notes": "The document contains redacted information marked as '(b) (6), (b) (7)(C)'. The document is labeled 'For Official Use Only / Law Enforcement Sensitive'."
}