{
  "document_metadata": {
    "page_number": "11 of 14",
    "document_number": "DOJ-OGR-00030991",
    "date": "2/9/2006",
    "document_type": "Public Records Request",
    "has_handwriting": false,
    "has_stamps": false
  },
  "full_text": "www.myspace.com/sublimehottie Page 11 of 14 burnt one?? wb...we need to chill sometime...and get blizzy!!! wb......sk I Heart Garrett Stein Sep 22, 2005 9:51 PM I love you!!! katie Sep 21, 2005 4:38 AM where ya been, woadie? I Will Definitely Light YOUR Candle Sep 20, 2005 1:04 PM yo hats upp??? ill pistol whip the shit out of you!!! How Do I my Spaced ? Sep 15, 2005 9:02 PM your GONNA LUV FSU everybody POT up there so finding a roomate witl your \"interests\" shouldnt be hard. 07/26/17 http://www.myspace.com/sublimehottie Page 66 of 72 Public Records Request No.: 17-295 2/9/2006 DOJ-OGR-00030991",
  "text_blocks": [
    {
      "type": "printed",
      "content": "www.myspace.com/sublimehottie",
      "position": "header"
    },
    {
      "type": "printed",
      "content": "Page 11 of 14",
      "position": "header"
    },
    {
      "type": "handwritten",
      "content": "burnt one?? wb...we need to chill sometime...and get blizzy!!! wb......sk",
      "position": "middle"
    },
    {
      "type": "printed",
      "content": "I Heart Garrett Stein Sep 22, 2005 9:51 PM I love you!!!",
      "position": "middle"
    },
    {
      "type": "printed",
      "content": "katie Sep 21, 2005 4:38 AM where ya been, woadie?",
      "position": "middle"
    },
    {
      "type": "printed",
      "content": "I Will Definitely Light YOUR Candle Sep 20, 2005 1:04 PM yo hats upp??? ill pistol whip the shit out of you!!!",
      "position": "middle"
    },
    {
      "type": "printed",
      "content": "How Do I my Spaced ? Sep 15, 2005 9:02 PM your GONNA LUV FSU everybody POT up there so finding a roomate witl your \"interests\" shouldnt be hard.",
      "position": "middle"
    },
    {
      "type": "printed",
      "content": "07/26/17 http://www.myspace.com/sublimehottie Page 66 of 72 Public Records Request No.: 17-295 2/9/2006 DOJ-OGR-00030991",
      "position": "footer"
    }
  ],
  "entities": {
    "people": [
      "Garrett Stein",
      "katie"
    ],
    "organizations": [
      "FSU"
    ],
    "locations": [],
    "dates": [
      "Sep 22, 2005",
      "Sep 21, 2005",
      "Sep 20, 2005",
      "Sep 15, 2005",
      "2/9/2006",
      "07/26/17"
    ],
    "reference_numbers": [
      "17-295",
      "DOJ-OGR-00030991"
    ]
  },
  "additional_notes": "The document appears to be a printout of a Myspace page with comments and profile information. The page has been stamped with a 'Public Records Request' number and date."
}