{
  "document_metadata": {
    "page_number": "1",
    "document_number": "IO25",
    "date": "04/28/2014",
    "document_type": "Inspection Remarks",
    "has_handwriting": false,
    "has_stamps": false
  },
  "full_text": "08:07:55 IO25 INSPECTION REMARKS 04/28/2014 *B *A *C +--------------------------------------------------------------- I N S P E C T I O N R E M A R K S ---------------------------------------------------------------+ PAGE 1 (b)(7)(E) . SUBJECT IS REGISTERED IN NEW YORK, FLORIDA AND THE VIRGIN ISLANDS. SUBJECT IS IN COMPLIANCE. NO ACTION TAKEN, SCBPO (b)(6)&(b)(7)(C) ADVISED. +-----------------------------------------------------------------------------------------------------------------------+ (b)(7)(E) (b)(7)(E) (b)(7)(E) Key: *A - (b)(7)(E) *B - (b)(6), (b)(7)(C) *C - (b)(7)(E) DOJ-OGR-00028598",
  "text_blocks": [
    {
      "type": "printed",
      "content": "08:07:55 IO25 INSPECTION REMARKS 04/28/2014",
      "position": "header"
    },
    {
      "type": "printed",
      "content": "+--------------------------------------------------------------- I N S P E C T I O N R E M A R K S ---------------------------------------------------------------+ PAGE 1",
      "position": "header"
    },
    {
      "type": "printed",
      "content": "(b)(7)(E) . SUBJECT IS REGISTERED IN NEW YORK, FLORIDA AND THE VIRGIN ISLANDS. SUBJECT IS IN COMPLIANCE. NO ACTION TAKEN, SCBPO (b)(6)&(b)(7)(C) ADVISED.",
      "position": "middle"
    },
    {
      "type": "printed",
      "content": "+-----------------------------------------------------------------------------------------------------------------------+",
      "position": "middle"
    },
    {
      "type": "printed",
      "content": "(b)(7)(E) (b)(7)(E) (b)(7)(E) Key: *A - (b)(7)(E) *B - (b)(6), (b)(7)(C) *C - (b)(7)(E)",
      "position": "middle"
    },
    {
      "type": "printed",
      "content": "DOJ-OGR-00028598",
      "position": "footer"
    }
  ],
  "entities": {
    "people": [],
    "organizations": [
      "SCBPO"
    ],
    "locations": [
      "New York",
      "Florida",
      "Virgin Islands"
    ],
    "dates": [
      "04/28/2014"
    ],
    "reference_numbers": [
      "IO25",
      "DOJ-OGR-00028598"
    ]
  },
  "additional_notes": "The document contains redactions, indicated by blacked-out text labeled with codes such as (b)(7)(E), (b)(6), and (b)(7)(C)."
}