{
  "document_metadata": {
    "page_number": "0031",
    "document_number": "DOJ-OGR-00028225",
    "date": "04282014",
    "document_type": "TECSII - PRIMARY QUERY HISTORY",
    "has_handwriting": false,
    "has_stamps": false
  },
  "full_text": "08:07 TECSII - PRIMARY QUERY HISTORY 04282014 *A *B PASSENGER ACTIVITY PAGE NO. 0031 NAME DOB QUERY DATE TIME AGN RSLT LNE TYP REF LANE TERM/ API DIM EPSTEIN, JEFFREY E 012053 072513 0000 *D API R N WEST PALM BEACH DOC: 469911707 US P INSP: APIS QRY EPSTEIN, JEFFREY E 012053 060313 0000 *E API R N LONG ISLAND MACARTHUR DOC: 469911707 US P INSP: APIS QRY EPSTEIN, JEFFREY E 012053 060613 0000 *F API R N UNKNOWN AIRPORT (USED ONLY W DOC: 469911707 US P INSP: APIS QRY EPSTEIN, JEFFREY E 012053 061513 0000 *G API R N ATATURK DOC: 469911707 US P INSP: APIS QRY EPSTEIN, JEFFREY E 012053 062413 0000 *H API R N TETERBORO DOC: 469911707 US P INSP: APIS QRY EPSTEIN, JEFFREY E 012053 051213 0000 *I API R N UNKNOWN AIRPORT (USED ONLY W DOC: 469911707 US P INSP: APIS QRY (b)(7)(E) <...MORE...> (b)(7)(E) (b)(7)(E) (b)(7)(E) (b)(7)(E) (b)(7)(E) Key: *A - (b)(7)(E) *B - (b)(6), (b)(7)(C) *C - (b)(7)(E) *D - (b)(7)(E) *E - (b)(7)(E) *F - (b)(7)(E) *G - (b)(7)(E) *H - (b)(7)(E) *I - (b)(7)(E) DOJ-OGR-00028225",
  "text_blocks": [
    {
      "type": "printed",
      "content": "TECSII - PRIMARY QUERY HISTORY",
      "position": "header"
    },
    {
      "type": "printed",
      "content": "PASSENGER ACTIVITY",
      "position": "header"
    },
    {
      "type": "printed",
      "content": "PAGE NO. 0031",
      "position": "header"
    },
    {
      "type": "printed",
      "content": "NAME DOB QUERY DATE TIME AGN RSLT LNE TYP REF LANE TERM/ API DIM",
      "position": "header"
    },
    {
      "type": "printed",
      "content": "EPSTEIN, JEFFREY E 012053 072513 0000 *D API R N WEST PALM BEACH DOC: 469911707 US P INSP: APIS QRY",
      "position": "body"
    },
    {
      "type": "printed",
      "content": "EPSTEIN, JEFFREY E 012053 060313 0000 *E API R N LONG ISLAND MACARTHUR DOC: 469911707 US P INSP: APIS QRY",
      "position": "body"
    },
    {
      "type": "printed",
      "content": "EPSTEIN, JEFFREY E 012053 060613 0000 *F API R N UNKNOWN AIRPORT (USED ONLY W DOC: 469911707 US P INSP: APIS QRY",
      "position": "body"
    },
    {
      "type": "printed",
      "content": "EPSTEIN, JEFFREY E 012053 061513 0000 *G API R N ATATURK DOC: 469911707 US P INSP: APIS QRY",
      "position": "body"
    },
    {
      "type": "printed",
      "content": "EPSTEIN, JEFFREY E 012053 062413 0000 *H API R N TETERBORO DOC: 469911707 US P INSP: APIS QRY",
      "position": "body"
    },
    {
      "type": "printed",
      "content": "EPSTEIN, JEFFREY E 012053 051213 0000 *I API R N UNKNOWN AIRPORT (USED ONLY W DOC: 469911707 US P INSP: APIS QRY",
      "position": "body"
    },
    {
      "type": "printed",
      "content": "(b)(7)(E) <...MORE...>",
      "position": "footer"
    },
    {
      "type": "printed",
      "content": "Key: *A - (b)(7)(E) *B - (b)(6), (b)(7)(C) *C - (b)(7)(E) *D - (b)(7)(E) *E - (b)(7)(E) *F - (b)(7)(E) *G - (b)(7)(E) *H - (b)(7)(E) *I - (b)(7)(E)",
      "position": "footer"
    }
  ],
  "entities": {
    "people": [
      "JEFFREY E EPSTEIN"
    ],
    "organizations": [],
    "locations": [
      "WEST PALM BEACH",
      "LONG ISLAND MACARTHUR",
      "UNKNOWN AIRPORT",
      "ATATURK",
      "TETERBORO"
    ],
    "dates": [
      "072513",
      "060313",
      "060613",
      "061513",
      "062413",
      "051213",
      "04282014"
    ],
    "reference_numbers": [
      "469911707",
      "DOJ-OGR-00028225"
    ]
  },
  "additional_notes": "The document appears to be a redacted version of a TECSII query history report. The redactions are indicated by (b)(7)(E) and other similar notations."
}