{
  "document_metadata": {
    "page_number": "17",
    "document_number": "17-295",
    "date": "07/26/17",
    "document_type": "transcript",
    "has_handwriting": false,
    "has_stamps": false
  },
  "full_text": "1 remember....that's how I remember.\n2 MP: Do you remember seeing the beach and the ocean?\n3 No but we went over that bridge where the ocean was and then the bridge went over.\n4 over.\n5 MP: Okay. So you definitely went over the bridge.\n6 Yeah. Went over a bridge. And it was up and we had wait for it to go down. So we were there for like 5 minutes.\n8 MP: That was time you were with Haley?\n9 Yes.\n10 MP: Okay. And then the house, you said, you described it as pink?\n11 It was like a, it was a two story house and then it was like a pinkish color, pinkish pink color.\n13 MP: Were there gates or something in front?\n14 Well, it wasn't a gate but, the back door had a gate to it and it was a white gate and Haley, just like she knew that you had to open it and it wasn't locked so we just opened it and there were three, two or three steps and you just walk up and then he had a pool and it had, like the floor, the floor was like a hard something, it wasn't concrete, it was squares of like concrete, but they were like...\n19 MP: Like tile, you mean?\n20 It was like a coral concrete, you know like.. And then the pool was there and the house was there, I guess it was like a security house because a man that was with the security came out and he was like what are you guys here for, cause you're knocking on the door and then Haley said we're here to see Jeff and\nPage 17 of 43\n07/26/17 Page 31 of 81 Public Records Request No.: 17-295 DOJ-OGR-00031123",
  "text_blocks": [
    {
      "type": "printed",
      "content": "1 remember....that's how I remember.\n2 MP: Do you remember seeing the beach and the ocean?\n3 No but we went over that bridge where the ocean was and then the bridge went over.\n4 over.\n5 MP: Okay. So you definitely went over the bridge.\n6 Yeah. Went over a bridge. And it was up and we had wait for it to go down. So we were there for like 5 minutes.\n8 MP: That was time you were with Haley?\n9 Yes.\n10 MP: Okay. And then the house, you said, you described it as pink?\n11 It was like a, it was a two story house and then it was like a pinkish color, pinkish pink color.\n13 MP: Were there gates or something in front?\n14 Well, it wasn't a gate but, the back door had a gate to it and it was a white gate and Haley, just like she knew that you had to open it and it wasn't locked so we just opened it and there were three, two or three steps and you just walk up and then he had a pool and it had, like the floor, the floor was like a hard something, it wasn't concrete, it was squares of like concrete, but they were like...\n19 MP: Like tile, you mean?\n20 It was like a coral concrete, you know like.. And then the pool was there and the house was there, I guess it was like a security house because a man that was with the security came out and he was like what are you guys here for, cause you're knocking on the door and then Haley said we're here to see Jeff and",
      "position": "main content"
    },
    {
      "type": "printed",
      "content": "Page 17 of 43",
      "position": "footer"
    },
    {
      "type": "printed",
      "content": "07/26/17 Page 31 of 81 Public Records Request No.: 17-295 DOJ-OGR-00031123",
      "position": "footer"
    }
  ],
  "entities": {
    "people": [
      "Haley",
      "Jeff",
      "MP"
    ],
    "organizations": [],
    "locations": [
      "beach",
      "ocean",
      "bridge"
    ],
    "dates": [
      "07/26/17"
    ],
    "reference_numbers": [
      "17-295",
      "DOJ-OGR-00031123"
    ]
  },
  "additional_notes": "The document appears to be a transcript of an interview. The text is mostly printed, with no visible handwriting or stamps. The document is well-formatted and easy to read."
}