{
  "document_metadata": {
    "page_number": "76",
    "document_number": "17-295",
    "date": "9-12-05",
    "document_type": "PROBABLE CAUSE AFFIDAVIT",
    "has_handwriting": true,
    "has_stamps": false
  },
  "full_text": "PROBABLE CAUSE AFFIDAVIT\n1 Arrest 3 Request for Warrant 2 Juvenile\n2 NTA 4 Request for Capias\nAgency ORI Number Agency Name Agency Report Number\nR , 0 5 0 0 6 0 0 PALM BEACH POLICE DEPARTMENT 7 6 5 1 0 0 1 2 6 3 1 0 2 7\nCharge Type  1. Felony  Misdemeanor  5. Ordinance\nCheck if many  2. Traffic Felony  4. Traffic Misdemeanor  6. Other\n05-2009\nCharge Description Charge Description Charge Description\nPossession of MARYJANA\nCharge Description\nPossession of Drug Paraphernalia\nVictim's Name (Last, First, Middle)\nLocal Address (Street, Apt. Number) (City) (State) (Zip) Phone\nBusiness Address (Name, Street) (City) (State) (Zip) Phone\nThe undersigned certifies and swears that he/she has just and reasonable grounds to believe, and does believe that the above named Defendant committed the following violation of law.\nThe Person taken into custody was observed by\nCommitted the below acts in my presence. that he/she saw the arrested person commit the below acts.\nconfessed to was found to have committed the below acts, resulting from my (described) investigation.\nadmitting to the below facts.\nOn the 11 day of SEPTEMBER 2005 at 1149 A.M. P.M. (Specifically include facts constituting cause for arrest.)\non SUNDAY, SEPTEMBER 11, 2005 AT APPROXIMATELY 2336 HOURS, I OBSERVED A FOUR DOOR WHITE MITSUBISHI, FL TAG #CJ07JY, PARKED IN A SAFETY ZONE WITHIN A CURVE IN THE ROADWAY, ACROSS FROM 760 NORTH OCEAN BLVD. AS I DROVE UP BEHIND THE VEHICLE, THE VEHICLE LEFT THE SAFETY ZONE WHICH I THEN CONDUCTED A CAR STOP ON THE 200 BLOCK OF BAHAMA LANE. UPON APPROACHING THE AUTO, I OBSERVED FIVE OCCUPANTS INSIDE THE CAR, SEVERAL HAVING BLOODSHOT EYES. I ALSO DETECTED AN ODOR OF MARYJANA FROM INSIDE THE AUTO ALONG WITH OBSERVING THE OCCUPANTS APPEARING TO BE NERVOUS, I SPOKE WITH THE OCCUPANTS OF THE VEHICLE AND ASKED THEM IF THEY HAD MARYJANA, THE DEFENDANT informed me that SHE DID. HANDING ME A CLEAR PLASTIC BAG CONTAINING MARYJANA, A BROWN PAPER BAG CONTAINING MARYJANA AND A GLASS PIPE CONTAINING MARYJANA RESIDUE. BOTH THE MARYJANA AND PARAPHERNALIA TESTED POSITIVE.\nBased on the aforementioned incident, I arrested and charged WITH POSSESSION OF MARYJANA, FSS 893.13(6)(8) AND Possession of Drug Paraphernalia, FSS 893.147.\nMARIJUANA WEIGHED AT 3.0 6(GRAMS)\nSWORN AND SUBSCRIBED BEFORE ME\nSat W Burdick\nNOTARY/PUBLIC/CLERK OF COURT/POLICE OFFICER\n9-12-05\nDATE\nDISTRIBUTION: WHITE - Court Copy GREEN - State Attorney YELLOW - Agency PINK - Agency\n07/26/17 Page 76 of 95 Public Records Request No.: 17-295 DOJ-OGR-00031073",
  "text_blocks": [
    {
      "type": "printed",
      "content": "PROBABLE CAUSE AFFIDAVIT",
      "position": "header"
    },
    {
      "type": "handwritten",
      "content": "On the 11 day of SEPTEMBER 2005 at 1149 A.M. P.M. (Specifically include facts constituting cause for arrest.)\non SUNDAY, SEPTEMBER 11, 2005 AT APPROXIMATELY 2336 HOURS, I OBSERVED A FOUR DOOR WHITE MITSUBISHI, FL TAG #CJ07JY, PARKED IN A SAFETY ZONE WITHIN A CURVE IN THE ROADWAY, ACROSS FROM 760 NORTH OCEAN BLVD. AS I DROVE UP BEHIND THE VEHICLE, THE VEHICLE LEFT THE SAFETY ZONE WHICH I THEN CONDUCTED A CAR STOP ON THE 200 BLOCK OF BAHAMA LANE. UPON APPROACHING THE AUTO, I OBSERVED FIVE OCCUPANTS INSIDE THE CAR, SEVERAL HAVING BLOODSHOT EYES. I ALSO DETECTED AN ODOR OF MARYJANA FROM INSIDE THE AUTO ALONG WITH OBSERVING THE OCCUPANTS APPEARING TO BE NERVOUS, I SPOKE WITH THE OCCUPANTS OF THE VEHICLE AND ASKED THEM IF THEY HAD MARYJANA, THE DEFENDANT informed me that SHE DID. HANDING ME A CLEAR PLASTIC BAG CONTAINING MARYJANA, A BROWN PAPER BAG CONTAINING MARYJANA AND A GLASS PIPE CONTAINING MARYJANA RESIDUE. BOTH THE MARYJANA AND PARAPHERNALIA TESTED POSITIVE.\nBased on the aforementioned incident, I arrested and charged WITH POSSESSION OF MARYJANA, FSS 893.13(6)(8) AND Possession of Drug Paraphernalia, FSS 893.147.\nMARIJUANA WEIGHED AT 3.0 6(GRAMS)",
      "position": "middle"
    },
    {
      "type": "handwritten",
      "content": "Sat W Burdick",
      "position": "footer"
    },
    {
      "type": "handwritten",
      "content": "Joe Nicolas Galvin",
      "position": "footer"
    }
  ],
  "entities": {
    "people": [
      "Joe Nicolas Galvin",
      "Sat W Burdick"
    ],
    "organizations": [
      "PALM BEACH POLICE DEPARTMENT"
    ],
    "locations": [
      "North Ocean Blvd",
      "Bahama Lane"
    ],
    "dates": [
      "September 11, 2005",
      "9-12-05",
      "07/26/17"
    ],
    "reference_numbers": [
      "17-295",
      "DOJ-OGR-00031073",
      "760",
      "200",
      "893.13(6)(8)",
      "893.147"
    ]
  },
  "additional_notes": "The document contains handwritten text and has some redacted information. The document is a probable cause affidavit related to a drug possession case."
}