{
  "document_metadata": {
    "page_number": "14 of 15",
    "document_number": "17-295",
    "date": "07/26/17",
    "document_type": "Public Records Request",
    "has_handwriting": false,
    "has_stamps": false
  },
  "full_text": "www.myspace.com/sublimehotline Page 14 of 15 Beef Knuckles 7/11/2005 10:34:00 PM ..., you should go back to that mess: sent you with those pics. Click on the F make them BIGGER. They're thumbnail 5|<y1ER 7/11/2005 6:39:00 AM This is bad news bears. Deus ex Machina 7/10/2005 10:41:00 PM I like country. You going to curb me? F been? I haven't seen you or Will in for you think waiting for college is tough, should see me while I wait to ship out. going nuts. Give me a call sometime. I -Billy amy lynn. 7/10/2005 9:56:00 PM WEED!!! http://profile.myspace.com/index.cfm?fuseaction=user.viewprofile&friendID=20425696... 11/14/2005 Page 15 of 72 Public Records Request No.: 17-295 07/26/17 DOJ-OGR-00030940",
  "text_blocks": [
    {
      "type": "printed",
      "content": "www.myspace.com/sublimehotline",
      "position": "header"
    },
    {
      "type": "printed",
      "content": "Page 14 of 15",
      "position": "header"
    },
    {
      "type": "printed",
      "content": "Beef Knuckles 7/11/2005 10:34:00 PM",
      "position": "top"
    },
    {
      "type": "printed",
      "content": "..., you should go back to that mess: sent you with those pics. Click on the F make them BIGGER. They're thumbnail",
      "position": "top"
    },
    {
      "type": "printed",
      "content": "5|<y1ER 7/11/2005 6:39:00 AM",
      "position": "middle"
    },
    {
      "type": "printed",
      "content": "This is bad news bears.",
      "position": "middle"
    },
    {
      "type": "printed",
      "content": "Deus ex Machina 7/10/2005 10:41:00 PM",
      "position": "middle"
    },
    {
      "type": "printed",
      "content": "I like country. You going to curb me? F been? I haven't seen you or Will in for you think waiting for college is tough, should see me while I wait to ship out. going nuts. Give me a call sometime. I -Billy",
      "position": "middle"
    },
    {
      "type": "printed",
      "content": "amy lynn. 7/10/2005 9:56:00 PM",
      "position": "bottom"
    },
    {
      "type": "printed",
      "content": "WEED!!!",
      "position": "bottom"
    },
    {
      "type": "printed",
      "content": "http://profile.myspace.com/index.cfm?fuseaction=user.viewprofile&friendID=20425696... 11/14/2005",
      "position": "footer"
    },
    {
      "type": "printed",
      "content": "Page 15 of 72",
      "position": "footer"
    },
    {
      "type": "printed",
      "content": "Public Records Request No.: 17-295",
      "position": "footer"
    },
    {
      "type": "printed",
      "content": "07/26/17",
      "position": "footer"
    },
    {
      "type": "printed",
      "content": "DOJ-OGR-00030940",
      "position": "footer"
    }
  ],
  "entities": {
    "people": [
      "Beef Knuckles",
      "5|<y1ER",
      "Deus ex Machina",
      "Billy",
      "amy lynn",
      "Will"
    ],
    "organizations": [],
    "locations": [],
    "dates": [
      "7/11/2005",
      "7/10/2005",
      "11/14/2005",
      "07/26/17"
    ],
    "reference_numbers": [
      "17-295",
      "DOJ-OGR-00030940"
    ]
  },
  "additional_notes": "The document appears to be a printout of a Myspace conversation or profile, with various usernames and timestamps. The content includes informal language and references to personal relationships. The document is likely a public records request response, given the presence of a request number and a DOJ reference number."
}