{
  "document_metadata": {
    "page_number": "2",
    "document_number": "17-295",
    "date": "07/26/17",
    "document_type": "Court Document",
    "has_handwriting": false,
    "has_stamps": false
  },
  "full_text": "minor.\n\n5. Defendant Jeffrey Epstein is a citizen and resident of the State of New York.\n6. This is an action for damages in excess of $50 million.\n7. This Court has jurisdiction of this action and the claims set forth herein pursuant to 28 U.S.C. ยง1332(a), as the matter in controversy (i) exceeds $75,000, exclusive of interest and costs; and (ii) is between citizens of different states.\n8. This Court has venue of this action pursuant to 28 U.S.C. ยง1391(a) as a substantial part of the events or omissions giving rise to the claim occurred in this District.\n\nFactual Allegations\n\n9. At all relevant times, Defendant Jeffrey Epstein (\"Epstein\") was an adult male, 52 years old. Epstein is a financier and money manager with a secret clientele limited exclusively to billionaires. He is himself a man of tremendous wealth, power and influence. He maintains his principal home in New York and also owns residences in New Mexico, St. Thomas and Palm Beach, FL. The allegations herein concern Epstein's conduct while at his lavish estate in Palm Beach.\n10. Upon information and belief, Epstein has a sexual preference and obsession for underage minor girls. He engaged in a plan and scheme in which he gained access to primarily economically disadvantaged minor girls in his home, sexually assaulted these girls, and then gave them money. In or about 2005, Jane Doe, then 14 years old, fell into Epstein's trap and became one of his victims.\n11. Upon information and belief, Jeffrey Epstein carried out his scheme and assaulted girls in Florida, New York and on his private island, known as Little St. James, in St. Thomas.\n12. An integral player in Epstein's Florida scheme was Haley Robson, a Palm Beach\n\nHERMAN & MERMELSTEIN, P. A.\n- 2 -\nwww.hermanlaw.com\n07/26/17 Page 81 of 114 Public Records Request No.: 17-295 DOJ-OGR-00030434",
  "text_blocks": [
    {
      "type": "printed",
      "content": "minor.",
      "position": "top"
    },
    {
      "type": "printed",
      "content": "5. Defendant Jeffrey Epstein is a citizen and resident of the State of New York.\n6. This is an action for damages in excess of $50 million.\n7. This Court has jurisdiction of this action and the claims set forth herein pursuant to 28 U.S.C. ยง1332(a), as the matter in controversy (i) exceeds $75,000, exclusive of interest and costs; and (ii) is between citizens of different states.\n8. This Court has venue of this action pursuant to 28 U.S.C. ยง1391(a) as a substantial part of the events or omissions giving rise to the claim occurred in this District.",
      "position": "top"
    },
    {
      "type": "printed",
      "content": "Factual Allegations",
      "position": "middle"
    },
    {
      "type": "printed",
      "content": "9. At all relevant times, Defendant Jeffrey Epstein (\"Epstein\") was an adult male, 52 years old. Epstein is a financier and money manager with a secret clientele limited exclusively to billionaires. He is himself a man of tremendous wealth, power and influence. He maintains his principal home in New York and also owns residences in New Mexico, St. Thomas and Palm Beach, FL. The allegations herein concern Epstein's conduct while at his lavish estate in Palm Beach.\n10. Upon information and belief, Epstein has a sexual preference and obsession for underage minor girls. He engaged in a plan and scheme in which he gained access to primarily economically disadvantaged minor girls in his home, sexually assaulted these girls, and then gave them money. In or about 2005, Jane Doe, then 14 years old, fell into Epstein's trap and became one of his victims.\n11. Upon information and belief, Jeffrey Epstein carried out his scheme and assaulted girls in Florida, New York and on his private island, known as Little St. James, in St. Thomas.\n12. An integral player in Epstein's Florida scheme was Haley Robson, a Palm Beach",
      "position": "middle"
    },
    {
      "type": "printed",
      "content": "HERMAN & MERMELSTEIN, P. A.\n- 2 -\nwww.hermanlaw.com",
      "position": "bottom"
    },
    {
      "type": "printed",
      "content": "07/26/17 Page 81 of 114 Public Records Request No.: 17-295 DOJ-OGR-00030434",
      "position": "footer"
    }
  ],
  "entities": {
    "people": [
      "Jeffrey Epstein",
      "Jane Doe",
      "Haley Robson"
    ],
    "organizations": [
      "HERMAN & MERMELSTEIN, P. A."
    ],
    "locations": [
      "New York",
      "New Mexico",
      "St. Thomas",
      "Palm Beach",
      "Florida",
      "Little St. James"
    ],
    "dates": [
      "2005",
      "07/26/17"
    ],
    "reference_numbers": [
      "17-295",
      "DOJ-OGR-00030434"
    ]
  },
  "additional_notes": "The document appears to be a court filing related to a case against Jeffrey Epstein. The text is mostly printed, with no visible handwriting or stamps. The document is page 81 of 114 and has a public records request number."
}