{
  "document_metadata": {
    "page_number": "27",
    "document_number": "17-295",
    "date": "07/26/17",
    "document_type": "Public Records Request",
    "has_handwriting": false,
    "has_stamps": false
  },
  "full_text": "YA FUCK YOU 2!!!!!! \"twins do have more fun\" View My: Pics | Videos Last Login: 6/13/2006 Contacting YA FUCK YOU 2!!!!!! Send Message Forward to Friend Add to Friends Add to Favorites Instant Message Block User Add to Group Rank User MySpace URL: http://www.myspace.com/love YA FUCK YOU 2!!!!!!'s Interests General [*]i love shopping [*] tanning [*] hanging out with friends[*]playing volleyball[*]sleeping in Music TELL ME ABOUT YOURSELF - The Survey Name: Birthday: Birthplace: Current Location: Eye Color: Hair Color: Height: Right Handed or Left Handed: Your Heritage: The Shoes You Wore Today: Public Records Request No.: 17-295 DOJ-OGR-00031024",
  "text_blocks": [
    {
      "type": "printed",
      "content": "YA FUCK YOU 2!!!!!!",
      "position": "top"
    },
    {
      "type": "printed",
      "content": "\"twins do have more fun\"",
      "position": "top"
    },
    {
      "type": "printed",
      "content": "View My: Pics | Videos",
      "position": "top"
    },
    {
      "type": "printed",
      "content": "Last Login: 6/13/2006",
      "position": "top"
    },
    {
      "type": "printed",
      "content": "Contacting YA FUCK YOU 2!!!!!!",
      "position": "middle"
    },
    {
      "type": "printed",
      "content": "Send Message Forward to Friend Add to Friends Add to Favorites Instant Message Block User Add to Group Rank User",
      "position": "middle"
    },
    {
      "type": "printed",
      "content": "MySpace URL: http://www.myspace.com/love",
      "position": "middle"
    },
    {
      "type": "printed",
      "content": "YA FUCK YOU 2!!!!!!'s Interests",
      "position": "bottom"
    },
    {
      "type": "printed",
      "content": "General [*]i love shopping [*] tanning [*] hanging out with friends[*]playing volleyball[*]sleeping in",
      "position": "bottom"
    },
    {
      "type": "printed",
      "content": "Music TELL ME ABOUT YOURSELF - The Survey",
      "position": "bottom"
    },
    {
      "type": "printed",
      "content": "Public Records Request No.: 17-295",
      "position": "footer"
    },
    {
      "type": "printed",
      "content": "DOJ-OGR-00031024",
      "position": "footer"
    }
  ],
  "entities": {
    "people": [],
    "organizations": [
      "MySpace"
    ],
    "locations": [],
    "dates": [
      "6/13/2006",
      "07/26/17"
    ],
    "reference_numbers": [
      "17-295",
      "DOJ-OGR-00031024"
    ]
  },
  "additional_notes": "The document appears to be a printed copy of a MySpace profile page with some obscured content. The page is part of a larger document, as indicated by the page number (27 of 95)."
}