{
  "document_metadata": {
    "page_number": "15",
    "document_number": "17-295",
    "date": "07/26/17",
    "document_type": "transcription",
    "has_handwriting": false,
    "has_stamps": false
  },
  "full_text": "Page 15\n1 towards the end, would they come alone or would they come\n2 with other people?\n3 A. Mostly they would come alone. It was one\n4 girl, one of the young girls, the one I can't think of\n5 it, she would bring somebody else. She'd bring other\n6 girls. But I didn't even know the names.\n7 Q. All of them would go downstairs?\n8 A. Yes.\n9 Q. Or would one stay downstairs?\n10 A. Most of the times when that girl came, it\n11 was at night. So after dinner -- after dinner, they went\n12 to the movies. And by the time they went to the movies,\n13 we clean up right away and tried to get out of there.\n14 And that was about 8, 9 o'clock at night.\n15 After, when they come back, I don't know\n16 what happened. Our quarters were a different -- I don't\n17 know if you've been in the house, but our quarters were\n18 separate.\n19 Q. It's separate.\n20 A. Separate. Before -- that building is new.\n21 They build the building in 2001.\n22 Q. The guest quarters?\n23 A. Yeah, the guest quarters.\n24 Before, we had an apartment upstairs.\n25 Q. They have the laundry and a little office\nJ. ONSOR & ASSOCIATES REPORTING & TRANSCRIPTION\n561.835.9738\nPage 95 of 131 Public Records Request No.: 17-295\n07/26/17 DOJ-OGR-00030562",
  "text_blocks": [
    {
      "type": "printed",
      "content": "Page 15",
      "position": "header"
    },
    {
      "type": "printed",
      "content": "1 towards the end, would they come alone or would they come\n2 with other people?\n3 A. Mostly they would come alone. It was one\n4 girl, one of the young girls, the one I can't think of\n5 it, she would bring somebody else. She'd bring other\n6 girls. But I didn't even know the names.\n7 Q. All of them would go downstairs?\n8 A. Yes.\n9 Q. Or would one stay downstairs?\n10 A. Most of the times when that girl came, it\n11 was at night. So after dinner -- after dinner, they went\n12 to the movies. And by the time they went to the movies,\n13 we clean up right away and tried to get out of there.\n14 And that was about 8, 9 o'clock at night.\n15 After, when they come back, I don't know\n16 what happened. Our quarters were a different -- I don't\n17 know if you've been in the house, but our quarters were\n18 separate.\n19 Q. It's separate.\n20 A. Separate. Before -- that building is new.\n21 They build the building in 2001.\n22 Q. The guest quarters?\n23 A. Yeah, the guest quarters.\n24 Before, we had an apartment upstairs.\n25 Q. They have the laundry and a little office",
      "position": "main"
    },
    {
      "type": "printed",
      "content": "J. ONSOR & ASSOCIATES REPORTING & TRANSCRIPTION\n561.835.9738",
      "position": "footer"
    },
    {
      "type": "printed",
      "content": "Page 95 of 131 Public Records Request No.: 17-295",
      "position": "footer"
    },
    {
      "type": "printed",
      "content": "07/26/17 DOJ-OGR-00030562",
      "position": "footer"
    }
  ],
  "entities": {
    "people": [],
    "organizations": [
      "J. ONSOR & ASSOCIATES REPORTING & TRANSCRIPTION",
      "DOJ"
    ],
    "locations": [
      "house"
    ],
    "dates": [
      "07/26/17",
      "2001"
    ],
    "reference_numbers": [
      "17-295",
      "561.835.9738",
      "DOJ-OGR-00030562"
    ]
  },
  "additional_notes": "The document appears to be a transcription of an interview or testimony. The text is typed and there are no visible redactions or damage."
}