{
  "document_metadata": {
    "page_number": "85",
    "document_number": "17-295",
    "date": "January 24, 2008",
    "document_type": "Court Document",
    "has_handwriting": true,
    "has_stamps": false
  },
  "full_text": "associated with the treatment of Jane. 28. Jane Doe's Father experienced and will continue to experience great mental anguish, pain and suffering from the time that Defendant's tortious conduct occurred. WHEREFORE, Plaintiff Jane Doe's Father demands judgment for loss of consortium damages, costs and such other and further relief as this Court deems proper. JURY TRIAL DEMAND Plaintiffs demand a jury trial in this action. Dated: January 24, 2008 Respectfully submitted, HERMAN & MERMELSTEIN, P.A. Attorneys for Plaintiffs 18205 Biscayne Blvd. Suite 2218 Miami, Florida 33160 Tel: 305-931-2200 Fax: 305-931-0877 By: Jeffrey M. Herman jherman@hermanlaw.com Florida Bar No. 521647 Stuart S. Mermelstein smermelstein@hermanlaw.com Florida Bar No. 947245 Adam D. Horowitz ahorowitz@hermanlaw.com Florida Bar No. 376980 HERMAN & MERMELSTEIN, P.A. - 6 - www.hermanlaw.com 07/26/17 Page 85 of 114 Public Records Request No.: 17-295 DOJ-OGR-00030438",
  "text_blocks": [
    {
      "type": "printed",
      "content": "associated with the treatment of Jane. 28. Jane Doe's Father experienced and will continue to experience great mental anguish, pain and suffering from the time that Defendant's tortious conduct occurred. WHEREFORE, Plaintiff Jane Doe's Father demands judgment for loss of consortium damages, costs and such other and further relief as this Court deems proper.",
      "position": "top"
    },
    {
      "type": "printed",
      "content": "JURY TRIAL DEMAND",
      "position": "middle"
    },
    {
      "type": "printed",
      "content": "Plaintiffs demand a jury trial in this action.",
      "position": "middle"
    },
    {
      "type": "handwritten",
      "content": "24",
      "position": "middle"
    },
    {
      "type": "printed",
      "content": "Dated: January 24, 2008 Respectfully submitted, HERMAN & MERMELSTEIN, P.A. Attorneys for Plaintiffs 18205 Biscayne Blvd. Suite 2218 Miami, Florida 33160 Tel: 305-931-2200 Fax: 305-931-0877 By:",
      "position": "middle"
    },
    {
      "type": "signature",
      "content": "",
      "position": "middle"
    },
    {
      "type": "printed",
      "content": "Jeffrey M. Herman jherman@hermanlaw.com Florida Bar No. 521647 Stuart S. Mermelstein smermelstein@hermanlaw.com Florida Bar No. 947245 Adam D. Horowitz ahorowitz@hermanlaw.com Florida Bar No. 376980",
      "position": "bottom"
    },
    {
      "type": "printed",
      "content": "HERMAN & MERMELSTEIN, P.A. - 6 - www.hermanlaw.com 07/26/17 Page 85 of 114 Public Records Request No.: 17-295 DOJ-OGR-00030438",
      "position": "footer"
    }
  ],
  "entities": {
    "people": [
      "Jane Doe",
      "Jane Doe's Father",
      "Jeffrey M. Herman",
      "Stuart S. Mermelstein",
      "Adam D. Horowitz"
    ],
    "organizations": [
      "HERMAN & MERMELSTEIN, P.A."
    ],
    "locations": [
      "Miami",
      "Florida"
    ],
    "dates": [
      "January 24, 2008",
      "07/26/17"
    ],
    "reference_numbers": [
      "17-295",
      "DOJ-OGR-00030438",
      "521647",
      "947245",
      "376980"
    ]
  },
  "additional_notes": "The document appears to be a court filing with a demand for a jury trial. It is dated January 24, 2008, and is from the law firm HERMAN & MERMELSTEIN, P.A. The document is page 85 of 114 and has a public records request number of 17-295."
}