{
  "document_metadata": {
    "page_number": "1 of 3",
    "document_number": "06049528",
    "date": "03/31/06",
    "document_type": "Offense Report",
    "has_handwriting": false,
    "has_stamps": false
  },
  "full_text": "OQS - Viewing Case Number 06049528 Page 1 of 3 PALM BEACH COUNTY SHERIFF'S OFFICE OFFENSE REPORT CASE NO. 06049528 DISPOSITION: CLEARED BY DIVISION: ROAD PATROL JUVENILE ARREST BATTERY SIGNAL CODE: 31D CRIME CODE: 1 NON CRIME CODE: CODE: 130B 03/31/06 FRIDAY ZONE: A34 GRID: IND5 DEPUTY I.D.: 6376 NAME: SHAFFER SARAH ASSIST: TIME D 0913 A 0918 OCCURRED BETWEEN DATE: 03/31/06 , 0925 HOURS AND DATE: 03/31/06 , 1028 HOURS EXCEPTION TYPE: INCIDENT LOCATION: LO NO. OFFENSES: 01 NO. OFFENDERS: 01 NO. VEHICLES STOLEN: 0 NO. PREMISES ENTERED: 0 LOCATION: RESIDENCE - SINGLE FAMILY NO. VICTIMS: 01 NO. ARRESTED: 1 FORCED ENTRY: 0 WEAPON TYPE: HANDS / FISTS / FEET OFFENSE NO. 1 FLORIDA STATE STATUTE: 784 03 CIS CODE 130B NAME LIST: ROLE: VICTIM NO. 001 BUSINESS OTHER RESIDENTIAL ADDRESS BUSINESS PHONE: OFFENSE INDICATOR: OFFENSE 1 VICTIM NUMBER: 1 VICTIM TYPE: ADULT RESIDENCE TYPE: COUNTY RESIDENCE STATUS: FULL YEAR EXTENT OF INJURY: NONE INJURY TYPE(1) : NOT APPLICABLE INJURY TYPE(2) : NOT APPLICABLE VICTIM RELATION: PARENT DOMESTIC VIOLENCE RELATED: YES printed by Employee Id #: 4541 on April 05, 2006 04. http://oqs.pbso.org/index.cfm?fa=dspCase&fromrec=1&srhta=d67d417bd0dae93-6BB4D08C 4/5/2006 07/26/17 Page 85 of 95 Public Records Request No.: 17-295 DOJ-OGR-00031082",
  "text_blocks": [
    {
      "type": "printed",
      "content": "OQS - Viewing Case Number 06049528 Page 1 of 3",
      "position": "header"
    },
    {
      "type": "printed",
      "content": "PALM BEACH COUNTY SHERIFF'S OFFICE OFFENSE REPORT",
      "position": "header"
    },
    {
      "type": "printed",
      "content": "CASE NO. 06049528 DISPOSITION: CLEARED BY DIVISION: ROAD PATROL JUVENILE ARREST",
      "position": "header"
    },
    {
      "type": "printed",
      "content": "BATTERY SIGNAL CODE: 31D CRIME CODE: 1 NON CRIME CODE: CODE: 130B 03/31/06 FRIDAY ZONE: A34 GRID: IND5 DEPUTY I.D.: 6376 NAME: SHAFFER SARAH ASSIST: TIME D 0913 A 0918 OCCURRED BETWEEN DATE: 03/31/06 , 0925 HOURS AND DATE: 03/31/06 , 1028 HOURS EXCEPTION TYPE: INCIDENT LOCATION: LO",
      "position": "body"
    },
    {
      "type": "printed",
      "content": "NO. OFFENSES: 01 NO. OFFENDERS: 01 NO. VEHICLES STOLEN: 0 NO. PREMISES ENTERED: 0 LOCATION: RESIDENCE - SINGLE FAMILY NO. VICTIMS: 01 NO. ARRESTED: 1 FORCED ENTRY: 0 WEAPON TYPE: HANDS / FISTS / FEET",
      "position": "body"
    },
    {
      "type": "printed",
      "content": "OFFENSE NO. 1 FLORIDA STATE STATUTE: 784 03 CIS CODE 130B NAME LIST: ROLE: VICTIM NO. 001",
      "position": "body"
    },
    {
      "type": "printed",
      "content": "BUSINESS OTHER RESIDENTIAL ADDRESS BUSINESS PHONE: OFFENSE INDICATOR: OFFENSE 1 VICTIM NUMBER: 1 VICTIM TYPE: ADULT RESIDENCE TYPE: COUNTY RESIDENCE STATUS: FULL YEAR EXTENT OF INJURY: NONE INJURY TYPE(1) : NOT APPLICABLE INJURY TYPE(2) : NOT APPLICABLE VICTIM RELATION: PARENT DOMESTIC VIOLENCE RELATED: YES",
      "position": "body"
    },
    {
      "type": "printed",
      "content": "printed by Employee Id #: 4541 on April 05, 2006 04.",
      "position": "footer"
    },
    {
      "type": "printed",
      "content": "http://oqs.pbso.org/index.cfm?fa=dspCase&fromrec=1&srhta=d67d417bd0dae93-6BB4D08C 4/5/2006",
      "position": "footer"
    },
    {
      "type": "printed",
      "content": "07/26/17 Page 85 of 95 Public Records Request No.: 17-295 DOJ-OGR-00031082",
      "position": "footer"
    }
  ],
  "entities": {
    "people": [
      "SHAFFER SARAH"
    ],
    "organizations": [
      "PALM BEACH COUNTY SHERIFF'S OFFICE"
    ],
    "locations": [
      "PALM BEACH COUNTY"
    ],
    "dates": [
      "03/31/06",
      "April 05, 2006",
      "4/5/2006",
      "07/26/17"
    ],
    "reference_numbers": [
      "06049528",
      "17-295",
      "DOJ-OGR-00031082"
    ]
  },
  "additional_notes": "The document appears to be a scanned copy of an offense report from the Palm Beach County Sheriff's Office. The report is related to a battery incident that occurred on March 31, 2006. The document contains some redacted information, likely due to privacy concerns."
}