{
  "document_metadata": {
    "page_number": "3",
    "document_number": "1-05-001263",
    "date": "11/18/05",
    "document_type": "Incident Report",
    "has_handwriting": false,
    "has_stamps": false
  },
  "full_text": "Date: 11/18/05 Time: 11:36:11 PALM BEACH POLICE DEPARTMENT Incident Report Page: 3 Program: CMS301L Case No. : 1-05-001263 Facial Hair : Build : SLIGHT Teeth : NO DISCERNIBLE FEATURES Hat : Speech : NORMAL Shirt : Coat : Shoes : Pants : Body Marks #1 : Body Marks #2 : Body Marks #3 : Body Marks #4 : Status : ARRESTED Arrest Case No.: 1-05-001418 Additional UCR?: ************* SUSPECT/ARRESTEE INFORMATION - # 2 ************* Case Number : 1-05-001263 Prompt valid in: Street Number : City : Birth Date : Employer? Oper Lic No. : Other Phone Nbr: Sex : Female Minimum Weight : 110 Maximum Weight : 0 Aliases? Hair Color : BLONDE OR STRAWBERRY Hair Style : Glasses : No Facial Hair : Teeth : NO DISCERNIBLE FEATURES Speech : NORMAL Coat : Hat : Pants : Shirt : Shoes : Body Marks #1 : Body Marks #2 : Body Marks #3 : Body Marks #4 : Status : ARRESTED Arrest Case No.: 1-05-001419 Additional UCR?: ************* NARRATIVE # 1 ************* Original Report LO Reported By: CARISTO, NICHOLAS 9/11/05 Entered By.: OREGERO, LAURA D. 9/12/05 On Sunday, 9/11/05 at approximately 2345 hours, I effected the arrests of two individuals, identified as Benjamin Skyler Bryan, dob/122986 and on the 200 block of Bahama Lane, charging them both with possession of marijuana under 20 grams and possession of drug paraphernalia under the following circumstances: On this date at approximately 2340 hours, I observed a four door white Mitsubishi, Florida tag C104VY, parked in a safety zone along a curve in the roadway, across from 760 N. Ocean Blvd. As I drove up behind the vehicle, the vehicle left the safety zone which I then conducted a car stop on the 200 block of Bahama Lane. Upon 07/26/17 Page 79 of 95 Public Records Request No.: 17-295 DOJ-OGR-00031076",
  "text_blocks": [
    {
      "type": "printed",
      "content": "Date: 11/18/05 Time: 11:36:11 PALM BEACH POLICE DEPARTMENT Incident Report Page: 3 Program: CMS301L",
      "position": "header"
    },
    {
      "type": "printed",
      "content": "Case No. : 1-05-001263 Facial Hair : Build : SLIGHT Teeth : NO DISCERNIBLE FEATURES Hat : Speech : NORMAL Shirt : Coat : Shoes : Pants : Body Marks #1 : Body Marks #2 : Body Marks #3 : Body Marks #4 : Status : ARRESTED Arrest Case No.: 1-05-001418 Additional UCR?:",
      "position": "middle"
    },
    {
      "type": "printed",
      "content": "************* SUSPECT/ARRESTEE INFORMATION - # 2 ************* Case Number : 1-05-001263 Prompt valid in: Street Number : City : Birth Date : Employer? Oper Lic No. : Other Phone Nbr: Sex : Female Minimum Weight : 110 Maximum Weight : 0 Aliases? Hair Color : BLONDE OR STRAWBERRY Hair Style : Glasses : No Facial Hair : Teeth : NO DISCERNIBLE FEATURES Speech : NORMAL Coat : Hat : Pants : Shirt : Shoes : Body Marks #1 : Body Marks #2 : Body Marks #3 : Body Marks #4 : Status : ARRESTED Arrest Case No.: 1-05-001419 Additional UCR?:",
      "position": "middle"
    },
    {
      "type": "printed",
      "content": "************* NARRATIVE # 1 ************* Original Report LO Reported By: CARISTO, NICHOLAS 9/11/05 Entered By.: OREGERO, LAURA D. 9/12/05",
      "position": "middle"
    },
    {
      "type": "printed",
      "content": "On Sunday, 9/11/05 at approximately 2345 hours, I effected the arrests of two individuals, identified as Benjamin Skyler Bryan, dob/122986 and on the 200 block of Bahama Lane, charging them both with possession of marijuana under 20 grams and possession of drug paraphernalia under the following circumstances: On this date at approximately 2340 hours, I observed a four door white Mitsubishi, Florida tag C104VY, parked in a safety zone along a curve in the roadway, across from 760 N. Ocean Blvd. As I drove up behind the vehicle, the vehicle left the safety zone which I then conducted a car stop on the 200 block of Bahama Lane. Upon",
      "position": "middle"
    },
    {
      "type": "printed",
      "content": "07/26/17 Page 79 of 95 Public Records Request No.: 17-295 DOJ-OGR-00031076",
      "position": "footer"
    }
  ],
  "entities": {
    "people": [
      "Benjamin Skyler Bryan",
      "CARISTO, NICHOLAS",
      "OREGERO, LAURA D."
    ],
    "organizations": [
      "PALM BEACH POLICE DEPARTMENT"
    ],
    "locations": [
      "Bahama Lane",
      "N. Ocean Blvd."
    ],
    "dates": [
      "11/18/05",
      "9/11/05",
      "9/12/05",
      "07/26/17"
    ],
    "reference_numbers": [
      "1-05-001263",
      "1-05-001418",
      "1-05-001419",
      "17-295",
      "DOJ-OGR-00031076",
      "C104VY"
    ]
  },
  "additional_notes": "The document appears to be a police incident report with some redacted information."
}