{
  "document_metadata": {
    "page_number": "3 of 10",
    "document_number": "DOJ-OGR-00031014",
    "date": "4/4/2006",
    "document_type": "Public Records Request",
    "has_handwriting": false,
    "has_stamps": false
  },
  "full_text": "www.myspace.com/ilovearisntool Watermelon: Hot tea or Ice tea: Ice tea Chocolate or Vanilla vanilla Hot Chocolate or Coffee: coffee Kiss or Hug: hug Dog or Cat: dog Rap or Punk: rap Summer or Winter: summer Scary Movies or Funny Movies: scary Love or Money: love YOUR... Bedtime: whenever Most Missed Memory: being with zach Best phyiscal feature: ass and eyes First Thought Waking Up: i gotta pee Goal for this year: to stay out of trouble Best Friends: amber Weakness: love Fears: what I cant control Heritage: cuban and irish and french Longest relationship: its curentyl taking place lol HAVE YOU... Ever Drank: yup Ever Smoked: yup Pot: yeah Ever been Drunk: oh yea Ever been beaten up: nope Ever beaten someone up: yup Ever Shoplifted: lots Ever Skinny Dipped: yeah Ever Kissed Opposite sex: yea Been Dumped Lately: nope LOveabLe dOrKk 3/29/2006 4:09 AM heyy... yea so im sittin here waitin for zack to get ready for school so we can leave and im lookin at all the comments and stuff that we left each other and now im over here bawlin ... lol... yea i was in school yesterday and i looked at clock and i was like aww saige is up n the air!! lol... and i had NOTHINg todo yesterday and i was like hey we all can hang out ... but now your in florida so it wont be all of us .. but it will be sooon!! =D mary 3/28/2006 4:56 PM r u packin to come back now!!!!!! we miss u :( katie B-RIZZLE 3/28/2006 1:55 PM i miss u too, biology sucks dick now and miss clarke is still a bitch sooooo where are u moving to in florida? Jesse 3/28/2006 10:04 AM whats up long time no see. http://profile.myspace.com/index.cfm?fuseaction=user.viewprofile&friendID=65739759 07/26/17 Page 17 of 95 4/4/2006 Public Records Request No.: 17-295 DOJ-OGR-00031014",
  "text_blocks": [
    {
      "type": "printed",
      "content": "www.myspace.com/ilovearisntool",
      "position": "header"
    },
    {
      "type": "printed",
      "content": "Watermelon: Hot tea or Ice tea: Ice tea Chocolate or Vanilla vanilla Hot Chocolate or Coffee: coffee Kiss or Hug: hug Dog or Cat: dog Rap or Punk: rap Summer or Winter: summer Scary Movies or Funny Movies: scary Love or Money: love YOUR... Bedtime: whenever Most Missed Memory: being with zach Best phyiscal feature: ass and eyes First Thought Waking Up: i gotta pee Goal for this year: to stay out of trouble Best Friends: amber Weakness: love Fears: what I cant control Heritage: cuban and irish and french Longest relationship: its curentyl taking place lol HAVE YOU... Ever Drank: yup Ever Smoked: yup Pot: yeah Ever been Drunk: oh yea Ever been beaten up: nope Ever beaten someone up: yup Ever Shoplifted: lots Ever Skinny Dipped: yeah Ever Kissed Opposite sex: yea Been Dumped Lately: nope",
      "position": "left"
    },
    {
      "type": "printed",
      "content": "LOveabLe dOrKk 3/29/2006 4:09 AM heyy... yea so im sittin here waitin for zack to get ready for school so we can leave and im lookin at all the comments and stuff that we left each other and now im over here bawlin ... lol... yea i was in school yesterday and i looked at clock and i was like aww saige is up n the air!! lol... and i had NOTHINg todo yesterday and i was like hey we all can hang out ... but now your in florida so it wont be all of us .. but it will be sooon!! =D",
      "position": "middle"
    },
    {
      "type": "printed",
      "content": "mary 3/28/2006 4:56 PM r u packin to come back now!!!!!! we miss u :( katie",
      "position": "middle"
    },
    {
      "type": "printed",
      "content": "B-RIZZLE 3/28/2006 1:55 PM i miss u too, biology sucks dick now and miss clarke is still a bitch sooooo where are u moving to in florida?",
      "position": "middle"
    },
    {
      "type": "printed",
      "content": "Jesse 3/28/2006 10:04 AM whats up long time no see.",
      "position": "middle"
    },
    {
      "type": "printed",
      "content": "http://profile.myspace.com/index.cfm?fuseaction=user.viewprofile&friendID=65739759 07/26/17 Page 17 of 95",
      "position": "footer"
    },
    {
      "type": "printed",
      "content": "4/4/2006 Public Records Request No.: 17-295 DOJ-OGR-00031014",
      "position": "footer"
    }
  ],
  "entities": {
    "people": [
      "zach",
      "amber",
      "zack",
      "mary",
      "katie",
      "B-RIZZLE",
      "Jesse",
      "clarke"
    ],
    "organizations": [],
    "locations": [
      "Florida"
    ],
    "dates": [
      "3/29/2006",
      "3/28/2006",
      "4/4/2006",
      "07/26/17"
    ],
    "reference_numbers": [
      "17-295",
      "DOJ-OGR-00031014"
    ]
  },
  "additional_notes": "The document appears to be a printout of a Myspace profile and comments. The content is informal and includes slang, profanity, and personal references. Some names and words are redacted."
}