{
  "document_metadata": {
    "page_number": "252",
    "document_number": "753",
    "date": "08/10/22",
    "document_type": "court transcript",
    "has_handwriting": false,
    "has_stamps": false
  },
  "full_text": "Case 1:20-cr-00330-PAE Document 753 Filed 08/10/22 Page 252 of 264 1693\nLC7Cmax8\nCarolyn - redirect\n1 A. No.\n2 Q. Did you write it yourself?\n3 A. No.\n4 Q. Did anyone ever ask you if it was accurate?\n5 A. No.\n6 Q. Do you know how old you were when you first saw Ghislaine Maxwell?\n7 \n8 A. I was 13.\n9 Q. Do you know how old you were when you first went to Jeffrey Epstein's house?\n10 \n11 A. I was 13.\n12 Q. Do you know what year it was?\n13 A. Not off the top of my head right now.\n14 Q. Do you know what year it was when you were 14 years old, Carolyn?\n15 \n16 A. I can't remember right now.\n17 Q. Are you able to tell us what year it was when you were 15 years old?\n18 \n19 A. No.\n20 Q. Can you tell us what year it was when you were 13?\n21 A. If I do the math, yes.\n22 Q. Did anyone tell you what to say here today on the stand?\n23 A. No.\n24 Q. Carolyn, are you trying to get money out of testifying here today?\n25 \nSOUTHERN DISTRICT REPORTERS, P.C.\n(212) 805-0300\nDOJ-OGR-00013265",
  "text_blocks": [
    {
      "type": "printed",
      "content": "Case 1:20-cr-00330-PAE Document 753 Filed 08/10/22 Page 252 of 264 1693",
      "position": "header"
    },
    {
      "type": "printed",
      "content": "LC7Cmax8\nCarolyn - redirect",
      "position": "header"
    },
    {
      "type": "printed",
      "content": "1 A. No.\n2 Q. Did you write it yourself?\n3 A. No.\n4 Q. Did anyone ever ask you if it was accurate?\n5 A. No.\n6 Q. Do you know how old you were when you first saw Ghislaine Maxwell?\n7 \n8 A. I was 13.\n9 Q. Do you know how old you were when you first went to Jeffrey Epstein's house?\n10 \n11 A. I was 13.\n12 Q. Do you know what year it was?\n13 A. Not off the top of my head right now.\n14 Q. Do you know what year it was when you were 14 years old, Carolyn?\n15 \n16 A. I can't remember right now.\n17 Q. Are you able to tell us what year it was when you were 15 years old?\n18 \n19 A. No.\n20 Q. Can you tell us what year it was when you were 13?\n21 A. If I do the math, yes.\n22 Q. Did anyone tell you what to say here today on the stand?\n23 A. No.\n24 Q. Carolyn, are you trying to get money out of testifying here today?\n25",
      "position": "main"
    },
    {
      "type": "printed",
      "content": "SOUTHERN DISTRICT REPORTERS, P.C.\n(212) 805-0300",
      "position": "footer"
    },
    {
      "type": "printed",
      "content": "DOJ-OGR-00013265",
      "position": "footer"
    }
  ],
  "entities": {
    "people": [
      "Ghislaine Maxwell",
      "Jeffrey Epstein",
      "Carolyn"
    ],
    "organizations": [
      "SOUTHERN DISTRICT REPORTERS, P.C."
    ],
    "locations": [],
    "dates": [
      "08/10/22"
    ],
    "reference_numbers": [
      "1:20-cr-00330-PAE",
      "753",
      "DOJ-OGR-00013265"
    ]
  },
  "additional_notes": "The document appears to be a court transcript with a clear and legible format. There are no visible redactions or damage."
}