{
  "document_metadata": {
    "page_number": "213",
    "document_number": "759",
    "date": "08/10/22",
    "document_type": "Court Transcript",
    "has_handwriting": false,
    "has_stamps": false
  },
  "full_text": "Case 1:20-cr-00330-PAE Document 759 Filed 08/10/22 Page 213 of 267 2241 LCACmax7 Mulligan - direct attempted to smuggle. Q. And what did she tell you happened after he was trying to snuggle with her? A. She told me that she got out of bed and locked herself in the bathroom. Q. Did Annie talk to you about what happened in New Mexico after high school? A. Yes. Q. When did she talk to you about what happened in New Mexico? A. I remember her talking to me about it in early 2003. Q. What was Annie's demeanor when you spoke with her when she talked to you about what happened in New Mexico in 2003? MS. MENNINGER: Objection. THE COURT: Sustained. Q. In 2003 when Annie talked to you about her experiences with Maxwell and Epstein in New Mexico, without going into the details, when did this come up? A. This came up at a time where we were being physically affectionate with each other. MS. POMERANTZ: Your Honor, may I have one moment, please? THE COURT: You may. MS. POMERANTZ: Nothing further, Judge. THE COURT: Ms. Sternheim. MS. STERNHEIM: Briefly, Judge. SOUTHERN DISTRICT REPORTERS, P.C. (212) 805-0300 DOJ-OGR-00013804",
  "text_blocks": [
    {
      "type": "printed",
      "content": "Case 1:20-cr-00330-PAE Document 759 Filed 08/10/22 Page 213 of 267 2241 LCACmax7 Mulligan - direct",
      "position": "header"
    },
    {
      "type": "printed",
      "content": "attempted to smuggle. Q. And what did she tell you happened after he was trying to snuggle with her? A. She told me that she got out of bed and locked herself in the bathroom. Q. Did Annie talk to you about what happened in New Mexico after high school? A. Yes. Q. When did she talk to you about what happened in New Mexico? A. I remember her talking to me about it in early 2003. Q. What was Annie's demeanor when you spoke with her when she talked to you about what happened in New Mexico in 2003? MS. MENNINGER: Objection. THE COURT: Sustained. Q. In 2003 when Annie talked to you about her experiences with Maxwell and Epstein in New Mexico, without going into the details, when did this come up? A. This came up at a time where we were being physically affectionate with each other. MS. POMERANTZ: Your Honor, may I have one moment, please? THE COURT: You may. MS. POMERANTZ: Nothing further, Judge. THE COURT: Ms. Sternheim. MS. STERNHEIM: Briefly, Judge.",
      "position": "main"
    },
    {
      "type": "printed",
      "content": "SOUTHERN DISTRICT REPORTERS, P.C. (212) 805-0300",
      "position": "footer"
    },
    {
      "type": "printed",
      "content": "DOJ-OGR-00013804",
      "position": "footer"
    }
  ],
  "entities": {
    "people": [
      "Annie",
      "Maxwell",
      "Epstein",
      "Ms. Menninger",
      "Ms. Pomerantz",
      "Ms. Sternheim"
    ],
    "organizations": [
      "SOUTHERN DISTRICT REPORTERS, P.C."
    ],
    "locations": [
      "New Mexico"
    ],
    "dates": [
      "08/10/22",
      "early 2003"
    ],
    "reference_numbers": [
      "1:20-cr-00330-PAE",
      "759",
      "DOJ-OGR-00013804"
    ]
  },
  "additional_notes": "The document appears to be a court transcript with a clear and legible format. There are no visible redactions or damage."
}