{
  "document_metadata": {
    "page_number": "157",
    "document_number": "749",
    "date": "08/10/22",
    "document_type": "court transcript",
    "has_handwriting": false,
    "has_stamps": false
  },
  "full_text": "Case 1:20-cr-00330-PAE Document 749 Filed 08/10/22 Page 157 of 236 1061 LC3Cmax5 Parkinson - direct. 1 A. These are photographs in frames. 2 Q. From where? 3 A. They were in the first floor on the west side of the building, either in the lake room or bordering on the garden room. 4 5 6 Q. Do these photographs fairly and accurately depict a portion 7 of the interior of the main house at 358 El Brillo Way as it 8 appeared on October 20th, 2005? 9 A. True. 10 MS. COMEY: Your Honor, the government offers these in 11 evidence. 12 MR. EVERDELL: No objection, your Honor. 13 MS. COMEY: I would ask that they be -- 14 THE COURT: Sorry. You said no objection? 15 MR. EVERDELL: No objection, your Honor. 16 THE COURT: GX252, 253, and 254 are admitted. 17 (Government's Exhibits 252, 253, 254 received in 18 evidence) 19 MS. COMEY: Your Honor, I would ask that these be 20 received under seal to protect the privacy of third parties. 21 MR. EVERDELL: No objection. 22 THE COURT: They are admitted under seal for the 23 reasons indicated. 24 MS. COMEY: May we ask the jurors please to turn in 25 their binders to Government Exhibit 252. C SOUTHERN DISTRICT REPORTERS, P.C. (212) 805-0300 DOJ-OGR-00012671",
  "text_blocks": [
    {
      "type": "printed",
      "content": "Case 1:20-cr-00330-PAE Document 749 Filed 08/10/22 Page 157 of 236 1061 LC3Cmax5 Parkinson - direct.",
      "position": "header"
    },
    {
      "type": "printed",
      "content": "1 A. These are photographs in frames. 2 Q. From where? 3 A. They were in the first floor on the west side of the building, either in the lake room or bordering on the garden room. 4 5 6 Q. Do these photographs fairly and accurately depict a portion 7 of the interior of the main house at 358 El Brillo Way as it 8 appeared on October 20th, 2005? 9 A. True. 10 MS. COMEY: Your Honor, the government offers these in 11 evidence. 12 MR. EVERDELL: No objection, your Honor. 13 MS. COMEY: I would ask that they be -- 14 THE COURT: Sorry. You said no objection? 15 MR. EVERDELL: No objection, your Honor. 16 THE COURT: GX252, 253, and 254 are admitted. 17 (Government's Exhibits 252, 253, 254 received in 18 evidence) 19 MS. COMEY: Your Honor, I would ask that these be 20 received under seal to protect the privacy of third parties. 21 MR. EVERDELL: No objection. 22 THE COURT: They are admitted under seal for the 23 reasons indicated. 24 MS. COMEY: May we ask the jurors please to turn in 25 their binders to Government Exhibit 252.",
      "position": "main"
    },
    {
      "type": "printed",
      "content": "C SOUTHERN DISTRICT REPORTERS, P.C. (212) 805-0300",
      "position": "footer"
    },
    {
      "type": "printed",
      "content": "DOJ-OGR-00012671",
      "position": "footer"
    }
  ],
  "entities": {
    "people": [
      "MS. COMEY",
      "MR. EVERDELL"
    ],
    "organizations": [
      "SOUTHERN DISTRICT REPORTERS, P.C."
    ],
    "locations": [
      "358 El Brillo Way"
    ],
    "dates": [
      "October 20th, 2005",
      "08/10/22"
    ],
    "reference_numbers": [
      "1:20-cr-00330-PAE",
      "749",
      "GX252",
      "253",
      "254",
      "252",
      "253",
      "254",
      "DOJ-OGR-00012671"
    ]
  },
  "additional_notes": "The document appears to be a court transcript with a clear and legible format. There are no visible redactions or damage."
}