{
  "document_metadata": {
    "page_number": "262",
    "document_number": "753",
    "date": "08/10/22",
    "document_type": "court transcript",
    "has_handwriting": false,
    "has_stamps": false
  },
  "full_text": "Case 1:20-cr-00330-PAE Document 753 Filed 08/10/22 Page 262 of 264 1703 LC7Cmax8\n\n1 THE COURT: I do just want to, in an admonishment, because this has gotten a little out of hand. Objection, one-word grounds. Cite a rule of evidence if a rule of evidence is available. If it's not, then you probably don't have a basis for your objection. But if a rule number can't be used, one-word basis for grounds. No more communicating to the witnesses or the jury via objections. Understood?\n\n8 MS. COMEY: Yes, your Honor.\n\n9 MR. PAGLIUCA: Yes, your Honor.\n\n10 THE COURT: Thank you. Have a goodnight, everyone. I'll see you -- sorry. Sorry.\n\n12 So we don't need any of the briefing related to the witness. So I think I'm not expecting anything tonight; is that true? It's like saying, oh, look, no traffic, but --\n\n15 MS. MOE: Nothing anticipated from the government, your Honor.\n\n17 THE COURT: Okay.\n\n18 MS. MENNINGER: Nor from us.\n\n19 THE COURT: I thank everyone. Goodnight.\n\n20 (Adjourned to December 8, 2021 at 8:45 a.m.)\n\n21 * * *\n\n24 SOUTHERN DISTRICT REPORTERS, P.C. (212) 805-0300\n\n25 DOJ-OGR-00013275",
  "text_blocks": [
    {
      "type": "printed",
      "content": "Case 1:20-cr-00330-PAE Document 753 Filed 08/10/22 Page 262 of 264 1703 LC7Cmax8",
      "position": "header"
    },
    {
      "type": "printed",
      "content": "1 THE COURT: I do just want to, in an admonishment, because this has gotten a little out of hand. Objection, one-word grounds. Cite a rule of evidence if a rule of evidence is available. If it's not, then you probably don't have a basis for your objection. But if a rule number can't be used, one-word basis for grounds. No more communicating to the witnesses or the jury via objections. Understood?\n\n8 MS. COMEY: Yes, your Honor.\n\n9 MR. PAGLIUCA: Yes, your Honor.\n\n10 THE COURT: Thank you. Have a goodnight, everyone. I'll see you -- sorry. Sorry.\n\n12 So we don't need any of the briefing related to the witness. So I think I'm not expecting anything tonight; is that true? It's like saying, oh, look, no traffic, but --\n\n15 MS. MOE: Nothing anticipated from the government, your Honor.\n\n17 THE COURT: Okay.\n\n18 MS. MENNINGER: Nor from us.\n\n19 THE COURT: I thank everyone. Goodnight.\n\n20 (Adjourned to December 8, 2021 at 8:45 a.m.)\n\n21 * * *",
      "position": "main"
    },
    {
      "type": "printed",
      "content": "SOUTHERN DISTRICT REPORTERS, P.C. (212) 805-0300",
      "position": "footer"
    },
    {
      "type": "printed",
      "content": "DOJ-OGR-00013275",
      "position": "footer"
    }
  ],
  "entities": {
    "people": [
      "MS. COMEY",
      "MR. PAGLIUCA",
      "MS. MOE",
      "MS. MENNINGER"
    ],
    "organizations": [
      "SOUTHERN DISTRICT REPORTERS, P.C."
    ],
    "locations": [],
    "dates": [
      "08/10/22",
      "December 8, 2021"
    ],
    "reference_numbers": [
      "1:20-cr-00330-PAE",
      "753",
      "DOJ-OGR-00013275"
    ]
  },
  "additional_notes": "The document appears to be a court transcript with a clear and legible format. There are no visible redactions or damage."
}