{
  "document_metadata": {
    "page_number": "159",
    "document_number": "759",
    "date": "08/10/22",
    "document_type": "court transcript",
    "has_handwriting": false,
    "has_stamps": false
  },
  "full_text": "Case 1:20-cr-00330-PAE Document 759 Filed 08/10/22 Page 159 of 267 2187\nLCAVMAX6 A. Farmer - cross\n1 about it when I returned from New Mexico.\n2 Q. When you got back from Thailand, you said you were not raped?\n3 A. That's right.\n4 Q. You were not sexually abused?\n5 A. I said I was not raped.\n6 Q. And you meant you were not sexually abused; correct?\n7 MS. POMERANTZ: Objection, your Honor.\n8 THE COURT: Overruled.\n9 A. I think those are two different things.\n10 Q. You spoke to the government on May 9th of 2020, right?\n11 A. Yes.\n12 Q. And I want to jump ahead about a month from that. In late\n13 June of 2020, the Epstein Victims Compensation Fund opened, right?\n14 A. I don't remember when it opened, but yes.\n15 MS. MENNINGER: Okay. I'd like to have the witness look at AF-12.\n16 THE COURT: The government has it?\n17 MS. MENNINGER: I will get them a copy, your Honor. I believe they do, but I'll give them a copy.\n18 If I could have the witness take a look at the first paragraph of text and just tell me if that refreshes your memory about when the Epstein Victims Compensation Program opened.\n19 SOUTHERN DISTRICT REPORTERS, P.C. (212) 805-0300\n20 DOJ-OGR-00013750",
  "text_blocks": [
    {
      "type": "printed",
      "content": "Case 1:20-cr-00330-PAE Document 759 Filed 08/10/22 Page 159 of 267 2187",
      "position": "header"
    },
    {
      "type": "printed",
      "content": "LCAVMAX6 A. Farmer - cross",
      "position": "header"
    },
    {
      "type": "printed",
      "content": "about it when I returned from New Mexico.\nQ. When you got back from Thailand, you said you were not raped?\nA. That's right.\nQ. You were not sexually abused?\nA. I said I was not raped.\nQ. And you meant you were not sexually abused; correct?\nMS. POMERANTZ: Objection, your Honor.\nTHE COURT: Overruled.\nA. I think those are two different things.\nQ. You spoke to the government on May 9th of 2020, right?\nA. Yes.\nQ. And I want to jump ahead about a month from that. In late June of 2020, the Epstein Victims Compensation Fund opened, right?\nA. I don't remember when it opened, but yes.\nMS. MENNINGER: Okay. I'd like to have the witness look at AF-12.\nTHE COURT: The government has it?\nMS. MENNINGER: I will get them a copy, your Honor. I believe they do, but I'll give them a copy.\nIf I could have the witness take a look at the first paragraph of text and just tell me if that refreshes your memory about when the Epstein Victims Compensation Program opened.",
      "position": "main"
    },
    {
      "type": "printed",
      "content": "SOUTHERN DISTRICT REPORTERS, P.C. (212) 805-0300",
      "position": "footer"
    },
    {
      "type": "printed",
      "content": "DOJ-OGR-00013750",
      "position": "footer"
    }
  ],
  "entities": {
    "people": [
      "A. Farmer",
      "MS. POMERANTZ",
      "MS. MENNINGER"
    ],
    "organizations": [
      "SOUTHERN DISTRICT REPORTERS, P.C."
    ],
    "locations": [
      "New Mexico",
      "Thailand"
    ],
    "dates": [
      "May 9th, 2020",
      "June 2020",
      "08/10/22"
    ],
    "reference_numbers": [
      "1:20-cr-00330-PAE",
      "759",
      "DOJ-OGR-00013750",
      "AF-12"
    ]
  },
  "additional_notes": "The document appears to be a court transcript with a clear and legible format. There are no visible redactions or damage."
}