{
  "document_metadata": {
    "page_number": "184",
    "document_number": "767",
    "date": "08/10/22",
    "document_type": "Court Transcript",
    "has_handwriting": false,
    "has_stamps": false
  },
  "full_text": "Case 1:20-cr-00330-PAE Document 767 Filed 08/10/22 Page 184 of 257 3018 LCKVMAX8 Charge reasonable doubt that the defendant participated in the sexual abuse of underage girls. Now it is time to hold her accountable. If you use your common sense, stay focused on the evidence, and follow Judge Nathan's instructions on the law, then you will reach the only verdict that is consistent with the evidence, the verdict that justice demands: The defendant is guilty. THE COURT: All right. Thank you, Ms. Comey. We will hand out the jury instructions to members of the jury who may read along while I read it to you. Please wait till I direct you. All right. Counsel, are you ready for me to read the charge? MR. ROHRBACH: Yes, your Honor. MS. STERNHEIM: Yes. THE COURT: Okay. Members of the jury, you may read along or not, as you like. I'm going to read you the jury instructions. Instructions begin on page 5, which is after the table of contents. Instruction No. 1. Role of the Court. You've now heard all of the evidence in the case, as well as the final arguments of the lawyers for the parties. My duty at this point is to instruct you as to the law. And it's your duty to accept these instructions of law and apply them to the facts as you determine them. SOUTHERN DISTRICT REPORTERS, P.C. (212) 805-0300 DOJ-OGR-00014584",
  "text_blocks": [
    {
      "type": "printed",
      "content": "Case 1:20-cr-00330-PAE Document 767 Filed 08/10/22 Page 184 of 257 3018 LCKVMAX8 Charge",
      "position": "header"
    },
    {
      "type": "printed",
      "content": "reasonable doubt that the defendant participated in the sexual abuse of underage girls. Now it is time to hold her accountable. If you use your common sense, stay focused on the evidence, and follow Judge Nathan's instructions on the law, then you will reach the only verdict that is consistent with the evidence, the verdict that justice demands: The defendant is guilty.",
      "position": "main"
    },
    {
      "type": "printed",
      "content": "THE COURT: All right. Thank you, Ms. Comey. We will hand out the jury instructions to members of the jury who may read along while I read it to you. Please wait till I direct you. All right. Counsel, are you ready for me to read the charge? MR. ROHRBACH: Yes, your Honor. MS. STERNHEIM: Yes. THE COURT: Okay. Members of the jury, you may read along or not, as you like. I'm going to read you the jury instructions. Instructions begin on page 5, which is after the table of contents. Instruction No. 1. Role of the Court. You've now heard all of the evidence in the case, as well as the final arguments of the lawyers for the parties. My duty at this point is to instruct you as to the law. And it's your duty to accept these instructions of law and apply them to the facts as you determine them.",
      "position": "main"
    },
    {
      "type": "printed",
      "content": "SOUTHERN DISTRICT REPORTERS, P.C. (212) 805-0300",
      "position": "footer"
    },
    {
      "type": "printed",
      "content": "DOJ-OGR-00014584",
      "position": "footer"
    }
  ],
  "entities": {
    "people": [
      "Judge Nathan",
      "Ms. Comey",
      "MR. ROHRBACH",
      "MS. STERNHEIM"
    ],
    "organizations": [
      "SOUTHERN DISTRICT REPORTERS, P.C."
    ],
    "locations": [],
    "dates": [
      "08/10/22"
    ],
    "reference_numbers": [
      "1:20-cr-00330-PAE",
      "767",
      "DOJ-OGR-00014584"
    ]
  },
  "additional_notes": "The document appears to be a court transcript with a clear and legible format. There are no visible redactions or damage."
}