{
  "document_metadata": {
    "page_number": "1",
    "document_number": "759",
    "date": "08/10/22",
    "document_type": "court document",
    "has_handwriting": false,
    "has_stamps": false
  },
  "full_text": "Case 1:20-cr-00330-PAE Document 759 Filed 08/10/22 Page 1 of 267 2028 LCACmax1 UNITED STATES DISTRICT COURT SOUTHERN DISTRICT OF NEW YORK -------------------------------x UNITED STATES OF AMERICA, v. 20 CR 330 (AJN) GHISLAINE MAXWELL, Defendant. Jury Trial -------------------------------x New York, N.Y. December 10, 2021 8:55 a.m. Before: HON. ALISON J. NATHAN, District Judge APPEARANCES DAMIAN WILLIAMS United States Attorney for the Southern District of New York BY: MAURENE COMEY ALISON MOE LARA POMERANTZ ANDREW ROHRBACH Assistant United States Attorneys HADDON MORGAN AND FOREMAN Attorneys for Defendant BY: JEFFREY S. PAGLIUCA LAURA A. MENNINGER -and- BOBBI C. STERNHEIM -and- COHEN & GRESSER BY: CHRISTIAN R. EVERDELL Also Present: Amanda Young, FBI Paul Byrne, NYPD Sunny Drescher, Paralegal, U.S. Attorney's Office Ann Lundberg, Paralegal, Haddon Morgan and Foreman SOUTHERN DISTRICT REPORTERS, P.C. (212) 805-0300 DOJ-OGR-00013592",
  "text_blocks": [
    {
      "type": "printed",
      "content": "Case 1:20-cr-00330-PAE Document 759 Filed 08/10/22 Page 1 of 267 2028 LCACmax1",
      "position": "header"
    },
    {
      "type": "printed",
      "content": "UNITED STATES DISTRICT COURT SOUTHERN DISTRICT OF NEW YORK -------------------------------x UNITED STATES OF AMERICA, v. 20 CR 330 (AJN) GHISLAINE MAXWELL, Defendant. Jury Trial -------------------------------x New York, N.Y. December 10, 2021 8:55 a.m. Before: HON. ALISON J. NATHAN, District Judge APPEARANCES",
      "position": "top"
    },
    {
      "type": "printed",
      "content": "DAMIAN WILLIAMS United States Attorney for the Southern District of New York BY: MAURENE COMEY ALISON MOE LARA POMERANTZ ANDREW ROHRBACH Assistant United States Attorneys HADDON MORGAN AND FOREMAN Attorneys for Defendant BY: JEFFREY S. PAGLIUCA LAURA A. MENNINGER -and- BOBBI C. STERNHEIM -and- COHEN & GRESSER BY: CHRISTIAN R. EVERDELL",
      "position": "middle"
    },
    {
      "type": "printed",
      "content": "Also Present: Amanda Young, FBI Paul Byrne, NYPD Sunny Drescher, Paralegal, U.S. Attorney's Office Ann Lundberg, Paralegal, Haddon Morgan and Foreman",
      "position": "middle"
    },
    {
      "type": "printed",
      "content": "SOUTHERN DISTRICT REPORTERS, P.C. (212) 805-0300",
      "position": "footer"
    },
    {
      "type": "printed",
      "content": "DOJ-OGR-00013592",
      "position": "footer"
    }
  ],
  "entities": {
    "people": [
      "GHISLAINE MAXWELL",
      "ALISON J. NATHAN",
      "DAMIAN WILLIAMS",
      "MAURENE COMEY",
      "ALISON MOE",
      "LARA POMERANTZ",
      "ANDREW ROHRBACH",
      "JEFFREY S. PAGLIUCA",
      "LAURA A. MENNINGER",
      "BOBBI C. STERNHEIM",
      "CHRISTIAN R. EVERDELL",
      "Amanda Young",
      "Paul Byrne",
      "Sunny Drescher",
      "Ann Lundberg"
    ],
    "organizations": [
      "UNITED STATES DISTRICT COURT",
      "SOUTHERN DISTRICT OF NEW YORK",
      "UNITED STATES OF AMERICA",
      "HADDON MORGAN AND FOREMAN",
      "COHEN & GRESSER",
      "FBI",
      "NYPD",
      "U.S. Attorney's Office",
      "SOUTHERN DISTRICT REPORTERS, P.C."
    ],
    "locations": [
      "New York"
    ],
    "dates": [
      "December 10, 2021",
      "08/10/22"
    ],
    "reference_numbers": [
      "1:20-cr-00330-PAE",
      "20 CR 330 (AJN)",
      "759",
      "DOJ-OGR-00013592"
    ]
  },
  "additional_notes": "The document appears to be a court transcript from the United States District Court for the Southern District of New York. The document is well-formatted and legible, with no visible redactions or damage."
}