{
  "document_metadata": {
    "page_number": "42",
    "document_number": "759",
    "date": "08/10/22",
    "document_type": "court transcript",
    "has_handwriting": false,
    "has_stamps": false
  },
  "full_text": "Case 1:20-cr-00330-PAE Document 759 Filed 08/10/22 Page 42 of 267 2070 LCAVMAX2 A. Farmer - direct (Government's Exhibit 102 received in evidence) MS. POMERANTZ: Your Honor, may we publish at this time? THE COURT: You may. Q. Annie, how old were you at the time this photograph was taken? A. I was 16 years old. Q. Where was the photograph taken? A. In my apartment. Q. Who invited you on this trip to New Mexico? A. Epstein invited me. Q. How did you learn you were going to be allowed to go on this trip to New Mexico? A. My best recollection is from my mom, that we had talked about it. Q. Who, if anyone, did you understand you would be seeing in New Mexico? MS. MENNINGER: Objection. Foundation, your Honor, hearsay or not. THE COURT: Sustained. Q. In the spring of 1996, did there come a time when you learned that you would be going to New Mexico? A. Yes. Q. I think you mentioned you learned about that from your mother; is that right? SOUTHERN DISTRICT REPORTERS, P.C. (212) 805-0300 DOJ-OGR-00013633",
  "text_blocks": [
    {
      "type": "printed",
      "content": "Case 1:20-cr-00330-PAE Document 759 Filed 08/10/22 Page 42 of 267 2070 LCAVMAX2",
      "position": "header"
    },
    {
      "type": "printed",
      "content": "A. Farmer - direct (Government's Exhibit 102 received in evidence) MS. POMERANTZ: Your Honor, may we publish at this time? THE COURT: You may. Q. Annie, how old were you at the time this photograph was taken? A. I was 16 years old. Q. Where was the photograph taken? A. In my apartment. Q. Who invited you on this trip to New Mexico? A. Epstein invited me. Q. How did you learn you were going to be allowed to go on this trip to New Mexico? A. My best recollection is from my mom, that we had talked about it. Q. Who, if anyone, did you understand you would be seeing in New Mexico? MS. MENNINGER: Objection. Foundation, your Honor, hearsay or not. THE COURT: Sustained. Q. In the spring of 1996, did there come a time when you learned that you would be going to New Mexico? A. Yes. Q. I think you mentioned you learned about that from your mother; is that right?",
      "position": "main"
    },
    {
      "type": "printed",
      "content": "SOUTHERN DISTRICT REPORTERS, P.C. (212) 805-0300",
      "position": "footer"
    },
    {
      "type": "printed",
      "content": "DOJ-OGR-00013633",
      "position": "footer"
    }
  ],
  "entities": {
    "people": [
      "Annie",
      "Epstein",
      "MS. POMERANTZ",
      "MS. MENNINGER"
    ],
    "organizations": [
      "SOUTHERN DISTRICT REPORTERS, P.C."
    ],
    "locations": [
      "New Mexico"
    ],
    "dates": [
      "08/10/22",
      "1996"
    ],
    "reference_numbers": [
      "1:20-cr-00330-PAE",
      "759",
      "102",
      "DOJ-OGR-00013633"
    ]
  },
  "additional_notes": "The document appears to be a court transcript with a clear and legible format. There are no visible redactions or damage."
}