{
  "document_metadata": {
    "page_number": "206",
    "document_number": "759",
    "date": "08/10/22",
    "document_type": "court transcript",
    "has_handwriting": false,
    "has_stamps": false
  },
  "full_text": "Case 1:20-cr-00330-PAE Document 759 Filed 08/10/22 Page 206 of 267 2234 LCACmax7 Mulligan - direct 1 A. We dated on and off through the end of 2003. 2 Q. Did you keep in touch with Annie after you and Annie broke up? 3 A. Yes. 4 Q. What is the nature of your current relationship with Annie? 5 A. We're still friends. 6 Q. About how often do you and Annie communicate? 7 A. On average, probably about once a month. 8 Q. What, if any, conversations have you had with Annie about 9 the substance of your testimony here today? 10 A. None. 11 Q. Did you go to Annie's house while you were dating in high 12 school? 13 A. Yes. 14 Q. During the time you dated Annie in high school, who did 15 Annie live with? 16 A. She lived with her mom and her sister, Ashley. 17 Q. Based on your observations, what did you understand to be 18 Annie's family's financial circumstances? 19 A. Her mom was a single mom and always working. So I would 20 say she was struggling to make ends meet. 21 Q. Did there come a time when Annie spoke with you about a 22 trip Annie took to New York? 23 A. Yes. 24 Q. When did Annie first tell you about her trip to New York? 25 SOUTHERN DISTRICT REPORTERS, P.C. (212) 805-0300 DOJ-OGR-00013797",
  "text_blocks": [
    {
      "type": "printed",
      "content": "Case 1:20-cr-00330-PAE Document 759 Filed 08/10/22 Page 206 of 267 2234 LCACmax7 Mulligan - direct",
      "position": "header"
    },
    {
      "type": "printed",
      "content": "1 A. We dated on and off through the end of 2003. 2 Q. Did you keep in touch with Annie after you and Annie broke up? 3 A. Yes. 4 Q. What is the nature of your current relationship with Annie? 5 A. We're still friends. 6 Q. About how often do you and Annie communicate? 7 A. On average, probably about once a month. 8 Q. What, if any, conversations have you had with Annie about 9 the substance of your testimony here today? 10 A. None. 11 Q. Did you go to Annie's house while you were dating in high 12 school? 13 A. Yes. 14 Q. During the time you dated Annie in high school, who did 15 Annie live with? 16 A. She lived with her mom and her sister, Ashley. 17 Q. Based on your observations, what did you understand to be 18 Annie's family's financial circumstances? 19 A. Her mom was a single mom and always working. So I would 20 say she was struggling to make ends meet. 21 Q. Did there come a time when Annie spoke with you about a 22 trip Annie took to New York? 23 A. Yes. 24 Q. When did Annie first tell you about her trip to New York? 25",
      "position": "main"
    },
    {
      "type": "printed",
      "content": "SOUTHERN DISTRICT REPORTERS, P.C. (212) 805-0300 DOJ-OGR-00013797",
      "position": "footer"
    }
  ],
  "entities": {
    "people": [
      "Annie",
      "Ashley"
    ],
    "organizations": [
      "SOUTHERN DISTRICT REPORTERS, P.C."
    ],
    "locations": [
      "New York"
    ],
    "dates": [
      "2003",
      "08/10/22"
    ],
    "reference_numbers": [
      "1:20-cr-00330-PAE",
      "759",
      "DOJ-OGR-00013797"
    ]
  },
  "additional_notes": "The document appears to be a court transcript with a clear and legible format. There are no visible redactions or damage."
}