{
  "document_metadata": {
    "page_number": "34",
    "document_number": "755",
    "date": "08/10/22",
    "document_type": "court transcript",
    "has_handwriting": false,
    "has_stamps": false
  },
  "full_text": "Case 1:20-cr-00330-PAE Document 755 Filed 08/10/22 Page 34 of 262 1739\nLC8VMAX2 Shawn - direct\n1 THE COURT: All right. Ms. Gill, thank you. You're excused. You may step down.\n2 (Witness excused)\n3 THE COURT: The government may call its next witness.\n4 MS. COMEY: The government calls Shawn.\n5 THE COURT: The witness testifying under the name \"Shawn\" may come forward.\n6 SHAWN,\n7 called as a witness by the Government,\n8 having been duly sworn, testified as follows:\n9 THE COURT: You may be seated. Please remove your mask. This witness will be testifying under the name Shawn to protect the anonymity of a prior witness who I permitted to testify by her first name.\n10 I do remind the sketch artists that the exact likeness of Shawn not be drawn, please, in order to protect the anonymity of the other witness.\n11 Ms. Comey, you may inquire.\n12 MS. COMEY: Thank you, your Honor.\n13 May the witness remove his mask?\n14 THE COURT: Oh, I'm sorry. Yes.\n15 Shawn, please remove your mask.\n16 DIRECT EXAMINATION\n17 BY MS. COMEY:\n18 Q. Good morning.\n19 SOUTHERN DISTRICT REPORTERS, P.C. (212) 805-0300\n20 DOJ-OGR-00013312",
  "text_blocks": [
    {
      "type": "printed",
      "content": "Case 1:20-cr-00330-PAE Document 755 Filed 08/10/22 Page 34 of 262 1739",
      "position": "header"
    },
    {
      "type": "printed",
      "content": "LC8VMAX2 Shawn - direct",
      "position": "header"
    },
    {
      "type": "printed",
      "content": "1 THE COURT: All right. Ms. Gill, thank you. You're excused. You may step down.\n2 (Witness excused)\n3 THE COURT: The government may call its next witness.\n4 MS. COMEY: The government calls Shawn.\n5 THE COURT: The witness testifying under the name \"Shawn\" may come forward.\n6 SHAWN,\n7 called as a witness by the Government,\n8 having been duly sworn, testified as follows:\n9 THE COURT: You may be seated. Please remove your mask. This witness will be testifying under the name Shawn to protect the anonymity of a prior witness who I permitted to testify by her first name.\n10 I do remind the sketch artists that the exact likeness of Shawn not be drawn, please, in order to protect the anonymity of the other witness.\n11 Ms. Comey, you may inquire.\n12 MS. COMEY: Thank you, your Honor.\n13 May the witness remove his mask?\n14 THE COURT: Oh, I'm sorry. Yes.\n15 Shawn, please remove your mask.\n16 DIRECT EXAMINATION\n17 BY MS. COMEY:\n18 Q. Good morning.",
      "position": "main"
    },
    {
      "type": "printed",
      "content": "SOUTHERN DISTRICT REPORTERS, P.C. (212) 805-0300",
      "position": "footer"
    },
    {
      "type": "printed",
      "content": "DOJ-OGR-00013312",
      "position": "footer"
    }
  ],
  "entities": {
    "people": [
      "Ms. Gill",
      "Ms. Comey",
      "Shawn"
    ],
    "organizations": [
      "SOUTHERN DISTRICT REPORTERS, P.C."
    ],
    "locations": [],
    "dates": [
      "08/10/22"
    ],
    "reference_numbers": [
      "1:20-cr-00330-PAE",
      "755",
      "DOJ-OGR-00013312"
    ]
  },
  "additional_notes": "The document appears to be a court transcript with a clear and legible format. There are no visible redactions or damage."
}