{
  "document_metadata": {
    "page_number": "41",
    "document_number": "743",
    "date": "08/10/22",
    "document_type": "Court Transcript",
    "has_handwriting": false,
    "has_stamps": false
  },
  "full_text": "Case 1:20-cr-00330-PAE Document 743 Filed 08/10/22 Page 41 of 247 169 LBUVMAX2 Visoski - direct 1 And then once you continue further walking to the back of the aircraft, there was the master bedroom that had a queen-size bed and two captain's chairs inside there. And then you're still walking to the back of the aircraft, there was the master -- the master lavatory or the bathroom in the rear of the aircraft. MS. COMEY: Ms. Drescher, would you please pull up Government Exhibit 303 for the witness, the Court, and the parties. Q. Mr. Visoski, do you recognize this? A. Yes. Q. What is it? A. That is actually the round room I described with the round couch or divan inside it. And then further in the photo you could see the red couch which was his office. And further after that led into the bedroom. Q. Is this a fair and accurate depiction of a portion of the interior of Jeffrey Epstein's Boeing 727? A. Yes, it is. MS. COMEY: Your Honor, the government offers this in evidence. MR. EVERDELL: No objection. THE COURT: Government 303 is admitted. You may publish. (Government's Exhibit 303 received in evidence) SOUTHERN DISTRICT REPORTERS, P.C. (212) 805-0300 DOJ-OGR-00011813",
  "text_blocks": [
    {
      "type": "printed",
      "content": "Case 1:20-cr-00330-PAE Document 743 Filed 08/10/22 Page 41 of 247 169 LBUVMAX2 Visoski - direct",
      "position": "header"
    },
    {
      "type": "printed",
      "content": "1 And then once you continue further walking to the back of the aircraft, there was the master bedroom that had a queen-size bed and two captain's chairs inside there. And then you're still walking to the back of the aircraft, there was the master -- the master lavatory or the bathroom in the rear of the aircraft.",
      "position": "middle"
    },
    {
      "type": "printed",
      "content": "MS. COMEY: Ms. Drescher, would you please pull up Government Exhibit 303 for the witness, the Court, and the parties.",
      "position": "middle"
    },
    {
      "type": "printed",
      "content": "Q. Mr. Visoski, do you recognize this? A. Yes. Q. What is it? A. That is actually the round room I described with the round couch or divan inside it. And then further in the photo you could see the red couch which was his office. And further after that led into the bedroom.",
      "position": "middle"
    },
    {
      "type": "printed",
      "content": "Q. Is this a fair and accurate depiction of a portion of the interior of Jeffrey Epstein's Boeing 727? A. Yes, it is.",
      "position": "middle"
    },
    {
      "type": "printed",
      "content": "MS. COMEY: Your Honor, the government offers this in evidence. MR. EVERDELL: No objection. THE COURT: Government 303 is admitted. You may publish.",
      "position": "middle"
    },
    {
      "type": "printed",
      "content": "(Government's Exhibit 303 received in evidence)",
      "position": "middle"
    },
    {
      "type": "printed",
      "content": "SOUTHERN DISTRICT REPORTERS, P.C. (212) 805-0300 DOJ-OGR-00011813",
      "position": "footer"
    }
  ],
  "entities": {
    "people": [
      "Jeffrey Epstein",
      "Visoski",
      "Ms. Drescher",
      "Ms. Comey",
      "Mr. Everdell"
    ],
    "organizations": [
      "SOUTHERN DISTRICT REPORTERS, P.C."
    ],
    "locations": [],
    "dates": [
      "08/10/22"
    ],
    "reference_numbers": [
      "1:20-cr-00330-PAE",
      "743",
      "303",
      "247",
      "169",
      "212-805-0300",
      "DOJ-OGR-00011813"
    ]
  },
  "additional_notes": "The document appears to be a court transcript with a clear and legible format. There are no visible redactions or damage."
}