{
  "document_metadata": {
    "page_number": "178",
    "document_number": "747",
    "date": "08/10/22",
    "document_type": "court transcript",
    "has_handwriting": false,
    "has_stamps": false
  },
  "full_text": "Case 1:20-cr-00330-PAE Document 747 Filed 08/10/22 Page 178 of 228 854 LC2Qmax5 - corrected Alessi - Direct 1 So, Mr. Alessi, would you please, with the Court's permission, look at the binder next to you and look at Government Exhibit 52A for identification. Do you recognize this? 2 3 4 A. Yes. 5 6 Q. Did you compare this exhibit to a page in the book that's marked for identification as Government Exhibit 52 earlier today? 7 8 9 A. Yes, I did. 10 Q. And is Government Exhibit 52A a copy of that page from Government Exhibit 52? 11 12 MR. PAGLIUCA: Objection. Lack of foundation. 13 THE COURT: Mr. Alessi, will you look through each 14 page of the copy? 15 MS. COMEY: Your Honor, it's a single page. 16 THE COURT: I'm sorry. What page? 17 MS. COMEY: It's marked for identification as 18 Government Exhibit 52A. Oh, you want us to look through 19 Government Exhibit 52? 20 THE COURT: 52A is one page of 52? 21 MS. COMEY: Yes, your Honor. 22 THE COURT: And what number page is it? 23 MS. COMEY: The pages are not numbered, your Honor. 24 MR. PAGLIUCA: Can we have a sidebar, your Honor? 25 THE COURT: Actually, I'm going to break for the SOUTHERN DISTRICT REPORTERS, P.C. (212) 805-0300 DOJ-OGR-00012463",
  "text_blocks": [
    {
      "type": "printed",
      "content": "Case 1:20-cr-00330-PAE Document 747 Filed 08/10/22 Page 178 of 228 854 LC2Qmax5 - corrected Alessi - Direct",
      "position": "header"
    },
    {
      "type": "printed",
      "content": "SOUTHERN DISTRICT REPORTERS, P.C. (212) 805-0300",
      "position": "footer"
    },
    {
      "type": "printed",
      "content": "DOJ-OGR-00012463",
      "position": "footer"
    },
    {
      "type": "printed",
      "content": "1 So, Mr. Alessi, would you please, with the Court's permission, look at the binder next to you and look at Government Exhibit 52A for identification. Do you recognize this? 2 3 4 A. Yes. 5 6 Q. Did you compare this exhibit to a page in the book that's marked for identification as Government Exhibit 52 earlier today? 7 8 9 A. Yes, I did. 10 Q. And is Government Exhibit 52A a copy of that page from Government Exhibit 52? 11 12 MR. PAGLIUCA: Objection. Lack of foundation. 13 THE COURT: Mr. Alessi, will you look through each 14 page of the copy? 15 MS. COMEY: Your Honor, it's a single page. 16 THE COURT: I'm sorry. What page? 17 MS. COMEY: It's marked for identification as 18 Government Exhibit 52A. Oh, you want us to look through 19 Government Exhibit 52? 20 THE COURT: 52A is one page of 52? 21 MS. COMEY: Yes, your Honor. 22 THE COURT: And what number page is it? 23 MS. COMEY: The pages are not numbered, your Honor. 24 MR. PAGLIUCA: Can we have a sidebar, your Honor? 25 THE COURT: Actually, I'm going to break for the",
      "position": "main content"
    }
  ],
  "entities": {
    "people": [
      "Mr. Alessi",
      "MR. PAGLIUCA",
      "MS. COMEY"
    ],
    "organizations": [
      "SOUTHERN DISTRICT REPORTERS, P.C."
    ],
    "locations": [],
    "dates": [
      "08/10/22"
    ],
    "reference_numbers": [
      "1:20-cr-00330-PAE",
      "Document 747",
      "Government Exhibit 52",
      "Government Exhibit 52A",
      "DOJ-OGR-00012463"
    ]
  },
  "additional_notes": "The document appears to be a court transcript with a clear and legible format. There are no visible redactions or damage."
}