{
  "document_metadata": {
    "page_number": "119",
    "document_number": "759",
    "date": "08/10/22",
    "document_type": "court transcript",
    "has_handwriting": false,
    "has_stamps": false
  },
  "full_text": "Case 1:20-cr-00330-PAE Document 759 Filed 08/10/22 Page 119 of 267 2147\nLCAVMAX4 A. Farmer - cross\n1 THE COURT: Overruled.\n2 Q. Right?\n3 A. Right.\n4 Q. You wanted to be accurate?\n5 A. Yes.\n6 Q. So you checked it against dates and you checked it against other people's memories, right?\n8 A. Right.\n9 Q. That's how you make sure it's accurate?\n10 MS. POMERANTZ: Objection, your Honor.\n11 THE COURT: Overruled.\n12 Q. Right?\n13 A. That's how I make sure --\n14 Q. Your memory is accurate.\n15 A. In general?\n16 Q. In this case.\n17 A. In this case that's what I did, yes. I said that, yes.\n18 Q. Talking about things that happened 25 years ago, right?\n19 A. Right.\n20 Q. You also were trying to figure out or you were telling him about the dates of your trip to Thailand, Mr. Baker?\n22 A. That's right.\n23 Q. And you were able to tell Mr. Baker the dates of your trip to Thailand because you always remember you went on your birthday?\n25 SOUTHERN DISTRICT REPORTERS, P.C. (212) 805-0300\nDOJ-OGR-00013710",
  "text_blocks": [
    {
      "type": "printed",
      "content": "Case 1:20-cr-00330-PAE Document 759 Filed 08/10/22 Page 119 of 267 2147",
      "position": "header"
    },
    {
      "type": "printed",
      "content": "LCAVMAX4 A. Farmer - cross",
      "position": "header"
    },
    {
      "type": "printed",
      "content": "1 THE COURT: Overruled.\n2 Q. Right?\n3 A. Right.\n4 Q. You wanted to be accurate?\n5 A. Yes.\n6 Q. So you checked it against dates and you checked it against other people's memories, right?\n8 A. Right.\n9 Q. That's how you make sure it's accurate?\n10 MS. POMERANTZ: Objection, your Honor.\n11 THE COURT: Overruled.\n12 Q. Right?\n13 A. That's how I make sure --\n14 Q. Your memory is accurate.\n15 A. In general?\n16 Q. In this case.\n17 A. In this case that's what I did, yes. I said that, yes.\n18 Q. Talking about things that happened 25 years ago, right?\n19 A. Right.\n20 Q. You also were trying to figure out or you were telling him about the dates of your trip to Thailand, Mr. Baker?\n22 A. That's right.\n23 Q. And you were able to tell Mr. Baker the dates of your trip to Thailand because you always remember you went on your birthday?",
      "position": "main"
    },
    {
      "type": "printed",
      "content": "SOUTHERN DISTRICT REPORTERS, P.C. (212) 805-0300",
      "position": "footer"
    },
    {
      "type": "printed",
      "content": "DOJ-OGR-00013710",
      "position": "footer"
    }
  ],
  "entities": {
    "people": [
      "MS. POMERANTZ",
      "Mr. Baker"
    ],
    "organizations": [
      "SOUTHERN DISTRICT REPORTERS, P.C."
    ],
    "locations": [
      "Thailand"
    ],
    "dates": [
      "08/10/22",
      "25 years ago"
    ],
    "reference_numbers": [
      "1:20-cr-00330-PAE",
      "759",
      "DOJ-OGR-00013710"
    ]
  },
  "additional_notes": "The document appears to be a court transcript with a clear and legible format. There are no visible redactions or damage."
}