{
  "document_metadata": {
    "page_number": "52",
    "document_number": "759",
    "date": "08/10/22",
    "document_type": "court transcript",
    "has_handwriting": false,
    "has_stamps": false
  },
  "full_text": "Case 1:20-cr-00330-PAE Document 759 Filed 08/10/22 Page 52 of 267 2080\nLCAVMAX2\nA. Farmer - direct\nschool, and I was writing a paper about some British authors. And I remember bringing this up to her and talking to her about that. And I think just, you know, kind of general life things, what I was doing.\nQ. You mentioned that Epstein and Maxwell gave you a tour of the ranch. Did you leave the ranch that weekend?\nA. We did.\nQ. Where did you go?\nA. We went into town, and I remember we did a little bit of shopping. We went to a natural food store of some sort. And Ghislaine offered to buy me some product. I remember she bought me this henna hair lightening cream of some kind. And then on that same outing, we went to a western wear store where they had me try on cowboy boots and purchased a pair of cowboy boots for me.\nQ. When you said \"we went shopping,\" who went shopping?\nA. Epstein, Maxwell, and myself.\nQ. What did the cowboy boots look like?\nA. They were black leather pointy standard cowboy boots.\nQ. Who bought the boots for you?\nA. Epstein.\nQ. And who was present at the time of the boots being purchased?\nA. Maxwell as well.\nQ. Did you keep the cowboy boots?\nSOUTHERN DISTRICT REPORTERS, P.C. (212) 805-0300\nDOJ-OGR-00013643",
  "text_blocks": [
    {
      "type": "printed",
      "content": "Case 1:20-cr-00330-PAE Document 759 Filed 08/10/22 Page 52 of 267 2080",
      "position": "header"
    },
    {
      "type": "printed",
      "content": "LCAVMAX2\nA. Farmer - direct",
      "position": "header"
    },
    {
      "type": "printed",
      "content": "school, and I was writing a paper about some British authors. And I remember bringing this up to her and talking to her about that. And I think just, you know, kind of general life things, what I was doing.\nQ. You mentioned that Epstein and Maxwell gave you a tour of the ranch. Did you leave the ranch that weekend?\nA. We did.\nQ. Where did you go?\nA. We went into town, and I remember we did a little bit of shopping. We went to a natural food store of some sort. And Ghislaine offered to buy me some product. I remember she bought me this henna hair lightening cream of some kind. And then on that same outing, we went to a western wear store where they had me try on cowboy boots and purchased a pair of cowboy boots for me.\nQ. When you said \"we went shopping,\" who went shopping?\nA. Epstein, Maxwell, and myself.\nQ. What did the cowboy boots look like?\nA. They were black leather pointy standard cowboy boots.\nQ. Who bought the boots for you?\nA. Epstein.\nQ. And who was present at the time of the boots being purchased?\nA. Maxwell as well.\nQ. Did you keep the cowboy boots?",
      "position": "main content"
    },
    {
      "type": "printed",
      "content": "SOUTHERN DISTRICT REPORTERS, P.C. (212) 805-0300",
      "position": "footer"
    },
    {
      "type": "printed",
      "content": "DOJ-OGR-00013643",
      "position": "footer"
    }
  ],
  "entities": {
    "people": [
      "Epstein",
      "Maxwell",
      "Ghislaine",
      "Farmer"
    ],
    "organizations": [
      "SOUTHERN DISTRICT REPORTERS, P.C."
    ],
    "locations": [],
    "dates": [
      "08/10/22"
    ],
    "reference_numbers": [
      "1:20-cr-00330-PAE",
      "759",
      "DOJ-OGR-00013643"
    ]
  },
  "additional_notes": "The document appears to be a court transcript with a clear Q&A format. The content discusses a trip to a ranch and subsequent shopping activities involving Epstein and Maxwell."
}