{
  "document_metadata": {
    "page_number": "143",
    "document_number": "743",
    "date": "08/10/22",
    "document_type": "court transcript",
    "has_handwriting": false,
    "has_stamps": false
  },
  "full_text": "Case 1:20-cr-00330-PAE Document 743 Filed 08/10/22 Page 143 of 247 271 LBUVMAX4 Visoski - cross 1 Q. Good afternoon, Mr. Visoski. 2 A. Good afternoon, Mr. Everdell. 3 Q. I just want to begin with a quick question about the ranch, all right? 4 5 A. Yes. 6 Q. You testified before that it had a lot of acreage? 7 A. Yes. 8 Q. I think you said roughly 10,000 acres or so? 9 A. 10,000, yes. 10 Q. And there was a lot of open space on that ranch, right? 11 A. That's correct. 12 Q. And one of the things that guests, I think, typically like to do when they were there was to go hiking, right? 13 14 A. Correct. Yes. 15 Q. Lots of places they could go hiking on the ranch? 16 A. Sure they could, yes. 17 Q. But it's true, isn't it, that the property had a lot of rattlesnakes on it, isn't it? 18 19 A. Yes, there are several rattlesnakes, yes. 20 Q. Okay. And it was wild country out there. 21 A. Yes. 22 Q. Okay. And so if you were going to hike on this property, you needed proper footwear to go hiking, right? 23 24 A. Yes. 25 Q. All right. So people would typically wear boots to go SOUTHERN DISTRICT REPORTERS, P.C. (212) 805-0300 DOJ-OGR-00011915",
  "text_blocks": [
    {
      "type": "printed",
      "content": "Case 1:20-cr-00330-PAE Document 743 Filed 08/10/22 Page 143 of 247 271 LBUVMAX4 Visoski - cross",
      "position": "header"
    },
    {
      "type": "printed",
      "content": "1 Q. Good afternoon, Mr. Visoski. 2 A. Good afternoon, Mr. Everdell. 3 Q. I just want to begin with a quick question about the ranch, all right? 4 5 A. Yes. 6 Q. You testified before that it had a lot of acreage? 7 A. Yes. 8 Q. I think you said roughly 10,000 acres or so? 9 A. 10,000, yes. 10 Q. And there was a lot of open space on that ranch, right? 11 A. That's correct. 12 Q. And one of the things that guests, I think, typically like to do when they were there was to go hiking, right? 13 14 A. Correct. Yes. 15 Q. Lots of places they could go hiking on the ranch? 16 A. Sure they could, yes. 17 Q. But it's true, isn't it, that the property had a lot of rattlesnakes on it, isn't it? 18 19 A. Yes, there are several rattlesnakes, yes. 20 Q. Okay. And it was wild country out there. 21 A. Yes. 22 Q. Okay. And so if you were going to hike on this property, you needed proper footwear to go hiking, right? 23 24 A. Yes. 25 Q. All right. So people would typically wear boots to go",
      "position": "main"
    },
    {
      "type": "printed",
      "content": "SOUTHERN DISTRICT REPORTERS, P.C. (212) 805-0300 DOJ-OGR-00011915",
      "position": "footer"
    }
  ],
  "entities": {
    "people": [
      "Mr. Visoski",
      "Mr. Everdell"
    ],
    "organizations": [
      "SOUTHERN DISTRICT REPORTERS, P.C."
    ],
    "locations": [
      "the ranch"
    ],
    "dates": [
      "08/10/22"
    ],
    "reference_numbers": [
      "1:20-cr-00330-PAE",
      "743",
      "143",
      "247",
      "271",
      "DOJ-OGR-00011915"
    ]
  },
  "additional_notes": "The document appears to be a court transcript with a clear and legible format. There are no visible redactions or damage."
}