{
  "document_metadata": {
    "page_number": "29",
    "document_number": "745",
    "date": "08/10/22",
    "document_type": "court transcript",
    "has_handwriting": false,
    "has_stamps": false
  },
  "full_text": "Case 1:20-cr-00330-PAE Document 745 Filed 08/10/22 Page 29 of 264 435 LC1VMAX1 Jane - cross 1 Q. And this was a reference to you and your two brothers, right? 2 A. Yes. 3 Q. I also believe, just in case it wasn't audible, it said 4 that you and your two brothers came from a strong and loving 5 family background: is that right? 6 A. That's what it says. 7 Q. I want to turn to -- and we could show for the Court -- 8 what's been marked for identification as J-4. But you're 9 certainly welcome, Jane, to turn to that in paper form. 10 11 THE COURT: Not the jurors. 12 MS. MENNINGER: Not the jurors. 13 THE COURT: Please wait till I direct you. Please 14 wait till I direct you. You can close your binders. 15 Thank you. 16 MS. MENNINGER: It's going to come out again, I hope 17 soon. 18 BY MS. MENNINGER: 19 Q. Do you recognize this document? 20 A. I do not recognize the document per se. 21 Q. J-4? 22 A. But I recognize my signature. 23 Q. Okay. Do you believe that this is your application? 24 A. Yes. 25 Q. And to the same Interlochen Arts Camp? 26 SOUTHERN DISTRICT REPORTERS, P.C. (212) 805-0300 DOJ-OGR-00012049",
  "text_blocks": [
    {
      "type": "printed",
      "content": "Case 1:20-cr-00330-PAE Document 745 Filed 08/10/22 Page 29 of 264 435",
      "position": "header"
    },
    {
      "type": "handwritten",
      "content": "LC1VMAX1 Jane - cross",
      "position": "header"
    },
    {
      "type": "printed",
      "content": "1 Q. And this was a reference to you and your two brothers, right? 2 A. Yes. 3 Q. I also believe, just in case it wasn't audible, it said 4 that you and your two brothers came from a strong and loving 5 family background: is that right? 6 A. That's what it says. 7 Q. I want to turn to -- and we could show for the Court -- 8 what's been marked for identification as J-4. But you're 9 certainly welcome, Jane, to turn to that in paper form. 10 11 THE COURT: Not the jurors. 12 MS. MENNINGER: Not the jurors. 13 THE COURT: Please wait till I direct you. Please 14 wait till I direct you. You can close your binders. 15 Thank you. 16 MS. MENNINGER: It's going to come out again, I hope 17 soon. 18 BY MS. MENNINGER: 19 Q. Do you recognize this document? 20 A. I do not recognize the document per se. 21 Q. J-4? 22 A. But I recognize my signature. 23 Q. Okay. Do you believe that this is your application? 24 A. Yes. 25 Q. And to the same Interlochen Arts Camp?",
      "position": "main"
    },
    {
      "type": "printed",
      "content": "SOUTHERN DISTRICT REPORTERS, P.C. (212) 805-0300",
      "position": "footer"
    },
    {
      "type": "printed",
      "content": "DOJ-OGR-00012049",
      "position": "footer"
    }
  ],
  "entities": {
    "people": [
      "Jane",
      "MS. MENNINGER"
    ],
    "organizations": [
      "SOUTHERN DISTRICT REPORTERS, P.C.",
      "Interlochen Arts Camp"
    ],
    "locations": [],
    "dates": [
      "08/10/22"
    ],
    "reference_numbers": [
      "1:20-cr-00330-PAE",
      "745",
      "J-4",
      "DOJ-OGR-00012049"
    ]
  },
  "additional_notes": "The document appears to be a court transcript with a clear and readable format. There are no visible redactions or damage."
}