{
  "document_metadata": {
    "page_number": "179",
    "document_number": "743",
    "date": "08/10/22",
    "document_type": "court transcript",
    "has_handwriting": false,
    "has_stamps": false
  },
  "full_text": "Case 1:20-cr-00330-PAE Document 743 Filed 08/10/22 Page 179 of 247 307 LBUVMAX4 Jane - direct 1 Q. After that day that you just described, did there ever come a time when you saw Ghislaine Maxwell without her clothes on? 2 A. Yes. 3 Q. Approximately when was that? 4 A. Shortly after the first incident. 5 Q. Could you please describe for the jury what happened that day. 6 A. The three of us were just spending time together hanging out and talking. And then all of a sudden, in that same manner, just abruptly said, you know, Follow me. And we went upstairs. I followed them up this -- felt like a winding staircase, up into Jeffrey's bedroom. 7 Q. Once you got to the bedroom with Epstein and Maxwell that day, could you please describe for the jury what happened next. 8 A. They moved me over to the bed and took their clothes off and started to like sort of, like, fondle each other and sort of, like, kind of casually giggling about it. And I was just standing there. 9 And he asked me to take my top off. And then, you know, sort of just there were hands everywhere. And Jeffrey proceeded to masturbate again. And Ghislaine was like rubbing on him and kissing on him and, you know, fondling. And then that was it. 10 Q. After the incident that you just described, did your visits to Epstein's house in Palm Beach include sexual contact? 11 SOUTHERN DISTRICT REPORTERS, P.C. (212) 805-0300 DOJ-OGR-00011951",
  "text_blocks": [
    {
      "type": "printed",
      "content": "Case 1:20-cr-00330-PAE Document 743 Filed 08/10/22 Page 179 of 247 307 LBUVMAX4 Jane - direct",
      "position": "header"
    },
    {
      "type": "printed",
      "content": "1 Q. After that day that you just described, did there ever come a time when you saw Ghislaine Maxwell without her clothes on? 2 A. Yes. 3 Q. Approximately when was that? 4 A. Shortly after the first incident. 5 Q. Could you please describe for the jury what happened that day. 6 A. The three of us were just spending time together hanging out and talking. And then all of a sudden, in that same manner, just abruptly said, you know, Follow me. And we went upstairs. I followed them up this -- felt like a winding staircase, up into Jeffrey's bedroom. 7 Q. Once you got to the bedroom with Epstein and Maxwell that day, could you please describe for the jury what happened next. 8 A. They moved me over to the bed and took their clothes off and started to like sort of, like, fondle each other and sort of, like, kind of casually giggling about it. And I was just standing there. 9 And he asked me to take my top off. And then, you know, sort of just there were hands everywhere. And Jeffrey proceeded to masturbate again. And Ghislaine was like rubbing on him and kissing on him and, you know, fondling. And then that was it. 10 Q. After the incident that you just described, did your visits to Epstein's house in Palm Beach include sexual contact?",
      "position": "main"
    },
    {
      "type": "printed",
      "content": "SOUTHERN DISTRICT REPORTERS, P.C. (212) 805-0300",
      "position": "footer"
    },
    {
      "type": "printed",
      "content": "DOJ-OGR-00011951",
      "position": "footer"
    }
  ],
  "entities": {
    "people": [
      "Ghislaine Maxwell",
      "Jeffrey Epstein",
      "Jane"
    ],
    "organizations": [
      "SOUTHERN DISTRICT REPORTERS, P.C."
    ],
    "locations": [
      "Palm Beach"
    ],
    "dates": [
      "08/10/22"
    ],
    "reference_numbers": [
      "1:20-cr-00330-PAE",
      "743",
      "DOJ-OGR-00011951"
    ]
  },
  "additional_notes": "The document appears to be a court transcript with a witness describing incidents involving Ghislaine Maxwell and Jeffrey Epstein. The text is mostly printed, with no visible handwriting or stamps. The document is likely a photocopy or scan of an original transcript."
}