{
  "document_metadata": {
    "page_number": "86 of 247",
    "document_number": "743",
    "date": "08/10/22",
    "document_type": "court transcript",
    "has_handwriting": false,
    "has_stamps": false
  },
  "full_text": "Case 1:20-cr-00330-PAE Document 743 Filed 08/10/22 Page 86 of 247 214 LBUCmax3 Visoski - cross recollection again. If we could pull up 3527-007 at page 2 just for the Court, the deputy, and the witness, please. We'll direct your attention, Mr. Visoski, from the bottom if you count up six or seven lines, if you look at those entries right there. A. Yes. Q. Okay. And you can look to the left-hand side, as well, in terms of the date. A. Yes. Q. Does that refresh your recollection about flying in the month of August to Interlochen? A. Sure it does, yeah. This certainly would be a trip that we would do. I recognize the identifiers. So it would be in the trip that we would do during that timeframe, yes. Q. So, you recall, I believe, right, that Epstein eventually had a cabin at Interlochen; isn't that right? A. That is correct. Q. So he would be going there at the end of the summers to stay in his cabin and see the performances at the end of the Interlochen Summer Camp; isn't that right? A. It was my understanding, which it could have been hearsay information, that I thought the cabin was bought or built for Itzhak Perlman, but that was just a rumor I heard, but I don't know whether or not Mr. Epstein actually stayed in the cabin or he donated it to the Interlochen School. I don't know a whole SOUTHERN DISTRICT REPORTERS, P.C. (212) 805-0300 DOJ-OGR-00011858",
  "text_blocks": [
    {
      "type": "printed",
      "content": "Case 1:20-cr-00330-PAE Document 743 Filed 08/10/22 Page 86 of 247 214 LBUCmax3 Visoski - cross",
      "position": "header"
    },
    {
      "type": "printed",
      "content": "recollection again. If we could pull up 3527-007 at page 2 just for the Court, the deputy, and the witness, please. We'll direct your attention, Mr. Visoski, from the bottom if you count up six or seven lines, if you look at those entries right there. A. Yes. Q. Okay. And you can look to the left-hand side, as well, in terms of the date. A. Yes. Q. Does that refresh your recollection about flying in the month of August to Interlochen? A. Sure it does, yeah. This certainly would be a trip that we would do. I recognize the identifiers. So it would be in the trip that we would do during that timeframe, yes. Q. So, you recall, I believe, right, that Epstein eventually had a cabin at Interlochen; isn't that right? A. That is correct. Q. So he would be going there at the end of the summers to stay in his cabin and see the performances at the end of the Interlochen Summer Camp; isn't that right? A. It was my understanding, which it could have been hearsay information, that I thought the cabin was bought or built for Itzhak Perlman, but that was just a rumor I heard, but I don't know whether or not Mr. Epstein actually stayed in the cabin or he donated it to the Interlochen School. I don't know a whole",
      "position": "main"
    },
    {
      "type": "printed",
      "content": "SOUTHERN DISTRICT REPORTERS, P.C. (212) 805-0300",
      "position": "footer"
    },
    {
      "type": "printed",
      "content": "DOJ-OGR-00011858",
      "position": "footer"
    }
  ],
  "entities": {
    "people": [
      "Visoski",
      "Epstein",
      "Itzhak Perlman"
    ],
    "organizations": [
      "SOUTHERN DISTRICT REPORTERS, P.C.",
      "Interlochen School"
    ],
    "locations": [
      "Interlochen"
    ],
    "dates": [
      "08/10/22",
      "August"
    ],
    "reference_numbers": [
      "1:20-cr-00330-PAE",
      "743",
      "3527-007",
      "DOJ-OGR-00011858"
    ]
  },
  "additional_notes": "The document appears to be a court transcript with a clear and legible format. There are no visible redactions or damage."
}