{
  "document_metadata": {
    "page_number": "39",
    "document_number": "753",
    "date": "08/10/22",
    "document_type": "court transcript",
    "has_handwriting": false,
    "has_stamps": false
  },
  "full_text": "Case 1:20-cr-00330-PAE Document 753 Filed 08/10/22 Page 39 of 264 1465 LC7VMAX1 Meder - cross 1 Q. And then you reviewed those photographs; correct? 2 A. Correct. 3 Q. And some of those photographs were shown to the jury today; correct? 4 A. Yes. 5 Q. Those CDs that you copied photographs from onto a computer, 6 those CDs were found all around the Epstein home; correct? 7 8 MS. COMEY: Objection. Foundation. 9 THE COURT: Sustained. 10 Q. Did you prepare for the government a location report for 11 the exhibits that were just shown to the jury? 12 A. I prepared a report showing the evidence item number of 13 where it came from. 14 Q. Within Mr. Epstein's house; correct? 15 A. Yes. 16 Q. So you found which CDs were found in which room of 17 Mr. Epstein's house; correct? 18 A. Yes, according to the evidence item numbers. 19 Q. Right. So you weren't at the house when the CDs were 20 seized, right? 21 A. I was on both searches. 22 Q. You were on both searches? 23 A. I was. 24 Q. Okay. And so you personally compared the numbers of these 25 CDs to where they were located in Mr. Epstein's house, right? SOUTHERN DISTRICT REPORTERS, P.C. (212) 805-0300 DOJ-OGR-00013052",
  "text_blocks": [
    {
      "type": "printed",
      "content": "Case 1:20-cr-00330-PAE Document 753 Filed 08/10/22 Page 39 of 264 1465 LC7VMAX1 Meder - cross",
      "position": "header"
    },
    {
      "type": "printed",
      "content": "1 Q. And then you reviewed those photographs; correct? 2 A. Correct. 3 Q. And some of those photographs were shown to the jury today; correct? 4 A. Yes. 5 Q. Those CDs that you copied photographs from onto a computer, 6 those CDs were found all around the Epstein home; correct? 7 8 MS. COMEY: Objection. Foundation. 9 THE COURT: Sustained. 10 Q. Did you prepare for the government a location report for 11 the exhibits that were just shown to the jury? 12 A. I prepared a report showing the evidence item number of 13 where it came from. 14 Q. Within Mr. Epstein's house; correct? 15 A. Yes. 16 Q. So you found which CDs were found in which room of 17 Mr. Epstein's house; correct? 18 A. Yes, according to the evidence item numbers. 19 Q. Right. So you weren't at the house when the CDs were 20 seized, right? 21 A. I was on both searches. 22 Q. You were on both searches? 23 A. I was. 24 Q. Okay. And so you personally compared the numbers of these 25 CDs to where they were located in Mr. Epstein's house, right?",
      "position": "main"
    },
    {
      "type": "printed",
      "content": "SOUTHERN DISTRICT REPORTERS, P.C. (212) 805-0300",
      "position": "footer"
    },
    {
      "type": "printed",
      "content": "DOJ-OGR-00013052",
      "position": "footer"
    }
  ],
  "entities": {
    "people": [
      "Meder",
      "Epstein",
      "Comey"
    ],
    "organizations": [
      "SOUTHERN DISTRICT REPORTERS, P.C."
    ],
    "locations": [
      "Epstein home"
    ],
    "dates": [
      "08/10/22"
    ],
    "reference_numbers": [
      "1:20-cr-00330-PAE",
      "753",
      "DOJ-OGR-00013052"
    ]
  },
  "additional_notes": "The document appears to be a court transcript with a clear and legible format. There are no visible redactions or damage."
}