{
  "document_metadata": {
    "page_number": "89",
    "document_number": "765",
    "date": "08/10/22",
    "document_type": "court transcript",
    "has_handwriting": false,
    "has_stamps": false
  },
  "full_text": "Case 1:20-cr-00330-PAE Document 765 Filed 08/10/22 Page 89 of 95 2827 LCIAMAX2ps\n\n1 Ms. Sternheim, go ahead.\n2 MS. STERNHEIM: Thank you, Judge. I don't know if the\n3 Court has found out if any of the jurors are having issues\n4 about staying later on Monday.\n5 THE COURT: They were all fine.\n6 MS. STERNHEIM: OK, because I just wanted to say that\n7 we are motivated, and I think the government would join me, in\n8 having us complete all of the closing arguments and the charge\n9 on Monday.\n10 THE COURT: Yes. I think we can do that.\n11 MS. COMEY: Yes, your Honor.\n12 THE COURT: Which gets to my next to-do item, which\n13 is -- I realize we don't have the relevant people, but I think\n14 Ms. Moe had indicated two to three hours.\n15 MS. COMEY: That's right, your Honor.\n16 THE COURT: Two sounds about right to me.\n17 MS. STERNHEIM: That's even better to us.\n18 THE COURT: I mean, length of trial, the complexity of\n19 the charges, this should be a two-hour closing.\n20 MS. COMEY: Your Honor, understood. We did, I will\n21 note, streamline our case significantly, and there were a\n22 number of exhibits that were not published to the jury, and I\n23 think we were explicitly told, that's for closing, when we\n24 wanted to do it with witnesses. So it's a little cumbersome,\n25 because there is more work to be done connecting up a number of\n\nSOUTHERN DISTRICT REPORTERS, P.C.\n(212) 805-0300\n\nDOJ-OGR-00014393",
  "text_blocks": [
    {
      "type": "printed",
      "content": "Case 1:20-cr-00330-PAE Document 765 Filed 08/10/22 Page 89 of 95 2827 LCIAMAX2ps",
      "position": "header"
    },
    {
      "type": "printed",
      "content": "1 Ms. Sternheim, go ahead.\n2 MS. STERNHEIM: Thank you, Judge. I don't know if the\n3 Court has found out if any of the jurors are having issues\n4 about staying later on Monday.\n5 THE COURT: They were all fine.\n6 MS. STERNHEIM: OK, because I just wanted to say that\n7 we are motivated, and I think the government would join me, in\n8 having us complete all of the closing arguments and the charge\n9 on Monday.\n10 THE COURT: Yes. I think we can do that.\n11 MS. COMEY: Yes, your Honor.\n12 THE COURT: Which gets to my next to-do item, which\n13 is -- I realize we don't have the relevant people, but I think\n14 Ms. Moe had indicated two to three hours.\n15 MS. COMEY: That's right, your Honor.\n16 THE COURT: Two sounds about right to me.\n17 MS. STERNHEIM: That's even better to us.\n18 THE COURT: I mean, length of trial, the complexity of\n19 the charges, this should be a two-hour closing.\n20 MS. COMEY: Your Honor, understood. We did, I will\n21 note, streamline our case significantly, and there were a\n22 number of exhibits that were not published to the jury, and I\n23 think we were explicitly told, that's for closing, when we\n24 wanted to do it with witnesses. So it's a little cumbersome,\n25 because there is more work to be done connecting up a number of",
      "position": "main"
    },
    {
      "type": "printed",
      "content": "SOUTHERN DISTRICT REPORTERS, P.C.\n(212) 805-0300",
      "position": "footer"
    },
    {
      "type": "printed",
      "content": "DOJ-OGR-00014393",
      "position": "footer"
    }
  ],
  "entities": {
    "people": [
      "Ms. Sternheim",
      "Judge",
      "Ms. Comey",
      "Ms. Moe"
    ],
    "organizations": [
      "SOUTHERN DISTRICT REPORTERS, P.C.",
      "DOJ"
    ],
    "locations": [],
    "dates": [
      "08/10/22"
    ],
    "reference_numbers": [
      "1:20-cr-00330-PAE",
      "765",
      "DOJ-OGR-00014393"
    ]
  },
  "additional_notes": "The document is a court transcript with a clear and readable format. The text is mostly printed, with no visible handwriting or stamps. The footer contains the name and contact information of the reporting agency and a reference number."
}