{
  "document_metadata": {
    "page_number": "106",
    "document_number": "753",
    "date": "08/10/22",
    "document_type": "court transcript",
    "has_handwriting": false,
    "has_stamps": false
  },
  "full_text": "Case 1:20-cr-00330-PAE Document 753 Filed 08/10/22 Page 106 of 264 1532\nLC7VMAX3 Carolyn - direct\n1 Q. When you got a cab or a car was sent for you, how did you know that those cars were on the way?\n2 A. I was told.\n3 Q. By who?\n4 A. Either Maxwell or Sarah, whoever called to schedule the appointment.\n5 Q. What would they say?\n6 A. That we would be sending a cab or a Town Car.\n7 Q. Did Shawn ever go inside Jeffrey Epstein's house when he drove you there?\n8 A. No.\n9 Q. Who, if anyone, did Shawn meet outside of Jeffrey Epstein's house when he went with you there?\n10 MR. PAGLIUCA: Objection.\n11 Lack of foundation, your Honor, under 602.\n12 THE COURT: Sustained.\n13 Q. When you and Shawn were together at Jeffrey Epstein's house, did you ever see someone else?\n14 A. When we were together at Mr. Epstein's house, yes.\n15 Q. Who did you see?\n16 A. I mean, he didn't go inside.\n17 Q. But when you were outside, did you ever see anyone?\n18 A. Yes, Mr. Epstein.\n19 Q. How many times did you see Mr. Epstein when Shawn was with you?\n20 SOUTHERN DISTRICT REPORTERS, P.C. (212) 805-0300\nDOJ-OGR-00013119",
  "text_blocks": [
    {
      "type": "printed",
      "content": "Case 1:20-cr-00330-PAE Document 753 Filed 08/10/22 Page 106 of 264 1532",
      "position": "header"
    },
    {
      "type": "printed",
      "content": "LC7VMAX3 Carolyn - direct",
      "position": "header"
    },
    {
      "type": "printed",
      "content": "1 Q. When you got a cab or a car was sent for you, how did you know that those cars were on the way?\n2 A. I was told.\n3 Q. By who?\n4 A. Either Maxwell or Sarah, whoever called to schedule the appointment.\n5 Q. What would they say?\n6 A. That we would be sending a cab or a Town Car.\n7 Q. Did Shawn ever go inside Jeffrey Epstein's house when he drove you there?\n8 A. No.\n9 Q. Who, if anyone, did Shawn meet outside of Jeffrey Epstein's house when he went with you there?\n10 MR. PAGLIUCA: Objection.\n11 Lack of foundation, your Honor, under 602.\n12 THE COURT: Sustained.\n13 Q. When you and Shawn were together at Jeffrey Epstein's house, did you ever see someone else?\n14 A. When we were together at Mr. Epstein's house, yes.\n15 Q. Who did you see?\n16 A. I mean, he didn't go inside.\n17 Q. But when you were outside, did you ever see anyone?\n18 A. Yes, Mr. Epstein.\n19 Q. How many times did you see Mr. Epstein when Shawn was with you?",
      "position": "main"
    },
    {
      "type": "printed",
      "content": "SOUTHERN DISTRICT REPORTERS, P.C. (212) 805-0300",
      "position": "footer"
    },
    {
      "type": "printed",
      "content": "DOJ-OGR-00013119",
      "position": "footer"
    }
  ],
  "entities": {
    "people": [
      "Carolyn",
      "Maxwell",
      "Sarah",
      "Shawn",
      "Jeffrey Epstein",
      "Mr. Epstein",
      "Mr. Pagliuca"
    ],
    "organizations": [
      "SOUTHERN DISTRICT REPORTERS, P.C."
    ],
    "locations": [],
    "dates": [
      "08/10/22"
    ],
    "reference_numbers": [
      "1:20-cr-00330-PAE",
      "753",
      "DOJ-OGR-00013119"
    ]
  },
  "additional_notes": "The document appears to be a court transcript with a clear and legible format. There are no visible redactions or damage."
}