{
  "document_metadata": {
    "page_number": "16 of 29",
    "document_number": "773",
    "date": "08/10/22",
    "document_type": "court document",
    "has_handwriting": false,
    "has_stamps": false
  },
  "full_text": "Case 1:20-cr-00330-PAE Document 773 Filed 08/10/22 Page 16 of 29 3133 LCRVMAXT\n1    to New Mexico, where/if there was an intent for Jane to engage\n2    in sexual activity. So there is still an open question in\n3    their minds about whether the flight to New Mexico, that\n4    travel, was for the purpose of engaging in illegal sexual\n5    activity.\n6        But they are now considering whether the flight out of\n7    New Mexico, if Ms. Maxwell had any -- did anything to do with\n8    that flight, with arranging that flight, could we convict her\n9    on that count alone. Because there is no, I think, evidence\n10   that she arranged the flight going to New Mexico; instead, they\n11   are considering now whether there's any evidence that she may\n12   have arranged the flight out of New Mexico. And is that enough\n13   to provide a conviction on Count Two? And I think the answer\n14   to that is pretty clearly no -- I'm sorry, Count Four I should\n15   have said, not Count Two. Because there's no evidence of that.\n16       And there is also -- there is no -- in the\n17   instructions themselves, that would not be a significant or\n18   motivating purpose for that travel across state lines. That\n19   would simply be for her to return home. That's not travel for\n20   the purpose of engaging in illegal sexual activity.\n21       MS. MOE: Your Honor, I think this colloquy\n22   illustrates how confusing the note is. We are now guessing at\n23   what hypothetical facts the jury is talking about; and then\n24   guessing hypothetically what their legal question is on top of\n25   that. And I think we're compounding guesswork, what this\n\nSOUTHERN DISTRICT REPORTERS, P.C.\n(212) 805-0300\nDOJ-OGR-00014702",
  "text_blocks": [
    {
      "type": "printed",
      "content": "Case 1:20-cr-00330-PAE Document 773 Filed 08/10/22 Page 16 of 29 3133 LCRVMAXT",
      "position": "header"
    },
    {
      "type": "printed",
      "content": "1    to New Mexico, where/if there was an intent for Jane to engage\n2    in sexual activity. So there is still an open question in\n3    their minds about whether the flight to New Mexico, that\n4    travel, was for the purpose of engaging in illegal sexual\n5    activity.\n6        But they are now considering whether the flight out of\n7    New Mexico, if Ms. Maxwell had any -- did anything to do with\n8    that flight, with arranging that flight, could we convict her\n9    on that count alone. Because there is no, I think, evidence\n10   that she arranged the flight going to New Mexico; instead, they\n11   are considering now whether there's any evidence that she may\n12   have arranged the flight out of New Mexico. And is that enough\n13   to provide a conviction on Count Two? And I think the answer\n14   to that is pretty clearly no -- I'm sorry, Count Four I should\n15   have said, not Count Two. Because there's no evidence of that.\n16       And there is also -- there is no -- in the\n17   instructions themselves, that would not be a significant or\n18   motivating purpose for that travel across state lines. That\n19   would simply be for her to return home. That's not travel for\n20   the purpose of engaging in illegal sexual activity.",
      "position": "main"
    },
    {
      "type": "printed",
      "content": "21       MS. MOE: Your Honor, I think this colloquy\n22   illustrates how confusing the note is. We are now guessing at\n23   what hypothetical facts the jury is talking about; and then\n24   guessing hypothetically what their legal question is on top of\n25   that. And I think we're compounding guesswork, what this",
      "position": "main"
    },
    {
      "type": "printed",
      "content": "SOUTHERN DISTRICT REPORTERS, P.C.\n(212) 805-0300",
      "position": "footer"
    },
    {
      "type": "printed",
      "content": "DOJ-OGR-00014702",
      "position": "footer"
    }
  ],
  "entities": {
    "people": [
      "Jane",
      "Ms. Maxwell",
      "MS. MOE"
    ],
    "organizations": [
      "SOUTHERN DISTRICT REPORTERS, P.C."
    ],
    "locations": [
      "New Mexico"
    ],
    "dates": [
      "08/10/22"
    ],
    "reference_numbers": [
      "1:20-cr-00330-PAE",
      "773",
      "DOJ-OGR-00014702",
      "Count Two",
      "Count Four"
    ]
  },
  "additional_notes": "The document appears to be a court transcript with a discussion about a case involving Ms. Maxwell and the intent behind travel to New Mexico. The text is mostly printed, with no visible handwriting or stamps. The footer contains information about the court reporters and a reference number."
}