{
  "document_metadata": {
    "page_number": "68",
    "document_number": "751",
    "date": "08/10/22",
    "document_type": "court transcript",
    "has_handwriting": false,
    "has_stamps": false
  },
  "full_text": "Case 1:20-cr-00330-PAE Document 751 Filed 08/10/22 Page 68 of 261 1208 LC6VMAX2 Kate - direct 1 immigration visa? 2 A. No. 3 Q. I'm going to switch gears. 4 Have you participated in a compensation fund called 5 the Epstein's Victims' Compensation Program? 6 A. Yes. 7 Q. What did you do as part of that fund? 8 A. I had an interview with a forensic psychologist and I 9 submitted a claim form. 10 Q. How much money did the fund pay you? 11 A. $3.25 million. 12 Q. Did that money come from the Estate of Jeffrey Epstein? 13 A. Yes. 14 Q. Has that money been wired to you already? 15 A. Not that total amount. 16 Q. But a portion of that has been? 17 A. Yes. 18 Q. As part of receiving that money, did you have to sign a 19 waiver agreeing not to sue any of Epstein's employees? 20 A. Yes. 21 Q. You mentioned that you didn't -- you weren't wired the 22 total amount. What happened to the rest of it? 23 A. The rest went to my attorneys. 24 Q. Have you ever sued Maxwell? 25 A. No. SOUTHERN DISTRICT REPORTERS, P.C. (212) 805-0300 DOJ-OGR-00012819",
  "text_blocks": [
    {
      "type": "printed",
      "content": "Case 1:20-cr-00330-PAE Document 751 Filed 08/10/22 Page 68 of 261 1208",
      "position": "header"
    },
    {
      "type": "printed",
      "content": "LC6VMAX2 Kate - direct",
      "position": "header"
    },
    {
      "type": "printed",
      "content": "1 immigration visa? 2 A. No. 3 Q. I'm going to switch gears. 4 Have you participated in a compensation fund called 5 the Epstein's Victims' Compensation Program? 6 A. Yes. 7 Q. What did you do as part of that fund? 8 A. I had an interview with a forensic psychologist and I 9 submitted a claim form. 10 Q. How much money did the fund pay you? 11 A. $3.25 million. 12 Q. Did that money come from the Estate of Jeffrey Epstein? 13 A. Yes. 14 Q. Has that money been wired to you already? 15 A. Not that total amount. 16 Q. But a portion of that has been? 17 A. Yes. 18 Q. As part of receiving that money, did you have to sign a 19 waiver agreeing not to sue any of Epstein's employees? 20 A. Yes. 21 Q. You mentioned that you didn't -- you weren't wired the 22 total amount. What happened to the rest of it? 23 A. The rest went to my attorneys. 24 Q. Have you ever sued Maxwell? 25 A. No.",
      "position": "main"
    },
    {
      "type": "printed",
      "content": "SOUTHERN DISTRICT REPORTERS, P.C. (212) 805-0300",
      "position": "footer"
    },
    {
      "type": "printed",
      "content": "DOJ-OGR-00012819",
      "position": "footer"
    }
  ],
  "entities": {
    "people": [
      "Jeffrey Epstein",
      "Maxwell",
      "Kate"
    ],
    "organizations": [
      "Epstein's Victims' Compensation Program",
      "Estate of Jeffrey Epstein",
      "SOUTHERN DISTRICT REPORTERS, P.C."
    ],
    "locations": [],
    "dates": [
      "08/10/22"
    ],
    "reference_numbers": [
      "1:20-cr-00330-PAE",
      "751",
      "DOJ-OGR-00012819",
      "$3.25 million",
      "(212) 805-0300"
    ]
  },
  "additional_notes": "The document appears to be a court transcript with a clear and legible format. There are no visible redactions or damage."
}