{
  "document_metadata": {
    "page_number": "114",
    "document_number": "747",
    "date": "08/10/22",
    "document_type": "Court Transcript",
    "has_handwriting": false,
    "has_stamps": false
  },
  "full_text": "Case 1:20-cr-00330-PAE Document 747 Filed 08/10/22 Page 114 of 228 790 LC2VMAX4 Alessi - Direct 1 Can you see that? 2 A. Yes. 3 Q. And that's at the center of this page. 4 Can you describe this area of the house for us please. 5 A. Yes, this is the front entrance. 6 THE COURT: I'm sorry. Mr. Alessi, could you pull up 7 the microphone, please. Thank you. 8 THE WITNESS: Put it closer? 9 THE COURT: That's good. Thank you. 10 A. Okay. This is the front entrance. And it's a single door, 11 very tall. At the left of the door was a stairway going to the 12 second floor. Coming into the foyer, to the right is going 13 into the lake room or living room. 14 To your right you have Mr. Epstein desk -- 15 Q. I'm going to pause you right there, Mr. Alessi. 16 A. Yup. 17 Q. I'm going to clear the markings and circle now the room 18 labeled lake room. Can you please continue describing that 19 room. 20 A. Yes. Coming into the lake room, to the right against the 21 wall, there was Mr. Epstein desk. Behind the desk is where 22 stereo equipment and hundreds and hundreds of books of all the 23 way to the wall. This are -- is sliding doors. All the 24 sliding door is glass. 25 Q. And for the record, are you indicating the far right wall SOUTHERN DISTRICT REPORTERS, P.C. (212) 805-0300 DOJ-OGR-00012399",
  "text_blocks": [
    {
      "type": "printed",
      "content": "Case 1:20-cr-00330-PAE Document 747 Filed 08/10/22 Page 114 of 228 790 LC2VMAX4 Alessi - Direct",
      "position": "header"
    },
    {
      "type": "printed",
      "content": "1 Can you see that? 2 A. Yes. 3 Q. And that's at the center of this page. 4 Can you describe this area of the house for us please. 5 A. Yes, this is the front entrance. 6 THE COURT: I'm sorry. Mr. Alessi, could you pull up 7 the microphone, please. Thank you. 8 THE WITNESS: Put it closer? 9 THE COURT: That's good. Thank you. 10 A. Okay. This is the front entrance. And it's a single door, 11 very tall. At the left of the door was a stairway going to the 12 second floor. Coming into the foyer, to the right is going 13 into the lake room or living room. 14 To your right you have Mr. Epstein desk -- 15 Q. I'm going to pause you right there, Mr. Alessi. 16 A. Yup. 17 Q. I'm going to clear the markings and circle now the room 18 labeled lake room. Can you please continue describing that 19 room. 20 A. Yes. Coming into the lake room, to the right against the 21 wall, there was Mr. Epstein desk. Behind the desk is where 22 stereo equipment and hundreds and hundreds of books of all the 23 way to the wall. This are -- is sliding doors. All the 24 sliding door is glass. 25 Q. And for the record, are you indicating the far right wall",
      "position": "main"
    },
    {
      "type": "printed",
      "content": "SOUTHERN DISTRICT REPORTERS, P.C. (212) 805-0300",
      "position": "footer"
    },
    {
      "type": "printed",
      "content": "DOJ-OGR-00012399",
      "position": "footer"
    }
  ],
  "entities": {
    "people": [
      "Mr. Alessi",
      "Mr. Epstein"
    ],
    "organizations": [
      "SOUTHERN DISTRICT REPORTERS, P.C."
    ],
    "locations": [],
    "dates": [
      "08/10/22"
    ],
    "reference_numbers": [
      "1:20-cr-00330-PAE",
      "747",
      "DOJ-OGR-00012399"
    ]
  },
  "additional_notes": "The document appears to be a court transcript with a clear and readable format. There are no visible redactions or damage."
}