{
  "document_metadata": {
    "page_number": "172",
    "document_number": "753",
    "date": "08/10/22",
    "document_type": "Court Transcript",
    "has_handwriting": false,
    "has_stamps": false
  },
  "full_text": "Case 1:20-cr-00330-PAE Document 753 Filed 08/10/22 Page 172 of 264 LC7Cmax6 Carolyn - cross 1 Q. That's what you told the FBI in 2007; correct? 2 A. Yes. 3 Q. Okay. You then left the house with Ms. Roberts after 4 Mr. Epstein paid you $300; is that correct? 5 A. Yes, we left after. 6 Q. And then after you left, isn't it true that you got 7 Mr. Epstein's phone number from the phonebook? 8 A. No. 9 MR. PAGLIUCA: We're going to show the witness, 10 please, 3505-005, page 2, third paragraph, first sentence. 11 Q. Isn't it true that you told the FBI, in 2007, \"Carolyn 12 obtained Epstein's phone number from a telephone book.\" Do you 13 see that? 14 A. Yeah, the telephone book that you're talking about was my 15 personal book. It wasn't like a phonebook. 16 Q. Well, what you told the FBI -- 17 A. It was a telephone book with my personal numbers of friends 18 and loved ones. 19 Q. And you called to schedule a massage session by leaving a 20 message with Sarah. Do you see that? 21 A. Yes. 22 Q. And then Epstein returned your call; correct? 23 A. It was not Epstein who called me. 24 Q. Well, isn't it true -- 25 A. It was someone in Epstein's house that called me. SOUTHERN DISTRICT REPORTERS, P.C. (212) 805-0300 DOJ-OGR-00013185",
  "text_blocks": [
    {
      "type": "printed",
      "content": "Case 1:20-cr-00330-PAE Document 753 Filed 08/10/22 Page 172 of 264",
      "position": "header"
    },
    {
      "type": "handwritten",
      "content": "LC7Cmax6 Carolyn - cross",
      "position": "header"
    },
    {
      "type": "printed",
      "content": "1 Q. That's what you told the FBI in 2007; correct? 2 A. Yes. 3 Q. Okay. You then left the house with Ms. Roberts after 4 Mr. Epstein paid you $300; is that correct? 5 A. Yes, we left after. 6 Q. And then after you left, isn't it true that you got 7 Mr. Epstein's phone number from the phonebook? 8 A. No. 9 MR. PAGLIUCA: We're going to show the witness, 10 please, 3505-005, page 2, third paragraph, first sentence. 11 Q. Isn't it true that you told the FBI, in 2007, \"Carolyn 12 obtained Epstein's phone number from a telephone book.\" Do you 13 see that? 14 A. Yeah, the telephone book that you're talking about was my 15 personal book. It wasn't like a phonebook. 16 Q. Well, what you told the FBI -- 17 A. It was a telephone book with my personal numbers of friends 18 and loved ones. 19 Q. And you called to schedule a massage session by leaving a 20 message with Sarah. Do you see that? 21 A. Yes. 22 Q. And then Epstein returned your call; correct? 23 A. It was not Epstein who called me. 24 Q. Well, isn't it true -- 25 A. It was someone in Epstein's house that called me.",
      "position": "main"
    },
    {
      "type": "printed",
      "content": "SOUTHERN DISTRICT REPORTERS, P.C. (212) 805-0300",
      "position": "footer"
    },
    {
      "type": "printed",
      "content": "DOJ-OGR-00013185",
      "position": "footer"
    }
  ],
  "entities": {
    "people": [
      "FBI",
      "Ms. Roberts",
      "Mr. Epstein",
      "MR. PAGLIUCA",
      "Carolyn",
      "Sarah",
      "Epstein"
    ],
    "organizations": [
      "FBI",
      "SOUTHERN DISTRICT REPORTERS, P.C."
    ],
    "locations": [],
    "dates": [
      "2007",
      "08/10/22"
    ],
    "reference_numbers": [
      "1:20-cr-00330-PAE",
      "753",
      "3505-005",
      "DOJ-OGR-00013185"
    ]
  },
  "additional_notes": "The document appears to be a court transcript with a clear and legible format. There are no visible redactions or damage."
}