{
  "document_metadata": {
    "page_number": "240",
    "document_number": "751",
    "date": "08/10/22",
    "document_type": "court transcript",
    "has_handwriting": false,
    "has_stamps": false
  },
  "full_text": "Case 1:20-cr-00330-PAE Document 751 Filed 08/10/22 Page 240 of 261 1401 LC6Cmax7 Meder - direct 1 A. Yes. 2 Q. And within that case file number, how does the FBI categorize evidence within a single file? 3 A. We categorize them into 1B numbers. 4 Q. What is a 1B number? 5 A. A way to categorize pieces of evidence. Multiple pieces 6 can be put into one 1B number. 7 8 Q. I'd like to direct your attention to the summer of 2020. 9 Were you involved in reviewing particular CDs that summer? 10 A. Yes. 11 Q. For what case? 12 A. The Epstein and Maxwell investigation. 13 Q. Were those CDs logged under 1B numbers within that case's 14 FBI file? 15 A. Yes. 16 Q. Who else, if anyone, reviewed those CDs with you? 17 A. Special Agent Amanda Young. 18 Q. What did you and Special Agent Amanda Young do with those 19 CDs? 20 A. We copied and saved each disc onto the computer in our 21 computer lab. 22 Q. What types of files did you find on those CDs? 23 A. Photos. 24 Q. Could you explain to the jury how you processed each file 25 on those CDs? So, for example, if you had a CD labeled A, B, C SOUTHERN DISTRICT REPORTERS, P.C. (212) 805-0300 DOJ-OGR-00012991",
  "text_blocks": [
    {
      "type": "printed",
      "content": "Case 1:20-cr-00330-PAE Document 751 Filed 08/10/22 Page 240 of 261 1401 LC6Cmax7 Meder - direct",
      "position": "header"
    },
    {
      "type": "printed",
      "content": "1 A. Yes. 2 Q. And within that case file number, how does the FBI categorize evidence within a single file? 3 A. We categorize them into 1B numbers. 4 Q. What is a 1B number? 5 A. A way to categorize pieces of evidence. Multiple pieces 6 can be put into one 1B number. 7 8 Q. I'd like to direct your attention to the summer of 2020. 9 Were you involved in reviewing particular CDs that summer? 10 A. Yes. 11 Q. For what case? 12 A. The Epstein and Maxwell investigation. 13 Q. Were those CDs logged under 1B numbers within that case's 14 FBI file? 15 A. Yes. 16 Q. Who else, if anyone, reviewed those CDs with you? 17 A. Special Agent Amanda Young. 18 Q. What did you and Special Agent Amanda Young do with those 19 CDs? 20 A. We copied and saved each disc onto the computer in our 21 computer lab. 22 Q. What types of files did you find on those CDs? 23 A. Photos. 24 Q. Could you explain to the jury how you processed each file 25 on those CDs? So, for example, if you had a CD labeled A, B, C",
      "position": "main"
    },
    {
      "type": "printed",
      "content": "SOUTHERN DISTRICT REPORTERS, P.C. (212) 805-0300 DOJ-OGR-00012991",
      "position": "footer"
    }
  ],
  "entities": {
    "people": [
      "Amanda Young"
    ],
    "organizations": [
      "FBI",
      "SOUTHERN DISTRICT REPORTERS, P.C."
    ],
    "locations": [],
    "dates": [
      "08/10/22",
      "summer of 2020"
    ],
    "reference_numbers": [
      "1:20-cr-00330-PAE",
      "751",
      "DOJ-OGR-00012991"
    ]
  },
  "additional_notes": "The document appears to be a court transcript with a clear and legible format. There are no visible redactions or damage."
}