{
  "document_metadata": {
    "page_number": "106",
    "document_number": "761",
    "date": "08/10/22",
    "document_type": "court transcript",
    "has_handwriting": false,
    "has_stamps": false
  },
  "full_text": "Case 1:20-cr-00330-PAE Document 761 Filed 08/10/22 Page 106 of 246 2401 LCGVMAX3 Loftus - direct 1 A. That would be helpful, yes. 2 MS. STERNHEIM: With the Court's permission, I would 3 ask that Dr. Loftus be permitted to look at her CV, which is 4 Defendant's Exhibit EL-1, a copy of which has been provided to 5 the government and the Court. 6 THE COURT: Marked for identification? 7 MS. STERNHEIM: Yes. 8 MS. POMERANTZ: No objection, your Honor. 9 THE COURT: She may. 10 MS. STERNHEIM: Thank you. 11 BY MS. STERNHEIM: 12 Q. In addition to the degrees that you've just discussed, have 13 you ever received any honorary degrees? 14 A. I have received a number of honorary doctorates from 15 universities other than the ones I officially attended. 16 Q. Of those universities, are they all in the United States or 17 elsewhere as well? 18 A. Some of them are in the United States, like John Jay 19 College of Criminal Justice, which is one of the honorary 20 doctorates. But I also have an honorary doctorate from a 21 British university, from -- actually, I think a couple of 22 British universities, from the University of Oslo, from Haifa 23 University in Israel. And I was supposed to be awarded an 24 honorary doctorate by an Australian university, Australian 25 National University, where I was supposed to go to the SOUTHERN DISTRICT REPORTERS, P.C. (212) 805-0300 DOJ-OGR-00013965",
  "text_blocks": [
    {
      "type": "printed",
      "content": "Case 1:20-cr-00330-PAE Document 761 Filed 08/10/22 Page 106 of 246 2401 LCGVMAX3 Loftus - direct",
      "position": "header"
    },
    {
      "type": "printed",
      "content": "1 A. That would be helpful, yes. 2 MS. STERNHEIM: With the Court's permission, I would 3 ask that Dr. Loftus be permitted to look at her CV, which is 4 Defendant's Exhibit EL-1, a copy of which has been provided to 5 the government and the Court. 6 THE COURT: Marked for identification? 7 MS. STERNHEIM: Yes. 8 MS. POMERANTZ: No objection, your Honor. 9 THE COURT: She may. 10 MS. STERNHEIM: Thank you. 11 BY MS. STERNHEIM: 12 Q. In addition to the degrees that you've just discussed, have 13 you ever received any honorary degrees? 14 A. I have received a number of honorary doctorates from 15 universities other than the ones I officially attended. 16 Q. Of those universities, are they all in the United States or 17 elsewhere as well? 18 A. Some of them are in the United States, like John Jay 19 College of Criminal Justice, which is one of the honorary 20 doctorates. But I also have an honorary doctorate from a 21 British university, from -- actually, I think a couple of 22 British universities, from the University of Oslo, from Haifa 23 University in Israel. And I was supposed to be awarded an 24 honorary doctorate by an Australian university, Australian 25 National University, where I was supposed to go to the",
      "position": "main content"
    },
    {
      "type": "printed",
      "content": "SOUTHERN DISTRICT REPORTERS, P.C. (212) 805-0300",
      "position": "footer"
    },
    {
      "type": "printed",
      "content": "DOJ-OGR-00013965",
      "position": "footer"
    }
  ],
  "entities": {
    "people": [
      "Loftus",
      "Sternheim",
      "Pomerantz"
    ],
    "organizations": [
      "John Jay College of Criminal Justice",
      "University of Oslo",
      "Haifa University",
      "Australian National University",
      "SOUTHERN DISTRICT REPORTERS, P.C."
    ],
    "locations": [
      "United States",
      "Israel",
      "Australia",
      "Britain"
    ],
    "dates": [
      "08/10/22"
    ],
    "reference_numbers": [
      "1:20-cr-00330-PAE",
      "761",
      "DOJ-OGR-00013965"
    ]
  },
  "additional_notes": "The document appears to be a court transcript with a clear and readable format. There are no visible redactions or damage."
}