{
  "document_metadata": {
    "page_number": "16",
    "document_number": "767",
    "date": "08/10/22",
    "document_type": "Summations",
    "has_handwriting": false,
    "has_stamps": false
  },
  "full_text": "Case 1:20-cr-00330-PAE Document 767 Filed 08/10/22 Page 16 of 257 2849 LCKVMAX2 Summations - Ms. Moe as a result of their childhood experiences. She told you that childhood sexual abuse typically occurs in an established relationship by a perpetrator who's known to the victim. Dr. Rocchio explained to you that perpetrators are able to abuse kids by using a series of techniques called grooming. She walked you through the stages of grooming. Here they are: Identifying and selecting the child. Obtaining access and isolating the child. Engaging in manipulation in order to build trust and attachment. Desensitizing the child to physical touch and sexual content. And finally, maintaining control over the child to continue abuse and decrease the likelihood that the victim will report. So let's talk through the ways that Maxwell and Epstein ran this exact playbook. First, the ways that they selected these girls tells you that they were targeting vulnerable kids. It is not an accident that Jane and Kate and Annie and Carolyn all came from single-mother households. It is not an accident that all of their families were struggling in different ways. What that tells you is that Maxwell and Epstein selected these girls carefully. When Jane was 14, her father had just died and her SOUTHERN DISTRICT REPORTERS, P.C. (212) 805-0300 DOJ-OGR-00014416",
  "text_blocks": [
    {
      "type": "printed",
      "content": "Case 1:20-cr-00330-PAE Document 767 Filed 08/10/22 Page 16 of 257 2849 LCKVMAX2 Summations - Ms. Moe",
      "position": "header"
    },
    {
      "type": "printed",
      "content": "as a result of their childhood experiences. She told you that childhood sexual abuse typically occurs in an established relationship by a perpetrator who's known to the victim. Dr. Rocchio explained to you that perpetrators are able to abuse kids by using a series of techniques called grooming. She walked you through the stages of grooming. Here they are: Identifying and selecting the child. Obtaining access and isolating the child. Engaging in manipulation in order to build trust and attachment. Desensitizing the child to physical touch and sexual content. And finally, maintaining control over the child to continue abuse and decrease the likelihood that the victim will report.",
      "position": "top"
    },
    {
      "type": "printed",
      "content": "So let's talk through the ways that Maxwell and Epstein ran this exact playbook. First, the ways that they selected these girls tells you that they were targeting vulnerable kids. It is not an accident that Jane and Kate and Annie and Carolyn all came from single-mother households. It is not an accident that all of their families were struggling in different ways. What that tells you is that Maxwell and Epstein selected these girls carefully. When Jane was 14, her father had just died and her",
      "position": "middle"
    },
    {
      "type": "printed",
      "content": "SOUTHERN DISTRICT REPORTERS, P.C. (212) 805-0300",
      "position": "footer"
    },
    {
      "type": "printed",
      "content": "DOJ-OGR-00014416",
      "position": "footer"
    }
  ],
  "entities": {
    "people": [
      "Dr. Rocchio",
      "Maxwell",
      "Epstein",
      "Jane",
      "Kate",
      "Annie",
      "Carolyn",
      "Jane's father"
    ],
    "organizations": [
      "SOUTHERN DISTRICT REPORTERS, P.C."
    ],
    "locations": [],
    "dates": [
      "08/10/22"
    ],
    "reference_numbers": [
      "1:20-cr-00330-PAE",
      "767",
      "2849",
      "LCKVMAX2",
      "DOJ-OGR-00014416",
      "(212) 805-0300"
    ]
  },
  "additional_notes": "The document appears to be a court transcript or legal document related to the case against Maxwell and Epstein. The text discusses the grooming techniques used by perpetrators of childhood sexual abuse and how Maxwell and Epstein targeted vulnerable victims."
}