{
  "document_metadata": {
    "page_number": "16",
    "document_number": "751",
    "date": "08/10/22",
    "document_type": "court transcript",
    "has_handwriting": false,
    "has_stamps": false
  },
  "full_text": "Case 1:20-cr-00330-PAE Document 751 Filed 08/10/22 Page 16 of 261 1156 LC6Cmax1 the defense could read that stipulation before the calling of the next witness. MR. ROHRBACH: No objection. THE COURT: And just by background, I imagine you had just one or two questions left and the government said rather than having him come back, would you stipulate to testimony, you agreed, and that's the stipulation? MR. EVERDELL: Actually, we offered, Judge, because we didn't want him to have to travel back from Florida, but yes, that's how it worked. THE COURT: I appreciate both sides doing that. As you see, when I tell the jury we'll end at 5:00, we end at 5:00, but sometimes that produces issues. Obviously let me know if we're one or two questions away, but I appreciate the parties working together to aid that. So the suggestion is the jury comes out, I tell them that -- what would you like me to tell them, Mr. Everdell? MR. EVERDELL: The government can weigh in, but I would simply tell them that the parties have reached a stipulation about some additional testimony that the last witness you heard from, Sergeant Michael Dawson, would have given on the stand. For matters of convenience, we didn't want to call him back. So the parties have agreed to read in a stipulation about his additional testimony. THE COURT: And then the defense could read the stip? SOUTHERN DISTRICT REPORTERS, P.C. (212) 805-0300 DOJ-OGR-00012767",
  "text_blocks": [
    {
      "type": "printed",
      "content": "Case 1:20-cr-00330-PAE Document 751 Filed 08/10/22 Page 16 of 261 1156 LC6Cmax1",
      "position": "header"
    },
    {
      "type": "printed",
      "content": "the defense could read that stipulation before the calling of the next witness. MR. ROHRBACH: No objection. THE COURT: And just by background, I imagine you had just one or two questions left and the government said rather than having him come back, would you stipulate to testimony, you agreed, and that's the stipulation? MR. EVERDELL: Actually, we offered, Judge, because we didn't want him to have to travel back from Florida, but yes, that's how it worked. THE COURT: I appreciate both sides doing that. As you see, when I tell the jury we'll end at 5:00, we end at 5:00, but sometimes that produces issues. Obviously let me know if we're one or two questions away, but I appreciate the parties working together to aid that. So the suggestion is the jury comes out, I tell them that -- what would you like me to tell them, Mr. Everdell? MR. EVERDELL: The government can weigh in, but I would simply tell them that the parties have reached a stipulation about some additional testimony that the last witness you heard from, Sergeant Michael Dawson, would have given on the stand. For matters of convenience, we didn't want to call him back. So the parties have agreed to read in a stipulation about his additional testimony. THE COURT: And then the defense could read the stip?",
      "position": "main content"
    },
    {
      "type": "printed",
      "content": "SOUTHERN DISTRICT REPORTERS, P.C. (212) 805-0300",
      "position": "footer"
    },
    {
      "type": "printed",
      "content": "DOJ-OGR-00012767",
      "position": "footer"
    }
  ],
  "entities": {
    "people": [
      "MR. ROHRBACH",
      "MR. EVERDELL",
      "Sergeant Michael Dawson"
    ],
    "organizations": [
      "SOUTHERN DISTRICT REPORTERS, P.C."
    ],
    "locations": [
      "Florida"
    ],
    "dates": [
      "08/10/22"
    ],
    "reference_numbers": [
      "1:20-cr-00330-PAE",
      "751",
      "DOJ-OGR-00012767"
    ]
  },
  "additional_notes": "The document appears to be a court transcript with clear and legible text. There are no visible redactions or damage."
}