{
  "document_metadata": {
    "page_number": "42",
    "document_number": "747",
    "date": "08/10/22",
    "document_type": "court transcript",
    "has_handwriting": false,
    "has_stamps": false
  },
  "full_text": "Case 1:20-cr-00330-PAE Document 747 Filed 08/10/22 Page 42 of 228 LC2VMAX2 Rocchio - Direct positive parts of the relationship and serve to remind the child that it wasn't all bad. Q. Dr. Rocchio, can you explain for the jury the next stage of grooming. A. So once this relationship of trust and attachment has been established, then the next stage involves a process of desensitization, which means slowly and gradually moving the line, and the perpetrator begins to define what is and is not normal. So with physical contact, for example, they may initially start by normalizing touch. Maybe, you know, touching on the arm, touching on the shoulder, giving hugs. That may escalate to, you know, sitting very close, touching a leg, giving a massage; normalizing the idea that in a relationship, you know, physical contact is happening. And at the same time, they're normalizing sexual material. So they may begin slowly by talking about sex, introducing the topic, telling sexual jokes. That may escalate to maybe showing risque movies, which might escalate to pornography. And then all of that will then escalate over time to combining the sexual activity to sexual touch in the form of sexual abuse. Q. Can you explain the fifth stage of grooming. A. So the fifth stage really is about maintaining the relationship. At this point now there's a dynamic of what's SOUTHERN DISTRICT REPORTERS, P.C. (212) 805-0300 DOJ-OGR-00012327",
  "text_blocks": [
    {
      "type": "printed",
      "content": "Case 1:20-cr-00330-PAE Document 747 Filed 08/10/22 Page 42 of 228 LC2VMAX2 Rocchio - Direct",
      "position": "header"
    },
    {
      "type": "printed",
      "content": "positive parts of the relationship and serve to remind the child that it wasn't all bad. Q. Dr. Rocchio, can you explain for the jury the next stage of grooming. A. So once this relationship of trust and attachment has been established, then the next stage involves a process of desensitization, which means slowly and gradually moving the line, and the perpetrator begins to define what is and is not normal. So with physical contact, for example, they may initially start by normalizing touch. Maybe, you know, touching on the arm, touching on the shoulder, giving hugs. That may escalate to, you know, sitting very close, touching a leg, giving a massage; normalizing the idea that in a relationship, you know, physical contact is happening. And at the same time, they're normalizing sexual material. So they may begin slowly by talking about sex, introducing the topic, telling sexual jokes. That may escalate to maybe showing risque movies, which might escalate to pornography. And then all of that will then escalate over time to combining the sexual activity to sexual touch in the form of sexual abuse. Q. Can you explain the fifth stage of grooming. A. So the fifth stage really is about maintaining the relationship. At this point now there's a dynamic of what's",
      "position": "main"
    },
    {
      "type": "printed",
      "content": "SOUTHERN DISTRICT REPORTERS, P.C. (212) 805-0300",
      "position": "footer"
    },
    {
      "type": "printed",
      "content": "DOJ-OGR-00012327",
      "position": "footer"
    }
  ],
  "entities": {
    "people": [
      "Dr. Rocchio"
    ],
    "organizations": [
      "SOUTHERN DISTRICT REPORTERS, P.C."
    ],
    "locations": [],
    "dates": [
      "08/10/22"
    ],
    "reference_numbers": [
      "1:20-cr-00330-PAE",
      "747",
      "DOJ-OGR-00012327"
    ]
  },
  "additional_notes": "The document appears to be a court transcript with a clear and legible format. There are no visible redactions or damage."
}