{
  "document_metadata": {
    "page_number": "188",
    "document_number": "745",
    "date": "08/10/22",
    "document_type": "court transcript",
    "has_handwriting": false,
    "has_stamps": false
  },
  "full_text": "Case 1:20-cr-00330-PAE Document 745 Filed 08/10/22 Page 188 of 264 599 LC1VMAX5 Jane - cross 1 MS. MENNINGER: Yes, your Honor. 2 THE COURT: Are you making an authentication 3 objection? 4 MS. MOE: Your Honor, it's about relevance and 5 personal knowledge. She's being asked about -- 6 THE COURT: Yes, I understand. 7 MS. MOE: Thank you. 8 THE COURT: Overruled. 9 J-15 is admitted. 10 (Defendant's Exhibit J-15 received in evidence) 11 MS. MENNINGER: Thank you. No further questions. 12 (Continued on next page) 13 14 15 16 17 18 19 20 21 22 23 24 25 SOUTHERN DISTRICT REPORTERS, P.C. (212) 805-0300 DOJ-OGR-00012208",
  "text_blocks": [
    {
      "type": "printed",
      "content": "Case 1:20-cr-00330-PAE Document 745 Filed 08/10/22 Page 188 of 264 599",
      "position": "header"
    },
    {
      "type": "printed",
      "content": "LC1VMAX5 Jane - cross",
      "position": "header"
    },
    {
      "type": "printed",
      "content": "1 MS. MENNINGER: Yes, your Honor. 2 THE COURT: Are you making an authentication 3 objection? 4 MS. MOE: Your Honor, it's about relevance and 5 personal knowledge. She's being asked about -- 6 THE COURT: Yes, I understand. 7 MS. MOE: Thank you. 8 THE COURT: Overruled. 9 J-15 is admitted. 10 (Defendant's Exhibit J-15 received in evidence) 11 MS. MENNINGER: Thank you. No further questions. 12 (Continued on next page)",
      "position": "main"
    },
    {
      "type": "printed",
      "content": "SOUTHERN DISTRICT REPORTERS, P.C. (212) 805-0300",
      "position": "footer"
    },
    {
      "type": "printed",
      "content": "DOJ-OGR-00012208",
      "position": "footer"
    }
  ],
  "entities": {
    "people": [
      "MS. MENNINGER",
      "MS. MOE"
    ],
    "organizations": [
      "SOUTHERN DISTRICT REPORTERS, P.C."
    ],
    "locations": [],
    "dates": [
      "08/10/22"
    ],
    "reference_numbers": [
      "1:20-cr-00330-PAE",
      "745",
      "J-15",
      "DOJ-OGR-00012208"
    ]
  },
  "additional_notes": "This is a court transcript document. The text is mostly printed, with no handwritten content or stamps visible."
}