{
  "document_metadata": {
    "page_number": "69",
    "document_number": "761",
    "date": "08/10/22",
    "document_type": "court transcript",
    "has_handwriting": false,
    "has_stamps": false
  },
  "full_text": "Case 1:20-cr-00330-PAE Document 761 Filed 08/10/22 Page 69 of 246 2364 LCGCmax2 Espinosa - direct\n1 THE COURT: Thank you.\n2 Q. Ms. Espinosa, let's first take a look --\n3 THE COURT: I think they're waiting for me. Would you like the jurors to look?\n4\n5 MR. EVERDELL: Yes. May I publish this to the jurors, your Honor?\n6\n7 THE COURT: So the jurors may look at the exhibits in the folder. Go ahead.\n8\n9 BY MR. EVERDELL:\n10 Q. Look first at CE3. Do you see what that is? Actually, can you hold that up? What is CE3?\n11\n12 A. CE3 is a manilla envelope addressed to Ms. Cimberly, care of Epstein & Co., 457 Madison Avenue, from Jane.\n13\n14 Q. Is there a date on the envelope?\n15 A. You can't read what the postage machine -- you can't see it.\n16\n17 THE COURT: Just my copy of the envelope doesn't have a mark.\n18\n19 MR. EVERDELL: Understood. The physical copy of the exhibit is what has the sticker on it. I don't know if we were able to copy the entire thing because it's a large envelope.\n20\n21\n22 THE COURT: Do you want to direct the jurors to look at a photocopy of an envelope and that is what you're indicating is CE3?\n23\n24\n25 MR. EVERDELL: Well, your Honor, I'm actually having SOUTHERN DISTRICT REPORTERS, P.C. (212) 805-0300\nDOJ-OGR-00013928",
  "text_blocks": [
    {
      "type": "printed",
      "content": "Case 1:20-cr-00330-PAE Document 761 Filed 08/10/22 Page 69 of 246 2364 LCGCmax2 Espinosa - direct",
      "position": "header"
    },
    {
      "type": "printed",
      "content": "SOUTHERN DISTRICT REPORTERS, P.C. (212) 805-0300",
      "position": "footer"
    },
    {
      "type": "printed",
      "content": "DOJ-OGR-00013928",
      "position": "footer"
    },
    {
      "type": "printed",
      "content": "1 THE COURT: Thank you. 2 Q. Ms. Espinosa, let's first take a look -- 3 THE COURT: I think they're waiting for me. Would you like the jurors to look? 4 5 MR. EVERDELL: Yes. May I publish this to the jurors, your Honor? 6 7 THE COURT: So the jurors may look at the exhibits in the folder. Go ahead. 8 9 BY MR. EVERDELL: 10 Q. Look first at CE3. Do you see what that is? Actually, can you hold that up? What is CE3? 11 12 A. CE3 is a manilla envelope addressed to Ms. Cimberly, care of Epstein & Co., 457 Madison Avenue, from Jane. 13 14 Q. Is there a date on the envelope? 15 A. You can't read what the postage machine -- you can't see it. 16 17 THE COURT: Just my copy of the envelope doesn't have a mark. 18 19 MR. EVERDELL: Understood. The physical copy of the exhibit is what has the sticker on it. I don't know if we were able to copy the entire thing because it's a large envelope. 20 21 22 THE COURT: Do you want to direct the jurors to look at a photocopy of an envelope and that is what you're indicating is CE3? 23 24 25 MR. EVERDELL: Well, your Honor, I'm actually having",
      "position": "main"
    }
  ],
  "entities": {
    "people": [
      "Ms. Espinosa",
      "MR. EVERDELL",
      "Ms. Cimberly",
      "Jane"
    ],
    "organizations": [
      "Epstein & Co.",
      "SOUTHERN DISTRICT REPORTERS, P.C."
    ],
    "locations": [
      "457 Madison Avenue"
    ],
    "dates": [
      "08/10/22"
    ],
    "reference_numbers": [
      "1:20-cr-00330-PAE",
      "761",
      "DOJ-OGR-00013928"
    ]
  },
  "additional_notes": "The document appears to be a court transcript with a clear and readable format. There are no visible redactions or damage."
}