{
  "document_metadata": {
    "page_number": "96",
    "document_number": "761",
    "date": "08/10/22",
    "document_type": "Court Transcript",
    "has_handwriting": false,
    "has_stamps": false
  },
  "full_text": "Case 1:20-cr-00330-PAE Document 761 Filed 08/10/22 Page 96 of 246 2391 LCGVMAX3 Sud - direct that profile customer? A. Yes, they do. Q. Okay. Do you ever have a profile for someone named Jeffrey Epstein? A. Yes, we do. Q. Okay. Was he a customer of Shoppers Travel? A. His office was a customer, yes. Q. Okay. And did you have interactions with his office about booking flights and other travel arrangements? A. Yes, we did. Q. Did there come a time when you were asked to verify certain records related to Epstein's office that you had at Shoppers Travel? A. To verify, not as of yet. Q. Okay. Did there come a time when you were asked to generate a report from your QuickBooks system? A. Yes. Q. And when were you asked to do that? A. In 2016. Q. Okay. And did there come a time when you were asked to review that same report later on? A. As of now, no. Q. How about this: I want to show you what's been marked for identification as RS-1. And we'll put that on the screen for the Court and the deputy and the witness for now. SOUTHERN DISTRICT REPORTERS, P.C. (212) 805-0300 DOJ-OGR-00013955",
  "text_blocks": [
    {
      "type": "printed",
      "content": "Case 1:20-cr-00330-PAE Document 761 Filed 08/10/22 Page 96 of 246 2391 LCGVMAX3 Sud - direct",
      "position": "header"
    },
    {
      "type": "printed",
      "content": "that profile customer? A. Yes, they do. Q. Okay. Do you ever have a profile for someone named Jeffrey Epstein? A. Yes, we do. Q. Okay. Was he a customer of Shoppers Travel? A. His office was a customer, yes. Q. Okay. And did you have interactions with his office about booking flights and other travel arrangements? A. Yes, we did. Q. Did there come a time when you were asked to verify certain records related to Epstein's office that you had at Shoppers Travel? A. To verify, not as of yet. Q. Okay. Did there come a time when you were asked to generate a report from your QuickBooks system? A. Yes. Q. And when were you asked to do that? A. In 2016. Q. Okay. And did there come a time when you were asked to review that same report later on? A. As of now, no. Q. How about this: I want to show you what's been marked for identification as RS-1. And we'll put that on the screen for the Court and the deputy and the witness for now.",
      "position": "main"
    },
    {
      "type": "printed",
      "content": "SOUTHERN DISTRICT REPORTERS, P.C. (212) 805-0300",
      "position": "footer"
    },
    {
      "type": "printed",
      "content": "DOJ-OGR-00013955",
      "position": "footer"
    }
  ],
  "entities": {
    "people": [
      "Jeffrey Epstein"
    ],
    "organizations": [
      "Shoppers Travel",
      "SOUTHERN DISTRICT REPORTERS, P.C."
    ],
    "locations": [],
    "dates": [
      "08/10/22",
      "2016"
    ],
    "reference_numbers": [
      "1:20-cr-00330-PAE",
      "761",
      "DOJ-OGR-00013955"
    ]
  },
  "additional_notes": "The document appears to be a court transcript with a clear and legible format. There are no visible redactions or damage."
}