{
  "document_metadata": {
    "page_number": "89",
    "document_number": "747",
    "date": "08/10/22",
    "document_type": "court transcript",
    "has_handwriting": false,
    "has_stamps": false
  },
  "full_text": "Case 1:20-cr-00330-PAE Document 747 Filed 08/10/22 Page 89 of 228 765 LC2Qmax3 Rocchio - Cross 1 Q. Confabulation is the brain under certain circumstances filling in gaps to make a whole picture of something, correct? 2 A. Yes. 3 Q. And a filling in of these gaps may or may not be accurate, but the person actually may believe what's been filled in? 4 5 MS. POMERANTZ: Objection, your Honor. 6 THE COURT: Sustained. 7 8 Q. When you're talking about delayed disclosure, Dr. Rocchio, you didn't talk about two concepts that can impact delayed closure and memory: One of those would be secondary gain. Are you familiar with that concept? 9 10 A. I am. 11 Q. That's a diagnostical and statistical manual definition -- 12 MS. POMERANTZ: Objection, your Honor. 13 THE COURT: Sustained. 14 15 Q. Are you familiar with the concept of malingering, Dr. Rocchio? 16 17 A. I am. 18 MS. POMERANTZ: Objection, your Honor. 19 THE COURT: Overruled. 20 21 Q. Malingering is the fabrication of symptoms for financial gain, correct? 22 MS. POMERANTZ: Objection. 23 THE COURT: Sustained. 24 25 Q. You talked about delays in disclosure about people being SOUTHERN DISTRICT REPORTERS, P.C. (212) 805-0300 DOJ-OGR-00012374",
  "text_blocks": [
    {
      "type": "printed",
      "content": "Case 1:20-cr-00330-PAE Document 747 Filed 08/10/22 Page 89 of 228 765",
      "position": "header"
    },
    {
      "type": "printed",
      "content": "LC2Qmax3 Rocchio - Cross",
      "position": "header"
    },
    {
      "type": "printed",
      "content": "1 Q. Confabulation is the brain under certain circumstances filling in gaps to make a whole picture of something, correct? 2 A. Yes. 3 Q. And a filling in of these gaps may or may not be accurate, but the person actually may believe what's been filled in? 4 5 MS. POMERANTZ: Objection, your Honor. 6 THE COURT: Sustained. 7 8 Q. When you're talking about delayed disclosure, Dr. Rocchio, you didn't talk about two concepts that can impact delayed closure and memory: One of those would be secondary gain. Are you familiar with that concept? 9 10 A. I am. 11 Q. That's a diagnostical and statistical manual definition -- 12 MS. POMERANTZ: Objection, your Honor. 13 THE COURT: Sustained. 14 15 Q. Are you familiar with the concept of malingering, Dr. Rocchio? 16 17 A. I am. 18 MS. POMERANTZ: Objection, your Honor. 19 THE COURT: Overruled. 20 21 Q. Malingering is the fabrication of symptoms for financial gain, correct? 22 MS. POMERANTZ: Objection. 23 THE COURT: Sustained. 24 25 Q. You talked about delays in disclosure about people being",
      "position": "main"
    },
    {
      "type": "printed",
      "content": "SOUTHERN DISTRICT REPORTERS, P.C. (212) 805-0300",
      "position": "footer"
    },
    {
      "type": "printed",
      "content": "DOJ-OGR-00012374",
      "position": "footer"
    }
  ],
  "entities": {
    "people": [
      "Dr. Rocchio",
      "MS. POMERANTZ"
    ],
    "organizations": [
      "SOUTHERN DISTRICT REPORTERS, P.C."
    ],
    "locations": [],
    "dates": [
      "08/10/22"
    ],
    "reference_numbers": [
      "1:20-cr-00330-PAE",
      "747",
      "DOJ-OGR-00012374"
    ]
  },
  "additional_notes": "The document appears to be a court transcript with a clear structure of questions and answers. There are no visible redactions or damage."
}