{
  "document_metadata": {
    "page_number": "103",
    "document_number": "755",
    "date": "08/10/22",
    "document_type": "court transcript",
    "has_handwriting": false,
    "has_stamps": false
  },
  "full_text": "Case 1:20-cr-00330-PAE Document 755 Filed 08/10/22 Page 103 of 262 1808 LC8VMAX4 Rodgers - direct in proper operating condition. And there's a lot of other duties, too: Budgeting, scheduling. Quite a few things. But that pretty much summarizes it. Q. Did you also fly the planes? A. Yes, I did. Q. And then you switched to captain and flight engineer. What were the responsibilities of those positions? A. As captain, you would get the weather for the flight, file the flight plan, fuel the airplane, you would reserve hotel rooms, cars, catering, stuff like that. Q. Between 1994 and 2004, about how often did you fly Jeffrey Epstein's private planes? A. On average, we flew every four days. Q. Was there a particular set schedule? A. No. Q. Was there any sort of routine or frequent stops? A. Primarily most of the time we were going to one of his houses. Q. Where was that? A. At that time it was Palm Beach, Florida; New York; Columbus, Ohio at that time. And then later on there were the ranch near Santa Fe, New Mexico, and then an island down at -- near St. Thomas. Q. About when do you remember starting to fly out to New SOUTHERN DISTRICT REPORTERS, P.C. (212) 805-0300 DOJ-OGR-00013381",
  "text_blocks": [
    {
      "type": "printed",
      "content": "Case 1:20-cr-00330-PAE Document 755 Filed 08/10/22 Page 103 of 262 1808 LC8VMAX4 Rodgers - direct",
      "position": "header"
    },
    {
      "type": "printed",
      "content": "in proper operating condition. And there's a lot of other duties, too: Budgeting, scheduling. Quite a few things. But that pretty much summarizes it. Q. Did you also fly the planes? A. Yes, I did. Q. And then you switched to captain and flight engineer. What were the responsibilities of those positions? A. As captain, you would get the weather for the flight, file the flight plan, fuel the airplane, you would reserve hotel rooms, cars, catering, stuff like that. Q. Between 1994 and 2004, about how often did you fly Jeffrey Epstein's private planes? A. On average, we flew every four days. Q. Was there a particular set schedule? A. No. Q. Was there any sort of routine or frequent stops? A. Primarily most of the time we were going to one of his houses. Q. Where was that? A. At that time it was Palm Beach, Florida; New York; Columbus, Ohio at that time. And then later on there were the ranch near Santa Fe, New Mexico, and then an island down at -- near St. Thomas. Q. About when do you remember starting to fly out to New",
      "position": "main"
    },
    {
      "type": "printed",
      "content": "SOUTHERN DISTRICT REPORTERS, P.C. (212) 805-0300",
      "position": "footer"
    },
    {
      "type": "printed",
      "content": "DOJ-OGR-00013381",
      "position": "footer"
    }
  ],
  "entities": {
    "people": [
      "Jeffrey Epstein"
    ],
    "organizations": [
      "SOUTHERN DISTRICT REPORTERS, P.C."
    ],
    "locations": [
      "Palm Beach",
      "Florida",
      "New York",
      "Columbus",
      "Ohio",
      "Santa Fe",
      "New Mexico",
      "St. Thomas"
    ],
    "dates": [
      "1994",
      "2004",
      "08/10/22"
    ],
    "reference_numbers": [
      "1:20-cr-00330-PAE",
      "755",
      "DOJ-OGR-00013381"
    ]
  },
  "additional_notes": "This is a court transcript document. The text is a Q&A session between a lawyer and a witness about their experience flying Jeffrey Epstein's private planes."
}