{
  "document_metadata": {
    "page_number": "113",
    "document_number": "753",
    "date": "08/10/22",
    "document_type": "court transcript",
    "has_handwriting": false,
    "has_stamps": false
  },
  "full_text": "Case 1:20-cr-00330-PAE Document 753 Filed 08/10/22 Page 113 of 264 1539\nLC7VMAX3\nCarolyn - direct\n1 Q. Who photographed you?\n2 A. Sarah.\n3 Q. How did Sarah come to photograph you?\n4 A. She had called me and asked -- well, she had said Mr. --\nshe called and said she was calling in regards to Mr. Epstein;\nand that I would get paid five to $600 if she could take\npictures of me.\n8 Q. How did you respond?\n9 A. I said okay.\n10 Q. Where were those pictures taken?\n11 A. In the Palm Beach house.\n12 Q. What were you wearing in those pictures?\n13 A. Nothing.\n14 Q. Who took those pictures?\n15 A. Sarah Kellen.\n16 Q. Do you remember anyone else being around at that time?\n17 A. No. It was just me and her that I was aware of.\n18 Q. During the massage appointments, after you set up the\nmassage table and got undressed, who would come inside the room?\n21 A. Mr. Epstein.\n22 Q. After Mr. Epstein came in the room, for the first\napproximately 45 minutes in the room, what would you do?\n24 A. Massage him.\n25 Q. How would he be lying down?\nSOUTHERN DISTRICT REPORTERS, P.C.\n(212) 805-0300\nDOJ-OGR-00013126",
  "text_blocks": [
    {
      "type": "printed",
      "content": "Case 1:20-cr-00330-PAE Document 753 Filed 08/10/22 Page 113 of 264 1539",
      "position": "header"
    },
    {
      "type": "printed",
      "content": "LC7VMAX3\nCarolyn - direct",
      "position": "header"
    },
    {
      "type": "printed",
      "content": "1 Q. Who photographed you?\n2 A. Sarah.\n3 Q. How did Sarah come to photograph you?\n4 A. She had called me and asked -- well, she had said Mr. --\nshe called and said she was calling in regards to Mr. Epstein;\nand that I would get paid five to $600 if she could take\npictures of me.\n8 Q. How did you respond?\n9 A. I said okay.\n10 Q. Where were those pictures taken?\n11 A. In the Palm Beach house.\n12 Q. What were you wearing in those pictures?\n13 A. Nothing.\n14 Q. Who took those pictures?\n15 A. Sarah Kellen.\n16 Q. Do you remember anyone else being around at that time?\n17 A. No. It was just me and her that I was aware of.\n18 Q. During the massage appointments, after you set up the\nmassage table and got undressed, who would come inside the room?\n21 A. Mr. Epstein.\n22 Q. After Mr. Epstein came in the room, for the first\napproximately 45 minutes in the room, what would you do?\n24 A. Massage him.\n25 Q. How would he be lying down?",
      "position": "main"
    },
    {
      "type": "printed",
      "content": "SOUTHERN DISTRICT REPORTERS, P.C.\n(212) 805-0300",
      "position": "footer"
    },
    {
      "type": "printed",
      "content": "DOJ-OGR-00013126",
      "position": "footer"
    }
  ],
  "entities": {
    "people": [
      "Sarah",
      "Mr. Epstein",
      "Sarah Kellen",
      "Carolyn"
    ],
    "organizations": [
      "SOUTHERN DISTRICT REPORTERS, P.C."
    ],
    "locations": [
      "Palm Beach"
    ],
    "dates": [
      "08/10/22"
    ],
    "reference_numbers": [
      "1:20-cr-00330-PAE",
      "753",
      "DOJ-OGR-00013126"
    ]
  },
  "additional_notes": "The document appears to be a court transcript with a clear and legible format. There are no visible redactions or damage."
}