{
  "document_metadata": {
    "page_number": "127",
    "document_number": "745",
    "date": "08/10/22",
    "document_type": "court transcript",
    "has_handwriting": false,
    "has_stamps": false
  },
  "full_text": "Case 1:20-cr-00330-PAE Document 745 Filed 08/10/22 Page 127 of 264 538 LC1Qmax4 Jane - Cross 1 A. Right. 2 Q. There's nothing on the photographs themselves? 3 A. Right. 4 Q. And you testified yesterday that Epstein just kept calling you and calling you in the 2000s until you stopped answering his phone calls, right? 5 6 7 A. Yes. 8 Q. So there would be phone records of all those calls, right? 9 A. Yes. 10 Q. It took you quite some time to report this to law enforcement, right? We talked about that at the beginning yesterday? 11 12 13 A. Yes. 14 Q. In the meantime, you got a job on a soap opera, right? 15 A. Right. 16 Q. You received an income from that job? 17 A. Yes. 18 Q. You had an agent? 19 A. Yes. 20 Q. You had a number of family members that lived nearby in the 2000s, right? 21 22 A. Yes. 23 Q. And once you had established yourself as an actress with income, you didn't call up the police to let them know what you claimed had happened to you, right? 24 25 SOUTHERN DISTRICT REPORTERS, P.C. (212) 805-0300 DOJ-OGR-00012147",
  "text_blocks": [
    {
      "type": "printed",
      "content": "Case 1:20-cr-00330-PAE Document 745 Filed 08/10/22 Page 127 of 264 538",
      "position": "header"
    },
    {
      "type": "handwritten",
      "content": "LC1Qmax4 Jane - Cross",
      "position": "header"
    },
    {
      "type": "printed",
      "content": "1 A. Right. 2 Q. There's nothing on the photographs themselves? 3 A. Right. 4 Q. And you testified yesterday that Epstein just kept calling you and calling you in the 2000s until you stopped answering his phone calls, right? 5 6 7 A. Yes. 8 Q. So there would be phone records of all those calls, right? 9 A. Yes. 10 Q. It took you quite some time to report this to law enforcement, right? We talked about that at the beginning yesterday? 11 12 13 A. Yes. 14 Q. In the meantime, you got a job on a soap opera, right? 15 A. Right. 16 Q. You received an income from that job? 17 A. Yes. 18 Q. You had an agent? 19 A. Yes. 20 Q. You had a number of family members that lived nearby in the 2000s, right? 21 22 A. Yes. 23 Q. And once you had established yourself as an actress with income, you didn't call up the police to let them know what you claimed had happened to you, right? 24 25",
      "position": "main"
    },
    {
      "type": "printed",
      "content": "SOUTHERN DISTRICT REPORTERS, P.C. (212) 805-0300",
      "position": "footer"
    },
    {
      "type": "printed",
      "content": "DOJ-OGR-00012147",
      "position": "footer"
    }
  ],
  "entities": {
    "people": [
      "Epstein"
    ],
    "organizations": [
      "SOUTHERN DISTRICT REPORTERS, P.C."
    ],
    "locations": [],
    "dates": [
      "08/10/22",
      "2000s"
    ],
    "reference_numbers": [
      "1:20-cr-00330-PAE",
      "745",
      "DOJ-OGR-00012147"
    ]
  },
  "additional_notes": "The document appears to be a court transcript with a clear and legible format. There are no visible redactions or damage."
}