{
  "document_metadata": {
    "page_number": "224",
    "document_number": "759",
    "date": "08/10/22",
    "document_type": "court transcript",
    "has_handwriting": false,
    "has_stamps": false
  },
  "full_text": "Case 1:20-cr-00330-PAE Document 759 Filed 08/10/22 Page 224 of 267 2252 LCACmax7 Swain - direct 1 of who Epstein was? 2 A. That he was Maria's boss. 3 Q. About how many calls in total did you have with Epstein? 4 A. At least six. 5 Q. What, if anything, did Epstein call you about, other than Maria? 6 7 A. He called me before the Christmas holiday to ask if I would allow Annie to come to New York to visit Maria as a gift to Maria for Christmas. 8 9 10 Q. Did you have one call or multiple calls with Jeffrey Epstein about Annie? 11 12 A. Multiple. 13 Q. When you had calls with Epstein, what, if anything, did he discuss with you about Annie's education? 14 15 A. He just said that he had -- he could probably help guide her in selecting a college and that he would like to introduce her to some other people who could help with that. 16 17 18 Q. Approximately when did Epstein first call you about Annie? 19 A. In December of '95. 20 Q. Based on the call, what was Epstein offering to do? 21 A. The first call, to offer her a flight to New York to visit Maria. 22 23 Q. Did you give Annie permission to go to New York? 24 A. I did. 25 Q. How come? SOUTHERN DISTRICT REPORTERS, P.C. (212) 805-0300 DOJ-OGR-00013815",
  "text_blocks": [
    {
      "type": "printed",
      "content": "Case 1:20-cr-00330-PAE Document 759 Filed 08/10/22 Page 224 of 267 2252 LCACmax7 Swain - direct",
      "position": "header"
    },
    {
      "type": "printed",
      "content": "1 of who Epstein was? 2 A. That he was Maria's boss. 3 Q. About how many calls in total did you have with Epstein? 4 A. At least six. 5 Q. What, if anything, did Epstein call you about, other than Maria? 6 7 A. He called me before the Christmas holiday to ask if I would allow Annie to come to New York to visit Maria as a gift to Maria for Christmas. 8 9 10 Q. Did you have one call or multiple calls with Jeffrey Epstein about Annie? 11 12 A. Multiple. 13 Q. When you had calls with Epstein, what, if anything, did he discuss with you about Annie's education? 14 15 A. He just said that he had -- he could probably help guide her in selecting a college and that he would like to introduce her to some other people who could help with that. 16 17 18 Q. Approximately when did Epstein first call you about Annie? 19 A. In December of '95. 20 Q. Based on the call, what was Epstein offering to do? 21 A. The first call, to offer her a flight to New York to visit Maria. 22 23 Q. Did you give Annie permission to go to New York? 24 A. I did. 25 Q. How come?",
      "position": "main"
    },
    {
      "type": "printed",
      "content": "SOUTHERN DISTRICT REPORTERS, P.C. (212) 805-0300",
      "position": "footer"
    },
    {
      "type": "printed",
      "content": "DOJ-OGR-00013815",
      "position": "footer"
    }
  ],
  "entities": {
    "people": [
      "Epstein",
      "Maria",
      "Annie",
      "Jeffrey Epstein",
      "Swain"
    ],
    "organizations": [
      "SOUTHERN DISTRICT REPORTERS, P.C."
    ],
    "locations": [
      "New York"
    ],
    "dates": [
      "08/10/22",
      "December '95"
    ],
    "reference_numbers": [
      "1:20-cr-00330-PAE",
      "759",
      "DOJ-OGR-00013815"
    ]
  },
  "additional_notes": "The document appears to be a court transcript with a clear and legible format. There are no visible redactions or damage."
}