{
  "document_metadata": {
    "page_number": "165",
    "document_number": "753",
    "date": "08/10/22",
    "document_type": "court transcript",
    "has_handwriting": false,
    "has_stamps": false
  },
  "full_text": "Case 1:20-cr-00330-PAE Document 753 Filed 08/10/22 Page 165 of 264 LC7VMAX5 Carolyn - cross 1 Q. -- we were talking about 2002, when you went to Mr. Epstein's house with Virginia Roberts. And I think where we stopped was you were -- you went into the house and you were taken upstairs by Ms. Roberts. Do you recall that? 5 A. Yes. 6 Q. Now, the only person that you saw when you entered the house, you identified as being an older lady with unknown hair and an unknown accent. Is that correct? 9 A. No. I said she had shoulder-length black hair with an accent. 11 Q. Do you recall again giving a statement to the FBI in August of 2007? 13 A. A what? A testimony? 14 Q. Do you recall being interviewed by the FBI in August of 2007, Special Agents Nesbitt and Kuyrkendall? 16 A. Yes. 17 Q. And they met with you at your house; is that right? 18 A. Yes. 19 Q. And they weren't there to be mean to you; they were trying to ask you questions. Correct? 21 A. Yes. 22 Q. And they introduced themselves to you, right? 23 A. Yes. 24 Q. And you certainly had no reason to lie to them; correct? 25 A. Correct. SOUTHERN DISTRICT REPORTERS, P.C. (212) 805-0300 DOJ-OGR-00013178",
  "text_blocks": [
    {
      "type": "printed",
      "content": "Case 1:20-cr-00330-PAE Document 753 Filed 08/10/22 Page 165 of 264",
      "position": "header"
    },
    {
      "type": "printed",
      "content": "LC7VMAX5 Carolyn - cross",
      "position": "header"
    },
    {
      "type": "printed",
      "content": "1 Q. -- we were talking about 2002, when you went to Mr. Epstein's house with Virginia Roberts. And I think where we stopped was you were -- you went into the house and you were taken upstairs by Ms. Roberts. Do you recall that? 5 A. Yes. 6 Q. Now, the only person that you saw when you entered the house, you identified as being an older lady with unknown hair and an unknown accent. Is that correct? 9 A. No. I said she had shoulder-length black hair with an accent. 11 Q. Do you recall again giving a statement to the FBI in August of 2007? 13 A. A what? A testimony? 14 Q. Do you recall being interviewed by the FBI in August of 2007, Special Agents Nesbitt and Kuyrkendall? 16 A. Yes. 17 Q. And they met with you at your house; is that right? 18 A. Yes. 19 Q. And they weren't there to be mean to you; they were trying to ask you questions. Correct? 21 A. Yes. 22 Q. And they introduced themselves to you, right? 23 A. Yes. 24 Q. And you certainly had no reason to lie to them; correct? 25 A. Correct.",
      "position": "main"
    },
    {
      "type": "printed",
      "content": "SOUTHERN DISTRICT REPORTERS, P.C. (212) 805-0300",
      "position": "footer"
    },
    {
      "type": "printed",
      "content": "DOJ-OGR-00013178",
      "position": "footer"
    }
  ],
  "entities": {
    "people": [
      "Virginia Roberts",
      "Ms. Roberts",
      "Nesbitt",
      "Kuyrkendall",
      "Mr. Epstein"
    ],
    "organizations": [
      "FBI",
      "SOUTHERN DISTRICT REPORTERS, P.C."
    ],
    "locations": [],
    "dates": [
      "2002",
      "August of 2007",
      "08/10/22"
    ],
    "reference_numbers": [
      "1:20-cr-00330-PAE",
      "Document 753",
      "LC7VMAX5",
      "DOJ-OGR-00013178"
    ]
  },
  "additional_notes": "The document appears to be a court transcript with a clear and legible format. There are no visible redactions or damage."
}