{
  "document_metadata": {
    "page_number": "1",
    "document_number": "745",
    "date": "08/10/22",
    "document_type": "court transcript",
    "has_handwriting": false,
    "has_stamps": false
  },
  "full_text": "Case 1:20-cr-00330-PAE Document 745 Filed 08/10/22 Page 1 of 264 407 LC1VMAX1\n\nUNITED STATES DISTRICT COURT\nSOUTHERN DISTRICT OF NEW YORK\n------------------------------------x\nUNITED STATES OF AMERICA,\n\nv.\n20 CR 330 (AJN)\nGHISLAINE MAXWELL,\nDefendant.\n------------------------------------x Jury Trial\nNew York, N.Y.\nDecember 1, 2021\n8:55 a.m.\n\nBefore:\nHON. ALISON J. NATHAN,\nDistrict Judge\n\nAPPEARANCES\nDAMIAN WILLIAMS\nUnited States Attorney for the\nSouthern District of New York\nBY: MAURENE COMEY\nALISON MOE\nLARA POMERANTZ\nANDREW ROHRBACH\nAssistant United States Attorneys\nHADDON MORGAN AND FOREMAN\nAttorneys for Defendant\nBY: JEFFREY S. PAGLIUCA\nCHRISTIAN R. EVERDELL\nLAURA A. MENNINGER\n-and-\nBOBBI C. STERNHEIM\n-and-\nRENATO STABILE\nAlso Present: Amanda Young, FBI\nPaul Byrne, NYPD\nSunny Drescher,\nParalegal, U.S. Attorney's Office\nAnn Lundberg,\nParalegal, Haddon Morgan and Foreman\n\nSOUTHERN DISTRICT REPORTERS, P.C.\n(212) 805-0300\nDOJ-OGR-00012021",
  "text_blocks": [
    {
      "type": "printed",
      "content": "Case 1:20-cr-00330-PAE Document 745 Filed 08/10/22 Page 1 of 264 407 LC1VMAX1",
      "position": "header"
    },
    {
      "type": "printed",
      "content": "UNITED STATES DISTRICT COURT\nSOUTHERN DISTRICT OF NEW YORK\n------------------------------------x\nUNITED STATES OF AMERICA,\n\nv.\n20 CR 330 (AJN)\nGHISLAINE MAXWELL,\nDefendant.\n------------------------------------x Jury Trial\nNew York, N.Y.\nDecember 1, 2021\n8:55 a.m.",
      "position": "top"
    },
    {
      "type": "printed",
      "content": "Before:\nHON. ALISON J. NATHAN,\nDistrict Judge",
      "position": "middle"
    },
    {
      "type": "printed",
      "content": "APPEARANCES\nDAMIAN WILLIAMS\nUnited States Attorney for the\nSouthern District of New York\nBY: MAURENE COMEY\nALISON MOE\nLARA POMERANTZ\nANDREW ROHRBACH\nAssistant United States Attorneys\nHADDON MORGAN AND FOREMAN\nAttorneys for Defendant\nBY: JEFFREY S. PAGLIUCA\nCHRISTIAN R. EVERDELL\nLAURA A. MENNINGER\n-and-\nBOBBI C. STERNHEIM\n-and-\nRENATO STABILE\nAlso Present: Amanda Young, FBI\nPaul Byrne, NYPD\nSunny Drescher,\nParalegal, U.S. Attorney's Office\nAnn Lundberg,\nParalegal, Haddon Morgan and Foreman",
      "position": "middle"
    },
    {
      "type": "printed",
      "content": "SOUTHERN DISTRICT REPORTERS, P.C.\n(212) 805-0300",
      "position": "footer"
    },
    {
      "type": "printed",
      "content": "DOJ-OGR-00012021",
      "position": "footer"
    }
  ],
  "entities": {
    "people": [
      "Ghislaine Maxwell",
      "Alison J. Nathan",
      "Damian Williams",
      "Maurene Comey",
      "Alison Moe",
      "Lara Pomerantz",
      "Andrew Rohrbach",
      "Jeffrey S. Pagliuca",
      "Christian R. Everdell",
      "Laura A. Menninger",
      "Bobbi C. Sternheim",
      "Renato Stabile",
      "Amanda Young",
      "Paul Byrne",
      "Sunny Drescher",
      "Ann Lundberg"
    ],
    "organizations": [
      "United States District Court",
      "Southern District of New York",
      "United States Attorney's Office",
      "FBI",
      "NYPD",
      "Haddon Morgan and Foreman",
      "Southern District Reporters, P.C."
    ],
    "locations": [
      "New York"
    ],
    "dates": [
      "08/10/22",
      "December 1, 2021"
    ],
    "reference_numbers": [
      "1:20-cr-00330-PAE",
      "20 CR 330 (AJN)",
      "745",
      "DOJ-OGR-00012021"
    ]
  },
  "additional_notes": "The document appears to be a court transcript from a jury trial. The text is clear and legible, with no visible redactions or damage."
}