{
  "document_metadata": {
    "page_number": "45",
    "document_number": "743",
    "date": "08/10/22",
    "document_type": "court transcript",
    "has_handwriting": false,
    "has_stamps": false
  },
  "full_text": "Case 1:20-cr-00330-PAE Document 743 Filed 08/10/22 Page 45 of 247 173 LBUVMAX2 Visoski - direct\n1 passenger name, I wanted to put whether they were male or\n2 female, the passenger -- as a pilot's standpoint, it's more\n3 important how many people and how much they weigh compared to a\n4 person's name. We tried to be as accurate as we could. So if\n5 I didn't know a name, I put whether they were male or female.\n6 Q. And remind us why you wouldn't necessarily know the name of\n7 everyone on your plane?\n8 A. It wasn't my first priority. Most of the time Mr. Epstein\n9 would, you know, indicate or introduce us to the passengers,\n10 but it just wasn't -- it wasn't the first thing, you know, on\n11 anybody's mind. Occasionally he would introduce and sometimes\n12 he wouldn't. We would try to gather their name if we asked\n13 them, if we had the time to ask them. But we tried to do the\n14 best we could is to get everybody's name.\n15 Q. During your employment with Mr. Epstein, did you ever fly\n16 to the airport in Traverse City, Michigan?\n17 A. Yes, I did.\n18 Q. About what years do you remember making those trips to\n19 Michigan?\n20 A. Definitely in the '90s is the best I could come up with.\n21 It was in the '90s.\n22 Q. During what season do you remember taking those trips to\n23 Michigan?\n24 A. I don't remember it being cold, because I know it gets\n25 pretty cold up there. It had to have been summer or, you know,\nSOUTHERN DISTRICT REPORTERS, P.C. (212) 805-0300 DOJ-OGR-00011817",
  "text_blocks": [
    {
      "type": "printed",
      "content": "Case 1:20-cr-00330-PAE Document 743 Filed 08/10/22 Page 45 of 247 173 LBUVMAX2 Visoski - direct",
      "position": "header"
    },
    {
      "type": "printed",
      "content": "1 passenger name, I wanted to put whether they were male or\n2 female, the passenger -- as a pilot's standpoint, it's more\n3 important how many people and how much they weigh compared to a\n4 person's name. We tried to be as accurate as we could. So if\n5 I didn't know a name, I put whether they were male or female.\n6 Q. And remind us why you wouldn't necessarily know the name of\n7 everyone on your plane?\n8 A. It wasn't my first priority. Most of the time Mr. Epstein\n9 would, you know, indicate or introduce us to the passengers,\n10 but it just wasn't -- it wasn't the first thing, you know, on\n11 anybody's mind. Occasionally he would introduce and sometimes\n12 he wouldn't. We would try to gather their name if we asked\n13 them, if we had the time to ask them. But we tried to do the\n14 best we could is to get everybody's name.\n15 Q. During your employment with Mr. Epstein, did you ever fly\n16 to the airport in Traverse City, Michigan?\n17 A. Yes, I did.\n18 Q. About what years do you remember making those trips to\n19 Michigan?\n20 A. Definitely in the '90s is the best I could come up with.\n21 It was in the '90s.\n22 Q. During what season do you remember taking those trips to\n23 Michigan?\n24 A. I don't remember it being cold, because I know it gets\n25 pretty cold up there. It had to have been summer or, you know,",
      "position": "main"
    },
    {
      "type": "printed",
      "content": "SOUTHERN DISTRICT REPORTERS, P.C. (212) 805-0300",
      "position": "footer"
    },
    {
      "type": "printed",
      "content": "DOJ-OGR-00011817",
      "position": "footer"
    }
  ],
  "entities": {
    "people": [
      "Mr. Epstein"
    ],
    "organizations": [
      "SOUTHERN DISTRICT REPORTERS, P.C."
    ],
    "locations": [
      "Michigan",
      "Traverse City"
    ],
    "dates": [
      "08/10/22",
      "'90s"
    ],
    "reference_numbers": [
      "1:20-cr-00330-PAE",
      "743",
      "DOJ-OGR-00011817"
    ]
  },
  "additional_notes": "The document appears to be a court transcript with a clear and readable format. There are no visible redactions or damage."
}