{
  "document_metadata": {
    "page_number": "42",
    "document_number": "749",
    "date": "08/10/22",
    "document_type": "court transcript",
    "has_handwriting": false,
    "has_stamps": false
  },
  "full_text": "Case 1:20-cr-00330-PAE Document 749 Filed 08/10/22 Page 42 of 236 LC3Cmax1 Alessi - cross 1 Q. That's what you testified to under oath, September 8th, 2009; correct? 3 A. I guess I did. 4 \"Q. When was the other time? 5 \"A. Couple weeks before. 6 \"Q. What time of day was that? 7 \"A. At night. 8 \"Q. How much did you take out the first time? 9 \"A. It was a total of $6,300. 10 \"Q. That's for both times? 11 \"A. Yeah. 12 \"Q. Can you break them down? 13 \"A. I think one time was $1,500. Another time was the rest.\" 14 Q. That was your testimony under oath, correct, Mr. Alessi? 15 A. Guess so. 16 MR. PAGLIUCA: Your Honor, I move for the admission of this testimony under Rule 801. 18 MS. COMEY: It's been read in already. 19 THE COURT: It's read in the record and admitted. 20 MR. PAGLIUCA: Thank you. 21 Q. Now, Mr. Alessi, yesterday you told the jury that you stole 22 the money because you were having -- 23 THE COURT: Pull up the microphone, please. 24 Q. -- you stole the money because you were having financial 25 problems. SOUTHERN DISTRICT REPORTERS, P.C. (212) 805-0300 DOJ-OGR-00012556",
  "text_blocks": [
    {
      "type": "printed",
      "content": "Case 1:20-cr-00330-PAE Document 749 Filed 08/10/22 Page 42 of 236 LC3Cmax1 Alessi - cross",
      "position": "header"
    },
    {
      "type": "printed",
      "content": "1 Q. That's what you testified to under oath, September 8th, 2009; correct? 3 A. I guess I did. 4 \"Q. When was the other time? 5 \"A. Couple weeks before. 6 \"Q. What time of day was that? 7 \"A. At night. 8 \"Q. How much did you take out the first time? 9 \"A. It was a total of $6,300. 10 \"Q. That's for both times? 11 \"A. Yeah. 12 \"Q. Can you break them down? 13 \"A. I think one time was $1,500. Another time was the rest.\" 14 Q. That was your testimony under oath, correct, Mr. Alessi? 15 A. Guess so. 16 MR. PAGLIUCA: Your Honor, I move for the admission of this testimony under Rule 801. 18 MS. COMEY: It's been read in already. 19 THE COURT: It's read in the record and admitted. 20 MR. PAGLIUCA: Thank you. 21 Q. Now, Mr. Alessi, yesterday you told the jury that you stole 22 the money because you were having -- 23 THE COURT: Pull up the microphone, please. 24 Q. -- you stole the money because you were having financial 25 problems.",
      "position": "main"
    },
    {
      "type": "printed",
      "content": "SOUTHERN DISTRICT REPORTERS, P.C. (212) 805-0300",
      "position": "footer"
    },
    {
      "type": "printed",
      "content": "DOJ-OGR-00012556",
      "position": "footer"
    }
  ],
  "entities": {
    "people": [
      "Mr. Alessi",
      "MR. PAGLIUCA",
      "MS. COMEY"
    ],
    "organizations": [
      "SOUTHERN DISTRICT REPORTERS, P.C."
    ],
    "locations": [],
    "dates": [
      "September 8th, 2009",
      "08/10/22"
    ],
    "reference_numbers": [
      "1:20-cr-00330-PAE",
      "Document 749",
      "DOJ-OGR-00012556"
    ]
  },
  "additional_notes": "The document appears to be a court transcript with clear and legible text. There are no visible redactions or damage."
}