{
  "document_metadata": {
    "page_number": "248",
    "document_number": "759",
    "date": "08/10/22",
    "document_type": "court transcript",
    "has_handwriting": false,
    "has_stamps": false
  },
  "full_text": "Case 1:20-cr-00330-PAE Document 759 Filed 08/10/22 Page 248 of 267 2276 LCAVMAX8\n\n1 So we would ask the defense to comply with the Court's\n2 order, produce those materials today, along with exhibits, a\n3 list of witnesses, and an order of the first witnesses.\n4 THE COURT: Yes. You'll do that.\n5 MR. PAGLIUCA: I think I said we were going to do\n6 that, your Honor.\n7 THE COURT: Right. To the extent you think one\n8 witness might be substituted for a different witness, you need\n9 to alert the government in your list today who the other\n10 witness might be and make disclosures accordingly.\n11 MR. PAGLIUCA: We will do what we are supposed to do;\n12 and we will do our best at it, your Honor.\n13 THE COURT: Okay. You have time, since we're not\n14 sitting again till Thursday, to arrange travel. We've known\n15 for some time the government would -- at least a few days, the\n16 government would rest this week; and we've known about my\n17 scheduling issues for Monday, Tuesday, Wednesday. So we're not\n18 at a moment of surprise at this point. I get that they've\n19 shaved witnesses and that might require -- it's not me.\n20 MS. MOE: It's not me, your Honor.\n21 MR. PAGLIUCA: It's not me, your Honor.\n22 THE COURT: Whoa. That's weird. Khalilah?\n23 It's the ghost of Friday, I guess.\n24 So I think you're in a position to do your full\n25 disclosures. To the extent there may be a substitute witness,\n\nSOUTHERN DISTRICT REPORTERS, P.C. (212) 805-0300\n\nDOJ-OGR-00013839",
  "text_blocks": [
    {
      "type": "printed",
      "content": "Case 1:20-cr-00330-PAE Document 759 Filed 08/10/22 Page 248 of 267 2276 LCAVMAX8",
      "position": "header"
    },
    {
      "type": "printed",
      "content": "SOUTHERN DISTRICT REPORTERS, P.C. (212) 805-0300",
      "position": "footer"
    },
    {
      "type": "printed",
      "content": "DOJ-OGR-00013839",
      "position": "footer"
    },
    {
      "type": "printed",
      "content": "1 So we would ask the defense to comply with the Court's order, produce those materials today, along with exhibits, a list of witnesses, and an order of the first witnesses. THE COURT: Yes. You'll do that. MR. PAGLIUCA: I think I said we were going to do that, your Honor. THE COURT: Right. To the extent you think one witness might be substituted for a different witness, you need to alert the government in your list today who the other witness might be and make disclosures accordingly. MR. PAGLIUCA: We will do what we are supposed to do; and we will do our best at it, your Honor. THE COURT: Okay. You have time, since we're not sitting again till Thursday, to arrange travel. We've known for some time the government would -- at least a few days, the government would rest this week; and we've known about my scheduling issues for Monday, Tuesday, Wednesday. So we're not at a moment of surprise at this point. I get that they've shaved witnesses and that might require -- it's not me. MS. MOE: It's not me, your Honor. MR. PAGLIUCA: It's not me, your Honor. THE COURT: Whoa. That's weird. Khalilah? It's the ghost of Friday, I guess. So I think you're in a position to do your full disclosures. To the extent there may be a substitute witness,",
      "position": "main"
    }
  ],
  "entities": {
    "people": [
      "MR. PAGLIUCA",
      "MS. MOE",
      "Khalilah"
    ],
    "organizations": [
      "SOUTHERN DISTRICT REPORTERS, P.C.",
      "DOJ"
    ],
    "locations": [],
    "dates": [
      "08/10/22",
      "Monday",
      "Tuesday",
      "Wednesday",
      "Thursday",
      "Friday"
    ],
    "reference_numbers": [
      "1:20-cr-00330-PAE",
      "759",
      "DOJ-OGR-00013839"
    ]
  },
  "additional_notes": "The document appears to be a court transcript with a clear and readable format. There are no visible redactions or damage."
}