{
  "document_metadata": {
    "page_number": "212",
    "document_number": "747",
    "date": "08/10/22",
    "document_type": "court transcript",
    "has_handwriting": false,
    "has_stamps": false
  },
  "full_text": "Case 1:20-cr-00330-PAE Document 747 Filed 08/10/22 Page 212 of 228 888 LC2VMAX6 Alessi - Direct\n1 MS. COMEY: I am seeking 2A, I'm not seeking 2B. Just\n2 C through W.\n3 THE COURT: All right. 2A on consent is admitted.\n4 And I am overruling the objection as to 2C through 2W based on\n5 the testimony of the witness.\n6 MS. COMEY: Thank you, your Honor. These are sealed\n7 exhibits. I would ask that we please go through them with the\n8 jurors in their binders.\n9 THE COURT: So are they all sealed?\n10 MS. COMEY: Yes, your Honor, I apologize. We are\n11 offering all of these under seal, consistent with prior\n12 applications.\n13 THE COURT: I presume 2A is not under seal.\n14 MS. COMEY: No, 2A is not under seal.\n15 Thank you for clarifying, your Honor.\n16 THE COURT: 2C through 2W.\n17 MS. COMEY: We are moving under seal.\n18 THE COURT: Under seal.\n19 MS. COMEY: And it's both to protect witnesses who\n20 you've authorized to testify under pseudonym, and to protect\n21 personal information of third parties who have names, phone\n22 numbers, and contact information in the other exhibits.\n23 THE COURT: Do you have any objection to the sealing\n24 request?\n25 MR. PAGLIUCA: No, the sealing I have no objection to,\nSOUTHERN DISTRICT REPORTERS, P.C.\n(212) 805-0300\nDOJ-OGR-00012497",
  "text_blocks": [
    {
      "type": "printed",
      "content": "Case 1:20-cr-00330-PAE Document 747 Filed 08/10/22 Page 212 of 228 888 LC2VMAX6 Alessi - Direct",
      "position": "header"
    },
    {
      "type": "printed",
      "content": "1 MS. COMEY: I am seeking 2A, I'm not seeking 2B. Just\n2 C through W.\n3 THE COURT: All right. 2A on consent is admitted.\n4 And I am overruling the objection as to 2C through 2W based on\n5 the testimony of the witness.\n6 MS. COMEY: Thank you, your Honor. These are sealed\n7 exhibits. I would ask that we please go through them with the\n8 jurors in their binders.\n9 THE COURT: So are they all sealed?\n10 MS. COMEY: Yes, your Honor, I apologize. We are\n11 offering all of these under seal, consistent with prior\n12 applications.\n13 THE COURT: I presume 2A is not under seal.\n14 MS. COMEY: No, 2A is not under seal.\n15 Thank you for clarifying, your Honor.\n16 THE COURT: 2C through 2W.\n17 MS. COMEY: We are moving under seal.\n18 THE COURT: Under seal.\n19 MS. COMEY: And it's both to protect witnesses who\n20 you've authorized to testify under pseudonym, and to protect\n21 personal information of third parties who have names, phone\n22 numbers, and contact information in the other exhibits.\n23 THE COURT: Do you have any objection to the sealing\n24 request?\n25 MR. PAGLIUCA: No, the sealing I have no objection to,",
      "position": "main content"
    },
    {
      "type": "printed",
      "content": "SOUTHERN DISTRICT REPORTERS, P.C.\n(212) 805-0300",
      "position": "footer"
    },
    {
      "type": "printed",
      "content": "DOJ-OGR-00012497",
      "position": "footer"
    }
  ],
  "entities": {
    "people": [
      "MS. COMEY",
      "THE COURT",
      "MR. PAGLIUCA"
    ],
    "organizations": [
      "SOUTHERN DISTRICT REPORTERS, P.C."
    ],
    "locations": [],
    "dates": [
      "08/10/22"
    ],
    "reference_numbers": [
      "1:20-cr-00330-PAE",
      "747",
      "DOJ-OGR-00012497"
    ]
  },
  "additional_notes": "The document is a court transcript with a clear and legible format. The content appears to be a discussion between MS. COMEY, THE COURT, and MR. PAGLIUCA regarding the sealing of exhibits."
}