{
  "document_metadata": {
    "page_number": "13",
    "document_number": "745",
    "date": "08/10/22",
    "document_type": "court transcript",
    "has_handwriting": false,
    "has_stamps": false
  },
  "full_text": "Case 1:20-cr-00330-PAE Document 745 Filed 08/10/22 Page 13 of 264 419 LC1VMAX1\n1 THE COURT: Could you pull up the microphone.\n2 MS. MOE: Yes, your Honor. I apologize.\n3 THE COURT: Even though we're three days in, I still can't hear you without the mic.\n4 MS. MOE: I'm sorry.\n5 THE COURT: That's okay.\n6 MS. MOE: I believe the witness would explain that when all of this began when she was 14, she was living in a pool house because of her family's financial circumstances. But at some point during the years that followed, her family moved to a second house.\n7 THE COURT: And that's the address listed in the 302, as you understand it?\n8 MS. MOE: I don't recall offhand whether that's the particular address. I'd want to review the 3500. But I believe the witness was clarifying that she lived at a second house.\n9 THE COURT: Okay. All right.\n10 MR. EVERDELL: Your Honor, I'm sorry.\n11 I believe -- and I'm checking this right now, but I believe the address she put on her 1994 Interlochen application was the address we were showing her the photograph of. And she's saying she's in a pool house or homeless. So I think this is impeaching. I think this goes directly --\n12 THE COURT: Again, she said she lived -- they move in\nSOUTHERN DISTRICT REPORTERS, P.C. (212) 805-0300 DOJ-OGR-00012033",
  "text_blocks": [
    {
      "type": "printed",
      "content": "Case 1:20-cr-00330-PAE Document 745 Filed 08/10/22 Page 13 of 264 419 LC1VMAX1",
      "position": "header"
    },
    {
      "type": "printed",
      "content": "1 THE COURT: Could you pull up the microphone.\n2 MS. MOE: Yes, your Honor. I apologize.\n3 THE COURT: Even though we're three days in, I still can't hear you without the mic.\n4 MS. MOE: I'm sorry.\n5 THE COURT: That's okay.\n6 MS. MOE: I believe the witness would explain that when all of this began when she was 14, she was living in a pool house because of her family's financial circumstances. But at some point during the years that followed, her family moved to a second house.\n7 THE COURT: And that's the address listed in the 302, as you understand it?\n8 MS. MOE: I don't recall offhand whether that's the particular address. I'd want to review the 3500. But I believe the witness was clarifying that she lived at a second house.\n9 THE COURT: Okay. All right.\n10 MR. EVERDELL: Your Honor, I'm sorry.\n11 I believe -- and I'm checking this right now, but I believe the address she put on her 1994 Interlochen application was the address we were showing her the photograph of. And she's saying she's in a pool house or homeless. So I think this is impeaching. I think this goes directly --\n12 THE COURT: Again, she said she lived -- they move in",
      "position": "main"
    },
    {
      "type": "printed",
      "content": "SOUTHERN DISTRICT REPORTERS, P.C. (212) 805-0300",
      "position": "footer"
    },
    {
      "type": "printed",
      "content": "DOJ-OGR-00012033",
      "position": "footer"
    }
  ],
  "entities": {
    "people": [
      "MS. MOE",
      "THE COURT",
      "MR. EVERDELL"
    ],
    "organizations": [
      "SOUTHERN DISTRICT REPORTERS, P.C.",
      "Interlochen"
    ],
    "locations": [],
    "dates": [
      "08/10/22",
      "1994"
    ],
    "reference_numbers": [
      "1:20-cr-00330-PAE",
      "745",
      "302",
      "3500",
      "DOJ-OGR-00012033"
    ]
  },
  "additional_notes": "The document appears to be a court transcript with a clear and legible format. There are no visible redactions or damage."
}