{
  "document_metadata": {
    "page_number": "81",
    "document_number": "763",
    "date": "08/10/22",
    "document_type": "court transcript",
    "has_handwriting": false,
    "has_stamps": false
  },
  "full_text": "Case 1:20-cr-00330-PAE Document 763 Filed 08/10/22 Page 81 of 197 2622\nLCHCmax3\nYoung - cross\n1 (In open court)\n2 MS. MENNINGER: Your Honor, can we strike the answer?\n3 THE COURT: Jury will disregard the answer regarding\n4 the agent's training in conducting interviews with children to gather information.\n5\n6 MS. COMEY: I'll move on, your Honor.\n7\n8 BY MS. COMEY:\n9 Q. Agent Young, did you participate in all of Jane's interviews with law enforcement?\n10\n11 A. Yes, I did.\n12 Q. During those interviews, was Jane able to talk about everything that happened with Maxwell and Epstein in a single meeting or did she disclose more over time?\n13\n14 A. No, she wasn't able to talk about everything in one meeting. It was a process and she disclosed at different points.\n15\n16 Q. Did you ever have to stop interviews with Jane when discussing abuse involving Epstein and Maxwell?\n17\n18 MS. MENNINGER: Objection, your Honor. Beyond the scope.\n19\n20 THE COURT: Sustained.\n21\n22 Q. Were you able to cover everything that Jane remembered about Jeffrey Epstein and Ghislaine Maxwell in a single interview?\n23\n24 SOUTHERN DISTRICT REPORTERS, P.C. (212) 805-0300\nDOJ-OGR-00014187",
  "text_blocks": [
    {
      "type": "printed",
      "content": "Case 1:20-cr-00330-PAE Document 763 Filed 08/10/22 Page 81 of 197 2622",
      "position": "header"
    },
    {
      "type": "printed",
      "content": "LCHCmax3\nYoung - cross",
      "position": "header"
    },
    {
      "type": "printed",
      "content": "(In open court)\nMS. MENNINGER: Your Honor, can we strike the answer?\nTHE COURT: Jury will disregard the answer regarding\nthe agent's training in conducting interviews with children to gather information.\nMS. COMEY: I'll move on, your Honor.\nTHE COURT: Thank you.\nBY MS. COMEY:\nQ. Agent Young, did you participate in all of Jane's interviews with law enforcement?\nA. Yes, I did.\nQ. During those interviews, was Jane able to talk about everything that happened with Maxwell and Epstein in a single meeting or did she disclose more over time?\nA. No, she wasn't able to talk about everything in one meeting. It was a process and she disclosed at different points.\nQ. Did you ever have to stop interviews with Jane when discussing abuse involving Epstein and Maxwell?\nMS. MENNINGER: Objection, your Honor. Beyond the scope.\nTHE COURT: Sustained.\nQ. Were you able to cover everything that Jane remembered about Jeffrey Epstein and Ghislaine Maxwell in a single interview?",
      "position": "main"
    },
    {
      "type": "printed",
      "content": "SOUTHERN DISTRICT REPORTERS, P.C. (212) 805-0300",
      "position": "footer"
    },
    {
      "type": "printed",
      "content": "DOJ-OGR-00014187",
      "position": "footer"
    }
  ],
  "entities": {
    "people": [
      "Jane",
      "Maxwell",
      "Epstein",
      "Jeffrey Epstein",
      "Ghislaine Maxwell",
      "Young",
      "MS. MENNINGER",
      "MS. COMEY"
    ],
    "organizations": [
      "SOUTHERN DISTRICT REPORTERS, P.C."
    ],
    "locations": [],
    "dates": [
      "08/10/22"
    ],
    "reference_numbers": [
      "1:20-cr-00330-PAE",
      "763",
      "DOJ-OGR-00014187"
    ]
  },
  "additional_notes": "The document appears to be a court transcript with a clear and readable format. There are no visible redactions or damage."
}