{
  "document_metadata": {
    "page_number": "26 of 95",
    "document_number": "765",
    "date": "08/10/22",
    "document_type": "court transcript",
    "has_handwriting": false,
    "has_stamps": false
  },
  "full_text": "Case 1:20-cr-00330-PAE Document 765 Filed 08/10/22 Page 26 of 95 2764 LCI1MAX1\nexplaining the fact that that causation needs to exist. In case there's any doubt in the minds of the jurors, there does need to be causation. There has to be an effect from the inducement, the persuasion, the enticement.\nMR. ROHRBACH: First there has to be some sort of causal relationship. That's what the word \"inducement\" means, for example, as a form of a causal relationship. I'm certainly not aware of any case or treatise that provided this instruction. Maybe perhaps defense counsel is. But, you know, the fact that it is in Broxmeyer does not mean it's appropriate to give a further and more specific instruction about causation than is already inherent in the ordinary meaning of these words.\nTHE COURT: Just so I have my head around it, the specific suggestion was what, Mr. Everdell?\nMR. EVERDELL: \"This element is satisfied only if the persuasion, inducement, or enticement caused Jane,\" or we can say \"caused the individual,\" \"to travel in interstate commerce as alleged in the indictment.\"\nMR. ROHRBACH: The problem, your Honor, is that to the extent that those words already mean to cause, inducement has a causal meaning, persuasion has a causal meaning. It's already in the instruction. And to say, you can only satisfy those words if she caused the travel suggests that there are two requirements -- there's the requirement that the defendant\nSOUTHERN DISTRICT REPORTERS, P.C. (212) 805-0300",
  "text_blocks": [
    {
      "type": "printed",
      "content": "Case 1:20-cr-00330-PAE Document 765 Filed 08/10/22 Page 26 of 95 2764 LCI1MAX1",
      "position": "header"
    },
    {
      "type": "printed",
      "content": "explaining the fact that that causation needs to exist. In case there's any doubt in the minds of the jurors, there does need to be causation. There has to be an effect from the inducement, the persuasion, the enticement.\nMR. ROHRBACH: First there has to be some sort of causal relationship. That's what the word \"inducement\" means, for example, as a form of a causal relationship. I'm certainly not aware of any case or treatise that provided this instruction. Maybe perhaps defense counsel is. But, you know, the fact that it is in Broxmeyer does not mean it's appropriate to give a further and more specific instruction about causation than is already inherent in the ordinary meaning of these words.\nTHE COURT: Just so I have my head around it, the specific suggestion was what, Mr. Everdell?\nMR. EVERDELL: \"This element is satisfied only if the persuasion, inducement, or enticement caused Jane,\" or we can say \"caused the individual,\" \"to travel in interstate commerce as alleged in the indictment.\"\nMR. ROHRBACH: The problem, your Honor, is that to the extent that those words already mean to cause, inducement has a causal meaning, persuasion has a causal meaning. It's already in the instruction. And to say, you can only satisfy those words if she caused the travel suggests that there are two requirements -- there's the requirement that the defendant",
      "position": "main content"
    },
    {
      "type": "printed",
      "content": "SOUTHERN DISTRICT REPORTERS, P.C. (212) 805-0300",
      "position": "footer"
    }
  ],
  "entities": {
    "people": [
      "Mr. Rohrbach",
      "Mr. Everdell",
      "Jane"
    ],
    "organizations": [
      "SOUTHERN DISTRICT REPORTERS, P.C."
    ],
    "locations": [],
    "dates": [
      "08/10/22"
    ],
    "reference_numbers": [
      "1:20-cr-00330-PAE",
      "765"
    ]
  },
  "additional_notes": "The document appears to be a court transcript with a discussion between the judge and lawyers about the concept of causation in a legal context. The text is typed, and there are no visible stamps or handwritten notes."
}