{
  "document_metadata": {
    "page_number": "98",
    "document_number": "747",
    "date": "08/10/22",
    "document_type": "Court Transcript",
    "has_handwriting": false,
    "has_stamps": false
  },
  "full_text": "Case 1:20-cr-00330-PAE Document 747 Filed 08/10/22 Page 98 of 228 774 LC2Qmax3 Rocchio - Redirect\n\n1 REDIRECT EXAMINATION\n2 BY MS. POMERANTZ:\n3 Q. Dr. Rocchio, you were asked about grooming the environment\n4 and about whether perpetrators deceive other adults around\n5 them. Dr. Rocchio, based on your experience, research, and\n6 training, if a perpetrator abused a child in front of another\n7 adult, is that grooming the environment?\n8 MR. PAGLIUCA: Your Honor, I object to this as being\n9 beyond the scope of my examination.\n10 THE COURT: I'm --\n11 A. No --\n12 THE COURT: I'm sorry, just a second.\n13 I'll sustain. The jury will disregard that response.\n14 MS. POMERANTZ: Your Honor, may I have one moment?\n15 THE COURT: You may.\n16 (Pause)\n17 MS. POMERANTZ: Your Honor, no further questions.\n18 THE COURT: Thank you, Dr. Rocchio.\n19 THE WITNESS: Thank you.\n20 THE COURT: You may step down.\n21 (Witness excused)\n22 THE COURT: The government may call its next witness.\n23 MS. COMEY: The government calls Juan Alessi.\n24 THE COURT: Juan Alessi may come forward.\n25 \nSOUTHERN DISTRICT REPORTERS, P.C. (212) 805-0300 DOJ-OGR-00012383",
  "text_blocks": [
    {
      "type": "printed",
      "content": "Case 1:20-cr-00330-PAE Document 747 Filed 08/10/22 Page 98 of 228 774 LC2Qmax3 Rocchio - Redirect",
      "position": "header"
    },
    {
      "type": "printed",
      "content": "1 REDIRECT EXAMINATION\n2 BY MS. POMERANTZ:\n3 Q. Dr. Rocchio, you were asked about grooming the environment\n4 and about whether perpetrators deceive other adults around\n5 them. Dr. Rocchio, based on your experience, research, and\n6 training, if a perpetrator abused a child in front of another\n7 adult, is that grooming the environment?\n8 MR. PAGLIUCA: Your Honor, I object to this as being\n9 beyond the scope of my examination.\n10 THE COURT: I'm --\n11 A. No --\n12 THE COURT: I'm sorry, just a second.\n13 I'll sustain. The jury will disregard that response.\n14 MS. POMERANTZ: Your Honor, may I have one moment?\n15 THE COURT: You may.\n16 (Pause)\n17 MS. POMERANTZ: Your Honor, no further questions.\n18 THE COURT: Thank you, Dr. Rocchio.\n19 THE WITNESS: Thank you.\n20 THE COURT: You may step down.\n21 (Witness excused)\n22 THE COURT: The government may call its next witness.\n23 MS. COMEY: The government calls Juan Alessi.\n24 THE COURT: Juan Alessi may come forward.",
      "position": "main"
    },
    {
      "type": "printed",
      "content": "SOUTHERN DISTRICT REPORTERS, P.C. (212) 805-0300 DOJ-OGR-00012383",
      "position": "footer"
    }
  ],
  "entities": {
    "people": [
      "MS. POMERANTZ",
      "Dr. Rocchio",
      "MR. PAGLIUCA",
      "Juan Alessi",
      "MS. COMEY"
    ],
    "organizations": [
      "SOUTHERN DISTRICT REPORTERS, P.C.",
      "THE COURT",
      "THE WITNESS"
    ],
    "locations": [],
    "dates": [
      "08/10/22"
    ],
    "reference_numbers": [
      "1:20-cr-00330-PAE",
      "747",
      "DOJ-OGR-00012383"
    ]
  },
  "additional_notes": "The document appears to be a court transcript with a clear structure and formatting. There are no visible redactions or damage."
}