{
  "document_metadata": {
    "page_number": "43",
    "document_number": "759",
    "date": "08/10/22",
    "document_type": "court transcript",
    "has_handwriting": false,
    "has_stamps": false
  },
  "full_text": "Case 1:20-cr-00330-PAE Document 759 Filed 08/10/22 Page 43 of 267 2071 LCAVMAX2 A. Farmer - direct 1 A. That's correct. 2 Q. Based on your conversations with your mother, who did you 3 understand you would be seeing in New Mexico? 4 MS. MENNINGER: Objection. 5 Hearsay, your Honor. 6 THE COURT: Sustained. 7 MS. POMERANTZ: Your Honor, this is not being offered 8 for the truth. 9 THE COURT: Sustained. 10 MS. POMERANTZ: May I have one moment? 11 THE COURT: You may. 12 (Counsel conferred) 13 MS. POMERANTZ: Your Honor, may we approach? 14 THE COURT: You may. 15 (Continued on next page) 16 17 18 19 20 21 22 23 24 25 SOUTHERN DISTRICT REPORTERS, P.C. (212) 805-0300 DOJ-OGR-00013634",
  "text_blocks": [
    {
      "type": "printed",
      "content": "Case 1:20-cr-00330-PAE Document 759 Filed 08/10/22 Page 43 of 267 2071",
      "position": "header"
    },
    {
      "type": "printed",
      "content": "LCAVMAX2 A. Farmer - direct",
      "position": "header"
    },
    {
      "type": "printed",
      "content": "1 A. That's correct. 2 Q. Based on your conversations with your mother, who did you 3 understand you would be seeing in New Mexico? 4 MS. MENNINGER: Objection. 5 Hearsay, your Honor. 6 THE COURT: Sustained. 7 MS. POMERANTZ: Your Honor, this is not being offered 8 for the truth. 9 THE COURT: Sustained. 10 MS. POMERANTZ: May I have one moment? 11 THE COURT: You may. 12 (Counsel conferred) 13 MS. POMERANTZ: Your Honor, may we approach? 14 THE COURT: You may. 15 (Continued on next page)",
      "position": "main content"
    },
    {
      "type": "printed",
      "content": "SOUTHERN DISTRICT REPORTERS, P.C. (212) 805-0300",
      "position": "footer"
    },
    {
      "type": "printed",
      "content": "DOJ-OGR-00013634",
      "position": "footer"
    }
  ],
  "entities": {
    "people": [
      "Farmer",
      "MS. MENNINGER",
      "MS. POMERANTZ"
    ],
    "organizations": [
      "SOUTHERN DISTRICT REPORTERS, P.C."
    ],
    "locations": [
      "New Mexico"
    ],
    "dates": [
      "08/10/22"
    ],
    "reference_numbers": [
      "1:20-cr-00330-PAE",
      "759",
      "DOJ-OGR-00013634"
    ]
  },
  "additional_notes": "The document appears to be a court transcript with a clear and legible format. There are no visible redactions or damage."
}