{
  "document_metadata": {
    "page_number": "83",
    "document_number": "759",
    "date": "08/10/22",
    "document_type": "court transcript",
    "has_handwriting": false,
    "has_stamps": false
  },
  "full_text": "Case 1:20-cr-00330-PAE Document 759 Filed 08/10/22 Page 83 of 267 2111\nLCACmax3 A. Farmer - cross\n1 A. No.\n2 Q. You had seen it before?\n3 A. Yeah, a friend invited me in Phoenix.\n4 Q. And it was better this time in New York?\n5 A. Yes.\n6 Q. And, again, Ghislaine Maxwell wasn't a part of this conversation at Epstein's home; right?\n7 \n8 A. She was not.\n9 Q. He didn't even mention her during this trip to his home; correct?\n10 \n11 A. That, I don't remember.\n12 Q. Well, you've spoken to the government a number of times; correct?\n13 \n14 A. Yes.\n15 Q. You filed a civil lawsuit against Ms. Maxwell; right?\n16 A. Yes.\n17 Q. You submitted a claim to the Victims Compensation Fund; right?\n18 \n19 A. Yes.\n20 Q. And on none of those occasions have you said that Mr. Epstein's conversation with you at his home involved Ghislaine Maxwell; right?\n21 \n22 A. It did not center on her. I don't remember if she was mentioned. I was trying to be accurate, yeah.\n23 \n24 Q. And if you didn't remember it, you didn't tell someone\n25 \nSOUTHERN DISTRICT REPORTERS, P.C. (212) 805-0300\nDOJ-OGR-00013674",
  "text_blocks": [
    {
      "type": "printed",
      "content": "Case 1:20-cr-00330-PAE Document 759 Filed 08/10/22 Page 83 of 267 2111",
      "position": "header"
    },
    {
      "type": "handwritten",
      "content": "LCACmax3 A. Farmer - cross",
      "position": "header"
    },
    {
      "type": "printed",
      "content": "1 A. No.\n2 Q. You had seen it before?\n3 A. Yeah, a friend invited me in Phoenix.\n4 Q. And it was better this time in New York?\n5 A. Yes.\n6 Q. And, again, Ghislaine Maxwell wasn't a part of this conversation at Epstein's home; right?\n7 \n8 A. She was not.\n9 Q. He didn't even mention her during this trip to his home; correct?\n10 \n11 A. That, I don't remember.\n12 Q. Well, you've spoken to the government a number of times; correct?\n13 \n14 A. Yes.\n15 Q. You filed a civil lawsuit against Ms. Maxwell; right?\n16 A. Yes.\n17 Q. You submitted a claim to the Victims Compensation Fund; right?\n18 \n19 A. Yes.\n20 Q. And on none of those occasions have you said that Mr. Epstein's conversation with you at his home involved Ghislaine Maxwell; right?\n21 \n22 A. It did not center on her. I don't remember if she was mentioned. I was trying to be accurate, yeah.\n23 \n24 Q. And if you didn't remember it, you didn't tell someone",
      "position": "main"
    },
    {
      "type": "printed",
      "content": "SOUTHERN DISTRICT REPORTERS, P.C. (212) 805-0300",
      "position": "footer"
    },
    {
      "type": "printed",
      "content": "DOJ-OGR-00013674",
      "position": "footer"
    }
  ],
  "entities": {
    "people": [
      "Ghislaine Maxwell",
      "Epstein"
    ],
    "organizations": [
      "Victims Compensation Fund",
      "SOUTHERN DISTRICT REPORTERS, P.C."
    ],
    "locations": [
      "Phoenix",
      "New York"
    ],
    "dates": [
      "08/10/22"
    ],
    "reference_numbers": [
      "1:20-cr-00330-PAE",
      "759",
      "DOJ-OGR-00013674"
    ]
  },
  "additional_notes": "The document appears to be a court transcript with a clear and legible format. There are no visible redactions or damage."
}