{
  "document_metadata": {
    "page_number": "51",
    "document_number": "767",
    "date": "08/10/22",
    "document_type": "Court Document",
    "has_handwriting": false,
    "has_stamps": false
  },
  "full_text": "Case 1:20-cr-00330-PAE Document 767 Filed 08/10/22 Page 51 of 257 2884\nLCKCmax3 Summation - Ms. Moe\n1 Melissa's birth certificate. Sean told you this is the girl.\n2 And sure enough, there are two entries under massage for\n3 Melissa, Carolyn's friend. Here they are.\n4 Again, remember how you learned that, by this point,\n5 things operated like a pyramid scheme. Virginia brought\n6 Carolyn. Carolyn brought Melissa and other girls. One girl\n7 would bring another, who would bring another.\n8 Ladies and gentlemen, this book, Maxwell's book, it\n9 proves to you that Maxwell is guilty. What you'll see in this\n10 book corroborates the witnesses who testified at this trial.\n11 She had victim names written in a little black book. This\n12 document is powerful evidence of the defendant's knowledge and\n13 intent. These were not real massages. What was happening was\n14 sexual abuse with underage girls. Maxwell knew it, she was\n15 part of it, she was responsible for it, and the fact that she\n16 had a little black book with her victims' names in it proves to\n17 you that she is guilty.\n18 That brings us to the seventh reason that you know\n19 Maxwell is guilty. It's the money. Now, we've already talked\n20 about Epstein's luxurious lifestyle and all of the perks that\n21 Maxwell got from being his partner in crime, but it wasn't just\n22 getting to live in the mansions and flying on the private jets,\n23 maxwell got millions of dollars from Epstein. You learned that\n24 between 1999 and 2007, Jeffrey Epstein gave Maxwell about $30\n25 million, and you know exactly what that money was for.\nSOUTHERN DISTRICT REPORTERS, P.C. (212) 805-0300\nDOJ-OGR-00014451",
  "text_blocks": [
    {
      "type": "printed",
      "content": "Case 1:20-cr-00330-PAE Document 767 Filed 08/10/22 Page 51 of 257 2884",
      "position": "header"
    },
    {
      "type": "printed",
      "content": "LCKCmax3 Summation - Ms. Moe",
      "position": "header"
    },
    {
      "type": "printed",
      "content": "1 Melissa's birth certificate. Sean told you this is the girl.\n2 And sure enough, there are two entries under massage for\n3 Melissa, Carolyn's friend. Here they are.\n4 Again, remember how you learned that, by this point,\n5 things operated like a pyramid scheme. Virginia brought\n6 Carolyn. Carolyn brought Melissa and other girls. One girl\n7 would bring another, who would bring another.\n8 Ladies and gentlemen, this book, Maxwell's book, it\n9 proves to you that Maxwell is guilty. What you'll see in this\n10 book corroborates the witnesses who testified at this trial.\n11 She had victim names written in a little black book. This\n12 document is powerful evidence of the defendant's knowledge and\n13 intent. These were not real massages. What was happening was\n14 sexual abuse with underage girls. Maxwell knew it, she was\n15 part of it, she was responsible for it, and the fact that she\n16 had a little black book with her victims' names in it proves to\n17 you that she is guilty.\n18 That brings us to the seventh reason that you know\n19 Maxwell is guilty. It's the money. Now, we've already talked\n20 about Epstein's luxurious lifestyle and all of the perks that\n21 Maxwell got from being his partner in crime, but it wasn't just\n22 getting to live in the mansions and flying on the private jets,\n23 maxwell got millions of dollars from Epstein. You learned that\n24 between 1999 and 2007, Jeffrey Epstein gave Maxwell about $30\n25 million, and you know exactly what that money was for.",
      "position": "main"
    },
    {
      "type": "printed",
      "content": "SOUTHERN DISTRICT REPORTERS, P.C. (212) 805-0300",
      "position": "footer"
    },
    {
      "type": "printed",
      "content": "DOJ-OGR-00014451",
      "position": "footer"
    }
  ],
  "entities": {
    "people": [
      "Melissa",
      "Sean",
      "Carolyn",
      "Virginia",
      "Maxwell",
      "Jeffrey Epstein"
    ],
    "organizations": [
      "SOUTHERN DISTRICT REPORTERS, P.C."
    ],
    "locations": [],
    "dates": [
      "08/10/22",
      "1999",
      "2007"
    ],
    "reference_numbers": [
      "1:20-cr-00330-PAE",
      "767",
      "DOJ-OGR-00014451"
    ]
  },
  "additional_notes": "The document appears to be a court transcript from the trial of Ghislaine Maxwell, with the speaker discussing evidence and testimony related to Maxwell's alleged crimes."
}