{
  "document_metadata": {
    "page_number": "86 of 95",
    "document_number": "765",
    "date": "08/10/22",
    "document_type": "court transcript",
    "has_handwriting": false,
    "has_stamps": false
  },
  "full_text": "Case 1:20-cr-00330-PAE Document 765 Filed 08/10/22 Page 86 of 95 2824 LCIAMAX2ps\n1 MR. EVERDELL: Count Two, \"enticement of an individual under the age of 17.\" And then we would propose \"(Jane only),\" to add the word \"only,\" your Honor.\n2\n3 THE COURT: So adding, after \"an individual,\" \"under the age of 17,\" adding in the parentheses, after the word \"Jane,\" \"only.\"\n4\n5 MR. EVERDELL: Correct.\n6\n7 THE COURT: OK.\n8\n9 MR. EVERDELL: Count Three, to transport and then take out the word \"a minor,\" this would be, I guess, \"individuals under the age of 17.\"\n10\n11 MR. ROHRBACH: Agreed, your Honor.\n12\n13 THE COURT: OK. I will make that change to \"individuals under the age of 17,\" taking out \"a minor.\"\n14\n15 MR. EVERDELL: And then Count Four, \"transportation of an individual,\" adding \"under the age of 17\" and adding the word \"only\" after \"Jane.\"\n16\n17 THE COURT: OK.\n18\n19 MR. ROHRBACH: That's fine, your Honor.\n20\n21 THE COURT: All right. Make that change, adding \"under the age of 17\" and then adding \"only\" after the word \"Jane.\"\n22\n23 MR. EVERDELL: Let's just skip over Count Five for a second. Count Six.\n24\n25 THE COURT: \"Only.\"\n    SOUTHERN DISTRICT REPORTERS, P.C. (212) 805-0300",
  "text_blocks": [
    {
      "type": "printed",
      "content": "Case 1:20-cr-00330-PAE Document 765 Filed 08/10/22 Page 86 of 95 2824 LCIAMAX2ps",
      "position": "header"
    },
    {
      "type": "printed",
      "content": "1 MR. EVERDELL: Count Two, \"enticement of an individual under the age of 17.\" And then we would propose \"(Jane only),\" to add the word \"only,\" your Honor.\n2\n3 THE COURT: So adding, after \"an individual,\" \"under the age of 17,\" adding in the parentheses, after the word \"Jane,\" \"only.\"\n4\n5 MR. EVERDELL: Correct.\n6\n7 THE COURT: OK.\n8\n9 MR. EVERDELL: Count Three, to transport and then take out the word \"a minor,\" this would be, I guess, \"individuals under the age of 17.\"\n10\n11 MR. ROHRBACH: Agreed, your Honor.\n12\n13 THE COURT: OK. I will make that change to \"individuals under the age of 17,\" taking out \"a minor.\"\n14\n15 MR. EVERDELL: And then Count Four, \"transportation of an individual,\" adding \"under the age of 17\" and adding the word \"only\" after \"Jane.\"\n16\n17 THE COURT: OK.\n18\n19 MR. ROHRBACH: That's fine, your Honor.\n20\n21 THE COURT: All right. Make that change, adding \"under the age of 17\" and then adding \"only\" after the word \"Jane.\"\n22\n23 MR. EVERDELL: Let's just skip over Count Five for a second. Count Six.\n24\n25 THE COURT: \"Only.\"",
      "position": "main content"
    },
    {
      "type": "printed",
      "content": "SOUTHERN DISTRICT REPORTERS, P.C. (212) 805-0300",
      "position": "footer"
    }
  ],
  "entities": {
    "people": [
      "MR. EVERDELL",
      "MR. ROHRBACH"
    ],
    "organizations": [
      "SOUTHERN DISTRICT REPORTERS, P.C."
    ],
    "locations": [],
    "dates": [
      "08/10/22"
    ],
    "reference_numbers": [
      "1:20-cr-00330-PAE",
      "765",
      "2824",
      "LCIAMAX2ps",
      "212-805-0300"
    ]
  },
  "additional_notes": "The document appears to be a court transcript with a clear and legible format. There are no visible redactions or damage."
}