{
  "document_metadata": {
    "page_number": "16",
    "document_number": "759",
    "date": "08/10/22",
    "document_type": "Court Transcript",
    "has_handwriting": false,
    "has_stamps": false
  },
  "full_text": "Case 1:20-cr-00330-PAE Document 759 Filed 08/10/22 Page 16 of 267 2044\nLCACmax1\nBrown - direct\n1 photograph?\n2 A. A motor vehicle representative will take that photograph at\n3 the counter.\n4 Q. Is making identification cards a regular practice of the\n5 Department of Motor Vehicles?\n6 A. Yes, it is.\n7 Q. I'd like you to pick up the folder next to you. Would you\n8 please look at what's been marked for identification as\n9 Government Exhibit 21.\n10 A. Okay.\n11 Q. Do you recognize this?\n12 A. Yes, I do.\n13 Q. Have you reviewed it before today?\n14 A. Yes, I have.\n15 Q. Without saying any names, what is it?\n16 A. It is a database -- New York State DMV compass database.\n17 Q. What is the compass database or what records are stored?\n18 A. ID cards, driver's licenses.\n19 Q. Is this a fair and accurate report from the compass\n20 database?\n21 A. Yes, it is.\n22 Q. Is the data stored in the compass database kept in the\n23 ordinary course of business?\n24 A. Yes, it is.\n25 MR. ROHRBACH: The government offers Government\nSOUTHERN DISTRICT REPORTERS, P.C.\n(212) 805-0300\nDOJ-OGR-00013607",
  "text_blocks": [
    {
      "type": "printed",
      "content": "Case 1:20-cr-00330-PAE Document 759 Filed 08/10/22 Page 16 of 267 2044",
      "position": "header"
    },
    {
      "type": "printed",
      "content": "LCACmax1\nBrown - direct",
      "position": "header"
    },
    {
      "type": "printed",
      "content": "1 photograph?\n2 A. A motor vehicle representative will take that photograph at\n3 the counter.\n4 Q. Is making identification cards a regular practice of the\n5 Department of Motor Vehicles?\n6 A. Yes, it is.\n7 Q. I'd like you to pick up the folder next to you. Would you\n8 please look at what's been marked for identification as\n9 Government Exhibit 21.\n10 A. Okay.\n11 Q. Do you recognize this?\n12 A. Yes, I do.\n13 Q. Have you reviewed it before today?\n14 A. Yes, I have.\n15 Q. Without saying any names, what is it?\n16 A. It is a database -- New York State DMV compass database.\n17 Q. What is the compass database or what records are stored?\n18 A. ID cards, driver's licenses.\n19 Q. Is this a fair and accurate report from the compass\n20 database?\n21 A. Yes, it is.\n22 Q. Is the data stored in the compass database kept in the\n23 ordinary course of business?\n24 A. Yes, it is.\n25 MR. ROHRBACH: The government offers Government",
      "position": "main"
    },
    {
      "type": "printed",
      "content": "SOUTHERN DISTRICT REPORTERS, P.C.\n(212) 805-0300",
      "position": "footer"
    },
    {
      "type": "printed",
      "content": "DOJ-OGR-00013607",
      "position": "footer"
    }
  ],
  "entities": {
    "people": [
      "MR. ROHRBACH"
    ],
    "organizations": [
      "Department of Motor Vehicles",
      "New York State DMV",
      "SOUTHERN DISTRICT REPORTERS, P.C."
    ],
    "locations": [
      "New York"
    ],
    "dates": [
      "08/10/22"
    ],
    "reference_numbers": [
      "1:20-cr-00330-PAE",
      "759",
      "21",
      "DOJ-OGR-00013607"
    ]
  },
  "additional_notes": "The document appears to be a court transcript with a clear and legible format. There are no visible redactions or damage."
}