{
  "document_metadata": {
    "page_number": "194",
    "document_number": "767",
    "date": "08/10/22",
    "document_type": "court document",
    "has_handwriting": false,
    "has_stamps": false
  },
  "full_text": "Case 1:20-cr-00330-PAE Document 767 Filed 08/10/22 Page 194 of 257 3028 LCKVMAX8 Charge the time period 1994 to 1997. Count Three of the indictment charges the defendant with conspiring with others to transport an individual under the age of 17 in interstate commerce with intent that the individual engaged in sexual activity for which a person can be charged with a criminal offense. Count Three relates to multiple alleged victims and the time period 1994 to 2004. Count Four of the indictment charges the defendant with transporting an individual under the age of 17 in interstate commerce, with the intent that the individual engage in sexual activity for which a person could be charged with a criminal offense. Count Four relates solely to Jane and the time period 1994 to 1997. Count Five of the indictment charges the defendant with conspiring to engage in sex trafficking of individuals under the age of 18. Count Five relates to multiple alleged victims in the time period 2001 to 2004. Count Six of the indictment charges the defendant with sex trafficking of an individual under the age of 18. Count Six relates solely to Carolyn and the time period 2001 to 2004. Instruction No. 11. Multiple counts. As I just explained, the indictment contains six counts. Each count charges Ms. Maxwell with a different crime. You must consider each count separately and return a separate verdict of guilty or not guilty for each. Whether you find Ms. SOUTHERN DISTRICT REPORTERS, P.C. (212) 805-0300 DOJ-OGR-00014594",
  "text_blocks": [
    {
      "type": "printed",
      "content": "Case 1:20-cr-00330-PAE Document 767 Filed 08/10/22 Page 194 of 257 3028 LCKVMAX8 Charge",
      "position": "header"
    },
    {
      "type": "printed",
      "content": "the time period 1994 to 1997. Count Three of the indictment charges the defendant with conspiring with others to transport an individual under the age of 17 in interstate commerce with intent that the individual engaged in sexual activity for which a person can be charged with a criminal offense. Count Three relates to multiple alleged victims and the time period 1994 to 2004. Count Four of the indictment charges the defendant with transporting an individual under the age of 17 in interstate commerce, with the intent that the individual engage in sexual activity for which a person could be charged with a criminal offense. Count Four relates solely to Jane and the time period 1994 to 1997. Count Five of the indictment charges the defendant with conspiring to engage in sex trafficking of individuals under the age of 18. Count Five relates to multiple alleged victims in the time period 2001 to 2004. Count Six of the indictment charges the defendant with sex trafficking of an individual under the age of 18. Count Six relates solely to Carolyn and the time period 2001 to 2004. Instruction No. 11. Multiple counts. As I just explained, the indictment contains six counts. Each count charges Ms. Maxwell with a different crime. You must consider each count separately and return a separate verdict of guilty or not guilty for each. Whether you find Ms.",
      "position": "main content"
    },
    {
      "type": "printed",
      "content": "SOUTHERN DISTRICT REPORTERS, P.C. (212) 805-0300",
      "position": "footer"
    },
    {
      "type": "printed",
      "content": "DOJ-OGR-00014594",
      "position": "footer"
    }
  ],
  "entities": {
    "people": [
      "Maxwell",
      "Jane",
      "Carolyn"
    ],
    "organizations": [
      "SOUTHERN DISTRICT REPORTERS, P.C."
    ],
    "locations": [],
    "dates": [
      "1994",
      "1997",
      "2001",
      "2004",
      "08/10/22"
    ],
    "reference_numbers": [
      "1:20-cr-00330-PAE",
      "767",
      "DOJ-OGR-00014594"
    ]
  },
  "additional_notes": "The document appears to be a court transcript or legal document related to the case of Ms. Maxwell. The text is printed and there are no visible stamps or handwritten notes. The document is from the Southern District Reporters, P.C. and contains a reference number DOJ-OGR-00014594."
}