{
  "document_metadata": {
    "page_number": "75",
    "document_number": "753",
    "date": "08/10/22",
    "document_type": "court transcript",
    "has_handwriting": false,
    "has_stamps": false
  },
  "full_text": "Case 1:20-cr-00330-PAE Document 753 Filed 08/10/22 Page 75 of 264 1501 LC7Cmax2 Flatley - cross course of that copying; correct? A. That is correct. Q. You just don't have something to compare it to; right? A. Correct. Q. If you had the other one, you could run the same program; right? MS. POMERANTZ: Objection, your Honor. THE COURT: Overruled. Q. If you had the other one, you could run the same program and make sure that they were identical; right? A. That's correct. Q. So, because you don't have that other thing to compare it to - what you think is a desktop; right? A. Correct. Q. - you don't know where that desktop was living when any of these exhibits were created; correct? MS. POMERANTZ: Objection, your Honor. THE COURT: Overruled. A. No, I don't. Q. Right. You don't have a location, a geo location for any of these particular documents you've been testifying about; correct? A. That's correct. Q. So the desktop could have been in Florida or in New York or somewhere else; right? SOUTHERN DISTRICT REPORTERS, P.C. (212) 805-0300 DOJ-OGR-00013088",
  "text_blocks": [
    {
      "type": "printed",
      "content": "Case 1:20-cr-00330-PAE Document 753 Filed 08/10/22 Page 75 of 264 1501 LC7Cmax2 Flatley - cross",
      "position": "header"
    },
    {
      "type": "printed",
      "content": "course of that copying; correct? A. That is correct. Q. You just don't have something to compare it to; right? A. Correct. Q. If you had the other one, you could run the same program; right? MS. POMERANTZ: Objection, your Honor. THE COURT: Overruled. Q. If you had the other one, you could run the same program and make sure that they were identical; right? A. That's correct. Q. So, because you don't have that other thing to compare it to - what you think is a desktop; right? A. Correct. Q. - you don't know where that desktop was living when any of these exhibits were created; correct? MS. POMERANTZ: Objection, your Honor. THE COURT: Overruled. A. No, I don't. Q. Right. You don't have a location, a geo location for any of these particular documents you've been testifying about; correct? A. That's correct. Q. So the desktop could have been in Florida or in New York or somewhere else; right?",
      "position": "main"
    },
    {
      "type": "printed",
      "content": "SOUTHERN DISTRICT REPORTERS, P.C. (212) 805-0300",
      "position": "footer"
    },
    {
      "type": "printed",
      "content": "DOJ-OGR-00013088",
      "position": "footer"
    }
  ],
  "entities": {
    "people": [
      "MS. POMERANTZ"
    ],
    "organizations": [
      "SOUTHERN DISTRICT REPORTERS, P.C."
    ],
    "locations": [
      "Florida",
      "New York"
    ],
    "dates": [
      "08/10/22"
    ],
    "reference_numbers": [
      "1:20-cr-00330-PAE",
      "753",
      "75",
      "264",
      "DOJ-OGR-00013088"
    ]
  },
  "additional_notes": "The document appears to be a court transcript with a clear and legible format. There are no visible redactions or damage."
}