{
  "document_metadata": {
    "page_number": "22",
    "document_number": "747",
    "date": "08/10/22",
    "document_type": "court transcript",
    "has_handwriting": false,
    "has_stamps": false
  },
  "full_text": "Case 1:20-cr-00330-PAE Document 747 Filed 08/10/22 Page 22 of 228 698 LC2VMAX2 Kane - Redirect 1 Q. On the first page there is the name of a counsellor or principal for the student's prior high school. Do you see that name? 2 3 A. Yes, I do. 4 Q. And while you don't need to read it out, do you have any 5 reason to doubt that that was, in fact, the student's prior 6 principal? 7 A. I have no reason to doubt. 8 Q. All right. Thank you. 9 10 REDIRECT EXAMINATION 11 BY MR. ROHRBACH: 12 Q. Mr. Kane, on cross-examination you were asked about payment 13 records for the student in this application. Did you find any 14 payment records reflecting who paid for that student's 15 education? 16 A. No. Financial records are kept separately from the student 17 file. 18 Q. Thank you. No further questions. 19 MS. MENNINGER: No, thank you, your Honor. 20 THE COURT: All right. Thank you, Mr. Kane. 21 You may step down. You are excused. Thank you. 22 (Witness excused) 23 THE COURT: The government may call its next witness. 24 MS. POMERANTZ: Your Honor, the government calls Dr. 25 Lisa Rocchio. SOUTHERN DISTRICT REPORTERS, P.C. (212) 805-0300 DOJ-OGR-00012307",
  "text_blocks": [
    {
      "type": "printed",
      "content": "Case 1:20-cr-00330-PAE Document 747 Filed 08/10/22 Page 22 of 228 698",
      "position": "header"
    },
    {
      "type": "printed",
      "content": "LC2VMAX2 Kane - Redirect",
      "position": "header"
    },
    {
      "type": "printed",
      "content": "1 Q. On the first page there is the name of a counsellor or principal for the student's prior high school. Do you see that name? 2 3 A. Yes, I do. 4 Q. And while you don't need to read it out, do you have any 5 reason to doubt that that was, in fact, the student's prior 6 principal? 7 A. I have no reason to doubt. 8 Q. All right. Thank you. 9 10 REDIRECT EXAMINATION 11 BY MR. ROHRBACH: 12 Q. Mr. Kane, on cross-examination you were asked about payment 13 records for the student in this application. Did you find any 14 payment records reflecting who paid for that student's 15 education? 16 A. No. Financial records are kept separately from the student 17 file. 18 Q. Thank you. No further questions. 19 MS. MENNINGER: No, thank you, your Honor. 20 THE COURT: All right. Thank you, Mr. Kane. 21 You may step down. You are excused. Thank you. 22 (Witness excused) 23 THE COURT: The government may call its next witness. 24 MS. POMERANTZ: Your Honor, the government calls Dr. 25 Lisa Rocchio.",
      "position": "main"
    },
    {
      "type": "printed",
      "content": "SOUTHERN DISTRICT REPORTERS, P.C. (212) 805-0300",
      "position": "footer"
    },
    {
      "type": "printed",
      "content": "DOJ-OGR-00012307",
      "position": "footer"
    }
  ],
  "entities": {
    "people": [
      "Mr. Kane",
      "MR. ROHRBACH",
      "MS. MENNINGER",
      "Dr. Lisa Rocchio",
      "MS. POMERANTZ"
    ],
    "organizations": [
      "SOUTHERN DISTRICT REPORTERS, P.C."
    ],
    "locations": [],
    "dates": [
      "08/10/22"
    ],
    "reference_numbers": [
      "1:20-cr-00330-PAE",
      "747",
      "DOJ-OGR-00012307"
    ]
  },
  "additional_notes": "The document appears to be a court transcript with clear and legible text. There are no visible redactions or damage."
}