{
  "document_metadata": {
    "page_number": "56",
    "document_number": "763",
    "date": "08/10/22",
    "document_type": "court transcript",
    "has_handwriting": false,
    "has_stamps": false
  },
  "full_text": "Case 1:20-cr-00330-PAE Document 763 Filed 08/10/22 Page 56 of 197 2597\nLCHVMAX2\nRichards - direct\n1 Q. And where were you before 2014?\n2 A. Prior to that I was at the Miami division's Palm Beach resident agency. I was there in 2006 to 2014.\n3 Q. Okay. And prior to 2006, where were you stationed?\n4 A. I was stationed at the Covington resident agency at the Louisville division in Kentucky.\n5 Q. I want to direct your attention to 2006, when you were in the Palm Beach area. Okay?\n6 A. Okay.\n7 Q. Were you assigned to a particular unit in 2006?\n8 A. Yes. At that time I was assigned to squad PB2.\n9 Q. And what is squad PV2?\n10 A. It's PB2.\n11 Q. PB2.\n12 A. Yes. It's the violent crimes squad and safe streets task force.\n13 Q. And were you involved at that point in an investigation regarding Jeffrey Epstein?\n14 A. Yes.\n15 Q. And did part of your job during that investigation involve talking to witnesses in that case?\n16 A. Yes.\n17 Q. You indicated that as part of your training as an FBI agent, you are trained to do interview techniques with witnesses, right?\n18 SOUTHERN DISTRICT REPORTERS, P.C. (212) 805-0300\nDOJ-OGR-00014162",
  "text_blocks": [
    {
      "type": "printed",
      "content": "Case 1:20-cr-00330-PAE Document 763 Filed 08/10/22 Page 56 of 197 2597",
      "position": "header"
    },
    {
      "type": "printed",
      "content": "LCHVMAX2\nRichards - direct",
      "position": "header"
    },
    {
      "type": "printed",
      "content": "1 Q. And where were you before 2014?\n2 A. Prior to that I was at the Miami division's Palm Beach resident agency. I was there in 2006 to 2014.\n3 Q. Okay. And prior to 2006, where were you stationed?\n4 A. I was stationed at the Covington resident agency at the Louisville division in Kentucky.\n5 Q. I want to direct your attention to 2006, when you were in the Palm Beach area. Okay?\n6 A. Okay.\n7 Q. Were you assigned to a particular unit in 2006?\n8 A. Yes. At that time I was assigned to squad PB2.\n9 Q. And what is squad PV2?\n10 A. It's PB2.\n11 Q. PB2.\n12 A. Yes. It's the violent crimes squad and safe streets task force.\n13 Q. And were you involved at that point in an investigation regarding Jeffrey Epstein?\n14 A. Yes.\n15 Q. And did part of your job during that investigation involve talking to witnesses in that case?\n16 A. Yes.\n17 Q. You indicated that as part of your training as an FBI agent, you are trained to do interview techniques with witnesses, right?",
      "position": "main"
    },
    {
      "type": "printed",
      "content": "SOUTHERN DISTRICT REPORTERS, P.C. (212) 805-0300",
      "position": "footer"
    },
    {
      "type": "printed",
      "content": "DOJ-OGR-00014162",
      "position": "footer"
    }
  ],
  "entities": {
    "people": [
      "Jeffrey Epstein"
    ],
    "organizations": [
      "FBI",
      "SOUTHERN DISTRICT REPORTERS, P.C."
    ],
    "locations": [
      "Palm Beach",
      "Miami",
      "Covington",
      "Kentucky",
      "Louisville"
    ],
    "dates": [
      "2006",
      "2014",
      "08/10/22"
    ],
    "reference_numbers": [
      "1:20-cr-00330-PAE",
      "763",
      "DOJ-OGR-00014162"
    ]
  },
  "additional_notes": "The document appears to be a court transcript with a clear and legible format. There are no visible redactions or damage."
}