{
  "document_metadata": {
    "page_number": "219",
    "document_number": "759",
    "date": "08/10/22",
    "document_type": "court transcript",
    "has_handwriting": false,
    "has_stamps": false
  },
  "full_text": "Case 1:20-cr-00330-PAE Document 759 Filed 08/10/22 Page 219 of 267 2247 LCACmax7 Swain - direct 1 THE COURT: Please be seated. If you remove your mask and please state and spell your name for the record. 3 THE WITNESS: Janice Swain, J-a-n-i-c-e S-w-a-i-n. 4 THE COURT: Ms. Swain, I'll ask you to please pull the microphone up to you and you need to speak directly into it. 5 Please keep your voice up. Thank you so much. 6 7 THE WITNESS: Okay. 8 THE COURT: Go ahead, Ms. Pomerantz, you may inquire. 9 MS. POMERANTZ: Thank you, your Honor. 10 DIRECT EXAMINATION 11 BY MS. POMERANTZ: 12 Q. Good afternoon, Ms. Swain. 13 A. Good afternoon. 14 Q. If I can ask you to speak directly into the microphone, I want to make sure everyone can hear you. 15 16 A. Okay. 17 Q. Thank you. Ms. Swain, how old are you? 18 A. I'm 71. 19 Q. How far did you go in school? 20 A. High school. 21 Q. What kind of work do you do now? 22 A. I'm a sales representative. 23 Q. How many children do you have? 24 A. I have three. 25 Q. What is the name of your oldest child? 26 27 SOUTHERN DISTRICT REPORTERS, P.C. (212) 805-0300 DOJ-OGR-00013810",
  "text_blocks": [
    {
      "type": "printed",
      "content": "Case 1:20-cr-00330-PAE Document 759 Filed 08/10/22 Page 219 of 267 2247 LCACmax7 Swain - direct",
      "position": "header"
    },
    {
      "type": "printed",
      "content": "1 THE COURT: Please be seated. If you remove your mask and please state and spell your name for the record. 3 THE WITNESS: Janice Swain, J-a-n-i-c-e S-w-a-i-n. 4 THE COURT: Ms. Swain, I'll ask you to please pull the microphone up to you and you need to speak directly into it. 5 Please keep your voice up. Thank you so much. 6 7 THE WITNESS: Okay. 8 THE COURT: Go ahead, Ms. Pomerantz, you may inquire. 9 MS. POMERANTZ: Thank you, your Honor. 10 DIRECT EXAMINATION 11 BY MS. POMERANTZ: 12 Q. Good afternoon, Ms. Swain. 13 A. Good afternoon. 14 Q. If I can ask you to speak directly into the microphone, I want to make sure everyone can hear you. 15 16 A. Okay. 17 Q. Thank you. Ms. Swain, how old are you? 18 A. I'm 71. 19 Q. How far did you go in school? 20 A. High school. 21 Q. What kind of work do you do now? 22 A. I'm a sales representative. 23 Q. How many children do you have? 24 A. I have three. 25 Q. What is the name of your oldest child?",
      "position": "main"
    },
    {
      "type": "printed",
      "content": "SOUTHERN DISTRICT REPORTERS, P.C. (212) 805-0300 DOJ-OGR-00013810",
      "position": "footer"
    }
  ],
  "entities": {
    "people": [
      "Janice Swain",
      "Ms. Pomerantz"
    ],
    "organizations": [
      "SOUTHERN DISTRICT REPORTERS, P.C."
    ],
    "locations": [],
    "dates": [
      "08/10/22"
    ],
    "reference_numbers": [
      "1:20-cr-00330-PAE",
      "759",
      "DOJ-OGR-00013810"
    ]
  },
  "additional_notes": "The document appears to be a court transcript with a clear and legible format. There are no visible redactions or damage."
}