{
  "document_metadata": {
    "page_number": "172",
    "document_number": "767",
    "date": "08/10/22",
    "document_type": "Court Document",
    "has_handwriting": false,
    "has_stamps": false
  },
  "full_text": "Case 1:20-cr-00330-PAE Document 767 Filed 08/10/22 Page 172 of 257 3006 LCKCmax7 Rebuttal - Ms. Comey she was 16. So the best argument the defense has is she was 16, not 14, when the abuse happened. That is not a defense. It is still illegal. It is not a defense to say, oh, no, no, no, she was 16, not 14, when I touched her breasts. It's still a crime. Now Carolyn. Carolyn vividly remembers the first time she met the defendant. You saw her correct defense counsel on cross examination. Remember, he tried to skip over the part of meeting her and she said no, no, you forgot about when I met Maxwell. That first day was a scarring memory for Carolyn, and she remembers Maxwell as a fixture in her experiences at the Palm Beach house, like the stuffing at Thanksgiving, there every time. The defense is very focused on the peripheral details that got mixed up for Carolyn between her earlier statements and her trial testimony more than a decade later. And they harped a lot on her memory of seeing a photo of Maxwell pregnant in the massage room. Ladies and gentlemen, I'd encourage you to take a look at Government Exhibits 286 and 287. Those show pictures that were on the wall in the closet where the massage table was kept in the Palm Beach master bathroom. You look at those and you'll see that there appear to be three different pictures that appear to show a pregnant woman in a two-piece swimsuit. So what if Carolyn mistakenly thought that one of those showed SOUTHERN DISTRICT REPORTERS, P.C. (212) 805-0300 DOJ-OGR-00014572",
  "text_blocks": [
    {
      "type": "printed",
      "content": "Case 1:20-cr-00330-PAE Document 767 Filed 08/10/22 Page 172 of 257 3006 LCKCmax7 Rebuttal - Ms. Comey",
      "position": "header"
    },
    {
      "type": "printed",
      "content": "she was 16. So the best argument the defense has is she was 16, not 14, when the abuse happened. That is not a defense. It is still illegal. It is not a defense to say, oh, no, no, no, she was 16, not 14, when I touched her breasts. It's still a crime. Now Carolyn. Carolyn vividly remembers the first time she met the defendant. You saw her correct defense counsel on cross examination. Remember, he tried to skip over the part of meeting her and she said no, no, you forgot about when I met Maxwell. That first day was a scarring memory for Carolyn, and she remembers Maxwell as a fixture in her experiences at the Palm Beach house, like the stuffing at Thanksgiving, there every time. The defense is very focused on the peripheral details that got mixed up for Carolyn between her earlier statements and her trial testimony more than a decade later. And they harped a lot on her memory of seeing a photo of Maxwell pregnant in the massage room. Ladies and gentlemen, I'd encourage you to take a look at Government Exhibits 286 and 287. Those show pictures that were on the wall in the closet where the massage table was kept in the Palm Beach master bathroom. You look at those and you'll see that there appear to be three different pictures that appear to show a pregnant woman in a two-piece swimsuit. So what if Carolyn mistakenly thought that one of those showed",
      "position": "main"
    },
    {
      "type": "printed",
      "content": "SOUTHERN DISTRICT REPORTERS, P.C. (212) 805-0300",
      "position": "footer"
    },
    {
      "type": "printed",
      "content": "DOJ-OGR-00014572",
      "position": "footer"
    }
  ],
  "entities": {
    "people": [
      "Carolyn",
      "Maxwell",
      "Ms. Comey"
    ],
    "organizations": [
      "SOUTHERN DISTRICT REPORTERS, P.C."
    ],
    "locations": [
      "Palm Beach"
    ],
    "dates": [
      "08/10/22"
    ],
    "reference_numbers": [
      "1:20-cr-00330-PAE",
      "767",
      "286",
      "287",
      "DOJ-OGR-00014572"
    ]
  },
  "additional_notes": "The document appears to be a court transcript with a clear and legible text. There are no visible redactions or damage."
}