{
  "document_metadata": {
    "page_number": "55",
    "document_number": "751",
    "date": "08/10/22",
    "document_type": "court transcript",
    "has_handwriting": false,
    "has_stamps": false
  },
  "full_text": "Case 1:20-cr-00330-PAE Document 751 Filed 08/10/22 Page 55 of 261 1195\nLC6VMAX2 Kate - direct\n1 Oxford?\n2 A. No.\n3 Q. During your late teens and early twenties, what did you do for a living?\n4 A. In my late teens and early twenties I -- I became a musician and a model.\n5 Q. You testified earlier that Epstein initiated sexual activity with you when you were 17 years old. Approximately when did he stop initiating sexual activity with you?\n6 A. Approximately in my early thirties.\n7 Q. When you spent time with Epstein in that time period, about how often did he initiate sexual activity with you?\n8 A. Sorry. Can you repeat that?\n9 Q. When you spent time with Epstein, how often did he initiate sexual activity with you?\n10 A. Every time.\n11 Q. When Epstein initiated sexual activity with you, was that always in the context of massage?\n12 A. No.\n13 Q. When you spent time with Epstein, did you provide him with sexualized massages?\n14 A. Yes.\n15 Q. In what locations did these sexualized massages with Epstein take place?\n16 A. In London, in Palm Beach, and on his island.\n17 SOUTHERN DISTRICT REPORTERS, P.C. (212) 805-0300\nDOJ-OGR-00012806",
  "text_blocks": [
    {
      "type": "printed",
      "content": "Case 1:20-cr-00330-PAE Document 751 Filed 08/10/22 Page 55 of 261 1195",
      "position": "header"
    },
    {
      "type": "printed",
      "content": "LC6VMAX2 Kate - direct",
      "position": "header"
    },
    {
      "type": "printed",
      "content": "1 Oxford?\n2 A. No.\n3 Q. During your late teens and early twenties, what did you do for a living?\n4 A. In my late teens and early twenties I -- I became a musician and a model.\n5 Q. You testified earlier that Epstein initiated sexual activity with you when you were 17 years old. Approximately when did he stop initiating sexual activity with you?\n6 A. Approximately in my early thirties.\n7 Q. When you spent time with Epstein in that time period, about how often did he initiate sexual activity with you?\n8 A. Sorry. Can you repeat that?\n9 Q. When you spent time with Epstein, how often did he initiate sexual activity with you?\n10 A. Every time.\n11 Q. When Epstein initiated sexual activity with you, was that always in the context of massage?\n12 A. No.\n13 Q. When you spent time with Epstein, did you provide him with sexualized massages?\n14 A. Yes.\n15 Q. In what locations did these sexualized massages with Epstein take place?\n16 A. In London, in Palm Beach, and on his island.",
      "position": "main"
    },
    {
      "type": "printed",
      "content": "SOUTHERN DISTRICT REPORTERS, P.C. (212) 805-0300",
      "position": "footer"
    },
    {
      "type": "printed",
      "content": "DOJ-OGR-00012806",
      "position": "footer"
    }
  ],
  "entities": {
    "people": [
      "Kate",
      "Epstein"
    ],
    "organizations": [
      "SOUTHERN DISTRICT REPORTERS, P.C."
    ],
    "locations": [
      "Oxford",
      "London",
      "Palm Beach"
    ],
    "dates": [
      "08/10/22"
    ],
    "reference_numbers": [
      "1:20-cr-00330-PAE",
      "751",
      "DOJ-OGR-00012806"
    ]
  },
  "additional_notes": "The document appears to be a court transcript with a clear and legible format. The content discusses a witness's testimony regarding their interactions with Jeffrey Epstein. There are no visible redactions or damage to the document."
}