{
  "document_metadata": {
    "page_number": "104",
    "document_number": "745",
    "date": "08/10/22",
    "document_type": "court transcript",
    "has_handwriting": false,
    "has_stamps": false
  },
  "full_text": "Case 1:20-cr-00330-PAE Document 745 Filed 08/10/22 Page 104 of 264 LC1VMAX3 Jane - cross 1 recollection, she said it did not. Now I'm asking her if she made the statement, and we haven't heard her answer yet. 3 THE COURT: So the question is did you make the statement? 4 5 MS. MENNINGER: Yes. 6 THE COURT: Okay. You may answer that. 7 A. No, I don't recall making these statements. 8 Q. Then you were asked the same question by the government in the same interview a third time; correct? 9 10 A. I don't know. 11 Q. I'm going to ask you to take a look at page 11, the top paragraph, the first sentence. Does that refresh your recollection about you being asked a third time in the same interview about abuse occurring in New Mexico? 12 13 14 15 A. No, it does not. 16 Q. Isn't it true what you told the government a third time was that you were asked about the New Mexico trips you took and if you recalled any specific abuse that occurred there, to which you answered you did not remember; correct? 17 18 19 20 MS. MOE: Objection. 21 THE COURT: Sustained. 22 Q. It didn't refresh your recollection -- 23 THE COURT: You said isn't it true that you told the government a third time that you were asked about the New Mexico trips. I think you lost the thread. 24 25 SOUTHERN DISTRICT REPORTERS, P.C. (212) 805-0300 DOJ-OGR-00012124",
  "text_blocks": [
    {
      "type": "printed",
      "content": "Case 1:20-cr-00330-PAE Document 745 Filed 08/10/22 Page 104 of 264",
      "position": "header"
    },
    {
      "type": "printed",
      "content": "LC1VMAX3 Jane - cross",
      "position": "header"
    },
    {
      "type": "printed",
      "content": "1 recollection, she said it did not. Now I'm asking her if she made the statement, and we haven't heard her answer yet. 3 THE COURT: So the question is did you make the statement? 4 5 MS. MENNINGER: Yes. 6 THE COURT: Okay. You may answer that. 7 A. No, I don't recall making these statements. 8 Q. Then you were asked the same question by the government in the same interview a third time; correct? 9 10 A. I don't know. 11 Q. I'm going to ask you to take a look at page 11, the top paragraph, the first sentence. Does that refresh your recollection about you being asked a third time in the same interview about abuse occurring in New Mexico? 12 13 14 15 A. No, it does not. 16 Q. Isn't it true what you told the government a third time was that you were asked about the New Mexico trips you took and if you recalled any specific abuse that occurred there, to which you answered you did not remember; correct? 17 18 19 20 MS. MOE: Objection. 21 THE COURT: Sustained. 22 Q. It didn't refresh your recollection -- 23 THE COURT: You said isn't it true that you told the government a third time that you were asked about the New Mexico trips. I think you lost the thread. 24 25",
      "position": "main"
    },
    {
      "type": "printed",
      "content": "SOUTHERN DISTRICT REPORTERS, P.C. (212) 805-0300",
      "position": "footer"
    },
    {
      "type": "printed",
      "content": "DOJ-OGR-00012124",
      "position": "footer"
    }
  ],
  "entities": {
    "people": [
      "MS. MENNINGER",
      "MS. MOE"
    ],
    "organizations": [
      "SOUTHERN DISTRICT REPORTERS, P.C.",
      "THE COURT",
      "THE GOVERNMENT"
    ],
    "locations": [
      "New Mexico"
    ],
    "dates": [
      "08/10/22"
    ],
    "reference_numbers": [
      "1:20-cr-00330-PAE",
      "745",
      "DOJ-OGR-00012124"
    ]
  },
  "additional_notes": "The document appears to be a court transcript with a clear and legible format. There are no visible redactions or damage."
}