{
  "document_metadata": {
    "page_number": "187",
    "document_number": "763",
    "date": "08/10/22",
    "document_type": "court transcript",
    "has_handwriting": false,
    "has_stamps": false
  },
  "full_text": "Case 1:20-cr-00330-PAE Document 763 Filed 08/10/22 Page 187 of 197 2728 LCHCmax7\n\n1 MS. COMEY: No objection, your Honor.\n2 THE COURT: A-1 is admitted.\n3 (Defendant's Exhibit A-1 received in evidence)\n4 MR. EVERDELL: Your Honor, I now have A2.\n5 THE COURT: And you could you skip the preface and\n6 say, between the parties.\n7 MR. EVERDELL: Sure, your Honor.\n8 THE COURT: Thank you.\n9 MR. EVERDELL: It is hereby stipulated and agreed by\n10 and among the parties that, if recalled as a witness, Dominique\n11 Hyppolite would testify as follows: The Palm Beach County\n12 school maintains school records in the ordinary course of\n13 business.\n14 The document marked Defense Exhibits DH1, DH2, and DH3\n15 are each a true and accurate copy of Palm Beach County school\n16 records for Virginia Robertson.\n17 The document marked Defendant's Exhibit J2 is a true\n18 and accurate copy of Palm Beach County school records for the\n19 witness identified as Jane.\n20 It is further stipulated and agreed that Defense\n21 Exhibits DH1, DH2, DH3, and J2, and this stipulation marked as\n22 Defense Exhibit DH4, may be received in evidence at trial.\n23 And it's dated today's date, signed by the parties.\n24 MS. COMEY: No objection. The government would\n25 request that Exhibit J2 be accepted under seal consistent with\n\nSOUTHERN DISTRICT REPORTERS, P.C.\n(212) 805-0300\n\nDOJ-OGR-00014293",
  "text_blocks": [
    {
      "type": "printed",
      "content": "Case 1:20-cr-00330-PAE Document 763 Filed 08/10/22 Page 187 of 197 2728 LCHCmax7",
      "position": "header"
    },
    {
      "type": "printed",
      "content": "1 MS. COMEY: No objection, your Honor.\n2 THE COURT: A-1 is admitted.\n3 (Defendant's Exhibit A-1 received in evidence)\n4 MR. EVERDELL: Your Honor, I now have A2.\n5 THE COURT: And you could you skip the preface and\n6 say, between the parties.\n7 MR. EVERDELL: Sure, your Honor.\n8 THE COURT: Thank you.\n9 MR. EVERDELL: It is hereby stipulated and agreed by\n10 and among the parties that, if recalled as a witness, Dominique\n11 Hyppolite would testify as follows: The Palm Beach County\n12 school maintains school records in the ordinary course of\n13 business.\n14 The document marked Defense Exhibits DH1, DH2, and DH3\n15 are each a true and accurate copy of Palm Beach County school\n16 records for Virginia Robertson.\n17 The document marked Defendant's Exhibit J2 is a true\n18 and accurate copy of Palm Beach County school records for the\n19 witness identified as Jane.\n20 It is further stipulated and agreed that Defense\n21 Exhibits DH1, DH2, DH3, and J2, and this stipulation marked as\n22 Defense Exhibit DH4, may be received in evidence at trial.\n23 And it's dated today's date, signed by the parties.\n24 MS. COMEY: No objection. The government would\n25 request that Exhibit J2 be accepted under seal consistent with",
      "position": "main content"
    },
    {
      "type": "printed",
      "content": "SOUTHERN DISTRICT REPORTERS, P.C.\n(212) 805-0300",
      "position": "footer"
    },
    {
      "type": "printed",
      "content": "DOJ-OGR-00014293",
      "position": "footer"
    }
  ],
  "entities": {
    "people": [
      "MS. COMEY",
      "MR. EVERDELL",
      "Dominique Hyppolite",
      "Virginia Robertson",
      "Jane"
    ],
    "organizations": [
      "Palm Beach County school",
      "SOUTHERN DISTRICT REPORTERS, P.C."
    ],
    "locations": [
      "Palm Beach County"
    ],
    "dates": [
      "08/10/22",
      "today's date"
    ],
    "reference_numbers": [
      "1:20-cr-00330-PAE",
      "763",
      "DOJ-OGR-00014293"
    ]
  },
  "additional_notes": "The document appears to be a court transcript with a clear and legible format. There are no visible redactions or damage."
}