{
  "document_metadata": {
    "page_number": "116",
    "document_number": "751",
    "date": "08/10/22",
    "document_type": "court transcript",
    "has_handwriting": false,
    "has_stamps": false
  },
  "full_text": "Case 1:20-cr-00330-PAE Document 751 Filed 08/10/22 Page 116 of 261 1277\nLC6Cmax3 Kate - cross\n1 exhibit that I'd like to show the government.\n2 THE COURT: Can you give it a trial mark for\n3 identification, please.\n4 MS. STERNHEIM: It would be Defendant's K9, please.\n5 May I give one to the witness, Kate, please?\n6 THE COURT: You may.\n7 BY MS. STERNHEIM:\n8 Q. Kate, I'm going to ask you to take a look at the exhibit I gave you, which we are marking as K9. Do you recognize that?\n9\n10 A. No.\n11 Q. Do you recognize your true name on it?\n12 A. Sorry. On which page?\n13 Q. On page 2, which is in the flip side of page 1. I would direct you to the left-hand column.\n14\n15 A. I've got, I think -- I've got pages 1 of 6, 3 of 6, and 5 of 6.\n16\n17 Q. If you turn 1 of 6 over?\n18 A. The other side. Thank you.\n19 Q. Do you see it now?\n20 A. Yes.\n21 Q. I'm going to ask you to look at the left-hand column.\n22 A. Yes.\n23 Q. Near what may be 2A?\n24 A. Yes. Yes.\n25 Q. Is that your true name?\nSOUTHERN DISTRICT REPORTERS, P.C. (212) 805-0300\nDOJ-OGR-00012867",
  "text_blocks": [
    {
      "type": "printed",
      "content": "Case 1:20-cr-00330-PAE Document 751 Filed 08/10/22 Page 116 of 261 1277",
      "position": "header"
    },
    {
      "type": "printed",
      "content": "LC6Cmax3 Kate - cross",
      "position": "header"
    },
    {
      "type": "printed",
      "content": "1 exhibit that I'd like to show the government.\n2 THE COURT: Can you give it a trial mark for\n3 identification, please.\n4 MS. STERNHEIM: It would be Defendant's K9, please.\n5 May I give one to the witness, Kate, please?\n6 THE COURT: You may.\n7 BY MS. STERNHEIM:\n8 Q. Kate, I'm going to ask you to take a look at the exhibit I gave you, which we are marking as K9. Do you recognize that?\n9\n10 A. No.\n11 Q. Do you recognize your true name on it?\n12 A. Sorry. On which page?\n13 Q. On page 2, which is in the flip side of page 1. I would direct you to the left-hand column.\n14\n15 A. I've got, I think -- I've got pages 1 of 6, 3 of 6, and 5 of 6.\n16\n17 Q. If you turn 1 of 6 over?\n18 A. The other side. Thank you.\n19 Q. Do you see it now?\n20 A. Yes.\n21 Q. I'm going to ask you to look at the left-hand column.\n22 A. Yes.\n23 Q. Near what may be 2A?\n24 A. Yes. Yes.\n25 Q. Is that your true name?",
      "position": "main"
    },
    {
      "type": "printed",
      "content": "SOUTHERN DISTRICT REPORTERS, P.C. (212) 805-0300",
      "position": "footer"
    },
    {
      "type": "printed",
      "content": "DOJ-OGR-00012867",
      "position": "footer"
    }
  ],
  "entities": {
    "people": [
      "MS. STERNHEIM",
      "Kate"
    ],
    "organizations": [
      "SOUTHERN DISTRICT REPORTERS, P.C."
    ],
    "locations": [],
    "dates": [
      "08/10/22"
    ],
    "reference_numbers": [
      "1:20-cr-00330-PAE",
      "751",
      "DOJ-OGR-00012867"
    ]
  },
  "additional_notes": "The document appears to be a court transcript with a clear and legible format. There are no visible redactions or damage."
}