{
  "document_metadata": {
    "page_number": "2",
    "document_number": "747",
    "date": "08/10/22",
    "document_type": "court transcript",
    "has_handwriting": false,
    "has_stamps": false
  },
  "full_text": "Case 1:20-cr-00330-PAE Document 747 Filed 08/10/22 Page 2 of 228 678 LC2Qmax1\n\n(In open court; jury not present)\nTHE COURT: Good morning. Matters to take up, counsel?\nMR. ROHRBACH: Your Honor, from the government, we just wanted to make sure the Court and defense counsel saw our letter of last night about Government Exhibits 52 and 606.\nTHE COURT: I did see it.\nMR. PAGLIUCA: Yes, your Honor. I received it roughly 1:00 a.m., give or take, something like that.\nTHE COURT: So you were just waking up.\nMR. PAGLIUCA: I had never gone to sleep.\nTHE COURT: I mean, I've had prior briefing. This is additional briefing. My view remains. We will see what comes in on the testimony, and then I'll make a ruling.\nI guess one question for defense is whether they do intend to -- and maybe you don't know yet, but to seek to voir dire before I rule on admission?\nMR. PAGLIUCA: Yes, I think so, your Honor. Well, I'm assuming that we're changing the witness that we're trying to introduce this through, which will happen later today, is my understanding of the briefing. So I don't think it changes the landscape of needing to do some voir dire on the exhibit prior to the Court's ruling.\nTHE COURT: Okay.\nMR. PAGLIUCA: I guess just -- I think -- there's an SOUTHERN DISTRICT REPORTERS, P.C. (212) 805-0300 DOJ-OGR-00012287",
  "text_blocks": [
    {
      "type": "printed",
      "content": "Case 1:20-cr-00330-PAE Document 747 Filed 08/10/22 Page 2 of 228 678 LC2Qmax1",
      "position": "header"
    },
    {
      "type": "printed",
      "content": "(In open court; jury not present)\nTHE COURT: Good morning. Matters to take up, counsel?\nMR. ROHRBACH: Your Honor, from the government, we just wanted to make sure the Court and defense counsel saw our letter of last night about Government Exhibits 52 and 606.\nTHE COURT: I did see it.\nMR. PAGLIUCA: Yes, your Honor. I received it roughly 1:00 a.m., give or take, something like that.\nTHE COURT: So you were just waking up.\nMR. PAGLIUCA: I had never gone to sleep.\nTHE COURT: I mean, I've had prior briefing. This is additional briefing. My view remains. We will see what comes in on the testimony, and then I'll make a ruling.\nI guess one question for defense is whether they do intend to -- and maybe you don't know yet, but to seek to voir dire before I rule on admission?\nMR. PAGLIUCA: Yes, I think so, your Honor. Well, I'm assuming that we're changing the witness that we're trying to introduce this through, which will happen later today, is my understanding of the briefing. So I don't think it changes the landscape of needing to do some voir dire on the exhibit prior to the Court's ruling.\nTHE COURT: Okay.\nMR. PAGLIUCA: I guess just -- I think -- there's an",
      "position": "main content"
    },
    {
      "type": "printed",
      "content": "SOUTHERN DISTRICT REPORTERS, P.C. (212) 805-0300",
      "position": "footer"
    },
    {
      "type": "printed",
      "content": "DOJ-OGR-00012287",
      "position": "footer"
    }
  ],
  "entities": {
    "people": [
      "MR. ROHRBACH",
      "MR. PAGLIUCA"
    ],
    "organizations": [
      "SOUTHERN DISTRICT REPORTERS, P.C."
    ],
    "locations": [],
    "dates": [
      "08/10/22"
    ],
    "reference_numbers": [
      "1:20-cr-00330-PAE",
      "Document 747",
      "Government Exhibits 52",
      "Government Exhibits 606",
      "DOJ-OGR-00012287"
    ]
  },
  "additional_notes": "The document appears to be a court transcript with a clear and readable format. There are no visible redactions or damage."
}