{
  "document_metadata": {
    "page_number": "208",
    "document_number": "743",
    "date": "08/10/22",
    "document_type": "court transcript",
    "has_handwriting": false,
    "has_stamps": false
  },
  "full_text": "Case 1:20-cr-00330-PAE Document 743 Filed 08/10/22 Page 208 of 247 336 LBUCmax5 Jane - direct talking about when you were 14 and 15 and 16, did you ever talk with your mother about Jeffrey Epstein and Ghislaine Maxwell? A. Yes. Q. What kinds of things would she say to you about Epstein and Maxwell during that time period. A. What would she say? I'm sorry. I'm not really understanding your question. Q. Of course. When would you talk to your mother during those years about Maxwell and Epstein, what, if anything, would she say to you about her impressions of them? A. My mother seemed very impressed and enamored with the sort of the wealth, the affluence. She thought they seemed very generous and they must think I'm special and that I should be grateful for the attention that I received. Q. During this time period, did you ever tell your mother about the sexual abuse that you were experiencing when were you at Epstein's house? A. No. Q. Why didn't you tell your mother during those years? A. Because I felt very ashamed, I felt very disgusted, I was confused, I didn't know if it was my fault, and my mother and I did not have that kind of a relationship. We didn't talk about our feelings. We weren't allowed to. I was raised in a household where you were sort of spoken to, and you don't speak unless you're spoken to, and I would be afraid that I would be SOUTHERN DISTRICT REPORTERS, P.C. (212) 805-0300 DOJ-OGR-00011980",
  "text_blocks": [
    {
      "type": "printed",
      "content": "Case 1:20-cr-00330-PAE Document 743 Filed 08/10/22 Page 208 of 247 336",
      "position": "header"
    },
    {
      "type": "printed",
      "content": "LBUCmax5 Jane - direct",
      "position": "header"
    },
    {
      "type": "printed",
      "content": "talking about when you were 14 and 15 and 16, did you ever talk with your mother about Jeffrey Epstein and Ghislaine Maxwell? A. Yes. Q. What kinds of things would she say to you about Epstein and Maxwell during that time period. A. What would she say? I'm sorry. I'm not really understanding your question. Q. Of course. When would you talk to your mother during those years about Maxwell and Epstein, what, if anything, would she say to you about her impressions of them? A. My mother seemed very impressed and enamored with the sort of the wealth, the affluence. She thought they seemed very generous and they must think I'm special and that I should be grateful for the attention that I received. Q. During this time period, did you ever tell your mother about the sexual abuse that you were experiencing when were you at Epstein's house? A. No. Q. Why didn't you tell your mother during those years? A. Because I felt very ashamed, I felt very disgusted, I was confused, I didn't know if it was my fault, and my mother and I did not have that kind of a relationship. We didn't talk about our feelings. We weren't allowed to. I was raised in a household where you were sort of spoken to, and you don't speak unless you're spoken to, and I would be afraid that I would be",
      "position": "main"
    },
    {
      "type": "printed",
      "content": "SOUTHERN DISTRICT REPORTERS, P.C. (212) 805-0300",
      "position": "footer"
    },
    {
      "type": "printed",
      "content": "DOJ-OGR-00011980",
      "position": "footer"
    }
  ],
  "entities": {
    "people": [
      "Jeffrey Epstein",
      "Ghislaine Maxwell"
    ],
    "organizations": [
      "SOUTHERN DISTRICT REPORTERS, P.C."
    ],
    "locations": [],
    "dates": [
      "08/10/22"
    ],
    "reference_numbers": [
      "1:20-cr-00330-PAE",
      "Document 743",
      "DOJ-OGR-00011980"
    ]
  },
  "additional_notes": "The document appears to be a court transcript with a clear and legible format. There are no visible redactions or damage."
}