{
  "document_metadata": {
    "page_number": "242",
    "document_number": "751",
    "date": "08/10/22",
    "document_type": "court transcript",
    "has_handwriting": false,
    "has_stamps": false
  },
  "full_text": "Case 1:20-cr-00330-PAE Document 751 Filed 08/10/22 Page 242 of 261 1403\nLC6Cmax7 Meder - direct\n1 corresponded it with the correct evidence item in the 1B number, as well as confirming the name of the CD.\n2 Q. And when we say the name of the CD, is that a label that was physically affixed to the CD?\n3 A. Yes, it was written on the disc.\n4 Q. Will this exhibit assist you in your testimony here today?\n5 A. Yes.\n6 MS. COMEY: Your Honor, I would ask permission for the witness to refer to this exhibit as an aid during her testimony.\n7 MS. MENNINGER: Your Honor, no objection to that, although there is certainly hearsay contained in the far right column, so I assume that won't be part of the testimony.\n8 MS. COMEY: Your Honor, I think we can take each objection as it comes.\n9 THE COURT: You're not moving for the admission?\n10 MS. COMEY: That's correct, your Honor.\n11 THE COURT: For now, we'll allow it to be an aid for memory and mindful of potential objections.\n12 MS. COMEY: Thank you, your Honor.\n13 Ms. Drescher, would you please pull up what's been marked for identification as Government Exhibit 304.\n14 BY MS. COMEY:\n15 Q. Do you recognize this?\n16 A. Yes.\n17 SOUTHERN DISTRICT REPORTERS, P.C. (212) 805-0300\n18 DOJ-OGR-00012993",
  "text_blocks": [
    {
      "type": "printed",
      "content": "Case 1:20-cr-00330-PAE Document 751 Filed 08/10/22 Page 242 of 261 1403",
      "position": "header"
    },
    {
      "type": "printed",
      "content": "LC6Cmax7 Meder - direct",
      "position": "header"
    },
    {
      "type": "printed",
      "content": "1 corresponded it with the correct evidence item in the 1B number, as well as confirming the name of the CD.\n2 Q. And when we say the name of the CD, is that a label that was physically affixed to the CD?\n3 A. Yes, it was written on the disc.\n4 Q. Will this exhibit assist you in your testimony here today?\n5 A. Yes.\n6 MS. COMEY: Your Honor, I would ask permission for the witness to refer to this exhibit as an aid during her testimony.\n7 MS. MENNINGER: Your Honor, no objection to that, although there is certainly hearsay contained in the far right column, so I assume that won't be part of the testimony.\n8 MS. COMEY: Your Honor, I think we can take each objection as it comes.\n9 THE COURT: You're not moving for the admission?\n10 MS. COMEY: That's correct, your Honor.\n11 THE COURT: For now, we'll allow it to be an aid for memory and mindful of potential objections.\n12 MS. COMEY: Thank you, your Honor.\n13 Ms. Drescher, would you please pull up what's been marked for identification as Government Exhibit 304.\n14 BY MS. COMEY:\n15 Q. Do you recognize this?\n16 A. Yes.",
      "position": "main content"
    },
    {
      "type": "printed",
      "content": "SOUTHERN DISTRICT REPORTERS, P.C. (212) 805-0300",
      "position": "footer"
    },
    {
      "type": "printed",
      "content": "DOJ-OGR-00012993",
      "position": "footer"
    }
  ],
  "entities": {
    "people": [
      "MS. COMEY",
      "MS. MENNINGER",
      "Ms. Drescher"
    ],
    "organizations": [
      "SOUTHERN DISTRICT REPORTERS, P.C."
    ],
    "locations": [],
    "dates": [
      "08/10/22"
    ],
    "reference_numbers": [
      "1:20-cr-00330-PAE",
      "751",
      "304",
      "DOJ-OGR-00012993"
    ]
  },
  "additional_notes": "The document appears to be a court transcript with a clear and legible format. There are no visible redactions or damage."
}