{
  "document_metadata": {
    "page_number": "26",
    "document_number": "749",
    "date": "08/10/22",
    "document_type": "court transcript",
    "has_handwriting": false,
    "has_stamps": false
  },
  "full_text": "Case 1:20-cr-00330-PAE Document 749 Filed 08/10/22 Page 26 of 236 930 LBUCmax1\na bag containing the costumes themselves and would anticipate otherwise asking Special Agent Maguire to publish them to the jury so that they can see both what they look like and also how small they are.\nSo I'm just thinking about the mechanics of this.\nOne option would be to offer the photographs and the bag without eliciting out loud what they are and just confirming without describing them that these are items that were recovered from the residence and where they were recovered without publishing the photographs or opening the bag.\nWould that be the Court's preference? I'd be happy to do it another way.\nTHE COURT: Mr. Everdell.\nMR. EVERDELL: Your Honor, I do have an issue with these being displayed or shown in any way, shape, or form until witness 3 testifies. I actually have some concerns and I hope they're not unfounded. They pushed her testimony off, she was originally supposed to testify today, I don't know if it maybe had to do with a travel issue or not, but I don't know is she going to testify or not, when is she going to testify, if she doesn't testify for whatever reason, then these items and the photographs of those items should not be seen by the jury at all. And so that is my concern. I don't want this to be in their heads, in their minds at all unless we have a witness on the stand who can connect their relevance to this case, and\nSOUTHERN DISTRICT REPORTERS, P.C. (212) 805-0300\nDOJ-OGR-00012540",
  "text_blocks": [
    {
      "type": "printed",
      "content": "Case 1:20-cr-00330-PAE Document 749 Filed 08/10/22 Page 26 of 236 930 LBUCmax1",
      "position": "header"
    },
    {
      "type": "printed",
      "content": "a bag containing the costumes themselves and would anticipate otherwise asking Special Agent Maguire to publish them to the jury so that they can see both what they look like and also how small they are.\nSo I'm just thinking about the mechanics of this.\nOne option would be to offer the photographs and the bag without eliciting out loud what they are and just confirming without describing them that these are items that were recovered from the residence and where they were recovered without publishing the photographs or opening the bag.\nWould that be the Court's preference? I'd be happy to do it another way.\nTHE COURT: Mr. Everdell.\nMR. EVERDELL: Your Honor, I do have an issue with these being displayed or shown in any way, shape, or form until witness 3 testifies. I actually have some concerns and I hope they're not unfounded. They pushed her testimony off, she was originally supposed to testify today, I don't know if it maybe had to do with a travel issue or not, but I don't know is she going to testify or not, when is she going to testify, if she doesn't testify for whatever reason, then these items and the photographs of those items should not be seen by the jury at all. And so that is my concern. I don't want this to be in their heads, in their minds at all unless we have a witness on the stand who can connect their relevance to this case, and",
      "position": "main content"
    },
    {
      "type": "printed",
      "content": "SOUTHERN DISTRICT REPORTERS, P.C. (212) 805-0300",
      "position": "footer"
    },
    {
      "type": "printed",
      "content": "DOJ-OGR-00012540",
      "position": "footer"
    }
  ],
  "entities": {
    "people": [
      "Maguire",
      "Everdell"
    ],
    "organizations": [
      "SOUTHERN DISTRICT REPORTERS, P.C."
    ],
    "locations": [],
    "dates": [
      "08/10/22"
    ],
    "reference_numbers": [
      "1:20-cr-00330-PAE",
      "749",
      "DOJ-OGR-00012540"
    ]
  },
  "additional_notes": "The document appears to be a court transcript with a clear and readable format. There are no visible redactions or damage."
}