{
  "document_metadata": {
    "page_number": "154",
    "document_number": "747",
    "date": "08/10/22",
    "document_type": "court transcript",
    "has_handwriting": false,
    "has_stamps": false
  },
  "full_text": "Case 1:20-cr-00330-PAE Document 747 Filed 08/10/22 Page 154 of 228 830 LC2Qmax5 - corrected Alessi - Direct the center portion of this page, please. This says Ms. Maxwell's desk. What is that referring to? A. The DSL computer -- Q. What do you understand Ms. Maxwell's desk to refer to? A. The desk that she use all the time down on the first floor. Q. What room was that in? A. That was in the garden room. Q. And the fourth bullet point, would you please read that for us? A. JE and GM telephone directories placed to the right of the telephone. Q. Is that the same telephone directories that we were talking about earlier? A. Yes. Q. Let's turn now, please, to page 24. I want to look at the section titled stationery. Would you read this aloud for us, please? A. The whole list? Q. Yes, please. A. Three sizes of Jeffrey Epstein notepads. Two sizes of Ghislaine Maxwell and Lady Ghislaine notepads. Letterhead, stationery and envelopes. One pack from each of Mr. Epstein's residences and businesses. Mr. Epstein's personal stationery (writing paper, notepads, envelopes, compliment slips). SOUTHERN DISTRICT REPORTERS, P.C. (212) 805-0300 DOJ-OGR-00012439",
  "text_blocks": [
    {
      "type": "printed",
      "content": "Case 1:20-cr-00330-PAE Document 747 Filed 08/10/22 Page 154 of 228 830",
      "position": "header"
    },
    {
      "type": "printed",
      "content": "LC2Qmax5 - corrected Alessi - Direct",
      "position": "header"
    },
    {
      "type": "printed",
      "content": "the center portion of this page, please. This says Ms. Maxwell's desk. What is that referring to? A. The DSL computer -- Q. What do you understand Ms. Maxwell's desk to refer to? A. The desk that she use all the time down on the first floor. Q. What room was that in? A. That was in the garden room. Q. And the fourth bullet point, would you please read that for us? A. JE and GM telephone directories placed to the right of the telephone. Q. Is that the same telephone directories that we were talking about earlier? A. Yes. Q. Let's turn now, please, to page 24. I want to look at the section titled stationery. Would you read this aloud for us, please? A. The whole list? Q. Yes, please. A. Three sizes of Jeffrey Epstein notepads. Two sizes of Ghislaine Maxwell and Lady Ghislaine notepads. Letterhead, stationery and envelopes. One pack from each of Mr. Epstein's residences and businesses. Mr. Epstein's personal stationery (writing paper, notepads, envelopes, compliment slips).",
      "position": "main"
    },
    {
      "type": "printed",
      "content": "SOUTHERN DISTRICT REPORTERS, P.C. (212) 805-0300",
      "position": "footer"
    },
    {
      "type": "printed",
      "content": "DOJ-OGR-00012439",
      "position": "footer"
    }
  ],
  "entities": {
    "people": [
      "Ms. Maxwell",
      "Jeffrey Epstein",
      "Ghislaine Maxwell",
      "Lady Ghislaine",
      "Mr. Epstein",
      "Alessi"
    ],
    "organizations": [
      "SOUTHERN DISTRICT REPORTERS, P.C."
    ],
    "locations": [
      "garden room"
    ],
    "dates": [
      "08/10/22"
    ],
    "reference_numbers": [
      "1:20-cr-00330-PAE",
      "747",
      "154",
      "228",
      "830",
      "24",
      "DOJ-OGR-00012439",
      "(212) 805-0300"
    ]
  },
  "additional_notes": "This is a court transcript document. The text is a Q&A session between a lawyer and a witness. The conversation is about Ms. Maxwell's desk and some stationery items."
}