{
  "document_metadata": {
    "page_number": "21",
    "document_number": "765",
    "date": "08/10/22",
    "document_type": "court transcript",
    "has_handwriting": false,
    "has_stamps": false
  },
  "full_text": "Case 1:20-cr-00330-PAE Document 765 Filed 08/10/22 Page 21 of 95 2759 LCI1MAX1\nthe conspiracy counts come later, I think there is an attempt here to generalize the wording of the elements because it's going to be applied later to the conspiracy counts, right? But this is the substantive count, and if we look at the line 5, it says first that the defendant knowingly persuaded or induced or enticed or coerced an individual to travel in interstate commerce. The individual in the substantive count is Jane. The defense request is for it to say not \"an individual,\" replace that with \"Jane to travel in interstate commerce from Florida to New York, as alleged in the indictment.\"\nTHE COURT: Mr. Rohrbach.\nMR. ROHRBACH: So, your Honor, I don't think the jury will be confused. Both in the summary and later on in this section, it says this relates to Jane. If the defense would like it to say it relates solely to Jane here as in the summary, that would be fine, but the Court is just laying out the elements of the offense and there's no need to put all of the factual predicates of the offense into the statement of the elements. I think here and elsewhere, the defense -- Mr. Everdell can correct me, but an issue in the parties' proposed requests to charge is whether things like the name Jane, travel to New York, the name Jeffrey Epstein should all be included in the recitation of the elements. I think the defense is getting that because it's in the \"to wit\" clause of the indictment, and the law is quite clear -- and I have\nSOUTHERN DISTRICT REPORTERS, P.C. (212) 805-0300\nDOJ-OGR-00014325",
  "text_blocks": [
    {
      "type": "printed",
      "content": "Case 1:20-cr-00330-PAE Document 765 Filed 08/10/22 Page 21 of 95 2759 LCI1MAX1",
      "position": "header"
    },
    {
      "type": "printed",
      "content": "the conspiracy counts come later, I think there is an attempt here to generalize the wording of the elements because it's going to be applied later to the conspiracy counts, right? But this is the substantive count, and if we look at the line 5, it says first that the defendant knowingly persuaded or induced or enticed or coerced an individual to travel in interstate commerce. The individual in the substantive count is Jane. The defense request is for it to say not \"an individual,\" replace that with \"Jane to travel in interstate commerce from Florida to New York, as alleged in the indictment.\"\nTHE COURT: Mr. Rohrbach.\nMR. ROHRBACH: So, your Honor, I don't think the jury will be confused. Both in the summary and later on in this section, it says this relates to Jane. If the defense would like it to say it relates solely to Jane here as in the summary, that would be fine, but the Court is just laying out the elements of the offense and there's no need to put all of the factual predicates of the offense into the statement of the elements. I think here and elsewhere, the defense -- Mr. Everdell can correct me, but an issue in the parties' proposed requests to charge is whether things like the name Jane, travel to New York, the name Jeffrey Epstein should all be included in the recitation of the elements. I think the defense is getting that because it's in the \"to wit\" clause of the indictment, and the law is quite clear -- and I have",
      "position": "middle"
    },
    {
      "type": "printed",
      "content": "SOUTHERN DISTRICT REPORTERS, P.C. (212) 805-0300",
      "position": "footer"
    },
    {
      "type": "printed",
      "content": "DOJ-OGR-00014325",
      "position": "footer"
    }
  ],
  "entities": {
    "people": [
      "Mr. Rohrbach",
      "Mr. Everdell",
      "Jeffrey Epstein",
      "Jane"
    ],
    "organizations": [
      "SOUTHERN DISTRICT REPORTERS, P.C."
    ],
    "locations": [
      "Florida",
      "New York"
    ],
    "dates": [
      "08/10/22"
    ],
    "reference_numbers": [
      "1:20-cr-00330-PAE",
      "765",
      "DOJ-OGR-00014325"
    ]
  },
  "additional_notes": "The document appears to be a court transcript with a clear and legible format. There are no visible redactions or damage to the document."
}