{
  "document_metadata": {
    "page_number": "18 of 19",
    "document_number": "769",
    "date": "08/10/22",
    "document_type": "court transcript",
    "has_handwriting": false,
    "has_stamps": false
  },
  "full_text": "Case 1:20-cr-00330-PAE Document 769 Filed 08/10/22 Page 18 of 19 3109 LCLVMAXT consuming of any information regarding the case. So we appreciate your diligence and wait to hear from you tomorrow. Have a good night. Thank you. (Jury not present) THE COURT: I want to know if the transcripts have been reviewed for the government. MS. COMEY: They have, your Honor. THE COURT: So they are ready to go? MS. COMEY: They are, your Honor. THE COURT: It was frustrating to have to have the jury wait for three hours to get what they requested. MS. COMEY: Yes, your Honor. And we apologize for that. THE COURT: Defense agrees that they are now ready to go? MR. EVERDELL: Yes, your Honor. We've conferred on every witness at this point. THE COURT: Okay. Second thing. I'm inclined to have Ms. Williams just call our alternates tonight to say deliberations are ongoing. All the rules continue to apply. She'll communicate with any further instructions. MS. COMEY: Yes, your Honor. MS. STERNHEIM: No problem. Thank you. SOUTHERN DISTRICT REPORTERS, P.C. (212) 805-0300 DOJ-OGR-00014676",
  "text_blocks": [
    {
      "type": "printed",
      "content": "Case 1:20-cr-00330-PAE Document 769 Filed 08/10/22 Page 18 of 19 3109 LCLVMAXT",
      "position": "header"
    },
    {
      "type": "printed",
      "content": "consuming of any information regarding the case. So we appreciate your diligence and wait to hear from you tomorrow. Have a good night. Thank you. (Jury not present) THE COURT: I want to know if the transcripts have been reviewed for the government. MS. COMEY: They have, your Honor. THE COURT: So they are ready to go? MS. COMEY: They are, your Honor. THE COURT: It was frustrating to have to have the jury wait for three hours to get what they requested. MS. COMEY: Yes, your Honor. And we apologize for that. THE COURT: Defense agrees that they are now ready to go? MR. EVERDELL: Yes, your Honor. We've conferred on every witness at this point. THE COURT: Okay. Second thing. I'm inclined to have Ms. Williams just call our alternates tonight to say deliberations are ongoing. All the rules continue to apply. She'll communicate with any further instructions. MS. COMEY: Yes, your Honor. MS. STERNHEIM: No problem. Thank you.",
      "position": "main content"
    },
    {
      "type": "printed",
      "content": "SOUTHERN DISTRICT REPORTERS, P.C. (212) 805-0300",
      "position": "footer"
    },
    {
      "type": "printed",
      "content": "DOJ-OGR-00014676",
      "position": "footer"
    }
  ],
  "entities": {
    "people": [
      "Ms. Comey",
      "Mr. Everdell",
      "Ms. Williams",
      "Ms. Sternheim"
    ],
    "organizations": [
      "SOUTHERN DISTRICT REPORTERS, P.C."
    ],
    "locations": [],
    "dates": [
      "08/10/22"
    ],
    "reference_numbers": [
      "1:20-cr-00330-PAE",
      "769",
      "DOJ-OGR-00014676"
    ]
  },
  "additional_notes": "The document appears to be a court transcript with a clear and legible format. There are no visible redactions or damage."
}