{
  "document_metadata": {
    "page_number": "56",
    "document_number": "753",
    "date": "08/10/22",
    "document_type": "Court Transcript",
    "has_handwriting": false,
    "has_stamps": false
  },
  "full_text": "Case 1:20-cr-00330-PAE Document 753 Filed 08/10/22 Page 56 of 264 1482\nLC7Cmax2 Flatley - direct\n1 Mr. Flatley, what is the date and time of the email?\n2 A. The email was sent on Friday, May 25th, 2001, at 12:05 p.m.\n3 Q. Who is the email from?\n4 A. It's from gmax1@mindspring.com.\n5 Q. Who is the recipient of the email?\n6 A. Sally Markham.\n7 MS. POMERANTZ: I'd like to ask, Ms. Drescher, if you could, highlight the language starting with \"I need to know\" and we can go through the end of number 6.\n8 Q. Mr. Flatley, can I ask you to read the highlighted language, please?\n9 A. \"I need to know what if any list John is using and he needs to understand that he is doing a truly awful job.\n10 1. There was no drinking water in the black Merc.\n11 2. There were no pens in the black Merc.\n12 3. The bulb on JE desk was burnt out when we arrived.\n13 4. The pool deck was so filthy, JE had to ask him to pressure wash it. Is this not the gardener's job? And if so, why does John not have it done?\n14 5. Even though John said that he changed the color card in the computer, having done it would it could not -- he could not see that it was exactly the same as before, i.e., no different, and that obviously JE would not be happy with it.\n15 6. The massage creams, et cetera, in JE's bathroom were a mess. No one had it tidied up and arranged them so it\nSOUTHERN DISTRICT REPORTERS, P.C. (212) 805-0300\nDOJ-OGR-00013069",
  "text_blocks": [
    {
      "type": "printed",
      "content": "Case 1:20-cr-00330-PAE Document 753 Filed 08/10/22 Page 56 of 264 1482",
      "position": "header"
    },
    {
      "type": "printed",
      "content": "LC7Cmax2 Flatley - direct",
      "position": "header"
    },
    {
      "type": "printed",
      "content": "1 Mr. Flatley, what is the date and time of the email?\n2 A. The email was sent on Friday, May 25th, 2001, at 12:05 p.m.\n3 Q. Who is the email from?\n4 A. It's from gmax1@mindspring.com.\n5 Q. Who is the recipient of the email?\n6 A. Sally Markham.\n7 MS. POMERANTZ: I'd like to ask, Ms. Drescher, if you could, highlight the language starting with \"I need to know\" and we can go through the end of number 6.\n8 Q. Mr. Flatley, can I ask you to read the highlighted language, please?\n9 A. \"I need to know what if any list John is using and he needs to understand that he is doing a truly awful job.\n10 1. There was no drinking water in the black Merc.\n11 2. There were no pens in the black Merc.\n12 3. The bulb on JE desk was burnt out when we arrived.\n13 4. The pool deck was so filthy, JE had to ask him to pressure wash it. Is this not the gardener's job? And if so, why does John not have it done?\n14 5. Even though John said that he changed the color card in the computer, having done it would it could not -- he could not see that it was exactly the same as before, i.e., no different, and that obviously JE would not be happy with it.\n15 6. The massage creams, et cetera, in JE's bathroom were a mess. No one had it tidied up and arranged them so it",
      "position": "main"
    },
    {
      "type": "printed",
      "content": "SOUTHERN DISTRICT REPORTERS, P.C. (212) 805-0300",
      "position": "footer"
    },
    {
      "type": "printed",
      "content": "DOJ-OGR-00013069",
      "position": "footer"
    }
  ],
  "entities": {
    "people": [
      "Mr. Flatley",
      "Sally Markham",
      "Ms. Drescher",
      "Ms. Pomerantz",
      "John",
      "JE"
    ],
    "organizations": [
      "SOUTHERN DISTRICT REPORTERS, P.C."
    ],
    "locations": [],
    "dates": [
      "May 25th, 2001",
      "08/10/22"
    ],
    "reference_numbers": [
      "1:20-cr-00330-PAE",
      "753",
      "DOJ-OGR-00013069"
    ]
  },
  "additional_notes": "The document appears to be a court transcript with a clear and legible format. There are no visible redactions or damage."
}