{
  "document_metadata": {
    "page_number": "2609",
    "document_number": "76318-054",
    "date": "07/09/2019",
    "document_type": "Vision Screens",
    "has_handwriting": false,
    "has_stamps": false
  },
  "full_text": "Page 2609 Bureau of Prisons Health Services Vision Screens Reg #: 76318-054 Inmate Name: EPSTEIN, JEFFREY EDWARD Vision Screen on 07/09/2019 12:52 Blindness: Distance Vision: OD: 20/100 OS: 20/70 OU: Near Vision: OD: OS: OU: With Corrective Distance Vision: OD: OS: OU: Near Vision: OD: OS: OU: Present Glasses - Distance Sphere Cylinder Axis Add Refraction - Distance Sphere Cylinder Axis Add R: R: L: L: Color Test: Tonometry: R: L: Comments: Needs evaluation with optometrist. Orig Entered: 07/09/2019 12:54 EST (b)(6); (b)(7)(C) MLP Generated 07/30/2019 15:33 by (b)(6); (b)(7)(C) FOIA Bureau of Prisons - NYM Page 1 of 1 DOJ-OGR-00026269",
  "text_blocks": [
    {
      "type": "printed",
      "content": "Bureau of Prisons Health Services Vision Screens",
      "position": "header"
    },
    {
      "type": "printed",
      "content": "Reg #: 76318-054 Inmate Name: EPSTEIN, JEFFREY EDWARD",
      "position": "header"
    },
    {
      "type": "printed",
      "content": "Vision Screen on 07/09/2019 12:52 Blindness: Distance Vision: OD: 20/100 OS: 20/70 OU: Near Vision: OD: OS: OU: With Corrective Distance Vision: OD: OS: OU: Near Vision: OD: OS: OU: Present Glasses - Distance Sphere Cylinder Axis Add Refraction - Distance Sphere Cylinder Axis Add R: R: L: L: Color Test: Tonometry: R: L: Comments: Needs evaluation with optometrist. Orig Entered: 07/09/2019 12:54 EST (b)(6); (b)(7)(C) MLP",
      "position": "middle"
    },
    {
      "type": "printed",
      "content": "Generated 07/30/2019 15:33 by (b)(6); (b)(7)(C) FOIA Bureau of Prisons - NYM Page 1 of 1 DOJ-OGR-00026269",
      "position": "footer"
    }
  ],
  "entities": {
    "people": [
      "JEFFREY EDWARD EPSTEIN"
    ],
    "organizations": [
      "Bureau of Prisons",
      "Bureau of Prisons - NYM"
    ],
    "locations": [],
    "dates": [
      "07/09/2019",
      "07/30/2019"
    ],
    "reference_numbers": [
      "76318-054",
      "DOJ-OGR-00026269"
    ]
  },
  "additional_notes": "The document contains redacted information marked as (b)(6); (b)(7)(C)."
}