{
  "document_metadata": {
    "page_number": "3377",
    "document_number": "DOJ-OGR-00026966",
    "date": "08/19/2019",
    "document_type": "Log Entries By Event Date",
    "has_handwriting": false,
    "has_stamps": false
  },
  "full_text": "Page 3377\nDate: 08/19/2019\nTime: 10:32 AM\nFederal Bureau of Prisons\nTRUINTEL\nLog Entries By Event Date\nSensitive But Unclassified\nEntered Date\tAlpha Code Level 1 Location\tLevel 2 Location\tLevel 3 Location\tEvent Date\tShift\tUser\tEvent\tBase Count\n8/10/2019 6:59 PM\tNYM\tHousing Units\tHousing Units, Secured\t10 SOUTH UPPER\t8/10/2019 6:33 PM\tEvening\t(b)(6); (b)(7)(C)\tRounds (Officer)\n8/10/2019 7:04 PM\tNYM\tHousing Units\tHousing Units, Secured\t10 SOUTH UPPER\t8/10/2019 7:04 PM\tEvening\t(b)(6); (b)(7)(C)\tRounds (Officer)\n8/10/2019 7:47 PM\tNYM\tHousing Units\tHousing Units, Secured\t10 SOUTH UPPER\t8/10/2019 7:37 PM\tEvening\t(b)(6); (b)(7)(C)\tRounds (Officer)\n8/10/2019 7:47 PM\tNYM\tHousing Units\tHousing Units, Secured\t10 SOUTH UPPER\t8/10/2019 7:47 PM\tEvening\t(b)(6); (b)(7)(C)\tSensitive Information\n8/10/2019 7:53 PM\tNYM\tHousing Units\tHousing Units, Secured\t10 SOUTH UPPER\t8/10/2019 7:52 PM\tEvening\t(b)(6); (b)(7)(C)\tDaily Activity\n8/10/2019 8:15 PM\tNYM\tHousing Units\tHousing Units, Secured\t10 SOUTH UPPER\t8/10/2019 8:10 PM\tEvening\t(b)(6); (b)(7)(C)\tRounds (Officer)\n8/10/2019 8:15 PM\tNYM\tHousing Units\tHousing Units, Secured\t10 SOUTH UPPER\t8/10/2019 8:15 PM\tEvening\t(b)(6); (b)(7)(C)\tSearch (Cells)\n8/10/2019 8:41 PM\tNYM\tHousing Units\tHousing Units, Secured\t10 SOUTH UPPER\t8/10/2019 8:41 PM\tEvening\t(b)(6); (b)(7)(C)\tRounds (Officer)\n8/11/2019 1:34 AM\tNYM\tHousing Units\tHousing Units, Secured\t10 SOUTH UPPER\t8/11/2019 1:12 AM\tMorning\t(b)(6); (b)(7)(C)\tRounds (Lieutenant)\n8/10/2019 9:58 PM\tNYM\tHousing Units\tHousing Units, Secured\t10 SOUTH UPPER\t8/10/2019 9:13 PM\tEvening\t(b)(6); (b)(7)(C)\tRounds (Officer)\n8/10/2019 9:58 PM\tNYM\tHousing Units\tHousing Units, Secured\t10 SOUTH UPPER\t8/10/2019 9:45 PM\tEvening\t(b)(6); (b)(7)(C)\tRounds (Officer)\n8/10/2019 10:05 PM\tNYM\tHousing Units\tHousing Units, Secured\t10 SOUTH UPPER\t8/10/2019 10:04 PM\tEvening\t(b)(6); (b)(7)(C)\tOfficial Count\n8/10/2019 10:17 PM\tNYM\tHousing Units\tHousing Units, Secured\t10 SOUTH UPPER\t8/10/2019 10:17 PM\tEvening\t(b)(6); (b)(7)(C)\tRounds (Officer)\nUser ID: (b)(6); (b)(7)(C)\tPage 137 of 183\nDOJ-OGR-00026966",
  "text_blocks": [
    {
      "type": "printed",
      "content": "Page 3377",
      "position": "header"
    },
    {
      "type": "printed",
      "content": "Date: 08/19/2019\nTime: 10:32 AM",
      "position": "header"
    },
    {
      "type": "printed",
      "content": "Federal Bureau of Prisons\nTRUINTEL\nLog Entries By Event Date\nSensitive But Unclassified",
      "position": "header"
    },
    {
      "type": "printed",
      "content": "Entered Date\tAlpha Code Level 1 Location\tLevel 2 Location\tLevel 3 Location\tEvent Date\tShift\tUser\tEvent\tBase Count",
      "position": "table header"
    },
    {
      "type": "printed",
      "content": "8/10/2019 6:59 PM\tNYM\tHousing Units\tHousing Units, Secured\t10 SOUTH UPPER\t8/10/2019 6:33 PM\tEvening\t(b)(6); (b)(7)(C)\tRounds (Officer)",
      "position": "table row"
    },
    {
      "type": "printed",
      "content": "8/10/2019 7:04 PM\tNYM\tHousing Units\tHousing Units, Secured\t10 SOUTH UPPER\t8/10/2019 7:04 PM\tEvening\t(b)(6); (b)(7)(C)\tRounds (Officer)",
      "position": "table row"
    },
    {
      "type": "printed",
      "content": "8/10/2019 7:47 PM\tNYM\tHousing Units\tHousing Units, Secured\t10 SOUTH UPPER\t8/10/2019 7:37 PM\tEvening\t(b)(6); (b)(7)(C)\tRounds (Officer)",
      "position": "table row"
    },
    {
      "type": "printed",
      "content": "8/10/2019 7:47 PM\tNYM\tHousing Units\tHousing Units, Secured\t10 SOUTH UPPER\t8/10/2019 7:47 PM\tEvening\t(b)(6); (b)(7)(C)\tSensitive Information",
      "position": "table row"
    },
    {
      "type": "printed",
      "content": "8/10/2019 7:53 PM\tNYM\tHousing Units\tHousing Units, Secured\t10 SOUTH UPPER\t8/10/2019 7:52 PM\tEvening\t(b)(6); (b)(7)(C)\tDaily Activity",
      "position": "table row"
    },
    {
      "type": "printed",
      "content": "8/10/2019 8:15 PM\tNYM\tHousing Units\tHousing Units, Secured\t10 SOUTH UPPER\t8/10/2019 8:10 PM\tEvening\t(b)(6); (b)(7)(C)\tRounds (Officer)",
      "position": "table row"
    },
    {
      "type": "printed",
      "content": "8/10/2019 8:15 PM\tNYM\tHousing Units\tHousing Units, Secured\t10 SOUTH UPPER\t8/10/2019 8:15 PM\tEvening\t(b)(6); (b)(7)(C)\tSearch (Cells)",
      "position": "table row"
    },
    {
      "type": "printed",
      "content": "8/10/2019 8:41 PM\tNYM\tHousing Units\tHousing Units, Secured\t10 SOUTH UPPER\t8/10/2019 8:41 PM\tEvening\t(b)(6); (b)(7)(C)\tRounds (Officer)",
      "position": "table row"
    },
    {
      "type": "printed",
      "content": "8/11/2019 1:34 AM\tNYM\tHousing Units\tHousing Units, Secured\t10 SOUTH UPPER\t8/11/2019 1:12 AM\tMorning\t(b)(6); (b)(7)(C)\tRounds (Lieutenant)",
      "position": "table row"
    },
    {
      "type": "printed",
      "content": "8/10/2019 9:58 PM\tNYM\tHousing Units\tHousing Units, Secured\t10 SOUTH UPPER\t8/10/2019 9:13 PM\tEvening\t(b)(6); (b)(7)(C)\tRounds (Officer)",
      "position": "table row"
    },
    {
      "type": "printed",
      "content": "8/10/2019 9:58 PM\tNYM\tHousing Units\tHousing Units, Secured\t10 SOUTH UPPER\t8/10/2019 9:45 PM\tEvening\t(b)(6); (b)(7)(C)\tRounds (Officer)",
      "position": "table row"
    },
    {
      "type": "printed",
      "content": "8/10/2019 10:05 PM\tNYM\tHousing Units\tHousing Units, Secured\t10 SOUTH UPPER\t8/10/2019 10:04 PM\tEvening\t(b)(6); (b)(7)(C)\tOfficial Count",
      "position": "table row"
    },
    {
      "type": "printed",
      "content": "8/10/2019 10:17 PM\tNYM\tHousing Units\tHousing Units, Secured\t10 SOUTH UPPER\t8/10/2019 10:17 PM\tEvening\t(b)(6); (b)(7)(C)\tRounds (Officer)",
      "position": "table row"
    },
    {
      "type": "printed",
      "content": "User ID: (b)(6); (b)(7)(C)",
      "position": "footer"
    },
    {
      "type": "printed",
      "content": "Page 137 of 183",
      "position": "footer"
    },
    {
      "type": "printed",
      "content": "DOJ-OGR-00026966",
      "position": "footer"
    }
  ],
  "entities": {
    "people": [],
    "organizations": [
      "Federal Bureau of Prisons"
    ],
    "locations": [
      "10 SOUTH UPPER"
    ],
    "dates": [
      "08/19/2019",
      "8/10/2019",
      "8/11/2019"
    ],
    "reference_numbers": [
      "DOJ-OGR-00026966"
    ]
  },
  "additional_notes": "The document appears to be a log entry report from the Federal Bureau of Prisons, detailing various events and activities at a correctional facility. The report includes information such as date, time, location, and user ID. Some user IDs are redacted."
}