{
  "document_metadata": {
    "page_number": "1754",
    "document_number": "DOJ-OGR-00025779",
    "date": null,
    "document_type": null,
    "has_handwriting": false,
    "has_stamps": false
  },
  "full_text": "Page 1754 FYI...AW portion for page 10 regarding SW cell assignment. Charisma Edge Associate Warden MCC New York 150 Park Row New York, NY 10007 646-836-6300 ext (b)(6); (b)(7)(C) (b)(6); (b)(7)(C) @bop.gov NYM/AW-Programs~@bop.gov >>> (b)(6); (b)(7)(C) 11/12/2019 2:12 PM >>> Updated to include (b)(6); (b)(7)(C) 's suggestions. >>> (b)(6); (b)(7)(C) 1/12/2019 1:31 PM >>> We are in the home stretch. There are highlighted sections that need some more information: p. 5: Correctional Services re expunged incident report p. 10: AWP/Correctional Services re Lt rounds and C&A follow up p. 11: HSA re approval of documentation for new procedures to inspect AEDs Psychology re NERO waiver attachment (b)(6); (b)(7)(C) Supervisory Staff Attorney CLC New York Metropolitan Correctional Center 150 Park Row New York, New York 10007 p: (646)836 (b)(6); (b)(7)(C) f: (646)836-7665 Page 9090 DOJ-OGR-00025779",
  "text_blocks": [
    {
      "type": "printed",
      "content": "Page 1754 FYI...AW portion for page 10 regarding SW cell assignment.",
      "position": "top"
    },
    {
      "type": "printed",
      "content": "Charisma Edge Associate Warden MCC New York 150 Park Row New York, NY 10007 646-836-6300 ext (b)(6); (b)(7)(C) (b)(6); (b)(7)(C) @bop.gov NYM/AW-Programs~@bop.gov",
      "position": "middle"
    },
    {
      "type": "printed",
      "content": ">>> (b)(6); (b)(7)(C) 11/12/2019 2:12 PM >>> Updated to include (b)(6); (b)(7)(C) 's suggestions.",
      "position": "middle"
    },
    {
      "type": "printed",
      "content": ">>> (b)(6); (b)(7)(C) 1/12/2019 1:31 PM >>> We are in the home stretch. There are highlighted sections that need some more information: p. 5: Correctional Services re expunged incident report p. 10: AWP/Correctional Services re Lt rounds and C&A follow up p. 11: HSA re approval of documentation for new procedures to inspect AEDs Psychology re NERO waiver attachment",
      "position": "middle"
    },
    {
      "type": "printed",
      "content": "(b)(6); (b)(7)(C) Supervisory Staff Attorney CLC New York Metropolitan Correctional Center 150 Park Row New York, New York 10007 p: (646)836 (b)(6); (b)(7)(C) f: (646)836-7665",
      "position": "bottom"
    },
    {
      "type": "printed",
      "content": "Page 9090 DOJ-OGR-00025779",
      "position": "footer"
    }
  ],
  "entities": {
    "people": [
      "Charisma Edge"
    ],
    "organizations": [
      "MCC New York",
      "CLC New York",
      "Metropolitan Correctional Center",
      "BOP"
    ],
    "locations": [
      "New York"
    ],
    "dates": [
      "11/12/2019",
      "1/12/2019"
    ],
    "reference_numbers": [
      "DOJ-OGR-00025779"
    ]
  },
  "additional_notes": "The document contains redactions marked as (b)(6); (b)(7)(C), indicating potentially sensitive information."
}