{
  "document_metadata": {
    "page_number": "2642",
    "document_number": "DOJ-OGR-00026298",
    "date": "07/11/2019",
    "document_type": "General Administrative Note",
    "has_handwriting": false,
    "has_stamps": false
  },
  "full_text": "Page 2642 Bureau of Prisons Psychology Services **SENSITIVE BUT UNCLASSIFIED** General Administrative Note Inmate Name: EPSTEIN, JEFFREY EDWARD Date of Birth: 01/20/1953 Sex: M Facility: NYM Date: 07/11/2019 14:28 Provider: [b)(6); (b)(7)(C) PsyD Unit Team: A&O Reg #: 76318-054 Comments This writer attempted to see Mr. Epstein in the morning and then again in the afternoon for a Psych Observation Follow Up, but he was in Attorney Conference. Completed by [b)(6); (b)(7)(C) PsyD on 07/11/2019 15:51 Generated 07/11/2019 15:51 by [b)(6); (b)(7)(C) PsyD Bureau of Prisons - NYM Page 1 of 1 DOJ-OGR-00026298",
  "text_blocks": [
    {
      "type": "printed",
      "content": "Bureau of Prisons Psychology Services General Administrative Note",
      "position": "header"
    },
    {
      "type": "printed",
      "content": "Inmate Name: EPSTEIN, JEFFREY EDWARD Date of Birth: 01/20/1953 Sex: M Facility: NYM Date: 07/11/2019 14:28 Provider: [b)(6); (b)(7)(C) PsyD Unit Team: A&O Reg #: 76318-054",
      "position": "top"
    },
    {
      "type": "printed",
      "content": "Comments This writer attempted to see Mr. Epstein in the morning and then again in the afternoon for a Psych Observation Follow Up, but he was in Attorney Conference.",
      "position": "middle"
    },
    {
      "type": "printed",
      "content": "Completed by [b)(6); (b)(7)(C) PsyD on 07/11/2019 15:51",
      "position": "middle"
    },
    {
      "type": "printed",
      "content": "Generated 07/11/2019 15:51 by [b)(6); (b)(7)(C) PsyD Bureau of Prisons - NYM Page 1 of 1 DOJ-OGR-00026298",
      "position": "footer"
    }
  ],
  "entities": {
    "people": [
      "JEFFREY EDWARD EPSTEIN",
      "Mr. Epstein"
    ],
    "organizations": [
      "Bureau of Prisons",
      "NYM"
    ],
    "locations": [],
    "dates": [
      "01/20/1953",
      "07/11/2019"
    ],
    "reference_numbers": [
      "76318-054",
      "DOJ-OGR-00026298"
    ]
  },
  "additional_notes": "The document contains redacted information marked as [b)(6); (b)(7)(C)]. The document is marked as 'SENSITIVE BUT UNCLASSIFIED'."
}