{
  "document_metadata": {
    "page_number": null,
    "document_number": "DOJ-OGR-00027455",
    "date": "04/01/2000",
    "document_type": "Air / Sea Baggage Secondary Inspection",
    "has_handwriting": false,
    "has_stamps": false
  },
  "full_text": "UNCLASSIFIED // FOR OFFICIAL USE ONLY\nEPSTEIN JEFFREY (b)(7)(E)\n04/01/2000 08:17:00\nAir / Sea Baggage Secondary Inspection (b)(7)(E)\n(b)(7)(E)\nSubject\nLast Name: EPSTEIN\nFirst Name: JEFFREY\nGender: Male (b)(7)(E)\nRace: White (b)(7)(E)\nDate Of Birth: 01/20/1953\nCrossing Information\nPort: JFK INTL ARPT (4701)\nSite: NEW YORK, JFK AIRPORT, TERM 1 (b)(7)(E)\nInbound/Outbound: Inbound\nPort Crossing Date: 04/01/2000 08:17:00\nEmbark Port: CHARLES DE GAULLE (b)(7)(E)\nDeparture Airport: CHARLES DE GAULLE (b)(7)(E)\nAirline: AIR FRANCE (AF)\nPassenger Document\nDocument Type I: PASSPORT (b)(7)(E)\nIssue Country: United States (US/USA)\nDocument Number: (b)(6),(b)(7)(C)\nReferral / Inspection Information\nReferral Office: (b)(7)(E)\nReferral Reason: (b)(7)(E)\nReferral Comment: (b)(7)(E)\nInspection Completion: Yes\nInspection Result: Negative\nMiscellaneous Info\nPersonnel Search: No\nBaggage Examination: Yes\nPassenger On Declare Number: 1\nRemarks\n(b)(7)(E)\nUNCLASSIFIED // FOR OFFICIAL USE ONLY",
  "text_blocks": [
    {
      "type": "printed",
      "content": "UNCLASSIFIED // FOR OFFICIAL USE ONLY",
      "position": "header"
    },
    {
      "type": "printed",
      "content": "EPSTEIN JEFFREY (b)(7)(E)\n04/01/2000 08:17:00\nAir / Sea Baggage Secondary Inspection (b)(7)(E)",
      "position": "top"
    },
    {
      "type": "printed",
      "content": "Subject\nLast Name: EPSTEIN\nFirst Name: JEFFREY\nGender: Male (b)(7)(E)\nRace: White (b)(7)(E)\nDate Of Birth: 01/20/1953",
      "position": "middle"
    },
    {
      "type": "printed",
      "content": "Crossing Information\nPort: JFK INTL ARPT (4701)\nSite: NEW YORK, JFK AIRPORT, TERM 1 (b)(7)(E)\nInbound/Outbound: Inbound\nPort Crossing Date: 04/01/2000 08:17:00\nEmbark Port: CHARLES DE GAULLE (b)(7)(E)\nDeparture Airport: CHARLES DE GAULLE (b)(7)(E)\nAirline: AIR FRANCE (AF)",
      "position": "middle"
    },
    {
      "type": "printed",
      "content": "Passenger Document\nDocument Type I: PASSPORT (b)(7)(E)\nIssue Country: United States (US/USA)\nDocument Number: (b)(6),(b)(7)(C)",
      "position": "middle"
    },
    {
      "type": "printed",
      "content": "Referral / Inspection Information\nReferral Office: (b)(7)(E)\nReferral Reason: (b)(7)(E)\nReferral Comment: (b)(7)(E)\nInspection Completion: Yes\nInspection Result: Negative",
      "position": "middle"
    },
    {
      "type": "printed",
      "content": "Miscellaneous Info\nPersonnel Search: No\nBaggage Examination: Yes\nPassenger On Declare Number: 1",
      "position": "middle"
    },
    {
      "type": "printed",
      "content": "Remarks\n(b)(7)(E)",
      "position": "middle"
    },
    {
      "type": "printed",
      "content": "UNCLASSIFIED // FOR OFFICIAL USE ONLY",
      "position": "footer"
    },
    {
      "type": "printed",
      "content": "DOJ-OGR-00027455",
      "position": "footer"
    }
  ],
  "entities": {
    "people": [
      "JEFFREY EPSTEIN"
    ],
    "organizations": [
      "AIR FRANCE"
    ],
    "locations": [
      "NEW YORK",
      "JFK AIRPORT",
      "CHARLES DE GAULLE",
      "United States"
    ],
    "dates": [
      "04/01/2000",
      "01/20/1953"
    ],
    "reference_numbers": [
      "(b)(6),(b)(7)(C)",
      "DOJ-OGR-00027455"
    ]
  },
  "additional_notes": "The document contains redactions marked as (b)(7)(E) and (b)(6),(b)(7)(C). The document is an Air / Sea Baggage Secondary Inspection report for JEFFREY EPSTEIN."
}