{
  "document_metadata": {
    "page_number": "3383",
    "document_number": "DOJ-OGR-00026972",
    "date": "08/19/2019",
    "document_type": "Log Entries By Event Date",
    "has_handwriting": false,
    "has_stamps": false
  },
  "full_text": "Page 3383 Date: 08/19/2019 Time: 10:15 AM Federal Bureau of Prisons TRUINTEL Log Entries By Event Date Sensitive But Unclassified Entered Date Alpha Code Level 1 Location Level 2 Location Level 3 Location Event Date Shift User Event Base Count 8/9/2019 7:35 AM NYM Housing Units Housing Units, General Population GN 8/9/2019 7:35 AM Morning [b(6); b(7)(C)] Daily Activity - Summary Text: Completed. 8/9/2019 8:25 AM NYM Housing Units Housing Units, General Population IN 8/9/2019 8:00 AM Day Begin Shift - Summary Text: PAIN AND OUT FROM DISTRIBUTING MED'S 8/9/2019 8:27 AM NYM Housing Units Housing Units, General Population IN 8/9/2019 8:00 AM Day [b(7)(E)] Check - Summary Text: Completed. 8/9/2019 8:27 AM NYM Housing Units Housing Units, General Population IN 8/9/2019 8:00 AM Day Fire Alarm Panel Check - Summary Text: Radio Number [b(7)(F)] 8/9/2019 8:27 AM NYM Housing Units Housing Units, General Population IN 8/9/2019 8:00 AM Day Inventory Sheet Verified - Summary Text: Completed. 8/9/2019 8:27 AM NYM Housing Units Housing Units, General Population IN 8/9/2019 8:00 AM Day Key Check - Summary Text: Completed. 8/9/2019 8:27 AM NYM Housing Units Housing Units, General Population IN 8/9/2019 8:00 AM Day Key Check - Summary Text: Ring Number [b(7)(F)] Count [b(7)(F)] 8/9/2019 8:27 AM NYM Housing Units Housing Units, General Population IN 8/9/2019 8:00 AM Day OC Spray Check - Summary Text: Ring Number [b(7)(F)] Count [b(7)(F)] 8/9/2019 8:27 AM NYM Housing Units Housing Units, General Population IN 8/9/2019 8:00 AM Day Radio Check - Summary Text: Completed. Serviceable. 8/9/2019 8:05 AM NYM Housing Units Housing Units, General Population GN 8/9/2019 8:05 AM Day Rounds (Officer) - Summary Text: Completed. User ID: [b(6); b(7)(C)] Page 911 of 1155 DOJ-OGR-00026972",
  "text_blocks": [
    {
      "type": "printed",
      "content": "Page 3383 Date: 08/19/2019 Time: 10:15 AM Federal Bureau of Prisons TRUINTEL Log Entries By Event Date Sensitive But Unclassified",
      "position": "header"
    },
    {
      "type": "printed",
      "content": "Entered Date Alpha Code Level 1 Location Level 2 Location Level 3 Location Event Date Shift User Event Base Count",
      "position": "header"
    },
    {
      "type": "printed",
      "content": "8/9/2019 7:35 AM NYM Housing Units Housing Units, General Population GN 8/9/2019 7:35 AM Morning [b(6); b(7)(C)] Daily Activity - Summary Text: Completed.",
      "position": "body"
    },
    {
      "type": "printed",
      "content": "8/9/2019 8:25 AM NYM Housing Units Housing Units, General Population IN 8/9/2019 8:00 AM Day Begin Shift - Summary Text: PAIN AND OUT FROM DISTRIBUTING MED'S",
      "position": "body"
    },
    {
      "type": "printed",
      "content": "8/9/2019 8:27 AM NYM Housing Units Housing Units, General Population IN 8/9/2019 8:00 AM Day [b(7)(E)] Check - Summary Text: Completed.",
      "position": "body"
    },
    {
      "type": "printed",
      "content": "8/9/2019 8:27 AM NYM Housing Units Housing Units, General Population IN 8/9/2019 8:00 AM Day Fire Alarm Panel Check - Summary Text: Radio Number [b(7)(F)]",
      "position": "body"
    },
    {
      "type": "printed",
      "content": "8/9/2019 8:27 AM NYM Housing Units Housing Units, General Population IN 8/9/2019 8:00 AM Day Inventory Sheet Verified - Summary Text: Completed.",
      "position": "body"
    },
    {
      "type": "printed",
      "content": "8/9/2019 8:27 AM NYM Housing Units Housing Units, General Population IN 8/9/2019 8:00 AM Day Key Check - Summary Text: Completed.",
      "position": "body"
    },
    {
      "type": "printed",
      "content": "8/9/2019 8:27 AM NYM Housing Units Housing Units, General Population IN 8/9/2019 8:00 AM Day Key Check - Summary Text: Ring Number [b(7)(F)] Count [b(7)(F)]",
      "position": "body"
    },
    {
      "type": "printed",
      "content": "8/9/2019 8:27 AM NYM Housing Units Housing Units, General Population IN 8/9/2019 8:00 AM Day OC Spray Check - Summary Text: Ring Number [b(7)(F)] Count [b(7)(F)]",
      "position": "body"
    },
    {
      "type": "printed",
      "content": "8/9/2019 8:27 AM NYM Housing Units Housing Units, General Population IN 8/9/2019 8:00 AM Day Radio Check - Summary Text: Completed. Serviceable.",
      "position": "body"
    },
    {
      "type": "printed",
      "content": "8/9/2019 8:05 AM NYM Housing Units Housing Units, General Population GN 8/9/2019 8:05 AM Day Rounds (Officer) - Summary Text: Completed.",
      "position": "body"
    },
    {
      "type": "printed",
      "content": "User ID: [b(6); b(7)(C)] Page 911 of 1155 DOJ-OGR-00026972",
      "position": "footer"
    }
  ],
  "entities": {
    "people": [],
    "organizations": [
      "Federal Bureau of Prisons"
    ],
    "locations": [
      "Housing Units",
      "Housing Units, General Population"
    ],
    "dates": [
      "08/19/2019",
      "8/9/2019"
    ],
    "reference_numbers": [
      "DOJ-OGR-00026972"
    ]
  },
  "additional_notes": "The document appears to be a log entry report from the Federal Bureau of Prisons, containing various events and activities recorded on August 9, 2019. Some information is redacted, indicated by [b(6); b(7)(C)] and [b(7)(E)]. The document is part of a larger collection, as indicated by 'Page 911 of 1155'."
}