{
  "document_metadata": {
    "page_number": "1944",
    "document_number": "DOJ-OGR-00025890",
    "date": "2019/08/12",
    "document_type": "email",
    "has_handwriting": false,
    "has_stamps": false
  },
  "full_text": "Page 1944\nRe: Jeffrey Epstein 19 cr 490\nFrom\n(b)(6); (b)(7)(C)\n@nyusd.uscourts.gov\n(b)(6); (b)(7)(C)\nTo\n(b)(6); (b)(7)(C)\n@nysd.uscourts.gov\n(b)(6); (b)(7)(C)\n(b)(6); (b)(7)(C)\n@nysd.uscourts.gov, Lamine N'Diaye\n(b)(6); (b)(7)(C)\n@att.net\nDate\n2019/08/12 14:33\nSubject:\nRe: Jeffrey Epstein 19 cr 490\nAttachments:\nTEXT.htm, 2019_08_12_14_31_06.pdf\nGood afternoon,\nAttached please find Warden N'Diaye's response to Your Honor's inquiry. Please let us know if you need further information.\nThank you,\n(b)(6); (b)(7)(C)\nSupervisory Staff Attorney\nCLC New York\nMetropolitan Correctional Center\n150 Park Row\nNew York, New York 10007\np: (646)836-(b)(6); (b)(7)(C)\nf: (646)836-7665\n>> (b)(6); (b)(7)(C)\n@nysd.uscourts.gov> 8/12/2019 12:47 PM >>>\nPlease see attached letter from Judge Richard M. Berman.\n(See attached file: Aug 12 letter.pdf)\nPage 10621\nDOJ-OGR-00025890",
  "text_blocks": [
    {
      "type": "printed",
      "content": "Re: Jeffrey Epstein 19 cr 490",
      "position": "top"
    },
    {
      "type": "printed",
      "content": "From",
      "position": "top"
    },
    {
      "type": "printed",
      "content": "(b)(6); (b)(7)(C)\n@nyusd.uscourts.gov\n(b)(6); (b)(7)(C)",
      "position": "top"
    },
    {
      "type": "printed",
      "content": "To",
      "position": "top"
    },
    {
      "type": "printed",
      "content": "(b)(6); (b)(7)(C)\n@nysd.uscourts.gov\n(b)(6); (b)(7)(C)\n(b)(6); (b)(7)(C)\n@nysd.uscourts.gov, Lamine N'Diaye\n(b)(6); (b)(7)(C)\n@att.net",
      "position": "top"
    },
    {
      "type": "printed",
      "content": "Date\n2019/08/12 14:33",
      "position": "top"
    },
    {
      "type": "printed",
      "content": "Subject:\nRe: Jeffrey Epstein 19 cr 490",
      "position": "top"
    },
    {
      "type": "printed",
      "content": "Attachments:\nTEXT.htm, 2019_08_12_14_31_06.pdf",
      "position": "top"
    },
    {
      "type": "printed",
      "content": "Good afternoon,\nAttached please find Warden N'Diaye's response to Your Honor's inquiry. Please let us know if you need further information.",
      "position": "middle"
    },
    {
      "type": "printed",
      "content": "Thank you,\n(b)(6); (b)(7)(C)",
      "position": "middle"
    },
    {
      "type": "printed",
      "content": "Supervisory Staff Attorney\nCLC New York\nMetropolitan Correctional Center\n150 Park Row\nNew York, New York 10007\np: (646)836-(b)(6); (b)(7)(C)\nf: (646)836-7665",
      "position": "middle"
    },
    {
      "type": "printed",
      "content": ">> (b)(6); (b)(7)(C)\n@nysd.uscourts.gov> 8/12/2019 12:47 PM >>>\nPlease see attached letter from Judge Richard M. Berman.",
      "position": "middle"
    },
    {
      "type": "printed",
      "content": "(See attached file: Aug 12 letter.pdf)",
      "position": "middle"
    },
    {
      "type": "printed",
      "content": "Page 10621\nDOJ-OGR-00025890",
      "position": "footer"
    }
  ],
  "entities": {
    "people": [
      "Jeffrey Epstein",
      "Lamine N'Diaye",
      "Richard M. Berman"
    ],
    "organizations": [
      "Metropolitan Correctional Center"
    ],
    "locations": [
      "New York"
    ],
    "dates": [
      "2019/08/12",
      "8/12/2019"
    ],
    "reference_numbers": [
      "19 cr 490",
      "DOJ-OGR-00025890"
    ]
  },
  "additional_notes": "The document contains redactions marked as (b)(6); (b)(7)(C), indicating potentially sensitive information has been removed."
}