{
  "document_metadata": {
    "page_number": "237",
    "document_number": "DOJ-OGR-00027199",
    "date": "7/24/2019",
    "document_type": "Email correspondence",
    "has_handwriting": false,
    "has_stamps": false
  },
  "full_text": "Black Berry: 646-423- [b(6); (b)(7)(C) @bop.gov >>> Ray Ormond 7/24/2019 9:42 AM >>> Thanks. Where and with who will he be housed after his Attorney visit? Also, what does \"Psychology Observation\" status mean? J. Ray Ormond Regional Director Northeast Region 215-521- [b(6); (b)(7)(C) >>> Shirley V. Skipper-Scott 7/24/2019 9:39 AM >>> Hello, Inmate Epstein #76318-054 was removed from Suicide Watch and stepped down to Psychological Observation. He was just escorted to Health Services for a follow-up assessment/evaluation. Once completed, he will be escorted to Attorney Conference to meet with his Attorney. I will provide you with information concerning the medical assessment, once I receive it. Thanks. Shirley Skipper-Scott Associate Warden MCC New York 150 Park Row New York, New York 10007 Office: 646-836- [b(6); (b)(7)(C) Black Berry: 646-423- [b(6); (b)(7)(C) @bop.gov >>> Ray Ormond 7/24/2019 8:45 AM >>> Shirley - Please provide me with a daily update on this inmate, including his status and any changes/activities I should be aware of. Thanks! J. Ray Ormond Regional Director Northeast Region 215-521- [b(6); (b)(7)(C) Page 237 DOJ-OGR-00027199",
  "text_blocks": [
    {
      "type": "printed",
      "content": "Black Berry: 646-423- [b(6); (b)(7)(C) @bop.gov",
      "position": "top"
    },
    {
      "type": "printed",
      "content": ">>> Ray Ormond 7/24/2019 9:42 AM >>> Thanks. Where and with who will he be housed after his Attorney visit? Also, what does \"Psychology Observation\" status mean?",
      "position": "top"
    },
    {
      "type": "printed",
      "content": "J. Ray Ormond Regional Director Northeast Region 215-521- [b(6); (b)(7)(C)",
      "position": "top"
    },
    {
      "type": "printed",
      "content": ">>> Shirley V. Skipper-Scott 7/24/2019 9:39 AM >>> Hello,",
      "position": "middle"
    },
    {
      "type": "printed",
      "content": "Inmate Epstein #76318-054 was removed from Suicide Watch and stepped down to Psychological Observation. He was just escorted to Health Services for a follow-up assessment/evaluation. Once completed, he will be escorted to Attorney Conference to meet with his Attorney. I will provide you with information concerning the medical assessment, once I receive it. Thanks.",
      "position": "middle"
    },
    {
      "type": "printed",
      "content": "Shirley Skipper-Scott Associate Warden MCC New York 150 Park Row New York, New York 10007 Office: 646-836- [b(6); (b)(7)(C) Black Berry: 646-423- [b(6); (b)(7)(C) @bop.gov",
      "position": "middle"
    },
    {
      "type": "printed",
      "content": ">>> Ray Ormond 7/24/2019 8:45 AM >>> Shirley - Please provide me with a daily update on this inmate, including his status and any changes/activities I should be aware of. Thanks!",
      "position": "bottom"
    },
    {
      "type": "printed",
      "content": "J. Ray Ormond Regional Director Northeast Region 215-521- [b(6); (b)(7)(C)",
      "position": "bottom"
    },
    {
      "type": "printed",
      "content": "Page 237 DOJ-OGR-00027199",
      "position": "footer"
    }
  ],
  "entities": {
    "people": [
      "Ray Ormond",
      "Shirley V. Skipper-Scott",
      "Epstein"
    ],
    "organizations": [
      "MCC New York",
      "BOP"
    ],
    "locations": [
      "New York"
    ],
    "dates": [
      "7/24/2019"
    ],
    "reference_numbers": [
      "76318-054",
      "DOJ-OGR-00027199"
    ]
  },
  "additional_notes": "The document appears to be a series of emails or correspondence regarding the status of Inmate Epstein. Some phone numbers and email addresses have been redacted."
}