{
  "document_metadata": {
    "page_number": "2",
    "document_number": "2673",
    "date": "07/23/2019",
    "document_type": "Medical Examination Report",
    "has_handwriting": false,
    "has_stamps": false
  },
  "full_text": "Page 2673\nInmate Name: EPSTEIN, JEFFREY EDWARD\nDate of Birth: 01/20/1953\nEncounter Date: 07/23/2019 06:20\nSex: M\nRace: WHITE\nReg #: 76318-054\nProvider: (b)(6); (b)(7)(C)\nFacility: NYM\nUnit: H01\nMLP\nExam:\nAcutely III\nPulmonary\nAuscultation\nYes: Clear to Auscultation, Vesicular Breath Sounds Bilaterally\nNo: Crackles, Rhonchi, Wheezing\nExam Comments\n(b)(7)(A)\nASSESSMENT:\nInjury, unspecified, T1490 - Current - R/O self inflicted injuries.\nPLAN:\nDisposition:\nFollow-up at Sick Call as Needed\nPlaced on Suicide Watch\nFollow-up in 2-4 Hours\nOther:\nFor follow up with psychology service.\nPatient Education Topics:\nDate Initiated Format Handout/Topic Provider Outcome\n07/23/2019 Counseling Access to Care (b)(6); (b)(7)(C) Verbalizes Understanding\n07/23/2019 Counseling Plan of Care (b)(6); (b)(7)(C) Verbalizes Understanding\nCopay Required: No Cosign Required: Yes\nTelephone/Verbal Order: No\nCompleted by (b)(6); (b)(7)(C) MLP on 07/23/2019 09:05\nRequested to be cosigned by (b)(6); (b)(7)(C) MD.\nCosign documentation will be displayed on the following page.\nGenerated 07/23/2019 09:05 by (b)(6); (b)(7)(C) MLP Bureau of Prisons - NYM Page 2 of 2 DOJ-OGR-00026329",
  "text_blocks": [
    {
      "type": "printed",
      "content": "Inmate Name: EPSTEIN, JEFFREY EDWARD\nDate of Birth: 01/20/1953\nEncounter Date: 07/23/2019 06:20\nSex: M\nRace: WHITE\nReg #: 76318-054\nProvider: (b)(6); (b)(7)(C)\nFacility: NYM\nUnit: H01\nMLP",
      "position": "top"
    },
    {
      "type": "printed",
      "content": "Exam:\nAcutely III\nPulmonary\nAuscultation\nYes: Clear to Auscultation, Vesicular Breath Sounds Bilaterally\nNo: Crackles, Rhonchi, Wheezing",
      "position": "middle"
    },
    {
      "type": "printed",
      "content": "Exam Comments\n(b)(7)(A)",
      "position": "middle"
    },
    {
      "type": "printed",
      "content": "ASSESSMENT:\nInjury, unspecified, T1490 - Current - R/O self inflicted injuries.",
      "position": "middle"
    },
    {
      "type": "printed",
      "content": "PLAN:\nDisposition:\nFollow-up at Sick Call as Needed\nPlaced on Suicide Watch\nFollow-up in 2-4 Hours\nOther:\nFor follow up with psychology service.",
      "position": "middle"
    },
    {
      "type": "printed",
      "content": "Patient Education Topics:\nDate Initiated Format Handout/Topic Provider Outcome\n07/23/2019 Counseling Access to Care (b)(6); (b)(7)(C) Verbalizes Understanding\n07/23/2019 Counseling Plan of Care (b)(6); (b)(7)(C) Verbalizes Understanding",
      "position": "middle"
    },
    {
      "type": "printed",
      "content": "Copay Required: No Cosign Required: Yes\nTelephone/Verbal Order: No\nCompleted by (b)(6); (b)(7)(C) MLP on 07/23/2019 09:05\nRequested to be cosigned by (b)(6); (b)(7)(C) MD.\nCosign documentation will be displayed on the following page.",
      "position": "bottom"
    },
    {
      "type": "printed",
      "content": "Generated 07/23/2019 09:05 by (b)(6); (b)(7)(C) MLP Bureau of Prisons - NYM Page 2 of 2 DOJ-OGR-00026329",
      "position": "footer"
    }
  ],
  "entities": {
    "people": [
      "JEFFREY EDWARD EPSTEIN"
    ],
    "organizations": [
      "Bureau of Prisons"
    ],
    "locations": [
      "NYM"
    ],
    "dates": [
      "01/20/1953",
      "07/23/2019"
    ],
    "reference_numbers": [
      "76318-054",
      "DOJ-OGR-00026329"
    ]
  },
  "additional_notes": "The document contains redacted information marked as '(b)(6); (b)(7)(C)' and '(b)(7)(A)'. The document is a medical examination report for Jeffrey Epstein, conducted on July 23, 2019."
}