{
  "document_metadata": {
    "page_number": null,
    "document_number": "DOJ-OGR-00027497",
    "date": "10/20/2012",
    "document_type": "Admissibility Secondary Inspection",
    "has_handwriting": false,
    "has_stamps": false
  },
  "full_text": "UNCLASSIFIED // FOR OFFICIAL USE ONLY\nEPSTEIN JEFFREY EDWARD (b)(7)(E)\n10/20/2012 13:31:06\nAdmissibility Secondary Inspection (b)(7)(E)\n(b)(7)(E)\nCrossing Information\nSite: CBP-NEWARK, INTL AIR TERM B (b)(7)(E)\nDisposition: U.S. Citizen (USC)\nPort Crossing Date: 10/20/2012 13:31:06\nReferred Date: 10/20/2012 13:31:06\nAirline: OPEN SKIES (EC)\nComment: CITY OF BIRTH:NEW YORK COUNTRY OF BIRTH:USA\nCOMMENTS: (b)(7)(E)\nSubject\nLast Name: EPSTEIN\nFirst Name: JEFFREY EDWARD\nDate Of Birth: 01/20/1953\nIns Country: Serbia (b)(7)(E)\nGender: Male (b)(7)(E)\nRace: White (b)(7)(E)\nPassenger Document\nDocument Type: PASSPORT (b)(7)(E)\nDocument Issue Country: United States (US/USA)\nDocument Number: (b)(6);(b)(7)(C)\nReferral/Vehicle Information\nReferral Reason: (b)(7)(E)\nMiscellaneous Info\nType Association: \nDocument Type\nRemarks\nCITY OF BIRTH:NEW YORK COUNTRY OF BIRTH:USA (b)(7)(E)\nCOMMENTS:\nUNCLASSIFIED // FOR OFFICIAL USE ONLY\nDOJ-OGR-00027497",
  "text_blocks": [
    {
      "type": "printed",
      "content": "UNCLASSIFIED // FOR OFFICIAL USE ONLY",
      "position": "header"
    },
    {
      "type": "printed",
      "content": "EPSTEIN JEFFREY EDWARD (b)(7)(E)\n10/20/2012 13:31:06\nAdmissibility Secondary Inspection (b)(7)(E)",
      "position": "top"
    },
    {
      "type": "printed",
      "content": "(b)(7)(E)",
      "position": "margin"
    },
    {
      "type": "printed",
      "content": "Crossing Information\nSite: CBP-NEWARK, INTL AIR TERM B (b)(7)(E)\nDisposition: U.S. Citizen (USC)\nPort Crossing Date: 10/20/2012 13:31:06\nReferred Date: 10/20/2012 13:31:06\nAirline: OPEN SKIES (EC)\nComment: CITY OF BIRTH:NEW YORK COUNTRY OF BIRTH:USA\nCOMMENTS: (b)(7)(E)",
      "position": "middle"
    },
    {
      "type": "printed",
      "content": "Subject\nLast Name: EPSTEIN\nFirst Name: JEFFREY EDWARD\nDate Of Birth: 01/20/1953\nIns Country: Serbia (b)(7)(E)\nGender: Male (b)(7)(E)\nRace: White (b)(7)(E)",
      "position": "middle"
    },
    {
      "type": "printed",
      "content": "Passenger Document\nDocument Type: PASSPORT (b)(7)(E)\nDocument Issue Country: United States (US/USA)\nDocument Number: (b)(6);(b)(7)(C)",
      "position": "middle"
    },
    {
      "type": "printed",
      "content": "Referral/Vehicle Information\nReferral Reason: (b)(7)(E)",
      "position": "middle"
    },
    {
      "type": "printed",
      "content": "Miscellaneous Info\nType Association: \nDocument Type",
      "position": "middle"
    },
    {
      "type": "printed",
      "content": "Remarks\nCITY OF BIRTH:NEW YORK COUNTRY OF BIRTH:USA (b)(7)(E)\nCOMMENTS:",
      "position": "middle"
    },
    {
      "type": "printed",
      "content": "UNCLASSIFIED // FOR OFFICIAL USE ONLY",
      "position": "footer"
    },
    {
      "type": "printed",
      "content": "DOJ-OGR-00027497",
      "position": "footer"
    }
  ],
  "entities": {
    "people": [
      "JEFFREY EDWARD EPSTEIN"
    ],
    "organizations": [
      "CBP",
      "OPEN SKIES"
    ],
    "locations": [
      "NEWARK",
      "NEW YORK",
      "SERBIA",
      "USA",
      "UNITED STATES"
    ],
    "dates": [
      "10/20/2012",
      "01/20/1953"
    ],
    "reference_numbers": [
      "DOJ-OGR-00027497"
    ]
  },
  "additional_notes": "The document contains redactions marked as (b)(7)(E), (b)(6);(b)(7)(C), and other similar notations, indicating sensitive information has been withheld."
}