{
  "document_metadata": {
    "page_number": "3384",
    "document_number": "DOJ-OGR-00026973",
    "date": "08/19/2019",
    "document_type": "Log Entries By Event Date",
    "has_handwriting": false,
    "has_stamps": false
  },
  "full_text": "Page 3384\nDate: 08/19/2019\nTime: 10:15 AM\nFederal Bureau of Prisons TRUINTEL Log Entries By Event Date Sensitive But Unclassified\nEntered Date Alpha Code Level 1 Location Level 2 Location Level 3 Location Event Date Shift User Event Base Count 8/9/2019 8:27 AM NYM Housing Units Housing Units, General Population IN 8/9/2019 8:07 AM Day (b)(6): (b)(7)(C) Fire and Security Check - Summary Text: Completed. 8/9/2019 8:27 AM NYM Housing Units Housing Units, General Population IN 8/9/2019 8:07 AM Day Sensitive Information 8/9/2019 8:29 AM NYM Housing Units Housing Units, General Population IN 8/9/2019 8:29 AM Day Search (Areas) - Summary Text: Nothing To Report. 8/9/2019 8:29 AM NYM Housing Units Housing Units, General Population IN 8/9/2019 8:29 AM Day Search (Areas) - Summary Text: Common Area: GYM AREA. 8/9/2019 8:29 AM NYM Housing Units Housing Units, General Population IN 8/9/2019 8:29 AM Day Search (Areas) - Summary Text: Common Area: KITCHEN AREA. 8/9/2019 8:29 AM NYM Housing Units Housing Units, General Population IN 8/9/2019 8:29 AM Day Search (Areas) - Summary Text: Common Area: LAUNDRY ROOM. 8/9/2019 8:29 AM NYM Housing Units Housing Units, General Population IN 8/9/2019 8:29 AM Day Search (Areas) - Summary Text: Common Area: MPA AREA. 8/9/2019 8:29 AM NYM Housing Units Housing Units, General Population IN 8/9/2019 8:29 AM Day Search (Areas) - Summary Text: Common Area: SHOWER AREA. 8/9/2019 8:29 AM NYM Housing Units Housing Units, General Population IN 8/9/2019 8:29 AM Day Search (Areas) - Summary Text: Common Area: VISITING STRIP ROOM. 8/9/2019 8:29 AM NYM Housing Units Housing Units, General Population IN 8/9/2019 8:29 AM Day Bed Book Check - Summary Text: Completed. 8/9/2019 8:29 AM NYM Housing Units Housing Units, General Population IN 8/9/2019 8:29 AM Day Rounds (Officer) - Summary Text: Completed. 8/9/2019 8:40 AM NYM Housing Units Housing Units, General Population GN 8/9/2019 8:40 AM Day Rounds (Officer) User ID: (b)(6): (b)(7)(C) Page 912 of 1155 DOJ-OGR-00026973",
  "text_blocks": [
    {
      "type": "printed",
      "content": "Page 3384",
      "position": "header"
    },
    {
      "type": "printed",
      "content": "Date: 08/19/2019 Time: 10:15 AM Federal Bureau of Prisons TRUINTEL Log Entries By Event Date Sensitive But Unclassified",
      "position": "header"
    },
    {
      "type": "printed",
      "content": "Entered Date Alpha Code Level 1 Location Level 2 Location Level 3 Location Event Date Shift User Event Base Count",
      "position": "table header"
    },
    {
      "type": "printed",
      "content": "8/9/2019 8:27 AM NYM Housing Units Housing Units, General Population IN 8/9/2019 8:07 AM Day (b)(6): (b)(7)(C) Fire and Security Check - Summary Text: Completed.",
      "position": "table row"
    },
    {
      "type": "printed",
      "content": "8/9/2019 8:27 AM NYM Housing Units Housing Units, General Population IN 8/9/2019 8:07 AM Day Sensitive Information",
      "position": "table row"
    },
    {
      "type": "printed",
      "content": "8/9/2019 8:29 AM NYM Housing Units Housing Units, General Population IN 8/9/2019 8:29 AM Day Search (Areas) - Summary Text: Nothing To Report.",
      "position": "table row"
    },
    {
      "type": "printed",
      "content": "8/9/2019 8:29 AM NYM Housing Units Housing Units, General Population IN 8/9/2019 8:29 AM Day Search (Areas) - Summary Text: Common Area: GYM AREA.",
      "position": "table row"
    },
    {
      "type": "printed",
      "content": "8/9/2019 8:29 AM NYM Housing Units Housing Units, General Population IN 8/9/2019 8:29 AM Day Search (Areas) - Summary Text: Common Area: KITCHEN AREA.",
      "position": "table row"
    },
    {
      "type": "printed",
      "content": "8/9/2019 8:29 AM NYM Housing Units Housing Units, General Population IN 8/9/2019 8:29 AM Day Search (Areas) - Summary Text: Common Area: LAUNDRY ROOM.",
      "position": "table row"
    },
    {
      "type": "printed",
      "content": "8/9/2019 8:29 AM NYM Housing Units Housing Units, General Population IN 8/9/2019 8:29 AM Day Search (Areas) - Summary Text: Common Area: MPA AREA.",
      "position": "table row"
    },
    {
      "type": "printed",
      "content": "8/9/2019 8:29 AM NYM Housing Units Housing Units, General Population IN 8/9/2019 8:29 AM Day Search (Areas) - Summary Text: Common Area: SHOWER AREA.",
      "position": "table row"
    },
    {
      "type": "printed",
      "content": "8/9/2019 8:29 AM NYM Housing Units Housing Units, General Population IN 8/9/2019 8:29 AM Day Search (Areas) - Summary Text: Common Area: VISITING STRIP ROOM.",
      "position": "table row"
    },
    {
      "type": "printed",
      "content": "8/9/2019 8:29 AM NYM Housing Units Housing Units, General Population IN 8/9/2019 8:29 AM Day Bed Book Check - Summary Text: Completed.",
      "position": "table row"
    },
    {
      "type": "printed",
      "content": "8/9/2019 8:29 AM NYM Housing Units Housing Units, General Population IN 8/9/2019 8:29 AM Day Rounds (Officer) - Summary Text: Completed.",
      "position": "table row"
    },
    {
      "type": "printed",
      "content": "8/9/2019 8:40 AM NYM Housing Units Housing Units, General Population GN 8/9/2019 8:40 AM Day Rounds (Officer)",
      "position": "table row"
    },
    {
      "type": "printed",
      "content": "User ID: (b)(6): (b)(7)(C)",
      "position": "footer"
    },
    {
      "type": "printed",
      "content": "Page 912 of 1155",
      "position": "footer"
    },
    {
      "type": "printed",
      "content": "DOJ-OGR-00026973",
      "position": "footer"
    }
  ],
  "entities": {
    "people": [],
    "organizations": [
      "Federal Bureau of Prisons"
    ],
    "locations": [
      "Housing Units"
    ],
    "dates": [
      "08/19/2019",
      "8/9/2019"
    ],
    "reference_numbers": [
      "DOJ-OGR-00026973"
    ]
  },
  "additional_notes": "The document appears to be a log entry report from the Federal Bureau of Prisons, detailing various events and activities that occurred on August 9, 2019. The report includes information such as the date, time, location, and type of event, as well as the user who entered the information. Some of the events listed include fire and security checks, searches, and rounds conducted by officers. The document also includes redactions, with certain information blacked out or marked as '(b)(6): (b)(7)(C)'."
}