{
  "document_metadata": {
    "page_number": "3058",
    "document_number": "BP-A0971",
    "date": "AUG 11",
    "document_type": "CHAIN OF CUSTODY LOG",
    "has_handwriting": true,
    "has_stamps": false
  },
  "full_text": "Page 3058\nBP-A0971\nAUG 11\nU.S. DEPARTMENT OF JUSTICE\nFEDERAL BUREAU OF PRISONS\nCHAIN OF CUSTODY LOG CDFRM\nCHAIN OF CUSTODY LOG\n(Enclose with/attach to evidence)\nECN #:\nITEM #:\nCASE ID NUMBER:\nSUSPECT (If Known):\nEpstein, Jeffrey Reg. No.\n76318-054\nDESCRIPTION OF ITEM:\nSpecial Housing Unit 30 Minute Rounds Sheets for 8/10/19\nDATE/TIME ITEM FOUND:\n8/10/19 8:10 am\nLOCATION:\nMCC Special Housing Unit\nSIGNATURE OF PERSON RECOVERING EVIDENCE:\n(b)(6); (b)(7)(C)\nPRINTED NAME:\n(b)(6); (b)(7)(C)\nEVIDENCE PLACED IN OVERNIGHT DROP-BOX BY: (printed name)\nDate & Time:\nWitness: (printed name)\nEVIDENCE RECOVERED FROM OVERNIGHT DROP BOX BY: (printed name)\nDate & Time:\nWitness: (printed name)\nEVIDENCE PLACED IN SAFE FROM DROP BOX BY: (printed name)\nDate & Time:\nWitness: (printed name)\nEVIDENCE PLACED DIRECTLY IN EVIDENCE SAFE BY: (printed name)\nDate & Time:\nWitness: (printed name)\nDISPOSITION:\n/ X /\nHold as evidence\n/ /\nReturn to finder\n/ /\nReturn to owner\n/ /\nLab Analysis\n/ /\nOther\n/ /\nDestroy immediately\nFBI\nREMARKS (condition of evidence)\nCHAIN OF CUSTODY\nEVIDENCE RELEASED BY\nDATE/TIME\nDESTINATION\nEVIDENCE RELEASED TO\n(b)(6); (b)(7)(C)\n8/10/19 8:11am\nSIS\n(b)(6); (b)(7)(C)\n(b)(6); (b)(7)(C)\n9/13/19 4:31pm\nDOJ-OIG\nATTACH TO EVIDENCE\nDOJ-OGR-00026698",
  "text_blocks": [
    {
      "type": "printed",
      "content": "CHAIN OF CUSTODY LOG CDFRM",
      "position": "header"
    },
    {
      "type": "printed",
      "content": "U.S. DEPARTMENT OF JUSTICE\nFEDERAL BUREAU OF PRISONS",
      "position": "header"
    },
    {
      "type": "printed",
      "content": "CHAIN OF CUSTODY LOG\n(Enclose with/attach to evidence)",
      "position": "header"
    },
    {
      "type": "printed",
      "content": "ECN #:\nITEM #:\nCASE ID NUMBER:\nSUSPECT (If Known):\nDESCRIPTION OF ITEM:\nDATE/TIME ITEM FOUND:\nLOCATION:\nSIGNATURE OF PERSON RECOVERING EVIDENCE:\nPRINTED NAME:",
      "position": "main"
    },
    {
      "type": "handwritten",
      "content": "Epstein, Jeffrey Reg. No.\n76318-054\nSpecial Housing Unit 30 Minute Rounds Sheets for 8/10/19\n8/10/19 8:10 am\nMCC Special Housing Unit",
      "position": "main"
    },
    {
      "type": "handwritten",
      "content": "(b)(6); (b)(7)(C)\n(b)(6); (b)(7)(C)",
      "position": "main"
    },
    {
      "type": "printed",
      "content": "EVIDENCE PLACED IN OVERNIGHT DROP-BOX BY: (printed name)\nDate & Time:\nWitness: (printed name)\nEVIDENCE RECOVERED FROM OVERNIGHT DROP BOX BY: (printed name)\nDate & Time:\nWitness: (printed name)\nEVIDENCE PLACED IN SAFE FROM DROP BOX BY: (printed name)\nDate & Time:\nWitness: (printed name)\nEVIDENCE PLACED DIRECTLY IN EVIDENCE SAFE BY: (printed name)\nDate & Time:\nWitness: (printed name)",
      "position": "main"
    },
    {
      "type": "printed",
      "content": "DISPOSITION:\n/ X /\nHold as evidence\n/ /\nReturn to finder\n/ /\nReturn to owner\n/ /\nLab Analysis\n/ /\nOther\n/ /\nDestroy immediately\nFBI",
      "position": "main"
    },
    {
      "type": "printed",
      "content": "REMARKS (condition of evidence)",
      "position": "main"
    },
    {
      "type": "printed",
      "content": "CHAIN OF CUSTODY",
      "position": "main"
    },
    {
      "type": "handwritten",
      "content": "(b)(6); (b)(7)(C)\n8/10/19 8:11am\nSIS\n(b)(6); (b)(7)(C)\n(b)(6); (b)(7)(C)\n9/13/19 4:31pm\nDOJ-OIG",
      "position": "main"
    }
  ],
  "entities": {
    "people": [
      "Jeffrey Epstein"
    ],
    "organizations": [
      "U.S. DEPARTMENT OF JUSTICE",
      "FEDERAL BUREAU OF PRISONS",
      "FBI",
      "DOJ-OIG"
    ],
    "locations": [
      "MCC Special Housing Unit"
    ],
    "dates": [
      "8/10/19",
      "9/13/19",
      "AUG 11"
    ],
    "reference_numbers": [
      "BP-A0971",
      "76318-054",
      "DOJ-OGR-00026698"
    ]
  },
  "additional_notes": "The document contains redactions marked as (b)(6); (b)(7)(C). The document is a Chain of Custody Log used by the Federal Bureau of Prisons."
}