{
  "document_metadata": {
    "page_number": "2947",
    "document_number": "DOJ-OGR-00026603",
    "date": "11/1/19",
    "document_type": "Official Out Count",
    "has_handwriting": true,
    "has_stamps": false
  },
  "full_text": "Page 2947\nMETROPOLITAN CORRECTIONAL CENTER\nNEW YORK, NY\nOFFICIAL OUT COUNT\nDATE: 11/1/19 COUNT TIME: 10 am\nFROM: (b)(6); (b)(7)(C) (Staff Member Dis Count)\nLOCATION: Hosp\nAPPROVED: (Officer Dis Count)\nREG # NAME UNIT REG # NAME UNIT\n(b)(6); (b)(7)(C) EU 13.\n(b)(6); (b)(7)(C) KS 14.\n4. 16.\n5. 17.\n6. 18.\n7. 19.\n8. 20.\n9. 21.\n10. 22.\n11. 23.\n12. 24.\nOUT-COUNT BY UNIT\nB-A C-A E-N E-S G-N G-S H-A\nI-N K-N K-S R-A Z-A Z-B\nTotal Out-Counted: 2\nThis form must be submitted to the Counts and Assignments Officer FORTY-FIVE MINUTES PRIOR to the affected count.\nPrepare this form in ink. Group the inmates according to their respective housing units. This form is to be used only as an Out-Count. No other form will be accepted in lieu of the Out-Count Form.\nDOJ-OGR-00026603",
  "text_blocks": [
    {
      "type": "printed",
      "content": "METROPOLITAN CORRECTIONAL CENTER\nNEW YORK, NY\nOFFICIAL OUT COUNT",
      "position": "header"
    },
    {
      "type": "handwritten",
      "content": "11/1/19",
      "position": "middle"
    },
    {
      "type": "handwritten",
      "content": "10 am",
      "position": "middle"
    },
    {
      "type": "handwritten",
      "content": "Hosp",
      "position": "middle"
    },
    {
      "type": "printed",
      "content": "REG # NAME UNIT REG # NAME UNIT",
      "position": "middle"
    },
    {
      "type": "handwritten",
      "content": "(b)(6); (b)(7)(C) EU",
      "position": "middle"
    },
    {
      "type": "handwritten",
      "content": "(b)(6); (b)(7)(C) KS",
      "position": "middle"
    },
    {
      "type": "printed",
      "content": "OUT-COUNT BY UNIT",
      "position": "middle"
    },
    {
      "type": "handwritten",
      "content": "1",
      "position": "middle"
    },
    {
      "type": "handwritten",
      "content": "1",
      "position": "middle"
    },
    {
      "type": "handwritten",
      "content": "2",
      "position": "middle"
    },
    {
      "type": "printed",
      "content": "This form must be submitted to the Counts and Assignments Officer FORTY-FIVE MINUTES PRIOR to the affected count.\nPrepare this form in ink. Group the inmates according to their respective housing units. This form is to be used only as an Out-Count. No other form will be accepted in lieu of the Out-Count Form.",
      "position": "footer"
    }
  ],
  "entities": {
    "people": [],
    "organizations": [
      "Metropolitan Correctional Center"
    ],
    "locations": [
      "New York, NY"
    ],
    "dates": [
      "11/1/19"
    ],
    "reference_numbers": [
      "DOJ-OGR-00026603",
      "(b)(6); (b)(7)(C)"
    ]
  },
  "additional_notes": "The document contains redactions marked as (b)(6); (b)(7)(C), indicating sensitive information has been removed for privacy or security reasons."
}