{
  "document_metadata": {
    "page_number": "2385",
    "document_number": "DOJ-OGR-00026062",
    "date": "10/22/2019",
    "document_type": "Internal Communication",
    "has_handwriting": false,
    "has_stamps": false
  },
  "full_text": "Page 2385\n\nQuestion:\n\nIn wake of the Epstein death, I understand that institutions across the bureau are designating specific officers to regularly monitor surveillance video in segregated housing units and other locations where inmates are at some risk for suicide. Is there someone who may be able to elaborate on this effort?\n\nProposed Response:\n\n(b)(5)\n\n(b)(6); (b)(7)(C) (b)(6); (b)(7)(C) 10/22/2019 12:35 PM >>>\n\nThe reporter now says his deadline is 3 pm, so I'll need to take this to IPPA leadership as soon as you return and review this.\n\nHere are two follow-up questions I have for you, following our call, to help finalize my draft answer below.\n\n(b)(5)\n\nPage 14402\nDOJ-OGR-00026062",
  "text_blocks": [
    {
      "type": "printed",
      "content": "Page 2385",
      "position": "header"
    },
    {
      "type": "printed",
      "content": "Question:",
      "position": "top"
    },
    {
      "type": "printed",
      "content": "In wake of the Epstein death, I understand that institutions across the bureau are designating specific officers to regularly monitor surveillance video in segregated housing units and other locations where inmates are at some risk for suicide. Is there someone who may be able to elaborate on this effort?",
      "position": "top"
    },
    {
      "type": "printed",
      "content": "Proposed Response:",
      "position": "middle"
    },
    {
      "type": "printed",
      "content": "(b)(5)",
      "position": "middle"
    },
    {
      "type": "printed",
      "content": "(b)(6); (b)(7)(C) (b)(6); (b)(7)(C) 10/22/2019 12:35 PM >>>",
      "position": "middle"
    },
    {
      "type": "printed",
      "content": "The reporter now says his deadline is 3 pm, so I'll need to take this to IPPA leadership as soon as you return and review this.",
      "position": "middle"
    },
    {
      "type": "printed",
      "content": "Here are two follow-up questions I have for you, following our call, to help finalize my draft answer below.",
      "position": "middle"
    },
    {
      "type": "printed",
      "content": "(b)(5)",
      "position": "bottom"
    },
    {
      "type": "printed",
      "content": "Page 14402",
      "position": "footer"
    },
    {
      "type": "printed",
      "content": "DOJ-OGR-00026062",
      "position": "footer"
    }
  ],
  "entities": {
    "people": [
      "Epstein"
    ],
    "organizations": [
      "IPPA",
      "DOJ"
    ],
    "locations": [],
    "dates": [
      "10/22/2019"
    ],
    "reference_numbers": [
      "DOJ-OGR-00026062"
    ]
  },
  "additional_notes": "The document appears to be a redacted internal communication within the Department of Justice (DOJ) regarding the Epstein death and subsequent actions taken by the bureau. The redactions are indicated by (b)(5), (b)(6), and (b)(7)(C), which are standard FOIA exemption markers."
}