{
  "document_metadata": {
    "page_number": "1",
    "document_number": "8224560609",
    "date": "12/04/2019",
    "document_type": "TECS - Advance Traveler Information - Traveler List",
    "has_handwriting": false,
    "has_stamps": false
  },
  "full_text": "U.S. Customs and Border Protection U.S. Department of Homeland Security TECS - Advance Traveler Information - Traveler List 12/04/2019 11:16 BOT Generated By: (b)(6);(b)(7)(C) Page 1 of 1 SUMMARY for Manifest ID: 8224560609 Mode of Travel Tail # I/O Private Air N212JE I Arrival Date Arrival Time Arrival Location Departure Date Departure Location 04/02/2019 20:01 KTEB 04/02/2019 LFPB List of Travelers Conf. Traveler's Name (L, F, M) DOB Hit Doc Type Doc # Country Gender Status ESTA Status EVUS Status Error R EPSTEIN, JEFFREY, EDWARD 01/20/1953 (b)(7)(E) P 566672615 USA M PAX NOT REQUIRED C (b)(6)&(b)(7)(C) (b)(6)&(b)(7)(C) P (b)(6)&(b)(7)(C) USA M CRW NOT REQUIRED C (b)(6)&(b)(7)(C) (b)(6)&(b)(7)(C) P (b)(6)&(b)(7)(C) USA M CR1 NOT REQUIRED Showing 3 record(s) out of 3 record(s) received. For Official Use Only / Law Enforcement Sensitive DOJ-OGR-00027400",
  "text_blocks": [
    {
      "type": "printed",
      "content": "U.S. Customs and Border Protection U.S. Department of Homeland Security TECS - Advance Traveler Information - Traveler List",
      "position": "header"
    },
    {
      "type": "printed",
      "content": "SUMMARY for Manifest ID: 8224560609",
      "position": "header"
    },
    {
      "type": "printed",
      "content": "List of Travelers",
      "position": "header"
    },
    {
      "type": "printed",
      "content": "Showing 3 record(s) out of 3 record(s) received.",
      "position": "footer"
    },
    {
      "type": "printed",
      "content": "For Official Use Only / Law Enforcement Sensitive",
      "position": "footer"
    }
  ],
  "entities": {
    "people": [
      "JEFFREY EDWARD EPSTEIN"
    ],
    "organizations": [
      "U.S. Customs and Border Protection",
      "U.S. Department of Homeland Security"
    ],
    "locations": [
      "KTEB",
      "LFPB",
      "USA"
    ],
    "dates": [
      "12/04/2019",
      "04/02/2019",
      "01/20/1953"
    ],
    "reference_numbers": [
      "8224560609",
      "N212JE",
      "566672615",
      "DOJ-OGR-00027400"
    ]
  },
  "additional_notes": "The document contains redacted information marked as (b)(6);(b)(7)(C) and (b)(7)(E). The document is labeled 'For Official Use Only / Law Enforcement Sensitive'."
}