{
  "document_metadata": {
    "page_number": "1771",
    "document_number": "DOJ-OGR-00025794",
    "date": "12/6/2019",
    "document_type": "email",
    "has_handwriting": false,
    "has_stamps": false
  },
  "full_text": "Page 1771\n\ncall me in the warden's office.\n\nCharisma Edge\nAssociate Warden\nMCC New York\n150 Park Row\nNew York, NY 10007\n646-836-6300 ext\n(b)(6); (b)(7)(C)\n(b)(6);\nNYM/AW-Programs--@bop.gov\n\n>> (b)(6); (b)(7)(C) (b)(6); (b)(7)(C)@bop.gov> 12/6/2019 3:22 PM >>>\n\nSent from my Verizon, Samsung Galaxy smartphone\n\n------ Original message -------\nFrom: (b)(6); (b)(7)(C) (b)(6); (b)(7)(C)@bop.gov>\nDate: 12/6/19 3:05 PM (GMT-5:00)\nTo: (b)(6); (b)(7)(C) (b)(6); (b)(7)(C)@bop.gov>\n(b)(6); (b)(7)(C) (b)(6); (b)(7)(C)@bop.gov>\nSubject: Media inquiry - due today - NY Daily News - re: conditions at MCC NY post-Epstein\n\n>>> (b)(6); (b)(7)(C) 12/06/2019 15:05 >>>\n(b)(6);\n(b)(7)(C)\n\nHere is a very rough draft for you and your staff to enhance if possible very quickly today. I can then run by (b)(6);\n(b)(7)(C) and my boss before I answer the reporter. Feel free to te\nThanks,\n(b)(6);\n(b)(7)(C)\n\nReporter:\n(b)(6); (b)(7)(C) NY DAILY NEWS\n\nQuestions & Proposed Responses:\n\nHello, I'm working on a story about morale at MCC in Manhattan in the wake of charges against (b)(6); (b)(7)(C) I've spoken to an AFGE union official and\n\nThe thrust of the story is that morale has plummeted at the facility in the wake of the falsification of documents charges. Morale was already bad because of staffing issues.\n\n(1) Has any money been allocated for improving MCC as a facility since Epstein's death?\n(b)(5)\n\n(2) Has there been a hiring surge since Epstein's suicide?\n(b)(5)\n(b)(6);\n(b)(7)(C)\n\n(3) Any changes in BOP policies following Epstein's suicide?\n(b)(5)\n(b)(6);\n(b)(7)(C)\n\n(4) Is it correct that (b)(6); (b)(7)(C) were responsible for roughly 50 to 70 inmates the night of the suicide?\n(b)(5)\n\n(5) What is the attrition rate for BOP correctional officers? What's the average length of time a person stays in the job? (NYC-area would be best if it's available.)\n(b)(5)\n(b)(6);\n\n(6) Can you share anything supervisors at MCC have told the rank and file in the wake of these charges? What's the message to overworked, disgruntled correctional office\n(b)(5)\n\n(b)(6); (b)(7)(C)\nPublic Information Office\nFederal Bureau of Prisons\n(202) 353\n(b)(6); (b)(7)(C)\n\nPage 9373\nDOJ-OGR-00025794",
  "text_blocks": [
    {
      "type": "printed",
      "content": "Page 1771",
      "position": "header"
    },
    {
      "type": "printed",
      "content": "call me in the warden's office.",
      "position": "top"
    },
    {
      "type": "printed",
      "content": "Charisma Edge\nAssociate Warden\nMCC New York\n150 Park Row\nNew York, NY 10007\n646-836-6300 ext\n(b)(6); (b)(7)(C)\n(b)(6);\nNYM/AW-Programs--@bop.gov",
      "position": "top"
    },
    {
      "type": "printed",
      "content": ">> (b)(6); (b)(7)(C) (b)(6); (b)(7)(C)@bop.gov> 12/6/2019 3:22 PM >>>",
      "position": "top"
    },
    {
      "type": "printed",
      "content": "Sent from my Verizon, Samsung Galaxy smartphone",
      "position": "top"
    },
    {
      "type": "printed",
      "content": "------ Original message -------\nFrom: (b)(6); (b)(7)(C) (b)(6); (b)(7)(C)@bop.gov>\nDate: 12/6/19 3:05 PM (GMT-5:00)\nTo: (b)(6); (b)(7)(C) (b)(6); (b)(7)(C)@bop.gov>\n(b)(6); (b)(7)(C) (b)(6); (b)(7)(C)@bop.gov>\nSubject: Media inquiry - due today - NY Daily News - re: conditions at MCC NY post-Epstein",
      "position": "middle"
    },
    {
      "type": "printed",
      "content": ">>> (b)(6); (b)(7)(C) 12/06/2019 15:05 >>>\n(b)(6);\n(b)(7)(C)",
      "position": "middle"
    },
    {
      "type": "printed",
      "content": "Here is a very rough draft for you and your staff to enhance if possible very quickly today. I can then run by (b)(6);\n(b)(7)(C) and my boss before I answer the reporter. Feel free to te\nThanks,\n(b)(6);\n(b)(7)(C)",
      "position": "middle"
    },
    {
      "type": "printed",
      "content": "Reporter:\n(b)(6); (b)(7)(C) NY DAILY NEWS",
      "position": "middle"
    },
    {
      "type": "printed",
      "content": "Questions & Proposed Responses:",
      "position": "middle"
    },
    {
      "type": "printed",
      "content": "Hello, I'm working on a story about morale at MCC in Manhattan in the wake of charges against (b)(6); (b)(7)(C) I've spoken to an AFGE union official and",
      "position": "middle"
    },
    {
      "type": "printed",
      "content": "The thrust of the story is that morale has plummeted at the facility in the wake of the falsification of documents charges. Morale was already bad because of staffing issues.",
      "position": "middle"
    },
    {
      "type": "printed",
      "content": "(1) Has any money been allocated for improving MCC as a facility since Epstein's death?\n(b)(5)",
      "position": "middle"
    },
    {
      "type": "printed",
      "content": "(2) Has there been a hiring surge since Epstein's suicide?\n(b)(5)\n(b)(6);\n(b)(7)(C)",
      "position": "middle"
    },
    {
      "type": "printed",
      "content": "(3) Any changes in BOP policies following Epstein's suicide?\n(b)(5)\n(b)(6);\n(b)(7)(C)",
      "position": "middle"
    },
    {
      "type": "printed",
      "content": "(4) Is it correct that (b)(6); (b)(7)(C) were responsible for roughly 50 to 70 inmates the night of the suicide?\n(b)(5)",
      "position": "middle"
    },
    {
      "type": "printed",
      "content": "(5) What is the attrition rate for BOP correctional officers? What's the average length of time a person stays in the job? (NYC-area would be best if it's available.)\n(b)(5)\n(b)(6);\n",
      "position": "middle"
    },
    {
      "type": "printed",
      "content": "(6) Can you share anything supervisors at MCC have told the rank and file in the wake of these charges? What's the message to overworked, disgruntled correctional office\n(b)(5)",
      "position": "middle"
    },
    {
      "type": "printed",
      "content": "(b)(6); (b)(7)(C)\nPublic Information Office\nFederal Bureau of Prisons\n(202) 353\n(b)(6); (b)(7)(C)",
      "position": "bottom"
    },
    {
      "type": "printed",
      "content": "Page 9373\nDOJ-OGR-00025794",
      "position": "footer"
    }
  ],
  "entities": {
    "people": [
      "Charisma Edge",
      "Epstein"
    ],
    "organizations": [
      "MCC New York",
      "NY Daily News",
      "AFGE",
      "Federal Bureau of Prisons"
    ],
    "locations": [
      "New York",
      "Manhattan"
    ],
    "dates": [
      "12/6/2019"
    ],
    "reference_numbers": [
      "DOJ-OGR-00025794"
    ]
  },
  "additional_notes": "The document appears to be a redacted email chain with sensitive information removed. The content is related to a media inquiry about conditions at MCC New York post-Epstein's death."
}