{
  "document_metadata": {
    "page_number": "2696",
    "document_number": "BP-A0292",
    "date": "APR 16",
    "document_type": "SPECIAL HOUSING UNIT RECORD",
    "has_handwriting": false,
    "has_stamps": false
  },
  "full_text": "Page 2696\n\nBP-A0292\nAPR 16\n\nSPECIAL HOUSING UNIT RECORD\n\nU.S. DEPARTMENT OF JUSTICE\nFEDERAL BUREAU OF PRISONS\n\nNEW YORK MCC\n(Institution)\n\nInmate Name: EPSTEIN, JEFFREY EDWARD\nReg. No. 76318-054\nTeam/caseworker: UNASSIGNED ADMISSION\nA&O (b)(6); (b)(7)(C)\nUNIT MANAGER (b)(6); (b)(7)(C)\nCell: A&O\nRegular Unit:\nViolation or Reason: N/A\nDate Rec'd: N/A\nTime Rec'd: N/A\nAdmittance Authorized: N/A\nDate Rel.: N/A\nTime Rel.: N/A\nPertinent Information: N/A\nSeparation Information: N/A\nSpecial Housing Unit Cell Number: Z05-124LAD\nInmate Is In: N/A\nDS: N/A\nAD Status\nIs Inmate on Medication: N/A\nMedical Department Notified: N/A\n\nDate Shift Meals SH Exercise Out of cell time (Total min/hrs) Comments Medical Staff Sign OIC Signature\nB D S\n07-14-2019 Morn Y N No\n07-14-2019 Day Y N No\n07-14-2019 Eve Y N No (b)(6); (b)(7)(C)\n07-15-2019 Morn Y Y No 01:00 See 2nd page\n07-15-2019 Day Y Y\n07-15-2019 Eve Y N\n07-16-2019 Morn Y Y\n07-16-2019 Day Y See 2nd page\n07-16-2019 Eve Y Y No\n07-17-2019 Morn Y Y Ref 01:00 See 2nd page\n07-17-2019 Day Y Y\n07-17-2019 Eve Y Y No\n07-18-2019 Morn Y N Ref\n07-18-2019 Day Y N See 2nd page\n07-18-2019 Eve Y Y No\n07-19-2019 Morn Y Y Y 00:15 See 2nd page\n07-19-2019 Day Y Y\n07-19-2019 Eve Y Y\n07-20-2019 Morn Y Y\n07-20-2019 Day Y N\n07-20-2019 Eve Y N N\n\nEXPLANATORY NOTES: Pertinent Info: I.e., Epileptic; Diabetic; Suicidal; Assaultive; etc. Meals/SH: Shower - Yes (Y); No (N); Refused (R) Out-of-Cell Time: (LL) Law Library,(LV) Legal Visit, (U) Unit Team, (P) Psychology, (E) Education, (H) Haircut, (C) Chapel, (R) Recreation, (X) Property Issue, (V) Visit, (M) Medical, (C) Court, (O) Other - Yes (Y) if applicable / Enter Actual Time Period Start and End (i.e., 0930 - 1030 hrs) in Out of Cell Time Block.\n\nMedical: Medical providers will sign the segregation log each shift and the record sheet each time the inmate is seen by a medical provider. At a minimum, the record sheet must be signed at least once each day by the medical provider. Comments: i.e., Conduct, Attitude, etc. Additional comments on reverse side must include date, signature, and title. OIC Signature: OIC must sign all record sheets each shift. (OIC - Unit Officer)\n\nPDF\nPrescribed by P5270 This form replaces BP-292(52) dated AUG 2011.\n\nDOJ-OGR-00026352",
  "text_blocks": [
    {
      "type": "printed",
      "content": "SPECIAL HOUSING UNIT RECORD",
      "position": "header"
    },
    {
      "type": "printed",
      "content": "U.S. DEPARTMENT OF JUSTICE\nFEDERAL BUREAU OF PRISONS",
      "position": "header"
    },
    {
      "type": "printed",
      "content": "NEW YORK MCC\n(Institution)",
      "position": "header"
    },
    {
      "type": "printed",
      "content": "Inmate Name: EPSTEIN, JEFFREY EDWARD\nReg. No. 76318-054",
      "position": "top"
    },
    {
      "type": "printed",
      "content": "Team/caseworker: UNASSIGNED ADMISSION\nA&O (b)(6); (b)(7)(C)\nUNIT MANAGER (b)(6); (b)(7)(C)\nCell: A&O\nRegular Unit:",
      "position": "top"
    },
    {
      "type": "printed",
      "content": "Violation or Reason: N/A\nDate Rec'd: N/A\nTime Rec'd: N/A",
      "position": "top"
    },
    {
      "type": "printed",
      "content": "Admittance Authorized: N/A\nDate Rel.: N/A\nTime Rel.: N/A",
      "position": "top"
    },
    {
      "type": "printed",
      "content": "Pertinent Information: N/A\nSeparation Information: N/A",
      "position": "top"
    },
    {
      "type": "printed",
      "content": "Special Housing Unit Cell Number: Z05-124LAD\nInmate Is In: N/A\nDS: N/A\nAD Status",
      "position": "top"
    },
    {
      "type": "printed",
      "content": "Is Inmate on Medication: N/A\nMedical Department Notified: N/A",
      "position": "top"
    },
    {
      "type": "printed",
      "content": "Date Shift Meals SH Exercise Out of cell time (Total min/hrs) Comments Medical Staff Sign OIC Signature",
      "position": "middle"
    },
    {
      "type": "printed",
      "content": "EXPLANATORY NOTES: Pertinent Info: I.e., Epileptic; Diabetic; Suicidal; Assaultive; etc. Meals/SH: Shower - Yes (Y); No (N); Refused (R) Out-of-Cell Time: (LL) Law Library,(LV) Legal Visit, (U) Unit Team, (P) Psychology, (E) Education, (H) Haircut, (C) Chapel, (R) Recreation, (X) Property Issue, (V) Visit, (M) Medical, (C) Court, (O) Other - Yes (Y) if applicable / Enter Actual Time Period Start and End (i.e., 0930 - 1030 hrs) in Out of Cell Time Block.",
      "position": "footer"
    },
    {
      "type": "printed",
      "content": "Medical: Medical providers will sign the segregation log each shift and the record sheet each time the inmate is seen by a medical provider. At a minimum, the record sheet must be signed at least once each day by the medical provider. Comments: i.e., Conduct, Attitude, etc. Additional comments on reverse side must include date, signature, and title. OIC Signature: OIC must sign all record sheets each shift. (OIC - Unit Officer)",
      "position": "footer"
    },
    {
      "type": "printed",
      "content": "PDF\nPrescribed by P5270 This form replaces BP-292(52) dated AUG 2011.",
      "position": "footer"
    }
  ],
  "entities": {
    "people": [
      "JEFFREY EDWARD EPSTEIN"
    ],
    "organizations": [
      "U.S. DEPARTMENT OF JUSTICE",
      "FEDERAL BUREAU OF PRISONS"
    ],
    "locations": [
      "NEW YORK MCC"
    ],
    "dates": [
      "07-14-2019",
      "07-15-2019",
      "07-16-2019",
      "07-17-2019",
      "07-18-2019",
      "07-19-2019",
      "07-20-2019",
      "APR 16",
      "AUG 2011"
    ],
    "reference_numbers": [
      "BP-A0292",
      "76318-054",
      "Z05-124LAD",
      "P5270",
      "BP-292(52)",
      "DOJ-OGR-00026352"
    ]
  },
  "additional_notes": "The document appears to be a scanned copy of a Special Housing Unit Record form used by the Federal Bureau of Prisons. The form contains information about an inmate named Jeffrey Edward Epstein, including his housing unit, meal times, and medical information. The document has some redacted information, indicated by (b)(6); (b)(7)(C)."
}