{
  "document_metadata": {
    "page_number": "1319",
    "document_number": "DOJ-OGR-00025502",
    "date": "11/14/2019",
    "document_type": "Email",
    "has_handwriting": false,
    "has_stamps": false
  },
  "full_text": "Page 1319 Network Name: (b)(6); (b)(7)(C) Preferred Name: ----------------- Network Job Title: UNIT MANAGER Contact Information Email Address: (b)(6); (b)(7)(C) @BOP.GOV Office Number: (718) 840-(b)(6); (b)(7)(C) Cell Number: ---------------- Fax Number: ---------------- Location Information Facility Home Page All Staff At This Facility Create and Print Labels Map and Directions Warden's Office Staff E-Mail Facility Physical Location: MDC BROOKLYN, NY Loc Start Date: 04-15-2007 (MCK) Address: 80 29TH STREET City: BROOKLYN State: NY Zip: 11232 >>> (b)(6); (b)(7)(C) @FOXNEWS.COM> 11/14/2019 3:45 PM >>> (b)(6); (b)(7)(C) Public Information Office Federal Bureau of Prisons (202) 353 (b)(6); (b)(7)(C) Hi there can you confirm whether case manager (b)(6); (b)(7)(C) is still working with SHU inmates at MCC or has he been transferred to a different caseload, unit or facility after Jeffrey Epstein death? Also can you confirm the status of Assistant Warden Shirley Skipper Scott? Thank you (b)(6); (b)(7)(C) 786863 (b)(6); (b)(7)(C) Get Outlook for iOS This message and its attachments may contain legally privileged or confidential information. It is intended solely for the named addressee. If you are not the addressee indicated in this message (or responsible for delivery of the message to the addressee), you may not copy or deliver this message or its attachments to anyone. Rather, you should permanently delete this message and its attachments and kindly notify the sender by reply e-mail. Any content of this message and its attachments that does not relate to the official Page 4895 DOJ-OGR-00025502",
  "text_blocks": [
    {
      "type": "printed",
      "content": "Network Name: (b)(6); (b)(7)(C) Preferred Name: ----------------- Network Job Title: UNIT MANAGER",
      "position": "top"
    },
    {
      "type": "printed",
      "content": "Contact Information Email Address: (b)(6); (b)(7)(C) @BOP.GOV Office Number: (718) 840-(b)(6); (b)(7)(C) Cell Number: ---------------- Fax Number: ----------------",
      "position": "top"
    },
    {
      "type": "printed",
      "content": "Location Information Facility Home Page All Staff At This Facility Create and Print Labels Map and Directions Warden's Office Staff E-Mail Facility Physical Location: MDC BROOKLYN, NY Loc Start Date: 04-15-2007 (MCK) Address: 80 29TH STREET City: BROOKLYN State: NY Zip: 11232",
      "position": "middle"
    },
    {
      "type": "printed",
      "content": ">>> (b)(6); (b)(7)(C) @FOXNEWS.COM> 11/14/2019 3:45 PM >>> (b)(6); (b)(7)(C) Public Information Office Federal Bureau of Prisons (202) 353 (b)(6); (b)(7)(C)",
      "position": "middle"
    },
    {
      "type": "printed",
      "content": "Hi there can you confirm whether case manager (b)(6); (b)(7)(C) is still working with SHU inmates at MCC or has he been transferred to a different caseload, unit or facility after Jeffrey Epstein death? Also can you confirm the status of Assistant Warden Shirley Skipper Scott?",
      "position": "middle"
    },
    {
      "type": "printed",
      "content": "Thank you (b)(6); (b)(7)(C) 786863 (b)(6); (b)(7)(C)",
      "position": "middle"
    },
    {
      "type": "printed",
      "content": "Get Outlook for iOS This message and its attachments may contain legally privileged or confidential information. It is intended solely for the named addressee. If you are not the addressee indicated in this message (or responsible for delivery of the message to the addressee), you may not copy or deliver this message or its attachments to anyone. Rather, you should permanently delete this message and its attachments and kindly notify the sender by reply e-mail. Any content of this message and its attachments that does not relate to the official",
      "position": "bottom"
    }
  ],
  "entities": {
    "people": [
      "Jeffrey Epstein",
      "Shirley Skipper Scott"
    ],
    "organizations": [
      "Federal Bureau of Prisons",
      "MCC",
      "FOXNEWS"
    ],
    "locations": [
      "MDC BROOKLYN",
      "BROOKLYN",
      "NY"
    ],
    "dates": [
      "04-15-2007",
      "11/14/2019"
    ],
    "reference_numbers": [
      "786863",
      "DOJ-OGR-00025502"
    ]
  },
  "additional_notes": "The document contains redacted information marked as (b)(6); (b)(7)(C). The email is from an unknown sender to the Public Information Office of the Federal Bureau of Prisons. The email discusses the status of a case manager and Assistant Warden Shirley Skipper Scott after Jeffrey Epstein's death."
}