{
  "document_metadata": {
    "page_number": "3359",
    "document_number": "DOJ-OGR-00026948",
    "date": "8/4/1999",
    "document_type": "Official Out Count",
    "has_handwriting": true,
    "has_stamps": false
  },
  "full_text": "METROPOLITAN CORRECTIONAL CENTER NEW YORK, NY OFFICIAL OUT COUNT DATE: 8/4/99 COUNT TIME: 10:00AM FROM: [redacted] LOCATION: SHU Conf APPROVED: [redacted] (Operations Lieutenant) REG # NAME UNIT REG # NAME UNIT 1. [redacted] GN 13. 2. [redacted] ZA 14. 3. 76317-054 Epstein ZA 15. 4. 16. 5. 17. 6. 18. 7. 19. 8. 20. 9. 21. 10. 22. 11. 23. 2 12. 24. OUT-COUNT BY UNIT B-A C-A E-N E-S G-N G-S H-A I-N K-N K-S R-A Z-A Z-B 1 2 Total Out-Counted: 3 This form must be submitted to the Counts and Assignments Officer FORTY-FIVE MINUTES PRIOR to the affected count. Prepare this form in ink. Group the inmates according to their respective housing units. This form is to be used only as an Out-Count. No other form will be accepted in lieu of the Out-Count Form. DOJ-OGR-00026948",
  "text_blocks": [
    {
      "type": "printed",
      "content": "METROPOLITAN CORRECTIONAL CENTER NEW YORK, NY OFFICIAL OUT COUNT",
      "position": "header"
    },
    {
      "type": "handwritten",
      "content": "8/4/99",
      "position": "top"
    },
    {
      "type": "printed",
      "content": "DATE:",
      "position": "top"
    },
    {
      "type": "handwritten",
      "content": "10:00AM",
      "position": "top"
    },
    {
      "type": "printed",
      "content": "COUNT TIME:",
      "position": "top"
    },
    {
      "type": "handwritten",
      "content": "SHU Conf",
      "position": "top"
    },
    {
      "type": "printed",
      "content": "LOCATION:",
      "position": "top"
    },
    {
      "type": "handwritten",
      "content": "76317-054 Epstein",
      "position": "middle"
    },
    {
      "type": "printed",
      "content": "REG # NAME UNIT REG # NAME UNIT",
      "position": "middle"
    },
    {
      "type": "handwritten",
      "content": "1 2",
      "position": "bottom"
    },
    {
      "type": "printed",
      "content": "OUT-COUNT BY UNIT",
      "position": "bottom"
    },
    {
      "type": "printed",
      "content": "Total Out-Counted: 3",
      "position": "bottom"
    },
    {
      "type": "printed",
      "content": "This form must be submitted to the Counts and Assignments Officer FORTY-FIVE MINUTES PRIOR to the affected count. Prepare this form in ink. Group the inmates according to their respective housing units. This form is to be used only as an Out-Count. No other form will be accepted in lieu of the Out-Count Form.",
      "position": "footer"
    },
    {
      "type": "printed",
      "content": "DOJ-OGR-00026948",
      "position": "footer"
    }
  ],
  "entities": {
    "people": [
      "Epstein"
    ],
    "organizations": [
      "Metropolitan Correctional Center"
    ],
    "locations": [
      "New York, NY"
    ],
    "dates": [
      "8/4/1999"
    ],
    "reference_numbers": [
      "76317-054",
      "DOJ-OGR-00026948"
    ]
  },
  "additional_notes": "The document contains redactions, likely for privacy or security reasons. The handwriting is generally legible, but some parts may be difficult to read due to the quality of the scan or the original document."
}