{
  "document_metadata": {
    "page_number": "3394",
    "document_number": "DOJ-OGR-00026983",
    "date": "08/19/2019",
    "document_type": "Log Entries By Event Date",
    "has_handwriting": false,
    "has_stamps": false
  },
  "full_text": "Page 3394 Date: 08/19/2019 Time: 10:15 AM Federal Bureau of Prisons TRUINTEL Log Entries By Event Date Sensitive But Unclassified Entered Date Alpha Code Level 1 Location Level 2 Location Level 3 Location Event Date Shift User Event Base Count 8/9/2019 6:00 PM NYM Housing Units Housing Units, General Population ES 8/9/2019 6:00 PM Evening (b)(6); (b)(7)(C) Rounds (Officer) 8/9/2019 6:01 PM NYM Housing Units Housing Units, General Population ES 8/9/2019 6:01 PM Evening (b)(7)(E); (b)(7)(F) 8/9/2019 6:02 PM NYM Housing Units Housing Units, General Population ES 8/9/2019 6:02 PM Evening Bar Taps (Cells) 8/9/2019 6:15 PM NYM Housing Units Housing Units, General Population EN 8/9/2019 6:14 PM Evening Search (Cells) 8/9/2019 6:27 PM NYM Housing Units Housing Units, General Population ES 8/9/2019 6:23 PM Evening Daily Activity 8/9/2019 6:28 PM NYM Housing Units Housing Units, General Population ES 8/9/2019 6:27 PM Evening (b)(7)(F) Change to Base Count In 8/9/2019 6:28 PM NYM Housing Units Housing Units, General Population ES 8/9/2019 6:27 PM Evening Change to Base Count In 8/9/2019 6:34 PM NYM Housing Units Housing Units, General Population EN 8/9/2019 6:30 PM Evening (b)(7)(E); (b)(7)(F) 8/9/2019 7:24 PM NYM Housing Units Housing Units, General Population EN 8/9/2019 7:00 PM Evening 8/9/2019 7:29 PM NYM Housing Units Housing Units, General Population KN 8/9/2019 7:29 PM Evening Rounds (Lieutenant) User ID: (b)(6); (b)(7)(C) Page 922 of 1155 DOJ-OGR-00026983",
  "text_blocks": [
    {
      "type": "printed",
      "content": "Federal Bureau of Prisons TRUINTEL Log Entries By Event Date Sensitive But Unclassified",
      "position": "header"
    },
    {
      "type": "printed",
      "content": "Entered Date Alpha Code Level 1 Location Level 2 Location Level 3 Location Event Date Shift User Event Base Count",
      "position": "header"
    },
    {
      "type": "printed",
      "content": "8/9/2019 6:00 PM NYM Housing Units Housing Units, General Population ES 8/9/2019 6:00 PM Evening (b)(6); (b)(7)(C) Rounds (Officer)",
      "position": "body"
    },
    {
      "type": "printed",
      "content": "User ID: (b)(6); (b)(7)(C)",
      "position": "footer"
    },
    {
      "type": "printed",
      "content": "Page 922 of 1155",
      "position": "footer"
    },
    {
      "type": "printed",
      "content": "DOJ-OGR-00026983",
      "position": "footer"
    }
  ],
  "entities": {
    "people": [],
    "organizations": [
      "Federal Bureau of Prisons"
    ],
    "locations": [
      "Housing Units",
      "9South"
    ],
    "dates": [
      "08/19/2019",
      "8/9/2019"
    ],
    "reference_numbers": [
      "DOJ-OGR-00026983"
    ]
  },
  "additional_notes": "The document appears to be a log entry from the Federal Bureau of Prisons, detailing various events and activities that occurred on August 9, 2019. The document contains redactions, indicated by (b)(6); (b)(7)(C) and other similar notations."
}