{
  "document_metadata": {
    "page_number": null,
    "document_number": "DOJ-OGR-00027507",
    "date": "03/17/2008",
    "document_type": "Admissibility Secondary Inspection",
    "has_handwriting": false,
    "has_stamps": false
  },
  "full_text": "UNCLASSIFIED // FOR OFFICIAL USE ONLY\n\nEPSTEIN JEFFREY (b)(7)(E)\n03/17/2008 01:32:00\nAdmissibility Secondary Inspection (b)(7)(E)\n\n(b)(7)(E)\n\nCrossing Information\n\nSite:\nDisposition:\nPort Crossing Date:\nReferred Date:\nAirline:\nCarrier Trip:\nComment:\n\nNEWARK, INTL AP TERMINAL C (b)(7)(E)\nU.S. Citizen (USC)\n03/17/2008 01:32:00\n03/17/2008 01:32:00\n(b)(7)(E)\nU.S. CARRIER UNKNOWN (b)(7)(E)\n*UU N909JE\n(b)(6); (b)(7)(C), (b)(7)(E)\n(b)(7)(E) ADMITTED AS USC.\n\nSubject\n\nLast Name:\nFirst Name:\nDate Of Birth:\nCitizenship:\nGender:\n\nEPSTEIN\nJEFFREY\n01/20/1953\nUnited States (US/USA)\nMale (b)(7)(E)\n\nPassenger Document\n\nDocument Issue Country:\nDocument Number:\n\nUnited States (US/USA)\n(b)(6),(b)(7)(C)\n\nReferral/Vehicle Information\n\nReferred From:\nReferral:\nReferral Reason:\n\n(b)(7)(E)\n(b)(7)(E)\n(b)(7)(E)\n\nMiscellaneous Info\n\n(b)(7)(E)\n\nType Association:\n\nDocument Type\n\nRemarks\n\n(b)(6); (b)(7)(C), (b)(7)(E)\n(b)(7)(E) ADMITTED AS USC.\n\nPort Location\n\nUNCLASSIFIED // FOR OFFICIAL USE ONLY\nDOJ-OGR-00027507",
  "text_blocks": [
    {
      "type": "printed",
      "content": "UNCLASSIFIED // FOR OFFICIAL USE ONLY",
      "position": "header"
    },
    {
      "type": "printed",
      "content": "EPSTEIN JEFFREY (b)(7)(E)\n03/17/2008 01:32:00\nAdmissibility Secondary Inspection (b)(7)(E)",
      "position": "top"
    },
    {
      "type": "printed",
      "content": "(b)(7)(E)",
      "position": "margin"
    },
    {
      "type": "printed",
      "content": "Crossing Information",
      "position": "middle"
    },
    {
      "type": "printed",
      "content": "Site:\nDisposition:\nPort Crossing Date:\nReferred Date:\nAirline:\nCarrier Trip:\nComment:",
      "position": "middle"
    },
    {
      "type": "printed",
      "content": "NEWARK, INTL AP TERMINAL C (b)(7)(E)\nU.S. Citizen (USC)\n03/17/2008 01:32:00\n03/17/2008 01:32:00\n(b)(7)(E)\nU.S. CARRIER UNKNOWN (b)(7)(E)\n*UU N909JE\n(b)(6); (b)(7)(C), (b)(7)(E)\n(b)(7)(E) ADMITTED AS USC.",
      "position": "middle"
    },
    {
      "type": "printed",
      "content": "Subject",
      "position": "middle"
    },
    {
      "type": "printed",
      "content": "Last Name:\nFirst Name:\nDate Of Birth:\nCitizenship:\nGender:",
      "position": "middle"
    },
    {
      "type": "printed",
      "content": "EPSTEIN\nJEFFREY\n01/20/1953\nUnited States (US/USA)\nMale (b)(7)(E)",
      "position": "middle"
    },
    {
      "type": "printed",
      "content": "Passenger Document",
      "position": "middle"
    },
    {
      "type": "printed",
      "content": "Document Issue Country:\nDocument Number:",
      "position": "middle"
    },
    {
      "type": "printed",
      "content": "United States (US/USA)\n(b)(6),(b)(7)(C)",
      "position": "middle"
    },
    {
      "type": "printed",
      "content": "Referral/Vehicle Information",
      "position": "middle"
    },
    {
      "type": "printed",
      "content": "Referred From:\nReferral:\nReferral Reason:",
      "position": "middle"
    },
    {
      "type": "printed",
      "content": "(b)(7)(E)\n(b)(7)(E)\n(b)(7)(E)",
      "position": "middle"
    },
    {
      "type": "printed",
      "content": "Miscellaneous Info",
      "position": "middle"
    },
    {
      "type": "printed",
      "content": "(b)(7)(E)",
      "position": "middle"
    },
    {
      "type": "printed",
      "content": "Type Association:\nDocument Type",
      "position": "middle"
    },
    {
      "type": "printed",
      "content": "Remarks",
      "position": "middle"
    },
    {
      "type": "printed",
      "content": "(b)(6); (b)(7)(C), (b)(7)(E)\n(b)(7)(E) ADMITTED AS USC.",
      "position": "middle"
    },
    {
      "type": "printed",
      "content": "Port Location",
      "position": "middle"
    },
    {
      "type": "printed",
      "content": "UNCLASSIFIED // FOR OFFICIAL USE ONLY",
      "position": "footer"
    },
    {
      "type": "printed",
      "content": "DOJ-OGR-00027507",
      "position": "footer"
    }
  ],
  "entities": {
    "people": [
      "JEFFREY EPSTEIN"
    ],
    "organizations": [
      "U.S. CARRIER"
    ],
    "locations": [
      "NEWARK, INTL AP TERMINAL C",
      "United States"
    ],
    "dates": [
      "03/17/2008",
      "01/20/1953"
    ],
    "reference_numbers": [
      "*UU N909JE",
      "DOJ-OGR-00027507"
    ]
  },
  "additional_notes": "The document contains redactions marked as (b)(7)(E), (b)(6), and (b)(7)(C). The document is an Admissibility Secondary Inspection report for JEFFREY EPSTEIN."
}