{
  "document_metadata": {
    "page_number": "2397",
    "document_number": "BP-S358.060",
    "date": "7-24-2019",
    "document_type": "MEDICAL TREATMENT REFUSAL",
    "has_handwriting": true,
    "has_stamps": false
  },
  "full_text": "Page 2397\nBP-S358.060\nSEP 05\nMEDICAL TREATMENT REFUSAL\nCDFRM\nU.S. DEPARTMENT OF JUSTICE\nFEDERAL BUREAU OF PRISONS\n7-24-2019\nDate\nI, JEFFREY EPSTEIN\n76318-054\n, refuse treatment recommended by the Federal Bureau of Prisons Medical staff for the following condition(s):\nDESCRIBE CONDITION IN LAYMAN'S TERMINOLOGY:\nEYE DOCTOR EVALUATION.\nThe following treatment(s) was/were recommended:\nEYE DOCTOR EVALUATION.\nFederal Bureau of Prisons Medical staff members have carefully explained to me that the following possible consequences and/or complications may result because of my refusal to accept treatment:\nINABILITY TO DIAGNOSE CURRENT OPHTHALMOLOGIC DISEASES.\nI understand the possible consequences and/or complications, listed above, and still refuse recommended treatment. I hereby assume all responsibility for my physical and/or mental condition, and release the Bureau of Prisons and its employees from any and all liability for respecting and following my expressed wishes and directions.\n(b)(6); (b)(7)(C)\n(b)(6); (b)(7)(C)\n7-24-2019\nDate\nCounseled by\n(b)(6); (b)(7)(C)\n8/6/19\nDate\nSignature of witness\n(b)(6); (b)(7)(C)\n8/6/19\nNYMâ€”NEW YORK MCC\nPatient's Signature\nDOJ-OGR-00026073",
  "text_blocks": [
    {
      "type": "printed",
      "content": "MEDICAL TREATMENT REFUSAL",
      "position": "header"
    },
    {
      "type": "printed",
      "content": "U.S. DEPARTMENT OF JUSTICE\nFEDERAL BUREAU OF PRISONS",
      "position": "header"
    },
    {
      "type": "printed",
      "content": "I, JEFFREY EPSTEIN\n76318-054\n, refuse treatment recommended by the Federal Bureau of Prisons Medical staff for the following condition(s):",
      "position": "body"
    },
    {
      "type": "printed",
      "content": "DESCRIBE CONDITION IN LAYMAN'S TERMINOLOGY:\nEYE DOCTOR EVALUATION.",
      "position": "body"
    },
    {
      "type": "printed",
      "content": "The following treatment(s) was/were recommended:\nEYE DOCTOR EVALUATION.",
      "position": "body"
    },
    {
      "type": "printed",
      "content": "Federal Bureau of Prisons Medical staff members have carefully explained to me that the following possible consequences and/or complications may result because of my refusal to accept treatment:",
      "position": "body"
    },
    {
      "type": "printed",
      "content": "INABILITY TO DIAGNOSE CURRENT OPHTHALMOLOGIC DISEASES.",
      "position": "body"
    },
    {
      "type": "printed",
      "content": "I understand the possible consequences and/or complications, listed above, and still refuse recommended treatment. I hereby assume all responsibility for my physical and/or mental condition, and release the Bureau of Prisons and its employees from any and all liability for respecting and following my expressed wishes and directions.",
      "position": "body"
    },
    {
      "type": "handwritten",
      "content": "JEFFREY EPSTEIN",
      "position": "body"
    },
    {
      "type": "handwritten",
      "content": "7-24-2019",
      "position": "body"
    },
    {
      "type": "handwritten",
      "content": "Patient's Signature",
      "position": "footer"
    },
    {
      "type": "handwritten",
      "content": "8/6/19",
      "position": "footer"
    }
  ],
  "entities": {
    "people": [
      "JEFFREY EPSTEIN"
    ],
    "organizations": [
      "U.S. DEPARTMENT OF JUSTICE",
      "FEDERAL BUREAU OF PRISONS"
    ],
    "locations": [
      "NEW YORK MCC"
    ],
    "dates": [
      "7-24-2019",
      "8/6/19"
    ],
    "reference_numbers": [
      "BP-S358.060",
      "76318-054",
      "DOJ-OGR-00026073"
    ]
  },
  "additional_notes": "The document contains redactions of personal information, indicated by (b)(6); (b)(7)(C)."
}