{
  "document_metadata": {
    "page_number": "3295",
    "document_number": "DOJ-OGR-00026884",
    "date": "7/24/19",
    "document_type": "Suicide Watch Observation Log",
    "has_handwriting": true,
    "has_stamps": false
  },
  "full_text": "Page 3295\nSuicide Watch Observation Log\nName of Inmate on watch: Epstein Reg #: 76318-054 Date: 7/24/19\nTime Observations: Briefly note your observations. Initial all entries. Initials\n0630am Im Epstein appears to be sleeping at this time, breakfast has arrived but has not been given to him as of yet (b)(6); (b)(7)(C)\n0645am Im Epstein appears to be sleeping\n0700m I/C Bullock end of tour (b)(6); (b)(7)(C)\n7:00AM start the new sheet (b)(6); (b)(7)(C)\nD/w Rds Ops (T\n7:15AM Im Epstein recive his breakfast and went back to Sleep and ask the L/T for his Madivation\n7:30 AM Im Epstein appears tobe Sleeping\n7:35AM Im Epstein got up and he is hearing\n7:40 AM Im Epstein ask for a Shower and I call ore Lt\n7:45AM Im Epstein steel eating his breakfast\n8:00AM Im Epstein is setting Slowon on his bed\n8:15AM Im Epstein working the bathroom\n8:20AM Dr reviewed the log Book and interviewed IM Epstein for psychology (b)(6); (b)(7)(C)\n8:30 AM Dr. still interviewing IM Epstein\n8:45AM Dr stepped IM Epstein down from Suicide watch to Psychological (b)(6); (b)(7)(C)\nOBSERVATION\nNote to all observers: Legibly print and sign your name at the beginning of your shift.\n7\nDOJ-OGR-00026884",
  "text_blocks": [
    {
      "type": "printed",
      "content": "Suicide Watch Observation Log",
      "position": "header"
    },
    {
      "type": "handwritten",
      "content": "Epstein",
      "position": "header"
    },
    {
      "type": "printed",
      "content": "Name of Inmate on watch:",
      "position": "header"
    },
    {
      "type": "printed",
      "content": "Reg #:",
      "position": "header"
    },
    {
      "type": "handwritten",
      "content": "76318-054",
      "position": "header"
    },
    {
      "type": "printed",
      "content": "Date:",
      "position": "header"
    },
    {
      "type": "handwritten",
      "content": "7/24/19",
      "position": "header"
    },
    {
      "type": "printed",
      "content": "Time Observations: Briefly note your observations. Initial all entries. Initials",
      "position": "header"
    },
    {
      "type": "handwritten",
      "content": "0630am Im Epstein appears to be sleeping at this time, breakfast has arrived but has not been given to him as of yet (b)(6); (b)(7)(C)",
      "position": "body"
    },
    {
      "type": "handwritten",
      "content": "0645am Im Epstein appears to be sleeping",
      "position": "body"
    },
    {
      "type": "handwritten",
      "content": "0700m I/C Bullock end of tour (b)(6); (b)(7)(C)",
      "position": "body"
    },
    {
      "type": "handwritten",
      "content": "7:00AM start the new sheet (b)(6); (b)(7)(C)",
      "position": "body"
    },
    {
      "type": "handwritten",
      "content": "D/w Rds Ops (T",
      "position": "body"
    },
    {
      "type": "handwritten",
      "content": "7:15AM Im Epstein recive his breakfast and went back to Sleep and ask the L/T for his Madivation",
      "position": "body"
    },
    {
      "type": "handwritten",
      "content": "7:30 AM Im Epstein appears tobe Sleeping",
      "position": "body"
    },
    {
      "type": "handwritten",
      "content": "7:35AM Im Epstein got up and he is hearing",
      "position": "body"
    },
    {
      "type": "handwritten",
      "content": "7:40 AM Im Epstein ask for a Shower and I call ore Lt",
      "position": "body"
    },
    {
      "type": "handwritten",
      "content": "7:45AM Im Epstein steel eating his breakfast",
      "position": "body"
    },
    {
      "type": "handwritten",
      "content": "8:00AM Im Epstein is setting Slowon on his bed",
      "position": "body"
    },
    {
      "type": "handwritten",
      "content": "8:15AM Im Epstein working the bathroom",
      "position": "body"
    },
    {
      "type": "handwritten",
      "content": "8:20AM Dr reviewed the log Book and interviewed IM Epstein for psychology (b)(6); (b)(7)(C)",
      "position": "body"
    },
    {
      "type": "handwritten",
      "content": "8:30 AM Dr. still interviewing IM Epstein",
      "position": "body"
    },
    {
      "type": "handwritten",
      "content": "8:45AM Dr stepped IM Epstein down from Suicide watch to Psychological (b)(6); (b)(7)(C)",
      "position": "body"
    },
    {
      "type": "printed",
      "content": "Note to all observers: Legibly print and sign your name at the beginning of your shift.",
      "position": "footer"
    }
  ],
  "entities": {
    "people": [
      "Epstein",
      "Bullock"
    ],
    "organizations": [],
    "locations": [],
    "dates": [
      "7/24/19"
    ],
    "reference_numbers": [
      "76318-054",
      "DOJ-OGR-00026884"
    ]
  },
  "additional_notes": "The document appears to be a scanned copy of a handwritten log. Some parts of the text are redacted."
}