{
  "document_metadata": {
    "page_number": "7",
    "document_number": "M-19-019432",
    "date": "Aug 27, 2019",
    "document_type": "Autopsy Report",
    "has_handwriting": false,
    "has_stamps": false
  },
  "full_text": "M-19-019432 JEFFREY EDWARD EPSTEIN Page 7 LEFT DELTOID MUSCLE x 1 (#10): Intramuscular and fascial hemorrhages consisting of intact erythrocytes. TOXICOLOGY: Specimens are submitted for toxicologic analysis. A separate report will be issued. FORENSIC BIOLOGY: Blood spot card, clippings from right and left fingernails, and swabs of the back and front of neck and right and left hands are submitted. NEUROPATHOLOGY: A separate report will be issued. ANTHROPOLOGY: A separate report will be issued. EVIDENCE: Received separately are a ligature and clothing. The items are examined, photographed, and submitted to Evidence. See also \"Additional Autopsy Notes\". RADIOGRAPHY: Post-mortem radiographs are taken. PHOTOGRAPHY: Autopsy photos are taken. This report is reviewed by First Deputy Chief Medical Examiner. The information provided above is true and correct to the best of my knowledge and belief. Electronically signed by on Aug 27, 2019 07:38:00 AM DOJ-OGR-00026828",
  "text_blocks": [
    {
      "type": "printed",
      "content": "M-19-019432 JEFFREY EDWARD EPSTEIN Page 7",
      "position": "header"
    },
    {
      "type": "printed",
      "content": "LEFT DELTOID MUSCLE x 1 (#10): Intramuscular and fascial hemorrhages consisting of intact erythrocytes.",
      "position": "top"
    },
    {
      "type": "printed",
      "content": "TOXICOLOGY: Specimens are submitted for toxicologic analysis. A separate report will be issued.",
      "position": "middle"
    },
    {
      "type": "printed",
      "content": "FORENSIC BIOLOGY: Blood spot card, clippings from right and left fingernails, and swabs of the back and front of neck and right and left hands are submitted.",
      "position": "middle"
    },
    {
      "type": "printed",
      "content": "NEUROPATHOLOGY: A separate report will be issued.",
      "position": "middle"
    },
    {
      "type": "printed",
      "content": "ANTHROPOLOGY: A separate report will be issued.",
      "position": "middle"
    },
    {
      "type": "printed",
      "content": "EVIDENCE: Received separately are a ligature and clothing. The items are examined, photographed, and submitted to Evidence. See also \"Additional Autopsy Notes\".",
      "position": "middle"
    },
    {
      "type": "printed",
      "content": "RADIOGRAPHY: Post-mortem radiographs are taken.",
      "position": "middle"
    },
    {
      "type": "printed",
      "content": "PHOTOGRAPHY: Autopsy photos are taken.",
      "position": "middle"
    },
    {
      "type": "printed",
      "content": "This report is reviewed by First Deputy Chief Medical Examiner.",
      "position": "middle"
    },
    {
      "type": "printed",
      "content": "The information provided above is true and correct to the best of my knowledge and belief. Electronically signed by on Aug 27, 2019 07:38:00 AM",
      "position": "bottom"
    },
    {
      "type": "other",
      "content": "(b)(6); (b)(7)(C)",
      "position": "bottom"
    },
    {
      "type": "printed",
      "content": "DOJ-OGR-00026828",
      "position": "footer"
    }
  ],
  "entities": {
    "people": [
      "JEFFREY EDWARD EPSTEIN"
    ],
    "organizations": [
      "DOJ"
    ],
    "locations": [],
    "dates": [
      "Aug 27, 2019"
    ],
    "reference_numbers": [
      "M-19-019432",
      "DOJ-OGR-00026828"
    ]
  },
  "additional_notes": "The document appears to be a page from an autopsy report for Jeffrey Edward Epstein. The page is marked as 'Page 7' and contains various sections related to the autopsy, including toxicology, forensic biology, and photography. The report is electronically signed by a First Deputy Chief Medical Examiner, with the name redacted."
}