{
  "document_metadata": {
    "page_number": "3316",
    "document_number": "NYM-19-0082",
    "date": "8/10/2019",
    "document_type": "Form 583 Report of Incident",
    "has_handwriting": false,
    "has_stamps": false
  },
  "full_text": "Page 3316\n\nForm 583 Report of Incident\n\nIncident #: NYM-19-0082 Submitted By: N' Diaye, L. Date/Time Of Incident: 8/10/2019 6:33 AM\n\nReg #: 76318054 Name: EPSTEIN, JEFFREY\nRole: Not Known Medical Attention Required: Outside Injury Category: Fatal Injury\nWeapon (per Inmate): No Use of Force (per Inmate): No Chemical Used (per Inmate): No\nCIMS: No STG: Yes\nRestraints (per Inmate): Escort Only\nDeath (per Inmate): No\n\nSection 3: Others Involved\n\nName: [b)(6); (b)(7)(C) Person Type: Staff\nMedical Attention Required: No Death: No\nInjury Category: No Injury Staff Injury by Inmate: No\nSexual Assault: No\n\nName: [b)(6); (b)(7)(C) Person Type: Staff\nMedical Attention Required: No Death: No\nInjury Category: No Injury Staff Injury by Inmate: No\nSexual Assault: No\n\nName: [b)(6); (b)(7)(C) Person Type: Staff\nMedical Attention Required: No Death: No\nInjury Category: No Injury Staff Injury by Inmate: No\nSexual Assault: No\n\nName: [b)(6); (b)(7)(C) Person Type: Staff\nMedical Attention Required: No Death: No\nInjury Category: No Injury Staff Injury by Inmate: No\nSexual Assault: No\n\nName: [b)(6); (b)(7)(C) Person Type: Staff\nMedical Attention Required: No Death: No\nInjury Category: No Injury Staff Injury by Inmate: No\nSexual Assault: No\n\nName: [b)(6); (b)(7)(C) Person Type: Staff\nMedical Attention Required: No Death: No\nInjury Category: No Injury Staff Injury by Inmate: No\nSexual Assault: No\n\nName: [b)(6); (b)(7)(C) Person Type: Staff\nMedical Attention Required: No Death: No\nInjury Category: No Injury Staff Injury by Inmate: No\nSexual Assault: No\n\nUNCLASSIFIED/LIMITED OFFICIAL USE ONLY/LAW ENFORCEMENT SENSITIVE\nThis document is marked Unclassified/Limited Official Use Only/Law Enforcement Sensitive and may be disseminated, with proper attribution, to active Law Enforcement, DOD, or U.S. Intelligence Agencies. This document, or any segment/attachment thereof, may not be released without the approval of the Bureau of Prisons to any media sources, any non-law enforcement entity, the general public or those without a \"need to know.\" It contains information that may be exempt from public release under the provisions of the Privacy Act (5 U.S.C. 552).\n\n2 of 3\n\nDOJ-OGR-00026905",
  "text_blocks": [
    {
      "type": "printed",
      "content": "Form 583 Report of Incident",
      "position": "header"
    },
    {
      "type": "printed",
      "content": "Incident #: NYM-19-0082 Submitted By: N' Diaye, L. Date/Time Of Incident: 8/10/2019 6:33 AM",
      "position": "header"
    },
    {
      "type": "printed",
      "content": "Reg #: 76318054 Name: EPSTEIN, JEFFREY Role: Not Known Medical Attention Required: Outside Injury Category: Fatal Injury Weapon (per Inmate): No Use of Force (per Inmate): No Chemical Used (per Inmate): No CIMS: No STG: Yes Restraints (per Inmate): Escort Only Death (per Inmate): No",
      "position": "middle"
    },
    {
      "type": "printed",
      "content": "Section 3: Others Involved",
      "position": "middle"
    },
    {
      "type": "printed",
      "content": "Name: [b)(6); (b)(7)(C) Person Type: Staff Medical Attention Required: No Death: No Injury Category: No Injury Staff Injury by Inmate: No Sexual Assault: No",
      "position": "middle"
    },
    {
      "type": "printed",
      "content": "UNCLASSIFIED/LIMITED OFFICIAL USE ONLY/LAW ENFORCEMENT SENSITIVE",
      "position": "footer"
    },
    {
      "type": "printed",
      "content": "This document is marked Unclassified/Limited Official Use Only/Law Enforcement Sensitive and may be disseminated, with proper attribution, to active Law Enforcement, DOD, or U.S. Intelligence Agencies. This document, or any segment/attachment thereof, may not be released without the approval of the Bureau of Prisons to any media sources, any non-law enforcement entity, the general public or those without a \"need to know.\" It contains information that may be exempt from public release under the provisions of the Privacy Act (5 U.S.C. 552).",
      "position": "footer"
    }
  ],
  "entities": {
    "people": [
      "N' Diaye, L.",
      "EPSTEIN, JEFFREY"
    ],
    "organizations": [
      "Bureau of Prisons",
      "DOD",
      "U.S. Intelligence Agencies"
    ],
    "locations": [],
    "dates": [
      "8/10/2019"
    ],
    "reference_numbers": [
      "NYM-19-0082",
      "76318054",
      "DOJ-OGR-00026905"
    ]
  },
  "additional_notes": "The document contains redacted names and is marked as 'UNCLASSIFIED/LIMITED OFFICIAL USE ONLY/LAW ENFORCEMENT SENSITIVE'. It is page 2 of 3."
}