{
  "document_metadata": {
    "page_number": "1",
    "document_number": "551",
    "date": "12/16/21",
    "document_type": "Court Order",
    "has_handwriting": false,
    "has_stamps": true
  },
  "full_text": "Case 1:20-cr-00330-PAE Document 551 Filed 12/16/21 Page 1 of 2 UNITED STATES DISTRICT COURT SOUTHERN DISTRICT OF NEW YORK United States of America, -v- Ghislaine Maxwell, Defendant. USD C SDNY DOCUMENT ELECTRONICALLY FILED DOC #: DATE FILED: 12/16/21 20-CR-330 (AJN) ORDER ALISON J. NATHAN, District Judge: The Court is in receipt of the parties' joint letter regarding the admission of prior inconsistent statements. The parties' letter notes \"that many of these statements raise one of two questions: (1) must counsel show the witness the prior inconsistent statement under Rule 613(b), and (2) is a statement admissible when the witness affirms that the 3500 material contains the inconsistent statement and also expresses disagreement with the substance.\" The parties are hereby ORDERED to submit a letter citing authority (beyond the rule itself) for their respective positions. The parties are FURTHER ORDERED to indicate each disputed prior inconsistent statement that was read into the record. Letters must be submitted as soon as possible but no later than today, December 16, 2021, at 10:15 p.m. The parties are FURTHER ORDERED to docket their respective letters by tomorrow, December 17, 2021, at 8:00 a.m. SO ORDERED. 1 DOJ-OGR-00008422",
  "text_blocks": [
    {
      "type": "printed",
      "content": "Case 1:20-cr-00330-PAE Document 551 Filed 12/16/21 Page 1 of 2",
      "position": "header"
    },
    {
      "type": "printed",
      "content": "UNITED STATES DISTRICT COURT SOUTHERN DISTRICT OF NEW YORK",
      "position": "header"
    },
    {
      "type": "printed",
      "content": "United States of America, -v- Ghislaine Maxwell, Defendant.",
      "position": "header"
    },
    {
      "type": "stamp",
      "content": "USD C SDNY DOCUMENT ELECTRONICALLY FILED DOC #: DATE FILED: 12/16/21",
      "position": "margin"
    },
    {
      "type": "printed",
      "content": "20-CR-330 (AJN) ORDER",
      "position": "header"
    },
    {
      "type": "printed",
      "content": "ALISON J. NATHAN, District Judge: The Court is in receipt of the parties' joint letter regarding the admission of prior inconsistent statements. The parties' letter notes \"that many of these statements raise one of two questions: (1) must counsel show the witness the prior inconsistent statement under Rule 613(b), and (2) is a statement admissible when the witness affirms that the 3500 material contains the inconsistent statement and also expresses disagreement with the substance.\" The parties are hereby ORDERED to submit a letter citing authority (beyond the rule itself) for their respective positions. The parties are FURTHER ORDERED to indicate each disputed prior inconsistent statement that was read into the record. Letters must be submitted as soon as possible but no later than today, December 16, 2021, at 10:15 p.m. The parties are FURTHER ORDERED to docket their respective letters by tomorrow, December 17, 2021, at 8:00 a.m. SO ORDERED.",
      "position": "body"
    },
    {
      "type": "printed",
      "content": "1",
      "position": "footer"
    },
    {
      "type": "printed",
      "content": "DOJ-OGR-00008422",
      "position": "footer"
    }
  ],
  "entities": {
    "people": [
      "Ghislaine Maxwell",
      "Alison J. Nathan"
    ],
    "organizations": [
      "United States District Court",
      "United States of America"
    ],
    "locations": [
      "New York"
    ],
    "dates": [
      "December 16, 2021",
      "December 17, 2021"
    ],
    "reference_numbers": [
      "1:20-cr-00330-PAE",
      "Document 551",
      "20-CR-330 (AJN)",
      "DOJ-OGR-00008422"
    ]
  },
  "additional_notes": "The document is a court order from the United States District Court for the Southern District of New York. It appears to be a formal and official document, with a stamp indicating electronic filing. The content is related to a court case involving Ghislaine Maxwell."
}