{
  "document_metadata": {
    "page_number": "25",
    "document_number": "499-2",
    "date": "11/23/21",
    "document_type": "court transcript",
    "has_handwriting": false,
    "has_stamps": false
  },
  "full_text": "Case 1:20-cr-00330-PAE Document 499-2 Filed 11/23/21 Page 25 of 159 24 LBAAMAX1ps Rocchio - Direct I've been doing it for conferences from, you know, 20, 25 years minimally. Q. Do you have any other involvement in professional publications? A. I, apart from serving on the editorial board for the journal of trauma psychology, not at the moment, no. Q. Do you hold -- A. Oh, can I actually correct that answer? Yes. Actually, the other thing is that for the publication I recently had, in addition to submitting articles for peer review, I was an invited guest editor in that particular edition -- special issue of that journal, so that meant that I had to, with my co-editor, solicit articles and then review them for publication. Q. Do you belong to any professional organizations? A. I do. Q. Do you hold any leadership positions with those organizations? A. I do. Q. What are those leadership positions that you hold? A. I'm currently the president-elect for the division of trauma psychology for the American Psychological Association. I am also a member of the ethics committee for the American Psychological Association. I serve as a -- on the executive board of the Rhode Island Psychological Association, where I am SOUTHERN DISTRICT REPORTERS, P.C. (212) 805-0300 DOJ-OGR-00007893",
  "text_blocks": [
    {
      "type": "printed",
      "content": "Case 1:20-cr-00330-PAE Document 499-2 Filed 11/23/21 Page 25 of 159 24",
      "position": "header"
    },
    {
      "type": "printed",
      "content": "LBAAMAX1ps Rocchio - Direct",
      "position": "header"
    },
    {
      "type": "printed",
      "content": "I've been doing it for conferences from, you know, 20, 25 years minimally. Q. Do you have any other involvement in professional publications? A. I, apart from serving on the editorial board for the journal of trauma psychology, not at the moment, no. Q. Do you hold -- A. Oh, can I actually correct that answer? Yes. Actually, the other thing is that for the publication I recently had, in addition to submitting articles for peer review, I was an invited guest editor in that particular edition -- special issue of that journal, so that meant that I had to, with my co-editor, solicit articles and then review them for publication. Q. Do you belong to any professional organizations? A. I do. Q. Do you hold any leadership positions with those organizations? A. I do. Q. What are those leadership positions that you hold? A. I'm currently the president-elect for the division of trauma psychology for the American Psychological Association. I am also a member of the ethics committee for the American Psychological Association. I serve as a -- on the executive board of the Rhode Island Psychological Association, where I am",
      "position": "main"
    },
    {
      "type": "printed",
      "content": "SOUTHERN DISTRICT REPORTERS, P.C. (212) 805-0300 DOJ-OGR-00007893",
      "position": "footer"
    }
  ],
  "entities": {
    "people": [],
    "organizations": [
      "American Psychological Association",
      "Rhode Island Psychological Association",
      "SOUTHERN DISTRICT REPORTERS, P.C."
    ],
    "locations": [],
    "dates": [
      "11/23/21"
    ],
    "reference_numbers": [
      "1:20-cr-00330-PAE",
      "499-2",
      "DOJ-OGR-00007893",
      "(212) 805-0300"
    ]
  },
  "additional_notes": "The document appears to be a court transcript with a clear and readable format. There are no visible redactions or damage."
}