{
  "document_metadata": {
    "page_number": "182",
    "document_number": "499-1",
    "date": "11/23/21",
    "document_type": "court document",
    "has_handwriting": false,
    "has_stamps": false
  },
  "full_text": "Case 1:20-cr-00330-PAE Document 499-1 Filed 11/23/21 Page 182 of 375\n2012-2015 American Academy of Psychiatry and the Law's Young Physician Delegate to the American Medical Association's House of Delegates meetings\n2013- present Interviewer of prospective medical school candidates University of Central Florida College of Medicine\n2017 - FIRE Research Mentor, University of Central Florida College of Medicine\n2017 Specialty Advisor for forensic and general psychiatry University of Central Florida College of Medicine\n2018 Simulation Leader, Global Health Conference: Healthcare as a Human Right, University of Central Florida College of Medicine\n2019 Florida Medical Association's Alternate Delegate to the American Medical Association's House of Delegates\n2019 Foundation Board of Directors, Physicians Society of Central Florida\n2020 Participant in Florida Division of Emergency Management's Rehabilitative Services Working Group on Coronavirus\n2020 Participant in University of Central Florida College of Medicine's AORTA admissions program\n2020 Florida Medical Association's representative to Florida's Suicide Prevention Coordinating Council (SPCC)\n2021 Virtual Forensic Psychiatry discussion with UCF PsychSign group on April 12, 2021\nREVIEWER:\n-AIMS Neuroscience\n-American Journal of Disaster Medicine\n-Archives of Internal Medicine\n-Clinical Geriatrics\n-Disaster Medicine and Public Health Preparedness\n-European Psychiatry\n-Journal of Adolescent Health\n-Journal of Clinical Psychopharmacology\n-Journal of Ethics\n-Journal of Immigrant and Minority Health\n-Journal of Neuropsychiatry and Clinical Neuroscience\n-Mayo Clinic Proceedings\n-Nature Clinical Practice Neurology\n11\nDOJ-OGR-00007675",
  "text_blocks": [
    {
      "type": "printed",
      "content": "Case 1:20-cr-00330-PAE Document 499-1 Filed 11/23/21 Page 182 of 375",
      "position": "header"
    },
    {
      "type": "printed",
      "content": "2012-2015 American Academy of Psychiatry and the Law's Young Physician Delegate to the American Medical Association's House of Delegates meetings\n2013- present Interviewer of prospective medical school candidates University of Central Florida College of Medicine\n2017 - FIRE Research Mentor, University of Central Florida College of Medicine\n2017 Specialty Advisor for forensic and general psychiatry University of Central Florida College of Medicine\n2018 Simulation Leader, Global Health Conference: Healthcare as a Human Right, University of Central Florida College of Medicine\n2019 Florida Medical Association's Alternate Delegate to the American Medical Association's House of Delegates\n2019 Foundation Board of Directors, Physicians Society of Central Florida\n2020 Participant in Florida Division of Emergency Management's Rehabilitative Services Working Group on Coronavirus\n2020 Participant in University of Central Florida College of Medicine's AORTA admissions program\n2020 Florida Medical Association's representative to Florida's Suicide Prevention Coordinating Council (SPCC)\n2021 Virtual Forensic Psychiatry discussion with UCF PsychSign group on April 12, 2021",
      "position": "main content"
    },
    {
      "type": "printed",
      "content": "REVIEWER:\n-AIMS Neuroscience\n-American Journal of Disaster Medicine\n-Archives of Internal Medicine\n-Clinical Geriatrics\n-Disaster Medicine and Public Health Preparedness\n-European Psychiatry\n-Journal of Adolescent Health\n-Journal of Clinical Psychopharmacology\n-Journal of Ethics\n-Journal of Immigrant and Minority Health\n-Journal of Neuropsychiatry and Clinical Neuroscience\n-Mayo Clinic Proceedings\n-Nature Clinical Practice Neurology",
      "position": "main content"
    },
    {
      "type": "printed",
      "content": "11",
      "position": "footer"
    },
    {
      "type": "printed",
      "content": "DOJ-OGR-00007675",
      "position": "footer"
    }
  ],
  "entities": {
    "people": [],
    "organizations": [
      "American Academy of Psychiatry and the Law",
      "American Medical Association",
      "University of Central Florida College of Medicine",
      "Florida Medical Association",
      "Physicians Society of Central Florida",
      "Florida Division of Emergency Management",
      "UCF PsychSign group"
    ],
    "locations": [
      "Florida",
      "Central Florida"
    ],
    "dates": [
      "2012-2015",
      "2013",
      "2017",
      "2018",
      "2019",
      "2020",
      "2021",
      "April 12, 2021",
      "11/23/21"
    ],
    "reference_numbers": [
      "1:20-cr-00330-PAE",
      "499-1",
      "182",
      "375",
      "DOJ-OGR-00007675"
    ]
  },
  "additional_notes": "The document appears to be a court filing with a CV or resume attached, detailing the professional experience and activities of a medical professional. The document is well-formatted and legible."
}