{
  "document_metadata": {
    "page_number": "208",
    "document_number": "499-1",
    "date": "11/23/21",
    "document_type": "court document",
    "has_handwriting": false,
    "has_stamps": false
  },
  "full_text": "Case 1:20-cr-00330-PAE Document 499-1 Filed 11/23/21 Page 208 of 375\n92. Cluster A personality disorders\n93. Cluster B personality disorders\n94. Cluster C personality disorders\n95. Keeping \"schizo\" straight\n96. Eating disorders\n97. Gender identity disorder\n98. Substance dependence\n99. Substance abuse\n100. Substance withdrawal\n101. Signs and symptoms of substance abuse\n102. Heroin addiction\n103. Alcoholism\n104. Delirium tremens (DTs)\nAPA On Demand, March 30, 2020\n1. The Good, the Bad, and the Ugly: Anabolic Androgenic Steroid (AAS) Use Depicted in Comics/Using Comics to Teach: Workshop Exercise\nMEDIA:\n1. Time Magazine, Definition, Diagnosis, and Forensic Implications of Postconcussional Syndrome, May 16, 2005\n2. Reach MD XM Radio, Pedophilia (Types and Classifications, Profile of Victims of Pedophilia, Treatment for Pedophiles and their Victims, and Pedophilia Research), May 14, 2007\n3. MD Consult. Doug Kaufman. Joint telephone interview with Richard C. W. Hall, MD, Pedophilia. May 2, 2007\n4. The Korean Broadcasting System, KBS Special, Pedophilia. March 11, 2008.\n5. Tony Pipitone, WKMG-TV Channel 6, Mothers Who Kill Their Children. October 28,\n37\nDOJ-OGR-00007701",
  "text_blocks": [
    {
      "type": "printed",
      "content": "Case 1:20-cr-00330-PAE Document 499-1 Filed 11/23/21 Page 208 of 375",
      "position": "header"
    },
    {
      "type": "printed",
      "content": "92. Cluster A personality disorders\n93. Cluster B personality disorders\n94. Cluster C personality disorders\n95. Keeping \"schizo\" straight\n96. Eating disorders\n97. Gender identity disorder\n98. Substance dependence\n99. Substance abuse\n100. Substance withdrawal\n101. Signs and symptoms of substance abuse\n102. Heroin addiction\n103. Alcoholism\n104. Delirium tremens (DTs)",
      "position": "top"
    },
    {
      "type": "printed",
      "content": "APA On Demand, March 30, 2020",
      "position": "middle"
    },
    {
      "type": "printed",
      "content": "1. The Good, the Bad, and the Ugly: Anabolic Androgenic Steroid (AAS) Use Depicted in Comics/Using Comics to Teach: Workshop Exercise",
      "position": "middle"
    },
    {
      "type": "printed",
      "content": "MEDIA:",
      "position": "middle"
    },
    {
      "type": "printed",
      "content": "1. Time Magazine, Definition, Diagnosis, and Forensic Implications of Postconcussional Syndrome, May 16, 2005\n2. Reach MD XM Radio, Pedophilia (Types and Classifications, Profile of Victims of Pedophilia, Treatment for Pedophiles and their Victims, and Pedophilia Research), May 14, 2007\n3. MD Consult. Doug Kaufman. Joint telephone interview with Richard C. W. Hall, MD, Pedophilia. May 2, 2007\n4. The Korean Broadcasting System, KBS Special, Pedophilia. March 11, 2008.\n5. Tony Pipitone, WKMG-TV Channel 6, Mothers Who Kill Their Children. October 28,",
      "position": "middle"
    },
    {
      "type": "printed",
      "content": "37",
      "position": "footer"
    },
    {
      "type": "printed",
      "content": "DOJ-OGR-00007701",
      "position": "footer"
    }
  ],
  "entities": {
    "people": [
      "Doug Kaufman",
      "Richard C. W. Hall",
      "Tony Pipitone"
    ],
    "organizations": [
      "Time Magazine",
      "Reach MD XM Radio",
      "MD Consult",
      "The Korean Broadcasting System",
      "WKMG-TV Channel 6",
      "APA"
    ],
    "locations": [],
    "dates": [
      "May 16, 2005",
      "May 14, 2007",
      "May 2, 2007",
      "March 11, 2008",
      "October 28",
      "March 30, 2020",
      "11/23/21"
    ],
    "reference_numbers": [
      "1:20-cr-00330-PAE",
      "499-1",
      "DOJ-OGR-00007701"
    ]
  },
  "additional_notes": "The document appears to be a court filing with a list of topics related to mental health and substance abuse, followed by a list of media references. The document is page 208 of 375."
}