{
  "document_metadata": {
    "page_number": "28",
    "document_number": "499-2",
    "date": "11/23/21",
    "document_type": "court document",
    "has_handwriting": false,
    "has_stamps": false
  },
  "full_text": "Case 1:20-cr-00330-PAE Document 499-2 Filed 11/23/21 Page 28 of 159 27 LBAGmax2 Rocchio - Direct\n1 training?\n2 A. Various treatment methods specific to treating individuals\n3 who have experienced various kinds of traumatic stress and\n4 personal violence, childhood abuse, complex trauma, specialized\n5 practice in forensic psychology, predominantly.\n6 Q. What kinds of training have you received?\n7 A. Attending numerous workshops conducted by reputable experts\n8 in the field that typically have been vetted so that I can\n9 receive continuing education credits and are required on an\n10 annual basis for various forms of licensure. Also, there have\n11 been some trainings that I have done online. For example, I\n12 participate in a weekly webinar on issues relevant to the signs\n13 and practice of forensic psychology that is conducted by\n14 experts in the field. I think that covers it.\n15 Q. In what way do you train others?\n16 A. I have done a variety of things. So I have been on the\n17 ethics committee for the psychological association and also on\n18 the American psychological association. So part of what I do\n19 is we have a call in opportunity for our members, and we\n20 provide education about ethical issues to -- and consultation\n21 to individuals who request that form of assistance. As I\n22 mentioned, I'm a clinical supervisor for psychology fellows in\n23 medical school at Brown University. I do provide consultation,\n24 supervision to all of my employees. And there are also times\n25 where others in the field may contact me on a professional\nSOUTHERN DISTRICT REPORTERS, P.C. (212) 805-0300 DOJ-OGR-00007896",
  "text_blocks": [
    {
      "type": "printed",
      "content": "Case 1:20-cr-00330-PAE Document 499-2 Filed 11/23/21 Page 28 of 159 27 LBAGmax2 Rocchio - Direct",
      "position": "header"
    },
    {
      "type": "printed",
      "content": "1 training?\n2 A. Various treatment methods specific to treating individuals\n3 who have experienced various kinds of traumatic stress and\n4 personal violence, childhood abuse, complex trauma, specialized\n5 practice in forensic psychology, predominantly.\n6 Q. What kinds of training have you received?\n7 A. Attending numerous workshops conducted by reputable experts\n8 in the field that typically have been vetted so that I can\n9 receive continuing education credits and are required on an\n10 annual basis for various forms of licensure. Also, there have\n11 been some trainings that I have done online. For example, I\n12 participate in a weekly webinar on issues relevant to the signs\n13 and practice of forensic psychology that is conducted by\n14 experts in the field. I think that covers it.\n15 Q. In what way do you train others?\n16 A. I have done a variety of things. So I have been on the\n17 ethics committee for the psychological association and also on\n18 the American psychological association. So part of what I do\n19 is we have a call in opportunity for our members, and we\n20 provide education about ethical issues to -- and consultation\n21 to individuals who request that form of assistance. As I\n22 mentioned, I'm a clinical supervisor for psychology fellows in\n23 medical school at Brown University. I do provide consultation,\n24 supervision to all of my employees. And there are also times\n25 where others in the field may contact me on a professional",
      "position": "main content"
    },
    {
      "type": "printed",
      "content": "SOUTHERN DISTRICT REPORTERS, P.C. (212) 805-0300 DOJ-OGR-00007896",
      "position": "footer"
    }
  ],
  "entities": {
    "people": [],
    "organizations": [
      "American Psychological Association",
      "Brown University",
      "Southern District Reporters, P.C."
    ],
    "locations": [],
    "dates": [
      "11/23/21"
    ],
    "reference_numbers": [
      "1:20-cr-00330-PAE",
      "499-2",
      "DOJ-OGR-00007896",
      "(212) 805-0300"
    ]
  },
  "additional_notes": "The document appears to be a court transcript, with a clear structure and formatting. The text is mostly legible, with some minor formatting issues. There are no visible redactions or damage to the document."
}