{
  "document_metadata": {
    "page_number": "5",
    "document_number": "1:13-cr-00835",
    "date": "2013",
    "document_type": "Court Document",
    "has_handwriting": false,
    "has_stamps": false
  },
  "full_text": "COUNT FIVE\n(Attempted Sex Trafficking of Minor Victim-4)\nThe Grand Jury further charges:\n5. At least in or about September 2013, in the Southern District of New York and elsewhere, CLAUDIUS ENGLISH, a/k/a \"Jay Barnes,\" a/k/a \"Brent English,\" the defendant, in or affecting interstate and foreign commerce, attempted to recruit, entice, harbor, transport, provide, obtain, advertise, maintain, patronize, and solicit a person who had not attained the age of 14 years at the time (\"Minor Victim-4\"), knowing, having had a reasonable opportunity to observe, and in reckless disregard of the fact that Minor Victim-4 had not attained the age of 14 years, and knowing that Minor Victim-4 would be caused to engage in commercial sex acts, to wit, ENGLISH attempted to recruit, entice, transport, and obtain Minor Victim-4, an eleven-year-old girl, to engage in sexual acts with at least one man in exchange for money, some of which ENGLISH would keep for himself.\n(Title 18, United States Code, Sections 1594(a), 1591(a)(1) and (b)(1), and 2.)\nCOUNT SIX\n(Attempted Sex Trafficking of Minor Victim-5)\nThe Grand Jury further charges:\n6. At least in or about October 2013, in the Southern District of New York and elsewhere, CLAUDIUS ENGLISH, a/k/a \"Jay Barnes,\" a/k/a \"Brent English,\" the defendant, in or affecting",
  "text_blocks": [
    {
      "type": "printed",
      "content": "COUNT FIVE\n(Attempted Sex Trafficking of Minor Victim-4)\nThe Grand Jury further charges:\n5. At least in or about September 2013, in the Southern District of New York and elsewhere, CLAUDIUS ENGLISH, a/k/a \"Jay Barnes,\" a/k/a \"Brent English,\" the defendant, in or affecting interstate and foreign commerce, attempted to recruit, entice, harbor, transport, provide, obtain, advertise, maintain, patronize, and solicit a person who had not attained the age of 14 years at the time (\"Minor Victim-4\"), knowing, having had a reasonable opportunity to observe, and in reckless disregard of the fact that Minor Victim-4 had not attained the age of 14 years, and knowing that Minor Victim-4 would be caused to engage in commercial sex acts, to wit, ENGLISH attempted to recruit, entice, transport, and obtain Minor Victim-4, an eleven-year-old girl, to engage in sexual acts with at least one man in exchange for money, some of which ENGLISH would keep for himself.\n(Title 18, United States Code, Sections 1594(a), 1591(a)(1) and (b)(1), and 2.)",
      "position": "top"
    },
    {
      "type": "printed",
      "content": "COUNT SIX\n(Attempted Sex Trafficking of Minor Victim-5)\nThe Grand Jury further charges:\n6. At least in or about October 2013, in the Southern District of New York and elsewhere, CLAUDIUS ENGLISH, a/k/a \"Jay Barnes,\" a/k/a \"Brent English,\" the defendant, in or affecting",
      "position": "bottom"
    }
  ],
  "entities": {
    "people": [
      "CLAUDIUS ENGLISH",
      "Minor Victim-4",
      "Minor Victim-5"
    ],
    "organizations": [
      "Grand Jury"
    ],
    "locations": [
      "Southern District of New York"
    ],
    "dates": [
      "September 2013",
      "October 2013"
    ],
    "reference_numbers": [
      "1:13-cr-00835"
    ]
  },
  "additional_notes": "The document appears to be a court document related to a case involving attempted sex trafficking of minors. The text is printed and there are no visible stamps or handwritten notes. The document is page 5 of a larger document."
}