{
  "document_metadata": {
    "page_number": "346 of 375",
    "document_number": "499-1",
    "date": "11/23/21",
    "document_type": "Curriculum Vitae",
    "has_handwriting": false,
    "has_stamps": false
  },
  "full_text": "Case 1:20-cr-00330-PAE Document 499-1 Filed 11/23/21 Page 346 of 375 CURRICULUM VITAE Robert P. Kelso Forensic Pursuit 2000 Arapahoe Street, Suite 1 | Denver, Colorado 80205 Office (303) 495-2082 | Email Robert.Kelso@ForensicPursuit.com Trial testimony at the City and County Court of Denver, Colorado Honorable Judge Robert L. McGahey Monica David Vickery v. Evelyn Trumble and Merry Gayle Vickery Retained by Plaintiff Case No: 07 CV 7674 Date: 1/6/2009 Special Master Appointments United States District Court for the District of Colorado United States Magistrate Judge Michael E. Hegarty Civil Action No: 11-cv-02560-MSK-MEH Date: 11/7/2012 District Court, Arapahoe County, Colorado Case No: 2010 CV 2203 Date: 3/23/2011 District Court, Arapahoe County, Colorado Case No: 2005 CV 1944 Date: 7/19/2010 United States District Court for the District of Colorado Kristen L. Mix, United States Magistrate Judge Civil Action No: 09-cv-01099-MSK-KLM Date: 1/21/2010 District Court, Arapahoe County, Colorado Case No: 2009 CV 1694 Date: 9/9/2009 District Court, Adams County, Colorado Case No: 08DR1992 Date: 6/3/2009 District Court City and County of Broomfield Case No: 2006 DR 60 Date: 9/13/2008 Honors Selected by the Republican National Committee to act as the local (Denver) computer forensics expert on call to respond to any instances of voter machine problems or other irregularities associated with computer security. Instructor - Faculty Member Adjunct Faculty Member at the University of Denver Current instructor of Computer Forensics as part of the University of Denver's Master of Science degree in Computer Security Architecture. DOJ-OGR-00007839",
  "text_blocks": [
    {
      "type": "printed",
      "content": "Case 1:20-cr-00330-PAE Document 499-1 Filed 11/23/21 Page 346 of 375",
      "position": "header"
    },
    {
      "type": "printed",
      "content": "CURRICULUM VITAE Robert P. Kelso",
      "position": "top"
    },
    {
      "type": "printed",
      "content": "Forensic Pursuit 2000 Arapahoe Street, Suite 1 | Denver, Colorado 80205 Office (303) 495-2082 | Email Robert.Kelso@ForensicPursuit.com",
      "position": "top"
    },
    {
      "type": "printed",
      "content": "Trial testimony at the City and County Court of Denver, Colorado Honorable Judge Robert L. McGahey Monica David Vickery v. Evelyn Trumble and Merry Gayle Vickery Retained by Plaintiff Case No: 07 CV 7674 Date: 1/6/2009",
      "position": "middle"
    },
    {
      "type": "printed",
      "content": "Special Master Appointments United States District Court for the District of Colorado United States Magistrate Judge Michael E. Hegarty Civil Action No: 11-cv-02560-MSK-MEH Date: 11/7/2012 District Court, Arapahoe County, Colorado Case No: 2010 CV 2203 Date: 3/23/2011 District Court, Arapahoe County, Colorado Case No: 2005 CV 1944 Date: 7/19/2010 United States District Court for the District of Colorado Kristen L. Mix, United States Magistrate Judge Civil Action No: 09-cv-01099-MSK-KLM Date: 1/21/2010 District Court, Arapahoe County, Colorado Case No: 2009 CV 1694 Date: 9/9/2009 District Court, Adams County, Colorado Case No: 08DR1992 Date: 6/3/2009 District Court City and County of Broomfield Case No: 2006 DR 60 Date: 9/13/2008",
      "position": "middle"
    },
    {
      "type": "printed",
      "content": "Honors Selected by the Republican National Committee to act as the local (Denver) computer forensics expert on call to respond to any instances of voter machine problems or other irregularities associated with computer security.",
      "position": "middle"
    },
    {
      "type": "printed",
      "content": "Instructor - Faculty Member Adjunct Faculty Member at the University of Denver Current instructor of Computer Forensics as part of the University of Denver's Master of Science degree in Computer Security Architecture.",
      "position": "bottom"
    },
    {
      "type": "printed",
      "content": "DOJ-OGR-00007839",
      "position": "footer"
    }
  ],
  "entities": {
    "people": [
      "Robert P. Kelso",
      "Robert L. McGahey",
      "Monica David Vickery",
      "Evelyn Trumble",
      "Merry Gayle Vickery",
      "Michael E. Hegarty",
      "Kristen L. Mix"
    ],
    "organizations": [
      "Forensic Pursuit",
      "City and County Court of Denver",
      "United States District Court for the District of Colorado",
      "District Court, Arapahoe County",
      "District Court, Adams County",
      "District Court City and County of Broomfield",
      "Republican National Committee",
      "University of Denver"
    ],
    "locations": [
      "Denver",
      "Colorado",
      "Arapahoe County",
      "Adams County",
      "Broomfield"
    ],
    "dates": [
      "1/6/2009",
      "11/7/2012",
      "3/23/2011",
      "7/19/2010",
      "1/21/2010",
      "9/9/2009",
      "6/3/2009",
      "9/13/2008",
      "11/23/21"
    ],
    "reference_numbers": [
      "07 CV 7674",
      "11-cv-02560-MSK-MEH",
      "2010 CV 2203",
      "2005 CV 1944",
      "09-cv-01099-MSK-KLM",
      "2009 CV 1694",
      "08DR1992",
      "2006 DR 60",
      "DOJ-OGR-00007839"
    ]
  },
  "additional_notes": "The document is a curriculum vitae for Robert P. Kelso, detailing his professional experience and qualifications in computer forensics."
}