{
  "document_metadata": {
    "page_number": "3",
    "document_number": "490",
    "date": "11/22/21",
    "document_type": "court document",
    "has_handwriting": true,
    "has_stamps": false
  },
  "full_text": "Case 1:20-cr-00330-PAE Document 490 Filed 11/22/21 Page 3 of 3\nThe Honorable Alison J. Nathan\nNovember 15, 2021\nPage 3\nauthentication. Ms. Maxwell requests that the government be precluded from discussing the book at trial prior to a proper evidentiary foundation being established. In addition, the government should be required to produce the entire book for inspection at trial and counsel for Ms. Maxwell should be afforded an opportunity to conduct voir dire of the exhibit with the proffering witness.\nRespectfully submitted,\nJeffrey S. Pagliuca\nLaura A. Menninger\nHADDON, MORGAN & FOREMAN P.C.\n150 East 10th Avenue\nDenver, CO 80203\nPhone: 303-831-7364\nChristian R. Everdell\nCOHEN & GRESSER LLP\n800 Third Avenue\nNew York, NY 10022\nPhone: 212-957-7600\nBobbi C. Sternheim\nLaw Offices of Bobbi C. Sternheim\n225 Broadway, Suite 715\nNew York, NY 10007\nPhone: 212-243-1100\nAttorneys for Ghislaine Maxwell\nDOJ-OGR-00007411",
  "text_blocks": [
    {
      "type": "printed",
      "content": "Case 1:20-cr-00330-PAE Document 490 Filed 11/22/21 Page 3 of 3",
      "position": "header"
    },
    {
      "type": "printed",
      "content": "The Honorable Alison J. Nathan\nNovember 15, 2021\nPage 3",
      "position": "top"
    },
    {
      "type": "printed",
      "content": "authentication. Ms. Maxwell requests that the government be precluded from discussing the book at trial prior to a proper evidentiary foundation being established. In addition, the government should be required to produce the entire book for inspection at trial and counsel for Ms. Maxwell should be afforded an opportunity to conduct voir dire of the exhibit with the proffering witness.",
      "position": "middle"
    },
    {
      "type": "printed",
      "content": "Respectfully submitted,",
      "position": "middle"
    },
    {
      "type": "handwritten",
      "content": "signature",
      "position": "middle"
    },
    {
      "type": "printed",
      "content": "Jeffrey S. Pagliuca\nLaura A. Menninger\nHADDON, MORGAN & FOREMAN P.C.\n150 East 10th Avenue\nDenver, CO 80203\nPhone: 303-831-7364\nChristian R. Everdell\nCOHEN & GRESSER LLP\n800 Third Avenue\nNew York, NY 10022\nPhone: 212-957-7600\nBobbi C. Sternheim\nLaw Offices of Bobbi C. Sternheim\n225 Broadway, Suite 715\nNew York, NY 10007\nPhone: 212-243-1100",
      "position": "bottom"
    },
    {
      "type": "printed",
      "content": "Attorneys for Ghislaine Maxwell",
      "position": "bottom"
    },
    {
      "type": "printed",
      "content": "DOJ-OGR-00007411",
      "position": "footer"
    }
  ],
  "entities": {
    "people": [
      "Alison J. Nathan",
      "Ghislaine Maxwell",
      "Jeffrey S. Pagliuca",
      "Laura A. Menninger",
      "Christian R. Everdell",
      "Bobbi C. Sternheim",
      "Ms. Maxwell"
    ],
    "organizations": [
      "HADDON, MORGAN & FOREMAN P.C.",
      "COHEN & GRESSER LLP",
      "Law Offices of Bobbi C. Sternheim"
    ],
    "locations": [
      "Denver, CO",
      "New York, NY"
    ],
    "dates": [
      "November 15, 2021",
      "11/22/21"
    ],
    "reference_numbers": [
      "1:20-cr-00330-PAE",
      "Document 490",
      "DOJ-OGR-00007411"
    ]
  },
  "additional_notes": "The document appears to be a court filing related to the case of Ghislaine Maxwell. The text is mostly printed, with one handwritten signature. There are no visible stamps or redactions. The document is well-formatted and legible."
}