{
  "document_metadata": {
    "page_number": "116",
    "document_number": "465",
    "date": "11/15/21",
    "document_type": "court transcript",
    "has_handwriting": false,
    "has_stamps": false
  },
  "full_text": "Case 1:20-cr-00330-PAE Document 465 Filed 11/15/21 Page 116 of 127 116 LB15max4\n1 Ms. Maxwell. Do you know anything about that?\n2 MS. MOE: Your Honor if I could have one moment?\n3 THE COURT: Sure.\n4 MS. MOE: Thank you.\n5 (Counsel conferring)\n6 MS. MOE: Your Honor, I don't have particular information about the series of disclosures we made last week and whether or not they've been processed by the MDC but we will certainly be conferring with the MDC in connection with a response to the defense's letter on Friday. Our understanding is that, generally, that drives have been received by MDC, processed through their warehouse, picked up by legal counsel and produced to the defense in regular time frame. I can't speak to any particular package that was mailed last week because I am hearing about it now for the first time.\n16 THE COURT: Well, OK. You will include in your letter -- I mean, I think at this point a week is too long. I think the representation in the prior letter was one to two days for legal mail, maybe this is different because this is different?\n21 MS. MOE: I don't believe so, your Honor. Part of the reason why I want to look into this and confer with my colleague is we are not quite sure whether the date was Monday or Wednesday that we produced this material to the defense and we want to just double-check the mailing date to make sure we\nSOUTHERN DISTRICT REPORTERS, P.C. (212) 805-0300 DOJ-OGR-00007167",
  "text_blocks": [
    {
      "type": "printed",
      "content": "Case 1:20-cr-00330-PAE Document 465 Filed 11/15/21 Page 116 of 127 116 LB15max4",
      "position": "header"
    },
    {
      "type": "printed",
      "content": "1 Ms. Maxwell. Do you know anything about that?\n2 MS. MOE: Your Honor if I could have one moment?\n3 THE COURT: Sure.\n4 MS. MOE: Thank you.\n5 (Counsel conferring)\n6 MS. MOE: Your Honor, I don't have particular information about the series of disclosures we made last week and whether or not they've been processed by the MDC but we will certainly be conferring with the MDC in connection with a response to the defense's letter on Friday. Our understanding is that, generally, that drives have been received by MDC, processed through their warehouse, picked up by legal counsel and produced to the defense in regular time frame. I can't speak to any particular package that was mailed last week because I am hearing about it now for the first time.\n16 THE COURT: Well, OK. You will include in your letter -- I mean, I think at this point a week is too long. I think the representation in the prior letter was one to two days for legal mail, maybe this is different because this is different?\n21 MS. MOE: I don't believe so, your Honor. Part of the reason why I want to look into this and confer with my colleague is we are not quite sure whether the date was Monday or Wednesday that we produced this material to the defense and we want to just double-check the mailing date to make sure we",
      "position": "main content"
    },
    {
      "type": "printed",
      "content": "SOUTHERN DISTRICT REPORTERS, P.C. (212) 805-0300",
      "position": "footer"
    },
    {
      "type": "printed",
      "content": "DOJ-OGR-00007167",
      "position": "footer"
    }
  ],
  "entities": {
    "people": [
      "Maxwell",
      "Moe"
    ],
    "organizations": [
      "MDC",
      "SOUTHERN DISTRICT REPORTERS, P.C."
    ],
    "locations": [],
    "dates": [
      "11/15/21",
      "Friday",
      "Monday",
      "Wednesday"
    ],
    "reference_numbers": [
      "1:20-cr-00330-PAE",
      "Document 465",
      "DOJ-OGR-00007167"
    ]
  },
  "additional_notes": "The document appears to be a court transcript with a clear and legible format. There are no visible redactions or damage."
}