{
  "document_metadata": {
    "page_number": "24 of 24",
    "document_number": "443",
    "date": "11/12/21",
    "document_type": "Certificate of Service",
    "has_handwriting": false,
    "has_stamps": false
  },
  "full_text": "Case 1:20-cr-00330-PAE Document 443 Filed 11/12/21 Page 24 of 24 Certificate of Service I hereby certify that on October 18, 2021, I electronically filed the foregoing Ghislaine Maxwell's Motion to Exclude Under Federal Rule of Evidence 702 and Daubert v. Merrell Dow Pharmaceuticals, Inc., 509 U.S. 579 (1993) and Request for Daubert Hearing with the Clerk of Court using the CM/ECF system which will send notification of such filing to the following: Alison Moe Maurene Comey Andrew Rohrbach Lara Pomerantz U.S. Attorney's Office, SDNY One Saint Andrew's Plaza New York, NY 10007 Alison.moe@usdoj.gov Maurene.comey@usdoj.gov Andrew.Rohrbach@usdoj.gov Lara.Pomerantz@usdoj.gov s/ Nicole Simmons 19 DOJ-OGR-00006610",
  "text_blocks": [
    {
      "type": "printed",
      "content": "Case 1:20-cr-00330-PAE Document 443 Filed 11/12/21 Page 24 of 24",
      "position": "header"
    },
    {
      "type": "printed",
      "content": "Certificate of Service",
      "position": "top"
    },
    {
      "type": "printed",
      "content": "I hereby certify that on October 18, 2021, I electronically filed the foregoing Ghislaine Maxwell's Motion to Exclude Under Federal Rule of Evidence 702 and Daubert v. Merrell Dow Pharmaceuticals, Inc., 509 U.S. 579 (1993) and Request for Daubert Hearing with the Clerk of Court using the CM/ECF system which will send notification of such filing to the following:",
      "position": "middle"
    },
    {
      "type": "printed",
      "content": "Alison Moe Maurene Comey Andrew Rohrbach Lara Pomerantz U.S. Attorney's Office, SDNY One Saint Andrew's Plaza New York, NY 10007 Alison.moe@usdoj.gov Maurene.comey@usdoj.gov Andrew.Rohrbach@usdoj.gov Lara.Pomerantz@usdoj.gov",
      "position": "middle"
    },
    {
      "type": "signature",
      "content": "s/ Nicole Simmons",
      "position": "bottom"
    },
    {
      "type": "printed",
      "content": "19 DOJ-OGR-00006610",
      "position": "footer"
    }
  ],
  "entities": {
    "people": [
      "Ghislaine Maxwell",
      "Alison Moe",
      "Maurene Comey",
      "Andrew Rohrbach",
      "Lara Pomerantz",
      "Nicole Simmons"
    ],
    "organizations": [
      "U.S. Attorney's Office, SDNY"
    ],
    "locations": [
      "New York"
    ],
    "dates": [
      "October 18, 2021",
      "11/12/21"
    ],
    "reference_numbers": [
      "1:20-cr-00330-PAE",
      "Document 443",
      "DOJ-OGR-00006610"
    ]
  },
  "additional_notes": "The document is a Certificate of Service, indicating that a motion was filed electronically on October 18, 2021. The document is well-formatted and clear, with no visible redactions or damage."
}