{
  "document_metadata": {
    "page_number": "87",
    "document_number": "410-1",
    "date": "11/04/21",
    "document_type": "court document",
    "has_handwriting": false,
    "has_stamps": false
  },
  "full_text": "Case 1:20-cr-00330-PAE Document 410-1 Filed 11/04/21 Page 87 of 93\n\nRedaction Of Evidentiary Items\n[If Applicable]\nWe have, among the exhibits received in evidence, some documents that are redacted. \"Redacted\" means that part of the document has been taken out. Material may be redacted for any number of reasons, including that it is not relevant to the issues you must decide in this case, among other reasons. You are to concern yourself only with the part of the item that has been admitted into evidence, and you should not consider any possible reason for the redactions.\n\nAdapted from the charge of the Hon. Alison J. Nathan in United States v. Jones, 16 Cr. 553 (AJN); and the charge of the Hon. Richard J. Sullivan, Jury Charge, United States v. Adony Nina, et al., 13 Cr. 322 (S.D.N.Y. 2013).\n\n87\n\nDOJ-OGR-00006153",
  "text_blocks": [
    {
      "type": "printed",
      "content": "Case 1:20-cr-00330-PAE Document 410-1 Filed 11/04/21 Page 87 of 93",
      "position": "header"
    },
    {
      "type": "printed",
      "content": "Redaction Of Evidentiary Items",
      "position": "top"
    },
    {
      "type": "printed",
      "content": "[If Applicable]",
      "position": "top"
    },
    {
      "type": "printed",
      "content": "We have, among the exhibits received in evidence, some documents that are redacted. \"Redacted\" means that part of the document has been taken out. Material may be redacted for any number of reasons, including that it is not relevant to the issues you must decide in this case, among other reasons. You are to concern yourself only with the part of the item that has been admitted into evidence, and you should not consider any possible reason for the redactions.",
      "position": "middle"
    },
    {
      "type": "printed",
      "content": "Adapted from the charge of the Hon. Alison J. Nathan in United States v. Jones, 16 Cr. 553 (AJN); and the charge of the Hon. Richard J. Sullivan, Jury Charge, United States v. Adony Nina, et al., 13 Cr. 322 (S.D.N.Y. 2013).",
      "position": "middle"
    },
    {
      "type": "printed",
      "content": "87",
      "position": "footer"
    },
    {
      "type": "printed",
      "content": "DOJ-OGR-00006153",
      "position": "footer"
    }
  ],
  "entities": {
    "people": [
      "Alison J. Nathan",
      "Richard J. Sullivan",
      "Adony Nina",
      "Jones"
    ],
    "organizations": [
      "United States"
    ],
    "locations": [
      "S.D.N.Y."
    ],
    "dates": [
      "11/04/21",
      "2013"
    ],
    "reference_numbers": [
      "1:20-cr-00330-PAE",
      "410-1",
      "16 Cr. 553",
      "13 Cr. 322",
      "DOJ-OGR-00006153"
    ]
  },
  "additional_notes": "The document appears to be a court filing with a clear and legible text. There are no visible redactions or handwritten notes on the page. The document is related to a court case and includes references to other court cases and judges."
}