{
  "document_metadata": {
    "page_number": "153",
    "document_number": "467",
    "date": "11/15/21",
    "document_type": "court transcript",
    "has_handwriting": false,
    "has_stamps": false
  },
  "full_text": "Case 1:20-cr-00330-PAE Document 467 Filed 11/15/21 Page 153 of 158 153 LBAAMAX5ps Rocchio - Cross\n\n1 THE COURT: And I would suggest that the microphone point directly at you.\n2\n3 MR. PAGLIUCA: Yes.\n4 THE COURT: Go ahead.\n5 A. So the significance of delayed disclosure as it relates to my opinion is, it is part of our understanding of phenomenology of child sexual abuse and the ways in which individuals tell.\n6 So I'm not identifying delayed disclosure as a predictor. I'm simply saying that it is a common phenomenon that is observed in the scientific literature to occur among children who are sexually abused.\n7\n8 Q. Well, there are many other reasons why these reports may surface not immediately. Correct?\n9 A. Again, I'm commenting at this point my opinion is that delayed disclosure is common. I'm not -- do you have a question about the reasons why?\n10 Q. Yeah. There are many reasons why. There are allegations that are made months, weeks, years, after an alleged event. Correct?\n11 A. Correct.\n12 Q. And they may or may not have anything to do with the veracity of the allegation. Correct?\n13 A. The reasons may not have -- again, are you -- I mean, are you asking me, can people make false claims?\n14 Q. Yes.\n15\nSOUTHERN DISTRICT REPORTERS, P.C. (212) 805-0300\nDOJ-OGR-00007332",
  "text_blocks": [
    {
      "type": "printed",
      "content": "Case 1:20-cr-00330-PAE Document 467 Filed 11/15/21 Page 153 of 158 153 LBAAMAX5ps Rocchio - Cross",
      "position": "header"
    },
    {
      "type": "printed",
      "content": "THE COURT: And I would suggest that the microphone point directly at you.\nMR. PAGLIUCA: Yes.\nTHE COURT: Go ahead.\nA. So the significance of delayed disclosure as it relates to my opinion is, it is part of our understanding of phenomenology of child sexual abuse and the ways in which individuals tell.\nSo I'm not identifying delayed disclosure as a predictor. I'm simply saying that it is a common phenomenon that is observed in the scientific literature to occur among children who are sexually abused.\nQ. Well, there are many other reasons why these reports may surface not immediately. Correct?\nA. Again, I'm commenting at this point my opinion is that delayed disclosure is common. I'm not -- do you have a question about the reasons why?\nQ. Yeah. There are many reasons why. There are allegations that are made months, weeks, years, after an alleged event. Correct?\nA. Correct.\nQ. And they may or may not have anything to do with the veracity of the allegation. Correct?\nA. The reasons may not have -- again, are you -- I mean, are you asking me, can people make false claims?\nQ. Yes.",
      "position": "main"
    },
    {
      "type": "printed",
      "content": "SOUTHERN DISTRICT REPORTERS, P.C. (212) 805-0300",
      "position": "footer"
    },
    {
      "type": "printed",
      "content": "DOJ-OGR-00007332",
      "position": "footer"
    }
  ],
  "entities": {
    "people": [
      "MR. PAGLIUCA"
    ],
    "organizations": [
      "SOUTHERN DISTRICT REPORTERS, P.C."
    ],
    "locations": [],
    "dates": [
      "11/15/21"
    ],
    "reference_numbers": [
      "1:20-cr-00330-PAE",
      "Document 467",
      "DOJ-OGR-00007332"
    ]
  },
  "additional_notes": "The document appears to be a court transcript with a clear and legible format. There are no visible redactions or damage."
}