{
  "document_metadata": {
    "page_number": "142 of 375",
    "document_number": "499-1",
    "date": "11/23/21",
    "document_type": "court document",
    "has_handwriting": false,
    "has_stamps": false
  },
  "full_text": "Case 1:20-cr-00330-PAE Document 499-1 Filed 11/23/21 Page 142 of 375 Park Dietz, M.D., M.P.H., Ph.D. Page 80 2017 Intimate Partner Violence and the Workplace (e-learning course) 2017 Stalking (e-learning course) 2017 Cybersstalking and Related Misconduct (e-learning course) 2017 Life Stress, Personality Disorder, and Substance Abuse (e-learning course) 2017 Mental Illnesses and Suicide Prevention (e-learning course) 2017 Safe Termination (e-learning course) 2017 Problematic Former Employees (e-learning course) 2017 Managing Unwanted Communications and Visits (e-learning course) 2017 Preparing for an Armed Attack (e-learning course) 2017 Managing Troubled People (e-learning course) 2017 Managing Troubling Situations (e-learning course) 2017 Responding to an Armed Attack (e-learning course) 2017 Your Role in Workplace Violence Prevention (e-learning course) 2017 Gatekeeper Safety: How to Deal with Unwanted Writings, Calls and Visits (e-learning course) 2019 Managing Troubled People (e-learning course) 2019 Managing Troubling Situations (e-learning course) 2019 Responding to an Armed Attack (e-learning course) 2019 Your Role in Workplace Violence Prevention (e-learning course) DOJ-OGR-00007635",
  "text_blocks": [
    {
      "type": "printed",
      "content": "Case 1:20-cr-00330-PAE Document 499-1 Filed 11/23/21 Page 142 of 375",
      "position": "header"
    },
    {
      "type": "printed",
      "content": "Park Dietz, M.D., M.P.H., Ph.D. Page 80",
      "position": "header"
    },
    {
      "type": "printed",
      "content": "2017 Intimate Partner Violence and the Workplace (e-learning course)\n2017 Stalking (e-learning course)\n2017 Cybersstalking and Related Misconduct (e-learning course)\n2017 Life Stress, Personality Disorder, and Substance Abuse (e-learning course)\n2017 Mental Illnesses and Suicide Prevention (e-learning course)\n2017 Safe Termination (e-learning course)\n2017 Problematic Former Employees (e-learning course)\n2017 Managing Unwanted Communications and Visits (e-learning course)\n2017 Preparing for an Armed Attack (e-learning course)\n2017 Managing Troubled People (e-learning course)\n2017 Managing Troubling Situations (e-learning course)\n2017 Responding to an Armed Attack (e-learning course)\n2017 Your Role in Workplace Violence Prevention (e-learning course)\n2017 Gatekeeper Safety: How to Deal with Unwanted Writings, Calls and Visits (e-learning course)\n2019 Managing Troubled People (e-learning course)\n2019 Managing Troubling Situations (e-learning course)\n2019 Responding to an Armed Attack (e-learning course)\n2019 Your Role in Workplace Violence Prevention (e-learning course)",
      "position": "main"
    },
    {
      "type": "printed",
      "content": "DOJ-OGR-00007635",
      "position": "footer"
    }
  ],
  "entities": {
    "people": [
      "Park Dietz"
    ],
    "organizations": [
      "DOJ"
    ],
    "locations": [],
    "dates": [
      "2017",
      "2019",
      "11/23/21"
    ],
    "reference_numbers": [
      "1:20-cr-00330-PAE",
      "499-1",
      "DOJ-OGR-00007635"
    ]
  },
  "additional_notes": "The document appears to be a court filing with a list of e-learning courses taken by an expert witness, Park Dietz, in the years 2017 and 2019. The document is well-formatted and legible."
}