{
  "document_metadata": {
    "page_number": "1 of 3",
    "document_number": "539",
    "date": "12/12/21",
    "document_type": "Letter",
    "has_handwriting": false,
    "has_stamps": true
  },
  "full_text": "Case 1:20-cr-00330-PAE Document 539 Filed 12/12/21 Page 1 of 3 U.S. Department of Justice United States Attorney Southern District of New York The Silvio J. Mollo Building One Saint Andrew's Plaza New York, New York 10007 December 12, 2021 BY ECF The Honorable Alison J. Nathan United States District Court Southern District of New York United States Courthouse 40 Foley Square New York, New York 10007 Re: United States v. Ghislaine Maxwell, S2 20 Cr. 330 (AJN) Dear Judge Nathan: The Government respectfully submits this letter seeking an order directing the defense to provide the Government with the witnesses it anticipates calling next week by 10:00 a.m. tomorrow, December 13, 2021.1 The Government previewed for several days prior to the close of the Government's case that it would rest sometime last week. Following the close of the Government's case, the Government requested that the defense provide the Government with Rule 26.2 material, along with \"a list of witnesses, and an order of the first witnesses.\" Tr. 2276. The Court ordered the defense to do so, stating, \"Yes. You'll do that.\" Id. 1 The defense also made an untimely production of Rule 16 materials on Friday evening, following the close of the Government's case. The Government will file a motion to preclude later this evening. 1 DOJ-OGR-00008357",
  "text_blocks": [
    {
      "type": "printed",
      "content": "Case 1:20-cr-00330-PAE Document 539 Filed 12/12/21 Page 1 of 3",
      "position": "header"
    },
    {
      "type": "printed",
      "content": "U.S. Department of Justice United States Attorney Southern District of New York The Silvio J. Mollo Building One Saint Andrew's Plaza New York, New York 10007 December 12, 2021",
      "position": "top"
    },
    {
      "type": "printed",
      "content": "BY ECF The Honorable Alison J. Nathan United States District Court Southern District of New York United States Courthouse 40 Foley Square New York, New York 10007 Re: United States v. Ghislaine Maxwell, S2 20 Cr. 330 (AJN) Dear Judge Nathan:",
      "position": "middle"
    },
    {
      "type": "printed",
      "content": "The Government respectfully submits this letter seeking an order directing the defense to provide the Government with the witnesses it anticipates calling next week by 10:00 a.m. tomorrow, December 13, 2021.1 The Government previewed for several days prior to the close of the Government's case that it would rest sometime last week. Following the close of the Government's case, the Government requested that the defense provide the Government with Rule 26.2 material, along with \"a list of witnesses, and an order of the first witnesses.\" Tr. 2276. The Court ordered the defense to do so, stating, \"Yes. You'll do that.\" Id. 1 The defense also made an untimely production of Rule 16 materials on Friday evening, following the close of the Government's case. The Government will file a motion to preclude later this evening.",
      "position": "middle"
    },
    {
      "type": "printed",
      "content": "1 DOJ-OGR-00008357",
      "position": "footer"
    }
  ],
  "entities": {
    "people": [
      "Alison J. Nathan",
      "Ghislaine Maxwell"
    ],
    "organizations": [
      "U.S. Department of Justice",
      "United States Attorney",
      "United States District Court"
    ],
    "locations": [
      "New York",
      "Southern District of New York"
    ],
    "dates": [
      "December 12, 2021",
      "December 13, 2021"
    ],
    "reference_numbers": [
      "1:20-cr-00330-PAE",
      "Document 539",
      "S2 20 Cr. 330 (AJN)",
      "DOJ-OGR-00008357"
    ]
  },
  "additional_notes": "The document appears to be a formal letter from the U.S. Department of Justice to the Honorable Alison J. Nathan regarding the case United States v. Ghislaine Maxwell. The document is typed and contains a stamp from the U.S. Department of Justice. There are no visible redactions or damage."
}