{
  "document_metadata": {
    "page_number": "149",
    "document_number": "499-1",
    "date": "11/23/21",
    "document_type": "court document",
    "has_handwriting": false,
    "has_stamps": false
  },
  "full_text": "Case 1:20-cr-00330-PAE Document 499-1 Filed 11/23/21 Page 149 of 375\nPark Dietz, M.D., M.P.H., Ph.D.\nPage 87\nMead Corporation, Dayton, OH, July 11-12, 2000\nOrganization Resource Counselors (Corporate Medical Directors), Washington, DC, August 1, 2000\n\"Workplace Violence 8 East: An Intensive Course Designed for Fortune 500 Companies and Selected Private and Government Organizations,\" New York, NY, October 2-4, 2000\n\"Investigation, Interviewing, and Termination,\" New York, NY, October 5-6, 2000\nPaineWebber, Weehawken, NJ, December 12-14, 2000\nAmerican Express, Phoenix, AZ, February 20, 2001\n\"Workplace Violence 9: An Intensive Course Designed for Fortune 500 Companies and Selected Private and Government Organizations,\" Newport Beach, CA, April 23-25, 2001\nThomson Legal & Regulatory, Egan, MN, April 15-16, 2001\nChiron Corporation, Emeryville, CA, May 31, 2001\nAllergan, Inc., Irvine, CA, June 5, 2001\nAT&T Broadband, Englewood, CO, June 14, 2001 Jefferson County, Colorado, Golden, CO, June 15, 2001\nFederated Department Stores (Arizona Mail Order), Tucson, AZ, June 19-20, 2001\nCorning, Inc., Corning, NY, September 11, 2001\nFederated Department Stores (Federated Marketing Group), New York, NY, November 15-16, 2001\nPaineWebber, Weehawken, NJ, November 19-20, 2001\n\"Workplace Violence 10: An Intensive Course Designed for Fortune 500 Companies and Selected Private and Government Organizations,\" Newport Beach, CA, April 15-17, 2002\nTribune Company, Chicago, IL, May 15, 2002\nDOJ-OGR-00007642",
  "text_blocks": [
    {
      "type": "printed",
      "content": "Case 1:20-cr-00330-PAE Document 499-1 Filed 11/23/21 Page 149 of 375",
      "position": "header"
    },
    {
      "type": "printed",
      "content": "Park Dietz, M.D., M.P.H., Ph.D.\nPage 87",
      "position": "top"
    },
    {
      "type": "printed",
      "content": "Mead Corporation, Dayton, OH, July 11-12, 2000\nOrganization Resource Counselors (Corporate Medical Directors), Washington, DC, August 1, 2000\n\"Workplace Violence 8 East: An Intensive Course Designed for Fortune 500 Companies and Selected Private and Government Organizations,\" New York, NY, October 2-4, 2000\n\"Investigation, Interviewing, and Termination,\" New York, NY, October 5-6, 2000\nPaineWebber, Weehawken, NJ, December 12-14, 2000\nAmerican Express, Phoenix, AZ, February 20, 2001\n\"Workplace Violence 9: An Intensive Course Designed for Fortune 500 Companies and Selected Private and Government Organizations,\" Newport Beach, CA, April 23-25, 2001\nThomson Legal & Regulatory, Egan, MN, April 15-16, 2001\nChiron Corporation, Emeryville, CA, May 31, 2001\nAllergan, Inc., Irvine, CA, June 5, 2001\nAT&T Broadband, Englewood, CO, June 14, 2001 Jefferson County, Colorado, Golden, CO, June 15, 2001\nFederated Department Stores (Arizona Mail Order), Tucson, AZ, June 19-20, 2001\nCorning, Inc., Corning, NY, September 11, 2001\nFederated Department Stores (Federated Marketing Group), New York, NY, November 15-16, 2001\nPaineWebber, Weehawken, NJ, November 19-20, 2001\n\"Workplace Violence 10: An Intensive Course Designed for Fortune 500 Companies and Selected Private and Government Organizations,\" Newport Beach, CA, April 15-17, 2002\nTribune Company, Chicago, IL, May 15, 2002",
      "position": "middle"
    },
    {
      "type": "printed",
      "content": "DOJ-OGR-00007642",
      "position": "footer"
    }
  ],
  "entities": {
    "people": [
      "Park Dietz"
    ],
    "organizations": [
      "Mead Corporation",
      "Organization Resource Counselors",
      "PaineWebber",
      "American Express",
      "Thomson Legal & Regulatory",
      "Chiron Corporation",
      "Allergan, Inc.",
      "AT&T Broadband",
      "Federated Department Stores",
      "Corning, Inc.",
      "Tribune Company"
    ],
    "locations": [
      "Dayton, OH",
      "Washington, DC",
      "New York, NY",
      "Weehawken, NJ",
      "Phoenix, AZ",
      "Newport Beach, CA",
      "Egan, MN",
      "Emeryville, CA",
      "Irvine, CA",
      "Englewood, CO",
      "Golden, CO",
      "Tucson, AZ",
      "Corning, NY",
      "Chicago, IL"
    ],
    "dates": [
      "July 11-12, 2000",
      "August 1, 2000",
      "October 2-4, 2000",
      "October 5-6, 2000",
      "December 12-14, 2000",
      "February 20, 2001",
      "April 23-25, 2001",
      "April 15-16, 2001",
      "May 31, 2001",
      "June 5, 2001",
      "June 14, 2001",
      "June 15, 2001",
      "June 19-20, 2001",
      "September 11, 2001",
      "November 15-16, 2001",
      "November 19-20, 2001",
      "April 15-17, 2002",
      "May 15, 2002"
    ],
    "reference_numbers": [
      "1:20-cr-00330-PAE",
      "499-1",
      "DOJ-OGR-00007642"
    ]
  },
  "additional_notes": "The document appears to be a court filing with a list of events or presentations attended by Park Dietz. The text is clear and legible, with no visible redactions or damage."
}