{
  "document_metadata": {
    "page_number": "124",
    "document_number": "499-1",
    "date": "11/23/21",
    "document_type": "court document",
    "has_handwriting": false,
    "has_stamps": false
  },
  "full_text": "Case 1:20-cr-00330-PAE Document 499-1 Filed 11/23/21 Page 124 of 375\nPark Dietz, M.D., M.P.H., Ph.D.\nPage 62\n126. Dietz P: \"Bullying and the Spectrum of Workplace Misconduct,\" Employee Assistance Roundtable, San Diego, CA, October 24, 2007\n127. Dietz P: \"The Sexual Tortfeasor: Implications for Litigation and Prevention,\" Butler Pappas' Sexual Tort Seminar, Tampa, FL, June 26, 2008\n128. Dietz P: \"Behavioral Warnings of Attacks on Public Figures and Their Families,\" Keynote Address, 2008 Executive Security International Alumni Conference, Las Vegas, NV, August 9, 2008\n129. Dietz P: \"Current Mental Health Issues,\" 2008 Summer Conference of the Association of Government Attorneys in Capital Litigation, San Francisco, CA, August 30, 2008\n130. Dietz P: \"The Role of Forensic Expertise in Capital Crimes Litigation,\" U.S. Department of Justice, Capital Crimes Symposium, Columbia, SC, November 14, 2008\n131. Dietz P: \"The Mind: Investigating and Preparing for Mental Defenses and Mitigation,\" National District Attorneys Association Forensic Evidence Course, San Francisco, CA, December 10, 2008\n132. Dietz P: \"Evidence-Based Forensic Psychiatry,\" 2nd World Thematic Conference on Legal & Forensic Psychiatry, Spanish Society of Legal Psychiatry and World Psychiatric Association, Toledo, Spain, June 17, 2009\n133. Dietz P: \"Evidence-Based Forensic Psychiatry,\" American Academy of Forensic Sciences, Seattle, WA, February 25, 2010\n134. Dietz P: \"New Insights into Columbine,\" American Society for Adolescent Psychiatry, Los Angeles, CA, March 6, 2010\n135. Dietz P: \"Preparing for Mental Defenses,\" International Criminal Investigative Analysis Fellowship, Myrtle Beach, SC, May 3, 2010\n136. Dietz P: \"Dangerous Delusions: When Fans are a Threat,\" National District Attorneys Association, Napa, CA, July 14, 2010\n137. Dietz P: Keynote Address: \"Health Care Workers as Victims of Threats and Stalking,\" International Association for Healthcare\nDOJ-OGR-00007617",
  "text_blocks": [
    {
      "type": "printed",
      "content": "Case 1:20-cr-00330-PAE Document 499-1 Filed 11/23/21 Page 124 of 375",
      "position": "header"
    },
    {
      "type": "printed",
      "content": "Park Dietz, M.D., M.P.H., Ph.D.\nPage 62",
      "position": "header"
    },
    {
      "type": "printed",
      "content": "126. Dietz P: \"Bullying and the Spectrum of Workplace Misconduct,\" Employee Assistance Roundtable, San Diego, CA, October 24, 2007\n127. Dietz P: \"The Sexual Tortfeasor: Implications for Litigation and Prevention,\" Butler Pappas' Sexual Tort Seminar, Tampa, FL, June 26, 2008\n128. Dietz P: \"Behavioral Warnings of Attacks on Public Figures and Their Families,\" Keynote Address, 2008 Executive Security International Alumni Conference, Las Vegas, NV, August 9, 2008\n129. Dietz P: \"Current Mental Health Issues,\" 2008 Summer Conference of the Association of Government Attorneys in Capital Litigation, San Francisco, CA, August 30, 2008\n130. Dietz P: \"The Role of Forensic Expertise in Capital Crimes Litigation,\" U.S. Department of Justice, Capital Crimes Symposium, Columbia, SC, November 14, 2008\n131. Dietz P: \"The Mind: Investigating and Preparing for Mental Defenses and Mitigation,\" National District Attorneys Association Forensic Evidence Course, San Francisco, CA, December 10, 2008\n132. Dietz P: \"Evidence-Based Forensic Psychiatry,\" 2nd World Thematic Conference on Legal & Forensic Psychiatry, Spanish Society of Legal Psychiatry and World Psychiatric Association, Toledo, Spain, June 17, 2009\n133. Dietz P: \"Evidence-Based Forensic Psychiatry,\" American Academy of Forensic Sciences, Seattle, WA, February 25, 2010\n134. Dietz P: \"New Insights into Columbine,\" American Society for Adolescent Psychiatry, Los Angeles, CA, March 6, 2010\n135. Dietz P: \"Preparing for Mental Defenses,\" International Criminal Investigative Analysis Fellowship, Myrtle Beach, SC, May 3, 2010\n136. Dietz P: \"Dangerous Delusions: When Fans are a Threat,\" National District Attorneys Association, Napa, CA, July 14, 2010\n137. Dietz P: Keynote Address: \"Health Care Workers as Victims of Threats and Stalking,\" International Association for Healthcare",
      "position": "main content"
    },
    {
      "type": "printed",
      "content": "DOJ-OGR-00007617",
      "position": "footer"
    }
  ],
  "entities": {
    "people": [
      "Park Dietz",
      "Butler Pappas"
    ],
    "organizations": [
      "Employee Assistance Roundtable",
      "U.S. Department of Justice",
      "National District Attorneys Association",
      "American Academy of Forensic Sciences",
      "American Society for Adolescent Psychiatry",
      "International Criminal Investigative Analysis Fellowship",
      "International Association for Healthcare",
      "Spanish Society of Legal Psychiatry",
      "World Psychiatric Association"
    ],
    "locations": [
      "San Diego, CA",
      "Tampa, FL",
      "Las Vegas, NV",
      "San Francisco, CA",
      "Columbia, SC",
      "Toledo, Spain",
      "Seattle, WA",
      "Los Angeles, CA",
      "Myrtle Beach, SC",
      "Napa, CA"
    ],
    "dates": [
      "October 24, 2007",
      "June 26, 2008",
      "August 9, 2008",
      "August 30, 2008",
      "November 14, 2008",
      "December 10, 2008",
      "June 17, 2009",
      "February 25, 2010",
      "March 6, 2010",
      "May 3, 2010",
      "July 14, 2010",
      "11/23/21"
    ],
    "reference_numbers": [
      "1:20-cr-00330-PAE",
      "499-1",
      "DOJ-OGR-00007617"
    ]
  },
  "additional_notes": "The document appears to be a court filing with a list of presentations by Park Dietz. The text is clear and legible, with no visible redactions or damage."
}