{
  "document_metadata": {
    "page_number": "1",
    "document_number": "421",
    "date": "11/08/21",
    "document_type": "Court Order",
    "has_handwriting": true,
    "has_stamps": true
  },
  "full_text": "Case 1:20-cr-00330-PAE Document 421 Filed 11/08/21 Page 1 of 1\nUNITED STATES DISTRICT COURT SOUTHERN DISTRICT OF NEW YORK\nUnited States of America,\n-v-\nGhislain Maxwell,\nDefendant.\n20-CR-330 (AJN)\nORDER\nALISON J. NATHAN, District Judge:\nA conference is scheduled for November 10, 2021 to address the Defendant's motion under Federal Rule of Evidence 412, Dkt. No. 378, the Defendant's motion in limine to exclude under Federal Rule of Evidence 702 and Daubert v. Merrell Dow Pharmaceuticals, Inc., 509 U.S. 579 (1993), Dkt. No. 386, and the other outstanding issues that overlap with these two motions as discussed at the November 1, 2021 conference. Dkt. No. 409.\nThe parties are ORDERED to confirm by 12:00 p.m. tomorrow, November 9, 2021, that the alleged victims referenced in the Defendant's Rule 412 Motion have been notified of the November 10 hearing and of their right to attend.\nSO ORDERED.\nDated: November 8, 2021 New York, New York\nALISON J. NATHAN United States District Judge\n1\nDOJ-OGR-00006198",
  "text_blocks": [
    {
      "type": "printed",
      "content": "Case 1:20-cr-00330-PAE Document 421 Filed 11/08/21 Page 1 of 1",
      "position": "header"
    },
    {
      "type": "printed",
      "content": "UNITED STATES DISTRICT COURT SOUTHERN DISTRICT OF NEW YORK",
      "position": "header"
    },
    {
      "type": "printed",
      "content": "United States of America,\n-v-\nGhislain Maxwell,\nDefendant.",
      "position": "top"
    },
    {
      "type": "printed",
      "content": "20-CR-330 (AJN)\nORDER",
      "position": "top"
    },
    {
      "type": "printed",
      "content": "ALISON J. NATHAN, District Judge:",
      "position": "middle"
    },
    {
      "type": "printed",
      "content": "A conference is scheduled for November 10, 2021 to address the Defendant's motion under Federal Rule of Evidence 412, Dkt. No. 378, the Defendant's motion in limine to exclude under Federal Rule of Evidence 702 and Daubert v. Merrell Dow Pharmaceuticals, Inc., 509 U.S. 579 (1993), Dkt. No. 386, and the other outstanding issues that overlap with these two motions as discussed at the November 1, 2021 conference. Dkt. No. 409.",
      "position": "middle"
    },
    {
      "type": "printed",
      "content": "The parties are ORDERED to confirm by 12:00 p.m. tomorrow, November 9, 2021, that the alleged victims referenced in the Defendant's Rule 412 Motion have been notified of the November 10 hearing and of their right to attend.",
      "position": "middle"
    },
    {
      "type": "printed",
      "content": "SO ORDERED.",
      "position": "middle"
    },
    {
      "type": "printed",
      "content": "Dated: November 8, 2021 New York, New York",
      "position": "footer"
    },
    {
      "type": "handwritten",
      "content": "Alison J. Nathan",
      "position": "footer"
    },
    {
      "type": "printed",
      "content": "ALISON J. NATHAN United States District Judge",
      "position": "footer"
    },
    {
      "type": "stamp",
      "content": "USDC SDNY DOCUMENT ELECTRONICALLY FILED DOC #: DATE FILED: 11/8/21",
      "position": "margin"
    }
  ],
  "entities": {
    "people": [
      "Ghislain Maxwell",
      "Alison J. Nathan"
    ],
    "organizations": [
      "United States District Court",
      "United States of America"
    ],
    "locations": [
      "New York"
    ],
    "dates": [
      "November 10, 2021",
      "November 1, 2021",
      "November 9, 2021",
      "November 8, 2021"
    ],
    "reference_numbers": [
      "1:20-cr-00330-PAE",
      "Document 421",
      "20-CR-330 (AJN)",
      "Dkt. No. 378",
      "Dkt. No. 386",
      "Dkt. No. 409",
      "DOJ-OGR-00006198"
    ]
  },
  "additional_notes": "The document is a court order from the United States District Court for the Southern District of New York. It is signed by Judge Alison J. Nathan and dated November 8, 2021. The document appears to be in good condition with no visible damage or redactions."
}