{
  "document_metadata": {
    "page_number": "3",
    "document_number": "523",
    "date": "12/04/21",
    "document_type": "court document",
    "has_handwriting": false,
    "has_stamps": false
  },
  "full_text": "Case 1:20-cr-00330-PAE Document 523 Filed 12/04/21 Page 3 of 9\ncase,\" and \"[h]er memory of every single detail of her childhood is central to the case.\" (12/01/21 Tr. at 413). Accordingly, photographs that corroborate Jane's testimony are highly relevant.\nThere are two sets of photographs that are particularly corroborative: photographs of Epstein's massage room and photographs that corroborate details of other portions of Epstein's house.\nA. The Massage Room\nJane testified that she was sexually abused in the massage room of Epstein's New York house, and she gave detailed testimony about permanent features of the room. Photographs taken of the massage room specifically corroborate that testimony.2\nJane described the walls of the room: \"[I]t was very dark,\" \"I don't know if it was painted dark, but - or maybe that was the lighting, but it sort of had this, like, red mood. And then there was just a giant black massage table in the middle of it.\" (11/30/21 Tr. at 320). More generally, she testified that the house was decorated with \"fabric wallpaper, like red curtains.\" (11/30/21 Tr. at 318).\nAs depicted in Government Exhibit 903, among other photos of the massage room, the massage room has reddish dark walls with wallpaper and red curtains. A large massage table is located in the middle of the room:\n[Redacted]\nJane explained that the room had a \"built-in bookcase on the right-hand side, and there was a stereo system.\" (11/30/21 Tr. at 320).\n2 In particular, the Government seeks admission of Government Exhibits 902 through 904, 917, and 928.\n3\nDOJ-OGR-00008216",
  "text_blocks": [
    {
      "type": "printed",
      "content": "Case 1:20-cr-00330-PAE Document 523 Filed 12/04/21 Page 3 of 9",
      "position": "header"
    },
    {
      "type": "printed",
      "content": "case,\" and \"[h]er memory of every single detail of her childhood is central to the case.\" (12/01/21 Tr. at 413). Accordingly, photographs that corroborate Jane's testimony are highly relevant.\nThere are two sets of photographs that are particularly corroborative: photographs of Epstein's massage room and photographs that corroborate details of other portions of Epstein's house.",
      "position": "top"
    },
    {
      "type": "printed",
      "content": "A. The Massage Room",
      "position": "middle"
    },
    {
      "type": "printed",
      "content": "Jane testified that she was sexually abused in the massage room of Epstein's New York house, and she gave detailed testimony about permanent features of the room. Photographs taken of the massage room specifically corroborate that testimony.2\nJane described the walls of the room: \"[I]t was very dark,\" \"I don't know if it was painted dark, but - or maybe that was the lighting, but it sort of had this, like, red mood. And then there was just a giant black massage table in the middle of it.\" (11/30/21 Tr. at 320). More generally, she testified that the house was decorated with \"fabric wallpaper, like red curtains.\" (11/30/21 Tr. at 318).\nAs depicted in Government Exhibit 903, among other photos of the massage room, the massage room has reddish dark walls with wallpaper and red curtains. A large massage table is located in the middle of the room:\n[Redacted]\nJane explained that the room had a \"built-in bookcase on the right-hand side, and there was a stereo system.\" (11/30/21 Tr. at 320).",
      "position": "middle"
    },
    {
      "type": "printed",
      "content": "2 In particular, the Government seeks admission of Government Exhibits 902 through 904, 917, and 928.",
      "position": "footer"
    },
    {
      "type": "printed",
      "content": "3",
      "position": "footer"
    },
    {
      "type": "printed",
      "content": "DOJ-OGR-00008216",
      "position": "footer"
    }
  ],
  "entities": {
    "people": [
      "Jane",
      "Epstein"
    ],
    "organizations": [
      "Government"
    ],
    "locations": [
      "New York"
    ],
    "dates": [
      "12/01/21",
      "11/30/21",
      "12/04/21"
    ],
    "reference_numbers": [
      "1:20-cr-00330-PAE",
      "523",
      "902",
      "903",
      "904",
      "917",
      "928",
      "DOJ-OGR-00008216"
    ]
  },
  "additional_notes": "The document appears to be a court filing related to the case against Epstein. The text discusses the testimony of a witness named Jane and the relevance of photographs of Epstein's massage room. There is a redacted section in the document."
}