{
  "document_metadata": {
    "page_number": "34",
    "document_number": "499-1",
    "date": "11/23/21",
    "document_type": "Case 1:20-cr-00330-PAE",
    "has_handwriting": false,
    "has_stamps": false
  },
  "full_text": "Case 1:20-cr-00330-PAE Document 499-1 Filed 11/23/21 Page 34 of 375\n\nLoftus, E.F. (1994) Tricked by memory. In J. Jeffrey and G. Edwall (Eds). Memory and History: Essays on recalling and interpreting experience. NY: University Press of America. p. 17-29.\nGarry, M., Loftus, E.F., Brown, S.W. (1994) Memory: A river runs through it. Consciousness and Cognition, 3, 438-451.\nBelli, R.F. & Loftus, E.F. (1994) Recovered memories of childhood abuse: A source monitoring perspective. In Lynn, S.J. & Rhue, J. (Eds.) Dissociation: Theory, clinical, and research perspectives. NY: Guilford Press, p. 415-433.\nGarry, M. & Loftus, E.F. (1994) Pseudomemories without hypnosis. International Journal of Clinical and Experimental Hypnosis, Vol. XLII, 363-378.\nWeingardt, K.R., Toland, H.K., & Loftus, E.F. (1994) Reports of suggested memories: Do people truly believe them? In D. Ross, J.D. Read & M.P. Toglia (Eds.) Adult eyewitness testimony: Current trends and developments. NY: Springer-Verlag, pp. 3-26.\nCeci, S.J. & Loftus, E.F. (1994) \"Memory work\": A royal road to false memories? Applied Cognitive Psychology, 8, 351-364.\n- Reprinted in Honech, R.P. (1998) Introductory readings for Cognitive Psychology, 3rd Ed. Guilford, CT: Dushkin Publishing Group, Chapter 31, 267-277.\nCeci, S.J., Loftus, E.F., Leichtman, M.D., & Bruck, M. (1994) The possible role of source misattributions in the creation of false beliefs among preschoolers. International Journal of Clinical and Experimental Hypnosis, Vol. XLII, 304-320.\nCeci, S.J., Huffman, M.L.C., Smith, E., and Loftus, E.F. (1994) Repeatedly thinking about a non-event: Source misattributions among preschoolers. Consciousness and Cognition, 3, 388-407.\n\n1995\nWeingardt, K.R., Loftus, E.F., & Lindsay, D.S. (1995) Misinformation revisited: New evidence on the suggestibility of memory. Memory & Cognition, 23 (1), 72-82.\nLoftus, E.F., Milo, E.M., & Paddock, J.R. (1995) The accidental executioner: Why psychotherapy must be informed by science. The Counseling Psychologist, 23, 300-309.\nLoftus, E.F. & Pickrell, J.E. (1995) The formation of false memories. Psychiatric Annals, 25, 720-725.\n- Reprinted in: Psykologia, 1997, 32 (2). (Published in Finnish, pages 112a-112k).\nLoftus, E.F., Feldman, J., & Dashiell, R. (1995) The reality of illusory memories. In Schacter, D.L., Coyle, J.T., Fishbach, G.D., Mesulam, M.M., and Sullivan, L.E. (Eds.) Memory Distortion: How minds, brains and societies reconstruct the past. Cambridge, MA: Harvard University Press, p. 47-68\nLoftus, E.F. (1995) Remembering dangerously. Skeptical Inquirer, 19, 20-29.\nLoftus, E.F. (1995) Memory malleability: Constructivist and fuzzy-trace explanations. Learning and Individual Differences, 7, 133-137..\nClark, S.E. & Loftus, E.F. (1995) The psychological pay-dirt of space-alien abduction memories. Review of Mack, J. (1995) Abduction: Human encounters with aliens. Contemporary Psychology,40, 861-863.\nLoftus, E.F, & Yapko, M. (1995) Psychotherapy and the recovery of repressed memories. In Ney, T. (Ed.) Allegations in Child Sexual Abuse: Assessment and case management. Brunner/Mazel, p. 176-191.\nLeichtman, M.D., Loftus, E.F., & Ceci, S.J. (1995) Current issues in early eyewitness memory. Scalpel and Quill: Bulletin of the Pittsburgh Institute of Legal Medicine, 30, 1-71. (Copies available from Pittsburgh Institute of Legal Medicine, 1200 Centre Ave, Pittsburgh, PA 15219).\nLoftus, E.F. (1995, August 25) The truth, the whole truth and & nothing but the truth? Los Angeles Times, p. B 9. (Invited editorial; Reprinted in newspapers in Minneapolis, Buffalo and elsewhere)\nLoftus, E.F. (1995) Afterword to Ross, C.A., Satanic ritual abuse. Toronto: University of Toronto Press, 203-209.\nLoftus, E.F. & Rosenwald, L.A. (1995, Fall) Recovered memories: unearthing the past in court. Journal of Psychiatry & Law, 349-361.\n\n1996\nGarry, M., Manning, C., Loftus, E.F., & Sherman, S.J. (1996) Imagination Inflation: Imagining a childhood event inflates confidence that it occurred. Psychonomic Bulletin and Review, 3, 208-214.\nLoftus, E.F., Paddock, J.R. & Guernsey, T.F. (1996) Patient-psychotherapist privilege: Access to clinical records in the tangled web of repressed memory litigation. University of Richmond Law Review, 30, 109-154. (Special issue devoted to Allen Chair recipients.).\n19\nDOJ-OGR-00007527",
  "text_blocks": [
    {
      "type": "printed",
      "content": "Case 1:20-cr-00330-PAE Document 499-1 Filed 11/23/21 Page 34 of 375",
      "position": "header"
    },
    {
      "type": "printed",
      "content": "The full list of references",
      "position": "main"
    },
    {
      "type": "printed",
      "content": "19",
      "position": "footer"
    },
    {
      "type": "printed",
      "content": "DOJ-OGR-00007527",
      "position": "footer"
    }
  ],
  "entities": {
    "people": [
      "Loftus, E.F.",
      "Jeffrey, J.",
      "Edwall, G.",
      "Garry, M.",
      "Brown, S.W.",
      "Belli, R.F.",
      "Lynn, S.J.",
      "Rhue, J.",
      "Weingardt, K.R.",
      "Toland, H.K.",
      "Ross, D.",
      "Read, J.D.",
      "Toglia, M.P.",
      "Ceci, S.J.",
      "Honech, R.P.",
      "Leichtman, M.D.",
      "Bruck, M.",
      "Huffman, M.L.C.",
      "Smith, E.",
      "Lindsay, D.S.",
      "Milo, E.M.",
      "Paddock, J.R.",
      "Pickrell, J.E.",
      "Feldman, J.",
      "Dashiell, R.",
      "Schacter, D.L.",
      "Coyle, J.T.",
      "Fishbach, G.D.",
      "Mesulam, M.M.",
      "Sullivan, L.E.",
      "Clark, S.E.",
      "Mack, J.",
      "Yapko, M.",
      "Ney, T.",
      "Leichtman, M.D.",
      "Ceci, S.J.",
      "Rosenwald, L.A.",
      "Ross, C.A.",
      "Manning, C.",
      "Sherman, S.J.",
      "Guernsey, T.F."
    ],
    "organizations": [
      "University Press of America",
      "Guilford Press",
      "Springer-Verlag",
      "Dushkin Publishing Group",
      "Harvard University Press",
      "Brunner/Mazel",
      "Pittsburgh Institute of Legal Medicine",
      "University of Toronto Press",
      "Los Angeles Times",
      "University of Richmond"
    ],
    "locations": [
      "NY",
      "America",
      "Guilford, CT",
      "Cambridge, MA",
      "Toronto",
      "Minneapolis",
      "Buffalo",
      "Pittsburgh, PA"
    ],
    "dates": [
      "1994",
      "1995",
      "1996",
      "1997",
      "1998",
      "11/23/21",
      "August 25",
      "Fall"
    ],
    "reference_numbers": [
      "1:20-cr-00330-PAE",
      "499-1",
      "DOJ-OGR-00007527"
    ]
  },
  "additional_notes": "The document appears to be a list of references related to the topic of memory and eyewitness testimony, with a focus on the work of Elizabeth Loftus. The document is well-formatted and easy to read, with clear headings and concise citations."
}