{
  "document_metadata": {
    "page_number": "21 of 84",
    "document_number": "452",
    "date": "11/12/21",
    "document_type": "court document",
    "has_handwriting": false,
    "has_stamps": false
  },
  "full_text": "Case 1:20-cr-00330-PAE Document 452 Filed 11/12/21 Page 21 of 84 return to Epstein's home for sexual abuse, or why some occasionally expressed affection for the defendant and Epstein. Although Dr. Rocchio will not testify about these specific Minor Victims, her testimony will help the jurors understand the \"psychological dynamic often seen in abusive relationships that leads an abuse victim to behave in counterintuitive ways, such as by declining to take opportunities to leave an abusive situation or by expressing gratitude to an abuser.\" Torres, 2021 WL 1947503, at *7. This psychological dynamic between a victim of child sexual abuse and her abusers is \"beyond the knowledge of the average juror and would or could plainly be helpful in understanding the psychological dynamics at play.\" Oct. 17, 2019 Tr. at 27:3-7, United States v. Dupigny, No. 18 Cr. 528 (JMF) (S.D.N.Y.), Dkt. No. 198; cf. See Feb. 25, 2020 Tr. at 38:13-20, United States v. Randall, 19 Cr. 131 (PAE) (S.D.N.Y.), Dkt. No. 335 (\"[B]y and large the relationship between prostitutes and pimps is not the subject of common knowledge. Jurors are not apt to intuitively understand the mechanisms that may lead a woman who is not physically restrained or confined to heed the demands of a pimp to traffic herself.\") Accordingly, Dr. Rocchio's testimony will help the jury understand and contextualize the other testimony it will hear.4 The defendant expresses concern that a lay jury will be unable to apply Dr. Rocchio's analyses to the facts of this case, stating \"[t]hat is not how Rule 702 works.\" (Def. Mot. at 10). 4 Relying again on Raymond, the District of Maine case, the defendant argues that expert testimony about \"general principles is helpful only when it 'describes widely recognized and highly predictable and verifiable phenomena.'\" (Def. Mot. 10 (quoting Raymond, 700 F. Supp. 2d at 150 n.12 (alterations omitted)). That proposition comes from footnote 12 of Raymond, which attempted to distinguish that expert's \"profile\" testimony from the Federal Rules Advisory Committee's observation that the 2000 amendment \"does not alter the venerable practice of using 20 DOJ-OGR-00006729",
  "text_blocks": [
    {
      "type": "printed",
      "content": "Case 1:20-cr-00330-PAE Document 452 Filed 11/12/21 Page 21 of 84",
      "position": "header"
    },
    {
      "type": "printed",
      "content": "return to Epstein's home for sexual abuse, or why some occasionally expressed affection for the defendant and Epstein. Although Dr. Rocchio will not testify about these specific Minor Victims, her testimony will help the jurors understand the \"psychological dynamic often seen in abusive relationships that leads an abuse victim to behave in counterintuitive ways, such as by declining to take opportunities to leave an abusive situation or by expressing gratitude to an abuser.\" Torres, 2021 WL 1947503, at *7. This psychological dynamic between a victim of child sexual abuse and her abusers is \"beyond the knowledge of the average juror and would or could plainly be helpful in understanding the psychological dynamics at play.\" Oct. 17, 2019 Tr. at 27:3-7, United States v. Dupigny, No. 18 Cr. 528 (JMF) (S.D.N.Y.), Dkt. No. 198; cf. See Feb. 25, 2020 Tr. at 38:13-20, United States v. Randall, 19 Cr. 131 (PAE) (S.D.N.Y.), Dkt. No. 335 (\"[B]y and large the relationship between prostitutes and pimps is not the subject of common knowledge. Jurors are not apt to intuitively understand the mechanisms that may lead a woman who is not physically restrained or confined to heed the demands of a pimp to traffic herself.\") Accordingly, Dr. Rocchio's testimony will help the jury understand and contextualize the other testimony it will hear.4 The defendant expresses concern that a lay jury will be unable to apply Dr. Rocchio's analyses to the facts of this case, stating \"[t]hat is not how Rule 702 works.\" (Def. Mot. at 10).",
      "position": "main body"
    },
    {
      "type": "printed",
      "content": "4 Relying again on Raymond, the District of Maine case, the defendant argues that expert testimony about \"general principles is helpful only when it 'describes widely recognized and highly predictable and verifiable phenomena.'\" (Def. Mot. 10 (quoting Raymond, 700 F. Supp. 2d at 150 n.12 (alterations omitted)). That proposition comes from footnote 12 of Raymond, which attempted to distinguish that expert's \"profile\" testimony from the Federal Rules Advisory Committee's observation that the 2000 amendment \"does not alter the venerable practice of using",
      "position": "main body"
    },
    {
      "type": "printed",
      "content": "20",
      "position": "footer"
    },
    {
      "type": "printed",
      "content": "DOJ-OGR-00006729",
      "position": "footer"
    }
  ],
  "entities": {
    "people": [
      "Dr. Rocchio",
      "Epstein",
      "Torres",
      "Dupigny",
      "Randall",
      "Raymond"
    ],
    "organizations": [
      "Federal Rules Advisory Committee"
    ],
    "locations": [
      "Maine",
      "S.D.N.Y."
    ],
    "dates": [
      "11/12/21",
      "Oct. 17, 2019",
      "Feb. 25, 2020"
    ],
    "reference_numbers": [
      "1:20-cr-00330-PAE",
      "Document 452",
      "18 Cr. 528 (JMF)",
      "19 Cr. 131 (PAE)",
      "Dkt. No. 198",
      "Dkt. No. 335",
      "700 F. Supp. 2d"
    ]
  },
  "additional_notes": "The document appears to be a court filing related to a criminal case involving Jeffrey Epstein. The text discusses the testimony of Dr. Rocchio and its relevance to understanding the psychological dynamics of child sexual abuse victims. The document includes citations to various court cases and references to specific docket numbers."
}