{
  "document_metadata": {
    "page_number": "165",
    "document_number": "499-1",
    "date": "11/23/21",
    "document_type": "court document",
    "has_handwriting": false,
    "has_stamps": false
  },
  "full_text": "Case 1:20-cr-00330-PAE Document 499-1 Filed 11/23/21 Page 165 of 375\nPark Dietz, M.D., M.P.H., Ph.D.\nPage 103\nMind of a Monster (TV Series documentary, 2020)\n- Jeffrey Dahmer (2020)\nCrazy, Not Insane (Documentary) 2020\nWaco Inferno: The Untold Story (TV Movie documentary) 2018\nDahmer on Dahmer: A Serial Killer Speaks (TV Mini-Series documentary) (2017)\n- Part 2 (2017)\n- Part 1 (2017)\nCampus Killer: Santa Barbara (TV Movie documentary) (2014)\nThe Virgin Killer (TV Special documentary) (2014)\nBehind Mansion Walls (TV Series documentary)\n- The Perfect Crime (2011)\nWicked Attraction (TV Series documentary)\n- Shoot to Thrill (2010)\nStaruckers (Documentary) (2009)\nWomen on Death Row (TV Movie documentary) (2006)\nThe Iceman and the Psychiatrist (TV Movie documentary) (2003)\nInvestigative Reports (TV Series documentary)\n- Columbine: Understanding Why (2002)\nSerial Killers: Profiling the Criminal Mind (Video documentary) (1999)\nThe Unexplained (TV Series documentary)\n- Dangerous Obsessions (1998)\nBiography (TV Series documentary)\nDOJ-OGR-00007658",
  "text_blocks": [
    {
      "type": "printed",
      "content": "Case 1:20-cr-00330-PAE Document 499-1 Filed 11/23/21 Page 165 of 375",
      "position": "header"
    },
    {
      "type": "printed",
      "content": "Park Dietz, M.D., M.P.H., Ph.D.\nPage 103",
      "position": "top"
    },
    {
      "type": "printed",
      "content": "Mind of a Monster (TV Series documentary, 2020)\n- Jeffrey Dahmer (2020)\nCrazy, Not Insane (Documentary) 2020\nWaco Inferno: The Untold Story (TV Movie documentary) 2018\nDahmer on Dahmer: A Serial Killer Speaks (TV Mini-Series documentary) (2017)\n- Part 2 (2017)\n- Part 1 (2017)\nCampus Killer: Santa Barbara (TV Movie documentary) (2014)\nThe Virgin Killer (TV Special documentary) (2014)\nBehind Mansion Walls (TV Series documentary)\n- The Perfect Crime (2011)\nWicked Attraction (TV Series documentary)\n- Shoot to Thrill (2010)\nStaruckers (Documentary) (2009)\nWomen on Death Row (TV Movie documentary) (2006)\nThe Iceman and the Psychiatrist (TV Movie documentary) (2003)\nInvestigative Reports (TV Series documentary)\n- Columbine: Understanding Why (2002)\nSerial Killers: Profiling the Criminal Mind (Video documentary) (1999)\nThe Unexplained (TV Series documentary)\n- Dangerous Obsessions (1998)\nBiography (TV Series documentary)",
      "position": "middle"
    },
    {
      "type": "printed",
      "content": "DOJ-OGR-00007658",
      "position": "footer"
    }
  ],
  "entities": {
    "people": [
      "Jeffrey Dahmer",
      "Park Dietz"
    ],
    "organizations": [
      "DOJ"
    ],
    "locations": [
      "Santa Barbara",
      "Waco",
      "Columbine"
    ],
    "dates": [
      "2020",
      "2018",
      "2017",
      "2014",
      "2011",
      "2010",
      "2009",
      "2006",
      "2003",
      "2002",
      "1999",
      "1998",
      "11/23/21"
    ],
    "reference_numbers": [
      "1:20-cr-00330-PAE",
      "499-1",
      "DOJ-OGR-00007658"
    ]
  },
  "additional_notes": "The document appears to be a court filing with a list of documentaries related to serial killers and crimes. The text is clear and legible, with no visible redactions or damage."
}