{
  "document_metadata": {
    "page_number": "1",
    "document_number": "409",
    "date": "11/03/21",
    "document_type": "Court Order",
    "has_handwriting": false,
    "has_stamps": true
  },
  "full_text": "Case 1:20-cr-00330-PAE Document 409 Filed 11/03/21 Page 1 of 2\nUNITED STATES DISTRICT COURT SOUTHERN DISTRICT OF NEW YORK\nUnited States of America,\n-v-\nGhislainc Maxwell,\nDefendant.\n20-CR-330 (AJN)\nORDER\nALISON J. NATHAN, District Judge:\nThe Court is in receipt of the parties' joint letter in response to this Court's order dated October 31, 2021. Dkt. No. 406. The Court will hold a hearing on November 10, 2021 at 9:00 a.m. on the Defendant's motion under Federal Rule of Evidence 412, Dkt. No. 378, the Defendant's motion in limine to exclude under Federal Rule of Evidence 702 and Daubert v. Merrell Dow Pharmaceuticals, Inc., 509 U.S. 579 (1993), Dkt. No. 386, and the other outstanding issues that overlap with these two motions as discussed at the November 1, 2021 conference. The proceeding will take place in Courtroom 110 of the United States District Court for the Southern District of New York, Thurgood Marshall U.S. Courthouse at 40 Foley Square, New York, New York. The Court will provide information on public access (for the portion of the Daubert hearing that does not overlap with the Rule 412 issues) as soon as it is available.\nOtherwise, the Court will order the following briefing schedule if the Government seeks to exclude any of the Defendant's anticipated witness testimony as disclosed in her November 1, 2021 notice. See Dkt. No. 406:\n- Government brief to be filed on ECF: November 8, 2021\n- Defense response brief to be filed on ECF: November 11, 2021\n1\nDOJ-OGR-00006063",
  "text_blocks": [
    {
      "type": "printed",
      "content": "Case 1:20-cr-00330-PAE Document 409 Filed 11/03/21 Page 1 of 2",
      "position": "header"
    },
    {
      "type": "printed",
      "content": "UNITED STATES DISTRICT COURT SOUTHERN DISTRICT OF NEW YORK",
      "position": "header"
    },
    {
      "type": "printed",
      "content": "United States of America,\n-v-\nGhislainc Maxwell,\nDefendant.",
      "position": "top"
    },
    {
      "type": "stamp",
      "content": "USDC SDNY DOCUMENT ELECTRONICALLY FILED DOC #: DATE FILED: 11/3/21",
      "position": "margin"
    },
    {
      "type": "printed",
      "content": "20-CR-330 (AJN)\nORDER",
      "position": "top"
    },
    {
      "type": "printed",
      "content": "ALISON J. NATHAN, District Judge:\nThe Court is in receipt of the parties' joint letter in response to this Court's order dated October 31, 2021. Dkt. No. 406. The Court will hold a hearing on November 10, 2021 at 9:00 a.m. on the Defendant's motion under Federal Rule of Evidence 412, Dkt. No. 378, the Defendant's motion in limine to exclude under Federal Rule of Evidence 702 and Daubert v. Merrell Dow Pharmaceuticals, Inc., 509 U.S. 579 (1993), Dkt. No. 386, and the other outstanding issues that overlap with these two motions as discussed at the November 1, 2021 conference. The proceeding will take place in Courtroom 110 of the United States District Court for the Southern District of New York, Thurgood Marshall U.S. Courthouse at 40 Foley Square, New York, New York. The Court will provide information on public access (for the portion of the Daubert hearing that does not overlap with the Rule 412 issues) as soon as it is available.\nOtherwise, the Court will order the following briefing schedule if the Government seeks to exclude any of the Defendant's anticipated witness testimony as disclosed in her November 1, 2021 notice. See Dkt. No. 406:\n- Government brief to be filed on ECF: November 8, 2021\n- Defense response brief to be filed on ECF: November 11, 2021",
      "position": "middle"
    },
    {
      "type": "printed",
      "content": "1",
      "position": "footer"
    },
    {
      "type": "printed",
      "content": "DOJ-OGR-00006063",
      "position": "footer"
    }
  ],
  "entities": {
    "people": [
      "Alison J. Nathan",
      "Ghislainc Maxwell"
    ],
    "organizations": [
      "United States District Court",
      "United States of America"
    ],
    "locations": [
      "New York"
    ],
    "dates": [
      "November 10, 2021",
      "October 31, 2021",
      "November 1, 2021",
      "November 8, 2021",
      "November 11, 2021",
      "11/03/21"
    ],
    "reference_numbers": [
      "1:20-cr-00330-PAE",
      "Document 409",
      "20-CR-330 (AJN)",
      "Dkt. No. 406",
      "Dkt. No. 378",
      "Dkt. No. 386"
    ]
  },
  "additional_notes": "The document is a court order from the United States District Court for the Southern District of New York. It appears to be a formal and official document, with no visible redactions or damage."
}