{
  "document_metadata": {
    "page_number": "96",
    "document_number": "499-1",
    "date": "11/23/21",
    "document_type": "court document",
    "has_handwriting": false,
    "has_stamps": false
  },
  "full_text": "Case 1:20-cr-00330-PAE Document 499-1 Filed 11/23/21 Page 96 of 375\nPark Dietz, M.D., M.P.H., Ph.D.\nPage 34\nWA v. Daniel J. Mustard (Port Orchard, WA)\nTestified at hearing, 8/31/10 and 9/1/10\nTestified at trial, 12/1/10, 12/2/10, 12/3/10, and 12/8/10\nRegina v. Sandra Rinella and Alexander Petraitis (Toronto, Canada)\nTestified at voir dire, 10/27/10 and 10/28/10\nTestified at trial, 11/2/10 and 11/3/10\nCA v. Eric Russell Andreasen (Vista, CA)\nTestified at trial, 3/22/11\nStevens v. U.S. (West Palm Beach, FL)\nTestified at deposition, 6/30/11\nDeepak Kalpoe and Satish Kalpoe v. Phillip C. McGraw, CBS Television Distribution Group F/K/A/ CBS Paramount Domestic Television, Peteski Productions, Inc., et al.\nTestified at deposition, 10/19/11\nCA v. Brendan O'Rourke (Vista, CA)\nTestified at trial, 3/12/12\nCA v. Joseph Naso (San Rafael, CA)\nTestified at pre-trial hearing, 4/19/13\nTestified at sentencing, 9/13/13\nUS v. David Brooks (Eastern District of New York, Central Islip, NY)\nAddressed Court at sentencing, 8/12/13\nCA v. Sidney Nathaniel Landau (Santa Ana, CA)\nTestified at deposition, 10/4/13\nTestified at trial, 11/7/13, 11/12/13, 11/13/13\nMichael Keister v. YMCA of Western North Carolina (Asheville, NC)\nTestified at deposition, 3/13/14\nTestified at trial deposition, 3/14/14\nJudith Cox and Charles Cox v. State of Washington, Department of Social and Health Services (Tacoma, WA)\nTestified at deposition, 5/9/14\nTestified at trial (by Zoom), 7/27/20, 7/28/20\nDOJ-OGR-00007589",
  "text_blocks": [
    {
      "type": "printed",
      "content": "Case 1:20-cr-00330-PAE Document 499-1 Filed 11/23/21 Page 96 of 375",
      "position": "header"
    },
    {
      "type": "printed",
      "content": "Park Dietz, M.D., M.P.H., Ph.D.\nPage 34",
      "position": "header"
    },
    {
      "type": "printed",
      "content": "WA v. Daniel J. Mustard (Port Orchard, WA)\nTestified at hearing, 8/31/10 and 9/1/10\nTestified at trial, 12/1/10, 12/2/10, 12/3/10, and 12/8/10",
      "position": "main"
    },
    {
      "type": "printed",
      "content": "Regina v. Sandra Rinella and Alexander Petraitis (Toronto, Canada)\nTestified at voir dire, 10/27/10 and 10/28/10\nTestified at trial, 11/2/10 and 11/3/10",
      "position": "main"
    },
    {
      "type": "printed",
      "content": "CA v. Eric Russell Andreasen (Vista, CA)\nTestified at trial, 3/22/11",
      "position": "main"
    },
    {
      "type": "printed",
      "content": "Stevens v. U.S. (West Palm Beach, FL)\nTestified at deposition, 6/30/11",
      "position": "main"
    },
    {
      "type": "printed",
      "content": "Deepak Kalpoe and Satish Kalpoe v. Phillip C. McGraw, CBS Television Distribution Group F/K/A/ CBS Paramount Domestic Television, Peteski Productions, Inc., et al.\nTestified at deposition, 10/19/11",
      "position": "main"
    },
    {
      "type": "printed",
      "content": "CA v. Brendan O'Rourke (Vista, CA)\nTestified at trial, 3/12/12",
      "position": "main"
    },
    {
      "type": "printed",
      "content": "CA v. Joseph Naso (San Rafael, CA)\nTestified at pre-trial hearing, 4/19/13\nTestified at sentencing, 9/13/13",
      "position": "main"
    },
    {
      "type": "printed",
      "content": "US v. David Brooks (Eastern District of New York, Central Islip, NY)\nAddressed Court at sentencing, 8/12/13",
      "position": "main"
    },
    {
      "type": "printed",
      "content": "CA v. Sidney Nathaniel Landau (Santa Ana, CA)\nTestified at deposition, 10/4/13\nTestified at trial, 11/7/13, 11/12/13, 11/13/13",
      "position": "main"
    },
    {
      "type": "printed",
      "content": "Michael Keister v. YMCA of Western North Carolina (Asheville, NC)\nTestified at deposition, 3/13/14\nTestified at trial deposition, 3/14/14",
      "position": "main"
    },
    {
      "type": "printed",
      "content": "Judith Cox and Charles Cox v. State of Washington, Department of Social and Health Services (Tacoma, WA)\nTestified at deposition, 5/9/14\nTestified at trial (by Zoom), 7/27/20, 7/28/20",
      "position": "main"
    },
    {
      "type": "printed",
      "content": "DOJ-OGR-00007589",
      "position": "footer"
    }
  ],
  "entities": {
    "people": [
      "Daniel J. Mustard",
      "Sandra Rinella",
      "Alexander Petraitis",
      "Eric Russell Andreasen",
      "Deepak Kalpoe",
      "Satish Kalpoe",
      "Phillip C. McGraw",
      "Brendan O'Rourke",
      "Joseph Naso",
      "David Brooks",
      "Sidney Nathaniel Landau",
      "Michael Keister",
      "Judith Cox",
      "Charles Cox",
      "Park Dietz"
    ],
    "organizations": [
      "CBS Television Distribution Group",
      "CBS Paramount Domestic Television",
      "Peteski Productions, Inc.",
      "YMCA of Western North Carolina",
      "State of Washington, Department of Social and Health Services"
    ],
    "locations": [
      "Port Orchard, WA",
      "Toronto, Canada",
      "Vista, CA",
      "West Palm Beach, FL",
      "San Rafael, CA",
      "Central Islip, NY",
      "Santa Ana, CA",
      "Asheville, NC",
      "Tacoma, WA"
    ],
    "dates": [
      "8/31/10",
      "9/1/10",
      "12/1/10",
      "12/2/10",
      "12/3/10",
      "12/8/10",
      "10/27/10",
      "10/28/10",
      "11/2/10",
      "11/3/10",
      "3/22/11",
      "6/30/11",
      "10/19/11",
      "3/12/12",
      "4/19/13",
      "9/13/13",
      "8/12/13",
      "10/4/13",
      "11/7/13",
      "11/12/13",
      "11/13/13",
      "3/13/14",
      "3/14/14",
      "5/9/14",
      "7/27/20",
      "7/28/20",
      "11/23/21"
    ],
    "reference_numbers": [
      "1:20-cr-00330-PAE",
      "499-1",
      "DOJ-OGR-00007589"
    ]
  },
  "additional_notes": "The document appears to be a court filing with a list of cases and testimonies. The text is clear and legible, with no visible redactions or damage."
}