{
  "document_metadata": {
    "page_number": "1",
    "document_number": "538",
    "date": "12/11/21",
    "document_type": "Letter",
    "has_handwriting": false,
    "has_stamps": true
  },
  "full_text": "Case 1:20-cr-00330-PAE Document 538 Filed 12/11/21 Page 1 of 2 U.S. Department of Justice United States Attorney Southern District of New York The Silvio J. Mollo Building One Saint Andrew's Plaza New York, New York 10007 December 9, 2021 The Honorable Alison J. Nathan United States District Court Southern District of New York United States Courthouse 40 Foley Square New York, New York 10007 Re: United States v. Ghislaine Maxwell, S2 20 Cr. 330 (AJN) Dear Judge Nathan: The Government respectfully submits this letter regarding the Court's order for the parties to confer and propose a limiting instruction regarding Government Exhibit 52. The parties have conferred and jointly propose the following instruction: This exhibit is being offered for a limited purpose. It is not being offered for the truth of the matters asserted therein, and you may not consider it for that purpose. Rather, you may consider it only to the extent you believe it is relevant to show a link, if any, between Ms. Maxwell and the names and phone numbers listed and how, if at all, the information was organized. 1 DOJ-OGR-00008355",
  "text_blocks": [
    {
      "type": "printed",
      "content": "Case 1:20-cr-00330-PAE Document 538 Filed 12/11/21 Page 1 of 2",
      "position": "header"
    },
    {
      "type": "printed",
      "content": "U.S. Department of Justice United States Attorney Southern District of New York",
      "position": "top"
    },
    {
      "type": "stamp",
      "content": "",
      "position": "margin"
    },
    {
      "type": "printed",
      "content": "The Silvio J. Mollo Building One Saint Andrew's Plaza New York, New York 10007 December 9, 2021",
      "position": "top"
    },
    {
      "type": "printed",
      "content": "The Honorable Alison J. Nathan United States District Court Southern District of New York United States Courthouse 40 Foley Square New York, New York 10007",
      "position": "middle"
    },
    {
      "type": "printed",
      "content": "Re: United States v. Ghislaine Maxwell, S2 20 Cr. 330 (AJN)",
      "position": "middle"
    },
    {
      "type": "printed",
      "content": "Dear Judge Nathan: The Government respectfully submits this letter regarding the Court's order for the parties to confer and propose a limiting instruction regarding Government Exhibit 52. The parties have conferred and jointly propose the following instruction: This exhibit is being offered for a limited purpose. It is not being offered for the truth of the matters asserted therein, and you may not consider it for that purpose. Rather, you may consider it only to the extent you believe it is relevant to show a link, if any, between Ms. Maxwell and the names and phone numbers listed and how, if at all, the information was organized.",
      "position": "middle"
    },
    {
      "type": "printed",
      "content": "1",
      "position": "bottom"
    },
    {
      "type": "printed",
      "content": "DOJ-OGR-00008355",
      "position": "footer"
    }
  ],
  "entities": {
    "people": [
      "Alison J. Nathan",
      "Ghislaine Maxwell"
    ],
    "organizations": [
      "U.S. Department of Justice",
      "United States Attorney",
      "United States District Court"
    ],
    "locations": [
      "New York"
    ],
    "dates": [
      "December 9, 2021",
      "12/11/21"
    ],
    "reference_numbers": [
      "1:20-cr-00330-PAE",
      "Document 538",
      "S2 20 Cr. 330 (AJN)",
      "DOJ-OGR-00008355"
    ]
  },
  "additional_notes": "The document is a letter from the U.S. Department of Justice to Judge Alison J. Nathan regarding the case United States v. Ghislaine Maxwell. The letter is dated December 9, 2021, and filed on December 11, 2021. It includes a proposed limiting instruction for Government Exhibit 52."
}