{
  "document_metadata": {
    "page_number": "91",
    "document_number": "499-1",
    "date": "11/23/21",
    "document_type": "court document",
    "has_handwriting": false,
    "has_stamps": false
  },
  "full_text": "Case 1:20-cr-00330-PAE Document 499-1 Filed 11/23/21 Page 153 of 375 Park Dietz, M.D., M.P.H., Ph.D. Page 91 Johns Hopkins Institutions, Baltimore, MD, December 1, 2008 DRS Technologies, Palm Beach, FL, January 29, 2009 Abbott Laboratories, Newport Beach, CA, February 10, 2009 Executive Resource Center, Oklahoma City, OK, July 16, 2009 Abbott Laboratories, Abbott Park, IL, September 15, 2009 Health Care Partners, Los Angeles, September 24-24, 2009 Abbott Laboratories, Abbott Park, IL, October 13-14, 2009 Lockheed Martin, Fort Worth, TX, May 5-6, 2010 Air Liquide, Newport Beach, CA, July 28-29, 2010 \"Workplace Violence 17: Prevention of Workplace Misconduct and Violence,\" Newport Beach, CA, March 28-29, 2011 \"Mental Disorder and the Workplace,\" Newport Beach, CA, March 30, 2011 Pitney Bowes, Stamford, CT, May 3-4, 2011 Federal Express, Webinar: Monitoring and Assessing Written Communications, August 12, 2011 Federal Express, Webinar: Suicide and Suicide Prevention, January 25, 2012 \"Workplace Violence 18: Prevention of Workplace Misconduct and Violence,\" Newport Beach, CA, March 19-21, 2012 Federal Express, Webinar: Safe Termination, July 11, 2012 Air Liquide, Newport Beach, CA, August 7-8, 2012 3M, Minneapolis, MN, November 5, 2012 Amgen, Thousand Oaks, CA, November 30, 2012 DOJ-OGR-00007646",
  "text_blocks": [
    {
      "type": "printed",
      "content": "Case 1:20-cr-00330-PAE Document 499-1 Filed 11/23/21 Page 153 of 375",
      "position": "header"
    },
    {
      "type": "printed",
      "content": "Park Dietz, M.D., M.P.H., Ph.D. Page 91",
      "position": "top"
    },
    {
      "type": "printed",
      "content": "Johns Hopkins Institutions, Baltimore, MD, December 1, 2008 DRS Technologies, Palm Beach, FL, January 29, 2009 Abbott Laboratories, Newport Beach, CA, February 10, 2009 Executive Resource Center, Oklahoma City, OK, July 16, 2009 Abbott Laboratories, Abbott Park, IL, September 15, 2009 Health Care Partners, Los Angeles, September 24-24, 2009 Abbott Laboratories, Abbott Park, IL, October 13-14, 2009 Lockheed Martin, Fort Worth, TX, May 5-6, 2010 Air Liquide, Newport Beach, CA, July 28-29, 2010 \"Workplace Violence 17: Prevention of Workplace Misconduct and Violence,\" Newport Beach, CA, March 28-29, 2011 \"Mental Disorder and the Workplace,\" Newport Beach, CA, March 30, 2011 Pitney Bowes, Stamford, CT, May 3-4, 2011 Federal Express, Webinar: Monitoring and Assessing Written Communications, August 12, 2011 Federal Express, Webinar: Suicide and Suicide Prevention, January 25, 2012 \"Workplace Violence 18: Prevention of Workplace Misconduct and Violence,\" Newport Beach, CA, March 19-21, 2012 Federal Express, Webinar: Safe Termination, July 11, 2012 Air Liquide, Newport Beach, CA, August 7-8, 2012 3M, Minneapolis, MN, November 5, 2012 Amgen, Thousand Oaks, CA, November 30, 2012",
      "position": "middle"
    },
    {
      "type": "printed",
      "content": "DOJ-OGR-00007646",
      "position": "footer"
    }
  ],
  "entities": {
    "people": [
      "Park Dietz"
    ],
    "organizations": [
      "Johns Hopkins Institutions",
      "DRS Technologies",
      "Abbott Laboratories",
      "Executive Resource Center",
      "Health Care Partners",
      "Lockheed Martin",
      "Air Liquide",
      "Pitney Bowes",
      "Federal Express",
      "3M",
      "Amgen"
    ],
    "locations": [
      "Baltimore, MD",
      "Palm Beach, FL",
      "Newport Beach, CA",
      "Oklahoma City, OK",
      "Abbott Park, IL",
      "Los Angeles",
      "Fort Worth, TX",
      "Stamford, CT",
      "Minneapolis, MN",
      "Thousand Oaks, CA"
    ],
    "dates": [
      "December 1, 2008",
      "January 29, 2009",
      "February 10, 2009",
      "July 16, 2009",
      "September 15, 2009",
      "September 24-24, 2009",
      "October 13-14, 2009",
      "May 5-6, 2010",
      "July 28-29, 2010",
      "March 28-29, 2011",
      "March 30, 2011",
      "May 3-4, 2011",
      "August 12, 2011",
      "January 25, 2012",
      "March 19-21, 2012",
      "July 11, 2012",
      "August 7-8, 2012",
      "November 5, 2012",
      "November 30, 2012",
      "11/23/21"
    ],
    "reference_numbers": [
      "1:20-cr-00330-PAE",
      "499-1",
      "DOJ-OGR-00007646"
    ]
  },
  "additional_notes": "The document appears to be a court filing with a list of events or presentations given by Park Dietz. The text is clear and legible, with no visible redactions or damage."
}