{
  "document_metadata": {
    "page_number": "6",
    "document_number": "499-2",
    "date": "11/23/21",
    "document_type": "court transcript",
    "has_handwriting": false,
    "has_stamps": false
  },
  "full_text": "Case 1:20-cr-00330-PAE Document 499-2 Filed 11/23/21 Page 6 of 159 5 LBAAMAX1ps\n1    And as I said, we'll discuss voir dire and take up\n2    questionnaire issues as needed.\n3    So that's Monday, November 15th.\n4    I would also like to just go ahead and schedule what\n5    will be our final pretrial conference for November 23rd, is\n6    what I propose, in the afternoon. I still need to work through\n7    the logistics and space and timing on that, use that to clear\n8    out any remaining issues or motions in advance of trial.\n9    Ms. Pomerantz, how does that sound to the government?\n10   MS. POMERANTZ: That all sounds fine. Thank you.\n11   THE COURT: Ms. Sternheim?\n12   MS. STERNHEIM: That sounds fine. I just have a\n13   question with regard to the commencement --\n14   THE COURT: Could you pull up the mike.\n15   MS. STERNHEIM: Oh. Sorry.\n16   With regard to the commencement of voir dire, what\n17   time will we begin on the 16th?\n18   THE COURT: I believe 9, but I will confirm and see\n19   what time I believe -- what time we think the jurors will\n20   actually be ready to go, checked in and ready to go, and I'll\n21   work backwards from that, give us time to get set up and\n22   address any preliminary issues. So let's assume 9 and I'll\n23   confer with the jury department.\n24   MS. STERNHEIM: Thank you.\n25   Just a moment.\n    SOUTHERN DISTRICT REPORTERS, P.C.\n    (212) 805-0300",
  "text_blocks": [
    {
      "type": "printed",
      "content": "Case 1:20-cr-00330-PAE Document 499-2 Filed 11/23/21 Page 6 of 159 5 LBAAMAX1ps",
      "position": "header"
    },
    {
      "type": "printed",
      "content": "1    And as I said, we'll discuss voir dire and take up\n2    questionnaire issues as needed.\n3    So that's Monday, November 15th.\n4    I would also like to just go ahead and schedule what\n5    will be our final pretrial conference for November 23rd, is\n6    what I propose, in the afternoon. I still need to work through\n7    the logistics and space and timing on that, use that to clear\n8    out any remaining issues or motions in advance of trial.\n9    Ms. Pomerantz, how does that sound to the government?\n10   MS. POMERANTZ: That all sounds fine. Thank you.\n11   THE COURT: Ms. Sternheim?\n12   MS. STERNHEIM: That sounds fine. I just have a\n13   question with regard to the commencement --\n14   THE COURT: Could you pull up the mike.\n15   MS. STERNHEIM: Oh. Sorry.\n16   With regard to the commencement of voir dire, what\n17   time will we begin on the 16th?\n18   THE COURT: I believe 9, but I will confirm and see\n19   what time I believe -- what time we think the jurors will\n20   actually be ready to go, checked in and ready to go, and I'll\n21   work backwards from that, give us time to get set up and\n22   address any preliminary issues. So let's assume 9 and I'll\n23   confer with the jury department.\n24   MS. STERNHEIM: Thank you.\n25   Just a moment.",
      "position": "main"
    },
    {
      "type": "printed",
      "content": "SOUTHERN DISTRICT REPORTERS, P.C.\n(212) 805-0300",
      "position": "footer"
    }
  ],
  "entities": {
    "people": [
      "Ms. Pomerantz",
      "Ms. Sternheim"
    ],
    "organizations": [
      "SOUTHERN DISTRICT REPORTERS, P.C."
    ],
    "locations": [],
    "dates": [
      "November 15th",
      "November 23rd",
      "16th"
    ],
    "reference_numbers": [
      "1:20-cr-00330-PAE",
      "499-2",
      "212-805-0300"
    ]
  },
  "additional_notes": "The document appears to be a court transcript with clear and legible text. There are no visible redactions or damage."
}