{
  "document_metadata": {
    "page_number": "1",
    "document_number": "454",
    "date": "11/12/21",
    "document_type": "Court Order",
    "has_handwriting": false,
    "has_stamps": true
  },
  "full_text": "Case 1:20-cr-00330-PAE Document 454 Filed 11/12/21 Page 1 of 2\nUNITED STATES DISTRICT COURT SOUTHERN DISTRICT OF NEW YORK\nUnited States of America,\n-v-\nGhislaine Maxwell,\nDefendant.\nALISON J. NATHAN, District Judge:\nAs discussed at Wednesday's conference, the Court will hold an in-person proceeding on November 15, 2021 at 9:30 a.m. The proceeding will take place in Courtroom 518 of the United States District Court for the Southern District of New York, Thurgood Marshall U.S. Courthouse at 40 Foley Square, New York, New York. In accordance with its prior Order, the Court will ensure access for alleged victims and any members of the Defendant's family. Dkt. No. 344.\nIn order to comply with the District's COVID-19 protocols, the public will be able to access the proceeding in overflow Courtrooms 110 and 506 of the Thurgood Marshall U.S. Courthouse. These overflow rooms will have live video and audio feeds of the proceeding. The use of any electronic devices during the proceeding in the overflow rooms is strictly prohibited.\nThe Court anticipates seating capacity in the overflow rooms for at least 50 members of the public. If capacity is reached, no additional persons will be admitted. Per the S.D.N.Y. Response to COVID-19, anyone who appears at any S.D.N.Y. courthouse must complete a questionnaire on the date of the proceeding prior to entering the courthouse. All visitors must also have their temperature taken when they arrive at the courthouse. Only persons who meet the\n1\nDOJ-OGR-00006948",
  "text_blocks": [
    {
      "type": "printed",
      "content": "Case 1:20-cr-00330-PAE Document 454 Filed 11/12/21 Page 1 of 2",
      "position": "header"
    },
    {
      "type": "printed",
      "content": "UNITED STATES DISTRICT COURT SOUTHERN DISTRICT OF NEW YORK",
      "position": "top"
    },
    {
      "type": "printed",
      "content": "United States of America,\n-v-\nGhislaine Maxwell,\nDefendant.",
      "position": "top"
    },
    {
      "type": "printed",
      "content": "ALISON J. NATHAN, District Judge:",
      "position": "middle"
    },
    {
      "type": "printed",
      "content": "As discussed at Wednesday's conference, the Court will hold an in-person proceeding on November 15, 2021 at 9:30 a.m. The proceeding will take place in Courtroom 518 of the United States District Court for the Southern District of New York, Thurgood Marshall U.S. Courthouse at 40 Foley Square, New York, New York. In accordance with its prior Order, the Court will ensure access for alleged victims and any members of the Defendant's family. Dkt. No. 344.",
      "position": "middle"
    },
    {
      "type": "printed",
      "content": "In order to comply with the District's COVID-19 protocols, the public will be able to access the proceeding in overflow Courtrooms 110 and 506 of the Thurgood Marshall U.S. Courthouse. These overflow rooms will have live video and audio feeds of the proceeding. The use of any electronic devices during the proceeding in the overflow rooms is strictly prohibited.",
      "position": "middle"
    },
    {
      "type": "printed",
      "content": "The Court anticipates seating capacity in the overflow rooms for at least 50 members of the public. If capacity is reached, no additional persons will be admitted. Per the S.D.N.Y. Response to COVID-19, anyone who appears at any S.D.N.Y. courthouse must complete a questionnaire on the date of the proceeding prior to entering the courthouse. All visitors must also have their temperature taken when they arrive at the courthouse. Only persons who meet the",
      "position": "middle"
    },
    {
      "type": "stamp",
      "content": "USDC SDNY DOCUMENT ELECTRONICALLY FILED DOC#: DATE FILED: 11/12/21",
      "position": "margin"
    },
    {
      "type": "printed",
      "content": "1",
      "position": "footer"
    },
    {
      "type": "printed",
      "content": "DOJ-OGR-00006948",
      "position": "footer"
    }
  ],
  "entities": {
    "people": [
      "Ghislaine Maxwell",
      "Alison J. Nathan"
    ],
    "organizations": [
      "United States District Court",
      "Southern District of New York"
    ],
    "locations": [
      "New York",
      "Thurgood Marshall U.S. Courthouse",
      "40 Foley Square"
    ],
    "dates": [
      "November 15, 2021",
      "11/12/21"
    ],
    "reference_numbers": [
      "1:20-cr-00330-PAE",
      "Document 454",
      "Dkt. No. 344",
      "20-CR-330 (AJN)",
      "DOJ-OGR-00006948"
    ]
  },
  "additional_notes": "The document is a court order from the United States District Court for the Southern District of New York. It appears to be a formal document with proper formatting and no visible damage or redactions."
}