{
  "document_metadata": {
    "page_number": "3",
    "document_number": "441",
    "date": "11/12/21",
    "document_type": "TABLE OF AUTHORITIES",
    "has_handwriting": false,
    "has_stamps": false
  },
  "full_text": "Case 1:20-cr-00330-PAE Document 441 Filed 11/12/21 Page 3 of 12\n\nTABLE OF AUTHORITIES\n\nCases\n\nTaylor v. Illinois, 484 U.S. 400 (1988)....................................................5\nUnited States v. Campagnolo, 592 F.2d 852 (5th Cir. 1979)............................6\nUnited States v. Katz, 178 F.3d 368 (5th Cir. 1999)........................................6\nUnited States v. Tellier, 83 F.3d 578 (2d Cir. 1996)........................................2\nUnited States v. Tracy, 12 F.3d 1186 (2d Cir.1993)........................................2\nUnited States v. Wicker, 848 F.2d 1059 (10th Cir.1988)..................................5, 6\n\nRules\n\nFed. R. Crim. P. 16 .......................................................................4, 5\nFed. R. Evid. 104 ............................................................................2\nFed. R. Evid. 801 ........................................................................1, 2, 4\n\niii\nDOJ-OGR-00006559",
  "text_blocks": [
    {
      "type": "printed",
      "content": "Case 1:20-cr-00330-PAE Document 441 Filed 11/12/21 Page 3 of 12",
      "position": "header"
    },
    {
      "type": "printed",
      "content": "TABLE OF AUTHORITIES",
      "position": "top"
    },
    {
      "type": "printed",
      "content": "Cases\n\nTaylor v. Illinois, 484 U.S. 400 (1988)....................................................5\nUnited States v. Campagnolo, 592 F.2d 852 (5th Cir. 1979)............................6\nUnited States v. Katz, 178 F.3d 368 (5th Cir. 1999)........................................6\nUnited States v. Tellier, 83 F.3d 578 (2d Cir. 1996)........................................2\nUnited States v. Tracy, 12 F.3d 1186 (2d Cir.1993)........................................2\nUnited States v. Wicker, 848 F.2d 1059 (10th Cir.1988)..................................5, 6",
      "position": "middle"
    },
    {
      "type": "printed",
      "content": "Rules\n\nFed. R. Crim. P. 16 .......................................................................4, 5\nFed. R. Evid. 104 ............................................................................2\nFed. R. Evid. 801 ........................................................................1, 2, 4",
      "position": "middle"
    },
    {
      "type": "printed",
      "content": "iii",
      "position": "bottom"
    },
    {
      "type": "printed",
      "content": "DOJ-OGR-00006559",
      "position": "footer"
    }
  ],
  "entities": {
    "people": [
      "Taylor",
      "Campagnolo",
      "Katz",
      "Tellier",
      "Tracy",
      "Wicker"
    ],
    "organizations": [
      "United States"
    ],
    "locations": [
      "Illinois"
    ],
    "dates": [
      "11/12/21",
      "1988",
      "1979",
      "1999",
      "1996",
      "1993",
      "1988"
    ],
    "reference_numbers": [
      "1:20-cr-00330-PAE",
      "441",
      "DOJ-OGR-00006559"
    ]
  },
  "additional_notes": "The document appears to be a table of authorities from a legal case, with a clear and organized structure. The text is printed and there are no visible stamps or handwritten notes."
}