{
  "document_metadata": {
    "page_number": "121",
    "document_number": "467",
    "date": "11/15/21",
    "document_type": "court transcript",
    "has_handwriting": false,
    "has_stamps": false
  },
  "full_text": "Case 1:20-cr-00330-PAE Document 467 Filed 11/15/21 Page 121 of 158 121 LBAGmax4 Rocchio - Cross 1 A. Yes, many of the studies specifically look at disclosure that is delayed, as in not occurring at the time of the abuse. 2 And then look at what are those rates at various points in time, so it could be a week later, it could be a month later, 3 it could be a year later or five years later. 4 Q. So those are all variables in this idea of when disclosure occurs; right? 5 A. They are variables in the dynamics of the delay. They are 6 all examples of delayed disclosure at various points in time. 7 Because delayed disclosure refers to disclosure at some point 8 after the incident that's being disclosed. 9 Q. I want to ask you some questions about memory now, which is 10 another area of your opinion. 11 You agree with me that memory is a complex topic? 12 A. I do. 13 Q. Memory is generally regarded as the mental registration, 14 retention and recollection of past experiences, sensations or 15 thoughts; would you agree with that? 16 A. I would. 17 Q. And there are a number of parts of the brain that work in 18 connection to form memories; would you agree with that? 19 A. I would. 20 Q. Do you know what those parts are? 21 A. I'm not an expert on neuroscience, so I would not -- I 22 could certainly go and review the literature and get back to 23 SOUTHERN DISTRICT REPORTERS, P.C. (212) 805-0300 DOJ-OGR-00007300",
  "text_blocks": [
    {
      "type": "printed",
      "content": "Case 1:20-cr-00330-PAE Document 467 Filed 11/15/21 Page 121 of 158 121 LBAGmax4 Rocchio - Cross",
      "position": "header"
    },
    {
      "type": "printed",
      "content": "1 A. Yes, many of the studies specifically look at disclosure that is delayed, as in not occurring at the time of the abuse. 2 And then look at what are those rates at various points in time, so it could be a week later, it could be a month later, 3 it could be a year later or five years later. 4 Q. So those are all variables in this idea of when disclosure occurs; right? 5 A. They are variables in the dynamics of the delay. They are 6 all examples of delayed disclosure at various points in time. 7 Because delayed disclosure refers to disclosure at some point 8 after the incident that's being disclosed. 9 Q. I want to ask you some questions about memory now, which is 10 another area of your opinion. 11 You agree with me that memory is a complex topic? 12 A. I do. 13 Q. Memory is generally regarded as the mental registration, 14 retention and recollection of past experiences, sensations or 15 thoughts; would you agree with that? 16 A. I would. 17 Q. And there are a number of parts of the brain that work in 18 connection to form memories; would you agree with that? 19 A. I would. 20 Q. Do you know what those parts are? 21 A. I'm not an expert on neuroscience, so I would not -- I 22 could certainly go and review the literature and get back to",
      "position": "main"
    },
    {
      "type": "printed",
      "content": "SOUTHERN DISTRICT REPORTERS, P.C. (212) 805-0300 DOJ-OGR-00007300",
      "position": "footer"
    }
  ],
  "entities": {
    "people": [],
    "organizations": [
      "SOUTHERN DISTRICT REPORTERS, P.C."
    ],
    "locations": [],
    "dates": [
      "11/15/21"
    ],
    "reference_numbers": [
      "1:20-cr-00330-PAE",
      "467",
      "DOJ-OGR-00007300"
    ]
  },
  "additional_notes": "The document appears to be a court transcript with a clear Q&A format. The content discusses the topics of delayed disclosure and memory. The footer contains the name of the reporting agency and a phone number, as well as a reference number."
}