{
  "document_metadata": {
    "page_number": "7",
    "document_number": "465",
    "date": "11/15/21",
    "document_type": "court document",
    "has_handwriting": false,
    "has_stamps": false
  },
  "full_text": "Case 1:20-cr-00330-PAE Document 465 Filed 11/15/21 Page 7 of 127\nLB1TMAX1\n\nSection 3771(a)(8).\n\nIt is quite common for alleged victims, both in cases that have garnered media attention and those involving allegations of sex abuse, to testify or be referred to by pseudonyms or first names. Courts have allowed this whether or not the alleged victims are minors or adults or adults testifying about abuse that allegedly occurred when they were minors.\n\nLet me give a bit of a string cite here. See, for example, United States v. Kelly, No. 19 CR 286, which is a high publicity trial involving adults testifying about sex abuse as minors, and that's in the Eastern District of New York; United States v. Raniere, No. 18 CR 204, a high-publicity trial involving at least one adult testifying about sex abuse as minor; United States v. Dupigny, No. 18 CR 528, involving sex trafficking, United States v. Kelly, No. 7 CR 374, and that could be found at 2008 WL 5068820, which is an Eastern District case involving an adult testifying about sex abuse as a minor; United States v. Graham, No. 14 CR 500, found at 2015 WL 6161292 (S.D.N.Y., October 2015), that involved adults testifying about sex trafficking as minors; United States v. Gardner, No. 16 CR 20135, found at 2016 WL 5404207, an Eastern District case from 2016 involving adults and adults testifying about sex abuse as a minor, and collecting similar cases.\n\nThe practice has been widely permitted because\n\nSOUTHERN DISTRICT REPORTERS, P.C.\n(212) 805-0300\n\nDOJ-OGR-00007058",
  "text_blocks": [
    {
      "type": "printed",
      "content": "Case 1:20-cr-00330-PAE Document 465 Filed 11/15/21 Page 7 of 127",
      "position": "header"
    },
    {
      "type": "printed",
      "content": "LB1TMAX1",
      "position": "header"
    },
    {
      "type": "printed",
      "content": "Section 3771(a)(8).",
      "position": "top"
    },
    {
      "type": "printed",
      "content": "It is quite common for alleged victims, both in cases that have garnered media attention and those involving allegations of sex abuse, to testify or be referred to by pseudonyms or first names. Courts have allowed this whether or not the alleged victims are minors or adults or adults testifying about abuse that allegedly occurred when they were minors.",
      "position": "top"
    },
    {
      "type": "printed",
      "content": "Let me give a bit of a string cite here. See, for example, United States v. Kelly, No. 19 CR 286, which is a high publicity trial involving adults testifying about sex abuse as minors, and that's in the Eastern District of New York; United States v. Raniere, No. 18 CR 204, a high-publicity trial involving at least one adult testifying about sex abuse as minor; United States v. Dupigny, No. 18 CR 528, involving sex trafficking, United States v. Kelly, No. 7 CR 374, and that could be found at 2008 WL 5068820, which is an Eastern District case involving an adult testifying about sex abuse as a minor; United States v. Graham, No. 14 CR 500, found at 2015 WL 6161292 (S.D.N.Y., October 2015), that involved adults testifying about sex trafficking as minors; United States v. Gardner, No. 16 CR 20135, found at 2016 WL 5404207, an Eastern District case from 2016 involving adults and adults testifying about sex abuse as a minor, and collecting similar cases.",
      "position": "middle"
    },
    {
      "type": "printed",
      "content": "The practice has been widely permitted because",
      "position": "middle"
    },
    {
      "type": "printed",
      "content": "SOUTHERN DISTRICT REPORTERS, P.C.\n(212) 805-0300",
      "position": "footer"
    },
    {
      "type": "printed",
      "content": "DOJ-OGR-00007058",
      "position": "footer"
    }
  ],
  "entities": {
    "people": [
      "Kelly",
      "Raniere",
      "Dupigny",
      "Graham",
      "Gardner"
    ],
    "organizations": [
      "SOUTHERN DISTRICT REPORTERS, P.C."
    ],
    "locations": [
      "New York",
      "Eastern District of New York",
      "S.D.N.Y."
    ],
    "dates": [
      "11/15/21",
      "October 2015",
      "2016"
    ],
    "reference_numbers": [
      "1:20-cr-00330-PAE",
      "465",
      "19 CR 286",
      "18 CR 204",
      "18 CR 528",
      "7 CR 374",
      "14 CR 500",
      "16 CR 20135",
      "2008 WL 5068820",
      "2015 WL 6161292",
      "2016 WL 5404207",
      "DOJ-OGR-00007058"
    ]
  },
  "additional_notes": "The document appears to be a court transcript or legal document discussing the use of pseudonyms for alleged victims in sex abuse cases. The text is typed, and there are no visible handwritten notes or stamps. The document includes citations to various court cases and references to specific court documents."
}