{
  "document_metadata": {
    "page_number": "332",
    "document_number": "499-1",
    "date": "11/23/21",
    "document_type": "court document",
    "has_handwriting": false,
    "has_stamps": false
  },
  "full_text": "Case 1:20-cr-00330-PAE Document 499-1 Filed 11/23/21 Page 332 of 375 Reporters Under Subpoena, National Law Journal, January 10, 2005 Cracking Justice's Facade, National Law Journal, October 11, 2004 Let's Untie Judicial Hands, National Law Journal, August 9, 2004 Independent Labs Are Best, National Law Journal, June 14, 2004 Prosecutors Tell Lies, Too, National Law Journal, March 22, 2004 The Spin, Confidentially, National Law Journal, July 21, 2003 Prosecutors' Tug of War, National Law Journal, November 18, 2002 Scholarly Papers at Conferences and Symposia Sentence Structure: The Elements of Punishment, Loyola University Chicago School of Law (April 4, 2014) Prosecutorial Ethics and Brady v. Maryland: Mercer Law School (October 5, 2012). Prosecutorial Immunity: Deconstructing Connick v. Thompson - Loyola University New Orleans Law School (November 4, 2011). The Most Dangerous Power of the Prosecutor - James Hopkins Memorial Lecture - Pace Law School (Oct. 6, 2008) Prosecutorial Ethics and the Right to a Fair Trial - Case Western School of Law (January 26, 2007) Reflections on Brady v. Maryland - South Texas Law School (November 4, 2005). Prosecutorial Ethics and Victim Rights - Lewis & Clark Law School (March 11, 2005) Misuse of Forensic Evidence By Prosecutors - Oklahoma City University Law School (March 6, 2003) Problems of Cooperating Witnesses - Benjamin Cardozo Law School (November 30, 2000) 12 DOJ-OGR-00007825",
  "text_blocks": [
    {
      "type": "printed",
      "content": "Case 1:20-cr-00330-PAE Document 499-1 Filed 11/23/21 Page 332 of 375",
      "position": "header"
    },
    {
      "type": "printed",
      "content": "Reporters Under Subpoena, National Law Journal, January 10, 2005 Cracking Justice's Facade, National Law Journal, October 11, 2004 Let's Untie Judicial Hands, National Law Journal, August 9, 2004 Independent Labs Are Best, National Law Journal, June 14, 2004 Prosecutors Tell Lies, Too, National Law Journal, March 22, 2004 The Spin, Confidentially, National Law Journal, July 21, 2003 Prosecutors' Tug of War, National Law Journal, November 18, 2002",
      "position": "top"
    },
    {
      "type": "printed",
      "content": "Scholarly Papers at Conferences and Symposia",
      "position": "middle"
    },
    {
      "type": "printed",
      "content": "Sentence Structure: The Elements of Punishment, Loyola University Chicago School of Law (April 4, 2014) Prosecutorial Ethics and Brady v. Maryland: Mercer Law School (October 5, 2012). Prosecutorial Immunity: Deconstructing Connick v. Thompson - Loyola University New Orleans Law School (November 4, 2011). The Most Dangerous Power of the Prosecutor - James Hopkins Memorial Lecture - Pace Law School (Oct. 6, 2008) Prosecutorial Ethics and the Right to a Fair Trial - Case Western School of Law (January 26, 2007) Reflections on Brady v. Maryland - South Texas Law School (November 4, 2005). Prosecutorial Ethics and Victim Rights - Lewis & Clark Law School (March 11, 2005) Misuse of Forensic Evidence By Prosecutors - Oklahoma City University Law School (March 6, 2003) Problems of Cooperating Witnesses - Benjamin Cardozo Law School (November 30, 2000)",
      "position": "middle"
    },
    {
      "type": "printed",
      "content": "12",
      "position": "footer"
    },
    {
      "type": "printed",
      "content": "DOJ-OGR-00007825",
      "position": "footer"
    }
  ],
  "entities": {
    "people": [],
    "organizations": [
      "National Law Journal",
      "Loyola University Chicago School of Law",
      "Mercer Law School",
      "Loyola University New Orleans Law School",
      "Pace Law School",
      "Case Western School of Law",
      "South Texas Law School",
      "Lewis & Clark Law School",
      "Oklahoma City University Law School",
      "Benjamin Cardozo Law School"
    ],
    "locations": [],
    "dates": [
      "January 10, 2005",
      "October 11, 2004",
      "August 9, 2004",
      "June 14, 2004",
      "March 22, 2004",
      "July 21, 2003",
      "November 18, 2002",
      "April 4, 2014",
      "October 5, 2012",
      "November 4, 2011",
      "October 6, 2008",
      "January 26, 2007",
      "November 4, 2005",
      "March 11, 2005",
      "March 6, 2003",
      "November 30, 2000",
      "11/23/21"
    ],
    "reference_numbers": [
      "1:20-cr-00330-PAE",
      "499-1",
      "332",
      "DOJ-OGR-00007825"
    ]
  },
  "additional_notes": "The document appears to be a court filing with a list of scholarly papers and articles related to prosecutorial ethics and practices. The text is clear and legible, with no visible redactions or damage."
}