{
  "document_metadata": {
    "page_number": "25",
    "document_number": "467",
    "date": "11/15/21",
    "document_type": "court transcript",
    "has_handwriting": false,
    "has_stamps": false
  },
  "full_text": "Case 1:20-cr-00330-PAE Document 467 Filed 11/15/21 Page 25 of 158 25 LBAAMAX1ps Rocchio - Direct their counsel representative to the National American Psychological Association. I believe those are my current leadership roles. I've held others in the past. Q. What do you do in your capacity as the president-elect of the division of trauma psychology? THE COURT: Ms. Pomerantz, you've gotten a little quieter, so into the mike and speak up. MS. POMERANTZ: Yes, your Honor. Q. What do you do in your capacity as president-elect of the division of trauma psychology? A. So I was elected to the position. It's a three-year term. I serve as part of what's called the presidential trio, which consists of the past president, the current president, and the president-elect. So I'll begin my term as president next year. And then, during my presidential year, I'm responsible for planning the topic and organizing and -- the theme of the program -- our division's program at the annual conference for the American Psychological Association. I sit on the executive board. I work closely with the executive director, overseeing, managing things related to finance, policy, particular outstanding projects or projects that -- ad hoc projects that I wish to execute during my presidential year. (Continued on next page) SOUTHERN DISTRICT REPORTERS, P.C. (212) 805-0300 DOJ-OGR-00007204",
  "text_blocks": [
    {
      "type": "printed",
      "content": "Case 1:20-cr-00330-PAE Document 467 Filed 11/15/21 Page 25 of 158 25",
      "position": "header"
    },
    {
      "type": "printed",
      "content": "LBAAMAX1ps Rocchio - Direct",
      "position": "header"
    },
    {
      "type": "printed",
      "content": "their counsel representative to the National American Psychological Association. I believe those are my current leadership roles. I've held others in the past. Q. What do you do in your capacity as the president-elect of the division of trauma psychology? THE COURT: Ms. Pomerantz, you've gotten a little quieter, so into the mike and speak up. MS. POMERANTZ: Yes, your Honor. Q. What do you do in your capacity as president-elect of the division of trauma psychology? A. So I was elected to the position. It's a three-year term. I serve as part of what's called the presidential trio, which consists of the past president, the current president, and the president-elect. So I'll begin my term as president next year. And then, during my presidential year, I'm responsible for planning the topic and organizing and -- the theme of the program -- our division's program at the annual conference for the American Psychological Association. I sit on the executive board. I work closely with the executive director, overseeing, managing things related to finance, policy, particular outstanding projects or projects that -- ad hoc projects that I wish to execute during my presidential year.",
      "position": "main"
    },
    {
      "type": "printed",
      "content": "(Continued on next page)",
      "position": "footer"
    },
    {
      "type": "printed",
      "content": "SOUTHERN DISTRICT REPORTERS, P.C. (212) 805-0300",
      "position": "footer"
    },
    {
      "type": "printed",
      "content": "DOJ-OGR-00007204",
      "position": "footer"
    }
  ],
  "entities": {
    "people": [
      "Pomerantz"
    ],
    "organizations": [
      "National American Psychological Association",
      "American Psychological Association",
      "SOUTHERN DISTRICT REPORTERS, P.C."
    ],
    "locations": [],
    "dates": [
      "11/15/21"
    ],
    "reference_numbers": [
      "1:20-cr-00330-PAE",
      "467",
      "DOJ-OGR-00007204"
    ]
  },
  "additional_notes": "The document appears to be a court transcript with a clear and readable format. There are no visible redactions or damage."
}