{
  "document_metadata": {
    "page_number": "12 of 25",
    "document_number": "508",
    "date": "11/24/21",
    "document_type": "court document",
    "has_handwriting": false,
    "has_stamps": false
  },
  "full_text": "Case 1:20-cr-00330-PAE Document 508 Filed 11/24/21 Page 12 of 25\n82)) (quotation omitted). See also United States v. Thompson, 976 F.2d 666, 671 (11th Cir. 1992) (cross-examination regarding witnesses' \"mental condition during the time periods about which they were testifying\" is appropriate since those \"records [a]re highly probative of the witnesses' credibility (citing United States v. Lindstrom, 698 F.2d 1154 (11th Cir. 1983); United States v. Partin, 493 F.2d 750 (5th Cir. 1974))). Applying Sasso, Dr. Hall's opinions are relevant and admissible.\nThe standard for relevance is \"very low,\" United States v. Litvak, 808 F.3d 160, 190 (2d Cir. 2015) (reversing conviction based on district court's erroneous conclusion that defendant's expert evidence was irrelevant); United States v. White, 692 F.3d 235, 246 (2d Cir. 2012) (explaining that Rule 401 prescribes a \"very low standard\"), and the definition of relevance is \"very broad,\" United States v. Certified Envtl. Servs., Inc., 753 F.3d 72, 90 (2d Cir. 2014).\n\"Evidence is relevant if: (a) it has any tendency to make a fact more or less probable than it would be without the evidence; and (b) the fact is of consequence in determining the action.\" Fed. R. Evid. 401. \"To be relevant, evidence need not be sufficient by itself to prove a fact in issue, much less to prove it beyond a reasonable doubt.\" United States v. Abu-Jihaad, 630 F.3d 102, 132 (2d Cir. 2010). \"[U]nless an exception applies, all 'relevant evidence is admissible.'\" White, 692 F.3d at 246. Under the \"very broad\" definition and \"very low\" standard of relevance, all of Dr. Hall's opinions are admissible.\nThe government first disputes the relevance of [REDACTED]\n8\nDOJ-OGR-00008097",
  "text_blocks": [
    {
      "type": "printed",
      "content": "Case 1:20-cr-00330-PAE Document 508 Filed 11/24/21 Page 12 of 25",
      "position": "header"
    },
    {
      "type": "printed",
      "content": "82)) (quotation omitted). See also United States v. Thompson, 976 F.2d 666, 671 (11th Cir. 1992) (cross-examination regarding witnesses' \"mental condition during the time periods about which they were testifying\" is appropriate since those \"records [a]re highly probative of the witnesses' credibility (citing United States v. Lindstrom, 698 F.2d 1154 (11th Cir. 1983); United States v. Partin, 493 F.2d 750 (5th Cir. 1974))). Applying Sasso, Dr. Hall's opinions are relevant and admissible.",
      "position": "top"
    },
    {
      "type": "printed",
      "content": "The standard for relevance is \"very low,\" United States v. Litvak, 808 F.3d 160, 190 (2d Cir. 2015) (reversing conviction based on district court's erroneous conclusion that defendant's expert evidence was irrelevant); United States v. White, 692 F.3d 235, 246 (2d Cir. 2012) (explaining that Rule 401 prescribes a \"very low standard\"), and the definition of relevance is \"very broad,\" United States v. Certified Envtl. Servs., Inc., 753 F.3d 72, 90 (2d Cir. 2014).",
      "position": "middle"
    },
    {
      "type": "printed",
      "content": "\"Evidence is relevant if: (a) it has any tendency to make a fact more or less probable than it would be without the evidence; and (b) the fact is of consequence in determining the action.\" Fed. R. Evid. 401. \"To be relevant, evidence need not be sufficient by itself to prove a fact in issue, much less to prove it beyond a reasonable doubt.\" United States v. Abu-Jihaad, 630 F.3d 102, 132 (2d Cir. 2010). \"[U]nless an exception applies, all 'relevant evidence is admissible.'\" White, 692 F.3d at 246. Under the \"very broad\" definition and \"very low\" standard of relevance, all of Dr. Hall's opinions are admissible.",
      "position": "middle"
    },
    {
      "type": "printed",
      "content": "The government first disputes the relevance of [REDACTED]",
      "position": "middle"
    },
    {
      "type": "printed",
      "content": "8",
      "position": "footer"
    },
    {
      "type": "printed",
      "content": "DOJ-OGR-00008097",
      "position": "footer"
    }
  ],
  "entities": {
    "people": [
      "Dr. Hall",
      "Sasso",
      "Litvak",
      "White",
      "Abu-Jihaad",
      "Thompson",
      "Lindstrom",
      "Partin"
    ],
    "organizations": [
      "United States"
    ],
    "locations": [],
    "dates": [
      "11/24/21"
    ],
    "reference_numbers": [
      "1:20-cr-00330-PAE",
      "Document 508",
      "DOJ-OGR-00008097"
    ]
  },
  "additional_notes": "The document appears to be a court filing with a redacted section. The text is mostly printed, with no handwritten content or stamps visible."
}