{
  "document_metadata": {
    "page_number": "1 of 11",
    "document_number": "497",
    "date": "11/23/21",
    "document_type": "Court Order",
    "has_handwriting": true,
    "has_stamps": true
  },
  "full_text": "Case 1:20-cr-00330-PAE Document 497 Filed 11/23/21 Page 1 of 11\nUNITED STATES DISTRICT COURT SOUTHERN DISTRICT OF NEW YORK\nUnited States of America,\n-v-\nGhislainc Maxwell,\nDefendant.\nALISON J. NATHAN, District Judge:\nAs discussed at today's conference, attached is the Court's draft preliminary instructions for the sworn jury. The Court has considered both parties' proposed instructions as to the Court's order that certain witnesses be permitted to testify or be referred to by first name only or pseudonym. Dkt. No. 432. The draft preliminary instructions include a limiting instruction regarding this process.\nThe parties may suggest any proposed edits to the preliminary instructions by letter on or before November 27, 2021, or they shall indicate by that date that they have no objections or suggestions.\nSO ORDERED.\nDated: November 23, 2021 New York, New York\nALISON J. NATHAN United States District Judge\nDOJ-OGR-00007453",
  "text_blocks": [
    {
      "type": "printed",
      "content": "Case 1:20-cr-00330-PAE Document 497 Filed 11/23/21 Page 1 of 11",
      "position": "header"
    },
    {
      "type": "printed",
      "content": "UNITED STATES DISTRICT COURT SOUTHERN DISTRICT OF NEW YORK",
      "position": "header"
    },
    {
      "type": "printed",
      "content": "United States of America, -v- Ghislainc Maxwell, Defendant.",
      "position": "header"
    },
    {
      "type": "printed",
      "content": "ALISON J. NATHAN, District Judge:",
      "position": "body"
    },
    {
      "type": "printed",
      "content": "As discussed at today's conference, attached is the Court's draft preliminary instructions for the sworn jury. The Court has considered both parties' proposed instructions as to the Court's order that certain witnesses be permitted to testify or be referred to by first name only or pseudonym. Dkt. No. 432. The draft preliminary instructions include a limiting instruction regarding this process.",
      "position": "body"
    },
    {
      "type": "printed",
      "content": "The parties may suggest any proposed edits to the preliminary instructions by letter on or before November 27, 2021, or they shall indicate by that date that they have no objections or suggestions.",
      "position": "body"
    },
    {
      "type": "printed",
      "content": "SO ORDERED.",
      "position": "body"
    },
    {
      "type": "printed",
      "content": "Dated: November 23, 2021 New York, New York",
      "position": "footer"
    },
    {
      "type": "handwritten",
      "content": "Alison J. Nathan",
      "position": "signature"
    },
    {
      "type": "printed",
      "content": "ALISON J. NATHAN United States District Judge",
      "position": "footer"
    },
    {
      "type": "stamp",
      "content": "USDC SDNY DOCUMENT ELECTRONICALLY FILED DOC #: DATE FILED: 11/23/21",
      "position": "margin"
    },
    {
      "type": "printed",
      "content": "DOJ-OGR-00007453",
      "position": "footer"
    }
  ],
  "entities": {
    "people": [
      "Ghislainc Maxwell",
      "Alison J. Nathan"
    ],
    "organizations": [
      "United States District Court",
      "United States of America"
    ],
    "locations": [
      "New York"
    ],
    "dates": [
      "November 23, 2021",
      "November 27, 2021"
    ],
    "reference_numbers": [
      "1:20-cr-00330-PAE",
      "Document 497",
      "Dkt. No. 432",
      "20-CR-330 (AJN)",
      "DOJ-OGR-00007453"
    ]
  },
  "additional_notes": "The document is a court order from the United States District Court for the Southern District of New York. It is signed by Judge Alison J. Nathan and includes a stamp indicating that it was electronically filed on November 23, 2021."
}