{
  "document_metadata": {
    "page_number": "16 of 32",
    "document_number": "462",
    "date": "11/15/21",
    "document_type": "Juror Questionnaire",
    "has_handwriting": false,
    "has_stamps": false
  },
  "full_text": "Case 1:20-cr-00330-PAE Document 462 Filed 11/15/21 Page 16 of 32 Juror ID: _______ 28b. If yes to 28, would this affect your ability to serve as a fair and impartial juror in this case? Yes No 28c. If yes to 28b, please explain: 29. Do you know or have any association—professional, business, or social, direct or indirect—with any member of the staff of the United States Attorney's Office for the Southern District of New York? Yes No 29a. If yes, please explain: 29b. If yes to 29, would this affect your ability to serve as a fair and impartial juror in this case? Yes No 29c. If yes to 29b, please explain: 30. Do you know or have any association—professional, business, or social, direct or indirect—with the Federal Bureau of Investigation, commonly known as the FBI? Yes No 30a. If yes, please explain: -15- DOJ-OGR-00007032",
  "text_blocks": [
    {
      "type": "printed",
      "content": "Case 1:20-cr-00330-PAE Document 462 Filed 11/15/21 Page 16 of 32",
      "position": "header"
    },
    {
      "type": "printed",
      "content": "Juror ID: _______",
      "position": "header"
    },
    {
      "type": "printed",
      "content": "28b. If yes to 28, would this affect your ability to serve as a fair and impartial juror in this case? Yes No",
      "position": "top"
    },
    {
      "type": "printed",
      "content": "28c. If yes to 28b, please explain:",
      "position": "top"
    },
    {
      "type": "printed",
      "content": "29. Do you know or have any association—professional, business, or social, direct or indirect—with any member of the staff of the United States Attorney's Office for the Southern District of New York? Yes No",
      "position": "middle"
    },
    {
      "type": "printed",
      "content": "29a. If yes, please explain:",
      "position": "middle"
    },
    {
      "type": "printed",
      "content": "29b. If yes to 29, would this affect your ability to serve as a fair and impartial juror in this case? Yes No",
      "position": "middle"
    },
    {
      "type": "printed",
      "content": "29c. If yes to 29b, please explain:",
      "position": "middle"
    },
    {
      "type": "printed",
      "content": "30. Do you know or have any association—professional, business, or social, direct or indirect—with the Federal Bureau of Investigation, commonly known as the FBI? Yes No",
      "position": "bottom"
    },
    {
      "type": "printed",
      "content": "30a. If yes, please explain:",
      "position": "bottom"
    },
    {
      "type": "printed",
      "content": "-15-",
      "position": "footer"
    },
    {
      "type": "printed",
      "content": "DOJ-OGR-00007032",
      "position": "footer"
    }
  ],
  "entities": {
    "people": [],
    "organizations": [
      "United States Attorney's Office",
      "Federal Bureau of Investigation",
      "FBI"
    ],
    "locations": [
      "Southern District of New York"
    ],
    "dates": [
      "11/15/21"
    ],
    "reference_numbers": [
      "1:20-cr-00330-PAE",
      "462",
      "DOJ-OGR-00007032"
    ]
  },
  "additional_notes": "The document appears to be a juror questionnaire for a court case. It contains a series of questions related to the juror's potential biases and associations with law enforcement or government agencies. The document is printed and does not contain any handwritten text."
}