{
  "document_metadata": {
    "page_number": "129",
    "document_number": "499-1",
    "date": "11/23/21",
    "document_type": "court document",
    "has_handwriting": false,
    "has_stamps": false
  },
  "full_text": "Case 1:20-cr-00330-PAE Document 499-1 Filed 11/23/21 Page 129 of 375\nPark Dietz, M.D., M.P.H., Ph.D.\nPage 67\n12. Rosner RR, Barry DJ, Bradford JMW, Pollack S, Rappeport JR, Dietz PE, Resnick PJ, Weiner B: \"Fellowship Programs in Forensic Psychiatry: Accreditation II,\" American Academy of Psychiatry and the Law, Coronado, California, October 18, 1981.\n13. Harry B, Dietz PE, Hazelwood RR: \"Bloody Instructions: Intolerable Crimes in Mass Market Magazines,\" American Academy of Psychiatry and the Law, New York, New York, October 24, 1982.\n14. Zwerling I, Watson U, Harding G, Dietz PE, Lymberis M, Sadoff RL: \"The Abuse and Misuse of Psychiatry in the United States,\" American Psychiatric Association, New York, New York, May 3, 1983.\n15. Showalter CR, Bonnie RJ, Dietz PE: \"Psychiatric Participation in the Capital Sentencing Process,\" American Academy of Psychiatry and the Law, Portland, Oregon, October 29, 1983.\n16. Harry BE, Dietz PE, Hucker SJ: \"Clinical Criminology as a Practice Paradigm in Forensic Psychiatry,\" American Academy of Psychiatry and the Law, Portland, Oregon, October 30, 1983.\n17. Miller RD, Dietz PE, Morrison HL, Sadoff RL: \"Harassment of Psychiatric Expert Witnesses,\" American Academy of Psychiatry and the Law, Nassau, Bahamas, October 26, 1984.\n18. Rappeport JR, Dietz PE, Basham O: \"Trends in the Standards for the Insanity Defense (Including the Comprehensive Crime Control Act of 1984),\" AMEDD Forensic Psychiatry Course, Walter Reed Army Medical Center, Bethesda, Maryland, April 2, 1985.\n19. Carparelli R, Rappeport JR, Dietz PE, Taylor VE, Thwing JB: \"Mock Trial,\" AMEDD Forensic Psychiatry Course, Walter Reed Army Medical Center, Bethesda, Maryland, April 2, 1985.\n20. Fitch WL, Dietz PE, Deitz SR, Showalter CR, Solomon MA: \"Forensic Reform Through Statewide Training,\" American Academy of Psychiatry and the Law, Albuquerque, New Mexico, October 11, 1985.\n21. Labowitz DI, Dietz PE, Farr W, Flaherty NS, Froede RC, Green DeAH: \"Media Relations for the Forensic Scientist,\" American\nDOJ-OGR-00007622",
  "text_blocks": [
    {
      "type": "printed",
      "content": "Case 1:20-cr-00330-PAE Document 499-1 Filed 11/23/21 Page 129 of 375",
      "position": "header"
    },
    {
      "type": "printed",
      "content": "Park Dietz, M.D., M.P.H., Ph.D.\nPage 67",
      "position": "header"
    },
    {
      "type": "printed",
      "content": "12. Rosner RR, Barry DJ, Bradford JMW, Pollack S, Rappeport JR, Dietz PE, Resnick PJ, Weiner B: \"Fellowship Programs in Forensic Psychiatry: Accreditation II,\" American Academy of Psychiatry and the Law, Coronado, California, October 18, 1981.\n13. Harry B, Dietz PE, Hazelwood RR: \"Bloody Instructions: Intolerable Crimes in Mass Market Magazines,\" American Academy of Psychiatry and the Law, New York, New York, October 24, 1982.\n14. Zwerling I, Watson U, Harding G, Dietz PE, Lymberis M, Sadoff RL: \"The Abuse and Misuse of Psychiatry in the United States,\" American Psychiatric Association, New York, New York, May 3, 1983.\n15. Showalter CR, Bonnie RJ, Dietz PE: \"Psychiatric Participation in the Capital Sentencing Process,\" American Academy of Psychiatry and the Law, Portland, Oregon, October 29, 1983.\n16. Harry BE, Dietz PE, Hucker SJ: \"Clinical Criminology as a Practice Paradigm in Forensic Psychiatry,\" American Academy of Psychiatry and the Law, Portland, Oregon, October 30, 1983.\n17. Miller RD, Dietz PE, Morrison HL, Sadoff RL: \"Harassment of Psychiatric Expert Witnesses,\" American Academy of Psychiatry and the Law, Nassau, Bahamas, October 26, 1984.\n18. Rappeport JR, Dietz PE, Basham O: \"Trends in the Standards for the Insanity Defense (Including the Comprehensive Crime Control Act of 1984),\" AMEDD Forensic Psychiatry Course, Walter Reed Army Medical Center, Bethesda, Maryland, April 2, 1985.\n19. Carparelli R, Rappeport JR, Dietz PE, Taylor VE, Thwing JB: \"Mock Trial,\" AMEDD Forensic Psychiatry Course, Walter Reed Army Medical Center, Bethesda, Maryland, April 2, 1985.\n20. Fitch WL, Dietz PE, Deitz SR, Showalter CR, Solomon MA: \"Forensic Reform Through Statewide Training,\" American Academy of Psychiatry and the Law, Albuquerque, New Mexico, October 11, 1985.\n21. Labowitz DI, Dietz PE, Farr W, Flaherty NS, Froede RC, Green DeAH: \"Media Relations for the Forensic Scientist,\" American",
      "position": "main content"
    },
    {
      "type": "printed",
      "content": "DOJ-OGR-00007622",
      "position": "footer"
    }
  ],
  "entities": {
    "people": [
      "Park Dietz",
      "Rosner RR",
      "Barry DJ",
      "Bradford JMW",
      "Pollack S",
      "Rappeport JR",
      "Dietz PE",
      "Resnick PJ",
      "Weiner B",
      "Harry B",
      "Hazelwood RR",
      "Zwerling I",
      "Watson U",
      "Harding G",
      "Lymberis M",
      "Sadoff RL",
      "Showalter CR",
      "Bonnie RJ",
      "Harry BE",
      "Hucker SJ",
      "Miller RD",
      "Morrison HL",
      "Basham O",
      "Carparelli R",
      "Taylor VE",
      "Thwing JB",
      "Fitch WL",
      "Deitz SR",
      "Solomon MA",
      "Labowitz DI",
      "Farr W",
      "Flaherty NS",
      "Froede RC",
      "Green DeAH"
    ],
    "organizations": [
      "American Academy of Psychiatry and the Law",
      "American Psychiatric Association",
      "AMEDD Forensic Psychiatry Course",
      "Walter Reed Army Medical Center"
    ],
    "locations": [
      "Coronado, California",
      "New York, New York",
      "Portland, Oregon",
      "Nassau, Bahamas",
      "Bethesda, Maryland",
      "Albuquerque, New Mexico"
    ],
    "dates": [
      "October 18, 1981",
      "October 24, 1982",
      "May 3, 1983",
      "October 29, 1983",
      "October 30, 1983",
      "October 26, 1984",
      "April 2, 1985",
      "October 11, 1985",
      "11/23/21"
    ],
    "reference_numbers": [
      "1:20-cr-00330-PAE",
      "499-1",
      "DOJ-OGR-00007622"
    ]
  },
  "additional_notes": "The document appears to be a court filing with a list of references related to forensic psychiatry. The text is typed, and there are no visible handwritten notes or stamps. The document is well-formatted and legible."
}