{
  "document_metadata": {
    "page_number": "135",
    "document_number": "499-1",
    "date": "11/23/21",
    "document_type": "court document",
    "has_handwriting": false,
    "has_stamps": false
  },
  "full_text": "Case 1:20-cr-00330-PAE Document 499-1 Filed 11/23/21 Page 135 of 375\nPark Dietz, M.D., M.P.H., Ph.D.\nPage 73\nLaw Enforcement Coordinating Committee, New Jersey\nLaw Enforcement Coordinating Committee, Texas\nLos Angeles Criminal Justice Inns of Court\nLos Angeles Police Department Threat Management Unit\nLouisiana District Attorneys Association\nMedical College of Virginia, Department of Legal Medicine\nMinnesota Employment Law Counsel\nMinnesota State Bar Association Criminal Justice Institute\nMinnesota State Bar Association Employment Law Institute\nNational College of District Attorneys\nNational Institute of Drug Abuse Research Center\nNewport Beach (CA) Police Department\nNorth Texas District Attorneys\nOffice of the District Attorney, County of Fresno, California\nOrange County Bar Association\nOrange County Bar Association Employment Law Section\nOrange County District Attorney's Office\nOrange County Homicide Investigators Association\nOrange County Inns of Court\nPackaging Institute International\nParamount Studios\nProsecuting Attorneys' Council of Georgia\nRichmond Psychiatric Society\nRobert Presley Institute of Criminal Investigation\nSan Diego Psychiatric Society\nSouth Beach Psychiatric Center, New York, New York\nSouthern California Chapter, American Academy of Psychiatry and the Law\nSoutheastern Prosecutors Institute\nSpace Coast Institute of Legal Medicine, Orlando, Florida\nSaint John's Hospital and Health Center, Santa Monica, California\nSt. Louis University School of Medicine, Department of Pathology, Division of Forensic and Environmental Pathology\nState Bar of California\nTarget\nTexas District & County Attorneys Association\nTulane University School of Public Health\nUnited States Secret Service, Intelligence Division\nUnited States Department of Justice\nUniversity of Alberta Forensic Pathology Fellowship\nUniversity of Arkansas for Medical Sciences\nUniversity of California, Irvine, Program in Psychology and Law\nUniversity of California, Irvine, Program in Social Ecology\nUniversity of California, Irvine, School of Law\nDOJ-OGR-00007628",
  "text_blocks": [
    {
      "type": "printed",
      "content": "Case 1:20-cr-00330-PAE Document 499-1 Filed 11/23/21 Page 135 of 375",
      "position": "header"
    },
    {
      "type": "printed",
      "content": "Park Dietz, M.D., M.P.H., Ph.D.\nPage 73",
      "position": "top"
    },
    {
      "type": "printed",
      "content": "Law Enforcement Coordinating Committee, New Jersey\nLaw Enforcement Coordinating Committee, Texas\nLos Angeles Criminal Justice Inns of Court\nLos Angeles Police Department Threat Management Unit\nLouisiana District Attorneys Association\nMedical College of Virginia, Department of Legal Medicine\nMinnesota Employment Law Counsel\nMinnesota State Bar Association Criminal Justice Institute\nMinnesota State Bar Association Employment Law Institute\nNational College of District Attorneys\nNational Institute of Drug Abuse Research Center\nNewport Beach (CA) Police Department\nNorth Texas District Attorneys\nOffice of the District Attorney, County of Fresno, California\nOrange County Bar Association\nOrange County Bar Association Employment Law Section\nOrange County District Attorney's Office\nOrange County Homicide Investigators Association\nOrange County Inns of Court\nPackaging Institute International\nParamount Studios\nProsecuting Attorneys' Council of Georgia\nRichmond Psychiatric Society\nRobert Presley Institute of Criminal Investigation\nSan Diego Psychiatric Society\nSouth Beach Psychiatric Center, New York, New York\nSouthern California Chapter, American Academy of Psychiatry and the Law\nSoutheastern Prosecutors Institute\nSpace Coast Institute of Legal Medicine, Orlando, Florida\nSaint John's Hospital and Health Center, Santa Monica, California\nSt. Louis University School of Medicine, Department of Pathology, Division of Forensic and Environmental Pathology\nState Bar of California\nTarget\nTexas District & County Attorneys Association\nTulane University School of Public Health\nUnited States Secret Service, Intelligence Division\nUnited States Department of Justice\nUniversity of Alberta Forensic Pathology Fellowship\nUniversity of Arkansas for Medical Sciences\nUniversity of California, Irvine, Program in Psychology and Law\nUniversity of California, Irvine, Program in Social Ecology\nUniversity of California, Irvine, School of Law",
      "position": "middle"
    },
    {
      "type": "printed",
      "content": "DOJ-OGR-00007628",
      "position": "footer"
    }
  ],
  "entities": {
    "people": [
      "Park Dietz"
    ],
    "organizations": [
      "Law Enforcement Coordinating Committee",
      "Los Angeles Criminal Justice Inns of Court",
      "Los Angeles Police Department Threat Management Unit",
      "Louisiana District Attorneys Association",
      "Medical College of Virginia",
      "Minnesota Employment Law Counsel",
      "Minnesota State Bar Association",
      "National College of District Attorneys",
      "National Institute of Drug Abuse Research Center",
      "Newport Beach Police Department",
      "North Texas District Attorneys",
      "Office of the District Attorney",
      "Orange County Bar Association",
      "Orange County District Attorney's Office",
      "Orange County Homicide Investigators Association",
      "Orange County Inns of Court",
      "Packaging Institute International",
      "Paramount Studios",
      "Prosecuting Attorneys' Council of Georgia",
      "Richmond Psychiatric Society",
      "Robert Presley Institute of Criminal Investigation",
      "San Diego Psychiatric Society",
      "South Beach Psychiatric Center",
      "Southern California Chapter, American Academy of Psychiatry and the Law",
      "Southeastern Prosecutors Institute",
      "Space Coast Institute of Legal Medicine",
      "Saint John's Hospital and Health Center",
      "St. Louis University School of Medicine",
      "State Bar of California",
      "Target",
      "Texas District & County Attorneys Association",
      "Tulane University School of Public Health",
      "United States Secret Service",
      "United States Department of Justice",
      "University of Alberta",
      "University of Arkansas for Medical Sciences",
      "University of California, Irvine"
    ],
    "locations": [
      "New Jersey",
      "Texas",
      "Los Angeles",
      "Louisiana",
      "Virginia",
      "Minnesota",
      "California",
      "Newport Beach",
      "Fresno",
      "Orange County",
      "Georgia",
      "New York",
      "Florida",
      "Santa Monica",
      "Orlando",
      "Alberta",
      "Arkansas",
      "Irvine"
    ],
    "dates": [
      "11/23/21"
    ],
    "reference_numbers": [
      "1:20-cr-00330-PAE",
      "499-1",
      "DOJ-OGR-00007628"
    ]
  },
  "additional_notes": "The document appears to be a list of organizations and individuals related to a court case, likely expert witnesses or organizations involved in the case. The document is well-formatted and easy to read."
}