{
  "document_metadata": {
    "page_number": "2 of 2",
    "document_number": "431",
    "date": "11/09/21",
    "document_type": "Court Document",
    "has_handwriting": true,
    "has_stamps": false
  },
  "full_text": "Case 1:20-cr-00330-PAE Document 431 Filed 11/09/21 Page 2 of 2\n\nSpace will be available in the courtroom proper for members of the media. In order to comply with the District's COVID-19 protocols, the public and additional members of the media will be able to access the proceeding in overflow Courtrooms 506 and 905 of the Thurgood Marshall U.S. Courthouse. These overflow rooms will have live video and audio feeds of the proceeding.\n\nThe use of any electronic devices during the proceeding in the overflow rooms is strictly prohibited.\n\nThe Court anticipates seating capacity in the overflow rooms for 50 members of the public. If capacity is reached, no additional persons will be admitted. Per the S.D.N.Y. Response to COVID-19, anyone who appears at any S.D.N.Y. courthouse must complete a questionnaire on the date of the proceeding prior to entering the courthouse. All visitors must also have their temperature taken when they arrive at the courthouse. Only persons who meet the entry requirements established by the questionnaire and whose temperatures are below 100.4 degrees will be allowed to enter the courthouse. All visitors must wear a mask that covers the person's nose and mouth. Bandannas, gaiters, and masks with valves are not permitted. If a person does not have an approved mask, a screener will provide one. Anyone who fails to comply with the COVID-19 protocols that have been adopted by the Court will be required to leave the courthouse. There are no exceptions. For more information, please see https://www.nysd.uscourts.gov/covid-19-coronavirus.\n\nSO ORDERED.\n\nDated: November 9, 2021\nNew York, New York\n\nALISON J. NATHAN\nUnited States District Judge",
  "text_blocks": [
    {
      "type": "printed",
      "content": "Case 1:20-cr-00330-PAE Document 431 Filed 11/09/21 Page 2 of 2",
      "position": "header"
    },
    {
      "type": "printed",
      "content": "Space will be available in the courtroom proper for members of the media. In order to comply with the District's COVID-19 protocols, the public and additional members of the media will be able to access the proceeding in overflow Courtrooms 506 and 905 of the Thurgood Marshall U.S. Courthouse. These overflow rooms will have live video and audio feeds of the proceeding.",
      "position": "top"
    },
    {
      "type": "printed",
      "content": "The use of any electronic devices during the proceeding in the overflow rooms is strictly prohibited.",
      "position": "middle"
    },
    {
      "type": "printed",
      "content": "The Court anticipates seating capacity in the overflow rooms for 50 members of the public. If capacity is reached, no additional persons will be admitted. Per the S.D.N.Y. Response to COVID-19, anyone who appears at any S.D.N.Y. courthouse must complete a questionnaire on the date of the proceeding prior to entering the courthouse. All visitors must also have their temperature taken when they arrive at the courthouse. Only persons who meet the entry requirements established by the questionnaire and whose temperatures are below 100.4 degrees will be allowed to enter the courthouse. All visitors must wear a mask that covers the person's nose and mouth. Bandannas, gaiters, and masks with valves are not permitted. If a person does not have an approved mask, a screener will provide one. Anyone who fails to comply with the COVID-19 protocols that have been adopted by the Court will be required to leave the courthouse. There are no exceptions. For more information, please see https://www.nysd.uscourts.gov/covid-19-coronavirus.",
      "position": "middle"
    },
    {
      "type": "printed",
      "content": "SO ORDERED.",
      "position": "middle"
    },
    {
      "type": "printed",
      "content": "Dated: November 9, 2021\nNew York, New York",
      "position": "bottom"
    },
    {
      "type": "handwritten",
      "content": "Alison J. Nathan",
      "position": "bottom"
    },
    {
      "type": "printed",
      "content": "ALISON J. NATHAN\nUnited States District Judge",
      "position": "bottom"
    },
    {
      "type": "printed",
      "content": "DOJ-OGR-00006332",
      "position": "footer"
    }
  ],
  "entities": {
    "people": [
      "Alison J. Nathan",
      "Thurgood Marshall"
    ],
    "organizations": [
      "S.D.N.Y.",
      "U.S. Courthouse",
      "United States District Court"
    ],
    "locations": [
      "New York"
    ],
    "dates": [
      "November 9, 2021",
      "11/09/21"
    ],
    "reference_numbers": [
      "1:20-cr-00330-PAE",
      "431",
      "DOJ-OGR-00006332"
    ]
  },
  "additional_notes": "The document appears to be a court order related to COVID-19 protocols in a U.S. courthouse. The text is mostly printed, with a handwritten signature at the bottom. There are no visible stamps or redactions."
}