{
  "document_metadata": {
    "page_number": "2",
    "document_number": "509-1",
    "date": "11/24/21",
    "document_type": "court document",
    "has_handwriting": false,
    "has_stamps": false
  },
  "full_text": "Case 1:20-cr-00330-PAE Document 509-1 Filed 11/24/21 Page 2 of 10\n\nPRELIMINARY STATEMENT\n\nOn November 15, 2021, the Government filed its motion (\"Mot.\") to exclude the testimony of Dr. Ryan Hall as irrelevant, more prejudicial than probative, and consisting of hearsay not subject to an exception. This reply addresses several of the most salient arguments in the defendant's November 19, 2021 opposition (\"Opp.\").1\n\nI. Do Not Bear on Minor Victim-4's Credibility.\nThe defendant does not dispute that Dr. Hall's principal conclusion—is inadmissible. (Compare Mot. 5-6 (moving to exclude this conclusion) with Opp. 4 (noting conclusion but not defending its admissibility)). The parties also appear to agree on the relevant legal standard for assessing Dr. Hall's . (Mot. 6 (quoting United States v. Sasso, 59 F.3d 341, 347-48 (2d Cir. 1995); Opp. 7 (same)). From there, however, the defendant's response strays. The Government's Motion applied the caselaw to (Mot. 6-10). The defendant expanded upon the general legal standard (Opp. 7-8) but then offered only ad hoc arguments, untied to the law and without offering evidence that they were sufficiently serious to satisfy the standard . The defendant's argument focuses on .\n\n1 This reply does not address the defendant's other five proposed experts (see Mot. 20-25), or those arguments of the defendant that seem entirely unresponsive.\n\n1\n\nDOJ-OGR-00008113",
  "text_blocks": [
    {
      "type": "printed",
      "content": "Case 1:20-cr-00330-PAE Document 509-1 Filed 11/24/21 Page 2 of 10",
      "position": "header"
    },
    {
      "type": "printed",
      "content": "PRELIMINARY STATEMENT",
      "position": "top"
    },
    {
      "type": "printed",
      "content": "On November 15, 2021, the Government filed its motion (\"Mot.\") to exclude the testimony of Dr. Ryan Hall as irrelevant, more prejudicial than probative, and consisting of hearsay not subject to an exception. This reply addresses several of the most salient arguments in the defendant's November 19, 2021 opposition (\"Opp.\").1",
      "position": "middle"
    },
    {
      "type": "printed",
      "content": "I. Do Not Bear on Minor Victim-4's Credibility.",
      "position": "middle"
    },
    {
      "type": "printed",
      "content": "The defendant does not dispute that Dr. Hall's principal conclusion—is inadmissible. (Compare Mot. 5-6 (moving to exclude this conclusion) with Opp. 4 (noting conclusion but not defending its admissibility)). The parties also appear to agree on the relevant legal standard for assessing Dr. Hall's . (Mot. 6 (quoting United States v. Sasso, 59 F.3d 341, 347-48 (2d Cir. 1995); Opp. 7 (same)). From there, however, the defendant's response strays. The Government's Motion applied the caselaw to (Mot. 6-10). The defendant expanded upon the general legal standard (Opp. 7-8) but then offered only ad hoc arguments, untied to the law and without offering evidence that they were sufficiently serious to satisfy the standard . The defendant's argument focuses on .",
      "position": "middle"
    },
    {
      "type": "printed",
      "content": "1 This reply does not address the defendant's other five proposed experts (see Mot. 20-25), or those arguments of the defendant that seem entirely unresponsive.",
      "position": "footer"
    },
    {
      "type": "printed",
      "content": "DOJ-OGR-00008113",
      "position": "footer"
    }
  ],
  "entities": {
    "people": [
      "Dr. Ryan Hall"
    ],
    "organizations": [
      "Government"
    ],
    "locations": [],
    "dates": [
      "November 15, 2021",
      "November 19, 2021",
      "11/24/21"
    ],
    "reference_numbers": [
      "1:20-cr-00330-PAE",
      "509-1",
      "DOJ-OGR-00008113"
    ]
  },
  "additional_notes": "The document appears to be a court filing with some redacted text. The redactions are likely due to sensitive information being removed."
}