{
  "document_metadata": {
    "page_number": "32",
    "document_number": "499-2",
    "date": "11/23/21",
    "document_type": "court transcript",
    "has_handwriting": false,
    "has_stamps": false
  },
  "full_text": "Case 1:20-cr-00330-PAE Document 499-2 Filed 11/23/21 Page 32 of 15931 LBAGmax2 Rocchio - Direct offender is trying to win over the trust and affection of the child. Then there's another stage where the child is gradually exposed to greater levels of physical touch and sexual content and material that slowly escalates over time, and then strategies that keep the relationship going and help to prevent exposure. Q. Based on your experience, research and training are you familiar with the term grooming the environment? A. I am. Q. What is grooming the environment? A. It's a term that applies to commonly recognized phenomenon and strategies, tactics, modus operandi used by perpetrators in the service of getting them access to victims and building that relationship of trust. So in addition to manipulating the child, they'll manipulate individuals or institutions in that child's life so that they're able to have greater access. So they might, for example, befriend a child's parent and hold themselves out as a trustworthy person who is going to help, say, a single mom and he'll serve as a father figure to the kid. Or they might groom an institution, they might work their way up through the boy scouts, for example, and become a leader there, become a pillar in the community to give them an air of respectability, disarming, gaining trust. Q. Are you familiar with the term attachment? A. I am. SOUTHERN DISTRICT REPORTERS, P.C. (212) 805-0300 DOJ-OGR-00007900",
  "text_blocks": [
    {
      "type": "printed",
      "content": "Case 1:20-cr-00330-PAE Document 499-2 Filed 11/23/21 Page 32 of 15931",
      "position": "header"
    },
    {
      "type": "printed",
      "content": "LBAGmax2 Rocchio - Direct",
      "position": "header"
    },
    {
      "type": "printed",
      "content": "offender is trying to win over the trust and affection of the child. Then there's another stage where the child is gradually exposed to greater levels of physical touch and sexual content and material that slowly escalates over time, and then strategies that keep the relationship going and help to prevent exposure.",
      "position": "main content"
    },
    {
      "type": "printed",
      "content": "Q. Based on your experience, research and training are you familiar with the term grooming the environment?",
      "position": "main content"
    },
    {
      "type": "printed",
      "content": "A. I am.",
      "position": "main content"
    },
    {
      "type": "printed",
      "content": "Q. What is grooming the environment?",
      "position": "main content"
    },
    {
      "type": "printed",
      "content": "A. It's a term that applies to commonly recognized phenomenon and strategies, tactics, modus operandi used by perpetrators in the service of getting them access to victims and building that relationship of trust. So in addition to manipulating the child, they'll manipulate individuals or institutions in that child's life so that they're able to have greater access. So they might, for example, befriend a child's parent and hold themselves out as a trustworthy person who is going to help, say, a single mom and he'll serve as a father figure to the kid. Or they might groom an institution, they might work their way up through the boy scouts, for example, and become a leader there, become a pillar in the community to give them an air of respectability, disarming, gaining trust.",
      "position": "main content"
    },
    {
      "type": "printed",
      "content": "Q. Are you familiar with the term attachment?",
      "position": "main content"
    },
    {
      "type": "printed",
      "content": "A. I am.",
      "position": "main content"
    },
    {
      "type": "printed",
      "content": "SOUTHERN DISTRICT REPORTERS, P.C. (212) 805-0300",
      "position": "footer"
    },
    {
      "type": "printed",
      "content": "DOJ-OGR-00007900",
      "position": "footer"
    }
  ],
  "entities": {
    "people": [],
    "organizations": [
      "SOUTHERN DISTRICT REPORTERS, P.C.",
      "Boy Scouts"
    ],
    "locations": [],
    "dates": [
      "11/23/21"
    ],
    "reference_numbers": [
      "1:20-cr-00330-PAE",
      "499-2",
      "DOJ-OGR-00007900"
    ]
  },
  "additional_notes": "The document appears to be a court transcript with a clear and legible format. There are no visible redactions or damage."
}