{
  "document_metadata": {
    "page_number": "149",
    "document_number": "499-2",
    "date": "11/23/21",
    "document_type": "court transcript",
    "has_handwriting": false,
    "has_stamps": false
  },
  "full_text": "Case 1:20-cr-00330-PAE Document 499-2 Filed 11/23/21 Page 149 of 159148 LBAAMAX5ps Rocchio - Cross 1 Q. All right. And if we go to the summary here, the author is critical of offender-generated data or questions \"offender-generated data through self-reports because it could be subject to cognitive distortions -- minimization or exaggerations,\" correct? 2 A. I think that they are identifying potential issues that could be present with offender-generated data. 3 Q. Right. If we go to page 4, the McElvany and Culhane article. 4 A. The opinions in that study did continue. You didn't refer to all of their opinions, just part of them. 5 Q. That's OK. The government can ask you questions on redirect if they'd like. 6 A. OK. 7 Q. In this opinion, in this, the findings are, \"Majority of children told their mothers and their peers first.\" Do you see that? 8 A. Of those who disclosed, the majority told mothers and peers, yes. 9 Q. Right. Then the next study, 2014, when the -- 10 A. So that study, though, was among -- everybody in that study had already disclosed. It was a study of children who had already disclosed, to look at who they disclosed to. 11 Q. Right. 12 Then we have the next study here, \"220 minor victims\" SOUTHERN DISTRICT REPORTERS, P.C. (212) 805-0300 DOJ-OGR-00008017",
  "text_blocks": [
    {
      "type": "printed",
      "content": "Case 1:20-cr-00330-PAE Document 499-2 Filed 11/23/21 Page 149 of 159148",
      "position": "header"
    },
    {
      "type": "printed",
      "content": "LBAAMAX5ps Rocchio - Cross",
      "position": "header"
    },
    {
      "type": "printed",
      "content": "1 Q. All right. And if we go to the summary here, the author is critical of offender-generated data or questions \"offender-generated data through self-reports because it could be subject to cognitive distortions -- minimization or exaggerations,\" correct? 2 A. I think that they are identifying potential issues that could be present with offender-generated data. 3 Q. Right. If we go to page 4, the McElvany and Culhane article. 4 A. The opinions in that study did continue. You didn't refer to all of their opinions, just part of them. 5 Q. That's OK. The government can ask you questions on redirect if they'd like. 6 A. OK. 7 Q. In this opinion, in this, the findings are, \"Majority of children told their mothers and their peers first.\" Do you see that? 8 A. Of those who disclosed, the majority told mothers and peers, yes. 9 Q. Right. Then the next study, 2014, when the -- 10 A. So that study, though, was among -- everybody in that study had already disclosed. It was a study of children who had already disclosed, to look at who they disclosed to. 11 Q. Right. 12 Then we have the next study here, \"220 minor victims\"",
      "position": "main content"
    },
    {
      "type": "printed",
      "content": "SOUTHERN DISTRICT REPORTERS, P.C. (212) 805-0300",
      "position": "footer"
    },
    {
      "type": "printed",
      "content": "DOJ-OGR-00008017",
      "position": "footer"
    }
  ],
  "entities": {
    "people": [
      "Rocchio"
    ],
    "organizations": [
      "SOUTHERN DISTRICT REPORTERS, P.C."
    ],
    "locations": [],
    "dates": [
      "11/23/21",
      "2014"
    ],
    "reference_numbers": [
      "1:20-cr-00330-PAE",
      "499-2",
      "DOJ-OGR-00008017"
    ]
  },
  "additional_notes": "The document appears to be a court transcript with a clear and legible format. There are no visible redactions or damage."
}