{
  "document_metadata": {
    "page_number": "374",
    "document_number": "499-1",
    "date": "11/23/21",
    "document_type": "Case document",
    "has_handwriting": false,
    "has_stamps": false
  },
  "full_text": "Case 1:20-cr-00330-PAE Document 499-1 Filed 11/23/21 Page 374 of 375\nMark Hofmann - Master Forger and Murderer workshop, American Society of Questioned Document Examiners, Park City, UT 2018.\nLatin American Writing Workshop, American Society of Questioned Document Examiners, Park City, UT 2018.\nPreparing a Digital Signature File for Forensic Analysis Workshop, American Society of Questioned Document Examiners, San Diego, CA 2017.\nForensic Science Research: Your Mission to Propose, Innovate, and Collaborate - Workshop, American Society of Questioned Document Examiners, San Diego, CA 2017.\nChinese Handwriting and Signatures Workshop: \"Hanzi\" through the eyes of the Forensic Document Examiner, American Society of Questioned Document Examiners, San Diego, CA 2017.\nLeveraging Technology for QD Courtroom Presentations Workshop, Mid-Atlantic Association of Forensic Scientists, Hunt Valley, MD 2009\nArabic Immersion Program, Gulf Arabic Program, Professional Training Institute, Buraimi, Oman 2008\nCharred Documents Workshop, by Gabe Watts, Mid-Atlantic Association of Forensic Scientists, Huntington, WV 2008\nExpert Witness Testimony Workshop, Mid-Atlantic Association of Forensic Scientists, Huntington, WV 2008\nPreparing for Daubert Hearing Workshop, Mid-Atlantic Association of Forensic Scientists, Huntington, WV 2008\nBeginning Modern Standard Arabic Level IV, Ibrahim Elgendy, Middle East Institute, Washington, D.C. 2008\nArabic Immersion Program, American Language Institute in Fes, Fes, Morocco 2007\nIntermediate Arabic I, Aisha Sherbiny, Arlington Adult Education Center, Arlington VA 2007\nInfrared and Ultraviolet Imaging Workshop, by Chandra Janney, International Association for Identification, San Diego, CA 2007\nForensic Identification of Print Processes, hosted by the United States Secret Service and the Rochester Institute of Technology, Rochester, NY 2007\nChemically Prepared Toner Workshop, by Graham J. Galliford, Mid-Atlantic Association of Forensic Science, Washington, DC 2007\nBeginning Arabic Level II, Aisha Sherbiny, Arlington Adult Education Center, Arlington, VA 2007\nFundamentals of Handwriting, hosted by the Federal Bureau of Investigation Forensics Laboratory, Quantico, VA 2007\nBeginning Arabic Level I, Aisha Sherbiny, Arlington Adult Education Center, Arlington, VA 2006\nAuthenticating and Dating Methods Used in Forensic Document Examination, by Gerry Laporte, American Board of Forensic Document Examiners Annual Meeting, Las Vegas, NV 2006\nDOJ-OGR-00007867",
  "text_blocks": [
    {
      "type": "printed",
      "content": "Case 1:20-cr-00330-PAE Document 499-1 Filed 11/23/21 Page 374 of 375",
      "position": "header"
    },
    {
      "type": "printed",
      "content": "Mark Hofmann - Master Forger and Murderer workshop, American Society of Questioned Document Examiners, Park City, UT 2018.\nLatin American Writing Workshop, American Society of Questioned Document Examiners, Park City, UT 2018.\nPreparing a Digital Signature File for Forensic Analysis Workshop, American Society of Questioned Document Examiners, San Diego, CA 2017.\nForensic Science Research: Your Mission to Propose, Innovate, and Collaborate - Workshop, American Society of Questioned Document Examiners, San Diego, CA 2017.\nChinese Handwriting and Signatures Workshop: \"Hanzi\" through the eyes of the Forensic Document Examiner, American Society of Questioned Document Examiners, San Diego, CA 2017.\nLeveraging Technology for QD Courtroom Presentations Workshop, Mid-Atlantic Association of Forensic Scientists, Hunt Valley, MD 2009\nArabic Immersion Program, Gulf Arabic Program, Professional Training Institute, Buraimi, Oman 2008\nCharred Documents Workshop, by Gabe Watts, Mid-Atlantic Association of Forensic Scientists, Huntington, WV 2008\nExpert Witness Testimony Workshop, Mid-Atlantic Association of Forensic Scientists, Huntington, WV 2008\nPreparing for Daubert Hearing Workshop, Mid-Atlantic Association of Forensic Scientists, Huntington, WV 2008\nBeginning Modern Standard Arabic Level IV, Ibrahim Elgendy, Middle East Institute, Washington, D.C. 2008\nArabic Immersion Program, American Language Institute in Fes, Fes, Morocco 2007\nIntermediate Arabic I, Aisha Sherbiny, Arlington Adult Education Center, Arlington VA 2007\nInfrared and Ultraviolet Imaging Workshop, by Chandra Janney, International Association for Identification, San Diego, CA 2007\nForensic Identification of Print Processes, hosted by the United States Secret Service and the Rochester Institute of Technology, Rochester, NY 2007\nChemically Prepared Toner Workshop, by Graham J. Galliford, Mid-Atlantic Association of Forensic Science, Washington, DC 2007\nBeginning Arabic Level II, Aisha Sherbiny, Arlington Adult Education Center, Arlington, VA 2007\nFundamentals of Handwriting, hosted by the Federal Bureau of Investigation Forensics Laboratory, Quantico, VA 2007\nBeginning Arabic Level I, Aisha Sherbiny, Arlington Adult Education Center, Arlington, VA 2006\nAuthenticating and Dating Methods Used in Forensic Document Examination, by Gerry Laporte, American Board of Forensic Document Examiners Annual Meeting, Las Vegas, NV 2006",
      "position": "main content"
    },
    {
      "type": "printed",
      "content": "DOJ-OGR-00007867",
      "position": "footer"
    }
  ],
  "entities": {
    "people": [
      "Mark Hofmann",
      "Gabe Watts",
      "Ibrahim Elgendy",
      "Aisha Sherbiny",
      "Chandra Janney",
      "Graham J. Galliford",
      "Gerry Laporte"
    ],
    "organizations": [
      "American Society of Questioned Document Examiners",
      "Mid-Atlantic Association of Forensic Scientists",
      "Gulf Arabic Program",
      "Professional Training Institute",
      "American Language Institute in Fes",
      "Arlington Adult Education Center",
      "International Association for Identification",
      "United States Secret Service",
      "Rochester Institute of Technology",
      "Federal Bureau of Investigation Forensics Laboratory",
      "American Board of Forensic Document Examiners"
    ],
    "locations": [
      "Park City, UT",
      "San Diego, CA",
      "Hunt Valley, MD",
      "Buraimi, Oman",
      "Huntington, WV",
      "Washington, D.C.",
      "Fes, Morocco",
      "Arlington, VA",
      "Rochester, NY",
      "Quantico, VA",
      "Las Vegas, NV"
    ],
    "dates": [
      "2018",
      "2017",
      "2009",
      "2008",
      "2007",
      "2006",
      "11/23/21"
    ],
    "reference_numbers": [
      "1:20-cr-00330-PAE",
      "499-1",
      "DOJ-OGR-00007867"
    ]
  },
  "additional_notes": "The document appears to be a list of workshops and training programs attended by an individual, likely related to forensic document examination. The document is well-formatted and legible."
}