{
  "document_metadata": {
    "page_number": "13",
    "document_number": "427",
    "date": "11/09/21",
    "document_type": "juror questionnaire",
    "has_handwriting": false,
    "has_stamps": false
  },
  "full_text": "Case 1:20-cr-00330-PAE Document 427 Filed 11/09/21 Page 13 of 16\n\nWhat type of case was it? Without telling us what the verdict was, did the jury reach a verdict?\n14. [For jurors who answered YES to question 8] On your questionnaire you said that you have served as a grand juror. When and where?\n15. [For jurors who answered YES to either question] Is there anything about your prior experiences as a juror that would prevent you from acting as a fair and impartial juror in this case?\n\nRelationship with, and View of, Government, Defense, and Others\n16. Have you, either through any experience you have had or anything you have seen or read, developed any bias or prejudice or other feelings for or against the United States Department of Justice, the United States Attorney's Office for the Southern District of New York, the FBI, or the NYPD?\n17. Do you have any opinions about prosecutors or criminal defense attorneys generally that might make it difficult for you to be a fair and impartial juror in this case?\n18. Do you have any opinion about the criminal justice system generally or the federal criminal justice system in particular that might make it difficult for you to be a fair and impartial juror in this case?\n19. Do you have any opinion about people who are wealthy or have luxurious lifestyles that might make it difficult for you to be a fair and impartial juror in this case?\n\n5\nDOJ-OGR-00006324",
  "text_blocks": [
    {
      "type": "printed",
      "content": "Case 1:20-cr-00330-PAE Document 427 Filed 11/09/21 Page 13 of 16",
      "position": "header"
    },
    {
      "type": "printed",
      "content": "What type of case was it? Without telling us what the verdict was, did the jury reach a verdict?\n14. [For jurors who answered YES to question 8] On your questionnaire you said that you have served as a grand juror. When and where?\n15. [For jurors who answered YES to either question] Is there anything about your prior experiences as a juror that would prevent you from acting as a fair and impartial juror in this case?",
      "position": "top"
    },
    {
      "type": "printed",
      "content": "Relationship with, and View of, Government, Defense, and Others",
      "position": "middle"
    },
    {
      "type": "printed",
      "content": "16. Have you, either through any experience you have had or anything you have seen or read, developed any bias or prejudice or other feelings for or against the United States Department of Justice, the United States Attorney's Office for the Southern District of New York, the FBI, or the NYPD?\n17. Do you have any opinions about prosecutors or criminal defense attorneys generally that might make it difficult for you to be a fair and impartial juror in this case?\n18. Do you have any opinion about the criminal justice system generally or the federal criminal justice system in particular that might make it difficult for you to be a fair and impartial juror in this case?\n19. Do you have any opinion about people who are wealthy or have luxurious lifestyles that might make it difficult for you to be a fair and impartial juror in this case?",
      "position": "middle"
    },
    {
      "type": "printed",
      "content": "5",
      "position": "bottom"
    },
    {
      "type": "printed",
      "content": "DOJ-OGR-00006324",
      "position": "footer"
    }
  ],
  "entities": {
    "people": [],
    "organizations": [
      "United States Department of Justice",
      "United States Attorney's Office",
      "FBI",
      "NYPD"
    ],
    "locations": [
      "Southern District of New York"
    ],
    "dates": [
      "11/09/21"
    ],
    "reference_numbers": [
      "1:20-cr-00330-PAE",
      "Document 427",
      "DOJ-OGR-00006324"
    ]
  },
  "additional_notes": "The document appears to be a juror questionnaire from a federal criminal case. The questions are designed to assess the juror's impartiality and potential biases. The document is well-formatted and legible."
}