{
  "document_metadata": {
    "page_number": "131",
    "document_number": "467",
    "date": "11/15/21",
    "document_type": "Court Transcript",
    "has_handwriting": false,
    "has_stamps": false
  },
  "full_text": "Case 1:20-cr-00330-PAE Document 467 Filed 11/15/21 Page 131 of 158 131 LBAAMAX5ps Rocchio - Cross 1 AFTERNOON SESSION 1:25 p.m. 2 3 LISA ROCCHIO, resumed. 4 THE COURT: Mr. Pagliuca, you may proceed. 5 MR. PAGLIUCA: Thank you, your Honor. 6 CROSS EXAMINATION (Cont'd) 7 BY MR. PAGLIUCA: 8 Q. Dr. Rocchio, we were talking about Exhibit 3, and as I understand it, this is the most recent attempt to validate the sexual grooming model of child sexual abusers; is that correct? 9 10 A. That's the most recent attempt to validate this particular model, yes. 11 12 Q. OK. Well -- 13 A. Actually, it's a recent. I'm not sure what research has been done since that. 14 15 Q. You were asked by the government to give the government whatever articles you thought were helpful with regard to your testimony here today. Is that correct? 16 17 A. I was asked by the government to give examples of articles that pertained to the subject matter of my testimony today. 18 19 Q. OK. And as I understand it, this is a hearing to determine whether or not there were scientifically valid principles under federal law to admit this testimony. You understand that. 20 21 A. Yes, I do. 22 23 Q. And one of the things that you did was provide the 24 25 SOUTHERN DISTRICT REPORTERS, P.C. (212) 805-0300 DOJ-OGR-00007310",
  "text_blocks": [
    {
      "type": "printed",
      "content": "Case 1:20-cr-00330-PAE Document 467 Filed 11/15/21 Page 131 of 158 131 LBAAMAX5ps Rocchio - Cross",
      "position": "header"
    },
    {
      "type": "printed",
      "content": "AFTERNOON SESSION 1:25 p.m. LISA ROCCHIO, resumed. THE COURT: Mr. Pagliuca, you may proceed. MR. PAGLIUCA: Thank you, your Honor. CROSS EXAMINATION (Cont'd) BY MR. PAGLIUCA: Q. Dr. Rocchio, we were talking about Exhibit 3, and as I understand it, this is the most recent attempt to validate the sexual grooming model of child sexual abusers; is that correct? A. That's the most recent attempt to validate this particular model, yes. Q. OK. Well -- A. Actually, it's a recent. I'm not sure what research has been done since that. Q. You were asked by the government to give the government whatever articles you thought were helpful with regard to your testimony here today. Is that correct? A. I was asked by the government to give examples of articles that pertained to the subject matter of my testimony today. Q. OK. And as I understand it, this is a hearing to determine whether or not there were scientifically valid principles under federal law to admit this testimony. You understand that. A. Yes, I do. Q. And one of the things that you did was provide the",
      "position": "main"
    },
    {
      "type": "printed",
      "content": "SOUTHERN DISTRICT REPORTERS, P.C. (212) 805-0300",
      "position": "footer"
    },
    {
      "type": "printed",
      "content": "DOJ-OGR-00007310",
      "position": "footer"
    }
  ],
  "entities": {
    "people": [
      "LISA ROCCHIO",
      "MR. PAGLIUCA"
    ],
    "organizations": [
      "SOUTHERN DISTRICT REPORTERS, P.C."
    ],
    "locations": [],
    "dates": [
      "11/15/21"
    ],
    "reference_numbers": [
      "1:20-cr-00330-PAE",
      "Document 467",
      "Exhibit 3",
      "DOJ-OGR-00007310"
    ]
  },
  "additional_notes": "The document is a court transcript from a criminal case. The transcript appears to be of good quality with clear text. There are no visible redactions or damage."
}