{
  "document_metadata": {
    "page_number": "5",
    "document_number": "533",
    "date": "12/09/21",
    "document_type": "court document",
    "has_handwriting": false,
    "has_stamps": false
  },
  "full_text": "Case 1:20-cr-00330-PAE Document 533 Filed 12/09/21 Page 5 of 8 Rule 901(b)(4) where the proposed evidence contained \"identical\" or \"substantially similar, pages of 'nonpublic information' as admitted evidence). The list under \"Massage - Florida\" in Government Exhibit 52-G2 includes the following entries: \"Virginia (parents).\" Entries for \"Melissa (Carolyn's friend)\" and \"Kristen (carolyn's friend).\" Carolyn testified that she brought other victims to Epstein's Palm Beach house, Tr. 1543, and Shawn testified this morning that one such friend was named Melissa. Gwendolyn Beck. David Rogers testified this evening that Gwendolyn Beck was a friend of Epstein's who flew on his private plane. Elsewhere, the contact book contains private information demonstrating its authenticity as an item that belonged to Epstein and Maxwell, including: 2 Government Exhibit 52-G is a photocopy of a page within Government Exhibit 52. 5 DOJ-OGR-00008277",
  "text_blocks": [
    {
      "type": "printed",
      "content": "Case 1:20-cr-00330-PAE Document 533 Filed 12/09/21 Page 5 of 8",
      "position": "header"
    },
    {
      "type": "printed",
      "content": "Rule 901(b)(4) where the proposed evidence contained \"identical\" or \"substantially similar, pages of 'nonpublic information' as admitted evidence). The list under \"Massage - Florida\" in Government Exhibit 52-G2 includes the following entries:",
      "position": "top"
    },
    {
      "type": "printed",
      "content": "\"Virginia (parents).\"",
      "position": "middle"
    },
    {
      "type": "printed",
      "content": "Entries for \"Melissa (Carolyn's friend)\" and \"Kristen (carolyn's friend).\" Carolyn testified that she brought other victims to Epstein's Palm Beach house, Tr. 1543, and Shawn testified this morning that one such friend was named Melissa.",
      "position": "middle"
    },
    {
      "type": "printed",
      "content": "Gwendolyn Beck. David Rogers testified this evening that Gwendolyn Beck was a friend of Epstein's who flew on his private plane.",
      "position": "middle"
    },
    {
      "type": "printed",
      "content": "Elsewhere, the contact book contains private information demonstrating its authenticity as an item that belonged to Epstein and Maxwell, including:",
      "position": "middle"
    },
    {
      "type": "printed",
      "content": "2 Government Exhibit 52-G is a photocopy of a page within Government Exhibit 52.",
      "position": "bottom"
    },
    {
      "type": "printed",
      "content": "5",
      "position": "footer"
    },
    {
      "type": "printed",
      "content": "DOJ-OGR-00008277",
      "position": "footer"
    }
  ],
  "entities": {
    "people": [
      "Carolyn",
      "Melissa",
      "Kristen",
      "Gwendolyn Beck",
      "David Rogers",
      "Epstein",
      "Maxwell",
      "Shawn"
    ],
    "organizations": [],
    "locations": [
      "Florida",
      "Virginia",
      "Palm Beach"
    ],
    "dates": [
      "12/09/21"
    ],
    "reference_numbers": [
      "1:20-cr-00330-PAE",
      "Document 533",
      "Government Exhibit 52-G2",
      "Government Exhibit 52",
      "Tr. 1543",
      "DOJ-OGR-00008277"
    ]
  },
  "additional_notes": "The document contains redactions, likely to protect sensitive information. The text is mostly printed, with no visible handwriting or stamps."
}