{
  "document_metadata": {
    "page_number": "98 of 375",
    "document_number": "499-1",
    "date": "11/23/21",
    "document_type": "Court Document",
    "has_handwriting": false,
    "has_stamps": false
  },
  "full_text": "Case 1:20-cr-00330-PAE Document 499-1 Filed 11/23/21 Page 98 of 375\nPark Dietz, M.D., M.P.H., Ph.D.\nPage 36\nPUBLICATIONS:\nJournal:\n1. Dietz PE, Baker SP: Drowning: Epidemiology and prevention. American Journal of Public Health 64:303-312, 1974.\n2. Rubin RR, Elkes J, Maris RW, Dietz PE: Medicine and the behavioral sciences: The Johns Hopkins M.D.-Ph.D. Program. Johns Hopkins Medical Journal 136:268-270, 1975.\n3. Dietz PE: Clinical approaches to teaching legal medicine to physicians: Medicolegal emergencies and consultations. American Journal of Law and Medicine 2:133-145, 1976.\n4. Dietz PE: Toward a scientific forensic psychiatry. Journal of Forensic Sciences 22:774-780, 1977.\n5. Dietz PE: Social discrediting of psychiatry: The protasis of legal disfranchisement. American Journal of Psychiatry 134:1356-1360, 1977.\n6. Dietz PE: Victim-precipitated criminal homicide. Bulletin of the American Academy of Psychiatry and the Law 5:367-370, 1977.\n7. Dietz PE: Cosmetic surgical treatment of offenders. Bulletin of the American Academy of Psychiatry and the Law 5:465-469, 1977.\n8. Rappeport JR, Dietz PE: Professional activities of Maryland and U.S. psychiatrists. Maryland State Medical Journal 27:45-48, March 1978.\n9. Dietz PE: Forensic and non-forensic psychiatrists: An empirical comparision. Bulletin of the American Academy of Psychiatry and the Law 6:13-23, 1978.\n10. Dietz PE: Access to medical literature in medical criminology. Bulletin of the American Academy of Psychiatry and the Law 6:110-117, 1978.\n11. Matthews D, Dietz PE: Labeling theory and the family dynamics of schizophrenia: A theoretical synthesis. Child Psychiatry Quarterly 11:83-97, 1978.\nDOJ-OGR-00007591",
  "text_blocks": [
    {
      "type": "printed",
      "content": "Case 1:20-cr-00330-PAE Document 499-1 Filed 11/23/21 Page 98 of 375",
      "position": "header"
    },
    {
      "type": "printed",
      "content": "Park Dietz, M.D., M.P.H., Ph.D.\nPage 36",
      "position": "header"
    },
    {
      "type": "printed",
      "content": "PUBLICATIONS:\nJournal:",
      "position": "top"
    },
    {
      "type": "printed",
      "content": "1. Dietz PE, Baker SP: Drowning: Epidemiology and prevention. American Journal of Public Health 64:303-312, 1974.\n2. Rubin RR, Elkes J, Maris RW, Dietz PE: Medicine and the behavioral sciences: The Johns Hopkins M.D.-Ph.D. Program. Johns Hopkins Medical Journal 136:268-270, 1975.\n3. Dietz PE: Clinical approaches to teaching legal medicine to physicians: Medicolegal emergencies and consultations. American Journal of Law and Medicine 2:133-145, 1976.\n4. Dietz PE: Toward a scientific forensic psychiatry. Journal of Forensic Sciences 22:774-780, 1977.\n5. Dietz PE: Social discrediting of psychiatry: The protasis of legal disfranchisement. American Journal of Psychiatry 134:1356-1360, 1977.\n6. Dietz PE: Victim-precipitated criminal homicide. Bulletin of the American Academy of Psychiatry and the Law 5:367-370, 1977.\n7. Dietz PE: Cosmetic surgical treatment of offenders. Bulletin of the American Academy of Psychiatry and the Law 5:465-469, 1977.\n8. Rappeport JR, Dietz PE: Professional activities of Maryland and U.S. psychiatrists. Maryland State Medical Journal 27:45-48, March 1978.\n9. Dietz PE: Forensic and non-forensic psychiatrists: An empirical comparision. Bulletin of the American Academy of Psychiatry and the Law 6:13-23, 1978.\n10. Dietz PE: Access to medical literature in medical criminology. Bulletin of the American Academy of Psychiatry and the Law 6:110-117, 1978.\n11. Matthews D, Dietz PE: Labeling theory and the family dynamics of schizophrenia: A theoretical synthesis. Child Psychiatry Quarterly 11:83-97, 1978.",
      "position": "middle"
    },
    {
      "type": "printed",
      "content": "DOJ-OGR-00007591",
      "position": "footer"
    }
  ],
  "entities": {
    "people": [
      "Park Dietz",
      "Dietz PE",
      "Baker SP",
      "Rubin RR",
      "Elkes J",
      "Maris RW",
      "Rappeport JR",
      "Matthews D"
    ],
    "organizations": [
      "Johns Hopkins University",
      "American Academy of Psychiatry and the Law"
    ],
    "locations": [
      "Maryland"
    ],
    "dates": [
      "11/23/21",
      "1974",
      "1975",
      "1976",
      "1977",
      "1978",
      "March 1978"
    ],
    "reference_numbers": [
      "1:20-cr-00330-PAE",
      "499-1",
      "DOJ-OGR-00007591"
    ]
  },
  "additional_notes": "The document appears to be a court filing related to a case involving Park Dietz, M.D., M.P.H., Ph.D. The document lists publications by Dietz PE, a prominent forensic psychiatrist. The text is well-formatted and easy to read."
}