{
  "document_metadata": {
    "page_number": "1",
    "document_number": "445",
    "date": "11/12/21",
    "document_type": "Court Document",
    "has_handwriting": false,
    "has_stamps": false
  },
  "full_text": "Case 1:20-cr-00330-PAE Document 445 Filed 11/12/21 Page 1 of 11\n\nUNITED STATES DISTRICT COURT\nSOUTHERN DISTRICT OF NEW YORK\n\nUNITED STATES OF AMERICA,\nv.\nGHISLAINE MAXWELL,\nDefendant.\n\nGHISLAINE MAXWELL'S MOTION IN LIMINE TO EXCLUDE GOVERNMENT EXHIBIT 52, AN UNAUTHENTICATED HEARSAY DOCUMENT FROM SUSPECT SOURCES\n\nJeffrey S. Pagliuca\nLaura A. Menninger\nHADDON, MORGAN & FOREMAN P.C.\n150 East 10th Avenue\nDenver, CO 80203\nPhone: 303-831-7364\n\nChristian R. Everdell\nCOHEN & GRESSER LLP\n800 Third Avenue New\nYork, NY 10022\nPhone: 212-957-7600\n\nBobbi C. Sternheim\nLaw Offices of Bobbi C. Sternheim\n225 Broadway, Suite 715\nNew York, NY 10007\nPhone: 212-243-1100\n\nAttorneys for Ghislaine Maxwell\n\nDOJ-OGR-00006650",
  "text_blocks": [
    {
      "type": "printed",
      "content": "Case 1:20-cr-00330-PAE Document 445 Filed 11/12/21 Page 1 of 11",
      "position": "header"
    },
    {
      "type": "printed",
      "content": "UNITED STATES DISTRICT COURT\nSOUTHERN DISTRICT OF NEW YORK",
      "position": "top"
    },
    {
      "type": "printed",
      "content": "UNITED STATES OF AMERICA,\nv.\nGHISLAINE MAXWELL,\nDefendant.",
      "position": "top"
    },
    {
      "type": "printed",
      "content": "GHISLAINE MAXWELL'S MOTION IN LIMINE TO EXCLUDE GOVERNMENT EXHIBIT 52, AN UNAUTHENTICATED HEARSAY DOCUMENT FROM SUSPECT SOURCES",
      "position": "middle"
    },
    {
      "type": "printed",
      "content": "Jeffrey S. Pagliuca\nLaura A. Menninger\nHADDON, MORGAN & FOREMAN P.C.\n150 East 10th Avenue\nDenver, CO 80203\nPhone: 303-831-7364\n\nChristian R. Everdell\nCOHEN & GRESSER LLP\n800 Third Avenue New\nYork, NY 10022\nPhone: 212-957-7600\n\nBobbi C. Sternheim\nLaw Offices of Bobbi C. Sternheim\n225 Broadway, Suite 715\nNew York, NY 10007\nPhone: 212-243-1100",
      "position": "middle"
    },
    {
      "type": "printed",
      "content": "Attorneys for Ghislaine Maxwell",
      "position": "middle"
    },
    {
      "type": "printed",
      "content": "DOJ-OGR-00006650",
      "position": "footer"
    }
  ],
  "entities": {
    "people": [
      "Jeffrey S. Pagliuca",
      "Laura A. Menninger",
      "Christian R. Everdell",
      "Bobbi C. Sternheim",
      "Ghislaine Maxwell"
    ],
    "organizations": [
      "HADDON, MORGAN & FOREMAN P.C.",
      "COHEN & GRESSER LLP",
      "Law Offices of Bobbi C. Sternheim",
      "UNITED STATES DISTRICT COURT",
      "UNITED STATES OF AMERICA"
    ],
    "locations": [
      "SOUTHERN DISTRICT OF NEW YORK",
      "Denver, CO",
      "New York, NY"
    ],
    "dates": [
      "11/12/21"
    ],
    "reference_numbers": [
      "1:20-cr-00330-PAE",
      "Document 445",
      "20 Cr. 330 (AJN)",
      "DOJ-OGR-00006650"
    ]
  },
  "additional_notes": "The document appears to be a court filing in a criminal case against Ghislaine Maxwell. The document is a motion in limine to exclude a government exhibit. The document is well-formatted and free of significant damage or redactions."
}