{
  "document_metadata": {
    "page_number": "202",
    "document_number": "499-1",
    "date": "11/23/21",
    "document_type": "court document",
    "has_handwriting": false,
    "has_stamps": false
  },
  "full_text": "Case 1:20-cr-00330-PAE Document 499-1 Filed 11/23/21 Page 202 of 375\n\n107. Hall RCW (chair), Hatters-Friedman S, Sorrentino R, Jain A: Outpatient Violence Risk Assessment – What Clinicians Need to Know. American Psychiatric Association, New York, NY, May 5, 2018\n108. Hall RCW: Marijuana Issues at Universities. The Maitland Men’s Club, Maitland, FL, June 29, 2018\n109. Hall RCW: Guns, Schools and Mental Illness. Orange County Health Department, Public Health Grand Rounds, August 14, 2018\n110. Hall RCW, Hatters-Friedman S, Jain, A, Sorrentino R, Landess J: Current Policy Topics on University Campuses. American Academy of Psychiatry and the Law, Austin, TX, October 27, 2018\n111. Greenspan M, Cooke B, Levin A, Hall RCW, Gage B: Forensic Considerations of Treatment When You Haven’t Seen the Patient. American Academy of Psychiatry and the Law, Austin, TX, October 28, 2018\n112. Hall RCW: Guns, Schools and Mental Health. Florida Department of Health, Cross City, Florida, November 29, 2018\n113. Hall RCW: Sanity. Spring Training Mental Health Panel, hosted by Robert Wesley, Public Defender, 9th Judicial Circuit, Barry University Dwayne O. Andreas School of Law, Orlando, FL, March 5, 2019\n114. Hall RCW, Sorrentino R, Jain A, Cooke B, Waggoner R: Burnout: Doctors and Lawyers and Other Professionals. .Oh My. American Psychiatric Association’s Annual Meeting, San Francisco, CA, May 19, 2019\n115. Packer S, Hall RCW, Forcen F, Hatters-Friedman S: The Profound and Long-Term Impact of Arkham Asylum on Psychiatry. American Psychiatric Association’s Annual Meeting, San Francisco, CA, May 21, 2019\n116. Hall RCW: New Controversies or Just a Repeat? Featuring Batman. Indienomicon, Melrose Center, Orlando, June 6, 2019\n117. Hall RCW: Retail E-Prescribing is Coming. Florida Psychiatric Society’s Leadership Conference, Jensen Beach, FL, June 22, 2019\n118. Hall RCW, Kass E: Comic superheroes: A Mental Health Crisis. Florida Psychiatric Society’s Annual Meeting, September 20, 2019\n119. Kolla N, Candilis P, Parker G, Hall RCW: What Forensic Psychiatrists Need to Know: Recent Research Findings. Workshop. American Academy of Psychiatry and the Law, Baltimore, MD, October 25, 3019\n120. Tamburello A, Hatters Friedman S, Hall RCW: Prescribing for Women in Corrections. Panel Discussion. American Academy of Psychiatry and the Law, Baltimore, MD, October 26, 3019\n\n31\nDOJ-OGR-00007695",
  "text_blocks": [
    {
      "type": "printed",
      "content": "Case 1:20-cr-00330-PAE Document 499-1 Filed 11/23/21 Page 202 of 375",
      "position": "header"
    },
    {
      "type": "printed",
      "content": "107. Hall RCW (chair), Hatters-Friedman S, Sorrentino R, Jain A: Outpatient Violence Risk Assessment – What Clinicians Need to Know. American Psychiatric Association, New York, NY, May 5, 2018\n108. Hall RCW: Marijuana Issues at Universities. The Maitland Men’s Club, Maitland, FL, June 29, 2018\n109. Hall RCW: Guns, Schools and Mental Illness. Orange County Health Department, Public Health Grand Rounds, August 14, 2018\n110. Hall RCW, Hatters-Friedman S, Jain, A, Sorrentino R, Landess J: Current Policy Topics on University Campuses. American Academy of Psychiatry and the Law, Austin, TX, October 27, 2018\n111. Greenspan M, Cooke B, Levin A, Hall RCW, Gage B: Forensic Considerations of Treatment When You Haven’t Seen the Patient. American Academy of Psychiatry and the Law, Austin, TX, October 28, 2018\n112. Hall RCW: Guns, Schools and Mental Health. Florida Department of Health, Cross City, Florida, November 29, 2018\n113. Hall RCW: Sanity. Spring Training Mental Health Panel, hosted by Robert Wesley, Public Defender, 9th Judicial Circuit, Barry University Dwayne O. Andreas School of Law, Orlando, FL, March 5, 2019\n114. Hall RCW, Sorrentino R, Jain A, Cooke B, Waggoner R: Burnout: Doctors and Lawyers and Other Professionals. .Oh My. American Psychiatric Association’s Annual Meeting, San Francisco, CA, May 19, 2019\n115. Packer S, Hall RCW, Forcen F, Hatters-Friedman S: The Profound and Long-Term Impact of Arkham Asylum on Psychiatry. American Psychiatric Association’s Annual Meeting, San Francisco, CA, May 21, 2019\n116. Hall RCW: New Controversies or Just a Repeat? Featuring Batman. Indienomicon, Melrose Center, Orlando, June 6, 2019\n117. Hall RCW: Retail E-Prescribing is Coming. Florida Psychiatric Society’s Leadership Conference, Jensen Beach, FL, June 22, 2019\n118. Hall RCW, Kass E: Comic superheroes: A Mental Health Crisis. Florida Psychiatric Society’s Annual Meeting, September 20, 2019\n119. Kolla N, Candilis P, Parker G, Hall RCW: What Forensic Psychiatrists Need to Know: Recent Research Findings. Workshop. American Academy of Psychiatry and the Law, Baltimore, MD, October 25, 3019\n120. Tamburello A, Hatters Friedman S, Hall RCW: Prescribing for Women in Corrections. Panel Discussion. American Academy of Psychiatry and the Law, Baltimore, MD, October 26, 3019",
      "position": "main content"
    },
    {
      "type": "printed",
      "content": "31",
      "position": "footer"
    },
    {
      "type": "printed",
      "content": "DOJ-OGR-00007695",
      "position": "footer"
    }
  ],
  "entities": {
    "people": [
      "Hall RCW",
      "Hatters-Friedman S",
      "Sorrentino R",
      "Jain A",
      "Landess J",
      "Greenspan M",
      "Cooke B",
      "Levin A",
      "Gage B",
      "Robert Wesley",
      "Waggoner R",
      "Packer S",
      "Forcen F",
      "Kass E",
      "Kolla N",
      "Candilis P",
      "Parker G",
      "Tamburello A"
    ],
    "organizations": [
      "American Psychiatric Association",
      "The Maitland Men’s Club",
      "Orange County Health Department",
      "American Academy of Psychiatry and the Law",
      "Florida Department of Health",
      "Barry University Dwayne O. Andreas School of Law",
      "Florida Psychiatric Society",
      "Indienomicon",
      "Melrose Center"
    ],
    "locations": [
      "New York, NY",
      "Maitland, FL",
      "Austin, TX",
      "Cross City, Florida",
      "Orlando, FL",
      "San Francisco, CA",
      "Jensen Beach, FL",
      "Baltimore, MD"
    ],
    "dates": [
      "May 5, 2018",
      "June 29, 2018",
      "August 14, 2018",
      "October 27, 2018",
      "October 28, 2018",
      "November 29, 2018",
      "March 5, 2019",
      "May 19, 2019",
      "May 21, 2019",
      "June 6, 2019",
      "June 22, 2019",
      "September 20, 2019",
      "October 25, 3019",
      "October 26, 3019",
      "11/23/21"
    ],
    "reference_numbers": [
      "1:20-cr-00330-PAE",
      "499-1",
      "202",
      "375",
      "DOJ-OGR-00007695"
    ]
  },
  "additional_notes": "The document appears to be a court filing with a list of references or presentations related to psychiatry and the law. The text is well-formatted and clear. There are no visible redactions or damage."
}