{
  "document_metadata": {
    "page_number": "2",
    "document_number": "212-2",
    "date": "04/16/21",
    "document_type": "Court Document",
    "has_handwriting": false,
    "has_stamps": false
  },
  "full_text": "Case 1:20-cr-00330-PAE Document 212-2 Filed 04/16/21 Page 2 of 30 App.-0805 G4LMGIUC 1 UNITED STATES DISTRICT COURT SOUTHERN DISTRICT OF NEW YORK 2 -------------------------------x 3 VIRGINIA L. GIUFFRE, 4 Plaintiff, 5 v. 15 Civ. 7433 (RWS) 6 GHISLAINE MAXWELL, 7 Defendant. 8 -------------------------------x 9 10 Before: 11 HON. ROBERT W. SWEET, 12 District Judge 13 14 APPEARANCES 15 BOIES, SCHILLER & FLEXNER LLP 16 Attorneys for Plaintiff 17 BY: SIGRID STONE Mccawley -and- 18 FARMER, JAFFE, WEISSING, EDWARDS, FISTOS & LEHRMAN, P.L. 19 BY: BRAD EDWARDS -and- 20 PAUL G. CASSELL 21 22 HADDON, MORGAN & FOREMAN 23 Attorneys for Defendant 24 BY: LAURA A. MENNINGER 25 JEFF PAGLUICA 26 27 SOUTHERN DISTRICT REPORTERS, P.C. (212) 805-0300 DOJ-OGR-00003804",
  "text_blocks": [
    {
      "type": "printed",
      "content": "Case 1:20-cr-00330-PAE Document 212-2 Filed 04/16/21 Page 2 of 30 App.-0805",
      "position": "header"
    },
    {
      "type": "printed",
      "content": "G4LMGIUC 1 UNITED STATES DISTRICT COURT SOUTHERN DISTRICT OF NEW YORK 2 -------------------------------x 3 VIRGINIA L. GIUFFRE, 4 Plaintiff, 5 v. 15 Civ. 7433 (RWS) 6 GHISLAINE MAXWELL, 7 Defendant. 8 -------------------------------x 9 10 Before: 11 HON. ROBERT W. SWEET, 12 District Judge 13 14 APPEARANCES 15 BOIES, SCHILLER & FLEXNER LLP 16 Attorneys for Plaintiff 17 BY: SIGRID STONE Mccawley -and- 18 FARMER, JAFFE, WEISSING, EDWARDS, FISTOS & LEHRMAN, P.L. 19 BY: BRAD EDWARDS -and- 20 PAUL G. CASSELL 21 22 HADDON, MORGAN & FOREMAN 23 Attorneys for Defendant 24 BY: LAURA A. MENNINGER 25 JEFF PAGLUICA 26 27 SOUTHERN DISTRICT REPORTERS, P.C. (212) 805-0300",
      "position": "main"
    },
    {
      "type": "printed",
      "content": "DOJ-OGR-00003804",
      "position": "footer"
    }
  ],
  "entities": {
    "people": [
      "VIRGINIA L. GIUFFRE",
      "GHISLAINE MAXWELL",
      "ROBERT W. SWEET",
      "SIGRID STONE MCCAWLEY",
      "BRAD EDWARDS",
      "PAUL G. CASSELL",
      "LAURA A. MENNINGER",
      "JEFF PAGLUICA"
    ],
    "organizations": [
      "UNITED STATES DISTRICT COURT",
      "SOUTHERN DISTRICT OF NEW YORK",
      "BOIES, SCHILLER & FLEXNER LLP",
      "FARMER, JAFFE, WEISSING, EDWARDS, FISTOS & LEHRMAN, P.L.",
      "HADDON, MORGAN & FOREMAN",
      "SOUTHERN DISTRICT REPORTERS, P.C."
    ],
    "locations": [
      "New York",
      "N.Y."
    ],
    "dates": [
      "April 21, 2016",
      "04/16/21"
    ],
    "reference_numbers": [
      "15 Civ. 7433 (RWS)",
      "1:20-cr-00330-PAE",
      "212-2",
      "DOJ-OGR-00003804"
    ]
  },
  "additional_notes": "The document appears to be a court transcript or legal document from a case involving Virginia L. Giuffre and Ghislaine Maxwell. The document is well-formatted and legible, with clear headings and sections. There are no visible redactions or damages."
}