{
  "document_metadata": {
    "page_number": "9",
    "document_number": "367-1",
    "date": "10/22/21",
    "document_type": "court document",
    "has_handwriting": false,
    "has_stamps": false
  },
  "full_text": "Case 1:20-cr-00330-PAE Document 367-1 Filed 10/22/21 Page 9 of 17\n\nYoung and FBI Task Force Officer Paul Byrne, and Sunny Drescher and Annie Phifer, paralegal specialists in the U.S. Attorney's Office. [Please ask them to stand]. Do any of you know Ms. Comey, Ms. Moe, Ms. Pomerantz, Mr. Rohrbach, Special Agent Young, Task Force Officer Byrne, Ms. Drescher, or Ms. Phifer? To your knowledge, have you, your family members, or your close friends had any dealings with them?\n\n26. I will now read a list of names of individuals who may be mentioned during the trial, or who may be witnesses in this case:\n\n[Names to be supplied]\n\n27. Do any of you know any of those people? Have you had any dealings, directly or indirectly, with any of these individuals? To your knowledge, have any of your relatives, friends, or associates had any dealings with any of these individuals?\n\nKnowledge of Location\n\n28. Events in this case are alleged to have taken place at the following locations:\n\n[List to be supplied]\n\n29. Are any of you particularly familiar with any of those locations?\n\nPrior Jury Service\n\n30. Have you ever served as a juror in a trial in any court? If so, in what court did you serve and was it a civil or criminal case? What type of case was it? Without telling us what the verdict was, did the jury reach a verdict?\n\n31. Have you ever at any time served as a member of a grand jury, whether in federal, state, county, or city court? If so, when and where?\n\n8\n\nDOJ-OGR-00005366",
  "text_blocks": [
    {
      "type": "printed",
      "content": "Case 1:20-cr-00330-PAE Document 367-1 Filed 10/22/21 Page 9 of 17",
      "position": "header"
    },
    {
      "type": "printed",
      "content": "Young and FBI Task Force Officer Paul Byrne, and Sunny Drescher and Annie Phifer, paralegal specialists in the U.S. Attorney's Office. [Please ask them to stand]. Do any of you know Ms. Comey, Ms. Moe, Ms. Pomerantz, Mr. Rohrbach, Special Agent Young, Task Force Officer Byrne, Ms. Drescher, or Ms. Phifer? To your knowledge, have you, your family members, or your close friends had any dealings with them?",
      "position": "top"
    },
    {
      "type": "printed",
      "content": "26. I will now read a list of names of individuals who may be mentioned during the trial, or who may be witnesses in this case:\n\n[Names to be supplied]",
      "position": "middle"
    },
    {
      "type": "printed",
      "content": "27. Do any of you know any of those people? Have you had any dealings, directly or indirectly, with any of these individuals? To your knowledge, have any of your relatives, friends, or associates had any dealings with any of these individuals?",
      "position": "middle"
    },
    {
      "type": "printed",
      "content": "Knowledge of Location\n\n28. Events in this case are alleged to have taken place at the following locations:\n\n[List to be supplied]\n\n29. Are any of you particularly familiar with any of those locations?",
      "position": "middle"
    },
    {
      "type": "printed",
      "content": "Prior Jury Service\n\n30. Have you ever served as a juror in a trial in any court? If so, in what court did you serve and was it a civil or criminal case? What type of case was it? Without telling us what the verdict was, did the jury reach a verdict?",
      "position": "middle"
    },
    {
      "type": "printed",
      "content": "31. Have you ever at any time served as a member of a grand jury, whether in federal, state, county, or city court? If so, when and where?",
      "position": "middle"
    },
    {
      "type": "printed",
      "content": "8",
      "position": "footer"
    },
    {
      "type": "printed",
      "content": "DOJ-OGR-00005366",
      "position": "footer"
    }
  ],
  "entities": {
    "people": [
      "Paul Byrne",
      "Sunny Drescher",
      "Annie Phifer",
      "Ms. Comey",
      "Ms. Moe",
      "Ms. Pomerantz",
      "Mr. Rohrbach",
      "Special Agent Young",
      "Task Force Officer Byrne"
    ],
    "organizations": [
      "FBI",
      "U.S. Attorney's Office"
    ],
    "locations": [],
    "dates": [
      "10/22/21"
    ],
    "reference_numbers": [
      "1:20-cr-00330-PAE",
      "367-1",
      "DOJ-OGR-00005366"
    ]
  },
  "additional_notes": "The document appears to be a court transcript or questionnaire for potential jurors. It contains a list of questions related to the case and the jurors' knowledge of individuals and locations involved. The document is well-formatted and legible."
}