{
  "document_metadata": {
    "page_number": "23",
    "document_number": "293-3",
    "date": "05/25/21",
    "document_type": "Testimony",
    "has_handwriting": false,
    "has_stamps": false
  },
  "full_text": "Case 1:20-cr-00330-PAE - Document 293-3 - Filed 05/25/21 - Page 21 of 34\n23\n1 engaged in sexual activity that I mentioned\nearlier where informed as that\n2 she sat on the couch and observed what she\n3 believed the two of them to engage in sexual\n4 intercourse.\n5 Q And at the time, was\n6 17 and was 14?\n7 A Yes.\n8 Q All right.\n9 A And I'm not sure if that was actually\n10 the first or second visit that she went. So it\n11 was either the first visit or the second that the\n12 sexual activity that I described took place.\n13 They may have gone there the first time\n14 and just performed a massage for Mr. Epstein, but\n15 on the second occasion the sexual activity that I\n16 described took place.\nstated that, you know, the three years that we discussed from 2001\n17 to 2004, she provided Mr. Epstein with over, in\n18 that three-year period, over 100 massages and all\n19 but three of the massages were sexually in nature.\n20 Q How much was she paid for performing\n21 sexual massages for Epstein?\n22 A She was paid between 200 and $400.\n23\nOFFICIAL REPORTING SERVICE, LLC\n(954) 467-8204\nCONFIDENTIAL\nMM20-GJ TESTIMONY-000325\n3501.125-020\nPage 23 of 65\nDOJ-OGR-00004683",
  "text_blocks": [
    {
      "type": "printed",
      "content": "Case 1:20-cr-00330-PAE - Document 293-3 - Filed 05/25/21 - Page 21 of 34",
      "position": "header"
    },
    {
      "type": "printed",
      "content": "23",
      "position": "header"
    },
    {
      "type": "printed",
      "content": "1 engaged in sexual activity that I mentioned\nearlier where informed as that\n2 she sat on the couch and observed what she\n3 believed the two of them to engage in sexual\n4 intercourse.\n5 Q And at the time, was\n6 17 and was 14?\n7 A Yes.\n8 Q All right.\n9 A And I'm not sure if that was actually\n10 the first or second visit that she went. So it\n11 was either the first visit or the second that the\n12 sexual activity that I described took place.\n13 They may have gone there the first time\n14 and just performed a massage for Mr. Epstein, but\n15 on the second occasion the sexual activity that I\n16 described took place.\nstated that, you know, the three years that we discussed from 2001\n17 to 2004, she provided Mr. Epstein with over, in\n18 that three-year period, over 100 massages and all\n19 but three of the massages were sexually in nature.\n20 Q How much was she paid for performing\n21 sexual massages for Epstein?\n22 A She was paid between 200 and $400.",
      "position": "main"
    },
    {
      "type": "printed",
      "content": "OFFICIAL REPORTING SERVICE, LLC\n(954) 467-8204",
      "position": "footer"
    },
    {
      "type": "printed",
      "content": "CONFIDENTIAL",
      "position": "footer"
    },
    {
      "type": "printed",
      "content": "MM20-GJ TESTIMONY-000325\n3501.125-020\nPage 23 of 65\nDOJ-OGR-00004683",
      "position": "footer"
    }
  ],
  "entities": {
    "people": [
      "Mr. Epstein"
    ],
    "organizations": [
      "OFFICIAL REPORTING SERVICE, LLC"
    ],
    "locations": [],
    "dates": [
      "2001",
      "2004",
      "05/25/21"
    ],
    "reference_numbers": [
      "1:20-cr-00330-PAE",
      "293-3",
      "MM20-GJ TESTIMONY-000325",
      "3501.125-020",
      "DOJ-OGR-00004683"
    ]
  },
  "additional_notes": "The document appears to be a testimony transcript with some redacted names. The content discusses sexual activities involving Mr. Epstein and a minor. The document is marked as 'CONFIDENTIAL'."
}