{
  "document_metadata": {
    "page_number": "29",
    "document_number": "293-3",
    "date": "05/25/21",
    "document_type": "Court Document",
    "has_handwriting": false,
    "has_stamps": false
  },
  "full_text": "Case 1:20-cr-00330-PAE Document 293-3 Filed 05/25/21 Page 27 of 34\n\n1 packages informed us that\n2 there was a Massage for Dummies book that she\n3 received by FedEx from Mr. Epstein.\n4 And the grand jury should know that we\n5 have received records from FedEx which corroborate\n6 Mr. Epstein's address and packages going to\n7 's residence.\n8 Q And those records relate to Mr.\n9 Epstein's personal Federal Express account?\n10 A Yes.\n11 A GRAND JUROR: do\n12 we know how old she was when Mr. Epstein\n13 asked her to bring younger friends? Was she\n14 already in his eyes up there and he wanted\n15 them younger?\n16 THE WITNESS: When was 16, about midway through her 16th year,\n17 at that point she did\n18 not provide Mr. Epstein with anymore\n19 massages.\n20 So I know she went away for a time\n21 period and when she came back, you know, she\n22 did not want to do massages\n23 anymore. So at that point, she may have\n24 brought her friends as well as prior to that.\n\nOFFICIAL REPORTING SERVICE, LLC\n(954) 467-8204\n\nMM20-GJ TESTIMONY-000331\nCONFIDENTIAL\n3501.125-020\nPage 29 of 65\nDOJ-OGR-00004689",
  "text_blocks": [
    {
      "type": "printed",
      "content": "Case 1:20-cr-00330-PAE Document 293-3 Filed 05/25/21 Page 27 of 34",
      "position": "header"
    },
    {
      "type": "printed",
      "content": "1 packages informed us that\n2 there was a Massage for Dummies book that she\n3 received by FedEx from Mr. Epstein.\n4 And the grand jury should know that we\n5 have received records from FedEx which corroborate\n6 Mr. Epstein's address and packages going to\n7 's residence.\n8 Q And those records relate to Mr.\n9 Epstein's personal Federal Express account?\n10 A Yes.\n11 A GRAND JUROR: do\n12 we know how old she was when Mr. Epstein\n13 asked her to bring younger friends? Was she\n14 already in his eyes up there and he wanted\n15 them younger?\n16 THE WITNESS: When was 16, about midway through her 16th year,\n17 at that point she did\n18 not provide Mr. Epstein with anymore\n19 massages.\n20 So I know she went away for a time\n21 period and when she came back, you know, she\n22 did not want to do massages\n23 anymore. So at that point, she may have\n24 brought her friends as well as prior to that.",
      "position": "main"
    },
    {
      "type": "printed",
      "content": "OFFICIAL REPORTING SERVICE, LLC\n(954) 467-8204",
      "position": "footer"
    },
    {
      "type": "printed",
      "content": "MM20-GJ TESTIMONY-000331\nCONFIDENTIAL\n3501.125-020\nPage 29 of 65\nDOJ-OGR-00004689",
      "position": "footer"
    }
  ],
  "entities": {
    "people": [
      "Mr. Epstein"
    ],
    "organizations": [
      "FedEx",
      "OFFICIAL REPORTING SERVICE, LLC",
      "DOJ"
    ],
    "locations": [],
    "dates": [
      "05/25/21"
    ],
    "reference_numbers": [
      "1:20-cr-00330-PAE",
      "293-3",
      "MM20-GJ TESTIMONY-000331",
      "3501.125-020",
      "DOJ-OGR-00004689"
    ]
  },
  "additional_notes": "The document appears to be a court transcript with some redactions. The content discusses a case involving Mr. Epstein and includes testimony about packages sent via FedEx and interactions with a minor."
}