{
  "document_metadata": {
    "page_number": "383",
    "document_number": "1:20-cv-00233-JPAE Document 1207-10 Filed 10/12/21 Page 383 of 435",
    "date": "10/12/21",
    "document_type": "Court Document",
    "has_handwriting": false,
    "has_stamps": false
  },
  "full_text": "Case 1:20-cv-00233-JPAE Document 1207-10 Filed 10/12/21 Page 383 of 435\nPage 383\n1 G Maxwell - Confidential\n2 Q. List all of the girls you met and\n3 brought to Jeffrey Epstein's home for the\n4 purposes of employment that were under the\n5 age of 18?\n6 MR. PAGLIUCA: Objection to the\n7 form and foundation.\n8 A. I've already characterized my job\n9 was to find people, adults, professional\n10 people to do the jobs I listed before; pool\n11 person, secretary, house person, chef, pilot,\n12 architect.\n13 Q. I'm asking about individuals under\n14 the age of 18, not adult persons, people\n15 under the age of 18.\n16 A. I looked for people or tried to\n17 find people to fill professional jobs in\n18 professional situations.\n19 Q. So Virginia Roberts was under the\n20 age of 18, correct?\n21 A. I think we've established that\n22 Virginia was 17.\n23 Q. Is she the -- sorry, go ahead.\n24 Is she the only individual that you\n25 met for purposes of hiring someone for\nMAGNA LEGAL SERVICES DOJ-OGR-00003597",
  "text_blocks": [
    {
      "type": "printed",
      "content": "Case 1:20-cv-00233-JPAE Document 1207-10 Filed 10/12/21 Page 383 of 435",
      "position": "header"
    },
    {
      "type": "printed",
      "content": "Page 383",
      "position": "header"
    },
    {
      "type": "printed",
      "content": "1 G Maxwell - Confidential\n2 Q. List all of the girls you met and\n3 brought to Jeffrey Epstein's home for the\n4 purposes of employment that were under the\n5 age of 18?\n6 MR. PAGLIUCA: Objection to the\n7 form and foundation.\n8 A. I've already characterized my job\n9 was to find people, adults, professional\n10 people to do the jobs I listed before; pool\n11 person, secretary, house person, chef, pilot,\n12 architect.\n13 Q. I'm asking about individuals under\n14 the age of 18, not adult persons, people\n15 under the age of 18.\n16 A. I looked for people or tried to\n17 find people to fill professional jobs in\n18 professional situations.\n19 Q. So Virginia Roberts was under the\n20 age of 18, correct?\n21 A. I think we've established that\n22 Virginia was 17.\n23 Q. Is she the -- sorry, go ahead.\n24 Is she the only individual that you\n25 met for purposes of hiring someone for",
      "position": "main"
    },
    {
      "type": "printed",
      "content": "MAGNA LEGAL SERVICES DOJ-OGR-00003597",
      "position": "footer"
    }
  ],
  "entities": {
    "people": [
      "G Maxwell",
      "Jeffrey Epstein",
      "Virginia Roberts",
      "MR. PAGLIUCA"
    ],
    "organizations": [
      "MAGNA LEGAL SERVICES"
    ],
    "locations": [],
    "dates": [
      "10/12/21"
    ],
    "reference_numbers": [
      "1:20-cv-00233-JPAE",
      "Document 1207-10",
      "DOJ-OGR-00003597"
    ]
  },
  "additional_notes": "The document appears to be a court transcript with a deposition from G Maxwell. The content is related to a legal case involving Jeffrey Epstein and Virginia Roberts. The document is marked as 'Confidential'."
}