{
  "document_metadata": {
    "page_number": "33",
    "document_number": "203-3",
    "date": "05/25/21",
    "document_type": "court document",
    "has_handwriting": false,
    "has_stamps": false
  },
  "full_text": "Case 1:20-cr-00330-PAE Document 203-3 Filed 05/25/21 Page 33 of 34 56 1 2 3 4 5 6 7 8 9 10 11 12 13 14 15 16 Q With respect to those Jane Does, did you go about getting independent corroboration for their statements so that you weren't relying exclusive on what they told you about Mr. Epstein? 20 A Yes. We talked about that today. 21 Specifically, with we have 22 her statement, but along with that statement we have telephone records. 23 24 Those telephone records indicate telephonic contact with We have the 25 OFFICIAL REPORTING SERVICE, LLC (954) 467-8204 MM20-GJ TESTIMONY-000357 CONFIDENTIAL 3501.125-020 Page 55 of 65 DOJ-OGR-00004695",
  "text_blocks": [
    {
      "type": "printed",
      "content": "Case 1:20-cr-00330-PAE Document 203-3 Filed 05/25/21 Page 33 of 34",
      "position": "header"
    },
    {
      "type": "printed",
      "content": "56",
      "position": "top"
    },
    {
      "type": "printed",
      "content": "1 2 3 4 5 6 7 8 9 10 11 12 13 14 15 16 Q With respect to those Jane Does, did you go about getting independent corroboration for their statements so that you weren't relying exclusive on what they told you about Mr. Epstein? 20 A Yes. We talked about that today. 21 Specifically, with we have 22 her statement, but along with that statement we have telephone records. 23 24 Those telephone records indicate telephonic contact with We have the 25",
      "position": "middle"
    },
    {
      "type": "printed",
      "content": "OFFICIAL REPORTING SERVICE, LLC (954) 467-8204",
      "position": "footer"
    },
    {
      "type": "printed",
      "content": "MM20-GJ TESTIMONY-000357 CONFIDENTIAL 3501.125-020 Page 55 of 65 DOJ-OGR-00004695",
      "position": "footer"
    }
  ],
  "entities": {
    "people": [
      "Jane Does",
      "Mr. Epstein"
    ],
    "organizations": [
      "OFFICIAL REPORTING SERVICE, LLC"
    ],
    "locations": [],
    "dates": [
      "05/25/21"
    ],
    "reference_numbers": [
      "1:20-cr-00330-PAE",
      "203-3",
      "MM20-GJ TESTIMONY-000357",
      "3501.125-020",
      "DOJ-OGR-00004695"
    ]
  },
  "additional_notes": "The document appears to be a court transcript with some redacted information. The page is marked as 'CONFIDENTIAL' and has a header indicating it is part of a larger document."
}