{
  "document_metadata": {
    "page_number": "14",
    "document_number": "212-2",
    "date": "04/16/21",
    "document_type": "Court Transcript",
    "has_handwriting": false,
    "has_stamps": false
  },
  "full_text": "Case 1:20-cr-00330-PAE Document 212-2 Filed 04/16/21 Page 14 of 30\nApp.-0817\n\nG4LMGIUC\n13\n1 moment. To the extent she is now alleging she suffers from\n2 emotional distress from any preexisting --\n3 THE COURT: That's from the defamation.\n4 MS. MENNINGER: She claims it's from the defamation.\n5 However, your Honor, if she has preexisting conditions that\n6 were truly the cause of whatever emotional injury she claims\n7 that she now possesses --\n8 THE COURT: Correct me if I'm wrong, and perhaps\n9 plaintiff will make it clear, my understanding is that the\n10 injuries alleged result from the claim of the alleged\n11 defamation, period.\n12 MS. MENNINGER: Your Honor, she has claimed emotional\n13 distress from the defamation, yes. We are requesting evidence\n14 that would show that she has preexisting emotional conditions.\n15 THE COURT: Not from the defamation.\n16 MS. MENNINGER: Not from the defamation. From the\n17 many, many other things that have occurred in her life\n18 predating even her meeting Mr. Epstein and Ms. Maxwell, as she\n19 has told the press, not because we told the press that.\n20 Your Honor, it is difficult, if not impossible, to\n21 address her claimed $30 million emotional distress from a\n22 defamation statement that was a denial of her allegations\n23 versus any emotional distress or emotional conditions she\n24 already had before any such statement was made.\n25 Similarly, your Honor, we have asked for discovery of\nSOUTHERN DISTRICT REPORTERS, P.C.\n(212) 805-0300\nDOJ-OGR-00003816",
  "text_blocks": [
    {
      "type": "printed",
      "content": "Case 1:20-cr-00330-PAE Document 212-2 Filed 04/16/21 Page 14 of 30",
      "position": "header"
    },
    {
      "type": "printed",
      "content": "App.-0817",
      "position": "header"
    },
    {
      "type": "printed",
      "content": "G4LMGIUC\n13\n1 moment. To the extent she is now alleging she suffers from\n2 emotional distress from any preexisting --\n3 THE COURT: That's from the defamation.\n4 MS. MENNINGER: She claims it's from the defamation.\n5 However, your Honor, if she has preexisting conditions that\n6 were truly the cause of whatever emotional injury she claims\n7 that she now possesses --\n8 THE COURT: Correct me if I'm wrong, and perhaps\n9 plaintiff will make it clear, my understanding is that the\n10 injuries alleged result from the claim of the alleged\n11 defamation, period.\n12 MS. MENNINGER: Your Honor, she has claimed emotional\n13 distress from the defamation, yes. We are requesting evidence\n14 that would show that she has preexisting emotional conditions.\n15 THE COURT: Not from the defamation.\n16 MS. MENNINGER: Not from the defamation. From the\n17 many, many other things that have occurred in her life\n18 predating even her meeting Mr. Epstein and Ms. Maxwell, as she\n19 has told the press, not because we told the press that.\n20 Your Honor, it is difficult, if not impossible, to\n21 address her claimed $30 million emotional distress from a\n22 defamation statement that was a denial of her allegations\n23 versus any emotional distress or emotional conditions she\n24 already had before any such statement was made.\n25 Similarly, your Honor, we have asked for discovery of",
      "position": "main"
    },
    {
      "type": "printed",
      "content": "SOUTHERN DISTRICT REPORTERS, P.C.\n(212) 805-0300",
      "position": "footer"
    },
    {
      "type": "printed",
      "content": "DOJ-OGR-00003816",
      "position": "footer"
    }
  ],
  "entities": {
    "people": [
      "Ms. Menninger"
    ],
    "organizations": [
      "SOUTHERN DISTRICT REPORTERS, P.C."
    ],
    "locations": [],
    "dates": [
      "04/16/21"
    ],
    "reference_numbers": [
      "1:20-cr-00330-PAE",
      "212-2",
      "App.-0817",
      "DOJ-OGR-00003816"
    ]
  },
  "additional_notes": "The document appears to be a court transcript with a clear and legible format. There are no visible redactions or damage."
}