{
  "document_metadata": {
    "page_number": "4 of 34",
    "document_number": "293-3",
    "date": "05/25/21",
    "document_type": "Grand Jury Testimony",
    "has_handwriting": false,
    "has_stamps": true
  },
  "full_text": "Case 1:20-cr-00330-PAE Document 293-3 Filed 05/25/21 Page 4 of 34\n(Witness enters the Grand Jury Room.)\nTHE FOREPERSON: You do solemnly swear that the testimony you give will be the truth, the whole truth, and nothing but the truth, so help you God?\nTHE WITNESS: I do.\nTHE FOREPERSON: Thank you. Please be seated.\nEXAMINATION\nBY MS. VILLAFANA:\nQ Good afternoon, Special Agent\nWould you just remind the grand jury of your name and for whom you work?\nA I am . My official name is and I work for the FBI here in West Palm Beach.\nQ All right. And you are still one of the case agents on Operation Leap Year?\nA Yes, I am.\nQ Have additional subpoenas been issued on behalf of this grand jury regarding Leap Year?\nA Yes, they have.\nQ And have documents been received in response to those subpoenas?\nA Yes, they have.\nOFFICIAL REPORTING SERVICE, LLC (954) 457-8204\nCONFIDENTIAL\nMM20-GJ TESTIMONY-000305 3501.125-020 Page 3 of 65 DOJ-OGR-00004666",
  "text_blocks": [
    {
      "type": "printed",
      "content": "Case 1:20-cr-00330-PAE Document 293-3 Filed 05/25/21 Page 4 of 34",
      "position": "header"
    },
    {
      "type": "printed",
      "content": "(Witness enters the Grand Jury Room.)\nTHE FOREPERSON: You do solemnly swear that the testimony you give will be the truth, the whole truth, and nothing but the truth, so help you God?\nTHE WITNESS: I do.\nTHE FOREPERSON: Thank you. Please be seated.\nEXAMINATION\nBY MS. VILLAFANA:\nQ Good afternoon, Special Agent\nWould you just remind the grand jury of your name and for whom you work?\nA I am . My official name is and I work for the FBI here in West Palm Beach.\nQ All right. And you are still one of the case agents on Operation Leap Year?\nA Yes, I am.\nQ Have additional subpoenas been issued on behalf of this grand jury regarding Leap Year?\nA Yes, they have.\nQ And have documents been received in response to those subpoenas?\nA Yes, they have.",
      "position": "main"
    },
    {
      "type": "printed",
      "content": "OFFICIAL REPORTING SERVICE, LLC (954) 457-8204",
      "position": "footer"
    },
    {
      "type": "printed",
      "content": "CONFIDENTIAL",
      "position": "footer"
    },
    {
      "type": "printed",
      "content": "MM20-GJ TESTIMONY-000305 3501.125-020 Page 3 of 65 DOJ-OGR-00004666",
      "position": "footer"
    }
  ],
  "entities": {
    "people": [
      "MS. VILLAFANA",
      "THE FOREPERSON",
      "THE WITNESS"
    ],
    "organizations": [
      "FBI",
      "OFFICIAL REPORTING SERVICE, LLC"
    ],
    "locations": [
      "West Palm Beach"
    ],
    "dates": [
      "05/25/21"
    ],
    "reference_numbers": [
      "1:20-cr-00330-PAE",
      "293-3",
      "MM20-GJ TESTIMONY-000305",
      "3501.125-020",
      "DOJ-OGR-00004666"
    ]
  },
  "additional_notes": "The document appears to be a transcript of grand jury testimony. Some names have been redacted. The document is marked 'CONFIDENTIAL'."
}