{
  "document_metadata": {
    "page_number": "5",
    "document_number": "243",
    "date": "04/23/21",
    "document_type": "court document",
    "has_handwriting": true,
    "has_stamps": false
  },
  "full_text": "Case 1:20-cr-00330-PAE Document 243 Filed 04/23/21 Page 5 of 5\nThe Hon. Alison J. Nathan\nApril 22, 2021\nPage 5\nFor these reasons, Ms. Maxwell respectfully requests that this Court hold an evidentiary hearing on her motions to suppress and that it rule on the merits of her arguments before the trial on the non-perjury counts.\nRespectfully submitted,\nJeffrey S. Pagliuca\nCC: Counsel of Record\nThe Court agrees with the position set forth in this letter that, unless the Government agrees to forgo any use of the documents subject to the motions to suppress at trial on the non-perjury counts, the Court must resolve those motions prior to that trial. The Court will resolve the motions in due course. SO ORDERED.\nSO ORDERED.\n4/23/2021\nALISON J. NATHAN, U.S.D.J.\nDOJ-OGR-00003971",
  "text_blocks": [
    {
      "type": "printed",
      "content": "Case 1:20-cr-00330-PAE Document 243 Filed 04/23/21 Page 5 of 5",
      "position": "header"
    },
    {
      "type": "printed",
      "content": "The Hon. Alison J. Nathan\nApril 22, 2021\nPage 5",
      "position": "header"
    },
    {
      "type": "printed",
      "content": "For these reasons, Ms. Maxwell respectfully requests that this Court hold an evidentiary hearing on her motions to suppress and that it rule on the merits of her arguments before the trial on the non-perjury counts.",
      "position": "body"
    },
    {
      "type": "printed",
      "content": "Respectfully submitted,",
      "position": "body"
    },
    {
      "type": "handwritten",
      "content": "Jeffrey S. Pagliuca",
      "position": "body"
    },
    {
      "type": "printed",
      "content": "CC: Counsel of Record",
      "position": "body"
    },
    {
      "type": "printed",
      "content": "The Court agrees with the position set forth in this letter that, unless the Government agrees to forgo any use of the documents subject to the motions to suppress at trial on the non-perjury counts, the Court must resolve those motions prior to that trial. The Court will resolve the motions in due course. SO ORDERED.",
      "position": "body"
    },
    {
      "type": "handwritten",
      "content": "Alison J. Nathan",
      "position": "footer"
    },
    {
      "type": "printed",
      "content": "SO ORDERED.\n4/23/2021\nALISON J. NATHAN, U.S.D.J.",
      "position": "footer"
    },
    {
      "type": "printed",
      "content": "DOJ-OGR-00003971",
      "position": "footer"
    }
  ],
  "entities": {
    "people": [
      "Alison J. Nathan",
      "Jeffrey S. Pagliuca",
      "Ms. Maxwell"
    ],
    "organizations": [
      "Government",
      "Court"
    ],
    "locations": [],
    "dates": [
      "April 22, 2021",
      "04/23/21",
      "4/23/2021"
    ],
    "reference_numbers": [
      "1:20-cr-00330-PAE",
      "Document 243",
      "DOJ-OGR-00003971"
    ]
  },
  "additional_notes": "The document appears to be a court filing with a signature from Judge Alison J. Nathan. The text is mostly printed, with two signatures present."
}