{
  "document_metadata": {
    "page_number": "3 of 3",
    "document_number": "1:20-cr-00330-PAE Document 636 Filed 05/04/21",
    "date": "5/4/2021",
    "document_type": "email",
    "has_handwriting": false,
    "has_stamps": false
  },
  "full_text": "5/4/2021 Case 1:20-cr-00330-PAE Document 636 Filed 05/04/21 Page 3 of 3 information is strictly prohibited. If you received this message in error, please notify us immediately to make arrangements for its return to us. >>> Nathan NYSD Chambers 5/3/2021 10:44 AM >>> Counsel, Please find attached a memorandum endorsement signed by Judge Nathan, which has been filed on the public docket. Respectfully, The Chambers of the Hon. Alison J. Nathan CAUTION - EXTERNAL EMAIL: This email originated outside the Judiciary. Exercise caution when opening attachments or clicking on links. https://outlook.office.com/mail/NathanNYSDChambers@nysd.uscourts.gov/inbox/id/AAMkAGI3N2ZmZDU5LTQ1OTctNDI1Yi1hMzkxLWJmYzk0YWVj... 2/2 DOJ-OGR-00004093",
  "text_blocks": [
    {
      "type": "printed",
      "content": "5/4/2021 Case 1:20-cr-00330-PAE Document 636 Filed 05/04/21 Page 3 of 3",
      "position": "header"
    },
    {
      "type": "printed",
      "content": "information is strictly prohibited. If you received this message in error, please notify us immediately to make arrangements for its return to us.",
      "position": "top"
    },
    {
      "type": "printed",
      "content": ">>> Nathan NYSD Chambers 5/3/2021 10:44 AM >>>",
      "position": "top"
    },
    {
      "type": "printed",
      "content": "Counsel,",
      "position": "top"
    },
    {
      "type": "printed",
      "content": "Please find attached a memorandum endorsement signed by Judge Nathan, which has been filed on the public docket.",
      "position": "middle"
    },
    {
      "type": "printed",
      "content": "Respectfully, The Chambers of the Hon. Alison J. Nathan",
      "position": "middle"
    },
    {
      "type": "printed",
      "content": "CAUTION - EXTERNAL EMAIL: This email originated outside the Judiciary. Exercise caution when opening attachments or clicking on links.",
      "position": "bottom"
    },
    {
      "type": "printed",
      "content": "https://outlook.office.com/mail/NathanNYSDChambers@nysd.uscourts.gov/inbox/id/AAMkAGI3N2ZmZDU5LTQ1OTctNDI1Yi1hMzkxLWJmYzk0YWVj... 2/2",
      "position": "footer"
    },
    {
      "type": "printed",
      "content": "DOJ-OGR-00004093",
      "position": "footer"
    }
  ],
  "entities": {
    "people": [
      "Alison J. Nathan",
      "Nathan"
    ],
    "organizations": [
      "Judiciary"
    ],
    "locations": [],
    "dates": [
      "5/4/2021",
      "5/3/2021"
    ],
    "reference_numbers": [
      "1:20-cr-00330-PAE",
      "Document 636",
      "DOJ-OGR-00004093"
    ]
  },
  "additional_notes": "The document is an email with a blacked-out recipient email address. The email contains a link to an Outlook inbox and a reference number 'DOJ-OGR-00004093' at the bottom."
}