{
  "document_metadata": {
    "page_number": "1",
    "document_number": "204-5",
    "date": "04/16/21",
    "document_type": "court document",
    "has_handwriting": true,
    "has_stamps": false
  },
  "full_text": "Case 1:20-cr-00330-PAE Document 204-5 Filed 04/16/21 Page 1 of 9\nP. Skinner 2/29/16\nBrad Edwards\nStan Pottinger\nA. Kramer (notes)\nBE - rep. Virginia Roberts\nSP - rep. Virginia\nLong history of litigation\nBE\nFirst inv. into Jeffrey Epstein was done by Coral Palmer Beach PD (~2005)\nrounded up approx. 24 girls related by JE\nrepresented about 10 girls\nJE's MO - w/ adults they'd tell 13 yr. old girl 'came to rich guy's house to give paid massage. JE naked - starts as massage & ultimate demand of sex acts (if you want $, do $). After paid 200/300 - then offered 800-300 finders fee. Victims recruited other victims. Mother complained & involved PD.\nPD turned case over to FBI & USAP. Most of girls (approx. 40+) in FL. No flight (logs).\nIssued CT subpoenas Epstein + 4 named co-conspirators\nEntered into a nina plea for state ct. to 2001-2007 prostitution minor & prostitution immunity\nfed. pros. for sex crimes comm. in FL btw 2001 - 2007\nJen Lefcourt, Jay Lefkowitz, Ken Starr, Roy Black Epstein\nMartin Weinberg, Gary Lewin - never Jem shared (ourselves)\nSD FL - at Palm Beach, Mariz Viagra\nLimited to FL in plea",
  "text_blocks": [
    {
      "type": "printed",
      "content": "Case 1:20-cr-00330-PAE Document 204-5 Filed 04/16/21 Page 1 of 9",
      "position": "header"
    },
    {
      "type": "handwritten",
      "content": "P. Skinner 2/29/16\nBrad Edwards\nStan Pottinger\nA. Kramer (notes)\nBE - rep. Virginia Roberts\nSP - rep. Virginia\nLong history of litigation\nBE\nFirst inv. into Jeffrey Epstein was done by Coral Palmer Beach PD (~2005)\nrounded up approx. 24 girls related by JE\nrepresented about 10 girls\nJE's MO - w/ adults they'd tell 13 yr. old girl 'came to rich guy's house to give paid massage. JE naked - starts as massage & ultimate demand of sex acts (if you want $, do $). After paid 200/300 - then offered 800-300 finders fee. Victims recruited other victims. Mother complained & involved PD.\nPD turned case over to FBI & USAP. Most of girls (approx. 40+) in FL. No flight (logs).\nIssued CT subpoenas Epstein + 4 named co-conspirators\nEntered into a nina plea for state ct. to 2001-2007 prostitution minor & prostitution immunity\nfed. pros. for sex crimes comm. in FL btw 2001 - 2007\nJen Lefcourt, Jay Lefkowitz, Ken Starr, Roy Black Epstein\nMartin Weinberg, Gary Lewin - never Jem shared (ourselves)\nSD FL - at Palm Beach, Mariz Viagra\nLimited to FL in plea",
      "position": "main content"
    }
  ],
  "entities": {
    "people": [
      "P. Skinner",
      "Brad Edwards",
      "Stan Pottinger",
      "A. Kramer",
      "Virginia Roberts",
      "Jeffrey Epstein",
      "Coral Palmer",
      "Jen Lefcourt",
      "Jay Lefkowitz",
      "Ken Starr",
      "Roy Black",
      "Martin Weinberg",
      "Gary Lewin",
      "Mariz Viagra"
    ],
    "organizations": [
      "FBI",
      "USAP"
    ],
    "locations": [
      "Virginia",
      "Florida",
      "Palm Beach"
    ],
    "dates": [
      "2/29/16",
      "04/16/21",
      "2005",
      "2001-2007"
    ],
    "reference_numbers": [
      "1:20-cr-00330-PAE",
      "204-5",
      "DOJ-OGR-00003531"
    ]
  },
  "additional_notes": "The document appears to be a handwritten note related to a court case involving Jeffrey Epstein. The handwriting is mostly legible, but some words are difficult to decipher. The document includes a header with case information and a footer with a document control number."
}