{
  "document_metadata": {
    "page_number": "137",
    "document_number": "1204-10",
    "date": "10/22/01",
    "document_type": "court document",
    "has_handwriting": false,
    "has_stamps": false
  },
  "full_text": "Case 1:20-cv-00233-PAE Document 1204-10 Filed 10/22/01 Page 881 of 455 Page 137 G Maxwell - Confidential 1 the flights? 2 A. I can't recollect having a meal 3 with them, but just so we are clear, the 4 allegations that had a meal on 5 Jeffrey's island is 100 percent false. 6 Q. But he may have had a meal on 7 Jeffrey's plane? 8 A. I'm sure he had a meal on Jeffrey's 9 plane. 10 Q. You do know how many times he flew 11 on Jeffrey's plane? 12 A. I don't. 13 Q. Do you know who is? 14 A. I do. 15 Q. How do you know him? 16 A. He used to work or still works for 17 18 Q. Did you ever have a relationship 19 with him? 20 A. We are talking about adult 21 consensual relationships, it's off the 22 record. 23 Q. I'm not asking what you did with 24 him, I'm asking if you ever had a 25 MAGNA LEGAL SERVICES DOJ-OGR-00003576",
  "text_blocks": [
    {
      "type": "printed",
      "content": "Case 1:20-cv-00233-PAE Document 1204-10 Filed 10/22/01 Page 881 of 455",
      "position": "header"
    },
    {
      "type": "printed",
      "content": "Page 137",
      "position": "header"
    },
    {
      "type": "printed",
      "content": "G Maxwell - Confidential",
      "position": "header"
    },
    {
      "type": "printed",
      "content": "1 the flights? 2 A. I can't recollect having a meal 3 with them, but just so we are clear, the 4 allegations that had a meal on 5 Jeffrey's island is 100 percent false. 6 Q. But he may have had a meal on 7 Jeffrey's plane? 8 A. I'm sure he had a meal on Jeffrey's 9 plane. 10 Q. You do know how many times he flew 11 on Jeffrey's plane? 12 A. I don't. 13 Q. Do you know who is? 14 A. I do. 15 Q. How do you know him? 16 A. He used to work or still works for 17 18 Q. Did you ever have a relationship 19 with him? 20 A. We are talking about adult 21 consensual relationships, it's off the 22 record. 23 Q. I'm not asking what you did with 24 him, I'm asking if you ever had a",
      "position": "main"
    },
    {
      "type": "printed",
      "content": "MAGNA LEGAL SERVICES",
      "position": "footer"
    },
    {
      "type": "printed",
      "content": "DOJ-OGR-00003576",
      "position": "footer"
    }
  ],
  "entities": {
    "people": [
      "G Maxwell",
      "Jeffrey"
    ],
    "organizations": [
      "MAGNA LEGAL SERVICES"
    ],
    "locations": [],
    "dates": [
      "10/22/01"
    ],
    "reference_numbers": [
      "Case 1:20-cv-00233-PAE",
      "Document 1204-10",
      "DOJ-OGR-00003576"
    ]
  },
  "additional_notes": "The document appears to be a court transcript with redactions. The content discusses a relationship and meals on a plane associated with 'Jeffrey', likely referring to Jeffrey Epstein."
}