{
  "document_metadata": {
    "page_number": "7",
    "document_number": "285-1",
    "date": "05/20/21",
    "document_type": "Court Document",
    "has_handwriting": true,
    "has_stamps": false
  },
  "full_text": "Case 1:20-cr-00330-PAE Document 285-1 Filed 05/20/21 Page 7 of 10\n\n6\nPhotos of naked girls on Maxwell's comp.\n\nSW searched an PB house. Collected photos included nude girls incl. children. Epstein tipped off. All computers were gone.\nVirginia says cammed all over NE house. She believes they were used for extortion or bm by Epstein. When lead att to other men had to report back.\nVideos recorded in bathroom - security?\nMaxwell took twice sexually explicit photos of her req'd.\nMaxwell gave photo to Epstein & bbday @ age 16. Prob hng on me & the homes\nSaved on computers.\n\n[REDACTED]\n\nSubp. issued for computers\nRegistered as sex offender in FL\nLevel 3\nRegistered in NY\nRepay by pwate jet\nSex acts on planes\nManhattan\n\nCONFIDENTIAL\nSDNY_GM_02742883\nDOJ-OGR-00004176",
  "text_blocks": [
    {
      "type": "printed",
      "content": "Case 1:20-cr-00330-PAE Document 285-1 Filed 05/20/21 Page 7 of 10",
      "position": "header"
    },
    {
      "type": "handwritten",
      "content": "Photos of naked girls on Maxwell's comp.\n\nSW searched an PB house. Collected photos included nude girls incl. children. Epstein tipped off. All computers were gone.\nVirginia says cammed all over NE house. She believes they were used for extortion or bm by Epstein. When lead att to other men had to report back.\nVideos recorded in bathroom - security?\nMaxwell took twice sexually explicit photos of her req'd.\nMaxwell gave photo to Epstein & bbday @ age 16. Prob hng on me & the homes\nSaved on computers.\n\n[REDACTED]\n\nSubp. issued for computers\nRegistered as sex offender in FL\nLevel 3\nRegistered in NY\nRepay by pwate jet\nSex acts on planes\nManhattan",
      "position": "middle"
    },
    {
      "type": "printed",
      "content": "CONFIDENTIAL\nSDNY_GM_02742883\nDOJ-OGR-00004176",
      "position": "footer"
    }
  ],
  "entities": {
    "people": [
      "Virginia",
      "Epstein",
      "Maxwell"
    ],
    "organizations": [],
    "locations": [
      "NE house",
      "FL",
      "NY",
      "Manhattan"
    ],
    "dates": [
      "05/20/21",
      "age 16"
    ],
    "reference_numbers": [
      "1:20-cr-00330-PAE",
      "285-1",
      "SDNY_GM_02742883",
      "DOJ-OGR-00004176"
    ]
  },
  "additional_notes": "The document contains handwritten notes with sensitive information, including allegations of sexual misconduct and exploitation. There are redactions in the document, indicating that some information has been withheld. The document is marked 'CONFIDENTIAL'."
}