{
  "document_metadata": {
    "page_number": "14 of 40",
    "document_number": "365",
    "date": "10/22/21",
    "document_type": "Juror Questionnaire",
    "has_handwriting": false,
    "has_stamps": false
  },
  "full_text": "Case 1:20-cr-00330-PAE Document 365 Filed 10/22/21 Page 14 of 40 Juror ID: 23.24 Have you, or has any relative or close friend, ever been the subject of any investigation or accusation by any grand jury, state or federal, or any other investigation? Yes (self) Yes (friend or family member) No 23a.2 If yes, is there anything about that experience that would prevent you from acting as a fair and impartial juror in this case? Yes No 23b24b. If yes to 23a24a, please explain: 24-25 Have you, or any of your relatives or close friends, ever been a victim of a crime? Yes (self) Yes (friend or family member) No 24a.2 If yes, is there anything about that experience that would prevent you from acting as a fair and impartial juror in this case? Yes No 24b25b. If yes to 24a25a, please explain: 25.26 Have you, or has any member of your family or any of your close friends—either as individuals or in the course of their business affairs—ever been a party to a legal action or dispute with the United States, or with any of the officers, departments, agencies, or employees of the United States, including the United States Attorney's Office, the FBI, or the NYPD? Yes (self) Yes (friend or family member) No -13- DOJ-OGR-00005290",
  "text_blocks": [
    {
      "type": "printed",
      "content": "Case 1:20-cr-00330-PAE Document 365 Filed 10/22/21 Page 14 of 40",
      "position": "header"
    },
    {
      "type": "printed",
      "content": "Juror ID:",
      "position": "header"
    },
    {
      "type": "printed",
      "content": "23.24 Have you, or has any relative or close friend, ever been the subject of any investigation or accusation by any grand jury, state or federal, or any other investigation? Yes (self) Yes (friend or family member) No",
      "position": "main"
    },
    {
      "type": "printed",
      "content": "23a.2 If yes, is there anything about that experience that would prevent you from acting as a fair and impartial juror in this case? Yes No",
      "position": "main"
    },
    {
      "type": "printed",
      "content": "23b24b. If yes to 23a24a, please explain:",
      "position": "main"
    },
    {
      "type": "printed",
      "content": "24-25 Have you, or any of your relatives or close friends, ever been a victim of a crime? Yes (self) Yes (friend or family member) No",
      "position": "main"
    },
    {
      "type": "printed",
      "content": "24a.2 If yes, is there anything about that experience that would prevent you from acting as a fair and impartial juror in this case? Yes No",
      "position": "main"
    },
    {
      "type": "printed",
      "content": "24b25b. If yes to 24a25a, please explain:",
      "position": "main"
    },
    {
      "type": "printed",
      "content": "25.26 Have you, or has any member of your family or any of your close friends—either as individuals or in the course of their business affairs—ever been a party to a legal action or dispute with the United States, or with any of the officers, departments, agencies, or employees of the United States, including the United States Attorney's Office, the FBI, or the NYPD? Yes (self) Yes (friend or family member) No",
      "position": "main"
    },
    {
      "type": "printed",
      "content": "-13-",
      "position": "footer"
    },
    {
      "type": "printed",
      "content": "DOJ-OGR-00005290",
      "position": "footer"
    }
  ],
  "entities": {
    "people": [],
    "organizations": [
      "FBI",
      "NYPD",
      "United States Attorney's Office"
    ],
    "locations": [],
    "dates": [
      "10/22/21"
    ],
    "reference_numbers": [
      "1:20-cr-00330-PAE",
      "365",
      "DOJ-OGR-00005290"
    ]
  },
  "additional_notes": "The document appears to be a juror questionnaire from a federal court case. It contains a series of questions related to the juror's background and potential biases. The document is clean and well-formatted, with no visible redactions or damage."
}