{
  "document_metadata": {
    "page_number": "8 of 40",
    "document_number": "365",
    "date": "10/22/21",
    "document_type": "Juror Questionnaire",
    "has_handwriting": false,
    "has_stamps": false
  },
  "full_text": "Case 1:20-cr-00330-PAE Document 365 Filed 10/22/21 Page 8 of 40 Juror ID: 4.5. Do you have any personal commitments that would make it difficult for you to get to court by 9:30 a.m., every day of trial, or remain at the courthouse until 5:00 p.m.? (Please note, the Court will arrange and provide transportation to and from the Courthouse each day for selected jurors). Yes No 4a.5a If yes, please explain why you would be unable to get to court by 9:30 a.m. or remain until 5:00 p.m.: 5.6. Do you have any difficulty reading, speaking, or understanding English? Yes No 6.7. Do you have any medical, physical, or mental condition or illness that makes you unable to serve on a jury, including difficulty hearing, seeing, reading, or concentrating? Yes No 6a.7a If yes, please briefly describe the condition or illness. If you believe you could serve as a juror if such condition were accommodated in some way, please state the accommodation. 7.8. Are you taking any medication which would prevent you from giving full attention to all the evidence at this trial? Yes No 7a.8a If yes, please explain: -7- DOJ-OGR-00005284",
  "text_blocks": [
    {
      "type": "printed",
      "content": "Case 1:20-cr-00330-PAE Document 365 Filed 10/22/21 Page 8 of 40",
      "position": "header"
    },
    {
      "type": "printed",
      "content": "Juror ID:",
      "position": "header"
    },
    {
      "type": "printed",
      "content": "4.5. Do you have any personal commitments that would make it difficult for you to get to court by 9:30 a.m., every day of trial, or remain at the courthouse until 5:00 p.m.? (Please note, the Court will arrange and provide transportation to and from the Courthouse each day for selected jurors). Yes No",
      "position": "main"
    },
    {
      "type": "printed",
      "content": "4a.5a If yes, please explain why you would be unable to get to court by 9:30 a.m. or remain until 5:00 p.m.:",
      "position": "main"
    },
    {
      "type": "printed",
      "content": "5.6. Do you have any difficulty reading, speaking, or understanding English? Yes No",
      "position": "main"
    },
    {
      "type": "printed",
      "content": "6.7. Do you have any medical, physical, or mental condition or illness that makes you unable to serve on a jury, including difficulty hearing, seeing, reading, or concentrating? Yes No",
      "position": "main"
    },
    {
      "type": "printed",
      "content": "6a.7a If yes, please briefly describe the condition or illness. If you believe you could serve as a juror if such condition were accommodated in some way, please state the accommodation.",
      "position": "main"
    },
    {
      "type": "printed",
      "content": "7.8. Are you taking any medication which would prevent you from giving full attention to all the evidence at this trial? Yes No",
      "position": "main"
    },
    {
      "type": "printed",
      "content": "7a.8a If yes, please explain:",
      "position": "main"
    },
    {
      "type": "printed",
      "content": "-7-",
      "position": "footer"
    },
    {
      "type": "printed",
      "content": "DOJ-OGR-00005284",
      "position": "footer"
    }
  ],
  "entities": {
    "people": [],
    "organizations": [
      "Court",
      "DOJ"
    ],
    "locations": [
      "Courthouse"
    ],
    "dates": [
      "10/22/21"
    ],
    "reference_numbers": [
      "1:20-cr-00330-PAE",
      "365",
      "DOJ-OGR-00005284"
    ]
  },
  "additional_notes": "The document appears to be a juror questionnaire with multiple choice questions and space for written responses. There are no handwritten annotations or stamps on the page."
}