{
  "document_metadata": {
    "page_number": "11",
    "document_number": "212",
    "date": "04/16/21",
    "document_type": "court document",
    "has_handwriting": false,
    "has_stamps": false
  },
  "full_text": "Case 1:20-cr-00330-PAE Document 212 Filed 04/16/21 Page 11 of 20\n\nSecond, the government's inevitable discovery doctrine is far too speculative. The \"typical application\" of the inevitable discovery doctrine is when \"the government seeks to invoke the doctrine on the basis of standardized, established procedures such as those requiring inventory searches.\" Stokes, 733 F.3d at 447. The government's \"inevitability analysis in this case,\" however, \"is predicated on an assessment of the actions that might have been taken by third parties,\" such as Judge Preska and the Miami Herald, who are \"not acting at the behest of the police.\" Id. \"Such an analysis is inherently speculative.\" Id.\n\nIn fact, unlike every other civil case in the Southern District of New York against Maxwell or Epstein's estate, the government deliberately chose not to intervene in the on-going unsealing process in Giuffre v. Maxwell. In the only other active SDNY case against Epstein, Doe v. Indyke, No. 20-cv-484-JLK, the government intervened and moved to stay discovery, saying that continued discovery could threaten its case against Maxwell.\n\nBy contrast, the government opted not to intervene and stay the unsealing in Giuffre v. Maxwell. The reason is obvious. Legitimately concerned about the propriety of its conduct in misleading Chief Judge McMahon and issuing an unconstitutionally overbroad subpoena to Boies Schiller, the government hoped to hedge its bets by allowing the unsealing process to unfold so it could make the inevitable discovery argument it now makes. This Court should not condone such gamesmanship.1\n\nThird, the government's inevitable discovery argument is far too broad. Even the government admits that the vast majority of material it obtained from Boies Schiller is not on the Giuffre v. Maxwell docket and has not been unsealed by Judge Preska. Resp. at 94. In fact, the government's response appears to concede that its inevitable discovery argument is limited to\n\n1 As the government recognizes, Judge Preska recognized this possibility, but deferred to this Court on the question since it is presiding over the criminal case. Resp. at 94 n.41.\n\n6\nDOJ-OGR-00003785",
  "text_blocks": [
    {
      "type": "printed",
      "content": "Case 1:20-cr-00330-PAE Document 212 Filed 04/16/21 Page 11 of 20",
      "position": "header"
    },
    {
      "type": "printed",
      "content": "Second, the government's inevitable discovery doctrine is far too speculative. The \"typical application\" of the inevitable discovery doctrine is when \"the government seeks to invoke the doctrine on the basis of standardized, established procedures such as those requiring inventory searches.\" Stokes, 733 F.3d at 447. The government's \"inevitability analysis in this case,\" however, \"is predicated on an assessment of the actions that might have been taken by third parties,\" such as Judge Preska and the Miami Herald, who are \"not acting at the behest of the police.\" Id. \"Such an analysis is inherently speculative.\" Id.",
      "position": "main"
    },
    {
      "type": "printed",
      "content": "In fact, unlike every other civil case in the Southern District of New York against Maxwell or Epstein's estate, the government deliberately chose not to intervene in the on-going unsealing process in Giuffre v. Maxwell. In the only other active SDNY case against Epstein, Doe v. Indyke, No. 20-cv-484-JLK, the government intervened and moved to stay discovery, saying that continued discovery could threaten its case against Maxwell.",
      "position": "main"
    },
    {
      "type": "printed",
      "content": "By contrast, the government opted not to intervene and stay the unsealing in Giuffre v. Maxwell. The reason is obvious. Legitimately concerned about the propriety of its conduct in misleading Chief Judge McMahon and issuing an unconstitutionally overbroad subpoena to Boies Schiller, the government hoped to hedge its bets by allowing the unsealing process to unfold so it could make the inevitable discovery argument it now makes. This Court should not condone such gamesmanship.1",
      "position": "main"
    },
    {
      "type": "printed",
      "content": "Third, the government's inevitable discovery argument is far too broad. Even the government admits that the vast majority of material it obtained from Boies Schiller is not on the Giuffre v. Maxwell docket and has not been unsealed by Judge Preska. Resp. at 94. In fact, the government's response appears to concede that its inevitable discovery argument is limited to",
      "position": "main"
    },
    {
      "type": "printed",
      "content": "1 As the government recognizes, Judge Preska recognized this possibility, but deferred to this Court on the question since it is presiding over the criminal case. Resp. at 94 n.41.",
      "position": "footnote"
    },
    {
      "type": "printed",
      "content": "6",
      "position": "footer"
    },
    {
      "type": "printed",
      "content": "DOJ-OGR-00003785",
      "position": "footer"
    }
  ],
  "entities": {
    "people": [
      "Judge Preska",
      "Chief Judge McMahon"
    ],
    "organizations": [
      "Boies Schiller",
      "Miami Herald",
      "Southern District of New York"
    ],
    "locations": [
      "New York"
    ],
    "dates": [
      "04/16/21"
    ],
    "reference_numbers": [
      "1:20-cr-00330-PAE",
      "Document 212",
      "20-cv-484-JLK",
      "DOJ-OGR-00003785"
    ]
  },
  "additional_notes": "The document appears to be a court filing related to a criminal case against an individual or entity associated with Epstein and Maxwell. The text discusses the government's inevitable discovery doctrine and its application in the case. The document includes citations to legal precedents and references to other court cases."
}