{
  "document_metadata": {
    "page_number": "29 of 30",
    "document_number": "204-12",
    "date": "04/16/21",
    "document_type": "Testimony Listing",
    "has_handwriting": false,
    "has_stamps": false
  },
  "full_text": "Case 1:20-cr-00330-PAE Document 204-12 Filed 04/16/21 Page 29 of 30 Testimony Listing for Bernard R. Siskin, Ph.D. Date Case Name Location Activity On Behalf Of 201 Rober so e al. . alle Comm ca o s Ce er P ladel a P De os o Pla ff 201 S a a oel mma ella Se a .C of ew or ew or C De os o Defe da 201 Ilma d s ral Pro er es e al. Merca le Ba P ladel a P De os o Pla ff 201 S e rel. ose R. alde . e a c. e al. Was go DC De os o Defe da 201 eal ew c. . merca er a o al P ladel a P De os o Pla ff 201 le sasser Progress e Sea le W ral Pla ff 201 Grea er Brm g am s res e al. . o orable o Was go DC De os o Pla ff 201 de e de L g Ce er of So er C e al C Was go DC De os o Pla ff 201 Marc Da el g a . Ils a e s ra ce Com a P ladel a P De os o Pla ff 201 Mar le sasser e al Progress e Drec s ra ce P ladel a P Declara o Pla ff 201 Bre da oe ler e al fos sec olog es e al Was go DC De os o Defe da BLDS, LLC - Friday, December 4, 2020 Page 1 of 1 DOJ-OGR-00003649",
  "text_blocks": [
    {
      "type": "printed",
      "content": "Case 1:20-cr-00330-PAE Document 204-12 Filed 04/16/21 Page 29 of 30",
      "position": "header"
    },
    {
      "type": "printed",
      "content": "Testimony Listing for Bernard R. Siskin, Ph.D.",
      "position": "header"
    },
    {
      "type": "printed",
      "content": "Date Case Name Location Activity On Behalf Of",
      "position": "header"
    },
    {
      "type": "printed",
      "content": "201 Rober so e al. . alle Comm ca o s Ce er P ladel a P De os o Pla ff",
      "position": "body"
    },
    {
      "type": "printed",
      "content": "201 S a a oel mma ella Se a .C of ew or ew or C De os o Defe da",
      "position": "body"
    },
    {
      "type": "printed",
      "content": "201 Ilma d s ral Pro er es e al. Merca le Ba P ladel a P De os o Pla ff",
      "position": "body"
    },
    {
      "type": "printed",
      "content": "201 S e rel. ose R. alde . e a c. e al. Was go DC De os o Defe da",
      "position": "body"
    },
    {
      "type": "printed",
      "content": "201 eal ew c. . merca er a o al P ladel a P De os o Pla ff",
      "position": "body"
    },
    {
      "type": "printed",
      "content": "201 le sasser Progress e Sea le W ral Pla ff",
      "position": "body"
    },
    {
      "type": "printed",
      "content": "201 Grea er Brm g am s res e al. . o orable o Was go DC De os o Pla ff",
      "position": "body"
    },
    {
      "type": "printed",
      "content": "201 de e de L g Ce er of So er C e al C Was go DC De os o Pla ff",
      "position": "body"
    },
    {
      "type": "printed",
      "content": "201 Marc Da el g a . Ils a e s ra ce Com a P ladel a P De os o Pla ff",
      "position": "body"
    },
    {
      "type": "printed",
      "content": "201 Mar le sasser e al Progress e Drec s ra ce P ladel a P Declara o Pla ff",
      "position": "body"
    },
    {
      "type": "printed",
      "content": "201 Bre da oe ler e al fos sec olog es e al Was go DC De os o Defe da",
      "position": "body"
    },
    {
      "type": "printed",
      "content": "BLDS, LLC - Friday, December 4, 2020 Page 1 of 1",
      "position": "footer"
    },
    {
      "type": "printed",
      "content": "DOJ-OGR-00003649",
      "position": "footer"
    }
  ],
  "entities": {
    "people": [
      "Bernard R. Siskin"
    ],
    "organizations": [
      "BLDS, LLC"
    ],
    "locations": [
      "Washington DC"
    ],
    "dates": [
      "04/16/21",
      "December 4, 2020"
    ],
    "reference_numbers": [
      "Case 1:20-cr-00330-PAE",
      "Document 204-12",
      "DOJ-OGR-00003649"
    ]
  },
  "additional_notes": "The document appears to be a testimony listing for Bernard R. Siskin, Ph.D. The text is mostly printed, with some garbled text in the body. The document has a header and footer with relevant metadata."
}