{
  "document_metadata": {
    "page_number": "7",
    "document_number": "386-2",
    "date": "10/29/21",
    "document_type": "court document",
    "has_handwriting": false,
    "has_stamps": false
  },
  "full_text": "Case 1:20-cr-00330-PAE Document 386-2 Filed 10/29/21 Page 7 of 12\nLisa Marie Rocchio, Ph.D. 6\nRocchio, L.M. (March, 2011). The effects of trauma on the therapist. Paper presented at the National Meeting of the American Anxiety Disorders Association, New Orleans, LA.\nHughes, D.M. & Rocchio, L.M. (November 2010). Forensic assessment of psychological trauma and PTSD. Workshop presented at the 26th Annual Meeting of the International Society for Traumatic Stress Studies, Montreal, Canada.\nRocchio, L.M. (August 2010). Professional and ethical considerations in trauma psychology: Psychotherapy. In L. Rocchio (Chair), Professional and ethical considerations in trauma psychology: Psychotherapy, forensics, research. Symposium conducted at the National Meeting of the American Psychological Association, San Diego, CA.\nRocchio, L.M. (March 2010). Trauma psychology: What the anxiety disorders specialist needs to know. Paper presented at the National Meeting of the American Anxiety Disorders Association, Baltimore, MD.\nEthics Committee of the Rhode Island Psychological Association (June 2008). From In Treatment to our treatment: Ethical considerations raised in the television program In Treatment. Continuing education salon presentation sponsored by the Rhode Island Psychological Association, Providence, RI.\nEthics Committee of the Rhode Island Psychological Association (January 2007). Sex, lies & confidentiality: A discussion of the top ten ethical issues posed to the RIPA Ethics Committee. Professional Continuing Education Workshop sponsored by the Rhode Island Psychological Association, Providence, RI.\nRocchio, L.M. (October 1999). The effects of trauma on the professional. Workshop presented at the Fifth Annual Conference of the RI Coalition Against Domestic Violence, Providence, RI.\nRocchio, L.M. (April 1999). Discussant. In J.C. Chrisler (Chair), Addressing fat oppression: Research and practice. Symposium conducted at the National Meeting of the Eastern Psychological Association, Providence, RI.\nRocchio, L.M. (October 1997). Discussant. In J.C. Chrisler (Chair), Current issues in feminist therapy. Symposium conducted at the National Meeting of the New England Psychological Association, Easton, MA.\nJohnston-Robledo, I., Rocchio, L. M., & Chrisler, J. C. (March 1997). AWP program content 1981 - 1996: Where we've been, where we're heading. Discussion facilitated at the National Meeting of the Association for Women in Psychology, Pittsburgh, PA.\nRocchio, L.M. (October 1996). Discussant. In J.C. Chrisler (Chair), Women and weight: Gendered messages from the media. Symposium conducted at the National Meeting of the New England Psychological Association, New London, CT.\nRocchio, L. M. (August 1996). The pursuit of beauty through thinness and the impact of advertising on college women's attitudes. In C. Smith (Chair), Empirical investigations of women's pursuit of beauty. Symposium conducted at the National Meeting of the American Psychological Association, Toronto, Canada.\nCogan, J. & Rocchio, L. M. (March 1995). Fat oppression and body hatred: Strategies for change. One-half day training workshop presented at the National Meeting of the Association for Women in Psychology, Indianapolis, IN.\n3502-006 Page 6 of 11 DOJ-OGR-00005659",
  "text_blocks": [
    {
      "type": "printed",
      "content": "Case 1:20-cr-00330-PAE Document 386-2 Filed 10/29/21 Page 7 of 12",
      "position": "header"
    },
    {
      "type": "printed",
      "content": "Lisa Marie Rocchio, Ph.D. 6",
      "position": "top"
    },
    {
      "type": "printed",
      "content": "Rocchio, L.M. (March, 2011). The effects of trauma on the therapist. Paper presented at the National Meeting of the American Anxiety Disorders Association, New Orleans, LA.",
      "position": "middle"
    },
    {
      "type": "printed",
      "content": "Hughes, D.M. & Rocchio, L.M. (November 2010). Forensic assessment of psychological trauma and PTSD. Workshop presented at the 26th Annual Meeting of the International Society for Traumatic Stress Studies, Montreal, Canada.",
      "position": "middle"
    },
    {
      "type": "printed",
      "content": "Rocchio, L.M. (August 2010). Professional and ethical considerations in trauma psychology: Psychotherapy. In L. Rocchio (Chair), Professional and ethical considerations in trauma psychology: Psychotherapy, forensics, research. Symposium conducted at the National Meeting of the American Psychological Association, San Diego, CA.",
      "position": "middle"
    },
    {
      "type": "printed",
      "content": "Rocchio, L.M. (March 2010). Trauma psychology: What the anxiety disorders specialist needs to know. Paper presented at the National Meeting of the American Anxiety Disorders Association, Baltimore, MD.",
      "position": "middle"
    },
    {
      "type": "printed",
      "content": "Ethics Committee of the Rhode Island Psychological Association (June 2008). From In Treatment to our treatment: Ethical considerations raised in the television program In Treatment. Continuing education salon presentation sponsored by the Rhode Island Psychological Association, Providence, RI.",
      "position": "middle"
    },
    {
      "type": "printed",
      "content": "Ethics Committee of the Rhode Island Psychological Association (January 2007). Sex, lies & confidentiality: A discussion of the top ten ethical issues posed to the RIPA Ethics Committee. Professional Continuing Education Workshop sponsored by the Rhode Island Psychological Association, Providence, RI.",
      "position": "middle"
    },
    {
      "type": "printed",
      "content": "Rocchio, L.M. (October 1999). The effects of trauma on the professional. Workshop presented at the Fifth Annual Conference of the RI Coalition Against Domestic Violence, Providence, RI.",
      "position": "middle"
    },
    {
      "type": "printed",
      "content": "Rocchio, L.M. (April 1999). Discussant. In J.C. Chrisler (Chair), Addressing fat oppression: Research and practice. Symposium conducted at the National Meeting of the Eastern Psychological Association, Providence, RI.",
      "position": "middle"
    },
    {
      "type": "printed",
      "content": "Rocchio, L.M. (October 1997). Discussant. In J.C. Chrisler (Chair), Current issues in feminist therapy. Symposium conducted at the National Meeting of the New England Psychological Association, Easton, MA.",
      "position": "middle"
    },
    {
      "type": "printed",
      "content": "Johnston-Robledo, I., Rocchio, L. M., & Chrisler, J. C. (March 1997). AWP program content 1981 - 1996: Where we've been, where we're heading. Discussion facilitated at the National Meeting of the Association for Women in Psychology, Pittsburgh, PA.",
      "position": "middle"
    },
    {
      "type": "printed",
      "content": "Rocchio, L.M. (October 1996). Discussant. In J.C. Chrisler (Chair), Women and weight: Gendered messages from the media. Symposium conducted at the National Meeting of the New England Psychological Association, New London, CT.",
      "position": "middle"
    },
    {
      "type": "printed",
      "content": "Rocchio, L. M. (August 1996). The pursuit of beauty through thinness and the impact of advertising on college women's attitudes. In C. Smith (Chair), Empirical investigations of women's pursuit of beauty. Symposium conducted at the National Meeting of the American Psychological Association, Toronto, Canada.",
      "position": "middle"
    },
    {
      "type": "printed",
      "content": "Cogan, J. & Rocchio, L. M. (March 1995). Fat oppression and body hatred: Strategies for change. One-half day training workshop presented at the National Meeting of the Association for Women in Psychology, Indianapolis, IN.",
      "position": "middle"
    },
    {
      "type": "printed",
      "content": "3502-006 Page 6 of 11 DOJ-OGR-00005659",
      "position": "footer"
    }
  ],
  "entities": {
    "people": [
      "Lisa Marie Rocchio",
      "D.M. Hughes",
      "J.C. Chrisler",
      "I. Johnston-Robledo",
      "C. Smith",
      "J. Cogan"
    ],
    "organizations": [
      "American Anxiety Disorders Association",
      "International Society for Traumatic Stress Studies",
      "American Psychological Association",
      "Rhode Island Psychological Association",
      "RI Coalition Against Domestic Violence",
      "Eastern Psychological Association",
      "New England Psychological Association",
      "Association for Women in Psychology"
    ],
    "locations": [
      "New Orleans, LA",
      "Montreal, Canada",
      "San Diego, CA",
      "Baltimore, MD",
      "Providence, RI",
      "Easton, MA",
      "Pittsburgh, PA",
      "New London, CT",
      "Toronto, Canada",
      "Indianapolis, IN"
    ],
    "dates": [
      "March, 2011",
      "November 2010",
      "August 2010",
      "March 2010",
      "June 2008",
      "January 2007",
      "October 1999",
      "April 1999",
      "October 1997",
      "March 1997",
      "October 1996",
      "August 1996",
      "March 1995"
    ],
    "reference_numbers": [
      "1:20-cr-00330-PAE",
      "386-2",
      "3502-006",
      "DOJ-OGR-00005659"
    ]
  },
  "additional_notes": "The document appears to be a CV or a list of professional presentations by Lisa Marie Rocchio, Ph.D. The text is typed and there are no visible stamps or handwritten notes."
}