{
  "document_metadata": {
    "page_number": "22 of 23",
    "document_number": "311-1",
    "date": "07/02/21",
    "document_type": "court transcript",
    "has_handwriting": false,
    "has_stamps": false
  },
  "full_text": "Case 1:20-cr-00330-PAE Document 311-1 Filed 07/02/21 Page 22 of 23\n\nxj3q1gra\n\nSEALED\n1\neverything will be filed under seal, and it will be \"In Re Grand Jury,\" you know, the usual, and it will have the treatment that \"In Re Grand Jury\" materials get, and everything will be filed under seal. But that way I at least have a place to put this, okay?\n\nMR. ROSSMILLER: I appreciate that, your Honor. I think we had expected that had the order been either granted or denied, that consistent with our usual All Writs application, that it would have then been identified with a number, but frankly, I'm not in the clerk's office, so --\n\nTHE COURT: Okay. But it has to have one, and I'm particularly acutely desirous of making sure that this is filed under a docket number with this court because I am concerned about the way everything has happened to date, given the Second Circuit's kind of, it seems to me, obvious displeasure with the fact that this whole thing has been litigated under seal. So grand jury material, absolutely. But let's be sure that there is a docket, you know, that we don't have something that's off the radar screen.\n\nMR. ROSSMILLER: Totally understood, your Honor, and I appreciate that, and we're grateful to the Court for that.\n\nTHE COURT: Great. Okay. And you'll get your answer by early next week. I have to go to the annual meeting of the chief district judges.\n\nMR. ROSSMILLER: I don't envy the Court that.\n\nSOUTHERN DISTRICT REPORTERS, P.C. (212) 805-0300 SDNY_GM_00000873 DOJ-OGR-00004915",
  "text_blocks": [
    {
      "type": "printed",
      "content": "Case 1:20-cr-00330-PAE Document 311-1 Filed 07/02/21 Page 22 of 23",
      "position": "header"
    },
    {
      "type": "printed",
      "content": "xj3q1gra\n\nSEALED",
      "position": "top"
    },
    {
      "type": "printed",
      "content": "1\neverything will be filed under seal, and it will be \"In Re Grand Jury,\" you know, the usual, and it will have the treatment that \"In Re Grand Jury\" materials get, and everything will be filed under seal. But that way I at least have a place to put this, okay?\n\nMR. ROSSMILLER: I appreciate that, your Honor. I think we had expected that had the order been either granted or denied, that consistent with our usual All Writs application, that it would have then been identified with a number, but frankly, I'm not in the clerk's office, so --\n\nTHE COURT: Okay. But it has to have one, and I'm particularly acutely desirous of making sure that this is filed under a docket number with this court because I am concerned about the way everything has happened to date, given the Second Circuit's kind of, it seems to me, obvious displeasure with the fact that this whole thing has been litigated under seal. So grand jury material, absolutely. But let's be sure that there is a docket, you know, that we don't have something that's off the radar screen.\n\nMR. ROSSMILLER: Totally understood, your Honor, and I appreciate that, and we're grateful to the Court for that.\n\nTHE COURT: Great. Okay. And you'll get your answer by early next week. I have to go to the annual meeting of the chief district judges.\n\nMR. ROSSMILLER: I don't envy the Court that.",
      "position": "middle"
    },
    {
      "type": "printed",
      "content": "SOUTHERN DISTRICT REPORTERS, P.C. (212) 805-0300 SDNY_GM_00000873 DOJ-OGR-00004915",
      "position": "footer"
    }
  ],
  "entities": {
    "people": [
      "MR. ROSSMILLER"
    ],
    "organizations": [
      "SOUTHERN DISTRICT REPORTERS, P.C.",
      "Second Circuit"
    ],
    "locations": [],
    "dates": [
      "07/02/21",
      "early next week"
    ],
    "reference_numbers": [
      "1:20-cr-00330-PAE",
      "311-1",
      "SDNY_GM_00000873",
      "DOJ-OGR-00004915"
    ]
  },
  "additional_notes": "The document appears to be a court transcript with a header indicating it is page 22 of 23. The content is a conversation between MR. ROSSMILLER and THE COURT. The document is marked as 'SEALED'."
}