{
  "document_metadata": {
    "page_number": "32",
    "document_number": "203-3",
    "date": "05/25/21",
    "document_type": "Testimony",
    "has_handwriting": false,
    "has_stamps": false
  },
  "full_text": "Case 1:20-cr-00330-PAE Document 203-3 Filed 05/25/21 Page 30 of 34\n32\nupstairs to meet Mr. Epstein.\nThey provided Mr. Epstein a massage in their underwear. Mr. Epstein asked to leave and finished the massage.\nMr. Epstein masturbated in front of on that first occasion, and , after the massage, she was paid $200 and she left the residence.\nQ All right.\nA On other occasions after that, would be the one to contact to come to the residence to provide massages for Mr. Epstein.\nQ And you have phone records showing calls from phone to 's phone?\nA Yes, I do.\nQ In addition to that, the masturbation during that massage, was there other sexual activity that occurred between the two of them?\nA Yes, there was. Mr. Epstein requested that rub his chest and nipples while he masturbated. He also used a \nOFFICIAL REPORTING SERVICE, LLC (954) 467-8204\nMM20-GJ TESTIMONY-000334\nCONFIDENTIAL\n3501.125-020\nPage 32 of 65\nDOJ-OGR-00004692",
  "text_blocks": [
    {
      "type": "printed",
      "content": "Case 1:20-cr-00330-PAE Document 203-3 Filed 05/25/21 Page 30 of 34",
      "position": "header"
    },
    {
      "type": "printed",
      "content": "32",
      "position": "header"
    },
    {
      "type": "printed",
      "content": "upstairs to meet Mr. Epstein.\nThey provided Mr. Epstein a massage in their underwear. Mr. Epstein asked to leave and finished the massage.\nMr. Epstein masturbated in front of on that first occasion, and , after the massage, she was paid $200 and she left the residence.\nQ All right.\nA On other occasions after that, would be the one to contact to come to the residence to provide massages for Mr. Epstein.\nQ And you have phone records showing calls from phone to 's phone?\nA Yes, I do.\nQ In addition to that, the masturbation during that massage, was there other sexual activity that occurred between the two of them?\nA Yes, there was. Mr. Epstein requested that rub his chest and nipples while he masturbated. He also used a",
      "position": "main"
    },
    {
      "type": "printed",
      "content": "OFFICIAL REPORTING SERVICE, LLC (954) 467-8204",
      "position": "footer"
    },
    {
      "type": "printed",
      "content": "MM20-GJ TESTIMONY-000334",
      "position": "footer"
    },
    {
      "type": "printed",
      "content": "CONFIDENTIAL",
      "position": "footer"
    },
    {
      "type": "printed",
      "content": "3501.125-020\nPage 32 of 65\nDOJ-OGR-00004692",
      "position": "footer"
    }
  ],
  "entities": {
    "people": [
      "Mr. Epstein"
    ],
    "organizations": [
      "OFFICIAL REPORTING SERVICE, LLC"
    ],
    "locations": [],
    "dates": [
      "05/25/21"
    ],
    "reference_numbers": [
      "1:20-cr-00330-PAE",
      "203-3",
      "MM20-GJ TESTIMONY-000334",
      "3501.125-020",
      "DOJ-OGR-00004692"
    ]
  },
  "additional_notes": "The document appears to be a testimony transcript related to a court case involving Mr. Epstein. The text contains redactions, indicating sensitive information has been removed. The document is marked 'CONFIDENTIAL' and includes a page number (32 of 65), suggesting it is part of a larger document."
}