{
  "document_metadata": {
    "page_number": "1",
    "document_number": "224",
    "date": "04/20/21",
    "document_type": "court document",
    "has_handwriting": false,
    "has_stamps": false
  },
  "full_text": "Case 1:20-cr-00330-PAE Document 224 Filed 04/20/21 Page 1 of 17\n\nUNITED STATES DISTRICT COURT\nSOUTHERN DISTRICT OF NEW YORK\n\nUNITED STATES OF AMERICA,\nv.\nGHISLAINE MAXWELL,\nDefendant.\n\nREPLY MEMORANDUM OF GHISLAINE MAXWELL\nIN SUPPORT OF HER MOTION FOR A SEVERANCE OF AND SEPARATE TRIAL\nON COUNTS FIVE AND SIX OF THE SUPERSEDING INDICTMENT\n\nJeffrey S. Pagliuca\nLaura A. Menninger\nHADDON, MORGAN & FOREMAN P.C.\n150 East 10th Avenue\nDenver, CO 80203\nPhone: 303-831-7364\n\nChristian R. Everdell\nCOHEN & GRESSER LLP\n800 Third Avenue New\nYork, NY 10022\nPhone: 212-957-7600\n\nBobbi C. Sternheim\nLaw Offices of Bobbi C. Sternheim\n33 West 19th Street - 4th Floor\nNew York, NY 10011\nPhone: 212-243-1100\n\nAttorneys for Ghislaine Maxwell\n\nDOJ-OGR-00003898",
  "text_blocks": [
    {
      "type": "printed",
      "content": "Case 1:20-cr-00330-PAE Document 224 Filed 04/20/21 Page 1 of 17",
      "position": "header"
    },
    {
      "type": "printed",
      "content": "UNITED STATES DISTRICT COURT\nSOUTHERN DISTRICT OF NEW YORK\n\nUNITED STATES OF AMERICA,\nv.\nGHISLAINE MAXWELL,\nDefendant.",
      "position": "top"
    },
    {
      "type": "printed",
      "content": "REPLY MEMORANDUM OF GHISLAINE MAXWELL\nIN SUPPORT OF HER MOTION FOR A SEVERANCE OF AND SEPARATE TRIAL\nON COUNTS FIVE AND SIX OF THE SUPERSEDING INDICTMENT",
      "position": "middle"
    },
    {
      "type": "printed",
      "content": "Jeffrey S. Pagliuca\nLaura A. Menninger\nHADDON, MORGAN & FOREMAN P.C.\n150 East 10th Avenue\nDenver, CO 80203\nPhone: 303-831-7364\n\nChristian R. Everdell\nCOHEN & GRESSER LLP\n800 Third Avenue New\nYork, NY 10022\nPhone: 212-957-7600\n\nBobbi C. Sternheim\nLaw Offices of Bobbi C. Sternheim\n33 West 19th Street - 4th Floor\nNew York, NY 10011\nPhone: 212-243-1100",
      "position": "middle"
    },
    {
      "type": "printed",
      "content": "Attorneys for Ghislaine Maxwell",
      "position": "middle"
    },
    {
      "type": "printed",
      "content": "DOJ-OGR-00003898",
      "position": "footer"
    }
  ],
  "entities": {
    "people": [
      "Jeffrey S. Pagliuca",
      "Laura A. Menninger",
      "Christian R. Everdell",
      "Bobbi C. Sternheim",
      "Ghislaine Maxwell"
    ],
    "organizations": [
      "HADDON, MORGAN & FOREMAN P.C.",
      "COHEN & GRESSER LLP",
      "Law Offices of Bobbi C. Sternheim",
      "UNITED STATES DISTRICT COURT",
      "UNITED STATES OF AMERICA"
    ],
    "locations": [
      "Denver, CO",
      "New York, NY"
    ],
    "dates": [
      "04/20/21"
    ],
    "reference_numbers": [
      "1:20-cr-00330-PAE",
      "Document 224",
      "20 Cr. 330 (AJN)",
      "DOJ-OGR-00003898"
    ]
  },
  "additional_notes": "The document appears to be a court filing related to the case of Ghislaine Maxwell. It is a reply memorandum in support of a motion for severance and separate trial on certain counts of the superseding indictment. The document is well-formatted and printed, with no visible handwriting or stamps."
}