{
  "document_metadata": {
    "page_number": "34 of 349",
    "document_number": "Document 293-1",
    "date": "05/25/2021",
    "document_type": "USAO Roles and Responsibilities in Epstein Investigation",
    "has_handwriting": false,
    "has_stamps": false
  },
  "full_text": "USAO Roles and Responsibilities in Epstein Investigation Mid-2006 through Mid-2009 United States Attorney Alexander Acosta Jeff Sloman (Acting) First Assistant United States Attorney [Vacant] Jeff Sloman Criminal Chief Jeff Sloman Matthew Menchel [Menchcl Successor] Managing Assistant United States Attorney West Palm Beach Office Andrew Lourie [Lourie Successor] Assistant United States Attorney Marie Villafaña May 23, 2006 - USAO opens federal investigation into Jeffrey Epstein Sept 24, 2007 - NPA is signed June 30, 2008 - Epstein pleads guilty in state court July 22, 2009 - Epstein is released from incarceration",
  "text_blocks": [
    {
      "type": "printed",
      "content": "USAO Roles and Responsibilities in Epstein Investigation Mid-2006 through Mid-2009",
      "position": "header"
    },
    {
      "type": "printed",
      "content": "United States Attorney Alexander Acosta Jeff Sloman (Acting)",
      "position": "middle"
    },
    {
      "type": "printed",
      "content": "First Assistant United States Attorney [Vacant] Jeff Sloman",
      "position": "middle"
    },
    {
      "type": "printed",
      "content": "Criminal Chief Jeff Sloman Matthew Menchel [Menchcl Successor]",
      "position": "middle"
    },
    {
      "type": "printed",
      "content": "Managing Assistant United States Attorney West Palm Beach Office Andrew Lourie [Lourie Successor]",
      "position": "middle"
    },
    {
      "type": "printed",
      "content": "Assistant United States Attorney Marie Villafaña",
      "position": "middle"
    },
    {
      "type": "printed",
      "content": "May 23, 2006 - USAO opens federal investigation into Jeffrey Epstein",
      "position": "bottom"
    },
    {
      "type": "printed",
      "content": "Sept 24, 2007 - NPA is signed",
      "position": "bottom"
    },
    {
      "type": "printed",
      "content": "June 30, 2008 - Epstein pleads guilty in state court",
      "position": "bottom"
    },
    {
      "type": "printed",
      "content": "July 22, 2009 - Epstein is released from incarceration",
      "position": "bottom"
    }
  ],
  "entities": {
    "people": [
      "Alexander Acosta",
      "Jeff Sloman",
      "Matthew Menchel",
      "Andrew Lourie",
      "Marie Villafaña",
      "Jeffrey Epstein"
    ],
    "organizations": [
      "USAO",
      "United States Attorney"
    ],
    "locations": [
      "West Palm Beach"
    ],
    "dates": [
      "Mid-2006",
      "Mid-2009",
      "May 23, 2006",
      "Sept 24, 2007",
      "June 30, 2008",
      "July 22, 2009",
      "2006",
      "2007",
      "2008",
      "2009"
    ],
    "reference_numbers": [
      "Document 293-1",
      "Case 1:20-cr-00330-PAE",
      "DOJ-OGR-00004331"
    ]
  },
  "additional_notes": "The document appears to be a timeline of the USAO's roles and responsibilities in the Epstein investigation from mid-2006 to mid-2009. The image is clear and legible, with no visible redactions or damage."
}