{
  "document_metadata": {
    "page_number": "15 of 40",
    "document_number": "365",
    "date": "10/22/21",
    "document_type": "Juror Questionnaire",
    "has_handwriting": false,
    "has_stamps": false
  },
  "full_text": "Case 1:20-cr-00330-PAE Document 365 Filed 10/22/21 Page 15 of 40 Juror ID: 25a.2 If yes, is there anything about that experience that would prevent you from acting as a fair and impartial juror in this case? Yes No 25b2 6b. If yes to 25a26a, please explain: 26.27 Have you, or has any member of your family, ever had a dispute concerning money owed to you by the Government or owed by you to the Government? Yes (self) Yes (friend or family member) No 26a.2 If yes, is there anything about that experience that would prevent you from acting as a fair and impartial juror in this case? Yes No 26b2 7b. If yes to 26a27a, please explain: RELATIONSHIP WITH, AND VIEW OF, GOVERNMENT, DEFENSE, AND OTHERS 27.28 Do you or any member of your family or a close friend work in law, law enforcement, the justice system, or the courts? Yes No 27a.2 If yes, please explain: -14- DOJ-OGR-00005291",
  "text_blocks": [
    {
      "type": "printed",
      "content": "Case 1:20-cr-00330-PAE Document 365 Filed 10/22/21 Page 15 of 40",
      "position": "header"
    },
    {
      "type": "printed",
      "content": "Juror ID:",
      "position": "header"
    },
    {
      "type": "printed",
      "content": "25a.2 If yes, is there anything about that experience that would prevent you from acting as a fair and impartial juror in this case? Yes No",
      "position": "top"
    },
    {
      "type": "printed",
      "content": "25b2 6b. If yes to 25a26a, please explain:",
      "position": "top"
    },
    {
      "type": "printed",
      "content": "26.27 Have you, or has any member of your family, ever had a dispute concerning money owed to you by the Government or owed by you to the Government? Yes (self) Yes (friend or family member) No",
      "position": "middle"
    },
    {
      "type": "printed",
      "content": "26a.2 If yes, is there anything about that experience that would prevent you from acting as a fair and impartial juror in this case? Yes No",
      "position": "middle"
    },
    {
      "type": "printed",
      "content": "26b2 7b. If yes to 26a27a, please explain:",
      "position": "middle"
    },
    {
      "type": "printed",
      "content": "RELATIONSHIP WITH, AND VIEW OF, GOVERNMENT, DEFENSE, AND OTHERS",
      "position": "middle"
    },
    {
      "type": "printed",
      "content": "27.28 Do you or any member of your family or a close friend work in law, law enforcement, the justice system, or the courts? Yes No",
      "position": "bottom"
    },
    {
      "type": "printed",
      "content": "27a.2 If yes, please explain:",
      "position": "bottom"
    },
    {
      "type": "printed",
      "content": "-14-",
      "position": "footer"
    },
    {
      "type": "printed",
      "content": "DOJ-OGR-00005291",
      "position": "footer"
    }
  ],
  "entities": {
    "people": [],
    "organizations": [
      "Government"
    ],
    "locations": [],
    "dates": [
      "10/22/21"
    ],
    "reference_numbers": [
      "1:20-cr-00330-PAE",
      "365",
      "DOJ-OGR-00005291"
    ]
  },
  "additional_notes": "The document appears to be a juror questionnaire with multiple choice and open-ended questions. There are no visible redactions or damage."
}