{
  "document_metadata": {
    "page_number": "15",
    "document_number": "287",
    "date": "05/20/2021",
    "document_type": "Court Document",
    "has_handwriting": false,
    "has_stamps": false
  },
  "full_text": "Case 1:20-cr-00330-PAE Document 287 Filed 05/20/21 Page 15 of 16\ndense because it is in the possession of a third party. (Opp. 187-88). Ms. Maxwell anticipates that the rest of the diary will contain exculpatory information and inconsistent statements. It is therefore critical that Ms. Maxwell be able to review the original diary and to test it to ensure it is authentic and written contemporaneously with the events it describes. If the government will not obtain the diary, the Court should order the government to disclose the author's identity so that Ms. Maxwell can seek an appropriate subpoena.8\n\nCONCLUSION\n\nFor the reasons set forth above, we respectfully request that the Court grant the motions presented in their entirety.\n\nDated: March 15, 2021\nNew York, New York\n\nRespectfully submitted,\n\n/s/ Christian R. Everdell\nChristian R. Everdell\nCOHEN & GRESSER LLP\n800 Third Avenue\nNew York, NY 10022\nPhone: 212-957-7600\n\nJeffrey S. Pagliuca\nLaura A. Menninger\nHADDON, MORGAN & FOREMAN P.C.\n150 East 10th Avenue\nDenver, Colorado 80203\nPhone: 303-831-7364\n\nBobbi C. Sternheim\nLaw Offices of Bobbi C. Sternheim\n33 West 19th Street - 4th Floor\nNew York, NY 10011\nPhone: 212-243-1100\n\nAttorneys for Ghislaine Maxwell\n\n8 The other documents that Ms. Maxwell has requested are relevant for her motions related to the Epstein Non-Prosecution Agreement and her suppression motions. (Dkt. 148 at 11). The Court should order the production of those documents for the reasons set forth in those motions.\n\n12\nDOJ-OGR-00004242",
  "text_blocks": [
    {
      "type": "printed",
      "content": "Case 1:20-cr-00330-PAE Document 287 Filed 05/20/21 Page 15 of 16",
      "position": "header"
    },
    {
      "type": "printed",
      "content": "defense because it is in the possession of a third party. (Opp. 187-88). Ms. Maxwell anticipates that the rest of the diary will contain exculpatory information and inconsistent statements. It is therefore critical that Ms. Maxwell be able to review the original diary and to test it to ensure it is authentic and written contemporaneously with the events it describes. If the government will not obtain the diary, the Court should order the government to disclose the author's identity so that Ms. Maxwell can seek an appropriate subpoena.8",
      "position": "top"
    },
    {
      "type": "printed",
      "content": "CONCLUSION",
      "position": "middle"
    },
    {
      "type": "printed",
      "content": "For the reasons set forth above, we respectfully request that the Court grant the motions presented in their entirety.",
      "position": "middle"
    },
    {
      "type": "printed",
      "content": "Dated: March 15, 2021\nNew York, New York",
      "position": "middle"
    },
    {
      "type": "printed",
      "content": "Respectfully submitted,",
      "position": "middle"
    },
    {
      "type": "signature",
      "content": "/s/ Christian R. Everdell",
      "position": "middle"
    },
    {
      "type": "printed",
      "content": "Christian R. Everdell\nCOHEN & GRESSER LLP\n800 Third Avenue\nNew York, NY 10022\nPhone: 212-957-7600",
      "position": "middle"
    },
    {
      "type": "printed",
      "content": "Jeffrey S. Pagliuca\nLaura A. Menninger\nHADDON, MORGAN & FOREMAN P.C.\n150 East 10th Avenue\nDenver, Colorado 80203\nPhone: 303-831-7364",
      "position": "middle"
    },
    {
      "type": "printed",
      "content": "Bobbi C. Sternheim\nLaw Offices of Bobbi C. Sternheim\n33 West 19th Street - 4th Floor\nNew York, NY 10011\nPhone: 212-243-1100",
      "position": "middle"
    },
    {
      "type": "printed",
      "content": "Attorneys for Ghislaine Maxwell",
      "position": "middle"
    },
    {
      "type": "printed",
      "content": "8 The other documents that Ms. Maxwell has requested are relevant for her motions related to the Epstein Non-Prosecution Agreement and her suppression motions. (Dkt. 148 at 11). The Court should order the production of those documents for the reasons set forth in those motions.",
      "position": "bottom"
    },
    {
      "type": "printed",
      "content": "12",
      "position": "footer"
    },
    {
      "type": "printed",
      "content": "DOJ-OGR-00004242",
      "position": "footer"
    }
  ],
  "entities": {
    "people": [
      "Ghislaine Maxwell",
      "Christian R. Everdell",
      "Jeffrey S. Pagliuca",
      "Laura A. Menninger",
      "Bobbi C. Sternheim",
      "Epstein"
    ],
    "organizations": [
      "COHEN & GRESSER LLP",
      "HADDON, MORGAN & FOREMAN P.C.",
      "Law Offices of Bobbi C. Sternheim"
    ],
    "locations": [
      "New York",
      "Denver",
      "Colorado"
    ],
    "dates": [
      "March 15, 2021",
      "05/20/2021"
    ],
    "reference_numbers": [
      "1:20-cr-00330-PAE",
      "287",
      "Dkt. 148",
      "DOJ-OGR-00004242"
    ]
  },
  "additional_notes": "The document appears to be a court filing related to the case of Ghislaine Maxwell. It is a formal legal document with a clear structure and formatting. The text is mostly printed, with one signature block. There are no visible redactions or damage to the document."
}