{
  "document_metadata": {
    "page_number": "5",
    "document_number": "338",
    "date": "10/12/21",
    "document_type": "court document",
    "has_handwriting": true,
    "has_stamps": false
  },
  "full_text": "Case 1:20-cr-00330-PAE Document 338 Filed 10/12/21 Page 5 of 22 united States 397 U.S. 112, 114-15 (1970) (\"A limitation carving out an exception should apply to cases shown to be clearly within its purpose.\") Congress' purpose was to extend the limitation period for Rape, and assault to commit Rape, where the United States had jurisdiction of these offenses. Only this explains the need for 18 U.S.C ยง3297 which is purposely not retroactive. To have made it retroactive would have violated Stogner v. California, because Chapter 77, 117, and 110 were not previously included. For these reasons David A. Dieni should be granted intervenor status, and the enclosed brief should be filed in the Maxwell's Case styled above. David A. Dieni, 5324018 Federal Correctional Complex USP Coleman II PO Box 1034 Coleman, FL 33521 David A. Dieni David A. Dieni 8-4-2021 DOJ-OGR-00005183",
  "text_blocks": [
    {
      "type": "printed",
      "content": "Case 1:20-cr-00330-PAE Document 338 Filed 10/12/21 Page 5 of 22",
      "position": "header"
    },
    {
      "type": "handwritten",
      "content": "united States 397 U.S. 112, 114-15 (1970) (\"A limitation carving out an exception should apply to cases shown to be clearly within its purpose.\") Congress' purpose was to extend the limitation period for Rape, and assault to commit Rape, where the United States had jurisdiction of these offenses. Only this explains the need for 18 U.S.C ยง3297 which is purposely not retroactive. To have made it retroactive would have violated Stogner v. California, because Chapter 77, 117, and 110 were not previously included. For these reasons David A. Dieni should be granted intervenor status, and the enclosed brief should be filed in the Maxwell's Case styled above.",
      "position": "main body"
    },
    {
      "type": "handwritten",
      "content": "David A. Dieni, 5324018 Federal Correctional Complex USP Coleman II PO Box 1034 Coleman, FL 33521",
      "position": "left margin"
    },
    {
      "type": "handwritten",
      "content": "David A. Dieni David A. Dieni 8-4-2021",
      "position": "right margin"
    },
    {
      "type": "printed",
      "content": "DOJ-OGR-00005183",
      "position": "footer"
    }
  ],
  "entities": {
    "people": [
      "David A. Dieni"
    ],
    "organizations": [
      "USP Coleman II",
      "Federal Correctional Complex"
    ],
    "locations": [
      "Coleman, FL"
    ],
    "dates": [
      "1970",
      "8-4-2021",
      "10/12/21"
    ],
    "reference_numbers": [
      "1:20-cr-00330-PAE",
      "Document 338",
      "5324018",
      "PO Box 1034",
      "33521",
      "DOJ-OGR-00005183"
    ]
  },
  "additional_notes": "The document appears to be a court filing with handwritten text. The content discusses legal matters and references specific court cases and statutes."
}