{
  "document_metadata": {
    "page_number": "20",
    "document_number": "367",
    "date": "10/22/21",
    "document_type": "Juror Questionnaire",
    "has_handwriting": false,
    "has_stamps": false
  },
  "full_text": "Case 1:20-cr-00330-PAE Document 367 Filed 10/22/21 Page 20 of 35 Juror ID: How accurate do you feel the reports about this case, in any medium, have been? Not accurate Not very accurate Somewhat accurate Very accurate Don't know/No Opinion Do you think Ghislaine Maxwell's association with Jeffrey Epstein will make it difficult for you to fairly and impartially consider the evidence presented at trial and render a verdict based solely on the evidence? Yes No If Yes or Unsure, please explain: If you are selected as a juror in this case, would you be able to refrain from reading about, listening to, or watching any print, electronic media, or Internet coverage in this case? Yes No Unsure If Yes or Unsure, please explain: During the trial, you will hear evidence alleging sex crimes against underage girls. Some of the evidence will involve sexually suggestive or sexually explicit conduct. Is there anything about the nature of this case and the accusations as summarized at the hearing that will make it difficult for you to be a fair and impartial juror in this case? Yes No Unsure If Yes, please explain: Do you have any specific views or feelings concerning laws regarding the age at which individuals can consent to sexual activity with other individuals? No If Yes, what are your views or opinions and would they affect your ability to serve as a fair and impartial juror? Yes No 15. 16. -20- Commented [A29]: The Government proposes the language in purple color font. DOJ-OGR-00005342",
  "text_blocks": [
    {
      "type": "printed",
      "content": "Case 1:20-cr-00330-PAE Document 367 Filed 10/22/21 Page 20 of 35",
      "position": "header"
    },
    {
      "type": "printed",
      "content": "Juror ID:",
      "position": "top"
    },
    {
      "type": "printed",
      "content": "How accurate do you feel the reports about this case, in any medium, have been? Not accurate Not very accurate Somewhat accurate Very accurate Don't know/No Opinion",
      "position": "top"
    },
    {
      "type": "printed",
      "content": "Do you think Ghislaine Maxwell's association with Jeffrey Epstein will make it difficult for you to fairly and impartially consider the evidence presented at trial and render a verdict based solely on the evidence?",
      "position": "top"
    },
    {
      "type": "printed",
      "content": "If Yes or Unsure, please explain:",
      "position": "top"
    },
    {
      "type": "printed",
      "content": "If you are selected as a juror in this case, would you be able to refrain from reading about, listening to, or watching any print, electronic media, or Internet coverage in this case?",
      "position": "top"
    },
    {
      "type": "printed",
      "content": "Yes No Unsure If Yes or Unsure, please explain:",
      "position": "top"
    },
    {
      "type": "printed",
      "content": "During the trial, you will hear evidence alleging sex crimes against underage girls. Some of the evidence will involve sexually suggestive or sexually explicit conduct. Is there anything about the nature of this case and the accusations as summarized at the hearing that will make it difficult for you to be a fair and impartial juror in this case?",
      "position": "top"
    },
    {
      "type": "printed",
      "content": "Yes No Unsure If Yes, please explain:",
      "position": "top"
    },
    {
      "type": "printed",
      "content": "Do you have any specific views or feelings concerning laws regarding the age at which individuals can consent to sexual activity with other individuals?",
      "position": "top"
    },
    {
      "type": "printed",
      "content": "No If Yes, what are your views or opinions and would they affect your ability to serve as a fair and impartial juror?",
      "position": "top"
    },
    {
      "type": "printed",
      "content": "Yes No",
      "position": "top"
    },
    {
      "type": "printed",
      "content": "15. 16.",
      "position": "bottom"
    },
    {
      "type": "printed",
      "content": "-20-",
      "position": "footer"
    },
    {
      "type": "handwritten",
      "content": "No Yes No Yes Yes No",
      "position": "middle"
    },
    {
      "type": "stamp",
      "content": "Commented [A29]: The Government proposes the language in purple color font.",
      "position": "margin"
    },
    {
      "type": "printed",
      "content": "DOJ-OGR-00005342",
      "position": "footer"
    }
  ],
  "entities": {
    "people": [
      "Jeffrey Epstein",
      "Ghislaine Maxwell"
    ],
    "organizations": [],
    "locations": [],
    "dates": [
      "10/22/21"
    ],
    "reference_numbers": [
      "1:20-cr-00330-PAE",
      "367",
      "DOJ-OGR-00005342"
    ]
  },
  "additional_notes": "The document appears to be a juror questionnaire from a court case involving Ghislaine Maxwell. The document is mostly printed, with some checkboxes filled in. There is a comment in the margin regarding proposed language changes."
}