{
  "document_metadata": {
    "page_number": "53",
    "document_number": "12087-103",
    "date": null,
    "document_type": "Deposition Transcript",
    "has_handwriting": false,
    "has_stamps": false
  },
  "full_text": "Case 1:205-cv-00728-PLF Document 12087-103 Filed 10/28/20 Page 54 of 654\n\nPage 53\n1 G Maxwell - Confidential\n2 acts. I'm asking whether any of the massage therapists performed sexual acts for Mr.\n3 Epstein, as I have just described?\n4 A. I have never seen anybody have\n5 sexual intercourse with with Jeffrey, ever.\n6 Q. I'm not asking about sexual\n7 intercourse. I'm asking about any sexual\n8 act, touching of the breast -- did you ever\n9 see -- can you read back the question?\n10 (Record read.)\n11\n12 A. I'm not addressing any questions\n13 about consensual adult sex. If you want to\n14 talk about what the subject matter, which is\n15 defamation and lying, Virginia Roberts, that\n16 you and Virginia Roberts are participating in\n17 perpetrating her lies, I'm happy to address\n18 those. I never saw any inappropriate\n19 underage activities with Jeffrey ever.\n20 Q. I'm not asking about underage. I'm\n21 asking about whether any of the masseuses\n22 that were at the home perform sexual acts for\n23 Jeffrey Epstein?\n24 A. I have just answered the question.\n25 Q. No, you haven't.\n\nMAGNA LEGAL SERVICES DOJ-OGR-00003569",
  "text_blocks": [
    {
      "type": "printed",
      "content": "Case 1:205-cv-00728-PLF Document 12087-103 Filed 10/28/20 Page 54 of 654",
      "position": "header"
    },
    {
      "type": "printed",
      "content": "Page 53",
      "position": "header"
    },
    {
      "type": "printed",
      "content": "1 G Maxwell - Confidential\n2 acts. I'm asking whether any of the massage therapists performed sexual acts for Mr.\n3 Epstein, as I have just described?\n4 A. I have never seen anybody have\n5 sexual intercourse with with Jeffrey, ever.\n6 Q. I'm not asking about sexual\n7 intercourse. I'm asking about any sexual\n8 act, touching of the breast -- did you ever\n9 see -- can you read back the question?\n10 (Record read.)\n11\n12 A. I'm not addressing any questions\n13 about consensual adult sex. If you want to\n14 talk about what the subject matter, which is\n15 defamation and lying, Virginia Roberts, that\n16 you and Virginia Roberts are participating in\n17 perpetrating her lies, I'm happy to address\n18 those. I never saw any inappropriate\n19 underage activities with Jeffrey ever.\n20 Q. I'm not asking about underage. I'm\n21 asking about whether any of the masseuses\n22 that were at the home perform sexual acts for\n23 Jeffrey Epstein?\n24 A. I have just answered the question.\n25 Q. No, you haven't.",
      "position": "main"
    },
    {
      "type": "printed",
      "content": "MAGNA LEGAL SERVICES",
      "position": "footer"
    },
    {
      "type": "printed",
      "content": "DOJ-OGR-00003569",
      "position": "footer"
    }
  ],
  "entities": {
    "people": [
      "G Maxwell",
      "Jeffrey Epstein",
      "Virginia Roberts"
    ],
    "organizations": [
      "MAGNA LEGAL SERVICES"
    ],
    "locations": [],
    "dates": [
      "10/28/20"
    ],
    "reference_numbers": [
      "12087-103",
      "DOJ-OGR-00003569"
    ]
  },
  "additional_notes": "The document appears to be a deposition transcript with a confidential designation. The content is related to a legal case involving Jeffrey Epstein and Ghislaine Maxwell. The transcript includes questions and answers regarding sexual acts performed by massage therapists for Jeffrey Epstein."
}