{
  "document_metadata": {
    "page_number": "15",
    "document_number": "293-3",
    "date": "05/25/21",
    "document_type": "Testimony transcript",
    "has_handwriting": false,
    "has_stamps": false
  },
  "full_text": "Case 1:20-cr-00330-PAE Document 293-3 Filed 05/25/21 Page 16 of 34\n\narriving in and what time he arrived at that airport, and the last would be the actual aircraft itself, which aircraft he was traveling on, and just to remind the grand jury, Hyperion is the Gulfstream and JEGE is the Boeing 727.\nQ And who created this chart, the Merged Flight Manifests Chart?\nA The FBI.\nQ And where did they gather this information from?\nA We subpoenaed or the grand jury issued a subpoena to the pilot and pilots of Mr. Epstein and through counsel the pilots gave us a copy of the flight manifest for those two years and I have here a set of the flight manifests that were provided to us by the grand jury subpoena and have marked each of the Overt Acts from 191 to 225.\nSo that if any time the grand jury would like to come and look at the actual manifest the pilots gave us, you'll be able to see the data that this form was taken from.\nQ Okay. Thank you.\nMS. VILLAFANA: Before I go on, does anyone have any questions about those overt Acts and where this information came from?\n\nOFFICIAL REPORTING SERVICE, LLC (954) 467-8204\nMM20-GJ TESTIMONY-000317\nCONFIDENTIAL\n3501.125-020\nPage 15 of 65\nDOJ-OGR-00004678",
  "text_blocks": [
    {
      "type": "printed",
      "content": "Case 1:20-cr-00330-PAE Document 293-3 Filed 05/25/21 Page 16 of 34",
      "position": "header"
    },
    {
      "type": "printed",
      "content": "arriving in and what time he arrived at that airport, and the last would be the actual aircraft itself, which aircraft he was traveling on, and just to remind the grand jury, Hyperion is the Gulfstream and JEGE is the Boeing 727.\nQ And who created this chart, the Merged Flight Manifests Chart?\nA The FBI.\nQ And where did they gather this information from?\nA We subpoenaed or the grand jury issued a subpoena to the pilot and pilots of Mr. Epstein and through counsel the pilots gave us a copy of the flight manifest for those two years and I have here a set of the flight manifests that were provided to us by the grand jury subpoena and have marked each of the Overt Acts from 191 to 225.\nSo that if any time the grand jury would like to come and look at the actual manifest the pilots gave us, you'll be able to see the data that this form was taken from.\nQ Okay. Thank you.\nMS. VILLAFANA: Before I go on, does anyone have any questions about those overt Acts and where this information came from?",
      "position": "main"
    },
    {
      "type": "printed",
      "content": "OFFICIAL REPORTING SERVICE, LLC (954) 467-8204",
      "position": "footer"
    },
    {
      "type": "printed",
      "content": "MM20-GJ TESTIMONY-000317\nCONFIDENTIAL\n3501.125-020\nPage 15 of 65\nDOJ-OGR-00004678",
      "position": "footer"
    }
  ],
  "entities": {
    "people": [
      "Epstein",
      "VILLAFANA"
    ],
    "organizations": [
      "FBI",
      "OFFICIAL REPORTING SERVICE, LLC"
    ],
    "locations": [],
    "dates": [
      "05/25/21"
    ],
    "reference_numbers": [
      "1:20-cr-00330-PAE",
      "293-3",
      "MM20-GJ TESTIMONY-000317",
      "3501.125-020",
      "DOJ-OGR-00004678"
    ]
  },
  "additional_notes": "The document appears to be a confidential testimony transcript related to a court case involving Mr. Epstein. The text is mostly typed, with no visible handwriting or stamps. The footer contains information about the reporting service and confidentiality."
}