{
  "document_metadata": {
    "page_number": "24",
    "document_number": "380",
    "date": "10/29/21",
    "document_type": "court document",
    "has_handwriting": false,
    "has_stamps": false
  },
  "full_text": "Case 1:20-cr-00330-PAE Document 380 Filed 10/29/21 Page 24 of 54 undue confusion and an unnecessary sideshow . . .'); United States v. Boyle, No. 08 Cr. 523 (CM), 2009 WL 5178525, at *3 (S.D.N.Y. Dec. 23, 2009) (explaining that the defendant \"may offer evidence that Powell killed Hydell. He may not, however, offer evidence concerning that Powell was arrested and prosecuted for the murder.\"); United States v. Rodriguez, 582 F. Supp. 2d 486, 487 (S.D.N.Y. 2008) (to avoid confusing jurors, defendants precluded from introducing evidence about dismissals of prior charges against them in trial for the same conduct four years later); United States v. Hill, No. 12 Cr. 214 (KAM), 2014 WL 198813, at *1-2 (E.D.N.Y. Jan. 14, 2014) (precluding evidence or cross examination of a detective regarding the Kings County District Attorney's Office decision to question but not charge the defendant for a murder that occurred in 1997 but was only indicted fifteen years later because such testimony is hearsay, irrelevant, and confusing); United States v. Watts, 934 F. Supp. 2d 451, 484-486 (E.D.N.Y. 2013) (precluding the defendant from eliciting basis of decision not to charge a possible co-conspirator); United States v. Carneglia, No. 08 Cr. 76 (JBW), 2009 WL 185725, at *1 (E.D.N.Y. Jan. 27, 2009) (\"[T]he government's charging decisions are not proper subjects for cross-examination and argument.' Evidence related to the government's charging decisions may be excluded at trial based on lack of relevance.\" (quoting United States v. Re, 401 F.3d 828, 832 (7th Cir. 2005))).8 8 Although there is no per se bar to admission of charging decisions, the Second Circuit has permitted such evidence under narrow circumstances not present here, as discussed in greater detail below. See infra pp. 25-26 (discussing United States v. White, 692 F.3d 235, 246 (2d Cir. 2012)). 23 DOJ-OGR-00005417",
  "text_blocks": [
    {
      "type": "printed",
      "content": "Case 1:20-cr-00330-PAE Document 380 Filed 10/29/21 Page 24 of 54",
      "position": "header"
    },
    {
      "type": "printed",
      "content": "undue confusion and an unnecessary sideshow . . .'); United States v. Boyle, No. 08 Cr. 523 (CM), 2009 WL 5178525, at *3 (S.D.N.Y. Dec. 23, 2009) (explaining that the defendant \"may offer evidence that Powell killed Hydell. He may not, however, offer evidence concerning that Powell was arrested and prosecuted for the murder.\"); United States v. Rodriguez, 582 F. Supp. 2d 486, 487 (S.D.N.Y. 2008) (to avoid confusing jurors, defendants precluded from introducing evidence about dismissals of prior charges against them in trial for the same conduct four years later); United States v. Hill, No. 12 Cr. 214 (KAM), 2014 WL 198813, at *1-2 (E.D.N.Y. Jan. 14, 2014) (precluding evidence or cross examination of a detective regarding the Kings County District Attorney's Office decision to question but not charge the defendant for a murder that occurred in 1997 but was only indicted fifteen years later because such testimony is hearsay, irrelevant, and confusing); United States v. Watts, 934 F. Supp. 2d 451, 484-486 (E.D.N.Y. 2013) (precluding the defendant from eliciting basis of decision not to charge a possible co-conspirator); United States v. Carneglia, No. 08 Cr. 76 (JBW), 2009 WL 185725, at *1 (E.D.N.Y. Jan. 27, 2009) (\"[T]he government's charging decisions are not proper subjects for cross-examination and argument.' Evidence related to the government's charging decisions may be excluded at trial based on lack of relevance.\" (quoting United States v. Re, 401 F.3d 828, 832 (7th Cir. 2005))).8",
      "position": "main body"
    },
    {
      "type": "printed",
      "content": "8 Although there is no per se bar to admission of charging decisions, the Second Circuit has permitted such evidence under narrow circumstances not present here, as discussed in greater detail below. See infra pp. 25-26 (discussing United States v. White, 692 F.3d 235, 246 (2d Cir. 2012)).",
      "position": "main body"
    },
    {
      "type": "printed",
      "content": "23",
      "position": "footer"
    },
    {
      "type": "printed",
      "content": "DOJ-OGR-00005417",
      "position": "footer"
    }
  ],
  "entities": {
    "people": [
      "Powell",
      "Hydell",
      "Boyle",
      "Rodriguez",
      "Hill",
      "Watts",
      "Carneglia",
      "Re",
      "White"
    ],
    "organizations": [
      "Kings County District Attorney's Office",
      "Second Circuit",
      "Seventh Circuit"
    ],
    "locations": [
      "S.D.N.Y.",
      "E.D.N.Y."
    ],
    "dates": [
      "Dec. 23, 2009",
      "Jan. 14, 2014",
      "Jan. 27, 2009",
      "2005",
      "2012",
      "10/29/21"
    ],
    "reference_numbers": [
      "Case 1:20-cr-00330-PAE",
      "Document 380",
      "No. 08 Cr. 523",
      "No. 12 Cr. 214",
      "No. 08 Cr. 76",
      "DOJ-OGR-00005417"
    ]
  },
  "additional_notes": "The document appears to be a court filing discussing the admissibility of certain evidence related to charging decisions in a criminal trial. The text is printed and there are no visible stamps or handwritten annotations."
}