{
  "document_metadata": {
    "page_number": "27",
    "document_number": "367",
    "date": "10/22/21",
    "document_type": "Juror Questionnaire",
    "has_handwriting": false,
    "has_stamps": false
  },
  "full_text": "Case 1:20-cr-00330-PAE Document 367 Filed 10/22/21 Page 27 of 35 Juror ID: 26. Have you, either through any experience you have had or anything you have seen or read, developed any bias or prejudice or other feelings for or against the United States Department of Justice, the United States Attorney's Office for the Southern District of New York, the FBI, or the NYPD? Yes No If yes, please explain: 27. Do you have any opinion of the U.S. Attorney's Office for the Southern District of New York or the U.S. Attorney Damian Williams that might make it difficult for you to be a fair and impartial juror in this case? Yes No If yes, please explain: 28. Do you have any opinions about prosecutors or criminal defense attorneys generally that might make it difficult for you to be a fair and impartial juror in this case? Yes No If yes, please explain: -27- DOJ-OGR-00005349",
  "text_blocks": [
    {
      "type": "printed",
      "content": "Case 1:20-cr-00330-PAE Document 367 Filed 10/22/21 Page 27 of 35",
      "position": "header"
    },
    {
      "type": "printed",
      "content": "Juror ID:",
      "position": "top"
    },
    {
      "type": "printed",
      "content": "26. Have you, either through any experience you have had or anything you have seen or read, developed any bias or prejudice or other feelings for or against the United States Department of Justice, the United States Attorney's Office for the Southern District of New York, the FBI, or the NYPD? Yes No If yes, please explain:",
      "position": "middle"
    },
    {
      "type": "printed",
      "content": "27. Do you have any opinion of the U.S. Attorney's Office for the Southern District of New York or the U.S. Attorney Damian Williams that might make it difficult for you to be a fair and impartial juror in this case? Yes No If yes, please explain:",
      "position": "middle"
    },
    {
      "type": "printed",
      "content": "28. Do you have any opinions about prosecutors or criminal defense attorneys generally that might make it difficult for you to be a fair and impartial juror in this case? Yes No If yes, please explain:",
      "position": "middle"
    },
    {
      "type": "printed",
      "content": "-27-",
      "position": "footer"
    },
    {
      "type": "printed",
      "content": "DOJ-OGR-00005349",
      "position": "footer"
    }
  ],
  "entities": {
    "people": [
      "Damian Williams"
    ],
    "organizations": [
      "United States Department of Justice",
      "United States Attorney's Office for the Southern District of New York",
      "FBI",
      "NYPD"
    ],
    "locations": [
      "New York"
    ],
    "dates": [
      "10/22/21"
    ],
    "reference_numbers": [
      "1:20-cr-00330-PAE",
      "367",
      "DOJ-OGR-00005349"
    ]
  },
  "additional_notes": "The document appears to be a juror questionnaire from a court case. It contains a series of questions related to potential biases or prejudices that could impact a juror's ability to be fair and impartial. The document is well-formatted and legible, with no visible redactions or damage."
}