{
  "document_metadata": {
    "page_number": "27 of 30",
    "document_number": "204-12",
    "date": "04/16/21",
    "document_type": "court document",
    "has_handwriting": false,
    "has_stamps": false
  },
  "full_text": "Case 1:20-cr-00330-PAE Document 204-12 Filed 04/16/21 Page 27 of 30\n\nBLDS, LLC\nPUBLICATIONS (Continued)\nBooks (Continued)\n5. B. Siskin and R. Johnson, Elementary Statistics: A First Course, Duxbury Press, 1982.\n6. B. Siskin and R. Johnson, Elementary Business Statistics, Duxbury Press, 1979 2nd Edition, 1985\n7. B. Siskin, Encyclopedia of Management, McGraw Hill, 1979. (Ed. Les Bechtel).\n8. B. Siskin and R. Johnson, Quantitative Techniques for Business Decisions, Prentice Hall, 1976.\n\nArticles\n1. B. Siskin and D. Griffin, \"Litigating Employment Discrimination & Sexual Harassment Claims,\" Litigation Handbook Series, 2002.\n2. B. Siskin, H. Carter, V. Lee, G. Page, M. Parker, R.G. Ford, G. Swartzman, S. Kress, S. Singer and D.M. Fry, \"The 1986 Apex Houston Oil Spill in Central California: Seabird Mortality and Population Impacts, Injury Assessments, Litigation Process, and Initial Restoration Efforts,\" Marine Ornithology, 2002.\n3. B. Siskin, Utilizing Statistics in Discrimination Cases, Litigation Handbook Series, 2001.\n4. B. Siskin, B. Sullivan, J. Staller, and E. Hull, Defending and Proving Damages in Employment Discrimination Cases, Litigation Handbook Series, 2000.\n5. B. Siskin, \"Litigating Employment Discrimination Cases,\" Litigation Handbook Series, 1998.\n6. B. Siskin and D. Kahn, \"Litigating Employment Discrimination Cases,\" Litigation Handbook Series, 1997.\n7. B. Siskin, R. DuPont, D. Griffin, S. Shiraki, and E. Katze \"Random Workplace Drug Testing. Does It Primarily Identify Casual or Regular Drug Users?,\" Employment Testing Law & Policy Reporter, Vol. 4, Number One, 1995.\n8. B. Siskin, R. DuPont, D. Griffin, S. Shiraki, and E. Katze \"Random Drug Tests at Work: The Probability of Identifying Frequent and Infrequent Users of Illicit Drugs,\" Journal of Addictive Diseases, Vol. 14, Number 3, 1995.\n9. B Siskin, J. Staller, B. Sullivan and L. Freifelder, \"Litigating Employment Discrimination Cases,\" Litigation Course Handbook Series, 1995.\n10. B. Siskin, \"Comparing the Role of Statistics In Lending and Employment Cases,\" Fair Lending Analysis: A Compendium of Essays on the Use of Statistics, American Bankers Association, 1995.\n11. B. Siskin, \"Relationship Between Performance and Banding,\" Human Performance, Vol. 8, No. 3, July 1995.\n12. B. Siskin, \"Statistical Issues in Litigating Employment Discrimination Claims,\" Federal Publications, 1993.\n13. B. Siskin, \"Use of Statistical Models to Provide Statistical Evidence of Discrimination in the Treatment of Mortgage Loan Applicants: A Study of One Lending Institution,\" Discrimination and Mortgage Lending Research and Enforcement Conference Department of Housing and Urban Development, May 1993.\n\n12/4/2020 www.bldsllic.com Page 3 of 4 DOJ-OGR-00003647",
  "text_blocks": [
    {
      "type": "printed",
      "content": "Case 1:20-cr-00330-PAE Document 204-12 Filed 04/16/21 Page 27 of 30",
      "position": "header"
    },
    {
      "type": "printed",
      "content": "BLDS, LLC\nPUBLICATIONS (Continued)\nBooks (Continued)\n5. B. Siskin and R. Johnson, Elementary Statistics: A First Course, Duxbury Press, 1982.\n6. B. Siskin and R. Johnson, Elementary Business Statistics, Duxbury Press, 1979 2nd Edition, 1985\n7. B. Siskin, Encyclopedia of Management, McGraw Hill, 1979. (Ed. Les Bechtel).\n8. B. Siskin and R. Johnson, Quantitative Techniques for Business Decisions, Prentice Hall, 1976.",
      "position": "top"
    },
    {
      "type": "printed",
      "content": "Articles\n1. B. Siskin and D. Griffin, \"Litigating Employment Discrimination & Sexual Harassment Claims,\" Litigation Handbook Series, 2002.\n2. B. Siskin, H. Carter, V. Lee, G. Page, M. Parker, R.G. Ford, G. Swartzman, S. Kress, S. Singer and D.M. Fry, \"The 1986 Apex Houston Oil Spill in Central California: Seabird Mortality and Population Impacts, Injury Assessments, Litigation Process, and Initial Restoration Efforts,\" Marine Ornithology, 2002.\n3. B. Siskin, Utilizing Statistics in Discrimination Cases, Litigation Handbook Series, 2001.\n4. B. Siskin, B. Sullivan, J. Staller, and E. Hull, Defending and Proving Damages in Employment Discrimination Cases, Litigation Handbook Series, 2000.\n5. B. Siskin, \"Litigating Employment Discrimination Cases,\" Litigation Handbook Series, 1998.\n6. B. Siskin and D. Kahn, \"Litigating Employment Discrimination Cases,\" Litigation Handbook Series, 1997.\n7. B. Siskin, R. DuPont, D. Griffin, S. Shiraki, and E. Katze \"Random Workplace Drug Testing. Does It Primarily Identify Casual or Regular Drug Users?,\" Employment Testing Law & Policy Reporter, Vol. 4, Number One, 1995.\n8. B. Siskin, R. DuPont, D. Griffin, S. Shiraki, and E. Katze \"Random Drug Tests at Work: The Probability of Identifying Frequent and Infrequent Users of Illicit Drugs,\" Journal of Addictive Diseases, Vol. 14, Number 3, 1995.\n9. B Siskin, J. Staller, B. Sullivan and L. Freifelder, \"Litigating Employment Discrimination Cases,\" Litigation Course Handbook Series, 1995.\n10. B. Siskin, \"Comparing the Role of Statistics In Lending and Employment Cases,\" Fair Lending Analysis: A Compendium of Essays on the Use of Statistics, American Bankers Association, 1995.\n11. B. Siskin, \"Relationship Between Performance and Banding,\" Human Performance, Vol. 8, No. 3, July 1995.\n12. B. Siskin, \"Statistical Issues in Litigating Employment Discrimination Claims,\" Federal Publications, 1993.\n13. B. Siskin, \"Use of Statistical Models to Provide Statistical Evidence of Discrimination in the Treatment of Mortgage Loan Applicants: A Study of One Lending Institution,\" Discrimination and Mortgage Lending Research and Enforcement Conference Department of Housing and Urban Development, May 1993.",
      "position": "middle"
    },
    {
      "type": "printed",
      "content": "12/4/2020 www.bldsllic.com Page 3 of 4 DOJ-OGR-00003647",
      "position": "footer"
    }
  ],
  "entities": {
    "people": [
      "B. Siskin",
      "R. Johnson",
      "Les Bechtel",
      "D. Griffin",
      "H. Carter",
      "V. Lee",
      "G. Page",
      "M. Parker",
      "R.G. Ford",
      "G. Swartzman",
      "S. Kress",
      "S. Singer",
      "D.M. Fry",
      "B. Sullivan",
      "J. Staller",
      "E. Hull",
      "D. Kahn",
      "R. DuPont",
      "S. Shiraki",
      "E. Katze",
      "L. Freifelder"
    ],
    "organizations": [
      "BLDS, LLC",
      "Duxbury Press",
      "McGraw Hill",
      "Prentice Hall",
      "Litigation Handbook Series",
      "Marine Ornithology",
      "American Bankers Association",
      "Federal Publications",
      "Department of Housing and Urban Development"
    ],
    "locations": [
      "California"
    ],
    "dates": [
      "1982",
      "1979",
      "1985",
      "1976",
      "2002",
      "2001",
      "2000",
      "1998",
      "1997",
      "1995",
      "1993",
      "04/16/21",
      "12/4/2020"
    ],
    "reference_numbers": [
      "1:20-cr-00330-PAE",
      "204-12",
      "DOJ-OGR-00003647"
    ]
  },
  "additional_notes": "The document appears to be a court filing related to a case involving BLDS, LLC. The page contains a list of publications, including books and articles, authored by B. Siskin and others. The document is well-formatted and legible, with no visible redactions or damage."
}