{
  "document_metadata": {
    "page_number": "10",
    "document_number": "208-1",
    "date": "04/16/2015",
    "document_type": "Court Document",
    "has_handwriting": true,
    "has_stamps": false
  },
  "full_text": "Case 1:20-cr-00330-PAE Document 208-1 Filed 04/16/21 Page 10 of 10\nagrees, and it concludes that justice does not require amending the petition this late in the proceedings.\n\nIII. Conclusion\nAccordingly, it is hereby ORDERED AND ADJUDGED as follows: the Rule 21 Motion (DE 280) is DENIED; the Rule 15 Motion (DE 311) is DENIED; Intervenor Dershowitz's Motion for Limited Intervention (DE 282) and Motion for Leave to File Supplemental Reply in Support of Motion for Limited Intervention (DE 317) are DENIED AS MOOT; Petitioners' Motion to Seal (DE 292) is DENIED AS MOOT; the following materials are hereby STRICKEN from the record:\n- DE 279, in its entirety.\n- DE 280, all sentences between the following sentences: \"The Government then concealed from Jane Doe #3 the existence of its NPA from Jane Doe #3, in violation of her rights under the CVRA\" (DE 280 at 3); and \"The Government was well aware of Jane Doc #3 when it was negotiating the NPA, as it listed her as a victim in the attachment to the NPA\" (DE 280 at 6).\n- DE 291-1, paragraphs 4, 5, 7, 11, 13, 15, 19 through 53, and 59.\n- DE 310-1, paragraphs 7 through 12, 16, 39, and 49.\n- DE 293, in its entirety.\nDONE AND ORDERED in chambers at West Palm Beach, Palm Beach County, Florida, this 6th day of April, 2015.\nKENNETH A. MARRA\nUnited States District Judge\nGIUFFRE002853\nDOJ-OGR-00003735",
  "text_blocks": [
    {
      "type": "printed",
      "content": "Case 1:20-cr-00330-PAE Document 208-1 Filed 04/16/21 Page 10 of 10",
      "position": "header"
    },
    {
      "type": "printed",
      "content": "agrees, and it concludes that justice does not require amending the petition this late in the proceedings.",
      "position": "top"
    },
    {
      "type": "printed",
      "content": "III. Conclusion",
      "position": "top"
    },
    {
      "type": "printed",
      "content": "Accordingly, it is hereby ORDERED AND ADJUDGED as follows: the Rule 21 Motion (DE 280) is DENIED; the Rule 15 Motion (DE 311) is DENIED; Intervenor Dershowitz's Motion for Limited Intervention (DE 282) and Motion for Leave to File Supplemental Reply in Support of Motion for Limited Intervention (DE 317) are DENIED AS MOOT; Petitioners' Motion to Seal (DE 292) is DENIED AS MOOT; the following materials are hereby STRICKEN from the record:",
      "position": "middle"
    },
    {
      "type": "printed",
      "content": "- DE 279, in its entirety.\n- DE 280, all sentences between the following sentences: \"The Government then concealed from Jane Doe #3 the existence of its NPA from Jane Doe #3, in violation of her rights under the CVRA\" (DE 280 at 3); and \"The Government was well aware of Jane Doc #3 when it was negotiating the NPA, as it listed her as a victim in the attachment to the NPA\" (DE 280 at 6).\n- DE 291-1, paragraphs 4, 5, 7, 11, 13, 15, 19 through 53, and 59.\n- DE 310-1, paragraphs 7 through 12, 16, 39, and 49.\n- DE 293, in its entirety.",
      "position": "middle"
    },
    {
      "type": "printed",
      "content": "DONE AND ORDERED in chambers at West Palm Beach, Palm Beach County, Florida, this 6th day of April, 2015.",
      "position": "bottom"
    },
    {
      "type": "handwritten",
      "content": "",
      "position": "bottom"
    },
    {
      "type": "printed",
      "content": "KENNETH A. MARRA\nUnited States District Judge",
      "position": "bottom"
    },
    {
      "type": "printed",
      "content": "GIUFFRE002853\nDOJ-OGR-00003735",
      "position": "footer"
    }
  ],
  "entities": {
    "people": [
      "Kenneth A. Marra",
      "Dershowitz",
      "Jane Doe #3"
    ],
    "organizations": [
      "United States District Court"
    ],
    "locations": [
      "West Palm Beach",
      "Palm Beach County",
      "Florida"
    ],
    "dates": [
      "April 6, 2015",
      "04/16/21"
    ],
    "reference_numbers": [
      "DE 280",
      "DE 311",
      "DE 282",
      "DE 317",
      "DE 292",
      "DE 279",
      "DE 291-1",
      "DE 310-1",
      "DE 293",
      "GIUFFRE002853",
      "DOJ-OGR-00003735",
      "Case 1:20-cr-00330-PAE",
      "Document 208-1"
    ]
  },
  "additional_notes": "The document appears to be a court order from the United States District Court for the Southern District of Florida. It is signed by Judge Kenneth A. Marra and dated April 6, 2015. The document contains various redactions and references to other court documents."
}