{
  "document_metadata": {
    "page_number": "11",
    "document_number": "1",
    "date": "07/02/20",
    "document_type": "court document",
    "has_handwriting": false,
    "has_stamps": false
  },
  "full_text": "Case 1:20-mj-0132-AJ Document 1 Filed 07/02/20 Page 11 of 193\nabuse of minor victims by Jeffrey Epstein, including some of the specific events and acts of abuse detailed above.\n\nSTATUTORY ALLEGATIONS\n\n9. From at least in or about 1994, up to and including in or about 1997, in the Southern District of New York and elsewhere, GHISLAINE MAXWELL, the defendant, Jeffrey Epstein, and others known and unknown, willfully and knowingly did combine, conspire, confederate, and agree together and with each other to commit an offense against the United States, to wit, enticement, in violation of Title 18, United States Code, Section 2422.\n\n10. It was a part and object of the conspiracy that GHISLAINE MAXWELL, the defendant, Jeffrey Epstein, and others known and unknown, would and did knowingly persuade, induce, entice, and coerce one and more individuals to travel in interstate and foreign commerce, to engage in sexual activity for which a person can be charged with a criminal offense, in violation of Title 18, United States Code, Section 2422.\n\nOvert Acts\n\n11. In furtherance of the conspiracy and to effect the illegal object thereof, the following overt acts, among others, were committed in the Southern District of New York and elsewhere:\n\n10\nDOJ-OGR-00019214",
  "text_blocks": [
    {
      "type": "printed",
      "content": "Case 1:20-mj-0132-AJ Document 1 Filed 07/02/20 Page 11 of 193",
      "position": "header"
    },
    {
      "type": "printed",
      "content": "abuse of minor victims by Jeffrey Epstein, including some of the specific events and acts of abuse detailed above.",
      "position": "top"
    },
    {
      "type": "printed",
      "content": "STATUTORY ALLEGATIONS",
      "position": "top"
    },
    {
      "type": "printed",
      "content": "9. From at least in or about 1994, up to and including in or about 1997, in the Southern District of New York and elsewhere, GHISLAINE MAXWELL, the defendant, Jeffrey Epstein, and others known and unknown, willfully and knowingly did combine, conspire, confederate, and agree together and with each other to commit an offense against the United States, to wit, enticement, in violation of Title 18, United States Code, Section 2422.",
      "position": "middle"
    },
    {
      "type": "printed",
      "content": "10. It was a part and object of the conspiracy that GHISLAINE MAXWELL, the defendant, Jeffrey Epstein, and others known and unknown, would and did knowingly persuade, induce, entice, and coerce one and more individuals to travel in interstate and foreign commerce, to engage in sexual activity for which a person can be charged with a criminal offense, in violation of Title 18, United States Code, Section 2422.",
      "position": "middle"
    },
    {
      "type": "printed",
      "content": "Overt Acts",
      "position": "middle"
    },
    {
      "type": "printed",
      "content": "11. In furtherance of the conspiracy and to effect the illegal object thereof, the following overt acts, among others, were committed in the Southern District of New York and elsewhere:",
      "position": "bottom"
    },
    {
      "type": "printed",
      "content": "10",
      "position": "footer"
    },
    {
      "type": "printed",
      "content": "DOJ-OGR-00019214",
      "position": "footer"
    }
  ],
  "entities": {
    "people": [
      "Jeffrey Epstein",
      "GHISLAINE MAXWELL"
    ],
    "organizations": [
      "United States"
    ],
    "locations": [
      "New York",
      "Southern District of New York"
    ],
    "dates": [
      "1994",
      "1997",
      "07/02/20"
    ],
    "reference_numbers": [
      "1:20-mj-0132-AJ",
      "Document 1",
      "DOJ-OGR-00019214"
    ]
  },
  "additional_notes": "The document appears to be a court filing related to the case against Ghislaine Maxwell. The text is typed, and there are no visible handwritten notes or stamps. The document is page 11 of 193."
}