{
  "document_metadata": {
    "page_number": "140",
    "document_number": "753",
    "date": "08/10/22",
    "document_type": "court transcript",
    "has_handwriting": true,
    "has_stamps": false
  },
  "full_text": "Case 1:20-cr-00330-PAE Document 753 Filed 08/10/22 Page 140 of 264 1566 LC7Cmax4 Carolyn - cross she approached me. Q. Did Virginia explain to you that you could make $300 by providing a man in Palm Beach with a massage? A. She told me that we were going to be meeting a friend of hers in Palm Beach. Q. And the friend you were meeting was older; is that correct? A. Yes. Q. Now, when Roberts approached you about making this $500, Ms. Maxwell, Ghislaine Maxwell was not there; correct? A. There was no $500. Q. $300. Ms. Maxwell was not there; correct? A. No, it was me and Virginia. Q. And Ms. Maxwell was not involved in this conversation that you had with Ms. Roberts about making this $300; correct? A. Correct. Q. During your conversation with Ms. Roberts, she told you that you could make this $300 by massaging this older man; is that right? A. No. She said we were going to meet one of her friends and -- I'm sorry. Repeat the question. Q. She told you that you could make money by massaging an older man; is that correct? MS. COMEY: Your Honor, can we just classify if Mr. Pagliuca is asking her about a document or her memory as she sits here today. SOUTHERN DISTRICT REPORTERS, P.C. (212) 805-0300 DOJ-OGR-00018738",
  "text_blocks": [
    {
      "type": "printed",
      "content": "Case 1:20-cr-00330-PAE Document 753 Filed 08/10/22 Page 140 of 264 1566",
      "position": "header"
    },
    {
      "type": "handwritten",
      "content": "LC7Cmax4 Carolyn - cross",
      "position": "header"
    },
    {
      "type": "printed",
      "content": "she approached me. Q. Did Virginia explain to you that you could make $300 by providing a man in Palm Beach with a massage? A. She told me that we were going to be meeting a friend of hers in Palm Beach. Q. And the friend you were meeting was older; is that correct? A. Yes. Q. Now, when Roberts approached you about making this $500, Ms. Maxwell, Ghislaine Maxwell was not there; correct? A. There was no $500. Q. $300. Ms. Maxwell was not there; correct? A. No, it was me and Virginia. Q. And Ms. Maxwell was not involved in this conversation that you had with Ms. Roberts about making this $300; correct? A. Correct. Q. During your conversation with Ms. Roberts, she told you that you could make this $300 by massaging this older man; is that right? A. No. She said we were going to meet one of her friends and -- I'm sorry. Repeat the question. Q. She told you that you could make money by massaging an older man; is that correct? MS. COMEY: Your Honor, can we just classify if Mr. Pagliuca is asking her about a document or her memory as she sits here today.",
      "position": "main"
    },
    {
      "type": "printed",
      "content": "SOUTHERN DISTRICT REPORTERS, P.C. (212) 805-0300",
      "position": "footer"
    },
    {
      "type": "printed",
      "content": "DOJ-OGR-00018738",
      "position": "footer"
    }
  ],
  "entities": {
    "people": [
      "Virginia",
      "Ghislaine Maxwell",
      "Roberts",
      "Mr. Pagliuca",
      "Ms. Comey"
    ],
    "organizations": [
      "SOUTHERN DISTRICT REPORTERS, P.C."
    ],
    "locations": [
      "Palm Beach"
    ],
    "dates": [
      "08/10/22"
    ],
    "reference_numbers": [
      "1:20-cr-00330-PAE",
      "753",
      "DOJ-OGR-00018738"
    ]
  },
  "additional_notes": "The document appears to be a court transcript with a mix of printed and handwritten text. The header contains the case number, document number, and filing date. The main content is a Q&A session between a lawyer and a witness. The footer contains the name and contact information of the reporting agency and a reference number."
}