{
  "document_metadata": {
    "page_number": "1",
    "document_number": "3-1",
    "date": "01/12/2021",
    "document_type": "Notice of Record on Appeal Filed",
    "has_handwriting": true,
    "has_stamps": false
  },
  "full_text": "Case 21-58, Document 3-1, 01/12/2021, 3011691, Page1 of 1\nUnited States Court of Appeals for the Second Circuit\nThurgood Marshall U.S. Courthouse\n40 Foley Square\nNew York, NY 10007\nDEBRA ANN LIVINGSTON\nCHIEF JUDGE\nCATHERINE O'HAGAN WOLFE\nCLERK OF COURT\nDate: January 12, 2021\nDocket #: 21-58\nDC Docket #: 1:20-cr-330-1\nShort Title: United States of America v. Maxwell\nDC Court: SDNY (NEW YORK CITY)\nDC Judge: Nathan\nNOTICE OF RECORD ON APPEAL FILED\nIn the above referenced case the document indicated below has been filed in the Court.\n___ Record on Appeal - Certified List\n___ Record on Appeal - CD ROM\n___ Record on Appeal - Paper Documents\nX___ Record on Appeal - Electronic Index\n___ Record on Appeal - Paper Index\nInquiries regarding this case may be directed to 212-857-8577.\nDOJ-OGR-00019715",
  "text_blocks": [
    {
      "type": "printed",
      "content": "Case 21-58, Document 3-1, 01/12/2021, 3011691, Page1 of 1",
      "position": "header"
    },
    {
      "type": "printed",
      "content": "United States Court of Appeals for the Second Circuit\nThurgood Marshall U.S. Courthouse\n40 Foley Square\nNew York, NY 10007",
      "position": "header"
    },
    {
      "type": "printed",
      "content": "DEBRA ANN LIVINGSTON\nCHIEF JUDGE\nCATHERINE O'HAGAN WOLFE\nCLERK OF COURT",
      "position": "middle"
    },
    {
      "type": "printed",
      "content": "Date: January 12, 2021\nDocket #: 21-58\nDC Docket #: 1:20-cr-330-1\nShort Title: United States of America v. Maxwell\nDC Court: SDNY (NEW YORK CITY)\nDC Judge: Nathan",
      "position": "middle"
    },
    {
      "type": "printed",
      "content": "NOTICE OF RECORD ON APPEAL FILED",
      "position": "middle"
    },
    {
      "type": "printed",
      "content": "In the above referenced case the document indicated below has been filed in the Court.",
      "position": "middle"
    },
    {
      "type": "handwritten",
      "content": "___ Record on Appeal - Certified List\n___ Record on Appeal - CD ROM\n___ Record on Appeal - Paper Documents\nX___ Record on Appeal - Electronic Index\n___ Record on Appeal - Paper Index",
      "position": "middle"
    },
    {
      "type": "printed",
      "content": "Inquiries regarding this case may be directed to 212-857-8577.",
      "position": "middle"
    },
    {
      "type": "printed",
      "content": "DOJ-OGR-00019715",
      "position": "footer"
    }
  ],
  "entities": {
    "people": [
      "Debra Ann Livingston",
      "Catherine O'Hagan Wolfe",
      "Nathan",
      "Maxwell"
    ],
    "organizations": [
      "United States Court of Appeals for the Second Circuit",
      "United States of America"
    ],
    "locations": [
      "New York",
      "New York City"
    ],
    "dates": [
      "January 12, 2021",
      "01/12/2021"
    ],
    "reference_numbers": [
      "21-58",
      "1:20-cr-330-1",
      "3011691",
      "212-857-8577",
      "DOJ-OGR-00019715"
    ]
  },
  "additional_notes": "The document appears to be a formal court filing with a mix of printed and handwritten content. The handwritten content is limited to checkboxes indicating the type of record on appeal filed."
}