{
  "document_metadata": {
    "page_number": "204",
    "document_number": "745",
    "date": "08/10/22",
    "document_type": "court transcript",
    "has_handwriting": false,
    "has_stamps": false
  },
  "full_text": "Case 1:20-cr-00330-PAE Document 745 Filed 08/10/22 Page 204 of 264 615 LC1Qmax6 Jane - Redirect 1 A. I'm sorry, I don't know what that means. 2 Q. Do you remember being shown a document on cross-examination 3 and being asked about whether that was your application to the 4 Professional Children's School? 5 A. Yes. 6 Q. And did you recognize that document as your application to 7 the Professional Children's School? 8 A. No. 9 Q. Do you recognize the handwriting on that document? 10 A. Is it here? Can I see it or -- 11 Q. That's all right. I can move on. 12 A. Okay. 13 Q. You were asked some questions on cross-examination about 14 your career as an actor. Do you remember being asked about 15 that? 16 A. Yes. 17 Q. Do you know the difference between acting on television and 18 testifying in court? 19 A. Yes. 20 Q. What's the difference? 21 A. Acting on television is not real, and testifying in court 22 is real, is the truth. 23 Q. Are you acting here today? 24 A. No. 25 Q. What are you here to do? SOUTHERN DISTRICT REPORTERS, P.C. (212) 805-0300 DOJ-OGR-00017813",
  "text_blocks": [
    {
      "type": "printed",
      "content": "Case 1:20-cr-00330-PAE Document 745 Filed 08/10/22 Page 204 of 264 615 LC1Qmax6 Jane - Redirect",
      "position": "header"
    },
    {
      "type": "printed",
      "content": "1 A. I'm sorry, I don't know what that means. 2 Q. Do you remember being shown a document on cross-examination 3 and being asked about whether that was your application to the 4 Professional Children's School? 5 A. Yes. 6 Q. And did you recognize that document as your application to 7 the Professional Children's School? 8 A. No. 9 Q. Do you recognize the handwriting on that document? 10 A. Is it here? Can I see it or -- 11 Q. That's all right. I can move on. 12 A. Okay. 13 Q. You were asked some questions on cross-examination about 14 your career as an actor. Do you remember being asked about 15 that? 16 A. Yes. 17 Q. Do you know the difference between acting on television and 18 testifying in court? 19 A. Yes. 20 Q. What's the difference? 21 A. Acting on television is not real, and testifying in court 22 is real, is the truth. 23 Q. Are you acting here today? 24 A. No. 25 Q. What are you here to do?",
      "position": "main"
    },
    {
      "type": "printed",
      "content": "SOUTHERN DISTRICT REPORTERS, P.C. (212) 805-0300",
      "position": "footer"
    },
    {
      "type": "printed",
      "content": "DOJ-OGR-00017813",
      "position": "footer"
    }
  ],
  "entities": {
    "people": [
      "Jane"
    ],
    "organizations": [
      "Professional Children's School",
      "SOUTHERN DISTRICT REPORTERS, P.C."
    ],
    "locations": [],
    "dates": [
      "08/10/22"
    ],
    "reference_numbers": [
      "1:20-cr-00330-PAE",
      "745",
      "DOJ-OGR-00017813"
    ]
  },
  "additional_notes": "The document appears to be a court transcript with a clear and legible format. There are no visible redactions or damage."
}