{
  "document_metadata": {
    "page_number": "135",
    "document_number": "749",
    "date": "08/10/22",
    "document_type": "Court Transcript",
    "has_handwriting": false,
    "has_stamps": false
  },
  "full_text": "Case 1:20-cr-00330-PAE Document 749 Filed 08/10/22 Page 135 of 236 1039 LC3KMAX4 Parkinson - Direct 1 GREGORY PARKINSON, resumed. 2 DIRECT EXAMINATION CONTINUED 3 BY MS. COMEY: 4 Q. Good afternoon, Mr. Parkinson. 5 A. Good afternoon, ma'am. 6 Q. I believe in front of you is an item marked for 7 identification as Government Exhibit 296. 8 Do you see that? In front of you to the left. 9 A. Oh. Yes. 10 Q. Do you see that disk right there? 11 A. I do. 12 Q. Do you recognize that? 13 A. I do. 14 Q. What is it? 15 A. It is a compact disk - I'm going to call it a CD - which 16 has Government Exhibit label of 296. 17 Q. Did you review the contents of that CD before coming to 18 testify here today? 19 A. Yes, I did. 20 Q. What is on that CD? 21 A. This is a CD of the reading of the search warrant, and then 22 the search of the building for other live persons, and then the 23 follow-up conclusion of the search process, showing there was 24 no damage to the residence. 25 Q. In other words, does it contain your walk-through video of SOUTHERN DISTRICT REPORTERS, P.C. (212) 805-0300 DOJ-OGR-00018236",
  "text_blocks": [
    {
      "type": "printed",
      "content": "Case 1:20-cr-00330-PAE Document 749 Filed 08/10/22 Page 135 of 236 1039",
      "position": "header"
    },
    {
      "type": "printed",
      "content": "LC3KMAX4 Parkinson - Direct",
      "position": "header"
    },
    {
      "type": "printed",
      "content": "1 GREGORY PARKINSON, resumed. 2 DIRECT EXAMINATION CONTINUED 3 BY MS. COMEY: 4 Q. Good afternoon, Mr. Parkinson. 5 A. Good afternoon, ma'am. 6 Q. I believe in front of you is an item marked for 7 identification as Government Exhibit 296. 8 Do you see that? In front of you to the left. 9 A. Oh. Yes. 10 Q. Do you see that disk right there? 11 A. I do. 12 Q. Do you recognize that? 13 A. I do. 14 Q. What is it? 15 A. It is a compact disk - I'm going to call it a CD - which 16 has Government Exhibit label of 296. 17 Q. Did you review the contents of that CD before coming to 18 testify here today? 19 A. Yes, I did. 20 Q. What is on that CD? 21 A. This is a CD of the reading of the search warrant, and then 22 the search of the building for other live persons, and then the 23 follow-up conclusion of the search process, showing there was 24 no damage to the residence. 25 Q. In other words, does it contain your walk-through video of",
      "position": "main"
    },
    {
      "type": "printed",
      "content": "SOUTHERN DISTRICT REPORTERS, P.C. (212) 805-0300",
      "position": "footer"
    },
    {
      "type": "printed",
      "content": "DOJ-OGR-00018236",
      "position": "footer"
    }
  ],
  "entities": {
    "people": [
      "GREGORY PARKINSON",
      "MS. COMEY"
    ],
    "organizations": [
      "SOUTHERN DISTRICT REPORTERS, P.C."
    ],
    "locations": [],
    "dates": [
      "08/10/22"
    ],
    "reference_numbers": [
      "1:20-cr-00330-PAE",
      "749",
      "296",
      "DOJ-OGR-00018236"
    ]
  },
  "additional_notes": "The document appears to be a court transcript with clear and legible text. There are no visible redactions or damage."
}