{
  "document_metadata": {
    "page_number": "123",
    "document_number": "753",
    "date": "08/10/22",
    "document_type": "court transcript",
    "has_handwriting": false,
    "has_stamps": true
  },
  "full_text": "Case 1:20-cr-00330-PAE Document 753 Filed 08/10/22 Page 123 of 264 1549\nLC7Cmax4 Carolyn - direct\n1 A. Yes, I did.\n2 Q. About how many times?\n3 A. Well, I had gone there while I was pregnant --\n4 Q. I'm asking about after you had the baby.\n5 A. Okay. I had gone back there more than, like, four or five times, and he asked me if I had any younger friends and I said no. And that's when I realized I was too old.\n6 \n7 \n8 Q. Why did you go back after you had your baby?\n9 A. Because I needed the money because I was so young when I had my son and I needed the money to buy stuff for him.\n10 \n11 Q. Why did you stop going to Jeffrey Epstein's house?\n12 A. Because I became too old.\n13 Q. How old were you?\n14 A. 18.\n15 MS. COMEY: May I have a moment, your Honor?\n16 THE COURT: Yes.\n17 Q. Carolyn?\n18 A. Yes.\n19 Q. After you stopped seeing Jeffrey Epstein, did you continue using drugs?\n20 \n21 A. Yes.\n22 Q. What drugs did you use?\n23 A. Cocaine and pain pills.\n24 Q. Were you addicted to both of those drugs?\n25 A. Yes.\nSOUTHERN DISTRICT REPORTERS, P.C. (212) 805-0300\nDOJ-OGR-00018721",
  "text_blocks": [
    {
      "type": "printed",
      "content": "Case 1:20-cr-00330-PAE Document 753 Filed 08/10/22 Page 123 of 264 1549",
      "position": "header"
    },
    {
      "type": "printed",
      "content": "LC7Cmax4 Carolyn - direct",
      "position": "header"
    },
    {
      "type": "printed",
      "content": "1 A. Yes, I did.\n2 Q. About how many times?\n3 A. Well, I had gone there while I was pregnant --\n4 Q. I'm asking about after you had the baby.\n5 A. Okay. I had gone back there more than, like, four or five times, and he asked me if I had any younger friends and I said no. And that's when I realized I was too old.\n8 Q. Why did you go back after you had your baby?\n9 A. Because I needed the money because I was so young when I had my son and I needed the money to buy stuff for him.\n11 Q. Why did you stop going to Jeffrey Epstein's house?\n12 A. Because I became too old.\n13 Q. How old were you?\n14 A. 18.\n15 MS. COMEY: May I have a moment, your Honor?\n16 THE COURT: Yes.\n17 Q. Carolyn?\n18 A. Yes.\n19 Q. After you stopped seeing Jeffrey Epstein, did you continue using drugs?\n21 A. Yes.\n22 Q. What drugs did you use?\n23 A. Cocaine and pain pills.\n24 Q. Were you addicted to both of those drugs?\n25 A. Yes.",
      "position": "main"
    },
    {
      "type": "printed",
      "content": "SOUTHERN DISTRICT REPORTERS, P.C. (212) 805-0300",
      "position": "footer"
    },
    {
      "type": "stamp",
      "content": "DOJ-OGR-00018721",
      "position": "footer"
    }
  ],
  "entities": {
    "people": [
      "Jeffrey Epstein",
      "Carolyn",
      "MS. COMEY"
    ],
    "organizations": [
      "SOUTHERN DISTRICT REPORTERS, P.C.",
      "THE COURT"
    ],
    "locations": [],
    "dates": [
      "08/10/22"
    ],
    "reference_numbers": [
      "1:20-cr-00330-PAE",
      "753",
      "DOJ-OGR-00018721"
    ]
  },
  "additional_notes": "The document appears to be a court transcript with a clear and legible format. There are no visible redactions or damage."
}