{
  "document_metadata": {
    "page_number": "18",
    "document_number": "94",
    "date": "10/08/2020",
    "document_type": "court document",
    "has_handwriting": false,
    "has_stamps": false
  },
  "full_text": "Case 20-3061, Document 94, 10/08/2020, 2948481, Page18 of 23\n\n\"the Government had charged her with perjury in connection with civil cases.\"\nAns.Br. 23 n.7. But knowing that the government had copies of her depositions is a far cry from knowing \n\nMs. Maxwell's original consent to the criminal protective order is irrelevant to this appeal.\n\nThe government next argues that Ms. Maxwell has not offered a \"coherent explanation of how the criminal discovery materials could have any conceivable impact on the issues pending in civil litigation.\" Ans.Br. 24. To the contrary, Ms. Maxwell has repeatedly explained why the criminal discovery is relevant to Judge Preska and the panel of this Court reviewing Judge Preska's order. Op.Br. 26-33.\n\nIn addition to the reasons identified above, This Brief, supra at 7-10, Judge Preska simply never had before her the full picture when deciding whether to unseal the deposition material. So Judge Preska never considered the government's position that the sealed material should not be released because it might prejudice the ongoing investigation. Nor did she consider Judge Nathan's view, embodied in\n\nmodification of the criminal protective order is fully consistent with that purpose, because she seeks only: (1) to share relevant information with Judge Preska; (2) under seal; (3) ; and (4) to facilitate Judge Preska in performing a non-merits task assigned to her by this Court.\n\n15\n\nDOJ-OGR-00019664",
  "text_blocks": [
    {
      "type": "printed",
      "content": "Case 20-3061, Document 94, 10/08/2020, 2948481, Page18 of 23",
      "position": "header"
    },
    {
      "type": "printed",
      "content": "\"the Government had charged her with perjury in connection with civil cases.\"\nAns.Br. 23 n.7. But knowing that the government had copies of her depositions is a far cry from knowing",
      "position": "top"
    },
    {
      "type": "printed",
      "content": "Ms. Maxwell's original consent to the criminal protective order is irrelevant to this appeal.",
      "position": "middle"
    },
    {
      "type": "printed",
      "content": "The government next argues that Ms. Maxwell has not offered a \"coherent explanation of how the criminal discovery materials could have any conceivable impact on the issues pending in civil litigation.\" Ans.Br. 24. To the contrary, Ms. Maxwell has repeatedly explained why the criminal discovery is relevant to Judge Preska and the panel of this Court reviewing Judge Preska's order. Op.Br. 26-33.",
      "position": "middle"
    },
    {
      "type": "printed",
      "content": "In addition to the reasons identified above, This Brief, supra at 7-10, Judge Preska simply never had before her the full picture when deciding whether to unseal the deposition material. So Judge Preska never considered the government's position that the sealed material should not be released because it might prejudice the ongoing investigation. Nor did she consider Judge Nathan's view, embodied in",
      "position": "middle"
    },
    {
      "type": "printed",
      "content": "modification of the criminal protective order is fully consistent with that purpose, because she seeks only: (1) to share relevant information with Judge Preska; (2) under seal; (3) ; and (4) to facilitate Judge Preska in performing a non-merits task assigned to her by this Court.",
      "position": "middle"
    },
    {
      "type": "printed",
      "content": "15",
      "position": "footer"
    },
    {
      "type": "printed",
      "content": "DOJ-OGR-00019664",
      "position": "footer"
    }
  ],
  "entities": {
    "people": [
      "Maxwell",
      "Preska",
      "Nathan"
    ],
    "organizations": [
      "Government",
      "Court"
    ],
    "locations": [],
    "dates": [
      "10/08/2020"
    ],
    "reference_numbers": [
      "20-3061",
      "94",
      "2948481",
      "DOJ-OGR-00019664"
    ]
  },
  "additional_notes": "The document appears to be a court filing related to the case of Ms. Maxwell. The text is mostly printed, with some redacted sections. The document includes references to other court documents and briefs."
}