{
  "document_metadata": {
    "page_number": "40",
    "document_number": "745",
    "date": "08/10/22",
    "document_type": "court transcript",
    "has_handwriting": false,
    "has_stamps": false
  },
  "full_text": "Case 1:20-cr-00330-PAE Document 745 Filed 08/10/22 Page 40 of 264 446 LC1VMAX1 Jane - cross 1 Epstein approached you; correct? 2 A. Correct. 3 Q. You didn't say anything to the reporter about Ghislaine being there; correct? 4 A. Correct. 5 Q. You spoke to the government for the first time, as we discussed yesterday, in September of 2019; correct? 6 A. I don't recall the exact date. 7 Q. Well, you were there in California with your lawyers and Ms. Moe and some others; correct? 8 A. Correct. 9 Q. And what happened when you spoke to them then is you were asked about the first time that you met Ghislaine, right? 10 A. Right. 11 Q. And what you told the government on that day with your attorneys there is that Ghislaine walked by with her dog; correct? 12 A. I don't recall my exact vernacular. 13 (Continued on next page) 14 15 16 17 18 19 20 21 22 23 24 25 SOUTHERN DISTRICT REPORTERS, P.C. (212) 805-0300 DOJ-OGR-00017649",
  "text_blocks": [
    {
      "type": "printed",
      "content": "Case 1:20-cr-00330-PAE Document 745 Filed 08/10/22 Page 40 of 264 446",
      "position": "header"
    },
    {
      "type": "printed",
      "content": "LC1VMAX1 Jane - cross",
      "position": "header"
    },
    {
      "type": "printed",
      "content": "1 Epstein approached you; correct? 2 A. Correct. 3 Q. You didn't say anything to the reporter about Ghislaine being there; correct? 4 A. Correct. 5 Q. You spoke to the government for the first time, as we discussed yesterday, in September of 2019; correct? 6 A. I don't recall the exact date. 7 Q. Well, you were there in California with your lawyers and Ms. Moe and some others; correct? 8 A. Correct. 9 Q. And what happened when you spoke to them then is you were asked about the first time that you met Ghislaine, right? 10 A. Right. 11 Q. And what you told the government on that day with your attorneys there is that Ghislaine walked by with her dog; correct? 12 A. I don't recall my exact vernacular. 13 (Continued on next page)",
      "position": "main"
    },
    {
      "type": "printed",
      "content": "SOUTHERN DISTRICT REPORTERS, P.C. (212) 805-0300",
      "position": "footer"
    },
    {
      "type": "printed",
      "content": "DOJ-OGR-00017649",
      "position": "footer"
    }
  ],
  "entities": {
    "people": [
      "Epstein",
      "Ghislaine",
      "Moe"
    ],
    "organizations": [
      "SOUTHERN DISTRICT REPORTERS, P.C."
    ],
    "locations": [
      "California"
    ],
    "dates": [
      "08/10/22",
      "September 2019"
    ],
    "reference_numbers": [
      "1:20-cr-00330-PAE",
      "745",
      "DOJ-OGR-00017649"
    ]
  },
  "additional_notes": "The document appears to be a court transcript with a clear and legible format. There are no visible redactions or damage."
}