{
  "document_metadata": {
    "page_number": "115",
    "document_number": "753",
    "date": "08/10/22",
    "document_type": "Court Transcript",
    "has_handwriting": false,
    "has_stamps": false
  },
  "full_text": "Case 1:20-cr-00330-PAE Document 753 Filed 08/10/22 Page 115 of 264 1541\nLC7VMAX3 Carolyn - direct\n1 A. Once or twice Ms. Maxwell did.\n2 Q. About how much money do you remember Ms. Maxwell handing you after you engaged in a sexualized massage with Jeffrey Epstein?\n3 A. $300.\n4 Q. What denominations were the bills?\n5 A. Hundreds.\n6 Q. Other than money, what gifts, if any, did you receive from Jeffrey Epstein?\n7 A. I received lingerie.\n8 Q. How did you get that lingerie?\n9 A. Through FedEx.\n10 Q. Where did you receive a FedEx package?\n11 A. At my home.\n12 Q. In what town was your home?\n13 A. West Palm Beach.\n14 Q. Is that the home where you lived with your mom and your younger brothers?\n15 A. Yes.\n16 Q. Did you notice the return address from those packages?\n17 A. Yes.\n18 Q. What was it?\n19 A. Manhattan, New York.\n20 Q. Any reason that stands out in your mind?\n21 A. Yeah. Because I was born in New York, so -- and also I\nSOUTHERN DISTRICT REPORTERS, P.C. (212) 805-0300\nDOJ-OGR-00018713",
  "text_blocks": [
    {
      "type": "printed",
      "content": "Case 1:20-cr-00330-PAE Document 753 Filed 08/10/22 Page 115 of 264 1541",
      "position": "header"
    },
    {
      "type": "printed",
      "content": "LC7VMAX3 Carolyn - direct",
      "position": "header"
    },
    {
      "type": "printed",
      "content": "1 A. Once or twice Ms. Maxwell did.\n2 Q. About how much money do you remember Ms. Maxwell handing you after you engaged in a sexualized massage with Jeffrey Epstein?\n3 A. $300.\n4 Q. What denominations were the bills?\n5 A. Hundreds.\n6 Q. Other than money, what gifts, if any, did you receive from Jeffrey Epstein?\n7 A. I received lingerie.\n8 Q. How did you get that lingerie?\n9 A. Through FedEx.\n10 Q. Where did you receive a FedEx package?\n11 A. At my home.\n12 Q. In what town was your home?\n13 A. West Palm Beach.\n14 Q. Is that the home where you lived with your mom and your younger brothers?\n15 A. Yes.\n16 Q. Did you notice the return address from those packages?\n17 A. Yes.\n18 Q. What was it?\n19 A. Manhattan, New York.\n20 Q. Any reason that stands out in your mind?\n21 A. Yeah. Because I was born in New York, so -- and also I",
      "position": "main"
    },
    {
      "type": "printed",
      "content": "SOUTHERN DISTRICT REPORTERS, P.C. (212) 805-0300",
      "position": "footer"
    },
    {
      "type": "printed",
      "content": "DOJ-OGR-00018713",
      "position": "footer"
    }
  ],
  "entities": {
    "people": [
      "Ms. Maxwell",
      "Jeffrey Epstein"
    ],
    "organizations": [
      "SOUTHERN DISTRICT REPORTERS, P.C.",
      "FedEx"
    ],
    "locations": [
      "West Palm Beach",
      "Manhattan",
      "New York"
    ],
    "dates": [
      "08/10/22"
    ],
    "reference_numbers": [
      "1:20-cr-00330-PAE",
      "753",
      "DOJ-OGR-00018713"
    ]
  },
  "additional_notes": "The document appears to be a court transcript with a clear and legible format. There are no visible redactions or damage."
}