{
  "document_metadata": {
    "page_number": "3",
    "document_number": "63",
    "date": "9/18/2020",
    "document_type": "Criminal Docket",
    "has_handwriting": false,
    "has_stamps": false
  },
  "full_text": "9/18/2020 Case 20-3061, Document 63, 09/18/2020, 2938382, Page3 of 125 Query Reports Utilities Help Log Out APPEAL,ECF U.S. District Court Southern District of New York (Foley Square) CRIMINAL DOCKET FOR CASE #: 1:20-cr-00330-AJN-1 Case title: USA v. Maxwell Date Filed: 06/29/2020 Assigned to: Judge Alison J. Nathan Defendant (1) Ghislaine Maxwell also known as Sealed Defendant 1 represented by Christian R. Everdell Cohen & Gresser LLP 800 Third Avenue New York, NY 10022 212-707-7268 Fax: 212-957-4514 Email: ceverdell@cohengresser.com LEAD ATTORNEY ATTORNEY TO BE NOTICED Jeffrey S. Pagliuca Haddon Morgan and Foreman 150 East 10th Avenue Denver, CO 80203 (303)-831-7364 Fax: (303)-832-2628 Email: jpagliuca@hmflaw.com LEAD ATTORNEY ATTORNEY TO BE NOTICED Laura A. Menninger Haddon, Morgan and Foreman, P.C. 150 East Tenth Avenue Denver, CO 80203 (303)-831-7364 Fax: (303)-832-2628 Email: lmenninger@hmflaw.com LEAD ATTORNEY ATTORNEY TO BE NOTICED Mark Stewart Cohen Cohen & Gresser, LLP (NYC) 800 Third Avenue New York, NY 10022 (212) 957-7600 Fax: (212)957-4514 Email: mcohen@cohengresser.com App.001 1/12 https://ecf.nysd.uscourts.gov/cgi-bin/DktRpt.pl?3477082771296555-L_1_0-1 DOJ-OGR-00019460",
  "text_blocks": [
    {
      "type": "printed",
      "content": "U.S. District Court Southern District of New York (Foley Square) CRIMINAL DOCKET FOR CASE #: 1:20-cr-00330-AJN-1",
      "position": "header"
    },
    {
      "type": "printed",
      "content": "Case title: USA v. Maxwell Date Filed: 06/29/2020",
      "position": "header"
    },
    {
      "type": "printed",
      "content": "Assigned to: Judge Alison J. Nathan",
      "position": "header"
    },
    {
      "type": "printed",
      "content": "Defendant (1) Ghislaine Maxwell also known as Sealed Defendant 1",
      "position": "body"
    },
    {
      "type": "printed",
      "content": "represented by Christian R. Everdell Cohen & Gresser LLP 800 Third Avenue New York, NY 10022 212-707-7268 Fax: 212-957-4514 Email: ceverdell@cohengresser.com LEAD ATTORNEY ATTORNEY TO BE NOTICED",
      "position": "body"
    },
    {
      "type": "printed",
      "content": "Jeffrey S. Pagliuca Haddon Morgan and Foreman 150 East 10th Avenue Denver, CO 80203 (303)-831-7364 Fax: (303)-832-2628 Email: jpagliuca@hmflaw.com LEAD ATTORNEY ATTORNEY TO BE NOTICED",
      "position": "body"
    },
    {
      "type": "printed",
      "content": "Laura A. Menninger Haddon, Morgan and Foreman, P.C. 150 East Tenth Avenue Denver, CO 80203 (303)-831-7364 Fax: (303)-832-2628 Email: lmenninger@hmflaw.com LEAD ATTORNEY ATTORNEY TO BE NOTICED",
      "position": "body"
    },
    {
      "type": "printed",
      "content": "Mark Stewart Cohen Cohen & Gresser, LLP (NYC) 800 Third Avenue New York, NY 10022 (212) 957-7600 Fax: (212)957-4514 Email: mcohen@cohengresser.com App.001 1/12",
      "position": "body"
    }
  ],
  "entities": {
    "people": [
      "Ghislaine Maxwell",
      "Alison J. Nathan",
      "Christian R. Everdell",
      "Jeffrey S. Pagliuca",
      "Laura A. Menninger",
      "Mark Stewart Cohen"
    ],
    "organizations": [
      "Cohen & Gresser LLP",
      "Haddon Morgan and Foreman",
      "Haddon, Morgan and Foreman, P.C.",
      "U.S. District Court",
      "Southern District of New York"
    ],
    "locations": [
      "New York",
      "Denver",
      "Foley Square"
    ],
    "dates": [
      "06/29/2020",
      "9/18/2020"
    ],
    "reference_numbers": [
      "1:20-cr-00330-AJN-1",
      "20-3061",
      "63"
    ]
  },
  "additional_notes": "The document appears to be a court docket sheet with printed text. There are no visible handwritten notes or stamps."
}