{
  "document_metadata": {
    "page_number": "66",
    "document_number": "751",
    "date": "08/10/22",
    "document_type": "court transcript",
    "has_handwriting": false,
    "has_stamps": false
  },
  "full_text": "Case 1:20-cr-00330-PAE Document 751 Filed 08/10/22 Page 66 of 261 1206\nLC6VMAX2 Kate - direct\n1 Q. Can you explain?\n2 A. The memories I have of significant events in my life have never changed. My memory -- there are things that I have missed that happened that sometimes I later recall. The memories I have are the memories I have.\n3 Q. Directing your attention to August 2019, did there come a time when you were interviewed by the government?\n4 A. Yes.\n5 Q. Was FBI present for the interview?\n6 A. Yes.\n7 Q. Before that day, had you ever talked to law enforcement about your experiences with Maxwell and Epstein?\n8 A. No.\n9 Q. That same day did you speak publicly about some of the experiences that you testified about here today?\n10 A. Did I speak publicly? Yes.\n11 Q. And when you did that, did you talk about all of the details that you shared with the government?\n12 A. No.\n13 Q. Why not?\n14 A. I have a huge amount of humiliation and shame and -- around the events that took place. I was not ready to share that in detail on a public level.\n15 Q. If you have spoken publicly before, why did you ask to testify under a pseudonym here today?\nSOUTHERN DISTRICT REPORTERS, P.C. (212) 805-0300\nDOJ-OGR-00018403",
  "text_blocks": [
    {
      "type": "printed",
      "content": "Case 1:20-cr-00330-PAE Document 751 Filed 08/10/22 Page 66 of 261 1206",
      "position": "header"
    },
    {
      "type": "printed",
      "content": "LC6VMAX2 Kate - direct",
      "position": "header"
    },
    {
      "type": "printed",
      "content": "1 Q. Can you explain?\n2 A. The memories I have of significant events in my life have never changed. My memory -- there are things that I have missed that happened that sometimes I later recall. The memories I have are the memories I have.\n3 Q. Directing your attention to August 2019, did there come a time when you were interviewed by the government?\n4 A. Yes.\n5 Q. Was FBI present for the interview?\n6 A. Yes.\n7 Q. Before that day, had you ever talked to law enforcement about your experiences with Maxwell and Epstein?\n8 A. No.\n9 Q. That same day did you speak publicly about some of the experiences that you testified about here today?\n10 A. Did I speak publicly? Yes.\n11 Q. And when you did that, did you talk about all of the details that you shared with the government?\n12 A. No.\n13 Q. Why not?\n14 A. I have a huge amount of humiliation and shame and -- around the events that took place. I was not ready to share that in detail on a public level.\n15 Q. If you have spoken publicly before, why did you ask to testify under a pseudonym here today?",
      "position": "main"
    },
    {
      "type": "printed",
      "content": "SOUTHERN DISTRICT REPORTERS, P.C. (212) 805-0300",
      "position": "footer"
    },
    {
      "type": "printed",
      "content": "DOJ-OGR-00018403",
      "position": "footer"
    }
  ],
  "entities": {
    "people": [
      "Kate",
      "Maxwell",
      "Epstein"
    ],
    "organizations": [
      "FBI",
      "SOUTHERN DISTRICT REPORTERS, P.C."
    ],
    "locations": [],
    "dates": [
      "August 2019",
      "08/10/22"
    ],
    "reference_numbers": [
      "1:20-cr-00330-PAE",
      "751",
      "DOJ-OGR-00018403"
    ]
  },
  "additional_notes": "The document appears to be a court transcript with a clear and legible format. There are no visible redactions or damage."
}