{
  "document_metadata": {
    "page_number": "33",
    "document_number": "4",
    "date": "07/06/20",
    "document_type": "Notice of Electronic Filing",
    "has_handwriting": false,
    "has_stamps": false
  },
  "full_text": "Case 1:20-mj-00132-AJ Document 4 Filed 07/06/20 Page 33 of 33 MIME-Version:1.0 From:ecf_bounce@nhd.uscourts.gov To:nef@nhd.uscourts.gov Bcc: --Case Participants: --Non Case Participants: --No Notice Sent: Message-Id:2212948@nhd.uscourts.gov Subject:Activity in Case 20-132 Sealed v. Sealed (Redacted Notice) Content-Type: text/html NOTE: This docket entry (or case) is sealed, no email notices have been sent. U.S. District Court District of New Hampshire Notice of Electronic Filing The following transaction was entered on 7/2/2020 at 9:45 AM EDT and filed on 7/2/2020 Case Name: USA v. Maxwell Case Number: 1:20-mj-00132-AJ *SEALED* Filer: Document Number: No document attached Docket Text: Arrest (Removal) of Ghislaine Maxwell.(kad) 1:20-mj-00132-AJ *SEALED*-1 No electronic public notice will be sent because the case/entry is sealed. DOJ-OGR-00019234",
  "text_blocks": [
    {
      "type": "printed",
      "content": "Case 1:20-mj-00132-AJ Document 4 Filed 07/06/20 Page 33 of 33",
      "position": "header"
    },
    {
      "type": "printed",
      "content": "MIME-Version:1.0 From:ecf_bounce@nhd.uscourts.gov To:nef@nhd.uscourts.gov Bcc: --Case Participants: --Non Case Participants: --No Notice Sent: Message-Id:2212948@nhd.uscourts.gov Subject:Activity in Case 20-132 Sealed v. Sealed (Redacted Notice) Content-Type: text/html",
      "position": "top"
    },
    {
      "type": "printed",
      "content": "NOTE: This docket entry (or case) is sealed, no email notices have been sent.",
      "position": "top"
    },
    {
      "type": "printed",
      "content": "U.S. District Court District of New Hampshire",
      "position": "middle"
    },
    {
      "type": "printed",
      "content": "Notice of Electronic Filing",
      "position": "middle"
    },
    {
      "type": "printed",
      "content": "The following transaction was entered on 7/2/2020 at 9:45 AM EDT and filed on 7/2/2020 Case Name: USA v. Maxwell Case Number: 1:20-mj-00132-AJ *SEALED* Filer: Document Number: No document attached Docket Text: Arrest (Removal) of Ghislaine Maxwell.(kad) 1:20-mj-00132-AJ *SEALED*-1 No electronic public notice will be sent because the case/entry is sealed.",
      "position": "middle"
    },
    {
      "type": "printed",
      "content": "DOJ-OGR-00019234",
      "position": "footer"
    }
  ],
  "entities": {
    "people": [
      "Ghislaine Maxwell"
    ],
    "organizations": [
      "U.S. District Court",
      "District of New Hampshire"
    ],
    "locations": [
      "New Hampshire"
    ],
    "dates": [
      "7/2/2020",
      "07/06/20"
    ],
    "reference_numbers": [
      "1:20-mj-00132-AJ",
      "DOJ-OGR-00019234"
    ]
  },
  "additional_notes": "The document is a Notice of Electronic Filing from the U.S. District Court, District of New Hampshire. The case is sealed, and no email notices have been sent. The document contains information about the arrest and removal of Ghislaine Maxwell."
}