{
  "document_metadata": {
    "page_number": "2 of 2",
    "document_number": "62",
    "date": "09/24/2020",
    "document_type": "Table of Contents",
    "has_handwriting": false,
    "has_stamps": false
  },
  "full_text": "Case 20-3061, Document 62, 09/24/2020, 2938281, Page2 of 2\nTable of Contents\n2020.08.17 JSP Ltr. re. Modification of the Protective Order....................124-131\n2020.08.17 JSP Rule 16.1 Affidavit...............................................132-133\nEx. 1 to JSP Ltr. re. Modification of the Protective Order ....................134-140\nEx. 2 to JSP Ltr. re. Modification of the Protective Order ....................141-147\nEx. 3 to JSP Ltr. re. Modification of the Protective Order ....................148-161\nEx. 4 to JSP Ltr. re. Modification of the Protective Order ....................162-175\nEx. 5 to JSP Ltr. re. Modification of the Protective Order ....................176-198\nEx. 6 to JSP Ltr. re. Modification of the Protective Order ....................199-202\nEx. 7 to JSP Ltr. re. Modification of the Protective Order ....................203-205\nEx. 8 to JSP Ltr. re. Modification of the Protective Order ....................206-237\nEx. 9 to JSP Ltr. re. Modification of the Protective Order ....................238-264\nEx. 10 to JSP Ltr. re. Modification of the Protective Order ....................265-272\n2020.08.21, SEALED, letter to Judge Nathan re proposed redactions and sealing ................................................................273-285\n2020.08.21, letter to Judge Nathan re proposed redactions and sealing (docketed)..............................................................286-289\n2020.08.24 JSP Ltr. Submitting Proposed Redactions Under Seal.............. 290-292\n2020.08.24 JSP Reply Ltr. re. Modification of the Protective Order ...........293-298\nEx. A 2020.08.17 JSP Proposed Redactions to Ltr. re. Modification of the Protective Order ...............................................299-307\nEx. B 2020.08.24 JSP Reply Ltr. re. Modification of the Protective Order......308-314\nDOJ-OGR-00019584",
  "text_blocks": [
    {
      "type": "printed",
      "content": "Case 20-3061, Document 62, 09/24/2020, 2938281, Page2 of 2",
      "position": "header"
    },
    {
      "type": "printed",
      "content": "Table of Contents",
      "position": "top"
    },
    {
      "type": "printed",
      "content": "2020.08.17 JSP Ltr. re. Modification of the Protective Order....................124-131\n2020.08.17 JSP Rule 16.1 Affidavit...............................................132-133\nEx. 1 to JSP Ltr. re. Modification of the Protective Order ....................134-140\nEx. 2 to JSP Ltr. re. Modification of the Protective Order ....................141-147\nEx. 3 to JSP Ltr. re. Modification of the Protective Order ....................148-161\nEx. 4 to JSP Ltr. re. Modification of the Protective Order ....................162-175\nEx. 5 to JSP Ltr. re. Modification of the Protective Order ....................176-198\nEx. 6 to JSP Ltr. re. Modification of the Protective Order ....................199-202\nEx. 7 to JSP Ltr. re. Modification of the Protective Order ....................203-205\nEx. 8 to JSP Ltr. re. Modification of the Protective Order ....................206-237\nEx. 9 to JSP Ltr. re. Modification of the Protective Order ....................238-264\nEx. 10 to JSP Ltr. re. Modification of the Protective Order ....................265-272\n2020.08.21, SEALED, letter to Judge Nathan re proposed redactions and sealing ................................................................273-285\n2020.08.21, letter to Judge Nathan re proposed redactions and sealing (docketed)..............................................................286-289\n2020.08.24 JSP Ltr. Submitting Proposed Redactions Under Seal.............. 290-292\n2020.08.24 JSP Reply Ltr. re. Modification of the Protective Order ...........293-298\nEx. A 2020.08.17 JSP Proposed Redactions to Ltr. re. Modification of the Protective Order ...............................................299-307\nEx. B 2020.08.24 JSP Reply Ltr. re. Modification of the Protective Order......308-314",
      "position": "middle"
    },
    {
      "type": "printed",
      "content": "DOJ-OGR-00019584",
      "position": "footer"
    }
  ],
  "entities": {
    "people": [
      "Judge Nathan"
    ],
    "organizations": [
      "DOJ"
    ],
    "locations": [],
    "dates": [
      "2020.08.17",
      "2020.08.21",
      "2020.08.24",
      "09/24/2020"
    ],
    "reference_numbers": [
      "20-3061",
      "62",
      "2938281",
      "DOJ-OGR-00019584"
    ]
  },
  "additional_notes": "The document appears to be a table of contents for a legal case, with various documents and exhibits listed along with their corresponding page numbers. The document is well-formatted and easy to read."
}