{
  "document_metadata": {
    "page_number": "9",
    "document_number": "58-1",
    "date": "04/12/2021",
    "document_type": "court document",
    "has_handwriting": false,
    "has_stamps": false
  },
  "full_text": "Case 21-58, Document 58-1, 04/12/2021, 3075763, Page9 of 25\n\nC. The Second Bail Application\n\n16. On December 8, 2020, Maxwell renewed her request for bail, presenting a revised bail package with additional financial restrictions. (Ex. E). After considering multiple written submissions (Ex. E, F, G), Judge Nathan denied Maxwell's application in a written opinion (Ex. H).\n\n17. Judge Nathan found that the arguments presented \"either were made at the initial bail hearing or could have been made then\" and the new information \"only solidifies the Court's view that [Maxwell] plainly poses a risk of flight and that no combination of conditions can ensure her appearance.\" (Ex. H at 1-2). Judge Nathan explained:\nthe charges, which carry a presumption of detention, are serious and carry lengthy terms of imprisonment if convicted; the evidence proffered by the Government, including multiple corroborating and corroborated witnesses, is strong; the Defendant has substantial resources and foreign ties (including citizenship in a country that does not extradite its citizens); and the Defendant, who lived in hiding and apart from the family to whom she now asserts important ties, has not been fully candid about her financial situation.\n(Id. at 2).\n\n18. Judge Nathan rejected Maxwell's claim that the Government overstated the strength of its case at the bail hearing, finding that Maxwell \"too easily discredits the witness testimony.\" (Id. at 9-10). Judge Nathan credited the\n\n9\nDOJ-OGR-00020243",
  "text_blocks": [
    {
      "type": "printed",
      "content": "Case 21-58, Document 58-1, 04/12/2021, 3075763, Page9 of 25",
      "position": "header"
    },
    {
      "type": "printed",
      "content": "C. The Second Bail Application",
      "position": "top"
    },
    {
      "type": "printed",
      "content": "16. On December 8, 2020, Maxwell renewed her request for bail, presenting a revised bail package with additional financial restrictions. (Ex. E). After considering multiple written submissions (Ex. E, F, G), Judge Nathan denied Maxwell's application in a written opinion (Ex. H).",
      "position": "middle"
    },
    {
      "type": "printed",
      "content": "17. Judge Nathan found that the arguments presented \"either were made at the initial bail hearing or could have been made then\" and the new information \"only solidifies the Court's view that [Maxwell] plainly poses a risk of flight and that no combination of conditions can ensure her appearance.\" (Ex. H at 1-2). Judge Nathan explained:\nthe charges, which carry a presumption of detention, are serious and carry lengthy terms of imprisonment if convicted; the evidence proffered by the Government, including multiple corroborating and corroborated witnesses, is strong; the Defendant has substantial resources and foreign ties (including citizenship in a country that does not extradite its citizens); and the Defendant, who lived in hiding and apart from the family to whom she now asserts important ties, has not been fully candid about her financial situation.",
      "position": "middle"
    },
    {
      "type": "printed",
      "content": "(Id. at 2).",
      "position": "middle"
    },
    {
      "type": "printed",
      "content": "18. Judge Nathan rejected Maxwell's claim that the Government overstated the strength of its case at the bail hearing, finding that Maxwell \"too easily discredits the witness testimony.\" (Id. at 9-10). Judge Nathan credited the",
      "position": "middle"
    },
    {
      "type": "printed",
      "content": "9",
      "position": "footer"
    },
    {
      "type": "printed",
      "content": "DOJ-OGR-00020243",
      "position": "footer"
    }
  ],
  "entities": {
    "people": [
      "Maxwell",
      "Judge Nathan"
    ],
    "organizations": [
      "Government",
      "Court"
    ],
    "locations": [],
    "dates": [
      "December 8, 2020",
      "04/12/2021"
    ],
    "reference_numbers": [
      "Case 21-58",
      "Document 58-1",
      "3075763",
      "DOJ-OGR-00020243"
    ]
  },
  "additional_notes": "The document appears to be a court filing related to the bail application of Maxwell. The text is printed and there are no visible stamps or handwritten notes. The document is page 9 of 25."
}