{
  "document_metadata": {
    "page_number": "45",
    "document_number": "757",
    "date": "08/10/22",
    "document_type": "court transcript",
    "has_handwriting": false,
    "has_stamps": false
  },
  "full_text": "Case 1:20-cr-00330-PAE Document 757 Filed 08/10/22 Page 45 of 49 2018 LC9VMAXT Chapell - cross 1 Q. And were these invoices kept in the regular course of FedEx's business? 2 A. Yes. 3 MR. EVERDELL: Your Honor, at this time the defense offers Defense Exhibit TC-1 under temporary seal. We have not 4 yet had the chance to make the appropriate redactions, but we 5 will do so as soon as we can. 6 MR. ROHRBACH: No objection. 7 THE COURT: Thank you. Defendant's TC-1 is admitted 8 under temporary seal until narrow redactions can be offered. 9 (Defendant's Exhibit TC-1 received in evidence) 10 MR. EVERDELL: Absolutely, your Honor. 11 And if the jurors would like to take a look, with the 12 Court's permission, there is a folder underneath their chairs 13 with this exhibit. 14 THE COURT: Yes, please. You can open the folder to 15 Defendant's Exhibit TC-1. 16 BY MR. EVERDELL: 17 Q. Ms. Chapell, I'm not going to go through these records with you -- and the jurors are free to review it if they like -- but 18 I have no further questions for this witness. 19 THE COURT: Okay. 20 MR. ROHRBACH: Nothing further, your Honor. 21 THE COURT: Okay. Ms. Chapell, thank you. 22 You are excused. You may step down. 23 SOUTHERN DISTRICT REPORTERS, P.C. (212) 805-0300 DOJ-OGR-00019169",
  "text_blocks": [
    {
      "type": "printed",
      "content": "Case 1:20-cr-00330-PAE Document 757 Filed 08/10/22 Page 45 of 49 2018 LC9VMAXT Chapell - cross",
      "position": "header"
    },
    {
      "type": "printed",
      "content": "1 Q. And were these invoices kept in the regular course of FedEx's business? 2 A. Yes. 3 MR. EVERDELL: Your Honor, at this time the defense offers Defense Exhibit TC-1 under temporary seal. We have not 4 yet had the chance to make the appropriate redactions, but we 5 will do so as soon as we can. 6 MR. ROHRBACH: No objection. 7 THE COURT: Thank you. Defendant's TC-1 is admitted 8 under temporary seal until narrow redactions can be offered. 9 (Defendant's Exhibit TC-1 received in evidence) 10 MR. EVERDELL: Absolutely, your Honor. 11 And if the jurors would like to take a look, with the 12 Court's permission, there is a folder underneath their chairs 13 with this exhibit. 14 THE COURT: Yes, please. You can open the folder to 15 Defendant's Exhibit TC-1. 16 BY MR. EVERDELL: 17 Q. Ms. Chapell, I'm not going to go through these records with you -- and the jurors are free to review it if they like -- but 18 I have no further questions for this witness. 19 THE COURT: Okay. 20 MR. ROHRBACH: Nothing further, your Honor. 21 THE COURT: Okay. Ms. Chapell, thank you. 22 You are excused. You may step down.",
      "position": "main"
    },
    {
      "type": "printed",
      "content": "SOUTHERN DISTRICT REPORTERS, P.C. (212) 805-0300",
      "position": "footer"
    },
    {
      "type": "printed",
      "content": "DOJ-OGR-00019169",
      "position": "footer"
    }
  ],
  "entities": {
    "people": [
      "MR. EVERDELL",
      "MR. ROHRBACH",
      "Ms. Chapell"
    ],
    "organizations": [
      "FedEx",
      "SOUTHERN DISTRICT REPORTERS, P.C."
    ],
    "locations": [],
    "dates": [
      "08/10/22"
    ],
    "reference_numbers": [
      "1:20-cr-00330-PAE",
      "757",
      "DOJ-OGR-00019169"
    ]
  },
  "additional_notes": "The document appears to be a court transcript with a clear and readable format. There are no visible redactions or damage to the text."
}