{
  "document_metadata": {
    "page_number": "120",
    "document_number": "745",
    "date": "08/10/22",
    "document_type": "court transcript",
    "has_handwriting": false,
    "has_stamps": false
  },
  "full_text": "Case 1:20-cr-00330-PAE Document 745 Filed 08/10/22 Page 120 of 264 531 LC1Qmax4 Jane - Cross 1 Q. You recall Adam Perry Lang being on a flight with you? 2 A. Yes. 3 Q. You remember Epstein's mom being on a flight with you? 4 A. Yes. 5 Q. You told the government you remembered all these people being on flights with you? 6 A. Yeah. 7 Q. Were you aware of whether the flight logs reflect any flights by you with those individuals? 8 A. I have no idea, no. 9 Q. You also had some recollections about flying on the private plane with Epstein, right? You recall being on the plane? 10 A. Yes. 11 Q. And you said that you were asked your weight when you were boarding the plane, correct? 12 A. Yes. 13 Q. And you also remember this Latin American driver for Mr. Epstein driving you up to the airport, correct? 14 A. Correct. 15 Q. So he could back up that story too, correct? 16 A. Correct. 17 Q. And you remember someone from Epstein's office named Lesley who called to set up travel arrangements for you, right? 18 A. Yes. 19 Q. And you recall Lesley calling your home phone in Florida, SOUTHERN DISTRICT REPORTERS, P.C. (212) 805-0300 DOJ-OGR-00017729",
  "text_blocks": [
    {
      "type": "printed",
      "content": "Case 1:20-cr-00330-PAE Document 745 Filed 08/10/22 Page 120 of 264 531",
      "position": "header"
    },
    {
      "type": "printed",
      "content": "LC1Qmax4 Jane - Cross",
      "position": "header"
    },
    {
      "type": "printed",
      "content": "1 Q. You recall Adam Perry Lang being on a flight with you? 2 A. Yes. 3 Q. You remember Epstein's mom being on a flight with you? 4 A. Yes. 5 Q. You told the government you remembered all these people being on flights with you? 6 A. Yeah. 7 Q. Were you aware of whether the flight logs reflect any flights by you with those individuals? 8 A. I have no idea, no. 9 Q. You also had some recollections about flying on the private plane with Epstein, right? You recall being on the plane? 10 A. Yes. 11 Q. And you said that you were asked your weight when you were boarding the plane, correct? 12 A. Yes. 13 Q. And you also remember this Latin American driver for Mr. Epstein driving you up to the airport, correct? 14 A. Correct. 15 Q. So he could back up that story too, correct? 16 A. Correct. 17 Q. And you remember someone from Epstein's office named Lesley who called to set up travel arrangements for you, right? 18 A. Yes. 19 Q. And you recall Lesley calling your home phone in Florida,",
      "position": "main"
    },
    {
      "type": "printed",
      "content": "SOUTHERN DISTRICT REPORTERS, P.C. (212) 805-0300",
      "position": "footer"
    },
    {
      "type": "printed",
      "content": "DOJ-OGR-00017729",
      "position": "footer"
    }
  ],
  "entities": {
    "people": [
      "Adam Perry Lang",
      "Epstein",
      "Lesley",
      "Mr. Epstein"
    ],
    "organizations": [
      "SOUTHERN DISTRICT REPORTERS, P.C."
    ],
    "locations": [
      "Florida"
    ],
    "dates": [
      "08/10/22"
    ],
    "reference_numbers": [
      "1:20-cr-00330-PAE",
      "745",
      "DOJ-OGR-00017729"
    ]
  },
  "additional_notes": "The document appears to be a court transcript with a clear and legible format. There are no visible redactions or damage."
}