{
  "document_metadata": {
    "page_number": "65",
    "document_number": "749",
    "date": "08/10/22",
    "document_type": "court transcript",
    "has_handwriting": false,
    "has_stamps": false
  },
  "full_text": "Case 1:20-cr-00330-PAE Document 749 Filed 08/10/22 Page 65 of 236 969 LC3KMAX2 Alessi - Cross 1 Q. And then we're giving instructions to the subcontractor here as well. Do you see that? In item 6. A. AC subcontractor shall... Yes, sir, I see it. MR. PAGLIUCA: We can take that down and go back to the notes to the left of that, please, and blow those up. Q. Do you see that the bathrooms are being redone with marble tile, the floors are being done, countertops are being done, the baths are being done, we're installing new molding in the guestrooms? Do you see those general notes, Mr. Alessi? A. Yes. MR. PAGLIUCA: If we can take that down and go back to the notes to the left of those notes. Q. We're removing windows, we're cutting masonry down to floor level, installing new doors, modifying, replacing windows. Do you see that, Mr. Alessi? A. Yes, sir. Q. So this was a major renovation, correct, Mr. Alessi? A. Yes, sir. Q. And the architects, if we can go to page 297, on the upper right, look at who the architects were, you remember these folks from New York, Mr. Alessi? A. Yes, sir. Q. And they would fly down to Palm Beach and supervise the SOUTHERN DISTRICT REPORTERS, P.C. (212) 805-0300 DOJ-OGR-00018166",
  "text_blocks": [
    {
      "type": "printed",
      "content": "Case 1:20-cr-00330-PAE Document 749 Filed 08/10/22 Page 65 of 236 969 LC3KMAX2 Alessi - Cross",
      "position": "header"
    },
    {
      "type": "printed",
      "content": "1 Q. And then we're giving instructions to the subcontractor here as well. Do you see that? In item 6. A. AC subcontractor shall... Yes, sir, I see it. MR. PAGLIUCA: We can take that down and go back to the notes to the left of that, please, and blow those up. Q. Do you see that the bathrooms are being redone with marble tile, the floors are being done, countertops are being done, the baths are being done, we're installing new molding in the guestrooms? Do you see those general notes, Mr. Alessi? A. Yes. MR. PAGLIUCA: If we can take that down and go back to the notes to the left of those notes. Q. We're removing windows, we're cutting masonry down to floor level, installing new doors, modifying, replacing windows. Do you see that, Mr. Alessi? A. Yes, sir. Q. So this was a major renovation, correct, Mr. Alessi? A. Yes, sir. Q. And the architects, if we can go to page 297, on the upper right, look at who the architects were, you remember these folks from New York, Mr. Alessi? A. Yes, sir. Q. And they would fly down to Palm Beach and supervise the",
      "position": "main body"
    },
    {
      "type": "printed",
      "content": "SOUTHERN DISTRICT REPORTERS, P.C. (212) 805-0300",
      "position": "footer"
    },
    {
      "type": "printed",
      "content": "DOJ-OGR-00018166",
      "position": "footer"
    }
  ],
  "entities": {
    "people": [
      "Mr. Alessi",
      "MR. PAGLIUCA"
    ],
    "organizations": [
      "SOUTHERN DISTRICT REPORTERS, P.C."
    ],
    "locations": [
      "New York",
      "Palm Beach"
    ],
    "dates": [
      "08/10/22"
    ],
    "reference_numbers": [
      "1:20-cr-00330-PAE",
      "749",
      "DOJ-OGR-00018166"
    ]
  },
  "additional_notes": "The document appears to be a court transcript with a clear Q&A format. The content is related to a renovation project and involves testimony from Mr. Alessi. The document is well-formatted and legible."
}