{
  "document_metadata": {
    "page_number": "111",
    "document_number": "751",
    "date": "08/10/22",
    "document_type": "court transcript",
    "has_handwriting": false,
    "has_stamps": false
  },
  "full_text": "Case 1:20-cr-00330-PAE Document 751 Filed 08/10/22 Page 111 of 261 1272\nLC6Cmax3 Kate - cross\n1 Q. But nonetheless, you completed the form; correct?\n2 A. Yes.\n3 Q. And they also alerted you to resources in the area where you were living?\n4 \n5 A. Yes.\n6 Q. Even though, as a therapist, you knew about the resources in the area where you were living; correct?\n7 \n8 A. No.\n9 Q. You were not aware of that?\n10 A. No.\n11 Q. And in connection with the work that you do in your foundation and the other residence, you were not familiar with therapeutic services for women claiming to have been abused?\n12 \n13 A. Not many of them.\n14 \n15 Q. Nonetheless, they put you in the direction of services that you could avail yourself of; correct?\n16 \n17 A. Yes.\n18 Q. Some of which they paid for; correct?\n19 A. Yes.\n20 Q. And they also alerted you to facilities or situations where you could get free therapy; correct?\n21 \n22 A. I don't recall that, but possibly, quite possibly, yes.\n23 Q. And in connection with the three and a quarter million dollars that you received from the compensation fund, you paid back some of that money; correct?\n24 \n25 \nSOUTHERN DISTRICT REPORTERS, P.C. (212) 805-0300\nDOJ-OGR-00018448",
  "text_blocks": [
    {
      "type": "printed",
      "content": "Case 1:20-cr-00330-PAE Document 751 Filed 08/10/22 Page 111 of 261 1272",
      "position": "header"
    },
    {
      "type": "handwritten",
      "content": "LC6Cmax3 Kate - cross",
      "position": "header"
    },
    {
      "type": "printed",
      "content": "1 Q. But nonetheless, you completed the form; correct?\n2 A. Yes.\n3 Q. And they also alerted you to resources in the area where you were living?\n4 \n5 A. Yes.\n6 Q. Even though, as a therapist, you knew about the resources in the area where you were living; correct?\n7 \n8 A. No.\n9 Q. You were not aware of that?\n10 A. No.\n11 Q. And in connection with the work that you do in your foundation and the other residence, you were not familiar with therapeutic services for women claiming to have been abused?\n12 \n13 A. Not many of them.\n14 \n15 Q. Nonetheless, they put you in the direction of services that you could avail yourself of; correct?\n16 \n17 A. Yes.\n18 Q. Some of which they paid for; correct?\n19 A. Yes.\n20 Q. And they also alerted you to facilities or situations where you could get free therapy; correct?\n21 \n22 A. I don't recall that, but possibly, quite possibly, yes.\n23 Q. And in connection with the three and a quarter million dollars that you received from the compensation fund, you paid back some of that money; correct?\n24 \n25",
      "position": "main"
    },
    {
      "type": "printed",
      "content": "SOUTHERN DISTRICT REPORTERS, P.C. (212) 805-0300",
      "position": "footer"
    },
    {
      "type": "printed",
      "content": "DOJ-OGR-00018448",
      "position": "footer"
    }
  ],
  "entities": {
    "people": [],
    "organizations": [
      "SOUTHERN DISTRICT REPORTERS, P.C."
    ],
    "locations": [],
    "dates": [
      "08/10/22"
    ],
    "reference_numbers": [
      "1:20-cr-00330-PAE",
      "751",
      "DOJ-OGR-00018448"
    ]
  },
  "additional_notes": "The document appears to be a court transcript with a clear Q&A format. The content is related to a legal case involving a compensation fund and therapeutic services for women claiming to have been abused. There are no visible redactions or damage to the document."
}