{
  "document_metadata": {
    "page_number": "183",
    "document_number": "749",
    "date": "08/10/22",
    "document_type": "Court Transcript",
    "has_handwriting": false,
    "has_stamps": false
  },
  "full_text": "Case 1:20-cr-00330-PAE Document 749 Filed 08/10/22 Page 183 of 236 1087 LC3KMAX6 Parkinson - Direct 1 A. I do. 2 Q. What is it? 3 A. This is a desktop. 4 Q. From where? 5 A. This is in the same bathroom but a little bit of an anteroom 6 anteroom. 7 Q. Is this a fair and accurate depiction of a portion of the 8 interior of 358 El Brillo Way as it appeared on October 20, 9 2005? 10 A. True. 11 MS. COMEY: Your Honor, the government offers this 12 exhibit under seal to protect the interests of a party. 13 MR. EVERDELL: No objection. 14 THE COURT: 285 is admitted for the reason indicated. 15 (Government's Exhibit 285 received in evidence) 16 MS. COMEY: May we ask the jurors to turn in their 17 binder to Government Exhibit 285, please? 18 THE COURT: Yes. 19 Q. Mr. Parkinson, would you please read the writing in the 20 lower center of this picture? 21 THE COURT: Sorry. It's admitted under seal. 22 MS. COMEY: Ah, then I apologize, your Honor. May I 23 direct the jurors' attention to that writing? 24 THE COURT: Sure. 25 MS. COMEY: Thank you, your Honor. I am done with the SOUTHERN DISTRICT REPORTERS, P.C. (212) 805-0300 DOJ-OGR-00018284",
  "text_blocks": [
    {
      "type": "printed",
      "content": "Case 1:20-cr-00330-PAE Document 749 Filed 08/10/22 Page 183 of 236 1087",
      "position": "header"
    },
    {
      "type": "printed",
      "content": "LC3KMAX6 Parkinson - Direct",
      "position": "header"
    },
    {
      "type": "printed",
      "content": "1 A. I do. 2 Q. What is it? 3 A. This is a desktop. 4 Q. From where? 5 A. This is in the same bathroom but a little bit of an anteroom 6 anteroom. 7 Q. Is this a fair and accurate depiction of a portion of the 8 interior of 358 El Brillo Way as it appeared on October 20, 9 2005? 10 A. True. 11 MS. COMEY: Your Honor, the government offers this 12 exhibit under seal to protect the interests of a party. 13 MR. EVERDELL: No objection. 14 THE COURT: 285 is admitted for the reason indicated. 15 (Government's Exhibit 285 received in evidence) 16 MS. COMEY: May we ask the jurors to turn in their 17 binder to Government Exhibit 285, please? 18 THE COURT: Yes. 19 Q. Mr. Parkinson, would you please read the writing in the 20 lower center of this picture? 21 THE COURT: Sorry. It's admitted under seal. 22 MS. COMEY: Ah, then I apologize, your Honor. May I 23 direct the jurors' attention to that writing? 24 THE COURT: Sure. 25 MS. COMEY: Thank you, your Honor. I am done with the",
      "position": "main"
    },
    {
      "type": "printed",
      "content": "SOUTHERN DISTRICT REPORTERS, P.C. (212) 805-0300",
      "position": "footer"
    },
    {
      "type": "printed",
      "content": "DOJ-OGR-00018284",
      "position": "footer"
    }
  ],
  "entities": {
    "people": [
      "MS. COMEY",
      "MR. EVERDELL",
      "Mr. Parkinson"
    ],
    "organizations": [
      "SOUTHERN DISTRICT REPORTERS, P.C."
    ],
    "locations": [
      "358 El Brillo Way"
    ],
    "dates": [
      "October 20, 2005",
      "08/10/22"
    ],
    "reference_numbers": [
      "1:20-cr-00330-PAE",
      "Document 749",
      "Government's Exhibit 285",
      "DOJ-OGR-00018284"
    ]
  },
  "additional_notes": "The document appears to be a court transcript with a clear and legible format. There are no visible redactions or damage."
}