{
  "document_metadata": {
    "page_number": "149",
    "document_number": "749",
    "date": "08/10/22",
    "document_type": "court transcript",
    "has_handwriting": false,
    "has_stamps": false
  },
  "full_text": "Case 1:20-cr-00330-PAE Document 749 Filed 08/10/22 Page 149 of 236 1053 LC3Cmax5 Parkinson - direct. THE COURT: Actually, for simplicity, let's have the jurors put the binders under the chair until they're directed to look at something in particular. MS. COMEY: Okay, your Honor. Thank you. Q. Do you have exhibits 226 through 241 in the binder in front of you, Mr. Parkinson? A. I do. Q. And have you reviewed those, 226 through 241? A. No, I was only taking inventory. Q. Would you please review all of those and then let us know when you've finished. A. I'm ready. Q. Do you recognize those? A. I do. Q. What are they? A. These are photographs of the interior of the house, the ground floor, mostly in the garden room and lake room, partially in the hallway to the center part of the house looking from east to west into the lake room. Q. Do these exhibits fairly and accurately depict portions of the interior of the main house at 358 El Brillo Way as it appeared on October 20th, 2005? A. They do. MS. COMEY: Your Honor, the government offers these into evidence and ask that 234 be under seal both with your SOUTHERN DISTRICT REPORTERS, P.C. (212) 805-0300 DOJ-OGR-00018250",
  "text_blocks": [
    {
      "type": "printed",
      "content": "Case 1:20-cr-00330-PAE Document 749 Filed 08/10/22 Page 149 of 236 1053 LC3Cmax5 Parkinson - direct.",
      "position": "header"
    },
    {
      "type": "printed",
      "content": "THE COURT: Actually, for simplicity, let's have the jurors put the binders under the chair until they're directed to look at something in particular. MS. COMEY: Okay, your Honor. Thank you. Q. Do you have exhibits 226 through 241 in the binder in front of you, Mr. Parkinson? A. I do. Q. And have you reviewed those, 226 through 241? A. No, I was only taking inventory. Q. Would you please review all of those and then let us know when you've finished. A. I'm ready. Q. Do you recognize those? A. I do. Q. What are they? A. These are photographs of the interior of the house, the ground floor, mostly in the garden room and lake room, partially in the hallway to the center part of the house looking from east to west into the lake room. Q. Do these exhibits fairly and accurately depict portions of the interior of the main house at 358 El Brillo Way as it appeared on October 20th, 2005? A. They do. MS. COMEY: Your Honor, the government offers these into evidence and ask that 234 be under seal both with your",
      "position": "main content"
    },
    {
      "type": "printed",
      "content": "SOUTHERN DISTRICT REPORTERS, P.C. (212) 805-0300",
      "position": "footer"
    },
    {
      "type": "printed",
      "content": "DOJ-OGR-00018250",
      "position": "footer"
    }
  ],
  "entities": {
    "people": [
      "MS. COMEY",
      "Mr. Parkinson"
    ],
    "organizations": [
      "SOUTHERN DISTRICT REPORTERS, P.C."
    ],
    "locations": [
      "358 El Brillo Way"
    ],
    "dates": [
      "08/10/22",
      "October 20th, 2005"
    ],
    "reference_numbers": [
      "1:20-cr-00330-PAE",
      "749",
      "226",
      "241",
      "234",
      "DOJ-OGR-00018250"
    ]
  },
  "additional_notes": "The document appears to be a court transcript with a clear and legible format. There are no visible redactions or damage."
}