{
  "document_metadata": {
    "page_number": "34",
    "document_number": "753",
    "date": "08/10/22",
    "document_type": "Court Transcript",
    "has_handwriting": false,
    "has_stamps": false
  },
  "full_text": "Case 1:20-cr-00330-PAE Document 753 Filed 08/10/22 Page 34 of 264 1460 LC7VMAX1 Meder - direct Maxwell investigation. Q. Under what 1B number was the CD logged? A. 1B75. Q. Who is in this photograph? A. Ghislaine Maxwell and Jeffrey Epstein. MS. COMEY: The government offers this in evidence, your Honor. THE COURT: Consistent with my ruling, GX-314 is admitted. You may publish. (Government's Exhibit 314 received in evidence) Q. Who is on the left, who's on the right? A. On the left, Ghislaine Maxwell; on the right, Jeffrey Epstein. MS. COMEY: Let's go now, please, Ms. Drescher, to Government Exhibit 317 for the witness, the Court, and the parties. Q. Do you recognize this? A. Yes. Q. What is it? A. It's a photo from a CD I reviewed from the Epstein and Maxwell investigation. Q. Under what 1B number was the CD logged? A. 1B75. Q. Who is in this photograph? A. Ghislaine Maxwell and Jeffrey Epstein. SOUTHERN DISTRICT REPORTERS, P.C. (212) 805-0300 DOJ-OGR-00018632",
  "text_blocks": [
    {
      "type": "printed",
      "content": "Case 1:20-cr-00330-PAE Document 753 Filed 08/10/22 Page 34 of 264 1460",
      "position": "header"
    },
    {
      "type": "printed",
      "content": "LC7VMAX1 Meder - direct",
      "position": "header"
    },
    {
      "type": "printed",
      "content": "Maxwell investigation. Q. Under what 1B number was the CD logged? A. 1B75. Q. Who is in this photograph? A. Ghislaine Maxwell and Jeffrey Epstein. MS. COMEY: The government offers this in evidence, your Honor. THE COURT: Consistent with my ruling, GX-314 is admitted. You may publish. (Government's Exhibit 314 received in evidence) Q. Who is on the left, who's on the right? A. On the left, Ghislaine Maxwell; on the right, Jeffrey Epstein. MS. COMEY: Let's go now, please, Ms. Drescher, to Government Exhibit 317 for the witness, the Court, and the parties. Q. Do you recognize this? A. Yes. Q. What is it? A. It's a photo from a CD I reviewed from the Epstein and Maxwell investigation. Q. Under what 1B number was the CD logged? A. 1B75. Q. Who is in this photograph? A. Ghislaine Maxwell and Jeffrey Epstein.",
      "position": "main"
    },
    {
      "type": "printed",
      "content": "SOUTHERN DISTRICT REPORTERS, P.C. (212) 805-0300",
      "position": "footer"
    },
    {
      "type": "printed",
      "content": "DOJ-OGR-00018632",
      "position": "footer"
    }
  ],
  "entities": {
    "people": [
      "Ghislaine Maxwell",
      "Jeffrey Epstein",
      "Ms. Drescher",
      "Ms. Comey"
    ],
    "organizations": [
      "SOUTHERN DISTRICT REPORTERS, P.C."
    ],
    "locations": [],
    "dates": [
      "08/10/22"
    ],
    "reference_numbers": [
      "1:20-cr-00330-PAE",
      "753",
      "1B75",
      "GX-314",
      "317",
      "DOJ-OGR-00018632"
    ]
  },
  "additional_notes": "The document appears to be a court transcript with a clear and legible format. There are no visible redactions or damage."
}