{
  "document_metadata": {
    "page_number": "97",
    "document_number": "755",
    "date": "08/10/22",
    "document_type": "court transcript",
    "has_handwriting": false,
    "has_stamps": false
  },
  "full_text": "Case 1:20-cr-00330-PAE Document 755 Filed 08/10/22 Page 97 of 262 1802 LC8VMAX4 Hesse - cross 1 A. That's correct. 2 Q. It appears to me that you were pretty precise when you were 3 taking messages, is that a fair statement? 4 A. That's fair. 5 Q. And then the other three on this page lack some of the 6 precision of your message-taking; correct? 7 A. That's true. 8 Q. Going forward, let's take a look at 1C. 9 MR. PAGLIUCA: And if the jurors could just follow 10 along, if that's all right, your Honor. 11 THE COURT: Yes. You may look at 1C, please, jurors. 12 Q. And again, 1C doesn't appear to have been taken at all by 13 you; correct? 14 A. I don't have anything on 1C; it's all blank. 15 Q. Okay. I have some messages on mine on 1C. 16 THE COURT: Mrs. Hesse is referring to the message on 17 the lower left-hand corner of 1C. The whole page is -- 18 THE WITNESS: Oh, the whole page is 1C, but the left 19 corner is blank. Okay. 20 Q. Yes. And just to orient us, this is not taken by you; 21 correct? 22 A. That is correct. 23 Q. And again, the top line, there is one in the top left for 24 Mr. Epstein, and then on the top right we've got Sarah, and 25 then I can't tell who the bottom right is. SOUTHERN DISTRICT REPORTERS, P.C. (212) 805-0300 DOJ-OGR-00018959",
  "text_blocks": [
    {
      "type": "printed",
      "content": "Case 1:20-cr-00330-PAE Document 755 Filed 08/10/22 Page 97 of 262 1802 LC8VMAX4 Hesse - cross",
      "position": "header"
    },
    {
      "type": "printed",
      "content": "1 A. That's correct. 2 Q. It appears to me that you were pretty precise when you were 3 taking messages, is that a fair statement? 4 A. That's fair. 5 Q. And then the other three on this page lack some of the 6 precision of your message-taking; correct? 7 A. That's true. 8 Q. Going forward, let's take a look at 1C. 9 MR. PAGLIUCA: And if the jurors could just follow 10 along, if that's all right, your Honor. 11 THE COURT: Yes. You may look at 1C, please, jurors. 12 Q. And again, 1C doesn't appear to have been taken at all by 13 you; correct? 14 A. I don't have anything on 1C; it's all blank. 15 Q. Okay. I have some messages on mine on 1C. 16 THE COURT: Mrs. Hesse is referring to the message on 17 the lower left-hand corner of 1C. The whole page is -- 18 THE WITNESS: Oh, the whole page is 1C, but the left 19 corner is blank. Okay. 20 Q. Yes. And just to orient us, this is not taken by you; 21 correct? 22 A. That is correct. 23 Q. And again, the top line, there is one in the top left for 24 Mr. Epstein, and then on the top right we've got Sarah, and 25 then I can't tell who the bottom right is.",
      "position": "main"
    },
    {
      "type": "printed",
      "content": "SOUTHERN DISTRICT REPORTERS, P.C. (212) 805-0300",
      "position": "footer"
    },
    {
      "type": "printed",
      "content": "DOJ-OGR-00018959",
      "position": "footer"
    }
  ],
  "entities": {
    "people": [
      "Mr. Pagliuca",
      "Mrs. Hesse",
      "Mr. Epstein",
      "Sarah"
    ],
    "organizations": [
      "SOUTHERN DISTRICT REPORTERS, P.C."
    ],
    "locations": [],
    "dates": [
      "08/10/22"
    ],
    "reference_numbers": [
      "1:20-cr-00330-PAE",
      "755",
      "DOJ-OGR-00018959"
    ]
  },
  "additional_notes": "The document appears to be a court transcript with a clear and legible format. There are no visible redactions or damage."
}