{
  "document_metadata": {
    "page_number": "1",
    "document_number": "99",
    "date": "10/09/2020",
    "document_type": "Court Order",
    "has_handwriting": true,
    "has_stamps": true
  },
  "full_text": "Case 20-3061, Document 99, 10/09/2020, 2948846, Page1 of 1\n\nUNITED STATES COURT OF APPEALS\nFOR THE\nSECOND CIRCUIT\n\nAt a Stated Term of the United States Court of Appeals for the Second Circuit, held at\nthe Thurgood Marshall United States Courthouse, 40 Foley Square, in the City of New York, on\nthe 9th day of October, two thousand nineteen,\n\nUnited States of America,\nAppellee,\n\nORDER\nDocket No. 20-3061\nv.\n\nGhislaine Maxwell, AKA Sealed Defendant 1,\nDefendant - Appellant.\n\nIT IS HEREBY ORDERED that the motion by Appellant for leave to file the unredacted\nreply brief under seal is GRANTED without prejudice to review by the panel in due course.\n\nFor The Court:\nCatherine O'Hagan Wolfe,\nClerk of Court\n\nCatherine O'Hagan Wolfe\nUNITED STATES COURT OF APPEALS\nSECOND CIRCUIT\n\nDOJ-OGR-00019676",
  "text_blocks": [
    {
      "type": "printed",
      "content": "Case 20-3061, Document 99, 10/09/2020, 2948846, Page1 of 1",
      "position": "header"
    },
    {
      "type": "printed",
      "content": "UNITED STATES COURT OF APPEALS\nFOR THE\nSECOND CIRCUIT",
      "position": "header"
    },
    {
      "type": "printed",
      "content": "At a Stated Term of the United States Court of Appeals for the Second Circuit, held at\nthe Thurgood Marshall United States Courthouse, 40 Foley Square, in the City of New York, on\nthe 9th day of October, two thousand nineteen,",
      "position": "body"
    },
    {
      "type": "printed",
      "content": "United States of America,\nAppellee,\n\nORDER\nDocket No. 20-3061\nv.\n\nGhislaine Maxwell, AKA Sealed Defendant 1,\nDefendant - Appellant.",
      "position": "body"
    },
    {
      "type": "printed",
      "content": "IT IS HEREBY ORDERED that the motion by Appellant for leave to file the unredacted\nreply brief under seal is GRANTED without prejudice to review by the panel in due course.",
      "position": "body"
    },
    {
      "type": "printed",
      "content": "For The Court:\nCatherine O'Hagan Wolfe,\nClerk of Court",
      "position": "body"
    },
    {
      "type": "handwritten",
      "content": "Catherine O'Hagan Wolfe",
      "position": "signature"
    },
    {
      "type": "stamp",
      "content": "UNITED STATES COURT OF APPEALS\nSECOND CIRCUIT",
      "position": "signature"
    },
    {
      "type": "printed",
      "content": "DOJ-OGR-00019676",
      "position": "footer"
    }
  ],
  "entities": {
    "people": [
      "Catherine O'Hagan Wolfe",
      "Ghislaine Maxwell"
    ],
    "organizations": [
      "United States Court of Appeals",
      "United States Courthouse"
    ],
    "locations": [
      "New York"
    ],
    "dates": [
      "10/09/2020",
      "9th day of October, two thousand nineteen"
    ],
    "reference_numbers": [
      "20-3061",
      "99",
      "2948846",
      "DOJ-OGR-00019676"
    ]
  },
  "additional_notes": "The document is a court order from the United States Court of Appeals for the Second Circuit. It appears to be a standard court document with a formal tone and language. The document is signed by Catherine O'Hagan Wolfe, Clerk of Court, and bears an official stamp of the court."
}