{
  "document_metadata": {
    "page_number": "219",
    "document_number": "745",
    "date": "08/10/22",
    "document_type": "Court Transcript",
    "has_handwriting": false,
    "has_stamps": false
  },
  "full_text": "Case 1:20-cr-00330-PAE Document 745 Filed 08/10/22 Page 219 of 264 630 LC1Qmax6 Matt - Direct examination of the witness testifying under the pseudonym Matt. MS. MOE: Thank you your Honor is the Court's order with respect to sketch artists now in effect? THE COURT: It is. MS. MOE: Thank you. DIRECT EXAMINATION BY MS. MOE: Q. Good afternoon. A. Good afternoon. Q. Are you testifying under the name Matt today? A. Yes. Q. Are you using a pseudonym in order to protect the privacy of the person you are going to be testifying about today? A. Yes. Q. I'd like you to just take a look at the witness stand. There's a folder in front of you. Would you mind just taking a look at that document. And that is what's marked for identification as Government Exhibit 17? A. Yes. Q. Without saying what's on the document, do you recognize that? A. Yes, I do. Q. What is that? A. It's my driver's license. Q. Is that your true name? SOUTHERN DISTRICT REPORTERS, P.C. (212) 805-0300 DOJ-OGR-00017828",
  "text_blocks": [
    {
      "type": "printed",
      "content": "Case 1:20-cr-00330-PAE Document 745 Filed 08/10/22 Page 219 of 264 630 LC1Qmax6 Matt - Direct",
      "position": "header"
    },
    {
      "type": "printed",
      "content": "examination of the witness testifying under the pseudonym Matt. MS. MOE: Thank you your Honor is the Court's order with respect to sketch artists now in effect? THE COURT: It is. MS. MOE: Thank you. DIRECT EXAMINATION BY MS. MOE: Q. Good afternoon. A. Good afternoon. Q. Are you testifying under the name Matt today? A. Yes. Q. Are you using a pseudonym in order to protect the privacy of the person you are going to be testifying about today? A. Yes. Q. I'd like you to just take a look at the witness stand. There's a folder in front of you. Would you mind just taking a look at that document. And that is what's marked for identification as Government Exhibit 17? A. Yes. Q. Without saying what's on the document, do you recognize that? A. Yes, I do. Q. What is that? A. It's my driver's license. Q. Is that your true name?",
      "position": "main"
    },
    {
      "type": "printed",
      "content": "SOUTHERN DISTRICT REPORTERS, P.C. (212) 805-0300",
      "position": "footer"
    },
    {
      "type": "printed",
      "content": "DOJ-OGR-00017828",
      "position": "footer"
    }
  ],
  "entities": {
    "people": [
      "Matt",
      "MS. MOE"
    ],
    "organizations": [
      "SOUTHERN DISTRICT REPORTERS, P.C.",
      "THE COURT"
    ],
    "locations": [],
    "dates": [
      "08/10/22"
    ],
    "reference_numbers": [
      "1:20-cr-00330-PAE",
      "745",
      "219",
      "264",
      "630",
      "LC1Qmax6",
      "Government Exhibit 17",
      "DOJ-OGR-00017828"
    ]
  },
  "additional_notes": "The document appears to be a court transcript with a clear and legible format. There are no visible redactions or damage."
}