{
  "document_metadata": {
    "page_number": "106",
    "document_number": "749",
    "date": "08/10/22",
    "document_type": "court transcript",
    "has_handwriting": false,
    "has_stamps": false
  },
  "full_text": "Case 1:20-cr-00330-PAE Document 749 Filed 08/10/22 Page 106 of 236 LC3Cmax3 Alessi - cross 1 different question. 2 THE COURT: Still has to be clear. 3 MR. PAGLIUCA: Yes. I will ask a different question. 4 BY MR. PAGLIUCA: 5 Q. You believed, when you were working for Mr. Epstein, that 6 the people who provided Mr. Epstein with massages were of age; 7 correct? 8 A. I believe -- I believe so, yes. 9 MR. PAGLIUCA: If I could have a moment, your Honor. 10 THE COURT: You may. 11 Q. One final question, Mr. Alessi. When you were there, you 12 don't recall meeting anyone named Carolyn; correct? 13 A. Karen? 14 Q. Carolyn. 15 A. Carolyn. Probably. 16 Q. You do or you don't? 17 A. Sir, I saw hundreds of guests at the house. I don't recall 18 their name. 19 MR. PAGLIUCA: Thank you. No other questions, your 20 Honor. 21 MS. COMEY: No redirect, your Honor. 22 THE COURT: Okay. Mr. Alessi, you may step down. You 23 are excused. Thank you. You're finished, yes. 24 THE WITNESS: Thank you. 25 THE COURT: Government may call its next witness. SOUTHERN DISTRICT REPORTERS, P.C. (212) 805-0300 DOJ-OGR-00018207",
  "text_blocks": [
    {
      "type": "printed",
      "content": "Case 1:20-cr-00330-PAE Document 749 Filed 08/10/22 Page 106 of 236",
      "position": "header"
    },
    {
      "type": "printed",
      "content": "LC3Cmax3 Alessi - cross",
      "position": "header"
    },
    {
      "type": "printed",
      "content": "1 different question. 2 THE COURT: Still has to be clear. 3 MR. PAGLIUCA: Yes. I will ask a different question. 4 BY MR. PAGLIUCA: 5 Q. You believed, when you were working for Mr. Epstein, that 6 the people who provided Mr. Epstein with massages were of age; 7 correct? 8 A. I believe -- I believe so, yes. 9 MR. PAGLIUCA: If I could have a moment, your Honor. 10 THE COURT: You may. 11 Q. One final question, Mr. Alessi. When you were there, you 12 don't recall meeting anyone named Carolyn; correct? 13 A. Karen? 14 Q. Carolyn. 15 A. Carolyn. Probably. 16 Q. You do or you don't? 17 A. Sir, I saw hundreds of guests at the house. I don't recall 18 their name. 19 MR. PAGLIUCA: Thank you. No other questions, your 20 Honor. 21 MS. COMEY: No redirect, your Honor. 22 THE COURT: Okay. Mr. Alessi, you may step down. You 23 are excused. Thank you. You're finished, yes. 24 THE WITNESS: Thank you. 25 THE COURT: Government may call its next witness.",
      "position": "main"
    },
    {
      "type": "printed",
      "content": "SOUTHERN DISTRICT REPORTERS, P.C. (212) 805-0300",
      "position": "footer"
    },
    {
      "type": "printed",
      "content": "DOJ-OGR-00018207",
      "position": "footer"
    }
  ],
  "entities": {
    "people": [
      "Mr. Epstein",
      "Mr. Alessi",
      "Mr. Pagliuca",
      "Carolyn",
      "Karen",
      "Ms. Comey"
    ],
    "organizations": [
      "SOUTHERN DISTRICT REPORTERS, P.C."
    ],
    "locations": [],
    "dates": [
      "08/10/22"
    ],
    "reference_numbers": [
      "1:20-cr-00330-PAE",
      "749",
      "DOJ-OGR-00018207"
    ]
  },
  "additional_notes": "The document appears to be a court transcript with a clear and legible format. There are no visible redactions or damage."
}