{
  "document_metadata": {
    "page_number": "36",
    "document_number": "749",
    "date": "08/10/22",
    "document_type": "court transcript",
    "has_handwriting": false,
    "has_stamps": false
  },
  "full_text": "Case 1:20-cr-00330-PAE Document 749 Filed 08/10/22 Page 36 of 236 940 LC3Cmax1 Alessi - cross 1 Q. And then you looked at the jury and you said, I will tell the truth. 2 the truth. 3 Do you remember that, telling the jury that yesterday? 4 A. Yes. 5 Q. But you didn't tell the jury the truth yesterday, did you, 6 Mr. Alessi? 7 A. I did tell the truth. 8 Q. Well, isn't it true, isn't it true that you went into 9 Mr. Epstein's house two times in 2003 and stole money twice 10 from Mr. Epstein? 11 A. No, it was one time. 12 Q. Isn't it true that the first time was in August or 13 September of 2003 and you went in to steal a gun, but you 14 couldn't find a gun? 15 A. That's not true. 16 Q. Isn't it true that the second time that you went into 17 Mr. Epstein's house -- well, when you couldn't find the gun, 18 isn't it true that you looked around and took $1,900 in $100 19 bills from a white envelope, isn't that true? 20 A. That's not true. 21 Q. Didn't you go back on October 5th, 2003 and steal $5,600 22 from Mr. Epstein? 23 A. No, that's not true. 24 Q. And isn't it true that you stole the money to pay for your 25 girlfriend's immigration papers? SOUTHERN DISTRICT REPORTERS, P.C. (212) 805-0300 DOJ-OGR-00018137",
  "text_blocks": [
    {
      "type": "printed",
      "content": "Case 1:20-cr-00330-PAE Document 749 Filed 08/10/22 Page 36 of 236 940",
      "position": "header"
    },
    {
      "type": "printed",
      "content": "LC3Cmax1 Alessi - cross",
      "position": "header"
    },
    {
      "type": "printed",
      "content": "1 Q. And then you looked at the jury and you said, I will tell the truth. 2 the truth. 3 Do you remember that, telling the jury that yesterday? 4 A. Yes. 5 Q. But you didn't tell the jury the truth yesterday, did you, 6 Mr. Alessi? 7 A. I did tell the truth. 8 Q. Well, isn't it true, isn't it true that you went into 9 Mr. Epstein's house two times in 2003 and stole money twice 10 from Mr. Epstein? 11 A. No, it was one time. 12 Q. Isn't it true that the first time was in August or 13 September of 2003 and you went in to steal a gun, but you 14 couldn't find a gun? 15 A. That's not true. 16 Q. Isn't it true that the second time that you went into 17 Mr. Epstein's house -- well, when you couldn't find the gun, 18 isn't it true that you looked around and took $1,900 in $100 19 bills from a white envelope, isn't that true? 20 A. That's not true. 21 Q. Didn't you go back on October 5th, 2003 and steal $5,600 22 from Mr. Epstein? 23 A. No, that's not true. 24 Q. And isn't it true that you stole the money to pay for your 25 girlfriend's immigration papers?",
      "position": "main"
    },
    {
      "type": "printed",
      "content": "SOUTHERN DISTRICT REPORTERS, P.C. (212) 805-0300",
      "position": "footer"
    },
    {
      "type": "printed",
      "content": "DOJ-OGR-00018137",
      "position": "footer"
    }
  ],
  "entities": {
    "people": [
      "Mr. Alessi",
      "Mr. Epstein"
    ],
    "organizations": [
      "SOUTHERN DISTRICT REPORTERS, P.C."
    ],
    "locations": [],
    "dates": [
      "08/10/22",
      "2003",
      "August 2003",
      "September 2003",
      "October 5th, 2003"
    ],
    "reference_numbers": [
      "1:20-cr-00330-PAE",
      "749",
      "DOJ-OGR-00018137"
    ]
  },
  "additional_notes": "The document appears to be a court transcript with a clear Q&A format. The content is related to a legal case involving Mr. Epstein and Mr. Alessi. The document is well-formatted and legible."
}