{
  "document_metadata": {
    "page_number": "204",
    "document_number": "751",
    "date": "08/10/22",
    "document_type": "court transcript",
    "has_handwriting": false,
    "has_stamps": false
  },
  "full_text": "Case 1:20-cr-00330-PAE Document 751 Filed 08/10/22 Page 204 of 261 1365 LC6VMAX6 Maguire - direct you encountered during the search? A. There were approximately 40. Q. After you had labeled the rooms within the residence, how did the search proceed from there? A. We started taking photographs of the residence, and then after that the search began. Q. Did there come a time when you obtained legal authority to continue searching the house for other items? A. Yes, that's correct. Q. Was that during the course of the same search? A. Yes. Q. I want to talk with you now about the interior of the residence. MS. MOE: Ms. Drescher, if you could please show just the witness, the Court, and counsel, just cycling through them, what's been marked for identification as Government Exhibits 933, 910, and 911. Q. Special Agent Maguire, do you recognize these? A. Yes, I do. THE COURT: It's really 911-R; correct? MS. MOE: Apologies, your Honor. 911-R. Q. Do you recognize these three exhibits? A. Yes, I do. Q. And what are Government Exhibits 933, 910, and 911-R? A. These are the first entryway and the main foyer near the SOUTHERN DISTRICT REPORTERS, P.C. (212) 805-0300 DOJ-OGR-00018541",
  "text_blocks": [
    {
      "type": "printed",
      "content": "Case 1:20-cr-00330-PAE Document 751 Filed 08/10/22 Page 204 of 261 1365 LC6VMAX6 Maguire - direct",
      "position": "header"
    },
    {
      "type": "printed",
      "content": "you encountered during the search? A. There were approximately 40. Q. After you had labeled the rooms within the residence, how did the search proceed from there? A. We started taking photographs of the residence, and then after that the search began. Q. Did there come a time when you obtained legal authority to continue searching the house for other items? A. Yes, that's correct. Q. Was that during the course of the same search? A. Yes. Q. I want to talk with you now about the interior of the residence. MS. MOE: Ms. Drescher, if you could please show just the witness, the Court, and counsel, just cycling through them, what's been marked for identification as Government Exhibits 933, 910, and 911. Q. Special Agent Maguire, do you recognize these? A. Yes, I do. THE COURT: It's really 911-R; correct? MS. MOE: Apologies, your Honor. 911-R. Q. Do you recognize these three exhibits? A. Yes, I do. Q. And what are Government Exhibits 933, 910, and 911-R? A. These are the first entryway and the main foyer near the",
      "position": "main"
    },
    {
      "type": "printed",
      "content": "SOUTHERN DISTRICT REPORTERS, P.C. (212) 805-0300",
      "position": "footer"
    },
    {
      "type": "printed",
      "content": "DOJ-OGR-00018541",
      "position": "footer"
    }
  ],
  "entities": {
    "people": [
      "Maguire",
      "Ms. Drescher",
      "Ms. Moe"
    ],
    "organizations": [
      "SOUTHERN DISTRICT REPORTERS, P.C."
    ],
    "locations": [],
    "dates": [
      "08/10/22"
    ],
    "reference_numbers": [
      "1:20-cr-00330-PAE",
      "751",
      "933",
      "910",
      "911",
      "911-R",
      "DOJ-OGR-00018541"
    ]
  },
  "additional_notes": "The document appears to be a court transcript with a clear and legible format. There are no visible redactions or damage."
}