{
  "document_metadata": {
    "page_number": "147",
    "document_number": "755",
    "date": "08/10/22",
    "document_type": "court transcript",
    "has_handwriting": false,
    "has_stamps": false
  },
  "full_text": "Case 1:20-cr-00330-PAE Document 755 Filed 08/10/22 Page 147 of 262 1858\nLC8Cmax5 Rodgers - direct\n1 Q. Is Jeffrey Epstein a passenger on this flight?\n2 A. Yes.\n3 Q. Is Ghislaine Maxwell a passenger on this flight?\n4 A. Yes.\n5 Q. Is Virginia Roberts a passenger on this flight?\n6 A. Yes.\n7 Q. Is her full name in this entry?\n8 A. Yes.\n9 Q. And is there one other passenger?\n10 A. Yes.\n11 Q. Let's go to the very next flight, please, 1446. What's the date of that?\n12 A. This is January the 30th, 2001.\n13 Q. Where were you flying from and where were you flying to?\n14 A. St. Thomas, U.S. Virgin Islands, to Palm Beach, Florida.\n15 Q. Was Jeffrey Epstein a passenger on this flight?\n16 A. Yes.\n17 Q. Was Ghislaine Maxwell a passenger on this flight?\n18 A. Yes.\n19 Q. Was Virginia Roberts a passenger on this flight?\n20 A. Yes.\n21 Q. Is her full name in this entry?\n22 A. Yes.\n23 Q. And was there another passenger on this flight?\n24 A. Yes.\n25 SOUTHERN DISTRICT REPORTERS, P.C. (212) 805-0300\nDOJ-OGR-00019009",
  "text_blocks": [
    {
      "type": "printed",
      "content": "Case 1:20-cr-00330-PAE Document 755 Filed 08/10/22 Page 147 of 262 1858",
      "position": "header"
    },
    {
      "type": "printed",
      "content": "LC8Cmax5 Rodgers - direct",
      "position": "header"
    },
    {
      "type": "printed",
      "content": "1 Q. Is Jeffrey Epstein a passenger on this flight?\n2 A. Yes.\n3 Q. Is Ghislaine Maxwell a passenger on this flight?\n4 A. Yes.\n5 Q. Is Virginia Roberts a passenger on this flight?\n6 A. Yes.\n7 Q. Is her full name in this entry?\n8 A. Yes.\n9 Q. And is there one other passenger?\n10 A. Yes.\n11 Q. Let's go to the very next flight, please, 1446. What's the date of that?\n12 A. This is January the 30th, 2001.\n13 Q. Where were you flying from and where were you flying to?\n14 A. St. Thomas, U.S. Virgin Islands, to Palm Beach, Florida.\n15 Q. Was Jeffrey Epstein a passenger on this flight?\n16 A. Yes.\n17 Q. Was Ghislaine Maxwell a passenger on this flight?\n18 A. Yes.\n19 Q. Was Virginia Roberts a passenger on this flight?\n20 A. Yes.\n21 Q. Is her full name in this entry?\n22 A. Yes.\n23 Q. And was there another passenger on this flight?\n24 A. Yes.",
      "position": "main"
    },
    {
      "type": "printed",
      "content": "SOUTHERN DISTRICT REPORTERS, P.C. (212) 805-0300",
      "position": "footer"
    },
    {
      "type": "printed",
      "content": "DOJ-OGR-00019009",
      "position": "footer"
    }
  ],
  "entities": {
    "people": [
      "Jeffrey Epstein",
      "Ghislaine Maxwell",
      "Virginia Roberts"
    ],
    "organizations": [
      "SOUTHERN DISTRICT REPORTERS, P.C."
    ],
    "locations": [
      "St. Thomas",
      "U.S. Virgin Islands",
      "Palm Beach",
      "Florida"
    ],
    "dates": [
      "January 30th, 2001",
      "08/10/22"
    ],
    "reference_numbers": [
      "1:20-cr-00330-PAE",
      "755",
      "DOJ-OGR-00019009"
    ]
  },
  "additional_notes": "The document appears to be a court transcript with a clear and legible format. There are no visible redactions or damage."
}