{
  "document_metadata": {
    "page_number": "118",
    "document_number": "39-2",
    "date": "04/01/2021",
    "document_type": "court document",
    "has_handwriting": false,
    "has_stamps": false
  },
  "full_text": "Case 21-58, Document 39-2, 04/01/2021, 3068530, Page118 of 200\n55\n1    breached the gate and they saw her through the window try to\n2    flee to another room in the house, quickly shutting the door,\n3    and that she -- agents were ultimately forced to breach the\n4    door. So here is the spin. It's as if the government is just\n5    sort of giving it for the media, here is the spin given to your\n6    Honor to try to influence your Honor's discretion. What\n7    actually happened? At least the court has said we can respond\n8    by proffer. We weren't given a chance to respond in writing.\n9    My client was at the property in the morning in her pajamas.\n10   She was there with one security guard. Two people in the\n11   house. The front door was unlocked. All the other doors of\n12   the house were open. The windows were open. Dozens of agents\n13   came storming up the drive, creating a disturbance. My client\n14   had to hire security because of the threats to her that I have\n15   already relayed before, and the protocol was that in a\n16   disturbance to go into new room. That's all she did. Not\n17   running out of the house, not, you know, looking for some\n18   secret tunnel, went in the other room. The F.B.I. knocked down\n19   the door which, by the way, was open, and my client surrendered\n20   herself for arrest. That's far from the picture painted by the\n21   government.\n22        Let me turn to another thing that the government\n23   mentioned today in an effort to sort of spin the facts, make\n24   everything look sinister with respect to my client. The\n25   government said in its opening brief, well, Judge, she is\n\nSOUTHERN DISTRICT REPORTERS, P.C.\n(212) 805-0300\nDOJ-OGR-00019977",
  "text_blocks": [
    {
      "type": "printed",
      "content": "Case 21-58, Document 39-2, 04/01/2021, 3068530, Page118 of 200",
      "position": "header"
    },
    {
      "type": "printed",
      "content": "55\n1    breached the gate and they saw her through the window try to\n2    flee to another room in the house, quickly shutting the door,\n3    and that she -- agents were ultimately forced to breach the\n4    door. So here is the spin. It's as if the government is just\n5    sort of giving it for the media, here is the spin given to your\n6    Honor to try to influence your Honor's discretion. What\n7    actually happened? At least the court has said we can respond\n8    by proffer. We weren't given a chance to respond in writing.\n9    My client was at the property in the morning in her pajamas.\n10   She was there with one security guard. Two people in the\n11   house. The front door was unlocked. All the other doors of\n12   the house were open. The windows were open. Dozens of agents\n13   came storming up the drive, creating a disturbance. My client\n14   had to hire security because of the threats to her that I have\n15   already relayed before, and the protocol was that in a\n16   disturbance to go into new room. That's all she did. Not\n17   running out of the house, not, you know, looking for some\n18   secret tunnel, went in the other room. The F.B.I. knocked down\n19   the door which, by the way, was open, and my client surrendered\n20   herself for arrest. That's far from the picture painted by the\n21   government.\n22        Let me turn to another thing that the government\n23   mentioned today in an effort to sort of spin the facts, make\n24   everything look sinister with respect to my client. The\n25   government said in its opening brief, well, Judge, she is",
      "position": "main content"
    },
    {
      "type": "printed",
      "content": "SOUTHERN DISTRICT REPORTERS, P.C.\n(212) 805-0300",
      "position": "footer"
    },
    {
      "type": "printed",
      "content": "DOJ-OGR-00019977",
      "position": "footer"
    }
  ],
  "entities": {
    "people": [],
    "organizations": [
      "F.B.I.",
      "SOUTHERN DISTRICT REPORTERS, P.C."
    ],
    "locations": [],
    "dates": [
      "04/01/2021"
    ],
    "reference_numbers": [
      "Case 21-58",
      "Document 39-2",
      "3068530",
      "DOJ-OGR-00019977"
    ]
  },
  "additional_notes": "The document appears to be a court transcript or legal document. It is typed and contains a formal tone. There are no visible redactions or damage."
}