{
  "document_metadata": {
    "page_number": "13",
    "document_number": "753",
    "date": "08/10/22",
    "document_type": "court transcript",
    "has_handwriting": false,
    "has_stamps": false
  },
  "full_text": "Case 1:20-cr-00330-PAE Document 753 Filed 08/10/22 Page 13 of 264 1435 LC7VMAX1\n\nYour Honor, with respect to any testimony that was in the November 26 disclosure, which I believe is not what was disclosed earlier in September, but most of it is what I would agree is factual testimony. If a document has metadata, any old person can right-click on it, look at the properties, and read what those properties are.\n\nThere's only one portion of the November 26 disclosure that I believe treads into opinion expert land, and that is on the second page of the November 26 disclosure where Mr. Flatley will testify that he verified the accuracy of metadata by running a particular program. He will explain what metadata is, such as the file name and when the file was created, and where it can be stored in a computer system.\n\nYour Honor, if those are the only things that Mr. Flatley intends to testify about, then I think we're fine. It's the things that came in the disclosures on November -- there were more on November 26 that were not in this letter and there were things on December 3rd that were disclosed. If he is limited to those things that were put in the September 26 disclosure, I'm fine with that, your Honor.\n\nHe also was not ever disclosed as a fact or expert witness with regard to CDs. The original notice and the supplemental notice all refer to his review of devices. So I believe that the government does not intend to put on evidence about CDs through him, but those are the two areas that I think\n\nSOUTHERN DISTRICT REPORTERS, P.C. (212) 805-0300\n\nDOJ-OGR-00018611",
  "text_blocks": [
    {
      "type": "printed",
      "content": "Case 1:20-cr-00330-PAE Document 753 Filed 08/10/22 Page 13 of 264 1435 LC7VMAX1",
      "position": "header"
    },
    {
      "type": "printed",
      "content": "Your Honor, with respect to any testimony that was in the November 26 disclosure, which I believe is not what was disclosed earlier in September, but most of it is what I would agree is factual testimony. If a document has metadata, any old person can right-click on it, look at the properties, and read what those properties are.",
      "position": "top"
    },
    {
      "type": "printed",
      "content": "There's only one portion of the November 26 disclosure that I believe treads into opinion expert land, and that is on the second page of the November 26 disclosure where Mr. Flatley will testify that he verified the accuracy of metadata by running a particular program. He will explain what metadata is, such as the file name and when the file was created, and where it can be stored in a computer system.",
      "position": "middle"
    },
    {
      "type": "printed",
      "content": "Your Honor, if those are the only things that Mr. Flatley intends to testify about, then I think we're fine. It's the things that came in the disclosures on November -- there were more on November 26 that were not in this letter and there were things on December 3rd that were disclosed. If he is limited to those things that were put in the September 26 disclosure, I'm fine with that, your Honor.",
      "position": "middle"
    },
    {
      "type": "printed",
      "content": "He also was not ever disclosed as a fact or expert witness with regard to CDs. The original notice and the supplemental notice all refer to his review of devices. So I believe that the government does not intend to put on evidence about CDs through him, but those are the two areas that I think",
      "position": "middle"
    },
    {
      "type": "printed",
      "content": "SOUTHERN DISTRICT REPORTERS, P.C. (212) 805-0300",
      "position": "footer"
    },
    {
      "type": "printed",
      "content": "DOJ-OGR-00018611",
      "position": "footer"
    }
  ],
  "entities": {
    "people": [
      "Mr. Flatley"
    ],
    "organizations": [
      "SOUTHERN DISTRICT REPORTERS, P.C."
    ],
    "locations": [],
    "dates": [
      "November 26",
      "September",
      "December 3rd",
      "September 26",
      "08/10/22"
    ],
    "reference_numbers": [
      "1:20-cr-00330-PAE",
      "753",
      "DOJ-OGR-00018611"
    ]
  },
  "additional_notes": "The document appears to be a court transcript with a clear and readable format. There are no visible redactions or damage."
}