{
  "document_metadata": {
    "page_number": "181",
    "document_number": "755",
    "date": "08/10/22",
    "document_type": "court transcript",
    "has_handwriting": false,
    "has_stamps": false
  },
  "full_text": "Case 1:20-cr-00330-PAE Document 755 Filed 08/10/22 Page 181 of 262 1892\nLC8VMAX6 Rodgers - cross\n1 A. I see it.\n2 According to this, it's been a long time ago.\n3 Q. Well, it is, sir, yes.\n4 A. I stand corrected.\n5 Q. Does that refresh your recollection that it was your impression that Sarah Kellen took over as Epstein's primary assistant in late 2001?\n6\n7 A. Yes.\n8\n9 Q. Okay. Thank you.\n10 You can put that away for now, Mr. Rodgers.\n11 A. Okay.\n12 Q. So, I'm sorry, I'll wait till you're ready.\n13 A. Yeah, sure.\n14\n15 Q. Okay. So then in the 2000s, starting in late 2001, I guess Larry Visoski would often speak to Sarah Kellen about scheduling flights; correct?\n16\n17 A. Yes.\n18 Q. She was the one who would arrange the flight departures generally?\n19\n20 A. Sarah?\n21 Q. Sarah.\n22 A. Yes.\n23 Q. And she was the one who arranged the luggage transfers back -- to and from the residences in your houses?\n24\n25 A. Yes, most likely.\nSOUTHERN DISTRICT REPORTERS, P.C. (212) 805-0300\nDOJ-OGR-00019043",
  "text_blocks": [
    {
      "type": "printed",
      "content": "Case 1:20-cr-00330-PAE Document 755 Filed 08/10/22 Page 181 of 262 1892",
      "position": "header"
    },
    {
      "type": "printed",
      "content": "LC8VMAX6 Rodgers - cross",
      "position": "header"
    },
    {
      "type": "printed",
      "content": "1 A. I see it.\n2 According to this, it's been a long time ago.\n3 Q. Well, it is, sir, yes.\n4 A. I stand corrected.\n5 Q. Does that refresh your recollection that it was your impression that Sarah Kellen took over as Epstein's primary assistant in late 2001?\n6\n7 A. Yes.\n8\n9 Q. Okay. Thank you.\n10 You can put that away for now, Mr. Rodgers.\n11 A. Okay.\n12 Q. So, I'm sorry, I'll wait till you're ready.\n13 A. Yeah, sure.\n14\n15 Q. Okay. So then in the 2000s, starting in late 2001, I guess Larry Visoski would often speak to Sarah Kellen about scheduling flights; correct?\n16\n17 A. Yes.\n18 Q. She was the one who would arrange the flight departures generally?\n19\n20 A. Sarah?\n21 Q. Sarah.\n22 A. Yes.\n23 Q. And she was the one who arranged the luggage transfers back -- to and from the residences in your houses?\n24\n25 A. Yes, most likely.",
      "position": "main"
    },
    {
      "type": "printed",
      "content": "SOUTHERN DISTRICT REPORTERS, P.C. (212) 805-0300",
      "position": "footer"
    },
    {
      "type": "printed",
      "content": "DOJ-OGR-00019043",
      "position": "footer"
    }
  ],
  "entities": {
    "people": [
      "Sarah Kellen",
      "Epstein",
      "Larry Visoski",
      "Mr. Rodgers"
    ],
    "organizations": [
      "SOUTHERN DISTRICT REPORTERS, P.C."
    ],
    "locations": [],
    "dates": [
      "08/10/22",
      "late 2001"
    ],
    "reference_numbers": [
      "1:20-cr-00330-PAE",
      "755",
      "DOJ-OGR-00019043",
      "LC8VMAX6",
      "(212) 805-0300"
    ]
  },
  "additional_notes": "The document appears to be a court transcript with a clear and legible format. There are no visible redactions or damage."
}