{
  "document_metadata": {
    "page_number": "11",
    "document_number": "755",
    "date": "08/10/22",
    "document_type": "court transcript",
    "has_handwriting": false,
    "has_stamps": false
  },
  "full_text": "Case 1:20-cr-00330-PAE Document 755 Filed 08/10/22 Page 11 of 262 1716 LC8Cmax1\nthat Virginia Roberts is the Virginia Roberts in the birth certificate, which relative to her age, to which is therefore relevant to the sex trafficking counts.\nI'd also note that the phone number for Sky Roberts in these documents is the phone number for an entry in Government Exhibit 52 for -- that's listed as Virginia parents. So in the event that Government Exhibit 52 comes in, this is relevant to show that that entry, in fact, is the phone number for Virginia Roberts's parents.\nSo those are the various three theories of relevance.\nIn terms of admissibility under the business record exception, Ms. Gill, the witness, is a records custodian for Mar-a-Lago. So she will say that personal action notices are created in the ordinary course of business by managers at Mar-a-Lago at the time an employee is hired and that once an employee is eligible for benefits at Mar-a-Lago, those employees fill out the benefit application form in Government Exhibit 824 and submit them to Mar-a-Lago, which processes them, sends them out to insurance companies and retains them for Mar-a-Lago's own business purposes.\nTHE COURT: And these were records that were maintained at Mar-a-Lago?\nMR. ROHRBACH: Yes, your Honor. I expect Ms. Gill to say that she has looked at these records in Mar-a-Lago's personnel file and confirms that they are true and accurate\nSOUTHERN DISTRICT REPORTERS, P.C. (212) 805-0300\nDOJ-OGR-00018873",
  "text_blocks": [
    {
      "type": "printed",
      "content": "Case 1:20-cr-00330-PAE Document 755 Filed 08/10/22 Page 11 of 262 1716 LC8Cmax1",
      "position": "header"
    },
    {
      "type": "printed",
      "content": "that Virginia Roberts is the Virginia Roberts in the birth certificate, which relative to her age, to which is therefore relevant to the sex trafficking counts.\nI'd also note that the phone number for Sky Roberts in these documents is the phone number for an entry in Government Exhibit 52 for -- that's listed as Virginia parents. So in the event that Government Exhibit 52 comes in, this is relevant to show that that entry, in fact, is the phone number for Virginia Roberts's parents.\nSo those are the various three theories of relevance.\nIn terms of admissibility under the business record exception, Ms. Gill, the witness, is a records custodian for Mar-a-Lago. So she will say that personal action notices are created in the ordinary course of business by managers at Mar-a-Lago at the time an employee is hired and that once an employee is eligible for benefits at Mar-a-Lago, those employees fill out the benefit application form in Government Exhibit 824 and submit them to Mar-a-Lago, which processes them, sends them out to insurance companies and retains them for Mar-a-Lago's own business purposes.",
      "position": "main content"
    },
    {
      "type": "printed",
      "content": "THE COURT: And these were records that were maintained at Mar-a-Lago?\nMR. ROHRBACH: Yes, your Honor. I expect Ms. Gill to say that she has looked at these records in Mar-a-Lago's personnel file and confirms that they are true and accurate",
      "position": "main content"
    },
    {
      "type": "printed",
      "content": "SOUTHERN DISTRICT REPORTERS, P.C. (212) 805-0300",
      "position": "footer"
    },
    {
      "type": "printed",
      "content": "DOJ-OGR-00018873",
      "position": "footer"
    }
  ],
  "entities": {
    "people": [
      "Virginia Roberts",
      "Sky Roberts",
      "Ms. Gill",
      "MR. ROHRBACH"
    ],
    "organizations": [
      "Mar-a-Lago",
      "SOUTHERN DISTRICT REPORTERS, P.C."
    ],
    "locations": [],
    "dates": [
      "08/10/22"
    ],
    "reference_numbers": [
      "1:20-cr-00330-PAE",
      "755",
      "DOJ-OGR-00018873",
      "Government Exhibit 52",
      "Government Exhibit 824"
    ]
  },
  "additional_notes": "The document appears to be a court transcript with clear and legible text. There are no visible redactions or damage."
}