{
  "document_metadata": {
    "page_number": "132",
    "document_number": "745",
    "date": "08/10/22",
    "document_type": "Court Transcript",
    "has_handwriting": false,
    "has_stamps": false
  },
  "full_text": "Case 1:20-cr-00330-PAE Document 745 Filed 08/10/22 Page 132 of 264 543 LC1Qmax4 Jane - Cross 1 A. Yes. 2 Q. Mr. Glassman is a personal injury lawyer, right? 3 A. Yes. 4 Q. Mr. Glassman, touts the very large verdicts that he has received on his web page, correct? 5 6 MS. MOE: Objection. 7 THE COURT: Grounds. 8 MS. MOE: Hearsay. 9 THE COURT: Sustained. 10 Q. Are you aware of Mr. Glassman's advertising? 11 A. No. 12 Q. Did you ever look at his website? 13 A. No. He's a friend of a friend. 14 Q. You hired him on September 3 of 2019, correct? 15 A. I don't know the exact date, but -- 16 Q. Okay. Let's take a look at J-14. Do you recognize that document? 17 18 A. Yes. 19 Q. And what is that document? 20 A. Attorney-client contingent fee contract. 21 Q. That's between you and Mr. Glassman, right? 22 A. Yes. 23 Q. If you could look at the last page, does that refresh your recollection about when you hired Mr. Glassman? 24 25 A. Yes. SOUTHERN DISTRICT REPORTERS, P.C. (212) 805-0300 DOJ-OGR-00017741",
  "text_blocks": [
    {
      "type": "printed",
      "content": "Case 1:20-cr-00330-PAE Document 745 Filed 08/10/22 Page 132 of 264 543",
      "position": "header"
    },
    {
      "type": "printed",
      "content": "LC1Qmax4 Jane - Cross",
      "position": "header"
    },
    {
      "type": "printed",
      "content": "1 A. Yes. 2 Q. Mr. Glassman is a personal injury lawyer, right? 3 A. Yes. 4 Q. Mr. Glassman, touts the very large verdicts that he has received on his web page, correct? 5 6 MS. MOE: Objection. 7 THE COURT: Grounds. 8 MS. MOE: Hearsay. 9 THE COURT: Sustained. 10 Q. Are you aware of Mr. Glassman's advertising? 11 A. No. 12 Q. Did you ever look at his website? 13 A. No. He's a friend of a friend. 14 Q. You hired him on September 3 of 2019, correct? 15 A. I don't know the exact date, but -- 16 Q. Okay. Let's take a look at J-14. Do you recognize that document? 17 18 A. Yes. 19 Q. And what is that document? 20 A. Attorney-client contingent fee contract. 21 Q. That's between you and Mr. Glassman, right? 22 A. Yes. 23 Q. If you could look at the last page, does that refresh your recollection about when you hired Mr. Glassman? 24 25 A. Yes.",
      "position": "main"
    },
    {
      "type": "printed",
      "content": "SOUTHERN DISTRICT REPORTERS, P.C. (212) 805-0300",
      "position": "footer"
    },
    {
      "type": "printed",
      "content": "DOJ-OGR-00017741",
      "position": "footer"
    }
  ],
  "entities": {
    "people": [
      "Mr. Glassman"
    ],
    "organizations": [
      "SOUTHERN DISTRICT REPORTERS, P.C."
    ],
    "locations": [],
    "dates": [
      "September 3 of 2019",
      "08/10/22"
    ],
    "reference_numbers": [
      "1:20-cr-00330-PAE",
      "745",
      "J-14",
      "DOJ-OGR-00017741"
    ]
  },
  "additional_notes": "The document appears to be a court transcript with a clear and legible format. There are no visible redactions or damage."
}