{
  "document_metadata": {
    "page_number": "253",
    "document_number": "755",
    "date": "08/10/22",
    "document_type": "court transcript",
    "has_handwriting": false,
    "has_stamps": false
  },
  "full_text": "Case 1:20-cr-00330-PAE Document 755 Filed 08/10/22 Page 253 of 262 1964 LC8Cmax7 Rodgers - redirect 1 A. Yes. 2 Q. And do you recall being shown defense LV3A and defense LV3B, two photographs? 3 4 A. I recall that, but can I look at the photographs? 5 MS. COMEY: With the Judge's permission, I have no problem with that. 6 7 THE COURT: Yes. 8 A. Oh, I think I know what it is. Yes, I recall. 9 Q. And the person in that photograph has the same first name as Jane's true first name; is that right? 10 11 A. Correct. 12 Q. Who did you meet first, Jane or the person in those photographs? 13 14 A. Jane. 15 (Continued on next page) 16 17 18 19 20 21 22 23 24 25 SOUTHERN DISTRICT REPORTERS, P.C. (212) 805-0300 DOJ-OGR-00019115",
  "text_blocks": [
    {
      "type": "printed",
      "content": "Case 1:20-cr-00330-PAE Document 755 Filed 08/10/22 Page 253 of 262 1964 LC8Cmax7 Rodgers - redirect",
      "position": "header"
    },
    {
      "type": "printed",
      "content": "1 A. Yes. 2 Q. And do you recall being shown defense LV3A and defense LV3B, two photographs? 3 4 A. I recall that, but can I look at the photographs? 5 MS. COMEY: With the Judge's permission, I have no problem with that. 6 7 THE COURT: Yes. 8 A. Oh, I think I know what it is. Yes, I recall. 9 Q. And the person in that photograph has the same first name as Jane's true first name; is that right? 10 11 A. Correct. 12 Q. Who did you meet first, Jane or the person in those photographs? 13 14 A. Jane. 15 (Continued on next page)",
      "position": "main content"
    },
    {
      "type": "printed",
      "content": "SOUTHERN DISTRICT REPORTERS, P.C. (212) 805-0300",
      "position": "footer"
    },
    {
      "type": "printed",
      "content": "DOJ-OGR-00019115",
      "position": "footer"
    }
  ],
  "entities": {
    "people": [
      "Jane",
      "Comey"
    ],
    "organizations": [
      "SOUTHERN DISTRICT REPORTERS, P.C."
    ],
    "locations": [],
    "dates": [
      "08/10/22"
    ],
    "reference_numbers": [
      "1:20-cr-00330-PAE",
      "755",
      "DOJ-OGR-00019115"
    ]
  },
  "additional_notes": "The document is a court transcript with a clear and readable format. There are no visible redactions or damage."
}