{
  "document_metadata": {
    "page_number": "180",
    "document_number": "745",
    "date": "08/10/22",
    "document_type": "court transcript",
    "has_handwriting": false,
    "has_stamps": false
  },
  "full_text": "Case 1:20-cr-00330-PAE Document 745 Filed 08/10/22 Page 180 of 264 591 LC1VMAX5 Jane - cross 1 Q. You played a prostitute? 2 A. Not my favorite storyline. 3 Q. You ran a restaurant? 4 A. Yes. 5 Q. You took down a Mexican drug cartel? 6 A. Yes. 7 Q. Essentially, there's no melodramatic role that you haven't played? 8 A. If you want to call it melodramatic. I just say dramatic, but yeah. 9 Q. It involves a significant amount of drama; correct? 10 A. Yes. 11 Q. You're able to cry on command? 12 A. No, not always. It's not really how it works. 13 Q. You express pain through your characters? 14 A. Yeah, of course. 15 Q. Vulnerability? 16 A. Yes. 17 Q. The job you've trained for for a long time, right? 18 A. Yes. 19 Q. You've been hired to work on other TV shows and series, right? 20 A. Yes. 21 Q. A feature-length movie? 22 A. Yes. 23 Q. 24 A. Yes. 25 SOUTHERN DISTRICT REPORTERS, P.C. (212) 805-0300 DOJ-OGR-00017789",
  "text_blocks": [
    {
      "type": "printed",
      "content": "Case 1:20-cr-00330-PAE Document 745 Filed 08/10/22 Page 180 of 264 591",
      "position": "header"
    },
    {
      "type": "handwritten",
      "content": "LC1VMAX5 Jane - cross",
      "position": "header"
    },
    {
      "type": "printed",
      "content": "Q. You played a prostitute? A. Not my favorite storyline. Q. You ran a restaurant? A. Yes. Q. You took down a Mexican drug cartel? A. Yes. Q. Essentially, there's no melodramatic role that you haven't played? A. If you want to call it melodramatic. I just say dramatic, but yeah. Q. It involves a significant amount of drama; correct? A. Yes. Q. You're able to cry on command? A. No, not always. It's not really how it works. Q. You express pain through your characters? A. Yeah, of course. Q. Vulnerability? A. Yes. Q. The job you've trained for for a long time, right? A. Yes. Q. You've been hired to work on other TV shows and series, right? A. Yes. Q. A feature-length movie? A. Yes.",
      "position": "main"
    },
    {
      "type": "printed",
      "content": "SOUTHERN DISTRICT REPORTERS, P.C. (212) 805-0300",
      "position": "footer"
    },
    {
      "type": "printed",
      "content": "DOJ-OGR-00017789",
      "position": "footer"
    }
  ],
  "entities": {
    "people": [
      "Jane"
    ],
    "organizations": [
      "SOUTHERN DISTRICT REPORTERS, P.C.",
      "Mexican drug cartel"
    ],
    "locations": [],
    "dates": [
      "08/10/22"
    ],
    "reference_numbers": [
      "1:20-cr-00330-PAE",
      "745",
      "DOJ-OGR-00017789"
    ]
  },
  "additional_notes": "The document appears to be a court transcript with a clear Q&A format. The text is mostly printed, with a handwritten note at the top. There are no visible redactions or damage."
}