{
  "document_metadata": {
    "page_number": "57",
    "document_number": "751",
    "date": "08/10/22",
    "document_type": "court transcript",
    "has_handwriting": false,
    "has_stamps": false
  },
  "full_text": "Case 1:20-cr-00330-PAE Document 751 Filed 08/10/22 Page 57 of 261 1197\nLC6VMAX2\nKate - direct\n1 A. I believe my 18th.\n2 Q. Did you receive this gift before or after the two times Epstein engaged in sex acts with you during massages at Maxwell's house?\n3 A. After.\n4 Q. What, if any, conversations do you remember having with Maxwell about travel?\n5 A. I remember that she was always very accommodating and told me that whenever I wanted to come and visit, that she would take care of everything; that they would take care of everything.\n6 Q. Did those conversations about travel happen before or after she gave you the handbag?\n7 A. Before.\n8 Q. Did there come a time when you traveled to meet Epstein and Maxwell?\n9 A. Yes.\n10 Q. Approximately how many times did you travel to meet them?\n11 A. To meet both of them?\n12 Q. Yes.\n13 A. Four or five times.\n14 Q. Do you remember approximately how old you were when you first traveled to meet Maxwell and Epstein?\n15 A. Approximately 18.\n16 Q. And do you remember approximately how old you were when you\nSOUTHERN DISTRICT REPORTERS, P.C. (212) 805-0300\nDOJ-OGR-00018394",
  "text_blocks": [
    {
      "type": "printed",
      "content": "Case 1:20-cr-00330-PAE Document 751 Filed 08/10/22 Page 57 of 261 1197",
      "position": "header"
    },
    {
      "type": "printed",
      "content": "LC6VMAX2\nKate - direct",
      "position": "header"
    },
    {
      "type": "printed",
      "content": "1 A. I believe my 18th.\n2 Q. Did you receive this gift before or after the two times Epstein engaged in sex acts with you during massages at Maxwell's house?\n3 A. After.\n4 Q. What, if any, conversations do you remember having with Maxwell about travel?\n5 A. I remember that she was always very accommodating and told me that whenever I wanted to come and visit, that she would take care of everything; that they would take care of everything.\n6 Q. Did those conversations about travel happen before or after she gave you the handbag?\n7 A. Before.\n8 Q. Did there come a time when you traveled to meet Epstein and Maxwell?\n9 A. Yes.\n10 Q. Approximately how many times did you travel to meet them?\n11 A. To meet both of them?\n12 Q. Yes.\n13 A. Four or five times.\n14 Q. Do you remember approximately how old you were when you first traveled to meet Maxwell and Epstein?\n15 A. Approximately 18.\n16 Q. And do you remember approximately how old you were when you",
      "position": "main"
    },
    {
      "type": "printed",
      "content": "SOUTHERN DISTRICT REPORTERS, P.C. (212) 805-0300",
      "position": "footer"
    },
    {
      "type": "printed",
      "content": "DOJ-OGR-00018394",
      "position": "footer"
    }
  ],
  "entities": {
    "people": [
      "Epstein",
      "Maxwell"
    ],
    "organizations": [
      "SOUTHERN DISTRICT REPORTERS, P.C."
    ],
    "locations": [],
    "dates": [
      "08/10/22"
    ],
    "reference_numbers": [
      "1:20-cr-00330-PAE",
      "751",
      "DOJ-OGR-00018394"
    ]
  },
  "additional_notes": "The document appears to be a court transcript. The text is clear and legible, with no visible redactions or damage."
}