{
  "document_metadata": {
    "page_number": "33",
    "document_number": "747",
    "date": "08/10/22",
    "document_type": "Court Transcript",
    "has_handwriting": false,
    "has_stamps": false
  },
  "full_text": "Case 1:20-cr-00330-PAE Document 747 Filed 08/10/22 Page 33 of 228 709 LC2VMAX2 Rocchio - Direct 1 Q. Have you published articles on traumatic stress and interpersonal violence? 2 A. I have. 3 Q. Do you have any other involvement in professional publications? 4 A. I do. I'm on the editorial advisory board for the primary journal for the division of trauma psychology within the American Psychological Association. And I also serve as a peer reviewer for a number of other journals when topics come up that pertain to my areas of expertise. 5 Q. What does it mean to serve as a peer reviewer? 6 A. So when someone wants to have an article published, they will submit the article to the journal. And then the editors will send that article out to experts in the field to review the article and provide feedback as to whether the article should be accepted, whether significant or minor revisions are in order, or whether the article should be rejected for publication. 7 Q. Have you given presentations in the area of traumatic stress and interpersonal violence? 8 A. Yes, many. 9 Q. How did you come to give those presentations? 10 A. So there are really two ways that I've given presentations. One is through professional conferences, where you go through a very similar peer review process for professional organizations 11 SOUTHERN DISTRICT REPORTERS, P.C. (212) 805-0300 DOJ-OGR-00017906",
  "text_blocks": [
    {
      "type": "printed",
      "content": "Case 1:20-cr-00330-PAE Document 747 Filed 08/10/22 Page 33 of 228 709",
      "position": "header"
    },
    {
      "type": "printed",
      "content": "LC2VMAX2 Rocchio - Direct",
      "position": "header"
    },
    {
      "type": "printed",
      "content": "1 Q. Have you published articles on traumatic stress and interpersonal violence? 2 A. I have. 3 Q. Do you have any other involvement in professional publications? 4 A. I do. I'm on the editorial advisory board for the primary journal for the division of trauma psychology within the American Psychological Association. And I also serve as a peer reviewer for a number of other journals when topics come up that pertain to my areas of expertise. 5 Q. What does it mean to serve as a peer reviewer? 6 A. So when someone wants to have an article published, they will submit the article to the journal. And then the editors will send that article out to experts in the field to review the article and provide feedback as to whether the article should be accepted, whether significant or minor revisions are in order, or whether the article should be rejected for publication. 7 Q. Have you given presentations in the area of traumatic stress and interpersonal violence? 8 A. Yes, many. 9 Q. How did you come to give those presentations? 10 A. So there are really two ways that I've given presentations. One is through professional conferences, where you go through a very similar peer review process for professional organizations",
      "position": "main"
    },
    {
      "type": "printed",
      "content": "SOUTHERN DISTRICT REPORTERS, P.C. (212) 805-0300",
      "position": "footer"
    },
    {
      "type": "printed",
      "content": "DOJ-OGR-00017906",
      "position": "footer"
    }
  ],
  "entities": {
    "people": [
      "Rocchio"
    ],
    "organizations": [
      "American Psychological Association",
      "SOUTHERN DISTRICT REPORTERS, P.C."
    ],
    "locations": [],
    "dates": [
      "08/10/22"
    ],
    "reference_numbers": [
      "1:20-cr-00330-PAE",
      "747",
      "DOJ-OGR-00017906"
    ]
  },
  "additional_notes": "The document appears to be a court transcript with a clear and legible format. There are no visible redactions or damage."
}