{
  "document_metadata": {
    "page_number": "174",
    "document_number": "747",
    "date": "08/10/22",
    "document_type": "court transcript",
    "has_handwriting": false,
    "has_stamps": false
  },
  "full_text": "Case 1:20-cr-00330-PAE Document 747 Filed 08/10/22 Page 174 of 228 850 LC2Qmax5 - corrected Alessi - Direct with a physical exhibit? THE COURT: I'm sorry? MS. COMEY: I have a physical exhibit that I would like to approach and give to the witness. THE COURT: Please identify it for the record. MS. COMEY: Government Exhibit 52, which I will show to defense counsel before I bring it up. THE COURT: Marked for identification GX-52? MS. COMEY: Yes. Thank you, your Honor. THE COURT: Before the witness, may I see it? MS. COMEY: Yes, your Honor. THE COURT: Okay. MS. COMEY: Thank you, your Honor. May I approach the witness? THE COURT: You may. BY MS. COMEY: Q. Mr. Alessi, I've just handed you what is marked for identification as Government Exhibit 52. Would you please take a look at that, and then tell us if you recognize it? A. Yes, I recognize it. The type of book, it was the same. Q. Hold on one second. What does this appear to be to you? A. This appear to be the direct -- these were the directories of Ms. Maxwell and Mr. Epstein. Q. Did you review this directory last night? A. Yes, I did. SOUTHERN DISTRICT REPORTERS, P.C. (212) 805-0300 DOJ-OGR-00018047",
  "text_blocks": [
    {
      "type": "printed",
      "content": "Case 1:20-cr-00330-PAE Document 747 Filed 08/10/22 Page 174 of 228 850",
      "position": "header"
    },
    {
      "type": "printed",
      "content": "LC2Qmax5 - corrected Alessi - Direct",
      "position": "header"
    },
    {
      "type": "printed",
      "content": "with a physical exhibit? THE COURT: I'm sorry? MS. COMEY: I have a physical exhibit that I would like to approach and give to the witness. THE COURT: Please identify it for the record. MS. COMEY: Government Exhibit 52, which I will show to defense counsel before I bring it up. THE COURT: Marked for identification GX-52? MS. COMEY: Yes. Thank you, your Honor. THE COURT: Before the witness, may I see it? MS. COMEY: Yes, your Honor. THE COURT: Okay. MS. COMEY: Thank you, your Honor. May I approach the witness? THE COURT: You may. BY MS. COMEY: Q. Mr. Alessi, I've just handed you what is marked for identification as Government Exhibit 52. Would you please take a look at that, and then tell us if you recognize it? A. Yes, I recognize it. The type of book, it was the same. Q. Hold on one second. What does this appear to be to you? A. This appear to be the direct -- these were the directories of Ms. Maxwell and Mr. Epstein. Q. Did you review this directory last night? A. Yes, I did.",
      "position": "main"
    },
    {
      "type": "printed",
      "content": "SOUTHERN DISTRICT REPORTERS, P.C. (212) 805-0300",
      "position": "footer"
    },
    {
      "type": "printed",
      "content": "DOJ-OGR-00018047",
      "position": "footer"
    }
  ],
  "entities": {
    "people": [
      "MS. COMEY",
      "Mr. Alessi",
      "Ms. Maxwell",
      "Mr. Epstein"
    ],
    "organizations": [
      "SOUTHERN DISTRICT REPORTERS, P.C."
    ],
    "locations": [],
    "dates": [
      "08/10/22"
    ],
    "reference_numbers": [
      "1:20-cr-00330-PAE",
      "Document 747",
      "Government Exhibit 52",
      "GX-52",
      "DOJ-OGR-00018047"
    ]
  },
  "additional_notes": "The document appears to be a court transcript with a clear and legible format. There are no visible redactions or damage."
}