{
  "document_metadata": {
    "page_number": "177",
    "document_number": "753",
    "date": "08/10/22",
    "document_type": "court transcript",
    "has_handwriting": false,
    "has_stamps": false
  },
  "full_text": "Case 1:20-cr-00330-PAE Document 753 Filed 08/10/22 Page 177 of 264 1615 LC7Cmax6 Carolyn - cross 1 A. It wasn't only Sarah, no. 2 Q. If you can look at the next paragraph, 005, page 2, second paragraph from the bottom. 3 A. Question. 4 Q. Does this refresh your memory that Sarah would call you from New York to schedule a massage appointment for Epstein? 5 A. On some occasions, yes. 6 Q. Ms. Maxwell's name does not appear in that paragraph; correct? 7 A. We were not talking about Ms. Maxwell in 2007. 8 Q. Okay. 9 A. So this has nothing to do with -- 10 Q. Now, in this entire first discussion with the FBI in 2007, 11 it's true that you never said the name, Ghislaine Maxwell, once; correct? 12 A. Yes, because it's not who we were talking about. 13 Q. So is it your testimony that the FBI limited your ability to talk in some fashion? 14 A. She was not the subject of the discussion. 15 Q. You talked about Virginia Roberts, you talked about Sarah, you talked about Sean, you talked about Epstein, you talked about a cook, you talked about going there, and you never mentioned Maxwell once; correct? 16 A. Correct, because she was not topic of what they were asking me. It had nothing to do with her at the time. But, yes, SOUTHERN DISTRICT REPORTERS, P.C. (212) 805-0300 DOJ-OGR-00018775",
  "text_blocks": [
    {
      "type": "printed",
      "content": "Case 1:20-cr-00330-PAE Document 753 Filed 08/10/22 Page 177 of 264 1615 LC7Cmax6 Carolyn - cross",
      "position": "header"
    },
    {
      "type": "printed",
      "content": "1 A. It wasn't only Sarah, no. 2 Q. If you can look at the next paragraph, 005, page 2, second paragraph from the bottom. 3 A. Question. 4 Q. Does this refresh your memory that Sarah would call you from New York to schedule a massage appointment for Epstein? 5 A. On some occasions, yes. 6 Q. Ms. Maxwell's name does not appear in that paragraph; correct? 7 A. We were not talking about Ms. Maxwell in 2007. 8 Q. Okay. 9 A. So this has nothing to do with -- 10 Q. Now, in this entire first discussion with the FBI in 2007, 11 it's true that you never said the name, Ghislaine Maxwell, once; correct? 12 A. Yes, because it's not who we were talking about. 13 Q. So is it your testimony that the FBI limited your ability to talk in some fashion? 14 A. She was not the subject of the discussion. 15 Q. You talked about Virginia Roberts, you talked about Sarah, you talked about Sean, you talked about Epstein, you talked about a cook, you talked about going there, and you never mentioned Maxwell once; correct? 16 A. Correct, because she was not topic of what they were asking me. It had nothing to do with her at the time. But, yes,",
      "position": "main"
    },
    {
      "type": "printed",
      "content": "SOUTHERN DISTRICT REPORTERS, P.C. (212) 805-0300",
      "position": "footer"
    },
    {
      "type": "printed",
      "content": "DOJ-OGR-00018775",
      "position": "footer"
    }
  ],
  "entities": {
    "people": [
      "Sarah",
      "Epstein",
      "Ghislaine Maxwell",
      "Virginia Roberts",
      "Sean",
      "Carolyn"
    ],
    "organizations": [
      "FBI",
      "SOUTHERN DISTRICT REPORTERS, P.C."
    ],
    "locations": [
      "New York"
    ],
    "dates": [
      "08/10/22",
      "2007"
    ],
    "reference_numbers": [
      "1:20-cr-00330-PAE",
      "753",
      "DOJ-OGR-00018775",
      "LC7Cmax6"
    ]
  },
  "additional_notes": "The document appears to be a court transcript with a clear and legible format. There are no visible redactions or damage."
}