{
  "document_metadata": {
    "page_number": "142",
    "document_number": "747",
    "date": "08/10/22",
    "document_type": "court transcript",
    "has_handwriting": false,
    "has_stamps": false
  },
  "full_text": "Case 1:20-cr-00330-PAE Document 747 Filed 08/10/22 Page 142 of 228\nLC2VMAX4 Alessi - Direct\n1 Q. Okay. Let's go to page 43.\n2 A. Yes.\n3 Q. Page 44? I'm sorry, page 44? I think I --\n4 THE COURT: Just a moment. My copy goes from page 42\n5 to page 49.\n6 THE WITNESS: Yeah, so do mine.\n7 THE COURT: Actually, counsel, it's out of order.\n8 MS. COMEY: I apologize, your Honor.\n9 THE WITNESS: Oh, wait.\n10 THE COURT: Just a second please. Wait till you're asked a question. Thank you.\n11\n12 Q. So we stopped at page 42.\n13 The next page in your copy, does it say page 49?\n14 A. Yes.\n15 Q. Okay. Do you recognize that page?\n16 A. Yes, I do.\n17 Q. Does the next page say page 50?\n18 A. Yes.\n19 Q. Do you recognize that page?\n20 A. Yes.\n21 Q. Does the next page say page 51?\n22 A. Yes, I recognize it.\n23 Q. And does the next page say 43?\n24 A. That's correct.\n25 Q. Do you recognize that page?\nSOUTHERN DISTRICT REPORTERS, P.C. (212) 805-0300\nDOJ-OGR-00018015",
  "text_blocks": [
    {
      "type": "printed",
      "content": "Case 1:20-cr-00330-PAE Document 747 Filed 08/10/22 Page 142 of 228",
      "position": "header"
    },
    {
      "type": "printed",
      "content": "LC2VMAX4 Alessi - Direct",
      "position": "header"
    },
    {
      "type": "printed",
      "content": "1 Q. Okay. Let's go to page 43.\n2 A. Yes.\n3 Q. Page 44? I'm sorry, page 44? I think I --\n4 THE COURT: Just a moment. My copy goes from page 42\n5 to page 49.\n6 THE WITNESS: Yeah, so do mine.\n7 THE COURT: Actually, counsel, it's out of order.\n8 MS. COMEY: I apologize, your Honor.\n9 THE WITNESS: Oh, wait.\n10 THE COURT: Just a second please. Wait till you're asked a question. Thank you.\n11\n12 Q. So we stopped at page 42.\n13 The next page in your copy, does it say page 49?\n14 A. Yes.\n15 Q. Okay. Do you recognize that page?\n16 A. Yes, I do.\n17 Q. Does the next page say page 50?\n18 A. Yes.\n19 Q. Do you recognize that page?\n20 A. Yes.\n21 Q. Does the next page say page 51?\n22 A. Yes, I recognize it.\n23 Q. And does the next page say 43?\n24 A. That's correct.\n25 Q. Do you recognize that page?",
      "position": "main"
    },
    {
      "type": "printed",
      "content": "SOUTHERN DISTRICT REPORTERS, P.C. (212) 805-0300",
      "position": "footer"
    },
    {
      "type": "printed",
      "content": "DOJ-OGR-00018015",
      "position": "footer"
    }
  ],
  "entities": {
    "people": [
      "Alessi",
      "Comey"
    ],
    "organizations": [
      "SOUTHERN DISTRICT REPORTERS, P.C."
    ],
    "locations": [],
    "dates": [
      "08/10/22"
    ],
    "reference_numbers": [
      "1:20-cr-00330-PAE",
      "747",
      "DOJ-OGR-00018015"
    ]
  },
  "additional_notes": "The document appears to be a court transcript with a clear and legible format. There are no visible redactions or damage."
}