{
  "document_metadata": {
    "page_number": "15",
    "document_number": "69",
    "date": "09/28/2020",
    "document_type": "Court Document",
    "has_handwriting": false,
    "has_stamps": false
  },
  "full_text": "Case 20-3061, Document 69, 09/28/2020, 2940206, Page15 of 15\nRespectfully submitted,\ns/ Adam Mueller\nTy Gee\nAdam Mueller\nHADDON, MORGAN AND FOREMAN, P.C.\n150 East 10th Avenue\nDenver, CO 80203\nTel 303.831.7364\nFax 303.832.2628\ntgee@hmflaw.com\namueller@hmflaw.com\nCounsel for Defendant-Appellant Ghislaine Maxwell\nCertificate of Compliance\nUnder Federal Rule of Appellate Procedure 32(g) and Rule 27(d)(2)(A), the undersigned counsel hereby certifies that this response complies with the type-volume limitation of the Federal Rules of Appellate Procedure. As measured by the word processing system used to prepare this response, there are 2,842 words in this response.\ns/ Adam Mueller\nCertificate of Service\nI certify that on September 28, 2020, I filed this Ms. Maxwell's Response to the Government's Motion to Dismiss Appeal with the Court via CM/ECF, which will send notification of the filing to all counsel of record. I also certify that I emailed a copy of this motion to all counsel of record.\ns/ Nicole Simmons\n14\nDOJ-OGR-00019606",
  "text_blocks": [
    {
      "type": "printed",
      "content": "Case 20-3061, Document 69, 09/28/2020, 2940206, Page15 of 15",
      "position": "header"
    },
    {
      "type": "printed",
      "content": "Respectfully submitted,\ns/ Adam Mueller\nTy Gee\nAdam Mueller\nHADDON, MORGAN AND FOREMAN, P.C.\n150 East 10th Avenue\nDenver, CO 80203\nTel 303.831.7364\nFax 303.832.2628\ntgee@hmflaw.com\namueller@hmflaw.com\nCounsel for Defendant-Appellant Ghislaine Maxwell",
      "position": "top"
    },
    {
      "type": "printed",
      "content": "Certificate of Compliance\nUnder Federal Rule of Appellate Procedure 32(g) and Rule 27(d)(2)(A), the undersigned counsel hereby certifies that this response complies with the type-volume limitation of the Federal Rules of Appellate Procedure. As measured by the word processing system used to prepare this response, there are 2,842 words in this response.\ns/ Adam Mueller",
      "position": "middle"
    },
    {
      "type": "printed",
      "content": "Certificate of Service\nI certify that on September 28, 2020, I filed this Ms. Maxwell's Response to the Government's Motion to Dismiss Appeal with the Court via CM/ECF, which will send notification of the filing to all counsel of record. I also certify that I emailed a copy of this motion to all counsel of record.\ns/ Nicole Simmons",
      "position": "middle"
    },
    {
      "type": "printed",
      "content": "14",
      "position": "footer"
    },
    {
      "type": "printed",
      "content": "DOJ-OGR-00019606",
      "position": "footer"
    }
  ],
  "entities": {
    "people": [
      "Adam Mueller",
      "Ty Gee",
      "Ghislaine Maxwell",
      "Nicole Simmons"
    ],
    "organizations": [
      "HADDON, MORGAN AND FOREMAN, P.C."
    ],
    "locations": [
      "Denver, CO"
    ],
    "dates": [
      "September 28, 2020",
      "09/28/2020"
    ],
    "reference_numbers": [
      "20-3061",
      "69",
      "2940206",
      "DOJ-OGR-00019606"
    ]
  },
  "additional_notes": "The document appears to be a court filing with signatures represented by '/s/'. The document is well-formatted and legible."
}