{
  "document_metadata": {
    "page_number": "122",
    "document_number": "751",
    "date": "08/10/22",
    "document_type": "court transcript",
    "has_handwriting": false,
    "has_stamps": false
  },
  "full_text": "Case 1:20-cr-00330-PAE Document 751 Filed 08/10/22 Page 122 of 261 1283 LC6Cmax3 Kate - cross 1 (Jury not present) 2 THE COURT: The witness may step down for the lunch break. 3 4 THE WITNESS: Thank you, your Honor. 5 (Witness excused) 6 THE COURT: Everyone may be seated. Matters to take up, counsel? 7 8 MS. POMERANTZ: Not from the government. Thank you, 9 your Honor. 10 MS. STERNHEIM: Not at this time. 11 THE COURT: We'll resume in 45 minutes. Let me know 12 if there is anything we need to address, please. Thank you. 13 (Recess) 14 (Continued on next page) 15 16 17 18 19 20 21 22 23 24 25 SOUTHERN DISTRICT REPORTERS, P.C. (212) 805-0300 DOJ-OGR-00018459",
  "text_blocks": [
    {
      "type": "printed",
      "content": "Case 1:20-cr-00330-PAE Document 751 Filed 08/10/22 Page 122 of 261 1283",
      "position": "header"
    },
    {
      "type": "handwritten",
      "content": "LC6Cmax3 Kate - cross",
      "position": "header"
    },
    {
      "type": "printed",
      "content": "1 (Jury not present) 2 THE COURT: The witness may step down for the lunch break. 3 4 THE WITNESS: Thank you, your Honor. 5 (Witness excused) 6 THE COURT: Everyone may be seated. Matters to take up, counsel? 7 8 MS. POMERANTZ: Not from the government. Thank you, 9 your Honor. 10 MS. STERNHEIM: Not at this time. 11 THE COURT: We'll resume in 45 minutes. Let me know 12 if there is anything we need to address, please. Thank you. 13 (Recess) 14 (Continued on next page)",
      "position": "main"
    },
    {
      "type": "printed",
      "content": "SOUTHERN DISTRICT REPORTERS, P.C. (212) 805-0300",
      "position": "footer"
    },
    {
      "type": "printed",
      "content": "DOJ-OGR-00018459",
      "position": "footer"
    }
  ],
  "entities": {
    "people": [
      "MS. POMERANTZ",
      "MS. STERNHEIM"
    ],
    "organizations": [
      "SOUTHERN DISTRICT REPORTERS, P.C."
    ],
    "locations": [],
    "dates": [
      "08/10/22"
    ],
    "reference_numbers": [
      "1:20-cr-00330-PAE",
      "751",
      "DOJ-OGR-00018459"
    ]
  },
  "additional_notes": "The document appears to be a court transcript with a clear and readable format. There are no visible redactions or damage."
}