{
  "document_metadata": {
    "page_number": "100",
    "document_number": "745",
    "date": "08/10/22",
    "document_type": "court transcript",
    "has_handwriting": false,
    "has_stamps": false
  },
  "full_text": "Case 1:20-cr-00330-PAE Document 745 Filed 08/10/22 Page 100 of 264 511\nLC1VMAX3 Jane - cross\n1 A. That's correct.\n2 Q. And that was in response to a question from the government to you through your attorney; correct?\n3 A. Correct.\n4 Q. That's because the government communicated to you through your attorney that The Lion King didn't come out until 1997; correct?\n5 A. Correct.\n6 Q. So although you had told the government twice previously that you flew to New York with Maxwell and Epstein when you were 14, you learned that the Broadway show didn't come out until you were 17; correct?\n7 A. That's right. But that wasn't the first time that we'd flown.\n8 Q. The government suggested to you that perhaps you meant to say The Lion King movie through your attorney to you; correct?\n9 MS. MOE: Objection, your Honor.\n10 THE COURT: Sustained.\n11 Q. Did Mr. Glassman share with you the email that he got from the government?\n12 MS. MOE: Objection.\n13 THE COURT: Sustained.\n14 Q. You knew at the time you communicated the information to Mr. Glassman that he intended to share it with the government; correct?\n15 SOUTHERN DISTRICT REPORTERS, P.C. (212) 805-0300\nDOJ-OGR-00017709",
  "text_blocks": [
    {
      "type": "printed",
      "content": "Case 1:20-cr-00330-PAE Document 745 Filed 08/10/22 Page 100 of 264 511",
      "position": "header"
    },
    {
      "type": "handwritten",
      "content": "LC1VMAX3 Jane - cross",
      "position": "header"
    },
    {
      "type": "printed",
      "content": "1 A. That's correct.\n2 Q. And that was in response to a question from the government to you through your attorney; correct?\n3 A. Correct.\n4 Q. That's because the government communicated to you through your attorney that The Lion King didn't come out until 1997; correct?\n5 A. Correct.\n6 Q. So although you had told the government twice previously that you flew to New York with Maxwell and Epstein when you were 14, you learned that the Broadway show didn't come out until you were 17; correct?\n7 A. That's right. But that wasn't the first time that we'd flown.\n8 Q. The government suggested to you that perhaps you meant to say The Lion King movie through your attorney to you; correct?\n9 MS. MOE: Objection, your Honor.\n10 THE COURT: Sustained.\n11 Q. Did Mr. Glassman share with you the email that he got from the government?\n12 MS. MOE: Objection.\n13 THE COURT: Sustained.\n14 Q. You knew at the time you communicated the information to Mr. Glassman that he intended to share it with the government; correct?",
      "position": "main"
    },
    {
      "type": "printed",
      "content": "SOUTHERN DISTRICT REPORTERS, P.C. (212) 805-0300",
      "position": "footer"
    },
    {
      "type": "printed",
      "content": "DOJ-OGR-00017709",
      "position": "footer"
    }
  ],
  "entities": {
    "people": [
      "Maxwell",
      "Epstein",
      "Glassman",
      "Moe"
    ],
    "organizations": [
      "SOUTHERN DISTRICT REPORTERS, P.C.",
      "THE COURT"
    ],
    "locations": [
      "New York"
    ],
    "dates": [
      "08/10/22",
      "1997"
    ],
    "reference_numbers": [
      "1:20-cr-00330-PAE",
      "745",
      "DOJ-OGR-00017709"
    ]
  },
  "additional_notes": "The document appears to be a court transcript with a clear and legible format. There are no visible redactions or damage."
}