{
  "document_metadata": {
    "page_number": "4",
    "document_number": "89-1",
    "date": "05/17/2021",
    "document_type": "court document",
    "has_handwriting": false,
    "has_stamps": false
  },
  "full_text": "Case 21-58, Document 89-1, 05/17/2021, 3102450, Page4 of 14\nof sleep would alleviate her stress instead of exacerbate it. Ms. Maxwell replied. Ex. E, Doc. 272.\nThe district court then issued an order saying that it would not tell the Bureau of Prisons what to do but “admonishe[d] the MDC and the Government to continue to ensure that Maxwell is subjected to only those security protocols that BOP determines are necessary for her safety and security, based upon neutral and applicable factors, and consistent with the treatment of similarly situated pre-trial detainees.” Ex. B, Doc. 282.\nBut Ms. Maxwell is not being treated like any other detainee. And the horrific conditions make it impossible to prepare for trial. Accordingly, we renewed our motion for bond and seek relief from this Court. Ms. Maxwell simply wants a fair opportunity to fight the charges against her at trial.\nCurrently, she (1) can’t sleep because the guards wake her every 15 minutes; (2) oftentimes can’t drink the water because it is brown and contains particles; (3) can’t meet in person with her lawyers because the guards use a handheld camera to video and audio tape record the meetings; (4) can’t manage the smell of overflowing sewage that comes up from the drain in her unit; (5) can’t keep the guards from seizing and\n2\nDOJ-OGR-00020328",
  "text_blocks": [
    {
      "type": "printed",
      "content": "Case 21-58, Document 89-1, 05/17/2021, 3102450, Page4 of 14",
      "position": "header"
    },
    {
      "type": "printed",
      "content": "of sleep would alleviate her stress instead of exacerbate it. Ms. Maxwell replied. Ex. E, Doc. 272.\nThe district court then issued an order saying that it would not tell the Bureau of Prisons what to do but “admonishe[d] the MDC and the Government to continue to ensure that Maxwell is subjected to only those security protocols that BOP determines are necessary for her safety and security, based upon neutral and applicable factors, and consistent with the treatment of similarly situated pre-trial detainees.” Ex. B, Doc. 282.\nBut Ms. Maxwell is not being treated like any other detainee. And the horrific conditions make it impossible to prepare for trial. Accordingly, we renewed our motion for bond and seek relief from this Court. Ms. Maxwell simply wants a fair opportunity to fight the charges against her at trial.\nCurrently, she (1) can’t sleep because the guards wake her every 15 minutes; (2) oftentimes can’t drink the water because it is brown and contains particles; (3) can’t meet in person with her lawyers because the guards use a handheld camera to video and audio tape record the meetings; (4) can’t manage the smell of overflowing sewage that comes up from the drain in her unit; (5) can’t keep the guards from seizing and",
      "position": "main content"
    },
    {
      "type": "printed",
      "content": "2",
      "position": "footer"
    },
    {
      "type": "printed",
      "content": "DOJ-OGR-00020328",
      "position": "footer"
    }
  ],
  "entities": {
    "people": [
      "Ms. Maxwell"
    ],
    "organizations": [
      "Bureau of Prisons",
      "MDC",
      "BOP",
      "Government",
      "Court"
    ],
    "locations": [],
    "dates": [
      "05/17/2021"
    ],
    "reference_numbers": [
      "Case 21-58",
      "Document 89-1",
      "Ex. E, Doc. 272",
      "Ex. B, Doc. 282",
      "DOJ-OGR-00020328"
    ]
  },
  "additional_notes": "The document appears to be a court filing discussing the treatment of Ms. Maxwell while in detention. The text is mostly printed, with no visible handwriting or stamps. The document is well-formatted and legible."
}