{
  "document_metadata": {
    "page_number": "78",
    "document_number": "39-2",
    "date": "04/01/2021",
    "document_type": "court transcript",
    "has_handwriting": false,
    "has_stamps": false
  },
  "full_text": "Case 21-58, Document 39-2, 04/01/2021, 3068530, Page78 of 200\n\n1 THE COURT: Among other things, but, yes, I'm drilling down specifically on that since that has been, in somewhat comparable circumstances in other matters, the source of issues related to timely disclosures.\n2 MS. MOE: Yes, your Honor. Our team met personally with the F.B.I. in Florida to make sure that we had the materials, and it was represented to us that the materials that the F.B.I. provided in Florida were the comprehensive set of materials. We will certainly have ongoing conversations to make sure that that is the case and if, in our review of files, we discover other materials, we will handle that with great care, and we are particularly sensitive to that concern.\n3 THE COURT: And I expect here, and in all matters, not just accepting of initial representations made regarding full disclosure, but thoughtful and critical pushing and pressing of questions and issues with respect to actively retrieving any appropriate files. Are we on the same page, Ms. Moe?\n4 MS. MOE: Yes, your Honor. Very much so.\n5 THE COURT: All right. Thank you.\n6 With that, why don't you go ahead and lay out the proposed schedule that you have discussed with Mr. Cohen, and then I will hear from Mr. Cohen if he has any concerns with that proposal.\n7 MS. MOE: Yes, your Honor.\n8 We would propose the completion of discovery, to\n\nSOUTHERN DISTRICT REPORTERS, P.C.\n(212) 805-0300\nDOJ-OGR-00019937",
  "text_blocks": [
    {
      "type": "printed",
      "content": "Case 21-58, Document 39-2, 04/01/2021, 3068530, Page78 of 200",
      "position": "header"
    },
    {
      "type": "printed",
      "content": "1 THE COURT: Among other things, but, yes, I'm drilling down specifically on that since that has been, in somewhat comparable circumstances in other matters, the source of issues related to timely disclosures.\n2 MS. MOE: Yes, your Honor. Our team met personally with the F.B.I. in Florida to make sure that we had the materials, and it was represented to us that the materials that the F.B.I. provided in Florida were the comprehensive set of materials. We will certainly have ongoing conversations to make sure that that is the case and if, in our review of files, we discover other materials, we will handle that with great care, and we are particularly sensitive to that concern.\n3 THE COURT: And I expect here, and in all matters, not just accepting of initial representations made regarding full disclosure, but thoughtful and critical pushing and pressing of questions and issues with respect to actively retrieving any appropriate files. Are we on the same page, Ms. Moe?\n4 MS. MOE: Yes, your Honor. Very much so.\n5 THE COURT: All right. Thank you.\n6 With that, why don't you go ahead and lay out the proposed schedule that you have discussed with Mr. Cohen, and then I will hear from Mr. Cohen if he has any concerns with that proposal.\n7 MS. MOE: Yes, your Honor.\n8 We would propose the completion of discovery, to",
      "position": "main"
    },
    {
      "type": "printed",
      "content": "SOUTHERN DISTRICT REPORTERS, P.C.\n(212) 805-0300",
      "position": "footer"
    },
    {
      "type": "printed",
      "content": "DOJ-OGR-00019937",
      "position": "footer"
    }
  ],
  "entities": {
    "people": [
      "Ms. Moe",
      "Mr. Cohen"
    ],
    "organizations": [
      "F.B.I.",
      "SOUTHERN DISTRICT REPORTERS, P.C."
    ],
    "locations": [
      "Florida"
    ],
    "dates": [
      "04/01/2021"
    ],
    "reference_numbers": [
      "Case 21-58",
      "Document 39-2",
      "3068530",
      "DOJ-OGR-00019937"
    ]
  },
  "additional_notes": "The document appears to be a court transcript with a clear and legible format. There are no visible redactions or damage."
}