{
  "document_metadata": {
    "page_number": "182",
    "document_number": "749",
    "date": "08/10/22",
    "document_type": "court transcript",
    "has_handwriting": false,
    "has_stamps": false
  },
  "full_text": "Case 1:20-cr-00330-PAE Document 749 Filed 08/10/22 Page 182 of 236 LC3KMAX6 Parkinson - Direct residence. It's adjoining the master bedroom, and this one has the tub in it. Q. Is this a fair and accurate depiction of a portion of the interior of 358 El Brillo Way as it appeared on October 20, 2005? THE COURT: Ms. Comey, you've got to speak up. Q. Is this a fair and accurate depiction of the interior of 358 El Brillo Way as it appeared on October 20, 2005? A. True. MS. COMEY: Your Honor, the government offers these in evidence. MR. EVERDELL: No objection. THE COURT: Thank you. 283 and 284 are admitted. (Government's Exhibits 283 and 284 received in evidence) MS. COMEY: May we publish? THE COURT: You may. MR. EVERDELL: Ms. Drescher, I'd like to do these one at a time, please. 283 first. And now on to 284, please. Q. While that stays up there, Mr. Parkinson, would you please turn in your binder to what's been marked for identification as Government Exhibit 285. A. Yes, I have it. Q. Do you recognize this? SOUTHERN DISTRICT REPORTERS, P.C. (212) 805-0300 DOJ-OGR-00018283",
  "text_blocks": [
    {
      "type": "printed",
      "content": "Case 1:20-cr-00330-PAE Document 749 Filed 08/10/22 Page 182 of 236 LC3KMAX6 Parkinson - Direct",
      "position": "header"
    },
    {
      "type": "printed",
      "content": "residence. It's adjoining the master bedroom, and this one has the tub in it. Q. Is this a fair and accurate depiction of a portion of the interior of 358 El Brillo Way as it appeared on October 20, 2005? THE COURT: Ms. Comey, you've got to speak up. Q. Is this a fair and accurate depiction of the interior of 358 El Brillo Way as it appeared on October 20, 2005? A. True. MS. COMEY: Your Honor, the government offers these in evidence. MR. EVERDELL: No objection. THE COURT: Thank you. 283 and 284 are admitted. (Government's Exhibits 283 and 284 received in evidence) MS. COMEY: May we publish? THE COURT: You may. MR. EVERDELL: Ms. Drescher, I'd like to do these one at a time, please. 283 first. And now on to 284, please. Q. While that stays up there, Mr. Parkinson, would you please turn in your binder to what's been marked for identification as Government Exhibit 285. A. Yes, I have it. Q. Do you recognize this?",
      "position": "main body"
    },
    {
      "type": "printed",
      "content": "SOUTHERN DISTRICT REPORTERS, P.C. (212) 805-0300",
      "position": "footer"
    },
    {
      "type": "printed",
      "content": "DOJ-OGR-00018283",
      "position": "footer"
    }
  ],
  "entities": {
    "people": [
      "Ms. Comey",
      "Mr. Everdell",
      "Ms. Drescher",
      "Mr. Parkinson"
    ],
    "organizations": [
      "SOUTHERN DISTRICT REPORTERS, P.C."
    ],
    "locations": [
      "358 El Brillo Way"
    ],
    "dates": [
      "October 20, 2005",
      "08/10/22"
    ],
    "reference_numbers": [
      "1:20-cr-00330-PAE",
      "749",
      "283",
      "284",
      "285",
      "DOJ-OGR-00018283"
    ]
  },
  "additional_notes": "The document appears to be a court transcript with a clear and legible format. There are no visible redactions or damage."
}