{
  "document_metadata": {
    "page_number": "21",
    "document_number": "17",
    "date": "09/08/2020",
    "document_type": "Court Document",
    "has_handwriting": false,
    "has_stamps": false
  },
  "full_text": "d. MAXWELL's personal residence in London, England.\n7. Among the victims induced or enticed by GHISLAINE MAXWELL, the defendant, were minor victims identified herein as Minor Victim-1, Minor Victim-2, and Minor Victim-3. In particular, and during time periods relevant to this Indictment, MAXWELL engaged in the following acts, among others, with respect to minor victims:\na. MAXWELL met Minor Victim-1 when Minor Victim-1 was approximately 14 years old. MAXWELL subsequently interacted with Minor Victim-1 on multiple occasions at Epstein's residences, knowing that Minor Victim-1 was under the age of 18 at the time. During these interactions, which took place between approximately 1994 and 1997, MAXWELL groomed Minor Victim-1 to engage in sexual acts with Epstein through multiple means. First, MAXWELL and Epstein attempted to befriend Minor Victim-1, taking her to the movies and on shopping trips. MAXWELL also asked Minor Victim-1 about school, her classes, her family, and other aspects of her life. MAXWELL then sought to normalize inappropriate and abusive conduct by, among other things, undressing in front of Minor Victim-1 and being present when Minor Victim-1 undressed in front of Epstein. Within the first year after MAXWELL and Epstein met Minor Victim-1, Epstein began sexually abusing Minor Victim-1. MAXWELL was present for\n7\nApp.019\nDOJ-OGR-00019478",
  "text_blocks": [
    {
      "type": "printed",
      "content": "d. MAXWELL's personal residence in London, England.",
      "position": "top"
    },
    {
      "type": "printed",
      "content": "7. Among the victims induced or enticed by GHISLAINE MAXWELL, the defendant, were minor victims identified herein as Minor Victim-1, Minor Victim-2, and Minor Victim-3. In particular, and during time periods relevant to this Indictment, MAXWELL engaged in the following acts, among others, with respect to minor victims:",
      "position": "top"
    },
    {
      "type": "printed",
      "content": "a. MAXWELL met Minor Victim-1 when Minor Victim-1 was approximately 14 years old. MAXWELL subsequently interacted with Minor Victim-1 on multiple occasions at Epstein's residences, knowing that Minor Victim-1 was under the age of 18 at the time. During these interactions, which took place between approximately 1994 and 1997, MAXWELL groomed Minor Victim-1 to engage in sexual acts with Epstein through multiple means. First, MAXWELL and Epstein attempted to befriend Minor Victim-1, taking her to the movies and on shopping trips. MAXWELL also asked Minor Victim-1 about school, her classes, her family, and other aspects of her life. MAXWELL then sought to normalize inappropriate and abusive conduct by, among other things, undressing in front of Minor Victim-1 and being present when Minor Victim-1 undressed in front of Epstein. Within the first year after MAXWELL and Epstein met Minor Victim-1, Epstein began sexually abusing Minor Victim-1. MAXWELL was present for",
      "position": "middle"
    },
    {
      "type": "printed",
      "content": "7",
      "position": "footer"
    },
    {
      "type": "printed",
      "content": "App.019",
      "position": "footer"
    },
    {
      "type": "printed",
      "content": "DOJ-OGR-00019478",
      "position": "footer"
    }
  ],
  "entities": {
    "people": [
      "GHISLAINE MAXWELL",
      "Epstein",
      "Minor Victim-1",
      "Minor Victim-2",
      "Minor Victim-3"
    ],
    "organizations": [],
    "locations": [
      "London",
      "England"
    ],
    "dates": [
      "1994",
      "1997"
    ],
    "reference_numbers": [
      "DOJ-OGR-00019478",
      "App.019"
    ]
  },
  "additional_notes": "The document appears to be a court filing related to the case against Ghislaine Maxwell. The text is typed, and there are no visible stamps or handwritten notes. The document is page 21 of 125."
}