{
  "document_metadata": {
    "page_number": "38",
    "document_number": "753",
    "date": "08/10/22",
    "document_type": "court transcript",
    "has_handwriting": false,
    "has_stamps": false
  },
  "full_text": "Case 1:20-cr-00330-PAE Document 753 Filed 08/10/22 Page 38 of 264 1464 LC7VMAX1 Meder - cross 1 A. Virginia Roberts. 2 MS. COMEY: Your Honor, the government offers this exhibit under seal to protect the privacy of a third party. 3 MS. MENNINGER: No further objection, your Honor. 4 THE COURT: Okay. 332 is admitted, and it's admitted under seal to protect the privacy of the third party. 5 (Government's Exhibit 332 received in evidence) 6 MS. COMEY: Your Honor, at this time I would ask that 7 the jurors be permitted to look in their binders at what's now 8 been admitted under seal as Government Exhibit 313 and 332. 9 THE COURT: Okay. Jurors, you may look at GX-313 and 10 GX-332. And after you've viewed them, please place your 11 binders back on the ground. 12 MS. COMEY: And, your Honor, once the jurors have 13 reviewed those exhibits, I have no further questions. 14 THE COURT: Okay. 15 All right. Ms. Menninger, you may set up for cross. 16 All right. Thank you. 17 18 CROSS-EXAMINATION 19 BY MS. MENNINGER: 20 Q. Good morning, Ms. Meder. Is that how you pronounce it? 21 A. Yes. 22 Q. You were testifying about some photographs that you copied 23 from CDs onto a computer; correct? 24 A. Correct. 25 SOUTHERN DISTRICT REPORTERS, P.C. (212) 805-0300 DOJ-OGR-00018636",
  "text_blocks": [
    {
      "type": "printed",
      "content": "Case 1:20-cr-00330-PAE Document 753 Filed 08/10/22 Page 38 of 264 1464",
      "position": "header"
    },
    {
      "type": "printed",
      "content": "LC7VMAX1 Meder - cross",
      "position": "header"
    },
    {
      "type": "printed",
      "content": "1 A. Virginia Roberts. 2 MS. COMEY: Your Honor, the government offers this exhibit under seal to protect the privacy of a third party. 3 MS. MENNINGER: No further objection, your Honor. 4 THE COURT: Okay. 332 is admitted, and it's admitted under seal to protect the privacy of the third party. 5 (Government's Exhibit 332 received in evidence) 6 MS. COMEY: Your Honor, at this time I would ask that 7 the jurors be permitted to look in their binders at what's now 8 been admitted under seal as Government Exhibit 313 and 332. 9 THE COURT: Okay. Jurors, you may look at GX-313 and 10 GX-332. And after you've viewed them, please place your 11 binders back on the ground. 12 MS. COMEY: And, your Honor, once the jurors have 13 reviewed those exhibits, I have no further questions. 14 THE COURT: Okay. 15 All right. Ms. Menninger, you may set up for cross. 16 All right. Thank you. 17 18 CROSS-EXAMINATION 19 BY MS. MENNINGER: 20 Q. Good morning, Ms. Meder. Is that how you pronounce it? 21 A. Yes. 22 Q. You were testifying about some photographs that you copied 23 from CDs onto a computer; correct? 24 A. Correct. 25",
      "position": "main"
    },
    {
      "type": "printed",
      "content": "SOUTHERN DISTRICT REPORTERS, P.C. (212) 805-0300",
      "position": "footer"
    },
    {
      "type": "printed",
      "content": "DOJ-OGR-00018636",
      "position": "footer"
    }
  ],
  "entities": {
    "people": [
      "Virginia Roberts",
      "MS. COMEY",
      "MS. MENNINGER",
      "MS. Meder"
    ],
    "organizations": [
      "SOUTHERN DISTRICT REPORTERS, P.C."
    ],
    "locations": [],
    "dates": [
      "08/10/22"
    ],
    "reference_numbers": [
      "1:20-cr-00330-PAE",
      "753",
      "332",
      "313",
      "GX-313",
      "GX-332",
      "DOJ-OGR-00018636"
    ]
  },
  "additional_notes": "The document appears to be a court transcript with a clear and legible format. There are no visible redactions or damage."
}