{
  "document_metadata": {
    "page_number": "234",
    "document_number": "753",
    "date": "08/10/22",
    "document_type": "court transcript",
    "has_handwriting": false,
    "has_stamps": false
  },
  "full_text": "Case 1:20-cr-00330-PAE Document 753 Filed 08/10/22 Page 234 of 264 1675 LC7VMAX7 Carolyn - cross 1 MR. PAGLIUCA: And, your Honor, may I continue reading? 2 THE COURT: What lines? 3 MR. PAGLIUCA: Sixteen through 107, 14. 4 THE COURT: Need to see 107. 5 Through what line? 6 MR. PAGLIUCA: Five, your Honor. 7 THE COURT: Okay. Go ahead. 8 MS. COMEY: I would object, your Honor. 9 THE COURT: I'm sorry? 10 MS. COMEY: Same objection, your Honor. 11 THE COURT: Go ahead. 12 13 BY MR. PAGLIUCA: 14 Q. (Reading) 15 \"Q. Do you know what I mean by sexual intercourse or do I need to go through the various acts? 16 \"A. Oh, I am pretty sure I know what sexual intercourse is being I have two children. 17 \"Q. Well, I just want to make sure we're clear about some things. Did Mr. Epstein ever insert his penis into any part of your body at all? 18 \"A. I just said that I've never had any sexual intercourse with Mr. Epstein, and that I knew what -- \" 19 THE COURT: You misread. 20 21 BY MR. PAGLIUCA: 22 23 SOUTHERN DISTRICT REPORTERS, P.C. (212) 805-0300 24 DOJ-OGR-00018832",
  "text_blocks": [
    {
      "type": "printed",
      "content": "Case 1:20-cr-00330-PAE Document 753 Filed 08/10/22 Page 234 of 264 1675 LC7VMAX7 Carolyn - cross",
      "position": "header"
    },
    {
      "type": "printed",
      "content": "1 MR. PAGLIUCA: And, your Honor, may I continue reading? 2 THE COURT: What lines? 3 MR. PAGLIUCA: Sixteen through 107, 14. 4 THE COURT: Need to see 107. 5 Through what line? 6 MR. PAGLIUCA: Five, your Honor. 7 THE COURT: Okay. Go ahead. 8 MS. COMEY: I would object, your Honor. 9 THE COURT: I'm sorry? 10 MS. COMEY: Same objection, your Honor. 11 THE COURT: Go ahead. 12 13 BY MR. PAGLIUCA: 14 Q. (Reading) 15 \"Q. Do you know what I mean by sexual intercourse or do I need to go through the various acts? 16 \"A. Oh, I am pretty sure I know what sexual intercourse is being I have two children. 17 \"Q. Well, I just want to make sure we're clear about some things. Did Mr. Epstein ever insert his penis into any part of your body at all? 18 \"A. I just said that I've never had any sexual intercourse with Mr. Epstein, and that I knew what -- \" 19 THE COURT: You misread. 20 21 BY MR. PAGLIUCA: 22 23",
      "position": "main"
    },
    {
      "type": "printed",
      "content": "SOUTHERN DISTRICT REPORTERS, P.C. (212) 805-0300",
      "position": "footer"
    },
    {
      "type": "printed",
      "content": "DOJ-OGR-00018832",
      "position": "footer"
    }
  ],
  "entities": {
    "people": [
      "MR. PAGLIUCA",
      "MS. COMEY",
      "Mr. Epstein"
    ],
    "organizations": [
      "SOUTHERN DISTRICT REPORTERS, P.C."
    ],
    "locations": [],
    "dates": [
      "08/10/22"
    ],
    "reference_numbers": [
      "1:20-cr-00330-PAE",
      "753",
      "DOJ-OGR-00018832"
    ]
  },
  "additional_notes": "The document appears to be a court transcript with a clear and legible format. There are no visible redactions or damage."
}