{
  "document_metadata": {
    "page_number": "211",
    "document_number": "753",
    "date": "08/10/22",
    "document_type": "court transcript",
    "has_handwriting": false,
    "has_stamps": false
  },
  "full_text": "Case 1:20-cr-00330-PAE Document 753 Filed 08/10/22 Page 211 of 264 1652 LC7VMAX7 Carolyn - cross 1 I'll sustain on 57 for the same reason. 2 Next. 3 MR. PAGLIUCA: I think I can -- I can just tell you 4 all of them, your Honor, which are going to be the same. 5 THE COURT: If they are all on that same theory, then 6 you can make the record. If there's any different theory of 7 inconsistency, either as to the specific time frame and 8 testimony or to some different inference available, I'll hear 9 it. But otherwise just make the record with respect to the 10 numbered paragraphs. 11 MR. PAGLIUCA: Sure. And when I get to the place 12 where it's different, I'll stop and we'll address that. 13 THE COURT: Okay. 14 MR. PAGLIUCA: Is that fair? 15 THE COURT: Fair. 16 MR. PAGLIUCA: 63. 17 THE COURT: Okay. Sustained. 18 MR. PAGLIUCA: 69, 75. 19 THE COURT: Sustained on 69. And sustained on 75. 20 MR. PAGLIUCA: 81. 21 THE COURT: Sustained. 22 MR. PAGLIUCA: 87. 23 THE COURT: Sustained. 24 MR. PAGLIUCA: 93. 25 THE COURT: Sustained. SOUTHERN DISTRICT REPORTERS, P.C. (212) 805-0300 DOJ-OGR-00018809",
  "text_blocks": [
    {
      "type": "printed",
      "content": "Case 1:20-cr-00330-PAE Document 753 Filed 08/10/22 Page 211 of 264",
      "position": "header"
    },
    {
      "type": "printed",
      "content": "1652 LC7VMAX7 Carolyn - cross",
      "position": "header"
    },
    {
      "type": "printed",
      "content": "1 I'll sustain on 57 for the same reason. 2 Next. 3 MR. PAGLIUCA: I think I can -- I can just tell you 4 all of them, your Honor, which are going to be the same. 5 THE COURT: If they are all on that same theory, then 6 you can make the record. If there's any different theory of 7 inconsistency, either as to the specific time frame and 8 testimony or to some different inference available, I'll hear 9 it. But otherwise just make the record with respect to the 10 numbered paragraphs. 11 MR. PAGLIUCA: Sure. And when I get to the place 12 where it's different, I'll stop and we'll address that. 13 THE COURT: Okay. 14 MR. PAGLIUCA: Is that fair? 15 THE COURT: Fair. 16 MR. PAGLIUCA: 63. 17 THE COURT: Okay. Sustained. 18 MR. PAGLIUCA: 69, 75. 19 THE COURT: Sustained on 69. And sustained on 75. 20 MR. PAGLIUCA: 81. 21 THE COURT: Sustained. 22 MR. PAGLIUCA: 87. 23 THE COURT: Sustained. 24 MR. PAGLIUCA: 93. 25 THE COURT: Sustained.",
      "position": "main"
    },
    {
      "type": "printed",
      "content": "SOUTHERN DISTRICT REPORTERS, P.C. (212) 805-0300",
      "position": "footer"
    },
    {
      "type": "printed",
      "content": "DOJ-OGR-00018809",
      "position": "footer"
    }
  ],
  "entities": {
    "people": [
      "MR. PAGLIUCA"
    ],
    "organizations": [
      "SOUTHERN DISTRICT REPORTERS, P.C."
    ],
    "locations": [],
    "dates": [
      "08/10/22"
    ],
    "reference_numbers": [
      "1:20-cr-00330-PAE",
      "753",
      "DOJ-OGR-00018809"
    ]
  },
  "additional_notes": "The document appears to be a court transcript with a clear and legible format. There are no visible redactions or damage."
}