{
  "document_metadata": {
    "page_number": "151",
    "document_number": "747",
    "date": "08/10/22",
    "document_type": "court transcript",
    "has_handwriting": false,
    "has_stamps": false
  },
  "full_text": "Case 1:20-cr-00330-PAE Document 747 Filed 08/10/22 Page 151 of 228 827 LC2Qmax5 - corrected Alessi - Direct\n\n1 page?\n2 A. Unless otherwise instructed, never disclose Mr. Epstein or\n3 Ms. Maxwell's activity or whereabouts to anyone. If the caller\n4 is insistent, you simply ask to take a message, a time, a\n5 number where the caller can be reached. Do not -- do not be\n6 bullied and do not show any reaction or impatience, simply be\n7 firm.\n8 Q. Can we please go now to the page marked page 10.\n9 Mr. Alessi, what are we looking at on this page?\n10 A. This is a list of things that have to be done before the\n11 arrival of Mr. Epstein or Ms. Maxwell.\n12 Q. There's a reference on this page to JE and GM telephone\n13 directories.\n14 A. Yes.\n15 Q. What were those?\n16 A. These were booklets with JE and GM. I think they were in\n17 the front or in the binding of the --\n18 THE COURT: Mr. Alessi, could you talk into the\n19 microphone please.\n20 Q. Mr. Alessi, what were these directories, JE and GM\n21 telephone directories to your understanding?\n22 A. This would mean Jeffrey Epstein and Ghislaine Maxwell.\n23 Q. What are the directories?\n24 A. The directories were books with hundreds and hundreds of\n25 names and their telephone numbers and contacts, directions,\n\nSOUTHERN DISTRICT REPORTERS, P.C.\n(212) 805-0300\nDOJ-OGR-00018024",
  "text_blocks": [
    {
      "type": "printed",
      "content": "Case 1:20-cr-00330-PAE Document 747 Filed 08/10/22 Page 151 of 228 827 LC2Qmax5 - corrected Alessi - Direct",
      "position": "header"
    },
    {
      "type": "printed",
      "content": "1 page?\n2 A. Unless otherwise instructed, never disclose Mr. Epstein or\n3 Ms. Maxwell's activity or whereabouts to anyone. If the caller\n4 is insistent, you simply ask to take a message, a time, a\n5 number where the caller can be reached. Do not -- do not be\n6 bullied and do not show any reaction or impatience, simply be\n7 firm.\n8 Q. Can we please go now to the page marked page 10.\n9 Mr. Alessi, what are we looking at on this page?\n10 A. This is a list of things that have to be done before the\n11 arrival of Mr. Epstein or Ms. Maxwell.\n12 Q. There's a reference on this page to JE and GM telephone\n13 directories.\n14 A. Yes.\n15 Q. What were those?\n16 A. These were booklets with JE and GM. I think they were in\n17 the front or in the binding of the --\n18 THE COURT: Mr. Alessi, could you talk into the\n19 microphone please.\n20 Q. Mr. Alessi, what were these directories, JE and GM\n21 telephone directories to your understanding?\n22 A. This would mean Jeffrey Epstein and Ghislaine Maxwell.\n23 Q. What are the directories?\n24 A. The directories were books with hundreds and hundreds of\n25 names and their telephone numbers and contacts, directions,",
      "position": "main content"
    },
    {
      "type": "printed",
      "content": "SOUTHERN DISTRICT REPORTERS, P.C.\n(212) 805-0300",
      "position": "footer"
    },
    {
      "type": "printed",
      "content": "DOJ-OGR-00018024",
      "position": "footer"
    }
  ],
  "entities": {
    "people": [
      "Mr. Epstein",
      "Ms. Maxwell",
      "Jeffrey Epstein",
      "Ghislaine Maxwell",
      "Mr. Alessi"
    ],
    "organizations": [
      "SOUTHERN DISTRICT REPORTERS, P.C."
    ],
    "locations": [],
    "dates": [
      "08/10/22"
    ],
    "reference_numbers": [
      "1:20-cr-00330-PAE",
      "747",
      "DOJ-OGR-00018024"
    ]
  },
  "additional_notes": "The document appears to be a court transcript with a clear and legible format. There are no visible redactions or damage."
}