{
  "document_metadata": {
    "page_number": "228",
    "document_number": "755",
    "date": "08/10/22",
    "document_type": "court transcript",
    "has_handwriting": false,
    "has_stamps": false
  },
  "full_text": "Case 1:20-cr-00330-PAE Document 755 Filed 08/10/22 Page 228 of 262 1939\nLC8Cmax7 Rodgers - cross\n1 THE COURT: The witness may look at GX250.\n2 THE WITNESS: Where is 250?\n3 THE COURT: It's on your screen.\n4 MR. EVERDELL: It should be on your screen, sir.\n5 THE WITNESS: Oh, okay.\n6 MR. EVERDELL: Do you see that?\n7 THE WITNESS: Yes.\n8 BY MR. EVERDELL:\n9 Q. Have you ever seen that photo before?\n10 A. No, I have not.\n11 MR. EVERDELL: One moment, your Honor.\n12 Q. Mr. Rodgers, I want to show you what is in your binder as C10.\n13 C10. There should be a tab, C10.\n14 A. Is this your binder?\n15 Q. The binder I gave to you, yeah. Is there a tab, C10, there?\n16\n17 A. Yes, I have C10.\n18 MR. EVERDELL: We can put it on the screen for the Court, the deputy, and the witness if he wants.\n19\n20 Q. Mr. Rodgers, have you ever seen this picture?\n21 A. No.\n22 Q. Do you recognize the person in that picture?\n23 A. I'm not sure positively, but it could be Eva.\n24 Q. Eva Dubin?\n25 A. Yes.\nSOUTHERN DISTRICT REPORTERS, P.C. (212) 805-0300\nDOJ-OGR-00019090",
  "text_blocks": [
    {
      "type": "printed",
      "content": "Case 1:20-cr-00330-PAE Document 755 Filed 08/10/22 Page 228 of 262 1939",
      "position": "header"
    },
    {
      "type": "printed",
      "content": "LC8Cmax7 Rodgers - cross",
      "position": "header"
    },
    {
      "type": "printed",
      "content": "1 THE COURT: The witness may look at GX250.\n2 THE WITNESS: Where is 250?\n3 THE COURT: It's on your screen.\n4 MR. EVERDELL: It should be on your screen, sir.\n5 THE WITNESS: Oh, okay.\n6 MR. EVERDELL: Do you see that?\n7 THE WITNESS: Yes.\n8 BY MR. EVERDELL:\n9 Q. Have you ever seen that photo before?\n10 A. No, I have not.\n11 MR. EVERDELL: One moment, your Honor.\n12 Q. Mr. Rodgers, I want to show you what is in your binder as C10.\n13 C10. There should be a tab, C10.\n14 A. Is this your binder?\n15 Q. The binder I gave to you, yeah. Is there a tab, C10, there?\n16\n17 A. Yes, I have C10.\n18 MR. EVERDELL: We can put it on the screen for the Court, the deputy, and the witness if he wants.\n19\n20 Q. Mr. Rodgers, have you ever seen this picture?\n21 A. No.\n22 Q. Do you recognize the person in that picture?\n23 A. I'm not sure positively, but it could be Eva.\n24 Q. Eva Dubin?\n25 A. Yes.",
      "position": "main content"
    },
    {
      "type": "printed",
      "content": "SOUTHERN DISTRICT REPORTERS, P.C. (212) 805-0300",
      "position": "footer"
    },
    {
      "type": "printed",
      "content": "DOJ-OGR-00019090",
      "position": "footer"
    }
  ],
  "entities": {
    "people": [
      "MR. EVERDELL",
      "MR. RODGERS",
      "EVA DUBIN"
    ],
    "organizations": [
      "SOUTHERN DISTRICT REPORTERS, P.C."
    ],
    "locations": [],
    "dates": [
      "08/10/22"
    ],
    "reference_numbers": [
      "1:20-cr-00330-PAE",
      "755",
      "DOJ-OGR-00019090"
    ]
  },
  "additional_notes": "The document appears to be a court transcript with a clear and legible format. There are no visible redactions or damage."
}