{
  "document_metadata": {
    "page_number": "8",
    "document_number": "89-1",
    "date": "05/17/2021",
    "document_type": "court document",
    "has_handwriting": false,
    "has_stamps": false
  },
  "full_text": "Case 21-58, Document 89-1, 05/17/2021, 3102450, Page8 of 14\nbe singled out in this way because she is alone, the nature of the charges, and that this is high profile case. But those reasons, individually or collectively, do not justify torturing someone by depriving them of sleep. Nevertheless, the district judge did not conduct a hearing or otherwise question BOP. It simply allowed the government to file a letter saying that this is what was relayed to the government from the jail lawyer from the jail guards. Even if that hearsay was true (which should be questioned based on other representations made by BOP to the government to the court), it is not at all sufficient for this type of treatment.\n3. Government misrepresentation to the district court: Ms. Maxwell “caused [her] cell to smell” by not flushing the toilet. Doc. 196, n.2 (April 6, 2021, gov’t letter to district court). This claim is absurd, of course, and was again made without any sworn statement. Ms. Maxwell responded and explained that the smell of sewage was caused by the conditions in MDC and not by her.\nThis was recently corroborated by another MDC inmate, Tiffany Days, who explained to Judge McMahon the sorts of conditions that are present at MDC: “I also survived the disgusting feces flood that we were\n6\nDOJ-OGR-00020332",
  "text_blocks": [
    {
      "type": "printed",
      "content": "Case 21-58, Document 89-1, 05/17/2021, 3102450, Page8 of 14",
      "position": "header"
    },
    {
      "type": "printed",
      "content": "be singled out in this way because she is alone, the nature of the charges, and that this is high profile case. But those reasons, individually or collectively, do not justify torturing someone by depriving them of sleep. Nevertheless, the district judge did not conduct a hearing or otherwise question BOP. It simply allowed the government to file a letter saying that this is what was relayed to the government from the jail lawyer from the jail guards. Even if that hearsay was true (which should be questioned based on other representations made by BOP to the government to the court), it is not at all sufficient for this type of treatment.",
      "position": "top"
    },
    {
      "type": "printed",
      "content": "3. Government misrepresentation to the district court: Ms. Maxwell “caused [her] cell to smell” by not flushing the toilet. Doc. 196, n.2 (April 6, 2021, gov’t letter to district court). This claim is absurd, of course, and was again made without any sworn statement. Ms. Maxwell responded and explained that the smell of sewage was caused by the conditions in MDC and not by her.",
      "position": "middle"
    },
    {
      "type": "printed",
      "content": "This was recently corroborated by another MDC inmate, Tiffany Days, who explained to Judge McMahon the sorts of conditions that are present at MDC: “I also survived the disgusting feces flood that we were",
      "position": "middle"
    },
    {
      "type": "printed",
      "content": "6",
      "position": "footer"
    },
    {
      "type": "printed",
      "content": "DOJ-OGR-00020332",
      "position": "footer"
    }
  ],
  "entities": {
    "people": [
      "Ms. Maxwell",
      "Tiffany Days",
      "Judge McMahon"
    ],
    "organizations": [
      "BOP",
      "MDC"
    ],
    "locations": [],
    "dates": [
      "05/17/2021",
      "April 6, 2021"
    ],
    "reference_numbers": [
      "Case 21-58",
      "Document 89-1",
      "3102450",
      "Doc. 196",
      "DOJ-OGR-00020332"
    ]
  },
  "additional_notes": "The document appears to be a court filing discussing the treatment of Ms. Maxwell in jail. The text is printed and there are no visible stamps or handwritten notes. The document is page 8 of 14."
}