{
  "document_metadata": {
    "page_number": "23 of 23",
    "document_number": "94",
    "date": "10/08/2020",
    "document_type": "Certificate of Compliance and Service",
    "has_handwriting": false,
    "has_stamps": false
  },
  "full_text": "Case 20-3061, Document 94, 10/08/2020, 2948481, Page23 of 23\n\nCertificate of Compliance with Rule 32(A)\n\nThis brief complies with the type-volume limitation of Fed. R. App. P. 32(a)(7)(B). It contains 4,096 words, excluding the parts of the brief exempted by Fed. R. App. P. 32(a)(7)(B)(III).\n\nThis brief complies with the typeface requirements of Fed. R. App. P. 32(a)(5) and the typestyle requirements of Fed. R. App. P. 32(a)(6). It has been prepared in a proportionally spaced typeface using Microsoft Word 2010 in 14 pt. Equity.\n\ns/ Adam Mueller\n\nCertificate of Service\n\nI certify that on October 8, 2020, I filed Ms. Maxwell's Reply Brief with the Court via CM/ECF, which will send notification of the filing to all counsel of record.\n\ns/ Nicole Simmons\n\n20\n\nDOJ-OGR-00019669",
  "text_blocks": [
    {
      "type": "printed",
      "content": "Case 20-3061, Document 94, 10/08/2020, 2948481, Page23 of 23",
      "position": "header"
    },
    {
      "type": "printed",
      "content": "Certificate of Compliance with Rule 32(A)",
      "position": "top"
    },
    {
      "type": "printed",
      "content": "This brief complies with the type-volume limitation of Fed. R. App. P. 32(a)(7)(B). It contains 4,096 words, excluding the parts of the brief exempted by Fed. R. App. P. 32(a)(7)(B)(III).",
      "position": "middle"
    },
    {
      "type": "printed",
      "content": "This brief complies with the typeface requirements of Fed. R. App. P. 32(a)(5) and the typestyle requirements of Fed. R. App. P. 32(a)(6). It has been prepared in a proportionally spaced typeface using Microsoft Word 2010 in 14 pt. Equity.",
      "position": "middle"
    },
    {
      "type": "signature",
      "content": "s/ Adam Mueller",
      "position": "middle"
    },
    {
      "type": "printed",
      "content": "Certificate of Service",
      "position": "middle"
    },
    {
      "type": "printed",
      "content": "I certify that on October 8, 2020, I filed Ms. Maxwell's Reply Brief with the Court via CM/ECF, which will send notification of the filing to all counsel of record.",
      "position": "middle"
    },
    {
      "type": "signature",
      "content": "s/ Nicole Simmons",
      "position": "middle"
    },
    {
      "type": "printed",
      "content": "20",
      "position": "footer"
    },
    {
      "type": "printed",
      "content": "DOJ-OGR-00019669",
      "position": "footer"
    }
  ],
  "entities": {
    "people": [
      "Adam Mueller",
      "Nicole Simmons",
      "Ms. Maxwell"
    ],
    "organizations": [
      "Court"
    ],
    "locations": [],
    "dates": [
      "October 8, 2020",
      "10/08/2020"
    ],
    "reference_numbers": [
      "20-3061",
      "94",
      "2948481",
      "DOJ-OGR-00019669"
    ]
  },
  "additional_notes": "The document appears to be a certificate of compliance and service for a court filing. It is a formal document with printed text and electronic signatures. The document is well-formatted and legible."
}