{
  "document_metadata": {
    "page_number": "122",
    "document_number": "745",
    "date": "08/10/22",
    "document_type": "court transcript",
    "has_handwriting": false,
    "has_stamps": false
  },
  "full_text": "Case 1:20-cr-00330-PAE Document 745 Filed 08/10/22 Page 122 of 264 533 LC1Qmax4 Jane - Cross 1 A. This timeline is not correct. I did not know Emmy or Michelle while living in Florida. I knew them in New York. 2 Q. You did not live in a house in New York, correct? 3 A. No. 4 Q. You lived in an apartment, right? 5 A. Yes. 6 Q. So you didn't have a house phone in New York? 7 A. I think we did have a house phone, actually. Actually, we did for sure. 8 Q. There was staff present at Mr. Epstein's eight-story mansion, right? 9 A. Yes. 10 Q. And the staff included a chef, right? 11 A. Yes. 12 Q. And a house manager? 13 A. Yes. 14 Q. And a driver? 15 A. Yes. 16 Q. And so all of those people saw you staying in this mansion by yourself as a 14 year old, right? 17 A. Yes. 18 Q. You said that Epstein gave you money almost every time that you saw him, right? 19 A. Correct. 20 Q. Hundreds of dollars at a time? 21 SOUTHERN DISTRICT REPORTERS, P.C. (212) 805-0300 DOJ-OGR-00017731",
  "text_blocks": [
    {
      "type": "printed",
      "content": "Case 1:20-cr-00330-PAE Document 745 Filed 08/10/22 Page 122 of 264 533",
      "position": "header"
    },
    {
      "type": "printed",
      "content": "LC1Qmax4 Jane - Cross",
      "position": "header"
    },
    {
      "type": "printed",
      "content": "1 A. This timeline is not correct. I did not know Emmy or Michelle while living in Florida. I knew them in New York. 2 Q. You did not live in a house in New York, correct? 3 A. No. 4 Q. You lived in an apartment, right? 5 A. Yes. 6 Q. So you didn't have a house phone in New York? 7 A. I think we did have a house phone, actually. Actually, we did for sure. 8 Q. There was staff present at Mr. Epstein's eight-story mansion, right? 9 A. Yes. 10 Q. And the staff included a chef, right? 11 A. Yes. 12 Q. And a house manager? 13 A. Yes. 14 Q. And a driver? 15 A. Yes. 16 Q. And so all of those people saw you staying in this mansion by yourself as a 14 year old, right? 17 A. Yes. 18 Q. You said that Epstein gave you money almost every time that you saw him, right? 19 A. Correct. 20 Q. Hundreds of dollars at a time? 21",
      "position": "main"
    },
    {
      "type": "printed",
      "content": "SOUTHERN DISTRICT REPORTERS, P.C. (212) 805-0300",
      "position": "footer"
    },
    {
      "type": "printed",
      "content": "DOJ-OGR-00017731",
      "position": "footer"
    }
  ],
  "entities": {
    "people": [
      "Emmy",
      "Michelle",
      "Epstein"
    ],
    "organizations": [
      "SOUTHERN DISTRICT REPORTERS, P.C."
    ],
    "locations": [
      "Florida",
      "New York"
    ],
    "dates": [
      "08/10/22"
    ],
    "reference_numbers": [
      "1:20-cr-00330-PAE",
      "745",
      "DOJ-OGR-00017731"
    ]
  },
  "additional_notes": "The document appears to be a court transcript with a clear and legible format. There are no visible redactions or damage."
}